.version 49 0
.class public final super aA
.super java/lang/Object
.field private field2183 I

.method public <init> : (I)V
    .code stack 5 locals 2
L0:     iconst_3
L1:     aload_0
L2:     invokespecial Method java/lang/Object <init> ()V
L5:     iconst_1
L6:     dup
L7:     pop2
L8:     iload_1
L9:     if_icmpge L40
L12:    new java/lang/IllegalArgumentException
L15:    dup
L16:    new java/lang/StringBuilder
L19:    dup
L20:    invokespecial Method java/lang/StringBuilder <init> ()V
L23:    iconst_0
L24:    ldc "Invalid OpenGL ES version specified: "
L26:    invokevirtual Method java/lang/StringBuilder insert (ILjava/lang/String;)Ljava/lang/StringBuilder;
L29:    iload_1
L30:    invokevirtual Method java/lang/StringBuilder append (I)Ljava/lang/StringBuilder;
L33:    invokevirtual Method java/lang/StringBuilder toString ()Ljava/lang/String;
L36:    invokespecial Method java/lang/IllegalArgumentException <init> (Ljava/lang/String;)V
L39:    athrow
L40:    aload_0
L41:    iload_1
L42:    putfield Field aA field2183 I
L45:    return
L46:    
        .attribute StackMap b'\x00\x01\x00\x28\x00\x02\x07\x00\x02\x01\x00\x00'
    .end code
.end method

.method public <init> : ()V
    .code stack 4 locals 1
L0:     aload_0
L1:     iconst_2
L2:     iconst_1
L3:     dup
L4:     pop2
L5:     invokespecial Method aA <init> (I)V
L8:     return
L9:     
    .end code
.end method

.method private <init> : (LaA;)V
    .code stack 3 locals 2
L0:     aload_1
L1:     aload_0
L2:     dup_x1
L3:     invokespecial Method java/lang/Object <init> ()V
L6:     getfield Field aA field2183 I
L9:     putfield Field aA field2183 I
L12:    return
L13:    
    .end code
.end method

.method public method1112 : ()I
    .code stack 1 locals 1
L0:     aload_0
L1:     getfield Field aA field2183 I
L4:     ireturn
L5:     
    .end code
.end method

.method public method1113 : ()Ljava/nio/IntBuffer;
    .code stack 5 locals 2
L0:     iconst_1
L1:     dup
L2:     pop2
L3:     iconst_2
L4:     iconst_1
L5:     dup_x1
L6:     dup
L7:     pop2
L8:     imul
L9:     iconst_1
L10:    dup
L11:    dup
L12:    pop2
L13:    iadd
L14:    invokestatic Method org/lwjgl/BufferUtils createIntBuffer (I)Ljava/nio/IntBuffer;
L17:    dup
L18:    astore_1
L19:    sipush 12440
L22:    iconst_1
L23:    dup
L24:    pop2
L25:    invokevirtual Method java/nio/IntBuffer put (I)Ljava/nio/IntBuffer;
L28:    aload_0
L29:    getfield Field aA field2183 I
L32:    invokevirtual Method java/nio/IntBuffer put (I)Ljava/nio/IntBuffer;
L35:    aload_1
L36:    sipush 12344
L39:    iconst_1
L40:    dup
L41:    pop2
L42:    invokevirtual Method java/nio/IntBuffer put (I)Ljava/nio/IntBuffer;
L45:    aload_1
L46:    dup_x2
L47:    invokevirtual Method java/nio/IntBuffer rewind ()Ljava/nio/Buffer;
L50:    pop
L51:    pop2
L52:    areturn
L53:    
    .end code
.end method

.method public toString : ()Ljava/lang/String;
    .code stack 5 locals 2
L0:     new java/lang/StringBuilder
L3:     dup
L4:     bipush 32
L6:     iconst_1
L7:     dup
L8:     pop2
L9:     invokespecial Method java/lang/StringBuilder <init> (I)V
L12:    dup
L13:    astore_1
L14:    ldc "ContextAttribs:"
L16:    invokevirtual Method java/lang/StringBuilder append (Ljava/lang/String;)Ljava/lang/StringBuilder;
L19:    aload_1
L20:    dup_x1
L21:    ldc " Version="
L23:    invokevirtual Method java/lang/StringBuilder append (Ljava/lang/String;)Ljava/lang/StringBuilder;
L26:    aload_0
L27:    getfield Field aA field2183 I
L30:    invokevirtual Method java/lang/StringBuilder append (I)Ljava/lang/StringBuilder;
L33:    pop2
L34:    invokevirtual Method java/lang/StringBuilder toString ()Ljava/lang/String;
L37:    areturn
L38:    
    .end code
.end method
.end class
