.version 49 0
.class public final super ab
.super qd
.field public "enum" Ljava/util/Set;
.field public do Ljava/util/List;

.method public varargs <init> : (Leb;[Led;)V
    .code stack 18 locals 3
L0:     aload_0
L1:     dup
L2:     dup_x1
L3:     aload_1
L4:     iconst_1
L5:     dup
L6:     pop2
L7:     iconst_0
L8:     iconst_1
L9:     dup
L10:    pop2
L11:    iconst_0
L12:    dup_x1
L13:    iconst_1
L14:    dup
L15:    pop2
L16:    ldc 2147483647
L18:    dup
L19:    iconst_m1
L20:    iconst_1
L21:    dup
L22:    pop2
L23:    iconst_1
L24:    dup
L25:    pop2
L26:    iconst_0
L27:    iconst_1
L28:    dup
L29:    pop2
L30:    iconst_0
L31:    iconst_1
L32:    dup_x2
L33:    dup
L34:    pop2
L35:    aconst_null
L36:    dup
L37:    iconst_m1
L38:    iconst_1
L39:    dup
L40:    pop2
L41:    invokespecial Method qd <init> (Leb;ZZZIIIZZZLjava/lang/String;Ljava/lang/String;I)V
L44:    new java/util/HashSet
L47:    aload_0
L48:    dup_x2
L49:    dup
L50:    pop2
L51:    dup
L52:    aload_2
L53:    invokestatic Method java/util/Arrays asList ([Ljava/lang/Object;)Ljava/util/List;
L56:    invokespecial Method java/util/HashSet <init> (Ljava/util/Collection;)V
L59:    putfield Field ab "enum" Ljava/util/Set;
L62:    new java/util/LinkedList
L65:    aload_0
L66:    dup
L67:    pop2
L68:    dup
L69:    invokespecial Method java/util/LinkedList <init> ()V
L72:    putfield Field ab do Ljava/util/List;
L75:    invokevirtual Method ab goto ()V
L78:    return
L79:    
    .end code
.end method

.method public break : (Led;ZLjava/lang/String;LK;)V
    .code stack 5 locals 5
L0:     new hd
L3:     dup
L4:     aload_0
L5:     aload_1
L6:     aload 4
L8:     invokespecial Method hd <init> (Lab;Led;LK;)V
L11:    invokestatic Method ib break (Ljava/lang/Runnable;)V
L14:    return
L15:    
    .end code
.end method

.method public <init> : (Leb;Led;Ljava/util/List;Z)V
    .code stack 17 locals 5
L0:     aload_0
L1:     dup
L2:     aload_1
L3:     iconst_1
L4:     dup
L5:     pop2
L6:     iconst_0
L7:     iconst_1
L8:     dup
L9:     pop2
L10:    iconst_0
L11:    dup_x1
L12:    iconst_1
L13:    dup
L14:    pop2
L15:    ldc 2147483647
L17:    dup
L18:    iconst_m1
L19:    iconst_1
L20:    dup
L21:    pop2
L22:    iconst_1
L23:    dup
L24:    pop2
L25:    iconst_0
L26:    iconst_1
L27:    dup_x1
L28:    dup
L29:    pop2
L30:    iload 4
L32:    aconst_null
L33:    dup
L34:    iconst_m1
L35:    iconst_1
L36:    dup
L37:    pop2
L38:    invokespecial Method qd <init> (Leb;ZZZIIIZZZLjava/lang/String;Ljava/lang/String;I)V
L41:    new java/util/HashSet
L44:    aload_0
L45:    dup_x2
L46:    dup
L47:    pop2
L48:    dup
L49:    invokespecial Method java/util/HashSet <init> ()V
L52:    putfield Field ab "enum" Ljava/util/Set;
L55:    getfield Field ab "enum" Ljava/util/Set;
L58:    aload_2
L59:    invokeinterface InterfaceMethod java/util/Set add (Ljava/lang/Object;)Z 2
L64:    new java/util/LinkedList
L67:    aload_0
L68:    dup_x1
L69:    dup_x2
L70:    dup
L71:    pop2
L72:    dup
L73:    aload_3
L74:    invokespecial Method java/util/LinkedList <init> (Ljava/util/Collection;)V
L77:    putfield Field ab do Ljava/util/List;
L80:    invokevirtual Method ab goto ()V
L83:    pop
L84:    return
L85:    
    .end code
.end method

.method public break : (Led;LK;)V
    .code stack 5 locals 3
L0:     aload_0
L1:     getfield Field ab new Ljava/util/LinkedHashMap;
L4:     aload_1
L5:     invokevirtual Method java/util/LinkedHashMap containsKey (Ljava/lang/Object;)Z
L8:     ifne L13
L11:    return
L12:    athrow
L13:    new tb
L16:    dup
L17:    aload_0
L18:    aload_1
L19:    aload_2
L20:    invokespecial Method tb <init> (Lab;Led;LK;)V
L23:    invokestatic Method ib break (Ljava/lang/Runnable;)V
L26:    return
L27:    
        .attribute StackMap b'\x00\x02\x00\x0C\x00\x00\x00\x01\x07\x00\x4A\x00\x0D\x00\x03\x07\x00\x02\x07\x00\x4C\x07\x00\x4E\x00\x00'
    .end code
.end method

.method public else : (LD;)V
    .code stack 4 locals 2
L0:     new Od
L3:     dup
L4:     aload_0
L5:     aload_1
L6:     invokespecial Method Od <init> (Lab;LD;)V
L9:     invokestatic Method ib break (Ljava/lang/Runnable;)V
L12:    return
L13:    
    .end code
.end method

.method public long : ()D
    .code stack 2 locals 1
L0:     ldc2_w 3e0
L3:     dreturn
L4:     
    .end code
.end method
.innerclasses
    Od [0] [0]
    hd [0] [0]
    tb [0] [0]
.end innerclasses
.end class
