.version 49 0
.class public final super Ab
.super java/lang/Object
.implements e

.method public else : ([B)V
    .code stack 6 locals 3
L0:     iconst_1
L1:     dup
L2:     dup
L3:     pop2
L4:     dup
L5:     istore_2
L6:     aload_1
L7:     arraylength
L8:     if_icmpge L32
L11:    aload_1
L12:    iload_2
L13:    dup2
L14:    baload
L15:    sipush 181
L18:    iconst_1
L19:    dup
L20:    pop2
L21:    ixor
L22:    i2b
L23:    iinc 2 1
L26:    bastore
L27:    iload_2
L28:    goto L6
L31:    athrow
L32:    return
L33:    
        .attribute StackMap b'\x00\x03\x00\x06\x00\x03\x07\x00\x02\x07\x00\x0A\x01\x00\x01\x01\x00\x1F\x00\x00\x00\x01\x07\x00\x0C\x00\x20\x00\x03\x07\x00\x02\x07\x00\x0A\x01\x00\x00'
    .end code
.end method

.method public break : ([B)V
    .code stack 6 locals 3
L0:     iconst_1
L1:     dup
L2:     dup
L3:     pop2
L4:     dup
L5:     istore_2
L6:     aload_1
L7:     arraylength
L8:     if_icmpge L32
L11:    aload_1
L12:    iload_2
L13:    dup2
L14:    baload
L15:    sipush 181
L18:    iconst_1
L19:    dup
L20:    pop2
L21:    ixor
L22:    i2b
L23:    iinc 2 1
L26:    bastore
L27:    iload_2
L28:    goto L6
L31:    athrow
L32:    return
L33:    
        .attribute StackMap b'\x00\x03\x00\x06\x00\x03\x07\x00\x02\x07\x00\x0A\x01\x00\x01\x01\x00\x1F\x00\x00\x00\x01\x07\x00\x0C\x00\x20\x00\x03\x07\x00\x02\x07\x00\x0A\x01\x00\x00'
    .end code
.end method

.method public <init> : ()V
    .code stack 1 locals 1
L0:     aload_0
L1:     invokespecial Method java/lang/Object <init> ()V
L4:     return
L5:     
    .end code
.end method
.end class
