.version 49 0
.class public final super AC
.super java/lang/Object
.field private do Ljava/io/DataOutputStream;

.method public break : ([[I)V
    .code stack 3 locals 5
L0:     aload_0
L1:     aload_1
L2:     arraylength
L3:     invokevirtual Method AC break (I)V
L6:     aload_1
L7:     dup
L8:     astore_1
L9:     arraylength
L10:    istore_2
L11:    iconst_0
L12:    iconst_1
L13:    dup
L14:    pop2
L15:    dup
L16:    istore_3
L17:    iload_2
L18:    if_icmpge L40
L21:    aload_1
L22:    iload_3
L23:    iinc 3 1
L26:    aaload
L27:    astore 4
L29:    aload_0
L30:    aload 4
L32:    invokevirtual Method AC break ([I)V
L35:    iload_3
L36:    goto L17
L39:    athrow
L40:    return
L41:    
        .attribute StackMap b'\x00\x03\x00\x11\x00\x04\x07\x00\x02\x07\x00\x14\x01\x01\x00\x01\x01\x00\x27\x00\x00\x00\x01\x07\x00\x19\x00\x28\x00\x04\x07\x00\x02\x07\x00\x14\x01\x01\x00\x00'
    .end code
    .exceptions java/io/IOException
.end method

.method public break : ([I)V
    .code stack 5 locals 7
L0:     aload_1
L1:     arraylength
L2:     istore_2
L3:     aload_1
L4:     dup
L5:     astore_3
L6:     arraylength
L7:     istore 4
L9:     iconst_0
L10:    iconst_1
L11:    dup
L12:    pop2
L13:    dup
L14:    istore 5
L16:    iload 4
L18:    if_icmpge L58
L21:    aload_3
L22:    iload 5
L24:    iaload
L25:    dup
L26:    istore 6
L28:    bipush -127
L30:    iconst_1
L31:    dup
L32:    pop2
L33:    if_icmplt L46
L36:    iload 6
L38:    bipush 127
L40:    iconst_1
L41:    dup
L42:    pop2
L43:    if_icmple L49
L46:    iinc 2 4
L49:    iinc 5 1
L52:    iload 5
L54:    goto L16
L57:    athrow
L58:    iload_2
L59:    aload_1
L60:    arraylength
L61:    iconst_4
L62:    iconst_1
L63:    dup
L64:    pop2
L65:    imul
L66:    if_icmpge L115
L69:    aload_0
L70:    aload_1
L71:    arraylength
L72:    ineg
L73:    invokevirtual Method AC break (I)V
L76:    aload_1
L77:    dup
L78:    astore_3
L79:    arraylength
L80:    istore 4
L82:    iconst_0
L83:    iconst_1
L84:    dup
L85:    pop2
L86:    dup
L87:    istore 5
L89:    iload 4
L91:    if_icmpge L162
L94:    aload_0
L95:    aload_3
L96:    iload 5
L98:    iinc 5 1
L101:   iaload
L102:   dup
L103:   istore 6
L105:   invokevirtual Method AC break (I)V
L108:   iload 5
L110:   goto L89
L113:   nop
L114:   athrow
L115:   aload_0
L116:   aload_1
L117:   arraylength
L118:   invokevirtual Method AC break (I)V
L121:   aload_1
L122:   dup
L123:   astore_3
L124:   arraylength
L125:   istore 4
L127:   iconst_0
L128:   iconst_1
L129:   dup
L130:   pop2
L131:   dup
L132:   istore 5
L134:   iload 4
L136:   if_icmpge L162
L139:   aload_0
L140:   aload_3
L141:   iload 5
L143:   iinc 5 1
L146:   iaload
L147:   istore 6
L149:   getfield Field AC do Ljava/io/DataOutputStream;
L152:   iload 6
L154:   invokevirtual Method java/io/DataOutputStream writeInt (I)V
L157:   iload 5
L159:   goto L134
L162:   return
L163:   
        .attribute StackMap b'\x00\x0A\x00\x10\x00\x06\x07\x00\x02\x07\x00\x1B\x01\x07\x00\x1B\x01\x01\x00\x01\x01\x00\x2E\x00\x07\x07\x00\x02\x07\x00\x1B\x01\x07\x00\x1B\x01\x01\x01\x00\x00\x00\x31\x00\x07\x07\x00\x02\x07\x00\x1B\x01\x07\x00\x1B\x01\x01\x01\x00\x00\x00\x39\x00\x00\x00\x01\x07\x00\x19\x00\x3A\x00\x06\x07\x00\x02\x07\x00\x1B\x01\x07\x00\x1B\x01\x01\x00\x00\x00\x59\x00\x06\x07\x00\x02\x07\x00\x1B\x01\x07\x00\x1B\x01\x01\x00\x01\x01\x00\x71\x00\x00\x00\x01\x07\x00\x19\x00\x73\x00\x06\x07\x00\x02\x07\x00\x1B\x01\x07\x00\x1B\x01\x01\x00\x00\x00\x86\x00\x06\x07\x00\x02\x07\x00\x1B\x01\x07\x00\x1B\x01\x01\x00\x01\x01\x00\xA2\x00\x06\x07\x00\x02\x07\x00\x1B\x01\x07\x00\x1B\x01\x01\x00\x00'
    .end code
    .exceptions java/io/IOException
.end method

.method public short : (I)V
    .code stack 2 locals 2
L0:     aload_0
L1:     getfield Field AC do Ljava/io/DataOutputStream;
L4:     iload_1
L5:     invokevirtual Method java/io/DataOutputStream writeInt (I)V
L8:     return
L9:     
    .end code
    .exceptions java/io/IOException
.end method

.method public const : (I)V
    .code stack 2 locals 2
L0:     aload_0
L1:     getfield Field AC do Ljava/io/DataOutputStream;
L4:     iload_1
L5:     invokevirtual Method java/io/DataOutputStream writeByte (I)V
L8:     return
L9:     
    .end code
    .exceptions java/io/IOException
.end method

.method public else : (I)V
    .code stack 2 locals 2
L0:     aload_0
L1:     getfield Field AC do Ljava/io/DataOutputStream;
L4:     iload_1
L5:     invokevirtual Method java/io/DataOutputStream writeShort (I)V
L8:     return
L9:     
    .end code
    .exceptions java/io/IOException
.end method

.method public else : ([B)V
    .code stack 2 locals 2
L0:     aload_0
L1:     getfield Field AC do Ljava/io/DataOutputStream;
L4:     aload_1
L5:     invokevirtual Method java/io/DataOutputStream write ([B)V
L8:     return
L9:     
    .end code
    .exceptions java/io/IOException
.end method

.method public else : (Ljava/lang/String;)V
    .code stack 4 locals 2
L0:     aload_0
L1:     aload_1
L2:     ifnull L13
L5:     iconst_1
L6:     dup
L7:     dup
L8:     pop2
L9:     goto L17
L12:    athrow
L13:    iconst_0
L14:    iconst_1
L15:    dup
L16:    pop2
L17:    invokevirtual Method AC break (Z)V
L20:    aload_1
L21:    ifnull L29
L24:    aload_0
L25:    aload_1
L26:    invokevirtual Method AC break (Ljava/lang/String;)V
L29:    return
L30:    
        .attribute StackMap b'\x00\x04\x00\x0C\x00\x00\x00\x01\x07\x00\x19\x00\x0D\x00\x02\x07\x00\x02\x07\x00\x32\x00\x01\x07\x00\x02\x00\x11\x00\x02\x07\x00\x02\x07\x00\x32\x00\x02\x07\x00\x02\x01\x00\x1D\x00\x02\x07\x00\x02\x07\x00\x32\x00\x00'
    .end code
    .exceptions java/io/IOException
.end method

.method public break : ([S)V
    .code stack 3 locals 5
L0:     aload_0
L1:     aload_1
L2:     arraylength
L3:     invokevirtual Method AC break (I)V
L6:     aload_1
L7:     dup
L8:     astore_1
L9:     arraylength
L10:    istore_2
L11:    iconst_0
L12:    iconst_1
L13:    dup
L14:    pop2
L15:    dup
L16:    istore_3
L17:    iload_2
L18:    if_icmpge L43
L21:    aload_0
L22:    aload_1
L23:    iload_3
L24:    iinc 3 1
L27:    saload
L28:    istore 4
L30:    getfield Field AC do Ljava/io/DataOutputStream;
L33:    iload 4
L35:    invokevirtual Method java/io/DataOutputStream writeShort (I)V
L38:    iload_3
L39:    goto L17
L42:    athrow
L43:    return
L44:    
        .attribute StackMap b'\x00\x03\x00\x11\x00\x04\x07\x00\x02\x07\x00\x3A\x01\x01\x00\x01\x01\x00\x2A\x00\x00\x00\x01\x07\x00\x19\x00\x2B\x00\x04\x07\x00\x02\x07\x00\x3A\x01\x01\x00\x00'
    .end code
    .exceptions java/io/IOException
.end method

.method public break : (D)V
    .code stack 3 locals 3
L0:     aload_0
L1:     getfield Field AC do Ljava/io/DataOutputStream;
L4:     dload_1
L5:     invokevirtual Method java/io/DataOutputStream writeDouble (D)V
L8:     return
L9:     
    .end code
    .exceptions java/io/IOException
.end method

.method public else : ()V
    .code stack 1 locals 1
L0:     aload_0
L1:     getfield Field AC do Ljava/io/DataOutputStream;
L4:     invokevirtual Method java/io/DataOutputStream flush ()V
L7:     return
L8:     
    .end code
    .exceptions java/io/IOException
.end method

.method public break : ([[S)V
    .code stack 3 locals 5
L0:     aload_0
L1:     aload_1
L2:     arraylength
L3:     invokevirtual Method AC break (I)V
L6:     aload_1
L7:     dup
L8:     astore_1
L9:     arraylength
L10:    istore_2
L11:    iconst_0
L12:    iconst_1
L13:    dup
L14:    pop2
L15:    dup
L16:    istore_3
L17:    iload_2
L18:    if_icmpge L40
L21:    aload_1
L22:    iload_3
L23:    iinc 3 1
L26:    aaload
L27:    astore 4
L29:    aload_0
L30:    aload 4
L32:    invokevirtual Method AC break ([S)V
L35:    iload_3
L36:    goto L17
L39:    athrow
L40:    return
L41:    
        .attribute StackMap b'\x00\x03\x00\x11\x00\x04\x07\x00\x02\x07\x00\x45\x01\x01\x00\x01\x01\x00\x27\x00\x00\x00\x01\x07\x00\x19\x00\x28\x00\x04\x07\x00\x02\x07\x00\x45\x01\x01\x00\x00'
    .end code
    .exceptions java/io/IOException
.end method

.method public break : (Ljava/lang/String;)V
    .code stack 2 locals 2
L0:     aload_0
L1:     getfield Field AC do Ljava/io/DataOutputStream;
L4:     aload_1
L5:     invokevirtual Method java/io/DataOutputStream writeUTF (Ljava/lang/String;)V
L8:     return
L9:     
    .end code
    .exceptions java/io/IOException
.end method

.method public break : (Z)V
    .code stack 5 locals 2
L0:     aload_0
L1:     getfield Field AC do Ljava/io/DataOutputStream;
L4:     invokestatic Method java/lang/Math random ()D
L7:     ldc2_w 2.56e2
L10:    dmul
L11:    d2i
L12:    sipush 251
L15:    iconst_1
L16:    dup
L17:    pop2
L18:    iand
L19:    iload_1
L20:    ifeq L31
L23:    iconst_4
L24:    iconst_1
L25:    dup
L26:    pop2
L27:    goto L35
L30:    athrow
L31:    iconst_0
L32:    iconst_1
L33:    dup
L34:    pop2
L35:    ior
L36:    invokevirtual Method java/io/DataOutputStream writeByte (I)V
L39:    return
L40:    
        .attribute StackMap b'\x00\x03\x00\x1E\x00\x00\x00\x01\x07\x00\x19\x00\x1F\x00\x02\x07\x00\x02\x01\x00\x02\x07\x00\x1F\x01\x00\x23\x00\x02\x07\x00\x02\x01\x00\x03\x07\x00\x1F\x01\x01'
    .end code
    .exceptions java/io/IOException
.end method

.method public break : (F)V
    .code stack 2 locals 2
L0:     aload_0
L1:     getfield Field AC do Ljava/io/DataOutputStream;
L4:     fload_1
L5:     invokevirtual Method java/io/DataOutputStream writeFloat (F)V
L8:     return
L9:     
    .end code
    .exceptions java/io/IOException
.end method

.method public break : (Ljava/util/Set;)V
    .code stack 3 locals 3
L0:     aload_0
L1:     aload_1
L2:     dup_x1
L3:     invokeinterface InterfaceMethod java/util/Set size ()I 1
L8:     invokevirtual Method AC break (I)V
L11:    invokeinterface InterfaceMethod java/util/Set iterator ()Ljava/util/Iterator; 1
L16:    dup
L17:    astore_1
L18:    invokeinterface InterfaceMethod java/util/Iterator hasNext ()Z 1
L23:    ifeq L49
L26:    aload_1
L27:    invokeinterface InterfaceMethod java/util/Iterator next ()Ljava/lang/Object; 1
L32:    checkcast Uf
L35:    astore_2
L36:    aload_1
L37:    aload_0
L38:    aload_2
L39:    getfield Field Uf null Ljava/lang/String;
L42:    invokevirtual Method AC break (Ljava/lang/String;)V
L45:    goto L18
L48:    athrow
L49:    return
L50:    
        .attribute StackMap b'\x00\x03\x00\x12\x00\x02\x07\x00\x02\x07\x00\x63\x00\x01\x07\x00\x63\x00\x30\x00\x00\x00\x01\x07\x00\x19\x00\x31\x00\x02\x07\x00\x02\x07\x00\x63\x00\x00'
    .end code
    .exceptions java/io/IOException
.end method

.method public break : (Ljava/util/Map;)V
    .code stack 3 locals 3
L0:     aload_0
L1:     aload_1
L2:     dup_x1
L3:     invokeinterface InterfaceMethod java/util/Map size ()I 1
L8:     invokevirtual Method AC break (I)V
L11:    invokeinterface InterfaceMethod java/util/Map entrySet ()Ljava/util/Set; 1
L16:    invokeinterface InterfaceMethod java/util/Set iterator ()Ljava/util/Iterator; 1
L21:    dup
L22:    astore_1
L23:    invokeinterface InterfaceMethod java/util/Iterator hasNext ()Z 1
L28:    ifeq L72
L31:    aload_1
L32:    invokeinterface InterfaceMethod java/util/Iterator next ()Ljava/lang/Object; 1
L37:    checkcast java/util/Map$Entry
L40:    astore_2
L41:    aload_0
L42:    aload_2
L43:    invokeinterface InterfaceMethod java/util/Map$Entry getKey ()Ljava/lang/Object; 1
L48:    checkcast java/lang/String
L51:    invokevirtual Method AC break (Ljava/lang/String;)V
L54:    aload_0
L55:    aload_2
L56:    invokeinterface InterfaceMethod java/util/Map$Entry getValue ()Ljava/lang/Object; 1
L61:    checkcast java/lang/String
L64:    invokevirtual Method AC else (Ljava/lang/String;)V
L67:    aload_1
L68:    goto L23
L71:    athrow
L72:    return
L73:    
        .attribute StackMap b'\x00\x03\x00\x17\x00\x02\x07\x00\x02\x07\x00\x63\x00\x01\x07\x00\x63\x00\x47\x00\x00\x00\x01\x07\x00\x19\x00\x48\x00\x02\x07\x00\x02\x07\x00\x63\x00\x00'
    .end code
    .exceptions java/io/IOException
.end method

.method public break : ([B)V
    .code stack 2 locals 2
L0:     aload_0
L1:     aload_1
L2:     arraylength
L3:     invokevirtual Method AC break (I)V
L6:     aload_0
L7:     aload_1
L8:     invokevirtual Method AC else ([B)V
L11:    return
L12:    
    .end code
    .exceptions java/io/IOException
.end method

.method public break : ()V
    .code stack 1 locals 1
L0:     aload_0
L1:     getfield Field AC do Ljava/io/DataOutputStream;
L4:     invokevirtual Method java/io/DataOutputStream close ()V
L7:     return
L8:     
    .end code
    .exceptions java/io/IOException
.end method

.method public <init> : (Ljava/io/OutputStream;)V
    .code stack 4 locals 2
L0:     aload_0
L1:     invokespecial Method java/lang/Object <init> ()V
L4:     new java/io/DataOutputStream
L7:     aload_0
L8:     dup_x1
L9:     dup
L10:    pop2
L11:    dup
L12:    aload_1
L13:    invokespecial Method java/io/DataOutputStream <init> (Ljava/io/OutputStream;)V
L16:    putfield Field AC do Ljava/io/DataOutputStream;
L19:    return
L20:    
    .end code
    .exceptions java/io/IOException
.end method

.method public break : (J)V
    .code stack 3 locals 3
L0:     aload_0
L1:     getfield Field AC do Ljava/io/DataOutputStream;
L4:     lload_1
L5:     invokevirtual Method java/io/DataOutputStream writeLong (J)V
L8:     return
L9:     
    .end code
    .exceptions java/io/IOException
.end method

.method public break : (I)V
    .code stack 5 locals 2
L0:     iload_1
L1:     bipush -127
L3:     iconst_1
L4:     dup
L5:     pop2
L6:     if_icmplt L28
L9:     iload_1
L10:    bipush 127
L12:    iconst_1
L13:    dup
L14:    pop2
L15:    if_icmpgt L28
L18:    aload_0
L19:    getfield Field AC do Ljava/io/DataOutputStream;
L22:    iload_1
L23:    invokevirtual Method java/io/DataOutputStream writeByte (I)V
L26:    return
L27:    athrow
L28:    aload_0
L29:    dup
L30:    getfield Field AC do Ljava/io/DataOutputStream;
L33:    bipush -128
L35:    iconst_1
L36:    dup
L37:    pop2
L38:    invokevirtual Method java/io/DataOutputStream writeByte (I)V
L41:    getfield Field AC do Ljava/io/DataOutputStream;
L44:    iload_1
L45:    invokevirtual Method java/io/DataOutputStream writeInt (I)V
L48:    return
L49:    
        .attribute StackMap b'\x00\x02\x00\x1B\x00\x00\x00\x01\x07\x00\x19\x00\x1C\x00\x02\x07\x00\x02\x01\x00\x00'
    .end code
    .exceptions java/io/IOException
.end method
.innerclasses
    java/util/Map$Entry java/util/Map Entry public static interface abstract
.end innerclasses
.end class
