.version 49 0
.class public final super Ac
.super vB
.field private field1014 Led;
.field private field1015 LYg;

.method public static synthetic method503 : (LAc;)LFE;
    .code stack 1 locals 1
L0:     aload_0
L1:     getfield Field Ac field1136 LFE;
L4:     areturn
L5:     
    .end code
.end method

.method public <init> : (Led;)V
    .code stack 3 locals 2
L0:     aload_1
L1:     aload_0
L2:     dup_x1
L3:     invokespecial Method vB <init> ()V
L6:     putfield Field Ac field1014 Led;
L9:     return
L10:    
    .end code
.end method

.method public method49 : ()V
    .code stack 12 locals 5
L0:     getstatic Field Kc field1931 LKc;
L3:     getstatic Field Pc field373 LPc;
L6:     invokevirtual Method Kc method853 (LPc;)Led;
L9:     astore_1
L10:    new qc
L13:    dup
L14:    new VD
L17:    dup
L18:    invokespecial Method VD <init> ()V
L21:    invokespecial Method qc <init> (Ld;)V
L24:    astore_2
L25:    new EG
L28:    aload_2
L29:    dup_x1
L30:    dup_x2
L31:    dup
L32:    pop2
L33:    dup
L34:    aload_1
L35:    getfield Field ed new Ljava/lang/String;
L38:    ldc 3.6e-1f
L40:    dup
L41:    invokespecial Method EG <init> (Ljava/lang/String;FF)V
L44:    ldc 1e-1f
L46:    new DF
L49:    dup
L50:    aload_1
L51:    getfield Field ed field701 Ljava/lang/String;
L54:    invokespecial Method DF <init> (Ljava/lang/String;)V
L57:    invokestatic Method Wd method1092 (LgB;FLgB;)Lqc;
L60:    getstatic Field VD field149 Ljava/lang/Object;
L63:    invokevirtual Method qc method31 (LgB;Ljava/lang/Object;)V
L66:    new EG
L69:    aload_2
L70:    dup
L71:    pop2
L72:    dup
L73:    aload_0
L74:    getfield Field Ac field1014 Led;
L77:    getfield Field ed new Ljava/lang/String;
L80:    ldc 3.6e-1f
L82:    dup
L83:    invokespecial Method EG <init> (Ljava/lang/String;FF)V
L86:    ldc 1e-1f
L88:    new DF
L91:    dup
L92:    aload_0
L93:    getfield Field Ac field1014 Led;
L96:    getfield Field ed field701 Ljava/lang/String;
L99:    invokespecial Method DF <init> (Ljava/lang/String;)V
L102:   invokestatic Method Wd method1092 (LgB;FLgB;)Lqc;
L105:   getstatic Field VD this Ljava/lang/Object;
L108:   invokevirtual Method qc method31 (LgB;Ljava/lang/Object;)V
L111:   new qc
L114:   dup
L115:   new VD
L118:   dup
L119:   invokespecial Method VD <init> ()V
L122:   invokespecial Method qc <init> (Ld;)V
L125:   astore_3
L126:   new DF
L129:   aload_3
L130:   dup_x1
L131:   dup_x2
L132:   dup
L133:   pop2
L134:   dup
L135:   new java/lang/StringBuilder
L138:   dup
L139:   invokespecial Method java/lang/StringBuilder <init> ()V
L142:   iconst_0
L143:   ldc "\u2605"
L145:   invokevirtual Method java/lang/StringBuilder insert (ILjava/lang/String;)Ljava/lang/StringBuilder;
L148:   aload_1
L149:   invokevirtual Method ed method134 ()I
L152:   invokevirtual Method java/lang/StringBuilder append (I)Ljava/lang/StringBuilder;
L155:   invokevirtual Method java/lang/StringBuilder toString ()Ljava/lang/String;
L158:   getstatic Field We field492 LWe;
L161:   invokespecial Method DF <init> (Ljava/lang/String;LWe;)V
L164:   ldc 2.2e0f
L166:   invokestatic Method Wd method1095 (LgB;F)Lqc;
L169:   getstatic Field VD field149 Ljava/lang/Object;
L172:   invokevirtual Method qc method31 (LgB;Ljava/lang/Object;)V
L175:   new DF
L178:   aload_3
L179:   dup
L180:   pop2
L181:   dup
L182:   ldc "Total"
L184:   getstatic Field vD field358 LvD;
L187:   invokespecial Method DF <init> (Ljava/lang/String;LvD;)V
L190:   invokevirtual Method qc method36 (LgB;)LgB;
L193:   new DF
L196:   aload_3
L197:   dup_x1
L198:   dup
L199:   pop2
L200:   dup
L201:   new java/lang/StringBuilder
L204:   dup
L205:   invokespecial Method java/lang/StringBuilder <init> ()V
L208:   iconst_0
L209:   ldc "\u2605"
L211:   invokevirtual Method java/lang/StringBuilder insert (ILjava/lang/String;)Ljava/lang/StringBuilder;
L214:   aload_0
L215:   getfield Field Ac field1014 Led;
L218:   invokevirtual Method ed method134 ()I
L221:   invokevirtual Method java/lang/StringBuilder append (I)Ljava/lang/StringBuilder;
L224:   invokevirtual Method java/lang/StringBuilder toString ()Ljava/lang/String;
L227:   getstatic Field We field492 LWe;
L230:   invokespecial Method DF <init> (Ljava/lang/String;LWe;)V
L233:   ldc 2.2e0f
L235:   invokestatic Method Wd method1095 (LgB;F)Lqc;
L238:   getstatic Field VD this Ljava/lang/Object;
L241:   invokevirtual Method qc method31 (LgB;Ljava/lang/Object;)V
L244:   new qc
L247:   dup
L248:   new VD
L251:   dup
L252:   invokespecial Method VD <init> ()V
L255:   invokespecial Method qc <init> (Ld;)V
L258:   astore 4
L260:   aload_0
L261:   aload_1
L262:   aload 4
L264:   dup_x2
L265:   new SB
L268:   aload 4
L270:   dup
L271:   pop2
L272:   dup
L273:   aload_2
L274:   ldc 5e-1f
L276:   fconst_0
L277:   dup_x1
L278:   dup_x2
L279:   invokespecial Method SB <init> (LgB;FFFF)V
L282:   getstatic Field VD field150 Ljava/lang/Object;
L285:   invokevirtual Method qc method31 (LgB;Ljava/lang/Object;)V
L288:   aload_0
L289:   getfield Field Ac field1014 Led;
L292:   invokespecial Method Ac method504 (Led;Led;)LgB;
L295:   invokevirtual Method qc method36 (LgB;)LgB;
L298:   new SB
L301:   aload 4
L303:   dup_x1
L304:   dup
L305:   pop2
L306:   dup
L307:   aload_3
L308:   ldc 5e-1f
L310:   fconst_0
L311:   dup_x1
L312:   dup_x2
L313:   invokespecial Method SB <init> (LgB;FFFF)V
L316:   getstatic Field VD field148 Ljava/lang/Object;
L319:   invokevirtual Method qc method31 (LgB;Ljava/lang/Object;)V
L322:   new qc
L325:   dup
L326:   new fG
L329:   dup
L330:   getstatic Field LE field634 LLE;
L333:   ldc 3e-1f
L335:   invokespecial Method fG <init> (LLE;F)V
L338:   invokespecial Method qc <init> (Ld;)V
L341:   astore_1
L342:   new Vg
L345:   aload_1
L346:   dup_x1
L347:   dup
L348:   pop2
L349:   dup
L350:   fconst_0
L351:   ldc 2e-1f
L353:   invokespecial Method Vg <init> (FF)V
L356:   invokevirtual Method qc method36 (LgB;)LgB;
L359:   pop
L360:   pop2
L361:   aload_1
L362:   new Yg
L365:   aload_0
L366:   dup_x1
L367:   dup
L368:   pop2
L369:   dup
L370:   ldc "OK"
L372:   new tB
L375:   dup
L376:   aload_0
L377:   invokespecial Method tB <init> (LAc;)V
L380:   invokespecial Method Yg <init> (Ljava/lang/String;Lh;)V
L383:   dup_x1
L384:   putfield Field Ac field1015 LYg;
L387:   getstatic Field dg field335 Ldg;
L390:   invokevirtual Method qc method31 (LgB;Ljava/lang/Object;)V
L393:   new qc
L396:   dup
L397:   new VD
L400:   dup
L401:   invokespecial Method VD <init> ()V
L404:   invokespecial Method qc <init> (Ld;)V
L407:   dup
L408:   astore_2
L409:   aload 4
L411:   invokevirtual Method qc method36 (LgB;)LgB;
L414:   aload_0
L415:   aload_2
L416:   dup
L417:   aload_1
L418:   getstatic Field VD field148 Ljava/lang/Object;
L421:   invokevirtual Method qc method31 (LgB;Ljava/lang/Object;)V
L424:   invokestatic Method Wd method1093 (LgB;)Lqc;
L427:   invokevirtual Method Ac method36 (LgB;)LgB;
L430:   pop2
L431:   return
L432:   
    .end code
.end method

.method private method504 : (Led;Led;)LgB;
    .code stack 10 locals 10
L0:     new qc
L3:     dup
L4:     new fG
L7:     dup
L8:     getstatic Field LE field634 LLE;
L11:    ldc 3.5e-1f
L13:    invokespecial Method fG <init> (LLE;F)V
L16:    invokespecial Method qc <init> (Ld;)V
L19:    astore_3
L20:    new java/util/ArrayList
L23:    dup
L24:    aload_1
L25:    getfield Field ed field704 Ljava/util/Set;
L28:    invokespecial Method java/util/ArrayList <init> (Ljava/util/Collection;)V
L31:    astore 4
L33:    aload_2
L34:    getfield Field ed field704 Ljava/util/Set;
L37:    invokeinterface InterfaceMethod java/util/Set iterator ()Ljava/util/Iterator; 1
L42:    astore 5
L44:    aload 5
L46:    invokeinterface InterfaceMethod java/util/Iterator hasNext ()Z 1
L51:    ifeq L92
L54:    aload 5
L56:    invokeinterface InterfaceMethod java/util/Iterator next ()Ljava/lang/Object; 1
L61:    checkcast Uf
L64:    astore 6
L66:    aload 4
L68:    aload 6
L70:    invokeinterface InterfaceMethod java/util/List contains (Ljava/lang/Object;)Z 2
L75:    ifne L44
L78:    aload 4
L80:    aload 6
L82:    invokeinterface InterfaceMethod java/util/List add (Ljava/lang/Object;)Z 2
L87:    pop
L88:    goto L44
L91:    athrow
L92:    aload 4
L94:    dup
L95:    new AD
L98:    dup
L99:    aload_0
L100:   aload_2
L101:   invokespecial Method AD <init> (LAc;Led;)V
L104:   invokestatic Method java/util/Collections sort (Ljava/util/List;Ljava/util/Comparator;)V
L107:   invokeinterface InterfaceMethod java/util/List iterator ()Ljava/util/Iterator; 1
L112:   dup
L113:   astore 5
L115:   invokeinterface InterfaceMethod java/util/Iterator hasNext ()Z 1
L120:   ifeq L488
L123:   aload 5
L125:   invokeinterface InterfaceMethod java/util/Iterator next ()Ljava/lang/Object; 1
L130:   checkcast Uf
L133:   astore 6
L135:   new qc
L138:   dup
L139:   new VD
L142:   dup
L143:   invokespecial Method VD <init> ()V
L146:   invokespecial Method qc <init> (Ld;)V
L149:   astore 4
L151:   new DF
L154:   aload 4
L156:   dup_x1
L157:   dup_x2
L158:   dup
L159:   pop2
L160:   dup
L161:   aload 6
L163:   getfield Field Uf field1351 Ljava/lang/String;
L166:   getstatic Field We field478 LWe;
L169:   invokespecial Method DF <init> (Ljava/lang/String;LWe;)V
L172:   getstatic Field VD field150 Ljava/lang/Object;
L175:   invokevirtual Method qc method31 (LgB;Ljava/lang/Object;)V
L178:   new DF
L181:   aload 4
L183:   dup
L184:   pop2
L185:   dup
L186:   aload 6
L188:   getfield Field Uf this Ljava/lang/String;
L191:   getstatic Field We field480 LWe;
L194:   invokespecial Method DF <init> (Ljava/lang/String;LWe;)V
L197:   getstatic Field VD field147 Ljava/lang/Object;
L200:   invokevirtual Method qc method31 (LgB;Ljava/lang/Object;)V
L203:   new qc
L206:   dup
L207:   new VD
L210:   dup
L211:   invokespecial Method VD <init> ()V
L214:   invokespecial Method qc <init> (Ld;)V
L217:   astore 7
L219:   new DF
L222:   aload 7
L224:   dup_x1
L225:   dup
L226:   pop2
L227:   dup
L228:   aload_1
L229:   getfield Field ed field704 Ljava/util/Set;
L232:   aload 6
L234:   invokeinterface InterfaceMethod java/util/Set contains (Ljava/lang/Object;)Z 2
L239:   ifeq L270
L242:   new java/lang/StringBuilder
L245:   dup
L246:   invokespecial Method java/lang/StringBuilder <init> ()V
L249:   aload 6
L251:   getfield Field Uf field1349 I
L254:   invokevirtual Method java/lang/StringBuilder append (I)Ljava/lang/StringBuilder;
L257:   ldc_w ""
L260:   invokevirtual Method java/lang/StringBuilder append (Ljava/lang/String;)Ljava/lang/StringBuilder;
L263:   invokevirtual Method java/lang/StringBuilder toString ()Ljava/lang/String;
L266:   goto L273
L269:   athrow
L270:   ldc_w "--"
L273:   getstatic Field We field492 LWe;
L276:   invokespecial Method DF <init> (Ljava/lang/String;LWe;)V
L279:   getstatic Field VD field147 Ljava/lang/Object;
L282:   invokevirtual Method qc method31 (LgB;Ljava/lang/Object;)V
L285:   new Vg
L288:   aload 7
L290:   dup_x1
L291:   dup_x2
L292:   dup
L293:   pop2
L294:   dup
L295:   ldc_w 2.4e0f
L298:   fconst_0
L299:   invokespecial Method Vg <init> (FF)V
L302:   getstatic Field VD field150 Ljava/lang/Object;
L305:   invokevirtual Method qc method31 (LgB;Ljava/lang/Object;)V
L308:   new Vg
L311:   aload 7
L313:   dup
L314:   pop2
L315:   dup
L316:   ldc 2e-1f
L318:   fconst_0
L319:   invokespecial Method Vg <init> (FF)V
L322:   getstatic Field VD this Ljava/lang/Object;
L325:   invokevirtual Method qc method31 (LgB;Ljava/lang/Object;)V
L328:   new qc
L331:   dup
L332:   new VD
L335:   dup
L336:   invokespecial Method VD <init> ()V
L339:   invokespecial Method qc <init> (Ld;)V
L342:   astore 8
L344:   new DF
L347:   aload 8
L349:   dup_x1
L350:   dup
L351:   pop2
L352:   dup
L353:   aload_2
L354:   getfield Field ed field704 Ljava/util/Set;
L357:   aload 6
L359:   invokeinterface InterfaceMethod java/util/Set contains (Ljava/lang/Object;)Z 2
L364:   ifeq L394
L367:   new java/lang/StringBuilder
L370:   dup
L371:   invokespecial Method java/lang/StringBuilder <init> ()V
L374:   aload 6
L376:   getfield Field Uf field1349 I
L379:   invokevirtual Method java/lang/StringBuilder append (I)Ljava/lang/StringBuilder;
L382:   ldc_w ""
L385:   invokevirtual Method java/lang/StringBuilder append (Ljava/lang/String;)Ljava/lang/StringBuilder;
L388:   invokevirtual Method java/lang/StringBuilder toString ()Ljava/lang/String;
L391:   goto L397
L394:   ldc_w "--"
L397:   getstatic Field We field492 LWe;
L400:   invokespecial Method DF <init> (Ljava/lang/String;LWe;)V
L403:   getstatic Field VD field147 Ljava/lang/Object;
L406:   invokevirtual Method qc method31 (LgB;Ljava/lang/Object;)V
L409:   new Vg
L412:   aload 8
L414:   dup_x1
L415:   dup
L416:   pop2
L417:   dup
L418:   ldc 2.2e0f
L420:   fconst_0
L421:   invokespecial Method Vg <init> (FF)V
L424:   getstatic Field VD field150 Ljava/lang/Object;
L427:   invokevirtual Method qc method31 (LgB;Ljava/lang/Object;)V
L430:   new qc
L433:   dup
L434:   new VD
L437:   dup
L438:   invokespecial Method VD <init> ()V
L441:   invokespecial Method qc <init> (Ld;)V
L444:   astore 9
L446:   aload 5
L448:   aload_3
L449:   aload 8
L451:   aload 9
L453:   dup_x1
L454:   dup_x2
L455:   aload 4
L457:   aload 9
L459:   aload 7
L461:   getstatic Field VD field149 Ljava/lang/Object;
L464:   invokevirtual Method qc method31 (LgB;Ljava/lang/Object;)V
L467:   getstatic Field VD field147 Ljava/lang/Object;
L470:   invokevirtual Method qc method31 (LgB;Ljava/lang/Object;)V
L473:   getstatic Field VD this Ljava/lang/Object;
L476:   invokevirtual Method qc method31 (LgB;Ljava/lang/Object;)V
L479:   getstatic Field dg field337 Ldg;
L482:   invokevirtual Method qc method31 (LgB;Ljava/lang/Object;)V
L485:   goto L115
L488:   new Cd
L491:   dup
L492:   aload_3
L493:   invokespecial Method Cd <init> (LgB;)V
L496:   areturn
L497:   
        .attribute StackMap b'\x00\x0A\x00\x2C\x00\x06\x07\x00\x02\x07\x00\x42\x07\x00\x42\x07\x00\x38\x07\x00\xC8\x07\x00\xD7\x00\x00\x00\x5B\x00\x00\x00\x01\x07\x00\xEC\x00\x5C\x00\x06\x07\x00\x02\x07\x00\x42\x07\x00\x42\x07\x00\x38\x07\x00\xC8\x07\x00\xD7\x00\x00\x00\x73\x00\x06\x07\x00\x02\x07\x00\x42\x07\x00\x42\x07\x00\x38\x07\x00\xF8\x07\x00\xD7\x00\x01\x07\x00\xD7\x01\x0D\x00\x00\x00\x01\x07\x00\xEC\x01\x0E\x00\x08\x07\x00\x02\x07\x00\x42\x07\x00\x42\x07\x00\x38\x07\x00\x38\x07\x00\xD7\x07\x00\xE1\x07\x00\x38\x00\x03\x07\x00\x38\x08\x00\xDB\x08\x00\xDB\x01\x11\x00\x08\x07\x00\x02\x07\x00\x42\x07\x00\x42\x07\x00\x38\x07\x00\x38\x07\x00\xD7\x07\x00\xE1\x07\x00\x38\x00\x04\x07\x00\x38\x08\x00\xDB\x08\x00\xDB\x07\x01\x14\x01\x8A\x00\x09\x07\x00\x02\x07\x00\x42\x07\x00\x42\x07\x00\x38\x07\x00\x38\x07\x00\xD7\x07\x00\xE1\x07\x00\x38\x07\x00\x38\x00\x03\x07\x00\x38\x08\x01\x58\x08\x01\x58\x01\x8D\x00\x09\x07\x00\x02\x07\x00\x42\x07\x00\x42\x07\x00\x38\x07\x00\x38\x07\x00\xD7\x07\x00\xE1\x07\x00\x38\x07\x00\x38\x00\x04\x07\x00\x38\x08\x01\x58\x08\x01\x58\x07\x01\x14\x01\xE8\x00\x06\x07\x00\x02\x07\x00\x42\x07\x00\x42\x07\x00\x38\x07\x00\xF8\x07\x00\xD7\x00\x00'
    .end code
.end method

.method public method57 : (LgB;IC)Z
    .code stack 4 locals 4
L0:     iload_2
L1:     iconst_1
L2:     dup
L3:     dup
L4:     pop2
L5:     if_icmpne L16
L8:     aload_0
L9:     getfield Field Ac field1136 LFE;
L12:    aload_0
L13:    invokevirtual Method FE method203 (LbC;)V
L16:    iconst_1
L17:    dup
L18:    dup
L19:    pop2
L20:    ireturn
L21:    
        .attribute StackMap b'\x00\x01\x00\x10\x00\x04\x07\x00\x02\x07\x01\x27\x01\x01\x00\x00'
    .end code
.end method

.method public method10 : ()V
    .code stack 2 locals 1
L0:     aload_0
L1:     dup
L2:     getfield Field Ac field1015 LYg;
L5:     invokevirtual Method Ac try (LgB;)V
L8:     return
L9:     
    .end code
.end method
.innerclasses
    AD [0] [0]
    LE fG [0] public static final enum
    Pc JB [0] public static final enum
    dg fG [0] public static final enum
    tB [0] [0]
    vD DF [0] public static final enum
.end innerclasses
.end class
