.version 49 0
.class public final super ad
.super java/lang/Object
.implements java/lang/Runnable
.field public final synthetic field1683 Lwb;

.method public run : ()V
    .code stack 5 locals 5
L0:     aconst_null
L1:     astore_1
        .catch java/io/IOException from L2 to L76 using L154
L2:     new java/io/DataInputStream
L5:     dup
L6:     new java/io/BufferedInputStream
L9:     dup
L10:    aload_0
L11:    getfield Field ad field1683 Lwb;
L14:    getfield Field wb new Ljava/net/Socket;
L17:    invokevirtual Method java/net/Socket getInputStream ()Ljava/io/InputStream;
L20:    invokespecial Method java/io/BufferedInputStream <init> (Ljava/io/InputStream;)V
L23:    invokespecial Method java/io/DataInputStream <init> (Ljava/io/InputStream;)V
L26:    dup
L27:    astore_1
L28:    invokevirtual Method java/io/DataInputStream read ()I
L31:    i2b
L32:    istore_2
L33:    aload_1
L34:    invokevirtual Method java/io/DataInputStream readByte ()B
L37:    iload_2
L38:    ixor
L39:    dup
L40:    istore_3
L41:    bipush -128
L43:    iconst_1
L44:    dup
L45:    pop2
L46:    if_icmpne L66
L49:    aload_1
L50:    invokevirtual Method java/io/DataInputStream readInt ()I
L53:    iload_2
L54:    sipush 255
L57:    iconst_1
L58:    dup
L59:    pop2
L60:    iand
L61:    ldc 16843009
L63:    imul
L64:    ixor
L65:    istore_3
L66:    iinc 3 127
L69:    iload_3
L70:    ifne L77
L73:    goto L155
L76:    athrow
        .catch java/io/IOException from L77 to L118 using L154
L77:    iload_3
L78:    newarray byte
L80:    iconst_1
L81:    dup
L82:    pop2
L83:    astore_3
L84:    iconst_0
L85:    aload_1
L86:    aload_3
L87:    invokevirtual Method java/io/DataInputStream readFully ([B)V
L90:    iconst_1
L91:    dup
L92:    pop2
L93:    dup
L94:    istore 4
L96:    aload_3
L97:    arraylength
L98:    if_icmpge L119
L101:   aload_3
L102:   iload 4
L104:   dup2
L105:   baload
L106:   iload_2
L107:   ixor
L108:   i2b
L109:   iinc 4 1
L112:   bastore
L113:   iload 4
L115:   goto L96
L118:   athrow
        .catch java/io/IOException from L119 to L151 using L154
L119:   aload_0
L120:   getfield Field ad field1683 Lwb;
L123:   getfield Field wb field5831 Lbc;
L126:   getfield Field bc field798 Ljava/util/concurrent/LinkedBlockingQueue;
L129:   new fD
L132:   dup
L133:   aload_0
L134:   getfield Field ad field1683 Lwb;
L137:   getfield Field wb field5832 I
L140:   aload_3
L141:   invokespecial Method fD <init> (I[B)V
L144:   invokevirtual Method java/util/concurrent/LinkedBlockingQueue add (Ljava/lang/Object;)Z
L147:   pop
L148:   goto L33
L151:   nop
L152:   nop
L153:   athrow
L154:   astore_2
L155:   aload_1
L156:   ifnull L172
        .catch java/io/IOException from L159 to L163 using L167
L159:   aload_1
L160:   invokevirtual Method java/io/DataInputStream close ()V
L163:   aload_0
L164:   goto L173
L167:   astore_2
L168:   aload_2
L169:   invokevirtual Method java/io/IOException printStackTrace ()V
L172:   aload_0
L173:   getfield Field ad field1683 Lwb;
L176:   invokevirtual Method wb method5822 ()V
L179:   return
L180:   
        .attribute StackMap b'\x00\x0D\x00\x21\x00\x03\x07\x00\x02\x07\x00\x10\x01\x00\x00\x00\x42\x00\x04\x07\x00\x02\x07\x00\x10\x01\x01\x00\x00\x00\x4C\x00\x00\x00\x01\x07\x00\x31\x00\x4D\x00\x04\x07\x00\x02\x07\x00\x10\x01\x01\x00\x00\x00\x60\x00\x05\x07\x00\x02\x07\x00\x10\x01\x07\x00\x37\x01\x00\x01\x01\x00\x76\x00\x00\x00\x01\x07\x00\x31\x00\x77\x00\x05\x07\x00\x02\x07\x00\x10\x01\x07\x00\x37\x01\x00\x00\x00\x97\x00\x00\x00\x01\x07\x00\x31\x00\x9A\x00\x02\x07\x00\x02\x07\x00\x10\x00\x01\x07\x00\x0E\x00\x9B\x00\x02\x07\x00\x02\x07\x00\x10\x00\x00\x00\xA7\x00\x02\x07\x00\x02\x07\x00\x10\x00\x01\x07\x00\x0E\x00\xAC\x00\x02\x07\x00\x02\x07\x00\x10\x00\x00\x00\xAD\x00\x02\x07\x00\x02\x07\x00\x10\x00\x01\x07\x00\x02'
    .end code
.end method

.method public <init> : (Lwb;)V
    .code stack 3 locals 2
L0:     aload_0
L1:     dup
L2:     aload_1
L3:     putfield Field ad field1683 Lwb;
L6:     invokespecial Method java/lang/Object <init> ()V
L9:     return
L10:    
    .end code
.end method
.innerclasses
    ad [0] [0]
.end innerclasses
.enclosing method wb [0]
.end class
