.version 49 0
.class public final super enum Ae
.super java/lang/Enum
.field private static final synthetic "super" [LAe;
.field public static final enum int LAe;
.field public static final enum short LAe;
.field public static final enum goto LAe;
.field public static final enum break LAe;
.field public static final enum long LAe;
.field public static final enum void LAe;
.field public static final enum try LAe;
.field public static final enum const LAe;
.field public static final enum new LAe;
.field public static final enum null LAe;
.field public static final enum this LAe;
.field public static final enum char LAe;
.field public static final enum else LAe;
.field public static final enum "enum" LAe;
.field public static final enum do LAe;

.method public static <clinit> : ()V
    .code stack 6 locals 0
L0:     new Ae
L3:     dup
L4:     ldc "ERROR"
L6:     iconst_0
L7:     iconst_1
L8:     dup
L9:     pop2
L10:    invokespecial Method Ae <init> (Ljava/lang/String;I)V
L13:    putstatic Field Ae else LAe;
L16:    new Ae
L19:    dup
L20:    ldc "QUESTION"
L22:    iconst_1
L23:    dup
L24:    dup
L25:    pop2
L26:    invokespecial Method Ae <init> (Ljava/lang/String;I)V
L29:    putstatic Field Ae break LAe;
L32:    new Ae
L35:    dup
L36:    ldc "ARROW_UP"
L38:    iconst_2
L39:    iconst_1
L40:    dup
L41:    pop2
L42:    invokespecial Method Ae <init> (Ljava/lang/String;I)V
L45:    putstatic Field Ae try LAe;
L48:    new Ae
L51:    dup
L52:    ldc "ARROW_DOWN"
L54:    iconst_3
L55:    iconst_1
L56:    dup
L57:    pop2
L58:    invokespecial Method Ae <init> (Ljava/lang/String;I)V
L61:    putstatic Field Ae long LAe;
L64:    new Ae
L67:    dup
L68:    ldc "WAIT"
L70:    iconst_4
L71:    iconst_1
L72:    dup
L73:    pop2
L74:    invokespecial Method Ae <init> (Ljava/lang/String;I)V
L77:    putstatic Field Ae goto LAe;
L80:    new Ae
L83:    dup
L84:    ldc "INFO"
L86:    iconst_5
L87:    iconst_1
L88:    dup
L89:    pop2
L90:    invokespecial Method Ae <init> (Ljava/lang/String;I)V
L93:    putstatic Field Ae null LAe;
L96:    new Ae
L99:    dup
L100:   ldc "WARNING"
L102:   bipush 6
L104:   iconst_1
L105:   dup
L106:   pop2
L107:   invokespecial Method Ae <init> (Ljava/lang/String;I)V
L110:   putstatic Field Ae new LAe;
L113:   new Ae
L116:   dup
L117:   ldc "PRESS_A_KEY"
L119:   bipush 7
L121:   iconst_1
L122:   dup
L123:   pop2
L124:   invokespecial Method Ae <init> (Ljava/lang/String;I)V
L127:   putstatic Field Ae this LAe;
L130:   new Ae
L133:   dup
L134:   ldc "CHALLENGE_MASTERED_CROWN"
L136:   bipush 8
L138:   iconst_1
L139:   dup
L140:   pop2
L141:   invokespecial Method Ae <init> (Ljava/lang/String;I)V
L144:   putstatic Field Ae do LAe;
L147:   new Ae
L150:   dup
L151:   ldc "AWARD_FASTEST"
L153:   bipush 9
L155:   iconst_1
L156:   dup
L157:   pop2
L158:   invokespecial Method Ae <init> (Ljava/lang/String;I)V
L161:   putstatic Field Ae void LAe;
L164:   new Ae
L167:   dup
L168:   ldc "AWARD_MOST_LINES_SENT"
L170:   bipush 10
L172:   iconst_1
L173:   dup
L174:   pop2
L175:   invokespecial Method Ae <init> (Ljava/lang/String;I)V
L178:   putstatic Field Ae "enum" LAe;
L181:   new Ae
L184:   dup
L185:   ldc "AWARD_LEAST_LINES_SENT"
L187:   bipush 11
L189:   iconst_1
L190:   dup
L191:   pop2
L192:   invokespecial Method Ae <init> (Ljava/lang/String;I)V
L195:   putstatic Field Ae short LAe;
L198:   new Ae
L201:   dup
L202:   ldc "AWARD_MOST_LINES_RECEIVED"
L204:   bipush 12
L206:   iconst_1
L207:   dup
L208:   pop2
L209:   invokespecial Method Ae <init> (Ljava/lang/String;I)V
L212:   putstatic Field Ae char LAe;
L215:   new Ae
L218:   dup
L219:   ldc "AWARD_HIGHEST_COMBO"
L221:   bipush 13
L223:   iconst_1
L224:   dup
L225:   pop2
L226:   invokespecial Method Ae <init> (Ljava/lang/String;I)V
L229:   putstatic Field Ae int LAe;
L232:   new Ae
L235:   dup
L236:   ldc "GEWALTIG_ENTERTAINMENT"
L238:   bipush 14
L240:   iconst_1
L241:   dup
L242:   pop2
L243:   invokespecial Method Ae <init> (Ljava/lang/String;I)V
L246:   putstatic Field Ae const LAe;
L249:   bipush 15
L251:   iconst_1
L252:   dup
L253:   pop2
L254:   anewarray Ae
L257:   iconst_1
L258:   dup
L259:   pop2
L260:   dup
L261:   iconst_0
L262:   iconst_1
L263:   dup
L264:   pop2
L265:   getstatic Field Ae else LAe;
L268:   aastore
L269:   dup
L270:   iconst_1
L271:   dup
L272:   dup
L273:   pop2
L274:   getstatic Field Ae break LAe;
L277:   aastore
L278:   dup
L279:   iconst_2
L280:   iconst_1
L281:   dup
L282:   pop2
L283:   getstatic Field Ae try LAe;
L286:   aastore
L287:   dup
L288:   iconst_3
L289:   iconst_1
L290:   dup
L291:   pop2
L292:   getstatic Field Ae long LAe;
L295:   aastore
L296:   dup
L297:   iconst_4
L298:   iconst_1
L299:   dup
L300:   pop2
L301:   getstatic Field Ae goto LAe;
L304:   aastore
L305:   dup
L306:   iconst_5
L307:   iconst_1
L308:   dup
L309:   pop2
L310:   getstatic Field Ae null LAe;
L313:   aastore
L314:   dup
L315:   bipush 6
L317:   iconst_1
L318:   dup
L319:   pop2
L320:   getstatic Field Ae new LAe;
L323:   aastore
L324:   dup
L325:   bipush 7
L327:   iconst_1
L328:   dup
L329:   pop2
L330:   getstatic Field Ae this LAe;
L333:   aastore
L334:   dup
L335:   bipush 8
L337:   iconst_1
L338:   dup
L339:   pop2
L340:   getstatic Field Ae do LAe;
L343:   aastore
L344:   dup
L345:   bipush 9
L347:   iconst_1
L348:   dup
L349:   pop2
L350:   getstatic Field Ae void LAe;
L353:   aastore
L354:   dup
L355:   bipush 10
L357:   iconst_1
L358:   dup
L359:   pop2
L360:   getstatic Field Ae "enum" LAe;
L363:   aastore
L364:   dup
L365:   bipush 11
L367:   iconst_1
L368:   dup
L369:   pop2
L370:   getstatic Field Ae short LAe;
L373:   aastore
L374:   dup
L375:   bipush 12
L377:   iconst_1
L378:   dup
L379:   pop2
L380:   getstatic Field Ae char LAe;
L383:   aastore
L384:   dup
L385:   bipush 13
L387:   iconst_1
L388:   dup
L389:   pop2
L390:   getstatic Field Ae int LAe;
L393:   aastore
L394:   dup
L395:   bipush 14
L397:   iconst_1
L398:   dup
L399:   pop2
L400:   getstatic Field Ae const LAe;
L403:   aastore
L404:   putstatic Field Ae "super" [LAe;
L407:   return
L408:   
    .end code
.end method

.method public static valueOf : (Ljava/lang/String;)LAe;
    .code stack 2 locals 1
L0:     ldc Class Ae
L2:     aload_0
L3:     invokestatic Method java/lang/Enum valueOf (Ljava/lang/Class;Ljava/lang/String;)Ljava/lang/Enum;
L6:     checkcast Ae
L9:     areturn
L10:    
    .end code
.end method

.method public static values : ()[LAe;
    .code stack 1 locals 0
L0:     getstatic Field Ae "super" [LAe;
L3:     invokevirtual Method [LAe; clone ()Ljava/lang/Object;
L6:     checkcast [LAe;
L9:     areturn
L10:    
    .end code
.end method

.method private <init> : (Ljava/lang/String;I)V
    .code stack 3 locals 3
L0:     aload_0
L1:     aload_1
L2:     iload_2
L3:     invokespecial Method java/lang/Enum <init> (Ljava/lang/String;I)V
L6:     return
L7:     
    .end code
.end method
.innerclasses
    Ae ig [0] public static final enum
.end innerclasses
.end class
