.version 49 0
.class public final super aE
.super Uf
.field public do I

.method public break : (LRg;[[ILff;[I)Z
    .code stack 3 locals 5
L0:     aload 4
L2:     arraylength
L3:     ifne L12
L6:     iconst_0
L7:     iconst_1
L8:     dup
L9:     pop2
L10:    ireturn
L11:    athrow
L12:    new java/lang/StringBuilder
L15:    dup
L16:    invokespecial Method java/lang/StringBuilder <init> ()V
L19:    iconst_0
L20:    aload_1
L21:    getfield Field Rg false Led;
L24:    getfield Field ed else LPc;
L27:    getfield Field Pc char Ljava/lang/String;
L30:    invokevirtual Method java/lang/StringBuilder insert (ILjava/lang/String;)Ljava/lang/StringBuilder;
L33:    ldc "dls"
L35:    invokevirtual Method java/lang/StringBuilder append (Ljava/lang/String;)Ljava/lang/StringBuilder;
L38:    aload_0
L39:    getfield Field aE null Ljava/lang/String;
L42:    invokevirtual Method java/lang/StringBuilder append (Ljava/lang/String;)Ljava/lang/StringBuilder;
L45:    invokevirtual Method java/lang/StringBuilder toString ()Ljava/lang/String;
L48:    aload 4
L50:    arraylength
L51:    invokestatic Method JB else (Ljava/lang/String;I)V
L54:    new java/lang/StringBuilder
L57:    dup
L58:    invokespecial Method java/lang/StringBuilder <init> ()V
L61:    iconst_0
L62:    aload_1
L63:    getfield Field Rg false Led;
L66:    getfield Field ed else LPc;
L69:    getfield Field Pc char Ljava/lang/String;
L72:    invokevirtual Method java/lang/StringBuilder insert (ILjava/lang/String;)Ljava/lang/StringBuilder;
L75:    ldc "dls"
L77:    invokevirtual Method java/lang/StringBuilder append (Ljava/lang/String;)Ljava/lang/StringBuilder;
L80:    aload_0
L81:    getfield Field aE null Ljava/lang/String;
L84:    invokevirtual Method java/lang/StringBuilder append (Ljava/lang/String;)Ljava/lang/StringBuilder;
L87:    invokevirtual Method java/lang/StringBuilder toString ()Ljava/lang/String;
L90:    invokestatic Method JB break (Ljava/lang/String;)I
L93:    aload_0
L94:    getfield Field aE do I
L97:    if_icmplt L106
L100:   iconst_1
L101:   dup
L102:   dup
L103:   pop2
L104:   ireturn
L105:   athrow
L106:   iconst_0
L107:   iconst_1
L108:   dup
L109:   pop2
L110:   ireturn
L111:   
        .attribute StackMap b'\x00\x04\x00\x0B\x00\x00\x00\x01\x07\x00\x0E\x00\x0C\x00\x05\x07\x00\x02\x07\x00\x10\x07\x00\x12\x07\x00\x14\x07\x00\x16\x00\x00\x00\x69\x00\x00\x00\x01\x07\x00\x0E\x00\x6A\x00\x05\x07\x00\x02\x07\x00\x10\x07\x00\x12\x07\x00\x14\x07\x00\x16\x00\x00'
    .end code
.end method

.method public <init> : (Ljava/lang/String;Ljava/lang/String;Ljava/lang/String;IIZ)V
    .code stack 9 locals 7
L0:     iload 4
L2:     aload_0
L3:     dup_x1
L4:     aload_1
L5:     aload_2
L6:     aload_3
L7:     aconst_null
L8:     iload 5
L10:    iload 6
L12:    invokespecial Method Uf <init> (Ljava/lang/String;Ljava/lang/String;Ljava/lang/String;Ljava/lang/String;IZ)V
L15:    putfield Field aE do I
L18:    return
L19:    
    .end code
.end method
.innerclasses
    Pc JB [0] public static final enum
.end innerclasses
.end class
