.version 49 0
.class public final super AE
.super nf

.method public <init> : (Ljava/lang/String;IF)V
    .code stack 4 locals 4
L0:     aload_0
L1:     aload_1
L2:     iload_2
L3:     fload_3
L4:     invokespecial Method nf <init> (Ljava/lang/String;IF)V
L7:     return
L8:     
    .end code
.end method

.method public else : ()Ljava/lang/String;
    .code stack 3 locals 2
L0:     ldc ""
L2:     dup
L3:     astore_1
L4:     invokevirtual Method java/lang/String length ()I
L7:     aload_0
L8:     getfield Field AE null Ljava/lang/String;
L11:    invokevirtual Method java/lang/String length ()I
L14:    if_icmpge L43
L17:    new java/lang/StringBuilder
L20:    dup
L21:    invokespecial Method java/lang/StringBuilder <init> ()V
L24:    iconst_0
L25:    aload_1
L26:    invokevirtual Method java/lang/StringBuilder insert (ILjava/lang/String;)Ljava/lang/StringBuilder;
L29:    ldc "*"
L31:    invokevirtual Method java/lang/StringBuilder append (Ljava/lang/String;)Ljava/lang/StringBuilder;
L34:    invokevirtual Method java/lang/StringBuilder toString ()Ljava/lang/String;
L37:    dup
L38:    astore_1
L39:    goto L4
L42:    athrow
L43:    aload_1
L44:    areturn
L45:    
        .attribute StackMap b'\x00\x03\x00\x04\x00\x02\x07\x00\x02\x07\x00\x0E\x00\x01\x07\x00\x0E\x00\x2A\x00\x00\x00\x01\x07\x00\x2A\x00\x2B\x00\x02\x07\x00\x02\x07\x00\x0E\x00\x00'
    .end code
.end method

.method public <init> : (Ljava/lang/String;I)V
    .code stack 3 locals 3
L0:     aload_0
L1:     aload_1
L2:     iload_2
L3:     invokespecial Method nf <init> (Ljava/lang/String;I)V
L6:     return
L7:     
    .end code
.end method
.end class
