.version 49 0
.class public final super AG
.super Uf

.method public <init> : ()V
    .code stack 1 locals 1
L0:     aload_0
L1:     invokespecial Method Uf <init> ()V
L4:     return
L5:     
    .end code
.end method

.method public method699 : (LRg;[[ILff;[I)Z
    .code stack 5 locals 6
L0:     getstatic Field ZF field94 Lsb;
L3:     dup
L4:     astore_2
L5:     ifnonnull L14
L8:     iconst_0
L9:     iconst_1
L10:    dup
L11:    pop2
L12:    ireturn
L13:    athrow
L14:    aload_2
L15:    aload_1
L16:    invokevirtual Method sb method139 (LRg;)LLD;
L19:    dup
L20:    astore_2
L21:    ifnonnull L30
L24:    iconst_0
L25:    iconst_1
L26:    dup
L27:    pop2
L28:    ireturn
L29:    athrow
L30:    new java/util/LinkedList
L33:    dup
L34:    invokespecial Method java/util/LinkedList <init> ()V
L37:    astore_3
L38:    iconst_0
L39:    iconst_1
L40:    dup
L41:    pop2
L42:    dup
L43:    istore 4
L45:    bipush 28
L47:    iconst_1
L48:    dup
L49:    pop2
L50:    if_icmpge L124
L53:    iconst_0
L54:    iconst_1
L55:    dup
L56:    pop2
L57:    dup
L58:    istore 5
L60:    bipush 10
L62:    iconst_1
L63:    dup
L64:    pop2
L65:    if_icmpge L116
L68:    aload_1
L69:    getfield Field Rg this [[I
L72:    iload 5
L74:    aaload
L75:    iload 4
L77:    iaload
L78:    ifeq L108
L81:    new Dc
L84:    aload_3
L85:    dup_x1
L86:    dup
L87:    pop2
L88:    dup
L89:    iload 5
L91:    invokestatic Method java/lang/Integer valueOf (I)Ljava/lang/Integer;
L94:    iload 4
L96:    invokestatic Method java/lang/Integer valueOf (I)Ljava/lang/Integer;
L99:    invokespecial Method Dc <init> (Ljava/lang/Object;Ljava/lang/Object;)V
L102:   invokeinterface InterfaceMethod java/util/List add (Ljava/lang/Object;)Z 2
L107:   pop
L108:   iinc 5 1
L111:   iload 5
L113:   goto L60
L116:   iinc 4 1
L119:   iload 4
L121:   goto L45
L124:   aload_3
L125:   invokeinterface InterfaceMethod java/util/List isEmpty ()Z 1
L130:   ifne L254
L133:   invokestatic Method java/lang/Math random ()D
L136:   aload_3
L137:   dup_x2
L138:   invokeinterface InterfaceMethod java/util/List size ()I 1
L143:   i2d
L144:   dmul
L145:   d2i
L146:   invokeinterface InterfaceMethod java/util/List get (I)Ljava/lang/Object; 2
L151:   checkcast Dc
L154:   astore 4
L156:   aload_2
L157:   getfield Field LD field139 LlG;
L160:   aload 4
L162:   getfield Field Dc field1793 Ljava/lang/Object;
L165:   checkcast java/lang/Integer
L168:   invokevirtual Method java/lang/Integer intValue ()I
L171:   aload 4
L173:   getfield Field Dc field1794 Ljava/lang/Object;
L176:   checkcast java/lang/Integer
L179:   invokevirtual Method java/lang/Integer intValue ()I
L182:   aload_1
L183:   getfield Field Rg this [[I
L186:   aload 4
L188:   getfield Field Dc field1793 Ljava/lang/Object;
L191:   checkcast java/lang/Integer
L194:   invokevirtual Method java/lang/Integer intValue ()I
L197:   aaload
L198:   aload 4
L200:   getfield Field Dc field1794 Ljava/lang/Object;
L203:   checkcast java/lang/Integer
L206:   invokevirtual Method java/lang/Integer intValue ()I
L209:   iaload
L210:   ldc 1.5e0f
L212:   invokevirtual Method lG method650 (IIIF)V
L215:   aload_1
L216:   getfield Field Rg this [[I
L219:   aload 4
L221:   getfield Field Dc field1793 Ljava/lang/Object;
L224:   checkcast java/lang/Integer
L227:   invokevirtual Method java/lang/Integer intValue ()I
L230:   aaload
L231:   aload 4
L233:   getfield Field Dc field1794 Ljava/lang/Object;
L236:   checkcast java/lang/Integer
L239:   invokevirtual Method java/lang/Integer intValue ()I
L242:   iconst_0
L243:   iconst_1
L244:   dup
L245:   pop2
L246:   iastore
L247:   aload_1
L248:   getfield Field Rg this [[I
L251:   invokestatic Method hE method1143 ([[I)V
L254:   iconst_0
L255:   iconst_1
L256:   dup
L257:   pop2
L258:   ireturn
L259:   
        .attribute StackMap b'\x00\x0A\x00\x0D\x00\x00\x00\x01\x07\x00\x12\x00\x0E\x00\x05\x07\x00\x02\x07\x00\x14\x07\x00\x16\x07\x00\x18\x07\x00\x1A\x00\x00\x00\x1D\x00\x00\x00\x01\x07\x00\x12\x00\x1E\x00\x05\x07\x00\x02\x07\x00\x14\x07\x00\x20\x07\x00\x18\x07\x00\x1A\x00\x00\x00\x2D\x00\x05\x07\x00\x02\x07\x00\x14\x07\x00\x20\x07\x00\x22\x01\x00\x01\x01\x00\x3C\x00\x06\x07\x00\x02\x07\x00\x14\x07\x00\x20\x07\x00\x22\x01\x01\x00\x01\x01\x00\x6C\x00\x06\x07\x00\x02\x07\x00\x14\x07\x00\x20\x07\x00\x22\x01\x01\x00\x00\x00\x74\x00\x06\x07\x00\x02\x07\x00\x14\x07\x00\x20\x07\x00\x22\x01\x01\x00\x00\x00\x7C\x00\x05\x07\x00\x02\x07\x00\x14\x07\x00\x20\x07\x00\x22\x01\x00\x00\x00\xFE\x00\x04\x07\x00\x02\x07\x00\x14\x07\x00\x20\x07\x00\x22\x00\x00'
    .end code
.end method
.end class
