.version 49 0
.class public final super ag
.super java/lang/Object
.implements D
.field public try LqE;
.field public field719 Lff;
.field public new I
.field public field720 Led;
.field public this F
.field public field721 I
.field public field722 Lff;
.field public field723 I
.field public field724 I

.method public <init> : (Led;LqE;)V
    .code stack 4 locals 3
L0:     aload_2
L1:     aload_0
L2:     invokespecial Method java/lang/Object <init> ()V
L5:     getstatic Field qE field626 LqE;
L8:     if_acmpeq L18
L11:    aload_2
L12:    getstatic Field qE new LqE;
L15:    if_acmpne L28
L18:    new java/lang/RuntimeException
L21:    dup
L22:    ldc "Wrong constructor"
L24:    invokespecial Method java/lang/RuntimeException <init> (Ljava/lang/String;)V
L27:    athrow
L28:    aload_0
L29:    aload_2
L30:    aload_0
L31:    aload_1
L32:    putfield Field ag field720 Led;
L35:    putfield Field ag try LqE;
L38:    return
L39:    
        .attribute StackMap b'\x00\x02\x00\x12\x00\x03\x07\x00\x02\x07\x00\x24\x07\x00\x1D\x00\x00\x00\x1C\x00\x03\x07\x00\x02\x07\x00\x24\x07\x00\x1D\x00\x00'
    .end code
.end method

.method public method384 : (LAC;)V
    .code stack 10 locals 2
L0:     aload_0
L1:     aload_1
L2:     dup_x1
L3:     aload_0
L4:     getfield Field ag field720 Led;
L7:     getfield Field ed try I
L10:    invokevirtual Method AC method691 (I)V
L13:    getfield Field ag try LqE;
L16:    invokevirtual Method qE ordinal ()I
L19:    invokevirtual Method AC method691 (I)V
L22:    getstatic Field be field2200 [I
L25:    aload_0
L26:    getfield Field ag try LqE;
L29:    invokevirtual Method qE ordinal ()I
L32:    iaload
L33:    tableswitch 1
            L80
            L126
            L144
            L144
            L144
            L144
            L144
            L144
            default : L144
L80:    aload_1
L81:    iconst_0
L82:    ifne L81
L85:    dup
L86:    aload_0
L87:    dup_x1
L88:    aload_0
L89:    aload_1
L90:    dup_x1
L91:    aload_1
L92:    aload_0
L93:    dup_x1
L94:    getfield Field ag this F
L97:    invokevirtual Method AC method685 (F)V
L100:   getfield Field ag new I
L103:   invokevirtual Method AC method691 (I)V
L106:   getfield Field ag field721 I
L109:   invokevirtual Method AC method691 (I)V
L112:   getfield Field ag field724 I
L115:   invokevirtual Method AC method691 (I)V
L118:   getfield Field ag field723 I
L121:   invokevirtual Method AC method691 (I)V
L124:   return
L125:   athrow
L126:   aload_0
L127:   dup
L128:   getfield Field ag field722 Lff;
L131:   aload_1
L132:   invokevirtual Method ff method384 (LAC;)V
L135:   getfield Field ag field719 Lff;
L138:   aload_1
L139:   invokevirtual Method ff method384 (LAC;)V
L142:   return
L143:   athrow
L144:   return
L145:   
        .attribute StackMap b'\x00\x06\x00\x50\x00\x02\x07\x00\x02\x07\x00\x37\x00\x00\x00\x51\x00\x02\x07\x00\x02\x07\x00\x37\x00\x01\x07\x00\x37\x00\x7D\x00\x00\x00\x01\x07\x00\x53\x00\x7E\x00\x02\x07\x00\x02\x07\x00\x37\x00\x00\x00\x8F\x00\x00\x00\x01\x07\x00\x53\x00\x90\x00\x02\x07\x00\x02\x07\x00\x37\x00\x00'
    .end code
    .exceptions java/io/IOException
.end method

.method public <init> : (Led;LqE;LRg;)V
    .code stack 13 locals 4
L0:     aload_2
L1:     aload_0
L2:     invokespecial Method java/lang/Object <init> ()V
L5:     getstatic Field qE new LqE;
L8:     if_acmpeq L21
L11:    new java/lang/RuntimeException
L14:    dup
L15:    ldc "Wrong constructor"
L17:    invokespecial Method java/lang/RuntimeException <init> (Ljava/lang/String;)V
L20:    athrow
L21:    aload_0
L22:    dup
L23:    aload_3
L24:    dup_x1
L25:    aload_3
L26:    aload_0
L27:    dup_x1
L28:    aload_0
L29:    aload_3
L30:    dup_x1
L31:    aload_0
L32:    dup
L33:    aload_1
L34:    putfield Field ag field720 Led;
L37:    getstatic Field qE new LqE;
L40:    putfield Field ag try LqE;
L43:    getfield Field Rg field241 F
L46:    putfield Field ag this F
L49:    getfield Field Rg field222 I
L52:    putfield Field ag new I
L55:    getfield Field Rg field232 I
L58:    putfield Field ag field721 I
L61:    getfield Field Rg field213 I
L64:    putfield Field ag field724 I
L67:    getfield Field Rg field230 I
L70:    putfield Field ag field723 I
L73:    return
L74:    
        .attribute StackMap b'\x00\x01\x00\x15\x00\x04\x07\x00\x02\x07\x00\x24\x07\x00\x1D\x07\x00\x5E\x00\x00'
    .end code
.end method

.method public <init> : (Led;LqE;Lff;Lff;)V
    .code stack 7 locals 5
L0:     aload_2
L1:     aload_0
L2:     invokespecial Method java/lang/Object <init> ()V
L5:     getstatic Field qE field626 LqE;
L8:     if_acmpeq L21
L11:    new java/lang/RuntimeException
L14:    dup
L15:    ldc "Wrong constructor"
L17:    invokespecial Method java/lang/RuntimeException <init> (Ljava/lang/String;)V
L20:    athrow
L21:    aload_0
L22:    aload 4
L24:    aload_3
L25:    aload_0
L26:    dup
L27:    dup_x2
L28:    aload_1
L29:    putfield Field ag field720 Led;
L32:    getstatic Field qE field626 LqE;
L35:    putfield Field ag try LqE;
L38:    invokevirtual Method ff method466 ()Lff;
L41:    putfield Field ag field722 Lff;
L44:    invokevirtual Method ff method466 ()Lff;
L47:    putfield Field ag field719 Lff;
L50:    return
L51:    
        .attribute StackMap b'\x00\x01\x00\x15\x00\x05\x07\x00\x02\x07\x00\x24\x07\x00\x1D\x07\x00\x57\x07\x00\x57\x00\x00'
    .end code
.end method

.method public <init> : (LMd;)V
    .code stack 11 locals 3
L0:     aload_1
L1:     aload_0
L2:     dup_x1
L3:     invokespecial Method java/lang/Object <init> ()V
L6:     invokevirtual Method Md method886 ()I
L9:     istore_2
L10:    invokestatic Method qE values ()[LqE;
L13:    aload_1
L14:    invokevirtual Method Md method886 ()I
L17:    aaload
L18:    putfield Field ag try LqE;
L21:    getstatic Field be field2200 [I
L24:    aload_0
L25:    getfield Field ag try LqE;
L28:    invokevirtual Method qE ordinal ()I
L31:    iaload
L32:    tableswitch 1
            L80
            L129
            L150
            L150
            L150
            L150
            L150
            L150
            default : L150
L80:    aload_0
L81:    iconst_0
L82:    ifne L81
L85:    aload_1
L86:    aload_0
L87:    dup_x1
L88:    aload_0
L89:    aload_1
L90:    dup_x1
L91:    aload_1
L92:    aload_0
L93:    dup_x1
L94:    aload_1
L95:    invokevirtual Method Md method885 ()F
L98:    putfield Field ag this F
L101:   invokevirtual Method Md method886 ()I
L104:   putfield Field ag new I
L107:   invokevirtual Method Md method886 ()I
L110:   putfield Field ag field721 I
L113:   invokevirtual Method Md method886 ()I
L116:   putfield Field ag field724 I
L119:   invokevirtual Method Md method886 ()I
L122:   putfield Field ag field723 I
L125:   goto L151
L128:   athrow
L129:   aload_0
L130:   aload_1
L131:   aload_0
L132:   dup_x1
L133:   aload_1
L134:   invokestatic Method ff method468 (LMd;)Lff;
L137:   putfield Field ag field722 Lff;
L140:   invokestatic Method ff method468 (LMd;)Lff;
L143:   putfield Field ag field719 Lff;
L146:   goto L151
L149:   athrow
L150:   aload_0
L151:   getstatic Field Kc field1931 LKc;
L154:   iload_2
L155:   invokevirtual Method Kc method856 (I)Led;
L158:   putfield Field ag field720 Led;
L161:   return
L162:   
        .attribute StackMap b'\x00\x07\x00\x50\x00\x03\x07\x00\x02\x07\x00\x75\x01\x00\x00\x00\x51\x00\x03\x07\x00\x02\x07\x00\x75\x01\x00\x01\x07\x00\x02\x00\x80\x00\x00\x00\x01\x07\x00\x53\x00\x81\x00\x03\x07\x00\x02\x07\x00\x75\x01\x00\x00\x00\x95\x00\x00\x00\x01\x07\x00\x53\x00\x96\x00\x03\x07\x00\x02\x07\x00\x75\x01\x00\x00\x00\x97\x00\x03\x07\x00\x02\x07\x00\x75\x01\x00\x01\x07\x00\x02'
    .end code
    .exceptions java/io/IOException
.end method
.innerclasses
    be ag [0] static synthetic
.end innerclasses
.end class
