.version 49 0
.class public super abstract bc
.super java/lang/Object
.implements M
.field public this Ljava/util/HashMap;
.field public char Ljava/util/concurrent/LinkedBlockingQueue;
.field public else Z
.field public "enum" Ljava/util/concurrent/LinkedBlockingQueue;
.field public do Ljava/util/List;

.method public fpsfoundhere : (F)Z
    .code stack 3 locals 2
L0:     iconst_0
L1:     iconst_1
L2:     dup
L3:     pop2
L4:     ireturn
L5:     
    .end code
    .exceptions java/lang/Exception
.end method

.method public abstract const : (ILD;)V
.end method

.method public else : (Lk;)V
    .code stack 2 locals 2
L0:     aload_0
L1:     getfield Field bc do Ljava/util/List;
L4:     aload_1
L5:     invokeinterface InterfaceMethod java/util/List contains (Ljava/lang/Object;)Z 2
L10:    ifne L24
L13:    aload_0
L14:    getfield Field bc do Ljava/util/List;
L17:    aload_1
L18:    invokeinterface InterfaceMethod java/util/List add (Ljava/lang/Object;)Z 2
L23:    pop
L24:    return
L25:    
        .attribute StackMap b'\x00\x01\x00\x18\x00\x02\x07\x00\x02\x07\x00\x23\x00\x00'
    .end code
.end method

.method public break : ()Z
    .code stack 3 locals 4
L0:     aconst_null
L1:     astore_1
L2:     aload_0
L3:     getfield Field bc "enum" Ljava/util/concurrent/LinkedBlockingQueue;
L6:     invokevirtual Method java/util/concurrent/LinkedBlockingQueue poll ()Ljava/lang/Object;
L9:     checkcast fD
L12:    dup
L13:    astore_1
L14:    ifnull L72
        .catch java/lang/Exception from L17 to L31 using L36
L17:    aload_1
L18:    invokevirtual Method fD else ()LD;
L21:    astore_2
L22:    aload_0
L23:    aload_1
L24:    invokevirtual Method fD const ()I
L27:    aload_2
L28:    invokevirtual Method bc const (ILD;)V
L31:    aload_0
L32:    goto L3
L35:    athrow
L36:    astore_2
        .catch java/lang/Exception from L37 to L64 using L68
L37:    aload_0
L38:    getfield Field bc this Ljava/util/HashMap;
L41:    aload_1
L42:    invokevirtual Method fD const ()I
L45:    invokestatic Method java/lang/Integer valueOf (I)Ljava/lang/Integer;
L48:    invokevirtual Method java/util/HashMap get (Ljava/lang/Object;)Ljava/lang/Object;
L51:    checkcast wb
L54:    getfield Field wb char Z
L57:    ifeq L2
L60:    aload_2
L61:    invokevirtual Method java/lang/Exception printStackTrace ()V
L64:    goto L2
L67:    athrow
L68:    astore_3
L69:    goto L2
L72:    aconst_null
L73:    astore_2
L74:    aload_0
L75:    getfield Field bc char Ljava/util/concurrent/LinkedBlockingQueue;
L78:    invokevirtual Method java/util/concurrent/LinkedBlockingQueue poll ()Ljava/lang/Object;
L81:    checkcast wb
L84:    dup
L85:    astore_2
L86:    ifnull L101
L89:    aload_0
L90:    dup
L91:    aload_2
L92:    getfield Field wb long I
L95:    invokevirtual Method bc else (I)V
L98:    goto L75
L101:   iconst_0
L102:   iconst_1
L103:   dup
L104:   pop2
L105:   ireturn
L106:   
        .attribute StackMap b'\x00\x09\x00\x02\x00\x02\x07\x00\x02\x07\x00\x27\x00\x00\x00\x03\x00\x02\x07\x00\x02\x07\x00\x27\x00\x01\x07\x00\x02\x00\x23\x00\x00\x00\x01\x07\x00\x39\x00\x24\x00\x02\x07\x00\x02\x07\x00\x27\x00\x01\x07\x00\x13\x00\x43\x00\x00\x00\x01\x07\x00\x39\x00\x44\x00\x03\x07\x00\x02\x07\x00\x27\x07\x00\x13\x00\x01\x07\x00\x13\x00\x48\x00\x02\x07\x00\x02\x07\x00\x27\x00\x00\x00\x4B\x00\x03\x07\x00\x02\x07\x00\x27\x07\x00\x49\x00\x01\x07\x00\x02\x00\x65\x00\x03\x07\x00\x02\x07\x00\x27\x07\x00\x49\x00\x00'
    .end code
    .exceptions java/lang/Exception
.end method

.method public break : (Lk;)V
    .code stack 2 locals 2
L0:     aload_0
L1:     getfield Field bc do Ljava/util/List;
L4:     aload_1
L5:     invokeinterface InterfaceMethod java/util/List remove (Ljava/lang/Object;)Z 2
L10:    pop
L11:    return
L12:    
    .end code
.end method

.method public short : ()V
    .code stack 4 locals 2
L0:     aload_0
L1:     dup
L2:     invokestatic Method ib else (LM;)V
L5:     getfield Field bc "enum" Ljava/util/concurrent/LinkedBlockingQueue;
L8:     invokevirtual Method java/util/concurrent/LinkedBlockingQueue clear ()V
L11:    new java/util/ArrayList
L14:    dup
L15:    aload_0
L16:    getfield Field bc this Ljava/util/HashMap;
L19:    invokevirtual Method java/util/HashMap values ()Ljava/util/Collection;
L22:    invokespecial Method java/util/ArrayList <init> (Ljava/util/Collection;)V
L25:    invokeinterface InterfaceMethod java/util/List iterator ()Ljava/util/Iterator; 1
L30:    dup
L31:    astore_1
L32:    invokeinterface InterfaceMethod java/util/Iterator hasNext ()Z 1
L37:    ifeq L57
L40:    aload_1
L41:    invokeinterface InterfaceMethod java/util/Iterator next ()Ljava/lang/Object; 1
L46:    checkcast wb
L49:    invokevirtual Method wb break ()V
L52:    aload_1
L53:    goto L32
L56:    athrow
L57:    aconst_null
L58:    astore_1
L59:    aload_0
L60:    getfield Field bc char Ljava/util/concurrent/LinkedBlockingQueue;
L63:    invokevirtual Method java/util/concurrent/LinkedBlockingQueue poll ()Ljava/lang/Object;
L66:    checkcast wb
L69:    dup
L70:    astore_1
L71:    ifnull L87
L74:    aload_0
L75:    dup
L76:    aload_1
L77:    getfield Field wb long I
L80:    invokevirtual Method bc else (I)V
L83:    goto L60
L86:    athrow
L87:    aload_0
L88:    iconst_0
L89:    iconst_1
L90:    dup
L91:    pop2
L92:    putfield Field bc else Z
L95:    return
L96:    
        .attribute StackMap b'\x00\x06\x00\x20\x00\x02\x07\x00\x02\x07\x00\x74\x00\x01\x07\x00\x74\x00\x38\x00\x00\x00\x01\x07\x00\x39\x00\x39\x00\x02\x07\x00\x02\x07\x00\x74\x00\x00\x00\x3C\x00\x02\x07\x00\x02\x07\x00\x49\x00\x01\x07\x00\x02\x00\x56\x00\x00\x00\x01\x07\x00\x39\x00\x57\x00\x02\x07\x00\x02\x07\x00\x49\x00\x00'
    .end code
.end method

.method public const : ()V
    .code stack 4 locals 1
L0:     iconst_1
L1:     aload_0
L2:     dup_x1
L3:     invokestatic Method ib break (LM;)V
L6:     iconst_1
L7:     dup
L8:     pop2
L9:     putfield Field bc else Z
L12:    return
L13:    
    .end code
    .exceptions java/lang/Exception
.end method

.method public else : (I)V
    .code stack 10 locals 3
L0:     aload_0
L1:     getfield Field bc this Ljava/util/HashMap;
L4:     iload_1
L5:     invokestatic Method java/lang/Integer valueOf (I)Ljava/lang/Integer;
L8:     invokevirtual Method java/util/HashMap remove (Ljava/lang/Object;)Ljava/lang/Object;
L11:    checkcast wb
L14:    dup
L15:    astore_2
L16:    getfield Field wb const Z
L19:    ifne L54
L22:    aload_2
L23:    iconst_1
L24:    aload_0
L25:    new Qd
L28:    iload_1
L29:    dup
L30:    pop2
L31:    dup
L32:    iload_1
L33:    dup_x2
L34:    iconst_1
L35:    dup
L36:    dup
L37:    pop2
L38:    aload_2
L39:    getfield Field wb try Z
L42:    invokespecial Method Qd <init> (IZZ)V
L45:    invokevirtual Method bc else (ILD;)V
L48:    iconst_1
L49:    dup
L50:    pop2
L51:    putfield Field wb const Z
L54:    return
L55:    
        .attribute StackMap b'\x00\x01\x00\x36\x00\x03\x07\x00\x02\x01\x07\x00\x49\x00\x00'
    .end code
.end method

.method public else : ()Ljava/lang/String;
    .code stack 8 locals 4
L0:     aload_0
L1:     getfield Field bc this Ljava/util/HashMap;
L4:     invokevirtual Method java/util/HashMap values ()Ljava/util/Collection;
L7:     invokeinterface InterfaceMethod java/util/Collection iterator ()Ljava/util/Iterator; 1
L12:    astore_1
L13:    aload_1
L14:    invokeinterface InterfaceMethod java/util/Iterator hasNext ()Z 1
L19:    ifeq L169
L22:    aload_1
L23:    invokeinterface InterfaceMethod java/util/Iterator next ()Ljava/lang/Object; 1
L28:    checkcast wb
L31:    astore_2
        .catch java/lang/ArrayIndexOutOfBoundsException from L32 to L154 using L156
        .catch java/net/SocketException from L32 to L154 using L161
        .catch java/lang/NullPointerException from L32 to L154 using L165
L32:    aload_2
L33:    getfield Field wb new Ljava/net/Socket;
L36:    invokevirtual Method java/net/Socket getLocalAddress ()Ljava/net/InetAddress;
L39:    dup
L40:    astore_2
L41:    invokestatic Method java/net/NetworkInterface getByInetAddress (Ljava/net/InetAddress;)Ljava/net/NetworkInterface;
L44:    invokevirtual Method java/net/NetworkInterface getHardwareAddress ()[B
L47:    astore_3
L48:    ldc "%02X-%02X-%02X-%02X-%02X-%02X"
L50:    bipush 6
L52:    iconst_1
L53:    dup
L54:    pop2
L55:    anewarray java/lang/Object
L58:    iconst_1
L59:    dup
L60:    pop2
L61:    dup
L62:    iconst_1
L63:    dup
L64:    pop2
L65:    aload_3
L66:    iconst_0
L67:    dup_x1
L68:    iconst_1
L69:    dup
L70:    pop2
L71:    baload
L72:    invokestatic Method java/lang/Byte valueOf (B)Ljava/lang/Byte;
L75:    aastore
L76:    dup
L77:    iconst_1
L78:    dup
L79:    pop2
L80:    aload_3
L81:    iconst_1
L82:    dup
L83:    dup_x2
L84:    dup
L85:    pop2
L86:    baload
L87:    invokestatic Method java/lang/Byte valueOf (B)Ljava/lang/Byte;
L90:    aastore
L91:    dup
L92:    iconst_1
L93:    dup
L94:    pop2
L95:    aload_3
L96:    iconst_2
L97:    dup_x1
L98:    iconst_1
L99:    dup
L100:   pop2
L101:   baload
L102:   invokestatic Method java/lang/Byte valueOf (B)Ljava/lang/Byte;
L105:   aastore
L106:   dup
L107:   iconst_1
L108:   dup
L109:   pop2
L110:   aload_3
L111:   iconst_3
L112:   dup_x1
L113:   iconst_1
L114:   dup
L115:   pop2
L116:   baload
L117:   invokestatic Method java/lang/Byte valueOf (B)Ljava/lang/Byte;
L120:   aastore
L121:   dup
L122:   iconst_1
L123:   dup
L124:   pop2
L125:   aload_3
L126:   iconst_4
L127:   dup_x1
L128:   iconst_1
L129:   dup
L130:   pop2
L131:   baload
L132:   invokestatic Method java/lang/Byte valueOf (B)Ljava/lang/Byte;
L135:   aastore
L136:   dup
L137:   iconst_1
L138:   dup
L139:   pop2
L140:   aload_3
L141:   iconst_5
L142:   dup_x1
L143:   iconst_1
L144:   dup
L145:   pop2
L146:   baload
L147:   invokestatic Method java/lang/Byte valueOf (B)Ljava/lang/Byte;
L150:   aastore
L151:   invokestatic Method java/lang/String format (Ljava/lang/String;[Ljava/lang/Object;)Ljava/lang/String;
L154:   areturn
L155:   athrow
L156:   astore_2
L157:   goto L13
L160:   athrow
L161:   astore_2
L162:   goto L13
L165:   astore_2
L166:   goto L13
L169:   aconst_null
L170:   areturn
L171:   
        .attribute StackMap b'\x00\x07\x00\x0D\x00\x02\x07\x00\x02\x07\x00\x74\x00\x00\x00\x9B\x00\x00\x00\x01\x07\x00\x39\x00\x9C\x00\x03\x07\x00\x02\x07\x00\x74\x07\x00\x04\x00\x01\x07\x00\x91\x00\xA0\x00\x00\x00\x01\x07\x00\x39\x00\xA1\x00\x03\x07\x00\x02\x07\x00\x74\x07\x00\x04\x00\x01\x07\x00\x93\x00\xA5\x00\x03\x07\x00\x02\x07\x00\x74\x07\x00\x04\x00\x01\x07\x00\x95\x00\xA9\x00\x02\x07\x00\x02\x07\x00\x74\x00\x00'
    .end code
.end method

.method public else : (ILD;)V
    .code stack 3 locals 4
L0:     aload_0
L1:     getfield Field bc do Ljava/util/List;
L4:     invokeinterface InterfaceMethod java/util/List iterator ()Ljava/util/Iterator; 1
L9:     dup
L10:    astore_3
L11:    invokeinterface InterfaceMethod java/util/Iterator hasNext ()Z 1
L16:    ifeq L40
L19:    aload_3
L20:    invokeinterface InterfaceMethod java/util/Iterator next ()Ljava/lang/Object; 1
L25:    checkcast k
L28:    iload_1
L29:    aload_2
L30:    invokeinterface InterfaceMethod k break (ILD;)V 3
L35:    aload_3
L36:    goto L11
L39:    athrow
L40:    return
L41:    
        .attribute StackMap b'\x00\x03\x00\x0B\x00\x04\x07\x00\x02\x01\x07\x00\xBB\x07\x00\x74\x00\x01\x07\x00\x74\x00\x27\x00\x00\x00\x01\x07\x00\x39\x00\x28\x00\x04\x07\x00\x02\x01\x07\x00\xBB\x07\x00\x74\x00\x00'
    .end code
.end method

.method public break : (I)Ljava/lang/String;
    .code stack 2 locals 2
L0:     aload_0
L1:     getfield Field bc this Ljava/util/HashMap;
L4:     iload_1
L5:     invokestatic Method java/lang/Integer valueOf (I)Ljava/lang/Integer;
L8:     invokevirtual Method java/util/HashMap get (Ljava/lang/Object;)Ljava/lang/Object;
L11:    checkcast wb
L14:    getfield Field wb else Ljava/lang/String;
L17:    areturn
L18:    
    .end code
.end method

.method public break : (ILD;)V
    .code stack 5 locals 4
L0:     aload_0
L1:     getfield Field bc else Z
L4:     ifne L24
        .catch java/lang/Exception from L7 to L17 using L17
        .catch java/lang/Exception from L0 to L23 using L56
L7:     new java/lang/Exception
L10:    dup
L11:    ldc "Network is not connected"
L13:    invokespecial Method java/lang/Exception <init> (Ljava/lang/String;)V
L16:    athrow
L17:    astore_3
L18:    aload_3
L19:    invokevirtual Method java/lang/Exception printStackTrace ()V
L22:    return
L23:    athrow
        .catch java/lang/Exception from L24 to L54 using L56
L24:    aload_0
L25:    getfield Field bc this Ljava/util/HashMap;
L28:    iload_1
L29:    invokestatic Method java/lang/Integer valueOf (I)Ljava/lang/Integer;
L32:    invokevirtual Method java/util/HashMap get (Ljava/lang/Object;)Ljava/lang/Object;
L35:    checkcast wb
L38:    getfield Field wb goto Ljava/util/concurrent/LinkedBlockingQueue;
L41:    new fD
L44:    dup
L45:    iload_1
L46:    aload_2
L47:    invokespecial Method fD <init> (ILD;)V
L50:    invokevirtual Method java/util/concurrent/LinkedBlockingQueue add (Ljava/lang/Object;)Z
L53:    pop
L54:    return
L55:    athrow
L56:    astore_3
L57:    aload_3
L58:    invokevirtual Method java/lang/Exception printStackTrace ()V
L61:    return
L62:    
        .attribute StackMap b'\x00\x05\x00\x11\x00\x03\x07\x00\x02\x01\x07\x00\xBB\x00\x01\x07\x00\x13\x00\x17\x00\x00\x00\x01\x07\x00\x39\x00\x18\x00\x03\x07\x00\x02\x01\x07\x00\xBB\x00\x00\x00\x37\x00\x00\x00\x01\x07\x00\x39\x00\x38\x00\x03\x07\x00\x02\x01\x07\x00\xBB\x00\x01\x07\x00\x13'
    .end code
.end method

.method public <init> : ()V
    .code stack 9 locals 1
L0:     iconst_0
L1:     aload_0
L2:     dup
L3:     dup_x2
L4:     aload_0
L5:     dup
L6:     invokespecial Method java/lang/Object <init> ()V
L9:     new java/util/concurrent/LinkedBlockingQueue
L12:    aload_0
L13:    dup_x2
L14:    dup
L15:    pop2
L16:    dup
L17:    invokespecial Method java/util/concurrent/LinkedBlockingQueue <init> ()V
L20:    putfield Field bc char Ljava/util/concurrent/LinkedBlockingQueue;
L23:    new java/util/concurrent/LinkedBlockingQueue
L26:    aload_0
L27:    dup
L28:    pop2
L29:    dup
L30:    invokespecial Method java/util/concurrent/LinkedBlockingQueue <init> ()V
L33:    putfield Field bc "enum" Ljava/util/concurrent/LinkedBlockingQueue;
L36:    new java/util/HashMap
L39:    aload_0
L40:    dup
L41:    pop2
L42:    dup
L43:    invokespecial Method java/util/HashMap <init> ()V
L46:    putfield Field bc this Ljava/util/HashMap;
L49:    new java/util/concurrent/CopyOnWriteArrayList
L52:    aload_0
L53:    dup
L54:    pop2
L55:    dup
L56:    invokespecial Method java/util/concurrent/CopyOnWriteArrayList <init> ()V
L59:    putfield Field bc do Ljava/util/List;
L62:    iconst_1
L63:    dup
L64:    pop2
L65:    putfield Field bc else Z
L68:    return
L69:    
    .end code
.end method
.end class
