.version 49 0
.class public final super bd
.super java/lang/Object
.implements java/lang/Runnable
.field public final synthetic "enum" Lmd;
.field public final synthetic do LK;

.method public run : ()V
    .code stack 3 locals 1
L0:     aload_0
L1:     getfield Field bd "enum" Lmd;
L4:     invokestatic Method md do (Lmd;)LuC;
L7:     aload_0
L8:     getfield Field bd do LK;
L11:    invokevirtual Method uC break (LK;)Z
L14:    ifeq L52
L17:    aload_0
L18:    getfield Field bd "enum" Lmd;
L21:    invokestatic Method md do (Lmd;)LuC;
L24:    aload_0
L25:    dup_x1
L26:    getfield Field bd do LK;
L29:    invokevirtual Method uC else (LK;)Z
L32:    pop
L33:    getfield Field bd do LK;
L36:    ifnull L52
L39:    aload_0
L40:    getfield Field bd do LK;
L43:    aconst_null
L44:    getstatic Field KD int LKD;
L47:    invokeinterface InterfaceMethod K break (Ljava/lang/Object;LKD;)V 3
L52:    return
L53:    
        .attribute StackMap b'\x00\x01\x00\x34\x00\x01\x07\x00\x02\x00\x00'
    .end code
.end method

.method public <init> : (Lmd;LK;)V
    .code stack 5 locals 3
L0:     aload_2
L1:     aload_0
L2:     dup_x1
L3:     dup_x2
L4:     aload_1
L5:     putfield Field bd "enum" Lmd;
L8:     putfield Field bd do LK;
L11:    invokespecial Method java/lang/Object <init> ()V
L14:    return
L15:    
    .end code
.end method
.innerclasses
    KD K [0] public static final enum
    bd [0] [0]
.end innerclasses
.enclosing method md break (Ljava/lang/String;Ljava/lang/String;Leb;ZZIILed;LK;)V
.end class
