.version 49 0
.class public final super bD
.super java/lang/Object
.implements D
.field private new I
.field private field714 I
.field private this I
.field private field715 I
.field private field716 I
.field private field717 I
.field private field718 I

.method public method384 : (LAC;)V
    .code stack 14 locals 2
L0:     aload_0
L1:     aload_1
L2:     dup_x1
L3:     aload_1
L4:     aload_0
L5:     dup_x1
L6:     aload_0
L7:     aload_1
L8:     dup_x1
L9:     aload_1
L10:    aload_0
L11:    dup_x1
L12:    aload_1
L13:    aload_0
L14:    getfield Field bD field715 I
L17:    invokevirtual Method AC method691 (I)V
L20:    getfield Field bD field716 I
L23:    invokevirtual Method AC method691 (I)V
L26:    getfield Field bD field714 I
L29:    invokevirtual Method AC method691 (I)V
L32:    getfield Field bD field717 I
L35:    invokevirtual Method AC method691 (I)V
L38:    getfield Field bD this I
L41:    invokevirtual Method AC method691 (I)V
L44:    getfield Field bD new I
L47:    invokevirtual Method AC method691 (I)V
L50:    getfield Field bD field718 I
L53:    invokevirtual Method AC method691 (I)V
L56:    return
L57:    
    .end code
    .exceptions java/io/IOException
.end method

.method public method390 : (Lff;)I
    .code stack 2 locals 2
L0:     aload_1
L1:     instanceof tF
L4:     ifeq L13
L7:     aload_0
L8:     getfield Field bD this I
L11:    ireturn
L12:    athrow
L13:    aload_1
L14:    instanceof AF
L17:    ifeq L26
L20:    aload_0
L21:    getfield Field bD field717 I
L24:    ireturn
L25:    athrow
L26:    aload_1
L27:    instanceof VF
L30:    ifeq L38
L33:    aload_0
L34:    getfield Field bD field714 I
L37:    ireturn
L38:    aload_1
L39:    instanceof Df
L42:    ifeq L50
L45:    aload_0
L46:    getfield Field bD new I
L49:    ireturn
L50:    aload_1
L51:    instanceof mE
L54:    ifeq L62
L57:    aload_0
L58:    getfield Field bD field715 I
L61:    ireturn
L62:    aload_1
L63:    instanceof TE
L66:    ifeq L74
L69:    aload_0
L70:    getfield Field bD field718 I
L73:    ireturn
L74:    aload_1
L75:    instanceof Af
L78:    ifeq L86
L81:    aload_0
L82:    getfield Field bD field716 I
L85:    ireturn
L86:    new java/lang/RuntimeException
L89:    dup
L90:    invokespecial Method java/lang/RuntimeException <init> ()V
L93:    athrow
L94:    
        .attribute StackMap b'\x00\x09\x00\x0C\x00\x00\x00\x01\x07\x00\x30\x00\x0D\x00\x02\x07\x00\x02\x07\x00\x32\x00\x00\x00\x19\x00\x00\x00\x01\x07\x00\x30\x00\x1A\x00\x02\x07\x00\x02\x07\x00\x32\x00\x00\x00\x26\x00\x02\x07\x00\x02\x07\x00\x32\x00\x00\x00\x32\x00\x02\x07\x00\x02\x07\x00\x32\x00\x00\x00\x3E\x00\x02\x07\x00\x02\x07\x00\x32\x00\x00\x00\x4A\x00\x02\x07\x00\x02\x07\x00\x32\x00\x00\x00\x56\x00\x02\x07\x00\x02\x07\x00\x32\x00\x00'
    .end code
.end method

.method public static method391 : (LPc;)LbD;
    .code stack 10 locals 2
L0:     aload_0
L1:     ifnonnull L9
L4:     invokestatic Method bD method392 ()LbD;
L7:     areturn
L8:     athrow
L9:     new bD
L12:    dup
L13:    invokespecial Method bD <init> ()V
L16:    dup
L17:    astore_1
L18:    dup
L19:    dup2
L20:    dup2
L21:    new java/lang/StringBuilder
L24:    aload_1
L25:    dup_x1
L26:    dup
L27:    pop2
L28:    dup
L29:    invokespecial Method java/lang/StringBuilder <init> ()V
L32:    aload_0
L33:    getfield Field Pc field370 Ljava/lang/String;
L36:    invokevirtual Method java/lang/StringBuilder append (Ljava/lang/String;)Ljava/lang/StringBuilder;
L39:    ldc "cs"
L41:    invokevirtual Method java/lang/StringBuilder append (Ljava/lang/String;)Ljava/lang/StringBuilder;
L44:    invokevirtual Method java/lang/StringBuilder toString ()Ljava/lang/String;
L47:    invokestatic Method JB method831 (Ljava/lang/String;)I
L50:    putfield Field bD field715 I
L53:    new java/lang/StringBuilder
L56:    aload_1
L57:    dup_x2
L58:    dup
L59:    pop2
L60:    dup
L61:    invokespecial Method java/lang/StringBuilder <init> ()V
L64:    aload_0
L65:    getfield Field Pc field370 Ljava/lang/String;
L68:    invokevirtual Method java/lang/StringBuilder append (Ljava/lang/String;)Ljava/lang/StringBuilder;
L71:    ldc "cz"
L73:    invokevirtual Method java/lang/StringBuilder append (Ljava/lang/String;)Ljava/lang/StringBuilder;
L76:    invokevirtual Method java/lang/StringBuilder toString ()Ljava/lang/String;
L79:    invokestatic Method JB method831 (Ljava/lang/String;)I
L82:    putfield Field bD field716 I
L85:    new java/lang/StringBuilder
L88:    aload_1
L89:    dup
L90:    pop2
L91:    dup
L92:    invokespecial Method java/lang/StringBuilder <init> ()V
L95:    aload_0
L96:    getfield Field Pc field370 Ljava/lang/String;
L99:    invokevirtual Method java/lang/StringBuilder append (Ljava/lang/String;)Ljava/lang/StringBuilder;
L102:   ldc "cl"
L104:   invokevirtual Method java/lang/StringBuilder append (Ljava/lang/String;)Ljava/lang/StringBuilder;
L107:   invokevirtual Method java/lang/StringBuilder toString ()Ljava/lang/String;
L110:   invokestatic Method JB method831 (Ljava/lang/String;)I
L113:   putfield Field bD field714 I
L116:   new java/lang/StringBuilder
L119:   aload_1
L120:   dup
L121:   pop2
L122:   dup
L123:   invokespecial Method java/lang/StringBuilder <init> ()V
L126:   aload_0
L127:   getfield Field Pc field370 Ljava/lang/String;
L130:   invokevirtual Method java/lang/StringBuilder append (Ljava/lang/String;)Ljava/lang/StringBuilder;
L133:   ldc "cj"
L135:   invokevirtual Method java/lang/StringBuilder append (Ljava/lang/String;)Ljava/lang/StringBuilder;
L138:   invokevirtual Method java/lang/StringBuilder toString ()Ljava/lang/String;
L141:   invokestatic Method JB method831 (Ljava/lang/String;)I
L144:   putfield Field bD field717 I
L147:   new java/lang/StringBuilder
L150:   aload_1
L151:   dup
L152:   pop2
L153:   dup
L154:   invokespecial Method java/lang/StringBuilder <init> ()V
L157:   aload_0
L158:   getfield Field Pc field370 Ljava/lang/String;
L161:   invokevirtual Method java/lang/StringBuilder append (Ljava/lang/String;)Ljava/lang/StringBuilder;
L164:   ldc "ci"
L166:   invokevirtual Method java/lang/StringBuilder append (Ljava/lang/String;)Ljava/lang/StringBuilder;
L169:   invokevirtual Method java/lang/StringBuilder toString ()Ljava/lang/String;
L172:   invokestatic Method JB method831 (Ljava/lang/String;)I
L175:   putfield Field bD this I
L178:   new java/lang/StringBuilder
L181:   aload_1
L182:   dup
L183:   pop2
L184:   dup
L185:   invokespecial Method java/lang/StringBuilder <init> ()V
L188:   aload_0
L189:   getfield Field Pc field370 Ljava/lang/String;
L192:   invokevirtual Method java/lang/StringBuilder append (Ljava/lang/String;)Ljava/lang/StringBuilder;
L195:   ldc "co"
L197:   invokevirtual Method java/lang/StringBuilder append (Ljava/lang/String;)Ljava/lang/StringBuilder;
L200:   invokevirtual Method java/lang/StringBuilder toString ()Ljava/lang/String;
L203:   invokestatic Method JB method831 (Ljava/lang/String;)I
L206:   putfield Field bD new I
L209:   new java/lang/StringBuilder
L212:   aload_1
L213:   dup
L214:   pop2
L215:   dup
L216:   invokespecial Method java/lang/StringBuilder <init> ()V
L219:   aload_0
L220:   getfield Field Pc field370 Ljava/lang/String;
L223:   invokevirtual Method java/lang/StringBuilder append (Ljava/lang/String;)Ljava/lang/StringBuilder;
L226:   ldc "ct"
L228:   invokevirtual Method java/lang/StringBuilder append (Ljava/lang/String;)Ljava/lang/StringBuilder;
L231:   invokevirtual Method java/lang/StringBuilder toString ()Ljava/lang/String;
L234:   invokestatic Method JB method831 (Ljava/lang/String;)I
L237:   putfield Field bD field718 I
L240:   areturn
L241:   
        .attribute StackMap b'\x00\x02\x00\x08\x00\x00\x00\x01\x07\x00\x30\x00\x09\x00\x01\x07\x00\x08\x00\x00'
    .end code
.end method

.method public static method392 : ()LbD;
    .code stack 17 locals 1
L0:     new bD
L3:     dup
L4:     invokespecial Method bD <init> ()V
L7:     astore_0
L8:     iconst_1
L9:     aload_0
L10:    dup_x1
L11:    dup_x2
L12:    iconst_3
L13:    iconst_2
L14:    aload_0
L15:    dup_x1
L16:    iconst_4
L17:    iconst_5
L18:    aload_0
L19:    dup_x1
L20:    bipush 7
L22:    aload_0
L23:    bipush 6
L25:    iconst_1
L26:    dup
L27:    pop2
L28:    putfield Field bD field715 I
L31:    iconst_1
L32:    dup
L33:    pop2
L34:    putfield Field bD field716 I
L37:    iconst_1
L38:    dup
L39:    pop2
L40:    putfield Field bD field714 I
L43:    iconst_1
L44:    dup
L45:    pop2
L46:    putfield Field bD field717 I
L49:    iconst_1
L50:    dup
L51:    pop2
L52:    putfield Field bD this I
L55:    iconst_1
L56:    dup
L57:    pop2
L58:    putfield Field bD new I
L61:    iconst_1
L62:    dup
L63:    pop2
L64:    putfield Field bD field718 I
L67:    areturn
L68:    
    .end code
.end method

.method private <init> : ()V
    .code stack 1 locals 1
L0:     aload_0
L1:     invokespecial Method java/lang/Object <init> ()V
L4:     return
L5:     
    .end code
.end method

.method public <init> : (LMd;)V
    .code stack 15 locals 2
L0:     aload_1
L1:     aload_0
L2:     dup_x1
L3:     aload_0
L4:     aload_1
L5:     dup_x1
L6:     aload_1
L7:     aload_0
L8:     dup_x1
L9:     aload_0
L10:    aload_1
L11:    dup_x1
L12:    aload_1
L13:    aload_0
L14:    dup_x1
L15:    invokespecial Method java/lang/Object <init> ()V
L18:    invokevirtual Method Md method886 ()I
L21:    putfield Field bD field715 I
L24:    invokevirtual Method Md method886 ()I
L27:    putfield Field bD field716 I
L30:    invokevirtual Method Md method886 ()I
L33:    putfield Field bD field714 I
L36:    invokevirtual Method Md method886 ()I
L39:    putfield Field bD field717 I
L42:    invokevirtual Method Md method886 ()I
L45:    putfield Field bD this I
L48:    invokevirtual Method Md method886 ()I
L51:    putfield Field bD new I
L54:    invokevirtual Method Md method886 ()I
L57:    putfield Field bD field718 I
L60:    return
L61:    
    .end code
    .exceptions java/io/IOException
.end method
.innerclasses
    Pc JB [0] public static final enum
.end innerclasses
.end class
