.version 49 0
.class public final super bE
.super Uf
.field public field1401 I
.field public field1402 I

.method public method699 : (LRg;[[ILff;[I)Z
    .code stack 6 locals 5
L0:     aload_1
L1:     getfield Field Rg field228 I
L4:     ifne L13
L7:     iconst_0
L8:     iconst_1
L9:     dup
L10:    pop2
L11:    ireturn
L12:    athrow
L13:    iconst_0
L14:    iconst_1
L15:    dup
L16:    pop2
L17:    dup
L18:    istore_2
L19:    bipush 28
L21:    iconst_1
L22:    dup
L23:    pop2
L24:    if_icmpge L72
L27:    iconst_0
L28:    iconst_1
L29:    dup
L30:    pop2
L31:    dup
L32:    istore_3
L33:    bipush 10
L35:    iconst_1
L36:    dup
L37:    pop2
L38:    if_icmpge L65
L41:    aload_1
L42:    getfield Field Rg this [[I
L45:    iload_3
L46:    aaload
L47:    iload_2
L48:    iaload
L49:    ifeq L58
L52:    iconst_0
L53:    iconst_1
L54:    dup
L55:    pop2
L56:    ireturn
L57:    athrow
L58:    iinc 3 1
L61:    iload_3
L62:    goto L33
L65:    iinc 2 1
L68:    iload_2
L69:    goto L19
L72:    aload_0
L73:    dup
L74:    dup
L75:    getfield Field bE field1402 I
L78:    iconst_1
L79:    dup
L80:    dup
L81:    pop2
L82:    isub
L83:    putfield Field bE field1402 I
L86:    getfield Field bE field1402 I
L89:    ifne L97
L92:    iconst_1
L93:    dup
L94:    dup
L95:    pop2
L96:    ireturn
L97:    iconst_0
L98:    iconst_1
L99:    dup
L100:   pop2
L101:   ireturn
L102:   
        .attribute StackMap b'\x00\x09\x00\x0C\x00\x00\x00\x01\x07\x00\x10\x00\x0D\x00\x05\x07\x00\x02\x07\x00\x0B\x07\x00\x12\x07\x00\x14\x07\x00\x16\x00\x00\x00\x13\x00\x05\x07\x00\x02\x07\x00\x0B\x01\x00\x07\x00\x16\x00\x01\x01\x00\x21\x00\x05\x07\x00\x02\x07\x00\x0B\x01\x01\x07\x00\x16\x00\x01\x01\x00\x39\x00\x00\x00\x01\x07\x00\x10\x00\x3A\x00\x05\x07\x00\x02\x07\x00\x0B\x01\x01\x07\x00\x16\x00\x00\x00\x41\x00\x05\x07\x00\x02\x07\x00\x0B\x01\x01\x07\x00\x16\x00\x00\x00\x48\x00\x05\x07\x00\x02\x07\x00\x0B\x01\x00\x07\x00\x16\x00\x00\x00\x61\x00\x05\x07\x00\x02\x07\x00\x0B\x01\x00\x07\x00\x16\x00\x00'
    .end code
.end method

.method public <init> : (Ljava/lang/String;Ljava/lang/String;Ljava/lang/String;IIZ)V
    .code stack 9 locals 7
L0:     iload 4
L2:     aload_0
L3:     dup_x1
L4:     aload_1
L5:     aload_2
L6:     aload_3
L7:     aconst_null
L8:     iload 5
L10:    iload 6
L12:    invokespecial Method Uf <init> (Ljava/lang/String;Ljava/lang/String;Ljava/lang/String;Ljava/lang/String;IZ)V
L15:    putfield Field bE field1401 I
L18:    return
L19:    
    .end code
.end method

.method public method703 : (LRg;)V
    .code stack 2 locals 2
L0:     aload_0
L1:     dup
L2:     getfield Field bE field1401 I
L5:     putfield Field bE field1402 I
L8:     return
L9:     
    .end code
.end method
.end class
