.version 49 0
.class public final super CC
.super Yd
.implements G
.field private true LDF;
.field private field172 Lnf;
.field private field173 Lqc;
.field private field174 Lqc;
.field private field175 LuF;
.field private field176 Led;
.field private field177 Lsb;
.field private field178 LzD;
.field private field179 LPg;
.field private field180 Lqd;
.field private static field181 I
.field private try LIe;
.field private field182 LYg;
.field private new Ljava/util/HashMap;
.field private field183 Z
.field private this Lqc;
.field private field184 LYg;
.field private field185 LUb;
.field private field186 LTe;
.field private field187 LmB;

.method public static synthetic method143 : (LCC;LTe;)V
    .code stack 2 locals 2
L0:     aload_0
L1:     aload_1
L2:     invokespecial Method CC method145 (LTe;)V
L5:     return
L6:     
    .end code
.end method

.method public static synthetic method144 : (LCC;)LFE;
    .code stack 1 locals 1
L0:     aload_0
L1:     getfield Field CC field1136 LFE;
L4:     areturn
L5:     
    .end code
.end method

.method private method145 : (LTe;)V
    .code stack 8 locals 2
L0:     aload_0
L1:     dup
L2:     invokevirtual Method CC method69 ()V
L5:     getfield Field CC field176 Led;
L8:     invokevirtual Method ed method94 ()Z
L11:    ifeq L41
L14:    aload_0
L15:    getfield Field CC field1136 LFE;
L18:    getstatic Field Ae field347 LAe;
L21:    ldc "If you play without a GEWALTIG.net account your result will\u000Anot be saved. Creating an account is free, easy and quick.\u000A\u000AWould you like to create an account now?"
L23:    getstatic Field jC field1045 [Ljava/lang/String;
L26:    new mb
L29:    dup
L30:    aload_0
L31:    aload_1
L32:    invokespecial Method mb <init> (LCC;LTe;)V
L35:    invokevirtual Method FE method446 (LAe;Ljava/lang/String;[Ljava/lang/String;Lh;)LjC;
L38:    pop
L39:    return
L40:    athrow
L41:    getstatic Field Kc field1931 LKc;
L44:    new Ze
L47:    dup
L48:    aload_0
L49:    getfield Field CC field176 Led;
L52:    aload_1
L53:    invokespecial Method Ze <init> (Led;LTe;)V
L56:    invokevirtual Method Kc method846 (LD;)V
L59:    aload_0
L60:    getfield Field CC field1136 LFE;
L63:    new Dg
L66:    aload_0
L67:    dup
L68:    pop2
L69:    dup
L70:    aload_0
L71:    dup_x2
L72:    getfield Field CC field176 Led;
L75:    aload_1
L76:    invokespecial Method Dg <init> (Led;LTe;)V
L79:    invokevirtual Method FE method455 (LbC;LbC;)V
L82:    return
L83:    
        .attribute StackMap b'\x00\x02\x00\x28\x00\x00\x00\x01\x07\x00\xBB\x00\x29\x00\x02\x07\x00\x02\x07\x00\xBD\x00\x00'
    .end code
.end method

.method public static synthetic return : (LCC;)LFE;
    .code stack 1 locals 1
L0:     aload_0
L1:     getfield Field CC field1136 LFE;
L4:     areturn
L5:     
    .end code
.end method

.method public method146 : (Lqd;)V
    .code stack 9 locals 3
L0:     aload_0
L1:     dup
L2:     invokevirtual Method CC method69 ()V
L5:     getfield Field CC field1136 LFE;
L8:     getstatic Field Ae field342 LAe;
L11:    ldc "Joining..."
L13:    getstatic Field jC field1036 [Ljava/lang/String;
L16:    invokevirtual Method FE method457 (LAe;Ljava/lang/String;[Ljava/lang/String;)LjC;
L19:    astore_2
        .catch java/lang/Exception from L20 to L46 using L48
L20:    aload_1
L21:    aload_0
L22:    getfield Field CC field176 Led;
L25:    iconst_1
L26:    dup
L27:    dup
L28:    pop2
L29:    new Lb
L32:    aconst_null
L33:    dup_x1
L34:    dup
L35:    pop2
L36:    dup
L37:    aload_0
L38:    aload_2
L39:    aload_1
L40:    invokespecial Method Lb <init> (LCC;LjC;Lqd;)V
L43:    invokevirtual Method qd method400 (Led;ZLjava/lang/String;LK;)V
L46:    return
L47:    athrow
L48:    astore_1
L49:    aload_0
L50:    aload_1
L51:    invokevirtual Method java/lang/Exception printStackTrace ()V
L54:    getstatic Field dc field2207 Ljava/util/HashMap;
L57:    getstatic Field KD field404 LKD;
L60:    invokevirtual Method java/util/HashMap get (Ljava/lang/Object;)Ljava/lang/Object;
L63:    checkcast java/lang/String
L66:    iconst_0
L67:    iconst_1
L68:    dup
L69:    pop2
L70:    invokevirtual Method CC method72 (Ljava/lang/String;Z)V
L73:    return
L74:    
        .attribute StackMap b'\x00\x02\x00\x2F\x00\x00\x00\x01\x07\x00\xBB\x00\x30\x00\x03\x07\x00\x02\x07\x00\xE9\x07\x00\xAC\x00\x01\x07\x00\xD8'
    .end code
.end method

.method public static synthetic method147 : (LCC;)Lnf;
    .code stack 1 locals 1
L0:     aload_0
L1:     getfield Field CC field172 Lnf;
L4:     areturn
L5:     
    .end code
.end method

.method public static synthetic method148 : (LCC;)LFE;
    .code stack 1 locals 1
L0:     aload_0
L1:     getfield Field CC field1136 LFE;
L4:     areturn
L5:     
    .end code
.end method

.method public method8 : (LD;)V
    .code stack 5 locals 3
L0:     aload_1
L1:     instanceof LB
L4:     ifeq L25
L7:     aload_1
L8:     checkcast LB
L11:    astore_2
L12:    aload_0
L13:    getfield Field CC field175 LuF;
L16:    aload_2
L17:    getfield Field LB field947 LRC;
L20:    invokevirtual Method uF method142 (Lqd;)V
L23:    return
L24:    athrow
L25:    aload_1
L26:    instanceof db
L29:    ifeq L50
L32:    aload_1
L33:    checkcast db
L36:    astore_2
L37:    aload_0
L38:    getfield Field CC field175 LuF;
L41:    aload_2
L42:    getfield Field db field965 LRC;
L45:    invokevirtual Method uF method142 (Lqd;)V
L48:    return
L49:    athrow
L50:    aload_1
L51:    instanceof tc
L54:    aload_1
L55:    swap
L56:    ifeq L75
L59:    checkcast tc
L62:    astore_2
L63:    aload_0
L64:    getfield Field CC field175 LuF;
L67:    aload_2
L68:    getfield Field tc field938 LRC;
L71:    invokevirtual Method uF method159 (Lqd;)V
L74:    return
L75:    instanceof Td
L78:    ifeq L122
L81:    aload_1
L82:    checkcast Td
L85:    astore_2
L86:    aload_0
L87:    dup
L88:    getfield Field CC field1136 LFE;
L91:    invokevirtual Method FE method113 ()V
L94:    getfield Field CC field183 Z
L97:    ifne L204
L100:   aload_0
L101:   getstatic Field dc field2207 Ljava/util/HashMap;
L104:   aload_2
L105:   getfield Field Td field683 LKD;
L108:   invokevirtual Method java/util/HashMap get (Ljava/lang/Object;)Ljava/lang/Object;
L111:   checkcast java/lang/String
L114:   iconst_1
L115:   dup
L116:   dup
L117:   pop2
L118:   invokevirtual Method CC method72 (Ljava/lang/String;Z)V
L121:   return
L122:   aload_1
L123:   instanceof Xd
L126:   ifeq L181
L129:   aload_1
L130:   checkcast Xd
L133:   dup
L134:   astore_2
L135:   getfield Field Xd field665 LHc;
L138:   getstatic Field Hc new LHc;
L141:   if_acmpne L204
L144:   getstatic Field Kc field1931 LKc;
L147:   aload_2
L148:   getfield Field Xd field663 Led;
L151:   invokevirtual Method Kc method860 (Led;)Z
L154:   ifeq L204
L157:   aload_0
L158:   getfield Field CC field1136 LFE;
L161:   new Dd
L164:   dup
L165:   aload_2
L166:   dup
L167:   getfield Field Xd field666 Led;
L170:   swap
L171:   getfield Field Xd field664 Ljava/lang/String;
L174:   invokespecial Method Dd <init> (Led;Ljava/lang/String;)V
L177:   invokevirtual Method FE method444 (LbC;)V
L180:   return
L181:   aload_1
L182:   instanceof pc
L185:   ifeq L193
L188:   aload_0
L189:   invokespecial Method CC try ()V
L192:   return
L193:   aload_1
L194:   instanceof gC
L197:   ifeq L204
L200:   aload_0
L201:   invokespecial Method CC try ()V
L204:   return
L205:   
        .attribute StackMap b'\x00\x09\x00\x18\x00\x00\x00\x01\x07\x00\xBB\x00\x19\x00\x02\x07\x00\x02\x07\x01\x1A\x00\x00\x00\x31\x00\x00\x00\x01\x07\x00\xBB\x00\x32\x00\x02\x07\x00\x02\x07\x01\x1A\x00\x00\x00\x4B\x00\x02\x07\x00\x02\x07\x01\x1A\x00\x01\x07\x01\x1A\x00\x7A\x00\x02\x07\x00\x02\x07\x01\x1A\x00\x00\x00\xB5\x00\x02\x07\x00\x02\x07\x01\x1A\x00\x00\x00\xC1\x00\x02\x07\x00\x02\x07\x01\x1A\x00\x00\x00\xCC\x00\x02\x07\x00\x02\x07\x01\x1A\x00\x00'
    .end code
.end method

.method private new : ()Lqc;
    .code stack 11 locals 6
L0:     new qc
L3:     dup
L4:     new og
L7:     dup
L8:     bipush 7
L10:    iconst_1
L11:    dup
L12:    pop2
L13:    ldc_w 1e-1f
L16:    ldc_w 4e-1f
L19:    invokespecial Method og <init> (IFF)V
L22:    invokespecial Method qc <init> (Ld;)V
L25:    astore_1
L26:    new DF
L29:    aload_1
L30:    dup_x1
L31:    dup
L32:    pop2
L33:    dup
L34:    ldc_w "Title"
L37:    invokespecial Method DF <init> (Ljava/lang/String;)V
L40:    invokevirtual Method qc method36 (LgB;)LgB;
L43:    aload_1
L44:    aload_0
L45:    dup
L46:    new nf
L49:    aload_0
L50:    dup_x2
L51:    dup
L52:    pop2
L53:    dup
L54:    ldc_w ""
L57:    invokespecial Method nf <init> (Ljava/lang/String;)V
L60:    putfield Field CC field172 Lnf;
L63:    getfield Field CC field172 Lnf;
L66:    ldc_w 5e0f
L69:    invokevirtual Method nf method104 (F)V
L72:    invokespecial Method CC method61 ()V
L75:    aload_0
L76:    getfield Field CC field172 Lnf;
L79:    bipush 6
L81:    iconst_1
L82:    dup
L83:    pop2
L84:    invokestatic Method java/lang/Integer valueOf (I)Ljava/lang/Integer;
L87:    invokevirtual Method qc method31 (LgB;Ljava/lang/Object;)V
L90:    new DF
L93:    aload_1
L94:    dup_x1
L95:    dup
L96:    pop2
L97:    dup
L98:    ldc_w "Game mode"
L101:   getstatic Field vD new LvD;
L104:   invokespecial Method DF <init> (Ljava/lang/String;LvD;)V
L107:   invokevirtual Method qc method36 (LgB;)LgB;
L110:   new qc
L113:   dup
L114:   new og
L117:   dup
L118:   iconst_1
L119:   dup
L120:   dup
L121:   pop2
L122:   fconst_0
L123:   ldc_w 2e-1f
L126:   invokespecial Method og <init> (IFF)V
L129:   invokespecial Method qc <init> (Ld;)V
L132:   astore_2
L133:   new java/util/HashMap
L136:   aload_0
L137:   dup_x1
L138:   dup
L139:   pop2
L140:   dup
L141:   invokespecial Method java/util/HashMap <init> ()V
L144:   putfield Field CC new Ljava/util/HashMap;
L147:   getstatic Field GF field1802 Ljava/util/HashMap;
L150:   invokevirtual Method java/util/HashMap entrySet ()Ljava/util/Set;
L153:   invokeinterface InterfaceMethod java/util/Set iterator ()Ljava/util/Iterator; 1
L158:   astore_3
L159:   pop2
L160:   aload_3
L161:   invokeinterface InterfaceMethod java/util/Iterator hasNext ()Z 1
L166:   ifeq L239
L169:   aload_3
L170:   invokeinterface InterfaceMethod java/util/Iterator next ()Ljava/lang/Object; 1
L175:   checkcast java/util/Map$Entry
L178:   astore 4
L180:   aload_0
L181:   getfield Field CC new Ljava/util/HashMap;
L184:   aload 4
L186:   invokeinterface InterfaceMethod java/util/Map$Entry getKey ()Ljava/lang/Object; 1
L191:   new Tg
L194:   dup
L195:   aload 4
L197:   invokeinterface InterfaceMethod java/util/Map$Entry getValue ()Ljava/lang/Object; 1
L202:   checkcast java/lang/String
L205:   invokespecial Method Tg <init> (Ljava/lang/String;)V
L208:   invokevirtual Method java/util/HashMap put (Ljava/lang/Object;Ljava/lang/Object;)Ljava/lang/Object;
L211:   pop
L212:   aload_2
L213:   aload_0
L214:   getfield Field CC new Ljava/util/HashMap;
L217:   aload 4
L219:   invokeinterface InterfaceMethod java/util/Map$Entry getKey ()Ljava/lang/Object; 1
L224:   invokevirtual Method java/util/HashMap get (Ljava/lang/Object;)Ljava/lang/Object;
L227:   checkcast gB
L230:   invokevirtual Method qc method36 (LgB;)LgB;
L233:   pop
L234:   aload_3
L235:   goto L161
L238:   athrow
        .catch java/lang/NullPointerException from L239 to L261 using L266
L239:   aload_0
L240:   getfield Field CC new Ljava/util/HashMap;
L243:   ldc_w "rm"
L246:   invokestatic Method JB method831 (Ljava/lang/String;)I
L249:   invokestatic Method java/lang/Integer valueOf (I)Ljava/lang/Integer;
L252:   invokevirtual Method java/util/HashMap get (Ljava/lang/Object;)Ljava/lang/Object;
L255:   checkcast Tg
L258:   invokevirtual Method Tg method56 ()V
L261:   aload_1
L262:   goto L291
L265:   athrow
L266:   astore_3
L267:   aload_0
L268:   getfield Field CC new Ljava/util/HashMap;
L271:   invokevirtual Method java/util/HashMap values ()Ljava/util/Collection;
L274:   invokeinterface InterfaceMethod java/util/Collection iterator ()Ljava/util/Iterator; 1
L279:   invokeinterface InterfaceMethod java/util/Iterator next ()Ljava/lang/Object; 1
L284:   checkcast Tg
L287:   invokevirtual Method Tg method56 ()V
L290:   aload_1
L291:   aload_2
L292:   bipush 6
L294:   iconst_1
L295:   dup
L296:   pop2
L297:   invokestatic Method java/lang/Integer valueOf (I)Ljava/lang/Integer;
L300:   invokevirtual Method qc method31 (LgB;Ljava/lang/Object;)V
L303:   new DF
L306:   aload_1
L307:   dup_x1
L308:   dup
L309:   pop2
L310:   dup
L311:   ldc_w "Speed limit"
L314:   getstatic Field vD new LvD;
L317:   invokespecial Method DF <init> (Ljava/lang/String;LvD;)V
L320:   invokevirtual Method qc method36 (LgB;)LgB;
L323:   aload_0
L324:   dup
L325:   dup_x1
L326:   new zD
L329:   aload_0
L330:   dup_x2
L331:   dup
L332:   pop2
L333:   dup
L334:   bipush 11
L336:   iconst_1
L337:   dup
L338:   pop2
L339:   invokespecial Method zD <init> (I)V
L342:   putfield Field CC field178 LzD;
L345:   new DF
L348:   dup
L349:   invokespecial Method DF <init> ()V
L352:   astore_3
L353:   getfield Field CC field178 LzD;
L356:   new BD
L359:   dup
L360:   aload_0
L361:   aload_3
L362:   invokespecial Method BD <init> (LCC;LDF;)V
L365:   invokevirtual Method zD method128 (Lh;)V
L368:   getfield Field CC field178 LzD;
L371:   iconst_0
L372:   iconst_1
L373:   dup
L374:   pop2
L375:   invokevirtual Method zD method14 (I)V
L378:   getfield Field CC field178 LzD;
L381:   iconst_1
L382:   dup
L383:   dup
L384:   pop2
L385:   invokevirtual Method zD method14 (I)V
L388:   pop
L389:   ldc_w "rmsl"
L392:   invokestatic Method JB method831 (Ljava/lang/String;)I
L395:   ldc_w 2147483647
L398:   if_icmpne L420
L401:   aload_1
L402:   aload_0
L403:   dup
L404:   getfield Field CC field178 LzD;
L407:   swap
L408:   getfield Field CC field178 LzD;
L411:   invokevirtual Method zD method247 ()I
L414:   invokevirtual Method zD method14 (I)V
L417:   goto L446
L420:   aload_0
L421:   getfield Field CC field178 LzD;
L424:   ldc_w "rmsl"
L427:   invokestatic Method JB method831 (Ljava/lang/String;)I
L430:   bipush 50
L432:   iconst_1
L433:   dup
L434:   pop2
L435:   isub
L436:   bipush 10
L438:   iconst_1
L439:   dup
L440:   pop2
L441:   idiv
L442:   invokevirtual Method zD method14 (I)V
L445:   aload_1
L446:   aload_0
L447:   getfield Field CC field178 LzD;
L450:   iconst_3
L451:   iconst_1
L452:   dup
L453:   pop2
L454:   invokestatic Method java/lang/Integer valueOf (I)Ljava/lang/Integer;
L457:   invokevirtual Method qc method31 (LgB;Ljava/lang/Object;)V
L460:   new SB
L463:   aload_1
L464:   dup_x1
L465:   dup
L466:   pop2
L467:   dup
L468:   aload_3
L469:   ldc_w 2e-1f
L472:   fconst_0
L473:   dup
L474:   dup_x1
L475:   invokespecial Method SB <init> (LgB;FFFF)V
L478:   iconst_3
L479:   iconst_1
L480:   dup
L481:   pop2
L482:   invokestatic Method java/lang/Integer valueOf (I)Ljava/lang/Integer;
L485:   invokevirtual Method qc method31 (LgB;Ljava/lang/Object;)V
L488:   new Pg
L491:   aload_0
L492:   dup_x1
L493:   dup
L494:   pop2
L495:   dup
L496:   ldc_w "Team play"
L499:   ldc_w "rmte"
L502:   invokestatic Method JB method831 (Ljava/lang/String;)I
L505:   ifeq L515
L508:   iconst_1
L509:   dup
L510:   dup
L511:   pop2
L512:   goto L519
L515:   iconst_0
L516:   iconst_1
L517:   dup
L518:   pop2
L519:   getstatic Field We new LWe;
L522:   invokespecial Method Pg <init> (Ljava/lang/String;ZLWe;)V
L525:   putfield Field CC field179 LPg;
L528:   iconst_5
L529:   aload_0
L530:   aload_1
L531:   dup_x1
L532:   new Vg
L535:   aload_1
L536:   dup
L537:   pop2
L538:   dup
L539:   invokespecial Method Vg <init> ()V
L542:   iconst_1
L543:   dup
L544:   dup
L545:   pop2
L546:   invokestatic Method java/lang/Integer valueOf (I)Ljava/lang/Integer;
L549:   invokevirtual Method qc method31 (LgB;Ljava/lang/Object;)V
L552:   getfield Field CC field179 LPg;
L555:   invokevirtual Method qc method36 (LgB;)LgB;
L558:   aload_0
L559:   dup
L560:   aload_1
L561:   dup_x2
L562:   new Vg
L565:   aload_1
L566:   dup_x1
L567:   dup
L568:   pop2
L569:   dup
L570:   invokespecial Method Vg <init> ()V
L573:   iconst_5
L574:   iconst_1
L575:   dup
L576:   pop2
L577:   invokestatic Method java/lang/Integer valueOf (I)Ljava/lang/Integer;
L580:   invokevirtual Method qc method31 (LgB;Ljava/lang/Object;)V
L583:   new Vg
L586:   aload_1
L587:   dup
L588:   pop2
L589:   dup
L590:   invokespecial Method Vg <init> ()V
L593:   bipush 6
L595:   iconst_1
L596:   dup
L597:   pop2
L598:   invokestatic Method java/lang/Integer valueOf (I)Ljava/lang/Integer;
L601:   invokevirtual Method qc method31 (LgB;Ljava/lang/Object;)V
L604:   new Yg
L607:   aload_0
L608:   dup
L609:   pop2
L610:   dup
L611:   ldc_w "Create room"
L614:   new FB
L617:   dup
L618:   aload_0
L619:   invokespecial Method FB <init> (LCC;)V
L622:   invokespecial Method Yg <init> (Ljava/lang/String;Lh;)V
L625:   putfield Field CC field184 LYg;
L628:   getfield Field CC field184 LYg;
L631:   invokevirtual Method qc method36 (LgB;)LgB;
L634:   pop2
L635:   iconst_1
L636:   dup
L637:   pop2
L638:   aload_0
L639:   getfield Field CC new Ljava/util/HashMap;
L642:   invokevirtual Method java/util/HashMap size ()I
L645:   iadd
L646:   iconst_1
L647:   dup
L648:   dup
L649:   pop2
L650:   multianewarray [[LgB; 2
L654:   astore 4
L656:   aload_0
L657:   aload 4
L659:   iconst_0
L660:   iconst_1
L661:   dup
L662:   pop2
L663:   aaload
L664:   iconst_0
L665:   dup_x1
L666:   iconst_1
L667:   dup
L668:   pop2
L669:   aload_0
L670:   getfield Field CC field172 Lnf;
L673:   aastore
L674:   iconst_1
L675:   dup
L676:   pop2
L677:   istore_2
L678:   getfield Field CC new Ljava/util/HashMap;
L681:   invokevirtual Method java/util/HashMap values ()Ljava/util/Collection;
L684:   invokeinterface InterfaceMethod java/util/Collection iterator ()Ljava/util/Iterator; 1
L689:   dup
L690:   astore_3
L691:   invokeinterface InterfaceMethod java/util/Iterator hasNext ()Z 1
L696:   ifeq L733
L699:   aload_3
L700:   invokeinterface InterfaceMethod java/util/Iterator next ()Ljava/lang/Object; 1
L705:   checkcast Tg
L708:   astore 5
L710:   aload_3
L711:   aload 4
L713:   iconst_1
L714:   dup
L715:   dup
L716:   pop2
L717:   iload_2
L718:   iadd
L719:   aaload
L720:   iconst_0
L721:   iconst_1
L722:   dup
L723:   pop2
L724:   aload 5
L726:   iinc 2 1
L729:   aastore
L730:   goto L691
L733:   aload 4
L735:   iconst_4
L736:   aload 4
L738:   dup_x1
L739:   iconst_3
L740:   iconst_2
L741:   aload 4
L743:   dup_x1
L744:   iconst_1
L745:   dup
L746:   dup
L747:   pop2
L748:   aload_0
L749:   getfield Field CC new Ljava/util/HashMap;
L752:   invokevirtual Method java/util/HashMap size ()I
L755:   iadd
L756:   aaload
L757:   iconst_0
L758:   iconst_1
L759:   dup
L760:   pop2
L761:   aload_0
L762:   getfield Field CC field178 LzD;
L765:   aastore
L766:   iconst_1
L767:   dup
L768:   pop2
L769:   aload_0
L770:   getfield Field CC new Ljava/util/HashMap;
L773:   invokevirtual Method java/util/HashMap size ()I
L776:   iadd
L777:   aaload
L778:   iconst_0
L779:   iconst_1
L780:   dup
L781:   pop2
L782:   aload_0
L783:   getfield Field CC field179 LPg;
L786:   aastore
L787:   iconst_1
L788:   dup
L789:   pop2
L790:   aload_0
L791:   getfield Field CC new Ljava/util/HashMap;
L794:   invokevirtual Method java/util/HashMap size ()I
L797:   iadd
L798:   aaload
L799:   iconst_0
L800:   iconst_1
L801:   dup
L802:   pop2
L803:   aload_0
L804:   getfield Field CC field184 LYg;
L807:   aastore
L808:   iconst_1
L809:   dup
L810:   pop2
L811:   aload_0
L812:   getfield Field CC new Ljava/util/HashMap;
L815:   invokevirtual Method java/util/HashMap size ()I
L818:   iadd
L819:   aaload
L820:   iconst_0
L821:   iconst_1
L822:   dup
L823:   pop2
L824:   aload_0
L825:   getfield Field CC field172 Lnf;
L828:   aastore
L829:   invokestatic Method mC method1702 ([[LgB;)V
L832:   new qc
L835:   dup
L836:   new VD
L839:   dup
L840:   invokespecial Method VD <init> ()V
L843:   invokespecial Method qc <init> (Ld;)V
L846:   astore_3
L847:   new SB
L850:   aload_3
L851:   dup_x1
L852:   dup_x2
L853:   dup
L854:   pop2
L855:   dup
L856:   aload_1
L857:   ldc_w 1.5e-1f
L860:   invokespecial Method SB <init> (LgB;F)V
L863:   getstatic Field VD field150 Ljava/lang/Object;
L866:   invokevirtual Method qc method31 (LgB;Ljava/lang/Object;)V
L869:   areturn
L870:   
        .attribute StackMap b'\x00\x0C\x00\xA1\x00\x04\x07\x00\x02\x07\x01\x59\x07\x01\x59\x07\x01\xA1\x00\x01\x07\x01\xA1\x00\xEE\x00\x00\x00\x01\x07\x00\xBB\x00\xEF\x00\x04\x07\x00\x02\x07\x01\x59\x07\x01\x59\x07\x01\xA1\x00\x00\x01\x09\x00\x00\x00\x01\x07\x00\xBB\x01\x0A\x00\x04\x07\x00\x02\x07\x01\x59\x07\x01\x59\x07\x01\xA1\x00\x01\x07\x01\x57\x01\x23\x00\x04\x07\x00\x02\x07\x01\x59\x07\x01\x59\x07\x01\xC9\x00\x01\x07\x01\x59\x01\xA4\x00\x04\x07\x00\x02\x07\x01\x59\x07\x01\x59\x07\x00\x5D\x00\x00\x01\xBE\x00\x04\x07\x00\x02\x07\x01\x59\x07\x01\x59\x07\x00\x5D\x00\x01\x07\x01\x59\x02\x03\x00\x04\x07\x00\x02\x07\x01\x59\x07\x01\x59\x07\x00\x5D\x00\x04\x07\x00\x02\x08\x01\xE8\x08\x01\xE8\x07\x01\x01\x02\x07\x00\x04\x07\x00\x02\x07\x01\x59\x07\x01\x59\x07\x00\x5D\x00\x05\x07\x00\x02\x08\x01\xE8\x08\x01\xE8\x07\x01\x01\x01\x02\xB3\x00\x05\x07\x00\x02\x07\x01\x59\x01\x07\x01\xA1\x07\x02\x0D\x00\x01\x07\x01\xA1\x02\xDD\x00\x05\x07\x00\x02\x07\x01\x59\x01\x07\x01\xA1\x07\x02\x0D\x00\x00'
    .end code
.end method

.method public static synthetic method149 : (LCC;)LFE;
    .code stack 1 locals 1
L0:     aload_0
L1:     getfield Field CC field1136 LFE;
L4:     areturn
L5:     
    .end code
.end method

.method private try : ()V
    .code stack 10 locals 4
L0:     aload_0
L1:     dup
L2:     getfield Field CC try LIe;
L5:     invokevirtual Method Ie method669 ()Ljava/lang/Object;
L8:     astore_1
L9:     getfield Field CC try LIe;
L12:    invokevirtual Method Ie method74 ()V
L15:    getstatic Field Kc field1931 LKc;
L18:    invokevirtual Method Kc method859 ()Ljava/util/Collection;
L21:    invokeinterface InterfaceMethod java/util/Collection iterator ()Ljava/util/Iterator; 1
L26:    dup
L27:    astore_2
L28:    invokeinterface InterfaceMethod java/util/Iterator hasNext ()Z 1
L33:    ifeq L101
L36:    aload_2
L37:    invokeinterface InterfaceMethod java/util/Iterator next ()Ljava/lang/Object; 1
L42:    checkcast ed
L45:    astore_3
L46:    aload_0
L47:    getfield Field CC try LIe;
L50:    aload_3
L51:    iconst_2
L52:    iconst_1
L53:    dup
L54:    pop2
L55:    anewarray java/lang/Object
L58:    iconst_1
L59:    dup
L60:    pop2
L61:    dup
L62:    iconst_0
L63:    iconst_1
L64:    dup
L65:    pop2
L66:    new EG
L69:    dup
L70:    aload_3
L71:    getfield Field ed new Ljava/lang/String;
L74:    ldc_w 2.9e-1f
L77:    dup
L78:    invokespecial Method EG <init> (Ljava/lang/String;FF)V
L81:    aastore
L82:    dup
L83:    iconst_1
L84:    dup
L85:    dup
L86:    pop2
L87:    aload_3
L88:    getfield Field ed field701 Ljava/lang/String;
L91:    aastore
L92:    invokevirtual Method Ie method635 (Ljava/lang/Object;[Ljava/lang/Object;)LDG;
L95:    pop
L96:    aload_2
L97:    goto L28
L100:   athrow
L101:   aload_0
L102:   dup
L103:   getfield Field CC try LIe;
L106:   aload_1
L107:   invokevirtual Method Ie method668 (Ljava/lang/Object;)V
L110:   getfield Field CC try LIe;
L113:   invokevirtual Method Ie method71 ()V
L116:   return
L117:   
        .attribute StackMap b'\x00\x03\x00\x1C\x00\x03\x07\x00\x02\x07\x01\xC9\x07\x01\xA1\x00\x01\x07\x01\xA1\x00\x64\x00\x00\x00\x01\x07\x00\xBB\x00\x65\x00\x03\x07\x00\x02\x07\x01\xC9\x07\x01\xA1\x00\x00'
    .end code
.end method

.method public static synthetic method150 : (LCC;)LFE;
    .code stack 1 locals 1
L0:     aload_0
L1:     getfield Field CC field1136 LFE;
L4:     areturn
L5:     
    .end code
.end method

.method public static synthetic method151 : (LCC;)LuF;
    .code stack 1 locals 1
L0:     aload_0
L1:     getfield Field CC field175 LuF;
L4:     areturn
L5:     
    .end code
.end method

.method public static synthetic false : (LCC;)LFE;
    .code stack 1 locals 1
L0:     aload_0
L1:     getfield Field CC field1136 LFE;
L4:     areturn
L5:     
    .end code
.end method

.method public static synthetic true : (LCC;)LFE;
    .code stack 1 locals 1
L0:     aload_0
L1:     getfield Field CC field1136 LFE;
L4:     areturn
L5:     
    .end code
.end method

.method public static synthetic method152 : (LCC;)LUb;
    .code stack 1 locals 1
L0:     aload_0
L1:     getfield Field CC field185 LUb;
L4:     areturn
L5:     
    .end code
.end method

.method public static synthetic this : ()I
    .code stack 1 locals 0
L0:     getstatic Field CC field181 I
L3:     ireturn
L4:     
    .end code
.end method

.method public method2 : ()V
    .code stack 4 locals 3
L0:     aload_0
L1:     dup
L2:     invokevirtual Method CC method69 ()V
L5:     invokespecial Method Yd method2 ()V
L8:     getstatic Field Kc field1931 LKc;
L11:    aload_0
L12:    dup_x1
L13:    invokevirtual Method Kc method849 (LG;)V
L16:    getfield Field CC new Ljava/util/HashMap;
L19:    ifnull L91
L22:    aload_0
L23:    getfield Field CC new Ljava/util/HashMap;
L26:    invokevirtual Method java/util/HashMap entrySet ()Ljava/util/Set;
L29:    invokeinterface InterfaceMethod java/util/Set iterator ()Ljava/util/Iterator; 1
L34:    astore_1
L35:    aload_1
L36:    invokeinterface InterfaceMethod java/util/Iterator hasNext ()Z 1
L41:    ifeq L91
L44:    aload_1
L45:    invokeinterface InterfaceMethod java/util/Iterator next ()Ljava/lang/Object; 1
L50:    checkcast java/util/Map$Entry
L53:    dup
L54:    astore_2
L55:    invokeinterface InterfaceMethod java/util/Map$Entry getValue ()Ljava/lang/Object; 1
L60:    checkcast Tg
L63:    invokevirtual Method Tg method227 ()Z
L66:    ifeq L35
L69:    ldc_w "rm"
L72:    aload_2
L73:    invokeinterface InterfaceMethod java/util/Map$Entry getKey ()Ljava/lang/Object; 1
L78:    checkcast java/lang/Integer
L81:    invokevirtual Method java/lang/Integer intValue ()I
L84:    invokestatic Method JB method827 (Ljava/lang/String;I)V
L87:    goto L35
L90:    athrow
L91:    aload_0
L92:    getfield Field CC field179 LPg;
L95:    ifnull L126
L98:    ldc_w "rmte"
L101:   aload_0
L102:   getfield Field CC field179 LPg;
L105:   invokevirtual Method Pg method227 ()Z
L108:   ifeq L119
L111:   iconst_1
L112:   dup
L113:   dup
L114:   pop2
L115:   goto L123
L118:   athrow
L119:   iconst_0
L120:   iconst_1
L121:   dup
L122:   pop2
L123:   invokestatic Method JB method827 (Ljava/lang/String;I)V
L126:   aload_0
L127:   getfield Field CC field178 LzD;
L130:   ifnull L180
L133:   aload_0
L134:   getfield Field CC field178 LzD;
L137:   invokevirtual Method zD method183 ()I
L140:   dup
L141:   istore_1
L142:   aload_0
L143:   getfield Field CC field178 LzD;
L146:   invokevirtual Method zD method247 ()I
L149:   if_icmpne L159
L152:   ldc_w 2147483647
L155:   istore_1
L156:   goto L173
L159:   iload_1
L160:   bipush 10
L162:   iconst_1
L163:   dup
L164:   pop2
L165:   imul
L166:   bipush 50
L168:   iconst_1
L169:   dup
L170:   pop2
L171:   iadd
L172:   istore_1
L173:   ldc_w "rmsl"
L176:   iload_1
L177:   invokestatic Method JB method827 (Ljava/lang/String;I)V
L180:   return
L181:   
        .attribute StackMap b'\x00\x0A\x00\x23\x00\x02\x07\x00\x02\x07\x01\xA1\x00\x00\x00\x5A\x00\x00\x00\x01\x07\x00\xBB\x00\x5B\x00\x01\x07\x00\x02\x00\x00\x00\x76\x00\x00\x00\x01\x07\x00\xBB\x00\x77\x00\x01\x07\x00\x02\x00\x01\x07\x01\x01\x00\x7B\x00\x01\x07\x00\x02\x00\x02\x07\x01\x01\x01\x00\x7E\x00\x01\x07\x00\x02\x00\x00\x00\x9F\x00\x02\x07\x00\x02\x01\x00\x00\x00\xAD\x00\x02\x07\x00\x02\x01\x00\x00\x00\xB4\x00\x01\x07\x00\x02\x00\x00'
    .end code
.end method

.method public static synthetic method153 : (LCC;I)LYg;
    .code stack 2 locals 2
L0:     aload_0
L1:     iload_1
L2:     invokespecial Method CC method161 (I)LYg;
L5:     areturn
L6:     
    .end code
.end method

.method private method154 : ()Lqc;
    .code stack 18 locals 3
L0:     new sb
L3:     aload_0
L4:     dup_x1
L5:     dup
L6:     pop2
L7:     dup
L8:     getstatic Field Id field638 LId;
L11:    new ab
L14:    dup
L15:    new Qb
L18:    dup
L19:    invokespecial Method Qb <init> ()V
L22:    iconst_0
L23:    iconst_1
L24:    dup
L25:    pop2
L26:    anewarray ed
L29:    iconst_1
L30:    dup
L31:    pop2
L32:    invokespecial Method ab <init> (Leb;[Led;)V
L35:    invokespecial Method sb <init> (LId;Lqd;)V
L38:    putfield Field CC field177 Lsb;
L41:    aload_0
L42:    dup
L43:    new uF
L46:    aload_0
L47:    dup_x1
L48:    dup
L49:    pop2
L50:    dup
L51:    invokespecial Method uF <init> ()V
L54:    putfield Field CC field175 LuF;
L57:    getfield Field CC field175 LuF;
L60:    new UB
L63:    dup
L64:    aload_0
L65:    invokespecial Method UB <init> (LCC;)V
L68:    invokevirtual Method uF method130 (Lh;)V
L71:    new qc
L74:    dup
L75:    new VD
L78:    dup
L79:    invokespecial Method VD <init> ()V
L82:    invokespecial Method qc <init> (Ld;)V
L85:    astore_1
L86:    new DF
L89:    aload_0
L90:    dup_x1
L91:    dup
L92:    pop2
L93:    dup
L94:    ldc_w ""
L97:    invokespecial Method DF <init> (Ljava/lang/String;)V
L100:   putfield Field CC true LDF;
L103:   getfield Field CC true LDF;
L106:   ldc_w 2.4e-1f
L109:   invokevirtual Method DF method104 (F)V
L112:   new qc
L115:   dup
L116:   new If
L119:   dup
L120:   invokespecial Method If <init> ()V
L123:   invokespecial Method qc <init> (Ld;)V
L126:   dup
L127:   astore_2
L128:   aload_0
L129:   getfield Field CC true LDF;
L132:   invokevirtual Method qc method36 (LgB;)LgB;
L135:   aload_2
L136:   aload_0
L137:   getfield Field CC field177 Lsb;
L140:   invokevirtual Method qc method36 (LgB;)LgB;
L143:   aload_0
L144:   dup
L145:   aload_1
L146:   dup_x2
L147:   new SB
L150:   aload_1
L151:   dup
L152:   pop2
L153:   dup
L154:   new IF
L157:   dup
L158:   aload_2
L159:   fconst_0
L160:   dup
L161:   getstatic Field FG field332 LFG;
L164:   iconst_1
L165:   dup
L166:   pop2
L167:   iconst_0
L168:   iconst_1
L169:   dup_x1
L170:   dup
L171:   pop2
L172:   invokespecial Method IF <init> (LgB;FFLFG;ZI)V
L175:   ldc_w 1e-1f
L178:   ldc_w 1.5e-1f
L181:   dup
L182:   dup_x2
L183:   invokespecial Method SB <init> (LgB;FFFF)V
L186:   getstatic Field VD field147 Ljava/lang/Object;
L189:   invokevirtual Method qc method31 (LgB;Ljava/lang/Object;)V
L192:   aload_0
L193:   iconst_0
L194:   iconst_1
L195:   dup
L196:   pop2
L197:   invokevirtual Method CC method125 (I)V
L200:   new Yg
L203:   aload_0
L204:   dup_x1
L205:   dup
L206:   pop2
L207:   dup
L208:   ldc_w "Join room"
L211:   invokespecial Method Yg <init> (Ljava/lang/String;)V
L214:   putfield Field CC field182 LYg;
L217:   getfield Field CC field182 LYg;
L220:   new Fc
L223:   dup
L224:   aload_0
L225:   invokespecial Method Fc <init> (LCC;)V
L228:   invokevirtual Method Yg method516 (Lh;)V
L231:   getfield Field CC field182 LYg;
L234:   iconst_0
L235:   iconst_1
L236:   dup
L237:   pop2
L238:   invokevirtual Method Yg method238 (Z)V
L241:   new qc
L244:   dup
L245:   new VD
L248:   dup
L249:   invokespecial Method VD <init> ()V
L252:   invokespecial Method qc <init> (Ld;)V
L255:   astore_2
L256:   new SB
L259:   aload_2
L260:   dup_x1
L261:   dup
L262:   pop2
L263:   dup
L264:   aload_0
L265:   getfield Field CC field182 LYg;
L268:   fconst_0
L269:   invokespecial Method SB <init> (LgB;F)V
L272:   getstatic Field VD this Ljava/lang/Object;
L275:   invokevirtual Method qc method31 (LgB;Ljava/lang/Object;)V
L278:   new SB
L281:   aload_1
L282:   dup
L283:   pop2
L284:   dup
L285:   aload_2
L286:   ldc_w 1.5e-1f
L289:   fconst_0
L290:   dup
L291:   dup_x2
L292:   invokespecial Method SB <init> (LgB;FFFF)V
L295:   getstatic Field VD field148 Ljava/lang/Object;
L298:   invokevirtual Method qc method31 (LgB;Ljava/lang/Object;)V
L301:   aload_0
L302:   dup
L303:   getfield Field CC field175 LuF;
L306:   swap
L307:   getfield Field CC field182 LYg;
L310:   invokevirtual Method uF method589 (LgB;)V
L313:   new qc
L316:   dup
L317:   new VD
L320:   dup
L321:   invokespecial Method VD <init> ()V
L324:   invokespecial Method qc <init> (Ld;)V
L327:   astore_2
L328:   new SB
L331:   aload_2
L332:   dup_x1
L333:   dup_x2
L334:   dup
L335:   pop2
L336:   dup
L337:   aload_0
L338:   getfield Field CC field175 LuF;
L341:   ldc_w 3e-1f
L344:   ldc_w 1.5e-1f
L347:   dup_x1
L348:   dup_x2
L349:   invokespecial Method SB <init> (LgB;FFFF)V
L352:   getstatic Field VD field149 Ljava/lang/Object;
L355:   invokevirtual Method qc method31 (LgB;Ljava/lang/Object;)V
L358:   new SB
L361:   aload_2
L362:   dup
L363:   pop2
L364:   dup
L365:   aload_1
L366:   ldc_w 1.5e-1f
L369:   dup
L370:   dup_x1
L371:   dup_x2
L372:   invokespecial Method SB <init> (LgB;FFFF)V
L375:   getstatic Field VD field147 Ljava/lang/Object;
L378:   invokevirtual Method qc method31 (LgB;Ljava/lang/Object;)V
L381:   pop2
L382:   aload_2
L383:   areturn
L384:   
    .end code
.end method

.method public static synthetic method155 : (LCC;LTe;)LTe;
    .code stack 3 locals 2
L0:     aload_0
L1:     aload_1
L2:     dup_x1
L3:     putfield Field CC field186 LTe;
L6:     areturn
L7:     
    .end code
.end method

.method public static synthetic method156 : (LCC;)LzD;
    .code stack 1 locals 1
L0:     aload_0
L1:     getfield Field CC field178 LzD;
L4:     areturn
L5:     
    .end code
.end method

.method public static synthetic method157 : (LCC;)LFE;
    .code stack 1 locals 1
L0:     aload_0
L1:     getfield Field CC field1136 LFE;
L4:     areturn
L5:     
    .end code
.end method

.method public static synthetic method158 : (LCC;)Lqc;
    .code stack 1 locals 1
L0:     aload_0
L1:     getfield Field CC this Lqc;
L4:     areturn
L5:     
    .end code
.end method

.method public method159 : (Lqd;)V
    .code stack 4 locals 2
L0:     aload_1
L1:     ifnonnull L18
L4:     iconst_0
L5:     aload_0
L6:     dup_x1
L7:     invokevirtual Method CC method69 ()V
L10:    iconst_1
L11:    dup
L12:    pop2
L13:    invokevirtual Method CC method125 (I)V
L16:    return
L17:    athrow
L18:    aload_0
L19:    getfield Field CC field180 Lqd;
L22:    aload_1
L23:    if_acmpne L43
L26:    aload_0
L27:    getfield Field CC field182 LYg;
L30:    invokevirtual Method Yg method584 ()Z
L33:    ifeq L43
L36:    aload_0
L37:    aload_1
L38:    invokevirtual Method CC method142 (Lqd;)V
L41:    return
L42:    athrow
L43:    aload_0
L44:    dup
L45:    aload_1
L46:    dup_x1
L47:    putfield Field CC field180 Lqd;
L50:    invokevirtual Method CC method146 (Lqd;)V
L53:    return
L54:    
        .attribute StackMap b'\x00\x04\x00\x11\x00\x00\x00\x01\x07\x00\xBB\x00\x12\x00\x02\x07\x00\x02\x07\x00\xE9\x00\x00\x00\x2A\x00\x00\x00\x01\x07\x00\xBB\x00\x2B\x00\x02\x07\x00\x02\x07\x00\xE9\x00\x00'
    .end code
.end method

.method private method16 : (Led;)V
    .code stack 5 locals 3
L0:     aload_0
L1:     dup
L2:     aload_1
L3:     putfield Field CC field176 Led;
L6:     getfield Field CC field176 Led;
L9:     invokevirtual Method ed method94 ()Z
L12:    ifne L26
L15:    ldc_w "Achievements"
L18:    aload_0
L19:    dup_x1
L20:    invokespecial Method CC method177 ()Lqc;
L23:    invokevirtual Method CC method182 (Ljava/lang/String;LgB;)V
L26:    aload_0
L27:    invokespecial Method CC method61 ()V
L30:    getstatic Field Kc field1931 LKc;
L33:    invokevirtual Method Kc method850 ()Ljava/util/LinkedHashMap;
L36:    invokevirtual Method java/util/LinkedHashMap values ()Ljava/util/Collection;
L39:    invokeinterface InterfaceMethod java/util/Collection iterator ()Ljava/util/Iterator; 1
L44:    dup
L45:    astore_1
L46:    invokeinterface InterfaceMethod java/util/Iterator hasNext ()Z 1
L51:    ifeq L77
L54:    aload_1
L55:    invokeinterface InterfaceMethod java/util/Iterator next ()Ljava/lang/Object; 1
L60:    checkcast RC
L63:    astore_2
L64:    aload_1
L65:    aload_0
L66:    getfield Field CC field175 LuF;
L69:    aload_2
L70:    invokevirtual Method uF method142 (Lqd;)V
L73:    goto L46
L76:    athrow
L77:    aload_0
L78:    dup
L79:    getfield Field CC field175 LuF;
L82:    invokevirtual Method uF method10 ()V
L85:    getfield Field CC this Lqc;
L88:    getfield Field qc field65 Ljava/util/ArrayList;
L91:    getstatic Field CC field181 I
L94:    invokevirtual Method java/util/ArrayList get (I)Ljava/lang/Object;
L97:    checkcast KE
L100:   fconst_0
L101:   dup
L102:   invokevirtual Method KE method577 (FF)V
L105:   getstatic Field Kc field1931 LKc;
L108:   new Ze
L111:   dup
L112:   aload_0
L113:   getfield Field CC field176 Led;
L116:   aconst_null
L117:   invokespecial Method Ze <init> (Led;LTe;)V
L120:   invokevirtual Method Kc method846 (LD;)V
L123:   return
L124:   
        .attribute StackMap b'\x00\x04\x00\x1A\x00\x02\x07\x00\x02\x07\x00\xA0\x00\x00\x00\x2E\x00\x02\x07\x00\x02\x07\x01\xA1\x00\x01\x07\x01\xA1\x00\x4C\x00\x00\x00\x01\x07\x00\xBB\x00\x4D\x00\x02\x07\x00\x02\x07\x01\xA1\x00\x00'
    .end code
.end method

.method public method32 : (FF)V
    .code stack 3 locals 3
L0:     aload_0
L1:     fload_1
L2:     fload_2
L3:     invokespecial Method Yd method32 (FF)V
L6:     return
L7:     
    .end code
.end method

.method public static synthetic method160 : (LCC;Led;)V
    .code stack 2 locals 2
L0:     aload_0
L1:     aload_1
L2:     invokespecial Method CC method16 (Led;)V
L5:     return
L6:     
    .end code
.end method

.method private method161 : (I)LYg;
    .code stack 8 locals 3
L0:     iload_1
L1:     ifne L7
L4:     aconst_null
L5:     areturn
L6:     athrow
L7:     new Yg
L10:    dup
L11:    new ID
L14:    dup
L15:    aload_0
L16:    ldc_w 1.5e-1f
L19:    dup
L20:    invokespecial Method ID <init> (LCC;FF)V
L23:    ldc_w 1.8e-1f
L26:    ldc_w 2.7e-1f
L29:    iconst_0
L30:    iconst_1
L31:    dup
L32:    pop2
L33:    invokespecial Method Yg <init> (LuB;FFZ)V
L36:    astore_2
L37:    ldc_w 2.5e-1f
L40:    aload_2
L41:    dup_x1
L42:    dup_x2
L43:    new Eb
L46:    aload_2
L47:    dup
L48:    pop2
L49:    dup
L50:    aload_0
L51:    iload_1
L52:    invokespecial Method Eb <init> (LCC;I)V
L55:    invokevirtual Method Yg method516 (Lh;)V
L58:    ldc_w 2.5e-1f
L61:    invokevirtual Method Yg method32 (FF)V
L64:    areturn
L65:    
        .attribute StackMap b'\x00\x02\x00\x06\x00\x00\x00\x01\x07\x00\xBB\x00\x07\x00\x02\x07\x00\x02\x01\x00\x00'
    .end code
.end method

.method public static synthetic method162 : (LCC;)LFE;
    .code stack 1 locals 1
L0:     aload_0
L1:     getfield Field CC field1136 LFE;
L4:     areturn
L5:     
    .end code
.end method

.method public static synthetic method163 : (LCC;)LFE;
    .code stack 1 locals 1
L0:     aload_0
L1:     getfield Field CC field1136 LFE;
L4:     areturn
L5:     
    .end code
.end method

.method public method164 : (Ljava/lang/String;Leb;ZZII)V
    .code stack 14 locals 8
L0:     aload_1
L1:     ifnull L17
L4:     ldc_w ""
L7:     aload_1
L8:     invokevirtual Method java/lang/String trim ()Ljava/lang/String;
L11:    invokevirtual Method java/lang/String equals (Ljava/lang/Object;)Z
L14:    ifeq L44
L17:    aload_0
L18:    getfield Field CC field1136 LFE;
L21:    getstatic Field Ae field349 LAe;
L24:    ldc_w "Please enter a name for the room."
L27:    getstatic Field jC field1048 [Ljava/lang/String;
L30:    new Vb
L33:    dup
L34:    aload_0
L35:    invokespecial Method Vb <init> (LCC;)V
L38:    invokevirtual Method FE method446 (LAe;Ljava/lang/String;[Ljava/lang/String;Lh;)LjC;
L41:    pop
L42:    return
L43:    athrow
L44:    iload_3
L45:    ifeq L85
L48:    aload_0
L49:    getfield Field CC field176 Led;
L52:    invokevirtual Method ed method94 ()Z
L55:    ifeq L85
L58:    aload_0
L59:    getfield Field CC field1136 LFE;
L62:    getstatic Field Ae field347 LAe;
L65:    ldc_w "If you play without a GEWALTIG.net account you cannot\u000Acreate team play rooms.\u000A\u000AWould you like to create an account now?"
L68:    getstatic Field jC field1049 [Ljava/lang/String;
L71:    new jD
L74:    dup
L75:    aload_0
L76:    invokespecial Method jD <init> (LCC;)V
L79:    invokevirtual Method FE method446 (LAe;Ljava/lang/String;[Ljava/lang/String;Lh;)LjC;
L82:    pop
L83:    return
L84:    athrow
L85:    aload_0
L86:    getfield Field CC field1136 LFE;
L89:    getstatic Field Ae field342 LAe;
L92:    ldc_w "Creating..."
L95:    getstatic Field jC field1036 [Ljava/lang/String;
L98:    invokevirtual Method FE method457 (LAe;Ljava/lang/String;[Ljava/lang/String;)LjC;
L101:   astore 7
L103:   getstatic Field Kc field1931 LKc;
L106:   aload_1
L107:   aconst_null
L108:   aload_2
L109:   iload_3
L110:   iload 4
L112:   iload 5
L114:   iload 6
L116:   getstatic Field Kc field1931 LKc;
L119:   getstatic Field Pc field373 LPc;
L122:   invokevirtual Method Kc method853 (LPc;)Led;
L125:   new Jd
L128:   dup
L129:   aload_0
L130:   aload 7
L132:   aload_1
L133:   invokespecial Method Jd <init> (LCC;LjC;Ljava/lang/String;)V
L136:   invokevirtual Method Kc method855 (Ljava/lang/String;Ljava/lang/String;Leb;ZZIILed;LK;)V
L139:   return
L140:   
        .attribute StackMap b'\x00\x05\x00\x11\x00\x07\x07\x00\x02\x07\x01\x01\x07\x03\x05\x01\x01\x01\x01\x00\x00\x00\x2B\x00\x00\x00\x01\x07\x00\xBB\x00\x2C\x00\x07\x07\x00\x02\x07\x01\x01\x07\x03\x05\x01\x01\x01\x01\x00\x00\x00\x54\x00\x00\x00\x01\x07\x00\xBB\x00\x55\x00\x07\x07\x00\x02\x07\x01\x01\x07\x03\x05\x01\x01\x01\x01\x00\x00'
    .end code
.end method

.method public static synthetic method165 : (LCC;)LmB;
    .code stack 1 locals 1
L0:     aload_0
L1:     getfield Field CC field187 LmB;
L4:     areturn
L5:     
    .end code
.end method

.method private method166 : (LfE;)Ljava/lang/String;
    .code stack 2 locals 2
L0:     getstatic Field Db field1792 [I
L3:     aload_1
L4:     invokevirtual Method fE ordinal ()I
L7:     iaload
L8:     tableswitch 1
            L52
            L61
            L61
            L66
            L70
            L70
            L77
            default : L81
L52:    ldc_w "Blocks"
L55:    iconst_0
L56:    ifne L74
L59:    areturn
L60:    athrow
L61:    ldc_w "Time"
L64:    areturn
L65:    athrow
L66:    ldc_w "Tetrises"
L69:    areturn
L70:    ldc_w "Lines"
L73:    areturn
L74:    goto L55
L77:    ldc_w "BPM"
L80:    areturn
L81:    new java/lang/RuntimeException
L84:    dup
L85:    invokespecial Method java/lang/RuntimeException <init> ()V
L88:    athrow
L89:    
        .attribute StackMap b'\x00\x0A\x00\x34\x00\x02\x07\x00\x02\x07\x03\x31\x00\x00\x00\x37\x00\x02\x07\x00\x02\x07\x03\x31\x00\x01\x07\x01\x01\x00\x3C\x00\x00\x00\x01\x07\x00\xBB\x00\x3D\x00\x02\x07\x00\x02\x07\x03\x31\x00\x00\x00\x41\x00\x00\x00\x01\x07\x00\xBB\x00\x42\x00\x02\x07\x00\x02\x07\x03\x31\x00\x00\x00\x46\x00\x02\x07\x00\x02\x07\x03\x31\x00\x00\x00\x4A\x00\x02\x07\x00\x02\x07\x03\x31\x00\x01\x07\x01\x01\x00\x4D\x00\x02\x07\x00\x02\x07\x03\x31\x00\x00\x00\x51\x00\x02\x07\x00\x02\x07\x03\x31\x00\x00'
    .end code
.end method

.method public method49 : ()V
    .code stack 13 locals 2
L0:     ldc_w "Challenges"
L3:     ldc_w "Rooms"
L6:     aload_0
L7:     dup_x2
L8:     ldc_w "Play online"
L11:    invokespecial Method Yd method12 (Ljava/lang/String;)V
L14:    aload_0
L15:    dup_x1
L16:    invokespecial Method CC method154 ()Lqc;
L19:    invokevirtual Method CC method182 (Ljava/lang/String;LgB;)V
L22:    aload_0
L23:    dup_x1
L24:    invokespecial Method CC method169 ()Lqc;
L27:    invokevirtual Method CC method182 (Ljava/lang/String;LgB;)V
L30:    new CD
L33:    aload_0
L34:    dup_x2
L35:    dup
L36:    pop2
L37:    dup
L38:    invokespecial Method CD <init> ()V
L41:    putfield Field CC field185 LUb;
L44:    new Ie
L47:    aload_0
L48:    dup
L49:    pop2
L50:    dup
L51:    iconst_2
L52:    iconst_1
L53:    dup
L54:    pop2
L55:    anewarray java/lang/String
L58:    iconst_1
L59:    dup
L60:    pop2
L61:    dup
L62:    iconst_0
L63:    iconst_1
L64:    dup
L65:    pop2
L66:    ldc_w ""
L69:    aastore
L70:    dup
L71:    iconst_1
L72:    dup
L73:    dup
L74:    pop2
L75:    ldc_w "Player"
L78:    aastore
L79:    iconst_2
L80:    iconst_1
L81:    dup
L82:    pop2
L83:    anewarray pF
L86:    iconst_1
L87:    dup
L88:    pop2
L89:    dup
L90:    iconst_0
L91:    iconst_1
L92:    dup
L93:    pop2
L94:    getstatic Field pF field388 LpF;
L97:    aastore
L98:    dup
L99:    iconst_1
L100:   dup
L101:   dup
L102:   pop2
L103:   getstatic Field pF field390 LpF;
L106:   aastore
L107:   ldc_w 2.5e-1f
L110:   bipush 10
L112:   iconst_1
L113:   dup
L114:   pop2
L115:   invokespecial Method Ie <init> ([Ljava/lang/String;[LpF;FI)V
L118:   putfield Field CC try LIe;
L121:   ldc_w "New room"
L124:   aload_0
L125:   dup
L126:   dup_x2
L127:   aload_0
L128:   dup
L129:   dup2
L130:   getfield Field CC try LIe;
L133:   new NC
L136:   dup
L137:   aload_0
L138:   invokespecial Method NC <init> (LCC;)V
L141:   invokevirtual Method Ie method587 (Lh;)V
L144:   invokespecial Method CC try ()V
L147:   new uc
L150:   aload_0
L151:   dup
L152:   pop2
L153:   dup
L154:   aload_0
L155:   dup_x2
L156:   new VD
L159:   aload_0
L160:   dup
L161:   pop2
L162:   dup
L163:   invokespecial Method VD <init> ()V
L166:   invokespecial Method uc <init> (LCC;Ld;)V
L169:   putfield Field CC field173 Lqc;
L172:   getfield Field CC field173 Lqc;
L175:   aload_0
L176:   getfield Field CC field185 LUb;
L179:   getstatic Field VD field147 Ljava/lang/Object;
L182:   invokevirtual Method qc method31 (LgB;Ljava/lang/Object;)V
L185:   getfield Field CC field173 Lqc;
L188:   new SB
L191:   dup
L192:   aload_0
L193:   getfield Field CC try LIe;
L196:   ldc_w 3e-1f
L199:   ldc_w 1.5e-1f
L202:   dup
L203:   dup_x1
L204:   invokespecial Method SB <init> (LgB;FFFF)V
L207:   getstatic Field VD this Ljava/lang/Object;
L210:   invokevirtual Method qc method31 (LgB;Ljava/lang/Object;)V
L213:   getfield Field CC field185 LUb;
L216:   invokevirtual Method Ub method13 ()Ljava/lang/String;
L219:   aload_0
L220:   getfield Field CC field173 Lqc;
L223:   invokevirtual Method CC method182 (Ljava/lang/String;LgB;)V
L226:   aload_0
L227:   invokespecial Method CC new ()Lqc;
L230:   invokevirtual Method CC method182 (Ljava/lang/String;LgB;)V
L233:   getstatic Field Kc field1931 LKc;
L236:   getstatic Field Pc field373 LPc;
L239:   invokevirtual Method Kc method853 (LPc;)Led;
L242:   ifnonnull L290
L245:   aload_0
L246:   iconst_0
L247:   iconst_1
L248:   dup
L249:   pop2
L250:   invokevirtual Method CC method14 (I)V
L253:   new GD
L256:   dup
L257:   aload_0
L258:   dup_x2
L259:   getstatic Field Pc field373 LPc;
L262:   invokespecial Method GD <init> (LCC;LPc;)V
L265:   astore_1
L266:   new Hd
L269:   aload_1
L270:   dup_x1
L271:   dup
L272:   pop2
L273:   dup
L274:   aload_0
L275:   invokespecial Method Hd <init> (LCC;)V
L278:   invokevirtual Method GD method551 (Lc;)V
L281:   getfield Field CC field1136 LFE;
L284:   aload_1
L285:   invokevirtual Method FE method444 (LbC;)V
L288:   return
L289:   athrow
L290:   getstatic Field Kc field1931 LKc;
L293:   aload_0
L294:   getstatic Field mc field387 Lmc;
L297:   invokevirtual Method Kc method844 (LG;Lmc;)V
L300:   aload_0
L301:   getstatic Field Kc field1931 LKc;
L304:   checkcast md
L307:   getstatic Field Pc field373 LPc;
L310:   invokevirtual Method md method853 (LPc;)Led;
L313:   invokespecial Method CC method16 (Led;)V
L316:   return
L317:   
        .attribute StackMap b'\x00\x02\x01\x21\x00\x00\x00\x01\x07\x00\xBB\x01\x22\x00\x01\x07\x00\x02\x00\x00'
    .end code
.end method

.method public method29 : ()V
    .code stack 5 locals 1
L0:     aload_0
L1:     invokespecial Method Yd method29 ()V
L4:     new mB
L7:     aload_0
L8:     dup_x1
L9:     dup
L10:    pop2
L11:    dup
L12:    getstatic Field xc field435 Lxc;
L15:    aload_0
L16:    getfield Field CC field174 Lqc;
L19:    invokespecial Method mB <init> (Lxc;Lqc;)V
L22:    putfield Field CC field187 LmB;
L25:    return
L26:    
    .end code
.end method

.method public static synthetic method167 : (LCC;)LPg;
    .code stack 1 locals 1
L0:     aload_0
L1:     getfield Field CC field179 LPg;
L4:     areturn
L5:     
    .end code
.end method

.method public static synthetic method168 : (LCC;)LIe;
    .code stack 1 locals 1
L0:     aload_0
L1:     getfield Field CC try LIe;
L4:     areturn
L5:     
    .end code
.end method

.method public static synthetic new : (LCC;)LFE;
    .code stack 1 locals 1
L0:     aload_0
L1:     getfield Field CC field1136 LFE;
L4:     areturn
L5:     
    .end code
.end method

.method public static synthetic try : (LCC;)Led;
    .code stack 1 locals 1
L0:     aload_0
L1:     getfield Field CC field176 Led;
L4:     areturn
L5:     
    .end code
.end method

.method private method169 : ()Lqc;
    .code stack 14 locals 12
L0:     new DF
L3:     dup
L4:     ldc_w ""
L7:     getstatic Field We field467 LWe;
L10:    invokespecial Method DF <init> (Ljava/lang/String;LWe;)V
L13:    astore_1
L14:    new DF
L17:    dup
L18:    ldc_w ""
L21:    getstatic Field We field479 LWe;
L24:    invokespecial Method DF <init> (Ljava/lang/String;LWe;)V
L27:    astore_2
L28:    new Ie
L31:    dup
L32:    iconst_5
L33:    iconst_1
L34:    dup
L35:    pop2
L36:    anewarray java/lang/String
L39:    iconst_1
L40:    dup
L41:    pop2
L42:    dup
L43:    iconst_0
L44:    iconst_1
L45:    dup
L46:    pop2
L47:    ldc_w ""
L50:    aastore
L51:    dup
L52:    iconst_1
L53:    dup
L54:    dup
L55:    pop2
L56:    ldc_w ""
L59:    aastore
L60:    dup
L61:    iconst_2
L62:    iconst_1
L63:    dup
L64:    pop2
L65:    ldc_w "Player"
L68:    aastore
L69:    dup
L70:    iconst_3
L71:    iconst_1
L72:    dup
L73:    pop2
L74:    ldc_w "Time"
L77:    aastore
L78:    dup
L79:    iconst_4
L80:    iconst_1
L81:    dup
L82:    pop2
L83:    ldc_w ""
L86:    aastore
L87:    iconst_5
L88:    iconst_1
L89:    dup
L90:    pop2
L91:    anewarray pF
L94:    iconst_1
L95:    dup
L96:    pop2
L97:    dup
L98:    iconst_0
L99:    iconst_1
L100:   dup
L101:   pop2
L102:   getstatic Field pF field391 LpF;
L105:   aastore
L106:   dup
L107:   iconst_1
L108:   dup
L109:   dup
L110:   pop2
L111:   getstatic Field pF field388 LpF;
L114:   aastore
L115:   dup
L116:   iconst_2
L117:   iconst_1
L118:   dup
L119:   pop2
L120:   getstatic Field pF field390 LpF;
L123:   aastore
L124:   dup
L125:   iconst_3
L126:   iconst_1
L127:   dup
L128:   pop2
L129:   getstatic Field pF field391 LpF;
L132:   aastore
L133:   dup
L134:   iconst_4
L135:   iconst_1
L136:   dup
L137:   pop2
L138:   getstatic Field pF field391 LpF;
L141:   aastore
L142:   ldc_w 2.5e-1f
L145:   bipush 10
L147:   iconst_1
L148:   dup
L149:   pop2
L150:   invokespecial Method Ie <init> ([Ljava/lang/String;[LpF;FI)V
L153:   astore_3
L154:   new ig
L157:   dup
L158:   getstatic Field Ae field342 LAe;
L161:   fconst_1
L162:   dup
L163:   invokespecial Method ig <init> (LAe;FF)V
L166:   astore 4
L168:   new qc
L171:   dup
L172:   new VD
L175:   dup
L176:   invokespecial Method VD <init> ()V
L179:   invokespecial Method qc <init> (Ld;)V
L182:   dup
L183:   astore 5
L185:   aload_0
L186:   aload 4
L188:   invokestatic Method Wd method1090 (LgB;)Lqc;
L191:   dup_x1
L192:   putfield Field CC field174 Lqc;
L195:   invokevirtual Method qc method36 (LgB;)LgB;
L198:   aload 5
L200:   aload_3
L201:   invokevirtual Method qc method36 (LgB;)LgB;
L204:   new ec
L207:   aload_3
L208:   dup_x1
L209:   dup
L210:   pop2
L211:   dup
L212:   aload_0
L213:   aload_3
L214:   invokespecial Method ec <init> (LCC;LIe;)V
L217:   invokevirtual Method Ie method587 (Lh;)V
L220:   new Yg
L223:   dup
L224:   ldc_w "Play challenge"
L227:   new Mb
L230:   dup
L231:   aload_0
L232:   invokespecial Method Mb <init> (LCC;)V
L235:   invokespecial Method Yg <init> (Ljava/lang/String;Lh;)V
L238:   astore 6
L240:   iconst_0
L241:   new qc
L244:   aload_0
L245:   dup_x1
L246:   dup
L247:   pop2
L248:   dup
L249:   new fG
L252:   dup
L253:   getstatic Field LE field634 LLE;
L256:   ldc_w 1e-1f
L259:   invokespecial Method fG <init> (LLE;F)V
L262:   invokespecial Method qc <init> (Ld;)V
L265:   putfield Field CC this Lqc;
L268:   iconst_1
L269:   dup
L270:   pop2
L271:   istore 7
L273:   getstatic Field SE field2069 Ljava/util/Map;
L276:   invokeinterface InterfaceMethod java/util/Map values ()Ljava/util/Collection; 1
L281:   invokeinterface InterfaceMethod java/util/Collection iterator ()Ljava/util/Iterator; 1
L286:   astore 8
L288:   pop2
L289:   aload 8
L291:   invokeinterface InterfaceMethod java/util/Iterator hasNext ()Z 1
L296:   ifeq L366
L299:   aload 8
L301:   invokeinterface InterfaceMethod java/util/Iterator next ()Ljava/lang/Object; 1
L306:   checkcast Te
L309:   dup
L310:   astore 9
L312:   astore 10
L314:   iload 7
L316:   istore 11
L318:   aload 8
L320:   aload_0
L321:   iinc 7 1
L324:   getfield Field CC this Lqc;
L327:   new KE
L330:   dup
L331:   aload 9
L333:   getfield Field Te true Ljava/lang/String;
L336:   new Mc
L339:   dup
L340:   aload_0
L341:   iload 11
L343:   aload 10
L345:   aload_1
L346:   aload_2
L347:   aload_3
L348:   aload 4
L350:   invokespecial Method Mc <init> (LCC;ILTe;LDF;LDF;LIe;Lig;)V
L353:   invokespecial Method KE <init> (Ljava/lang/String;Lh;)V
L356:   getstatic Field dg field337 Ldg;
L359:   invokevirtual Method qc method31 (LgB;Ljava/lang/Object;)V
L362:   goto L291
L365:   athrow
L366:   iconst_0
L367:   iconst_1
L368:   dup
L369:   pop2
L370:   dup
L371:   istore 7
L373:   aload_0
L374:   getfield Field CC this Lqc;
L377:   getfield Field qc field65 Ljava/util/ArrayList;
L380:   invokevirtual Method java/util/ArrayList size ()I
L383:   if_icmpge L458
L386:   iload 7
L388:   ifle L429
L391:   aload_0
L392:   getfield Field CC this Lqc;
L395:   getfield Field qc field65 Ljava/util/ArrayList;
L398:   iload 7
L400:   invokevirtual Method java/util/ArrayList get (I)Ljava/lang/Object;
L403:   checkcast gB
L406:   aload_0
L407:   getfield Field CC this Lqc;
L410:   getfield Field qc field65 Ljava/util/ArrayList;
L413:   iload 7
L415:   iconst_1
L416:   dup
L417:   dup
L418:   pop2
L419:   isub
L420:   invokevirtual Method java/util/ArrayList get (I)Ljava/lang/Object;
L423:   checkcast gB
L426:   invokevirtual Method gB method594 (LgB;)V
L429:   aload_0
L430:   getfield Field CC this Lqc;
L433:   getfield Field qc field65 Ljava/util/ArrayList;
L436:   iload 7
L438:   invokevirtual Method java/util/ArrayList get (I)Ljava/lang/Object;
L441:   iinc 7 1
L444:   checkcast gB
L447:   aload 6
L449:   invokevirtual Method gB method589 (LgB;)V
L452:   iload 7
L454:   goto L373
L457:   athrow
L458:   new qc
L461:   dup
L462:   new fG
L465:   dup
L466:   getstatic Field LE field634 LLE;
L469:   ldc_w 1e-1f
L472:   invokespecial Method fG <init> (LLE;F)V
L475:   invokespecial Method qc <init> (Ld;)V
L478:   astore 7
L480:   aload_2
L481:   aload 7
L483:   dup_x1
L484:   aload_1
L485:   getstatic Field dg field337 Ldg;
L488:   invokevirtual Method qc method31 (LgB;Ljava/lang/Object;)V
L491:   getstatic Field dg field337 Ldg;
L494:   invokevirtual Method qc method31 (LgB;Ljava/lang/Object;)V
L497:   new qc
L500:   dup
L501:   new VD
L504:   dup
L505:   invokespecial Method VD <init> ()V
L508:   invokespecial Method qc <init> (Ld;)V
L511:   astore 8
L513:   aconst_null
L514:   aload 8
L516:   dup_x1
L517:   aload 7
L519:   getstatic Field VD field147 Ljava/lang/Object;
L522:   invokevirtual Method qc method31 (LgB;Ljava/lang/Object;)V
L525:   aconst_null
L526:   aload 6
L528:   invokestatic Method Wd method1087 (LgB;LgB;LgB;)Lqc;
L531:   getstatic Field VD field148 Ljava/lang/Object;
L534:   invokevirtual Method qc method31 (LgB;Ljava/lang/Object;)V
L537:   new lC
L540:   dup
L541:   new VD
L544:   aload_0
L545:   dup_x1
L546:   dup
L547:   pop2
L548:   dup
L549:   invokespecial Method VD <init> ()V
L552:   invokespecial Method lC <init> (LCC;Ld;)V
L555:   dup
L556:   astore 9
L558:   dup
L559:   new SB
L562:   aload 9
L564:   dup_x1
L565:   dup
L566:   pop2
L567:   dup
L568:   new Cd
L571:   dup
L572:   aload_0
L573:   getfield Field CC this Lqc;
L576:   invokespecial Method Cd <init> (LgB;)V
L579:   ldc_w 3e-1f
L582:   ldc_w 1.5e-1f
L585:   dup_x1
L586:   dup_x2
L587:   invokespecial Method SB <init> (LgB;FFFF)V
L590:   getstatic Field VD field149 Ljava/lang/Object;
L593:   invokevirtual Method qc method31 (LgB;Ljava/lang/Object;)V
L596:   new SB
L599:   aload 9
L601:   dup_x2
L602:   dup
L603:   pop2
L604:   dup
L605:   aload 8
L607:   ldc_w 1.5e-1f
L610:   dup
L611:   dup_x1
L612:   dup_x2
L613:   invokespecial Method SB <init> (LgB;FFFF)V
L616:   getstatic Field VD field147 Ljava/lang/Object;
L619:   invokevirtual Method qc method31 (LgB;Ljava/lang/Object;)V
L622:   new SB
L625:   aload 9
L627:   dup
L628:   pop2
L629:   dup
L630:   aload 5
L632:   ldc_w 1.5e-1f
L635:   dup
L636:   dup_x1
L637:   dup_x2
L638:   invokespecial Method SB <init> (LgB;FFFF)V
L641:   getstatic Field VD this Ljava/lang/Object;
L644:   invokevirtual Method qc method31 (LgB;Ljava/lang/Object;)V
L647:   areturn
L648:   
        .attribute StackMap b'\x00\x07\x01\x23\x00\x09\x07\x00\x02\x07\x00\x5D\x07\x00\x5D\x07\x00\x57\x07\x00\x0A\x07\x01\x59\x07\x01\xFE\x01\x07\x01\xA1\x00\x01\x07\x01\xA1\x01\x6D\x00\x00\x00\x01\x07\x00\xBB\x01\x6E\x00\x09\x07\x00\x02\x07\x00\x5D\x07\x00\x5D\x07\x00\x57\x07\x00\x0A\x07\x01\x59\x07\x01\xFE\x01\x07\x01\xA1\x00\x00\x01\x75\x00\x09\x07\x00\x02\x07\x00\x5D\x07\x00\x5D\x07\x00\x57\x07\x00\x0A\x07\x01\x59\x07\x01\xFE\x01\x07\x01\xA1\x00\x01\x01\x01\xAD\x00\x09\x07\x00\x02\x07\x00\x5D\x07\x00\x5D\x07\x00\x57\x07\x00\x0A\x07\x01\x59\x07\x01\xFE\x01\x07\x01\xA1\x00\x00\x01\xC9\x00\x00\x00\x01\x07\x00\xBB\x01\xCA\x00\x09\x07\x00\x02\x07\x00\x5D\x07\x00\x5D\x07\x00\x57\x07\x00\x0A\x07\x01\x59\x07\x01\xFE\x01\x07\x01\xA1\x00\x00'
    .end code
.end method

.method public method47 : (LgB;I)Z
    .code stack 4 locals 3
L0:     iload_2
L1:     ldc_w "j"
L4:     invokestatic Method JB method831 (Ljava/lang/String;)I
L7:     if_icmpne L47
L10:    aload_0
L11:    invokevirtual Method CC method181 ()LgB;
L14:    aload_0
L15:    getfield Field CC field173 Lqc;
L18:    if_acmpeq L33
L21:    aload_0
L22:    dup
L23:    getfield Field CC field173 Lqc;
L26:    invokevirtual Method CC new (LgB;)V
L29:    goto L41
L32:    athrow
L33:    aload_0
L34:    iconst_0
L35:    iconst_1
L36:    dup
L37:    pop2
L38:    invokevirtual Method CC method14 (I)V
L41:    iconst_1
L42:    dup
L43:    dup
L44:    pop2
L45:    ireturn
L46:    athrow
L47:    iconst_0
L48:    iconst_1
L49:    dup
L50:    pop2
L51:    ireturn
L52:    
        .attribute StackMap b'\x00\x05\x00\x20\x00\x00\x00\x01\x07\x00\xBB\x00\x21\x00\x03\x07\x00\x02\x07\x01\xB7\x01\x00\x00\x00\x29\x00\x03\x07\x00\x02\x07\x01\xB7\x01\x00\x00\x00\x2E\x00\x00\x00\x01\x07\x00\xBB\x00\x2F\x00\x03\x07\x00\x02\x07\x01\xB7\x01\x00\x00'
    .end code
.end method

.method public static synthetic this : (LCC;)Ljava/util/HashMap;
    .code stack 1 locals 1
L0:     aload_0
L1:     getfield Field CC new Ljava/util/HashMap;
L4:     areturn
L5:     
    .end code
.end method

.method public static synthetic method170 : (LCC;)LYg;
    .code stack 1 locals 1
L0:     aload_0
L1:     getfield Field CC field182 LYg;
L4:     areturn
L5:     
    .end code
.end method

.method public method142 : (Lqd;)V
    .code stack 9 locals 3
L0:     aload_0
L1:     dup
L2:     invokevirtual Method CC method69 ()V
L5:     getfield Field CC field1136 LFE;
L8:     getstatic Field Ae field342 LAe;
L11:    ldc "Joining..."
L13:    getstatic Field jC field1036 [Ljava/lang/String;
L16:    invokevirtual Method FE method457 (LAe;Ljava/lang/String;[Ljava/lang/String;)LjC;
L19:    astore_2
        .catch java/lang/Exception from L20 to L46 using L48
L20:    aload_1
L21:    aload_0
L22:    getfield Field CC field176 Led;
L25:    iconst_0
L26:    iconst_1
L27:    dup
L28:    pop2
L29:    new Nd
L32:    aconst_null
L33:    dup_x1
L34:    dup
L35:    pop2
L36:    dup
L37:    aload_0
L38:    aload_2
L39:    aload_1
L40:    invokespecial Method Nd <init> (LCC;LjC;Lqd;)V
L43:    invokevirtual Method qd method400 (Led;ZLjava/lang/String;LK;)V
L46:    return
L47:    athrow
L48:    astore_1
L49:    aload_0
L50:    dup
L51:    aload_1
L52:    invokevirtual Method java/lang/Exception printStackTrace ()V
L55:    getfield Field CC field1136 LFE;
L58:    aload_2
L59:    invokevirtual Method FE method458 (LjC;)V
L62:    getstatic Field dc field2207 Ljava/util/HashMap;
L65:    getstatic Field KD field404 LKD;
L68:    invokevirtual Method java/util/HashMap get (Ljava/lang/Object;)Ljava/lang/Object;
L71:    checkcast java/lang/String
L74:    iconst_0
L75:    iconst_1
L76:    dup
L77:    pop2
L78:    invokevirtual Method CC method72 (Ljava/lang/String;Z)V
L81:    return
L82:    
        .attribute StackMap b'\x00\x02\x00\x2F\x00\x00\x00\x01\x07\x00\xBB\x00\x30\x00\x03\x07\x00\x02\x07\x00\xE9\x07\x00\xAC\x00\x01\x07\x00\xD8'
    .end code
.end method

.method public static synthetic method171 : (LCC;)LFE;
    .code stack 1 locals 1
L0:     aload_0
L1:     getfield Field CC field1136 LFE;
L4:     areturn
L5:     
    .end code
.end method

.method public method48 : (LgB;IC)Z
    .code stack 3 locals 4
L0:     iload_2
L1:     ldc_w "j"
L4:     invokestatic Method JB method831 (Ljava/lang/String;)I
L7:     if_icmpne L16
L10:    iconst_1
L11:    dup
L12:    dup
L13:    pop2
L14:    ireturn
L15:    athrow
L16:    aload_0
L17:    invokevirtual Method CC method181 ()LgB;
L20:    aload_0
L21:    getfield Field CC field173 Lqc;
L24:    if_acmpne L115
L27:    iload_2
L28:    lookupswitch
            1 : L104
            15 : L104
            28 : L104
            57 : L104
            200 : L104
            203 : L104
            205 : L104
            208 : L104
            default : L108
L104:   goto L115
L107:   athrow
L108:   aload_0
L109:   getfield Field CC field185 LUb;
L112:   invokevirtual Method Ub method10 ()V
L115:   iconst_0
L116:   iconst_1
L117:   dup
L118:   pop2
L119:   ireturn
L120:   
        .attribute StackMap b'\x00\x06\x00\x0F\x00\x00\x00\x01\x07\x00\xBB\x00\x10\x00\x04\x07\x00\x02\x07\x01\xB7\x01\x01\x00\x00\x00\x68\x00\x04\x07\x00\x02\x07\x01\xB7\x01\x01\x00\x00\x00\x6B\x00\x00\x00\x01\x07\x00\xBB\x00\x6C\x00\x04\x07\x00\x02\x07\x01\xB7\x01\x01\x00\x00\x00\x73\x00\x04\x07\x00\x02\x07\x01\xB7\x01\x01\x00\x00'
    .end code
.end method

.method public method14 : (I)V
    .code stack 4 locals 2
L0:     aload_0
L1:     dup
L2:     iload_1
L3:     invokespecial Method Yd method14 (I)V
L6:     getfield Field CC field177 Lsb;
L9:     ifnull L35
L12:    aload_0
L13:    getfield Field CC field177 Lsb;
L16:    iload_1
L17:    ifeq L28
L20:    iconst_1
L21:    dup
L22:    dup
L23:    pop2
L24:    goto L32
L27:    athrow
L28:    iconst_0
L29:    iconst_1
L30:    dup
L31:    pop2
L32:    invokevirtual Method sb method95 (Z)V
L35:    return
L36:    
        .attribute StackMap b'\x00\x04\x00\x1B\x00\x00\x00\x01\x07\x00\xBB\x00\x1C\x00\x02\x07\x00\x02\x01\x00\x01\x07\x00\x24\x00\x20\x00\x02\x07\x00\x02\x01\x00\x02\x07\x00\x24\x01\x00\x23\x00\x02\x07\x00\x02\x01\x00\x00'
    .end code
.end method

.method public static synthetic method172 : (LCC;)LFE;
    .code stack 1 locals 1
L0:     aload_0
L1:     getfield Field CC field1136 LFE;
L4:     areturn
L5:     
    .end code
.end method

.method public static synthetic method173 : (LCC;)LTe;
    .code stack 1 locals 1
L0:     aload_0
L1:     getfield Field CC field186 LTe;
L4:     areturn
L5:     
    .end code
.end method

.method public static synthetic method174 : (LCC;)LFE;
    .code stack 1 locals 1
L0:     aload_0
L1:     getfield Field CC field1136 LFE;
L4:     areturn
L5:     
    .end code
.end method

.method public static synthetic method175 : (LCC;LfE;)Ljava/lang/String;
    .code stack 2 locals 2
L0:     aload_0
L1:     aload_1
L2:     invokespecial Method CC method166 (LfE;)Ljava/lang/String;
L5:     areturn
L6:     
    .end code
.end method

.method public static synthetic method176 : (LCC;)LFE;
    .code stack 1 locals 1
L0:     aload_0
L1:     getfield Field CC field1136 LFE;
L4:     areturn
L5:     
    .end code
.end method

.method public method125 : (I)V
    .code stack 2 locals 2
L0:     aload_0
L1:     getfield Field CC field175 LuF;
L4:     invokevirtual Method uF method581 ()Lqd;
L7:     ifnonnull L22
L10:    aload_0
L11:    getfield Field CC true LDF;
L14:    ldc_w "Please select a room to join on the left side."
L17:    invokevirtual Method DF method12 (Ljava/lang/String;)V
L20:    return
L21:    athrow
L22:    aload_0
L23:    getfield Field CC true LDF;
L26:    iload_1
L27:    ifne L37
L30:    ldc_w "No players are playing here."
L33:    goto L40
L36:    athrow
L37:    ldc_w ""
L40:    invokevirtual Method DF method12 (Ljava/lang/String;)V
L43:    return
L44:    
        .attribute StackMap b'\x00\x05\x00\x15\x00\x00\x00\x01\x07\x00\xBB\x00\x16\x00\x02\x07\x00\x02\x01\x00\x00\x00\x24\x00\x00\x00\x01\x07\x00\xBB\x00\x25\x00\x02\x07\x00\x02\x01\x00\x01\x07\x00\x5D\x00\x28\x00\x02\x07\x00\x02\x01\x00\x02\x07\x00\x5D\x07\x01\x01'
    .end code
.end method

.method private method61 : ()V
    .code stack 5 locals 1
L0:     aload_0
L1:     getfield Field CC field172 Lnf;
L4:     new java/lang/StringBuilder
L7:     dup
L8:     invokespecial Method java/lang/StringBuilder <init> ()V
L11:    iconst_0
L12:    getstatic Field Kc field1931 LKc;
L15:    getstatic Field Pc field373 LPc;
L18:    invokevirtual Method Kc method858 (LPc;)Ljava/lang/String;
L21:    invokevirtual Method java/lang/StringBuilder insert (ILjava/lang/String;)Ljava/lang/StringBuilder;
L24:    ldc_w "'s room"
L27:    invokevirtual Method java/lang/StringBuilder append (Ljava/lang/String;)Ljava/lang/StringBuilder;
L30:    invokevirtual Method java/lang/StringBuilder toString ()Ljava/lang/String;
L33:    invokevirtual Method nf method12 (Ljava/lang/String;)V
L36:    return
L37:    
    .end code
.end method

.method private method177 : ()Lqc;
    .code stack 8 locals 7
L0:     new qc
L3:     dup
L4:     new fG
L7:     dup
L8:     getstatic Field LE field634 LLE;
L11:    ldc_w 3.5e-1f
L14:    invokespecial Method fG <init> (LLE;F)V
L17:    invokespecial Method qc <init> (Ld;)V
L20:    astore_1
L21:    new java/util/ArrayList
L24:    dup
L25:    aload_0
L26:    getfield Field CC field176 Led;
L29:    getfield Field ed field704 Ljava/util/Set;
L32:    invokespecial Method java/util/ArrayList <init> (Ljava/util/Collection;)V
L35:    astore_2
L36:    getstatic Field xF field5850 Ljava/util/List;
L39:    invokeinterface InterfaceMethod java/util/List iterator ()Ljava/util/Iterator; 1
L44:    astore_3
L45:    aload_3
L46:    invokeinterface InterfaceMethod java/util/Iterator hasNext ()Z 1
L51:    ifeq L103
L54:    aload_3
L55:    invokeinterface InterfaceMethod java/util/Iterator next ()Ljava/lang/Object; 1
L60:    checkcast Uf
L63:    astore 4
L65:    aload_0
L66:    getfield Field CC field176 Led;
L69:    getfield Field ed field704 Ljava/util/Set;
L72:    aload 4
L74:    invokeinterface InterfaceMethod java/util/Set contains (Ljava/lang/Object;)Z 2
L79:    ifne L45
L82:    aload 4
L84:    getfield Field Uf field1350 Z
L87:    ifeq L45
L90:    aload_2
L91:    aload 4
L93:    invokeinterface InterfaceMethod java/util/List add (Ljava/lang/Object;)Z 2
L98:    pop
L99:    goto L45
L102:   athrow
L103:   aload_2
L104:   dup
L105:   new Nb
L108:   dup
L109:   aload_0
L110:   invokespecial Method Nb <init> (LCC;)V
L113:   invokestatic Method java/util/Collections sort (Ljava/util/List;Ljava/util/Comparator;)V
L116:   invokeinterface InterfaceMethod java/util/List iterator ()Ljava/util/Iterator; 1
L121:   dup
L122:   astore_3
L123:   invokeinterface InterfaceMethod java/util/Iterator hasNext ()Z 1
L128:   ifeq L382
L131:   aload_3
L132:   invokeinterface InterfaceMethod java/util/Iterator next ()Ljava/lang/Object; 1
L137:   checkcast Uf
L140:   astore 4
L142:   new qc
L145:   dup
L146:   new VD
L149:   dup
L150:   invokespecial Method VD <init> ()V
L153:   invokespecial Method qc <init> (Ld;)V
L156:   astore_2
L157:   new DF
L160:   aload_2
L161:   dup_x1
L162:   dup_x2
L163:   dup
L164:   pop2
L165:   dup
L166:   aload 4
L168:   getfield Field Uf field1351 Ljava/lang/String;
L171:   getstatic Field We field478 LWe;
L174:   invokespecial Method DF <init> (Ljava/lang/String;LWe;)V
L177:   getstatic Field VD field150 Ljava/lang/Object;
L180:   invokevirtual Method qc method31 (LgB;Ljava/lang/Object;)V
L183:   new DF
L186:   aload_2
L187:   dup
L188:   pop2
L189:   dup
L190:   aload 4
L192:   getfield Field Uf this Ljava/lang/String;
L195:   getstatic Field We field480 LWe;
L198:   invokespecial Method DF <init> (Ljava/lang/String;LWe;)V
L201:   getstatic Field VD field147 Ljava/lang/Object;
L204:   invokevirtual Method qc method31 (LgB;Ljava/lang/Object;)V
L207:   new qc
L210:   dup
L211:   new VD
L214:   dup
L215:   invokespecial Method VD <init> ()V
L218:   invokespecial Method qc <init> (Ld;)V
L221:   astore 5
L223:   new DF
L226:   aload 5
L228:   dup_x1
L229:   dup
L230:   pop2
L231:   dup
L232:   aload_0
L233:   getfield Field CC field176 Led;
L236:   getfield Field ed field704 Ljava/util/Set;
L239:   aload 4
L241:   invokeinterface InterfaceMethod java/util/Set contains (Ljava/lang/Object;)Z 2
L246:   ifeq L277
L249:   new java/lang/StringBuilder
L252:   dup
L253:   invokespecial Method java/lang/StringBuilder <init> ()V
L256:   aload 4
L258:   getfield Field Uf field1349 I
L261:   invokevirtual Method java/lang/StringBuilder append (I)Ljava/lang/StringBuilder;
L264:   ldc_w ""
L267:   invokevirtual Method java/lang/StringBuilder append (Ljava/lang/String;)Ljava/lang/StringBuilder;
L270:   invokevirtual Method java/lang/StringBuilder toString ()Ljava/lang/String;
L273:   goto L280
L276:   athrow
L277:   ldc_w "-- "
L280:   getstatic Field We field492 LWe;
L283:   invokespecial Method DF <init> (Ljava/lang/String;LWe;)V
L286:   getstatic Field VD field147 Ljava/lang/Object;
L289:   invokevirtual Method qc method31 (LgB;Ljava/lang/Object;)V
L292:   new Vg
L295:   aload 5
L297:   dup_x1
L298:   dup_x2
L299:   dup
L300:   pop2
L301:   dup
L302:   ldc_w 2.4e0f
L305:   fconst_0
L306:   invokespecial Method Vg <init> (FF)V
L309:   getstatic Field VD field150 Ljava/lang/Object;
L312:   invokevirtual Method qc method31 (LgB;Ljava/lang/Object;)V
L315:   new Vg
L318:   aload 5
L320:   dup
L321:   pop2
L322:   dup
L323:   ldc_w 2e-1f
L326:   fconst_0
L327:   invokespecial Method Vg <init> (FF)V
L330:   getstatic Field VD this Ljava/lang/Object;
L333:   invokevirtual Method qc method31 (LgB;Ljava/lang/Object;)V
L336:   new qc
L339:   dup
L340:   new VD
L343:   dup
L344:   invokespecial Method VD <init> ()V
L347:   invokespecial Method qc <init> (Ld;)V
L350:   astore 6
L352:   aload_3
L353:   aload_1
L354:   aload_2
L355:   aload 6
L357:   dup_x1
L358:   dup_x2
L359:   aload 5
L361:   getstatic Field VD field149 Ljava/lang/Object;
L364:   invokevirtual Method qc method31 (LgB;Ljava/lang/Object;)V
L367:   getstatic Field VD field147 Ljava/lang/Object;
L370:   invokevirtual Method qc method31 (LgB;Ljava/lang/Object;)V
L373:   getstatic Field dg field337 Ldg;
L376:   invokevirtual Method qc method31 (LgB;Ljava/lang/Object;)V
L379:   goto L123
L382:   new Cd
L385:   dup
L386:   aload_1
L387:   invokespecial Method Cd <init> (LgB;)V
L390:   areturn
L391:   
        .attribute StackMap b'\x00\x08\x00\x2D\x00\x04\x07\x00\x02\x07\x01\x59\x07\x02\xDA\x07\x01\xA1\x00\x00\x00\x66\x00\x00\x00\x01\x07\x00\xBB\x00\x67\x00\x04\x07\x00\x02\x07\x01\x59\x07\x02\xDA\x07\x01\xA1\x00\x00\x00\x7B\x00\x04\x07\x00\x02\x07\x01\x59\x07\x01\xC9\x07\x01\xA1\x00\x01\x07\x01\xA1\x01\x14\x00\x00\x00\x01\x07\x00\xBB\x01\x15\x00\x06\x07\x00\x02\x07\x01\x59\x07\x01\x59\x07\x01\xA1\x07\x04\x2D\x07\x01\x59\x00\x03\x07\x01\x59\x08\x00\xDF\x08\x00\xDF\x01\x18\x00\x06\x07\x00\x02\x07\x01\x59\x07\x01\x59\x07\x01\xA1\x07\x04\x2D\x07\x01\x59\x00\x04\x07\x01\x59\x08\x00\xDF\x08\x00\xDF\x07\x01\x01\x01\x7E\x00\x04\x07\x00\x02\x07\x01\x59\x07\x01\xC9\x07\x01\xA1\x00\x00'
    .end code
.end method

.method public method72 : (Ljava/lang/String;Z)V
    .code stack 8 locals 3
L0:     aload_0
L1:     getfield Field CC field1136 LFE;
L4:     getstatic Field Ae field349 LAe;
L7:     aload_1
L8:     getstatic Field jC field1048 [Ljava/lang/String;
L11:    new ND
L14:    dup
L15:    aload_0
L16:    iload_2
L17:    invokespecial Method ND <init> (LCC;Z)V
L20:    invokevirtual Method FE method446 (LAe;Ljava/lang/String;[Ljava/lang/String;Lh;)LjC;
L23:    pop
L24:    return
L25:    
    .end code
.end method

.method public static synthetic method178 : (LCC;)LFE;
    .code stack 1 locals 1
L0:     aload_0
L1:     getfield Field CC field1136 LFE;
L4:     areturn
L5:     
    .end code
.end method

.method public method74 : ()V
    .code stack 6 locals 1
L0:     aload_0
L1:     dup
L2:     dup_x1
L3:     iconst_1
L4:     dup
L5:     dup
L6:     pop2
L7:     putfield Field CC field183 Z
L10:    invokevirtual Method CC method69 ()V
L13:    getfield Field CC field176 Led;
L16:    ifnull L30
L19:    getstatic Field Kc field1931 LKc;
L22:    aload_0
L23:    getfield Field CC field176 Led;
L26:    aconst_null
L27:    invokevirtual Method Kc method839 (Led;LK;)V
L30:    aload_0
L31:    getfield Field CC field1136 LFE;
L34:    new cb
L37:    aload_0
L38:    dup_x1
L39:    dup
L40:    pop2
L41:    dup
L42:    invokespecial Method cb <init> ()V
L45:    invokevirtual Method FE method455 (LbC;LbC;)V
L48:    return
L49:    
        .attribute StackMap b'\x00\x01\x00\x1E\x00\x01\x07\x00\x02\x00\x00'
    .end code
.end method

.method public static synthetic method179 : (LCC;)LFE;
    .code stack 1 locals 1
L0:     aload_0
L1:     getfield Field CC field1136 LFE;
L4:     areturn
L5:     
    .end code
.end method

.method public static synthetic method180 : (LCC;)Lsb;
    .code stack 1 locals 1
L0:     aload_0
L1:     getfield Field CC field177 Lsb;
L4:     areturn
L5:     
    .end code
.end method

.method public <init> : ()V
    .code stack 2 locals 1
L0:     aload_0
L1:     ldc Class CC
L3:     invokespecial Method Yd <init> (Ljava/lang/Class;)V
L6:     return
L7:     
    .end code
.end method

.method public method69 : ()V
    .code stack 7 locals 1
L0:     aload_0
L1:     getfield Field CC field177 Lsb;
L4:     ifnull L52
L7:     aload_0
L8:     getfield Field CC field177 Lsb;
L11:    getfield Field sb field162 Lqd;
L14:    aload_0
L15:    dup_x1
L16:    getfield Field CC field176 Led;
L19:    invokevirtual Method qd method410 (Led;)V
L22:    getfield Field CC field177 Lsb;
L25:    new ab
L28:    dup
L29:    new Qb
L32:    dup
L33:    invokespecial Method Qb <init> ()V
L36:    iconst_0
L37:    iconst_1
L38:    dup
L39:    pop2
L40:    anewarray ed
L43:    iconst_1
L44:    dup
L45:    pop2
L46:    invokespecial Method ab <init> (Leb;[Led;)V
L49:    invokevirtual Method sb method142 (Lqd;)V
L52:    aload_0
L53:    getfield Field CC field182 LYg;
L56:    ifnull L70
L59:    aload_0
L60:    getfield Field CC field182 LYg;
L63:    iconst_0
L64:    iconst_1
L65:    dup
L66:    pop2
L67:    invokevirtual Method Yg method238 (Z)V
L70:    return
L71:    
        .attribute StackMap b'\x00\x02\x00\x34\x00\x01\x07\x00\x02\x00\x00\x00\x46\x00\x01\x07\x00\x02\x00\x00'
    .end code
.end method

.method public static synthetic method19 : (I)I
    .code stack 2 locals 1
L0:     iload_0
L1:     dup
L2:     putstatic Field CC field181 I
L5:     ireturn
L6:     
    .end code
.end method
.innerclasses
    Ae ig [0] public static final enum
    BD [0] [0]
    Db CC [0] static synthetic
    Eb [0] [0]
    FB [0] [0]
    FG IF [0] public static final enum
    Fc [0] [0]
    Hc Xd [0] public static final enum
    Hd [0] [0]
    ID [0] [0]
    Id sb [0] public static final enum
    Jd [0] [0]
    KD K [0] public static final enum
    LE fG [0] public static final enum
    Lb [0] [0]
    Mb [0] [0]
    Mc [0] [0]
    NC [0] [0]
    ND [0] [0]
    Nb [0] [0]
    Nd [0] [0]
    Pc JB [0] public static final enum
    UB [0] [0]
    Vb [0] [0]
    dg fG [0] public static final enum
    ec [0] [0]
    jD [0] [0]
    java/util/Map$Entry java/util/Map Entry public static interface abstract
    lC [0] [0]
    mb [0] [0]
    pF Ie [0] public static final enum
    uc [0] [0]
    vD DF [0] public static final enum
    xc mB [0] public static final enum
    c GD [0] public static interface abstract
    DG Ie [0] public
.end innerclasses
.end class
