.version 49 0
.class public final super CD
.super Ub
.field private static field62 I
.field private static field63 Ljava/util/LinkedList;

.method public method5 : (Led;Ljava/lang/String;)V
    .code stack 5 locals 3
L0:     getstatic Field CD field59 Ljava/util/Set;
L3:     aload_1
L4:     invokeinterface InterfaceMethod java/util/Set contains (Ljava/lang/Object;)Z 2
L9:     ifeq L14
L12:    return
L13:    athrow
L14:    getstatic Field CD field63 Ljava/util/LinkedList;
L17:    new Dc
L20:    dup
L21:    aload_1
L22:    aload_2
L23:    invokespecial Method Dc <init> (Ljava/lang/Object;Ljava/lang/Object;)V
L26:    invokevirtual Method java/util/LinkedList add (Ljava/lang/Object;)Z
L29:    pop
L30:    getstatic Field CD field63 Ljava/util/LinkedList;
L33:    invokevirtual Method java/util/LinkedList size ()I
L36:    sipush 300
L39:    iconst_1
L40:    dup
L41:    pop2
L42:    if_icmple L56
L45:    getstatic Field CD field63 Ljava/util/LinkedList;
L48:    invokevirtual Method java/util/LinkedList removeFirst ()Ljava/lang/Object;
L51:    pop
L52:    goto L30
L55:    athrow
L56:    aload_0
L57:    aload_1
L58:    aload_2
L59:    invokespecial Method Ub method5 (Led;Ljava/lang/String;)V
L62:    return
L63:    
        .attribute StackMap b'\x00\x05\x00\x0D\x00\x00\x00\x01\x07\x00\x18\x00\x0E\x00\x03\x07\x00\x02\x07\x00\x1A\x07\x00\x1C\x00\x00\x00\x1E\x00\x03\x07\x00\x02\x07\x00\x1A\x07\x00\x1C\x00\x00\x00\x37\x00\x00\x00\x01\x07\x00\x18\x00\x38\x00\x03\x07\x00\x02\x07\x00\x1A\x07\x00\x1C\x00\x00'
    .end code
.end method

.method public static <clinit> : ()V
    .code stack 3 locals 0
L0:     new java/util/LinkedList
L3:     dup
L4:     invokespecial Method java/util/LinkedList <init> ()V
L7:     putstatic Field CD field63 Ljava/util/LinkedList;
L10:    getstatic Field Kc field1931 LKc;
L13:    new Ec
L16:    dup
L17:    invokespecial Method Ec <init> ()V
L20:    getstatic Field mc field387 Lmc;
L23:    invokevirtual Method Kc method844 (LG;Lmc;)V
L26:    return
L27:    
    .end code
.end method

.method public method7 : (Ljava/lang/String;)V
    .code stack 5 locals 2
L0:     getstatic Field CD field63 Ljava/util/LinkedList;
L3:     new Dc
L6:     dup
L7:     aconst_null
L8:     aload_1
L9:     invokespecial Method Dc <init> (Ljava/lang/Object;Ljava/lang/Object;)V
L12:    invokevirtual Method java/util/LinkedList add (Ljava/lang/Object;)Z
L15:    pop
L16:    getstatic Field CD field63 Ljava/util/LinkedList;
L19:    invokevirtual Method java/util/LinkedList size ()I
L22:    sipush 300
L25:    iconst_1
L26:    dup
L27:    pop2
L28:    if_icmple L42
L31:    getstatic Field CD field63 Ljava/util/LinkedList;
L34:    invokevirtual Method java/util/LinkedList removeFirst ()Ljava/lang/Object;
L37:    pop
L38:    goto L16
L41:    athrow
L42:    aload_0
L43:    aload_1
L44:    invokespecial Method Ub method7 (Ljava/lang/String;)V
L47:    return
L48:    
        .attribute StackMap b'\x00\x03\x00\x10\x00\x02\x07\x00\x02\x07\x00\x1C\x00\x00\x00\x29\x00\x00\x00\x01\x07\x00\x18\x00\x2A\x00\x02\x07\x00\x02\x07\x00\x1C\x00\x00'
    .end code
.end method

.method public static synthetic method18 : ()Ljava/util/LinkedList;
    .code stack 1 locals 0
L0:     getstatic Field CD field63 Ljava/util/LinkedList;
L3:     areturn
L4:     
    .end code
.end method

.method public method1 : ()Lqd;
    .code stack 1 locals 1
L0:     aconst_null
L1:     areturn
L2:     
    .end code
.end method

.method public method6 : (Led;)LsE;
    .code stack 1 locals 2
L0:     aconst_null
L1:     areturn
L2:     
    .end code
.end method

.method public method14 : (I)V
    .code stack 3 locals 2
L0:     aload_0
L1:     dup
L2:     iload_1
L3:     invokespecial Method Ub method14 (I)V
L6:     getfield Field CD this I
L9:     putstatic Field CD field62 I
L12:    return
L13:    
    .end code
.end method

.method public method3 : (Led;Ljava/lang/String;)V
    .code stack 5 locals 3
L0:     getstatic Field Kc field1931 LKc;
L3:     new Ge
L6:     dup
L7:     aload_1
L8:     aload_2
L9:     invokespecial Method Ge <init> (Led;Ljava/lang/String;)V
L12:    invokevirtual Method Kc method846 (LD;)V
L15:    return
L16:    
    .end code
.end method

.method public method2 : ()V
    .code stack 2 locals 1
L0:     aload_0
L1:     invokespecial Method Ub method2 ()V
L4:     getstatic Field Kc field1931 LKc;
L7:     aload_0
L8:     invokevirtual Method Kc method849 (LG;)V
L11:    return
L12:    
    .end code
.end method

.method public method8 : (LD;)V
    .code stack 4 locals 3
L0:     aload_1
L1:     instanceof pc
L4:     ifeq L73
L7:     aload_1
L8:     checkcast pc
L11:    astore_2
L12:    aload_0
L13:    getfield Field CD field56 Ljava/util/Set;
L16:    aload_2
L17:    getfield Field pc field943 Led;
L20:    invokeinterface InterfaceMethod java/util/Set add (Ljava/lang/Object;)Z 2
L25:    ifeq L73
L28:    getstatic Field Kc field1931 LKc;
L31:    aload_2
L32:    getfield Field pc field943 Led;
L35:    invokevirtual Method Kc method860 (Led;)Z
L38:    ifne L73
L41:    new java/lang/StringBuilder
L44:    aload_0
L45:    dup_x1
L46:    dup
L47:    pop2
L48:    dup
L49:    invokespecial Method java/lang/StringBuilder <init> ()V
L52:    aload_2
L53:    getfield Field pc field943 Led;
L56:    getfield Field ed field701 Ljava/lang/String;
L59:    invokevirtual Method java/lang/StringBuilder append (Ljava/lang/String;)Ljava/lang/StringBuilder;
L62:    ldc " joined"
L64:    invokevirtual Method java/lang/StringBuilder append (Ljava/lang/String;)Ljava/lang/StringBuilder;
L67:    invokevirtual Method java/lang/StringBuilder toString ()Ljava/lang/String;
L70:    invokevirtual Method CD method7 (Ljava/lang/String;)V
L73:    aload_0
L74:    aload_1
L75:    invokespecial Method Ub method8 (LD;)V
L78:    return
L79:    
        .attribute StackMap b'\x00\x01\x00\x49\x00\x02\x07\x00\x02\x07\x00\x8E\x00\x00'
    .end code
.end method

.method public <init> : ()V
    .code stack 5 locals 3
L0:     aload_0
L1:     ldc "\u270ELobby"
L3:     invokespecial Method Ub <init> (Ljava/lang/String;)V
L6:     getstatic Field Kc field1931 LKc;
L9:     aload_0
L10:    dup_x1
L11:    getstatic Field mc field387 Lmc;
L14:    invokevirtual Method Kc method844 (LG;Lmc;)V
L17:    getfield Field CD field56 Ljava/util/Set;
L20:    getstatic Field Kc field1931 LKc;
L23:    invokevirtual Method Kc method859 ()Ljava/util/Collection;
L26:    invokeinterface InterfaceMethod java/util/Set addAll (Ljava/util/Collection;)Z 2
L31:    getstatic Field CD field63 Ljava/util/LinkedList;
L34:    invokevirtual Method java/util/LinkedList iterator ()Ljava/util/Iterator;
L37:    astore_1
L38:    pop
L39:    aload_1
L40:    invokeinterface InterfaceMethod java/util/Iterator hasNext ()Z 1
L45:    ifeq L86
L48:    aload_1
L49:    invokeinterface InterfaceMethod java/util/Iterator next ()Ljava/lang/Object; 1
L54:    checkcast Dc
L57:    astore_2
L58:    aload_0
L59:    getfield Field CD try LtD;
L62:    aload_2
L63:    getfield Field Dc field1793 Ljava/lang/Object;
L66:    checkcast ed
L69:    aconst_null
L70:    dup
L71:    aload_2
L72:    getfield Field Dc field1794 Ljava/lang/Object;
L75:    checkcast java/lang/String
L78:    invokevirtual Method tD method96 (Led;Lqd;LsE;Ljava/lang/String;)V
L81:    aload_1
L82:    goto L40
L85:    athrow
L86:    aload_0
L87:    getstatic Field CD field62 I
L90:    invokevirtual Method CD method14 (I)V
L93:    getstatic Field CD field61 Ljava/lang/String;
L96:    ifnull L106
L99:    aload_0
L100:   getstatic Field CD field61 Ljava/lang/String;
L103:   invokevirtual Method CD method12 (Ljava/lang/String;)V
L106:   return
L107:   
        .attribute StackMap b'\x00\x04\x00\x28\x00\x02\x07\x00\x02\x07\x00\xA2\x00\x01\x07\x00\xA2\x00\x55\x00\x00\x00\x01\x07\x00\x18\x00\x56\x00\x02\x07\x00\x02\x07\x00\xA2\x00\x00\x00\x6A\x00\x02\x07\x00\x02\x07\x00\xA2\x00\x00'
    .end code
.end method

.method public method4 : ()Ljava/util/LinkedList;
    .code stack 1 locals 1
L0:     getstatic Field CD field63 Ljava/util/LinkedList;
L3:     areturn
L4:     
    .end code
.end method

.method public static synthetic method19 : (I)I
    .code stack 2 locals 1
L0:     iload_0
L1:     dup
L2:     putstatic Field CD field62 I
L5:     ireturn
L6:     
    .end code
.end method
.innerclasses
    Ec [0] [0] static
.end innerclasses
.end class
