.version 49 0
.class public final super ce
.super java/lang/Object
.implements D
.field public field927 I
.field public this F
.field public field928 F
.field public field929 I
.field public field930 Ljava/lang/String;
.field public field931 Ljava/lang/String;

.method public method384 : (LAC;)V
    .code stack 12 locals 2
L0:     aload_0
L1:     aload_1
L2:     dup_x1
L3:     aload_1
L4:     aload_0
L5:     dup_x1
L6:     aload_0
L7:     aload_1
L8:     dup_x1
L9:     aload_1
L10:    aload_0
L11:    dup_x1
L12:    getfield Field ce field927 I
L15:    invokevirtual Method AC method674 (I)V
L18:    getfield Field ce field930 Ljava/lang/String;
L21:    invokevirtual Method AC method683 (Ljava/lang/String;)V
L24:    getfield Field ce field931 Ljava/lang/String;
L27:    invokevirtual Method AC method683 (Ljava/lang/String;)V
L30:    getfield Field ce field928 F
L33:    invokevirtual Method AC method685 (F)V
L36:    getfield Field ce this F
L39:    invokevirtual Method AC method685 (F)V
L42:    getfield Field ce field929 I
L45:    invokevirtual Method AC method674 (I)V
L48:    return
L49:    
    .end code
    .exceptions java/io/IOException
.end method

.method public <init> : (LMd;)V
    .code stack 13 locals 2
L0:     aload_1
L1:     aload_0
L2:     dup_x1
L3:     aload_0
L4:     aload_1
L5:     dup_x1
L6:     aload_1
L7:     aload_0
L8:     dup_x1
L9:     aload_0
L10:    aload_1
L11:    dup_x1
L12:    aload_0
L13:    invokespecial Method java/lang/Object <init> ()V
L16:    invokevirtual Method Md method889 ()I
L19:    putfield Field ce field927 I
L22:    invokevirtual Method Md new ()Ljava/lang/String;
L25:    putfield Field ce field930 Ljava/lang/String;
L28:    invokevirtual Method Md new ()Ljava/lang/String;
L31:    putfield Field ce field931 Ljava/lang/String;
L34:    invokevirtual Method Md method885 ()F
L37:    putfield Field ce field928 F
L40:    invokevirtual Method Md method885 ()F
L43:    putfield Field ce this F
L46:    invokevirtual Method Md method889 ()I
L49:    putfield Field ce field929 I
L52:    return
L53:    
    .end code
    .exceptions java/io/IOException
.end method

.method public <init> : (ILjava/lang/String;Ljava/lang/String;FFI)V
    .code stack 8 locals 7
L0:     aload_3
L1:     aload_2
L2:     aload_0
L3:     dup_x1
L4:     iload_1
L5:     aload_0
L6:     invokespecial Method java/lang/Object <init> ()V
L9:     putfield Field ce field927 I
L12:    putfield Field ce field930 Ljava/lang/String;
L15:    ifnonnull L24
L18:    ldc ""
L20:    astore_3
L21:    invokestatic Method java/lang/Thread dumpStack ()V
L24:    aload_0
L25:    iload 6
L27:    fload 5
L29:    aload_0
L30:    dup_x1
L31:    fload 4
L33:    aload_0
L34:    aload_3
L35:    putfield Field ce field931 Ljava/lang/String;
L38:    putfield Field ce field928 F
L41:    putfield Field ce this F
L44:    putfield Field ce field929 I
L47:    return
L48:    
        .attribute StackMap b'\x00\x01\x00\x18\x00\x07\x07\x00\x02\x01\x07\x00\x4C\x07\x00\x4C\x02\x02\x01\x00\x00'
    .end code
.end method
.innerclasses
    ce JE [0] public static
.end innerclasses
.end class
