.version 49 0
.class public super cF
.super eb
.field private field1766 F

.method public method758 : (Lqd;)F
    .code stack 5 locals 2
L0:     aload_1
L1:     aload_0
L2:     dup_x1
L3:     aload_1
L4:     fconst_0
L5:     invokespecial Method cF method769 (Lqd;F)F
L8:     invokespecial Method cF method769 (Lqd;F)F
L11:    freturn
L12:    
    .end code
.end method

.method public method759 : (LRg;[I)I
    .code stack 3 locals 3
L0:     iconst_0
L1:     iconst_1
L2:     dup
L3:     pop2
L4:     ireturn
L5:     
    .end code
.end method

.method private method769 : (Lqd;F)F
    .code stack 5 locals 3
L0:     invokestatic Method OC method1015 ()D
L3:     aload_1
L4:     getfield Field qd while D
L7:     dsub
L8:     d2f
L9:     fload_2
L10:    fadd
L11:    fstore_1
L12:    ldc 2e-1f
L14:    fconst_2
L15:    ldc 1.25e2f
L17:    fload_1
L18:    ldc 4e0f
L20:    fmul
L21:    ldc 5e1f
L23:    fadd
L24:    fdiv
L25:    fadd
L26:    fload_1
L27:    ldc 2.4e2f
L29:    fdiv
L30:    fsub
L31:    invokestatic Method java/lang/Math max (FF)F
L34:    freturn
L35:    
    .end code
.end method

.method public <init> : ()V
    .code stack 1 locals 1
L0:     aload_0
L1:     invokespecial Method eb <init> ()V
L4:     return
L5:     
    .end code
.end method

.method public method754 : (LRg;)V
    .code stack 5 locals 2
L0:     aload_1
L1:     aload_0
L2:     dup_x1
L3:     dup_x2
L4:     aload_1
L5:     invokespecial Method eb method754 (LRg;)V
L8:     getfield Field Rg field239 Lqd;
L11:    fconst_0
L12:    invokespecial Method cF method769 (Lqd;F)F
L15:    ldc 2.5e-1f
L17:    fsub
L18:    putfield Field cF field1766 F
L21:    return
L22:    
    .end code
.end method

.method public method751 : ()[LEF;
    .code stack 5 locals 1
L0:     iconst_3
L1:     iconst_1
L2:     dup
L3:     pop2
L4:     anewarray EF
L7:     iconst_1
L8:     dup
L9:     pop2
L10:    dup
L11:    iconst_0
L12:    iconst_1
L13:    dup
L14:    pop2
L15:    getstatic Field EF try LEF;
L18:    aastore
L19:    dup
L20:    iconst_1
L21:    dup
L22:    dup
L23:    pop2
L24:    getstatic Field EF field431 LEF;
L27:    aastore
L28:    dup
L29:    iconst_2
L30:    iconst_1
L31:    dup
L32:    pop2
L33:    getstatic Field EF this LEF;
L36:    aastore
L37:    areturn
L38:    
    .end code
.end method

.method public method763 : (Lqd;F)V
    .code stack 12 locals 5
L0:     aload_1
L1:     fconst_0
L2:     aload_0
L3:     dup_x2
L4:     dup_x2
L5:     dup
L6:     getfield Field cF field1766 F
L9:     fload_2
L10:    fadd
L11:    putfield Field cF field1766 F
L14:    invokespecial Method cF method769 (Lqd;F)F
L17:    fstore_2
L18:    getfield Field cF field1766 F
L21:    fload_2
L22:    fcmpl
L23:    ifle L136
L26:    aload_1
L27:    getfield Field qd new Ljava/util/LinkedHashMap;
L30:    invokevirtual Method java/util/LinkedHashMap values ()Ljava/util/Collection;
L33:    invokeinterface InterfaceMethod java/util/Collection iterator ()Ljava/util/Iterator; 1
L38:    astore_3
L39:    aload_3
L40:    invokeinterface InterfaceMethod java/util/Iterator hasNext ()Z 1
L45:    ifeq L121
L48:    aload_3
L49:    invokeinterface InterfaceMethod java/util/Iterator next ()Ljava/lang/Object; 1
L54:    checkcast Rg
L57:    dup
L58:    astore 4
L60:    getfield Field Rg field227 LqE;
L63:    getstatic Field qE this LqE;
L66:    if_acmpne L39
L69:    new uE
L72:    aload_1
L73:    dup_x1
L74:    dup
L75:    pop2
L76:    dup
L77:    aload 4
L79:    dup
L80:    getfield Field Rg false Led;
L83:    swap
L84:    getfield Field Rg false Led;
L87:    iconst_1
L88:    dup
L89:    pop2
L90:    iconst_1
L91:    dup
L92:    dup
L93:    pop2
L94:    newarray int
L96:    iconst_1
L97:    dup_x1
L98:    dup
L99:    pop2
L100:   dup
L101:   iconst_0
L102:   iconst_1
L103:   dup
L104:   pop2
L105:   bipush 27
L107:   iconst_1
L108:   dup
L109:   pop2
L110:   iastore
L111:   invokespecial Method uE <init> (Led;Led;I[I)V
L114:   invokevirtual Method qd method394 (LD;)V
L117:   goto L39
L120:   athrow
L121:   aload_0
L122:   dup
L123:   dup
L124:   getfield Field cF field1766 F
L127:   fload_2
L128:   fsub
L129:   putfield Field cF field1766 F
L132:   goto L18
L135:   athrow
L136:   return
L137:   
        .attribute StackMap b'\x00\x06\x00\x12\x00\x03\x07\x00\x02\x07\x00\x18\x02\x00\x01\x07\x00\x02\x00\x27\x00\x04\x07\x00\x02\x07\x00\x18\x02\x07\x00\x58\x00\x00\x00\x78\x00\x00\x00\x01\x07\x00\x77\x00\x79\x00\x04\x07\x00\x02\x07\x00\x18\x02\x07\x00\x58\x00\x00\x00\x87\x00\x00\x00\x01\x07\x00\x77\x00\x88\x00\x03\x07\x00\x02\x07\x00\x18\x02\x00\x00'
    .end code
.end method

.method public method764 : (Lqd;)F
    .code stack 1 locals 2
L0:     fconst_0
L1:     freturn
L2:     
    .end code
.end method

.method public method768 : ()Z
    .code stack 3 locals 1
L0:     iconst_0
L1:     iconst_1
L2:     dup
L3:     pop2
L4:     ireturn
L5:     
    .end code
.end method
.innerclasses
    EF eb [0] public static final enum
.end innerclasses
.end class
