.version 49 0
.class public final super CF
.super gg
.field private short LFE;
.field private goto [[F
.field private break F
.field private long LbC;
.field private void Z
.field private static final try F = 1e0f
.field private const Lgg;
.field private new LbC;
.field private static final null F = 1.5e0f
.field private static final this F = 4e0f
.field private static final char F = 2.5e-1f

.method private const : (F)V
    .code stack 9 locals 4
L0:     fload_1
L1:     dup
L2:     fmul
L3:     fstore_1
L4:     fconst_1
L5:     fload_1
L6:     ldc 6.7e-1f
L8:     fmul
L9:     fsub
L10:    fstore_2
L11:    iconst_1
L12:    dup
L13:    dup
L14:    pop2
L15:    invokestatic Method org/lwjgl/opengl/GL11 "strictfp" (I)V
L18:    iconst_0
L19:    iconst_1
L20:    dup
L21:    pop2
L22:    dup
L23:    istore_3
L24:    aload_0
L25:    getfield Field CF goto [[F
L28:    arraylength
L29:    if_icmpge L259
L32:    fconst_1
L33:    dup
L34:    dup_x1
L35:    dup_x2
L36:    invokestatic Method org/lwjgl/opengl/GL11 else (FFFF)V
L39:    fconst_1
L40:    dup
L41:    aload_0
L42:    dup
L43:    dup_x2
L44:    getfield Field CF goto [[F
L47:    iload_3
L48:    aaload
L49:    iconst_0
L50:    iconst_1
L51:    dup
L52:    pop2
L53:    faload
L54:    fload_2
L55:    fmul
L56:    fload_1
L57:    ldc 5.8e0f
L59:    fmul
L60:    fsub
L61:    aload_0
L62:    getfield Field CF goto [[F
L65:    iload_3
L66:    aaload
L67:    iconst_1
L68:    dup
L69:    dup
L70:    pop2
L71:    faload
L72:    fload_2
L73:    fmul
L74:    fload_1
L75:    ldc 6e-1f
L77:    fmul
L78:    fsub
L79:    invokestatic Method org/lwjgl/opengl/GL11 break (FF)V
L82:    getfield Field CF goto [[F
L85:    iload_3
L86:    aaload
L87:    iconst_2
L88:    iconst_1
L89:    dup
L90:    pop2
L91:    faload
L92:    fload_2
L93:    fmul
L94:    fload_1
L95:    ldc 5.8e0f
L97:    fmul
L98:    fsub
L99:    aload_0
L100:   getfield Field CF goto [[F
L103:   iload_3
L104:   aaload
L105:   iconst_3
L106:   iconst_1
L107:   dup
L108:   pop2
L109:   faload
L110:   fload_2
L111:   fmul
L112:   fload_1
L113:   ldc 6e-1f
L115:   fmul
L116:   fsub
L117:   invokestatic Method org/lwjgl/opengl/GL11 break (FF)V
L120:   aload_0
L121:   getfield Field CF goto [[F
L124:   iload_3
L125:   aaload
L126:   iconst_1
L127:   dup
L128:   dup
L129:   pop2
L130:   faload
L131:   ldc 1e-1f
L133:   fmul
L134:   fconst_1
L135:   dup_x1
L136:   dup_x2
L137:   fload_1
L138:   fsub
L139:   fmul
L140:   invokestatic Method org/lwjgl/opengl/GL11 else (FFFF)V
L143:   getfield Field CF goto [[F
L146:   iload_3
L147:   aaload
L148:   iconst_0
L149:   iconst_1
L150:   dup
L151:   pop2
L152:   faload
L153:   fload_2
L154:   fmul
L155:   fload_1
L156:   ldc 5.8e0f
L158:   fmul
L159:   fsub
L160:   aload_0
L161:   dup_x2
L162:   getfield Field CF goto [[F
L165:   iload_3
L166:   aaload
L167:   iconst_1
L168:   dup
L169:   dup
L170:   pop2
L171:   faload
L172:   fneg
L173:   fload_2
L174:   fmul
L175:   ldc 2.8e0f
L177:   fadd
L178:   fload_1
L179:   ldc 6e-1f
L181:   fmul
L182:   fadd
L183:   invokestatic Method org/lwjgl/opengl/GL11 break (FF)V
L186:   aload_0
L187:   getfield Field CF goto [[F
L190:   iload_3
L191:   aaload
L192:   iconst_3
L193:   iconst_1
L194:   dup
L195:   pop2
L196:   faload
L197:   ldc 1e-1f
L199:   fmul
L200:   fconst_1
L201:   dup_x1
L202:   dup_x2
L203:   fload_1
L204:   fsub
L205:   fmul
L206:   invokestatic Method org/lwjgl/opengl/GL11 else (FFFF)V
L209:   getfield Field CF goto [[F
L212:   iload_3
L213:   aaload
L214:   iconst_2
L215:   iconst_1
L216:   dup
L217:   pop2
L218:   faload
L219:   fload_2
L220:   fmul
L221:   fload_1
L222:   ldc 5.8e0f
L224:   fmul
L225:   fsub
L226:   aload_0
L227:   getfield Field CF goto [[F
L230:   iload_3
L231:   aaload
L232:   iconst_3
L233:   iconst_1
L234:   dup
L235:   pop2
L236:   iinc 3 1
L239:   faload
L240:   fneg
L241:   fload_2
L242:   fmul
L243:   ldc 2.8e0f
L245:   fadd
L246:   fload_1
L247:   ldc 6e-1f
L249:   fmul
L250:   fadd
L251:   invokestatic Method org/lwjgl/opengl/GL11 break (FF)V
L254:   iload_3
L255:   goto L24
L258:   athrow
L259:   invokestatic Method org/lwjgl/opengl/GL11 float ()V
L262:   return
L263:   
        .attribute StackMap b'\x00\x03\x00\x18\x00\x04\x07\x00\x02\x02\x02\x01\x00\x01\x01\x01\x02\x00\x00\x00\x01\x07\x00\x30\x01\x03\x00\x04\x07\x00\x02\x02\x02\x01\x00\x00'
    .end code
.end method

.method private else : ()V
    .code stack 4 locals 3
L0:     aload_0
L1:     getfield Field CF void Z
L4:     ifeq L9
L7:     return
L8:     athrow
L9:     aload_0
L10:    iconst_1
L11:    dup
L12:    dup
L13:    pop2
L14:    putfield Field CF void Z
L17:    ldc ""
L19:    astore_1
L20:    iconst_0
L21:    iconst_1
L22:    dup
L23:    pop2
L24:    dup
L25:    istore_2
L26:    sipush 255
L29:    iconst_1
L30:    dup
L31:    pop2
L32:    if_icmpgt L68
L35:    new java/lang/StringBuilder
L38:    dup
L39:    invokespecial Method java/lang/StringBuilder <init> ()V
L42:    iconst_0
L43:    aload_1
L44:    invokevirtual Method java/lang/StringBuilder insert (ILjava/lang/String;)Ljava/lang/StringBuilder;
L47:    iload_2
L48:    invokevirtual Method java/lang/StringBuilder append (C)Ljava/lang/StringBuilder;
L51:    invokevirtual Method java/lang/StringBuilder toString ()Ljava/lang/String;
L54:    astore_1
L55:    iload_2
L56:    iconst_1
L57:    dup
L58:    dup
L59:    pop2
L60:    iadd
L61:    i2c
L62:    dup
L63:    istore_2
L64:    goto L26
L67:    athrow
L68:    invokestatic Method org/lwjgl/opengl/GL11 char ()V
L71:    new QD
L74:    dup
L75:    aload_1
L76:    invokespecial Method QD <init> (Ljava/lang/String;)V
L79:    iconst_1
L80:    dup
L81:    dup
L82:    pop2
L83:    invokevirtual Method QD break (Z)V
L86:    new QD
L89:    dup
L90:    aload_1
L91:    invokespecial Method QD <init> (Ljava/lang/String;)V
L94:    iconst_0
L95:    iconst_1
L96:    dup
L97:    pop2
L98:    invokevirtual Method QD break (Z)V
L101:   invokestatic Method org/lwjgl/opengl/GL11 do ()V
L104:   return
L105:   
        .attribute StackMap b'\x00\x05\x00\x08\x00\x00\x00\x01\x07\x00\x30\x00\x09\x00\x01\x07\x00\x02\x00\x00\x00\x1A\x00\x03\x07\x00\x02\x07\x00\x3A\x01\x00\x01\x01\x00\x43\x00\x00\x00\x01\x07\x00\x30\x00\x44\x00\x03\x07\x00\x02\x07\x00\x3A\x01\x00\x00'
    .end code
.end method

.method public int : ()V
    .code stack 7 locals 1
L0:     aload_0
L1:     dup
L2:     dup
L3:     getfield Field CF break F
L6:     getstatic Field ib do F
L9:     fadd
L10:    putfield Field CF break F
L13:    getfield Field CF break F
L16:    ldc 6.75e0f
L18:    fcmpl
L19:    iflt L79
L22:    invokestatic Method cD break ()LcD;
L25:    invokevirtual Method cD const ()V
L28:    aload_0
L29:    dup
L30:    dup_x1
L31:    getfield Field CF short LFE;
L34:    aload_0
L35:    dup_x2
L36:    getfield Field CF new LbC;
L39:    aload_0
L40:    getfield Field CF long LbC;
L43:    fconst_0
L44:    invokevirtual Method FE break (LbC;LbC;F)V
L47:    getfield Field CF short LFE;
L50:    new UF
L53:    dup
L54:    ldc 2.5e-1f
L56:    invokespecial Method UF <init> (F)V
L59:    fconst_0
L60:    invokevirtual Method FE else (LbC;F)V
L63:    getfield Field CF short LFE;
L66:    aload_0
L67:    getfield Field CF const Lgg;
L70:    invokevirtual Method FE break (Lgg;)V
L73:    getfield Field CF short LFE;
L76:    invokestatic Method OC break (LFE;)V
L79:    return
L80:    
        .attribute StackMap b'\x00\x01\x00\x4F\x00\x01\x07\x00\x02\x00\x00'
    .end code
.end method

.method public <init> : (LFE;LbC;LbC;Lgg;)V
    .code stack 16 locals 5
L0:     ldc "Cultris II"
L2:     ldc "Cultris II"
L4:     aload_0
L5:     dup_x1
L6:     aload 4
L8:     aload_3
L9:     aload_0
L10:    dup_x1
L11:    aload_2
L12:    aload_1
L13:    aload_0
L14:    dup_x1
L15:    iconst_0
L16:    fconst_0
L17:    aload_0
L18:    dup_x1
L19:    invokespecial Method gg <init> ()V
L22:    putfield Field CF break F
L25:    iconst_1
L26:    dup
L27:    pop2
L28:    putfield Field CF void Z
L31:    putfield Field CF short LFE;
L34:    putfield Field CF new LbC;
L37:    putfield Field CF long LbC;
L40:    putfield Field CF const Lgg;
L43:    invokestatic Method QD break (Ljava/lang/String;)[[F
L46:    putfield Field CF goto [[F
L49:    invokestatic Method QD else (Ljava/lang/String;)F
L52:    ldc 5e-1f
L54:    fmul
L55:    fstore_1
L56:    ldc +Infinityf
L58:    fstore_2
L59:    ldc -Infinityf
L61:    fstore_3
L62:    iconst_0
L63:    iconst_1
L64:    dup
L65:    pop2
L66:    dup
L67:    istore 4
L69:    aload_0
L70:    getfield Field CF goto [[F
L73:    arraylength
L74:    if_icmpge L206
L77:    aload_0
L78:    getfield Field CF goto [[F
L81:    iload 4
L83:    aaload
L84:    iconst_1
L85:    dup
L86:    dup
L87:    pop2
L88:    faload
L89:    fload_2
L90:    fcmpg
L91:    ifge L107
L94:    aload_0
L95:    getfield Field CF goto [[F
L98:    iload 4
L100:   aaload
L101:   iconst_1
L102:   dup
L103:   dup
L104:   pop2
L105:   faload
L106:   fstore_2
L107:   aload_0
L108:   getfield Field CF goto [[F
L111:   iload 4
L113:   aaload
L114:   iconst_3
L115:   iconst_1
L116:   dup
L117:   pop2
L118:   faload
L119:   fload_2
L120:   fcmpg
L121:   ifge L137
L124:   aload_0
L125:   getfield Field CF goto [[F
L128:   iload 4
L130:   aaload
L131:   iconst_3
L132:   iconst_1
L133:   dup
L134:   pop2
L135:   faload
L136:   fstore_2
L137:   aload_0
L138:   getfield Field CF goto [[F
L141:   iload 4
L143:   aaload
L144:   iconst_1
L145:   dup
L146:   dup
L147:   pop2
L148:   faload
L149:   fload_3
L150:   fcmpl
L151:   ifle L167
L154:   aload_0
L155:   getfield Field CF goto [[F
L158:   iload 4
L160:   aaload
L161:   iconst_1
L162:   dup
L163:   dup
L164:   pop2
L165:   faload
L166:   fstore_3
L167:   aload_0
L168:   getfield Field CF goto [[F
L171:   iload 4
L173:   aaload
L174:   iconst_3
L175:   iconst_1
L176:   dup
L177:   pop2
L178:   faload
L179:   fload_3
L180:   fcmpl
L181:   ifle L197
L184:   aload_0
L185:   getfield Field CF goto [[F
L188:   iload 4
L190:   aaload
L191:   iconst_3
L192:   iconst_1
L193:   dup
L194:   pop2
L195:   faload
L196:   fstore_3
L197:   iinc 4 1
L200:   iload 4
L202:   goto L69
L205:   athrow
L206:   fload_3
L207:   fload_2
L208:   fsub
L209:   ldc 5e-1f
L211:   fmul
L212:   fstore 4
L214:   iconst_0
L215:   iconst_1
L216:   dup
L217:   pop2
L218:   dup
L219:   istore_2
L220:   aload_0
L221:   getfield Field CF goto [[F
L224:   arraylength
L225:   if_icmpge L346
L228:   aload_0
L229:   dup
L230:   dup_x1
L231:   getfield Field CF goto [[F
L234:   iload_2
L235:   aaload
L236:   iconst_1
L237:   dup
L238:   pop2
L239:   aload_0
L240:   getfield Field CF goto [[F
L243:   iload_2
L244:   aaload
L245:   iconst_0
L246:   dup_x1
L247:   iconst_1
L248:   dup
L249:   pop2
L250:   faload
L251:   fload_1
L252:   fsub
L253:   ldc 3e0f
L255:   fmul
L256:   fastore
L257:   getfield Field CF goto [[F
L260:   iload_2
L261:   aaload
L262:   iconst_1
L263:   dup
L264:   dup
L265:   pop2
L266:   aload_0
L267:   dup_x2
L268:   getfield Field CF goto [[F
L271:   iload_2
L272:   aaload
L273:   iconst_1
L274:   dup
L275:   dup
L276:   pop2
L277:   faload
L278:   fload 4
L280:   fadd
L281:   ldc 3e0f
L283:   fmul
L284:   fastore
L285:   getfield Field CF goto [[F
L288:   iload_2
L289:   aaload
L290:   iconst_1
L291:   dup
L292:   pop2
L293:   aload_0
L294:   getfield Field CF goto [[F
L297:   iload_2
L298:   aaload
L299:   iconst_2
L300:   dup_x1
L301:   iconst_1
L302:   dup
L303:   pop2
L304:   faload
L305:   fload_1
L306:   fsub
L307:   ldc 3e0f
L309:   fmul
L310:   fastore
L311:   getfield Field CF goto [[F
L314:   iload_2
L315:   aaload
L316:   iconst_1
L317:   dup
L318:   pop2
L319:   aload_0
L320:   getfield Field CF goto [[F
L323:   iload_2
L324:   aaload
L325:   iconst_3
L326:   dup_x1
L327:   iconst_1
L328:   dup
L329:   pop2
L330:   faload
L331:   fload 4
L333:   fadd
L334:   ldc 3e0f
L336:   fmul
L337:   iinc 2 1
L340:   fastore
L341:   iload_2
L342:   goto L220
L345:   athrow
L346:   return
L347:   
        .attribute StackMap b'\x00\x0A\x00\x45\x00\x05\x07\x00\x02\x02\x02\x02\x01\x00\x01\x01\x00\x6B\x00\x05\x07\x00\x02\x02\x02\x02\x01\x00\x00\x00\x89\x00\x05\x07\x00\x02\x02\x02\x02\x01\x00\x00\x00\xA7\x00\x05\x07\x00\x02\x02\x02\x02\x01\x00\x00\x00\xC5\x00\x05\x07\x00\x02\x02\x02\x02\x01\x00\x00\x00\xCD\x00\x00\x00\x01\x07\x00\x30\x00\xCE\x00\x05\x07\x00\x02\x02\x02\x02\x01\x00\x00\x00\xDC\x00\x05\x07\x00\x02\x02\x01\x02\x02\x00\x01\x01\x01\x59\x00\x00\x00\x01\x07\x00\x30\x01\x5A\x00\x05\x07\x00\x02\x02\x01\x02\x02\x00\x00'
    .end code
.end method

.method private else : (F)V
    .code stack 9 locals 7
L0:     new java/util/Random
L3:     dup
L4:     ldc2_w 1337L
L7:     invokespecial Method java/util/Random <init> (J)V
L10:    astore_2
L11:    iconst_1
L12:    dup
L13:    dup
L14:    pop2
L15:    invokestatic Method org/lwjgl/opengl/GL11 "strictfp" (I)V
L18:    iconst_0
L19:    iconst_1
L20:    dup
L21:    pop2
L22:    dup
L23:    istore_3
L24:    aload_0
L25:    getfield Field CF goto [[F
L28:    arraylength
L29:    if_icmpge L334
L32:    ldc 2.5e0f
L34:    fload_1
L35:    fmul
L36:    ldc 1.5e0f
L38:    iload_3
L39:    i2f
L40:    aload_0
L41:    getfield Field CF goto [[F
L44:    arraylength
L45:    iconst_1
L46:    dup
L47:    dup
L48:    pop2
L49:    isub
L50:    i2f
L51:    fdiv
L52:    fmul
L53:    fsub
L54:    dup
L55:    fstore 4
L57:    fconst_1
L58:    fcmpl
L59:    ifle L65
L62:    fconst_1
L63:    fstore 4
L65:    fload 4
L67:    fconst_0
L68:    fcmpg
L69:    ifge L75
L72:    fconst_0
L73:    fstore 4
L75:    fconst_1
L76:    fload 4
L78:    fsub
L79:    dup
L80:    fstore 4
L82:    dup
L83:    fmul
L84:    fload 4
L86:    fmul
L87:    fstore 4
L89:    aload_2
L90:    invokevirtual Method java/util/Random nextFloat ()F
L93:    fconst_2
L94:    fmul
L95:    ldc 3.1415927e0f
L97:    fmul
L98:    fload 4
L100:   ldc 5e-1f
L102:   fadd
L103:   fload 4
L105:   ldc 5e-1f
L107:   fadd
L108:   fmul
L109:   fload 4
L111:   ldc 5e-1f
L113:   fadd
L114:   fmul
L115:   fadd
L116:   dup
L117:   fstore 5
L119:   f2d
L120:   invokestatic Method java/lang/Math sin (D)D
L123:   d2f
L124:   ldc 1.6e1f
L126:   fmul
L127:   fload 4
L129:   fmul
L130:   fstore 6
L132:   fload 5
L134:   f2d
L135:   invokestatic Method java/lang/Math cos (D)D
L138:   d2f
L139:   ldc 1e1f
L141:   fmul
L142:   fload 4
L144:   fmul
L145:   fstore 4
L147:   fconst_1
L148:   dup
L149:   dup_x1
L150:   dup_x2
L151:   invokestatic Method org/lwjgl/opengl/GL11 else (FFFF)V
L154:   fconst_1
L155:   dup
L156:   aload_0
L157:   dup
L158:   dup_x2
L159:   getfield Field CF goto [[F
L162:   iload_3
L163:   aaload
L164:   iconst_0
L165:   iconst_1
L166:   dup
L167:   pop2
L168:   faload
L169:   fload 6
L171:   fadd
L172:   aload_0
L173:   getfield Field CF goto [[F
L176:   iload_3
L177:   aaload
L178:   iconst_1
L179:   dup
L180:   dup
L181:   pop2
L182:   faload
L183:   fload 4
L185:   fadd
L186:   invokestatic Method org/lwjgl/opengl/GL11 break (FF)V
L189:   getfield Field CF goto [[F
L192:   iload_3
L193:   aaload
L194:   iconst_2
L195:   iconst_1
L196:   dup
L197:   pop2
L198:   faload
L199:   fload 6
L201:   fadd
L202:   aload_0
L203:   getfield Field CF goto [[F
L206:   iload_3
L207:   aaload
L208:   iconst_3
L209:   iconst_1
L210:   dup
L211:   pop2
L212:   faload
L213:   fload 4
L215:   fadd
L216:   invokestatic Method org/lwjgl/opengl/GL11 break (FF)V
L219:   fconst_1
L220:   dup
L221:   aload_0
L222:   getfield Field CF goto [[F
L225:   iload_3
L226:   aaload
L227:   iconst_1
L228:   dup
L229:   dup
L230:   pop2
L231:   faload
L232:   ldc 1e-1f
L234:   fmul
L235:   invokestatic Method org/lwjgl/opengl/GL11 else (FFFF)V
L238:   getfield Field CF goto [[F
L241:   iload_3
L242:   aaload
L243:   iconst_0
L244:   iconst_1
L245:   dup
L246:   pop2
L247:   faload
L248:   fload 6
L250:   fadd
L251:   aload_0
L252:   dup_x2
L253:   getfield Field CF goto [[F
L256:   iload_3
L257:   aaload
L258:   iconst_1
L259:   dup
L260:   dup
L261:   pop2
L262:   faload
L263:   fneg
L264:   fload 4
L266:   fsub
L267:   ldc 2.8e0f
L269:   fadd
L270:   invokestatic Method org/lwjgl/opengl/GL11 break (FF)V
L273:   fconst_1
L274:   dup
L275:   aload_0
L276:   getfield Field CF goto [[F
L279:   iload_3
L280:   aaload
L281:   iconst_3
L282:   iconst_1
L283:   dup
L284:   pop2
L285:   faload
L286:   ldc 1e-1f
L288:   fmul
L289:   invokestatic Method org/lwjgl/opengl/GL11 else (FFFF)V
L292:   getfield Field CF goto [[F
L295:   iload_3
L296:   aaload
L297:   iconst_2
L298:   iconst_1
L299:   dup
L300:   pop2
L301:   faload
L302:   fload 6
L304:   fadd
L305:   aload_0
L306:   getfield Field CF goto [[F
L309:   iload_3
L310:   aaload
L311:   iconst_3
L312:   iconst_1
L313:   dup
L314:   pop2
L315:   iinc 3 1
L318:   faload
L319:   fneg
L320:   fload 4
L322:   fsub
L323:   ldc 2.8e0f
L325:   fadd
L326:   invokestatic Method org/lwjgl/opengl/GL11 break (FF)V
L329:   iload_3
L330:   goto L24
L333:   athrow
L334:   invokestatic Method org/lwjgl/opengl/GL11 float ()V
L337:   return
L338:   
        .attribute StackMap b'\x00\x05\x00\x18\x00\x04\x07\x00\x02\x02\x07\x00\x93\x01\x00\x01\x01\x00\x41\x00\x05\x07\x00\x02\x02\x07\x00\x93\x01\x02\x00\x00\x00\x4B\x00\x05\x07\x00\x02\x02\x07\x00\x93\x01\x02\x00\x00\x01\x4D\x00\x00\x00\x01\x07\x00\x30\x01\x4E\x00\x04\x07\x00\x02\x02\x07\x00\x93\x01\x00\x00'
    .end code
.end method

.method public background : (ZF)V
    .code stack 4 locals 4
L0:     aload_0
L1:     getfield Field CF break F
L4:     dup
L5:     fstore_2
L6:     fconst_1
L7:     fdiv
L8:     ldc 5e-1f
L10:    fmul
L11:    f2d
L12:    invokestatic Method OC break (D)D
L15:    d2f
L16:    fstore_3
L17:    iload_1
L18:    ifne L91
L21:    bipush 7
L23:    iconst_1
L24:    dup
L25:    pop2
L26:    invokestatic Method org/lwjgl/opengl/GL11 "strictfp" (I)V
L29:    ldc 1e-1f
L31:    fload_3
L32:    fmul
L33:    ldc 3.5e-1f
L35:    fload_3
L36:    fmul
L37:    ldc 5e-1f
L39:    fload_3
L40:    fmul
L41:    fconst_1
L42:    invokestatic Method org/lwjgl/opengl/GL11 else (FFFF)V
L45:    ldc -3.2e1f
L47:    ldc 2.4e1f
L49:    ldc 7.9e1f
L51:    invokestatic Method org/lwjgl/opengl/GL11 catch (FFF)V
L54:    ldc 3.2e1f
L56:    ldc 2.4e1f
L58:    ldc 7.9e1f
L60:    invokestatic Method org/lwjgl/opengl/GL11 catch (FFF)V
L63:    fconst_0
L64:    dup
L65:    dup_x1
L66:    fconst_1
L67:    invokestatic Method org/lwjgl/opengl/GL11 else (FFFF)V
L70:    ldc 3.2e1f
L72:    ldc -2.4e1f
L74:    ldc 7.9e1f
L76:    invokestatic Method org/lwjgl/opengl/GL11 catch (FFF)V
L79:    ldc -3.2e1f
L81:    ldc -2.4e1f
L83:    ldc 7.9e1f
L85:    invokestatic Method org/lwjgl/opengl/GL11 catch (FFF)V
L88:    invokestatic Method org/lwjgl/opengl/GL11 float ()V
L91:    invokestatic Method FE goto ()V
L94:    fconst_0
L95:    dup
L96:    ldc 2e1f
L98:    invokestatic Method org/lwjgl/opengl/GL11 const (FFF)V
L101:   fload_2
L102:   fconst_1
L103:   fsub
L104:   dup
L105:   fstore_2
L106:   fconst_0
L107:   fcmpl
L108:   iflt L126
L111:   fload_2
L112:   ldc 4e0f
L114:   fcmpg
L115:   ifgt L126
L118:   aload_0
L119:   fload_2
L120:   ldc 4e0f
L122:   fdiv
L123:   invokespecial Method CF else (F)V
L126:   fload_2
L127:   ldc 4e0f
L129:   fsub
L130:   dup
L131:   fstore_2
L132:   fconst_0
L133:   fcmpl
L134:   iflt L153
L137:   fload_2
L138:   ldc 1.5e0f
L140:   fcmpg
L141:   ifgt L153
L144:   aload_0
L145:   dup
L146:   fconst_1
L147:   invokespecial Method CF else (F)V
L150:   invokespecial Method CF else ()V
L153:   fload_2
L154:   ldc 1.5e0f
L156:   fsub
L157:   dup
L158:   fstore_2
L159:   fconst_0
L160:   fcmpl
L161:   iflt L179
L164:   fload_2
L165:   ldc 2.5e-1f
L167:   fcmpg
L168:   ifgt L179
L171:   aload_0
L172:   fload_2
L173:   ldc 2.5e-1f
L175:   fdiv
L176:   invokespecial Method CF const (F)V
L179:   fconst_0
L180:   dup
L181:   ldc -2e1f
L183:   invokestatic Method org/lwjgl/opengl/GL11 const (FFF)V
L186:   return
L187:   
        .attribute StackMap b'\x00\x04\x00\x5B\x00\x04\x07\x00\x02\x01\x02\x02\x00\x00\x00\x7E\x00\x04\x07\x00\x02\x01\x02\x02\x00\x00\x00\x99\x00\x04\x07\x00\x02\x01\x02\x02\x00\x00\x00\xB3\x00\x04\x07\x00\x02\x01\x02\x02\x00\x00'
    .end code
.end method
.end class
