.version 61 0
.class super ColorPicker
.super java/lang/Object
.implements javax/swing/event/ChangeListener
.field static frame Ljavax/swing/JFrame;
.field static coloredTextField Ljavax/swing/JTextField;
.field static hexTextField Ljavax/swing/JTextField;
.field static colorComboList Ljavax/swing/JComboBox; .fieldattributes
    .signature Ljavax/swing/JComboBox<Ljava/lang/String;>;
.end fieldattributes
.field saveButton Ljavax/swing/JButton;
.field sliderRLabel Ljavax/swing/JLabel;
.field sliderGLabel Ljavax/swing/JLabel;
.field sliderBLabel Ljavax/swing/JLabel;
.field hexLabel Ljavax/swing/JLabel;
.field sliderR Ljavax/swing/JSlider;
.field sliderG Ljavax/swing/JSlider;
.field sliderB Ljavax/swing/JSlider;
.field uiFont Ljava/awt/Font;

.method <init> : ()V
    .code stack 6 locals 1
L0:     aload_0
L1:     invokespecial Method java/lang/Object <init> ()V
L4:     aload_0
L5:     new java/awt/Font
L8:     dup
L9:     ldc "SansSerif"
L11:    iconst_0
L12:    bipush 22
L14:    invokespecial Method java/awt/Font <init> (Ljava/lang/String;II)V
L17:    putfield Field ColorPicker uiFont Ljava/awt/Font;
L20:    aload_0
L21:    invokevirtual Method ColorPicker setupFrame ()V
L24:    getstatic Field ColorPicker frame Ljavax/swing/JFrame;
L27:    iconst_1
L28:    invokevirtual Method javax/swing/JFrame setVisible (Z)V
L31:    getstatic Field ColorPicker colorComboList Ljavax/swing/JComboBox;
L34:    invokevirtual Method javax/swing/JComboBox getItemCount ()I
L37:    ifle L51
L40:    getstatic Field ColorPicker colorComboList Ljavax/swing/JComboBox;
L43:    iconst_0
L44:    invokevirtual Method javax/swing/JComboBox setSelectedIndex (I)V
L47:    aload_0
L48:    invokevirtual Method ColorPicker applySelectedColor ()V

        .stack full
            locals Object ColorPicker
            stack
        .end stack
L51:    return
L52:    
        .linenumbertable
            L0 20
            L4 18
            L20 21
            L24 23
            L31 26
            L40 27
            L47 28
            L51 30
        .end linenumbertable
    .end code
.end method

.method private setupFrame : ()V
    .code stack 5 locals 2
L0:     new javax/swing/JFrame
L3:     dup
L4:     ldc "Color Picker Tool"
L6:     invokespecial Method javax/swing/JFrame <init> (Ljava/lang/String;)V
L9:     putstatic Field ColorPicker frame Ljavax/swing/JFrame;
L12:    getstatic Field ColorPicker frame Ljavax/swing/JFrame;
L15:    iconst_3
L16:    invokevirtual Method javax/swing/JFrame setDefaultCloseOperation (I)V
L19:    getstatic Field ColorPicker frame Ljavax/swing/JFrame;
L22:    sipush 800
L25:    sipush 600
L28:    invokevirtual Method javax/swing/JFrame setSize (II)V
L31:    getstatic Field ColorPicker frame Ljavax/swing/JFrame;
L34:    aconst_null
L35:    invokevirtual Method javax/swing/JFrame setLocationRelativeTo (Ljava/awt/Component;)V
L38:    getstatic Field ColorPicker frame Ljavax/swing/JFrame;
L41:    new java/awt/BorderLayout
L44:    dup
L45:    invokespecial Method java/awt/BorderLayout <init> ()V
L48:    invokevirtual Method javax/swing/JFrame setLayout (Ljava/awt/LayoutManager;)V
L51:    new javax/swing/JPanel
L54:    dup
L55:    invokespecial Method javax/swing/JPanel <init> ()V
L58:    astore_1
L59:    aload_1
L60:    new java/awt/GridLayout
L63:    dup
L64:    iconst_0
L65:    iconst_1
L66:    invokespecial Method java/awt/GridLayout <init> (II)V
L69:    invokevirtual Method javax/swing/JPanel setLayout (Ljava/awt/LayoutManager;)V
L72:    getstatic Field ColorPicker frame Ljavax/swing/JFrame;
L75:    aload_1
L76:    ldc "Center"
L78:    invokevirtual Method javax/swing/JFrame add (Ljava/awt/Component;Ljava/lang/Object;)V
L81:    new javax/swing/JTextField
L84:    dup
L85:    invokespecial Method javax/swing/JTextField <init> ()V
L88:    putstatic Field ColorPicker coloredTextField Ljavax/swing/JTextField;
L91:    getstatic Field ColorPicker coloredTextField Ljavax/swing/JTextField;
L94:    aload_0
L95:    getfield Field ColorPicker uiFont Ljava/awt/Font;
L98:    invokevirtual Method javax/swing/JTextField setFont (Ljava/awt/Font;)V
L101:   getstatic Field ColorPicker coloredTextField Ljavax/swing/JTextField;
L104:   iconst_0
L105:   invokevirtual Method javax/swing/JTextField setEditable (Z)V
L108:   getstatic Field ColorPicker frame Ljavax/swing/JFrame;
L111:   getstatic Field ColorPicker coloredTextField Ljavax/swing/JTextField;
L114:   ldc "South"
L116:   invokevirtual Method javax/swing/JFrame add (Ljava/awt/Component;Ljava/lang/Object;)V
L119:   aload_0
L120:   aload_1
L121:   invokevirtual Method ColorPicker setupUIComponents (Ljavax/swing/JPanel;)V
L124:   aload_0
L125:   invokevirtual Method ColorPicker loadColorPresets ()V
L128:   return
L129:   
        .linenumbertable
            L0 33
            L12 34
            L19 35
            L31 36
            L38 37
            L51 39
            L59 40
            L72 41
            L81 44
            L91 45
            L101 46
            L108 47
            L119 49
            L124 50
            L128 51
        .end linenumbertable
    .end code
.end method

.method private setupUIComponents : (Ljavax/swing/JPanel;)V
    .code stack 4 locals 2
L0:     new javax/swing/JComboBox
L3:     dup
L4:     invokespecial Method javax/swing/JComboBox <init> ()V
L7:     putstatic Field ColorPicker colorComboList Ljavax/swing/JComboBox;
L10:    getstatic Field ColorPicker colorComboList Ljavax/swing/JComboBox;
L13:    aload_0
L14:    getfield Field ColorPicker uiFont Ljava/awt/Font;
L17:    invokevirtual Method javax/swing/JComboBox setFont (Ljava/awt/Font;)V
L20:    getstatic Field ColorPicker colorComboList Ljavax/swing/JComboBox;
L23:    aload_0
L24:    invokedynamic [_112]
L29:    invokevirtual Method javax/swing/JComboBox addActionListener (Ljava/awt/event/ActionListener;)V
L32:    aload_1
L33:    getstatic Field ColorPicker colorComboList Ljavax/swing/JComboBox;
L36:    invokevirtual Method javax/swing/JPanel add (Ljava/awt/Component;)Ljava/awt/Component;
L39:    pop
L40:    aload_0
L41:    new javax/swing/JLabel
L44:    dup
L45:    ldc "HEX:"
L47:    invokespecial Method javax/swing/JLabel <init> (Ljava/lang/String;)V
L50:    putfield Field ColorPicker hexLabel Ljavax/swing/JLabel;
L53:    aload_0
L54:    getfield Field ColorPicker hexLabel Ljavax/swing/JLabel;
L57:    aload_0
L58:    getfield Field ColorPicker uiFont Ljava/awt/Font;
L61:    invokevirtual Method javax/swing/JLabel setFont (Ljava/awt/Font;)V
L64:    aload_1
L65:    aload_0
L66:    getfield Field ColorPicker hexLabel Ljavax/swing/JLabel;
L69:    invokevirtual Method javax/swing/JPanel add (Ljava/awt/Component;)Ljava/awt/Component;
L72:    pop
L73:    new javax/swing/JTextField
L76:    dup
L77:    invokespecial Method javax/swing/JTextField <init> ()V
L80:    putstatic Field ColorPicker hexTextField Ljavax/swing/JTextField;
L83:    getstatic Field ColorPicker hexTextField Ljavax/swing/JTextField;
L86:    aload_0
L87:    getfield Field ColorPicker uiFont Ljava/awt/Font;
L90:    invokevirtual Method javax/swing/JTextField setFont (Ljava/awt/Font;)V
L93:    getstatic Field ColorPicker hexTextField Ljavax/swing/JTextField;
L96:    ldc "Enter HEX color code"
L98:    invokevirtual Method javax/swing/JTextField setToolTipText (Ljava/lang/String;)V
L101:   getstatic Field ColorPicker hexTextField Ljavax/swing/JTextField;
L104:   aload_0
L105:   invokedynamic [_141]
L110:   invokevirtual Method javax/swing/JTextField addActionListener (Ljava/awt/event/ActionListener;)V
L113:   aload_1
L114:   getstatic Field ColorPicker hexTextField Ljavax/swing/JTextField;
L117:   invokevirtual Method javax/swing/JPanel add (Ljava/awt/Component;)Ljava/awt/Component;
L120:   pop
L121:   aload_0
L122:   aload_1
L123:   invokevirtual Method ColorPicker setupSliders (Ljavax/swing/JPanel;)V
L126:   aload_0
L127:   new javax/swing/JButton
L130:   dup
L131:   ldc "Save Color"
L133:   invokespecial Method javax/swing/JButton <init> (Ljava/lang/String;)V
L136:   putfield Field ColorPicker saveButton Ljavax/swing/JButton;
L139:   aload_0
L140:   getfield Field ColorPicker saveButton Ljavax/swing/JButton;
L143:   aload_0
L144:   getfield Field ColorPicker uiFont Ljava/awt/Font;
L147:   invokevirtual Method javax/swing/JButton setFont (Ljava/awt/Font;)V
L150:   aload_0
L151:   getfield Field ColorPicker saveButton Ljavax/swing/JButton;
L154:   aload_0
L155:   invokedynamic [_156]
L160:   invokevirtual Method javax/swing/JButton addActionListener (Ljava/awt/event/ActionListener;)V
L163:   aload_1
L164:   aload_0
L165:   getfield Field ColorPicker saveButton Ljavax/swing/JButton;
L168:   invokevirtual Method javax/swing/JPanel add (Ljava/awt/Component;)Ljava/awt/Component;
L171:   pop
L172:   return
L173:   
        .linenumbertable
            L0 54
            L10 55
            L20 56
            L32 57
            L40 59
            L53 60
            L64 61
            L73 63
            L83 64
            L93 65
            L101 66
            L113 67
            L121 69
            L126 71
            L139 72
            L150 73
            L163 74
            L172 75
        .end linenumbertable
    .end code
.end method

.method private setupSliders : (Ljavax/swing/JPanel;)V
    .code stack 6 locals 2
L0:     aload_0
L1:     new javax/swing/JLabel
L4:     dup
L5:     ldc "Red: 128"
L7:     invokespecial Method javax/swing/JLabel <init> (Ljava/lang/String;)V
L10:    putfield Field ColorPicker sliderRLabel Ljavax/swing/JLabel;
L13:    aload_0
L14:    getfield Field ColorPicker sliderRLabel Ljavax/swing/JLabel;
L17:    aload_0
L18:    getfield Field ColorPicker uiFont Ljava/awt/Font;
L21:    invokevirtual Method javax/swing/JLabel setFont (Ljava/awt/Font;)V
L24:    aload_1
L25:    aload_0
L26:    getfield Field ColorPicker sliderRLabel Ljavax/swing/JLabel;
L29:    invokevirtual Method javax/swing/JPanel add (Ljava/awt/Component;)Ljava/awt/Component;
L32:    pop
L33:    aload_0
L34:    new javax/swing/JSlider
L37:    dup
L38:    iconst_0
L39:    sipush 255
L42:    sipush 128
L45:    invokespecial Method javax/swing/JSlider <init> (III)V
L48:    putfield Field ColorPicker sliderR Ljavax/swing/JSlider;
L51:    aload_0
L52:    getfield Field ColorPicker sliderR Ljavax/swing/JSlider;
L55:    aload_0
L56:    getfield Field ColorPicker uiFont Ljava/awt/Font;
L59:    invokevirtual Method javax/swing/JSlider setFont (Ljava/awt/Font;)V
L62:    aload_0
L63:    getfield Field ColorPicker sliderR Ljavax/swing/JSlider;
L66:    aload_0
L67:    invokevirtual Method javax/swing/JSlider addChangeListener (Ljavax/swing/event/ChangeListener;)V
L70:    aload_1
L71:    aload_0
L72:    getfield Field ColorPicker sliderR Ljavax/swing/JSlider;
L75:    invokevirtual Method javax/swing/JPanel add (Ljava/awt/Component;)Ljava/awt/Component;
L78:    pop
L79:    aload_0
L80:    new javax/swing/JLabel
L83:    dup
L84:    ldc "Green: 128"
L86:    invokespecial Method javax/swing/JLabel <init> (Ljava/lang/String;)V
L89:    putfield Field ColorPicker sliderGLabel Ljavax/swing/JLabel;
L92:    aload_0
L93:    getfield Field ColorPicker sliderGLabel Ljavax/swing/JLabel;
L96:    aload_0
L97:    getfield Field ColorPicker uiFont Ljava/awt/Font;
L100:   invokevirtual Method javax/swing/JLabel setFont (Ljava/awt/Font;)V
L103:   aload_1
L104:   aload_0
L105:   getfield Field ColorPicker sliderGLabel Ljavax/swing/JLabel;
L108:   invokevirtual Method javax/swing/JPanel add (Ljava/awt/Component;)Ljava/awt/Component;
L111:   pop
L112:   aload_0
L113:   new javax/swing/JSlider
L116:   dup
L117:   iconst_0
L118:   sipush 255
L121:   sipush 128
L124:   invokespecial Method javax/swing/JSlider <init> (III)V
L127:   putfield Field ColorPicker sliderG Ljavax/swing/JSlider;
L130:   aload_0
L131:   getfield Field ColorPicker sliderG Ljavax/swing/JSlider;
L134:   aload_0
L135:   getfield Field ColorPicker uiFont Ljava/awt/Font;
L138:   invokevirtual Method javax/swing/JSlider setFont (Ljava/awt/Font;)V
L141:   aload_0
L142:   getfield Field ColorPicker sliderG Ljavax/swing/JSlider;
L145:   aload_0
L146:   invokevirtual Method javax/swing/JSlider addChangeListener (Ljavax/swing/event/ChangeListener;)V
L149:   aload_1
L150:   aload_0
L151:   getfield Field ColorPicker sliderG Ljavax/swing/JSlider;
L154:   invokevirtual Method javax/swing/JPanel add (Ljava/awt/Component;)Ljava/awt/Component;
L157:   pop
L158:   aload_0
L159:   new javax/swing/JLabel
L162:   dup
L163:   ldc "Blue: 128"
L165:   invokespecial Method javax/swing/JLabel <init> (Ljava/lang/String;)V
L168:   putfield Field ColorPicker sliderBLabel Ljavax/swing/JLabel;
L171:   aload_0
L172:   getfield Field ColorPicker sliderBLabel Ljavax/swing/JLabel;
L175:   aload_0
L176:   getfield Field ColorPicker uiFont Ljava/awt/Font;
L179:   invokevirtual Method javax/swing/JLabel setFont (Ljava/awt/Font;)V
L182:   aload_1
L183:   aload_0
L184:   getfield Field ColorPicker sliderBLabel Ljavax/swing/JLabel;
L187:   invokevirtual Method javax/swing/JPanel add (Ljava/awt/Component;)Ljava/awt/Component;
L190:   pop
L191:   aload_0
L192:   new javax/swing/JSlider
L195:   dup
L196:   iconst_0
L197:   sipush 255
L200:   sipush 128
L203:   invokespecial Method javax/swing/JSlider <init> (III)V
L206:   putfield Field ColorPicker sliderB Ljavax/swing/JSlider;
L209:   aload_0
L210:   getfield Field ColorPicker sliderB Ljavax/swing/JSlider;
L213:   aload_0
L214:   getfield Field ColorPicker uiFont Ljava/awt/Font;
L217:   invokevirtual Method javax/swing/JSlider setFont (Ljava/awt/Font;)V
L220:   aload_0
L221:   getfield Field ColorPicker sliderB Ljavax/swing/JSlider;
L224:   aload_0
L225:   invokevirtual Method javax/swing/JSlider addChangeListener (Ljavax/swing/event/ChangeListener;)V
L228:   aload_1
L229:   aload_0
L230:   getfield Field ColorPicker sliderB Ljavax/swing/JSlider;
L233:   invokevirtual Method javax/swing/JPanel add (Ljava/awt/Component;)Ljava/awt/Component;
L236:   pop
L237:   return
L238:   
        .linenumbertable
            L0 78
            L13 79
            L24 80
            L33 82
            L51 83
            L62 84
            L70 85
            L79 87
            L92 88
            L103 89
            L112 91
            L130 92
            L141 93
            L149 94
            L158 96
            L171 97
            L182 98
            L191 100
            L209 101
            L220 102
            L228 103
            L237 104
        .end linenumbertable
    .end code
.end method

.method public stateChanged : (Ljavax/swing/event/ChangeEvent;)V
    .code stack 2 locals 2
L0:     aload_0
L1:     invokevirtual Method ColorPicker updateColor ()V
L4:     aload_0
L5:     getfield Field ColorPicker sliderRLabel Ljavax/swing/JLabel;
L8:     aload_0
L9:     getfield Field ColorPicker sliderR Ljavax/swing/JSlider;
L12:    invokevirtual Method javax/swing/JSlider getValue ()I
L15:    invokedynamic [_199]
L20:    invokevirtual Method javax/swing/JLabel setText (Ljava/lang/String;)V
L23:    aload_0
L24:    getfield Field ColorPicker sliderGLabel Ljavax/swing/JLabel;
L27:    aload_0
L28:    getfield Field ColorPicker sliderG Ljavax/swing/JSlider;
L31:    invokevirtual Method javax/swing/JSlider getValue ()I
L34:    invokedynamic [_206]
L39:    invokevirtual Method javax/swing/JLabel setText (Ljava/lang/String;)V
L42:    aload_0
L43:    getfield Field ColorPicker sliderBLabel Ljavax/swing/JLabel;
L46:    aload_0
L47:    getfield Field ColorPicker sliderB Ljavax/swing/JSlider;
L50:    invokevirtual Method javax/swing/JSlider getValue ()I
L53:    invokedynamic [_207]
L58:    invokevirtual Method javax/swing/JLabel setText (Ljava/lang/String;)V
L61:    aload_0
L62:    invokevirtual Method ColorPicker updateHexFromColor ()V
L65:    return
L66:    
        .linenumbertable
            L0 107
            L4 108
            L23 109
            L42 110
            L61 113
            L65 114
        .end linenumbertable
    .end code
.end method

.method private updateColor : ()V
    .code stack 6 locals 4
L0:     getstatic Field ColorPicker coloredTextField Ljavax/swing/JTextField;
L3:     ifnull L46
L6:     aload_0
L7:     getfield Field ColorPicker sliderR Ljavax/swing/JSlider;
L10:    invokevirtual Method javax/swing/JSlider getValue ()I
L13:    istore_1
L14:    aload_0
L15:    getfield Field ColorPicker sliderG Ljavax/swing/JSlider;
L18:    invokevirtual Method javax/swing/JSlider getValue ()I
L21:    istore_2
L22:    aload_0
L23:    getfield Field ColorPicker sliderB Ljavax/swing/JSlider;
L26:    invokevirtual Method javax/swing/JSlider getValue ()I
L29:    istore_3
L30:    getstatic Field ColorPicker coloredTextField Ljavax/swing/JTextField;
L33:    new java/awt/Color
L36:    dup
L37:    iload_1
L38:    iload_2
L39:    iload_3
L40:    invokespecial Method java/awt/Color <init> (III)V
L43:    invokevirtual Method javax/swing/JTextField setBackground (Ljava/awt/Color;)V

        .stack same
L46:    return
L47:    
        .linenumbertable
            L0 117
            L6 118
            L14 119
            L22 120
            L30 121
            L46 123
        .end linenumbertable
    .end code
.end method

.method private updateHexFromColor : ()V
    .code stack 5 locals 5
L0:     aload_0
L1:     getfield Field ColorPicker sliderR Ljavax/swing/JSlider;
L4:     invokevirtual Method javax/swing/JSlider getValue ()I
L7:     istore_1
L8:     aload_0
L9:     getfield Field ColorPicker sliderG Ljavax/swing/JSlider;
L12:    invokevirtual Method javax/swing/JSlider getValue ()I
L15:    istore_2
L16:    aload_0
L17:    getfield Field ColorPicker sliderB Ljavax/swing/JSlider;
L20:    invokevirtual Method javax/swing/JSlider getValue ()I
L23:    istore_3
L24:    ldc "#%02X%02X%02X"
L26:    iconst_3
L27:    anewarray java/lang/Object
L30:    dup
L31:    iconst_0
L32:    iload_1
L33:    invokestatic Method java/lang/Integer valueOf (I)Ljava/lang/Integer;
L36:    aastore
L37:    dup
L38:    iconst_1
L39:    iload_2
L40:    invokestatic Method java/lang/Integer valueOf (I)Ljava/lang/Integer;
L43:    aastore
L44:    dup
L45:    iconst_2
L46:    iload_3
L47:    invokestatic Method java/lang/Integer valueOf (I)Ljava/lang/Integer;
L50:    aastore
L51:    invokestatic Method java/lang/String format (Ljava/lang/String;[Ljava/lang/Object;)Ljava/lang/String;
L54:    astore 4
L56:    getstatic Field ColorPicker hexTextField Ljavax/swing/JTextField;
L59:    aload 4
L61:    invokevirtual Method javax/swing/JTextField setText (Ljava/lang/String;)V
L64:    return
L65:    
        .linenumbertable
            L0 126
            L8 127
            L16 128
            L24 129
            L56 130
            L64 131
        .end linenumbertable
    .end code
.end method

.method private loadColorPresets : ()V
    .code stack 5 locals 4
L0:     new java/io/BufferedReader
L3:     dup
L4:     new java/io/FileReader
L7:     dup
L8:     ldc "settings/colorPresets.txt"
L10:    invokespecial Method java/io/FileReader <init> (Ljava/lang/String;)V
L13:    invokespecial Method java/io/BufferedReader <init> (Ljava/io/Reader;)V
L16:    astore_1
        .catch java/lang/Throwable from L17 to L36 using L43

        .stack append Object java/io/BufferedReader
L17:    aload_1
L18:    invokevirtual Method java/io/BufferedReader readLine ()Ljava/lang/String;
L21:    dup
L22:    astore_2
L23:    ifnull L36
L26:    getstatic Field ColorPicker colorComboList Ljavax/swing/JComboBox;
L29:    aload_2
L30:    invokevirtual Method javax/swing/JComboBox addItem (Ljava/lang/Object;)V
L33:    goto L17

        .stack same
L36:    aload_1
L37:    invokevirtual Method java/io/BufferedReader close ()V
L40:    goto L59

        .stack stack_1 Object java/lang/Throwable
L43:    astore_2
        .catch java/lang/Throwable from L44 to L48 using L51
        .catch java/io/IOException from L0 to L59 using L62
L44:    aload_1
L45:    invokevirtual Method java/io/BufferedReader close ()V
L48:    goto L57

        .stack full
            locals Object ColorPicker Object java/io/BufferedReader Object java/lang/Throwable
            stack Object java/lang/Throwable
        .end stack
L51:    astore_3
L52:    aload_2
L53:    aload_3
L54:    invokevirtual Method java/lang/Throwable addSuppressed (Ljava/lang/Throwable;)V

        .stack same
L57:    aload_2
L58:    athrow

        .stack chop 2
L59:    goto L80

        .stack stack_1 Object java/io/IOException
L62:    astore_1
L63:    aload_1
L64:    invokevirtual Method java/io/IOException printStackTrace ()V
L67:    getstatic Field ColorPicker frame Ljavax/swing/JFrame;
L70:    ldc_w "Error loading color presets"
L73:    ldc_w "File Read Error"
L76:    iconst_0
L77:    invokestatic Method javax/swing/JOptionPane showMessageDialog (Ljava/awt/Component;Ljava/lang/Object;Ljava/lang/String;I)V

        .stack same
L80:    return
L81:    
        .linenumbertable
            L0 134
            L17 136
            L26 137
            L36 139
            L43 134
            L59 142
            L62 139
            L63 140
            L67 141
            L80 143
        .end linenumbertable
    .end code
.end method

.method private applySelectedColor : ()V
    .code stack 4 locals 6
L0:     getstatic Field ColorPicker colorComboList Ljavax/swing/JComboBox;
L3:     invokevirtual Method javax/swing/JComboBox getSelectedItem ()Ljava/lang/Object;
L6:     checkcast java/lang/String
L9:     astore_1
L10:    aload_1
L11:    ifnull L148
L14:    aload_1
L15:    ldc_w ","
L18:    invokevirtual Method java/lang/String split (Ljava/lang/String;)[Ljava/lang/String;
L21:    astore_2
L22:    aload_2
L23:    arraylength
L24:    iconst_4
L25:    if_icmpne L135
        .catch java/lang/NumberFormatException from L28 to L111 using L114
L28:    aload_2
L29:    iconst_1
L30:    aaload
L31:    invokevirtual Method java/lang/String trim ()Ljava/lang/String;
L34:    invokestatic Method java/lang/Float parseFloat (Ljava/lang/String;)F
L37:    fstore_3
L38:    aload_2
L39:    iconst_2
L40:    aaload
L41:    invokevirtual Method java/lang/String trim ()Ljava/lang/String;
L44:    invokestatic Method java/lang/Float parseFloat (Ljava/lang/String;)F
L47:    fstore 4
L49:    aload_2
L50:    iconst_3
L51:    aaload
L52:    invokevirtual Method java/lang/String trim ()Ljava/lang/String;
L55:    invokestatic Method java/lang/Float parseFloat (Ljava/lang/String;)F
L58:    fstore 5
L60:    aload_0
L61:    getfield Field ColorPicker sliderR Ljavax/swing/JSlider;
L64:    fload_3
L65:    ldc_w 2.55e2f
L68:    fmul
L69:    invokestatic Method java/lang/Math round (F)I
L72:    invokevirtual Method javax/swing/JSlider setValue (I)V
L75:    aload_0
L76:    getfield Field ColorPicker sliderG Ljavax/swing/JSlider;
L79:    fload 4
L81:    ldc_w 2.55e2f
L84:    fmul
L85:    invokestatic Method java/lang/Math round (F)I
L88:    invokevirtual Method javax/swing/JSlider setValue (I)V
L91:    aload_0
L92:    getfield Field ColorPicker sliderB Ljavax/swing/JSlider;
L95:    fload 5
L97:    ldc_w 2.55e2f
L100:   fmul
L101:   invokestatic Method java/lang/Math round (F)I
L104:   invokevirtual Method javax/swing/JSlider setValue (I)V
L107:   aload_0
L108:   invokevirtual Method ColorPicker updateColor ()V
L111:   goto L148

        .stack full
            locals Object ColorPicker Object java/lang/String Object [Ljava/lang/String;
            stack Object java/lang/NumberFormatException
        .end stack
L114:   astore_3
L115:   aload_3
L116:   invokevirtual Method java/lang/NumberFormatException printStackTrace ()V
L119:   getstatic Field ColorPicker frame Ljavax/swing/JFrame;
L122:   ldc_w "Invalid color values"
L125:   ldc_w "Error"
L128:   iconst_0
L129:   invokestatic Method javax/swing/JOptionPane showMessageDialog (Ljava/awt/Component;Ljava/lang/Object;Ljava/lang/String;I)V
L132:   goto L148

        .stack same
L135:   getstatic Field ColorPicker frame Ljavax/swing/JFrame;
L138:   ldc_w "Invalid color format"
L141:   ldc_w "Error"
L144:   iconst_0
L145:   invokestatic Method javax/swing/JOptionPane showMessageDialog (Ljava/awt/Component;Ljava/lang/Object;Ljava/lang/String;I)V

        .stack chop 1
L148:   return
L149:   
        .linenumbertable
            L0 146
            L10 147
            L14 149
            L22 150
            L28 152
            L38 153
            L49 154
            L60 157
            L75 158
            L91 159
            L107 161
            L111 165
            L114 162
            L115 163
            L119 164
            L132 165
            L135 167
            L148 170
        .end linenumbertable
    .end code
.end method

.method private updateColorFromHex : ()V
    .code stack 4 locals 2
        .catch java/lang/NumberFormatException from L0 to L47 using L50
L0:     getstatic Field ColorPicker hexTextField Ljavax/swing/JTextField;
L3:     invokevirtual Method javax/swing/JTextField getText ()Ljava/lang/String;
L6:     invokestatic Method java/awt/Color decode (Ljava/lang/String;)Ljava/awt/Color;
L9:     astore_1
L10:    aload_0
L11:    getfield Field ColorPicker sliderR Ljavax/swing/JSlider;
L14:    aload_1
L15:    invokevirtual Method java/awt/Color getRed ()I
L18:    invokevirtual Method javax/swing/JSlider setValue (I)V
L21:    aload_0
L22:    getfield Field ColorPicker sliderG Ljavax/swing/JSlider;
L25:    aload_1
L26:    invokevirtual Method java/awt/Color getGreen ()I
L29:    invokevirtual Method javax/swing/JSlider setValue (I)V
L32:    aload_0
L33:    getfield Field ColorPicker sliderB Ljavax/swing/JSlider;
L36:    aload_1
L37:    invokevirtual Method java/awt/Color getBlue ()I
L40:    invokevirtual Method javax/swing/JSlider setValue (I)V
L43:    aload_0
L44:    invokevirtual Method ColorPicker updateColor ()V
L47:    goto L68

        .stack stack_1 Object java/lang/NumberFormatException
L50:    astore_1
L51:    aload_1
L52:    invokevirtual Method java/lang/NumberFormatException printStackTrace ()V
L55:    getstatic Field ColorPicker frame Ljavax/swing/JFrame;
L58:    ldc_w "Invalid HEX code"
L61:    ldc_w "Error"
L64:    iconst_0
L65:    invokestatic Method javax/swing/JOptionPane showMessageDialog (Ljava/awt/Component;Ljava/lang/Object;Ljava/lang/String;I)V

        .stack same
L68:    return
L69:    
        .linenumbertable
            L0 174
            L10 175
            L21 176
            L32 177
            L43 178
            L47 182
            L50 179
            L51 180
            L55 181
            L68 183
        .end linenumbertable
    .end code
.end method

.method private saveColorToFile : ()V
    .code stack 6 locals 6
        .catch java/io/IOException from L0 to L141 using L144
L0:     ldc_w "settings"
L3:     iconst_0
L4:     anewarray java/lang/String
L7:     invokestatic Method java/nio/file/Paths get (Ljava/lang/String;[Ljava/lang/String;)Ljava/nio/file/Path;
L10:    astore_1
L11:    aload_1
L12:    iconst_0
L13:    anewarray java/nio/file/LinkOption
L16:    invokestatic Method java/nio/file/Files exists (Ljava/nio/file/Path;[Ljava/nio/file/LinkOption;)Z
L19:    ifne L31
L22:    aload_1
L23:    iconst_0
L24:    anewarray java/nio/file/attribute/FileAttribute
L27:    invokestatic Method java/nio/file/Files createDirectories (Ljava/nio/file/Path;[Ljava/nio/file/attribute/FileAttribute;)Ljava/nio/file/Path;
L30:    pop

        .stack append Object java/nio/file/Path
L31:    aload_0
L32:    getfield Field ColorPicker sliderR Ljavax/swing/JSlider;
L35:    invokevirtual Method javax/swing/JSlider getValue ()I
L38:    i2f
L39:    ldc_w 2.55e2f
L42:    fdiv
L43:    fstore_2
L44:    aload_0
L45:    getfield Field ColorPicker sliderG Ljavax/swing/JSlider;
L48:    invokevirtual Method javax/swing/JSlider getValue ()I
L51:    i2f
L52:    ldc_w 2.55e2f
L55:    fdiv
L56:    fstore_3
L57:    aload_0
L58:    getfield Field ColorPicker sliderB Ljavax/swing/JSlider;
L61:    invokevirtual Method javax/swing/JSlider getValue ()I
L64:    i2f
L65:    ldc_w 2.55e2f
L68:    fdiv
L69:    fstore 4
L71:    getstatic Field java/util/Locale ENGLISH Ljava/util/Locale;
L74:    ldc_w "%.9f, %.9f, %.9f"
L77:    iconst_3
L78:    anewarray java/lang/Object
L81:    dup
L82:    iconst_0
L83:    fload_2
L84:    invokestatic Method java/lang/Float valueOf (F)Ljava/lang/Float;
L87:    aastore
L88:    dup
L89:    iconst_1
L90:    fload_3
L91:    invokestatic Method java/lang/Float valueOf (F)Ljava/lang/Float;
L94:    aastore
L95:    dup
L96:    iconst_2
L97:    fload 4
L99:    invokestatic Method java/lang/Float valueOf (F)Ljava/lang/Float;
L102:   aastore
L103:   invokestatic Method java/lang/String format (Ljava/util/Locale;Ljava/lang/String;[Ljava/lang/Object;)Ljava/lang/String;
L106:   astore 5
L108:   ldc_w "settings/background-color.txt"
L111:   iconst_0
L112:   anewarray java/lang/String
L115:   invokestatic Method java/nio/file/Paths get (Ljava/lang/String;[Ljava/lang/String;)Ljava/nio/file/Path;
L118:   aload 5
L120:   iconst_0
L121:   anewarray java/nio/file/OpenOption
L124:   invokestatic Method java/nio/file/Files writeString (Ljava/nio/file/Path;Ljava/lang/CharSequence;[Ljava/nio/file/OpenOption;)Ljava/nio/file/Path;
L127:   pop
L128:   getstatic Field ColorPicker frame Ljavax/swing/JFrame;
L131:   ldc_w "Color saved successfully!"
L134:   ldc_w "Success"
L137:   iconst_1
L138:   invokestatic Method javax/swing/JOptionPane showMessageDialog (Ljava/awt/Component;Ljava/lang/Object;Ljava/lang/String;I)V
L141:   goto L162

        .stack full
            locals Object ColorPicker
            stack Object java/io/IOException
        .end stack
L144:   astore_1
L145:   aload_1
L146:   invokevirtual Method java/io/IOException printStackTrace ()V
L149:   getstatic Field ColorPicker frame Ljavax/swing/JFrame;
L152:   ldc_w "Failed to save color!"
L155:   ldc_w "Error"
L158:   iconst_0
L159:   invokestatic Method javax/swing/JOptionPane showMessageDialog (Ljava/awt/Component;Ljava/lang/Object;Ljava/lang/String;I)V

        .stack same
L162:   return
L163:   
        .linenumbertable
            L0 188
            L11 189
            L22 190
            L31 193
            L44 194
            L57 195
            L71 198
            L108 200
            L128 201
            L141 205
            L144 202
            L145 203
            L149 204
            L162 206
        .end linenumbertable
    .end code
.end method

.method public static main : ([Ljava/lang/String;)V
    .code stack 1 locals 1
L0:     invokedynamic [_381]
L5:     invokestatic Method javax/swing/SwingUtilities invokeLater (Ljava/lang/Runnable;)V
L8:     return
L9:     
        .linenumbertable
            L0 209
            L8 210
        .end linenumbertable
    .end code
.end method

.method private synthetic lambda$setupUIComponents$2 : (Ljava/awt/event/ActionEvent;)V
    .code stack 1 locals 2
L0:     aload_0
L1:     invokevirtual Method ColorPicker saveColorToFile ()V
L4:     return
L5:     
        .linenumbertable
            L0 73
        .end linenumbertable
    .end code
.end method

.method private synthetic lambda$setupUIComponents$1 : (Ljava/awt/event/ActionEvent;)V
    .code stack 1 locals 2
L0:     aload_0
L1:     invokevirtual Method ColorPicker updateColorFromHex ()V
L4:     return
L5:     
        .linenumbertable
            L0 66
        .end linenumbertable
    .end code
.end method

.method private synthetic lambda$setupUIComponents$0 : (Ljava/awt/event/ActionEvent;)V
    .code stack 1 locals 2
L0:     aload_0
L1:     invokevirtual Method ColorPicker applySelectedColor ()V
L4:     return
L5:     
        .linenumbertable
            L0 56
        .end linenumbertable
    .end code
.end method
.sourcefile "ColorPicker.java"
.bootstrapmethods
.innerclasses
    java/lang/invoke/MethodHandles$Lookup java/lang/invoke/MethodHandles Lookup public static final
.end innerclasses
.const [_112] = InvokeDynamic invokeStatic Method java/lang/invoke/LambdaMetafactory metafactory (Ljava/lang/invoke/MethodHandles$Lookup;Ljava/lang/String;Ljava/lang/invoke/MethodType;Ljava/lang/invoke/MethodType;Ljava/lang/invoke/MethodHandle;Ljava/lang/invoke/MethodType;)Ljava/lang/invoke/CallSite; MethodType (Ljava/awt/event/ActionEvent;)V [_427] MethodType (Ljava/awt/event/ActionEvent;)V : actionPerformed (LColorPicker;)Ljava/awt/event/ActionListener;
.const [_141] = InvokeDynamic invokeStatic Method java/lang/invoke/LambdaMetafactory metafactory (Ljava/lang/invoke/MethodHandles$Lookup;Ljava/lang/String;Ljava/lang/invoke/MethodType;Ljava/lang/invoke/MethodType;Ljava/lang/invoke/MethodHandle;Ljava/lang/invoke/MethodType;)Ljava/lang/invoke/CallSite; MethodType (Ljava/awt/event/ActionEvent;)V [_430] MethodType (Ljava/awt/event/ActionEvent;)V : actionPerformed (LColorPicker;)Ljava/awt/event/ActionListener;
.const [_156] = InvokeDynamic invokeStatic Method java/lang/invoke/LambdaMetafactory metafactory (Ljava/lang/invoke/MethodHandles$Lookup;Ljava/lang/String;Ljava/lang/invoke/MethodType;Ljava/lang/invoke/MethodType;Ljava/lang/invoke/MethodHandle;Ljava/lang/invoke/MethodType;)Ljava/lang/invoke/CallSite; MethodType (Ljava/awt/event/ActionEvent;)V [_433] MethodType (Ljava/awt/event/ActionEvent;)V : actionPerformed (LColorPicker;)Ljava/awt/event/ActionListener;
.const [_199] = InvokeDynamic invokeStatic Method java/lang/invoke/StringConcatFactory makeConcatWithConstants (Ljava/lang/invoke/MethodHandles$Lookup;Ljava/lang/String;Ljava/lang/invoke/MethodType;Ljava/lang/String;[Ljava/lang/Object;)Ljava/lang/invoke/CallSite; String "Red: \u0001" : makeConcatWithConstants (I)Ljava/lang/String;
.const [_206] = InvokeDynamic invokeStatic Method java/lang/invoke/StringConcatFactory makeConcatWithConstants (Ljava/lang/invoke/MethodHandles$Lookup;Ljava/lang/String;Ljava/lang/invoke/MethodType;Ljava/lang/String;[Ljava/lang/Object;)Ljava/lang/invoke/CallSite; String "Green: \u0001" : makeConcatWithConstants (I)Ljava/lang/String;
.const [_207] = InvokeDynamic invokeStatic Method java/lang/invoke/StringConcatFactory makeConcatWithConstants (Ljava/lang/invoke/MethodHandles$Lookup;Ljava/lang/String;Ljava/lang/invoke/MethodType;Ljava/lang/String;[Ljava/lang/Object;)Ljava/lang/invoke/CallSite; String "Blue: \u0001" : makeConcatWithConstants (I)Ljava/lang/String;
.const [_381] = InvokeDynamic invokeStatic Method java/lang/invoke/LambdaMetafactory metafactory (Ljava/lang/invoke/MethodHandles$Lookup;Ljava/lang/String;Ljava/lang/invoke/MethodType;Ljava/lang/invoke/MethodType;Ljava/lang/invoke/MethodHandle;Ljava/lang/invoke/MethodType;)Ljava/lang/invoke/CallSite; MethodType ()V [_449] MethodType ()V : run ()Ljava/lang/Runnable;
.const [_427] = MethodHandle invokeVirtual Method ColorPicker lambda$setupUIComponents$0 (Ljava/awt/event/ActionEvent;)V
.const [_430] = MethodHandle invokeVirtual Method ColorPicker lambda$setupUIComponents$1 (Ljava/awt/event/ActionEvent;)V
.const [_433] = MethodHandle invokeVirtual Method ColorPicker lambda$setupUIComponents$2 (Ljava/awt/event/ActionEvent;)V
.const [_449] = MethodHandle newInvokeSpecial Method ColorPicker <init> ()V
.end class
