.version 49 0
.class public final super Dc
.super java/lang/Object
.field public "enum" Ljava/lang/Object;
.field public do Ljava/lang/Object;

.method public <init> : (Ljava/lang/Object;Ljava/lang/Object;)V
    .code stack 5 locals 3
L0:     aload_2
L1:     aload_0
L2:     dup_x1
L3:     aload_1
L4:     aload_0
L5:     invokespecial Method java/lang/Object <init> ()V
L8:     putfield Field Dc "enum" Ljava/lang/Object;
L11:    putfield Field Dc do Ljava/lang/Object;
L14:    return
L15:    
    .end code
.end method

.method public equals : (Ljava/lang/Object;)Z
    .code stack 3 locals 2
L0:     aload_1
L1:     instanceof Dc
L4:     ifne L13
L7:     iconst_0
L8:     iconst_1
L9:     dup
L10:    pop2
L11:    ireturn
L12:    athrow
L13:    aload_1
L14:    checkcast Dc
L17:    astore_1
L18:    aload_0
L19:    getfield Field Dc "enum" Ljava/lang/Object;
L22:    ifnull L71
L25:    aload_0
L26:    getfield Field Dc do Ljava/lang/Object;
L29:    ifnull L71
L32:    aload_0
L33:    getfield Field Dc "enum" Ljava/lang/Object;
L36:    aload_1
L37:    getfield Field Dc "enum" Ljava/lang/Object;
L40:    invokevirtual Method java/lang/Object equals (Ljava/lang/Object;)Z
L43:    ifeq L66
L46:    aload_0
L47:    getfield Field Dc do Ljava/lang/Object;
L50:    aload_1
L51:    getfield Field Dc do Ljava/lang/Object;
L54:    invokevirtual Method java/lang/Object equals (Ljava/lang/Object;)Z
L57:    ifeq L66
L60:    iconst_1
L61:    dup
L62:    dup
L63:    pop2
L64:    ireturn
L65:    athrow
L66:    iconst_0
L67:    iconst_1
L68:    dup
L69:    pop2
L70:    ireturn
L71:    aload_0
L72:    getfield Field Dc "enum" Ljava/lang/Object;
L75:    ifnull L113
L78:    aload_0
L79:    getfield Field Dc "enum" Ljava/lang/Object;
L82:    aload_1
L83:    getfield Field Dc "enum" Ljava/lang/Object;
L86:    invokevirtual Method java/lang/Object equals (Ljava/lang/Object;)Z
L89:    ifeq L108
L92:    aload_0
L93:    getfield Field Dc do Ljava/lang/Object;
L96:    aload_1
L97:    getfield Field Dc do Ljava/lang/Object;
L100:   if_acmpne L108
L103:   iconst_1
L104:   dup
L105:   dup
L106:   pop2
L107:   ireturn
L108:   iconst_0
L109:   iconst_1
L110:   dup
L111:   pop2
L112:   ireturn
L113:   aload_0
L114:   getfield Field Dc do Ljava/lang/Object;
L117:   ifnull L155
L120:   aload_0
L121:   getfield Field Dc do Ljava/lang/Object;
L124:   aload_1
L125:   getfield Field Dc do Ljava/lang/Object;
L128:   invokevirtual Method java/lang/Object equals (Ljava/lang/Object;)Z
L131:   ifeq L150
L134:   aload_0
L135:   getfield Field Dc "enum" Ljava/lang/Object;
L138:   aload_1
L139:   getfield Field Dc "enum" Ljava/lang/Object;
L142:   if_acmpne L150
L145:   iconst_1
L146:   dup
L147:   dup
L148:   pop2
L149:   ireturn
L150:   iconst_0
L151:   iconst_1
L152:   dup
L153:   pop2
L154:   ireturn
L155:   aload_0
L156:   getfield Field Dc "enum" Ljava/lang/Object;
L159:   aload_1
L160:   getfield Field Dc "enum" Ljava/lang/Object;
L163:   if_acmpne L182
L166:   aload_0
L167:   getfield Field Dc do Ljava/lang/Object;
L170:   aload_1
L171:   getfield Field Dc do Ljava/lang/Object;
L174:   if_acmpne L182
L177:   iconst_1
L178:   dup
L179:   dup
L180:   pop2
L181:   ireturn
L182:   iconst_0
L183:   iconst_1
L184:   dup
L185:   pop2
L186:   ireturn
L187:   
        .attribute StackMap b'\x00\x0A\x00\x0C\x00\x00\x00\x01\x07\x00\x14\x00\x0D\x00\x02\x07\x00\x02\x07\x00\x04\x00\x00\x00\x41\x00\x00\x00\x01\x07\x00\x14\x00\x42\x00\x02\x07\x00\x02\x07\x00\x02\x00\x00\x00\x47\x00\x02\x07\x00\x02\x07\x00\x02\x00\x00\x00\x6C\x00\x02\x07\x00\x02\x07\x00\x02\x00\x00\x00\x71\x00\x02\x07\x00\x02\x07\x00\x02\x00\x00\x00\x96\x00\x02\x07\x00\x02\x07\x00\x02\x00\x00\x00\x9B\x00\x02\x07\x00\x02\x07\x00\x02\x00\x00\x00\xB6\x00\x02\x07\x00\x02\x07\x00\x02\x00\x00'
    .end code
.end method

.method public hashCode : ()I
    .code stack 5 locals 1
L0:     aload_0
L1:     getfield Field Dc "enum" Ljava/lang/Object;
L4:     ifnonnull L20
L7:     aload_0
L8:     getfield Field Dc do Ljava/lang/Object;
L11:    ifnonnull L20
L14:    iconst_0
L15:    iconst_1
L16:    dup
L17:    pop2
L18:    ireturn
L19:    athrow
L20:    aload_0
L21:    getfield Field Dc "enum" Ljava/lang/Object;
L24:    ifnonnull L56
L27:    aload_0
L28:    getfield Field Dc do Ljava/lang/Object;
L31:    invokevirtual Method java/lang/Object hashCode ()I
L34:    bipush 16
L36:    iconst_1
L37:    dup
L38:    pop2
L39:    ishl
L40:    aload_0
L41:    getfield Field Dc do Ljava/lang/Object;
L44:    invokevirtual Method java/lang/Object hashCode ()I
L47:    bipush 16
L49:    iconst_1
L50:    dup
L51:    pop2
L52:    ishr
L53:    ixor
L54:    ireturn
L55:    athrow
L56:    aload_0
L57:    getfield Field Dc do Ljava/lang/Object;
L60:    ifnonnull L71
L63:    aload_0
L64:    getfield Field Dc "enum" Ljava/lang/Object;
L67:    invokevirtual Method java/lang/Object hashCode ()I
L70:    ireturn
L71:    aload_0
L72:    getfield Field Dc "enum" Ljava/lang/Object;
L75:    invokevirtual Method java/lang/Object hashCode ()I
L78:    aload_0
L79:    getfield Field Dc do Ljava/lang/Object;
L82:    invokevirtual Method java/lang/Object hashCode ()I
L85:    bipush 16
L87:    iconst_1
L88:    dup
L89:    pop2
L90:    ishl
L91:    ixor
L92:    aload_0
L93:    getfield Field Dc do Ljava/lang/Object;
L96:    invokevirtual Method java/lang/Object hashCode ()I
L99:    bipush 16
L101:   iconst_1
L102:   dup
L103:   pop2
L104:   ishr
L105:   ixor
L106:   ireturn
L107:   
        .attribute StackMap b'\x00\x05\x00\x13\x00\x00\x00\x01\x07\x00\x14\x00\x14\x00\x01\x07\x00\x02\x00\x00\x00\x37\x00\x00\x00\x01\x07\x00\x14\x00\x38\x00\x01\x07\x00\x02\x00\x00\x00\x47\x00\x01\x07\x00\x02\x00\x00'
    .end code
.end method
.end class
