.version 49 0
.class public final super synthetic DD
.super java/lang/Object
.field public static final synthetic do [I

.method public static <clinit> : ()V
    .code stack 5 locals 1
L0:     invokestatic Method oc values ()[Loc;
L3:     arraylength
L4:     newarray int
L6:     iconst_1
L7:     dup
L8:     pop2
L9:     putstatic Field DD do [I
        .catch java/lang/NoSuchFieldError from L12 to L26 using L30
L12:    getstatic Field DD do [I
L15:    getstatic Field oc this Loc;
L18:    invokevirtual Method oc ordinal ()I
L21:    iconst_1
L22:    dup
L23:    dup
L24:    pop2
L25:    iastore
L26:    goto L31
L29:    athrow
L30:    astore_0
        .catch java/lang/NoSuchFieldError from L31 to L45 using L49
L31:    getstatic Field DD do [I
L34:    getstatic Field oc try Loc;
L37:    invokevirtual Method oc ordinal ()I
L40:    iconst_2
L41:    iconst_1
L42:    dup
L43:    pop2
L44:    iastore
L45:    goto L50
L48:    athrow
L49:    astore_0
        .catch java/lang/NoSuchFieldError from L50 to L64 using L67
L50:    getstatic Field DD do [I
L53:    getstatic Field oc else Loc;
L56:    invokevirtual Method oc ordinal ()I
L59:    iconst_3
L60:    iconst_1
L61:    dup
L62:    pop2
L63:    iastore
L64:    goto L68
L67:    astore_0
        .catch java/lang/NoSuchFieldError from L68 to L82 using L85
L68:    getstatic Field DD do [I
L71:    getstatic Field oc const Loc;
L74:    invokevirtual Method oc ordinal ()I
L77:    iconst_4
L78:    iconst_1
L79:    dup
L80:    pop2
L81:    iastore
L82:    goto L86
L85:    astore_0
        .catch java/lang/NoSuchFieldError from L86 to L100 using L103
L86:    getstatic Field DD do [I
L89:    getstatic Field oc char Loc;
L92:    invokevirtual Method oc ordinal ()I
L95:    iconst_5
L96:    iconst_1
L97:    dup
L98:    pop2
L99:    iastore
L100:   goto L104
L103:   astore_0
        .catch java/lang/NoSuchFieldError from L104 to L119 using L122
L104:   getstatic Field DD do [I
L107:   getstatic Field oc null Loc;
L110:   invokevirtual Method oc ordinal ()I
L113:   bipush 6
L115:   iconst_1
L116:   dup
L117:   pop2
L118:   iastore
L119:   goto L123
L122:   astore_0
        .catch java/lang/NoSuchFieldError from L123 to L138 using L141
L123:   getstatic Field DD do [I
L126:   getstatic Field oc do Loc;
L129:   invokevirtual Method oc ordinal ()I
L132:   bipush 7
L134:   iconst_1
L135:   dup
L136:   pop2
L137:   iastore
L138:   goto L142
L141:   astore_0
        .catch java/lang/NoSuchFieldError from L142 to L157 using L160
L142:   getstatic Field DD do [I
L145:   getstatic Field oc void Loc;
L148:   invokevirtual Method oc ordinal ()I
L151:   bipush 8
L153:   iconst_1
L154:   dup
L155:   pop2
L156:   iastore
L157:   goto L161
L160:   astore_0
        .catch java/lang/NoSuchFieldError from L161 to L176 using L179
L161:   getstatic Field DD do [I
L164:   getstatic Field oc "enum" Loc;
L167:   invokevirtual Method oc ordinal ()I
L170:   bipush 9
L172:   iconst_1
L173:   dup
L174:   pop2
L175:   iastore
L176:   goto L180
L179:   astore_0
        .catch java/lang/NoSuchFieldError from L180 to L195 using L196
L180:   getstatic Field DD do [I
L183:   getstatic Field oc new Loc;
L186:   invokevirtual Method oc ordinal ()I
L189:   bipush 10
L191:   iconst_1
L192:   dup
L193:   pop2
L194:   iastore
L195:   return
L196:   astore_0
L197:   return
L198:   
        .attribute StackMap b'\x00\x15\x00\x1D\x00\x00\x00\x01\x07\x00\x1E\x00\x1E\x00\x00\x00\x01\x07\x00\x0E\x00\x1F\x00\x00\x00\x00\x00\x30\x00\x00\x00\x01\x07\x00\x1E\x00\x31\x00\x00\x00\x01\x07\x00\x0E\x00\x32\x00\x00\x00\x00\x00\x43\x00\x00\x00\x01\x07\x00\x0E\x00\x44\x00\x00\x00\x00\x00\x55\x00\x00\x00\x01\x07\x00\x0E\x00\x56\x00\x00\x00\x00\x00\x67\x00\x00\x00\x01\x07\x00\x0E\x00\x68\x00\x00\x00\x00\x00\x7A\x00\x00\x00\x01\x07\x00\x0E\x00\x7B\x00\x00\x00\x00\x00\x8D\x00\x00\x00\x01\x07\x00\x0E\x00\x8E\x00\x00\x00\x00\x00\xA0\x00\x00\x00\x01\x07\x00\x0E\x00\xA1\x00\x00\x00\x00\x00\xB3\x00\x00\x00\x01\x07\x00\x0E\x00\xB4\x00\x00\x00\x00\x00\xC4\x00\x00\x00\x01\x07\x00\x0E'
    .end code
.end method
.innerclasses
    DD fc [0] static synthetic
    oc fc [0] public static final enum
.end innerclasses
.enclosing method fc [0]
.end class
