.version 49 0
.class public final super EC
.super td
.field public final synthetic field101 LUc;
.field public final synthetic field102 LRg;

.method public method91 : (Lff;)V
    .code stack 5 locals 6
L0:     bipush 28
L2:     iconst_1
L3:     dup
L4:     pop2
L5:     istore_2
L6:     iconst_0
L7:     iconst_1
L8:     dup
L9:     pop2
L10:    dup
L11:    istore_3
L12:    bipush 28
L14:    iconst_1
L15:    dup
L16:    pop2
L17:    if_icmpge L76
L20:    iconst_0
L21:    iconst_1
L22:    dup
L23:    pop2
L24:    dup
L25:    istore 4
L27:    bipush 10
L29:    iconst_1
L30:    dup
L31:    pop2
L32:    if_icmpge L69
L35:    aload_0
L36:    getfield Field EC field102 LRg;
L39:    getfield Field Rg this [[I
L42:    iload 4
L44:    aaload
L45:    iload_3
L46:    iaload
L47:    ifeq L60
L50:    iload_2
L51:    iload_3
L52:    invokestatic Method java/lang/Math min (II)I
L55:    istore_2
L56:    goto L69
L59:    athrow
L60:    iinc 4 1
L63:    iload 4
L65:    goto L27
L68:    athrow
L69:    iinc 3 1
L72:    iload_3
L73:    goto L12
L76:    bipush 15
L78:    iconst_1
L79:    dup
L80:    pop2
L81:    iload_2
L82:    isub
L83:    dup
L84:    istore_3
L85:    ifgt L89
L88:    return
L89:    iload_3
L90:    newarray int
L92:    iconst_1
L93:    dup
L94:    pop2
L95:    astore 4
L97:    iconst_0
L98:    iconst_1
L99:    dup
L100:   pop2
L101:   dup
L102:   istore 5
L104:   iload_3
L105:   if_icmpge L126
L108:   aload 4
L110:   iload 5
L112:   bipush 27
L114:   iconst_1
L115:   dup
L116:   pop2
L117:   iinc 5 1
L120:   iastore
L121:   iload 5
L123:   goto L104
L126:   aload_0
L127:   getfield Field EC field102 LRg;
L130:   aload 4
L132:   iconst_0
L133:   iconst_1
L134:   dup
L135:   pop2
L136:   invokevirtual Method Rg method241 ([IZ)V
L139:   return
L140:   
        .attribute StackMap b'\x00\x0A\x00\x0C\x00\x04\x07\x00\x02\x07\x00\x11\x01\x01\x00\x01\x01\x00\x1B\x00\x05\x07\x00\x02\x07\x00\x11\x01\x01\x01\x00\x01\x01\x00\x3B\x00\x00\x00\x01\x07\x00\x21\x00\x3C\x00\x05\x07\x00\x02\x07\x00\x11\x01\x01\x01\x00\x00\x00\x44\x00\x00\x00\x01\x07\x00\x21\x00\x45\x00\x05\x07\x00\x02\x07\x00\x11\x01\x01\x01\x00\x00\x00\x4C\x00\x04\x07\x00\x02\x07\x00\x11\x01\x01\x00\x00\x00\x59\x00\x04\x07\x00\x02\x07\x00\x11\x01\x01\x00\x00\x00\x68\x00\x06\x07\x00\x02\x07\x00\x11\x01\x01\x07\x00\x23\x01\x00\x01\x01\x00\x7E\x00\x06\x07\x00\x02\x07\x00\x11\x01\x01\x07\x00\x23\x01\x00\x00'
    .end code
.end method

.method public <init> : (LUc;LRg;)V
    .code stack 5 locals 3
L0:     aload_2
L1:     aload_0
L2:     dup_x1
L3:     dup_x2
L4:     aload_1
L5:     putfield Field EC field101 LUc;
L8:     putfield Field EC field102 LRg;
L11:    invokespecial Method td <init> ()V
L14:    return
L15:    
    .end code
.end method
.innerclasses
    EC [0] [0]
    Uc [0] [0]
.end innerclasses
.enclosing method Uc method737 (LRg;)V
.end class
