.version 49 0
.class public final super ed
.super java/lang/Object
.implements D
.field public field701 Ljava/lang/String;
.field public static final field702 I = -1
.field public field703 LTe;
.field public field704 Ljava/util/Set;
.field public field705 Ljava/lang/String;
.field public field706 I
.field public field707 D
.field public try I
.field public field708 Ljava/util/LinkedList;
.field public new Ljava/lang/String;
.field public field709 J
.field public this Z
.field public field710 Ljava/lang/String;
.field public field711 LPc;
.field public field712 I
.field public static final field713 J = -1L

.method public method134 : ()I
    .code stack 3 locals 4
L0:     iconst_0
L1:     iconst_1
L2:     dup
L3:     pop2
L4:     istore_1
L5:     aload_0
L6:     getfield Field ed field704 Ljava/util/Set;
L9:     invokeinterface InterfaceMethod java/util/Set iterator ()Ljava/util/Iterator; 1
L14:    dup
L15:    astore_2
L16:    invokeinterface InterfaceMethod java/util/Iterator hasNext ()Z 1
L21:    ifeq L46
L24:    aload_2
L25:    invokeinterface InterfaceMethod java/util/Iterator next ()Ljava/lang/Object; 1
L30:    checkcast Uf
L33:    astore_3
L34:    iload_1
L35:    aload_3
L36:    getfield Field Uf field1349 I
L39:    iadd
L40:    istore_1
L41:    aload_2
L42:    goto L16
L45:    athrow
L46:    iload_1
L47:    ireturn
L48:    
        .attribute StackMap b'\x00\x03\x00\x10\x00\x03\x07\x00\x02\x01\x07\x00\x31\x00\x01\x07\x00\x31\x00\x2D\x00\x00\x00\x01\x07\x00\x40\x00\x2E\x00\x03\x07\x00\x02\x01\x07\x00\x31\x00\x00'
    .end code
.end method

.method public <init> : (LMd;)V
    .code stack 23 locals 2
L0:     aload_0
L1:     aload_1
L2:     dup_x1
L3:     aload_1
L4:     aload_0
L5:     dup_x1
L6:     aload_0
L7:     dup
L8:     aload_1
L9:     dup_x2
L10:    aload_1
L11:    aload_0
L12:    dup_x1
L13:    aload_1
L14:    iconst_1
L15:    aload_0
L16:    dup_x1
L17:    ldc2_w -1L
L20:    iconst_m1
L21:    aload_0
L22:    dup_x1
L23:    invokespecial Method java/lang/Object <init> ()V
L26:    iconst_1
L27:    dup
L28:    pop2
L29:    putfield Field ed field712 I
L32:    putfield Field ed field709 J
L35:    iconst_1
L36:    dup
L37:    pop2
L38:    putfield Field ed this Z
L41:    invokevirtual Method Md new ()Ljava/lang/String;
L44:    putfield Field ed field701 Ljava/lang/String;
L47:    invokevirtual Method Md method886 ()I
L50:    putfield Field ed try I
L53:    invokevirtual Method Md method889 ()I
L56:    putfield Field ed field712 I
L59:    invokestatic Method Pc values ()[LPc;
L62:    aload_1
L63:    invokevirtual Method Md method886 ()I
L66:    aaload
L67:    putfield Field ed field711 LPc;
L70:    invokevirtual Method Md method898 ()Ljava/util/Set;
L73:    putfield Field ed field704 Ljava/util/Set;
L76:    invokevirtual Method Md new ()Ljava/lang/String;
L79:    putfield Field ed new Ljava/lang/String;
L82:    invokevirtual Method Md method886 ()I
L85:    putfield Field ed field706 I
L88:    invokevirtual Method Md method892 ()Z
L91:    ifeq L102
L94:    aload_0
L95:    aload_1
L96:    invokevirtual Method Md new ()Ljava/lang/String;
L99:    putfield Field ed field710 Ljava/lang/String;
L102:   aload_1
L103:   invokevirtual Method Md method892 ()Z
L106:   ifeq L117
L109:   aload_0
L110:   aload_1
L111:   invokevirtual Method Md new ()Ljava/lang/String;
L114:   putfield Field ed field705 Ljava/lang/String;
L117:   return
L118:   
        .attribute StackMap b'\x00\x02\x00\x66\x00\x02\x07\x00\x02\x07\x00\x4F\x00\x00\x00\x75\x00\x02\x07\x00\x02\x07\x00\x4F\x00\x00'
    .end code
    .exceptions java/io/IOException
.end method

.method public <init> : (Ljava/lang/String;ILjava/lang/String;)V
    .code stack 13 locals 4
L0:     iconst_0
L1:     aload_0
L2:     dup_x1
L3:     aload_1
L4:     getstatic Field Pc field373 LPc;
L7:     new java/util/LinkedHashSet
L10:    iload_2
L11:    dup_x1
L12:    dup
L13:    pop2
L14:    dup
L15:    invokespecial Method java/util/LinkedHashSet <init> ()V
L18:    aload_3
L19:    iconst_0
L20:    iconst_1
L21:    dup
L22:    pop2
L23:    ldc2_w -1L
L26:    aconst_null
L27:    dup
L28:    invokespecial Method ed <init> (Ljava/lang/String;LPc;ILjava/util/Set;Ljava/lang/String;IJLjava/lang/String;Ljava/lang/String;)V
L31:    iconst_1
L32:    dup
L33:    pop2
L34:    putfield Field ed this Z
L37:    return
L38:    
    .end code
.end method

.method public <init> : (Ljava/lang/String;LPc;ILjava/util/Set;Ljava/lang/String;IJLjava/lang/String;Ljava/lang/String;)V
    .code stack 28 locals 11
L0:     aload 10
L2:     aload_0
L3:     dup_x1
L4:     aload 9
L6:     lload 7
L8:     aload_0
L9:     dup_x2
L10:    iload 6
L12:    aload 5
L14:    aload_0
L15:    dup_x1
L16:    aload 4
L18:    iload_3
L19:    aload_0
L20:    dup_x1
L21:    aload_2
L22:    aload_1
L23:    aload_0
L24:    dup_x1
L25:    iconst_1
L26:    ldc2_w -1L
L29:    aload_0
L30:    dup_x2
L31:    iconst_m1
L32:    aload_0
L33:    invokespecial Method java/lang/Object <init> ()V
L36:    iconst_1
L37:    dup
L38:    pop2
L39:    putfield Field ed field712 I
L42:    putfield Field ed field709 J
L45:    iconst_1
L46:    dup
L47:    pop2
L48:    putfield Field ed this Z
L51:    putfield Field ed field701 Ljava/lang/String;
L54:    putfield Field ed field711 LPc;
L57:    putfield Field ed field712 I
L60:    putfield Field ed field704 Ljava/util/Set;
L63:    putfield Field ed new Ljava/lang/String;
L66:    putfield Field ed field706 I
L69:    putfield Field ed field709 J
L72:    putfield Field ed field710 Ljava/lang/String;
L75:    putfield Field ed field705 Ljava/lang/String;
L78:    return
L79:    
    .end code
.end method

.method public method94 : ()Z
    .code stack 4 locals 1
L0:     aload_0
L1:     getfield Field ed field712 I
L4:     iconst_m1
L5:     iconst_1
L6:     dup
L7:     pop2
L8:     if_icmpne L17
L11:    iconst_1
L12:    dup
L13:    dup
L14:    pop2
L15:    ireturn
L16:    athrow
L17:    iconst_0
L18:    iconst_1
L19:    dup
L20:    pop2
L21:    ireturn
L22:    
        .attribute StackMap b'\x00\x02\x00\x10\x00\x00\x00\x01\x07\x00\x40\x00\x11\x00\x01\x07\x00\x02\x00\x00'
    .end code
.end method

.method public method227 : ()Z
    .code stack 5 locals 3
L0:     aload_0
L1:     getfield Field ed field708 Ljava/util/LinkedList;
L4:     ifnonnull L21
L7:     new java/util/LinkedList
L10:    aload_0
L11:    dup_x1
L12:    dup
L13:    pop2
L14:    dup
L15:    invokespecial Method java/util/LinkedList <init> ()V
L18:    putfield Field ed field708 Ljava/util/LinkedList;
L21:    invokestatic Method OC method1015 ()D
L24:    dup2
L25:    dstore_1
L26:    aload_0
L27:    getfield Field ed field707 D
L30:    dcmpg
L31:    ifge L40
L34:    iconst_0
L35:    iconst_1
L36:    dup
L37:    pop2
L38:    ireturn
L39:    athrow
L40:    aload_0
L41:    getfield Field ed field708 Ljava/util/LinkedList;
L44:    invokevirtual Method java/util/LinkedList isEmpty ()Z
L47:    ifne L85
L50:    aload_0
L51:    getfield Field ed field708 Ljava/util/LinkedList;
L54:    invokevirtual Method java/util/LinkedList getFirst ()Ljava/lang/Object;
L57:    checkcast java/lang/Double
L60:    invokevirtual Method java/lang/Double doubleValue ()D
L63:    ldc2_w 5e0
L66:    dadd
L67:    dload_1
L68:    dcmpg
L69:    ifge L85
L72:    aload_0
L73:    dup
L74:    getfield Field ed field708 Ljava/util/LinkedList;
L77:    invokevirtual Method java/util/LinkedList removeFirst ()Ljava/lang/Object;
L80:    pop
L81:    goto L41
L84:    athrow
L85:    aload_0
L86:    getfield Field ed field708 Ljava/util/LinkedList;
L89:    invokevirtual Method java/util/LinkedList size ()I
L92:    i2d
L93:    ldc2_w 8e0
L96:    dcmpg
L97:    ifge L118
L100:   iconst_1
L101:   aload_0
L102:   getfield Field ed field708 Ljava/util/LinkedList;
L105:   invokestatic Method OC method1015 ()D
L108:   invokestatic Method java/lang/Double valueOf (D)Ljava/lang/Double;
L111:   invokevirtual Method java/util/LinkedList addLast (Ljava/lang/Object;)V
L114:   iconst_1
L115:   dup
L116:   pop2
L117:   ireturn
L118:   aload_0
L119:   dload_1
L120:   ldc2_w 3e1
L123:   dadd
L124:   putfield Field ed field707 D
L127:   iconst_0
L128:   iconst_1
L129:   dup
L130:   pop2
L131:   ireturn
L132:   
        .attribute StackMap b'\x00\x07\x00\x15\x00\x01\x07\x00\x02\x00\x00\x00\x27\x00\x00\x00\x01\x07\x00\x40\x00\x28\x00\x02\x07\x00\x02\x03\x00\x00\x00\x29\x00\x02\x07\x00\x02\x03\x00\x01\x07\x00\x02\x00\x54\x00\x00\x00\x01\x07\x00\x40\x00\x55\x00\x02\x07\x00\x02\x03\x00\x00\x00\x76\x00\x02\x07\x00\x02\x03\x00\x00'
    .end code
.end method

.method public <init> : (LPc;)V
    .code stack 11 locals 2
L0:     aload_0
L1:     aload_1
L2:     invokestatic Method JB method817 (LPc;)Ljava/lang/String;
L5:     aload_1
L6:     iconst_m1
L7:     iconst_1
L8:     dup
L9:     pop2
L10:    new java/util/LinkedHashSet
L13:    dup
L14:    invokespecial Method java/util/LinkedHashSet <init> ()V
L17:    ldc "anon"
L19:    iconst_0
L20:    iconst_1
L21:    dup
L22:    pop2
L23:    ldc2_w -1L
L26:    aconst_null
L27:    dup
L28:    invokespecial Method ed <init> (Ljava/lang/String;LPc;ILjava/util/Set;Ljava/lang/String;IJLjava/lang/String;Ljava/lang/String;)V
L31:    return
L32:    
    .end code
.end method

.method public method384 : (LAC;)V
    .code stack 16 locals 2
L0:     aload_0
L1:     aload_1
L2:     dup_x1
L3:     aload_1
L4:     aload_0
L5:     dup_x1
L6:     aload_0
L7:     aload_1
L8:     dup_x1
L9:     aload_1
L10:    aload_0
L11:    dup_x1
L12:    aload_0
L13:    aload_1
L14:    dup_x1
L15:    aload_0
L16:    getfield Field ed field701 Ljava/lang/String;
L19:    invokevirtual Method AC method683 (Ljava/lang/String;)V
L22:    getfield Field ed try I
L25:    invokevirtual Method AC method691 (I)V
L28:    getfield Field ed field712 I
L31:    invokevirtual Method AC method674 (I)V
L34:    getfield Field ed field711 LPc;
L37:    invokevirtual Method Pc ordinal ()I
L40:    invokevirtual Method AC method691 (I)V
L43:    getfield Field ed field704 Ljava/util/Set;
L46:    invokevirtual Method AC method686 (Ljava/util/Set;)V
L49:    getfield Field ed new Ljava/lang/String;
L52:    invokevirtual Method AC method683 (Ljava/lang/String;)V
L55:    getfield Field ed field706 I
L58:    invokevirtual Method AC method691 (I)V
L61:    getfield Field ed field710 Ljava/lang/String;
L64:    ifnull L75
L67:    iconst_1
L68:    dup
L69:    dup
L70:    pop2
L71:    goto L79
L74:    athrow
L75:    iconst_0
L76:    iconst_1
L77:    dup
L78:    pop2
L79:    invokevirtual Method AC method684 (Z)V
L82:    aload_0
L83:    getfield Field ed field710 Ljava/lang/String;
L86:    ifnull L97
L89:    aload_1
L90:    aload_0
L91:    getfield Field ed field710 Ljava/lang/String;
L94:    invokevirtual Method AC method683 (Ljava/lang/String;)V
L97:    aload_1
L98:    aload_0
L99:    getfield Field ed field705 Ljava/lang/String;
L102:   ifnull L113
L105:   iconst_1
L106:   dup
L107:   dup
L108:   pop2
L109:   goto L117
L112:   athrow
L113:   iconst_0
L114:   iconst_1
L115:   dup
L116:   pop2
L117:   invokevirtual Method AC method684 (Z)V
L120:   aload_0
L121:   getfield Field ed field705 Ljava/lang/String;
L124:   ifnull L135
L127:   aload_1
L128:   aload_0
L129:   getfield Field ed field705 Ljava/lang/String;
L132:   invokevirtual Method AC method683 (Ljava/lang/String;)V
L135:   return
L136:   
        .attribute StackMap b'\x00\x08\x00\x4A\x00\x00\x00\x01\x07\x00\x40\x00\x4B\x00\x02\x07\x00\x02\x07\x00\xB4\x00\x01\x07\x00\xB4\x00\x4F\x00\x02\x07\x00\x02\x07\x00\xB4\x00\x02\x07\x00\xB4\x01\x00\x61\x00\x02\x07\x00\x02\x07\x00\xB4\x00\x00\x00\x70\x00\x00\x00\x01\x07\x00\x40\x00\x71\x00\x02\x07\x00\x02\x07\x00\xB4\x00\x01\x07\x00\xB4\x00\x75\x00\x02\x07\x00\x02\x07\x00\xB4\x00\x02\x07\x00\xB4\x01\x00\x87\x00\x02\x07\x00\x02\x07\x00\xB4\x00\x00'
    .end code
    .exceptions java/io/IOException
.end method
.innerclasses
    Pc JB [0] public static final enum
.end innerclasses
.end class
