.version 49 0
.class public final super enum EF
.super java/lang/Enum
.field private static final synthetic void [LEF;
.field public static final enum try LEF;
.field public static final enum const LEF;
.field public static final enum new LEF;
.field public static final enum null LEF;
.field public static final enum this LEF;
.field public static final enum char LEF;
.field public static final enum else LEF;
.field public static final enum "enum" LEF;
.field public static final enum do LEF;

.method public static values : ()[LEF;
    .code stack 1 locals 0
L0:     getstatic Field EF void [LEF;
L3:     invokevirtual Method [LEF; clone ()Ljava/lang/Object;
L6:     checkcast [LEF;
L9:     areturn
L10:    
    .end code
.end method

.method private <init> : (Ljava/lang/String;I)V
    .code stack 3 locals 3
L0:     aload_0
L1:     aload_1
L2:     iload_2
L3:     invokespecial Method java/lang/Enum <init> (Ljava/lang/String;I)V
L6:     return
L7:     
    .end code
.end method

.method public static valueOf : (Ljava/lang/String;)LEF;
    .code stack 2 locals 1
L0:     ldc Class EF
L2:     aload_0
L3:     invokestatic Method java/lang/Enum valueOf (Ljava/lang/Class;Ljava/lang/String;)Ljava/lang/Enum;
L6:     checkcast EF
L9:     areturn
L10:    
    .end code
.end method

.method public static <clinit> : ()V
    .code stack 6 locals 0
L0:     new EF
L3:     dup
L4:     ldc "NEXT_PIECE"
L6:     iconst_0
L7:     iconst_1
L8:     dup
L9:     pop2
L10:    invokespecial Method EF <init> (Ljava/lang/String;I)V
L13:    putstatic Field EF try LEF;
L16:    new EF
L19:    dup
L20:    ldc "COMBO"
L22:    iconst_1
L23:    dup
L24:    dup
L25:    pop2
L26:    invokespecial Method EF <init> (Ljava/lang/String;I)V
L29:    putstatic Field EF new LEF;
L32:    new EF
L35:    dup
L36:    ldc "REMAINING_LINES"
L38:    iconst_2
L39:    iconst_1
L40:    dup
L41:    pop2
L42:    invokespecial Method EF <init> (Ljava/lang/String;I)V
L45:    putstatic Field EF else LEF;
L48:    new EF
L51:    dup
L52:    ldc "PENDING_LINES"
L54:    iconst_3
L55:    iconst_1
L56:    dup
L57:    pop2
L58:    invokespecial Method EF <init> (Ljava/lang/String;I)V
L61:    putstatic Field EF null LEF;
L64:    new EF
L67:    dup
L68:    ldc "SPEED_O_METER"
L70:    iconst_4
L71:    iconst_1
L72:    dup
L73:    pop2
L74:    invokespecial Method EF <init> (Ljava/lang/String;I)V
L77:    putstatic Field EF char LEF;
L80:    new EF
L83:    dup
L84:    ldc "PLAY_DURATION"
L86:    iconst_5
L87:    iconst_1
L88:    dup
L89:    pop2
L90:    invokespecial Method EF <init> (Ljava/lang/String;I)V
L93:    putstatic Field EF this LEF;
L96:    new EF
L99:    dup
L100:   ldc "CLEARED_LINES"
L102:   bipush 6
L104:   iconst_1
L105:   dup
L106:   pop2
L107:   invokespecial Method EF <init> (Ljava/lang/String;I)V
L110:   putstatic Field EF const LEF;
L113:   new EF
L116:   dup
L117:   ldc "CLEARED_TETRII"
L119:   bipush 7
L121:   iconst_1
L122:   dup
L123:   pop2
L124:   invokespecial Method EF <init> (Ljava/lang/String;I)V
L127:   putstatic Field EF "enum" LEF;
L130:   new EF
L133:   dup
L134:   ldc "SENT_LINES"
L136:   bipush 8
L138:   iconst_1
L139:   dup
L140:   pop2
L141:   invokespecial Method EF <init> (Ljava/lang/String;I)V
L144:   putstatic Field EF do LEF;
L147:   bipush 9
L149:   iconst_1
L150:   dup
L151:   pop2
L152:   anewarray EF
L155:   iconst_1
L156:   dup
L157:   pop2
L158:   dup
L159:   iconst_0
L160:   iconst_1
L161:   dup
L162:   pop2
L163:   getstatic Field EF try LEF;
L166:   aastore
L167:   dup
L168:   iconst_1
L169:   dup
L170:   dup
L171:   pop2
L172:   getstatic Field EF new LEF;
L175:   aastore
L176:   dup
L177:   iconst_2
L178:   iconst_1
L179:   dup
L180:   pop2
L181:   getstatic Field EF else LEF;
L184:   aastore
L185:   dup
L186:   iconst_3
L187:   iconst_1
L188:   dup
L189:   pop2
L190:   getstatic Field EF null LEF;
L193:   aastore
L194:   dup
L195:   iconst_4
L196:   iconst_1
L197:   dup
L198:   pop2
L199:   getstatic Field EF char LEF;
L202:   aastore
L203:   dup
L204:   iconst_5
L205:   iconst_1
L206:   dup
L207:   pop2
L208:   getstatic Field EF this LEF;
L211:   aastore
L212:   dup
L213:   bipush 6
L215:   iconst_1
L216:   dup
L217:   pop2
L218:   getstatic Field EF const LEF;
L221:   aastore
L222:   dup
L223:   bipush 7
L225:   iconst_1
L226:   dup
L227:   pop2
L228:   getstatic Field EF "enum" LEF;
L231:   aastore
L232:   dup
L233:   bipush 8
L235:   iconst_1
L236:   dup
L237:   pop2
L238:   getstatic Field EF do LEF;
L241:   aastore
L242:   putstatic Field EF void [LEF;
L245:   return
L246:   
    .end code
.end method
.innerclasses
    EF eb [0] public static final enum
.end innerclasses
.end class
