.version 49 0
.class public final super enum eg
.super fE

.method public method302 : (F)Ljava/lang/String;
    .code stack 6 locals 3
L0:     fload_1
L1:     ldc 4e0f
L3:     fmul
L4:     invokestatic Method java/lang/Math round (F)I
L7:     istore_2
L8:     new java/lang/StringBuilder
L11:    dup
L12:    invokespecial Method java/lang/StringBuilder <init> ()V
L15:    iconst_0
L16:    iload_2
L17:    iconst_4
L18:    iconst_1
L19:    dup
L20:    pop2
L21:    idiv
L22:    invokestatic Method java/lang/Integer toString (I)Ljava/lang/String;
L25:    invokevirtual Method java/lang/StringBuilder insert (ILjava/lang/String;)Ljava/lang/StringBuilder;
L28:    iconst_4
L29:    iconst_1
L30:    dup
L31:    pop2
L32:    anewarray java/lang/String
L35:    iconst_1
L36:    dup
L37:    pop2
L38:    dup
L39:    iconst_0
L40:    iconst_1
L41:    dup
L42:    pop2
L43:    ldc "   "
L45:    aastore
L46:    dup
L47:    iconst_1
L48:    dup
L49:    dup
L50:    pop2
L51:    ldc "\u00BC"
L53:    aastore
L54:    dup
L55:    iconst_2
L56:    iconst_1
L57:    dup
L58:    pop2
L59:    ldc "\u00BD"
L61:    aastore
L62:    dup
L63:    iconst_3
L64:    iconst_1
L65:    dup
L66:    pop2
L67:    ldc "\u00BE"
L69:    aastore
L70:    iload_2
L71:    iconst_4
L72:    iconst_1
L73:    dup
L74:    pop2
L75:    irem
L76:    aaload
L77:    invokevirtual Method java/lang/StringBuilder append (Ljava/lang/String;)Ljava/lang/StringBuilder;
L80:    invokevirtual Method java/lang/StringBuilder toString ()Ljava/lang/String;
L83:    areturn
L84:    
    .end code
.end method

.method public method303 : (LRg;F)Z
    .code stack 3 locals 3
L0:     aload_1
L1:     getfield Field Rg field215 F
L4:     fload_2
L5:     fcmpl
L6:     ifle L15
L9:     iconst_1
L10:    dup
L11:    dup
L12:    pop2
L13:    ireturn
L14:    athrow
L15:    iconst_0
L16:    iconst_1
L17:    dup
L18:    pop2
L19:    ireturn
L20:    
        .attribute StackMap b'\x00\x02\x00\x0E\x00\x00\x00\x01\x07\x00\x3A\x00\x0F\x00\x03\x07\x00\x02\x07\x00\x34\x02\x00\x00'
    .end code
.end method

.method public <init> : (Ljava/lang/String;IZ)V
    .code stack 5 locals 4
L0:     aload_0
L1:     aload_1
L2:     iload_2
L3:     iload_3
L4:     aconst_null
L5:     invokespecial Method fE <init> (Ljava/lang/String;IZLXe;)V
L8:     return
L9:     
    .end code
.end method

.method public method305 : (LRg;)Ljava/lang/String;
    .code stack 2 locals 2
L0:     aload_0
L1:     aload_1
L2:     getfield Field Rg field215 F
L5:     invokevirtual Method eg method304 (F)Ljava/lang/String;
L8:     areturn
L9:     
    .end code
.end method

.method public method304 : (F)Ljava/lang/String;
    .code stack 6 locals 3
L0:     fload_1
L1:     ldc 4e0f
L3:     fmul
L4:     invokestatic Method java/lang/Math round (F)I
L7:     istore_2
L8:     new java/lang/StringBuilder
L11:    dup
L12:    invokespecial Method java/lang/StringBuilder <init> ()V
L15:    iconst_0
L16:    iload_2
L17:    iconst_4
L18:    iconst_1
L19:    dup
L20:    pop2
L21:    idiv
L22:    invokestatic Method java/lang/Integer toString (I)Ljava/lang/String;
L25:    invokevirtual Method java/lang/StringBuilder insert (ILjava/lang/String;)Ljava/lang/StringBuilder;
L28:    iconst_4
L29:    iconst_1
L30:    dup
L31:    pop2
L32:    anewarray java/lang/String
L35:    iconst_1
L36:    dup
L37:    pop2
L38:    dup
L39:    iconst_0
L40:    iconst_1
L41:    dup
L42:    pop2
L43:    ldc ""
L45:    aastore
L46:    dup
L47:    iconst_1
L48:    dup
L49:    dup
L50:    pop2
L51:    ldc "\u00BC"
L53:    aastore
L54:    dup
L55:    iconst_2
L56:    iconst_1
L57:    dup
L58:    pop2
L59:    ldc "\u00BD"
L61:    aastore
L62:    dup
L63:    iconst_3
L64:    iconst_1
L65:    dup
L66:    pop2
L67:    ldc "\u00BE"
L69:    aastore
L70:    iload_2
L71:    iconst_4
L72:    iconst_1
L73:    dup
L74:    pop2
L75:    irem
L76:    aaload
L77:    invokevirtual Method java/lang/StringBuilder append (Ljava/lang/String;)Ljava/lang/StringBuilder;
L80:    ldc " tetris"
L82:    invokevirtual Method java/lang/StringBuilder append (Ljava/lang/String;)Ljava/lang/StringBuilder;
L85:    invokevirtual Method java/lang/StringBuilder toString ()Ljava/lang/String;
L88:    astore_2
L89:    fload_1
L90:    ldc 4e0f
L92:    fmul
L93:    invokestatic Method java/lang/Math round (F)I
L96:    iconst_4
L97:    iconst_1
L98:    dup
L99:    pop2
L100:   if_icmpeq L124
L103:   new java/lang/StringBuilder
L106:   dup
L107:   invokespecial Method java/lang/StringBuilder <init> ()V
L110:   iconst_0
L111:   aload_2
L112:   invokevirtual Method java/lang/StringBuilder insert (ILjava/lang/String;)Ljava/lang/StringBuilder;
L115:   ldc "es"
L117:   invokevirtual Method java/lang/StringBuilder append (Ljava/lang/String;)Ljava/lang/StringBuilder;
L120:   invokevirtual Method java/lang/StringBuilder toString ()Ljava/lang/String;
L123:   astore_2
L124:   aload_2
L125:   areturn
L126:   
        .attribute StackMap b'\x00\x01\x00\x7C\x00\x03\x07\x00\x02\x02\x07\x00\x21\x00\x00'
    .end code
.end method
.innerclasses
    eg [0] [0] static enum
    Xe [0] [0] static enum
.end innerclasses
.enclosing method fE [0]
.end class
