.version 49 0
.class public final super FB
.super java/lang/Object
.implements h
.field public final synthetic field1575 LCC;

.method public <init> : (LCC;)V
    .code stack 3 locals 2
L0:     aload_0
L1:     dup
L2:     aload_1
L3:     putfield Field FB field1575 LCC;
L6:     invokespecial Method java/lang/Object <init> ()V
L9:     return
L10:    
    .end code
.end method

.method public method728 : (LgB;)V
    .code stack 7 locals 5
L0:     aconst_null
L1:     astore_2
L2:     aload_0
L3:     getfield Field FB field1575 LCC;
L6:     invokestatic Method CC this (LCC;)Ljava/util/HashMap;
L9:     invokevirtual Method java/util/HashMap entrySet ()Ljava/util/Set;
L12:    invokeinterface InterfaceMethod java/util/Set iterator ()Ljava/util/Iterator; 1
L17:    astore_3
L18:    aload_3
L19:    invokeinterface InterfaceMethod java/util/Iterator hasNext ()Z 1
L24:    ifeq L74
L27:    aload_3
L28:    invokeinterface InterfaceMethod java/util/Iterator next ()Ljava/lang/Object; 1
L33:    checkcast java/util/Map$Entry
L36:    dup
L37:    astore 4
L39:    invokeinterface InterfaceMethod java/util/Map$Entry getValue ()Ljava/lang/Object; 1
L44:    checkcast Tg
L47:    invokevirtual Method Tg method227 ()Z
L50:    ifeq L18
L53:    aload 4
L55:    invokeinterface InterfaceMethod java/util/Map$Entry getKey ()Ljava/lang/Object; 1
L60:    checkcast java/lang/Integer
L63:    invokevirtual Method java/lang/Integer intValue ()I
L66:    invokestatic Method GF method793 (I)Leb;
L69:    astore_2
L70:    goto L18
L73:    athrow
L74:    iconst_m1
L75:    iconst_1
L76:    dup
L77:    pop2
L78:    istore_3
L79:    aload_0
L80:    getfield Field FB field1575 LCC;
L83:    invokestatic Method CC method156 (LCC;)LzD;
L86:    invokevirtual Method zD method183 ()I
L89:    dup
L90:    istore 4
L92:    aload_0
L93:    getfield Field FB field1575 LCC;
L96:    invokestatic Method CC method156 (LCC;)LzD;
L99:    invokevirtual Method zD method247 ()I
L102:   if_icmpne L114
L105:   ldc 2147483647
L107:   istore 4
L109:   aload_0
L110:   goto L131
L113:   athrow
L114:   iload 4
L116:   bipush 10
L118:   iconst_1
L119:   dup
L120:   pop2
L121:   imul
L122:   bipush 50
L124:   iconst_1
L125:   dup
L126:   pop2
L127:   iadd
L128:   istore 4
L130:   aload_0
L131:   getfield Field FB field1575 LCC;
L134:   aload_0
L135:   getfield Field FB field1575 LCC;
L138:   invokestatic Method CC method147 (LCC;)Lnf;
L141:   invokevirtual Method nf method426 ()Ljava/lang/String;
L144:   aload_2
L145:   aload_0
L146:   getfield Field FB field1575 LCC;
L149:   invokestatic Method CC method167 (LCC;)LPg;
L152:   invokevirtual Method Pg method227 ()Z
L155:   iconst_0
L156:   iconst_1
L157:   dup
L158:   pop2
L159:   iload_3
L160:   iload 4
L162:   invokevirtual Method CC method164 (Ljava/lang/String;Leb;ZZII)V
L165:   return
L166:   
        .attribute StackMap b'\x00\x06\x00\x12\x00\x04\x07\x00\x02\x07\x00\x2D\x07\x00\x2F\x07\x00\x31\x00\x00\x00\x49\x00\x00\x00\x01\x07\x00\x52\x00\x4A\x00\x04\x07\x00\x02\x07\x00\x2D\x07\x00\x2F\x07\x00\x31\x00\x00\x00\x71\x00\x00\x00\x01\x07\x00\x52\x00\x72\x00\x05\x07\x00\x02\x07\x00\x2D\x07\x00\x2F\x01\x01\x00\x00\x00\x83\x00\x05\x07\x00\x02\x07\x00\x2D\x07\x00\x2F\x01\x01\x00\x01\x07\x00\x02'
    .end code
.end method
.innerclasses
    FB [0] [0]
    java/util/Map$Entry java/util/Map Entry public static interface abstract
.end innerclasses
.enclosing method CC new ()Lqc;
.end class
