.version 49 0
.class public final super fc
.super java/lang/Object
.implements D
.field public field873 LsE;
.field public field874 Led;
.field public field875 Led;
.field public field876 Loc;

.method public <init> : (Led;Loc;)V
    .code stack 4 locals 3
L0:     aload_0
L1:     invokespecial Method java/lang/Object <init> ()V
L4:     getstatic Field DD field1786 [I
L7:     aload_2
L8:     invokevirtual Method oc ordinal ()I
L11:    iaload
L12:    tableswitch 1
            L56
            L56
            L56
            L56
            L56
            L56
            L56
            default : L60
L56:    goto L68
L59:    athrow
L60:    new java/lang/RuntimeException
L63:    dup
L64:    invokespecial Method java/lang/RuntimeException <init> ()V
L67:    athrow
L68:    aload_0
L69:    aload_2
L70:    aload_0
L71:    aload_1
L72:    putfield Field fc field874 Led;
L75:    putfield Field fc field876 Loc;
L78:    return
L79:    
        .attribute StackMap b'\x00\x04\x00\x38\x00\x03\x07\x00\x02\x07\x00\x20\x07\x00\x0A\x00\x00\x00\x3B\x00\x00\x00\x01\x07\x00\x22\x00\x3C\x00\x03\x07\x00\x02\x07\x00\x20\x07\x00\x0A\x00\x00\x00\x44\x00\x03\x07\x00\x02\x07\x00\x20\x07\x00\x0A\x00\x00'
    .end code
.end method

.method public <init> : (Led;Loc;Led;LsE;)V
    .code stack 8 locals 5
L0:     aload_0
L1:     invokespecial Method java/lang/Object <init> ()V
L4:     getstatic Field DD field1786 [I
L7:     aload_2
L8:     invokevirtual Method oc ordinal ()I
L11:    iaload
L12:    lookupswitch
            10 : L32
            default : L36
L32:    goto L44
L35:    athrow
L36:    new java/lang/RuntimeException
L39:    dup
L40:    invokespecial Method java/lang/RuntimeException <init> ()V
L43:    athrow
L44:    aload_0
L45:    aload 4
L47:    aload_3
L48:    aload_0
L49:    dup_x1
L50:    aload_2
L51:    aload_0
L52:    aload_1
L53:    putfield Field fc field874 Led;
L56:    putfield Field fc field876 Loc;
L59:    putfield Field fc field875 Led;
L62:    putfield Field fc field873 LsE;
L65:    return
L66:    
        .attribute StackMap b'\x00\x04\x00\x20\x00\x05\x07\x00\x02\x07\x00\x20\x07\x00\x0A\x07\x00\x20\x07\x00\x2C\x00\x00\x00\x23\x00\x00\x00\x01\x07\x00\x22\x00\x24\x00\x05\x07\x00\x02\x07\x00\x20\x07\x00\x0A\x07\x00\x20\x07\x00\x2C\x00\x00\x00\x2C\x00\x05\x07\x00\x02\x07\x00\x20\x07\x00\x0A\x07\x00\x20\x07\x00\x2C\x00\x00'
    .end code
.end method

.method public <init> : (Led;Loc;Led;)V
    .code stack 6 locals 4
L0:     aload_0
L1:     invokespecial Method java/lang/Object <init> ()V
L4:     getstatic Field DD field1786 [I
L7:     aload_2
L8:     invokevirtual Method oc ordinal ()I
L11:    iaload
L12:    lookupswitch
            8 : L40
            9 : L40
            default : L44
L40:    goto L52
L43:    athrow
L44:    new java/lang/RuntimeException
L47:    dup
L48:    invokespecial Method java/lang/RuntimeException <init> ()V
L51:    athrow
L52:    aload_0
L53:    aload_3
L54:    aload_2
L55:    aload_0
L56:    dup_x1
L57:    aload_1
L58:    putfield Field fc field874 Led;
L61:    putfield Field fc field876 Loc;
L64:    putfield Field fc field875 Led;
L67:    return
L68:    
        .attribute StackMap b'\x00\x04\x00\x28\x00\x04\x07\x00\x02\x07\x00\x20\x07\x00\x0A\x07\x00\x20\x00\x00\x00\x2B\x00\x00\x00\x01\x07\x00\x22\x00\x2C\x00\x04\x07\x00\x02\x07\x00\x20\x07\x00\x0A\x07\x00\x20\x00\x00\x00\x34\x00\x04\x07\x00\x02\x07\x00\x20\x07\x00\x0A\x07\x00\x20\x00\x00'
    .end code
.end method

.method public method384 : (LAC;)V
    .code stack 6 locals 2
L0:     aload_0
L1:     aload_1
L2:     dup_x1
L3:     aload_1
L4:     aload_0
L5:     dup_x1
L6:     getfield Field fc field876 Loc;
L9:     invokevirtual Method oc ordinal ()I
L12:    invokevirtual Method AC method691 (I)V
L15:    getfield Field fc field874 Led;
L18:    getfield Field ed try I
L21:    invokevirtual Method AC method691 (I)V
L24:    getfield Field fc field875 Led;
L27:    ifnull L38
L30:    iconst_1
L31:    dup
L32:    dup
L33:    pop2
L34:    goto L42
L37:    athrow
L38:    iconst_0
L39:    iconst_1
L40:    dup
L41:    pop2
L42:    invokevirtual Method AC method684 (Z)V
L45:    aload_0
L46:    getfield Field fc field875 Led;
L49:    ifnull L63
L52:    aload_1
L53:    aload_0
L54:    getfield Field fc field875 Led;
L57:    getfield Field ed try I
L60:    invokevirtual Method AC method691 (I)V
L63:    aload_1
L64:    aload_0
L65:    getfield Field fc field873 LsE;
L68:    ifnull L79
L71:    iconst_1
L72:    dup
L73:    dup
L74:    pop2
L75:    goto L83
L78:    athrow
L79:    iconst_0
L80:    iconst_1
L81:    dup
L82:    pop2
L83:    invokevirtual Method AC method684 (Z)V
L86:    aload_0
L87:    getfield Field fc field873 LsE;
L90:    ifnull L104
L93:    aload_1
L94:    aload_0
L95:    getfield Field fc field873 LsE;
L98:    invokevirtual Method sE ordinal ()I
L101:   invokevirtual Method AC method691 (I)V
L104:   return
L105:   
        .attribute StackMap b'\x00\x08\x00\x25\x00\x00\x00\x01\x07\x00\x22\x00\x26\x00\x02\x07\x00\x02\x07\x00\x37\x00\x01\x07\x00\x37\x00\x2A\x00\x02\x07\x00\x02\x07\x00\x37\x00\x02\x07\x00\x37\x01\x00\x3F\x00\x02\x07\x00\x02\x07\x00\x37\x00\x00\x00\x4E\x00\x00\x00\x01\x07\x00\x22\x00\x4F\x00\x02\x07\x00\x02\x07\x00\x37\x00\x01\x07\x00\x37\x00\x53\x00\x02\x07\x00\x02\x07\x00\x37\x00\x02\x07\x00\x37\x01\x00\x68\x00\x02\x07\x00\x02\x07\x00\x37\x00\x00'
    .end code
    .exceptions java/io/IOException
.end method

.method public <init> : (LMd;)V
    .code stack 5 locals 7
L0:     aload_0
L1:     dup
L2:     invokespecial Method java/lang/Object <init> ()V
L5:     invokestatic Method oc values ()[Loc;
L8:     aload_1
L9:     dup_x2
L10:    dup_x2
L11:    invokevirtual Method Md method886 ()I
L14:    aaload
L15:    putfield Field fc field876 Loc;
L18:    invokevirtual Method Md method886 ()I
L21:    istore_2
L22:    invokevirtual Method Md method892 ()Z
L25:    istore_3
L26:    iconst_0
L27:    iconst_1
L28:    dup
L29:    pop2
L30:    istore 4
L32:    iload_3
L33:    ifeq L42
L36:    aload_1
L37:    invokevirtual Method Md method886 ()I
L40:    istore 4
L42:    aload_1
L43:    invokevirtual Method Md method892 ()Z
L46:    istore 5
L48:    iconst_0
L49:    iconst_1
L50:    dup
L51:    pop2
L52:    istore 6
L54:    iload 5
L56:    ifeq L65
L59:    aload_1
L60:    invokevirtual Method Md method886 ()I
L63:    istore 6
L65:    aload_0
L66:    getstatic Field Kc field1931 LKc;
L69:    iload_2
L70:    invokevirtual Method Kc method856 (I)Led;
L73:    putfield Field fc field874 Led;
L76:    iload_3
L77:    ifeq L92
L80:    aload_0
L81:    getstatic Field Kc field1931 LKc;
L84:    iload 4
L86:    invokevirtual Method Kc method856 (I)Led;
L89:    putfield Field fc field875 Led;
L92:    iload 5
L94:    ifeq L107
L97:    aload_0
L98:    invokestatic Method sE values ()[LsE;
L101:   iload 6
L103:   aaload
L104:   putfield Field fc field873 LsE;
L107:   return
L108:   
        .attribute StackMap b'\x00\x04\x00\x2A\x00\x05\x07\x00\x02\x07\x00\x4B\x01\x01\x01\x00\x00\x00\x41\x00\x07\x07\x00\x02\x07\x00\x4B\x01\x01\x01\x01\x01\x00\x00\x00\x5C\x00\x07\x07\x00\x02\x07\x00\x4B\x01\x01\x01\x01\x01\x00\x00\x00\x6B\x00\x07\x07\x00\x02\x07\x00\x4B\x01\x01\x01\x01\x01\x00\x00'
    .end code
    .exceptions java/io/IOException
.end method
.innerclasses
    DD fc [0] static synthetic
    oc fc [0] public static final enum
.end innerclasses
.end class
