.version 49 0
.class public final super fd
.super java/lang/Object
.implements java/lang/Runnable
.field public final synthetic char LJD;
.field public final synthetic else Lff;
.field public final synthetic "enum" LlG;
.field public final synthetic do Ljava/lang/String;

.method public run : ()V
    .code stack 4 locals 1
L0:     aload_0
L1:     dup
L2:     getfield Field fd char LJD;
L5:     swap
L6:     getfield Field fd "enum" LlG;
L9:     aload_0
L10:    dup
L11:    getfield Field fd else Lff;
L14:    swap
L15:    getfield Field fd do Ljava/lang/String;
L18:    invokestatic Method JD break (LJD;LlG;Lff;Ljava/lang/String;)V
L21:    return
L22:    
    .end code
.end method

.method public <init> : (LJD;LlG;Lff;Ljava/lang/String;)V
    .code stack 9 locals 5
L0:     aload 4
L2:     aload_0
L3:     dup_x1
L4:     dup_x2
L5:     aload_3
L6:     aload_2
L7:     aload_0
L8:     dup_x1
L9:     aload_1
L10:    putfield Field fd char LJD;
L13:    putfield Field fd "enum" LlG;
L16:    putfield Field fd else Lff;
L19:    putfield Field fd do Ljava/lang/String;
L22:    invokespecial Method java/lang/Object <init> ()V
L25:    return
L26:    
    .end code
.end method
.innerclasses
    fd [0] [0]
.end innerclasses
.enclosing method JD break (Lqc;Ljava/lang/String;Ljava/lang/String;Lff;)[LYg;
.end class
