.version 49 0
.class public super abstract ff
.super java/lang/Object
.implements D
.field public null I
.field public this [[I
.field public static final char I = 4
.field public else I
.field public "enum" I
.field public do I

.method public for : ()I
    .code stack 3 locals 1
L0:     iconst_4
L1:     iconst_1
L2:     dup
L3:     pop2
L4:     ireturn
L5:     
    .end code
.end method

.method public catch : ()Lff;
    .code stack 9 locals 4
L0:     aload_0
L1:     invokevirtual Method ff short ()Lff;
L4:     dup
L5:     astore_1
L6:     aload_0
L7:     dup_x1
L8:     aload_0
L9:     aload_1
L10:    dup_x1
L11:    aload_1
L12:    aload_0
L13:    dup_x1
L14:    getfield Field ff else I
L17:    putfield Field ff else I
L20:    getfield Field ff do I
L23:    putfield Field ff do I
L26:    getfield Field ff "enum" I
L29:    putfield Field ff "enum" I
L32:    getfield Field ff null I
L35:    putfield Field ff null I
L38:    getfield Field ff this [[I
L41:    arraylength
L42:    istore_2
L43:    iconst_0
L44:    iconst_1
L45:    dup
L46:    pop2
L47:    dup
L48:    istore_3
L49:    iload_2
L50:    if_icmpge L85
L53:    aload_0
L54:    getfield Field ff this [[I
L57:    iload_3
L58:    aaload
L59:    iconst_1
L60:    dup
L61:    pop2
L62:    aload_1
L63:    getfield Field ff this [[I
L66:    iload_3
L67:    iinc 3 1
L70:    aaload
L71:    iconst_0
L72:    dup_x1
L73:    iconst_1
L74:    dup
L75:    pop2
L76:    iload_2
L77:    invokestatic Method java/lang/System arraycopy (Ljava/lang/Object;ILjava/lang/Object;II)V
L80:    iload_3
L81:    goto L49
L84:    athrow
L85:    aload_1
L86:    areturn
L87:    
        .attribute StackMap b'\x00\x03\x00\x31\x00\x04\x07\x00\x02\x07\x00\x02\x01\x01\x00\x01\x01\x00\x54\x00\x00\x00\x01\x07\x00\x28\x00\x55\x00\x04\x07\x00\x02\x07\x00\x02\x01\x01\x00\x00'
    .end code
.end method

.method public abstract toString : ()Ljava/lang/String;
.end method

.method public static else : (I)Lff;
    .code stack 2 locals 1
L0:     iload_0
L1:     tableswitch 0
            L44
            L57
            L66
            L74
            L82
            L90
            L101
            default : L109
L44:    new tF
L47:    iconst_0
L48:    ifne L98
L51:    dup
L52:    invokespecial Method tF <init> ()V
L55:    areturn
L56:    athrow
L57:    new AF
L60:    dup
L61:    invokespecial Method AF <init> ()V
L64:    areturn
L65:    athrow
L66:    new VF
L69:    dup
L70:    invokespecial Method VF <init> ()V
L73:    areturn
L74:    new Df
L77:    dup
L78:    invokespecial Method Df <init> ()V
L81:    areturn
L82:    new mE
L85:    dup
L86:    invokespecial Method mE <init> ()V
L89:    areturn
L90:    new TE
L93:    dup
L94:    invokespecial Method TE <init> ()V
L97:    areturn
L98:    goto L47
L101:   new Af
L104:   dup
L105:   invokespecial Method Af <init> ()V
L108:   areturn
L109:   new java/lang/RuntimeException
L112:   dup
L113:   invokespecial Method java/lang/RuntimeException <init> ()V
L116:   athrow
L117:   
        .attribute StackMap b'\x00\x0C\x00\x2C\x00\x01\x01\x00\x00\x00\x2F\x00\x01\x01\x00\x01\x08\x00\x2C\x00\x38\x00\x00\x00\x01\x07\x00\x28\x00\x39\x00\x01\x01\x00\x00\x00\x41\x00\x00\x00\x01\x07\x00\x28\x00\x42\x00\x01\x01\x00\x00\x00\x4A\x00\x01\x01\x00\x00\x00\x52\x00\x01\x01\x00\x00\x00\x5A\x00\x01\x01\x00\x00\x00\x62\x00\x01\x01\x00\x01\x08\x00\x2C\x00\x65\x00\x01\x01\x00\x00\x00\x6D\x00\x01\x01\x00\x00'
    .end code
.end method

.method public static break : (LMd;)Lff;
    .code stack 3 locals 4
L0:     aload_0
L1:     invokevirtual Method Md this ()B
L4:     invokestatic Method ff else (I)Lff;
L7:     dup
L8:     astore_1
L9:     aload_0
L10:    dup_x1
L11:    invokevirtual Method Md long ()I
L14:    invokevirtual Method ff break (I)V
L17:    invokevirtual Method Md this ()B
L20:    istore_2
L21:    iconst_0
L22:    iconst_1
L23:    dup
L24:    pop2
L25:    dup
L26:    istore_3
L27:    iload_2
L28:    if_icmpge L43
L31:    iinc 3 1
L34:    aload_1
L35:    invokevirtual Method ff break ()V
L38:    iload_3
L39:    goto L27
L42:    athrow
L43:    aload_1
L44:    areturn
L45:    
        .attribute StackMap b'\x00\x03\x00\x1B\x00\x04\x07\x00\x4C\x07\x00\x02\x01\x01\x00\x01\x01\x00\x2A\x00\x00\x00\x01\x07\x00\x28\x00\x2B\x00\x04\x07\x00\x4C\x07\x00\x02\x01\x01\x00\x00'
    .end code
    .exceptions java/io/IOException
.end method

.method public bridge synthetic clone : ()Ljava/lang/Object;
    .code stack 1 locals 1
L0:     aload_0
L1:     invokevirtual Method ff catch ()Lff;
L4:     areturn
L5:     
    .end code
    .exceptions java/lang/CloneNotSupportedException
.end method

.method public float : ()V
    .code stack 2 locals 1
L0:     aload_0
L1:     dup
L2:     invokevirtual Method ff break ()V
L5:     invokevirtual Method ff break ()V
L8:     return
L9:     
    .end code
.end method

.method public short : ()Lff;
    .code stack 2 locals 2
L0:     aconst_null
L1:     astore_1
L2:     aload_0
L3:     instanceof tF
L6:     ifeq L17
L9:     new tF
L12:    dup
L13:    invokespecial Method tF <init> ()V
L16:    astore_1
L17:    aload_0
L18:    instanceof AF
L21:    ifeq L32
L24:    new AF
L27:    dup
L28:    invokespecial Method AF <init> ()V
L31:    astore_1
L32:    aload_0
L33:    instanceof VF
L36:    ifeq L47
L39:    new VF
L42:    dup
L43:    invokespecial Method VF <init> ()V
L46:    astore_1
L47:    aload_0
L48:    instanceof Df
L51:    ifeq L62
L54:    new Df
L57:    dup
L58:    invokespecial Method Df <init> ()V
L61:    astore_1
L62:    aload_0
L63:    instanceof mE
L66:    ifeq L77
L69:    new mE
L72:    dup
L73:    invokespecial Method mE <init> ()V
L76:    astore_1
L77:    aload_0
L78:    instanceof TE
L81:    ifeq L92
L84:    new TE
L87:    dup
L88:    invokespecial Method TE <init> ()V
L91:    astore_1
L92:    aload_0
L93:    instanceof Af
L96:    ifeq L107
L99:    new Af
L102:   dup
L103:   invokespecial Method Af <init> ()V
L106:   astore_1
L107:   aload_1
L108:   areturn
L109:   
        .attribute StackMap b'\x00\x07\x00\x11\x00\x02\x07\x00\x02\x07\x00\x2D\x00\x00\x00\x20\x00\x02\x07\x00\x02\x07\x00\x02\x00\x00\x00\x2F\x00\x02\x07\x00\x02\x07\x00\x02\x00\x00\x00\x3E\x00\x02\x07\x00\x02\x07\x00\x02\x00\x00\x00\x4D\x00\x02\x07\x00\x02\x07\x00\x02\x00\x00\x00\x5C\x00\x02\x07\x00\x02\x07\x00\x02\x00\x00\x00\x6B\x00\x02\x07\x00\x02\x07\x00\x02\x00\x00'
    .end code
.end method

.method public break : (LAC;)V
    .code stack 6 locals 2
L0:     aload_0
L1:     aload_1
L2:     dup_x1
L3:     aload_1
L4:     aload_0
L5:     dup_x1
L6:     invokevirtual Method ff else ()I
L9:     invokevirtual Method AC const (I)V
L12:    getfield Field ff "enum" I
L15:    invokevirtual Method AC break (I)V
L18:    getfield Field ff null I
L21:    invokevirtual Method AC const (I)V
L24:    return
L25:    
    .end code
    .exceptions java/io/IOException
.end method

.method public const : ([[I)Z
    .code stack 5 locals 2
L0:     aload_0
L1:     iconst_0
L2:     iconst_1
L3:     dup
L4:     pop2
L5:     iconst_1
L6:     dup
L7:     dup
L8:     pop2
L9:     aload_1
L10:    invokevirtual Method ff break (II[[I)Z
L13:    ifne L22
L16:    iconst_0
L17:    iconst_1
L18:    dup
L19:    pop2
L20:    ireturn
L21:    athrow
L22:    aload_0
L23:    iconst_0
L24:    iconst_1
L25:    dup
L26:    pop2
L27:    iconst_1
L28:    dup
L29:    dup
L30:    pop2
L31:    aload_1
L32:    invokevirtual Method ff break (II[[I)Z
L35:    ifeq L43
L38:    aload_0
L39:    goto L23
L42:    athrow
L43:    iconst_1
L44:    dup
L45:    dup
L46:    pop2
L47:    ireturn
L48:    
        .attribute StackMap b'\x00\x05\x00\x15\x00\x00\x00\x01\x07\x00\x28\x00\x16\x00\x02\x07\x00\x02\x07\x00\x6E\x00\x00\x00\x17\x00\x02\x07\x00\x02\x07\x00\x6E\x00\x01\x07\x00\x02\x00\x2A\x00\x00\x00\x01\x07\x00\x28\x00\x2B\x00\x02\x07\x00\x02\x07\x00\x6E\x00\x00'
    .end code
.end method

.method public const : ()V
    .code stack 3 locals 1
L0:     aload_0
L1:     dup
L2:     dup_x1
L3:     invokevirtual Method ff break ()V
L6:     invokevirtual Method ff break ()V
L9:     invokevirtual Method ff break ()V
L12:    return
L13:    
    .end code
.end method

.method public else : ([[I)V
    .code stack 7 locals 4
L0:     iconst_0
L1:     iconst_1
L2:     dup
L3:     pop2
L4:     dup
L5:     istore_2
L6:     aload_0
L7:     getfield Field ff this [[I
L10:    arraylength
L11:    if_icmpge L331
L14:    iconst_0
L15:    iconst_1
L16:    dup
L17:    pop2
L18:    dup
L19:    istore_3
L20:    aload_0
L21:    getfield Field ff this [[I
L24:    arraylength
L25:    if_icmpge L323
L28:    aload_0
L29:    getfield Field ff this [[I
L32:    iload_3
L33:    aaload
L34:    iload_2
L35:    iaload
L36:    ifeq L315
L39:    iload_3
L40:    aload_0
L41:    getfield Field ff else I
L44:    iadd
L45:    iflt L59
L48:    iload_3
L49:    aload_0
L50:    getfield Field ff else I
L53:    iadd
L54:    aload_1
L55:    arraylength
L56:    if_icmplt L163
L59:    new java/lang/RuntimeException
L62:    dup
L63:    new java/lang/StringBuilder
L66:    dup
L67:    invokespecial Method java/lang/StringBuilder <init> ()V
L70:    iconst_0
L71:    ldc "Ruggu X: "
L73:    invokevirtual Method java/lang/StringBuilder insert (ILjava/lang/String;)Ljava/lang/StringBuilder;
L76:    iload_3
L77:    invokevirtual Method java/lang/StringBuilder append (I)Ljava/lang/StringBuilder;
L80:    ldc " "
L82:    invokevirtual Method java/lang/StringBuilder append (Ljava/lang/String;)Ljava/lang/StringBuilder;
L85:    iload_2
L86:    invokevirtual Method java/lang/StringBuilder append (I)Ljava/lang/StringBuilder;
L89:    ldc " "
L91:    invokevirtual Method java/lang/StringBuilder append (Ljava/lang/String;)Ljava/lang/StringBuilder;
L94:    aload_0
L95:    getfield Field ff else I
L98:    invokevirtual Method java/lang/StringBuilder append (I)Ljava/lang/StringBuilder;
L101:   ldc " "
L103:   invokevirtual Method java/lang/StringBuilder append (Ljava/lang/String;)Ljava/lang/StringBuilder;
L106:   aload_0
L107:   getfield Field ff do I
L110:   invokevirtual Method java/lang/StringBuilder append (I)Ljava/lang/StringBuilder;
L113:   ldc " "
L115:   invokevirtual Method java/lang/StringBuilder append (Ljava/lang/String;)Ljava/lang/StringBuilder;
L118:   aload_0
L119:   getfield Field ff this [[I
L122:   arraylength
L123:   invokevirtual Method java/lang/StringBuilder append (I)Ljava/lang/StringBuilder;
L126:   ldc " "
L128:   invokevirtual Method java/lang/StringBuilder append (Ljava/lang/String;)Ljava/lang/StringBuilder;
L131:   aload_0
L132:   getfield Field ff this [[I
L135:   iconst_0
L136:   iconst_1
L137:   dup
L138:   pop2
L139:   aaload
L140:   arraylength
L141:   invokevirtual Method java/lang/StringBuilder append (I)Ljava/lang/StringBuilder;
L144:   ldc " "
L146:   invokevirtual Method java/lang/StringBuilder append (Ljava/lang/String;)Ljava/lang/StringBuilder;
L149:   aload_0
L150:   invokevirtual Method ff else ()I
L153:   invokevirtual Method java/lang/StringBuilder append (I)Ljava/lang/StringBuilder;
L156:   invokevirtual Method java/lang/StringBuilder toString ()Ljava/lang/String;
L159:   invokespecial Method java/lang/RuntimeException <init> (Ljava/lang/String;)V
L162:   athrow
L163:   iload_2
L164:   aload_0
L165:   getfield Field ff do I
L168:   iadd
L169:   iflt L188
L172:   iload_2
L173:   aload_0
L174:   getfield Field ff do I
L177:   iadd
L178:   aload_1
L179:   iconst_0
L180:   iconst_1
L181:   dup
L182:   pop2
L183:   aaload
L184:   arraylength
L185:   if_icmplt L292
L188:   new java/lang/RuntimeException
L191:   dup
L192:   new java/lang/StringBuilder
L195:   dup
L196:   invokespecial Method java/lang/StringBuilder <init> ()V
L199:   iconst_0
L200:   ldc "Ruggu Y: "
L202:   invokevirtual Method java/lang/StringBuilder insert (ILjava/lang/String;)Ljava/lang/StringBuilder;
L205:   iload_3
L206:   invokevirtual Method java/lang/StringBuilder append (I)Ljava/lang/StringBuilder;
L209:   ldc " "
L211:   invokevirtual Method java/lang/StringBuilder append (Ljava/lang/String;)Ljava/lang/StringBuilder;
L214:   iload_2
L215:   invokevirtual Method java/lang/StringBuilder append (I)Ljava/lang/StringBuilder;
L218:   ldc " "
L220:   invokevirtual Method java/lang/StringBuilder append (Ljava/lang/String;)Ljava/lang/StringBuilder;
L223:   aload_0
L224:   getfield Field ff else I
L227:   invokevirtual Method java/lang/StringBuilder append (I)Ljava/lang/StringBuilder;
L230:   ldc " "
L232:   invokevirtual Method java/lang/StringBuilder append (Ljava/lang/String;)Ljava/lang/StringBuilder;
L235:   aload_0
L236:   getfield Field ff do I
L239:   invokevirtual Method java/lang/StringBuilder append (I)Ljava/lang/StringBuilder;
L242:   ldc " "
L244:   invokevirtual Method java/lang/StringBuilder append (Ljava/lang/String;)Ljava/lang/StringBuilder;
L247:   aload_0
L248:   getfield Field ff this [[I
L251:   arraylength
L252:   invokevirtual Method java/lang/StringBuilder append (I)Ljava/lang/StringBuilder;
L255:   ldc " "
L257:   invokevirtual Method java/lang/StringBuilder append (Ljava/lang/String;)Ljava/lang/StringBuilder;
L260:   aload_0
L261:   getfield Field ff this [[I
L264:   iconst_0
L265:   iconst_1
L266:   dup
L267:   pop2
L268:   aaload
L269:   arraylength
L270:   invokevirtual Method java/lang/StringBuilder append (I)Ljava/lang/StringBuilder;
L273:   ldc " "
L275:   invokevirtual Method java/lang/StringBuilder append (Ljava/lang/String;)Ljava/lang/StringBuilder;
L278:   aload_0
L279:   invokevirtual Method ff else ()I
L282:   invokevirtual Method java/lang/StringBuilder append (I)Ljava/lang/StringBuilder;
L285:   invokevirtual Method java/lang/StringBuilder toString ()Ljava/lang/String;
L288:   invokespecial Method java/lang/RuntimeException <init> (Ljava/lang/String;)V
L291:   athrow
L292:   aload_1
L293:   iload_3
L294:   aload_0
L295:   getfield Field ff else I
L298:   iadd
L299:   aaload
L300:   iload_2
L301:   aload_0
L302:   getfield Field ff do I
L305:   iadd
L306:   aload_0
L307:   getfield Field ff this [[I
L310:   iload_3
L311:   aaload
L312:   iload_2
L313:   iaload
L314:   iastore
L315:   iinc 3 1
L318:   iload_3
L319:   goto L20
L322:   athrow
L323:   iinc 2 1
L326:   iload_2
L327:   goto L6
L330:   athrow
L331:   return
L332:   
        .attribute StackMap b'\x00\x0B\x00\x06\x00\x03\x07\x00\x02\x07\x00\x6E\x01\x00\x01\x01\x00\x14\x00\x04\x07\x00\x02\x07\x00\x6E\x01\x01\x00\x01\x01\x00\x3B\x00\x04\x07\x00\x02\x07\x00\x6E\x01\x01\x00\x00\x00\xA3\x00\x04\x07\x00\x02\x07\x00\x6E\x01\x01\x00\x00\x00\xBC\x00\x04\x07\x00\x02\x07\x00\x6E\x01\x01\x00\x00\x01\x24\x00\x04\x07\x00\x02\x07\x00\x6E\x01\x01\x00\x00\x01\x3B\x00\x04\x07\x00\x02\x07\x00\x6E\x01\x01\x00\x00\x01\x42\x00\x00\x00\x01\x07\x00\x28\x01\x43\x00\x04\x07\x00\x02\x07\x00\x6E\x01\x01\x00\x00\x01\x4A\x00\x00\x00\x01\x07\x00\x28\x01\x4B\x00\x03\x07\x00\x02\x07\x00\x6E\x01\x00\x00'
    .end code
.end method

.method public abstract else : ()I
.end method

.method public break : (I)V
    .code stack 3 locals 4
L0:     iconst_0
L1:     aload_0
L2:     iload_1
L3:     putfield Field ff "enum" I
L6:     iconst_1
L7:     dup
L8:     pop2
L9:     dup
L10:    istore_2
L11:    aload_0
L12:    getfield Field ff this [[I
L15:    arraylength
L16:    if_icmpge L69
L19:    iconst_0
L20:    iconst_1
L21:    dup
L22:    pop2
L23:    dup
L24:    istore_3
L25:    aload_0
L26:    getfield Field ff this [[I
L29:    arraylength
L30:    if_icmpge L61
L33:    aload_0
L34:    getfield Field ff this [[I
L37:    iload_3
L38:    aaload
L39:    iload_2
L40:    iaload
L41:    ifeq L53
L44:    aload_0
L45:    getfield Field ff this [[I
L48:    iload_3
L49:    aaload
L50:    iload_2
L51:    iload_1
L52:    iastore
L53:    iinc 3 1
L56:    iload_3
L57:    goto L25
L60:    athrow
L61:    iinc 2 1
L64:    iload_2
L65:    goto L11
L68:    athrow
L69:    aload_0
L70:    getfield Field ff this [[I
L73:    invokestatic Method hE else ([[I)V
L76:    return
L77:    
        .attribute StackMap b'\x00\x07\x00\x0B\x00\x03\x07\x00\x02\x01\x01\x00\x01\x01\x00\x19\x00\x04\x07\x00\x02\x01\x01\x01\x00\x01\x01\x00\x35\x00\x04\x07\x00\x02\x01\x01\x01\x00\x00\x00\x3C\x00\x00\x00\x01\x07\x00\x28\x00\x3D\x00\x04\x07\x00\x02\x01\x01\x01\x00\x00\x00\x44\x00\x00\x00\x01\x07\x00\x28\x00\x45\x00\x03\x07\x00\x02\x01\x01\x00\x00'
    .end code
.end method

.method public break : ([[I)Z
    .code stack 5 locals 5
L0:     aload_0
L1:     getfield Field ff this [[I
L4:     arraylength
L5:     istore_2
L6:     iconst_0
L7:     iconst_1
L8:     dup
L9:     pop2
L10:    dup
L11:    istore_3
L12:    iload_2
L13:    if_icmpge L118
L16:    iconst_0
L17:    iconst_1
L18:    dup
L19:    pop2
L20:    dup
L21:    istore 4
L23:    iload_2
L24:    if_icmpge L111
L27:    aload_0
L28:    getfield Field ff this [[I
L31:    iload 4
L33:    aaload
L34:    iload_3
L35:    iaload
L36:    ifeq L102
L39:    iload 4
L41:    aload_0
L42:    getfield Field ff else I
L45:    iadd
L46:    aload_1
L47:    arraylength
L48:    if_icmpge L96
L51:    iload_3
L52:    aload_0
L53:    getfield Field ff do I
L56:    iadd
L57:    aload_1
L58:    iconst_0
L59:    iconst_1
L60:    dup
L61:    pop2
L62:    aaload
L63:    arraylength
L64:    if_icmpge L96
L67:    iload 4
L69:    aload_0
L70:    getfield Field ff else I
L73:    iadd
L74:    iflt L96
L77:    aload_1
L78:    iload 4
L80:    aload_0
L81:    getfield Field ff else I
L84:    iadd
L85:    aaload
L86:    iload_3
L87:    aload_0
L88:    getfield Field ff do I
L91:    iadd
L92:    iaload
L93:    ifeq L102
L96:    iconst_1
L97:    dup
L98:    dup
L99:    pop2
L100:   ireturn
L101:   athrow
L102:   iinc 4 1
L105:   iload 4
L107:   goto L23
L110:   athrow
L111:   iinc 3 1
L114:   iload_3
L115:   goto L12
L118:   iconst_0
L119:   iconst_1
L120:   dup
L121:   pop2
L122:   ireturn
L123:   
        .attribute StackMap b'\x00\x08\x00\x0C\x00\x04\x07\x00\x02\x07\x00\x6E\x01\x01\x00\x01\x01\x00\x17\x00\x05\x07\x00\x02\x07\x00\x6E\x01\x01\x01\x00\x01\x01\x00\x60\x00\x05\x07\x00\x02\x07\x00\x6E\x01\x01\x01\x00\x00\x00\x65\x00\x00\x00\x01\x07\x00\x28\x00\x66\x00\x05\x07\x00\x02\x07\x00\x6E\x01\x01\x01\x00\x00\x00\x6E\x00\x00\x00\x01\x07\x00\x28\x00\x6F\x00\x05\x07\x00\x02\x07\x00\x6E\x01\x01\x01\x00\x00\x00\x76\x00\x04\x07\x00\x02\x07\x00\x6E\x01\x01\x00\x00'
    .end code
.end method

.method public break : ()V
    .code stack 7 locals 5
L0:     aload_0
L1:     getfield Field ff this [[I
L4:     arraylength
L5:     dup
L6:     istore_1
L7:     dup
L8:     multianewarray [[I 2
L12:    astore_2
L13:    iconst_0
L14:    aload_0
L15:    dup
L16:    getfield Field ff null I
L19:    iconst_1
L20:    dup
L21:    dup
L22:    pop2
L23:    iadd
L24:    iconst_3
L25:    iconst_1
L26:    dup
L27:    pop2
L28:    iand
L29:    putfield Field ff null I
L32:    iconst_1
L33:    dup
L34:    pop2
L35:    dup
L36:    istore_3
L37:    iload_1
L38:    if_icmpge L94
L41:    iconst_0
L42:    iconst_1
L43:    dup
L44:    pop2
L45:    dup
L46:    istore 4
L48:    iload_1
L49:    if_icmpge L86
L52:    aload_2
L53:    iload 4
L55:    aaload
L56:    aload_0
L57:    getfield Field ff this [[I
L60:    iload_3
L61:    dup_x1
L62:    aaload
L63:    iload_1
L64:    iconst_1
L65:    dup
L66:    dup
L67:    pop2
L68:    isub
L69:    iload 4
L71:    isub
L72:    iaload
L73:    invokestatic Method hE break (I)I
L76:    iinc 4 1
L79:    iastore
L80:    iload 4
L82:    goto L48
L85:    athrow
L86:    iinc 3 1
L89:    iload_3
L90:    goto L37
L93:    athrow
L94:    aload_0
L95:    dup
L96:    aload_2
L97:    putfield Field ff this [[I
L100:   getfield Field ff this [[I
L103:   invokestatic Method hE else ([[I)V
L106:   return
L107:   
        .attribute StackMap b'\x00\x06\x00\x25\x00\x04\x07\x00\x02\x01\x07\x00\x6E\x01\x00\x01\x01\x00\x30\x00\x05\x07\x00\x02\x01\x07\x00\x6E\x01\x01\x00\x01\x01\x00\x55\x00\x00\x00\x01\x07\x00\x28\x00\x56\x00\x05\x07\x00\x02\x01\x07\x00\x6E\x01\x01\x00\x00\x00\x5D\x00\x00\x00\x01\x07\x00\x28\x00\x5E\x00\x04\x07\x00\x02\x01\x07\x00\x6E\x01\x00\x00'
    .end code
.end method

.method public <init> : ()V
    .code stack 1 locals 1
L0:     aload_0
L1:     invokespecial Method java/lang/Object <init> ()V
L4:     return
L5:     
    .end code
.end method

.method public break : (Lff;)Z
    .code stack 3 locals 2
L0:     aload_1
L1:     getfield Field ff else I
L4:     aload_0
L5:     getfield Field ff else I
L8:     if_icmpeq L17
L11:    iconst_0
L12:    iconst_1
L13:    dup
L14:    pop2
L15:    ireturn
L16:    athrow
L17:    aload_1
L18:    getfield Field ff do I
L21:    aload_0
L22:    getfield Field ff do I
L25:    if_icmpeq L34
L28:    iconst_0
L29:    iconst_1
L30:    dup
L31:    pop2
L32:    ireturn
L33:    athrow
L34:    aload_1
L35:    getfield Field ff null I
L38:    aload_0
L39:    getfield Field ff null I
L42:    if_icmpeq L50
L45:    iconst_0
L46:    iconst_1
L47:    dup
L48:    pop2
L49:    ireturn
L50:    aload_1
L51:    getfield Field ff "enum" I
L54:    aload_0
L55:    getfield Field ff "enum" I
L58:    if_icmpeq L66
L61:    iconst_0
L62:    iconst_1
L63:    dup
L64:    pop2
L65:    ireturn
L66:    aload_1
L67:    invokevirtual Method java/lang/Object getClass ()Ljava/lang/Class;
L70:    aload_0
L71:    invokevirtual Method java/lang/Object getClass ()Ljava/lang/Class;
L74:    if_acmpeq L82
L77:    iconst_0
L78:    iconst_1
L79:    dup
L80:    pop2
L81:    ireturn
L82:    iconst_1
L83:    dup
L84:    dup
L85:    pop2
L86:    ireturn
L87:    
        .attribute StackMap b'\x00\x07\x00\x10\x00\x00\x00\x01\x07\x00\x28\x00\x11\x00\x02\x07\x00\x02\x07\x00\x02\x00\x00\x00\x21\x00\x00\x00\x01\x07\x00\x28\x00\x22\x00\x02\x07\x00\x02\x07\x00\x02\x00\x00\x00\x32\x00\x02\x07\x00\x02\x07\x00\x02\x00\x00\x00\x42\x00\x02\x07\x00\x02\x07\x00\x02\x00\x00\x00\x52\x00\x02\x07\x00\x02\x07\x00\x02\x00\x00'
    .end code
.end method

.method public break : (II[[I)Z
    .code stack 6 locals 4
L0:     aload_3
L1:     aload_0
L2:     dup
L3:     dup_x2
L4:     dup
L5:     getfield Field ff else I
L8:     iload_1
L9:     iadd
L10:    putfield Field ff else I
L13:    dup
L14:    getfield Field ff do I
L17:    iload_2
L18:    iadd
L19:    putfield Field ff do I
L22:    invokevirtual Method ff break ([[I)Z
L25:    ifeq L54
L28:    iconst_0
L29:    aload_0
L30:    dup
L31:    dup
L32:    getfield Field ff else I
L35:    iload_1
L36:    isub
L37:    putfield Field ff else I
L40:    dup
L41:    getfield Field ff do I
L44:    iload_2
L45:    isub
L46:    putfield Field ff do I
L49:    iconst_1
L50:    dup
L51:    pop2
L52:    ireturn
L53:    athrow
L54:    iconst_1
L55:    dup
L56:    dup
L57:    pop2
L58:    ireturn
L59:    
        .attribute StackMap b'\x00\x02\x00\x35\x00\x00\x00\x01\x07\x00\x28\x00\x36\x00\x04\x07\x00\x02\x01\x01\x07\x00\x6E\x00\x00'
    .end code
.end method
.end class
