.version 49 0
.class public super abstract gB
.super uB
.field public "final" Ljava/util/List;
.field public catch F
.field public false LWe;
.field public class LgB;
.field public if F
.field public true LgB;
.field public for Lqc;
.field public case F
.field private static byte F
.field private "super" Ljava/util/List;
.field public int Z
.field public short Z
.field private static goto F
.field public break F
.field public long Z
.field public void F
.field private static try F
.field public const Ljava/lang/Object;
.field public new LgB;
.field public null LFE;
.field private static this F
.field public char F
.field private static final else Ljava/util/List;
.field private "enum" Ljava/util/List;
.field public do LgB;

.method public default : ()Z
    .code stack 1 locals 1
L0:     aload_0
L1:     getfield Field gB long Z
L4:     ireturn
L5:     
    .end code
.end method

.method public break : (LgB;LgB;LgB;LgB;)V
    .code stack 2 locals 5
L0:     aload_1
L1:     ifnull L9
L4:     aload_0
L5:     aload_1
L6:     invokevirtual Method gB else (LgB;)V
L9:     aload_3
L10:    ifnull L18
L13:    aload_0
L14:    aload_3
L15:    invokevirtual Method gB const (LgB;)V
L18:    aload 4
L20:    ifnull L29
L23:    aload_0
L24:    aload 4
L26:    invokevirtual Method gB break (LgB;)V
L29:    aload_2
L30:    ifnull L38
L33:    aload_0
L34:    aload_2
L35:    invokevirtual Method gB short (LgB;)V
L38:    return
L39:    
        .attribute StackMap b'\x00\x04\x00\x09\x00\x05\x07\x00\x02\x07\x00\x02\x07\x00\x02\x07\x00\x02\x07\x00\x02\x00\x00\x00\x12\x00\x05\x07\x00\x02\x07\x00\x02\x07\x00\x02\x07\x00\x02\x07\x00\x02\x00\x00\x00\x1D\x00\x05\x07\x00\x02\x07\x00\x02\x07\x00\x02\x07\x00\x02\x07\x00\x02\x00\x00\x00\x26\x00\x05\x07\x00\x02\x07\x00\x02\x07\x00\x02\x07\x00\x02\x07\x00\x02\x00\x00'
    .end code
.end method

.method public break : (LFE;)V
    .code stack 2 locals 2
L0:     aload_0
L1:     aload_1
L2:     putfield Field gB null LFE;
L5:     return
L6:     
    .end code
.end method

.method public "super" : ()V
    .code stack 2 locals 1
L0:     aload_0
L1:     getfield Field gB for Lqc;
L4:     ifnull L15
L7:     aload_0
L8:     getfield Field gB for Lqc;
L11:    aload_0
L12:    invokevirtual Method qc do (LgB;)V
L15:    return
L16:    
        .attribute StackMap b'\x00\x01\x00\x0F\x00\x01\x07\x00\x02\x00\x00'
    .end code
.end method

.method public goto : (FF)Z
    .code stack 3 locals 3
L0:     aload_0
L1:     getfield Field gB long Z
L4:     ifne L13
L7:     iconst_0
L8:     iconst_1
L9:     dup
L10:    pop2
L11:    ireturn
L12:    athrow
L13:    fload_1
L14:    aload_0
L15:    getfield Field gB void F
L18:    fcmpl
L19:    iflt L67
L22:    fload_2
L23:    aload_0
L24:    getfield Field gB if F
L27:    fcmpl
L28:    iflt L67
L31:    fload_1
L32:    aload_0
L33:    dup
L34:    getfield Field gB void F
L37:    swap
L38:    getfield Field gB catch F
L41:    fadd
L42:    fcmpg
L43:    ifgt L67
L46:    fload_2
L47:    aload_0
L48:    dup
L49:    getfield Field gB if F
L52:    swap
L53:    getfield Field gB break F
L56:    fadd
L57:    fcmpg
L58:    ifgt L67
L61:    iconst_1
L62:    dup
L63:    dup
L64:    pop2
L65:    ireturn
L66:    athrow
L67:    iconst_0
L68:    iconst_1
L69:    dup
L70:    pop2
L71:    ireturn
L72:    
        .attribute StackMap b'\x00\x04\x00\x0C\x00\x00\x00\x01\x07\x00\x42\x00\x0D\x00\x03\x07\x00\x02\x02\x02\x00\x00\x00\x42\x00\x00\x00\x01\x07\x00\x42\x00\x43\x00\x03\x07\x00\x02\x02\x02\x00\x00'
    .end code
.end method

.method public break : (LgB;IC)Z
    .code stack 4 locals 6
L0:     iconst_0
L1:     iconst_1
L2:     dup
L3:     pop2
L4:     istore_3
L5:     iload_2
L6:     bipush 15
L8:     iconst_1
L9:     dup
L10:    pop2
L11:    if_icmpne L42
L14:    bipush 29
L16:    iconst_1
L17:    dup
L18:    pop2
L19:    invokestatic Method org/lwjgl/input/Keyboard break (I)Z
L22:    ifne L42
L25:    sipush 157
L28:    iconst_1
L29:    dup
L30:    pop2
L31:    invokestatic Method org/lwjgl/input/Keyboard break (I)Z
L34:    ifne L42
L37:    iconst_1
L38:    dup
L39:    dup
L40:    pop2
L41:    istore_3
L42:    iload_2
L43:    sipush 200
L46:    iconst_1
L47:    dup
L48:    pop2
L49:    if_icmpne L57
L52:    iconst_1
L53:    dup
L54:    dup
L55:    pop2
L56:    istore_3
L57:    iload_2
L58:    sipush 208
L61:    iconst_1
L62:    dup
L63:    pop2
L64:    if_icmpne L72
L67:    iconst_1
L68:    dup
L69:    dup
L70:    pop2
L71:    istore_3
L72:    iload_2
L73:    sipush 203
L76:    iconst_1
L77:    dup
L78:    pop2
L79:    if_icmpne L87
L82:    iconst_1
L83:    dup
L84:    dup
L85:    pop2
L86:    istore_3
L87:    iload_2
L88:    sipush 205
L91:    iconst_1
L92:    dup
L93:    pop2
L94:    if_icmpne L102
L97:    iconst_1
L98:    dup
L99:    dup
L100:   pop2
L101:   istore_3
L102:   iload_3
L103:   ifne L112
L106:   iconst_0
L107:   iconst_1
L108:   dup
L109:   pop2
L110:   ireturn
L111:   athrow
L112:   bipush 42
L114:   iconst_1
L115:   dup
L116:   pop2
L117:   invokestatic Method org/lwjgl/input/Keyboard break (I)Z
L120:   ifne L134
L123:   bipush 54
L125:   iconst_1
L126:   dup
L127:   pop2
L128:   invokestatic Method org/lwjgl/input/Keyboard break (I)Z
L131:   ifeq L142
L134:   iconst_1
L135:   dup
L136:   dup
L137:   pop2
L138:   goto L146
L141:   athrow
L142:   iconst_0
L143:   iconst_1
L144:   dup
L145:   pop2
L146:   istore_3
L147:   aload_1
L148:   astore_1
L149:   iconst_0
L150:   iconst_1
L151:   dup
L152:   pop2
L153:   dup
L154:   istore 4
L156:   bipush 100
L158:   iconst_1
L159:   dup
L160:   pop2
L161:   if_icmpge L453
L164:   aload_1
L165:   ifnonnull L173
L168:   iconst_0
L169:   iconst_1
L170:   dup
L171:   pop2
L172:   ireturn
L173:   iload_2
L174:   lookupswitch
            15 : L224
            200 : L340
            203 : L375
            205 : L391
            208 : L359
            default : L403
L224:   iload_3
L225:   iconst_0
L226:   ifne L356
L229:   ifeq L286
L232:   aload_1
L233:   getfield Field gB true LgB;
L236:   aload_1
L237:   swap
L238:   ifnull L249
L241:   getfield Field gB true LgB;
L244:   dup
L245:   astore_1
L246:   goto L404
L249:   getfield Field gB do LgB;
L252:   ifnull L403
L255:   aload_1
L256:   getfield Field gB do LgB;
L259:   dup
L260:   astore 5
L262:   getfield Field gB class LgB;
L265:   ifnull L279
L268:   aload 5
L270:   getfield Field gB class LgB;
L273:   dup
L274:   astore 5
L276:   goto L262
L279:   aload 5
L281:   dup
L282:   astore_1
L283:   goto L404
L286:   aload_1
L287:   getfield Field gB class LgB;
L290:   aload_1
L291:   swap
L292:   ifnull L303
L295:   getfield Field gB class LgB;
L298:   dup
L299:   astore_1
L300:   goto L404
L303:   getfield Field gB new LgB;
L306:   ifnull L403
L309:   aload_1
L310:   getfield Field gB new LgB;
L313:   dup
L314:   astore 5
L316:   getfield Field gB true LgB;
L319:   ifnull L333
L322:   aload 5
L324:   getfield Field gB true LgB;
L327:   dup
L328:   astore 5
L330:   goto L316
L333:   aload 5
L335:   dup
L336:   astore_1
L337:   goto L404
L340:   aload_1
L341:   getfield Field gB do LgB;
L344:   ifnull L403
L347:   aload_1
L348:   getfield Field gB do LgB;
L351:   dup
L352:   astore_1
L353:   goto L404
L356:   goto L225
L359:   aload_1
L360:   getfield Field gB new LgB;
L363:   ifnull L403
L366:   aload_1
L367:   getfield Field gB new LgB;
L370:   dup
L371:   astore_1
L372:   goto L404
L375:   aload_1
L376:   getfield Field gB true LgB;
L379:   ifnull L403
L382:   aload_1
L383:   getfield Field gB true LgB;
L386:   dup
L387:   astore_1
L388:   goto L404
L391:   aload_1
L392:   getfield Field gB class LgB;
L395:   ifnull L403
L398:   aload_1
L399:   getfield Field gB class LgB;
L402:   astore_1
L403:   aload_1
L404:   ifnonnull L412
L407:   iconst_0
L408:   iconst_1
L409:   dup
L410:   pop2
L411:   ireturn
L412:   aload_1
L413:   invokevirtual Method gB default ()Z
L416:   ifeq L445
L419:   aload_0
L420:   invokevirtual Method gB void ()LbC;
L423:   dup
L424:   astore 5
L426:   ifnonnull L434
L429:   iconst_0
L430:   iconst_1
L431:   dup
L432:   pop2
L433:   ireturn
L434:   aload 5
L436:   aload_1
L437:   invokevirtual Method bC try (LgB;)V
L440:   iconst_1
L441:   dup
L442:   dup
L443:   pop2
L444:   ireturn
L445:   iinc 4 1
L448:   iload 4
L450:   goto L156
L453:   iconst_0
L454:   iconst_1
L455:   dup
L456:   pop2
L457:   ireturn
L458:   
        .attribute StackMap b'\x00\x21\x00\x2A\x00\x04\x07\x00\x02\x07\x00\x02\x01\x01\x00\x00\x00\x39\x00\x04\x07\x00\x02\x07\x00\x02\x01\x01\x00\x00\x00\x48\x00\x04\x07\x00\x02\x07\x00\x02\x01\x01\x00\x00\x00\x57\x00\x04\x07\x00\x02\x07\x00\x02\x01\x01\x00\x00\x00\x66\x00\x04\x07\x00\x02\x07\x00\x02\x01\x01\x00\x00\x00\x6F\x00\x00\x00\x01\x07\x00\x42\x00\x70\x00\x04\x07\x00\x02\x07\x00\x02\x01\x01\x00\x00\x00\x86\x00\x04\x07\x00\x02\x07\x00\x02\x01\x01\x00\x00\x00\x8D\x00\x00\x00\x01\x07\x00\x42\x00\x8E\x00\x04\x07\x00\x02\x07\x00\x02\x01\x01\x00\x00\x00\x92\x00\x04\x07\x00\x02\x07\x00\x02\x01\x01\x00\x01\x01\x00\x9C\x00\x05\x07\x00\x02\x07\x00\x02\x01\x01\x01\x00\x01\x01\x00\xAD\x00\x05\x07\x00\x02\x07\x00\x02\x01\x01\x01\x00\x00\x00\xE0\x00\x05\x07\x00\x02\x07\x00\x02\x01\x01\x01\x00\x00\x00\xE1\x00\x05\x07\x00\x02\x07\x00\x02\x01\x01\x01\x00\x01\x01\x00\xF9\x00\x05\x07\x00\x02\x07\x00\x02\x01\x01\x01\x00\x01\x07\x00\x02\x01\x06\x00\x06\x07\x00\x02\x07\x00\x02\x01\x01\x01\x07\x00\x02\x00\x01\x07\x00\x02\x01\x17\x00\x06\x07\x00\x02\x07\x00\x02\x01\x01\x01\x07\x00\x02\x00\x00\x01\x1E\x00\x05\x07\x00\x02\x07\x00\x02\x01\x01\x01\x00\x00\x01\x2F\x00\x05\x07\x00\x02\x07\x00\x02\x01\x01\x01\x00\x01\x07\x00\x02\x01\x3C\x00\x06\x07\x00\x02\x07\x00\x02\x01\x01\x01\x07\x00\x02\x00\x01\x07\x00\x02\x01\x4D\x00\x06\x07\x00\x02\x07\x00\x02\x01\x01\x01\x07\x00\x02\x00\x00\x01\x54\x00\x05\x07\x00\x02\x07\x00\x02\x01\x01\x01\x00\x00\x01\x64\x00\x05\x07\x00\x02\x07\x00\x02\x01\x01\x01\x00\x01\x01\x01\x67\x00\x05\x07\x00\x02\x07\x00\x02\x01\x01\x01\x00\x00\x01\x77\x00\x05\x07\x00\x02\x07\x00\x02\x01\x01\x01\x00\x00\x01\x87\x00\x05\x07\x00\x02\x07\x00\x02\x01\x01\x01\x00\x00\x01\x93\x00\x05\x07\x00\x02\x07\x00\x02\x01\x01\x01\x00\x00\x01\x94\x00\x05\x07\x00\x02\x07\x00\x02\x01\x01\x01\x00\x01\x07\x00\x02\x01\x9C\x00\x05\x07\x00\x02\x07\x00\x02\x01\x01\x01\x00\x00\x01\xB2\x00\x06\x07\x00\x02\x07\x00\x02\x01\x01\x01\x07\x00\x5F\x00\x00\x01\xBD\x00\x05\x07\x00\x02\x07\x00\x02\x01\x01\x01\x00\x00\x01\xC5\x00\x05\x07\x00\x02\x07\x00\x02\x01\x01\x01\x00\x00'
    .end code
.end method

.method public catch : (Lh;)V
    .code stack 4 locals 2
L0:     aload_0
L1:     getfield Field gB "final" Ljava/util/List;
L4:     ifnonnull L21
L7:     new java/util/ArrayList
L10:    aload_0
L11:    dup_x1
L12:    dup
L13:    pop2
L14:    dup
L15:    invokespecial Method java/util/ArrayList <init> ()V
L18:    putfield Field gB "final" Ljava/util/List;
L21:    aload_0
L22:    getfield Field gB "final" Ljava/util/List;
L25:    aload_1
L26:    invokeinterface InterfaceMethod java/util/List add (Ljava/lang/Object;)Z 2
L31:    pop
L32:    return
L33:    
        .attribute StackMap b'\x00\x01\x00\x15\x00\x02\x07\x00\x02\x07\x00\x6B\x00\x00'
    .end code
.end method

.method public <init> : ()V
    .code stack 14 locals 1
L0:     iconst_1
L1:     aload_0
L2:     dup_x1
L3:     aconst_null
L4:     fconst_0
L5:     aload_0
L6:     dup_x1
L7:     fconst_0
L8:     dup
L9:     aload_0
L10:    dup_x1
L11:    fconst_0
L12:    aload_0
L13:    dup
L14:    invokespecial Method uB <init> ()V
L17:    getstatic Field We new LWe;
L20:    putfield Field gB false LWe;
L23:    putfield Field gB catch F
L26:    putfield Field gB break F
L29:    putfield Field gB void F
L32:    putfield Field gB if F
L35:    putfield Field gB for Lqc;
L38:    iconst_1
L39:    dup
L40:    pop2
L41:    putfield Field gB long Z
L44:    return
L45:    
    .end code
.end method

.method public case : ()V
    .code stack 0 locals 1
L0:     return
L1:     
    .end code
.end method

.method public break : (FFFF)V
    .code stack 6 locals 5
L0:     getstatic Field gB else Ljava/util/List;
L3:     iconst_4
L4:     iconst_1
L5:     dup
L6:     pop2
L7:     newarray float
L9:     iconst_1
L10:    dup
L11:    pop2
L12:    dup
L13:    iconst_0
L14:    iconst_1
L15:    dup
L16:    pop2
L17:    aload_0
L18:    getfield Field gB void F
L21:    fload_1
L22:    fadd
L23:    fastore
L24:    dup
L25:    iconst_1
L26:    dup
L27:    dup
L28:    pop2
L29:    aload_0
L30:    getfield Field gB if F
L33:    fload_2
L34:    fadd
L35:    fastore
L36:    dup
L37:    iconst_2
L38:    iconst_1
L39:    dup
L40:    pop2
L41:    aload_0
L42:    getfield Field gB void F
L45:    fload_3
L46:    fadd
L47:    fastore
L48:    dup
L49:    iconst_3
L50:    iconst_1
L51:    dup
L52:    pop2
L53:    aload_0
L54:    getfield Field gB if F
L57:    fload 4
L59:    fadd
L60:    fastore
L61:    invokeinterface InterfaceMethod java/util/List add (Ljava/lang/Object;)Z 2
L66:    aload_0
L67:    invokespecial Method gB "final" ()V
L70:    pop
L71:    return
L72:    
    .end code
.end method

.method public do : (FF)V
    .code stack 0 locals 3
L0:     return
L1:     
    .end code
.end method

.method public for : (FF)V
    .code stack 0 locals 3
L0:     return
L1:     
    .end code
.end method

.method public short : (LgB;)V
    .code stack 2 locals 2
L0:     aload_1
L1:     aload_0
L2:     if_acmpne L7
L5:     return
L6:     athrow
L7:     aload_0
L8:     aload_1
L9:     putfield Field gB class LgB;
L12:    aload_1
L13:    ifnull L21
L16:    aload_1
L17:    aload_0
L18:    putfield Field gB true LgB;
L21:    return
L22:    
        .attribute StackMap b'\x00\x03\x00\x06\x00\x00\x00\x01\x07\x00\x42\x00\x07\x00\x02\x07\x00\x02\x07\x00\x02\x00\x00\x00\x15\x00\x02\x07\x00\x02\x07\x00\x02\x00\x00'
    .end code
.end method

.method public short : (I)V
    .code stack 2 locals 2
L0:     aload_0
L1:     getfield Field gB for Lqc;
L4:     ifnull L15
L7:     aload_0
L8:     getfield Field gB for Lqc;
L11:    iload_1
L12:    invokevirtual Method qc short (I)V
L15:    return
L16:    
        .attribute StackMap b'\x00\x01\x00\x0F\x00\x02\x07\x00\x02\x01\x00\x00'
    .end code
.end method

.method public break : (Z)V
    .code stack 6 locals 2
L0:     aload_0
L1:     dup
L2:     iload_1
L3:     putfield Field gB long Z
L6:     getfield Field gB short Z
L9:     ifeq L39
L12:    aload_0
L13:    getfield Field gB long Z
L16:    ifne L39
L19:    aload_0
L20:    dup
L21:    dup_x1
L22:    iconst_0
L23:    iconst_1
L24:    dup
L25:    pop2
L26:    putfield Field gB short Z
L29:    invokevirtual Method gB null ()V
L32:    invokevirtual Method gB void ()LbC;
L35:    aconst_null
L36:    invokevirtual Method bC try (LgB;)V
L39:    return
L40:    
        .attribute StackMap b'\x00\x01\x00\x27\x00\x02\x07\x00\x02\x01\x00\x00'
    .end code
.end method

.method public null : ()V
    .code stack 2 locals 2
L0:     aload_0
L1:     getfield Field gB "enum" Ljava/util/List;
L4:     ifnonnull L9
L7:     return
L8:     athrow
L9:     aload_0
L10:    getfield Field gB "enum" Ljava/util/List;
L13:    invokeinterface InterfaceMethod java/util/List iterator ()Ljava/util/Iterator; 1
L18:    dup
L19:    astore_1
L20:    invokeinterface InterfaceMethod java/util/Iterator hasNext ()Z 1
L25:    ifeq L48
L28:    aload_1
L29:    invokeinterface InterfaceMethod java/util/Iterator next ()Ljava/lang/Object; 1
L34:    checkcast h
L37:    aload_0
L38:    invokeinterface InterfaceMethod h break (LgB;)V 2
L43:    aload_1
L44:    goto L20
L47:    athrow
L48:    return
L49:    
        .attribute StackMap b'\x00\x05\x00\x08\x00\x00\x00\x01\x07\x00\x42\x00\x09\x00\x01\x07\x00\x02\x00\x00\x00\x14\x00\x02\x07\x00\x02\x07\x00\x8E\x00\x01\x07\x00\x8E\x00\x2F\x00\x00\x00\x01\x07\x00\x42\x00\x30\x00\x02\x07\x00\x02\x07\x00\x8E\x00\x00'
    .end code
.end method

.method public false : ()Z
    .code stack 3 locals 1
L0:     iconst_0
L1:     iconst_1
L2:     dup
L3:     pop2
L4:     ireturn
L5:     
    .end code
.end method

.method public float : (Lh;)V
    .code stack 2 locals 2
L0:     aload_0
L1:     getfield Field gB "super" Ljava/util/List;
L4:     aload_1
L5:     invokeinterface InterfaceMethod java/util/List remove (Ljava/lang/Object;)Z 2
L10:    pop
L11:    return
L12:    
    .end code
.end method

.method public true : ()V
    .code stack 2 locals 2
L0:     aload_0
L1:     dup
L2:     invokevirtual Method gB "super" ()V
L5:     getfield Field gB "super" Ljava/util/List;
L8:     ifnonnull L13
L11:    return
L12:    athrow
L13:    aload_0
L14:    getfield Field gB "super" Ljava/util/List;
L17:    invokeinterface InterfaceMethod java/util/List iterator ()Ljava/util/Iterator; 1
L22:    dup
L23:    astore_1
L24:    invokeinterface InterfaceMethod java/util/Iterator hasNext ()Z 1
L29:    ifeq L52
L32:    aload_1
L33:    invokeinterface InterfaceMethod java/util/Iterator next ()Ljava/lang/Object; 1
L38:    checkcast h
L41:    aload_0
L42:    invokeinterface InterfaceMethod h break (LgB;)V 2
L47:    aload_1
L48:    goto L24
L51:    athrow
L52:    return
L53:    
        .attribute StackMap b'\x00\x05\x00\x0C\x00\x00\x00\x01\x07\x00\x42\x00\x0D\x00\x01\x07\x00\x02\x00\x00\x00\x18\x00\x02\x07\x00\x02\x07\x00\x8E\x00\x01\x07\x00\x8E\x00\x33\x00\x00\x00\x01\x07\x00\x42\x00\x34\x00\x02\x07\x00\x02\x07\x00\x8E\x00\x00'
    .end code
.end method

.method public const : (LgB;)V
    .code stack 2 locals 2
L0:     aload_1
L1:     aload_0
L2:     if_acmpne L7
L5:     return
L6:     athrow
L7:     aload_0
L8:     aload_1
L9:     putfield Field gB new LgB;
L12:    aload_1
L13:    ifnull L21
L16:    aload_1
L17:    aload_0
L18:    putfield Field gB do LgB;
L21:    return
L22:    
        .attribute StackMap b'\x00\x03\x00\x06\x00\x00\x00\x01\x07\x00\x42\x00\x07\x00\x02\x07\x00\x02\x07\x00\x02\x00\x00\x00\x15\x00\x02\x07\x00\x02\x07\x00\x02\x00\x00'
    .end code
.end method

.method public static <clinit> : ()V
    .code stack 2 locals 0
L0:     new java/util/ArrayList
L3:     dup
L4:     invokespecial Method java/util/ArrayList <init> ()V
L7:     putstatic Field gB else Ljava/util/List;
L10:    return
L11:    
    .end code
.end method

.method public byte : ()V
    .code stack 5 locals 1
L0:     getstatic Field gB else Ljava/util/List;
L3:     getstatic Field gB else Ljava/util/List;
L6:     invokeinterface InterfaceMethod java/util/List size ()I 1
L11:    iconst_1
L12:    dup
L13:    dup
L14:    pop2
L15:    isub
L16:    invokeinterface InterfaceMethod java/util/List remove (I)Ljava/lang/Object; 2
L21:    aload_0
L22:    invokespecial Method gB "final" ()V
L25:    pop
L26:    return
L27:    
    .end code
.end method

.method public short : (Lh;)V
    .code stack 2 locals 2
L0:     aload_0
L1:     getfield Field gB "final" Ljava/util/List;
L4:     aload_1
L5:     invokeinterface InterfaceMethod java/util/List remove (Ljava/lang/Object;)Z 2
L10:    pop
L11:    return
L12:    
    .end code
.end method

.method public catch : (FF)V
    .code stack 6 locals 3
L0:     aload_0
L1:     getfield Field gB void F
L4:     fload_1
L5:     fcmpl
L6:     ifne L20
L9:     aload_0
L10:    getfield Field gB if F
L13:    fload_2
L14:    fcmpl
L15:    ifne L20
L18:    return
L19:    athrow
L20:    aload_0
L21:    dup
L22:    fload_2
L23:    aload_0
L24:    dup_x2
L25:    fload_1
L26:    putfield Field gB void F
L29:    putfield Field gB if F
L32:    invokevirtual Method gB long ()V
L35:    getfield Field gB for Lqc;
L38:    ifnull L73
L41:    aload_0
L42:    dup
L43:    getfield Field gB void F
L46:    swap
L47:    getfield Field gB for Lqc;
L50:    getfield Field qc void F
L53:    fsub
L54:    aload_0
L55:    getfield Field gB if F
L58:    aload_0
L59:    dup_x2
L60:    getfield Field gB for Lqc;
L63:    getfield Field qc if F
L66:    fsub
L67:    fconst_0
L68:    invokevirtual Method gB break (FFF)V
L71:    return
L72:    athrow
L73:    aload_0
L74:    dup
L75:    dup_x1
L76:    getfield Field gB void F
L79:    swap
L80:    getfield Field gB if F
L83:    fconst_0
L84:    invokevirtual Method gB break (FFF)V
L87:    return
L88:    
        .attribute StackMap b'\x00\x04\x00\x13\x00\x00\x00\x01\x07\x00\x42\x00\x14\x00\x03\x07\x00\x02\x02\x02\x00\x00\x00\x48\x00\x00\x00\x01\x07\x00\x42\x00\x49\x00\x03\x07\x00\x02\x02\x02\x00\x00'
    .end code
.end method

.method public const : (Lh;)V
    .code stack 4 locals 2
L0:     aload_0
L1:     getfield Field gB "super" Ljava/util/List;
L4:     ifnonnull L21
L7:     new java/util/LinkedList
L10:    aload_0
L11:    dup_x1
L12:    dup
L13:    pop2
L14:    dup
L15:    invokespecial Method java/util/LinkedList <init> ()V
L18:    putfield Field gB "super" Ljava/util/List;
L21:    aload_0
L22:    getfield Field gB "super" Ljava/util/List;
L25:    aload_1
L26:    invokeinterface InterfaceMethod java/util/List add (Ljava/lang/Object;)Z 2
L31:    pop
L32:    return
L33:    
        .attribute StackMap b'\x00\x01\x00\x15\x00\x02\x07\x00\x02\x07\x00\x6B\x00\x00'
    .end code
.end method

.method public float : (FF)V
    .code stack 0 locals 3
L0:     return
L1:     
    .end code
.end method

.method public const : (I)V
    .code stack 0 locals 2
L0:     return
L1:     
    .end code
.end method

.method public void : ()LbC;
    .code stack 1 locals 1
L0:     aload_0
L1:     getfield Field gB for Lqc;
L4:     ifnull L16
L7:     aload_0
L8:     getfield Field gB for Lqc;
L11:    invokevirtual Method qc void ()LbC;
L14:    areturn
L15:    athrow
L16:    aconst_null
L17:    areturn
L18:    
        .attribute StackMap b'\x00\x02\x00\x0F\x00\x00\x00\x01\x07\x00\x42\x00\x10\x00\x01\x07\x00\x02\x00\x00'
    .end code
.end method

.method public short : (FF)V
    .code stack 2 locals 3
L0:     aload_0
L1:     getfield Field gB "final" Ljava/util/List;
L4:     ifnonnull L9
L7:     return
L8:     athrow
L9:     aload_0
L10:    getfield Field gB "final" Ljava/util/List;
L13:    invokeinterface InterfaceMethod java/util/List iterator ()Ljava/util/Iterator; 1
L18:    dup
L19:    astore_1
L20:    invokeinterface InterfaceMethod java/util/Iterator hasNext ()Z 1
L25:    ifeq L48
L28:    aload_1
L29:    invokeinterface InterfaceMethod java/util/Iterator next ()Ljava/lang/Object; 1
L34:    checkcast h
L37:    aload_0
L38:    invokeinterface InterfaceMethod h break (LgB;)V 2
L43:    aload_1
L44:    goto L20
L47:    athrow
L48:    return
L49:    
        .attribute StackMap b'\x00\x05\x00\x08\x00\x00\x00\x01\x07\x00\x42\x00\x09\x00\x03\x07\x00\x02\x02\x02\x00\x00\x00\x14\x00\x03\x07\x00\x02\x07\x00\x8E\x02\x00\x01\x07\x00\x8E\x00\x2F\x00\x00\x00\x01\x07\x00\x42\x00\x30\x00\x03\x07\x00\x02\x07\x00\x8E\x02\x00\x00'
    .end code
.end method

.method public const : (FF)V
    .code stack 4 locals 3
L0:     fload_2
L1:     aload_0
L2:     dup_x1
L3:     fload_1
L4:     putfield Field gB catch F
L7:     putfield Field gB break F
L10:    return
L11:    
    .end code
.end method

.method public else : (LgB;)V
    .code stack 2 locals 2
L0:     aload_1
L1:     aload_0
L2:     if_acmpne L7
L5:     return
L6:     athrow
L7:     aload_0
L8:     aload_1
L9:     putfield Field gB do LgB;
L12:    aload_1
L13:    ifnull L21
L16:    aload_1
L17:    aload_0
L18:    putfield Field gB new LgB;
L21:    return
L22:    
        .attribute StackMap b'\x00\x03\x00\x06\x00\x00\x00\x01\x07\x00\x42\x00\x07\x00\x02\x07\x00\x02\x07\x00\x02\x00\x00\x00\x15\x00\x02\x07\x00\x02\x07\x00\x02\x00\x00'
    .end code
.end method

.method public varargs break : ([LZd;)V
    .code stack 5 locals 2
L0:     new Ef
L3:     aload_0
L4:     dup
L5:     pop2
L6:     dup
L7:     aload_0
L8:     dup_x2
L9:     aload_1
L10:    invokespecial Method Ef <init> (LgB;[LZd;)V
L13:    invokevirtual Method gB catch (Lh;)V
L16:    return
L17:    
    .end code
.end method

.method public else : (FF)LgB;
    .code stack 3 locals 3
L0:     aload_0
L1:     getfield Field gB long Z
L4:     ifeq L14
L7:     aload_0
L8:     invokevirtual Method gB false ()Z
L11:    ifne L17
L14:    aconst_null
L15:    areturn
L16:    athrow
L17:    aload_0
L18:    fload_1
L19:    fload_2
L20:    invokevirtual Method gB goto (FF)Z
L23:    ifeq L29
L26:    aload_0
L27:    areturn
L28:    athrow
L29:    aconst_null
L30:    areturn
L31:    
        .attribute StackMap b'\x00\x05\x00\x0E\x00\x03\x07\x00\x02\x02\x02\x00\x00\x00\x10\x00\x00\x00\x01\x07\x00\x42\x00\x11\x00\x03\x07\x00\x02\x02\x02\x00\x00\x00\x1C\x00\x00\x00\x01\x07\x00\x42\x00\x1D\x00\x03\x07\x00\x02\x02\x02\x00\x00'
    .end code
.end method

.method public break : (LgB;I)Z
    .code stack 4 locals 3
L0:     iload_2
L1:     lookupswitch
            221 : L20
            default : L46
L20:    aload_0
L21:    iconst_0
L22:    ifne L21
L25:    dup
L26:    getfield Field gB catch F
L29:    fconst_2
L30:    fdiv
L31:    aload_0
L32:    getfield Field gB break F
L35:    fconst_2
L36:    fdiv
L37:    invokevirtual Method gB short (FF)V
L40:    iconst_1
L41:    dup
L42:    dup
L43:    pop2
L44:    ireturn
L45:    athrow
L46:    iconst_0
L47:    iconst_1
L48:    dup
L49:    pop2
L50:    ireturn
L51:    
        .attribute StackMap b'\x00\x04\x00\x14\x00\x03\x07\x00\x02\x07\x00\x02\x01\x00\x00\x00\x15\x00\x03\x07\x00\x02\x07\x00\x02\x01\x00\x01\x07\x00\x02\x00\x2D\x00\x00\x00\x01\x07\x00\x42\x00\x2E\x00\x03\x07\x00\x02\x07\x00\x02\x01\x00\x00'
    .end code
.end method

.method public else : (Lh;)V
    .code stack 2 locals 2
L0:     aload_0
L1:     getfield Field gB "enum" Ljava/util/List;
L4:     aload_1
L5:     invokeinterface InterfaceMethod java/util/List remove (Ljava/lang/Object;)Z 2
L10:    pop
L11:    return
L12:    
    .end code
.end method

.method public break : (LgB;)V
    .code stack 2 locals 2
L0:     aload_1
L1:     aload_0
L2:     if_acmpne L7
L5:     return
L6:     athrow
L7:     aload_0
L8:     aload_1
L9:     putfield Field gB true LgB;
L12:    aload_1
L13:    ifnull L21
L16:    aload_1
L17:    aload_0
L18:    putfield Field gB class LgB;
L21:    return
L22:    
        .attribute StackMap b'\x00\x03\x00\x06\x00\x00\x00\x01\x07\x00\x42\x00\x07\x00\x02\x07\x00\x02\x07\x00\x02\x00\x00\x00\x15\x00\x02\x07\x00\x02\x07\x00\x02\x00\x00'
    .end code
.end method

.method public break : (Lh;)V
    .code stack 4 locals 2
L0:     aload_0
L1:     getfield Field gB "enum" Ljava/util/List;
L4:     ifnonnull L21
L7:     new java/util/LinkedList
L10:    aload_0
L11:    dup_x1
L12:    dup
L13:    pop2
L14:    dup
L15:    invokespecial Method java/util/LinkedList <init> ()V
L18:    putfield Field gB "enum" Ljava/util/List;
L21:    aload_0
L22:    getfield Field gB "enum" Ljava/util/List;
L25:    aload_1
L26:    invokeinterface InterfaceMethod java/util/List add (Ljava/lang/Object;)Z 2
L31:    pop
L32:    return
L33:    
        .attribute StackMap b'\x00\x01\x00\x15\x00\x02\x07\x00\x02\x07\x00\x6B\x00\x00'
    .end code
.end method

.method private "final" : ()V
    .code stack 5 locals 7
L0:     ldc -Infinityf
L2:     fstore_1
L3:     ldc -Infinityf
L5:     fstore_2
L6:     ldc +Infinityf
L8:     fstore_3
L9:     ldc +Infinityf
L11:    fstore 4
L13:    getstatic Field gB else Ljava/util/List;
L16:    invokeinterface InterfaceMethod java/util/List iterator ()Ljava/util/Iterator; 1
L21:    astore 5
L23:    aload 5
L25:    invokeinterface InterfaceMethod java/util/Iterator hasNext ()Z 1
L30:    ifeq L131
L33:    aload 5
L35:    invokeinterface InterfaceMethod java/util/Iterator next ()Ljava/lang/Object; 1
L40:    checkcast [F
L43:    astore 6
L45:    fload_1
L46:    aload 6
L48:    iconst_0
L49:    iconst_1
L50:    dup
L51:    pop2
L52:    faload
L53:    fcmpg
L54:    ifge L65
L57:    aload 6
L59:    iconst_0
L60:    iconst_1
L61:    dup
L62:    pop2
L63:    faload
L64:    fstore_1
L65:    fload_2
L66:    aload 6
L68:    iconst_1
L69:    dup
L70:    dup
L71:    pop2
L72:    faload
L73:    fcmpg
L74:    ifge L85
L77:    aload 6
L79:    iconst_1
L80:    dup
L81:    dup
L82:    pop2
L83:    faload
L84:    fstore_2
L85:    aload 6
L87:    iconst_2
L88:    iconst_1
L89:    dup
L90:    pop2
L91:    faload
L92:    fload_3
L93:    fcmpg
L94:    ifge L105
L97:    aload 6
L99:    iconst_2
L100:   iconst_1
L101:   dup
L102:   pop2
L103:   faload
L104:   fstore_3
L105:   aload 6
L107:   iconst_3
L108:   iconst_1
L109:   dup
L110:   pop2
L111:   faload
L112:   fload 4
L114:   fcmpg
L115:   ifge L23
L118:   aload 6
L120:   iconst_3
L121:   iconst_1
L122:   dup
L123:   pop2
L124:   faload
L125:   fstore 4
L127:   goto L23
L130:   athrow
L131:   fload_1
L132:   getstatic Field gB this F
L135:   fcmpl
L136:   ifne L166
L139:   fload_2
L140:   getstatic Field gB goto F
L143:   fcmpl
L144:   ifne L166
L147:   fload_3
L148:   getstatic Field gB try F
L151:   fcmpl
L152:   ifne L166
L155:   fload 4
L157:   getstatic Field gB byte F
L160:   fcmpl
L161:   ifne L166
L164:   return
L165:   athrow
L166:   fload_1
L167:   putstatic Field gB this F
L170:   fload_3
L171:   putstatic Field gB try F
L174:   fload_2
L175:   putstatic Field gB goto F
L178:   fload 4
L180:   putstatic Field gB byte F
L183:   fload_1
L184:   aload_0
L185:   getfield Field gB void F
L188:   fsub
L189:   fload_2
L190:   aload_0
L191:   getfield Field gB if F
L194:   fsub
L195:   fload_3
L196:   aload_0
L197:   getfield Field gB void F
L200:   fsub
L201:   fload 4
L203:   aload_0
L204:   getfield Field gB if F
L207:   fsub
L208:   invokestatic Method FE break (FFFF)V
L211:   return
L212:   
        .attribute StackMap b'\x00\x08\x00\x17\x00\x06\x07\x00\x02\x02\x02\x02\x02\x07\x00\x8E\x00\x00\x00\x41\x00\x07\x07\x00\x02\x02\x02\x02\x02\x07\x00\x8E\x07\x00\xC3\x00\x00\x00\x55\x00\x07\x07\x00\x02\x02\x02\x02\x02\x07\x00\x8E\x07\x00\xC3\x00\x00\x00\x69\x00\x07\x07\x00\x02\x02\x02\x02\x02\x07\x00\x8E\x07\x00\xC3\x00\x00\x00\x82\x00\x00\x00\x01\x07\x00\x42\x00\x83\x00\x06\x07\x00\x02\x02\x02\x02\x02\x07\x00\x8E\x00\x00\x00\xA5\x00\x00\x00\x01\x07\x00\x42\x00\xA6\x00\x06\x07\x00\x02\x02\x02\x02\x02\x07\x00\x8E\x00\x00'
    .end code
.end method

.method public break : (FF)V
    .code stack 0 locals 3
L0:     return
L1:     
    .end code
.end method
.innerclasses
    Ef [0] [0]
.end innerclasses
.end class
