.version 49 0
.class public final super Gd
.super Yd
.field private static final field198 Ljava/lang/String;
.field private try LmG;
.field private field199 LDF;
.field private new LvF;
.field private field200 LDF;
.field private this Ljava/util/Map;
.field private field201 LmG;
.field private static final field202 Ljava/lang/String;
.field private field203 Ljava/util/Map;
.field private static final field204 Ljava/lang/String;

.method public method49 : ()V
    .code stack 5 locals 1
L0:     ldc "Split-screen"
L2:     ldc "VS"
L4:     ldc "Challenges"
L6:     aload_0
L7:     ldc "Training"
L9:     invokespecial Method Yd method12 (Ljava/lang/String;)V
L12:    aload_0
L13:    dup_x1
L14:    invokespecial Method Gd method204 ()Lqc;
L17:    invokevirtual Method Gd method182 (Ljava/lang/String;LgB;)V
L20:    aload_0
L21:    dup_x1
L22:    invokespecial Method Gd method205 ()Lqc;
L25:    invokevirtual Method Gd method182 (Ljava/lang/String;LgB;)V
L28:    aload_0
L29:    dup_x1
L30:    invokespecial Method Gd method211 ()Lqc;
L33:    invokevirtual Method Gd method182 (Ljava/lang/String;LgB;)V
L36:    return
L37:    
    .end code
.end method

.method private method204 : ()Lqc;
    .code stack 11 locals 4
L0:     new qc
L3:     dup
L4:     new VD
L7:     dup
L8:     invokespecial Method VD <init> ()V
L11:    invokespecial Method qc <init> (Ld;)V
L14:    astore_1
L15:    aload_0
L16:    dup
L17:    new DF
L20:    aload_0
L21:    dup_x1
L22:    dup
L23:    pop2
L24:    dup
L25:    ldc ""
L27:    getstatic Field We field467 LWe;
L30:    invokespecial Method DF <init> (Ljava/lang/String;LWe;)V
L33:    putfield Field Gd field200 LDF;
L36:    new DF
L39:    aload_0
L40:    dup_x2
L41:    dup
L42:    pop2
L43:    dup
L44:    ldc ""
L46:    getstatic Field We field479 LWe;
L49:    invokespecial Method DF <init> (Ljava/lang/String;LWe;)V
L52:    putfield Field Gd field199 LDF;
L55:    getfield Field Gd field199 LDF;
L58:    getstatic Field vD new LvD;
L61:    invokevirtual Method DF method610 (LvD;)V
L64:    aload_1
L65:    dup_x1
L66:    aload_0
L67:    getfield Field Gd field200 LDF;
L70:    getstatic Field VD field150 Ljava/lang/Object;
L73:    invokevirtual Method qc method31 (LgB;Ljava/lang/Object;)V
L76:    getfield Field Gd field199 LDF;
L79:    invokevirtual Method qc method36 (LgB;)LgB;
L82:    new PF
L85:    dup
L86:    invokespecial Method PF <init> ()V
L89:    astore_2
L90:    aload_0
L91:    getstatic Field Pc field373 LPc;
L94:    aload_2
L95:    invokevirtual Method PF method494 ()LmG;
L98:    getstatic Field SE field2070 LTe;
L101:   invokespecial Method Gd method210 (LPc;LmG;LTe;)V
L104:   new Qc
L107:   dup
L108:   new VD
L111:   aload_0
L112:   dup_x1
L113:   dup
L114:   pop2
L115:   dup
L116:   invokespecial Method VD <init> ()V
L119:   invokespecial Method Qc <init> (LGd;Ld;)V
L122:   astore_3
L123:   aload_1
L124:   aload_3
L125:   dup_x1
L126:   new SB
L129:   aload_3
L130:   dup
L131:   pop2
L132:   dup
L133:   aload_2
L134:   ldc 1e-1f
L136:   fconst_0
L137:   ldc 3e-1f
L139:   getstatic Field FE field822 F
L142:   invokespecial Method SB <init> (LgB;FFFF)V
L145:   getstatic Field VD field149 Ljava/lang/Object;
L148:   invokevirtual Method qc method31 (LgB;Ljava/lang/Object;)V
L151:   getstatic Field VD field147 Ljava/lang/Object;
L154:   invokevirtual Method qc method31 (LgB;Ljava/lang/Object;)V
L157:   pop
L158:   aload_3
L159:   areturn
L160:   
    .end code
.end method

.method public <init> : ()V
    .code stack 2 locals 1
L0:     aload_0
L1:     ldc Class Gd
L3:     invokespecial Method Yd <init> (Ljava/lang/Class;)V
L6:     return
L7:     
    .end code
.end method

.method public method2 : ()V
    .code stack 2 locals 3
L0:     aload_0
L1:     dup
L2:     invokespecial Method Yd method2 ()V
L5:     getfield Field Gd field203 Ljava/util/Map;
L8:     ifnull L81
L11:    aload_0
L12:    getfield Field Gd field203 Ljava/util/Map;
L15:    invokeinterface InterfaceMethod java/util/Map entrySet ()Ljava/util/Set; 1
L20:    invokeinterface InterfaceMethod java/util/Set iterator ()Ljava/util/Iterator; 1
L25:    astore_1
L26:    aload_1
L27:    invokeinterface InterfaceMethod java/util/Iterator hasNext ()Z 1
L32:    ifeq L81
L35:    aload_1
L36:    invokeinterface InterfaceMethod java/util/Iterator next ()Ljava/lang/Object; 1
L41:    checkcast java/util/Map$Entry
L44:    dup
L45:    astore_2
L46:    invokeinterface InterfaceMethod java/util/Map$Entry getValue ()Ljava/lang/Object; 1
L51:    checkcast Tg
L54:    invokevirtual Method Tg method227 ()Z
L57:    ifeq L26
L60:    ldc "w"
L62:    aload_2
L63:    invokeinterface InterfaceMethod java/util/Map$Entry getKey ()Ljava/lang/Object; 1
L68:    checkcast java/lang/Integer
L71:    invokevirtual Method java/lang/Integer intValue ()I
L74:    invokestatic Method JB method827 (Ljava/lang/String;I)V
L77:    goto L26
L80:    athrow
L81:    aload_0
L82:    getfield Field Gd this Ljava/util/Map;
L85:    ifnull L158
L88:    aload_0
L89:    getfield Field Gd this Ljava/util/Map;
L92:    invokeinterface InterfaceMethod java/util/Map entrySet ()Ljava/util/Set; 1
L97:    invokeinterface InterfaceMethod java/util/Set iterator ()Ljava/util/Iterator; 1
L102:   astore_1
L103:   aload_1
L104:   invokeinterface InterfaceMethod java/util/Iterator hasNext ()Z 1
L109:   ifeq L158
L112:   aload_1
L113:   invokeinterface InterfaceMethod java/util/Iterator next ()Ljava/lang/Object; 1
L118:   checkcast java/util/Map$Entry
L121:   dup
L122:   astore_2
L123:   invokeinterface InterfaceMethod java/util/Map$Entry getValue ()Ljava/lang/Object; 1
L128:   checkcast Tg
L131:   invokevirtual Method Tg method227 ()Z
L134:   ifeq L103
L137:   ldc "twpm"
L139:   aload_2
L140:   invokeinterface InterfaceMethod java/util/Map$Entry getKey ()Ljava/lang/Object; 1
L145:   checkcast java/lang/Integer
L148:   invokevirtual Method java/lang/Integer intValue ()I
L151:   invokestatic Method JB method827 (Ljava/lang/String;I)V
L154:   goto L103
L157:   athrow
L158:   return
L159:   
        .attribute StackMap b'\x00\x06\x00\x1A\x00\x02\x07\x00\x02\x07\x00\xC6\x00\x00\x00\x50\x00\x00\x00\x01\x07\x00\xEB\x00\x51\x00\x01\x07\x00\x02\x00\x00\x00\x67\x00\x02\x07\x00\x02\x07\x00\xC6\x00\x00\x00\x9D\x00\x00\x00\x01\x07\x00\xEB\x00\x9E\x00\x01\x07\x00\x02\x00\x00'
    .end code
.end method

.method private method205 : ()Lqc;
    .code stack 15 locals 9
L0:     new qc
L3:     dup
L4:     new og
L7:     dup
L8:     bipush 7
L10:    iconst_1
L11:    dup
L12:    pop2
L13:    ldc 1e-1f
L15:    dup
L16:    invokespecial Method og <init> (IFF)V
L19:    invokespecial Method qc <init> (Ld;)V
L22:    astore_1
L23:    new Pg
L26:    dup
L27:    ldc "Auto-adjust difficulty"
L29:    ldc "v"
L31:    invokestatic Method JB method831 (Ljava/lang/String;)I
L34:    ifeq L45
L37:    iconst_1
L38:    dup
L39:    dup
L40:    pop2
L41:    goto L49
L44:    athrow
L45:    iconst_0
L46:    iconst_1
L47:    dup
L48:    pop2
L49:    getstatic Field We new LWe;
L52:    invokespecial Method Pg <init> (Ljava/lang/String;ZLWe;)V
L55:    astore_2
L56:    new kC
L59:    aload_2
L60:    dup_x1
L61:    dup
L62:    pop2
L63:    dup
L64:    aload_0
L65:    aload_2
L66:    invokespecial Method kC <init> (LGd;LPg;)V
L69:    invokevirtual Method Pg method130 (Lh;)V
L72:    new DF
L75:    dup
L76:    ldc_w "0"
L79:    invokespecial Method DF <init> (Ljava/lang/String;)V
L82:    dup
L83:    astore_3
L84:    getstatic Field vD field359 LvD;
L87:    invokevirtual Method DF method610 (LvD;)V
L90:    new zD
L93:    dup
L94:    iconst_0
L95:    iconst_1
L96:    dup
L97:    pop2
L98:    sipush 1000
L101:   iconst_1
L102:   dup
L103:   pop2
L104:   ldc_w 1.6e1f
L107:   invokespecial Method zD <init> (IIF)V
L110:   astore 4
L112:   ldc_w "t"
L115:   new pd
L118:   aload 4
L120:   dup_x2
L121:   dup_x1
L122:   dup
L123:   pop2
L124:   dup
L125:   aload_0
L126:   aload_3
L127:   aload 4
L129:   aload_1
L130:   invokespecial Method pd <init> (LGd;LDF;LzD;Lqc;)V
L133:   invokevirtual Method zD method128 (Lh;)V
L136:   invokestatic Method JB method831 (Ljava/lang/String;)I
L139:   invokevirtual Method zD method14 (I)V
L142:   new DF
L145:   aload_1
L146:   dup_x1
L147:   dup
L148:   pop2
L149:   dup
L150:   ldc_w "Opponents"
L153:   invokespecial Method DF <init> (Ljava/lang/String;)V
L156:   invokevirtual Method qc method36 (LgB;)LgB;
L159:   aload_1
L160:   aload 4
L162:   iconst_4
L163:   iconst_1
L164:   dup
L165:   pop2
L166:   invokestatic Method java/lang/Integer valueOf (I)Ljava/lang/Integer;
L169:   invokevirtual Method qc method31 (LgB;Ljava/lang/Object;)V
L172:   new SB
L175:   aload_1
L176:   dup_x1
L177:   dup
L178:   pop2
L179:   dup
L180:   aload_3
L181:   ldc_w 2e-1f
L184:   fconst_0
L185:   dup
L186:   dup_x1
L187:   invokespecial Method SB <init> (LgB;FFFF)V
L190:   invokevirtual Method qc method36 (LgB;)LgB;
L193:   new Vg
L196:   aload_1
L197:   dup_x1
L198:   dup
L199:   pop2
L200:   dup
L201:   invokespecial Method Vg <init> ()V
L204:   invokevirtual Method qc method36 (LgB;)LgB;
L207:   new Vg
L210:   aload_1
L211:   dup_x1
L212:   dup_x2
L213:   dup
L214:   pop2
L215:   dup
L216:   fconst_0
L217:   ldc_w 5e-1f
L220:   invokespecial Method Vg <init> (FF)V
L223:   bipush 7
L225:   iconst_1
L226:   dup
L227:   pop2
L228:   invokestatic Method java/lang/Integer valueOf (I)Ljava/lang/Integer;
L231:   invokevirtual Method qc method31 (LgB;Ljava/lang/Object;)V
L234:   new DF
L237:   dup
L238:   ldc ""
L240:   invokespecial Method DF <init> (Ljava/lang/String;)V
L243:   astore_3
L244:   new zD
L247:   dup
L248:   iconst_0
L249:   iconst_1
L250:   dup
L251:   pop2
L252:   sipush 399
L255:   iconst_1
L256:   dup
L257:   pop2
L258:   ldc_w 1.6e1f
L261:   invokespecial Method zD <init> (IIF)V
L264:   dup
L265:   astore 5
L267:   dup
L268:   ldc_w "u"
L271:   aload 5
L273:   dup_x2
L274:   new Nc
L277:   aload 5
L279:   dup
L280:   pop2
L281:   dup
L282:   aload_0
L283:   aload 5
L285:   aload_3
L286:   aload_1
L287:   invokespecial Method Nc <init> (LGd;LzD;LDF;Lqc;)V
L290:   invokevirtual Method zD method128 (Lh;)V
L293:   invokestatic Method JB method831 (Ljava/lang/String;)I
L296:   istore 6
L298:   iconst_0
L299:   iconst_1
L300:   dup
L301:   pop2
L302:   invokevirtual Method zD method14 (I)V
L305:   iconst_1
L306:   dup
L307:   dup
L308:   pop2
L309:   invokevirtual Method zD method14 (I)V
L312:   iload 6
L314:   invokevirtual Method zD method14 (I)V
L317:   new DF
L320:   aload_1
L321:   dup
L322:   pop2
L323:   dup
L324:   ldc_w "Difficulty"
L327:   invokespecial Method DF <init> (Ljava/lang/String;)V
L330:   invokevirtual Method qc method36 (LgB;)LgB;
L333:   aload_1
L334:   aload 5
L336:   iconst_4
L337:   iconst_1
L338:   dup
L339:   pop2
L340:   invokestatic Method java/lang/Integer valueOf (I)Ljava/lang/Integer;
L343:   invokevirtual Method qc method31 (LgB;Ljava/lang/Object;)V
L346:   new SB
L349:   aload_1
L350:   dup_x1
L351:   dup
L352:   pop2
L353:   dup
L354:   aload_3
L355:   ldc_w 2e-1f
L358:   fconst_0
L359:   dup
L360:   dup_x1
L361:   invokespecial Method SB <init> (LgB;FFFF)V
L364:   invokevirtual Method qc method36 (LgB;)LgB;
L367:   new Vg
L370:   aload_1
L371:   dup_x1
L372:   dup
L373:   pop2
L374:   dup
L375:   invokespecial Method Vg <init> ()V
L378:   invokevirtual Method qc method36 (LgB;)LgB;
L381:   new Vg
L384:   aload_1
L385:   dup_x1
L386:   dup
L387:   pop2
L388:   dup
L389:   invokespecial Method Vg <init> ()V
L392:   invokevirtual Method qc method36 (LgB;)LgB;
L395:   aload_1
L396:   aload_2
L397:   bipush 6
L399:   iconst_1
L400:   dup
L401:   pop2
L402:   invokestatic Method java/lang/Integer valueOf (I)Ljava/lang/Integer;
L405:   invokevirtual Method qc method31 (LgB;Ljava/lang/Object;)V
L408:   new Vg
L411:   aload_1
L412:   dup_x1
L413:   dup
L414:   pop2
L415:   dup
L416:   fconst_0
L417:   ldc_w 5e-1f
L420:   invokespecial Method Vg <init> (FF)V
L423:   bipush 7
L425:   iconst_1
L426:   dup
L427:   pop2
L428:   invokestatic Method java/lang/Integer valueOf (I)Ljava/lang/Integer;
L431:   invokevirtual Method qc method31 (LgB;Ljava/lang/Object;)V
L434:   new qc
L437:   dup
L438:   new og
L441:   dup
L442:   iconst_1
L443:   dup
L444:   dup
L445:   pop2
L446:   fconst_0
L447:   ldc_w 2e-1f
L450:   invokespecial Method og <init> (IFF)V
L453:   invokespecial Method qc <init> (Ld;)V
L456:   astore_3
L457:   new java/util/HashMap
L460:   aload_0
L461:   dup_x1
L462:   dup
L463:   pop2
L464:   dup
L465:   invokespecial Method java/util/HashMap <init> ()V
L468:   putfield Field Gd field203 Ljava/util/Map;
L471:   getstatic Field GF field1804 Ljava/util/HashMap;
L474:   invokevirtual Method java/util/HashMap entrySet ()Ljava/util/Set;
L477:   invokeinterface InterfaceMethod java/util/Set iterator ()Ljava/util/Iterator; 1
L482:   astore 6
L484:   pop
L485:   pop2
L486:   pop2
L487:   pop2
L488:   aload 6
L490:   invokeinterface InterfaceMethod java/util/Iterator hasNext ()Z 1
L495:   ifeq L574
L498:   aload 6
L500:   invokeinterface InterfaceMethod java/util/Iterator next ()Ljava/lang/Object; 1
L505:   checkcast java/util/Map$Entry
L508:   astore 7
L510:   aload_0
L511:   getfield Field Gd field203 Ljava/util/Map;
L514:   aload 7
L516:   invokeinterface InterfaceMethod java/util/Map$Entry getKey ()Ljava/lang/Object; 1
L521:   new Tg
L524:   dup
L525:   aload 7
L527:   invokeinterface InterfaceMethod java/util/Map$Entry getValue ()Ljava/lang/Object; 1
L532:   checkcast java/lang/String
L535:   invokespecial Method Tg <init> (Ljava/lang/String;)V
L538:   invokeinterface InterfaceMethod java/util/Map put (Ljava/lang/Object;Ljava/lang/Object;)Ljava/lang/Object; 3
L543:   pop
L544:   aload_3
L545:   aload_0
L546:   getfield Field Gd field203 Ljava/util/Map;
L549:   aload 7
L551:   invokeinterface InterfaceMethod java/util/Map$Entry getKey ()Ljava/lang/Object; 1
L556:   invokeinterface InterfaceMethod java/util/Map get (Ljava/lang/Object;)Ljava/lang/Object; 2
L561:   checkcast gB
L564:   invokevirtual Method qc method36 (LgB;)LgB;
L567:   pop
L568:   aload 6
L570:   goto L490
L573:   athrow
        .catch java/lang/NullPointerException from L574 to L597 using L600
L574:   aload_0
L575:   getfield Field Gd field203 Ljava/util/Map;
L578:   ldc "w"
L580:   invokestatic Method JB method831 (Ljava/lang/String;)I
L583:   invokestatic Method java/lang/Integer valueOf (I)Ljava/lang/Integer;
L586:   invokeinterface InterfaceMethod java/util/Map get (Ljava/lang/Object;)Ljava/lang/Object; 2
L591:   checkcast Tg
L594:   invokevirtual Method Tg method56 ()V
L597:   goto L627
L600:   astore 6
L602:   aload_0
L603:   getfield Field Gd field203 Ljava/util/Map;
L606:   invokeinterface InterfaceMethod java/util/Map values ()Ljava/util/Collection; 1
L611:   invokeinterface InterfaceMethod java/util/Collection iterator ()Ljava/util/Iterator; 1
L616:   invokeinterface InterfaceMethod java/util/Iterator next ()Ljava/lang/Object; 1
L621:   checkcast Tg
L624:   invokevirtual Method Tg method56 ()V
L627:   new DF
L630:   dup
L631:   ldc_w "Game mode"
L634:   invokespecial Method DF <init> (Ljava/lang/String;)V
L637:   astore 6
L639:   aload_1
L640:   aload 6
L642:   dup
L643:   getstatic Field vD new LvD;
L646:   invokevirtual Method DF method610 (LvD;)V
L649:   invokevirtual Method qc method36 (LgB;)LgB;
L652:   aload_1
L653:   aload_3
L654:   iconst_4
L655:   iconst_1
L656:   dup
L657:   pop2
L658:   invokestatic Method java/lang/Integer valueOf (I)Ljava/lang/Integer;
L661:   invokevirtual Method qc method31 (LgB;Ljava/lang/Object;)V
L664:   new Yg
L667:   dup
L668:   ldc_w "Start game"
L671:   new Pb
L674:   dup
L675:   aload_0
L676:   aload 4
L678:   aload 5
L680:   aload_2
L681:   invokespecial Method Pb <init> (LGd;LzD;LzD;LPg;)V
L684:   invokespecial Method Yg <init> (Ljava/lang/String;Lh;)V
L687:   astore 7
L689:   new DF
L692:   dup
L693:   ldc_w "Improve your skills by playing against the computer. Difficulty may impact FPS."
L696:   invokespecial Method DF <init> (Ljava/lang/String;)V
L699:   astore_2
L700:   iconst_1
L701:   aload_2
L702:   dup_x1
L703:   getstatic Field vD new LvD;
L706:   invokevirtual Method DF method610 (LvD;)V
L709:   iconst_1
L710:   dup
L711:   pop2
L712:   invokevirtual Method DF method95 (Z)V
L715:   pop
L716:   iconst_4
L717:   iconst_1
L718:   dup
L719:   pop2
L720:   aload_0
L721:   getfield Field Gd field203 Ljava/util/Map;
L724:   invokeinterface InterfaceMethod java/util/Map size ()I 1
L729:   iadd
L730:   iconst_1
L731:   dup
L732:   dup
L733:   pop2
L734:   multianewarray [[LgB; 2
L738:   astore_3
L739:   aload_0
L740:   iconst_0
L741:   iconst_1
L742:   aload_3
L743:   dup_x1
L744:   iconst_0
L745:   iconst_1
L746:   dup
L747:   pop2
L748:   aaload
L749:   iconst_0
L750:   iconst_1
L751:   dup
L752:   pop2
L753:   aload 4
L755:   aastore
L756:   iconst_1
L757:   dup
L758:   pop2
L759:   aaload
L760:   iconst_0
L761:   iconst_1
L762:   dup
L763:   pop2
L764:   aload 5
L766:   aastore
L767:   iconst_1
L768:   dup
L769:   pop2
L770:   istore 5
L772:   getfield Field Gd field203 Ljava/util/Map;
L775:   invokeinterface InterfaceMethod java/util/Map values ()Ljava/util/Collection; 1
L780:   invokeinterface InterfaceMethod java/util/Collection iterator ()Ljava/util/Iterator; 1
L785:   dup
L786:   astore 6
L788:   invokeinterface InterfaceMethod java/util/Iterator hasNext ()Z 1
L793:   ifeq L832
L796:   aload 6
L798:   invokeinterface InterfaceMethod java/util/Iterator next ()Ljava/lang/Object; 1
L803:   checkcast Tg
L806:   astore 8
L808:   aload 6
L810:   aload_3
L811:   iconst_2
L812:   iconst_1
L813:   dup
L814:   pop2
L815:   iload 5
L817:   iadd
L818:   aaload
L819:   iconst_0
L820:   iconst_1
L821:   dup
L822:   pop2
L823:   aload 8
L825:   iinc 5 1
L828:   aastore
L829:   goto L788
L832:   aload_3
L833:   iconst_3
L834:   aload_3
L835:   dup_x1
L836:   iconst_2
L837:   iconst_1
L838:   dup
L839:   pop2
L840:   aload_0
L841:   getfield Field Gd field203 Ljava/util/Map;
L844:   invokeinterface InterfaceMethod java/util/Map size ()I 1
L849:   iadd
L850:   aaload
L851:   iconst_0
L852:   iconst_1
L853:   dup
L854:   pop2
L855:   aload 7
L857:   aastore
L858:   iconst_1
L859:   dup
L860:   pop2
L861:   aload_0
L862:   getfield Field Gd field203 Ljava/util/Map;
L865:   invokeinterface InterfaceMethod java/util/Map size ()I 1
L870:   iadd
L871:   aaload
L872:   iconst_0
L873:   iconst_1
L874:   dup
L875:   pop2
L876:   aload 4
L878:   aastore
L879:   invokestatic Method mC method1702 ([[LgB;)V
L882:   new Fd
L885:   dup
L886:   new fG
L889:   aload_0
L890:   dup_x1
L891:   dup
L892:   pop2
L893:   dup
L894:   getstatic Field LE field634 LLE;
L897:   ldc 1e-1f
L899:   invokespecial Method fG <init> (LLE;F)V
L902:   aload 7
L904:   invokespecial Method Fd <init> (LGd;Ld;LYg;)V
L907:   dup
L908:   astore 6
L910:   dup
L911:   new SB
L914:   aload 6
L916:   dup_x1
L917:   dup
L918:   pop2
L919:   dup
L920:   aload_2
L921:   ldc_w 2e-1f
L924:   invokespecial Method SB <init> (LgB;F)V
L927:   getstatic Field dg field337 Ldg;
L930:   invokevirtual Method qc method31 (LgB;Ljava/lang/Object;)V
L933:   new SB
L936:   aload 6
L938:   dup_x2
L939:   dup
L940:   pop2
L941:   dup
L942:   aload_1
L943:   ldc_w 2e-1f
L946:   invokespecial Method SB <init> (LgB;F)V
L949:   getstatic Field dg field337 Ldg;
L952:   invokevirtual Method qc method31 (LgB;Ljava/lang/Object;)V
L955:   new SB
L958:   aload 6
L960:   dup
L961:   pop2
L962:   dup
L963:   aload 7
L965:   ldc_w 2e-1f
L968:   dup
L969:   fconst_0
L970:   dup_x2
L971:   invokespecial Method SB <init> (LgB;FFFF)V
L974:   getstatic Field dg this Ldg;
L977:   invokevirtual Method qc method31 (LgB;Ljava/lang/Object;)V
L980:   areturn
L981:   
        .attribute StackMap b'\x00\x0A\x00\x2C\x00\x00\x00\x01\x07\x00\xEB\x00\x2D\x00\x02\x07\x00\x02\x07\x00\x5C\x00\x03\x08\x00\x17\x08\x00\x17\x07\x01\x42\x00\x31\x00\x02\x07\x00\x02\x07\x00\x5C\x00\x04\x08\x00\x17\x08\x00\x17\x07\x01\x42\x01\x01\xEA\x00\x07\x07\x00\x02\x07\x00\x5C\x07\x00\xF4\x07\x00\x5C\x07\x01\x11\x07\x01\x11\x07\x00\xC6\x00\x01\x07\x00\xC6\x02\x3D\x00\x00\x00\x01\x07\x00\xEB\x02\x3E\x00\x07\x07\x00\x02\x07\x00\x5C\x07\x00\xF4\x07\x00\x5C\x07\x01\x11\x07\x01\x11\x07\x00\xC6\x00\x00\x02\x58\x00\x07\x07\x00\x02\x07\x00\x5C\x07\x00\xF4\x07\x00\x5C\x07\x01\x11\x07\x01\x11\x07\x00\xC6\x00\x01\x07\x00\xED\x02\x73\x00\x07\x07\x00\x02\x07\x00\x5C\x07\x00\xF4\x07\x00\x5C\x07\x01\x11\x07\x01\x11\x07\x01\x89\x00\x00\x03\x14\x00\x08\x07\x00\x02\x07\x00\x5C\x07\x00\x2F\x07\x01\x6E\x07\x01\x11\x01\x07\x00\xC6\x07\x01\x5B\x00\x01\x07\x00\xC6\x03\x40\x00\x08\x07\x00\x02\x07\x00\x5C\x07\x00\x2F\x07\x01\x6E\x07\x01\x11\x01\x07\x00\xC6\x07\x01\x5B\x00\x00'
    .end code
.end method

.method public static synthetic method206 : (LGd;)LFE;
    .code stack 1 locals 1
L0:     aload_0
L1:     getfield Field Gd field1136 LFE;
L4:     areturn
L5:     
    .end code
.end method

.method public method74 : ()V
    .code stack 5 locals 1
L0:     aload_0
L1:     getfield Field Gd field1136 LFE;
L4:     new cb
L7:     aload_0
L8:     dup_x1
L9:     dup
L10:    pop2
L11:    dup
L12:    invokespecial Method cb <init> ()V
L15:    invokevirtual Method FE method455 (LbC;LbC;)V
L18:    return
L19:    
    .end code
.end method

.method public static synthetic method207 : (LGd;LTe;)V
    .code stack 2 locals 2
L0:     aload_0
L1:     aload_1
L2:     invokespecial Method Gd method216 (LTe;)V
L5:     return
L6:     
    .end code
.end method

.method public static synthetic method208 : (LGd;)Ljava/util/Map;
    .code stack 1 locals 1
L0:     aload_0
L1:     getfield Field Gd field203 Ljava/util/Map;
L4:     areturn
L5:     
    .end code
.end method

.method public static synthetic method209 : (LGd;)Ljava/util/Map;
    .code stack 1 locals 1
L0:     aload_0
L1:     getfield Field Gd this Ljava/util/Map;
L4:     areturn
L5:     
    .end code
.end method

.method private method210 : (LPc;LmG;LTe;)V
    .code stack 7 locals 6
L0:     aload_3
L1:     aload_1
L2:     invokevirtual Method Te method1053 (LPc;)Z
L5:     ifne L54
L8:     aload_3
L9:     getfield Field Te field2119 Ljava/util/LinkedList;
L12:    invokevirtual Method java/util/LinkedList iterator ()Ljava/util/Iterator;
L15:    dup
L16:    astore 4
L18:    invokeinterface InterfaceMethod java/util/Iterator hasNext ()Z 1
L23:    ifeq L52
L26:    aload 4
L28:    invokeinterface InterfaceMethod java/util/Iterator next ()Ljava/lang/Object; 1
L33:    checkcast Te
L36:    astore 5
L38:    aload 4
L40:    aload_0
L41:    aload_1
L42:    aload_2
L43:    aload 5
L45:    invokespecial Method Gd method210 (LPc;LmG;LTe;)V
L48:    goto L18
L51:    athrow
L52:    return
L53:    athrow
L54:    aload_2
L55:    dup
L56:    new WB
L59:    dup
L60:    aload_0
L61:    aload_3
L62:    invokespecial Method WB <init> (LGd;LTe;)V
L65:    invokevirtual Method mG method516 (Lh;)V
L68:    new MD
L71:    aload_2
L72:    dup
L73:    pop2
L74:    dup
L75:    aload_0
L76:    aload_3
L77:    aload_1
L78:    invokespecial Method MD <init> (LGd;LTe;LPc;)V
L81:    invokevirtual Method mG method593 (Lh;)V
L84:    aload_3
L85:    aload_1
L86:    invokevirtual Method Te method1059 (LPc;)Z
L89:    ifeq L223
L92:    ldc_w "\u2606"
L95:    astore 4
L97:    aload_3
L98:    aload_1
L99:    invokevirtual Method Te method1057 (LPc;)Z
L102:   ifeq L113
L105:   ldc_w "\u2605"
L108:   astore 4
L110:   goto L139
L113:   aload_0
L114:   getfield Field Gd field201 LmG;
L117:   ifnull L134
L120:   aload_0
L121:   getfield Field Gd field201 LmG;
L124:   invokevirtual Method mG method183 ()I
L127:   aload_2
L128:   invokevirtual Method mG method183 ()I
L131:   if_icmpge L139
L134:   aload_0
L135:   aload_2
L136:   putfield Field Gd field201 LmG;
L139:   new vF
L142:   dup
L143:   aload 4
L145:   fconst_0
L146:   dup
L147:   invokespecial Method vF <init> (Ljava/lang/String;FF)V
L150:   astore 5
L152:   aload_3
L153:   aload_1
L154:   invokevirtual Method Te method1057 (LPc;)Z
L157:   ifeq L170
L160:   aload 5
L162:   ldc 1e-1f
L164:   fconst_1
L165:   dup_x1
L166:   dup_x2
L167:   invokevirtual Method vF method464 (FFFF)V
L170:   aload_3
L171:   getstatic Field Te field2116 Ljava/util/Map;
L174:   aload_1
L175:   invokeinterface InterfaceMethod java/util/Map get (Ljava/lang/Object;)Ljava/lang/Object; 2
L180:   if_acmpne L194
L183:   aload_3
L184:   aload_0
L185:   dup_x1
L186:   aload 5
L188:   putfield Field Gd new LvF;
L191:   invokespecial Method Gd method216 (LTe;)V
L194:   aload_2
L195:   aload 5
L197:   invokevirtual Method mG method632 (Lid;)V
L200:   aload_3
L201:   getstatic Field Te this Ljava/util/Map;
L204:   getstatic Field Pc field373 LPc;
L207:   invokeinterface InterfaceMethod java/util/Map get (Ljava/lang/Object;)Ljava/lang/Object; 2
L212:   if_acmpne L262
L215:   aload_0
L216:   aload_2
L217:   putfield Field Gd try LmG;
L220:   goto L262
L223:   new vF
L226:   dup
L227:   ldc_w "\u2716"
L230:   fconst_0
L231:   dup
L232:   invokespecial Method vF <init> (Ljava/lang/String;FF)V
L235:   astore 4
L237:   aload_2
L238:   dup
L239:   aload 4
L241:   ldc_w 2e-1f
L244:   dup
L245:   dup_x1
L246:   fconst_1
L247:   invokevirtual Method vF method464 (FFFF)V
L250:   aload 4
L252:   invokevirtual Method mG method632 (Lid;)V
L255:   iconst_0
L256:   iconst_1
L257:   dup
L258:   pop2
L259:   invokevirtual Method mG method238 (Z)V
L262:   aload_3
L263:   getfield Field Te field2119 Ljava/util/LinkedList;
L266:   invokevirtual Method java/util/LinkedList iterator ()Ljava/util/Iterator;
L269:   dup
L270:   astore 4
L272:   invokeinterface InterfaceMethod java/util/Iterator hasNext ()Z 1
L277:   ifeq L308
L280:   aload 4
L282:   invokeinterface InterfaceMethod java/util/Iterator next ()Ljava/lang/Object; 1
L287:   checkcast Te
L290:   astore 5
L292:   aload 4
L294:   aload_0
L295:   aload_1
L296:   aload_2
L297:   invokevirtual Method mG method630 ()LmG;
L300:   aload 5
L302:   invokespecial Method Gd method210 (LPc;LmG;LTe;)V
L305:   goto L272
L308:   return
L309:   
        .attribute StackMap b'\x00\x0E\x00\x12\x00\x05\x07\x00\x02\x07\x00\x14\x07\x00\x27\x07\x01\xA2\x07\x00\xC6\x00\x01\x07\x00\xC6\x00\x33\x00\x00\x00\x01\x07\x00\xEB\x00\x34\x00\x05\x07\x00\x02\x07\x00\x14\x07\x00\x27\x07\x01\xA2\x07\x00\xC6\x00\x00\x00\x35\x00\x00\x00\x01\x07\x00\xEB\x00\x36\x00\x04\x07\x00\x02\x07\x00\x14\x07\x00\x27\x07\x01\xA2\x00\x00\x00\x71\x00\x05\x07\x00\x02\x07\x00\x14\x07\x00\x27\x07\x01\xA2\x07\x01\x42\x00\x00\x00\x86\x00\x05\x07\x00\x02\x07\x00\x14\x07\x00\x27\x07\x01\xA2\x07\x01\x42\x00\x00\x00\x8B\x00\x05\x07\x00\x02\x07\x00\x14\x07\x00\x27\x07\x01\xA2\x07\x01\x42\x00\x00\x00\xAA\x00\x06\x07\x00\x02\x07\x00\x14\x07\x00\x27\x07\x01\xA2\x07\x01\x42\x07\x01\xC9\x00\x00\x00\xC2\x00\x06\x07\x00\x02\x07\x00\x14\x07\x00\x27\x07\x01\xA2\x07\x01\x42\x07\x01\xC9\x00\x00\x00\xDF\x00\x04\x07\x00\x02\x07\x00\x14\x07\x00\x27\x07\x01\xA2\x00\x00\x01\x06\x00\x05\x07\x00\x02\x07\x00\x14\x07\x00\x27\x07\x01\xA2\x07\x01\x89\x00\x00\x01\x10\x00\x05\x07\x00\x02\x07\x00\x14\x07\x00\x27\x07\x01\xA2\x07\x00\xC6\x00\x01\x07\x00\xC6\x01\x34\x00\x05\x07\x00\x02\x07\x00\x14\x07\x00\x27\x07\x01\xA2\x07\x00\xC6\x00\x00'
    .end code
.end method

.method private method211 : ()Lqc;
    .code stack 7 locals 8
L0:     new qc
L3:     dup
L4:     new og
L7:     dup
L8:     bipush 7
L10:    iconst_1
L11:    dup
L12:    pop2
L13:    ldc 1e-1f
L15:    ldc_w 4e-1f
L18:    invokespecial Method og <init> (IFF)V
L21:    invokespecial Method qc <init> (Ld;)V
L24:    astore_1
L25:    new qc
L28:    dup
L29:    new og
L32:    dup
L33:    iconst_1
L34:    dup
L35:    dup
L36:    pop2
L37:    fconst_0
L38:    ldc_w 2e-1f
L41:    invokespecial Method og <init> (IFF)V
L44:    invokespecial Method qc <init> (Ld;)V
L47:    astore_2
L48:    new java/util/HashMap
L51:    aload_0
L52:    dup_x1
L53:    dup
L54:    pop2
L55:    dup
L56:    invokespecial Method java/util/HashMap <init> ()V
L59:    putfield Field Gd this Ljava/util/Map;
L62:    getstatic Field GF field1804 Ljava/util/HashMap;
L65:    invokevirtual Method java/util/HashMap entrySet ()Ljava/util/Set;
L68:    invokeinterface InterfaceMethod java/util/Set iterator ()Ljava/util/Iterator; 1
L73:    dup
L74:    astore_3
L75:    invokeinterface InterfaceMethod java/util/Iterator hasNext ()Z 1
L80:    ifeq L157
L83:    aload_3
L84:    invokeinterface InterfaceMethod java/util/Iterator next ()Ljava/lang/Object; 1
L89:    checkcast java/util/Map$Entry
L92:    astore 4
L94:    aload_0
L95:    getfield Field Gd this Ljava/util/Map;
L98:    aload 4
L100:   invokeinterface InterfaceMethod java/util/Map$Entry getKey ()Ljava/lang/Object; 1
L105:   new Tg
L108:   dup
L109:   aload 4
L111:   invokeinterface InterfaceMethod java/util/Map$Entry getValue ()Ljava/lang/Object; 1
L116:   checkcast java/lang/String
L119:   invokespecial Method Tg <init> (Ljava/lang/String;)V
L122:   invokeinterface InterfaceMethod java/util/Map put (Ljava/lang/Object;Ljava/lang/Object;)Ljava/lang/Object; 3
L127:   pop
L128:   aload_2
L129:   aload_0
L130:   getfield Field Gd this Ljava/util/Map;
L133:   aload 4
L135:   invokeinterface InterfaceMethod java/util/Map$Entry getKey ()Ljava/lang/Object; 1
L140:   invokeinterface InterfaceMethod java/util/Map get (Ljava/lang/Object;)Ljava/lang/Object; 2
L145:   checkcast gB
L148:   invokevirtual Method qc method36 (LgB;)LgB;
L151:   pop
L152:   aload_3
L153:   goto L75
L156:   athrow
        .catch java/lang/NullPointerException from L157 to L180 using L184
L157:   aload_0
L158:   getfield Field Gd this Ljava/util/Map;
L161:   ldc "twpm"
L163:   invokestatic Method JB method831 (Ljava/lang/String;)I
L166:   invokestatic Method java/lang/Integer valueOf (I)Ljava/lang/Integer;
L169:   invokeinterface InterfaceMethod java/util/Map get (Ljava/lang/Object;)Ljava/lang/Object; 2
L174:   checkcast Tg
L177:   invokevirtual Method Tg method56 ()V
L180:   goto L210
L183:   athrow
L184:   astore_3
L185:   aload_0
L186:   getfield Field Gd this Ljava/util/Map;
L189:   invokeinterface InterfaceMethod java/util/Map values ()Ljava/util/Collection; 1
L194:   invokeinterface InterfaceMethod java/util/Collection iterator ()Ljava/util/Iterator; 1
L199:   invokeinterface InterfaceMethod java/util/Iterator next ()Ljava/lang/Object; 1
L204:   checkcast Tg
L207:   invokevirtual Method Tg method56 ()V
L210:   new DF
L213:   dup
L214:   ldc_w "Game mode"
L217:   invokespecial Method DF <init> (Ljava/lang/String;)V
L220:   astore_3
L221:   aload_1
L222:   aload_3
L223:   dup
L224:   getstatic Field vD new LvD;
L227:   invokevirtual Method DF method610 (LvD;)V
L230:   invokevirtual Method qc method36 (LgB;)LgB;
L233:   aload_1
L234:   aload_2
L235:   bipush 6
L237:   iconst_1
L238:   dup
L239:   pop2
L240:   invokestatic Method java/lang/Integer valueOf (I)Ljava/lang/Integer;
L243:   invokevirtual Method qc method31 (LgB;Ljava/lang/Object;)V
L246:   new Yg
L249:   dup
L250:   ldc_w "Start game"
L253:   new hD
L256:   dup
L257:   aload_0
L258:   invokespecial Method hD <init> (LGd;)V
L261:   invokespecial Method Yg <init> (Ljava/lang/String;Lh;)V
L264:   astore 4
L266:   new DF
L269:   dup
L270:   ldc_w "Play against your fellow comrade."
L273:   invokespecial Method DF <init> (Ljava/lang/String;)V
L276:   astore_2
L277:   iconst_1
L278:   aload_2
L279:   dup_x1
L280:   getstatic Field vD new LvD;
L283:   invokevirtual Method DF method610 (LvD;)V
L286:   iconst_1
L287:   dup
L288:   pop2
L289:   invokevirtual Method DF method95 (Z)V
L292:   pop
L293:   iconst_2
L294:   iconst_1
L295:   dup
L296:   pop2
L297:   aload_0
L298:   getfield Field Gd this Ljava/util/Map;
L301:   invokeinterface InterfaceMethod java/util/Map size ()I 1
L306:   iadd
L307:   iconst_1
L308:   dup
L309:   dup
L310:   pop2
L311:   multianewarray [[LgB; 2
L315:   astore_3
L316:   iconst_0
L317:   iconst_1
L318:   dup
L319:   pop2
L320:   istore 5
L322:   aload_0
L323:   getfield Field Gd this Ljava/util/Map;
L326:   invokeinterface InterfaceMethod java/util/Map values ()Ljava/util/Collection; 1
L331:   invokeinterface InterfaceMethod java/util/Collection iterator ()Ljava/util/Iterator; 1
L336:   dup
L337:   astore 6
L339:   invokeinterface InterfaceMethod java/util/Iterator hasNext ()Z 1
L344:   ifeq L378
L347:   aload 6
L349:   invokeinterface InterfaceMethod java/util/Iterator next ()Ljava/lang/Object; 1
L354:   checkcast Tg
L357:   astore 7
L359:   aload 6
L361:   aload_3
L362:   iload 5
L364:   aaload
L365:   iconst_0
L366:   iconst_1
L367:   dup
L368:   pop2
L369:   aload 7
L371:   iinc 5 1
L374:   aastore
L375:   goto L339
L378:   aload_3
L379:   aload_3
L380:   iconst_0
L381:   iconst_1
L382:   dup_x2
L383:   dup
L384:   pop2
L385:   aload_0
L386:   getfield Field Gd this Ljava/util/Map;
L389:   invokeinterface InterfaceMethod java/util/Map size ()I 1
L394:   iadd
L395:   aaload
L396:   iconst_0
L397:   iconst_1
L398:   dup
L399:   pop2
L400:   aload 4
L402:   aastore
L403:   iconst_1
L404:   dup
L405:   pop2
L406:   aload_0
L407:   getfield Field Gd this Ljava/util/Map;
L410:   invokeinterface InterfaceMethod java/util/Map size ()I 1
L415:   iadd
L416:   aaload
L417:   iconst_0
L418:   iconst_1
L419:   dup
L420:   pop2
L421:   aload_0
L422:   getfield Field Gd this Ljava/util/Map;
L425:   invokeinterface InterfaceMethod java/util/Map values ()Ljava/util/Collection; 1
L430:   invokeinterface InterfaceMethod java/util/Collection iterator ()Ljava/util/Iterator; 1
L435:   invokeinterface InterfaceMethod java/util/Iterator next ()Ljava/lang/Object; 1
L440:   checkcast gB
L443:   aastore
L444:   aload_3
L445:   invokestatic Method mC method1702 ([[LgB;)V
L448:   new BC
L451:   dup
L452:   new fG
L455:   aload_0
L456:   dup_x1
L457:   dup
L458:   pop2
L459:   dup
L460:   getstatic Field LE field634 LLE;
L463:   ldc 1e-1f
L465:   invokespecial Method fG <init> (LLE;F)V
L468:   aload 4
L470:   invokespecial Method BC <init> (LGd;Ld;LYg;)V
L473:   dup
L474:   astore 6
L476:   dup
L477:   new SB
L480:   aload 6
L482:   dup_x1
L483:   dup
L484:   pop2
L485:   dup
L486:   aload_2
L487:   ldc_w 2e-1f
L490:   invokespecial Method SB <init> (LgB;F)V
L493:   getstatic Field dg field337 Ldg;
L496:   invokevirtual Method qc method31 (LgB;Ljava/lang/Object;)V
L499:   new SB
L502:   aload 6
L504:   dup_x2
L505:   dup
L506:   pop2
L507:   dup
L508:   aload_1
L509:   ldc_w 2e-1f
L512:   invokespecial Method SB <init> (LgB;F)V
L515:   getstatic Field dg field337 Ldg;
L518:   invokevirtual Method qc method31 (LgB;Ljava/lang/Object;)V
L521:   new SB
L524:   aload 6
L526:   dup
L527:   pop2
L528:   dup
L529:   aload 4
L531:   ldc_w 2e-1f
L534:   invokespecial Method SB <init> (LgB;F)V
L537:   getstatic Field dg this Ldg;
L540:   invokevirtual Method qc method31 (LgB;Ljava/lang/Object;)V
L543:   areturn
L544:   
        .attribute StackMap b'\x00\x08\x00\x4B\x00\x04\x07\x00\x02\x07\x00\x5C\x07\x00\x5C\x07\x00\xC6\x00\x01\x07\x00\xC6\x00\x9C\x00\x00\x00\x01\x07\x00\xEB\x00\x9D\x00\x04\x07\x00\x02\x07\x00\x5C\x07\x00\x5C\x07\x00\xC6\x00\x00\x00\xB7\x00\x00\x00\x01\x07\x00\xEB\x00\xB8\x00\x04\x07\x00\x02\x07\x00\x5C\x07\x00\x5C\x07\x00\xC6\x00\x01\x07\x00\xED\x00\xD2\x00\x04\x07\x00\x02\x07\x00\x5C\x07\x00\x5C\x07\x01\x89\x00\x00\x01\x53\x00\x07\x07\x00\x02\x07\x00\x5C\x07\x00\x2F\x07\x01\x6E\x07\x01\x5B\x01\x07\x00\xC6\x00\x01\x07\x00\xC6\x01\x7A\x00\x07\x07\x00\x02\x07\x00\x5C\x07\x00\x2F\x07\x01\x6E\x07\x01\x5B\x01\x07\x00\xC6\x00\x00'
    .end code
.end method

.method public static synthetic method212 : (LGd;)LmG;
    .code stack 1 locals 1
L0:     aload_0
L1:     getfield Field Gd field201 LmG;
L4:     areturn
L5:     
    .end code
.end method

.method public static synthetic method213 : (LGd;)LFE;
    .code stack 1 locals 1
L0:     aload_0
L1:     getfield Field Gd field1136 LFE;
L4:     areturn
L5:     
    .end code
.end method

.method public method26 : ()V
    .code stack 5 locals 2
L0:     aload_0
L1:     dup
L2:     invokespecial Method Yd method26 ()V
L5:     getfield Field Gd new LvF;
L8:     ifnull L44
L11:    ldc_w 4e-1f
L14:    invokestatic Method OC method1015 ()D
L17:    ldc2_w 4e0
L20:    dmul
L21:    invokestatic Method java/lang/Math sin (D)D
L24:    d2f
L25:    fmul
L26:    fstore_1
L27:    aload_0
L28:    getfield Field Gd new LvF;
L31:    fconst_1
L32:    fload_1
L33:    fadd
L34:    ldc_w 5e-1f
L37:    fload_1
L38:    fadd
L39:    fconst_1
L40:    dup_x2
L41:    invokevirtual Method vF method464 (FFFF)V
L44:    return
L45:    
        .attribute StackMap b'\x00\x01\x00\x2C\x00\x01\x07\x00\x02\x00\x00'
    .end code
.end method

.method public static synthetic method214 : (LGd;)LFE;
    .code stack 1 locals 1
L0:     aload_0
L1:     getfield Field Gd field1136 LFE;
L4:     areturn
L5:     
    .end code
.end method

.method public static synthetic method215 : (LGd;)LmG;
    .code stack 1 locals 1
L0:     aload_0
L1:     getfield Field Gd try LmG;
L4:     areturn
L5:     
    .end code
.end method

.method private method216 : (LTe;)V
    .code stack 4 locals 5
L0:     aload_0
L1:     getfield Field Gd field200 LDF;
L4:     new java/lang/StringBuilder
L7:     dup
L8:     invokespecial Method java/lang/StringBuilder <init> ()V
L11:    iconst_0
L12:    ldc_w "\u00AB"
L15:    invokevirtual Method java/lang/StringBuilder insert (ILjava/lang/String;)Ljava/lang/StringBuilder;
L18:    aload_1
L19:    getfield Field Te true Ljava/lang/String;
L22:    invokevirtual Method java/lang/StringBuilder append (Ljava/lang/String;)Ljava/lang/StringBuilder;
L25:    ldc_w "\u00BB"
L28:    invokevirtual Method java/lang/StringBuilder append (Ljava/lang/String;)Ljava/lang/StringBuilder;
L31:    invokevirtual Method java/lang/StringBuilder toString ()Ljava/lang/String;
L34:    invokevirtual Method DF method12 (Ljava/lang/String;)V
L37:    new java/lang/StringBuilder
L40:    dup
L41:    invokespecial Method java/lang/StringBuilder <init> ()V
L44:    iconst_0
L45:    ldc_w "Opponents: "
L48:    invokevirtual Method java/lang/StringBuilder insert (ILjava/lang/String;)Ljava/lang/StringBuilder;
L51:    aload_1
L52:    getfield Field Te field2105 I
L55:    ifne L65
L58:    ldc_w "none"
L61:    goto L72
L64:    athrow
L65:    aload_1
L66:    getfield Field Te field2105 I
L69:    invokestatic Method java/lang/Integer valueOf (I)Ljava/lang/Integer;
L72:    invokevirtual Method java/lang/StringBuilder append (Ljava/lang/Object;)Ljava/lang/StringBuilder;
L75:    ldc_w "\u000A"
L78:    invokevirtual Method java/lang/StringBuilder append (Ljava/lang/String;)Ljava/lang/StringBuilder;
L81:    invokevirtual Method java/lang/StringBuilder toString ()Ljava/lang/String;
L84:    astore_2
L85:    aload_1
L86:    getfield Field Te try Ljava/util/List;
L89:    invokeinterface InterfaceMethod java/util/List iterator ()Ljava/util/Iterator; 1
L94:    astore_3
L95:    aload_3
L96:    invokeinterface InterfaceMethod java/util/Iterator hasNext ()Z 1
L101:   ifeq L156
L104:   aload_3
L105:   invokeinterface InterfaceMethod java/util/Iterator next ()Ljava/lang/Object; 1
L110:   checkcast Uf
L113:   dup
L114:   astore 4
L116:   getfield Field Uf new Ljava/lang/String;
L119:   ifnull L95
L122:   new java/lang/StringBuilder
L125:   dup
L126:   invokespecial Method java/lang/StringBuilder <init> ()V
L129:   iconst_0
L130:   aload_2
L131:   invokevirtual Method java/lang/StringBuilder insert (ILjava/lang/String;)Ljava/lang/StringBuilder;
L134:   aload 4
L136:   getfield Field Uf new Ljava/lang/String;
L139:   invokevirtual Method java/lang/StringBuilder append (Ljava/lang/String;)Ljava/lang/StringBuilder;
L142:   ldc_w "\u000A"
L145:   invokevirtual Method java/lang/StringBuilder append (Ljava/lang/String;)Ljava/lang/StringBuilder;
L148:   invokevirtual Method java/lang/StringBuilder toString ()Ljava/lang/String;
L151:   astore_2
L152:   goto L95
L155:   athrow
L156:   new java/lang/StringBuilder
L159:   dup
L160:   invokespecial Method java/lang/StringBuilder <init> ()V
L163:   iconst_0
L164:   aload_2
L165:   invokevirtual Method java/lang/StringBuilder insert (ILjava/lang/String;)Ljava/lang/StringBuilder;
L168:   ldc_w "\u000A"
L171:   invokevirtual Method java/lang/StringBuilder append (Ljava/lang/String;)Ljava/lang/StringBuilder;
L174:   invokevirtual Method java/lang/StringBuilder toString ()Ljava/lang/String;
L177:   astore_2
L178:   new java/lang/StringBuilder
L181:   dup
L182:   invokespecial Method java/lang/StringBuilder <init> ()V
L185:   iconst_0
L186:   aload_2
L187:   invokevirtual Method java/lang/StringBuilder insert (ILjava/lang/String;)Ljava/lang/StringBuilder;
L190:   aload_1
L191:   getfield Field Te field2112 Ljava/lang/String;
L194:   invokevirtual Method java/lang/StringBuilder append (Ljava/lang/String;)Ljava/lang/StringBuilder;
L197:   invokevirtual Method java/lang/StringBuilder toString ()Ljava/lang/String;
L200:   astore_2
L201:   aload_0
L202:   getfield Field Gd field199 LDF;
L205:   aload_2
L206:   invokevirtual Method DF method12 (Ljava/lang/String;)V
L209:   return
L210:   
        .attribute StackMap b'\x00\x06\x00\x40\x00\x00\x00\x01\x07\x00\xEB\x00\x41\x00\x02\x07\x00\x02\x07\x01\xA2\x00\x01\x07\x02\x03\x00\x48\x00\x02\x07\x00\x02\x07\x01\xA2\x00\x02\x07\x02\x03\x07\x02\x34\x00\x5F\x00\x04\x07\x00\x02\x07\x01\xA2\x07\x01\x42\x07\x00\xC6\x00\x00\x00\x9B\x00\x00\x00\x01\x07\x00\xEB\x00\x9C\x00\x04\x07\x00\x02\x07\x01\xA2\x07\x01\x42\x07\x00\xC6\x00\x00'
    .end code
.end method

.method public static <clinit> : ()V
    .code stack 1 locals 0
L0:     ldc_w "\u2716"
L3:     putstatic Field Gd field198 Ljava/lang/String;
L6:     ldc_w "\u2605"
L9:     putstatic Field Gd field202 Ljava/lang/String;
L12:    ldc_w "\u2606"
L15:    putstatic Field Gd field204 Ljava/lang/String;
L18:    return
L19:    
    .end code
.end method
.innerclasses
    BC [0] [0]
    Fd [0] [0]
    LE fG [0] public static final enum
    MD [0] [0]
    Nc [0] [0]
    Pb [0] [0]
    Pc JB [0] public static final enum
    Qc [0] [0]
    WB [0] [0]
    dg fG [0] public static final enum
    hD [0] [0]
    java/util/Map$Entry java/util/Map Entry public static interface abstract
    kC [0] [0]
    mG PF [0] public
    pd [0] [0]
    vD DF [0] public static final enum
.end innerclasses
.end class
