.version 49 0
.class public final super GE
.super eb

.method public <init> : ()V
    .code stack 1 locals 1
L0:     aload_0
L1:     invokespecial Method eb <init> ()V
L4:     return
L5:     
    .end code
.end method

.method public method754 : (LRg;)V
    .code stack 5 locals 4
L0:     bipush 15
L2:     aload_0
L3:     aload_1
L4:     invokespecial Method eb method754 (LRg;)V
L7:     iconst_1
L8:     dup
L9:     pop2
L10:    dup
L11:    istore_2
L12:    bipush 28
L14:    iconst_1
L15:    dup
L16:    pop2
L17:    if_icmpge L63
L20:    iconst_0
L21:    iconst_1
L22:    dup
L23:    pop2
L24:    dup
L25:    istore_3
L26:    bipush 10
L28:    iconst_1
L29:    dup
L30:    pop2
L31:    if_icmpge L55
L34:    aload_1
L35:    getfield Field Rg this [[I
L38:    iload_3
L39:    aaload
L40:    iload_2
L41:    bipush 43
L43:    iconst_1
L44:    dup
L45:    pop2
L46:    iinc 3 1
L49:    iastore
L50:    iload_3
L51:    goto L26
L54:    athrow
L55:    iinc 2 1
L58:    iload_2
L59:    goto L12
L62:    athrow
L63:    aload_1
L64:    getfield Field Rg this [[I
L67:    invokestatic Method hE method1143 ([[I)V
L70:    return
L71:    
        .attribute StackMap b'\x00\x06\x00\x0C\x00\x03\x07\x00\x02\x07\x00\x13\x01\x00\x01\x01\x00\x1A\x00\x04\x07\x00\x02\x07\x00\x13\x01\x01\x00\x01\x01\x00\x36\x00\x00\x00\x01\x07\x00\x19\x00\x37\x00\x04\x07\x00\x02\x07\x00\x13\x01\x01\x00\x00\x00\x3E\x00\x00\x00\x01\x07\x00\x19\x00\x3F\x00\x03\x07\x00\x02\x07\x00\x13\x01\x00\x00'
    .end code
.end method
.innerclasses
    GE [0] [0] static
.end innerclasses
.enclosing method SE garbageman ([LTe;)LTe;
.end class
