.version 49 0
.class public final super Gf
.super java/lang/Object
.implements D
.field public field968 I
.field public field969 Led;

.method public <init> : (LMd;)V
    .code stack 6 locals 4
L0:     aload_0
L1:     aload_1
L2:     dup_x1
L3:     aload_0
L4:     invokespecial Method java/lang/Object <init> ()V
L7:     invokevirtual Method Md method886 ()I
L10:    putfield Field Gf field968 I
L13:    invokevirtual Method Md method892 ()Z
L16:    ifeq L35
L19:    aload_0
L20:    getstatic Field Kc field1931 LKc;
L23:    aload_1
L24:    invokevirtual Method Md method886 ()I
L27:    invokevirtual Method Kc method856 (I)Led;
L30:    putfield Field Gf field969 Led;
L33:    return
L34:    athrow
L35:    aload_1
L36:    invokevirtual Method Md method889 ()I
L39:    istore_1
L40:    getstatic Field Kc field1931 LKc;
L43:    invokevirtual Method Kc method859 ()Ljava/util/Collection;
L46:    invokeinterface InterfaceMethod java/util/Collection iterator ()Ljava/util/Iterator; 1
L51:    astore_2
L52:    aload_2
L53:    invokeinterface InterfaceMethod java/util/Iterator hasNext ()Z 1
L58:    ifeq L92
L61:    aload_2
L62:    invokeinterface InterfaceMethod java/util/Iterator next ()Ljava/lang/Object; 1
L67:    checkcast ed
L70:    dup
L71:    astore_3
L72:    getfield Field ed field712 I
L75:    iload_1
L76:    if_icmpne L52
L79:    aload_0
L80:    dup
L81:    aload_3
L82:    putfield Field Gf field969 Led;
L85:    goto L93
L88:    nop
L89:    nop
L90:    nop
L91:    athrow
L92:    aload_0
L93:    getfield Field Gf field969 Led;
L96:    ifnonnull L116
L99:    new ed
L102:   aload_0
L103:   dup_x1
L104:   dup
L105:   pop2
L106:   dup
L107:   iload_1
L108:   aconst_null
L109:   dup_x1
L110:   invokespecial Method ed <init> (Ljava/lang/String;ILjava/lang/String;)V
L113:   putfield Field Gf field969 Led;
L116:   return
L117:   
        .attribute StackMap b'\x00\x07\x00\x22\x00\x00\x00\x01\x07\x00\x2B\x00\x23\x00\x02\x07\x00\x02\x07\x00\x13\x00\x00\x00\x34\x00\x03\x07\x00\x02\x01\x07\x00\x3A\x00\x00\x00\x58\x00\x00\x00\x01\x07\x00\x2B\x00\x5C\x00\x03\x07\x00\x02\x01\x07\x00\x3A\x00\x00\x00\x5D\x00\x03\x07\x00\x02\x01\x07\x00\x3A\x00\x01\x07\x00\x02\x00\x74\x00\x03\x07\x00\x02\x01\x07\x00\x3A\x00\x00'
    .end code
    .exceptions java/io/IOException
.end method

.method public method384 : (LAC;)V
    .code stack 5 locals 2
L0:     aload_1
L1:     aload_0
L2:     dup_x1
L3:     aload_1
L4:     aload_0
L5:     getfield Field Gf field968 I
L8:     invokevirtual Method AC method691 (I)V
L11:    getfield Field Gf field969 Led;
L14:    invokevirtual Method ed method94 ()Z
L17:    invokevirtual Method AC method684 (Z)V
L20:    getfield Field Gf field969 Led;
L23:    invokevirtual Method ed method94 ()Z
L26:    ifeq L42
L29:    aload_1
L30:    aload_0
L31:    getfield Field Gf field969 Led;
L34:    getfield Field ed try I
L37:    invokevirtual Method AC method691 (I)V
L40:    return
L41:    athrow
L42:    aload_1
L43:    aload_0
L44:    getfield Field Gf field969 Led;
L47:    getfield Field ed field712 I
L50:    invokevirtual Method AC method674 (I)V
L53:    return
L54:    
        .attribute StackMap b'\x00\x02\x00\x29\x00\x00\x00\x01\x07\x00\x2B\x00\x2A\x00\x02\x07\x00\x02\x07\x00\x4D\x00\x00'
    .end code
    .exceptions java/io/IOException
.end method

.method public <init> : (ILed;)V
    .code stack 5 locals 3
L0:     aload_2
L1:     aload_0
L2:     dup_x1
L3:     iload_1
L4:     aload_0
L5:     invokespecial Method java/lang/Object <init> ()V
L8:     putfield Field Gf field968 I
L11:    putfield Field Gf field969 Led;
L14:    return
L15:    
    .end code
.end method
.end class
