.version 49 0
.class public final super GG
.super NF
.field public static final for I = 11
.field public static final case I = 2
.field public static final byte I = 0
.field public static final "super" I = 14
.field public static final int I = 3
.field public static final short I = 17
.field public static final goto I = 16
.field public static final break I = 5
.field public static final long I = 7
.field public static final void I = 10
.field public static final try I = 13
.field public static final const I = 12
.field public static final new I = 6
.field public static final null I = 4
.field public static final this I = 19
.field public static final char I = 15
.field public static final else I = 8
.field public static final "enum" I = 9
.field public static final do I = 1

.method public goto : ([[I)D
    .code stack 8 locals 7
L0:     dconst_0
L1:     dstore_2
L2:     iconst_0
L3:     iconst_1
L4:     dup
L5:     pop2
L6:     dup
L7:     istore 4
L9:     aload_1
L10:    arraylength
L11:    if_icmpge L161
L14:    aload_1
L15:    iconst_0
L16:    iconst_1
L17:    dup
L18:    pop2
L19:    aaload
L20:    arraylength
L21:    iconst_1
L22:    dup
L23:    dup
L24:    pop2
L25:    isub
L26:    istore 5
L28:    aload_1
L29:    iconst_0
L30:    iconst_1
L31:    dup
L32:    pop2
L33:    aaload
L34:    arraylength
L35:    iconst_2
L36:    iconst_1
L37:    dup
L38:    pop2
L39:    isub
L40:    dup
L41:    istore 6
L43:    iflt L69
L46:    aload_1
L47:    iload 4
L49:    aaload
L50:    iload 6
L52:    iaload
L53:    ifeq L60
L56:    iload 6
L58:    istore 5
L60:    iinc 6 -1
L63:    iload 6
L65:    goto L43
L68:    athrow
L69:    iload 5
L71:    aload_1
L72:    iconst_0
L73:    iconst_1
L74:    dup
L75:    pop2
L76:    aaload
L77:    arraylength
L78:    iconst_1
L79:    dup
L80:    dup
L81:    pop2
L82:    isub
L83:    if_icmpeq L153
L86:    iload 5
L88:    iconst_1
L89:    dup
L90:    dup
L91:    pop2
L92:    iadd
L93:    dup
L94:    istore 6
L96:    aload_1
L97:    iconst_0
L98:    iconst_1
L99:    dup
L100:   pop2
L101:   aaload
L102:   arraylength
L103:   if_icmpge L153
L106:   aload_1
L107:   iload 4
L109:   aaload
L110:   iload 6
L112:   iaload
L113:   ifne L144
L116:   dload_2
L117:   ldc2_w 5e0
L120:   aload_0
L121:   getfield Field GG do [D
L124:   bipush 16
L126:   iconst_1
L127:   dup
L128:   pop2
L129:   daload
L130:   dmul
L131:   ldc2_w 1e-3
L134:   iload 6
L136:   iload 5
L138:   isub
L139:   i2d
L140:   dmul
L141:   dadd
L142:   dadd
L143:   dstore_2
L144:   iinc 6 1
L147:   iload 6
L149:   goto L96
L152:   athrow
L153:   iinc 4 1
L156:   iload 4
L158:   goto L9
L161:   dload_2
L162:   dreturn
L163:   
        .attribute StackMap b'\x00\x0A\x00\x09\x00\x04\x07\x00\x02\x07\x00\x2E\x03\x01\x00\x01\x01\x00\x2B\x00\x06\x07\x00\x02\x07\x00\x2E\x03\x01\x01\x01\x00\x01\x01\x00\x3C\x00\x06\x07\x00\x02\x07\x00\x2E\x03\x01\x01\x01\x00\x00\x00\x44\x00\x00\x00\x01\x07\x00\x30\x00\x45\x00\x06\x07\x00\x02\x07\x00\x2E\x03\x01\x01\x01\x00\x00\x00\x60\x00\x06\x07\x00\x02\x07\x00\x2E\x03\x01\x01\x01\x00\x01\x01\x00\x90\x00\x06\x07\x00\x02\x07\x00\x2E\x03\x01\x01\x01\x00\x00\x00\x98\x00\x00\x00\x01\x07\x00\x30\x00\x99\x00\x06\x07\x00\x02\x07\x00\x2E\x03\x01\x01\x01\x00\x00\x00\xA1\x00\x04\x07\x00\x02\x07\x00\x2E\x03\x01\x00\x00'
    .end code
.end method

.method public <init> : ()V
    .code stack 6 locals 1
L0:     bipush 20
L2:     aload_0
L3:     dup_x1
L4:     invokespecial Method NF <init> ()V
L7:     iconst_1
L8:     dup
L9:     pop2
L10:    newarray double
L12:    iconst_1
L13:    dup
L14:    pop2
L15:    dup
L16:    iconst_0
L17:    iconst_1
L18:    dup
L19:    pop2
L20:    ldc2_w 9.234826080841721e-2
L23:    dastore
L24:    dup
L25:    iconst_1
L26:    dup
L27:    dup
L28:    pop2
L29:    ldc2_w 7.206073933714242e-1
L32:    dastore
L33:    dup
L34:    iconst_2
L35:    iconst_1
L36:    dup
L37:    pop2
L38:    ldc2_w -7.137663688470691e-1
L41:    dastore
L42:    dup
L43:    iconst_3
L44:    iconst_1
L45:    dup
L46:    pop2
L47:    ldc2_w 5.451670965973166e-2
L50:    dastore
L51:    dup
L52:    iconst_4
L53:    iconst_1
L54:    dup
L55:    pop2
L56:    ldc2_w -6.475096133836045e-2
L59:    dastore
L60:    dup
L61:    iconst_5
L62:    iconst_1
L63:    dup
L64:    pop2
L65:    ldc2_w -2.0558294370626523e-1
L68:    dastore
L69:    dup
L70:    bipush 6
L72:    iconst_1
L73:    dup
L74:    pop2
L75:    ldc2_w -2.5502476276754366e-1
L78:    dastore
L79:    dup
L80:    bipush 7
L82:    iconst_1
L83:    dup
L84:    pop2
L85:    ldc2_w 5.658772689018516e-1
L88:    dastore
L89:    dup
L90:    bipush 8
L92:    iconst_1
L93:    dup
L94:    pop2
L95:    ldc2_w -1.0695393844382879e0
L98:    dastore
L99:    dup
L100:   bipush 9
L102:   iconst_1
L103:   dup
L104:   pop2
L105:   ldc2_w 1.6408875672273998e-1
L108:   dastore
L109:   dup
L110:   bipush 10
L112:   iconst_1
L113:   dup
L114:   pop2
L115:   ldc2_w -7.923403931776657e-1
L118:   dastore
L119:   dup
L120:   bipush 11
L122:   iconst_1
L123:   dup
L124:   pop2
L125:   ldc2_w -1.0271622944652044e0
L128:   dastore
L129:   dup
L130:   bipush 12
L132:   iconst_1
L133:   dup
L134:   pop2
L135:   ldc2_w -9.589882466939406e-2
L138:   dastore
L139:   dup
L140:   bipush 13
L142:   iconst_1
L143:   dup
L144:   pop2
L145:   ldc2_w -1.104138343573882e-1
L148:   dastore
L149:   dup
L150:   bipush 14
L152:   iconst_1
L153:   dup
L154:   pop2
L155:   ldc2_w 4.4237234574818807e-1
L158:   dastore
L159:   dup
L160:   bipush 15
L162:   iconst_1
L163:   dup
L164:   pop2
L165:   ldc2_w 1.0108953770710462e-1
L168:   dastore
L169:   dup
L170:   bipush 16
L172:   iconst_1
L173:   dup
L174:   pop2
L175:   ldc2_w 7.523745342021438e-1
L178:   dastore
L179:   dup
L180:   bipush 17
L182:   iconst_1
L183:   dup
L184:   pop2
L185:   ldc2_w -6.166455357475791e-1
L188:   dastore
L189:   dup
L190:   bipush 18
L192:   iconst_1
L193:   dup
L194:   pop2
L195:   ldc2_w -2.942146169319919e-1
L198:   dastore
L199:   dup
L200:   bipush 19
L202:   iconst_1
L203:   dup
L204:   pop2
L205:   ldc2_w -9.468674781665999e-1
L208:   dastore
L209:   putfield Field GG do [D
L212:   return
L213:   
    .end code
.end method

.method public break : ([[I[[I[D[D)D
    .code stack 18 locals 21
L0:     aload 4
L2:     bipush 7
L4:     iconst_1
L5:     dup
L6:     pop2
L7:     daload
L8:     aload_0
L9:     dup_x2
L10:    getfield Field GG do [D
L13:    bipush 11
L15:    iconst_1
L16:    dup
L17:    pop2
L18:    daload
L19:    aload_2
L20:    invokestatic Method GG break ([[I)I
L23:    i2d
L24:    dmul
L25:    dadd
L26:    dstore 5
L28:    aload_0
L29:    aload_2
L30:    dup_x1
L31:    aload_2
L32:    aload_0
L33:    dup_x1
L34:    aload_0
L35:    aload_2
L36:    dup_x1
L37:    aload_2
L38:    aload_0
L39:    dup_x1
L40:    aload_2
L41:    invokevirtual Method GG do ([[I)D
L44:    aload_0
L45:    getfield Field GG do [D
L48:    bipush 8
L50:    iconst_1
L51:    dup
L52:    pop2
L53:    daload
L54:    dmul
L55:    aload 4
L57:    iconst_0
L58:    iconst_1
L59:    dup
L60:    pop2
L61:    daload
L62:    dadd
L63:    dstore 7
L65:    invokevirtual Method GG const ([[I)I
L68:    i2d
L69:    aload_0
L70:    getfield Field GG do [D
L73:    bipush 10
L75:    iconst_1
L76:    dup
L77:    pop2
L78:    daload
L79:    dmul
L80:    aload 4
L82:    iconst_1
L83:    dup
L84:    dup
L85:    pop2
L86:    daload
L87:    dadd
L88:    dstore 9
L90:    invokevirtual Method GG for ([[I)D
L93:    aload_0
L94:    getfield Field GG do [D
L97:    bipush 9
L99:    iconst_1
L100:   dup
L101:   pop2
L102:   daload
L103:   dmul
L104:   aload 4
L106:   iconst_2
L107:   iconst_1
L108:   dup
L109:   pop2
L110:   daload
L111:   dadd
L112:   dstore 11
L114:   invokevirtual Method GG short ([[I)D
L117:   aload_0
L118:   getfield Field GG do [D
L121:   bipush 12
L123:   iconst_1
L124:   dup
L125:   pop2
L126:   daload
L127:   dmul
L128:   aload 4
L130:   iconst_3
L131:   iconst_1
L132:   dup
L133:   pop2
L134:   daload
L135:   dadd
L136:   dstore 13
L138:   invokevirtual Method GG goto ([[I)D
L141:   aload_0
L142:   getfield Field GG do [D
L145:   bipush 13
L147:   iconst_1
L148:   dup
L149:   pop2
L150:   daload
L151:   dmul
L152:   aload 4
L154:   iconst_5
L155:   iconst_1
L156:   dup
L157:   pop2
L158:   daload
L159:   dadd
L160:   dstore 15
L162:   invokevirtual Method GG catch ([[I)I
L165:   i2d
L166:   aload_0
L167:   getfield Field GG do [D
L170:   bipush 7
L172:   iconst_1
L173:   dup
L174:   pop2
L175:   daload
L176:   dmul
L177:   aload 4
L179:   bipush 6
L181:   iconst_1
L182:   dup
L183:   pop2
L184:   daload
L185:   dadd
L186:   dstore 17
L188:   invokevirtual Method GG float ([[I)I
L191:   i2d
L192:   ldc2_w 9e-1
L195:   dmul
L196:   aload 4
L198:   bipush 8
L200:   iconst_1
L201:   dup
L202:   pop2
L203:   daload
L204:   dadd
L205:   dstore 19
L207:   dconst_0
L208:   aload_0
L209:   getfield Field GG do [D
L212:   iconst_4
L213:   iconst_1
L214:   dup
L215:   pop2
L216:   daload
L217:   dload 5
L219:   dmul
L220:   dadd
L221:   aload_0
L222:   getfield Field GG do [D
L225:   iconst_1
L226:   dup
L227:   dup
L228:   pop2
L229:   daload
L230:   dload 7
L232:   dmul
L233:   dadd
L234:   aload_0
L235:   getfield Field GG do [D
L238:   iconst_2
L239:   iconst_1
L240:   dup
L241:   pop2
L242:   daload
L243:   dload 11
L245:   dmul
L246:   dadd
L247:   aload_0
L248:   getfield Field GG do [D
L251:   iconst_3
L252:   iconst_1
L253:   dup
L254:   pop2
L255:   daload
L256:   dload 9
L258:   dmul
L259:   dadd
L260:   aload_0
L261:   getfield Field GG do [D
L264:   bipush 6
L266:   iconst_1
L267:   dup
L268:   pop2
L269:   daload
L270:   dload 15
L272:   dmul
L273:   dadd
L274:   aload_0
L275:   getfield Field GG do [D
L278:   iconst_5
L279:   iconst_1
L280:   dup
L281:   pop2
L282:   daload
L283:   dload 13
L285:   dmul
L286:   dadd
L287:   aload_0
L288:   getfield Field GG do [D
L291:   bipush 19
L293:   iconst_1
L294:   dup
L295:   pop2
L296:   daload
L297:   dload 17
L299:   dmul
L300:   dadd
L301:   dload 19
L303:   ldc2_w 1e4
L306:   dmul
L307:   dadd
L308:   dreturn
L309:   
    .end code
.end method

.method public do : ([[I)D
    .code stack 8 locals 8
L0:     dconst_0
L1:     dstore_2
L2:     iconst_0
L3:     iconst_1
L4:     dup
L5:     pop2
L6:     dup
L7:     istore 4
L9:     aload_1
L10:    arraylength
L11:    if_icmpge L148
L14:    iconst_m1
L15:    iconst_1
L16:    dup
L17:    pop2
L18:    istore 5
L20:    iconst_0
L21:    iconst_1
L22:    dup
L23:    pop2
L24:    dup
L25:    istore 6
L27:    bipush 28
L29:    iconst_1
L30:    dup
L31:    pop2
L32:    if_icmpge L63
L35:    aload_1
L36:    iload 4
L38:    aaload
L39:    iload 6
L41:    iaload
L42:    ifeq L54
L45:    iload 6
L47:    dup
L48:    istore 5
L50:    goto L65
L53:    athrow
L54:    iinc 6 1
L57:    iload 6
L59:    goto L27
L62:    athrow
L63:    iload 5
L65:    ifle L140
L68:    iconst_0
L69:    iconst_1
L70:    dup
L71:    pop2
L72:    istore 6
L74:    bipush 27
L76:    iconst_1
L77:    dup
L78:    pop2
L79:    istore 7
L81:    aload_1
L82:    iload 4
L84:    aaload
L85:    iload 7
L87:    iaload
L88:    ifne L99
L91:    iload 7
L93:    dup
L94:    istore 6
L96:    goto L108
L99:    iinc 7 -1
L102:   aload_1
L103:   goto L82
L106:   nop
L107:   athrow
L108:   iload 5
L110:   if_icmple L140
L113:   dload_2
L114:   ldc2_w 1e1
L117:   aload_0
L118:   getfield Field GG do [D
L121:   bipush 15
L123:   iconst_1
L124:   dup
L125:   pop2
L126:   daload
L127:   dmul
L128:   iload 6
L130:   iload 5
L132:   isub
L133:   i2d
L134:   invokestatic Method java/lang/Math sqrt (D)D
L137:   dadd
L138:   dadd
L139:   dstore_2
L140:   iinc 4 1
L143:   iload 4
L145:   goto L9
L148:   dload_2
L149:   dreturn
L150:   
        .attribute StackMap b'\x00\x0D\x00\x09\x00\x04\x07\x00\x02\x07\x00\x2E\x03\x01\x00\x01\x01\x00\x1B\x00\x06\x07\x00\x02\x07\x00\x2E\x03\x01\x01\x01\x00\x01\x01\x00\x35\x00\x00\x00\x01\x07\x00\x30\x00\x36\x00\x06\x07\x00\x02\x07\x00\x2E\x03\x01\x01\x01\x00\x00\x00\x3E\x00\x00\x00\x01\x07\x00\x30\x00\x3F\x00\x06\x07\x00\x02\x07\x00\x2E\x03\x01\x01\x01\x00\x00\x00\x41\x00\x06\x07\x00\x02\x07\x00\x2E\x03\x01\x01\x01\x00\x01\x01\x00\x52\x00\x07\x07\x00\x02\x07\x00\x2E\x03\x01\x01\x01\x01\x00\x01\x07\x00\x2E\x00\x63\x00\x07\x07\x00\x02\x07\x00\x2E\x03\x01\x01\x01\x01\x00\x00\x00\x6A\x00\x00\x00\x01\x07\x00\x30\x00\x6C\x00\x07\x07\x00\x02\x07\x00\x2E\x03\x01\x01\x01\x01\x00\x01\x01\x00\x8C\x00\x06\x07\x00\x02\x07\x00\x2E\x03\x01\x01\x01\x00\x00\x00\x94\x00\x04\x07\x00\x02\x07\x00\x2E\x03\x01\x00\x00'
    .end code
.end method

.method public for : ([[I)D
    .code stack 10 locals 9
L0:     dconst_0
L1:     dstore_2
L2:     aload_1
L3:     iconst_0
L4:     iconst_1
L5:     dup
L6:     pop2
L7:     aaload
L8:     arraylength
L9:     istore 4
L11:    aload_1
L12:    iconst_0
L13:    iconst_1
L14:    dup
L15:    pop2
L16:    aaload
L17:    arraylength
L18:    iconst_1
L19:    dup
L20:    dup
L21:    pop2
L22:    isub
L23:    dup
L24:    istore 5
L26:    iflt L54
L29:    aload_1
L30:    iconst_0
L31:    iconst_1
L32:    dup
L33:    pop2
L34:    aaload
L35:    iload 5
L37:    iaload
L38:    ifeq L45
L41:    iload 5
L43:    istore 4
L45:    iinc 5 -1
L48:    iload 5
L50:    goto L26
L53:    athrow
L54:    iconst_1
L55:    dup
L56:    dup
L57:    pop2
L58:    dup
L59:    istore 5
L61:    aload_1
L62:    arraylength
L63:    if_icmpge L192
L66:    aload_1
L67:    iload 5
L69:    aaload
L70:    arraylength
L71:    istore 6
L73:    aload_1
L74:    iload 5
L76:    aaload
L77:    arraylength
L78:    iconst_1
L79:    dup
L80:    dup
L81:    pop2
L82:    isub
L83:    dup
L84:    istore 7
L86:    iflt L112
L89:    aload_1
L90:    iload 5
L92:    aaload
L93:    iload 7
L95:    iaload
L96:    ifeq L103
L99:    iload 7
L101:   istore 6
L103:   iinc 7 -1
L106:   iload 7
L108:   goto L86
L111:   athrow
L112:   iload 4
L114:   iload 6
L116:   isub
L117:   i2d
L118:   dup2
L119:   dstore 7
L121:   dconst_0
L122:   dcmpg
L123:   ifge L131
L126:   dload 7
L128:   dneg
L129:   dstore 7
L131:   dload 7
L133:   ldc2_w 5e0
L136:   aload_0
L137:   getfield Field GG do [D
L140:   bipush 17
L142:   iconst_1
L143:   dup
L144:   pop2
L145:   daload
L146:   dmul
L147:   dsub
L148:   dup2
L149:   dstore 7
L151:   dconst_0
L152:   dcmpg
L153:   ifge L159
L156:   dconst_0
L157:   dstore 7
L159:   dload_2
L160:   dload 7
L162:   ldc2_w 8e0
L165:   aload_0
L166:   getfield Field GG do [D
L169:   iconst_0
L170:   iconst_1
L171:   dup
L172:   pop2
L173:   iinc 5 1
L176:   daload
L177:   dmul
L178:   invokestatic Method java/lang/Math pow (DD)D
L181:   dadd
L182:   dstore_2
L183:   iload 6
L185:   istore 4
L187:   iload 5
L189:   goto L61
L192:   dload_2
L193:   dreturn
L194:   
        .attribute StackMap b'\x00\x0C\x00\x1A\x00\x05\x07\x00\x02\x07\x00\x2E\x03\x01\x01\x00\x01\x01\x00\x2D\x00\x05\x07\x00\x02\x07\x00\x2E\x03\x01\x01\x00\x00\x00\x35\x00\x00\x00\x01\x07\x00\x30\x00\x36\x00\x05\x07\x00\x02\x07\x00\x2E\x03\x01\x01\x00\x00\x00\x3D\x00\x05\x07\x00\x02\x07\x00\x2E\x03\x01\x01\x00\x01\x01\x00\x56\x00\x07\x07\x00\x02\x07\x00\x2E\x03\x01\x01\x01\x01\x00\x01\x01\x00\x67\x00\x07\x07\x00\x02\x07\x00\x2E\x03\x01\x01\x01\x01\x00\x00\x00\x6F\x00\x00\x00\x01\x07\x00\x30\x00\x70\x00\x07\x07\x00\x02\x07\x00\x2E\x03\x01\x01\x01\x01\x00\x00\x00\x83\x00\x07\x07\x00\x02\x07\x00\x2E\x03\x01\x01\x01\x03\x00\x00\x00\x9F\x00\x07\x07\x00\x02\x07\x00\x2E\x03\x01\x01\x01\x03\x00\x00\x00\xC0\x00\x05\x07\x00\x02\x07\x00\x2E\x03\x01\x01\x00\x00'
    .end code
.end method

.method public catch : ([[I)I
    .code stack 5 locals 5
L0:     iconst_0
L1:     iconst_1
L2:     dup
L3:     pop2
L4:     istore_2
L5:     iconst_0
L6:     iconst_1
L7:     dup
L8:     pop2
L9:     dup
L10:    istore_3
L11:    bipush 27
L13:    iconst_1
L14:    dup
L15:    pop2
L16:    if_icmpge L77
L19:    iconst_0
L20:    iconst_1
L21:    dup
L22:    pop2
L23:    dup
L24:    istore 4
L26:    bipush 10
L28:    iconst_1
L29:    dup
L30:    pop2
L31:    if_icmpge L69
L34:    aload_1
L35:    iload 4
L37:    aaload
L38:    iload_3
L39:    iaload
L40:    ifeq L60
L43:    aload_1
L44:    iload 4
L46:    aaload
L47:    iload_3
L48:    iconst_1
L49:    dup
L50:    dup
L51:    pop2
L52:    iadd
L53:    iaload
L54:    ifne L60
L57:    iinc 2 1
L60:    iinc 4 1
L63:    iload 4
L65:    goto L26
L68:    athrow
L69:    iinc 3 1
L72:    iload_3
L73:    goto L11
L76:    athrow
L77:    iload_2
L78:    ireturn
L79:    
        .attribute StackMap b'\x00\x07\x00\x0B\x00\x04\x07\x00\x02\x07\x00\x2E\x01\x01\x00\x01\x01\x00\x1A\x00\x05\x07\x00\x02\x07\x00\x2E\x01\x01\x01\x00\x01\x01\x00\x3C\x00\x05\x07\x00\x02\x07\x00\x2E\x01\x01\x01\x00\x00\x00\x44\x00\x00\x00\x01\x07\x00\x30\x00\x45\x00\x05\x07\x00\x02\x07\x00\x2E\x01\x01\x01\x00\x00\x00\x4C\x00\x00\x00\x01\x07\x00\x30\x00\x4D\x00\x04\x07\x00\x02\x07\x00\x2E\x01\x01\x00\x00'
    .end code
.end method

.method public float : ([[I)I
    .code stack 4 locals 2
L0:     aload_1
L1:     iconst_0
L2:     iconst_1
L3:     dup
L4:     pop2
L5:     aaload
L6:     bipush 27
L8:     iconst_1
L9:     dup
L10:    pop2
L11:    iaload
L12:    bipush 31
L14:    iconst_1
L15:    dup
L16:    pop2
L17:    iand
L18:    bipush 13
L20:    iconst_1
L21:    dup
L22:    pop2
L23:    if_icmpeq L52
L26:    aload_1
L27:    iconst_1
L28:    dup
L29:    dup
L30:    pop2
L31:    aaload
L32:    bipush 27
L34:    iconst_1
L35:    dup
L36:    pop2
L37:    iaload
L38:    bipush 31
L40:    iconst_1
L41:    dup
L42:    pop2
L43:    iand
L44:    bipush 13
L46:    iconst_1
L47:    dup
L48:    pop2
L49:    if_icmpne L58
L52:    iconst_0
L53:    iconst_1
L54:    dup
L55:    pop2
L56:    ireturn
L57:    athrow
L58:    iconst_1
L59:    dup
L60:    dup
L61:    pop2
L62:    ireturn
L63:    
        .attribute StackMap b'\x00\x03\x00\x34\x00\x02\x07\x00\x02\x07\x00\x2E\x00\x00\x00\x39\x00\x00\x00\x01\x07\x00\x30\x00\x3A\x00\x02\x07\x00\x02\x07\x00\x2E\x00\x00'
    .end code
.end method

.method public short : ([[I)D
    .code stack 8 locals 6
L0:     iconst_0
L1:     iconst_1
L2:     dup
L3:     pop2
L4:     istore_2
L5:     iconst_0
L6:     iconst_1
L7:     dup
L8:     pop2
L9:     istore_3
L10:    iconst_0
L11:    iconst_1
L12:    dup
L13:    pop2
L14:    dup
L15:    istore 4
L17:    aload_1
L18:    iconst_0
L19:    iconst_1
L20:    dup
L21:    pop2
L22:    aaload
L23:    arraylength
L24:    if_icmpge L83
L27:    iconst_0
L28:    iconst_1
L29:    dup
L30:    pop2
L31:    dup
L32:    istore 5
L34:    aload_1
L35:    arraylength
L36:    if_icmpge L74
L39:    aload_1
L40:    iload 5
L42:    aaload
L43:    iload 4
L45:    iaload
L46:    ifeq L65
L49:    iload_3
L50:    aload_1
L51:    iconst_0
L52:    iconst_1
L53:    dup
L54:    pop2
L55:    iinc 2 1
L58:    aaload
L59:    arraylength
L60:    iload 4
L62:    isub
L63:    iadd
L64:    istore_3
L65:    iinc 5 1
L68:    iload 5
L70:    goto L34
L73:    athrow
L74:    iinc 4 1
L77:    iload 4
L79:    goto L17
L82:    athrow
L83:    dconst_0
L84:    dstore 4
L86:    iload_2
L87:    ifeq L121
L90:    iload_3
L91:    i2d
L92:    iload_2
L93:    i2d
L94:    ddiv
L95:    ldc2_w 1e1
L98:    aload_0
L99:    getfield Field GG do [D
L102:   bipush 14
L104:   iconst_1
L105:   dup
L106:   pop2
L107:   daload
L108:   dmul
L109:   dsub
L110:   dup2
L111:   dstore 4
L113:   dconst_0
L114:   dcmpg
L115:   ifge L121
L118:   dconst_0
L119:   dstore 4
L121:   dload 4
L123:   dup2
L124:   dmul
L125:   dreturn
L126:   
        .attribute StackMap b'\x00\x08\x00\x11\x00\x05\x07\x00\x02\x07\x00\x2E\x01\x01\x01\x00\x01\x01\x00\x22\x00\x06\x07\x00\x02\x07\x00\x2E\x01\x01\x01\x01\x00\x01\x01\x00\x41\x00\x06\x07\x00\x02\x07\x00\x2E\x01\x01\x01\x01\x00\x00\x00\x49\x00\x00\x00\x01\x07\x00\x30\x00\x4A\x00\x06\x07\x00\x02\x07\x00\x2E\x01\x01\x01\x01\x00\x00\x00\x52\x00\x00\x00\x01\x07\x00\x30\x00\x53\x00\x05\x07\x00\x02\x07\x00\x2E\x01\x01\x01\x00\x00\x00\x79\x00\x05\x07\x00\x02\x07\x00\x2E\x01\x01\x03\x00\x00'
    .end code
.end method

.method public break : ([[II)I
    .code stack 4 locals 4
L0:     iconst_0
L1:     iconst_1
L2:     dup
L3:     pop2
L4:     dup
L5:     istore_3
L6:     bipush 10
L8:     iconst_1
L9:     dup
L10:    pop2
L11:    if_icmpge L33
L14:    aload_1
L15:    iload_3
L16:    aaload
L17:    iload_2
L18:    iaload
L19:    ifne L25
L22:    iload_3
L23:    ireturn
L24:    athrow
L25:    iinc 3 1
L28:    iload_3
L29:    goto L6
L32:    athrow
L33:    iconst_m1
L34:    iconst_1
L35:    dup
L36:    pop2
L37:    ireturn
L38:    
        .attribute StackMap b'\x00\x05\x00\x06\x00\x04\x07\x00\x02\x07\x00\x2E\x01\x01\x00\x01\x01\x00\x18\x00\x00\x00\x01\x07\x00\x30\x00\x19\x00\x04\x07\x00\x02\x07\x00\x2E\x01\x01\x00\x00\x00\x20\x00\x00\x00\x01\x07\x00\x30\x00\x21\x00\x04\x07\x00\x02\x07\x00\x2E\x01\x01\x00\x00'
    .end code
.end method

.method public break : ()LNF;
    .code stack 2 locals 1
L0:     new GG
L3:     dup
L4:     invokespecial Method GG <init> ()V
L7:     areturn
L8:     
    .end code
.end method

.method public break : ([[III)I
    .code stack 3 locals 5
L0:     iconst_0
L1:     iconst_1
L2:     dup
L3:     pop2
L4:     dup
L5:     istore 4
L7:     iload_3
L8:     if_icmpge L35
L11:    aload_1
L12:    iload_2
L13:    aaload
L14:    iload 4
L16:    iaload
L17:    ifeq L26
L20:    iload_3
L21:    iload 4
L23:    isub
L24:    ireturn
L25:    athrow
L26:    iinc 4 1
L29:    iload 4
L31:    goto L7
L34:    athrow
L35:    iconst_0
L36:    iconst_1
L37:    dup
L38:    pop2
L39:    ireturn
L40:    
        .attribute StackMap b'\x00\x05\x00\x07\x00\x05\x07\x00\x02\x07\x00\x2E\x01\x01\x01\x00\x01\x01\x00\x19\x00\x00\x00\x01\x07\x00\x30\x00\x1A\x00\x05\x07\x00\x02\x07\x00\x2E\x01\x01\x01\x00\x00\x00\x22\x00\x00\x00\x01\x07\x00\x30\x00\x23\x00\x05\x07\x00\x02\x07\x00\x2E\x01\x01\x01\x00\x00'
    .end code
.end method

.method public break : ([[I[D)[D
    .code stack 5 locals 3
L0:     aload_1
L1:     invokestatic Method GG break ([[I)I
L4:     istore_2
L5:     bipush 9
L7:     iconst_1
L8:     dup
L9:     pop2
L10:    newarray double
L12:    iconst_1
L13:    dup
L14:    pop2
L15:    dup
L16:    iconst_0
L17:    iconst_1
L18:    dup
L19:    pop2
L20:    aload_0
L21:    aload_1
L22:    invokevirtual Method GG do ([[I)D
L25:    dastore
L26:    dup
L27:    iconst_1
L28:    dup
L29:    dup
L30:    pop2
L31:    aload_0
L32:    aload_1
L33:    invokevirtual Method GG const ([[I)I
L36:    i2d
L37:    dastore
L38:    dup
L39:    iconst_2
L40:    iconst_1
L41:    dup
L42:    pop2
L43:    aload_0
L44:    aload_1
L45:    invokevirtual Method GG for ([[I)D
L48:    dastore
L49:    dup
L50:    iconst_3
L51:    iconst_1
L52:    dup
L53:    pop2
L54:    aload_0
L55:    aload_1
L56:    invokevirtual Method GG short ([[I)D
L59:    dastore
L60:    dup
L61:    iconst_4
L62:    iconst_1
L63:    dup
L64:    pop2
L65:    aload_0
L66:    aload_1
L67:    invokevirtual Method GG float ([[I)I
L70:    i2d
L71:    dastore
L72:    dup
L73:    iconst_5
L74:    iconst_1
L75:    dup
L76:    pop2
L77:    aload_0
L78:    aload_1
L79:    invokevirtual Method GG goto ([[I)D
L82:    dastore
L83:    dup
L84:    bipush 6
L86:    iconst_1
L87:    dup
L88:    pop2
L89:    aload_0
L90:    aload_1
L91:    invokevirtual Method GG catch ([[I)I
L94:    i2d
L95:    dastore
L96:    dup
L97:    bipush 7
L99:    iconst_1
L100:   dup
L101:   pop2
L102:   iload_2
L103:   i2d
L104:   dastore
L105:   dup
L106:   bipush 8
L108:   iconst_1
L109:   dup
L110:   pop2
L111:   aload_0
L112:   aload_1
L113:   invokevirtual Method GG float ([[I)I
L116:   i2d
L117:   dastore
L118:   areturn
L119:   
    .end code
.end method

.method public const : ([[I)I
    .code stack 4 locals 5
L0:     aload_1
L1:     iconst_0
L2:     iconst_1
L3:     dup
L4:     pop2
L5:     aaload
L6:     arraylength
L7:     istore_2
L8:     iconst_0
L9:     iconst_1
L10:    dup
L11:    pop2
L12:    dup
L13:    istore_3
L14:    bipush 10
L16:    iconst_1
L17:    dup
L18:    pop2
L19:    if_icmpge L65
L22:    iconst_0
L23:    iconst_1
L24:    dup
L25:    pop2
L26:    dup
L27:    istore 4
L29:    iload_2
L30:    if_icmpge L58
L33:    aload_1
L34:    iload_3
L35:    aaload
L36:    iload 4
L38:    iaload
L39:    ifeq L49
L42:    iload 4
L44:    istore_2
L45:    goto L58
L48:    athrow
L49:    iinc 4 1
L52:    iload 4
L54:    goto L29
L57:    athrow
L58:    iinc 3 1
L61:    iload_3
L62:    goto L14
L65:    bipush 28
L67:    iconst_1
L68:    dup
L69:    pop2
L70:    iload_2
L71:    isub
L72:    ireturn
L73:    
        .attribute StackMap b'\x00\x07\x00\x0E\x00\x04\x07\x00\x02\x07\x00\x2E\x01\x01\x00\x01\x01\x00\x1D\x00\x05\x07\x00\x02\x07\x00\x2E\x01\x01\x01\x00\x01\x01\x00\x30\x00\x00\x00\x01\x07\x00\x30\x00\x31\x00\x05\x07\x00\x02\x07\x00\x2E\x01\x01\x01\x00\x00\x00\x39\x00\x00\x00\x01\x07\x00\x30\x00\x3A\x00\x05\x07\x00\x02\x07\x00\x2E\x01\x01\x01\x00\x00\x00\x41\x00\x04\x07\x00\x02\x07\x00\x2E\x01\x01\x00\x00'
    .end code
.end method
.end class
