.version 49 0
.class public final super hd
.super java/lang/Object
.implements java/lang/Runnable
.field public final synthetic field1714 Lab;
.field public final synthetic field1715 Led;
.field public final synthetic field1716 LK;

.method public <init> : (Lab;Led;LK;)V
    .code stack 7 locals 4
L0:     aload_3
L1:     aload_0
L2:     dup_x1
L3:     dup_x2
L4:     aload_2
L5:     aload_0
L6:     aload_1
L7:     putfield Field hd field1714 Lab;
L10:    putfield Field hd field1715 Led;
L13:    putfield Field hd field1716 LK;
L16:    invokespecial Method java/lang/Object <init> ()V
L19:    return
L20:    
    .end code
.end method

.method public run : ()V
    .code stack 7 locals 9
L0:     aload_0
L1:     getfield Field hd field1714 Lab;
L4:     getfield Field ab field768 Ljava/util/Set;
L7:     aload_0
L8:     getfield Field hd field1715 Led;
L11:    invokeinterface InterfaceMethod java/util/Set contains (Ljava/lang/Object;)Z 2
L16:    ifeq L51
L19:    new oF
L22:    dup
L23:    aload_0
L24:    dup
L25:    getfield Field hd field1715 Led;
L28:    swap
L29:    getfield Field hd field1714 Lab;
L32:    aload_0
L33:    getfield Field hd field1714 Lab;
L36:    getfield Field ab field769 Ljava/util/List;
L39:    getstatic Field qE field627 LqE;
L42:    invokespecial Method oF <init> (Led;Lqd;Ljava/util/List;LqE;)V
L45:    astore_1
L46:    aload_0
L47:    goto L69
L50:    athrow
L51:    new ae
L54:    dup
L55:    aload_0
L56:    dup
L57:    getfield Field hd field1715 Led;
L60:    swap
L61:    getfield Field hd field1714 Lab;
L64:    invokespecial Method ae <init> (Led;Lqd;)V
L67:    astore_1
L68:    aload_0
L69:    getfield Field hd field1714 Lab;
L72:    getfield Field ab new Ljava/util/LinkedHashMap;
L75:    aload_0
L76:    getfield Field hd field1715 Led;
L79:    invokevirtual Method java/util/LinkedHashMap containsKey (Ljava/lang/Object;)Z
L82:    ifeq L122
L85:    getstatic Field java/lang/System out Ljava/io/PrintStream;
L88:    new java/lang/StringBuilder
L91:    dup
L92:    invokespecial Method java/lang/StringBuilder <init> ()V
L95:    iconst_0
L96:    ldc "Something's fishy here. Joining player "
L98:    invokevirtual Method java/lang/StringBuilder insert (ILjava/lang/String;)Ljava/lang/StringBuilder;
L101:   aload_0
L102:   getfield Field hd field1715 Led;
L105:   getfield Field ed field701 Ljava/lang/String;
L108:   invokevirtual Method java/lang/StringBuilder append (Ljava/lang/String;)Ljava/lang/StringBuilder;
L111:   ldc " is already in RoomLocal."
L113:   invokevirtual Method java/lang/StringBuilder append (Ljava/lang/String;)Ljava/lang/StringBuilder;
L116:   invokevirtual Method java/lang/StringBuilder toString ()Ljava/lang/String;
L119:   invokevirtual Method java/io/PrintStream println (Ljava/lang/String;)V
L122:   aload_0
L123:   dup
L124:   getfield Field hd field1714 Lab;
L127:   getfield Field ab new Ljava/util/LinkedHashMap;
L130:   aload_0
L131:   getfield Field hd field1715 Led;
L134:   aload_1
L135:   invokevirtual Method java/util/LinkedHashMap put (Ljava/lang/Object;Ljava/lang/Object;)Ljava/lang/Object;
L138:   aload_0
L139:   getfield Field hd field1714 Lab;
L142:   getfield Field ab field760 Ljava/util/LinkedHashMap;
L145:   aload_0
L146:   getfield Field hd field1715 Led;
L149:   iconst_0
L150:   iconst_1
L151:   dup
L152:   pop2
L153:   invokestatic Method java/lang/Integer valueOf (I)Ljava/lang/Integer;
L156:   invokevirtual Method java/util/LinkedHashMap put (Ljava/lang/Object;Ljava/lang/Object;)Ljava/lang/Object;
L159:   aload_0
L160:   getfield Field hd field1714 Lab;
L163:   invokevirtual Method ab try ()V
L166:   pop2
L167:   getfield Field hd field1716 LK;
L170:   ifnull L183
L173:   aload_0
L174:   getfield Field hd field1716 LK;
L177:   aload_1
L178:   invokeinterface InterfaceMethod K method734 (Ljava/lang/Object;)V 2
L183:   new pc
L186:   dup
L187:   aload_0
L188:   getfield Field hd field1715 Led;
L191:   iconst_1
L192:   dup
L193:   dup
L194:   pop2
L195:   invokespecial Method pc <init> (Led;Z)V
L198:   astore_2
L199:   invokestatic Method mc values ()[Lmc;
L202:   dup
L203:   astore_3
L204:   arraylength
L205:   istore 4
L207:   iconst_0
L208:   iconst_1
L209:   dup
L210:   pop2
L211:   dup
L212:   istore 5
L214:   iload 4
L216:   if_icmpge L296
L219:   aload_3
L220:   iload 5
L222:   aaload
L223:   astore 6
L225:   aload_0
L226:   getfield Field hd field1714 Lab;
L229:   getfield Field ab field745 Ljava/util/Set;
L232:   invokeinterface InterfaceMethod java/util/Set iterator ()Ljava/util/Iterator; 1
L237:   astore 7
L239:   aload 7
L241:   invokeinterface InterfaceMethod java/util/Iterator hasNext ()Z 1
L246:   ifeq L288
L249:   aload 7
L251:   invokeinterface InterfaceMethod java/util/Iterator next ()Ljava/lang/Object; 1
L256:   checkcast Dc
L259:   dup
L260:   astore 8
L262:   getfield Field Dc field1794 Ljava/lang/Object;
L265:   aload 6
L267:   if_acmpne L239
L270:   aload 8
L272:   getfield Field Dc field1793 Ljava/lang/Object;
L275:   checkcast G
L278:   aload_2
L279:   invokeinterface InterfaceMethod G method8 (LD;)V 2
L284:   goto L239
L287:   athrow
L288:   iinc 5 1
L291:   iload 5
L293:   goto L214
L296:   return
L297:   
        .attribute StackMap b'\x00\x0A\x00\x32\x00\x00\x00\x01\x07\x00\x38\x00\x33\x00\x01\x07\x00\x02\x00\x00\x00\x45\x00\x02\x07\x00\x02\x07\x00\x3F\x00\x01\x07\x00\x02\x00\x7A\x00\x02\x07\x00\x02\x07\x00\x3F\x00\x00\x00\xB7\x00\x02\x07\x00\x02\x07\x00\x3F\x00\x00\x00\xD6\x00\x06\x07\x00\x02\x07\x00\x3F\x07\x00\x85\x07\x00\x90\x01\x01\x00\x01\x01\x00\xEF\x00\x08\x07\x00\x02\x07\x00\x3F\x07\x00\x85\x07\x00\x90\x01\x01\x07\x00\x8A\x07\x00\x99\x00\x00\x01\x1F\x00\x00\x00\x01\x07\x00\x38\x01\x20\x00\x08\x07\x00\x02\x07\x00\x3F\x07\x00\x85\x07\x00\x90\x01\x01\x07\x00\x8A\x07\x00\x99\x00\x00\x01\x28\x00\x06\x07\x00\x02\x07\x00\x3F\x07\x00\x85\x07\x00\x90\x01\x01\x00\x00'
    .end code
.end method
.innerclasses
    hd [0] [0]
.end innerclasses
.enclosing method ab method400 (Led;ZLjava/lang/String;LK;)V
.end class
