.version 49 0
.class public final super hE
.super java/lang/Object

.method public static method1141 : ([[I)V
    .code stack 5 locals 3
L0:     iconst_0
L1:     iconst_1
L2:     dup
L3:     pop2
L4:     dup
L5:     istore_1
L6:     aload_0
L7:     arraylength
L8:     if_icmpge L56
L11:    iconst_0
L12:    iconst_1
L13:    dup
L14:    pop2
L15:    dup
L16:    istore_2
L17:    aload_0
L18:    iconst_0
L19:    iconst_1
L20:    dup
L21:    pop2
L22:    aaload
L23:    arraylength
L24:    if_icmpge L48
L27:    aload_0
L28:    iload_1
L29:    aaload
L30:    aload_0
L31:    iload_1
L32:    aaload
L33:    iload_2
L34:    dup_x1
L35:    iaload
L36:    invokestatic Method hE method1145 (I)I
L39:    iinc 2 1
L42:    iastore
L43:    iload_2
L44:    goto L17
L47:    athrow
L48:    iinc 1 1
L51:    iload_1
L52:    goto L6
L55:    athrow
L56:    aload_0
L57:    invokestatic Method hE method1143 ([[I)V
L60:    return
L61:    
        .attribute StackMap b'\x00\x06\x00\x06\x00\x02\x07\x00\x08\x01\x00\x01\x01\x00\x11\x00\x03\x07\x00\x08\x01\x01\x00\x01\x01\x00\x2F\x00\x00\x00\x01\x07\x00\x0E\x00\x30\x00\x03\x07\x00\x08\x01\x01\x00\x00\x00\x37\x00\x00\x00\x01\x07\x00\x0E\x00\x38\x00\x02\x07\x00\x08\x01\x00\x00'
    .end code
.end method

.method public static method1142 : ([[I)[I
    .code stack 5 locals 5
L0:     new java/util/ArrayList
L3:     dup
L4:     iconst_0
L5:     iconst_1
L6:     dup
L7:     pop2
L8:     invokespecial Method java/util/ArrayList <init> (I)V
L11:    astore_1
L12:    iconst_0
L13:    iconst_1
L14:    dup
L15:    pop2
L16:    dup
L17:    istore_2
L18:    bipush 28
L20:    iconst_1
L21:    dup
L22:    pop2
L23:    if_icmpge L114
L26:    iconst_1
L27:    dup
L28:    dup
L29:    pop2
L30:    istore_3
L31:    iconst_0
L32:    iconst_1
L33:    dup
L34:    pop2
L35:    dup
L36:    istore 4
L38:    bipush 10
L40:    iconst_1
L41:    dup
L42:    pop2
L43:    if_icmpge L94
L46:    aload_0
L47:    iload 4
L49:    aaload
L50:    iload_2
L51:    iaload
L52:    ifeq L75
L55:    aload_0
L56:    iload 4
L58:    aaload
L59:    iload_2
L60:    iaload
L61:    bipush 31
L63:    iconst_1
L64:    dup
L65:    pop2
L66:    iand
L67:    bipush 11
L69:    iconst_1
L70:    dup
L71:    pop2
L72:    if_icmpne L85
L75:    iconst_0
L76:    iconst_1
L77:    dup
L78:    pop2
L79:    dup
L80:    istore_3
L81:    goto L95
L84:    athrow
L85:    iinc 4 1
L88:    iload 4
L90:    goto L38
L93:    athrow
L94:    iload_3
L95:    ifeq L107
L98:    aload_1
L99:    iload_2
L100:   invokestatic Method java/lang/Integer valueOf (I)Ljava/lang/Integer;
L103:   invokevirtual Method java/util/ArrayList add (Ljava/lang/Object;)Z
L106:   pop
L107:   iinc 2 1
L110:   iload_2
L111:   goto L18
L114:   aload_1
L115:   invokevirtual Method java/util/ArrayList size ()I
L118:   newarray int
L120:   iconst_1
L121:   dup
L122:   pop2
L123:   astore_2
L124:   iconst_0
L125:   iconst_1
L126:   dup
L127:   pop2
L128:   dup
L129:   istore_3
L130:   aload_1
L131:   invokevirtual Method java/util/ArrayList size ()I
L134:   if_icmpge L158
L137:   aload_2
L138:   aload_1
L139:   iload_3
L140:   dup_x1
L141:   invokevirtual Method java/util/ArrayList get (I)Ljava/lang/Object;
L144:   checkcast java/lang/Integer
L147:   invokevirtual Method java/lang/Integer intValue ()I
L150:   iinc 3 1
L153:   iastore
L154:   iload_3
L155:   goto L130
L158:   aload_2
L159:   areturn
L160:   
        .attribute StackMap b'\x00\x0C\x00\x12\x00\x03\x07\x00\x08\x07\x00\x15\x01\x00\x01\x01\x00\x26\x00\x05\x07\x00\x08\x07\x00\x15\x01\x01\x01\x00\x01\x01\x00\x4B\x00\x05\x07\x00\x08\x07\x00\x15\x01\x01\x01\x00\x00\x00\x54\x00\x00\x00\x01\x07\x00\x0E\x00\x55\x00\x05\x07\x00\x08\x07\x00\x15\x01\x01\x01\x00\x00\x00\x5D\x00\x00\x00\x01\x07\x00\x0E\x00\x5E\x00\x05\x07\x00\x08\x07\x00\x15\x01\x01\x01\x00\x00\x00\x5F\x00\x05\x07\x00\x08\x07\x00\x15\x01\x01\x01\x00\x01\x01\x00\x6B\x00\x05\x07\x00\x08\x07\x00\x15\x01\x01\x01\x00\x00\x00\x72\x00\x03\x07\x00\x08\x07\x00\x15\x01\x00\x00\x00\x82\x00\x04\x07\x00\x08\x07\x00\x15\x07\x00\x29\x01\x00\x01\x01\x00\x9E\x00\x04\x07\x00\x08\x07\x00\x15\x07\x00\x29\x01\x00\x00'
    .end code
.end method

.method public <init> : ()V
    .code stack 1 locals 1
L0:     aload_0
L1:     invokespecial Method java/lang/Object <init> ()V
L4:     return
L5:     
    .end code
.end method

.method public static method1143 : ([[I)V
    .code stack 7 locals 4
L0:     iconst_0
L1:     iconst_1
L2:     dup
L3:     pop2
L4:     dup
L5:     istore_1
L6:     aload_0
L7:     arraylength
L8:     if_icmpge L319
L11:    iconst_0
L12:    iconst_1
L13:    dup
L14:    pop2
L15:    dup
L16:    istore_2
L17:    aload_0
L18:    iconst_0
L19:    iconst_1
L20:    dup
L21:    pop2
L22:    aaload
L23:    arraylength
L24:    if_icmpge L312
L27:    aload_0
L28:    iload_1
L29:    aaload
L30:    iload_2
L31:    iaload
L32:    bipush 31
L34:    iconst_1
L35:    dup
L36:    pop2
L37:    iand
L38:    dup
L39:    istore_3
L40:    ifeq L305
L43:    iload_1
L44:    ifeq L86
L47:    aload_0
L48:    iload_1
L49:    iconst_1
L50:    dup
L51:    dup
L52:    pop2
L53:    isub
L54:    aaload
L55:    iload_2
L56:    iaload
L57:    bipush 31
L59:    iconst_1
L60:    dup
L61:    pop2
L62:    iand
L63:    iload_3
L64:    if_icmpeq L100
L67:    aload_0
L68:    iload_1
L69:    dup_x1
L70:    aaload
L71:    iload_2
L72:    dup2
L73:    iaload
L74:    sipush 2048
L77:    iconst_1
L78:    dup
L79:    pop2
L80:    ior
L81:    iastore
L82:    goto L101
L85:    athrow
L86:    aload_0
L87:    iload_1
L88:    aaload
L89:    iload_2
L90:    dup2
L91:    iaload
L92:    sipush 2048
L95:    iconst_1
L96:    dup
L97:    pop2
L98:    ior
L99:    iastore
L100:   iload_1
L101:   aload_0
L102:   arraylength
L103:   iconst_1
L104:   dup
L105:   dup
L106:   pop2
L107:   isub
L108:   if_icmpeq L150
L111:   aload_0
L112:   iload_1
L113:   iconst_1
L114:   dup
L115:   dup
L116:   pop2
L117:   iadd
L118:   aaload
L119:   iload_2
L120:   iaload
L121:   bipush 31
L123:   iconst_1
L124:   dup
L125:   pop2
L126:   iand
L127:   iload_3
L128:   if_icmpeq L164
L131:   aload_0
L132:   iload_1
L133:   aaload
L134:   iload_2
L135:   dup_x1
L136:   dup2
L137:   iaload
L138:   sipush 512
L141:   iconst_1
L142:   dup
L143:   pop2
L144:   ior
L145:   iastore
L146:   goto L165
L149:   athrow
L150:   aload_0
L151:   iload_1
L152:   aaload
L153:   iload_2
L154:   dup2
L155:   iaload
L156:   sipush 512
L159:   iconst_1
L160:   dup
L161:   pop2
L162:   ior
L163:   iastore
L164:   iload_2
L165:   aload_0
L166:   iconst_0
L167:   iconst_1
L168:   dup
L169:   pop2
L170:   aaload
L171:   arraylength
L172:   iconst_1
L173:   dup
L174:   dup
L175:   pop2
L176:   isub
L177:   if_icmpeq L218
L180:   aload_0
L181:   iload_1
L182:   aaload
L183:   iload_2
L184:   iconst_1
L185:   dup
L186:   dup
L187:   pop2
L188:   iadd
L189:   iaload
L190:   bipush 31
L192:   iconst_1
L193:   dup
L194:   pop2
L195:   iand
L196:   iload_3
L197:   if_icmpeq L250
L200:   aload_0
L201:   iload_1
L202:   aaload
L203:   iload_2
L204:   dup_x1
L205:   dup2
L206:   iaload
L207:   sipush 1024
L210:   iconst_1
L211:   dup
L212:   pop2
L213:   ior
L214:   iastore
L215:   goto L251
L218:   iload_3
L219:   bipush 9
L221:   iconst_1
L222:   dup
L223:   pop2
L224:   if_icmpeq L250
L227:   iload_3
L228:   bipush 11
L230:   iconst_1
L231:   dup
L232:   pop2
L233:   if_icmpeq L250
L236:   aload_0
L237:   iload_1
L238:   aaload
L239:   iload_2
L240:   dup2
L241:   iaload
L242:   sipush 1024
L245:   iconst_1
L246:   dup
L247:   pop2
L248:   ior
L249:   iastore
L250:   iload_2
L251:   ifeq L291
L254:   aload_0
L255:   iload_1
L256:   aaload
L257:   iload_2
L258:   iconst_1
L259:   dup
L260:   dup
L261:   pop2
L262:   isub
L263:   iaload
L264:   bipush 31
L266:   iconst_1
L267:   dup
L268:   pop2
L269:   iand
L270:   iload_3
L271:   if_icmpeq L305
L274:   aload_0
L275:   iload_1
L276:   aaload
L277:   iload_2
L278:   dup2
L279:   iaload
L280:   sipush 256
L283:   iconst_1
L284:   dup
L285:   pop2
L286:   ior
L287:   iastore
L288:   goto L305
L291:   aload_0
L292:   iload_1
L293:   aaload
L294:   iload_2
L295:   dup2
L296:   iaload
L297:   sipush 256
L300:   iconst_1
L301:   dup
L302:   pop2
L303:   ior
L304:   iastore
L305:   iinc 2 1
L308:   iload_2
L309:   goto L17
L312:   iinc 1 1
L315:   iload_1
L316:   goto L6
L319:   return
L320:   
        .attribute StackMap b'\x00\x11\x00\x06\x00\x02\x07\x00\x08\x01\x00\x01\x01\x00\x11\x00\x03\x07\x00\x08\x01\x01\x00\x01\x01\x00\x55\x00\x00\x00\x01\x07\x00\x0E\x00\x56\x00\x04\x07\x00\x08\x01\x01\x01\x00\x00\x00\x64\x00\x04\x07\x00\x08\x01\x01\x01\x00\x00\x00\x65\x00\x04\x07\x00\x08\x01\x01\x01\x00\x01\x01\x00\x95\x00\x00\x00\x01\x07\x00\x0E\x00\x96\x00\x04\x07\x00\x08\x01\x01\x01\x00\x00\x00\xA4\x00\x04\x07\x00\x08\x01\x01\x01\x00\x00\x00\xA5\x00\x04\x07\x00\x08\x01\x01\x01\x00\x01\x01\x00\xDA\x00\x04\x07\x00\x08\x01\x01\x01\x00\x00\x00\xFA\x00\x04\x07\x00\x08\x01\x01\x01\x00\x00\x00\xFB\x00\x04\x07\x00\x08\x01\x01\x01\x00\x01\x01\x01\x23\x00\x04\x07\x00\x08\x01\x01\x01\x00\x00\x01\x31\x00\x04\x07\x00\x08\x01\x01\x01\x00\x00\x01\x38\x00\x03\x07\x00\x08\x01\x01\x00\x00\x01\x3F\x00\x02\x07\x00\x08\x01\x00\x00'
    .end code
.end method

.method public static method1144 : (J)[[I
    .code stack 5 locals 6
L0:     bipush 10
L2:     iconst_1
L3:     dup
L4:     pop2
L5:     bipush 28
L7:     iconst_1
L8:     dup
L9:     pop2
L10:    multianewarray [[I 2
L14:    astore_2
L15:    bipush 19
L17:    iconst_1
L18:    dup
L19:    pop2
L20:    dup
L21:    istore_3
L22:    bipush 28
L24:    iconst_1
L25:    dup
L26:    pop2
L27:    if_icmpge L73
L30:    iconst_0
L31:    iconst_1
L32:    dup
L33:    pop2
L34:    dup
L35:    istore 4
L37:    bipush 10
L39:    iconst_1
L40:    dup
L41:    pop2
L42:    if_icmpge L65
L45:    aload_2
L46:    iload 4
L48:    aaload
L49:    iload_3
L50:    bipush 45
L52:    iconst_1
L53:    dup
L54:    pop2
L55:    iinc 4 1
L58:    iastore
L59:    iload 4
L61:    goto L37
L64:    athrow
L65:    iinc 3 1
L68:    iload_3
L69:    goto L22
L72:    athrow
L73:    iconst_m1
L74:    iconst_1
L75:    dup
L76:    pop2
L77:    istore_3
L78:    new java/util/Random
L81:    dup
L82:    lload_0
L83:    invokespecial Method java/util/Random <init> (J)V
L86:    astore 4
L88:    bipush 19
L90:    iconst_1
L91:    dup
L92:    pop2
L93:    dup
L94:    istore_1
L95:    bipush 28
L97:    iconst_1
L98:    dup
L99:    pop2
L100:   if_icmpge L146
L103:   iconst_m1
L104:   iconst_1
L105:   dup
L106:   pop2
L107:   istore 5
L109:   aload 4
L111:   bipush 10
L113:   iconst_1
L114:   dup
L115:   pop2
L116:   invokevirtual Method java/util/Random nextInt (I)I
L119:   dup
L120:   istore 5
L122:   iload_3
L123:   if_icmpeq L109
L126:   iload 5
L128:   istore_3
L129:   aload_2
L130:   iload 5
L132:   aaload
L133:   iload_1
L134:   iconst_0
L135:   iconst_1
L136:   dup
L137:   pop2
L138:   iinc 1 1
L141:   iastore
L142:   iload_1
L143:   goto L95
L146:   aload_2
L147:   dup
L148:   invokestatic Method hE method1143 ([[I)V
L151:   areturn
L152:   
        .attribute StackMap b'\x00\x09\x00\x16\x00\x03\x04\x07\x00\x08\x01\x00\x01\x01\x00\x25\x00\x04\x04\x07\x00\x08\x01\x01\x00\x01\x01\x00\x40\x00\x00\x00\x01\x07\x00\x0E\x00\x41\x00\x04\x04\x07\x00\x08\x01\x01\x00\x00\x00\x48\x00\x00\x00\x01\x07\x00\x0E\x00\x49\x00\x03\x04\x07\x00\x08\x01\x00\x00\x00\x5F\x00\x05\x00\x01\x07\x00\x08\x01\x07\x00\x37\x00\x01\x01\x00\x6D\x00\x06\x00\x01\x07\x00\x08\x01\x07\x00\x37\x01\x00\x00\x00\x92\x00\x05\x00\x01\x07\x00\x08\x01\x07\x00\x37\x00\x00'
    .end code
.end method

.method public static method1145 : (I)I
    .code stack 4 locals 1
L0:     iload_0
L1:     sipush -3841
L4:     iconst_1
L5:     dup
L6:     pop2
L7:     iand
L8:     ireturn
L9:     
    .end code
.end method

.method public static method1146 : ([[I)[[I
    .code stack 7 locals 3
L0:     bipush 10
L2:     iconst_1
L3:     dup
L4:     pop2
L5:     bipush 18
L7:     iconst_1
L8:     dup
L9:     pop2
L10:    multianewarray [[I 2
L14:    astore_1
L15:    iconst_0
L16:    iconst_1
L17:    dup
L18:    pop2
L19:    dup
L20:    istore_2
L21:    bipush 10
L23:    iconst_1
L24:    dup
L25:    pop2
L26:    if_icmpge L60
L29:    aload_0
L30:    iload_2
L31:    aaload
L32:    bipush 10
L34:    iconst_1
L35:    dup
L36:    pop2
L37:    aload_1
L38:    iload_2
L39:    iinc 2 1
L42:    aaload
L43:    iconst_0
L44:    iconst_1
L45:    dup
L46:    pop2
L47:    bipush 18
L49:    iconst_1
L50:    dup
L51:    pop2
L52:    invokestatic Method java/lang/System arraycopy (Ljava/lang/Object;ILjava/lang/Object;II)V
L55:    iload_2
L56:    goto L21
L59:    athrow
L60:    aload_1
L61:    areturn
L62:    
        .attribute StackMap b'\x00\x03\x00\x15\x00\x03\x07\x00\x08\x07\x00\x08\x01\x00\x01\x01\x00\x3B\x00\x00\x00\x01\x07\x00\x0E\x00\x3C\x00\x03\x07\x00\x08\x07\x00\x08\x01\x00\x00'
    .end code
.end method
.end class
