.version 49 0
.class public final super HF
.super java/lang/Object
.implements f

.method public break : (LRg;)Ljava/lang/Object;
    .code stack 3 locals 3
L0:     bipush 9
L2:     iconst_1
L3:     dup
L4:     pop2
L5:     istore_2
L6:     new java/lang/StringBuilder
L9:     dup
L10:    invokespecial Method java/lang/StringBuilder <init> ()V
L13:    iload_2
L14:    aload_1
L15:    invokevirtual Method Rg goto ()I
L18:    isub
L19:    invokevirtual Method java/lang/StringBuilder append (I)Ljava/lang/StringBuilder;
L22:    ldc "/"
L24:    invokevirtual Method java/lang/StringBuilder append (Ljava/lang/String;)Ljava/lang/StringBuilder;
L27:    iload_2
L28:    invokevirtual Method java/lang/StringBuilder append (I)Ljava/lang/StringBuilder;
L31:    invokevirtual Method java/lang/StringBuilder toString ()Ljava/lang/String;
L34:    areturn
L35:    
    .end code
.end method

.method public <init> : ()V
    .code stack 1 locals 1
L0:     aload_0
L1:     invokespecial Method java/lang/Object <init> ()V
L4:     return
L5:     
    .end code
.end method
.innerclasses
    HF [0] [0] static
    f wD [0] static interface abstract
.end innerclasses
.enclosing method wD [0]
.end class
