.version 49 0
.class public final super hF
.super java/lang/Object
.implements java/util/concurrent/Callable
.field public final synthetic null F
.field public final synthetic this Lff;
.field public final synthetic char Lff;
.field public final synthetic else LNF;
.field public final synthetic "enum" Lae;
.field public final synthetic do [[I

.method public bridge synthetic call : ()Ljava/lang/Object;
    .code stack 1 locals 1
L0:     aload_0
L1:     invokevirtual Method hF break ()Lff;
L4:     areturn
L5:     
    .end code
    .exceptions java/lang/Exception
.end method

.method public <init> : (Lae;LNF;Lff;Lff;[[IF)V
    .code stack 13 locals 7
L0:     fload 6
L2:     aload_0
L3:     dup_x1
L4:     dup_x2
L5:     aload 5
L7:     aload 4
L9:     aload_0
L10:    dup_x1
L11:    aload_3
L12:    aload_2
L13:    aload_0
L14:    dup_x1
L15:    aload_1
L16:    putfield Field hF "enum" Lae;
L19:    putfield Field hF else LNF;
L22:    putfield Field hF char Lff;
L25:    putfield Field hF this Lff;
L28:    putfield Field hF do [[I
L31:    putfield Field hF null F
L34:    invokespecial Method java/lang/Object <init> ()V
L37:    return
L38:    
    .end code
.end method

.method public break : ()Lff;
    .code stack 8 locals 1
L0:     aload_0
L1:     dup
L2:     getfield Field hF else LNF;
L5:     swap
L6:     getfield Field hF char Lff;
L9:     aload_0
L10:    dup
L11:    getfield Field hF this Lff;
L14:    swap
L15:    getfield Field hF do [[I
L18:    aload_0
L19:    getfield Field hF null F
L22:    iconst_1
L23:    dup
L24:    dup
L25:    pop2
L26:    invokevirtual Method NF break (Lff;Lff;[[IFZ)Lff;
L29:    areturn
L30:    
    .end code
    .exceptions java/lang/Exception
.end method
.innerclasses
    hF [0] [0]
.end innerclasses
.enclosing method ae for ()V
.end class
