.version 49 0
.class public final super JB
.super java/lang/Object
.field public static final E Ljava/lang/String;
.field public static final C Ljava/lang/String;
.field public static final K Ljava/lang/String;
.field public static final G Ljava/lang/String;
.field private static final B Ljava/util/HashMap;
.field public static final c Ljava/lang/String;
.field public static final field1880 Ljava/lang/String;
.field public static final i Ljava/lang/String;
.field public static final m Ljava/lang/String;
.field private static final h I = 4096
.field public static final J Ljava/lang/String;
.field public static final l Ljava/lang/String;
.field private static D Ljava/util/HashMap;
.field public static final f Ljava/lang/String;
.field public static final j Ljava/lang/String;
.field public static final I Ljava/lang/String;
.field public static final b Ljava/lang/String;
.field public static final field1881 Ljava/lang/String;
.field public static final return Ljava/lang/String;
.field public static final field1882 Ljava/lang/String;
.field public static final switch Ljava/lang/String;
.field public static final field1883 Ljava/lang/String;
.field public static final field1884 Ljava/lang/String;
.field public static final field1885 Ljava/lang/String;
.field public static final field1886 Ljava/lang/String;
.field public static final field1887 Ljava/lang/String;
.field public static final field1888 Ljava/lang/String;
.field public static final field1889 Ljava/lang/String;
.field public static final field1890 Ljava/lang/String;
.field public static final field1891 Ljava/lang/String;
.field public static final throw Ljava/lang/String;
.field public static final package Ljava/lang/String;
.field public static final field1892 Ljava/lang/String;
.field public static final field1893 Ljava/lang/String;
.field public static final while Ljava/lang/String;
.field private static field1894 Ljavax/crypto/SecretKey;
.field public static final field1895 Ljava/lang/String;
.field public static final field1896 Ljava/lang/String;
.field public static final field1897 Ljava/lang/String;
.field public static final field1898 Ljava/lang/String;
.field public static final field1899 Ljava/lang/String;
.field public static final field1900 Ljava/lang/String;
.field public static final field1901 Ljava/lang/String;
.field public static final field1902 Ljava/lang/String;
.field public static final field1903 Ljava/lang/String;
.field public static final field1904 Ljava/lang/String;
.field public static final false Ljava/lang/String;
.field public static final field1905 Ljava/lang/String;
.field private static field1906 Ljava/util/prefs/Preferences;
.field public static final true Ljava/lang/String;
.field public static final field1907 Ljava/lang/String;
.field public static final field1908 Ljava/lang/String;
.field public static final field1909 Ljava/lang/String;
.field public static final field1910 Ljava/lang/String;
.field public static final field1911 Ljava/lang/String;
.field public static final field1912 Ljava/lang/String;
.field public static final field1913 Ljava/lang/String;
.field public static final field1914 Ljava/lang/String;
.field private static field1915 Ljava/util/HashMap;
.field public static final field1916 Ljava/lang/String;
.field public static final try Ljava/lang/String;
.field public static final field1917 Ljava/lang/String;
.field public static final new Ljava/lang/String;
.field public static final field1918 Ljava/lang/String;
.field public static final this Ljava/lang/String;
.field private static final field1919 Ljava/util/HashMap;
.field public static final field1920 Ljava/lang/String;
.field public static final field1921 Ljava/lang/String;
.field public static final field1922 Ljava/lang/String;

.method public static method815 : (LPc;)Z
    .code stack 4 locals 1
L0:     ldc ""
L2:     new java/lang/StringBuilder
L5:     dup
L6:     invokespecial Method java/lang/StringBuilder <init> ()V
L9:     iconst_0
L10:    aload_0
L11:    getfield Field Pc field370 Ljava/lang/String;
L14:    invokevirtual Method java/lang/StringBuilder insert (ILjava/lang/String;)Ljava/lang/StringBuilder;
L17:    ldc "a"
L19:    invokevirtual Method java/lang/StringBuilder append (Ljava/lang/String;)Ljava/lang/StringBuilder;
L22:    invokevirtual Method java/lang/StringBuilder toString ()Ljava/lang/String;
L25:    invokestatic Method JB method822 (Ljava/lang/String;)Ljava/lang/String;
L28:    invokevirtual Method java/lang/String equals (Ljava/lang/Object;)Z
L31:    ifne L40
L34:    iconst_1
L35:    dup
L36:    dup
L37:    pop2
L38:    ireturn
L39:    athrow
L40:    iconst_0
L41:    iconst_1
L42:    dup
L43:    pop2
L44:    ireturn
L45:    
        .attribute StackMap b'\x00\x02\x00\x27\x00\x00\x00\x01\x07\x00\x78\x00\x28\x00\x01\x07\x00\x06\x00\x00'
    .end code
.end method

.method public static new : ()V
    .code stack 9 locals 3
        .catch java/lang/Exception from L0 to L212 using L221
L0:     ldc "DES/ECB/PKCS5Padding"
L2:     invokestatic Method javax/crypto/Cipher getInstance (Ljava/lang/String;)Ljavax/crypto/Cipher;
L5:     dup
L6:     astore_0
L7:     iconst_1
L8:     dup
L9:     dup
L10:    pop2
L11:    getstatic Field JB field1894 Ljavax/crypto/SecretKey;
L14:    invokevirtual Method javax/crypto/Cipher init (ILjava/security/Key;)V
L17:    new java/io/ByteArrayOutputStream
L20:    dup
L21:    invokespecial Method java/io/ByteArrayOutputStream <init> ()V
L24:    astore_1
L25:    new java/io/ObjectOutputStream
L28:    dup
L29:    new javax/crypto/CipherOutputStream
L32:    dup
L33:    aload_1
L34:    aload_0
L35:    invokespecial Method javax/crypto/CipherOutputStream <init> (Ljava/io/OutputStream;Ljavax/crypto/Cipher;)V
L38:    invokespecial Method java/io/ObjectOutputStream <init> (Ljava/io/OutputStream;)V
L41:    astore_2
L42:    getstatic Field JB D Ljava/util/HashMap;
L45:    ldc "sv"
L47:    getstatic Field JB B Ljava/util/HashMap;
L50:    ldc "sv"
L52:    invokevirtual Method java/util/HashMap get (Ljava/lang/Object;)Ljava/lang/Object;
L55:    invokevirtual Method java/util/HashMap put (Ljava/lang/Object;Ljava/lang/Object;)Ljava/lang/Object;
L58:    aload_1
L59:    aload_2
L60:    dup
L61:    dup_x1
L62:    dup2
L63:    invokestatic Method java/lang/Math random ()D
L66:    invokevirtual Method java/io/ObjectOutputStream writeDouble (D)V
L69:    invokestatic Method JB method834 ()Ljava/lang/String;
L72:    invokevirtual Method java/io/ObjectOutputStream writeUTF (Ljava/lang/String;)V
L75:    getstatic Field JB field1915 Ljava/util/HashMap;
L78:    invokevirtual Method java/io/ObjectOutputStream writeObject (Ljava/lang/Object;)V
L81:    getstatic Field JB D Ljava/util/HashMap;
L84:    invokevirtual Method java/io/ObjectOutputStream writeObject (Ljava/lang/Object;)V
L87:    invokevirtual Method java/io/ObjectOutputStream close ()V
L90:    invokevirtual Method java/io/ByteArrayOutputStream toByteArray ()[B
L93:    astore_1
L94:    pop
L95:    getstatic Field JB field1906 Ljava/util/prefs/Preferences;
L98:    ldc "n"
L100:   aload_1
L101:   arraylength
L102:   sipush 4096
L105:   iconst_1
L106:   dup
L107:   pop2
L108:   iadd
L109:   iconst_1
L110:   dup
L111:   dup
L112:   pop2
L113:   isub
L114:   sipush 4096
L117:   iconst_1
L118:   dup
L119:   pop2
L120:   idiv
L121:   invokevirtual Method java/util/prefs/Preferences putInt (Ljava/lang/String;I)V
L124:   iconst_0
L125:   iconst_1
L126:   dup
L127:   pop2
L128:   dup
L129:   istore_2
L130:   aload_1
L131:   arraylength
L132:   sipush 4096
L135:   iconst_1
L136:   dup
L137:   pop2
L138:   iadd
L139:   iconst_1
L140:   dup
L141:   dup
L142:   pop2
L143:   isub
L144:   sipush 4096
L147:   iconst_1
L148:   dup
L149:   pop2
L150:   idiv
L151:   if_icmpge L213
L154:   getstatic Field JB field1906 Ljava/util/prefs/Preferences;
L157:   new java/lang/StringBuilder
L160:   dup
L161:   invokespecial Method java/lang/StringBuilder <init> ()V
L164:   iconst_0
L165:   ldc "c"
L167:   invokevirtual Method java/lang/StringBuilder insert (ILjava/lang/String;)Ljava/lang/StringBuilder;
L170:   iload_2
L171:   invokevirtual Method java/lang/StringBuilder append (I)Ljava/lang/StringBuilder;
L174:   invokevirtual Method java/lang/StringBuilder toString ()Ljava/lang/String;
L177:   aload_1
L178:   iload_2
L179:   sipush 4096
L182:   iconst_1
L183:   dup
L184:   pop2
L185:   imul
L186:   iload_2
L187:   iconst_1
L188:   dup
L189:   dup
L190:   pop2
L191:   iadd
L192:   sipush 4096
L195:   iconst_1
L196:   dup
L197:   pop2
L198:   iinc 2 1
L201:   imul
L202:   invokestatic Method java/util/Arrays copyOfRange ([BII)[B
L205:   invokevirtual Method java/util/prefs/Preferences putByteArray (Ljava/lang/String;[B)V
L208:   iload_2
L209:   goto L130
L212:   athrow
        .catch java/lang/Exception from L213 to L219 using L221
L213:   getstatic Field JB field1906 Ljava/util/prefs/Preferences;
L216:   invokevirtual Method java/util/prefs/Preferences flush ()V
L219:   return
L220:   athrow
L221:   astore_0
L222:   aload_0
L223:   invokevirtual Method java/lang/Exception printStackTrace ()V
L226:   return
L227:   
        .attribute StackMap b'\x00\x05\x00\x82\x00\x03\x07\x00\x7E\x07\x00\xCF\x01\x00\x01\x01\x00\xD4\x00\x00\x00\x01\x07\x00\x78\x00\xD5\x00\x03\x07\x00\x7E\x07\x00\xCF\x01\x00\x00\x00\xDC\x00\x00\x00\x01\x07\x00\x78\x00\xDD\x00\x00\x00\x01\x07\x00\x7A'
    .end code
.end method

.method public static try : ()Ljava/util/Map;
    .code stack 24 locals 3
L0:     new java/util/LinkedHashMap
L3:     dup
L4:     invokespecial Method java/util/LinkedHashMap <init> ()V
L7:     dup
L8:     astore_0
L9:     ldc "uuid"
L11:    ldc "uuid"
L13:    invokestatic Method JB method822 (Ljava/lang/String;)Ljava/lang/String;
L16:    invokeinterface InterfaceMethod java/util/Map put (Ljava/lang/Object;Ljava/lang/Object;)Ljava/lang/Object; 3
L21:    aload_0
L22:    ldc "CultrisVersion"
L24:    ldc "1.4c"
L26:    invokeinterface InterfaceMethod java/util/Map put (Ljava/lang/Object;Ljava/lang/Object;)Ljava/lang/Object; 3
L31:    aload_0
L32:    ldc "Cores"
L34:    new java/lang/StringBuilder
L37:    dup
L38:    invokespecial Method java/lang/StringBuilder <init> ()V
L41:    invokestatic Method java/lang/Runtime getRuntime ()Ljava/lang/Runtime;
L44:    invokevirtual Method java/lang/Runtime availableProcessors ()I
L47:    invokevirtual Method java/lang/StringBuilder append (I)Ljava/lang/StringBuilder;
L50:    ldc ""
L52:    invokevirtual Method java/lang/StringBuilder append (Ljava/lang/String;)Ljava/lang/StringBuilder;
L55:    invokevirtual Method java/lang/StringBuilder toString ()Ljava/lang/String;
L58:    invokeinterface InterfaceMethod java/util/Map put (Ljava/lang/Object;Ljava/lang/Object;)Ljava/lang/Object; 3
L63:    aload_0
L64:    ldc "Adapter"
L66:    invokestatic Method org/lwjgl/opengl/Display method3025 ()Ljava/lang/String;
L69:    invokeinterface InterfaceMethod java/util/Map put (Ljava/lang/Object;Ljava/lang/Object;)Ljava/lang/Object; 3
L74:    aload_0
L75:    ldc_w "OS"
L78:    ldc_w "os.name"
L81:    invokestatic Method java/lang/System getProperty (Ljava/lang/String;)Ljava/lang/String;
L84:    invokeinterface InterfaceMethod java/util/Map put (Ljava/lang/Object;Ljava/lang/Object;)Ljava/lang/Object; 3
L89:    aload_0
L90:    ldc_w "OS-Arch"
L93:    ldc_w "os.arch"
L96:    invokestatic Method java/lang/System getProperty (Ljava/lang/String;)Ljava/lang/String;
L99:    invokeinterface InterfaceMethod java/util/Map put (Ljava/lang/Object;Ljava/lang/Object;)Ljava/lang/Object; 3
L104:   aload_0
L105:   ldc_w "OS-Version"
L108:   ldc_w "os.version"
L111:   invokestatic Method java/lang/System getProperty (Ljava/lang/String;)Ljava/lang/String;
L114:   invokeinterface InterfaceMethod java/util/Map put (Ljava/lang/Object;Ljava/lang/Object;)Ljava/lang/Object; 3
L119:   aload_0
L120:   ldc_w "li"
L123:   new java/lang/StringBuilder
L126:   dup
L127:   invokespecial Method java/lang/StringBuilder <init> ()V
L130:   iconst_0
L131:   getstatic Field Pc field373 LPc;
L134:   getfield Field Pc field370 Ljava/lang/String;
L137:   invokevirtual Method java/lang/StringBuilder insert (ILjava/lang/String;)Ljava/lang/StringBuilder;
L140:   ldc_w "li"
L143:   invokevirtual Method java/lang/StringBuilder append (Ljava/lang/String;)Ljava/lang/StringBuilder;
L146:   invokevirtual Method java/lang/StringBuilder toString ()Ljava/lang/String;
L149:   invokestatic Method JB method822 (Ljava/lang/String;)Ljava/lang/String;
L152:   invokeinterface InterfaceMethod java/util/Map put (Ljava/lang/Object;Ljava/lang/Object;)Ljava/lang/Object; 3
L157:   aload_0
L158:   ldc "a"
L160:   new java/lang/StringBuilder
L163:   dup
L164:   invokespecial Method java/lang/StringBuilder <init> ()V
L167:   iconst_0
L168:   getstatic Field Pc field373 LPc;
L171:   getfield Field Pc field370 Ljava/lang/String;
L174:   invokevirtual Method java/lang/StringBuilder insert (ILjava/lang/String;)Ljava/lang/StringBuilder;
L177:   ldc "a"
L179:   invokevirtual Method java/lang/StringBuilder append (Ljava/lang/String;)Ljava/lang/StringBuilder;
L182:   invokevirtual Method java/lang/StringBuilder toString ()Ljava/lang/String;
L185:   invokestatic Method JB method822 (Ljava/lang/String;)Ljava/lang/String;
L188:   invokeinterface InterfaceMethod java/util/Map put (Ljava/lang/Object;Ljava/lang/Object;)Ljava/lang/Object; 3
L193:   aload_0
L194:   ldc_w "dc"
L197:   new java/lang/StringBuilder
L200:   dup
L201:   invokespecial Method java/lang/StringBuilder <init> ()V
L204:   iconst_0
L205:   ldc ""
L207:   invokevirtual Method java/lang/StringBuilder insert (ILjava/lang/String;)Ljava/lang/StringBuilder;
L210:   ldc_w "dc"
L213:   invokestatic Method JB method831 (Ljava/lang/String;)I
L216:   invokevirtual Method java/lang/StringBuilder append (I)Ljava/lang/StringBuilder;
L219:   invokevirtual Method java/lang/StringBuilder toString ()Ljava/lang/String;
L222:   invokeinterface InterfaceMethod java/util/Map put [_163] 3
L227:   aload_0
L228:   ldc_w "det_sw"
L231:   new java/lang/StringBuilder
L234:   dup
L235:   invokespecial Method java/lang/StringBuilder <init> ()V
L238:   iconst_0
L239:   ldc ""
L241:   invokevirtual Method java/lang/StringBuilder insert (ILjava/lang/String;)Ljava/lang/StringBuilder;
L244:   ldc_w "det_sw"
L247:   invokestatic Method JB method831 (Ljava/lang/String;)I
L250:   invokevirtual Method java/lang/StringBuilder append (I)Ljava/lang/StringBuilder;
L253:   invokevirtual Method java/lang/StringBuilder toString ()Ljava/lang/String;
L256:   invokeinterface InterfaceMethod java/util/Map put [_163] 3
L261:   aload_0
L262:   ldc_w "q"
L265:   new java/lang/StringBuilder
L268:   dup
L269:   invokespecial Method java/lang/StringBuilder <init> ()V
L272:   iconst_0
L273:   ldc ""
L275:   invokevirtual Method java/lang/StringBuilder insert (ILjava/lang/String;)Ljava/lang/StringBuilder;
L278:   ldc_w "q"
L281:   invokestatic Method JB method831 (Ljava/lang/String;)I
L284:   invokevirtual Method java/lang/StringBuilder append (I)Ljava/lang/StringBuilder;
L287:   invokevirtual Method java/lang/StringBuilder toString ()Ljava/lang/String;
L290:   invokeinterface InterfaceMethod java/util/Map put [_163] 3
L295:   aload_0
L296:   ldc_w "s"
L299:   new java/lang/StringBuilder
L302:   dup
L303:   invokespecial Method java/lang/StringBuilder <init> ()V
L306:   iconst_0
L307:   ldc ""
L309:   invokevirtual Method java/lang/StringBuilder insert (ILjava/lang/String;)Ljava/lang/StringBuilder;
L312:   ldc_w "s"
L315:   invokestatic Method JB method831 (Ljava/lang/String;)I
L318:   invokevirtual Method java/lang/StringBuilder append (I)Ljava/lang/StringBuilder;
L321:   invokevirtual Method java/lang/StringBuilder toString ()Ljava/lang/String;
L324:   invokeinterface InterfaceMethod java/util/Map put [_163] 3
L329:   aload_0
L330:   ldc_w "r"
L333:   new java/lang/StringBuilder
L336:   dup
L337:   invokespecial Method java/lang/StringBuilder <init> ()V
L340:   iconst_0
L341:   ldc ""
L343:   invokevirtual Method java/lang/StringBuilder insert (ILjava/lang/String;)Ljava/lang/StringBuilder;
L346:   ldc_w "r"
L349:   invokestatic Method JB method831 (Ljava/lang/String;)I
L352:   invokevirtual Method java/lang/StringBuilder append (I)Ljava/lang/StringBuilder;
L355:   invokevirtual Method java/lang/StringBuilder toString ()Ljava/lang/String;
L358:   invokeinterface InterfaceMethod java/util/Map put [_163] 3
L363:   aload_0
L364:   ldc_w "h"
L367:   new java/lang/StringBuilder
L370:   dup
L371:   invokespecial Method java/lang/StringBuilder <init> ()V
L374:   iconst_0
L375:   ldc ""
L377:   invokevirtual Method java/lang/StringBuilder insert (ILjava/lang/String;)Ljava/lang/StringBuilder;
L380:   new java/lang/StringBuilder
L383:   dup
L384:   invokespecial Method java/lang/StringBuilder <init> ()V
L387:   iconst_0
L388:   getstatic Field Pc field373 LPc;
L391:   getfield Field Pc field370 Ljava/lang/String;
L394:   invokevirtual Method java/lang/StringBuilder insert (ILjava/lang/String;)Ljava/lang/StringBuilder;
L397:   ldc_w "h"
L400:   invokevirtual Method java/lang/StringBuilder append (Ljava/lang/String;)Ljava/lang/StringBuilder;
L403:   invokevirtual Method java/lang/StringBuilder toString ()Ljava/lang/String;
L406:   invokestatic Method JB method831 (Ljava/lang/String;)I
L409:   invokevirtual Method java/lang/StringBuilder append (I)Ljava/lang/StringBuilder;
L412:   invokevirtual Method java/lang/StringBuilder toString ()Ljava/lang/String;
L415:   invokeinterface InterfaceMethod java/util/Map put [_163] 3
L420:   aload_0
L421:   ldc_w "i"
L424:   new java/lang/StringBuilder
L427:   dup
L428:   invokespecial Method java/lang/StringBuilder <init> ()V
L431:   iconst_0
L432:   ldc ""
L434:   invokevirtual Method java/lang/StringBuilder insert (ILjava/lang/String;)Ljava/lang/StringBuilder;
L437:   new java/lang/StringBuilder
L440:   dup
L441:   invokespecial Method java/lang/StringBuilder <init> ()V
L444:   iconst_0
L445:   getstatic Field Pc field373 LPc;
L448:   getfield Field Pc field370 Ljava/lang/String;
L451:   invokevirtual Method java/lang/StringBuilder insert (ILjava/lang/String;)Ljava/lang/StringBuilder;
L454:   ldc_w "i"
L457:   invokevirtual Method java/lang/StringBuilder append (Ljava/lang/String;)Ljava/lang/StringBuilder;
L460:   invokevirtual Method java/lang/StringBuilder toString ()Ljava/lang/String;
L463:   invokestatic Method JB method831 (Ljava/lang/String;)I
L466:   invokevirtual Method java/lang/StringBuilder append (I)Ljava/lang/StringBuilder;
L469:   invokevirtual Method java/lang/StringBuilder toString ()Ljava/lang/String;
L472:   invokeinterface InterfaceMethod java/util/Map put [_163] 3
L477:   aload_0
L478:   ldc_w "l"
L481:   new java/lang/StringBuilder
L484:   dup
L485:   invokespecial Method java/lang/StringBuilder <init> ()V
L488:   iconst_0
L489:   ldc ""
L491:   invokevirtual Method java/lang/StringBuilder insert (ILjava/lang/String;)Ljava/lang/StringBuilder;
L494:   ldc_w "l"
L497:   invokestatic Method JB method831 (Ljava/lang/String;)I
L500:   invokevirtual Method java/lang/StringBuilder append (I)Ljava/lang/StringBuilder;
L503:   invokevirtual Method java/lang/StringBuilder toString ()Ljava/lang/String;
L506:   invokeinterface InterfaceMethod java/util/Map put [_163] 3
L511:   aload_0
L512:   ldc_w "k"
L515:   new java/lang/StringBuilder
L518:   dup
L519:   invokespecial Method java/lang/StringBuilder <init> ()V
L522:   iconst_0
L523:   ldc ""
L525:   invokevirtual Method java/lang/StringBuilder insert (ILjava/lang/String;)Ljava/lang/StringBuilder;
L528:   ldc_w "k"
L531:   invokestatic Method JB method831 (Ljava/lang/String;)I
L534:   invokevirtual Method java/lang/StringBuilder append (I)Ljava/lang/StringBuilder;
L537:   invokevirtual Method java/lang/StringBuilder toString ()Ljava/lang/String;
L540:   invokeinterface InterfaceMethod java/util/Map put [_163] 3
L545:   aload_0
L546:   ldc "sv"
L548:   new java/lang/StringBuilder
L551:   dup
L552:   invokespecial Method java/lang/StringBuilder <init> ()V
L555:   iconst_0
L556:   ldc ""
L558:   invokevirtual Method java/lang/StringBuilder insert (ILjava/lang/String;)Ljava/lang/StringBuilder;
L561:   ldc "sv"
L563:   invokestatic Method JB method831 (Ljava/lang/String;)I
L566:   invokevirtual Method java/lang/StringBuilder append (I)Ljava/lang/StringBuilder;
L569:   invokevirtual Method java/lang/StringBuilder toString ()Ljava/lang/String;
L572:   invokeinterface InterfaceMethod java/util/Map put [_163] 3
L577:   new java/lang/StringBuilder
L580:   aload_0
L581:   dup_x1
L582:   dup
L583:   pop2
L584:   dup
L585:   invokespecial Method java/lang/StringBuilder <init> ()V
L588:   getstatic Field Pc field373 LPc;
L591:   getfield Field Pc field370 Ljava/lang/String;
L594:   invokevirtual Method java/lang/StringBuilder append (Ljava/lang/String;)Ljava/lang/StringBuilder;
L597:   ldc_w "mc"
L600:   invokevirtual Method java/lang/StringBuilder append (Ljava/lang/String;)Ljava/lang/StringBuilder;
L603:   invokevirtual Method java/lang/StringBuilder toString ()Ljava/lang/String;
L606:   new java/lang/StringBuilder
L609:   dup
L610:   invokespecial Method java/lang/StringBuilder <init> ()V
L613:   iconst_0
L614:   getstatic Field Pc field373 LPc;
L617:   getfield Field Pc field370 Ljava/lang/String;
L620:   invokevirtual Method java/lang/StringBuilder insert (ILjava/lang/String;)Ljava/lang/StringBuilder;
L623:   ldc_w "mc"
L626:   invokevirtual Method java/lang/StringBuilder append (Ljava/lang/String;)Ljava/lang/StringBuilder;
L629:   invokevirtual Method java/lang/StringBuilder toString ()Ljava/lang/String;
L632:   invokestatic Method JB method822 (Ljava/lang/String;)Ljava/lang/String;
L635:   invokeinterface InterfaceMethod java/util/Map put [_163] 3
L640:   getstatic Field SE field2071 Ljava/util/Map;
L643:   invokeinterface InterfaceMethod java/util/Map keySet ()Ljava/util/Set; 1
L648:   invokeinterface InterfaceMethod java/util/Set iterator ()Ljava/util/Iterator; 1
L653:   astore_1
L654:   pop2
L655:   pop2
L656:   pop2
L657:   pop2
L658:   pop2
L659:   pop2
L660:   pop2
L661:   pop2
L662:   pop2
L663:   pop2
L664:   aload_1
L665:   invokeinterface InterfaceMethod java/util/Iterator hasNext ()Z 1
L670:   ifeq L903
L673:   aload_1
L674:   invokeinterface InterfaceMethod java/util/Iterator next ()Ljava/lang/Object; 1
L679:   checkcast java/lang/String
L682:   astore_2
L683:   aload_1
L684:   new java/lang/StringBuilder
L687:   aload_0
L688:   dup_x1
L689:   dup
L690:   pop2
L691:   dup
L692:   invokespecial Method java/lang/StringBuilder <init> ()V
L695:   ldc_w "chg|s|"
L698:   invokevirtual Method java/lang/StringBuilder append (Ljava/lang/String;)Ljava/lang/StringBuilder;
L701:   aload_2
L702:   invokevirtual Method java/lang/StringBuilder append (Ljava/lang/String;)Ljava/lang/StringBuilder;
L705:   invokevirtual Method java/lang/StringBuilder toString ()Ljava/lang/String;
L708:   new java/lang/StringBuilder
L711:   dup
L712:   invokespecial Method java/lang/StringBuilder <init> ()V
L715:   new java/lang/StringBuilder
L718:   dup
L719:   invokespecial Method java/lang/StringBuilder <init> ()V
L722:   iconst_0
L723:   ldc_w "chg|s|"
L726:   invokevirtual Method java/lang/StringBuilder insert (ILjava/lang/String;)Ljava/lang/StringBuilder;
L729:   aload_2
L730:   invokevirtual Method java/lang/StringBuilder append (Ljava/lang/String;)Ljava/lang/StringBuilder;
L733:   invokevirtual Method java/lang/StringBuilder toString ()Ljava/lang/String;
L736:   invokestatic Method JB method831 (Ljava/lang/String;)I
L739:   invokevirtual Method java/lang/StringBuilder append (I)Ljava/lang/StringBuilder;
L742:   ldc ""
L744:   invokevirtual Method java/lang/StringBuilder append (Ljava/lang/String;)Ljava/lang/StringBuilder;
L747:   invokevirtual Method java/lang/StringBuilder toString ()Ljava/lang/String;
L750:   invokeinterface InterfaceMethod java/util/Map put [_163] 3
L755:   new java/lang/StringBuilder
L758:   aload_0
L759:   dup_x1
L760:   dup
L761:   pop2
L762:   dup
L763:   invokespecial Method java/lang/StringBuilder <init> ()V
L766:   ldc_w "chg|t|"
L769:   invokevirtual Method java/lang/StringBuilder append (Ljava/lang/String;)Ljava/lang/StringBuilder;
L772:   aload_2
L773:   invokevirtual Method java/lang/StringBuilder append (Ljava/lang/String;)Ljava/lang/StringBuilder;
L776:   invokevirtual Method java/lang/StringBuilder toString ()Ljava/lang/String;
L779:   new java/lang/StringBuilder
L782:   dup
L783:   invokespecial Method java/lang/StringBuilder <init> ()V
L786:   new java/lang/StringBuilder
L789:   dup
L790:   invokespecial Method java/lang/StringBuilder <init> ()V
L793:   iconst_0
L794:   ldc_w "chg|t|"
L797:   invokevirtual Method java/lang/StringBuilder insert (ILjava/lang/String;)Ljava/lang/StringBuilder;
L800:   aload_2
L801:   invokevirtual Method java/lang/StringBuilder append (Ljava/lang/String;)Ljava/lang/StringBuilder;
L804:   invokevirtual Method java/lang/StringBuilder toString ()Ljava/lang/String;
L807:   invokestatic Method JB method831 (Ljava/lang/String;)I
L810:   invokevirtual Method java/lang/StringBuilder append (I)Ljava/lang/StringBuilder;
L813:   ldc ""
L815:   invokevirtual Method java/lang/StringBuilder append (Ljava/lang/String;)Ljava/lang/StringBuilder;
L818:   invokevirtual Method java/lang/StringBuilder toString ()Ljava/lang/String;
L821:   invokeinterface InterfaceMethod java/util/Map put [_163] 3
L826:   new java/lang/StringBuilder
L829:   aload_0
L830:   dup_x1
L831:   dup
L832:   pop2
L833:   dup
L834:   invokespecial Method java/lang/StringBuilder <init> ()V
L837:   ldc_w "chg|w|"
L840:   invokevirtual Method java/lang/StringBuilder append (Ljava/lang/String;)Ljava/lang/StringBuilder;
L843:   aload_2
L844:   invokevirtual Method java/lang/StringBuilder append (Ljava/lang/String;)Ljava/lang/StringBuilder;
L847:   invokevirtual Method java/lang/StringBuilder toString ()Ljava/lang/String;
L850:   new java/lang/StringBuilder
L853:   dup
L854:   invokespecial Method java/lang/StringBuilder <init> ()V
L857:   new java/lang/StringBuilder
L860:   dup
L861:   invokespecial Method java/lang/StringBuilder <init> ()V
L864:   iconst_0
L865:   ldc_w "chg|w|"
L868:   invokevirtual Method java/lang/StringBuilder insert (ILjava/lang/String;)Ljava/lang/StringBuilder;
L871:   aload_2
L872:   invokevirtual Method java/lang/StringBuilder append (Ljava/lang/String;)Ljava/lang/StringBuilder;
L875:   invokevirtual Method java/lang/StringBuilder toString ()Ljava/lang/String;
L878:   invokestatic Method JB method831 (Ljava/lang/String;)I
L881:   invokevirtual Method java/lang/StringBuilder append (I)Ljava/lang/StringBuilder;
L884:   ldc ""
L886:   invokevirtual Method java/lang/StringBuilder append (Ljava/lang/String;)Ljava/lang/StringBuilder;
L889:   invokevirtual Method java/lang/StringBuilder toString ()Ljava/lang/String;
L892:   invokeinterface InterfaceMethod java/util/Map put [_163] 3
L897:   pop
L898:   pop2
L899:   goto L665
L902:   athrow
L903:   aload_0
L904:   areturn
L905:   
        .attribute StackMap b'\x00\x03\x02\x99\x00\x02\x07\x00\xE6\x07\x01\x41\x00\x01\x07\x01\x41\x03\x86\x00\x00\x00\x01\x07\x00\x78\x03\x87\x00\x02\x07\x00\xE6\x07\x01\x41\x00\x00'
    .end code
.end method

.method public static method816 : (LPc;)Z
    .code stack 3 locals 1
L0:     new java/lang/StringBuilder
L3:     dup
L4:     invokespecial Method java/lang/StringBuilder <init> ()V
L7:     iconst_0
L8:     aload_0
L9:     getfield Field Pc field370 Ljava/lang/String;
L12:    invokevirtual Method java/lang/StringBuilder insert (ILjava/lang/String;)Ljava/lang/StringBuilder;
L15:    ldc_w "pag"
L18:    invokevirtual Method java/lang/StringBuilder append (Ljava/lang/String;)Ljava/lang/StringBuilder;
L21:    invokevirtual Method java/lang/StringBuilder toString ()Ljava/lang/String;
L24:    invokestatic Method JB method831 (Ljava/lang/String;)I
L27:    ifeq L36
L30:    iconst_1
L31:    dup
L32:    dup
L33:    pop2
L34:    ireturn
L35:    athrow
L36:    iconst_0
L37:    iconst_1
L38:    dup
L39:    pop2
L40:    ireturn
L41:    
        .attribute StackMap b'\x00\x02\x00\x23\x00\x00\x00\x01\x07\x00\x78\x00\x24\x00\x01\x07\x00\x06\x00\x00'
    .end code
.end method

.method public static method817 : (LPc;)Ljava/lang/String;
    .code stack 3 locals 1
L0:     new java/lang/StringBuilder
L3:     dup
L4:     invokespecial Method java/lang/StringBuilder <init> ()V
L7:     iconst_0
L8:     aload_0
L9:     getfield Field Pc field370 Ljava/lang/String;
L12:    invokevirtual Method java/lang/StringBuilder insert (ILjava/lang/String;)Ljava/lang/StringBuilder;
L15:    ldc "a"
L17:    invokevirtual Method java/lang/StringBuilder append (Ljava/lang/String;)Ljava/lang/StringBuilder;
L20:    invokevirtual Method java/lang/StringBuilder toString ()Ljava/lang/String;
L23:    invokestatic Method JB method822 (Ljava/lang/String;)Ljava/lang/String;
L26:    areturn
L27:    
    .end code
.end method

.method public static this : ()V
    .code stack 3 locals 0
L0:     ldc_w "lum"
L3:     invokestatic Method java/lang/System currentTimeMillis ()J
L6:     invokestatic Method java/lang/Long toString (J)Ljava/lang/String;
L9:     invokestatic Method JB method826 (Ljava/lang/String;Ljava/lang/String;)V
L12:    return
L13:    
    .end code
.end method

.method public static method818 : ()F
    .code stack 2 locals 0
L0:     ldc_w "r"
L3:     invokestatic Method JB method831 (Ljava/lang/String;)I
L6:     ldc_w "r"
L9:     invokestatic Method JB method831 (Ljava/lang/String;)I
L12:    imul
L13:    i2f
L14:    ldc_w 8.1e1f
L17:    fdiv
L18:    freturn
L19:    
    .end code
.end method

.method public static method819 : ()V
    .code stack 7 locals 7
        .catch java/lang/Exception from L0 to L33 using L602
L0:     getstatic Field JB field1906 Ljava/util/prefs/Preferences;
L3:     ldc "n"
L5:     iconst_0
L6:     iconst_1
L7:     dup
L8:     pop2
L9:     invokevirtual Method java/util/prefs/Preferences getInt (Ljava/lang/String;I)I
L12:    sipush 4096
L15:    iconst_1
L16:    dup
L17:    pop2
L18:    imul
L19:    newarray byte
L21:    iconst_1
L22:    dup
L23:    pop2
L24:    dup
L25:    astore_0
L26:    arraylength
L27:    ifne L35
L30:    invokestatic Method JB method821 ()V
L33:    return
L34:    athrow
        .catch java/lang/Exception from L35 to L117 using L602
L35:    iconst_0
L36:    iconst_1
L37:    dup
L38:    pop2
L39:    dup
L40:    istore_1
L41:    aload_0
L42:    arraylength
L43:    sipush 4096
L46:    iconst_1
L47:    dup
L48:    pop2
L49:    idiv
L50:    if_icmpge L118
L53:    getstatic Field JB field1906 Ljava/util/prefs/Preferences;
L56:    new java/lang/StringBuilder
L59:    dup
L60:    invokespecial Method java/lang/StringBuilder <init> ()V
L63:    iconst_0
L64:    ldc "c"
L66:    invokevirtual Method java/lang/StringBuilder insert (ILjava/lang/String;)Ljava/lang/StringBuilder;
L69:    iload_1
L70:    invokevirtual Method java/lang/StringBuilder append (I)Ljava/lang/StringBuilder;
L73:    invokevirtual Method java/lang/StringBuilder toString ()Ljava/lang/String;
L76:    iconst_0
L77:    iconst_1
L78:    dup
L79:    pop2
L80:    newarray byte
L82:    iconst_1
L83:    dup
L84:    pop2
L85:    invokevirtual Method java/util/prefs/Preferences getByteArray (Ljava/lang/String;[B)[B
L88:    iconst_0
L89:    iconst_1
L90:    dup
L91:    pop2
L92:    aload_0
L93:    iload_1
L94:    sipush 4096
L97:    iconst_1
L98:    dup
L99:    pop2
L100:   imul
L101:   sipush 4096
L104:   iconst_1
L105:   iinc 1 1
L108:   dup
L109:   pop2
L110:   invokestatic Method java/lang/System arraycopy (Ljava/lang/Object;ILjava/lang/Object;II)V
L113:   iload_1
L114:   goto L41
L117:   athrow
        .catch java/lang/Exception from L118 to L599 using L602
L118:   ldc "DES/ECB/PKCS5Padding"
L120:   invokestatic Method javax/crypto/Cipher getInstance (Ljava/lang/String;)Ljavax/crypto/Cipher;
L123:   dup
L124:   astore_1
L125:   iconst_2
L126:   iconst_1
L127:   dup
L128:   pop2
L129:   getstatic Field JB field1894 Ljavax/crypto/SecretKey;
L132:   invokevirtual Method javax/crypto/Cipher init (ILjava/security/Key;)V
L135:   new java/io/ObjectInputStream
L138:   dup
L139:   new javax/crypto/CipherInputStream
L142:   dup
L143:   new java/io/ByteArrayInputStream
L146:   dup
L147:   aload_0
L148:   invokespecial Method java/io/ByteArrayInputStream <init> ([B)V
L151:   aload_1
L152:   invokespecial Method javax/crypto/CipherInputStream <init> (Ljava/io/InputStream;Ljavax/crypto/Cipher;)V
L155:   invokespecial Method java/io/ObjectInputStream <init> (Ljava/io/InputStream;)V
L158:   dup
L159:   astore_2
L160:   dup
L161:   invokevirtual Method java/io/ObjectInputStream readDouble ()D
L164:   pop2
L165:   invokevirtual Method java/io/ObjectInputStream readUTF ()Ljava/lang/String;
L168:   invokestatic Method JB method834 ()Ljava/lang/String;
L171:   invokevirtual Method java/lang/String equals (Ljava/lang/Object;)Z
L174:   ifne L186
L177:   getstatic Field java/lang/System out Ljava/io/PrintStream;
L180:   ldc_w "Hash mismatch"
L183:   invokevirtual Method java/io/PrintStream println (Ljava/lang/String;)V
L186:   aload_2
L187:   invokevirtual Method java/io/ObjectInputStream readObject ()Ljava/lang/Object;
L190:   checkcast java/util/HashMap
L193:   putstatic Field JB field1915 Ljava/util/HashMap;
L196:   aload_2
L197:   invokevirtual Method java/io/ObjectInputStream readObject ()Ljava/lang/Object;
L200:   checkcast java/util/HashMap
L203:   putstatic Field JB D Ljava/util/HashMap;
L206:   aload_2
L207:   invokevirtual Method java/io/ObjectInputStream close ()V
L210:   getstatic Field JB D Ljava/util/HashMap;
L213:   ldc "sv"
L215:   invokevirtual Method java/util/HashMap containsKey (Ljava/lang/Object;)Z
L218:   ifne L237
L221:   getstatic Field JB D Ljava/util/HashMap;
L224:   ldc "sv"
L226:   iconst_0
L227:   iconst_1
L228:   dup
L229:   pop2
L230:   invokestatic Method java/lang/Integer valueOf (I)Ljava/lang/Integer;
L233:   invokevirtual Method java/util/HashMap put [_163]
L236:   pop
L237:   getstatic Field JB D Ljava/util/HashMap;
L240:   ldc "sv"
L242:   invokevirtual Method java/util/HashMap get (Ljava/lang/Object;)Ljava/lang/Object;
L245:   checkcast java/lang/Integer
L248:   invokevirtual Method java/lang/Integer intValue ()I
L251:   tableswitch 0
            L276
            L563
            L580
            default : L583
L276:   invokestatic Method Pc values ()[LPc;
L279:   iconst_0
L280:   ifne L560
L283:   dup
L284:   astore_3
L285:   arraylength
L286:   istore 4
L288:   iconst_0
L289:   iconst_1
L290:   dup
L291:   pop2
L292:   dup
L293:   istore 5
L295:   iload 4
L297:   if_icmpge L563
L300:   aload_3
L301:   iload 5
L303:   aaload
L304:   astore 6
L306:   getstatic Field JB D Ljava/util/HashMap;
L309:   new java/lang/StringBuilder
L312:   dup
L313:   invokespecial Method java/lang/StringBuilder <init> ()V
L316:   iconst_0
L317:   aload 6
L319:   getfield Field Pc field370 Ljava/lang/String;
L322:   invokevirtual Method java/lang/StringBuilder insert (ILjava/lang/String;)Ljava/lang/StringBuilder;
L325:   ldc_w "h"
L328:   invokevirtual Method java/lang/StringBuilder append (Ljava/lang/String;)Ljava/lang/StringBuilder;
L331:   invokevirtual Method java/lang/StringBuilder toString ()Ljava/lang/String;
L334:   invokevirtual Method java/util/HashMap containsKey (Ljava/lang/Object;)Z
L337:   ifeq L429
L340:   getstatic Field JB D Ljava/util/HashMap;
L343:   new java/lang/StringBuilder
L346:   dup
L347:   invokespecial Method java/lang/StringBuilder <init> ()V
L350:   iconst_0
L351:   aload 6
L353:   getfield Field Pc field370 Ljava/lang/String;
L356:   invokevirtual Method java/lang/StringBuilder insert (ILjava/lang/String;)Ljava/lang/StringBuilder;
L359:   ldc_w "h"
L362:   invokevirtual Method java/lang/StringBuilder append (Ljava/lang/String;)Ljava/lang/StringBuilder;
L365:   invokevirtual Method java/lang/StringBuilder toString ()Ljava/lang/String;
L368:   iconst_2
L369:   iconst_1
L370:   dup
L371:   pop2
L372:   getstatic Field JB D Ljava/util/HashMap;
L375:   new java/lang/StringBuilder
L378:   dup
L379:   invokespecial Method java/lang/StringBuilder <init> ()V
L382:   iconst_0
L383:   aload 6
L385:   getfield Field Pc field370 Ljava/lang/String;
L388:   invokevirtual Method java/lang/StringBuilder insert (ILjava/lang/String;)Ljava/lang/StringBuilder;
L391:   ldc_w "h"
L394:   invokevirtual Method java/lang/StringBuilder append (Ljava/lang/String;)Ljava/lang/StringBuilder;
L397:   invokevirtual Method java/lang/StringBuilder toString ()Ljava/lang/String;
L400:   invokevirtual Method java/util/HashMap get (Ljava/lang/Object;)Ljava/lang/Object;
L403:   checkcast java/lang/Integer
L406:   invokevirtual Method java/lang/Integer intValue ()I
L409:   imul
L410:   iconst_0
L411:   iconst_1
L412:   dup
L413:   pop2
L414:   bipush 19
L416:   iconst_1
L417:   dup
L418:   pop2
L419:   invokestatic Method OC method993 (III)I
L422:   invokestatic Method java/lang/Integer valueOf (I)Ljava/lang/Integer;
L425:   invokevirtual Method java/util/HashMap put [_163]
L428:   pop
L429:   getstatic Field JB D Ljava/util/HashMap;
L432:   new java/lang/StringBuilder
L435:   dup
L436:   invokespecial Method java/lang/StringBuilder <init> ()V
L439:   iconst_0
L440:   aload 6
L442:   getfield Field Pc field370 Ljava/lang/String;
L445:   invokevirtual Method java/lang/StringBuilder insert (ILjava/lang/String;)Ljava/lang/StringBuilder;
L448:   ldc_w "i"
L451:   invokevirtual Method java/lang/StringBuilder append (Ljava/lang/String;)Ljava/lang/StringBuilder;
L454:   invokevirtual Method java/lang/StringBuilder toString ()Ljava/lang/String;
L457:   invokevirtual Method java/util/HashMap containsKey (Ljava/lang/Object;)Z
L460:   ifeq L552
L463:   getstatic Field JB D Ljava/util/HashMap;
L466:   new java/lang/StringBuilder
L469:   dup
L470:   invokespecial Method java/lang/StringBuilder <init> ()V
L473:   iconst_0
L474:   aload 6
L476:   getfield Field Pc field370 Ljava/lang/String;
L479:   invokevirtual Method java/lang/StringBuilder insert (ILjava/lang/String;)Ljava/lang/StringBuilder;
L482:   ldc_w "i"
L485:   invokevirtual Method java/lang/StringBuilder append (Ljava/lang/String;)Ljava/lang/StringBuilder;
L488:   invokevirtual Method java/lang/StringBuilder toString ()Ljava/lang/String;
L491:   iconst_2
L492:   iconst_1
L493:   dup
L494:   pop2
L495:   getstatic Field JB D Ljava/util/HashMap;
L498:   new java/lang/StringBuilder
L501:   dup
L502:   invokespecial Method java/lang/StringBuilder <init> ()V
L505:   iconst_0
L506:   aload 6
L508:   getfield Field Pc field370 Ljava/lang/String;
L511:   invokevirtual Method java/lang/StringBuilder insert (ILjava/lang/String;)Ljava/lang/StringBuilder;
L514:   ldc_w "i"
L517:   invokevirtual Method java/lang/StringBuilder append (Ljava/lang/String;)Ljava/lang/StringBuilder;
L520:   invokevirtual Method java/lang/StringBuilder toString ()Ljava/lang/String;
L523:   invokevirtual Method java/util/HashMap get (Ljava/lang/Object;)Ljava/lang/Object;
L526:   checkcast java/lang/Integer
L529:   invokevirtual Method java/lang/Integer intValue ()I
L532:   imul
L533:   iconst_0
L534:   iconst_1
L535:   dup
L536:   pop2
L537:   bipush 20
L539:   iconst_1
L540:   dup
L541:   pop2
L542:   invokestatic Method OC method993 (III)I
L545:   invokestatic Method java/lang/Integer valueOf (I)Ljava/lang/Integer;
L548:   invokevirtual Method java/util/HashMap put [_163]
L551:   pop
L552:   iinc 5 1
L555:   iload 5
L557:   goto L295
L560:   goto L279
L563:   getstatic Field JB D Ljava/util/HashMap;
L566:   ldc_w "dc"
L569:   iconst_0
L570:   iconst_1
L571:   dup
L572:   pop2
L573:   invokestatic Method java/lang/Integer valueOf (I)Ljava/lang/Integer;
L576:   invokevirtual Method java/util/HashMap put [_163]
L579:   pop
L580:   goto L610
L583:   ldc_w "Cultris II"
L586:   ldc_w "Running older and newer versions on the same system is not supported."
L589:   invokestatic Method org/lwjgl/Sys method1890 (Ljava/lang/String;Ljava/lang/String;)V
L592:   iconst_0
L593:   iconst_1
L594:   dup
L595:   pop2
L596:   invokestatic Method java/lang/System exit (I)V
L599:   goto L610
L602:   astore_0
L603:   aload_0
L604:   invokevirtual Method java/lang/Exception printStackTrace ()V
L607:   invokestatic Method JB method821 ()V
L610:   iconst_1
L611:   dup
L612:   dup
L613:   pop2
L614:   istore_0
L615:   ldc "a"
L617:   invokestatic Method JB method822 (Ljava/lang/String;)Ljava/lang/String;
L620:   invokestatic Method QD method626 (Ljava/lang/String;)F
L623:   ldc_w 7.7e0f
L626:   fcmpl
L627:   ifle L635
L630:   iconst_0
L631:   iconst_1
L632:   dup
L633:   pop2
L634:   istore_0
L635:   ldc_w "w"
L638:   invokestatic Method JB method831 (Ljava/lang/String;)I
L641:   invokestatic Method GF method791 (I)Z
L644:   ifne L663
L647:   ldc_w "w"
L650:   new Qb
L653:   dup
L654:   invokespecial Method Qb <init> ()V
L657:   invokestatic Method GF method790 (Leb;)I
L660:   invokestatic Method JB method827 (Ljava/lang/String;I)V
L663:   ldc_w "rm"
L666:   invokestatic Method JB method831 (Ljava/lang/String;)I
L669:   invokestatic Method GF method791 (I)Z
L672:   ifne L691
L675:   ldc_w "rm"
L678:   new Qb
L681:   dup
L682:   invokespecial Method Qb <init> ()V
L685:   invokestatic Method GF method790 (Leb;)I
L688:   invokestatic Method JB method827 (Ljava/lang/String;I)V
L691:   ldc "uuid"
L693:   invokestatic Method JB method822 (Ljava/lang/String;)Ljava/lang/String;
L696:   invokevirtual Method java/lang/String length ()I
L699:   bipush 36
L701:   iconst_1
L702:   dup
L703:   pop2
L704:   if_icmpeq L712
L707:   iconst_0
L708:   iconst_1
L709:   dup
L710:   pop2
L711:   istore_0
L712:   invokestatic Method Pc values ()[LPc;
L715:   dup
L716:   astore_1
L717:   arraylength
L718:   istore_2
L719:   iconst_0
L720:   iconst_1
L721:   dup
L722:   pop2
L723:   dup
L724:   istore_3
L725:   iload_2
L726:   if_icmpge L885
L729:   aload_1
L730:   iload_3
L731:   aaload
L732:   astore 4
L734:   new java/lang/StringBuilder
L737:   dup
L738:   invokespecial Method java/lang/StringBuilder <init> ()V
L741:   iconst_0
L742:   aload 4
L744:   getfield Field Pc field370 Ljava/lang/String;
L747:   invokevirtual Method java/lang/StringBuilder insert (ILjava/lang/String;)Ljava/lang/StringBuilder;
L750:   ldc_w "h"
L753:   invokevirtual Method java/lang/StringBuilder append (Ljava/lang/String;)Ljava/lang/StringBuilder;
L756:   invokevirtual Method java/lang/StringBuilder toString ()Ljava/lang/String;
L759:   invokestatic Method JB method831 (Ljava/lang/String;)I
L762:   iflt L801
L765:   new java/lang/StringBuilder
L768:   dup
L769:   invokespecial Method java/lang/StringBuilder <init> ()V
L772:   iconst_0
L773:   aload 4
L775:   getfield Field Pc field370 Ljava/lang/String;
L778:   invokevirtual Method java/lang/StringBuilder insert (ILjava/lang/String;)Ljava/lang/StringBuilder;
L781:   ldc_w "h"
L784:   invokevirtual Method java/lang/StringBuilder append (Ljava/lang/String;)Ljava/lang/StringBuilder;
L787:   invokevirtual Method java/lang/StringBuilder toString ()Ljava/lang/String;
L790:   invokestatic Method JB method831 (Ljava/lang/String;)I
L793:   bipush 19
L795:   iconst_1
L796:   dup
L797:   pop2
L798:   if_icmple L806
L801:   iconst_0
L802:   iconst_1
L803:   dup
L804:   pop2
L805:   istore_0
L806:   new java/lang/StringBuilder
L809:   dup
L810:   invokespecial Method java/lang/StringBuilder <init> ()V
L813:   iconst_0
L814:   aload 4
L816:   getfield Field Pc field370 Ljava/lang/String;
L819:   invokevirtual Method java/lang/StringBuilder insert (ILjava/lang/String;)Ljava/lang/StringBuilder;
L822:   ldc_w "i"
L825:   invokevirtual Method java/lang/StringBuilder append (Ljava/lang/String;)Ljava/lang/StringBuilder;
L828:   invokevirtual Method java/lang/StringBuilder toString ()Ljava/lang/String;
L831:   invokestatic Method JB method831 (Ljava/lang/String;)I
L834:   iflt L873
L837:   new java/lang/StringBuilder
L840:   dup
L841:   invokespecial Method java/lang/StringBuilder <init> ()V
L844:   iconst_0
L845:   aload 4
L847:   getfield Field Pc field370 Ljava/lang/String;
L850:   invokevirtual Method java/lang/StringBuilder insert (ILjava/lang/String;)Ljava/lang/StringBuilder;
L853:   ldc_w "i"
L856:   invokevirtual Method java/lang/StringBuilder append (Ljava/lang/String;)Ljava/lang/StringBuilder;
L859:   invokevirtual Method java/lang/StringBuilder toString ()Ljava/lang/String;
L862:   invokestatic Method JB method831 (Ljava/lang/String;)I
L865:   bipush 20
L867:   iconst_1
L868:   dup
L869:   pop2
L870:   if_icmple L878
L873:   iconst_0
L874:   iconst_1
L875:   dup
L876:   pop2
L877:   istore_0
L878:   iinc 3 1
L881:   iload_3
L882:   goto L725
L885:   iload_0
L886:   ifne L892
L889:   invokestatic Method JB method821 ()V
L892:   return
L893:   
        .attribute StackMap b'\x00\x1D\x00\x22\x00\x00\x00\x01\x07\x00\x78\x00\x23\x00\x01\x07\x00\xCF\x00\x00\x00\x29\x00\x02\x07\x00\xCF\x01\x00\x01\x01\x00\x75\x00\x00\x00\x01\x07\x00\x78\x00\x76\x00\x02\x07\x00\xCF\x01\x00\x00\x00\xBA\x00\x03\x07\x00\xCF\x07\x00\x7E\x07\x01\x78\x00\x00\x00\xED\x00\x03\x07\x00\xCF\x07\x00\x7E\x07\x01\x78\x00\x00\x01\x14\x00\x03\x07\x00\xCF\x07\x00\x7E\x07\x01\x78\x00\x00\x01\x17\x00\x03\x07\x00\xCF\x07\x00\x7E\x07\x01\x78\x00\x01\x07\x01\xAC\x01\x27\x00\x06\x07\x00\xCF\x07\x00\x7E\x07\x01\x78\x07\x01\xAC\x01\x01\x00\x01\x01\x01\xAD\x00\x07\x07\x00\xCF\x07\x00\x7E\x07\x01\x78\x07\x01\xAC\x01\x01\x07\x00\x06\x00\x00\x02\x28\x00\x07\x07\x00\xCF\x07\x00\x7E\x07\x01\x78\x07\x01\xAC\x01\x01\x07\x00\x06\x00\x00\x02\x30\x00\x03\x07\x00\xCF\x07\x00\x7E\x07\x01\x78\x00\x01\x07\x01\xAC\x02\x33\x00\x03\x07\x00\xCF\x07\x00\x7E\x07\x01\x78\x00\x00\x02\x44\x00\x03\x07\x00\xCF\x07\x00\x7E\x07\x01\x78\x00\x00\x02\x47\x00\x03\x07\x00\xCF\x07\x00\x7E\x07\x01\x78\x00\x00\x02\x5A\x00\x00\x00\x01\x07\x00\x7A\x02\x62\x00\x01\x07\x00\x04\x00\x00\x02\x7B\x00\x01\x01\x00\x00\x02\x97\x00\x01\x01\x00\x00\x02\xB3\x00\x01\x01\x00\x00\x02\xC8\x00\x01\x01\x00\x00\x02\xD5\x00\x04\x01\x07\x01\xAC\x01\x01\x00\x01\x01\x03\x21\x00\x05\x01\x07\x01\xAC\x01\x01\x07\x00\x06\x00\x00\x03\x26\x00\x05\x01\x07\x01\xAC\x01\x01\x07\x00\x06\x00\x00\x03\x69\x00\x05\x01\x07\x01\xAC\x01\x01\x07\x00\x06\x00\x00\x03\x6E\x00\x05\x01\x07\x01\xAC\x01\x01\x07\x00\x06\x00\x00\x03\x75\x00\x04\x01\x07\x01\xAC\x01\x01\x00\x00\x03\x7C\x00\x04\x01\x07\x01\xAC\x01\x01\x00\x00'
    .end code
.end method

.method public static method820 : (LPc;)F
    .code stack 3 locals 2
L0:     new java/lang/StringBuilder
L3:     dup
L4:     invokespecial Method java/lang/StringBuilder <init> ()V
L7:     iconst_0
L8:     aload_0
L9:     getfield Field Pc field370 Ljava/lang/String;
L12:    invokevirtual Method java/lang/StringBuilder insert (ILjava/lang/String;)Ljava/lang/StringBuilder;
L15:    ldc_w "h"
L18:    invokevirtual Method java/lang/StringBuilder append (Ljava/lang/String;)Ljava/lang/StringBuilder;
L21:    invokevirtual Method java/lang/StringBuilder toString ()Ljava/lang/String;
L24:    invokestatic Method JB method831 (Ljava/lang/String;)I
L27:    i2f
L28:    fconst_2
L29:    fdiv
L30:    fstore_1
L31:    ldc_w 3.9444445e-3f
L34:    fload_1
L35:    fmul
L36:    fload_1
L37:    fmul
L38:    ldc_w -7.7222222e-3f
L41:    fload_1
L42:    fmul
L43:    fadd
L44:    ldc_w 5e-2f
L47:    fadd
L48:    freturn
L49:    
    .end code
.end method

.method private static method821 : ()V
    .code stack 3 locals 0
L0:     getstatic Field JB D Ljava/util/HashMap;
L3:     invokevirtual Method java/util/HashMap clear ()V
L6:     getstatic Field JB field1915 Ljava/util/HashMap;
L9:     invokevirtual Method java/util/HashMap clear ()V
L12:    getstatic Field JB field1915 Ljava/util/HashMap;
L15:    ldc "uuid"
L17:    invokestatic Method java/util/UUID randomUUID ()Ljava/util/UUID;
L20:    invokevirtual Method java/util/UUID toString ()Ljava/lang/String;
L23:    invokevirtual Method java/util/HashMap put [_163]
L26:    pop
L27:    return
L28:    
    .end code
.end method

.method public static method822 : (Ljava/lang/String;)Ljava/lang/String;
    .code stack 2 locals 2
L0:     getstatic Field JB field1915 Ljava/util/HashMap;
L3:     aload_0
L4:     invokevirtual Method java/util/HashMap get (Ljava/lang/Object;)Ljava/lang/Object;
L7:     checkcast java/lang/String
L10:    dup
L11:    astore_1
L12:    ifnonnull L27
L15:    getstatic Field JB field1919 Ljava/util/HashMap;
L18:    aload_0
L19:    invokevirtual Method java/util/HashMap get (Ljava/lang/Object;)Ljava/lang/Object;
L22:    checkcast java/lang/String
L25:    areturn
L26:    athrow
L27:    aload_1
L28:    areturn
L29:    
        .attribute StackMap b'\x00\x02\x00\x1A\x00\x00\x00\x01\x07\x00\x78\x00\x1B\x00\x02\x07\x00\x72\x07\x00\x72\x00\x00'
    .end code
.end method

.method public static method823 : (Ljava/lang/String;)V
    .code stack 3 locals 1
L0:     getstatic Field JB D Ljava/util/HashMap;
L3:     aload_0
L4:     invokevirtual Method java/util/HashMap remove (Ljava/lang/Object;)Ljava/lang/Object;
L7:     getstatic Field JB field1915 Ljava/util/HashMap;
L10:    aload_0
L11:    invokevirtual Method java/util/HashMap remove (Ljava/lang/Object;)Ljava/lang/Object;
L14:    pop2
L15:    return
L16:    
    .end code
.end method

.method public static method824 : (Ljava/lang/String;I)V
    .code stack 3 locals 2
L0:     aload_0
L1:     dup
L2:     invokestatic Method JB method831 (Ljava/lang/String;)I
L5:     iload_1
L6:     iadd
L7:     invokestatic Method JB method827 (Ljava/lang/String;I)V
L10:    return
L11:    
    .end code
.end method

.method public static method825 : ()F
    .code stack 2 locals 0
L0:     ldc_w "q"
L3:     invokestatic Method JB method831 (Ljava/lang/String;)I
L6:     ldc_w "q"
L9:     invokestatic Method JB method831 (Ljava/lang/String;)I
L12:    imul
L13:    i2f
L14:    ldc_w 8.1e1f
L17:    fdiv
L18:    freturn
L19:    
    .end code
.end method

.method public static method826 : (Ljava/lang/String;Ljava/lang/String;)V
    .code stack 3 locals 2
L0:     getstatic Field JB field1919 Ljava/util/HashMap;
L3:     aload_0
L4:     invokevirtual Method java/util/HashMap containsKey (Ljava/lang/Object;)Z
L7:     ifne L18
L10:    new java/lang/RuntimeException
L13:    dup
L14:    invokespecial Method java/lang/RuntimeException <init> ()V
L17:    athrow
L18:    getstatic Field JB field1915 Ljava/util/HashMap;
L21:    aload_0
L22:    aload_1
L23:    invokevirtual Method java/util/HashMap put [_163]
L26:    pop
L27:    return
L28:    
        .attribute StackMap b'\x00\x01\x00\x12\x00\x02\x07\x00\x72\x07\x00\x72\x00\x00'
    .end code
.end method

.method public static method827 : (Ljava/lang/String;I)V
    .code stack 3 locals 2
L0:     getstatic Field JB B Ljava/util/HashMap;
L3:     aload_0
L4:     invokevirtual Method java/util/HashMap containsKey (Ljava/lang/Object;)Z
L7:     ifne L18
L10:    new java/lang/RuntimeException
L13:    dup
L14:    invokespecial Method java/lang/RuntimeException <init> ()V
L17:    athrow
L18:    getstatic Field JB D Ljava/util/HashMap;
L21:    aload_0
L22:    iload_1
L23:    invokestatic Method java/lang/Integer valueOf (I)Ljava/lang/Integer;
L26:    invokevirtual Method java/util/HashMap put [_163]
L29:    pop
L30:    return
L31:    
        .attribute StackMap b'\x00\x01\x00\x12\x00\x02\x07\x00\x72\x01\x00\x00'
    .end code
.end method

.method public static method828 : (LPc;)F
    .code stack 4 locals 2
L0:     new java/lang/StringBuilder
L3:     dup
L4:     invokespecial Method java/lang/StringBuilder <init> ()V
L7:     iconst_0
L8:     aload_0
L9:     getfield Field Pc field370 Ljava/lang/String;
L12:    invokevirtual Method java/lang/StringBuilder insert (ILjava/lang/String;)Ljava/lang/StringBuilder;
L15:    ldc_w "i"
L18:    invokevirtual Method java/lang/StringBuilder append (Ljava/lang/String;)Ljava/lang/StringBuilder;
L21:    invokevirtual Method java/lang/StringBuilder toString ()Ljava/lang/String;
L24:    invokestatic Method JB method831 (Ljava/lang/String;)I
L27:    bipush 20
L29:    iconst_1
L30:    dup
L31:    pop2
L32:    if_icmpne L40
L35:    ldc_w 1e-6f
L38:    freturn
L39:    athrow
L40:    new java/lang/StringBuilder
L43:    dup
L44:    invokespecial Method java/lang/StringBuilder <init> ()V
L47:    iconst_0
L48:    aload_0
L49:    getfield Field Pc field370 Ljava/lang/String;
L52:    invokevirtual Method java/lang/StringBuilder insert (ILjava/lang/String;)Ljava/lang/StringBuilder;
L55:    ldc_w "i"
L58:    invokevirtual Method java/lang/StringBuilder append (Ljava/lang/String;)Ljava/lang/StringBuilder;
L61:    invokevirtual Method java/lang/StringBuilder toString ()Ljava/lang/String;
L64:    invokestatic Method JB method831 (Ljava/lang/String;)I
L67:    i2f
L68:    fconst_2
L69:    fdiv
L70:    fstore_1
L71:    ldc_w 5e-4f
L74:    fload_1
L75:    fmul
L76:    fload_1
L77:    fmul
L78:    ldc_w -1.45e-2f
L81:    fload_1
L82:    fmul
L83:    fadd
L84:    ldc_w 1e-1f
L87:    fadd
L88:    freturn
L89:    
        .attribute StackMap b'\x00\x02\x00\x27\x00\x00\x00\x01\x07\x00\x78\x00\x28\x00\x01\x07\x00\x06\x00\x00'
    .end code
.end method

.method public static method829 : ()F
    .code stack 2 locals 0
L0:     ldc_w "s"
L3:     invokestatic Method JB method831 (Ljava/lang/String;)I
L6:     ldc_w "s"
L9:     invokestatic Method JB method831 (Ljava/lang/String;)I
L12:    imul
L13:    i2f
L14:    ldc_w 8.1e1f
L17:    fdiv
L18:    freturn
L19:    
    .end code
.end method

.method public static method830 : ()V
    .code stack 1 locals 0
L0:     ldc_w "k"
L3:     invokestatic Method JB method823 (Ljava/lang/String;)V
L6:     ldc_w "l"
L9:     invokestatic Method JB method823 (Ljava/lang/String;)V
L12:    ldc_w "m"
L15:    invokestatic Method JB method823 (Ljava/lang/String;)V
L18:    return
L19:    
    .end code
.end method

.method public static method831 : (Ljava/lang/String;)I
    .code stack 2 locals 2
        .catch java/lang/Exception from L0 to L23 using L40
L0:     getstatic Field JB D Ljava/util/HashMap;
L3:     aload_0
L4:     invokevirtual Method java/util/HashMap containsKey (Ljava/lang/Object;)Z
L7:     ifne L25
L10:    getstatic Field JB B Ljava/util/HashMap;
L13:    aload_0
L14:    invokevirtual Method java/util/HashMap get (Ljava/lang/Object;)Ljava/lang/Object;
L17:    checkcast java/lang/Integer
L20:    invokevirtual Method java/lang/Integer intValue ()I
L23:    ireturn
L24:    athrow
        .catch java/lang/Exception from L25 to L38 using L40
L25:    getstatic Field JB D Ljava/util/HashMap;
L28:    aload_0
L29:    invokevirtual Method java/util/HashMap get (Ljava/lang/Object;)Ljava/lang/Object;
L32:    checkcast java/lang/Integer
L35:    invokevirtual Method java/lang/Integer intValue ()I
L38:    ireturn
L39:    athrow
L40:    astore_1
L41:    aload_1
L42:    invokevirtual Method java/lang/Exception printStackTrace ()V
L45:    getstatic Field JB B Ljava/util/HashMap;
L48:    aload_0
L49:    invokevirtual Method java/util/HashMap get (Ljava/lang/Object;)Ljava/lang/Object;
L52:    checkcast java/lang/Integer
L55:    invokevirtual Method java/lang/Integer intValue ()I
L58:    ireturn
L59:    
        .attribute StackMap b'\x00\x04\x00\x18\x00\x00\x00\x01\x07\x00\x78\x00\x19\x00\x01\x07\x00\x72\x00\x00\x00\x27\x00\x00\x00\x01\x07\x00\x78\x00\x28\x00\x01\x07\x00\x72\x00\x01\x07\x00\x7A'
    .end code
.end method

.method public static method832 : (Ljava/lang/String;Ljava/lang/String;)Z
    .code stack 4 locals 2
L0:     aload_0
L1:     invokestatic Method JB method822 (Ljava/lang/String;)Ljava/lang/String;
L4:     new java/lang/StringBuilder
L7:     dup
L8:     invokespecial Method java/lang/StringBuilder <init> ()V
L11:    iconst_0
L12:    ldc_w "|"
L15:    invokevirtual Method java/lang/StringBuilder insert (ILjava/lang/String;)Ljava/lang/StringBuilder;
L18:    aload_1
L19:    invokevirtual Method java/lang/StringBuilder append (Ljava/lang/String;)Ljava/lang/StringBuilder;
L22:    ldc_w "|"
L25:    invokevirtual Method java/lang/StringBuilder append (Ljava/lang/String;)Ljava/lang/StringBuilder;
L28:    invokevirtual Method java/lang/StringBuilder toString ()Ljava/lang/String;
L31:    invokevirtual Method java/lang/String contains (Ljava/lang/CharSequence;)Z
L34:    ireturn
L35:    
    .end code
.end method

.method public static method833 : (Ljava/lang/String;Ljava/lang/String;)V
    .code stack 5 locals 2
L0:     aload_0
L1:     dup
L2:     invokestatic Method JB method822 (Ljava/lang/String;)Ljava/lang/String;
L5:     new java/lang/StringBuilder
L8:     dup
L9:     invokespecial Method java/lang/StringBuilder <init> ()V
L12:    iconst_0
L13:    aload_1
L14:    invokevirtual Method java/lang/StringBuilder insert (ILjava/lang/String;)Ljava/lang/StringBuilder;
L17:    ldc_w "|"
L20:    invokevirtual Method java/lang/StringBuilder append (Ljava/lang/String;)Ljava/lang/StringBuilder;
L23:    invokevirtual Method java/lang/StringBuilder toString ()Ljava/lang/String;
L26:    ldc ""
L28:    invokevirtual Method java/lang/String replace (Ljava/lang/CharSequence;Ljava/lang/CharSequence;)Ljava/lang/String;
L31:    invokestatic Method JB method826 (Ljava/lang/String;Ljava/lang/String;)V
L34:    return
L35:    
    .end code
.end method

.method public static <clinit> : ()V
    .code stack 39 locals 4
L0:     ldc_w "b"
L3:     putstatic Field JB new Ljava/lang/String;
L6:     ldc "c"
L8:     putstatic Field JB field1882 Ljava/lang/String;
L11:    ldc_w "d"
L14:    putstatic Field JB field1895 Ljava/lang/String;
L17:    ldc_w "e"
L20:    putstatic Field JB field1921 Ljava/lang/String;
L23:    ldc_w "f"
L26:    putstatic Field JB field1922 Ljava/lang/String;
L29:    ldc_w "180"
L32:    putstatic Field JB field1903 Ljava/lang/String;
L35:    ldc_w "g"
L38:    putstatic Field JB field1893 Ljava/lang/String;
L41:    ldc "a"
L43:    putstatic Field JB field1886 Ljava/lang/String;
L46:    ldc_w "h"
L49:    putstatic Field JB false Ljava/lang/String;
L52:    ldc_w "i"
L55:    putstatic Field JB field1901 Ljava/lang/String;
L58:    ldc_w "lum"
L61:    putstatic Field JB field1916 Ljava/lang/String;
L64:    ldc_w "uda"
L67:    putstatic Field JB field1914 Ljava/lang/String;
L70:    ldc_w "udf"
L73:    putstatic Field JB this Ljava/lang/String;
L76:    ldc_w "j"
L79:    putstatic Field JB I Ljava/lang/String;
L82:    ldc_w "mc"
L85:    putstatic Field JB J Ljava/lang/String;
L88:    ldc_w "ua"
L91:    putstatic Field JB E Ljava/lang/String;
L94:    ldc_w "sj"
L97:    putstatic Field JB K Ljava/lang/String;
L100:   ldc_w "sl"
L103:   putstatic Field JB field1909 Ljava/lang/String;
L106:   ldc_w "st"
L109:   putstatic Field JB field1905 Ljava/lang/String;
L112:   ldc_w "si"
L115:   putstatic Field JB field1920 Ljava/lang/String;
L118:   ldc_w "ss"
L121:   putstatic Field JB m Ljava/lang/String;
L124:   ldc_w "sz"
L127:   putstatic Field JB field1885 Ljava/lang/String;
L130:   ldc_w "li"
L133:   putstatic Field JB field1913 Ljava/lang/String;
L136:   ldc_w "pw"
L139:   putstatic Field JB field1897 Ljava/lang/String;
L142:   ldc_w "pag"
L145:   putstatic Field JB field1918 Ljava/lang/String;
L148:   ldc_w "cl"
L151:   putstatic Field JB field1896 Ljava/lang/String;
L154:   ldc_w "cj"
L157:   putstatic Field JB field1884 Ljava/lang/String;
L160:   ldc_w "ct"
L163:   putstatic Field JB field1889 Ljava/lang/String;
L166:   ldc_w "ci"
L169:   putstatic Field JB return Ljava/lang/String;
L172:   ldc_w "cz"
L175:   putstatic Field JB field1892 Ljava/lang/String;
L178:   ldc_w "cs"
L181:   putstatic Field JB C Ljava/lang/String;
L184:   ldc_w "co"
L187:   putstatic Field JB b Ljava/lang/String;
L190:   ldc_w "k"
L193:   putstatic Field JB field1888 Ljava/lang/String;
L196:   ldc_w "l"
L199:   putstatic Field JB throw Ljava/lang/String;
L202:   ldc_w "m"
L205:   putstatic Field JB field1917 Ljava/lang/String;
L208:   ldc_w "det_sw"
L211:   putstatic Field JB try Ljava/lang/String;
L214:   ldc_w "q"
L217:   putstatic Field JB field1880 Ljava/lang/String;
L220:   ldc_w "r"
L223:   putstatic Field JB field1904 Ljava/lang/String;
L226:   ldc_w "s"
L229:   putstatic Field JB field1891 Ljava/lang/String;
L232:   ldc_w "t"
L235:   putstatic Field JB field1881 Ljava/lang/String;
L238:   ldc_w "u"
L241:   putstatic Field JB field1912 Ljava/lang/String;
L244:   ldc_w "v"
L247:   putstatic Field JB field1911 Ljava/lang/String;
L250:   ldc_w "w"
L253:   putstatic Field JB package Ljava/lang/String;
L256:   ldc_w "twpm"
L259:   putstatic Field JB c Ljava/lang/String;
L262:   ldc_w "rm"
L265:   putstatic Field JB field1902 Ljava/lang/String;
L268:   ldc_w "rmte"
L271:   putstatic Field JB field1883 Ljava/lang/String;
L274:   ldc_w "mphc"
L277:   putstatic Field JB field1907 Ljava/lang/String;
L280:   ldc_w "rmrl"
L283:   putstatic Field JB field1900 Ljava/lang/String;
L286:   ldc_w "rmsl"
L289:   putstatic Field JB G Ljava/lang/String;
L292:   ldc "uuid"
L294:   putstatic Field JB switch Ljava/lang/String;
L297:   ldc_w "dls"
L300:   putstatic Field JB j Ljava/lang/String;
L303:   ldc_w "pts"
L306:   putstatic Field JB f Ljava/lang/String;
L309:   ldc_w "ws"
L312:   putstatic Field JB field1887 Ljava/lang/String;
L315:   ldc_w "rs"
L318:   putstatic Field JB field1908 Ljava/lang/String;
L321:   ldc_w "chg|t|"
L324:   putstatic Field JB field1898 Ljava/lang/String;
L327:   ldc_w "chg|w|"
L330:   putstatic Field JB field1899 Ljava/lang/String;
L333:   ldc_w "chg|s|"
L336:   putstatic Field JB field1890 Ljava/lang/String;
L339:   ldc_w "load_successful"
L342:   putstatic Field JB field1910 Ljava/lang/String;
L345:   ldc_w "lmotd"
L348:   putstatic Field JB while Ljava/lang/String;
L351:   ldc_w "upftr"
L354:   putstatic Field JB i Ljava/lang/String;
L357:   ldc "sv"
L359:   putstatic Field JB l Ljava/lang/String;
L362:   ldc_w "dc"
L365:   putstatic Field JB true Ljava/lang/String;
L368:   invokestatic Method java/util/prefs/Preferences userRoot ()Ljava/util/prefs/Preferences;
L371:   ldc_w "/gewaltig/cultris"
L374:   invokevirtual Method java/util/prefs/Preferences node (Ljava/lang/String;)Ljava/util/prefs/Preferences;
L377:   putstatic Field JB field1906 Ljava/util/prefs/Preferences;
L380:   new java/util/HashMap
L383:   dup
L384:   invokespecial Method java/util/HashMap <init> ()V
L387:   putstatic Field JB D Ljava/util/HashMap;
L390:   new java/util/HashMap
L393:   dup
L394:   invokespecial Method java/util/HashMap <init> ()V
L397:   putstatic Field JB field1915 Ljava/util/HashMap;
L400:   new java/util/HashMap
L403:   dup
L404:   invokespecial Method java/util/HashMap <init> ()V
L407:   putstatic Field JB B Ljava/util/HashMap;
L410:   new java/util/HashMap
L413:   dup
L414:   invokespecial Method java/util/HashMap <init> ()V
L417:   putstatic Field JB field1919 Ljava/util/HashMap;
        .catch java/lang/Exception from L420 to L538 using L542
L420:   ldc_w "DES"
L423:   invokestatic Method javax/crypto/SecretKeyFactory getInstance (Ljava/lang/String;)Ljavax/crypto/SecretKeyFactory;
L426:   new javax/crypto/spec/DESKeySpec
L429:   dup
L430:   bipush 8
L432:   iconst_1
L433:   dup
L434:   pop2
L435:   newarray byte
L437:   iconst_1
L438:   dup
L439:   pop2
L440:   dup
L441:   iconst_0
L442:   iconst_1
L443:   dup
L444:   pop2
L445:   bipush 87
L447:   iconst_1
L448:   dup
L449:   pop2
L450:   bastore
L451:   dup
L452:   iconst_1
L453:   dup
L454:   pop2
L455:   bipush 87
L457:   iconst_1
L458:   dup_x1
L459:   dup
L460:   pop2
L461:   bastore
L462:   dup
L463:   iconst_2
L464:   iconst_1
L465:   dup
L466:   pop2
L467:   bipush 26
L469:   iconst_1
L470:   dup
L471:   pop2
L472:   bastore
L473:   dup
L474:   iconst_3
L475:   iconst_1
L476:   dup
L477:   pop2
L478:   bipush -97
L480:   iconst_1
L481:   dup
L482:   pop2
L483:   bastore
L484:   dup
L485:   iconst_4
L486:   iconst_1
L487:   dup
L488:   pop2
L489:   bipush 7
L491:   iconst_1
L492:   dup
L493:   pop2
L494:   bastore
L495:   dup
L496:   iconst_5
L497:   iconst_1
L498:   dup
L499:   pop2
L500:   iconst_0
L501:   iconst_1
L502:   dup
L503:   pop2
L504:   bastore
L505:   dup
L506:   bipush 6
L508:   iconst_1
L509:   dup
L510:   pop2
L511:   bipush -57
L513:   iconst_1
L514:   dup
L515:   pop2
L516:   bastore
L517:   dup
L518:   bipush 7
L520:   iconst_1
L521:   dup
L522:   pop2
L523:   bipush -48
L525:   iconst_1
L526:   dup
L527:   pop2
L528:   bastore
L529:   invokespecial Method javax/crypto/spec/DESKeySpec <init> ([B)V
L532:   invokevirtual Method javax/crypto/SecretKeyFactory generateSecret (Ljava/security/spec/KeySpec;)Ljavax/crypto/SecretKey;
L535:   putstatic Field JB field1894 Ljavax/crypto/SecretKey;
L538:   goto L547
L541:   athrow
L542:   astore_0
L543:   aload_0
L544:   invokevirtual Method java/lang/Exception printStackTrace ()V
L547:   getstatic Field JB B Ljava/util/HashMap;
L550:   ldc "sv"
L552:   iconst_2
L553:   iconst_1
L554:   dup
L555:   pop2
L556:   invokestatic Method java/lang/Integer valueOf (I)Ljava/lang/Integer;
L559:   invokevirtual Method java/util/HashMap put [_163]
L562:   getstatic Field JB field1919 Ljava/util/HashMap;
L565:   ldc "uuid"
L567:   ldc ""
L569:   invokevirtual Method java/util/HashMap put [_163]
L572:   getstatic Field SE field2071 Ljava/util/Map;
L575:   invokeinterface InterfaceMethod java/util/Map keySet ()Ljava/util/Set; 1
L580:   invokeinterface InterfaceMethod java/util/Set iterator ()Ljava/util/Iterator; 1
L585:   astore_0
L586:   pop2
L587:   aload_0
L588:   invokeinterface InterfaceMethod java/util/Iterator hasNext ()Z 1
L593:   ifeq L715
L596:   aload_0
L597:   invokeinterface InterfaceMethod java/util/Iterator next ()Ljava/lang/Object; 1
L602:   checkcast java/lang/String
L605:   astore_1
L606:   getstatic Field JB B Ljava/util/HashMap;
L609:   new java/lang/StringBuilder
L612:   dup
L613:   invokespecial Method java/lang/StringBuilder <init> ()V
L616:   iconst_0
L617:   ldc_w "chg|t|"
L620:   invokevirtual Method java/lang/StringBuilder insert (ILjava/lang/String;)Ljava/lang/StringBuilder;
L623:   aload_1
L624:   invokevirtual Method java/lang/StringBuilder append (Ljava/lang/String;)Ljava/lang/StringBuilder;
L627:   invokevirtual Method java/lang/StringBuilder toString ()Ljava/lang/String;
L630:   iconst_0
L631:   iconst_1
L632:   dup
L633:   pop2
L634:   invokestatic Method java/lang/Integer valueOf (I)Ljava/lang/Integer;
L637:   invokevirtual Method java/util/HashMap put [_163]
L640:   getstatic Field JB B Ljava/util/HashMap;
L643:   new java/lang/StringBuilder
L646:   dup
L647:   invokespecial Method java/lang/StringBuilder <init> ()V
L650:   iconst_0
L651:   ldc_w "chg|w|"
L654:   invokevirtual Method java/lang/StringBuilder insert (ILjava/lang/String;)Ljava/lang/StringBuilder;
L657:   aload_1
L658:   invokevirtual Method java/lang/StringBuilder append (Ljava/lang/String;)Ljava/lang/StringBuilder;
L661:   invokevirtual Method java/lang/StringBuilder toString ()Ljava/lang/String;
L664:   iconst_0
L665:   iconst_1
L666:   dup
L667:   pop2
L668:   invokestatic Method java/lang/Integer valueOf (I)Ljava/lang/Integer;
L671:   invokevirtual Method java/util/HashMap put [_163]
L674:   getstatic Field JB B Ljava/util/HashMap;
L677:   new java/lang/StringBuilder
L680:   dup
L681:   invokespecial Method java/lang/StringBuilder <init> ()V
L684:   iconst_0
L685:   ldc_w "chg|s|"
L688:   invokevirtual Method java/lang/StringBuilder insert (ILjava/lang/String;)Ljava/lang/StringBuilder;
L691:   aload_1
L692:   invokevirtual Method java/lang/StringBuilder append (Ljava/lang/String;)Ljava/lang/StringBuilder;
L695:   invokevirtual Method java/lang/StringBuilder toString ()Ljava/lang/String;
L698:   iconst_0
L699:   iconst_1
L700:   dup
L701:   pop2
L702:   invokestatic Method java/lang/Integer valueOf (I)Ljava/lang/Integer;
L705:   invokevirtual Method java/util/HashMap put [_163]
L708:   pop
L709:   pop2
L710:   aload_0
L711:   goto L588
L714:   athrow
L715:   getstatic Field SE field2069 Ljava/util/Map;
L718:   invokeinterface InterfaceMethod java/util/Map keySet ()Ljava/util/Set; 1
L723:   invokeinterface InterfaceMethod java/util/Set iterator ()Ljava/util/Iterator; 1
L728:   dup
L729:   astore_0
L730:   invokeinterface InterfaceMethod java/util/Iterator hasNext ()Z 1
L735:   ifeq L856
L738:   aload_0
L739:   invokeinterface InterfaceMethod java/util/Iterator next ()Ljava/lang/Object; 1
L744:   checkcast java/lang/String
L747:   astore_1
L748:   getstatic Field JB B Ljava/util/HashMap;
L751:   new java/lang/StringBuilder
L754:   dup
L755:   invokespecial Method java/lang/StringBuilder <init> ()V
L758:   iconst_0
L759:   ldc_w "chg|t|"
L762:   invokevirtual Method java/lang/StringBuilder insert (ILjava/lang/String;)Ljava/lang/StringBuilder;
L765:   aload_1
L766:   invokevirtual Method java/lang/StringBuilder append (Ljava/lang/String;)Ljava/lang/StringBuilder;
L769:   invokevirtual Method java/lang/StringBuilder toString ()Ljava/lang/String;
L772:   iconst_0
L773:   iconst_1
L774:   dup
L775:   pop2
L776:   invokestatic Method java/lang/Integer valueOf (I)Ljava/lang/Integer;
L779:   invokevirtual Method java/util/HashMap put [_163]
L782:   getstatic Field JB B Ljava/util/HashMap;
L785:   new java/lang/StringBuilder
L788:   dup
L789:   invokespecial Method java/lang/StringBuilder <init> ()V
L792:   iconst_0
L793:   ldc_w "chg|w|"
L796:   invokevirtual Method java/lang/StringBuilder insert (ILjava/lang/String;)Ljava/lang/StringBuilder;
L799:   aload_1
L800:   invokevirtual Method java/lang/StringBuilder append (Ljava/lang/String;)Ljava/lang/StringBuilder;
L803:   invokevirtual Method java/lang/StringBuilder toString ()Ljava/lang/String;
L806:   iconst_0
L807:   iconst_1
L808:   dup
L809:   pop2
L810:   invokestatic Method java/lang/Integer valueOf (I)Ljava/lang/Integer;
L813:   invokevirtual Method java/util/HashMap put [_163]
L816:   getstatic Field JB B Ljava/util/HashMap;
L819:   new java/lang/StringBuilder
L822:   dup
L823:   invokespecial Method java/lang/StringBuilder <init> ()V
L826:   iconst_0
L827:   ldc_w "chg|s|"
L830:   invokevirtual Method java/lang/StringBuilder insert (ILjava/lang/String;)Ljava/lang/StringBuilder;
L833:   aload_1
L834:   invokevirtual Method java/lang/StringBuilder append (Ljava/lang/String;)Ljava/lang/StringBuilder;
L837:   invokevirtual Method java/lang/StringBuilder toString ()Ljava/lang/String;
L840:   iconst_0
L841:   iconst_1
L842:   dup
L843:   pop2
L844:   invokestatic Method java/lang/Integer valueOf (I)Ljava/lang/Integer;
L847:   invokevirtual Method java/util/HashMap put [_163]
L850:   pop
L851:   pop2
L852:   aload_0
L853:   goto L730
L856:   invokestatic Method org/lwjgl/LWJGLUtil getPlatform ()I
L859:   iconst_2
L860:   iconst_1
L861:   dup
L862:   pop2
L863:   if_icmpne L911
L866:   getstatic Field JB B Ljava/util/HashMap;
L869:   new java/lang/StringBuilder
L872:   dup
L873:   invokespecial Method java/lang/StringBuilder <init> ()V
L876:   iconst_0
L877:   getstatic Field Pc field373 LPc;
L880:   getfield Field Pc field370 Ljava/lang/String;
L883:   invokevirtual Method java/lang/StringBuilder insert (ILjava/lang/String;)Ljava/lang/StringBuilder;
L886:   ldc_w "b"
L889:   invokevirtual Method java/lang/StringBuilder append (Ljava/lang/String;)Ljava/lang/StringBuilder;
L892:   invokevirtual Method java/lang/StringBuilder toString ()Ljava/lang/String;
L895:   sipush 220
L898:   iconst_1
L899:   dup
L900:   pop2
L901:   invokestatic Method java/lang/Integer valueOf (I)Ljava/lang/Integer;
L904:   invokevirtual Method java/util/HashMap put [_163]
L907:   pop
L908:   goto L953
L911:   getstatic Field JB B Ljava/util/HashMap;
L914:   new java/lang/StringBuilder
L917:   dup
L918:   invokespecial Method java/lang/StringBuilder <init> ()V
L921:   iconst_0
L922:   getstatic Field Pc field373 LPc;
L925:   getfield Field Pc field370 Ljava/lang/String;
L928:   invokevirtual Method java/lang/StringBuilder insert (ILjava/lang/String;)Ljava/lang/StringBuilder;
L931:   ldc_w "b"
L934:   invokevirtual Method java/lang/StringBuilder append (Ljava/lang/String;)Ljava/lang/StringBuilder;
L937:   invokevirtual Method java/lang/StringBuilder toString ()Ljava/lang/String;
L940:   sipush 157
L943:   iconst_1
L944:   dup
L945:   pop2
L946:   invokestatic Method java/lang/Integer valueOf (I)Ljava/lang/Integer;
L949:   invokevirtual Method java/util/HashMap put [_163]
L952:   pop
L953:   getstatic Field JB B Ljava/util/HashMap;
L956:   new java/lang/StringBuilder
L959:   dup
L960:   invokespecial Method java/lang/StringBuilder <init> ()V
L963:   iconst_0
L964:   getstatic Field Pc field373 LPc;
L967:   getfield Field Pc field370 Ljava/lang/String;
L970:   invokevirtual Method java/lang/StringBuilder insert (ILjava/lang/String;)Ljava/lang/StringBuilder;
L973:   ldc "c"
L975:   invokevirtual Method java/lang/StringBuilder append (Ljava/lang/String;)Ljava/lang/StringBuilder;
L978:   invokevirtual Method java/lang/StringBuilder toString ()Ljava/lang/String;
L981:   sipush 203
L984:   iconst_1
L985:   dup
L986:   pop2
L987:   invokestatic Method java/lang/Integer valueOf (I)Ljava/lang/Integer;
L990:   invokevirtual Method java/util/HashMap put [_163]
L993:   getstatic Field JB B Ljava/util/HashMap;
L996:   new java/lang/StringBuilder
L999:   dup
L1000:  invokespecial Method java/lang/StringBuilder <init> ()V
L1003:  iconst_0
L1004:  getstatic Field Pc field373 LPc;
L1007:  getfield Field Pc field370 Ljava/lang/String;
L1010:  invokevirtual Method java/lang/StringBuilder insert (ILjava/lang/String;)Ljava/lang/StringBuilder;
L1013:  ldc_w "d"
L1016:  invokevirtual Method java/lang/StringBuilder append (Ljava/lang/String;)Ljava/lang/StringBuilder;
L1019:  invokevirtual Method java/lang/StringBuilder toString ()Ljava/lang/String;
L1022:  sipush 205
L1025:  iconst_1
L1026:  dup
L1027:  pop2
L1028:  invokestatic Method java/lang/Integer valueOf (I)Ljava/lang/Integer;
L1031:  invokevirtual Method java/util/HashMap put [_163]
L1034:  getstatic Field JB B Ljava/util/HashMap;
L1037:  new java/lang/StringBuilder
L1040:  dup
L1041:  invokespecial Method java/lang/StringBuilder <init> ()V
L1044:  iconst_0
L1045:  getstatic Field Pc field373 LPc;
L1048:  getfield Field Pc field370 Ljava/lang/String;
L1051:  invokevirtual Method java/lang/StringBuilder insert (ILjava/lang/String;)Ljava/lang/StringBuilder;
L1054:  ldc_w "e"
L1057:  invokevirtual Method java/lang/StringBuilder append (Ljava/lang/String;)Ljava/lang/StringBuilder;
L1060:  invokevirtual Method java/lang/StringBuilder toString ()Ljava/lang/String;
L1063:  sipush 208
L1066:  iconst_1
L1067:  dup
L1068:  pop2
L1069:  invokestatic Method java/lang/Integer valueOf (I)Ljava/lang/Integer;
L1072:  invokevirtual Method java/util/HashMap put [_163]
L1075:  getstatic Field JB B Ljava/util/HashMap;
L1078:  new java/lang/StringBuilder
L1081:  dup
L1082:  invokespecial Method java/lang/StringBuilder <init> ()V
L1085:  iconst_0
L1086:  getstatic Field Pc field373 LPc;
L1089:  getfield Field Pc field370 Ljava/lang/String;
L1092:  invokevirtual Method java/lang/StringBuilder insert (ILjava/lang/String;)Ljava/lang/StringBuilder;
L1095:  ldc_w "f"
L1098:  invokevirtual Method java/lang/StringBuilder append (Ljava/lang/String;)Ljava/lang/StringBuilder;
L1101:  invokevirtual Method java/lang/StringBuilder toString ()Ljava/lang/String;
L1104:  sipush 200
L1107:  iconst_1
L1108:  dup
L1109:  pop2
L1110:  invokestatic Method java/lang/Integer valueOf (I)Ljava/lang/Integer;
L1113:  invokevirtual Method java/util/HashMap put [_163]
L1116:  getstatic Field JB B Ljava/util/HashMap;
L1119:  new java/lang/StringBuilder
L1122:  dup
L1123:  invokespecial Method java/lang/StringBuilder <init> ()V
L1126:  iconst_0
L1127:  getstatic Field Pc field373 LPc;
L1130:  getfield Field Pc field370 Ljava/lang/String;
L1133:  invokevirtual Method java/lang/StringBuilder insert (ILjava/lang/String;)Ljava/lang/StringBuilder;
L1136:  ldc_w "180"
L1139:  invokevirtual Method java/lang/StringBuilder append (Ljava/lang/String;)Ljava/lang/StringBuilder;
L1142:  invokevirtual Method java/lang/StringBuilder toString ()Ljava/lang/String;
L1145:  iconst_0
L1146:  iconst_1
L1147:  dup
L1148:  pop2
L1149:  invokestatic Method java/lang/Integer valueOf (I)Ljava/lang/Integer;
L1152:  invokevirtual Method java/util/HashMap put [_163]
L1155:  getstatic Field JB B Ljava/util/HashMap;
L1158:  new java/lang/StringBuilder
L1161:  dup
L1162:  invokespecial Method java/lang/StringBuilder <init> ()V
L1165:  iconst_0
L1166:  getstatic Field Pc field373 LPc;
L1169:  getfield Field Pc field370 Ljava/lang/String;
L1172:  invokevirtual Method java/lang/StringBuilder insert (ILjava/lang/String;)Ljava/lang/StringBuilder;
L1175:  ldc_w "g"
L1178:  invokevirtual Method java/lang/StringBuilder append (Ljava/lang/String;)Ljava/lang/StringBuilder;
L1181:  invokevirtual Method java/lang/StringBuilder toString ()Ljava/lang/String;
L1184:  bipush 57
L1186:  iconst_1
L1187:  dup
L1188:  pop2
L1189:  invokestatic Method java/lang/Integer valueOf (I)Ljava/lang/Integer;
L1192:  invokevirtual Method java/util/HashMap put [_163]
L1195:  getstatic Field JB field1919 Ljava/util/HashMap;
L1198:  new java/lang/StringBuilder
L1201:  dup
L1202:  invokespecial Method java/lang/StringBuilder <init> ()V
L1205:  iconst_0
L1206:  getstatic Field Pc field373 LPc;
L1209:  getfield Field Pc field370 Ljava/lang/String;
L1212:  invokevirtual Method java/lang/StringBuilder insert (ILjava/lang/String;)Ljava/lang/StringBuilder;
L1215:  ldc "a"
L1217:  invokevirtual Method java/lang/StringBuilder append (Ljava/lang/String;)Ljava/lang/StringBuilder;
L1220:  invokevirtual Method java/lang/StringBuilder toString ()Ljava/lang/String;
L1223:  ldc_w "user.name"
L1226:  invokestatic Method java/lang/System getProperty (Ljava/lang/String;)Ljava/lang/String;
L1229:  invokevirtual Method java/util/HashMap put [_163]
L1232:  getstatic Field JB B Ljava/util/HashMap;
L1235:  ldc_w "j"
L1238:  bipush 53
L1240:  iconst_1
L1241:  dup
L1242:  pop2
L1243:  invokestatic Method java/lang/Integer valueOf (I)Ljava/lang/Integer;
L1246:  invokevirtual Method java/util/HashMap put [_163]
L1249:  getstatic Field JB B Ljava/util/HashMap;
L1252:  new java/lang/StringBuilder
L1255:  dup
L1256:  invokespecial Method java/lang/StringBuilder <init> ()V
L1259:  iconst_0
L1260:  getstatic Field Pc field371 LPc;
L1263:  getfield Field Pc field370 Ljava/lang/String;
L1266:  invokevirtual Method java/lang/StringBuilder insert (ILjava/lang/String;)Ljava/lang/StringBuilder;
L1269:  ldc_w "b"
L1272:  invokevirtual Method java/lang/StringBuilder append (Ljava/lang/String;)Ljava/lang/StringBuilder;
L1275:  invokevirtual Method java/lang/StringBuilder toString ()Ljava/lang/String;
L1278:  bipush 42
L1280:  iconst_1
L1281:  dup
L1282:  pop2
L1283:  invokestatic Method java/lang/Integer valueOf (I)Ljava/lang/Integer;
L1286:  invokevirtual Method java/util/HashMap put [_163]
L1289:  getstatic Field JB B Ljava/util/HashMap;
L1292:  new java/lang/StringBuilder
L1295:  dup
L1296:  invokespecial Method java/lang/StringBuilder <init> ()V
L1299:  iconst_0
L1300:  getstatic Field Pc field371 LPc;
L1303:  getfield Field Pc field370 Ljava/lang/String;
L1306:  invokevirtual Method java/lang/StringBuilder insert (ILjava/lang/String;)Ljava/lang/StringBuilder;
L1309:  ldc "c"
L1311:  invokevirtual Method java/lang/StringBuilder append (Ljava/lang/String;)Ljava/lang/StringBuilder;
L1314:  invokevirtual Method java/lang/StringBuilder toString ()Ljava/lang/String;
L1317:  bipush 30
L1319:  iconst_1
L1320:  dup
L1321:  pop2
L1322:  invokestatic Method java/lang/Integer valueOf (I)Ljava/lang/Integer;
L1325:  invokevirtual Method java/util/HashMap put [_163]
L1328:  getstatic Field JB B Ljava/util/HashMap;
L1331:  new java/lang/StringBuilder
L1334:  dup
L1335:  invokespecial Method java/lang/StringBuilder <init> ()V
L1338:  iconst_0
L1339:  getstatic Field Pc field371 LPc;
L1342:  getfield Field Pc field370 Ljava/lang/String;
L1345:  invokevirtual Method java/lang/StringBuilder insert (ILjava/lang/String;)Ljava/lang/StringBuilder;
L1348:  ldc_w "d"
L1351:  invokevirtual Method java/lang/StringBuilder append (Ljava/lang/String;)Ljava/lang/StringBuilder;
L1354:  invokevirtual Method java/lang/StringBuilder toString ()Ljava/lang/String;
L1357:  bipush 32
L1359:  iconst_1
L1360:  dup
L1361:  pop2
L1362:  invokestatic Method java/lang/Integer valueOf (I)Ljava/lang/Integer;
L1365:  invokevirtual Method java/util/HashMap put [_163]
L1368:  getstatic Field JB B Ljava/util/HashMap;
L1371:  new java/lang/StringBuilder
L1374:  dup
L1375:  invokespecial Method java/lang/StringBuilder <init> ()V
L1378:  iconst_0
L1379:  getstatic Field Pc field371 LPc;
L1382:  getfield Field Pc field370 Ljava/lang/String;
L1385:  invokevirtual Method java/lang/StringBuilder insert (ILjava/lang/String;)Ljava/lang/StringBuilder;
L1388:  ldc_w "e"
L1391:  invokevirtual Method java/lang/StringBuilder append (Ljava/lang/String;)Ljava/lang/StringBuilder;
L1394:  invokevirtual Method java/lang/StringBuilder toString ()Ljava/lang/String;
L1397:  bipush 31
L1399:  iconst_1
L1400:  dup
L1401:  pop2
L1402:  invokestatic Method java/lang/Integer valueOf (I)Ljava/lang/Integer;
L1405:  invokevirtual Method java/util/HashMap put [_163]
L1408:  getstatic Field JB B Ljava/util/HashMap;
L1411:  new java/lang/StringBuilder
L1414:  dup
L1415:  invokespecial Method java/lang/StringBuilder <init> ()V
L1418:  iconst_0
L1419:  getstatic Field Pc field371 LPc;
L1422:  getfield Field Pc field370 Ljava/lang/String;
L1425:  invokevirtual Method java/lang/StringBuilder insert (ILjava/lang/String;)Ljava/lang/StringBuilder;
L1428:  ldc_w "f"
L1431:  invokevirtual Method java/lang/StringBuilder append (Ljava/lang/String;)Ljava/lang/StringBuilder;
L1434:  invokevirtual Method java/lang/StringBuilder toString ()Ljava/lang/String;
L1437:  bipush 17
L1439:  iconst_1
L1440:  dup
L1441:  pop2
L1442:  invokestatic Method java/lang/Integer valueOf (I)Ljava/lang/Integer;
L1445:  invokevirtual Method java/util/HashMap put [_163]
L1448:  getstatic Field JB B Ljava/util/HashMap;
L1451:  new java/lang/StringBuilder
L1454:  dup
L1455:  invokespecial Method java/lang/StringBuilder <init> ()V
L1458:  iconst_0
L1459:  getstatic Field Pc field371 LPc;
L1462:  getfield Field Pc field370 Ljava/lang/String;
L1465:  invokevirtual Method java/lang/StringBuilder insert (ILjava/lang/String;)Ljava/lang/StringBuilder;
L1468:  ldc_w "180"
L1471:  invokevirtual Method java/lang/StringBuilder append (Ljava/lang/String;)Ljava/lang/StringBuilder;
L1474:  invokevirtual Method java/lang/StringBuilder toString ()Ljava/lang/String;
L1477:  iconst_0
L1478:  iconst_1
L1479:  dup
L1480:  pop2
L1481:  invokestatic Method java/lang/Integer valueOf (I)Ljava/lang/Integer;
L1484:  invokevirtual Method java/util/HashMap put [_163]
L1487:  getstatic Field JB B Ljava/util/HashMap;
L1490:  new java/lang/StringBuilder
L1493:  dup
L1494:  invokespecial Method java/lang/StringBuilder <init> ()V
L1497:  iconst_0
L1498:  getstatic Field Pc field371 LPc;
L1501:  getfield Field Pc field370 Ljava/lang/String;
L1504:  invokevirtual Method java/lang/StringBuilder insert (ILjava/lang/String;)Ljava/lang/StringBuilder;
L1507:  ldc_w "g"
L1510:  invokevirtual Method java/lang/StringBuilder append (Ljava/lang/String;)Ljava/lang/StringBuilder;
L1513:  invokevirtual Method java/lang/StringBuilder toString ()Ljava/lang/String;
L1516:  bipush 29
L1518:  iconst_1
L1519:  dup
L1520:  pop2
L1521:  invokestatic Method java/lang/Integer valueOf (I)Ljava/lang/Integer;
L1524:  invokevirtual Method java/util/HashMap put [_163]
L1527:  getstatic Field JB field1919 Ljava/util/HashMap;
L1530:  new java/lang/StringBuilder
L1533:  dup
L1534:  invokespecial Method java/lang/StringBuilder <init> ()V
L1537:  iconst_0
L1538:  getstatic Field Pc field371 LPc;
L1541:  getfield Field Pc field370 Ljava/lang/String;
L1544:  invokevirtual Method java/lang/StringBuilder insert (ILjava/lang/String;)Ljava/lang/StringBuilder;
L1547:  ldc "a"
L1549:  invokevirtual Method java/lang/StringBuilder append (Ljava/lang/String;)Ljava/lang/StringBuilder;
L1552:  invokevirtual Method java/lang/StringBuilder toString ()Ljava/lang/String;
L1555:  ldc_w "Player 2"
L1558:  invokevirtual Method java/util/HashMap put [_163]
L1561:  invokestatic Method Pc values ()[LPc;
L1564:  astore_0
L1565:  pop2
L1566:  pop2
L1567:  pop2
L1568:  pop2
L1569:  pop2
L1570:  pop2
L1571:  pop2
L1572:  pop2
L1573:  aload_0
L1574:  arraylength
L1575:  istore_1
L1576:  iconst_0
L1577:  iconst_1
L1578:  dup
L1579:  pop2
L1580:  dup
L1581:  istore_2
L1582:  iload_1
L1583:  if_icmpge L2986
L1586:  aload_0
L1587:  iload_2
L1588:  iinc 2 1
L1591:  aaload
L1592:  astore_3
L1593:  getstatic Field JB B Ljava/util/HashMap;
L1596:  new java/lang/StringBuilder
L1599:  dup
L1600:  invokespecial Method java/lang/StringBuilder <init> ()V
L1603:  iconst_0
L1604:  aload_3
L1605:  getfield Field Pc field370 Ljava/lang/String;
L1608:  invokevirtual Method java/lang/StringBuilder insert (ILjava/lang/String;)Ljava/lang/StringBuilder;
L1611:  ldc_w "h"
L1614:  invokevirtual Method java/lang/StringBuilder append (Ljava/lang/String;)Ljava/lang/StringBuilder;
L1617:  invokevirtual Method java/lang/StringBuilder toString ()Ljava/lang/String;
L1620:  bipush 10
L1622:  iconst_1
L1623:  dup
L1624:  pop2
L1625:  invokestatic Method java/lang/Integer valueOf (I)Ljava/lang/Integer;
L1628:  invokevirtual Method java/util/HashMap put [_163]
L1631:  getstatic Field JB B Ljava/util/HashMap;
L1634:  new java/lang/StringBuilder
L1637:  dup
L1638:  invokespecial Method java/lang/StringBuilder <init> ()V
L1641:  iconst_0
L1642:  aload_3
L1643:  getfield Field Pc field370 Ljava/lang/String;
L1646:  invokevirtual Method java/lang/StringBuilder insert (ILjava/lang/String;)Ljava/lang/StringBuilder;
L1649:  ldc_w "i"
L1652:  invokevirtual Method java/lang/StringBuilder append (Ljava/lang/String;)Ljava/lang/StringBuilder;
L1655:  invokevirtual Method java/lang/StringBuilder toString ()Ljava/lang/String;
L1658:  bipush 10
L1660:  iconst_1
L1661:  dup
L1662:  pop2
L1663:  invokestatic Method java/lang/Integer valueOf (I)Ljava/lang/Integer;
L1666:  invokevirtual Method java/util/HashMap put [_163]
L1669:  getstatic Field JB B Ljava/util/HashMap;
L1672:  new java/lang/StringBuilder
L1675:  dup
L1676:  invokespecial Method java/lang/StringBuilder <init> ()V
L1679:  iconst_0
L1680:  aload_3
L1681:  getfield Field Pc field370 Ljava/lang/String;
L1684:  invokevirtual Method java/lang/StringBuilder insert (ILjava/lang/String;)Ljava/lang/StringBuilder;
L1687:  ldc_w "sj"
L1690:  invokevirtual Method java/lang/StringBuilder append (Ljava/lang/String;)Ljava/lang/StringBuilder;
L1693:  invokevirtual Method java/lang/StringBuilder toString ()Ljava/lang/String;
L1696:  iconst_0
L1697:  iconst_1
L1698:  dup
L1699:  pop2
L1700:  invokestatic Method java/lang/Integer valueOf (I)Ljava/lang/Integer;
L1703:  invokevirtual Method java/util/HashMap put [_163]
L1706:  getstatic Field JB B Ljava/util/HashMap;
L1709:  new java/lang/StringBuilder
L1712:  dup
L1713:  invokespecial Method java/lang/StringBuilder <init> ()V
L1716:  iconst_0
L1717:  aload_3
L1718:  getfield Field Pc field370 Ljava/lang/String;
L1721:  invokevirtual Method java/lang/StringBuilder insert (ILjava/lang/String;)Ljava/lang/StringBuilder;
L1724:  ldc_w "si"
L1727:  invokevirtual Method java/lang/StringBuilder append (Ljava/lang/String;)Ljava/lang/StringBuilder;
L1730:  invokevirtual Method java/lang/StringBuilder toString ()Ljava/lang/String;
L1733:  iconst_0
L1734:  iconst_1
L1735:  dup
L1736:  pop2
L1737:  invokestatic Method java/lang/Integer valueOf (I)Ljava/lang/Integer;
L1740:  invokevirtual Method java/util/HashMap put [_163]
L1743:  getstatic Field JB B Ljava/util/HashMap;
L1746:  new java/lang/StringBuilder
L1749:  dup
L1750:  invokespecial Method java/lang/StringBuilder <init> ()V
L1753:  iconst_0
L1754:  aload_3
L1755:  getfield Field Pc field370 Ljava/lang/String;
L1758:  invokevirtual Method java/lang/StringBuilder insert (ILjava/lang/String;)Ljava/lang/StringBuilder;
L1761:  ldc_w "sl"
L1764:  invokevirtual Method java/lang/StringBuilder append (Ljava/lang/String;)Ljava/lang/StringBuilder;
L1767:  invokevirtual Method java/lang/StringBuilder toString ()Ljava/lang/String;
L1770:  iconst_0
L1771:  iconst_1
L1772:  dup
L1773:  pop2
L1774:  invokestatic Method java/lang/Integer valueOf (I)Ljava/lang/Integer;
L1777:  invokevirtual Method java/util/HashMap put [_163]
L1780:  getstatic Field JB B Ljava/util/HashMap;
L1783:  new java/lang/StringBuilder
L1786:  dup
L1787:  invokespecial Method java/lang/StringBuilder <init> ()V
L1790:  iconst_0
L1791:  aload_3
L1792:  getfield Field Pc field370 Ljava/lang/String;
L1795:  invokevirtual Method java/lang/StringBuilder insert (ILjava/lang/String;)Ljava/lang/StringBuilder;
L1798:  ldc_w "sz"
L1801:  invokevirtual Method java/lang/StringBuilder append (Ljava/lang/String;)Ljava/lang/StringBuilder;
L1804:  invokevirtual Method java/lang/StringBuilder toString ()Ljava/lang/String;
L1807:  iconst_0
L1808:  iconst_1
L1809:  dup
L1810:  pop2
L1811:  invokestatic Method java/lang/Integer valueOf (I)Ljava/lang/Integer;
L1814:  invokevirtual Method java/util/HashMap put [_163]
L1817:  getstatic Field JB B Ljava/util/HashMap;
L1820:  new java/lang/StringBuilder
L1823:  dup
L1824:  invokespecial Method java/lang/StringBuilder <init> ()V
L1827:  iconst_0
L1828:  aload_3
L1829:  getfield Field Pc field370 Ljava/lang/String;
L1832:  invokevirtual Method java/lang/StringBuilder insert (ILjava/lang/String;)Ljava/lang/StringBuilder;
L1835:  ldc_w "ss"
L1838:  invokevirtual Method java/lang/StringBuilder append (Ljava/lang/String;)Ljava/lang/StringBuilder;
L1841:  invokevirtual Method java/lang/StringBuilder toString ()Ljava/lang/String;
L1844:  iconst_0
L1845:  iconst_1
L1846:  dup
L1847:  pop2
L1848:  invokestatic Method java/lang/Integer valueOf (I)Ljava/lang/Integer;
L1851:  invokevirtual Method java/util/HashMap put [_163]
L1854:  getstatic Field JB B Ljava/util/HashMap;
L1857:  new java/lang/StringBuilder
L1860:  dup
L1861:  invokespecial Method java/lang/StringBuilder <init> ()V
L1864:  iconst_0
L1865:  aload_3
L1866:  getfield Field Pc field370 Ljava/lang/String;
L1869:  invokevirtual Method java/lang/StringBuilder insert (ILjava/lang/String;)Ljava/lang/StringBuilder;
L1872:  ldc_w "st"
L1875:  invokevirtual Method java/lang/StringBuilder append (Ljava/lang/String;)Ljava/lang/StringBuilder;
L1878:  invokevirtual Method java/lang/StringBuilder toString ()Ljava/lang/String;
L1881:  iconst_0
L1882:  iconst_1
L1883:  dup
L1884:  pop2
L1885:  invokestatic Method java/lang/Integer valueOf (I)Ljava/lang/Integer;
L1888:  invokevirtual Method java/util/HashMap put [_163]
L1891:  getstatic Field JB B Ljava/util/HashMap;
L1894:  new java/lang/StringBuilder
L1897:  dup
L1898:  invokespecial Method java/lang/StringBuilder <init> ()V
L1901:  iconst_0
L1902:  aload_3
L1903:  getfield Field Pc field370 Ljava/lang/String;
L1906:  invokevirtual Method java/lang/StringBuilder insert (ILjava/lang/String;)Ljava/lang/StringBuilder;
L1909:  ldc_w "cl"
L1912:  invokevirtual Method java/lang/StringBuilder append (Ljava/lang/String;)Ljava/lang/StringBuilder;
L1915:  invokevirtual Method java/lang/StringBuilder toString ()Ljava/lang/String;
L1918:  iconst_5
L1919:  iconst_1
L1920:  dup
L1921:  pop2
L1922:  invokestatic Method java/lang/Integer valueOf (I)Ljava/lang/Integer;
L1925:  invokevirtual Method java/util/HashMap put [_163]
L1928:  getstatic Field JB B Ljava/util/HashMap;
L1931:  new java/lang/StringBuilder
L1934:  dup
L1935:  invokespecial Method java/lang/StringBuilder <init> ()V
L1938:  iconst_0
L1939:  aload_3
L1940:  getfield Field Pc field370 Ljava/lang/String;
L1943:  invokevirtual Method java/lang/StringBuilder insert (ILjava/lang/String;)Ljava/lang/StringBuilder;
L1946:  ldc_w "ci"
L1949:  invokevirtual Method java/lang/StringBuilder append (Ljava/lang/String;)Ljava/lang/StringBuilder;
L1952:  invokevirtual Method java/lang/StringBuilder toString ()Ljava/lang/String;
L1955:  iconst_2
L1956:  iconst_1
L1957:  dup
L1958:  pop2
L1959:  invokestatic Method java/lang/Integer valueOf (I)Ljava/lang/Integer;
L1962:  invokevirtual Method java/util/HashMap put [_163]
L1965:  getstatic Field JB B Ljava/util/HashMap;
L1968:  new java/lang/StringBuilder
L1971:  dup
L1972:  invokespecial Method java/lang/StringBuilder <init> ()V
L1975:  iconst_0
L1976:  aload_3
L1977:  getfield Field Pc field370 Ljava/lang/String;
L1980:  invokevirtual Method java/lang/StringBuilder insert (ILjava/lang/String;)Ljava/lang/StringBuilder;
L1983:  ldc_w "cj"
L1986:  invokevirtual Method java/lang/StringBuilder append (Ljava/lang/String;)Ljava/lang/StringBuilder;
L1989:  invokevirtual Method java/lang/StringBuilder toString ()Ljava/lang/String;
L1992:  iconst_4
L1993:  iconst_1
L1994:  dup
L1995:  pop2
L1996:  invokestatic Method java/lang/Integer valueOf (I)Ljava/lang/Integer;
L1999:  invokevirtual Method java/util/HashMap put [_163]
L2002:  getstatic Field JB B Ljava/util/HashMap;
L2005:  new java/lang/StringBuilder
L2008:  dup
L2009:  invokespecial Method java/lang/StringBuilder <init> ()V
L2012:  iconst_0
L2013:  aload_3
L2014:  getfield Field Pc field370 Ljava/lang/String;
L2017:  invokevirtual Method java/lang/StringBuilder insert (ILjava/lang/String;)Ljava/lang/StringBuilder;
L2020:  ldc_w "cs"
L2023:  invokevirtual Method java/lang/StringBuilder append (Ljava/lang/String;)Ljava/lang/StringBuilder;
L2026:  invokevirtual Method java/lang/StringBuilder toString ()Ljava/lang/String;
L2029:  bipush 6
L2031:  iconst_1
L2032:  dup
L2033:  pop2
L2034:  invokestatic Method java/lang/Integer valueOf (I)Ljava/lang/Integer;
L2037:  invokevirtual Method java/util/HashMap put [_163]
L2040:  getstatic Field JB B Ljava/util/HashMap;
L2043:  new java/lang/StringBuilder
L2046:  dup
L2047:  invokespecial Method java/lang/StringBuilder <init> ()V
L2050:  iconst_0
L2051:  aload_3
L2052:  getfield Field Pc field370 Ljava/lang/String;
L2055:  invokevirtual Method java/lang/StringBuilder insert (ILjava/lang/String;)Ljava/lang/StringBuilder;
L2058:  ldc_w "cz"
L2061:  invokevirtual Method java/lang/StringBuilder append (Ljava/lang/String;)Ljava/lang/StringBuilder;
L2064:  invokevirtual Method java/lang/StringBuilder toString ()Ljava/lang/String;
L2067:  bipush 7
L2069:  iconst_1
L2070:  dup
L2071:  pop2
L2072:  invokestatic Method java/lang/Integer valueOf (I)Ljava/lang/Integer;
L2075:  invokevirtual Method java/util/HashMap put [_163]
L2078:  getstatic Field JB B Ljava/util/HashMap;
L2081:  new java/lang/StringBuilder
L2084:  dup
L2085:  invokespecial Method java/lang/StringBuilder <init> ()V
L2088:  iconst_0
L2089:  aload_3
L2090:  getfield Field Pc field370 Ljava/lang/String;
L2093:  invokevirtual Method java/lang/StringBuilder insert (ILjava/lang/String;)Ljava/lang/StringBuilder;
L2096:  ldc_w "ct"
L2099:  invokevirtual Method java/lang/StringBuilder append (Ljava/lang/String;)Ljava/lang/StringBuilder;
L2102:  invokevirtual Method java/lang/StringBuilder toString ()Ljava/lang/String;
L2105:  iconst_1
L2106:  dup
L2107:  dup
L2108:  pop2
L2109:  invokestatic Method java/lang/Integer valueOf (I)Ljava/lang/Integer;
L2112:  invokevirtual Method java/util/HashMap put [_163]
L2115:  getstatic Field JB B Ljava/util/HashMap;
L2118:  new java/lang/StringBuilder
L2121:  dup
L2122:  invokespecial Method java/lang/StringBuilder <init> ()V
L2125:  iconst_0
L2126:  aload_3
L2127:  getfield Field Pc field370 Ljava/lang/String;
L2130:  invokevirtual Method java/lang/StringBuilder insert (ILjava/lang/String;)Ljava/lang/StringBuilder;
L2133:  ldc_w "co"
L2136:  invokevirtual Method java/lang/StringBuilder append (Ljava/lang/String;)Ljava/lang/StringBuilder;
L2139:  invokevirtual Method java/lang/StringBuilder toString ()Ljava/lang/String;
L2142:  iconst_3
L2143:  iconst_1
L2144:  dup
L2145:  pop2
L2146:  invokestatic Method java/lang/Integer valueOf (I)Ljava/lang/Integer;
L2149:  invokevirtual Method java/util/HashMap put [_163]
L2152:  getstatic Field JB field1919 Ljava/util/HashMap;
L2155:  new java/lang/StringBuilder
L2158:  dup
L2159:  invokespecial Method java/lang/StringBuilder <init> ()V
L2162:  iconst_0
L2163:  aload_3
L2164:  getfield Field Pc field370 Ljava/lang/String;
L2167:  invokevirtual Method java/lang/StringBuilder insert (ILjava/lang/String;)Ljava/lang/StringBuilder;
L2170:  ldc_w "mc"
L2173:  invokevirtual Method java/lang/StringBuilder append (Ljava/lang/String;)Ljava/lang/StringBuilder;
L2176:  invokevirtual Method java/lang/StringBuilder toString ()Ljava/lang/String;
L2179:  ldc_w "|"
L2182:  invokevirtual Method java/util/HashMap put [_163]
L2185:  getstatic Field JB field1919 Ljava/util/HashMap;
L2188:  new java/lang/StringBuilder
L2191:  dup
L2192:  invokespecial Method java/lang/StringBuilder <init> ()V
L2195:  iconst_0
L2196:  aload_3
L2197:  getfield Field Pc field370 Ljava/lang/String;
L2200:  invokevirtual Method java/lang/StringBuilder insert (ILjava/lang/String;)Ljava/lang/StringBuilder;
L2203:  ldc_w "li"
L2206:  invokevirtual Method java/lang/StringBuilder append (Ljava/lang/String;)Ljava/lang/StringBuilder;
L2209:  invokevirtual Method java/lang/StringBuilder toString ()Ljava/lang/String;
L2212:  ldc ""
L2214:  invokevirtual Method java/util/HashMap put [_163]
L2217:  getstatic Field JB field1919 Ljava/util/HashMap;
L2220:  new java/lang/StringBuilder
L2223:  dup
L2224:  invokespecial Method java/lang/StringBuilder <init> ()V
L2227:  iconst_0
L2228:  aload_3
L2229:  getfield Field Pc field370 Ljava/lang/String;
L2232:  invokevirtual Method java/lang/StringBuilder insert (ILjava/lang/String;)Ljava/lang/StringBuilder;
L2235:  ldc_w "pw"
L2238:  invokevirtual Method java/lang/StringBuilder append (Ljava/lang/String;)Ljava/lang/StringBuilder;
L2241:  invokevirtual Method java/lang/StringBuilder toString ()Ljava/lang/String;
L2244:  ldc ""
L2246:  invokevirtual Method java/util/HashMap put [_163]
L2249:  getstatic Field JB B Ljava/util/HashMap;
L2252:  new java/lang/StringBuilder
L2255:  dup
L2256:  invokespecial Method java/lang/StringBuilder <init> ()V
L2259:  iconst_0
L2260:  aload_3
L2261:  getfield Field Pc field370 Ljava/lang/String;
L2264:  invokevirtual Method java/lang/StringBuilder insert (ILjava/lang/String;)Ljava/lang/StringBuilder;
L2267:  ldc_w "pag"
L2270:  invokevirtual Method java/lang/StringBuilder append (Ljava/lang/String;)Ljava/lang/StringBuilder;
L2273:  invokevirtual Method java/lang/StringBuilder toString ()Ljava/lang/String;
L2276:  iconst_1
L2277:  dup
L2278:  dup
L2279:  pop2
L2280:  invokestatic Method java/lang/Integer valueOf (I)Ljava/lang/Integer;
L2283:  invokevirtual Method java/util/HashMap put [_163]
L2286:  getstatic Field JB field1919 Ljava/util/HashMap;
L2289:  new java/lang/StringBuilder
L2292:  dup
L2293:  invokespecial Method java/lang/StringBuilder <init> ()V
L2296:  iconst_0
L2297:  aload_3
L2298:  getfield Field Pc field370 Ljava/lang/String;
L2301:  invokevirtual Method java/lang/StringBuilder insert (ILjava/lang/String;)Ljava/lang/StringBuilder;
L2304:  ldc_w "ua"
L2307:  invokevirtual Method java/lang/StringBuilder append (Ljava/lang/String;)Ljava/lang/StringBuilder;
L2310:  invokevirtual Method java/lang/StringBuilder toString ()Ljava/lang/String;
L2313:  ldc_w "|"
L2316:  invokevirtual Method java/util/HashMap put [_163]
L2319:  getstatic Field JB B Ljava/util/HashMap;
L2322:  new java/lang/StringBuilder
L2325:  dup
L2326:  invokespecial Method java/lang/StringBuilder <init> ()V
L2329:  iconst_0
L2330:  aload_3
L2331:  getfield Field Pc field370 Ljava/lang/String;
L2334:  invokevirtual Method java/lang/StringBuilder insert (ILjava/lang/String;)Ljava/lang/StringBuilder;
L2337:  ldc_w "dls"
L2340:  invokevirtual Method java/lang/StringBuilder append (Ljava/lang/String;)Ljava/lang/StringBuilder;
L2343:  ldc_w "9000"
L2346:  invokevirtual Method java/lang/StringBuilder append (Ljava/lang/String;)Ljava/lang/StringBuilder;
L2349:  invokevirtual Method java/lang/StringBuilder toString ()Ljava/lang/String;
L2352:  iconst_0
L2353:  iconst_1
L2354:  dup
L2355:  pop2
L2356:  invokestatic Method java/lang/Integer valueOf (I)Ljava/lang/Integer;
L2359:  invokevirtual Method java/util/HashMap put [_163]
L2362:  getstatic Field JB B Ljava/util/HashMap;
L2365:  new java/lang/StringBuilder
L2368:  dup
L2369:  invokespecial Method java/lang/StringBuilder <init> ()V
L2372:  iconst_0
L2373:  aload_3
L2374:  getfield Field Pc field370 Ljava/lang/String;
L2377:  invokevirtual Method java/lang/StringBuilder insert (ILjava/lang/String;)Ljava/lang/StringBuilder;
L2380:  ldc_w "dls"
L2383:  invokevirtual Method java/lang/StringBuilder append (Ljava/lang/String;)Ljava/lang/StringBuilder;
L2386:  ldc_w "lifetime"
L2389:  invokevirtual Method java/lang/StringBuilder append (Ljava/lang/String;)Ljava/lang/StringBuilder;
L2392:  invokevirtual Method java/lang/StringBuilder toString ()Ljava/lang/String;
L2395:  iconst_0
L2396:  iconst_1
L2397:  dup
L2398:  pop2
L2399:  invokestatic Method java/lang/Integer valueOf (I)Ljava/lang/Integer;
L2402:  invokevirtual Method java/util/HashMap put [_163]
L2405:  getstatic Field JB B Ljava/util/HashMap;
L2408:  new java/lang/StringBuilder
L2411:  dup
L2412:  invokespecial Method java/lang/StringBuilder <init> ()V
L2415:  iconst_0
L2416:  aload_3
L2417:  getfield Field Pc field370 Ljava/lang/String;
L2420:  invokevirtual Method java/lang/StringBuilder insert (ILjava/lang/String;)Ljava/lang/StringBuilder;
L2423:  ldc_w "dls"
L2426:  invokevirtual Method java/lang/StringBuilder append (Ljava/lang/String;)Ljava/lang/StringBuilder;
L2429:  ldc_w "lifetimes"
L2432:  invokevirtual Method java/lang/StringBuilder append (Ljava/lang/String;)Ljava/lang/StringBuilder;
L2435:  invokevirtual Method java/lang/StringBuilder toString ()Ljava/lang/String;
L2438:  iconst_0
L2439:  iconst_1
L2440:  dup
L2441:  pop2
L2442:  invokestatic Method java/lang/Integer valueOf (I)Ljava/lang/Integer;
L2445:  invokevirtual Method java/util/HashMap put [_163]
L2448:  getstatic Field JB B Ljava/util/HashMap;
L2451:  new java/lang/StringBuilder
L2454:  dup
L2455:  invokespecial Method java/lang/StringBuilder <init> ()V
L2458:  iconst_0
L2459:  aload_3
L2460:  getfield Field Pc field370 Ljava/lang/String;
L2463:  invokevirtual Method java/lang/StringBuilder insert (ILjava/lang/String;)Ljava/lang/StringBuilder;
L2466:  ldc_w "ws"
L2469:  invokevirtual Method java/lang/StringBuilder append (Ljava/lang/String;)Ljava/lang/StringBuilder;
L2472:  ldc_w "wA"
L2475:  invokevirtual Method java/lang/StringBuilder append (Ljava/lang/String;)Ljava/lang/StringBuilder;
L2478:  invokevirtual Method java/lang/StringBuilder toString ()Ljava/lang/String;
L2481:  iconst_0
L2482:  iconst_1
L2483:  dup
L2484:  pop2
L2485:  invokestatic Method java/lang/Integer valueOf (I)Ljava/lang/Integer;
L2488:  invokevirtual Method java/util/HashMap put [_163]
L2491:  getstatic Field JB B Ljava/util/HashMap;
L2494:  new java/lang/StringBuilder
L2497:  dup
L2498:  invokespecial Method java/lang/StringBuilder <init> ()V
L2501:  iconst_0
L2502:  aload_3
L2503:  getfield Field Pc field370 Ljava/lang/String;
L2506:  invokevirtual Method java/lang/StringBuilder insert (ILjava/lang/String;)Ljava/lang/StringBuilder;
L2509:  ldc_w "ws"
L2512:  invokevirtual Method java/lang/StringBuilder append (Ljava/lang/String;)Ljava/lang/StringBuilder;
L2515:  ldc_w "wB"
L2518:  invokevirtual Method java/lang/StringBuilder append (Ljava/lang/String;)Ljava/lang/StringBuilder;
L2521:  invokevirtual Method java/lang/StringBuilder toString ()Ljava/lang/String;
L2524:  iconst_0
L2525:  iconst_1
L2526:  dup
L2527:  pop2
L2528:  invokestatic Method java/lang/Integer valueOf (I)Ljava/lang/Integer;
L2531:  invokevirtual Method java/util/HashMap put [_163]
L2534:  getstatic Field JB B Ljava/util/HashMap;
L2537:  new java/lang/StringBuilder
L2540:  dup
L2541:  invokespecial Method java/lang/StringBuilder <init> ()V
L2544:  iconst_0
L2545:  aload_3
L2546:  getfield Field Pc field370 Ljava/lang/String;
L2549:  invokevirtual Method java/lang/StringBuilder insert (ILjava/lang/String;)Ljava/lang/StringBuilder;
L2552:  ldc_w "ws"
L2555:  invokevirtual Method java/lang/StringBuilder append (Ljava/lang/String;)Ljava/lang/StringBuilder;
L2558:  ldc_w "wC"
L2561:  invokevirtual Method java/lang/StringBuilder append (Ljava/lang/String;)Ljava/lang/StringBuilder;
L2564:  invokevirtual Method java/lang/StringBuilder toString ()Ljava/lang/String;
L2567:  iconst_0
L2568:  iconst_1
L2569:  dup
L2570:  pop2
L2571:  invokestatic Method java/lang/Integer valueOf (I)Ljava/lang/Integer;
L2574:  invokevirtual Method java/util/HashMap put [_163]
L2577:  getstatic Field JB B Ljava/util/HashMap;
L2580:  new java/lang/StringBuilder
L2583:  dup
L2584:  invokespecial Method java/lang/StringBuilder <init> ()V
L2587:  iconst_0
L2588:  aload_3
L2589:  getfield Field Pc field370 Ljava/lang/String;
L2592:  invokevirtual Method java/lang/StringBuilder insert (ILjava/lang/String;)Ljava/lang/StringBuilder;
L2595:  ldc_w "ws"
L2598:  invokevirtual Method java/lang/StringBuilder append (Ljava/lang/String;)Ljava/lang/StringBuilder;
L2601:  ldc_w "wD"
L2604:  invokevirtual Method java/lang/StringBuilder append (Ljava/lang/String;)Ljava/lang/StringBuilder;
L2607:  invokevirtual Method java/lang/StringBuilder toString ()Ljava/lang/String;
L2610:  iconst_0
L2611:  iconst_1
L2612:  dup
L2613:  pop2
L2614:  invokestatic Method java/lang/Integer valueOf (I)Ljava/lang/Integer;
L2617:  invokevirtual Method java/util/HashMap put [_163]
L2620:  getstatic Field JB B Ljava/util/HashMap;
L2623:  new java/lang/StringBuilder
L2626:  dup
L2627:  invokespecial Method java/lang/StringBuilder <init> ()V
L2630:  iconst_0
L2631:  aload_3
L2632:  getfield Field Pc field370 Ljava/lang/String;
L2635:  invokevirtual Method java/lang/StringBuilder insert (ILjava/lang/String;)Ljava/lang/StringBuilder;
L2638:  ldc_w "rs"
L2641:  invokevirtual Method java/lang/StringBuilder append (Ljava/lang/String;)Ljava/lang/StringBuilder;
L2644:  ldc_w "rA"
L2647:  invokevirtual Method java/lang/StringBuilder append (Ljava/lang/String;)Ljava/lang/StringBuilder;
L2650:  invokevirtual Method java/lang/StringBuilder toString ()Ljava/lang/String;
L2653:  iconst_0
L2654:  iconst_1
L2655:  dup
L2656:  pop2
L2657:  invokestatic Method java/lang/Integer valueOf (I)Ljava/lang/Integer;
L2660:  invokevirtual Method java/util/HashMap put [_163]
L2663:  getstatic Field JB B Ljava/util/HashMap;
L2666:  new java/lang/StringBuilder
L2669:  dup
L2670:  invokespecial Method java/lang/StringBuilder <init> ()V
L2673:  iconst_0
L2674:  aload_3
L2675:  getfield Field Pc field370 Ljava/lang/String;
L2678:  invokevirtual Method java/lang/StringBuilder insert (ILjava/lang/String;)Ljava/lang/StringBuilder;
L2681:  ldc_w "rs"
L2684:  invokevirtual Method java/lang/StringBuilder append (Ljava/lang/String;)Ljava/lang/StringBuilder;
L2687:  ldc_w "rB"
L2690:  invokevirtual Method java/lang/StringBuilder append (Ljava/lang/String;)Ljava/lang/StringBuilder;
L2693:  invokevirtual Method java/lang/StringBuilder toString ()Ljava/lang/String;
L2696:  iconst_0
L2697:  iconst_1
L2698:  dup
L2699:  pop2
L2700:  invokestatic Method java/lang/Integer valueOf (I)Ljava/lang/Integer;
L2703:  invokevirtual Method java/util/HashMap put [_163]
L2706:  getstatic Field JB B Ljava/util/HashMap;
L2709:  new java/lang/StringBuilder
L2712:  dup
L2713:  invokespecial Method java/lang/StringBuilder <init> ()V
L2716:  iconst_0
L2717:  aload_3
L2718:  getfield Field Pc field370 Ljava/lang/String;
L2721:  invokevirtual Method java/lang/StringBuilder insert (ILjava/lang/String;)Ljava/lang/StringBuilder;
L2724:  ldc_w "rs"
L2727:  invokevirtual Method java/lang/StringBuilder append (Ljava/lang/String;)Ljava/lang/StringBuilder;
L2730:  ldc_w "rC"
L2733:  invokevirtual Method java/lang/StringBuilder append (Ljava/lang/String;)Ljava/lang/StringBuilder;
L2736:  invokevirtual Method java/lang/StringBuilder toString ()Ljava/lang/String;
L2739:  iconst_0
L2740:  iconst_1
L2741:  dup
L2742:  pop2
L2743:  invokestatic Method java/lang/Integer valueOf (I)Ljava/lang/Integer;
L2746:  invokevirtual Method java/util/HashMap put [_163]
L2749:  getstatic Field JB B Ljava/util/HashMap;
L2752:  new java/lang/StringBuilder
L2755:  dup
L2756:  invokespecial Method java/lang/StringBuilder <init> ()V
L2759:  iconst_0
L2760:  aload_3
L2761:  getfield Field Pc field370 Ljava/lang/String;
L2764:  invokevirtual Method java/lang/StringBuilder insert (ILjava/lang/String;)Ljava/lang/StringBuilder;
L2767:  ldc_w "rs"
L2770:  invokevirtual Method java/lang/StringBuilder append (Ljava/lang/String;)Ljava/lang/StringBuilder;
L2773:  ldc_w "rD"
L2776:  invokevirtual Method java/lang/StringBuilder append (Ljava/lang/String;)Ljava/lang/StringBuilder;
L2779:  invokevirtual Method java/lang/StringBuilder toString ()Ljava/lang/String;
L2782:  iconst_0
L2783:  iconst_1
L2784:  dup
L2785:  pop2
L2786:  invokestatic Method java/lang/Integer valueOf (I)Ljava/lang/Integer;
L2789:  invokevirtual Method java/util/HashMap put [_163]
L2792:  getstatic Field JB B Ljava/util/HashMap;
L2795:  new java/lang/StringBuilder
L2798:  dup
L2799:  invokespecial Method java/lang/StringBuilder <init> ()V
L2802:  iconst_0
L2803:  aload_3
L2804:  getfield Field Pc field370 Ljava/lang/String;
L2807:  invokevirtual Method java/lang/StringBuilder insert (ILjava/lang/String;)Ljava/lang/StringBuilder;
L2810:  ldc_w "pts"
L2813:  invokevirtual Method java/lang/StringBuilder append (Ljava/lang/String;)Ljava/lang/StringBuilder;
L2816:  ldc_w "doctor"
L2819:  invokevirtual Method java/lang/StringBuilder append (Ljava/lang/String;)Ljava/lang/StringBuilder;
L2822:  invokevirtual Method java/lang/StringBuilder toString ()Ljava/lang/String;
L2825:  iconst_0
L2826:  iconst_1
L2827:  dup
L2828:  pop2
L2829:  invokestatic Method java/lang/Integer valueOf (I)Ljava/lang/Integer;
L2832:  invokevirtual Method java/util/HashMap put [_163]
L2835:  getstatic Field JB B Ljava/util/HashMap;
L2838:  new java/lang/StringBuilder
L2841:  dup
L2842:  invokespecial Method java/lang/StringBuilder <init> ()V
L2845:  iconst_0
L2846:  aload_3
L2847:  getfield Field Pc field370 Ljava/lang/String;
L2850:  invokevirtual Method java/lang/StringBuilder insert (ILjava/lang/String;)Ljava/lang/StringBuilder;
L2853:  ldc_w "pts"
L2856:  invokevirtual Method java/lang/StringBuilder append (Ljava/lang/String;)Ljava/lang/StringBuilder;
L2859:  ldc_w "amber_lamps"
L2862:  invokevirtual Method java/lang/StringBuilder append (Ljava/lang/String;)Ljava/lang/StringBuilder;
L2865:  invokevirtual Method java/lang/StringBuilder toString ()Ljava/lang/String;
L2868:  iconst_0
L2869:  iconst_1
L2870:  dup
L2871:  pop2
L2872:  invokestatic Method java/lang/Integer valueOf (I)Ljava/lang/Integer;
L2875:  invokevirtual Method java/util/HashMap put [_163]
L2878:  getstatic Field JB B Ljava/util/HashMap;
L2881:  new java/lang/StringBuilder
L2884:  dup
L2885:  invokespecial Method java/lang/StringBuilder <init> ()V
L2888:  iconst_0
L2889:  aload_3
L2890:  getfield Field Pc field370 Ljava/lang/String;
L2893:  invokevirtual Method java/lang/StringBuilder insert (ILjava/lang/String;)Ljava/lang/StringBuilder;
L2896:  ldc_w "pts"
L2899:  invokevirtual Method java/lang/StringBuilder append (Ljava/lang/String;)Ljava/lang/StringBuilder;
L2902:  ldc_w "epic_beard"
L2905:  invokevirtual Method java/lang/StringBuilder append (Ljava/lang/String;)Ljava/lang/StringBuilder;
L2908:  invokevirtual Method java/lang/StringBuilder toString ()Ljava/lang/String;
L2911:  iconst_0
L2912:  iconst_1
L2913:  dup
L2914:  pop2
L2915:  invokestatic Method java/lang/Integer valueOf (I)Ljava/lang/Integer;
L2918:  invokevirtual Method java/util/HashMap put [_163]
L2921:  getstatic Field JB B Ljava/util/HashMap;
L2924:  new java/lang/StringBuilder
L2927:  dup
L2928:  invokespecial Method java/lang/StringBuilder <init> ()V
L2931:  iconst_0
L2932:  aload_3
L2933:  getfield Field Pc field370 Ljava/lang/String;
L2936:  invokevirtual Method java/lang/StringBuilder insert (ILjava/lang/String;)Ljava/lang/StringBuilder;
L2939:  ldc_w "pts"
L2942:  invokevirtual Method java/lang/StringBuilder append (Ljava/lang/String;)Ljava/lang/StringBuilder;
L2945:  ldc_w "chuck_testa"
L2948:  invokevirtual Method java/lang/StringBuilder append (Ljava/lang/String;)Ljava/lang/StringBuilder;
L2951:  invokevirtual Method java/lang/StringBuilder toString ()Ljava/lang/String;
L2954:  iconst_0
L2955:  iconst_1
L2956:  dup
L2957:  pop2
L2958:  invokestatic Method java/lang/Integer valueOf (I)Ljava/lang/Integer;
L2961:  invokevirtual Method java/util/HashMap put [_163]
L2964:  pop
L2965:  pop2
L2966:  pop2
L2967:  pop2
L2968:  pop2
L2969:  pop2
L2970:  pop2
L2971:  pop2
L2972:  pop2
L2973:  pop2
L2974:  pop2
L2975:  pop2
L2976:  pop2
L2977:  pop2
L2978:  pop2
L2979:  pop2
L2980:  pop2
L2981:  pop2
L2982:  iload_2
L2983:  goto L1582
L2986:  invokestatic Method org/lwjgl/opengl/Display method3011 ()Lorg/lwjgl/opengl/DisplayMode;
L2989:  astore_0
L2990:  getstatic Field JB B Ljava/util/HashMap;
L2993:  ldc_w "k"
L2996:  ldc_w 8e-1f
L2999:  aload_0
L3000:  invokevirtual Method org/lwjgl/opengl/DisplayMode method3047 ()I
L3003:  bipush 64
L3005:  iconst_1
L3006:  dup
L3007:  pop2
L3008:  isub
L3009:  i2f
L3010:  aload_0
L3011:  invokevirtual Method org/lwjgl/opengl/DisplayMode method3049 ()I
L3014:  i2f
L3015:  ldc_w 1e1f
L3018:  fdiv
L3019:  ldc_w 1.6e1f
L3022:  fmul
L3023:  ldc_w 1.28e2f
L3026:  fsub
L3027:  invokestatic Method java/lang/Math min (FF)F
L3030:  fmul
L3031:  f2i
L3032:  invokestatic Method java/lang/Integer valueOf (I)Ljava/lang/Integer;
L3035:  invokevirtual Method java/util/HashMap put [_163]
L3038:  getstatic Field JB B Ljava/util/HashMap;
L3041:  ldc_w "l"
L3044:  iconst_0
L3045:  iconst_1
L3046:  dup
L3047:  pop2
L3048:  invokestatic Method java/lang/Integer valueOf (I)Ljava/lang/Integer;
L3051:  invokevirtual Method java/util/HashMap put [_163]
L3054:  pop2
L3055:  getstatic Field JB B Ljava/util/HashMap;
L3058:  ldc_w "m"
L3061:  invokestatic Method FE hzfoundhere ()[Lorg/lwjgl/opengl/DisplayMode;
L3064:  arraylength
L3065:  iconst_1
L3066:  dup
L3067:  dup
L3068:  pop2
L3069:  isub
L3070:  invokestatic Method java/lang/Integer valueOf (I)Ljava/lang/Integer;
L3073:  invokevirtual Method java/util/HashMap put [_163]
L3076:  getstatic Field JB B Ljava/util/HashMap;
L3079:  ldc_w "q"
L3082:  bipush 6
L3084:  iconst_1
L3085:  dup
L3086:  pop2
L3087:  invokestatic Method java/lang/Integer valueOf (I)Ljava/lang/Integer;
L3090:  invokevirtual Method java/util/HashMap put [_163]
L3093:  getstatic Field JB B Ljava/util/HashMap;
L3096:  ldc_w "r"
L3099:  iconst_4
L3100:  iconst_1
L3101:  dup
L3102:  pop2
L3103:  invokestatic Method java/lang/Integer valueOf (I)Ljava/lang/Integer;
L3106:  invokevirtual Method java/util/HashMap put [_163]
L3109:  getstatic Field JB B Ljava/util/HashMap;
L3112:  ldc_w "s"
L3115:  bipush 9
L3117:  iconst_1
L3118:  dup
L3119:  pop2
L3120:  invokestatic Method java/lang/Integer valueOf (I)Ljava/lang/Integer;
L3123:  invokevirtual Method java/util/HashMap put [_163]
L3126:  getstatic Field JB B Ljava/util/HashMap;
L3129:  ldc_w "t"
L3132:  iconst_4
L3133:  iconst_1
L3134:  dup
L3135:  pop2
L3136:  invokestatic Method java/lang/Integer valueOf (I)Ljava/lang/Integer;
L3139:  invokevirtual Method java/util/HashMap put [_163]
L3142:  getstatic Field JB B Ljava/util/HashMap;
L3145:  ldc_w "u"
L3148:  bipush 10
L3150:  iconst_1
L3151:  dup
L3152:  pop2
L3153:  invokestatic Method java/lang/Integer valueOf (I)Ljava/lang/Integer;
L3156:  invokevirtual Method java/util/HashMap put [_163]
L3159:  getstatic Field JB B Ljava/util/HashMap;
L3162:  ldc_w "v"
L3165:  iconst_1
L3166:  dup
L3167:  dup
L3168:  pop2
L3169:  invokestatic Method java/lang/Integer valueOf (I)Ljava/lang/Integer;
L3172:  invokevirtual Method java/util/HashMap put [_163]
L3175:  getstatic Field JB B Ljava/util/HashMap;
L3178:  ldc_w "w"
L3181:  iconst_0
L3182:  iconst_1
L3183:  dup
L3184:  pop2
L3185:  invokestatic Method java/lang/Integer valueOf (I)Ljava/lang/Integer;
L3188:  invokevirtual Method java/util/HashMap put [_163]
L3191:  getstatic Field JB B Ljava/util/HashMap;
L3194:  ldc_w "twpm"
L3197:  iconst_0
L3198:  iconst_1
L3199:  dup
L3200:  pop2
L3201:  invokestatic Method java/lang/Integer valueOf (I)Ljava/lang/Integer;
L3204:  invokevirtual Method java/util/HashMap put [_163]
L3207:  getstatic Field JB B Ljava/util/HashMap;
L3210:  ldc_w "rm"
L3213:  iconst_0
L3214:  iconst_1
L3215:  dup
L3216:  pop2
L3217:  invokestatic Method java/lang/Integer valueOf (I)Ljava/lang/Integer;
L3220:  invokevirtual Method java/util/HashMap put [_163]
L3223:  getstatic Field JB B Ljava/util/HashMap;
L3226:  ldc_w "rmte"
L3229:  iconst_0
L3230:  iconst_1
L3231:  dup
L3232:  pop2
L3233:  invokestatic Method java/lang/Integer valueOf (I)Ljava/lang/Integer;
L3236:  invokevirtual Method java/util/HashMap put [_163]
L3239:  getstatic Field JB B Ljava/util/HashMap;
L3242:  ldc_w "mphc"
L3245:  iconst_0
L3246:  iconst_1
L3247:  dup
L3248:  pop2
L3249:  invokestatic Method java/lang/Integer valueOf (I)Ljava/lang/Integer;
L3252:  invokevirtual Method java/util/HashMap put [_163]
L3255:  getstatic Field JB B Ljava/util/HashMap;
L3258:  ldc_w "rmrl"
L3261:  iconst_m1
L3262:  iconst_1
L3263:  dup
L3264:  pop2
L3265:  invokestatic Method java/lang/Integer valueOf (I)Ljava/lang/Integer;
L3268:  invokevirtual Method java/util/HashMap put [_163]
L3271:  getstatic Field JB B Ljava/util/HashMap;
L3274:  ldc_w "rmsl"
L3277:  ldc_w 2147483647
L3280:  invokestatic Method java/lang/Integer valueOf (I)Ljava/lang/Integer;
L3283:  invokevirtual Method java/util/HashMap put [_163]
L3286:  getstatic Field JB B Ljava/util/HashMap;
L3289:  ldc_w "load_successful"
L3292:  iconst_1
L3293:  dup
L3294:  dup
L3295:  pop2
L3296:  invokestatic Method java/lang/Integer valueOf (I)Ljava/lang/Integer;
L3299:  invokevirtual Method java/util/HashMap put [_163]
L3302:  getstatic Field JB B Ljava/util/HashMap;
L3305:  ldc_w "dc"
L3308:  iconst_0
L3309:  iconst_1
L3310:  dup
L3311:  pop2
L3312:  invokestatic Method java/lang/Integer valueOf (I)Ljava/lang/Integer;
L3315:  invokevirtual Method java/util/HashMap put [_163]
L3318:  getstatic Field JB B Ljava/util/HashMap;
L3321:  ldc_w "det_sw"
L3324:  iconst_1
L3325:  dup
L3326:  dup
L3327:  pop2
L3328:  invokestatic Method java/lang/Integer valueOf (I)Ljava/lang/Integer;
L3331:  invokevirtual Method java/util/HashMap put [_163]
L3334:  getstatic Field JB field1919 Ljava/util/HashMap;
L3337:  ldc_w "lum"
L3340:  ldc_w "0"
L3343:  invokevirtual Method java/util/HashMap put [_163]
L3346:  getstatic Field JB field1919 Ljava/util/HashMap;
L3349:  ldc_w "upftr"
L3352:  ldc ""
L3354:  invokevirtual Method java/util/HashMap put [_163]
L3357:  getstatic Field JB B Ljava/util/HashMap;
L3360:  ldc_w "uda"
L3363:  iconst_0
L3364:  iconst_1
L3365:  dup
L3366:  pop2
L3367:  invokestatic Method java/lang/Integer valueOf (I)Ljava/lang/Integer;
L3370:  invokevirtual Method java/util/HashMap put [_163]
L3373:  getstatic Field JB B Ljava/util/HashMap;
L3376:  ldc_w "udf"
L3379:  iconst_0
L3380:  iconst_1
L3381:  dup
L3382:  pop2
L3383:  invokestatic Method java/lang/Integer valueOf (I)Ljava/lang/Integer;
L3386:  invokevirtual Method java/util/HashMap put [_163]
L3389:  getstatic Field JB field1919 Ljava/util/HashMap;
L3392:  ldc_w "lmotd"
L3395:  aconst_null
L3396:  invokevirtual Method java/util/HashMap put [_163]
L3399:  pop2
L3400:  pop2
L3401:  pop2
L3402:  pop2
L3403:  pop2
L3404:  pop2
L3405:  pop2
L3406:  pop2
L3407:  pop2
L3408:  pop2
L3409:  pop2
L3410:  return
L3411:  
        .attribute StackMap b'\x00\x0C\x02\x1D\x00\x00\x00\x01\x07\x00\x78\x02\x1E\x00\x00\x00\x01\x07\x00\x7A\x02\x23\x00\x00\x00\x00\x02\x4C\x00\x01\x07\x01\x41\x00\x01\x07\x01\x41\x02\xCA\x00\x00\x00\x01\x07\x00\x78\x02\xCB\x00\x01\x07\x01\x41\x00\x00\x02\xDA\x00\x01\x07\x01\x41\x00\x01\x07\x01\x41\x03\x58\x00\x01\x07\x01\x41\x00\x00\x03\x8F\x00\x01\x07\x01\x41\x00\x00\x03\xB9\x00\x01\x07\x01\x41\x00\x00\x06\x2E\x00\x03\x07\x01\xAC\x01\x01\x00\x01\x01\x0B\xAA\x00\x03\x07\x01\xAC\x01\x01\x00\x00'
    .end code
.end method

.method public <init> : ()V
    .code stack 1 locals 1
L0:     aload_0
L1:     invokespecial Method java/lang/Object <init> ()V
L4:     return
L5:     
    .end code
.end method

.method private static method834 : ()Ljava/lang/String;
    .code stack 3 locals 0
L0:     new java/lang/StringBuilder
L3:     dup
L4:     invokespecial Method java/lang/StringBuilder <init> ()V
L7:     iconst_0
L8:     ldc_w "os.name"
L11:    invokestatic Method java/lang/System getProperty (Ljava/lang/String;)Ljava/lang/String;
L14:    invokevirtual Method java/lang/StringBuilder insert (ILjava/lang/String;)Ljava/lang/StringBuilder;
L17:    ldc_w "|"
L20:    invokevirtual Method java/lang/StringBuilder append (Ljava/lang/String;)Ljava/lang/StringBuilder;
L23:    ldc_w "os.arch"
L26:    invokestatic Method java/lang/System getProperty (Ljava/lang/String;)Ljava/lang/String;
L29:    invokevirtual Method java/lang/StringBuilder append (Ljava/lang/String;)Ljava/lang/StringBuilder;
L32:    ldc_w "|"
L35:    invokevirtual Method java/lang/StringBuilder append (Ljava/lang/String;)Ljava/lang/StringBuilder;
L38:    ldc_w "user.name"
L41:    invokestatic Method java/lang/System getProperty (Ljava/lang/String;)Ljava/lang/String;
L44:    invokevirtual Method java/lang/StringBuilder append (Ljava/lang/String;)Ljava/lang/StringBuilder;
L47:    ldc_w "|"
L50:    invokevirtual Method java/lang/StringBuilder append (Ljava/lang/String;)Ljava/lang/StringBuilder;
L53:    ldc_w "user.home"
L56:    invokestatic Method java/lang/System getProperty (Ljava/lang/String;)Ljava/lang/String;
L59:    invokevirtual Method java/lang/StringBuilder append (Ljava/lang/String;)Ljava/lang/StringBuilder;
L62:    ldc_w "|"
L65:    invokevirtual Method java/lang/StringBuilder append (Ljava/lang/String;)Ljava/lang/StringBuilder;
L68:    ldc_w "COMPUTERNAME"
L71:    invokestatic Method java/lang/System getenv (Ljava/lang/String;)Ljava/lang/String;
L74:    invokevirtual Method java/lang/StringBuilder append (Ljava/lang/String;)Ljava/lang/StringBuilder;
L77:    ldc_w "|"
L80:    invokevirtual Method java/lang/StringBuilder append (Ljava/lang/String;)Ljava/lang/StringBuilder;
L83:    invokestatic Method java/lang/Runtime getRuntime ()Ljava/lang/Runtime;
L86:    invokevirtual Method java/lang/Runtime availableProcessors ()I
L89:    invokevirtual Method java/lang/StringBuilder append (I)Ljava/lang/StringBuilder;
L92:    ldc_w "|"
L95:    invokevirtual Method java/lang/StringBuilder append (Ljava/lang/String;)Ljava/lang/StringBuilder;
L98:    ldc_w "PROCESSOR_IDENTIFIER"
L101:   invokestatic Method java/lang/System getenv (Ljava/lang/String;)Ljava/lang/String;
L104:   invokevirtual Method java/lang/StringBuilder append (Ljava/lang/String;)Ljava/lang/StringBuilder;
L107:   ldc_w "|"
L110:   invokevirtual Method java/lang/StringBuilder append (Ljava/lang/String;)Ljava/lang/StringBuilder;
L113:   ldc_w "PROCESSOR_LEVEL"
L116:   invokestatic Method java/lang/System getenv (Ljava/lang/String;)Ljava/lang/String;
L119:   invokevirtual Method java/lang/StringBuilder append (Ljava/lang/String;)Ljava/lang/StringBuilder;
L122:   ldc_w "|"
L125:   invokevirtual Method java/lang/StringBuilder append (Ljava/lang/String;)Ljava/lang/StringBuilder;
L128:   ldc_w "USERDOMAIN"
L131:   invokestatic Method java/lang/System getenv (Ljava/lang/String;)Ljava/lang/String;
L134:   invokevirtual Method java/lang/StringBuilder append (Ljava/lang/String;)Ljava/lang/StringBuilder;
L137:   invokevirtual Method java/lang/StringBuilder toString ()Ljava/lang/String;
L140:   areturn
L141:   
    .end code
.end method

.method public static method835 : (Ljava/lang/String;Ljava/lang/String;)V
    .code stack 4 locals 2
L0:     aload_0
L1:     aload_1
L2:     invokestatic Method JB method832 (Ljava/lang/String;Ljava/lang/String;)Z
L5:     ifeq L10
L8:     return
L9:     athrow
L10:    aload_0
L11:    new java/lang/StringBuilder
L14:    dup
L15:    invokespecial Method java/lang/StringBuilder <init> ()V
L18:    iconst_0
L19:    aload_0
L20:    invokestatic Method JB method822 (Ljava/lang/String;)Ljava/lang/String;
L23:    invokevirtual Method java/lang/StringBuilder insert (ILjava/lang/String;)Ljava/lang/StringBuilder;
L26:    aload_1
L27:    invokevirtual Method java/lang/StringBuilder append (Ljava/lang/String;)Ljava/lang/StringBuilder;
L30:    ldc_w "|"
L33:    invokevirtual Method java/lang/StringBuilder append (Ljava/lang/String;)Ljava/lang/StringBuilder;
L36:    invokevirtual Method java/lang/StringBuilder toString ()Ljava/lang/String;
L39:    invokestatic Method JB method826 (Ljava/lang/String;Ljava/lang/String;)V
L42:    return
L43:    
        .attribute StackMap b'\x00\x02\x00\x09\x00\x00\x00\x01\x07\x00\x78\x00\x0A\x00\x02\x07\x00\x72\x07\x00\x72\x00\x00'
    .end code
.end method

.method public static method836 : ()V
    .code stack 2 locals 0
L0:     ldc_w "lum"
L3:     ldc_w "0"
L6:     invokestatic Method JB method826 (Ljava/lang/String;Ljava/lang/String;)V
L9:     return
L10:    
    .end code
.end method

.method public static method837 : ()Z
    .code stack 6 locals 2
L0:     ldc_w "lum"
L3:     invokestatic Method JB method822 (Ljava/lang/String;)Ljava/lang/String;
L6:     invokestatic Method java/lang/Long parseLong (Ljava/lang/String;)J
L9:     lstore_0
L10:    invokestatic Method java/lang/System currentTimeMillis ()J
L13:    lload_0
L14:    ldc2_w 604800000L
L17:    ladd
L18:    lcmp
L19:    ifle L28
L22:    iconst_1
L23:    dup
L24:    dup
L25:    pop2
L26:    ireturn
L27:    athrow
L28:    iconst_0
L29:    iconst_1
L30:    dup
L31:    pop2
L32:    ireturn
L33:    
        .attribute StackMap b'\x00\x02\x00\x1B\x00\x00\x00\x01\x07\x00\x78\x00\x1C\x00\x01\x04\x00\x00'
    .end code
.end method
.innerclasses
    Pc JB [0] public static final enum
    m JB [0] public static interface abstract
.end innerclasses
.const [_163] = Utf8 (Ljava/lang/Object;Ljava/lang/Object;)Ljava/lang/Object;
.end class
