.version 49 0
.class public final super jb
.super RC
.field public field855 I
.field private field856 LuC;
.field private field857 LM;

.method public method395 : (LD;)V
    .code stack 7 locals 10
L0:     aload_1
L1:     instanceof rd
L4:     ifeq L159
L7:     aload_1
L8:     checkcast rd
L11:    astore_2
L12:    aload_0
L13:    getfield Field jb field856 LuC;
L16:    aload_2
L17:    getfield Field rd field859 I
L20:    invokevirtual Method uC method5816 (I)LK;
L23:    dup
L24:    astore_3
L25:    ifnull L1524
L28:    aload_2
L29:    getfield Field rd this LKD;
L32:    getstatic Field KD this LKD;
L35:    if_acmpne L146
L38:    aload_0
L39:    getfield Field jb new Ljava/util/LinkedHashMap;
L42:    aload_2
L43:    getfield Field rd field860 Led;
L46:    invokevirtual Method java/util/LinkedHashMap containsKey (Ljava/lang/Object;)Z
L49:    ifeq L60
L52:    getstatic Field java/lang/System out Ljava/io/PrintStream;
L55:    ldc "Something's fishy here. Joining player is already in room."
L57:    invokevirtual Method java/io/PrintStream println (Ljava/lang/String;)V
L60:    new java/util/LinkedList
L63:    dup
L64:    getstatic Field xF field5850 Ljava/util/List;
L67:    invokespecial Method java/util/LinkedList <init> (Ljava/util/Collection;)V
L70:    dup
L71:    astore 4
L73:    aload_2
L74:    dup_x1
L75:    getfield Field rd field860 Led;
L78:    getfield Field ed field704 Ljava/util/Set;
L81:    invokeinterface InterfaceMethod java/util/List removeAll (Ljava/util/Collection;)Z 2
L86:    pop
L87:    getfield Field rd field860 Led;
L90:    invokevirtual Method ed method94 ()Z
L93:    ifeq L103
L96:    aload 4
L98:    invokeinterface InterfaceMethod java/util/List clear ()V 1
L103:   new oF
L106:   dup
L107:   aload_2
L108:   getfield Field rd field860 Led;
L111:   aload_0
L112:   aload 4
L114:   getstatic Field qE try LqE;
L117:   invokespecial Method oF <init> (Led;Lqd;Ljava/util/List;LqE;)V
L120:   astore 5
L122:   aload_0
L123:   getfield Field jb new Ljava/util/LinkedHashMap;
L126:   aload_2
L127:   getfield Field rd field860 Led;
L130:   aload 5
L132:   invokevirtual Method java/util/LinkedHashMap put (Ljava/lang/Object;Ljava/lang/Object;)Ljava/lang/Object;
L135:   aload_3
L136:   aload 5
L138:   invokeinterface InterfaceMethod K method734 (Ljava/lang/Object;)V 2
L143:   pop
L144:   return
L145:   athrow
L146:   aload_3
L147:   aconst_null
L148:   aload_2
L149:   getfield Field rd this LKD;
L152:   invokeinterface InterfaceMethod K method735 (Ljava/lang/Object;LKD;)V 3
L157:   return
L158:   athrow
L159:   aload_1
L160:   instanceof Yc
L163:   ifeq L227
L166:   aload_1
L167:   checkcast Yc
L170:   astore_2
L171:   aload_0
L172:   getfield Field jb field856 LuC;
L175:   aload_2
L176:   getfield Field Yc field727 I
L179:   invokevirtual Method uC method5816 (I)LK;
L182:   dup
L183:   astore_3
L184:   ifnull L1524
L187:   aload_2
L188:   getfield Field Yc field728 LKD;
L191:   getstatic Field KD this LKD;
L194:   if_acmpne L215
L197:   aload_3
L198:   aload_0
L199:   getfield Field jb new Ljava/util/LinkedHashMap;
L202:   aload_2
L203:   getfield Field Yc field729 Led;
L206:   invokevirtual Method java/util/LinkedHashMap get (Ljava/lang/Object;)Ljava/lang/Object;
L209:   invokeinterface InterfaceMethod K method734 (Ljava/lang/Object;)V 2
L214:   return
L215:   aload_3
L216:   aconst_null
L217:   aload_2
L218:   getfield Field Yc field728 LKD;
L221:   invokeinterface InterfaceMethod K method735 (Ljava/lang/Object;LKD;)V 3
L226:   return
L227:   aload_1
L228:   instanceof pc
L231:   ifeq L300
L234:   aload_1
L235:   checkcast pc
L238:   astore_2
L239:   aload_0
L240:   getfield Field jb new Ljava/util/LinkedHashMap;
L243:   aload_2
L244:   getfield Field pc field943 Led;
L247:   invokevirtual Method java/util/LinkedHashMap containsKey (Ljava/lang/Object;)Z
L250:   ifne L280
L253:   aload_0
L254:   getfield Field jb new Ljava/util/LinkedHashMap;
L257:   aload_2
L258:   getfield Field pc field943 Led;
L261:   new Mg
L264:   dup
L265:   aload_2
L266:   getfield Field pc field943 Led;
L269:   aload_0
L270:   getstatic Field qE try LqE;
L273:   invokespecial Method Mg <init> (Led;Lqd;LqE;)V
L276:   invokevirtual Method java/util/LinkedHashMap put (Ljava/lang/Object;Ljava/lang/Object;)Ljava/lang/Object;
L279:   pop
L280:   aload_0
L281:   dup
L282:   aload_2
L283:   invokevirtual Method jb method8 (LD;)V
L286:   getfield Field jb field857 LM;
L289:   ifnull L1524
L292:   aload_0
L293:   getfield Field jb field857 LM;
L296:   invokestatic Method ib method1156 (LM;)V
L299:   return
L300:   aload_1
L301:   instanceof gC
L304:   ifeq L473
L307:   aload_1
L308:   checkcast gC
L311:   astore_2
L312:   aload_0
L313:   getfield Field jb new Ljava/util/LinkedHashMap;
L316:   aload_2
L317:   getfield Field gC field872 Led;
L320:   invokevirtual Method java/util/LinkedHashMap remove (Ljava/lang/Object;)Ljava/lang/Object;
L323:   checkcast Rg
L326:   dup
L327:   astore_3
L328:   aload_0
L329:   aload_1
L330:   invokevirtual Method jb method8 (LD;)V
L333:   instanceof oF
L336:   ifne L346
L339:   aload_3
L340:   instanceof ae
L343:   ifeq L1524
L346:   iconst_0
L347:   iconst_1
L348:   dup
L349:   pop2
L350:   istore 4
L352:   aload_0
L353:   getfield Field jb new Ljava/util/LinkedHashMap;
L356:   invokevirtual Method java/util/LinkedHashMap values ()Ljava/util/Collection;
L359:   invokeinterface InterfaceMethod java/util/Collection iterator ()Ljava/util/Iterator; 1
L364:   astore 5
L366:   aload 5
L368:   invokeinterface InterfaceMethod java/util/Iterator hasNext ()Z 1
L373:   ifeq L401
L376:   aload 5
L378:   invokeinterface InterfaceMethod java/util/Iterator next ()Ljava/lang/Object; 1
L383:   checkcast Rg
L386:   dup
L387:   astore 6
L389:   instanceof Mg
L392:   ifeq L366
L395:   iinc 4 1
L398:   goto L366
L401:   iload 4
L403:   aload_0
L404:   getfield Field jb new Ljava/util/LinkedHashMap;
L407:   invokevirtual Method java/util/LinkedHashMap size ()I
L410:   if_icmpne L1524
L413:   aload_0
L414:   getfield Field jb new Ljava/util/LinkedHashMap;
L417:   invokevirtual Method java/util/LinkedHashMap values ()Ljava/util/Collection;
L420:   invokeinterface InterfaceMethod java/util/Collection iterator ()Ljava/util/Iterator; 1
L425:   dup
L426:   astore 5
L428:   invokeinterface InterfaceMethod java/util/Iterator hasNext ()Z 1
L433:   ifeq L458
L436:   aload 5
L438:   invokeinterface InterfaceMethod java/util/Iterator next ()Ljava/lang/Object; 1
L443:   checkcast Rg
L446:   astore 6
L448:   aload 5
L450:   aload 6
L452:   invokevirtual Method Rg method52 ()V
L455:   goto L428
L458:   aload_0
L459:   getfield Field jb field857 LM;
L462:   ifnull L1524
L465:   aload_0
L466:   getfield Field jb field857 LM;
L469:   invokestatic Method ib method1153 (LM;)V
L472:   return
L473:   aload_1
L474:   instanceof Ad
L477:   ifeq L695
L480:   aload_1
L481:   checkcast Ad
L484:   astore_2
L485:   aconst_null
L486:   astore_3
        .catch java/lang/Exception from L487 to L498 using L502
L487:   getstatic Field Kc field1931 LKc;
L490:   aload_2
L491:   getfield Field Ad field882 I
L494:   invokevirtual Method Kc method856 (I)Led;
L497:   astore_3
L498:   aload_3
L499:   goto L623
L502:   astore 4
L504:   aload_0
L505:   getfield Field jb new Ljava/util/LinkedHashMap;
L508:   invokevirtual Method java/util/LinkedHashMap keySet ()Ljava/util/Set;
L511:   invokeinterface InterfaceMethod java/util/Set iterator ()Ljava/util/Iterator; 1
L516:   astore 5
L518:   aload 5
L520:   invokeinterface InterfaceMethod java/util/Iterator hasNext ()Z 1
L525:   ifeq L557
L528:   aload 5
L530:   invokeinterface InterfaceMethod java/util/Iterator next ()Ljava/lang/Object; 1
L535:   checkcast ed
L538:   dup
L539:   astore 6
L541:   getfield Field ed try I
L544:   aload_2
L545:   getfield Field Ad field882 I
L548:   if_icmpne L518
L551:   aload 6
L553:   astore_3
L554:   goto L518
L557:   aload_3
L558:   ifnonnull L622
L561:   aload_0
L562:   getfield Field jb field766 Ljava/util/Map;
L565:   invokeinterface InterfaceMethod java/util/Map keySet ()Ljava/util/Set; 1
L570:   invokeinterface InterfaceMethod java/util/Set iterator ()Ljava/util/Iterator; 1
L575:   astore 5
L577:   aload 5
L579:   invokeinterface InterfaceMethod java/util/Iterator hasNext ()Z 1
L584:   ifeq L622
L587:   aload 5
L589:   invokeinterface InterfaceMethod java/util/Iterator next ()Ljava/lang/Object; 1
L594:   checkcast Rg
L597:   dup
L598:   astore 6
L600:   getfield Field Rg false Led;
L603:   getfield Field ed try I
L606:   aload_2
L607:   getfield Field Ad field882 I
L610:   if_icmpne L577
L613:   aload 6
L615:   getfield Field Rg false Led;
L618:   astore_3
L619:   goto L577
L622:   aload_3
L623:   ifnull L664
L626:   aload_0
L627:   getfield Field jb new Ljava/util/LinkedHashMap;
L630:   aload_3
L631:   invokevirtual Method java/util/LinkedHashMap containsKey (Ljava/lang/Object;)Z
L634:   ifeq L664
L637:   aload_0
L638:   dup
L639:   getfield Field jb field766 Ljava/util/Map;
L642:   swap
L643:   getfield Field jb new Ljava/util/LinkedHashMap;
L646:   aload_3
L647:   invokevirtual Method java/util/LinkedHashMap get (Ljava/lang/Object;)Ljava/lang/Object;
L650:   aload_2
L651:   getfield Field Ad field883 I
L654:   invokestatic Method java/lang/Integer valueOf (I)Ljava/lang/Integer;
L657:   invokeinterface InterfaceMethod java/util/Map put (Ljava/lang/Object;Ljava/lang/Object;)Ljava/lang/Object; 3
L662:   pop
L663:   return
L664:   getstatic Field java/lang/System out Ljava/io/PrintStream;
L667:   new java/lang/StringBuilder
L670:   dup
L671:   invokespecial Method java/lang/StringBuilder <init> ()V
L674:   iconst_0
L675:   ldc_w "RoomRankChanged: Cannot locate player #"
L678:   invokevirtual Method java/lang/StringBuilder insert (ILjava/lang/String;)Ljava/lang/StringBuilder;
L681:   aload_2
L682:   getfield Field Ad field882 I
L685:   invokevirtual Method java/lang/StringBuilder append (I)Ljava/lang/StringBuilder;
L688:   invokevirtual Method java/lang/StringBuilder toString ()Ljava/lang/String;
L691:   invokevirtual Method java/io/PrintStream println (Ljava/lang/String;)V
L694:   return
L695:   aload_1
L696:   instanceof ag
L699:   ifeq L746
L702:   aload_1
L703:   checkcast ag
L706:   astore_2
L707:   aload_0
L708:   getfield Field jb field760 Ljava/util/LinkedHashMap;
L711:   aload_2
L712:   getfield Field ag field720 Led;
L715:   invokevirtual Method java/util/LinkedHashMap containsKey (Ljava/lang/Object;)Z
L718:   ifne L740
L721:   aload_0
L722:   getfield Field jb field760 Ljava/util/LinkedHashMap;
L725:   aload_2
L726:   getfield Field ag field720 Led;
L729:   iconst_0
L730:   iconst_1
L731:   dup
L732:   pop2
L733:   invokestatic Method java/lang/Integer valueOf (I)Ljava/lang/Integer;
L736:   invokevirtual Method java/util/LinkedHashMap put (Ljava/lang/Object;Ljava/lang/Object;)Ljava/lang/Object;
L739:   pop
L740:   aload_0
L741:   aload_1
L742:   invokevirtual Method jb method8 (LD;)V
L745:   return
L746:   aload_1
L747:   instanceof fc
L750:   ifeq L1054
L753:   aload_1
L754:   checkcast fc
L757:   dup
L758:   astore_2
L759:   getfield Field fc field874 Led;
L762:   aload_0
L763:   invokestatic Method Ob method1020 (Led;Lqd;)Z
L766:   ifeq L1524
L769:   getstatic Field nD field2392 [I
L772:   aload_2
L773:   getfield Field fc field876 Loc;
L776:   invokevirtual Method oc ordinal ()I
L779:   iaload
L780:   tableswitch 1
            L836
            L839
            L855
            L867
            L887
            L899
            L902
            L1013
            L1048
            L1048
            default : L1048
L836:   goto L1048
L839:   aload_0
L840:   iconst_0
L841:   ifne L1045
L844:   dup
L845:   iconst_0
L846:   iconst_1
L847:   dup
L848:   pop2
L849:   putfield Field jb field767 Z
L852:   goto L1049
L855:   aload_0
L856:   dup
L857:   iconst_1
L858:   dup
L859:   dup
L860:   pop2
L861:   putfield Field jb field767 Z
L864:   goto L1049
L867:   aload_0
L868:   iconst_0
L869:   aload_0
L870:   dup_x1
L871:   iconst_1
L872:   dup
L873:   dup
L874:   pop2
L875:   putfield Field jb field754 Z
L878:   iconst_1
L879:   dup
L880:   pop2
L881:   putfield Field jb field746 Z
L884:   goto L1049
L887:   aload_0
L888:   dup
L889:   iconst_0
L890:   iconst_1
L891:   dup
L892:   pop2
L893:   putfield Field jb field754 Z
L896:   goto L1049
L899:   goto L1048
L902:   aload_0
L903:   getfield Field jb field760 Ljava/util/LinkedHashMap;
L906:   invokevirtual Method java/util/LinkedHashMap keySet ()Ljava/util/Set;
L909:   invokeinterface InterfaceMethod java/util/Set iterator ()Ljava/util/Iterator; 1
L914:   dup
L915:   astore_3
L916:   invokeinterface InterfaceMethod java/util/Iterator hasNext ()Z 1
L921:   ifeq L956
L924:   aload_3
L925:   invokeinterface InterfaceMethod java/util/Iterator next ()Ljava/lang/Object; 1
L930:   checkcast ed
L933:   astore 4
L935:   aload_3
L936:   aload_0
L937:   getfield Field jb field760 Ljava/util/LinkedHashMap;
L940:   aload 4
L942:   iconst_0
L943:   iconst_1
L944:   dup
L945:   pop2
L946:   invokestatic Method java/lang/Integer valueOf (I)Ljava/lang/Integer;
L949:   invokevirtual Method java/util/LinkedHashMap put (Ljava/lang/Object;Ljava/lang/Object;)Ljava/lang/Object;
L952:   pop
L953:   goto L916
L956:   aload_0
L957:   getfield Field jb field744 Ljava/util/LinkedHashMap;
L960:   invokevirtual Method java/util/LinkedHashMap keySet ()Ljava/util/Set;
L963:   invokeinterface InterfaceMethod java/util/Set iterator ()Ljava/util/Iterator; 1
L968:   dup
L969:   astore_3
L970:   invokeinterface InterfaceMethod java/util/Iterator hasNext ()Z 1
L975:   ifeq L1048
L978:   aload_3
L979:   invokeinterface InterfaceMethod java/util/Iterator next ()Ljava/lang/Object; 1
L984:   checkcast sE
L987:   astore 4
L989:   aload_3
L990:   aload_0
L991:   getfield Field jb field744 Ljava/util/LinkedHashMap;
L994:   aload 4
L996:   iconst_0
L997:   iconst_1
L998:   dup
L999:   pop2
L1000:  invokestatic Method java/lang/Integer valueOf (I)Ljava/lang/Integer;
L1003:  invokevirtual Method java/util/LinkedHashMap put (Ljava/lang/Object;Ljava/lang/Object;)Ljava/lang/Object;
L1006:  pop
L1007:  goto L970
L1010:  nop
L1011:  nop
L1012:  athrow
L1013:  aload_0
L1014:  getfield Field jb field763 LQB;
L1017:  getstatic Field QB field367 LQB;
L1020:  if_acmpeq L1033
L1023:  aload_0
L1024:  getfield Field jb field763 LQB;
L1027:  getstatic Field QB field366 LQB;
L1030:  if_acmpne L1048
L1033:  aload_0
L1034:  dup
L1035:  iconst_1
L1036:  dup
L1037:  dup
L1038:  pop2
L1039:  putfield Field jb field746 Z
L1042:  goto L1049
L1045:  goto L840
L1048:  aload_0
L1049:  aload_1
L1050:  invokevirtual Method jb method8 (LD;)V
L1053:  return
L1054:  aload_1
L1055:  instanceof xC
L1058:  ifeq L1463
L1061:  aload_1
L1062:  checkcast xC
L1065:  astore_2
L1066:  aload_0
L1067:  aload_2
L1068:  getfield Field xC field888 LQB;
L1071:  putfield Field jb field763 LQB;
L1074:  getstatic Field nD field2391 [I
L1077:  aload_0
L1078:  getfield Field jb field763 LQB;
L1081:  invokevirtual Method QB ordinal ()I
L1084:  iaload
L1085:  tableswitch 1
            L1116
            L1144
            L1147
            L1453
            default : L1457
L1116:  aload_0
L1117:  iconst_0
L1118:  ifne L1450
L1121:  dup
L1122:  dup2
L1123:  aload_2
L1124:  getfield Field xC field889 J
L1127:  putfield Field jb field756 J
L1130:  getfield Field jb field766 Ljava/util/Map;
L1133:  invokeinterface InterfaceMethod java/util/Map clear ()V 1
L1138:  invokevirtual Method jb method52 ()V
L1141:  goto L1458
L1144:  goto L1457
L1147:  aload_0
L1148:  dup
L1149:  getfield Field jb field766 Ljava/util/Map;
L1152:  astore_3
L1153:  new java/util/LinkedHashMap
L1156:  aload_0
L1157:  dup
L1158:  pop2
L1159:  dup
L1160:  invokespecial Method java/util/LinkedHashMap <init> ()V
L1163:  putfield Field jb field766 Ljava/util/Map;
L1166:  aload_2
L1167:  getfield Field xC field887 Ljava/util/Map;
L1170:  invokeinterface InterfaceMethod java/util/Map entrySet ()Ljava/util/Set; 1
L1175:  invokeinterface InterfaceMethod java/util/Set iterator ()Ljava/util/Iterator; 1
L1180:  astore 4
L1182:  aload 4
L1184:  invokeinterface InterfaceMethod java/util/Iterator hasNext ()Z 1
L1189:  ifeq L1430
L1192:  aload 4
L1194:  invokeinterface InterfaceMethod java/util/Iterator next ()Ljava/lang/Object; 1
L1199:  checkcast java/util/Map$Entry
L1202:  dup
L1203:  astore 5
L1205:  invokeinterface InterfaceMethod java/util/Map$Entry getKey ()Ljava/lang/Object; 1
L1210:  checkcast java/lang/Integer
L1213:  invokevirtual Method java/lang/Integer intValue ()I
L1216:  istore 6
L1218:  aconst_null
L1219:  astore 7
        .catch java/lang/Exception from L1221 to L1231 using L1236
L1221:  getstatic Field Kc field1931 LKc;
L1224:  iload 6
L1226:  invokevirtual Method Kc method856 (I)Led;
L1229:  astore 7
L1231:  aload 7
L1233:  goto L1354
L1236:  astore 8
L1238:  aload_0
L1239:  getfield Field jb new Ljava/util/LinkedHashMap;
L1242:  invokevirtual Method java/util/LinkedHashMap keySet ()Ljava/util/Set;
L1245:  invokeinterface InterfaceMethod java/util/Set iterator ()Ljava/util/Iterator; 1
L1250:  astore 8
L1252:  aload 8
L1254:  invokeinterface InterfaceMethod java/util/Iterator hasNext ()Z 1
L1259:  ifeq L1290
L1262:  aload 8
L1264:  invokeinterface InterfaceMethod java/util/Iterator next ()Ljava/lang/Object; 1
L1269:  checkcast ed
L1272:  dup
L1273:  astore 9
L1275:  getfield Field ed try I
L1278:  iload 6
L1280:  if_icmpne L1252
L1283:  aload 9
L1285:  astore 7
L1287:  goto L1252
L1290:  aload 7
L1292:  ifnonnull L1352
L1295:  aload_3
L1296:  invokeinterface InterfaceMethod java/util/Map keySet ()Ljava/util/Set; 1
L1301:  invokeinterface InterfaceMethod java/util/Set iterator ()Ljava/util/Iterator; 1
L1306:  astore 8
L1308:  aload 8
L1310:  invokeinterface InterfaceMethod java/util/Iterator hasNext ()Z 1
L1315:  ifeq L1352
L1318:  aload 8
L1320:  invokeinterface InterfaceMethod java/util/Iterator next ()Ljava/lang/Object; 1
L1325:  checkcast Rg
L1328:  dup
L1329:  astore 9
L1331:  getfield Field Rg false Led;
L1334:  getfield Field ed try I
L1337:  iload 6
L1339:  if_icmpne L1308
L1342:  aload 9
L1344:  getfield Field Rg false Led;
L1347:  astore 7
L1349:  goto L1308
L1352:  aload 7
L1354:  ifnull L1399
L1357:  aload_0
L1358:  getfield Field jb new Ljava/util/LinkedHashMap;
L1361:  aload 7
L1363:  invokevirtual Method java/util/LinkedHashMap containsKey (Ljava/lang/Object;)Z
L1366:  ifeq L1399
L1369:  aload_0
L1370:  dup
L1371:  getfield Field jb field766 Ljava/util/Map;
L1374:  swap
L1375:  getfield Field jb new Ljava/util/LinkedHashMap;
L1378:  aload 7
L1380:  invokevirtual Method java/util/LinkedHashMap get (Ljava/lang/Object;)Ljava/lang/Object;
L1383:  aload 5
L1385:  invokeinterface InterfaceMethod java/util/Map$Entry getValue ()Ljava/lang/Object; 1
L1390:  invokeinterface InterfaceMethod java/util/Map put (Ljava/lang/Object;Ljava/lang/Object;)Ljava/lang/Object; 3
L1395:  pop
L1396:  goto L1182
L1399:  getstatic Field java/lang/System out Ljava/io/PrintStream;
L1402:  new java/lang/StringBuilder
L1405:  dup
L1406:  invokespecial Method java/lang/StringBuilder <init> ()V
L1409:  iconst_0
L1410:  ldc_w "RoomStateChanged/GAME_OVER: Cannot locate player #"
L1413:  invokevirtual Method java/lang/StringBuilder insert (ILjava/lang/String;)Ljava/lang/StringBuilder;
L1416:  iload 6
L1418:  invokevirtual Method java/lang/StringBuilder append (I)Ljava/lang/StringBuilder;
L1421:  invokevirtual Method java/lang/StringBuilder toString ()Ljava/lang/String;
L1424:  invokevirtual Method java/io/PrintStream println (Ljava/lang/String;)V
L1427:  goto L1182
L1430:  aload_0
L1431:  aload_2
L1432:  aload_0
L1433:  dup_x1
L1434:  aload_2
L1435:  getfield Field xC this Ljava/util/LinkedHashMap;
L1438:  putfield Field jb field760 Ljava/util/LinkedHashMap;
L1441:  getfield Field xC field886 Ljava/util/LinkedHashMap;
L1444:  putfield Field jb field744 Ljava/util/LinkedHashMap;
L1447:  goto L1458
L1450:  goto L1117
L1453:  aload_0
L1454:  invokevirtual Method jb method52 ()V
L1457:  aload_0
L1458:  aload_1
L1459:  invokevirtual Method jb method8 (LD;)V
L1462:  return
L1463:  aload_1
L1464:  instanceof tc
L1467:  ifeq L1519
L1470:  aload_0
L1471:  getfield Field jb new Ljava/util/LinkedHashMap;
L1474:  invokevirtual Method java/util/LinkedHashMap values ()Ljava/util/Collection;
L1477:  invokeinterface InterfaceMethod java/util/Collection iterator ()Ljava/util/Iterator; 1
L1482:  dup
L1483:  astore_2
L1484:  invokeinterface InterfaceMethod java/util/Iterator hasNext ()Z 1
L1489:  ifeq L1513
L1492:  aload_2
L1493:  invokeinterface InterfaceMethod java/util/Iterator next ()Ljava/lang/Object; 1
L1498:  checkcast Rg
L1501:  astore_3
L1502:  aload_2
L1503:  aload_3
L1504:  getstatic Field qE new LqE;
L1507:  invokevirtual Method Rg method226 (LqE;)V
L1510:  goto L1484
L1513:  aload_0
L1514:  aload_1
L1515:  invokevirtual Method jb method8 (LD;)V
L1518:  return
L1519:  aload_0
L1520:  aload_1
L1521:  invokevirtual Method jb method8 (LD;)V
L1524:  return
L1525:  
        .attribute StackMap b'\x00\x42\x00\x3C\x00\x04\x07\x00\x02\x07\x00\x57\x07\x00\x29\x07\x00\x08\x00\x00\x00\x67\x00\x05\x07\x00\x02\x07\x00\x57\x07\x00\x29\x07\x00\x08\x07\x00\x59\x00\x00\x00\x91\x00\x00\x00\x01\x07\x00\x8C\x00\x92\x00\x04\x07\x00\x02\x07\x00\x57\x07\x00\x29\x07\x00\x08\x00\x00\x00\x9E\x00\x00\x00\x01\x07\x00\x8C\x00\x9F\x00\x02\x07\x00\x02\x07\x00\x57\x00\x00\x00\xD7\x00\x04\x07\x00\x02\x07\x00\x57\x07\x00\x92\x07\x00\x08\x00\x00\x00\xE3\x00\x02\x07\x00\x02\x07\x00\x57\x00\x00\x01\x18\x00\x03\x07\x00\x02\x07\x00\x57\x07\x00\xA1\x00\x00\x01\x2C\x00\x02\x07\x00\x02\x07\x00\x57\x00\x00\x01\x5A\x00\x04\x07\x00\x02\x07\x00\x57\x07\x00\xB6\x07\x00\xBE\x00\x00\x01\x6E\x00\x06\x07\x00\x02\x07\x00\x57\x07\x00\xB6\x07\x00\xBE\x01\x07\x00\xCC\x00\x00\x01\x91\x00\x06\x07\x00\x02\x07\x00\x57\x07\x00\xB6\x07\x00\xBE\x01\x07\x00\xCC\x00\x00\x01\xAC\x00\x06\x07\x00\x02\x07\x00\x57\x07\x00\xB6\x07\x00\xBE\x01\x07\x00\xCC\x00\x01\x07\x00\xCC\x01\xCA\x00\x06\x07\x00\x02\x07\x00\x57\x07\x00\xB6\x07\x00\xBE\x01\x07\x00\xCC\x00\x00\x01\xD9\x00\x02\x07\x00\x02\x07\x00\x57\x00\x00\x01\xF6\x00\x04\x07\x00\x02\x07\x00\x57\x07\x00\xDF\x07\x00\x65\x00\x01\x07\x00\x27\x02\x06\x00\x06\x07\x00\x02\x07\x00\x57\x07\x00\xDF\x07\x00\x65\x07\x00\x27\x07\x00\xCC\x00\x00\x02\x2D\x00\x06\x07\x00\x02\x07\x00\x57\x07\x00\xDF\x07\x00\x65\x07\x00\x27\x07\x00\xCC\x00\x00\x02\x41\x00\x06\x07\x00\x02\x07\x00\x57\x07\x00\xDF\x07\x00\x65\x07\x00\x27\x07\x00\xCC\x00\x00\x02\x6E\x00\x06\x07\x00\x02\x07\x00\x57\x07\x00\xDF\x07\x00\x65\x07\x00\x27\x07\x00\xCC\x00\x00\x02\x6F\x00\x04\x07\x00\x02\x07\x00\x57\x07\x00\xDF\x07\x00\x65\x00\x01\x07\x00\x65\x02\x98\x00\x04\x07\x00\x02\x07\x00\x57\x07\x00\xDF\x07\x00\x65\x00\x00\x02\xB7\x00\x02\x07\x00\x02\x07\x00\x57\x00\x00\x02\xE4\x00\x03\x07\x00\x02\x07\x00\x57\x07\x01\x1B\x00\x00\x02\xEA\x00\x02\x07\x00\x02\x07\x00\x57\x00\x00\x03\x44\x00\x03\x07\x00\x02\x07\x00\x57\x07\x00\x19\x00\x00\x03\x47\x00\x03\x07\x00\x02\x07\x00\x57\x07\x00\x19\x00\x00\x03\x48\x00\x03\x07\x00\x02\x07\x00\x57\x07\x00\x19\x00\x01\x07\x00\x02\x03\x57\x00\x03\x07\x00\x02\x07\x00\x57\x07\x00\x19\x00\x00\x03\x63\x00\x03\x07\x00\x02\x07\x00\x57\x07\x00\x19\x00\x00\x03\x77\x00\x03\x07\x00\x02\x07\x00\x57\x07\x00\x19\x00\x00\x03\x83\x00\x03\x07\x00\x02\x07\x00\x57\x07\x00\x19\x00\x00\x03\x86\x00\x03\x07\x00\x02\x07\x00\x57\x07\x00\x19\x00\x00\x03\x94\x00\x04\x07\x00\x02\x07\x00\x57\x07\x00\x19\x07\x00\xCC\x00\x01\x07\x00\xCC\x03\xBC\x00\x04\x07\x00\x02\x07\x00\x57\x07\x00\x19\x07\x00\xCC\x00\x00\x03\xCA\x00\x04\x07\x00\x02\x07\x00\x57\x07\x00\x19\x07\x00\xCC\x00\x01\x07\x00\xCC\x03\xF2\x00\x00\x00\x01\x07\x00\x8C\x03\xF5\x00\x03\x07\x00\x02\x07\x00\x57\x07\x00\x19\x00\x00\x04\x09\x00\x03\x07\x00\x02\x07\x00\x57\x07\x00\x19\x00\x00\x04\x15\x00\x03\x07\x00\x02\x07\x00\x57\x07\x00\x19\x00\x01\x07\x00\x02\x04\x18\x00\x03\x07\x00\x02\x07\x00\x57\x07\x00\x19\x00\x00\x04\x19\x00\x03\x07\x00\x02\x07\x00\x57\x07\x00\x19\x00\x01\x07\x00\x02\x04\x1E\x00\x02\x07\x00\x02\x07\x00\x57\x00\x00\x04\x5C\x00\x03\x07\x00\x02\x07\x00\x57\x07\x01\x50\x00\x00\x04\x5D\x00\x03\x07\x00\x02\x07\x00\x57\x07\x01\x50\x00\x01\x07\x00\x02\x04\x78\x00\x03\x07\x00\x02\x07\x00\x57\x07\x01\x50\x00\x00\x04\x7B\x00\x03\x07\x00\x02\x07\x00\x57\x07\x01\x50\x00\x00\x04\x9E\x00\x05\x07\x00\x02\x07\x00\x57\x07\x01\x50\x07\x00\x12\x07\x00\xCC\x00\x00\x04\xD4\x00\x08\x07\x00\x02\x07\x00\x57\x07\x01\x50\x07\x00\x12\x07\x00\xCC\x07\x00\x10\x01\x07\x00\x65\x00\x01\x07\x00\x27\x04\xE4\x00\x09\x07\x00\x02\x07\x00\x57\x07\x01\x50\x07\x00\x12\x07\x00\xCC\x07\x00\x10\x01\x07\x00\x65\x07\x00\xCC\x00\x00\x05\x0A\x00\x09\x07\x00\x02\x07\x00\x57\x07\x01\x50\x07\x00\x12\x07\x00\xCC\x07\x00\x10\x01\x07\x00\x65\x07\x00\xCC\x00\x00\x05\x1C\x00\x09\x07\x00\x02\x07\x00\x57\x07\x01\x50\x07\x00\x12\x07\x00\xCC\x07\x00\x10\x01\x07\x00\x65\x07\x00\xCC\x00\x00\x05\x48\x00\x09\x07\x00\x02\x07\x00\x57\x07\x01\x50\x07\x00\x12\x07\x00\xCC\x07\x00\x10\x01\x07\x00\x65\x07\x00\xCC\x00\x00\x05\x4A\x00\x08\x07\x00\x02\x07\x00\x57\x07\x01\x50\x07\x00\x12\x07\x00\xCC\x07\x00\x10\x01\x07\x00\x65\x00\x01\x07\x00\x65\x05\x77\x00\x08\x07\x00\x02\x07\x00\x57\x07\x01\x50\x07\x00\x12\x07\x00\xCC\x07\x00\x10\x01\x07\x00\x65\x00\x00\x05\x96\x00\x05\x07\x00\x02\x07\x00\x57\x07\x01\x50\x07\x00\x12\x07\x00\xCC\x00\x00\x05\xAA\x00\x03\x07\x00\x02\x07\x00\x57\x07\x01\x50\x00\x01\x07\x00\x02\x05\xAD\x00\x03\x07\x00\x02\x07\x00\x57\x07\x01\x50\x00\x00\x05\xB1\x00\x03\x07\x00\x02\x07\x00\x57\x07\x01\x50\x00\x00\x05\xB2\x00\x03\x07\x00\x02\x07\x00\x57\x07\x01\x50\x00\x01\x07\x00\x02\x05\xB7\x00\x02\x07\x00\x02\x07\x00\x57\x00\x00\x05\xCC\x00\x03\x07\x00\x02\x07\x00\x57\x07\x00\xCC\x00\x01\x07\x00\xCC\x05\xE9\x00\x03\x07\x00\x02\x07\x00\x57\x07\x00\xCC\x00\x00\x05\xEF\x00\x02\x07\x00\x02\x07\x00\x57\x00\x00\x05\xF4\x00\x02\x07\x00\x02\x07\x00\x57\x00\x00'
    .end code
.end method

.method public method84 : ()V
    .code stack 0 locals 1
L0:     return
L1:     
    .end code
.end method

.method public <init> : (LMd;)V
    .code stack 6 locals 2
L0:     aconst_null
L1:     aload_0
L2:     dup
L3:     dup_x2
L4:     aload_1
L5:     invokespecial Method RC <init> (LMd;)V
L8:     new uC
L11:    aload_0
L12:    dup
L13:    pop2
L14:    dup
L15:    invokespecial Method uC <init> ()V
L18:    putfield Field jb field856 LuC;
L21:    putfield Field jb field857 LM;
L24:    return
L25:    
    .end code
    .exceptions java/io/IOException
.end method

.method public static synthetic method465 : (Ljb;)LuC;
    .code stack 1 locals 1
L0:     aload_0
L1:     getfield Field jb field856 LuC;
L4:     areturn
L5:     
    .end code
.end method

.method public method393 : (Led;LK;)V
    .code stack 6 locals 3
L0:     getstatic Field Kc field1931 LKc;
L3:     invokevirtual Method Kc method852 ()Z
L6:     ifne L11
L9:     return
L10:    athrow
        .catch java/lang/Exception from L11 to L31 using L35
L11:    aload_0
L12:    new EB
L15:    dup
L16:    aload_1
L17:    aload_0
L18:    getfield Field jb field856 LuC;
L21:    aload_2
L22:    invokevirtual Method uC method5812 (LK;)I
L25:    invokespecial Method EB <init> (Led;I)V
L28:    invokevirtual Method jb method394 (LD;)V
L31:    goto L36
L34:    athrow
L35:    astore_1
L36:    new ub
L39:    dup
L40:    aload_0
L41:    aload_2
L42:    invokespecial Method ub <init> (Ljb;LK;)V
L45:    ldc2_w 5e0
L48:    invokestatic Method ib method1150 (Ljava/lang/Runnable;D)V
L51:    return
L52:    
        .attribute StackMap b'\x00\x05\x00\x0A\x00\x00\x00\x01\x07\x00\x8C\x00\x0B\x00\x03\x07\x00\x02\x07\x00\x65\x07\x00\x08\x00\x00\x00\x22\x00\x00\x00\x01\x07\x00\x8C\x00\x23\x00\x03\x07\x00\x02\x07\x00\x65\x07\x00\x08\x00\x01\x07\x00\x27\x00\x24\x00\x03\x07\x00\x02\x07\x01\x9B\x07\x00\x08\x00\x00'
    .end code
.end method

.method public method400 : (Led;ZLjava/lang/String;LK;)V
    .code stack 7 locals 5
L0:     getstatic Field Kc field1931 LKc;
L3:     invokevirtual Method Kc method852 ()Z
L6:     ifne L29
L9:     aload 4
L11:    ifnull L27
L14:    new pC
L17:    dup
L18:    aload_0
L19:    aload 4
L21:    invokespecial Method pC <init> (Ljb;LK;)V
L24:    invokestatic Method ib method1154 (Ljava/lang/Runnable;)V
L27:    return
L28:    athrow
        .catch java/lang/Exception from L29 to L51 using L55
L29:    aload_0
L30:    new Jc
L33:    dup
L34:    aload_1
L35:    aload_3
L36:    aload_0
L37:    getfield Field jb field856 LuC;
L40:    aload 4
L42:    invokevirtual Method uC method5812 (LK;)I
L45:    invokespecial Method Jc <init> (Led;Ljava/lang/String;I)V
L48:    invokevirtual Method jb method394 (LD;)V
L51:    goto L56
L54:    athrow
L55:    astore_1
L56:    new Yb
L59:    dup
L60:    aload_0
L61:    aload 4
L63:    invokespecial Method Yb <init> (Ljb;LK;)V
L66:    ldc2_w 5e0
L69:    invokestatic Method ib method1150 (Ljava/lang/Runnable;D)V
L72:    return
L73:    
        .attribute StackMap b'\x00\x06\x00\x1B\x00\x05\x07\x00\x02\x07\x00\x65\x01\x07\x01\xAD\x07\x00\x08\x00\x00\x00\x1C\x00\x00\x00\x01\x07\x00\x8C\x00\x1D\x00\x05\x07\x00\x02\x07\x00\x65\x01\x07\x01\xAD\x07\x00\x08\x00\x00\x00\x36\x00\x00\x00\x01\x07\x00\x8C\x00\x37\x00\x05\x07\x00\x02\x07\x00\x65\x01\x07\x01\xAD\x07\x00\x08\x00\x01\x07\x00\x27\x00\x38\x00\x05\x07\x00\x02\x07\x01\x9B\x01\x07\x01\xAD\x07\x00\x08\x00\x00'
    .end code
.end method

.method public method330 : ()I
    .code stack 1 locals 1
L0:     aload_0
L1:     getfield Field jb field855 I
L4:     ireturn
L5:     
    .end code
.end method
.innerclasses
    KD K [0] public static final enum
    QB qd [0] public static final enum
    Yb [0] [0]
    java/util/Map$Entry java/util/Map Entry public static interface abstract
    nD jb [0] static synthetic
    oc fc [0] public static final enum
    pC [0] [0]
    ub [0] [0]
.end innerclasses
.end class
