.version 49 0
.class public super jC
.super vB
.field public static final field1026 [Ljava/lang/String;
.field public static final field1027 I = 1
.field private field1028 Lig;
.field public static final field1029 I = 1
.field private field1030 [Ljava/lang/String;
.field public static final field1031 I = 0
.field private field1032 Ljava/lang/String;
.field private false LAe;
.field private field1033 I
.field private field1034 Lqc;
.field public static final true [Ljava/lang/String;
.field public static final field1035 [Ljava/lang/String;
.field public static final field1036 [Ljava/lang/String;
.field public field1037 Ljava/util/List;
.field public static final field1038 [Ljava/lang/String;
.field private field1039 I
.field public static final field1040 I = 0
.field public static final field1041 I = 2
.field private field1042 LDF;
.field public static final field1043 I = 1
.field public field1044 Ljava/util/List;
.field private try Z
.field public static final field1045 [Ljava/lang/String;
.field public static final new I = -1
.field public static final field1046 I = 2
.field private this [LYg;
.field public static final field1047 [Ljava/lang/String;
.field public static final field1048 [Ljava/lang/String;
.field public static final field1049 [Ljava/lang/String;
.field public static final field1050 I = 0

.method public method132 : ()I
    .code stack 4 locals 1
L0:     aload_0
L1:     getfield Field jC field1030 [Ljava/lang/String;
L4:     getstatic Field jC field1026 [Ljava/lang/String;
L7:     if_acmpne L23
L10:    aload_0
L11:    getfield Field jC field1033 I
L14:    ifne L23
L17:    iconst_1
L18:    dup
L19:    dup
L20:    pop2
L21:    ireturn
L22:    athrow
L23:    aload_0
L24:    getfield Field jC field1030 [Ljava/lang/String;
L27:    getstatic Field jC field1026 [Ljava/lang/String;
L30:    if_acmpne L50
L33:    aload_0
L34:    getfield Field jC field1033 I
L37:    iconst_1
L38:    dup
L39:    dup
L40:    pop2
L41:    if_icmpne L50
L44:    iconst_2
L45:    iconst_1
L46:    dup
L47:    pop2
L48:    ireturn
L49:    athrow
L50:    aload_0
L51:    getfield Field jC field1030 [Ljava/lang/String;
L54:    getstatic Field jC field1038 [Ljava/lang/String;
L57:    if_acmpne L76
L60:    aload_0
L61:    getfield Field jC field1033 I
L64:    iconst_1
L65:    dup
L66:    dup
L67:    pop2
L68:    if_icmpne L76
L71:    iconst_2
L72:    iconst_1
L73:    dup
L74:    pop2
L75:    ireturn
L76:    aload_0
L77:    getfield Field jC field1030 [Ljava/lang/String;
L80:    getstatic Field jC true [Ljava/lang/String;
L83:    if_acmpne L91
L86:    iconst_2
L87:    iconst_1
L88:    dup
L89:    pop2
L90:    ireturn
L91:    aload_0
L92:    getfield Field jC field1033 I
L95:    ireturn
L96:    
        .attribute StackMap b'\x00\x06\x00\x16\x00\x00\x00\x01\x07\x00\x46\x00\x17\x00\x01\x07\x00\x02\x00\x00\x00\x31\x00\x00\x00\x01\x07\x00\x46\x00\x32\x00\x01\x07\x00\x02\x00\x00\x00\x4C\x00\x01\x07\x00\x02\x00\x00\x00\x5B\x00\x01\x07\x00\x02\x00\x00'
    .end code
.end method

.method public <init> : (LAe;Ljava/lang/String;[Ljava/lang/String;Lh;)V
    .code stack 5 locals 5
L0:     aload 4
L2:     aload_0
L3:     aload_1
L4:     aload_2
L5:     aload_3
L6:     invokespecial Method jC <init> (LAe;Ljava/lang/String;[Ljava/lang/String;)V
L9:     ifnull L18
L12:    aload_0
L13:    aload 4
L15:    invokevirtual Method jC method516 (Lh;)V
L18:    return
L19:    
        .attribute StackMap b'\x00\x01\x00\x12\x00\x05\x07\x00\x02\x07\x00\x0E\x07\x00\x55\x07\x00\x56\x07\x00\x58\x00\x00'
    .end code
.end method

.method public method52 : ()V
    .code stack 5 locals 4
L0:     aload_0
L1:     dup
L2:     iconst_1
L3:     dup
L4:     dup
L5:     pop2
L6:     putfield Field jC try Z
L9:     getfield Field jC this [LYg;
L12:    ifnull L72
L15:    aload_0
L16:    getfield Field jC this [LYg;
L19:    dup
L20:    astore_1
L21:    arraylength
L22:    istore_2
L23:    iconst_0
L24:    iconst_1
L25:    dup
L26:    pop2
L27:    dup
L28:    istore_3
L29:    iload_2
L30:    if_icmpge L51
L33:    aload_1
L34:    iload_3
L35:    iinc 3 1
L38:    aaload
L39:    iconst_1
L40:    dup
L41:    dup
L42:    pop2
L43:    invokevirtual Method Yg method238 (Z)V
L46:    iload_3
L47:    goto L29
L50:    athrow
L51:    aload_0
L52:    getfield Field jC this [LYg;
L55:    arraylength
L56:    ifle L72
L59:    aload_0
L60:    dup
L61:    getfield Field jC this [LYg;
L64:    iconst_0
L65:    iconst_1
L66:    dup
L67:    pop2
L68:    aaload
L69:    invokevirtual Method jC try (LgB;)V
L72:    return
L73:    
        .attribute StackMap b'\x00\x04\x00\x1D\x00\x04\x07\x00\x02\x07\x00\x5F\x01\x01\x00\x01\x01\x00\x32\x00\x00\x00\x01\x07\x00\x46\x00\x33\x00\x04\x07\x00\x02\x07\x00\x5F\x01\x01\x00\x00\x00\x48\x00\x01\x07\x00\x02\x00\x00'
    .end code
.end method

.method public static synthetic method515 : (LjC;I)I
    .code stack 3 locals 2
L0:     aload_0
L1:     iload_1
L2:     dup_x1
L3:     putfield Field jC field1039 I
L6:     ireturn
L7:     
    .end code
.end method

.method public this : (Lh;)V
    .code stack 2 locals 2
L0:     aload_0
L1:     getfield Field jC field1044 Ljava/util/List;
L4:     aload_1
L5:     invokeinterface InterfaceMethod java/util/List remove (Ljava/lang/Object;)Z 2
L10:    pop
L11:    return
L12:    
    .end code
.end method

.method public <init> : (LAe;Ljava/lang/String;[Ljava/lang/String;)V
    .code stack 12 locals 4
L0:     aload_3
L1:     aload_0
L2:     dup_x1
L3:     dup_x2
L4:     iconst_0
L5:     iconst_m1
L6:     aload_0
L7:     dup
L8:     dup_x2
L9:     aload_0
L10:    invokespecial Method vB <init> ()V
L13:    new java/util/LinkedList
L16:    aload_0
L17:    dup
L18:    pop2
L19:    dup
L20:    invokespecial Method java/util/LinkedList <init> ()V
L23:    putfield Field jC field1037 Ljava/util/List;
L26:    new java/util/LinkedList
L29:    aload_0
L30:    dup
L31:    pop2
L32:    dup
L33:    invokespecial Method java/util/LinkedList <init> ()V
L36:    putfield Field jC field1044 Ljava/util/List;
L39:    iconst_1
L40:    dup
L41:    pop2
L42:    putfield Field jC field1033 I
L45:    iconst_1
L46:    dup
L47:    pop2
L48:    putfield Field jC field1039 I
L51:    putfield Field jC field1030 [Ljava/lang/String;
L54:    getfield Field jC field1030 [Ljava/lang/String;
L57:    ifnonnull L74
L60:    aload_0
L61:    iconst_0
L62:    iconst_1
L63:    dup
L64:    pop2
L65:    anewarray java/lang/String
L68:    iconst_1
L69:    dup
L70:    pop2
L71:    putfield Field jC field1030 [Ljava/lang/String;
L74:    aload_0
L75:    aload_1
L76:    aload_2
L77:    aload_0
L78:    dup_x1
L79:    iconst_1
L80:    dup
L81:    dup
L82:    pop2
L83:    putfield Field jC try Z
L86:    putfield Field jC field1032 Ljava/lang/String;
L89:    putfield Field jC false LAe;
L92:    return
L93:    
        .attribute StackMap b'\x00\x01\x00\x4A\x00\x04\x07\x00\x02\x07\x00\x0E\x07\x00\x55\x07\x00\x56\x00\x00'
    .end code
.end method

.method public method56 : ()V
    .code stack 5 locals 4
L0:     aload_0
L1:     dup
L2:     iconst_0
L3:     iconst_1
L4:     dup
L5:     pop2
L6:     putfield Field jC try Z
L9:     getfield Field jC this [LYg;
L12:    ifnull L51
L15:    aload_0
L16:    getfield Field jC this [LYg;
L19:    dup
L20:    astore_1
L21:    arraylength
L22:    istore_2
L23:    iconst_0
L24:    iconst_1
L25:    dup
L26:    pop2
L27:    dup
L28:    istore_3
L29:    iload_2
L30:    if_icmpge L51
L33:    aload_1
L34:    iload_3
L35:    iinc 3 1
L38:    aaload
L39:    iconst_0
L40:    iconst_1
L41:    dup
L42:    pop2
L43:    invokevirtual Method Yg method238 (Z)V
L46:    iload_3
L47:    goto L29
L50:    athrow
L51:    return
L52:    
        .attribute StackMap b'\x00\x03\x00\x1D\x00\x04\x07\x00\x02\x07\x00\x5F\x01\x01\x00\x01\x01\x00\x32\x00\x00\x00\x01\x07\x00\x46\x00\x33\x00\x01\x07\x00\x02\x00\x00'
    .end code
.end method

.method public method49 : ()V
    .code stack 9 locals 3
L0:     new qc
L3:     dup
L4:     new og
L7:     dup
L8:     iconst_1
L9:     dup
L10:    dup
L11:    pop2
L12:    aload_0
L13:    getfield Field jC field1030 [Ljava/lang/String;
L16:    arraylength
L17:    invokestatic Method java/lang/Math max (II)I
L20:    ldc 2e-1f
L22:    fconst_0
L23:    invokespecial Method og <init> (IFF)V
L26:    invokespecial Method qc <init> (Ld;)V
L29:    astore_1
L30:    aload_0
L31:    dup
L32:    getfield Field jC field1030 [Ljava/lang/String;
L35:    arraylength
L36:    anewarray Yg
L39:    iconst_1
L40:    dup
L41:    pop2
L42:    putfield Field jC this [LYg;
L45:    iconst_0
L46:    iconst_1
L47:    dup
L48:    pop2
L49:    dup
L50:    istore_2
L51:    aload_0
L52:    getfield Field jC field1030 [Ljava/lang/String;
L55:    arraylength
L56:    if_icmpge L128
L59:    aload_0
L60:    dup
L61:    getfield Field jC this [LYg;
L64:    new Yg
L67:    iload_2
L68:    dup_x1
L69:    dup
L70:    pop2
L71:    dup
L72:    aload_0
L73:    getfield Field jC field1030 [Ljava/lang/String;
L76:    iload_2
L77:    aaload
L78:    new zf
L81:    dup
L82:    aload_0
L83:    invokespecial Method zf <init> (LjC;)V
L86:    invokespecial Method Yg <init> (Ljava/lang/String;Lh;)V
L89:    aastore
L90:    getfield Field jC try Z
L93:    ifne L109
L96:    aload_0
L97:    getfield Field jC this [LYg;
L100:   iload_2
L101:   aaload
L102:   iconst_0
L103:   iconst_1
L104:   dup
L105:   pop2
L106:   invokevirtual Method Yg method238 (Z)V
L109:   aload_1
L110:   aload_0
L111:   getfield Field jC this [LYg;
L114:   iload_2
L115:   iinc 2 1
L118:   aaload
L119:   invokevirtual Method qc method36 (LgB;)LgB;
L122:   pop
L123:   iload_2
L124:   goto L51
L127:   athrow
L128:   iconst_1
L129:   dup
L130:   dup
L131:   pop2
L132:   anewarray [LgB;
L135:   iconst_1
L136:   dup
L137:   pop2
L138:   dup
L139:   iconst_0
L140:   iconst_1
L141:   dup
L142:   pop2
L143:   aload_0
L144:   getfield Field jC this [LYg;
L147:   aastore
L148:   invokestatic Method mC method1702 ([[LgB;)V
L151:   new qc
L154:   dup
L155:   new VD
L158:   dup
L159:   invokespecial Method VD <init> ()V
L162:   invokespecial Method qc <init> (Ld;)V
L165:   dup
L166:   astore_2
L167:   new DF
L170:   aload_0
L171:   dup
L172:   pop2
L173:   dup
L174:   aload_0
L175:   dup_x2
L176:   getfield Field jC field1032 Ljava/lang/String;
L179:   invokespecial Method DF <init> (Ljava/lang/String;)V
L182:   dup_x1
L183:   putfield Field jC field1042 LDF;
L186:   getstatic Field VD field147 Ljava/lang/Object;
L189:   invokevirtual Method qc method31 (LgB;Ljava/lang/Object;)V
L192:   new SB
L195:   aload_2
L196:   dup_x1
L197:   dup
L198:   pop2
L199:   dup
L200:   new ig
L203:   aload_0
L204:   dup
L205:   pop2
L206:   dup
L207:   aload_0
L208:   dup_x2
L209:   getfield Field jC false LAe;
L212:   ldc 8e-1f
L214:   dup
L215:   invokespecial Method ig <init> (LAe;FF)V
L218:   dup_x1
L219:   putfield Field jC field1028 Lig;
L222:   fconst_0
L223:   ldc 1e-1f
L225:   ldc 2e-1f
L227:   getstatic Field FE field822 F
L230:   invokespecial Method SB <init> (LgB;FFFF)V
L233:   getstatic Field VD field149 Ljava/lang/Object;
L236:   invokevirtual Method qc method31 (LgB;Ljava/lang/Object;)V
L239:   aload_0
L240:   dup
L241:   new qc
L244:   aload_0
L245:   dup_x2
L246:   dup
L247:   pop2
L248:   dup
L249:   new fG
L252:   dup
L253:   getstatic Field LE field634 LLE;
L256:   ldc 5e-1f
L258:   invokespecial Method fG <init> (LLE;F)V
L261:   invokespecial Method qc <init> (Ld;)V
L264:   putfield Field jC field1034 Lqc;
L267:   getfield Field jC field1034 Lqc;
L270:   aload_2
L271:   getstatic Field dg field337 Ldg;
L274:   invokevirtual Method qc method31 (LgB;Ljava/lang/Object;)V
L277:   getfield Field jC this [LYg;
L280:   arraylength
L281:   ifeq L295
L284:   aload_0
L285:   getfield Field jC field1034 Lqc;
L288:   aload_1
L289:   getstatic Field dg field335 Ldg;
L292:   invokevirtual Method qc method31 (LgB;Ljava/lang/Object;)V
L295:   aload_0
L296:   dup
L297:   getfield Field jC field1034 Lqc;
L300:   invokestatic Method Wd method1093 (LgB;)Lqc;
L303:   invokevirtual Method jC method36 (LgB;)LgB;
L306:   pop
L307:   return
L308:   
        .attribute StackMap b'\x00\x05\x00\x33\x00\x03\x07\x00\x02\x07\x00\x83\x01\x00\x01\x01\x00\x6D\x00\x03\x07\x00\x02\x07\x00\x83\x01\x00\x00\x00\x7F\x00\x00\x00\x01\x07\x00\x46\x00\x80\x00\x03\x07\x00\x02\x07\x00\x83\x01\x00\x00\x01\x27\x00\x03\x07\x00\x02\x07\x00\x83\x07\x00\x83\x00\x00'
    .end code
.end method

.method public method12 : (Ljava/lang/String;)V
    .code stack 3 locals 2
L0:     aload_0
L1:     dup
L2:     aload_1
L3:     putfield Field jC field1032 Ljava/lang/String;
L6:     getfield Field jC field1042 LDF;
L9:     ifnull L20
L12:    aload_0
L13:    getfield Field jC field1042 LDF;
L16:    aload_1
L17:    invokevirtual Method DF method12 (Ljava/lang/String;)V
L20:    return
L21:    
        .attribute StackMap b'\x00\x01\x00\x14\x00\x02\x07\x00\x02\x07\x00\x55\x00\x00'
    .end code
.end method

.method public method516 : (Lh;)V
    .code stack 2 locals 2
L0:     aload_0
L1:     getfield Field jC field1037 Ljava/util/List;
L4:     aload_1
L5:     invokeinterface InterfaceMethod java/util/List add (Ljava/lang/Object;)Z 2
L10:    pop
L11:    return
L12:    
    .end code
.end method

.method public method57 : (LgB;IC)Z
    .code stack 7 locals 4
L0:     aload_0
L1:     getfield Field jC field1030 [Ljava/lang/String;
L4:     getstatic Field jC field1049 [Ljava/lang/String;
L7:     if_acmpne L215
L10:    iload_2
L11:    lookupswitch
            21 : L126
            49 : L36
            default : L215
L36:    aload_0
L37:    bipush 49
L39:    aload_0
L40:    dup_x1
L41:    iconst_1
L42:    dup
L43:    dup
L44:    pop2
L45:    putfield Field jC field1033 I
L48:    iconst_1
L49:    dup
L50:    pop2
L51:    putfield Field jC field1039 I
L54:    getfield Field jC field1037 Ljava/util/List;
L57:    invokeinterface InterfaceMethod java/util/List isEmpty ()Z 1
L62:    ifeq L77
L65:    aload_0
L66:    getfield Field jC field1136 LFE;
L69:    aload_0
L70:    invokevirtual Method FE method458 (LjC;)V
L73:    goto L118
L76:    athrow
L77:    aload_0
L78:    getfield Field jC field1037 Ljava/util/List;
L81:    invokeinterface InterfaceMethod java/util/List iterator ()Ljava/util/Iterator; 1
L86:    dup
L87:    astore_1
L88:    invokeinterface InterfaceMethod java/util/Iterator hasNext ()Z 1
L93:    ifeq L118
L96:    aload_1
L97:    invokeinterface InterfaceMethod java/util/Iterator next ()Ljava/lang/Object; 1
L102:   checkcast h
L105:   astore_3
L106:   aload_1
L107:   aload_3
L108:   aload_0
L109:   invokeinterface InterfaceMethod h method728 (LgB;)V 2
L114:   goto L88
L117:   athrow
L118:   iconst_1
L119:   dup
L120:   dup
L121:   pop2
L122:   ireturn
L123:   goto L127
L126:   aload_0
L127:   iconst_0
L128:   ifne L123
L131:   bipush 21
L133:   aload_0
L134:   dup_x1
L135:   iconst_0
L136:   iconst_1
L137:   dup
L138:   pop2
L139:   putfield Field jC field1033 I
L142:   iconst_1
L143:   dup
L144:   pop2
L145:   putfield Field jC field1039 I
L148:   getfield Field jC field1037 Ljava/util/List;
L151:   invokeinterface InterfaceMethod java/util/List isEmpty ()Z 1
L156:   aload_0
L157:   swap
L158:   ifeq L171
L161:   getfield Field jC field1136 LFE;
L164:   aload_0
L165:   invokevirtual Method FE method458 (LjC;)V
L168:   goto L210
L171:   getfield Field jC field1037 Ljava/util/List;
L174:   invokeinterface InterfaceMethod java/util/List iterator ()Ljava/util/Iterator; 1
L179:   dup
L180:   astore_1
L181:   invokeinterface InterfaceMethod java/util/Iterator hasNext ()Z 1
L186:   ifeq L210
L189:   aload_1
L190:   invokeinterface InterfaceMethod java/util/Iterator next ()Ljava/lang/Object; 1
L195:   checkcast h
L198:   astore_3
L199:   aload_1
L200:   aload_3
L201:   aload_0
L202:   invokeinterface InterfaceMethod h method728 (LgB;)V 2
L207:   goto L181
L210:   iconst_1
L211:   dup
L212:   dup
L213:   pop2
L214:   ireturn
L215:   aload_0
L216:   iload_2
L217:   aload_0
L218:   dup_x1
L219:   iconst_m1
L220:   iconst_1
L221:   dup
L222:   pop2
L223:   putfield Field jC field1033 I
L226:   putfield Field jC field1039 I
L229:   getfield Field jC field1044 Ljava/util/List;
L232:   invokeinterface InterfaceMethod java/util/List iterator ()Ljava/util/Iterator; 1
L237:   dup
L238:   astore_1
L239:   invokeinterface InterfaceMethod java/util/Iterator hasNext ()Z 1
L244:   ifeq L268
L247:   aload_1
L248:   invokeinterface InterfaceMethod java/util/Iterator next ()Ljava/lang/Object; 1
L253:   checkcast h
L256:   astore_3
L257:   aload_1
L258:   aload_3
L259:   aload_0
L260:   invokeinterface InterfaceMethod h method728 (LgB;)V 2
L265:   goto L239
L268:   aload_0
L269:   iconst_0
L270:   iconst_1
L271:   dup
L272:   pop2
L273:   putfield Field jC field1039 I
L276:   iconst_1
L277:   dup
L278:   dup
L279:   pop2
L280:   ireturn
L281:   
        .attribute StackMap b'\x00\x0F\x00\x24\x00\x04\x07\x00\x02\x07\x00\xEF\x01\x01\x00\x00\x00\x4C\x00\x00\x00\x01\x07\x00\x46\x00\x4D\x00\x04\x07\x00\x02\x07\x00\xEF\x01\x01\x00\x00\x00\x58\x00\x03\x07\x00\x02\x07\x01\x00\x01\x00\x01\x07\x01\x00\x00\x75\x00\x00\x00\x01\x07\x00\x46\x00\x76\x00\x03\x07\x00\x02\x07\x01\x0C\x01\x00\x00\x00\x7B\x00\x04\x07\x00\x02\x07\x00\xEF\x01\x01\x00\x01\x07\x00\x02\x00\x7E\x00\x04\x07\x00\x02\x07\x00\xEF\x01\x01\x00\x00\x00\x7F\x00\x04\x07\x00\x02\x07\x00\xEF\x01\x01\x00\x01\x07\x00\x02\x00\xAB\x00\x04\x07\x00\x02\x07\x00\xEF\x01\x01\x00\x01\x07\x00\x02\x00\xB5\x00\x03\x07\x00\x02\x07\x01\x00\x01\x00\x01\x07\x01\x00\x00\xD2\x00\x03\x07\x00\x02\x07\x01\x0C\x01\x00\x00\x00\xD7\x00\x04\x07\x00\x02\x07\x00\xEF\x01\x01\x00\x00\x00\xEF\x00\x03\x07\x00\x02\x07\x01\x00\x01\x00\x01\x07\x01\x00\x01\x0C\x00\x03\x07\x00\x02\x07\x01\x00\x01\x00\x00'
    .end code
.end method

.method public method128 : (Lh;)V
    .code stack 2 locals 2
L0:     aload_0
L1:     getfield Field jC field1044 Ljava/util/List;
L4:     aload_1
L5:     invokeinterface InterfaceMethod java/util/List add (Ljava/lang/Object;)Z 2
L10:    pop
L11:    return
L12:    
    .end code
.end method

.method public method130 : (Lh;)V
    .code stack 2 locals 2
L0:     aload_0
L1:     getfield Field jC field1037 Ljava/util/List;
L4:     aload_1
L5:     invokeinterface InterfaceMethod java/util/List remove (Ljava/lang/Object;)Z 2
L10:    pop
L11:    return
L12:    
    .end code
.end method

.method public static <clinit> : ()V
    .code stack 5 locals 0
L0:     iconst_0
L1:     iconst_1
L2:     dup
L3:     pop2
L4:     anewarray java/lang/String
L7:     iconst_1
L8:     dup
L9:     pop2
L10:    putstatic Field jC field1036 [Ljava/lang/String;
L13:    iconst_2
L14:    iconst_1
L15:    dup
L16:    pop2
L17:    anewarray java/lang/String
L20:    iconst_1
L21:    dup
L22:    pop2
L23:    dup
L24:    iconst_0
L25:    iconst_1
L26:    dup
L27:    pop2
L28:    ldc_w "Yes"
L31:    aastore
L32:    dup
L33:    iconst_1
L34:    dup
L35:    dup
L36:    pop2
L37:    ldc_w "No"
L40:    aastore
L41:    putstatic Field jC field1049 [Ljava/lang/String;
L44:    iconst_3
L45:    iconst_1
L46:    dup
L47:    pop2
L48:    anewarray java/lang/String
L51:    iconst_1
L52:    dup
L53:    pop2
L54:    dup
L55:    iconst_0
L56:    iconst_1
L57:    dup
L58:    pop2
L59:    ldc_w "Yes"
L62:    aastore
L63:    dup
L64:    iconst_1
L65:    dup
L66:    dup
L67:    pop2
L68:    ldc_w "No"
L71:    aastore
L72:    dup
L73:    iconst_2
L74:    iconst_1
L75:    dup
L76:    pop2
L77:    ldc_w "Cancel"
L80:    aastore
L81:    putstatic Field jC field1045 [Ljava/lang/String;
L84:    iconst_2
L85:    iconst_1
L86:    dup
L87:    pop2
L88:    anewarray java/lang/String
L91:    iconst_1
L92:    dup
L93:    pop2
L94:    dup
L95:    iconst_0
L96:    iconst_1
L97:    dup
L98:    pop2
L99:    ldc_w "OK"
L102:   aastore
L103:   dup
L104:   iconst_1
L105:   dup
L106:   dup
L107:   pop2
L108:   ldc_w "Cancel"
L111:   aastore
L112:   putstatic Field jC field1038 [Ljava/lang/String;
L115:   iconst_1
L116:   dup
L117:   dup
L118:   pop2
L119:   anewarray java/lang/String
L122:   iconst_1
L123:   dup
L124:   pop2
L125:   dup
L126:   iconst_0
L127:   iconst_1
L128:   dup
L129:   pop2
L130:   ldc_w "OK"
L133:   aastore
L134:   putstatic Field jC field1048 [Ljava/lang/String;
L137:   iconst_2
L138:   iconst_1
L139:   dup
L140:   pop2
L141:   anewarray java/lang/String
L144:   iconst_1
L145:   dup
L146:   pop2
L147:   dup
L148:   iconst_0
L149:   iconst_1
L150:   dup
L151:   pop2
L152:   ldc_w "OK"
L155:   aastore
L156:   dup
L157:   iconst_1
L158:   dup
L159:   dup
L160:   pop2
L161:   ldc_w "Again"
L164:   aastore
L165:   putstatic Field jC field1035 [Ljava/lang/String;
L168:   iconst_2
L169:   iconst_1
L170:   dup
L171:   pop2
L172:   anewarray java/lang/String
L175:   iconst_1
L176:   dup
L177:   pop2
L178:   dup
L179:   iconst_0
L180:   iconst_1
L181:   dup
L182:   pop2
L183:   ldc_w "Again"
L186:   aastore
L187:   dup
L188:   iconst_1
L189:   dup
L190:   dup
L191:   pop2
L192:   ldc_w "Back to menu"
L195:   aastore
L196:   putstatic Field jC field1026 [Ljava/lang/String;
L199:   iconst_1
L200:   dup
L201:   dup
L202:   pop2
L203:   anewarray java/lang/String
L206:   iconst_1
L207:   dup
L208:   pop2
L209:   dup
L210:   iconst_0
L211:   iconst_1
L212:   dup
L213:   pop2
L214:   ldc_w "Cancel"
L217:   aastore
L218:   putstatic Field jC true [Ljava/lang/String;
L221:   iconst_2
L222:   iconst_1
L223:   dup
L224:   pop2
L225:   anewarray java/lang/String
L228:   iconst_1
L229:   dup
L230:   pop2
L231:   dup
L232:   iconst_0
L233:   iconst_1
L234:   dup
L235:   pop2
L236:   ldc_w "Retry"
L239:   aastore
L240:   dup
L241:   iconst_1
L242:   dup
L243:   dup
L244:   pop2
L245:   ldc_w "Abort"
L248:   aastore
L249:   putstatic Field jC field1047 [Ljava/lang/String;
L252:   return
L253:   
    .end code
.end method

.method public static synthetic method517 : (LjC;)[LYg;
    .code stack 1 locals 1
L0:     aload_0
L1:     getfield Field jC this [LYg;
L4:     areturn
L5:     
    .end code
.end method

.method public method518 : (LAe;)V
    .code stack 3 locals 2
L0:     aload_0
L1:     dup
L2:     aload_1
L3:     putfield Field jC false LAe;
L6:     getfield Field jC field1028 Lig;
L9:     ifnull L20
L12:    aload_0
L13:    getfield Field jC field1028 Lig;
L16:    aload_1
L17:    invokevirtual Method ig method518 (LAe;)V
L20:    return
L21:    
        .attribute StackMap b'\x00\x01\x00\x14\x00\x02\x07\x00\x02\x07\x00\x0E\x00\x00'
    .end code
.end method

.method public method247 : ()I
    .code stack 1 locals 1
L0:     aload_0
L1:     getfield Field jC field1039 I
L4:     ireturn
L5:     
    .end code
.end method

.method public static synthetic method519 : (LjC;I)I
    .code stack 3 locals 2
L0:     aload_0
L1:     iload_1
L2:     dup_x1
L3:     putfield Field jC field1033 I
L6:     ireturn
L7:     
    .end code
.end method

.method public method10 : ()V
    .code stack 5 locals 1
L0:     aload_0
L1:     getfield Field jC this [LYg;
L4:     arraylength
L5:     ifle L24
L8:     aload_0
L9:     invokevirtual Method jC method51 ()LbC;
L12:    aload_0
L13:    getfield Field jC this [LYg;
L16:    iconst_0
L17:    iconst_1
L18:    dup
L19:    pop2
L20:    aaload
L21:    invokevirtual Method bC try (LgB;)V
L24:    return
L25:    
        .attribute StackMap b'\x00\x01\x00\x18\x00\x01\x07\x00\x02\x00\x00'
    .end code
.end method
.innerclasses
    LE fG [0] public static final enum
    dg fG [0] public static final enum
    zf [0] [0]
    Ae ig [0] public static final enum
.end innerclasses
.end class
