.version 49 0
.class public final super jd
.super java/lang/Thread
.field public final synthetic do LkB;

.method public <init> : (LkB;)V
    .code stack 3 locals 2
L0:     aload_0
L1:     dup
L2:     aload_1
L3:     putfield Field jd do LkB;
L6:     invokespecial Method java/lang/Thread <init> ()V
L9:     return
L10:    
    .end code
.end method

.method public run : ()V
    .code stack 9 locals 10
L0:     iconst_0
L1:     iconst_1
L2:     dup
L3:     pop2
L4:     dup
L5:     istore_1
L6:     iconst_2
L7:     iconst_1
L8:     dup
L9:     pop2
L10:    if_icmpge L460
L13:    aconst_null
L14:    astore_2
L15:    aconst_null
L16:    astore_3
L17:    new java/net/URL
L20:    dup
L21:    invokestatic Method dc break ()Ljava/lang/String;
L24:    invokespecial Method java/net/URL <init> (Ljava/lang/String;)V
L27:    invokevirtual Method java/net/URL openConnection ()Ljava/net/URLConnection;
L30:    checkcast java/net/HttpURLConnection
L33:    astore_2
L34:    sipush 30000
L37:    aload_2
L38:    dup_x1
L39:    dup_x2
L40:    sipush 30000
L43:    aload_2
L44:    iconst_0
L45:    iconst_1
L46:    dup
L47:    pop2
L48:    invokevirtual Method java/net/HttpURLConnection setAllowUserInteraction (Z)V
L51:    iconst_1
L52:    dup
L53:    pop2
L54:    invokevirtual Method java/net/HttpURLConnection setConnectTimeout (I)V
L57:    iconst_1
L58:    dup
L59:    pop2
L60:    invokevirtual Method java/net/HttpURLConnection setReadTimeout (I)V
L63:    invokevirtual Method java/net/HttpURLConnection getResponseCode ()I
L66:    lookupswitch
            200 : L84
            default : L302
L84:    new java/io/ByteArrayOutputStream
L87:    iconst_0
L88:    ifne L87
L91:    dup
L92:    invokespecial Method java/io/ByteArrayOutputStream <init> ()V
L95:    astore 4
L97:    ldc 65536
L99:    newarray byte
L101:   iconst_1
L102:   dup
L103:   pop2
L104:   astore 5
L106:   iconst_0
L107:   iconst_1
L108:   dup
L109:   pop2
L110:   istore 6
L112:   aload_2
L113:   invokevirtual Method java/net/HttpURLConnection getContentLength ()I
L116:   dup
L117:   istore 7
L119:   iconst_1
L120:   dup
L121:   dup
L122:   pop2
L123:   if_icmpge L130
L126:   ldc 16777216
L128:   istore 7
L130:   aload_2
L131:   invokevirtual Method java/net/HttpURLConnection getInputStream ()Ljava/io/InputStream;
L134:   aload 5
L136:   invokevirtual Method java/io/InputStream read ([B)I
L139:   dup
L140:   istore 8
L142:   ifge L151
L145:   aload 4
L147:   goto L192
L150:   athrow
L151:   aload 4
L153:   aload 5
L155:   iconst_0
L156:   iconst_1
L157:   dup
L158:   pop2
L159:   iload 8
L161:   invokevirtual Method java/io/ByteArrayOutputStream write ([BII)V
L164:   iload 6
L166:   iload 8
L168:   iadd
L169:   istore 6
L171:   aload_2
L172:   aload_0
L173:   getfield Field jd do LkB;
L176:   iload 6
L178:   i2f
L179:   iload 7
L181:   i2f
L182:   fdiv
L183:   putfield Field kB null F
L186:   goto L131
L189:   nop
L190:   nop
L191:   athrow
L192:   invokevirtual Method java/io/ByteArrayOutputStream toByteArray ()[B
L195:   astore 8
L197:   getstatic Field Kc else LKc;
L200:   checkcast md
L203:   aload 8
L205:   invokevirtual Method md break ([B)Z
L208:   ifne L221
L211:   new java/lang/RuntimeException
L214:   dup
L215:   ldc "Invalid MD5 checksum"
L217:   invokespecial Method java/lang/RuntimeException <init> (Ljava/lang/String;)V
L220:   athrow
L221:   ldc "cultris2-setup-"
L223:   ldc ".exe"
L225:   invokestatic Method java/io/File createTempFile (Ljava/lang/String;Ljava/lang/String;)Ljava/io/File;
L228:   astore 7
L230:   ldc "upftr"
L232:   aload 7
L234:   invokevirtual Method java/io/File getAbsolutePath ()Ljava/lang/String;
L237:   invokestatic Method JB short (Ljava/lang/String;Ljava/lang/String;)V
L240:   new java/io/FileOutputStream
L243:   dup
L244:   aload 7
L246:   invokespecial Method java/io/FileOutputStream <init> (Ljava/io/File;)V
L249:   dup
L250:   astore_3
L251:   dup
L252:   aload 8
L254:   invokevirtual Method java/io/FileOutputStream write ([B)V
L257:   invokevirtual Method java/io/FileOutputStream close ()V
L260:   invokestatic Method JB new ()V
L263:   new oD
L266:   dup
L267:   aload_0
L268:   aload 7
L270:   invokespecial Method oD <init> (Ljd;Ljava/io/File;)V
L273:   invokestatic Method ib break (Ljava/lang/Runnable;)V
L276:   aload_2
L277:   ifnull L290
        .catch java/lang/Exception from L280 to L284 using L288
L280:   aload_2
L281:   invokevirtual Method java/net/HttpURLConnection disconnect ()V
L284:   aload_3
L285:   goto L291
L288:   astore 7
L290:   aload_3
L291:   ifnull L301
        .catch java/lang/Exception from L294 to L298 using L299
        .catch java/lang/Exception from L17 to L150 using L333
        .catch java/lang/Exception from L151 to L189 using L333
        .catch java/lang/Exception from L192 to L276 using L333
L294:   aload_3
L295:   invokevirtual Method java/io/FileOutputStream close ()V
L298:   return
L299:   astore 7
L301:   return
        .catch java/lang/Exception from L302 to L333 using L333
L302:   new java/io/IOException
L305:   dup
L306:   new java/lang/StringBuilder
L309:   dup
L310:   invokespecial Method java/lang/StringBuilder <init> ()V
L313:   iconst_0
L314:   ldc "HTTP error "
L316:   invokevirtual Method java/lang/StringBuilder insert (ILjava/lang/String;)Ljava/lang/StringBuilder;
L319:   aload_2
L320:   invokevirtual Method java/net/HttpURLConnection getResponseCode ()I
L323:   invokevirtual Method java/lang/StringBuilder append (I)Ljava/lang/StringBuilder;
L326:   invokevirtual Method java/lang/StringBuilder toString ()Ljava/lang/String;
L329:   invokespecial Method java/io/IOException <init> (Ljava/lang/String;)V
L332:   athrow
L333:   astore 4
L335:   aload 4
L337:   invokevirtual Method java/lang/Exception printStackTrace ()V
        .catch java/lang/InterruptedException from L340 to L346 using L350
L340:   ldc2_w 1000L
L343:   invokestatic Method java/lang/Thread sleep (J)V
L346:   aload_2
L347:   goto L390
L350:   astore 5
L352:   aload 5
L354:   invokevirtual Method java/lang/InterruptedException printStackTrace ()V
L357:   aload_2
L358:   ifnull L371
        .catch java/lang/Exception from L361 to L365 using L369
L361:   aload_2
L362:   invokevirtual Method java/net/HttpURLConnection disconnect ()V
L365:   aload_3
L366:   goto L372
L369:   astore 6
L371:   aload_3
L372:   ifnull L460
        .catch java/lang/Exception from L375 to L379 using L383
L375:   aload_3
L376:   invokevirtual Method java/io/FileOutputStream close ()V
L379:   aload_0
L380:   goto L461
L383:   astore 6
L385:   aload_0
L386:   goto L461
L389:   athrow
L390:   ifnull L403
        .catch java/lang/Exception from L393 to L397 using L401
L393:   aload_2
L394:   invokevirtual Method java/net/HttpURLConnection disconnect ()V
L397:   aload_3
L398:   goto L404
L401:   astore 4
L403:   aload_3
L404:   ifnull L453
        .catch java/lang/Exception from L407 to L411 using L414
        .catch [0] from L17 to L150 using L419
        .catch [0] from L151 to L189 using L419
        .catch [0] from L192 to L276 using L419
        .catch [0] from L302 to L357 using L419
L407:   aload_3
L408:   invokevirtual Method java/io/FileOutputStream close ()V
L411:   goto L453
L414:   astore 4
L416:   goto L453
L419:   astore 9
L421:   aload_2
L422:   ifnull L435
        .catch java/lang/Exception from L425 to L429 using L433
L425:   aload_2
L426:   invokevirtual Method java/net/HttpURLConnection disconnect ()V
L429:   aload_3
L430:   goto L436
L433:   astore 4
L435:   aload_3
L436:   ifnull L450
        .catch java/lang/Exception from L439 to L443 using L448
        .catch [0] from L419 to L421 using L419
L439:   aload_3
L440:   invokevirtual Method java/io/FileOutputStream close ()V
L443:   aload 9
L445:   goto L452
L448:   astore 4
L450:   aload 9
L452:   athrow
L453:   iinc 1 1
L456:   iload_1
L457:   goto L6
L460:   aload_0
L461:   getfield Field jd do LkB;
L464:   iconst_1
L465:   dup
L466:   dup
L467:   pop2
L468:   putfield Field kB new Z
L471:   return
L472:   
        .attribute StackMap b'\x00\x26\x00\x06\x00\x02\x07\x00\x02\x01\x00\x01\x01\x00\x54\x00\x04\x07\x00\x02\x01\x07\x00\x2E\x05\x00\x00\x00\x57\x00\x04\x07\x00\x02\x01\x07\x00\x2E\x05\x00\x01\x08\x00\x54\x00\x82\x00\x08\x07\x00\x02\x01\x07\x00\x2E\x05\x07\x00\x3F\x07\x00\xBB\x01\x01\x00\x00\x00\x83\x00\x08\x07\x00\x02\x01\x07\x00\x2E\x05\x07\x00\x3F\x07\x00\xBB\x01\x01\x00\x01\x07\x00\x2E\x00\x96\x00\x00\x00\x01\x07\x00\xBD\x00\x97\x00\x09\x07\x00\x02\x01\x07\x00\x2E\x05\x07\x00\x3F\x07\x00\xBB\x01\x01\x01\x00\x00\x00\xBD\x00\x00\x00\x01\x07\x00\xBD\x00\xC0\x00\x09\x07\x00\x02\x01\x07\x00\x2E\x05\x07\x00\x3F\x07\x00\xBB\x01\x01\x01\x00\x01\x07\x00\x3F\x00\xDD\x00\x09\x07\x00\x02\x01\x07\x00\x2E\x05\x07\x00\x3F\x07\x00\xBB\x01\x01\x07\x00\xBB\x00\x00\x01\x20\x00\x09\x07\x00\x02\x01\x07\x00\x2E\x07\x00\x82\x07\x00\x3F\x07\x00\xBB\x01\x07\x00\x71\x07\x00\xBB\x00\x01\x07\x00\x1B\x01\x22\x00\x09\x07\x00\x02\x01\x07\x00\x2E\x07\x00\x82\x07\x00\x3F\x07\x00\xBB\x01\x07\x00\xBF\x07\x00\xBB\x00\x00\x01\x23\x00\x09\x07\x00\x02\x01\x07\x00\x2E\x07\x00\x82\x07\x00\x3F\x07\x00\xBB\x01\x07\x00\xBF\x07\x00\xBB\x00\x01\x07\x00\x82\x01\x2B\x00\x09\x07\x00\x02\x01\x07\x00\x2E\x07\x00\x82\x07\x00\x3F\x07\x00\xBB\x01\x07\x00\xBF\x07\x00\xBB\x00\x01\x07\x00\x1B\x01\x2D\x00\x09\x07\x00\x02\x01\x07\x00\x2E\x07\x00\x82\x07\x00\x3F\x07\x00\xBB\x01\x07\x00\xBF\x07\x00\xBB\x00\x00\x01\x2E\x00\x04\x07\x00\x02\x01\x07\x00\x2E\x05\x00\x00\x01\x4D\x00\x04\x07\x00\x02\x01\x07\x00\x2E\x07\x00\x82\x00\x01\x07\x00\x1B\x01\x5E\x00\x05\x07\x00\x02\x01\x07\x00\x2E\x07\x00\x82\x07\x00\x1B\x00\x01\x07\x00\x1D\x01\x71\x00\x06\x07\x00\x02\x01\x07\x00\x2E\x07\x00\x82\x07\x00\x1B\x07\x00\x1D\x00\x01\x07\x00\x1B\x01\x73\x00\x06\x07\x00\x02\x01\x07\x00\x2E\x07\x00\x82\x07\x00\x1B\x07\x00\x1D\x00\x00\x01\x74\x00\x06\x07\x00\x02\x01\x07\x00\x2E\x07\x00\x82\x07\x00\x1B\x07\x00\x1D\x00\x01\x07\x00\x82\x01\x7F\x00\x06\x07\x00\x02\x01\x07\x00\x2E\x07\x00\x82\x07\x00\x1B\x07\x00\x1D\x00\x01\x07\x00\x1B\x01\x85\x00\x00\x00\x01\x07\x00\xBD\x01\x86\x00\x05\x07\x00\x02\x01\x07\x00\x2E\x07\x00\x82\x07\x00\x1B\x00\x01\x07\x00\x2E\x01\x91\x00\x05\x07\x00\x02\x01\x07\x00\x2E\x07\x00\x82\x07\x00\x1B\x00\x01\x07\x00\x1B\x01\x93\x00\x05\x07\x00\x02\x01\x07\x00\x2E\x07\x00\x82\x07\x00\x1B\x00\x00\x01\x94\x00\x05\x07\x00\x02\x01\x07\x00\x2E\x07\x00\x82\x07\x00\x1B\x00\x01\x07\x00\x82\x01\x9E\x00\x05\x07\x00\x02\x01\x07\x00\x2E\x07\x00\x82\x07\x00\x1B\x00\x01\x07\x00\x1B\x01\xA3\x00\x04\x07\x00\x02\x01\x07\x00\x2E\x07\x00\x82\x00\x01\x07\x00\xBD\x01\xB1\x00\x0A\x07\x00\x02\x01\x07\x00\x2E\x07\x00\x82\x00\x00\x00\x00\x00\x07\x00\xBD\x00\x01\x07\x00\x1B\x01\xB3\x00\x0A\x07\x00\x02\x01\x07\x00\x2E\x07\x00\x82\x00\x00\x00\x00\x00\x07\x00\xBD\x00\x00\x01\xB4\x00\x0A\x07\x00\x02\x01\x07\x00\x2E\x07\x00\x82\x00\x00\x00\x00\x00\x07\x00\xBD\x00\x01\x07\x00\x82\x01\xC0\x00\x0A\x07\x00\x02\x01\x07\x00\x2E\x07\x00\x82\x00\x00\x00\x00\x00\x07\x00\xBD\x00\x01\x07\x00\x1B\x01\xC2\x00\x0A\x07\x00\x02\x01\x07\x00\x2E\x07\x00\x82\x00\x00\x00\x00\x00\x07\x00\xBD\x00\x00\x01\xC4\x00\x0A\x07\x00\x02\x01\x07\x00\x2E\x07\x00\x82\x00\x00\x00\x00\x00\x07\x00\xBD\x00\x01\x07\x00\xBD\x01\xC5\x00\x05\x07\x00\x02\x01\x07\x00\x2E\x07\x00\x82\x07\x00\x1B\x00\x00\x01\xCC\x00\x02\x07\x00\x02\x01\x00\x00\x01\xCD\x00\x02\x07\x00\x02\x01\x00\x01\x07\x00\x02'
    .end code
    .runtime visible annotations
        .annotation Lme/coley/recaf/metadata/InsnComment;
            At_25 = string "Connect Timeout"
        .end annotation
        .annotation Lme/coley/recaf/metadata/InsnComment;
            At_29 = string "Read Timeout"
        .end annotation
    .end runtime
.end method
.innerclasses
    jd [0] [0]
    oD [0] [0]
.end innerclasses
.enclosing method kB "strictfp" ()V
.end class
