.version 49 0
.class public final super JD
.super vB
.field private field1056 LYg;
.field private field1057 LYg;
.field private field1058 LPc;
.field private field1059 Ljava/util/List;

.method public method10 : ()V
    .code stack 2 locals 1
L0:     aload_0
L1:     dup
L2:     getfield Field JD field1056 LYg;
L5:     invokevirtual Method JD try (LgB;)V
L8:     return
L9:     
    .end code
.end method

.method private method527 : (Lqc;Ljava/lang/String;Ljava/lang/String;Lff;)[LYg;
    .code stack 12 locals 8
L0:     new lG
L3:     dup
L4:     iconst_1
L5:     dup
L6:     pop2
L7:     iconst_4
L8:     iconst_1
L9:     dup
L10:    pop2
L11:    iconst_4
L12:    dup_x1
L13:    iconst_1
L14:    dup
L15:    pop2
L16:    iconst_0
L17:    iconst_1
L18:    dup
L19:    pop2
L20:    invokespecial Method lG <init> (IIIZ)V
L23:    astore 5
L25:    aload_0
L26:    ldc 1.1e0f
L28:    aload 5
L30:    dup_x1
L31:    dup_x2
L32:    ldc 1.1e0f
L34:    putfield Field lG field1128 F
L37:    putfield Field lG field1137 F
L40:    aload 4
L42:    aload_3
L43:    invokespecial Method JD method530 (LlG;Lff;Ljava/lang/String;)V
L46:    new qc
L49:    dup
L50:    new og
L53:    dup
L54:    iconst_2
L55:    iconst_1
L56:    dup
L57:    pop2
L58:    ldc 1e-1f
L60:    dup
L61:    invokespecial Method og <init> (IFF)V
L64:    invokespecial Method qc <init> (Ld;)V
L67:    astore 6
L69:    new Yg
L72:    aload 6
L74:    dup_x1
L75:    dup
L76:    pop2
L77:    dup
L78:    ldc "\u21C6"
L80:    ldc 4e-1f
L82:    new wC
L85:    dup
L86:    aload_0
L87:    aload_2
L88:    aload 5
L90:    aload 4
L92:    aload_3
L93:    invokespecial Method wC <init> (LJD;Ljava/lang/String;LlG;Lff;Ljava/lang/String;)V
L96:    invokespecial Method Yg <init> (Ljava/lang/String;FLh;)V
L99:    dup
L100:   astore_2
L101:   invokevirtual Method qc method36 (LgB;)LgB;
L104:   aload_0
L105:   getfield Field JD field1059 Ljava/util/List;
L108:   new fd
L111:   dup
L112:   aload_0
L113:   aload 5
L115:   aload 4
L117:   aload_3
L118:   invokespecial Method fd <init> (LJD;LlG;Lff;Ljava/lang/String;)V
L121:   invokeinterface InterfaceMethod java/util/List add (Ljava/lang/Object;)Z 2
L126:   aconst_null
L127:   astore 7
L129:   pop2
L130:   aload_3
L131:   ifnull L168
L134:   new Yg
L137:   aload 6
L139:   dup_x1
L140:   dup
L141:   pop2
L142:   dup
L143:   ldc "\u21BB"
L145:   new lD
L148:   dup
L149:   aload_0
L150:   aload_3
L151:   aload 5
L153:   aload 4
L155:   invokespecial Method lD <init> (LJD;Ljava/lang/String;LlG;Lff;)V
L158:   invokespecial Method Yg <init> (Ljava/lang/String;Lh;)V
L161:   dup
L162:   astore 7
L164:   invokevirtual Method qc method36 (LgB;)LgB;
L167:   pop
L168:   new qc
L171:   dup
L172:   new VD
L175:   dup
L176:   invokespecial Method VD <init> ()V
L179:   invokespecial Method qc <init> (Ld;)V
L182:   astore_3
L183:   iconst_2
L184:   aload_1
L185:   aload 6
L187:   aload_3
L188:   dup_x1
L189:   dup_x2
L190:   aload_3
L191:   aload 5
L193:   invokestatic Method Wd method1090 (LgB;)Lqc;
L196:   getstatic Field VD field150 Ljava/lang/Object;
L199:   invokevirtual Method qc method31 (LgB;Ljava/lang/Object;)V
L202:   new Vg
L205:   aload_3
L206:   dup
L207:   pop2
L208:   dup
L209:   fconst_0
L210:   ldc 2e-1f
L212:   invokespecial Method Vg <init> (FF)V
L215:   getstatic Field VD field147 Ljava/lang/Object;
L218:   invokevirtual Method qc method31 (LgB;Ljava/lang/Object;)V
L221:   getstatic Field VD field148 Ljava/lang/Object;
L224:   invokevirtual Method qc method31 (LgB;Ljava/lang/Object;)V
L227:   invokevirtual Method qc method36 (LgB;)LgB;
L230:   pop
L231:   iconst_1
L232:   dup
L233:   pop2
L234:   anewarray Yg
L237:   iconst_1
L238:   dup
L239:   pop2
L240:   dup
L241:   iconst_0
L242:   iconst_1
L243:   dup
L244:   pop2
L245:   aload_2
L246:   aastore
L247:   dup
L248:   iconst_1
L249:   dup
L250:   dup
L251:   pop2
L252:   aload 7
L254:   aastore
L255:   areturn
L256:   
        .attribute StackMap b'\x00\x01\x00\xA8\x00\x08\x07\x00\x02\x07\x00\x49\x07\x00\x54\x07\x00\x76\x07\x00\x78\x07\x00\x37\x07\x00\x49\x07\x00\x54\x00\x00'
    .end code
.end method

.method public static synthetic method528 : (LJD;)LFE;
    .code stack 1 locals 1
L0:     aload_0
L1:     getfield Field JD field1136 LFE;
L4:     areturn
L5:     
    .end code
.end method

.method public method49 : ()V
    .code stack 13 locals 8
L0:     new java/util/LinkedList
L3:     aload_0
L4:     dup_x1
L5:     dup
L6:     pop2
L7:     dup
L8:     invokespecial Method java/util/LinkedList <init> ()V
L11:    putfield Field JD field1059 Ljava/util/List;
L14:    new qc
L17:    dup
L18:    new og
L21:    dup
L22:    iconst_3
L23:    iconst_1
L24:    dup
L25:    pop2
L26:    ldc 1e-1f
L28:    dup
L29:    invokespecial Method og <init> (IFF)V
L32:    invokespecial Method qc <init> (Ld;)V
L35:    astore_1
L36:    new java/lang/StringBuilder
L39:    aload_1
L40:    dup_x1
L41:    dup_x2
L42:    dup
L43:    pop2
L44:    dup
L45:    invokespecial Method java/lang/StringBuilder <init> ()V
L48:    aload_0
L49:    getfield Field JD field1058 LPc;
L52:    getfield Field Pc field370 Ljava/lang/String;
L55:    invokevirtual Method java/lang/StringBuilder append (Ljava/lang/String;)Ljava/lang/StringBuilder;
L58:    ldc "h"
L60:    invokevirtual Method java/lang/StringBuilder append (Ljava/lang/String;)Ljava/lang/StringBuilder;
L63:    invokevirtual Method java/lang/StringBuilder toString ()Ljava/lang/String;
L66:    iconst_0
L67:    iconst_1
L68:    dup
L69:    pop2
L70:    bipush 19
L72:    iconst_1
L73:    dup
L74:    pop2
L75:    ldc2_w 5e-1
L78:    ldc "Delay"
L80:    ldc "Short"
L82:    ldc "Long"
L84:    iconst_1
L85:    dup
L86:    dup
L87:    pop2
L88:    invokestatic Method hB method1140 (Lqc;Ljava/lang/String;IIDLjava/lang/String;Ljava/lang/String;Ljava/lang/String;Z)LzD;
L91:    astore_2
L92:    new Vg
L95:    aload_1
L96:    dup
L97:    pop2
L98:    dup
L99:    invokespecial Method Vg <init> ()V
L102:   invokevirtual Method qc method36 (LgB;)LgB;
L105:   new java/lang/StringBuilder
L108:   aload_1
L109:   dup_x1
L110:   dup
L111:   pop2
L112:   dup
L113:   invokespecial Method java/lang/StringBuilder <init> ()V
L116:   aload_0
L117:   getfield Field JD field1058 LPc;
L120:   getfield Field Pc field370 Ljava/lang/String;
L123:   invokevirtual Method java/lang/StringBuilder append (Ljava/lang/String;)Ljava/lang/StringBuilder;
L126:   ldc "i"
L128:   invokevirtual Method java/lang/StringBuilder append (Ljava/lang/String;)Ljava/lang/StringBuilder;
L131:   invokevirtual Method java/lang/StringBuilder toString ()Ljava/lang/String;
L134:   iconst_0
L135:   iconst_1
L136:   dup
L137:   pop2
L138:   bipush 20
L140:   iconst_1
L141:   dup
L142:   pop2
L143:   ldc "Repeat speed"
L145:   new YC
L148:   dup
L149:   aload_0
L150:   invokespecial Method YC <init> (LJD;)V
L153:   ldc "Slow"
L155:   ldc "Fast"
L157:   iconst_1
L158:   dup
L159:   dup
L160:   pop2
L161:   invokestatic Method hB method1139 (Lqc;Ljava/lang/String;IILjava/lang/String;LE;Ljava/lang/String;Ljava/lang/String;Z)LzD;
L164:   astore_3
L165:   aload_0
L166:   getfield Field JD field1059 Ljava/util/List;
L169:   new Pd
L172:   dup
L173:   aload_0
L174:   aload_2
L175:   aload_3
L176:   invokespecial Method Pd <init> (LJD;LzD;LzD;)V
L179:   invokeinterface InterfaceMethod java/util/List add (Ljava/lang/Object;)Z 2
L184:   new qc
L187:   dup
L188:   new og
L191:   dup
L192:   iconst_3
L193:   iconst_1
L194:   dup
L195:   pop2
L196:   ldc 1e-1f
L198:   fconst_0
L199:   invokespecial Method og <init> (IFF)V
L202:   invokespecial Method qc <init> (Ld;)V
L205:   astore 4
L207:   new Yg
L210:   aload 4
L212:   dup_x1
L213:   dup
L214:   pop2
L215:   dup
L216:   ldc "Reset"
L218:   new gd
L221:   dup
L222:   aload_0
L223:   invokespecial Method gd <init> (LJD;)V
L226:   invokespecial Method Yg <init> (Ljava/lang/String;Lh;)V
L229:   dup
L230:   astore 5
L232:   invokevirtual Method qc method36 (LgB;)LgB;
L235:   pop
L236:   pop2
L237:   aload 4
L239:   new Yg
L242:   aload_0
L243:   dup_x1
L244:   dup
L245:   pop2
L246:   dup
L247:   ldc "Test"
L249:   new nB
L252:   dup
L253:   aload_0
L254:   invokespecial Method nB <init> (LJD;)V
L257:   invokespecial Method Yg <init> (Ljava/lang/String;Lh;)V
L260:   dup_x1
L261:   putfield Field JD field1057 LYg;
L264:   invokevirtual Method qc method36 (LgB;)LgB;
L267:   pop
L268:   aload 4
L270:   new Yg
L273:   aload_0
L274:   dup_x1
L275:   dup
L276:   pop2
L277:   dup
L278:   ldc "OK"
L280:   new ud
L283:   dup
L284:   aload_0
L285:   invokespecial Method ud <init> (LJD;)V
L288:   invokespecial Method Yg <init> (Ljava/lang/String;Lh;)V
L291:   dup_x1
L292:   putfield Field JD field1056 LYg;
L295:   invokevirtual Method qc method36 (LgB;)LgB;
L298:   new qc
L301:   dup
L302:   new og
L305:   dup
L306:   bipush 7
L308:   iconst_1
L309:   dup
L310:   pop2
L311:   ldc 3e-1f
L313:   fconst_0
L314:   invokespecial Method og <init> (IFF)V
L317:   invokespecial Method qc <init> (Ld;)V
L320:   astore 6
L322:   pop
L323:   bipush 7
L325:   iconst_1
L326:   dup
L327:   pop2
L328:   anewarray [LYg;
L331:   iconst_1
L332:   dup
L333:   pop2
L334:   dup
L335:   iconst_0
L336:   iconst_1
L337:   dup
L338:   pop2
L339:   new java/lang/StringBuilder
L342:   aload 6
L344:   dup_x1
L345:   dup
L346:   pop2
L347:   dup
L348:   invokespecial Method java/lang/StringBuilder <init> ()V
L351:   aload_0
L352:   dup_x2
L353:   getfield Field JD field1058 LPc;
L356:   getfield Field Pc field370 Ljava/lang/String;
L359:   invokevirtual Method java/lang/StringBuilder append (Ljava/lang/String;)Ljava/lang/StringBuilder;
L362:   ldc "co"
L364:   invokevirtual Method java/lang/StringBuilder append (Ljava/lang/String;)Ljava/lang/StringBuilder;
L367:   invokevirtual Method java/lang/StringBuilder toString ()Ljava/lang/String;
L370:   new Df
L373:   aconst_null
L374:   dup_x1
L375:   dup
L376:   pop2
L377:   dup
L378:   invokespecial Method Df <init> ()V
L381:   invokespecial Method JD method527 (Lqc;Ljava/lang/String;Ljava/lang/String;Lff;)[LYg;
L384:   aastore
L385:   dup
L386:   iconst_1
L387:   dup
L388:   dup
L389:   pop2
L390:   new java/lang/StringBuilder
L393:   aload 6
L395:   dup_x1
L396:   dup
L397:   pop2
L398:   dup
L399:   invokespecial Method java/lang/StringBuilder <init> ()V
L402:   aload_0
L403:   dup_x2
L404:   getfield Field JD field1058 LPc;
L407:   getfield Field Pc field370 Ljava/lang/String;
L410:   invokevirtual Method java/lang/StringBuilder append (Ljava/lang/String;)Ljava/lang/StringBuilder;
L413:   ldc "ci"
L415:   invokevirtual Method java/lang/StringBuilder append (Ljava/lang/String;)Ljava/lang/StringBuilder;
L418:   invokevirtual Method java/lang/StringBuilder toString ()Ljava/lang/String;
L421:   new java/lang/StringBuilder
L424:   dup
L425:   invokespecial Method java/lang/StringBuilder <init> ()V
L428:   iconst_0
L429:   aload_0
L430:   getfield Field JD field1058 LPc;
L433:   getfield Field Pc field370 Ljava/lang/String;
L436:   invokevirtual Method java/lang/StringBuilder insert (ILjava/lang/String;)Ljava/lang/StringBuilder;
L439:   ldc "si"
L441:   invokevirtual Method java/lang/StringBuilder append (Ljava/lang/String;)Ljava/lang/StringBuilder;
L444:   invokevirtual Method java/lang/StringBuilder toString ()Ljava/lang/String;
L447:   new tF
L450:   dup
L451:   invokespecial Method tF <init> ()V
L454:   invokespecial Method JD method527 (Lqc;Ljava/lang/String;Ljava/lang/String;Lff;)[LYg;
L457:   aastore
L458:   dup
L459:   iconst_2
L460:   iconst_1
L461:   dup
L462:   pop2
L463:   new java/lang/StringBuilder
L466:   aload 6
L468:   dup_x1
L469:   dup
L470:   pop2
L471:   dup
L472:   invokespecial Method java/lang/StringBuilder <init> ()V
L475:   aload_0
L476:   dup_x2
L477:   getfield Field JD field1058 LPc;
L480:   getfield Field Pc field370 Ljava/lang/String;
L483:   invokevirtual Method java/lang/StringBuilder append (Ljava/lang/String;)Ljava/lang/StringBuilder;
L486:   ldc "cl"
L488:   invokevirtual Method java/lang/StringBuilder append (Ljava/lang/String;)Ljava/lang/StringBuilder;
L491:   invokevirtual Method java/lang/StringBuilder toString ()Ljava/lang/String;
L494:   new java/lang/StringBuilder
L497:   dup
L498:   invokespecial Method java/lang/StringBuilder <init> ()V
L501:   iconst_0
L502:   aload_0
L503:   getfield Field JD field1058 LPc;
L506:   getfield Field Pc field370 Ljava/lang/String;
L509:   invokevirtual Method java/lang/StringBuilder insert (ILjava/lang/String;)Ljava/lang/StringBuilder;
L512:   ldc "sl"
L514:   invokevirtual Method java/lang/StringBuilder append (Ljava/lang/String;)Ljava/lang/StringBuilder;
L517:   invokevirtual Method java/lang/StringBuilder toString ()Ljava/lang/String;
L520:   new VF
L523:   dup
L524:   invokespecial Method VF <init> ()V
L527:   invokespecial Method JD method527 (Lqc;Ljava/lang/String;Ljava/lang/String;Lff;)[LYg;
L530:   aastore
L531:   dup
L532:   iconst_3
L533:   iconst_1
L534:   dup
L535:   pop2
L536:   new java/lang/StringBuilder
L539:   aload 6
L541:   dup_x1
L542:   dup
L543:   pop2
L544:   dup
L545:   invokespecial Method java/lang/StringBuilder <init> ()V
L548:   aload_0
L549:   dup_x2
L550:   getfield Field JD field1058 LPc;
L553:   getfield Field Pc field370 Ljava/lang/String;
L556:   invokevirtual Method java/lang/StringBuilder append (Ljava/lang/String;)Ljava/lang/StringBuilder;
L559:   ldc "cj"
L561:   invokevirtual Method java/lang/StringBuilder append (Ljava/lang/String;)Ljava/lang/StringBuilder;
L564:   invokevirtual Method java/lang/StringBuilder toString ()Ljava/lang/String;
L567:   new java/lang/StringBuilder
L570:   dup
L571:   invokespecial Method java/lang/StringBuilder <init> ()V
L574:   iconst_0
L575:   aload_0
L576:   getfield Field JD field1058 LPc;
L579:   getfield Field Pc field370 Ljava/lang/String;
L582:   invokevirtual Method java/lang/StringBuilder insert (ILjava/lang/String;)Ljava/lang/StringBuilder;
L585:   ldc "sj"
L587:   invokevirtual Method java/lang/StringBuilder append (Ljava/lang/String;)Ljava/lang/StringBuilder;
L590:   invokevirtual Method java/lang/StringBuilder toString ()Ljava/lang/String;
L593:   new AF
L596:   dup
L597:   invokespecial Method AF <init> ()V
L600:   invokespecial Method JD method527 (Lqc;Ljava/lang/String;Ljava/lang/String;Lff;)[LYg;
L603:   aastore
L604:   dup
L605:   iconst_4
L606:   iconst_1
L607:   dup
L608:   pop2
L609:   new java/lang/StringBuilder
L612:   aload 6
L614:   dup_x1
L615:   dup
L616:   pop2
L617:   dup
L618:   invokespecial Method java/lang/StringBuilder <init> ()V
L621:   aload_0
L622:   dup_x2
L623:   getfield Field JD field1058 LPc;
L626:   getfield Field Pc field370 Ljava/lang/String;
L629:   invokevirtual Method java/lang/StringBuilder append (Ljava/lang/String;)Ljava/lang/StringBuilder;
L632:   ldc_w "cs"
L635:   invokevirtual Method java/lang/StringBuilder append (Ljava/lang/String;)Ljava/lang/StringBuilder;
L638:   invokevirtual Method java/lang/StringBuilder toString ()Ljava/lang/String;
L641:   new java/lang/StringBuilder
L644:   dup
L645:   invokespecial Method java/lang/StringBuilder <init> ()V
L648:   iconst_0
L649:   aload_0
L650:   getfield Field JD field1058 LPc;
L653:   getfield Field Pc field370 Ljava/lang/String;
L656:   invokevirtual Method java/lang/StringBuilder insert (ILjava/lang/String;)Ljava/lang/StringBuilder;
L659:   ldc_w "ss"
L662:   invokevirtual Method java/lang/StringBuilder append (Ljava/lang/String;)Ljava/lang/StringBuilder;
L665:   invokevirtual Method java/lang/StringBuilder toString ()Ljava/lang/String;
L668:   new mE
L671:   dup
L672:   invokespecial Method mE <init> ()V
L675:   invokespecial Method JD method527 (Lqc;Ljava/lang/String;Ljava/lang/String;Lff;)[LYg;
L678:   aastore
L679:   dup
L680:   iconst_5
L681:   iconst_1
L682:   dup
L683:   pop2
L684:   new java/lang/StringBuilder
L687:   aload 6
L689:   dup_x1
L690:   dup
L691:   pop2
L692:   dup
L693:   invokespecial Method java/lang/StringBuilder <init> ()V
L696:   aload_0
L697:   dup_x2
L698:   getfield Field JD field1058 LPc;
L701:   getfield Field Pc field370 Ljava/lang/String;
L704:   invokevirtual Method java/lang/StringBuilder append (Ljava/lang/String;)Ljava/lang/StringBuilder;
L707:   ldc_w "cz"
L710:   invokevirtual Method java/lang/StringBuilder append (Ljava/lang/String;)Ljava/lang/StringBuilder;
L713:   invokevirtual Method java/lang/StringBuilder toString ()Ljava/lang/String;
L716:   new java/lang/StringBuilder
L719:   dup
L720:   invokespecial Method java/lang/StringBuilder <init> ()V
L723:   iconst_0
L724:   aload_0
L725:   getfield Field JD field1058 LPc;
L728:   getfield Field Pc field370 Ljava/lang/String;
L731:   invokevirtual Method java/lang/StringBuilder insert (ILjava/lang/String;)Ljava/lang/StringBuilder;
L734:   ldc_w "sz"
L737:   invokevirtual Method java/lang/StringBuilder append (Ljava/lang/String;)Ljava/lang/StringBuilder;
L740:   invokevirtual Method java/lang/StringBuilder toString ()Ljava/lang/String;
L743:   new Af
L746:   dup
L747:   invokespecial Method Af <init> ()V
L750:   invokespecial Method JD method527 (Lqc;Ljava/lang/String;Ljava/lang/String;Lff;)[LYg;
L753:   aastore
L754:   dup
L755:   bipush 6
L757:   iconst_1
L758:   dup
L759:   pop2
L760:   new java/lang/StringBuilder
L763:   aload 6
L765:   dup_x1
L766:   dup
L767:   pop2
L768:   dup
L769:   invokespecial Method java/lang/StringBuilder <init> ()V
L772:   aload_0
L773:   dup_x2
L774:   getfield Field JD field1058 LPc;
L777:   getfield Field Pc field370 Ljava/lang/String;
L780:   invokevirtual Method java/lang/StringBuilder append (Ljava/lang/String;)Ljava/lang/StringBuilder;
L783:   ldc_w "ct"
L786:   invokevirtual Method java/lang/StringBuilder append (Ljava/lang/String;)Ljava/lang/StringBuilder;
L789:   invokevirtual Method java/lang/StringBuilder toString ()Ljava/lang/String;
L792:   new java/lang/StringBuilder
L795:   dup
L796:   invokespecial Method java/lang/StringBuilder <init> ()V
L799:   iconst_0
L800:   aload_0
L801:   getfield Field JD field1058 LPc;
L804:   getfield Field Pc field370 Ljava/lang/String;
L807:   invokevirtual Method java/lang/StringBuilder insert (ILjava/lang/String;)Ljava/lang/StringBuilder;
L810:   ldc_w "st"
L813:   invokevirtual Method java/lang/StringBuilder append (Ljava/lang/String;)Ljava/lang/StringBuilder;
L816:   invokevirtual Method java/lang/StringBuilder toString ()Ljava/lang/String;
L819:   new TE
L822:   dup
L823:   invokespecial Method TE <init> ()V
L826:   invokespecial Method JD method527 (Lqc;Ljava/lang/String;Ljava/lang/String;Lff;)[LYg;
L829:   aastore
L830:   invokestatic Method OC method992 ([[LYg;)[LYg;
L833:   astore 7
L835:   iconst_4
L836:   iconst_1
L837:   dup
L838:   pop2
L839:   anewarray [LgB;
L842:   iconst_1
L843:   dup
L844:   pop2
L845:   dup
L846:   iconst_0
L847:   iconst_1
L848:   dup
L849:   pop2
L850:   aload 7
L852:   aastore
L853:   dup
L854:   iconst_1
L855:   dup
L856:   pop2
L857:   bipush 14
L859:   iconst_1
L860:   dup_x1
L861:   dup
L862:   pop2
L863:   anewarray gB
L866:   iconst_1
L867:   dup
L868:   pop2
L869:   dup
L870:   iconst_0
L871:   iconst_1
L872:   dup
L873:   pop2
L874:   aload_2
L875:   aastore
L876:   dup
L877:   iconst_1
L878:   dup
L879:   dup
L880:   pop2
L881:   aload_2
L882:   aastore
L883:   dup
L884:   iconst_2
L885:   iconst_1
L886:   dup
L887:   pop2
L888:   aload_2
L889:   aastore
L890:   dup
L891:   iconst_3
L892:   iconst_1
L893:   dup
L894:   pop2
L895:   aload_2
L896:   aastore
L897:   dup
L898:   iconst_4
L899:   iconst_1
L900:   dup
L901:   pop2
L902:   aload_2
L903:   aastore
L904:   dup
L905:   iconst_5
L906:   iconst_1
L907:   dup
L908:   pop2
L909:   aload_2
L910:   aastore
L911:   dup
L912:   bipush 6
L914:   iconst_1
L915:   dup
L916:   pop2
L917:   aload_2
L918:   aastore
L919:   dup
L920:   bipush 7
L922:   iconst_1
L923:   dup
L924:   pop2
L925:   aload_3
L926:   aastore
L927:   dup
L928:   bipush 8
L930:   iconst_1
L931:   dup
L932:   pop2
L933:   aload_3
L934:   aastore
L935:   dup
L936:   bipush 9
L938:   iconst_1
L939:   dup
L940:   pop2
L941:   aload_3
L942:   aastore
L943:   dup
L944:   bipush 10
L946:   iconst_1
L947:   dup
L948:   pop2
L949:   aload_3
L950:   aastore
L951:   dup
L952:   bipush 11
L954:   iconst_1
L955:   dup
L956:   pop2
L957:   aload_3
L958:   aastore
L959:   dup
L960:   bipush 12
L962:   iconst_1
L963:   dup
L964:   pop2
L965:   aload_3
L966:   aastore
L967:   dup
L968:   bipush 13
L970:   iconst_1
L971:   dup
L972:   pop2
L973:   aload_3
L974:   aastore
L975:   aastore
L976:   dup
L977:   iconst_2
L978:   iconst_1
L979:   dup
L980:   pop2
L981:   bipush 14
L983:   iconst_1
L984:   dup
L985:   pop2
L986:   anewarray gB
L989:   iconst_1
L990:   dup
L991:   pop2
L992:   dup
L993:   iconst_0
L994:   iconst_1
L995:   dup
L996:   pop2
L997:   aload 5
L999:   aastore
L1000:  dup
L1001:  iconst_1
L1002:  dup
L1003:  dup
L1004:  pop2
L1005:  aload_0
L1006:  getfield Field JD field1057 LYg;
L1009:  aastore
L1010:  dup
L1011:  iconst_2
L1012:  iconst_1
L1013:  dup
L1014:  pop2
L1015:  aload_0
L1016:  getfield Field JD field1056 LYg;
L1019:  aastore
L1020:  dup
L1021:  iconst_3
L1022:  iconst_1
L1023:  dup
L1024:  pop2
L1025:  aload_0
L1026:  getfield Field JD field1056 LYg;
L1029:  aastore
L1030:  dup
L1031:  iconst_4
L1032:  iconst_1
L1033:  dup
L1034:  pop2
L1035:  aload_0
L1036:  getfield Field JD field1056 LYg;
L1039:  aastore
L1040:  dup
L1041:  iconst_5
L1042:  iconst_1
L1043:  dup
L1044:  pop2
L1045:  aload_0
L1046:  getfield Field JD field1056 LYg;
L1049:  aastore
L1050:  dup
L1051:  bipush 6
L1053:  iconst_1
L1054:  dup
L1055:  pop2
L1056:  aload_0
L1057:  getfield Field JD field1056 LYg;
L1060:  aastore
L1061:  dup
L1062:  bipush 7
L1064:  iconst_1
L1065:  dup
L1066:  pop2
L1067:  aload_0
L1068:  getfield Field JD field1056 LYg;
L1071:  aastore
L1072:  dup
L1073:  bipush 8
L1075:  iconst_1
L1076:  dup
L1077:  pop2
L1078:  aload_0
L1079:  getfield Field JD field1056 LYg;
L1082:  aastore
L1083:  dup
L1084:  bipush 9
L1086:  iconst_1
L1087:  dup
L1088:  pop2
L1089:  aload_0
L1090:  getfield Field JD field1056 LYg;
L1093:  aastore
L1094:  dup
L1095:  bipush 10
L1097:  iconst_1
L1098:  dup
L1099:  pop2
L1100:  aload_0
L1101:  getfield Field JD field1056 LYg;
L1104:  aastore
L1105:  dup
L1106:  bipush 11
L1108:  iconst_1
L1109:  dup
L1110:  pop2
L1111:  aload_0
L1112:  getfield Field JD field1056 LYg;
L1115:  aastore
L1116:  dup
L1117:  bipush 12
L1119:  iconst_1
L1120:  dup
L1121:  pop2
L1122:  aload_0
L1123:  getfield Field JD field1056 LYg;
L1126:  aastore
L1127:  dup
L1128:  bipush 13
L1130:  iconst_1
L1131:  dup
L1132:  pop2
L1133:  aload_0
L1134:  getfield Field JD field1056 LYg;
L1137:  aastore
L1138:  aastore
L1139:  dup
L1140:  iconst_3
L1141:  iconst_1
L1142:  dup
L1143:  pop2
L1144:  aload 7
L1146:  aastore
L1147:  invokestatic Method mC method1702 ([[LgB;)V
L1150:  new qc
L1153:  dup
L1154:  new fG
L1157:  dup
L1158:  getstatic Field LE field634 LLE;
L1161:  ldc 1e-1f
L1163:  invokespecial Method fG <init> (LLE;F)V
L1166:  invokespecial Method qc <init> (Ld;)V
L1169:  astore_2
L1170:  new DF
L1173:  aload_2
L1174:  dup_x1
L1175:  dup
L1176:  pop2
L1177:  dup
L1178:  ldc_w "Blocks"
L1181:  invokespecial Method DF <init> (Ljava/lang/String;)V
L1184:  invokevirtual Method qc method36 (LgB;)LgB;
L1187:  new SB
L1190:  aload_2
L1191:  dup_x1
L1192:  dup_x2
L1193:  dup
L1194:  pop2
L1195:  dup
L1196:  aload 6
L1198:  fconst_1
L1199:  fconst_0
L1200:  dup
L1201:  dup_x1
L1202:  invokespecial Method SB <init> (LgB;FFFF)V
L1205:  getstatic Field dg field337 Ldg;
L1208:  invokevirtual Method qc method31 (LgB;Ljava/lang/Object;)V
L1211:  new Vg
L1214:  aload_2
L1215:  dup
L1216:  pop2
L1217:  dup
L1218:  fconst_0
L1219:  ldc_w 5e-1f
L1222:  invokespecial Method Vg <init> (FF)V
L1225:  invokevirtual Method qc method36 (LgB;)LgB;
L1228:  new DF
L1231:  aload_2
L1232:  dup_x1
L1233:  dup
L1234:  pop2
L1235:  dup
L1236:  ldc_w "Keyboard"
L1239:  invokespecial Method DF <init> (Ljava/lang/String;)V
L1242:  invokevirtual Method qc method36 (LgB;)LgB;
L1245:  new SB
L1248:  aload_2
L1249:  dup_x1
L1250:  dup_x1
L1251:  dup
L1252:  pop2
L1253:  dup
L1254:  aload_1
L1255:  fconst_1
L1256:  fconst_0
L1257:  dup
L1258:  dup_x1
L1259:  invokespecial Method SB <init> (LgB;FFFF)V
L1262:  getstatic Field dg field337 Ldg;
L1265:  invokevirtual Method qc method31 (LgB;Ljava/lang/Object;)V
L1268:  new SB
L1271:  aload_2
L1272:  dup
L1273:  pop2
L1274:  dup
L1275:  aload 4
L1277:  ldc_w 5e-1f
L1280:  fconst_0
L1281:  dup
L1282:  dup_x2
L1283:  invokespecial Method SB <init> (LgB;FFFF)V
L1286:  getstatic Field dg field335 Ldg;
L1289:  invokevirtual Method qc method31 (LgB;Ljava/lang/Object;)V
L1292:  new SB
L1295:  aload_0
L1296:  dup_x1
L1297:  dup
L1298:  pop2
L1299:  dup
L1300:  aload_2
L1301:  fconst_2
L1302:  fconst_0
L1303:  invokespecial Method SB <init> (LgB;FF)V
L1306:  invokestatic Method Wd method1093 (LgB;)Lqc;
L1309:  invokevirtual Method JD method36 (LgB;)LgB;
L1312:  pop2
L1313:  pop2
L1314:  return
L1315:  
    .end code
.end method

.method public static synthetic method529 : (LJD;LlG;Lff;Ljava/lang/String;)V
    .code stack 4 locals 4
L0:     aload_0
L1:     aload_1
L2:     aload_2
L3:     aload_3
L4:     invokespecial Method JD method530 (LlG;Lff;Ljava/lang/String;)V
L7:     return
L8:     
    .end code
.end method

.method public method57 : (LgB;IC)Z
    .code stack 4 locals 4
L0:     iload_2
L1:     iconst_1
L2:     dup
L3:     dup
L4:     pop2
L5:     if_icmpne L16
L8:     aload_0
L9:     getfield Field JD field1136 LFE;
L12:    aload_0
L13:    invokevirtual Method FE method203 (LbC;)V
L16:    iconst_1
L17:    dup
L18:    dup
L19:    pop2
L20:    ireturn
L21:    
        .attribute StackMap b'\x00\x01\x00\x10\x00\x04\x07\x00\x02\x07\x01\x1F\x01\x01\x00\x00'
    .end code
.end method

.method private method530 : (LlG;Lff;Ljava/lang/String;)V
    .code stack 5 locals 5
L0:     aload_2
L1:     invokevirtual Method ff method469 ()Lff;
L4:     astore 4
L6:     aload_3
L7:     aload 4
L9:     aload_0
L10:    getfield Field JD field1058 LPc;
L13:    invokestatic Method bD method391 (LPc;)LbD;
L16:    aload_2
L17:    invokevirtual Method bD method390 (Lff;)I
L20:    invokevirtual Method ff method14 (I)V
L23:    ifnull L52
L26:    iconst_0
L27:    iconst_1
L28:    dup
L29:    pop2
L30:    dup
L31:    istore_2
L32:    aload_3
L33:    invokestatic Method JB method831 (Ljava/lang/String;)I
L36:    if_icmpge L52
L39:    iinc 2 1
L42:    aload 4
L44:    invokevirtual Method ff method74 ()V
L47:    iload_2
L48:    goto L32
L51:    athrow
L52:    aload_1
L53:    iconst_4
L54:    aload_1
L55:    aload 4
L57:    getfield Field ff this [[I
L60:    invokevirtual Method lG method471 ([[I)V
L63:    iconst_1
L64:    dup
L65:    pop2
L66:    aload 4
L68:    getfield Field ff this [[I
L71:    arraylength
L72:    isub
L73:    i2f
L74:    fconst_2
L75:    fdiv
L76:    iconst_4
L77:    iconst_1
L78:    dup
L79:    pop2
L80:    aload 4
L82:    getfield Field ff this [[I
L85:    arraylength
L86:    isub
L87:    i2f
L88:    fconst_2
L89:    fdiv
L90:    invokevirtual Method lG this (FF)V
L93:    return
L94:    
        .attribute StackMap b'\x00\x03\x00\x20\x00\x05\x07\x00\x02\x07\x00\x37\x01\x07\x00\x76\x07\x00\x78\x00\x01\x01\x00\x33\x00\x00\x00\x01\x07\x01\x6D\x00\x34\x00\x05\x07\x00\x02\x07\x00\x37\x00\x07\x00\x76\x07\x00\x78\x00\x00'
    .end code
.end method

.method public static synthetic method531 : (LJD;)LFE;
    .code stack 1 locals 1
L0:     aload_0
L1:     getfield Field JD field1136 LFE;
L4:     areturn
L5:     
    .end code
.end method

.method public <init> : (LPc;)V
    .code stack 3 locals 2
L0:     aload_1
L1:     aload_0
L2:     dup_x1
L3:     invokespecial Method vB <init> ()V
L6:     putfield Field JD field1058 LPc;
L9:     return
L10:    
    .end code
.end method

.method public static synthetic method532 : (LJD;)LPc;
    .code stack 1 locals 1
L0:     aload_0
L1:     getfield Field JD field1058 LPc;
L4:     areturn
L5:     
    .end code
.end method

.method public static synthetic method533 : (LJD;)Ljava/util/List;
    .code stack 1 locals 1
L0:     aload_0
L1:     getfield Field JD field1059 Ljava/util/List;
L4:     areturn
L5:     
    .end code
.end method
.innerclasses
    LE fG [0] public static final enum
    Pc JB [0] public static final enum
    Pd [0] [0]
    YC [0] [0]
    dg fG [0] public static final enum
    fd [0] [0]
    gd [0] [0]
    hB Lc [0] static
    lD [0] [0]
    nB [0] [0]
    ud [0] [0]
    wC [0] [0]
    E hB [0] static interface abstract
.end innerclasses
.end class
