.version 49 0
.class public final super JE
.super java/lang/Object
.implements D
.field public this F
.field public char I
.field public else I
.field public "enum" Ljava/util/List;
.field public do F

.method public break : (LAC;)V
    .code stack 6 locals 3
L0:     aload_1
L1:     aload_0
L2:     dup_x1
L3:     aload_1
L4:     aload_0
L5:     getfield Field JE else I
L8:     invokevirtual Method AC break (I)V
L11:    getfield Field JE "enum" Ljava/util/List;
L14:    invokeinterface InterfaceMethod java/util/List size ()I 1
L19:    invokevirtual Method AC break (I)V
L22:    getfield Field JE "enum" Ljava/util/List;
L25:    invokeinterface InterfaceMethod java/util/List iterator ()Ljava/util/Iterator; 1
L30:    dup
L31:    astore_2
L32:    invokeinterface InterfaceMethod java/util/Iterator hasNext ()Z 1
L37:    ifeq L58
L40:    aload_2
L41:    invokeinterface InterfaceMethod java/util/Iterator next ()Ljava/lang/Object; 1
L46:    checkcast ce
L49:    aload_1
L50:    invokevirtual Method ce break (LAC;)V
L53:    aload_2
L54:    goto L32
L57:    athrow
L58:    aload_1
L59:    dup
L60:    aload_0
L61:    dup_x1
L62:    aload_1
L63:    aload_0
L64:    getfield Field JE char I
L67:    invokevirtual Method AC short (I)V
L70:    getfield Field JE do F
L73:    invokevirtual Method AC break (F)V
L76:    getfield Field JE this F
L79:    invokevirtual Method AC break (F)V
L82:    return
L83:    
        .attribute StackMap b'\x00\x03\x00\x20\x00\x03\x07\x00\x02\x07\x00\x18\x07\x00\x29\x00\x01\x07\x00\x29\x00\x39\x00\x00\x00\x01\x07\x00\x35\x00\x3A\x00\x03\x07\x00\x02\x07\x00\x18\x07\x00\x29\x00\x00'
    .end code
    .exceptions java/io/IOException
.end method

.method public <init> : (IIFFLjava/util/List;)V
    .code stack 11 locals 6
L0:     aload 5
L2:     aload_0
L3:     dup_x1
L4:     fload 4
L6:     fload_3
L7:     aload_0
L8:     dup_x1
L9:     iload_2
L10:    iload_1
L11:    aload_0
L12:    dup_x1
L13:    invokespecial Method java/lang/Object <init> ()V
L16:    putfield Field JE else I
L19:    putfield Field JE char I
L22:    putfield Field JE do F
L25:    putfield Field JE this F
L28:    putfield Field JE "enum" Ljava/util/List;
L31:    return
L32:    
    .end code
.end method

.method public <init> : (LMd;)V
    .code stack 6 locals 4
L0:     aload_1
L1:     dup
L2:     aload_0
L3:     dup_x1
L4:     invokespecial Method java/lang/Object <init> ()V
L7:     invokevirtual Method Md long ()I
L10:    putfield Field JE else I
L13:    invokevirtual Method Md long ()I
L16:    istore_2
L17:    new java/util/ArrayList
L20:    aload_0
L21:    dup_x1
L22:    dup
L23:    pop2
L24:    dup
L25:    iload_2
L26:    invokespecial Method java/util/ArrayList <init> (I)V
L29:    putfield Field JE "enum" Ljava/util/List;
L32:    iconst_0
L33:    iconst_1
L34:    dup
L35:    pop2
L36:    dup
L37:    istore_3
L38:    iload_2
L39:    if_icmpge L68
L42:    aload_0
L43:    getfield Field JE "enum" Ljava/util/List;
L46:    new ce
L49:    dup
L50:    iinc 3 1
L53:    aload_1
L54:    invokespecial Method ce <init> (LMd;)V
L57:    invokeinterface InterfaceMethod java/util/List add (Ljava/lang/Object;)Z 2
L62:    pop
L63:    iload_3
L64:    goto L38
L67:    athrow
L68:    aload_0
L69:    dup
L70:    aload_1
L71:    dup_x1
L72:    aload_0
L73:    aload_1
L74:    invokevirtual Method Md char ()I
L77:    putfield Field JE char I
L80:    invokevirtual Method Md "enum" ()F
L83:    putfield Field JE do F
L86:    invokevirtual Method Md "enum" ()F
L89:    putfield Field JE this F
L92:    return
L93:    
        .attribute StackMap b'\x00\x03\x00\x26\x00\x04\x07\x00\x02\x07\x00\x49\x01\x01\x00\x01\x01\x00\x43\x00\x00\x00\x01\x07\x00\x35\x00\x44\x00\x04\x07\x00\x02\x07\x00\x49\x01\x01\x00\x00'
    .end code
    .exceptions java/io/IOException
.end method
.innerclasses
    ce JE [0] public static
.end innerclasses
.end class
