.version 49 0
.class public final super kF
.super java/lang/Object
.implements java/util/Comparator
.field public final synthetic field1347 LuF;

.method public <init> : (LuF;)V
    .code stack 3 locals 2
L0:     aload_0
L1:     dup
L2:     aload_1
L3:     putfield Field kF field1347 LuF;
L6:     invokespecial Method java/lang/Object <init> ()V
L9:     return
L10:    
    .end code
.end method

.method public bridge synthetic compare : (Ljava/lang/Object;Ljava/lang/Object;)I
    .code stack 3 locals 3
L0:     aload_0
L1:     aload_1
L2:     checkcast gB
L5:     aload_2
L6:     checkcast gB
L9:     invokevirtual Method kF method696 (LgB;LgB;)I
L12:    ireturn
L13:    
    .end code
.end method

.method public method696 : (LgB;LgB;)I
    .code stack 2 locals 4
L0:     aload_1
L1:     checkcast Ke
L4:     invokevirtual Method Ke method1 ()Lqd;
L7:     astore_3
L8:     aload_2
L9:     checkcast Ke
L12:    invokevirtual Method Ke method1 ()Lqd;
L15:    astore_2
L16:    aload_3
L17:    getfield Field qd field737 B
L20:    aload_2
L21:    getfield Field qd field737 B
L24:    if_icmpeq L38
L27:    aload_3
L28:    getfield Field qd field737 B
L31:    aload_2
L32:    getfield Field qd field737 B
L35:    isub
L36:    ireturn
L37:    athrow
L38:    aload_3
L39:    getfield Field qd this Ljava/lang/String;
L42:    aload_2
L43:    getfield Field qd this Ljava/lang/String;
L46:    invokevirtual Method java/lang/String compareTo (Ljava/lang/String;)I
L49:    ireturn
L50:    
        .attribute StackMap b'\x00\x02\x00\x25\x00\x00\x00\x01\x07\x00\x29\x00\x26\x00\x04\x07\x00\x02\x07\x00\x19\x07\x00\x23\x07\x00\x23\x00\x00'
    .end code
.end method
.innerclasses
    Ke uF [0] private
    kF [0] [0]
.end innerclasses
.enclosing method uF method52 ()V
.end class
