.version 49 0
.class public final super Lb
.super java/lang/Object
.implements K
.field public final synthetic field1746 LCC;
.field public final synthetic field1747 LjC;
.field public final synthetic field1748 Lqd;

.method public bridge synthetic method735 : (Ljava/lang/Object;LKD;)V
    .code stack 3 locals 3
L0:     aload_0
L1:     aload_1
L2:     checkcast Rg
L5:     aload_2
L6:     invokevirtual Method Lb method736 (LRg;LKD;)V
L9:     return
L10:    
    .end code
.end method

.method public <init> : (LCC;LjC;Lqd;)V
    .code stack 7 locals 4
L0:     aload_3
L1:     aload_0
L2:     dup_x1
L3:     dup_x2
L4:     aload_2
L5:     aload_0
L6:     aload_1
L7:     putfield Field Lb field1746 LCC;
L10:    putfield Field Lb field1747 LjC;
L13:    putfield Field Lb field1748 Lqd;
L16:    invokespecial Method java/lang/Object <init> ()V
L19:    return
L20:    
    .end code
.end method

.method public method736 : (LRg;LKD;)V
    .code stack 5 locals 3
L0:     aload_0
L1:     getfield Field Lb field1746 LCC;
L4:     invokestatic Method CC new (LCC;)LFE;
L7:     aload_0
L8:     dup_x1
L9:     getfield Field Lb field1747 LjC;
L12:    invokevirtual Method FE method458 (LjC;)V
L15:    getfield Field Lb field1746 LCC;
L18:    getstatic Field dc field2207 Ljava/util/HashMap;
L21:    aload_2
L22:    invokevirtual Method java/util/HashMap get (Ljava/lang/Object;)Ljava/lang/Object;
L25:    checkcast java/lang/String
L28:    iconst_0
L29:    iconst_1
L30:    dup
L31:    pop2
L32:    invokevirtual Method CC method72 (Ljava/lang/String;Z)V
L35:    return
L36:    
    .end code
.end method

.method public method737 : (LRg;)V
    .code stack 5 locals 2
L0:     aload_0
L1:     dup
L2:     dup_x1
L3:     getfield Field Lb field1746 LCC;
L6:     invokestatic Method CC true (LCC;)LFE;
L9:     aload_0
L10:    dup_x2
L11:    getfield Field Lb field1747 LjC;
L14:    invokevirtual Method FE method458 (LjC;)V
L17:    getfield Field Lb field1746 LCC;
L20:    invokestatic Method CC method180 (LCC;)Lsb;
L23:    aload_0
L24:    getfield Field Lb field1748 Lqd;
L27:    invokevirtual Method sb method142 (Lqd;)V
L30:    getfield Field Lb field1746 LCC;
L33:    invokestatic Method CC method170 (LCC;)LYg;
L36:    iconst_1
L37:    dup
L38:    dup
L39:    pop2
L40:    invokevirtual Method Yg method238 (Z)V
L43:    getfield Field Lb field1746 LCC;
L46:    aload_0
L47:    getfield Field Lb field1748 Lqd;
L50:    getfield Field qd new Ljava/util/LinkedHashMap;
L53:    invokevirtual Method java/util/LinkedHashMap size ()I
L56:    invokevirtual Method CC method125 (I)V
L59:    return
L60:    
    .end code
.end method

.method public bridge synthetic method734 : (Ljava/lang/Object;)V
    .code stack 2 locals 2
L0:     aload_0
L1:     aload_1
L2:     checkcast Rg
L5:     invokevirtual Method Lb method737 (LRg;)V
L8:     return
L9:     
    .end code
.end method
.innerclasses
    Lb [0] [0]
    KD K [0] public static final enum
.end innerclasses
.enclosing method CC method146 (Lqd;)V
.end class
