.version 49 0
.class public final super lE
.super Uf
.field public field1384 F

.method public <init> : (Ljava/lang/String;Ljava/lang/String;Ljava/lang/String;FIZ)V
    .code stack 9 locals 7
L0:     fload 4
L2:     aload_0
L3:     dup_x1
L4:     aload_1
L5:     aload_2
L6:     aload_3
L7:     aconst_null
L8:     iload 5
L10:    iload 6
L12:    invokespecial Method Uf <init> (Ljava/lang/String;Ljava/lang/String;Ljava/lang/String;Ljava/lang/String;IZ)V
L15:    putfield Field lE field1384 F
L18:    return
L19:    
    .end code
.end method

.method public method704 : (LRg;)Z
    .code stack 4 locals 2
L0:     aload_1
L1:     getfield Field Rg field239 Lqd;
L4:     getfield Field qd field763 LQB;
L7:     getstatic Field QB field367 LQB;
L10:    if_acmpne L62
L13:    aload_1
L14:    invokevirtual Method Rg new ()I
L17:    iconst_2
L18:    iconst_1
L19:    dup
L20:    pop2
L21:    if_icmpne L62
L24:    aload_1
L25:    getfield Field Rg field239 Lqd;
L28:    getfield Field qd field766 Ljava/util/Map;
L31:    invokeinterface InterfaceMethod java/util/Map size ()I 1
L36:    bipush 6
L38:    iconst_1
L39:    dup
L40:    pop2
L41:    if_icmple L62
L44:    aload_1
L45:    getfield Field Rg field241 F
L48:    aload_0
L49:    getfield Field lE field1384 F
L52:    fcmpl
L53:    ifle L62
L56:    iconst_1
L57:    dup
L58:    dup
L59:    pop2
L60:    ireturn
L61:    athrow
L62:    iconst_0
L63:    iconst_1
L64:    dup
L65:    pop2
L66:    ireturn
L67:    
        .attribute StackMap b'\x00\x02\x00\x3D\x00\x00\x00\x01\x07\x00\x32\x00\x3E\x00\x02\x07\x00\x02\x07\x00\x15\x00\x00'
    .end code
.end method
.innerclasses
    QB qd [0] public static final enum
.end innerclasses
.end class
