.version 49 0
.class public final super Le
.super Uf

.method public break : (LRg;[[ILff;[I)Z
    .code stack 7 locals 5
L0:     iconst_0
L1:     iconst_1
L2:     dup
L3:     pop2
L4:     dup
L5:     istore_2
L6:     bipush 28
L8:     iconst_1
L9:     dup
L10:    pop2
L11:    if_icmpge L89
L14:    iconst_0
L15:    iconst_1
L16:    dup
L17:    pop2
L18:    dup
L19:    istore 4
L21:    bipush 10
L23:    iconst_1
L24:    dup
L25:    pop2
L26:    if_icmpge L81
L29:    aload_1
L30:    getfield Field Rg this [[I
L33:    iload 4
L35:    aaload
L36:    iload_2
L37:    iaload
L38:    ifeq L72
L41:    aload_1
L42:    getfield Field Rg this [[I
L45:    iload 4
L47:    aaload
L48:    bipush 12
L50:    iconst_1
L51:    dup
L52:    pop2
L53:    aload_1
L54:    getfield Field Rg this [[I
L57:    iload 4
L59:    aaload
L60:    iload_2
L61:    dup_x2
L62:    iaload
L63:    sipush 3840
L66:    iconst_1
L67:    dup
L68:    pop2
L69:    iand
L70:    ior
L71:    iastore
L72:    iinc 4 1
L75:    iload 4
L77:    goto L21
L80:    athrow
L81:    iinc 2 1
L84:    iload_2
L85:    goto L6
L88:    athrow
L89:    getstatic Field ZF const Lsb;
L92:    dup
L93:    astore_2
L94:    ifnull L187
L97:    aload_2
L98:    aload_1
L99:    invokevirtual Method sb else (LRg;)LLD;
L102:   dup
L103:   astore 4
L105:   ifnull L187
L108:   iconst_0
L109:   iconst_1
L110:   dup
L111:   pop2
L112:   dup
L113:   istore_1
L114:   aload_3
L115:   getfield Field ff this [[I
L118:   arraylength
L119:   if_icmpge L187
L122:   iconst_0
L123:   iconst_1
L124:   dup
L125:   pop2
L126:   dup
L127:   istore_2
L128:   aload_3
L129:   getfield Field ff this [[I
L132:   arraylength
L133:   if_icmpge L180
L136:   aload_3
L137:   getfield Field ff this [[I
L140:   iload_2
L141:   aaload
L142:   iload_1
L143:   iaload
L144:   ifeq L173
L147:   aload 4
L149:   getfield Field LD void LlG;
L152:   iload_2
L153:   aload_3
L154:   getfield Field ff else I
L157:   iadd
L158:   iload_1
L159:   aload_3
L160:   getfield Field ff do I
L163:   iadd
L164:   aload_3
L165:   getfield Field ff "enum" I
L168:   ldc 4e0f
L170:   invokevirtual Method lG break (IIIF)V
L173:   iinc 2 1
L176:   iload_2
L177:   goto L128
L180:   iinc 1 1
L183:   iload_1
L184:   goto L114
L187:   iconst_0
L188:   iconst_1
L189:   dup
L190:   pop2
L191:   ireturn
L192:   
        .attribute StackMap b'\x00\x0C\x00\x06\x00\x04\x07\x00\x02\x07\x00\x0A\x01\x07\x00\x0C\x00\x01\x01\x00\x15\x00\x05\x07\x00\x02\x07\x00\x0A\x01\x07\x00\x0C\x01\x00\x01\x01\x00\x48\x00\x05\x07\x00\x02\x07\x00\x0A\x01\x07\x00\x0C\x01\x00\x00\x00\x50\x00\x00\x00\x01\x07\x00\x12\x00\x51\x00\x05\x07\x00\x02\x07\x00\x0A\x01\x07\x00\x0C\x01\x00\x00\x00\x58\x00\x00\x00\x01\x07\x00\x12\x00\x59\x00\x04\x07\x00\x02\x07\x00\x0A\x01\x07\x00\x0C\x00\x00\x00\x72\x00\x05\x07\x00\x02\x01\x00\x07\x00\x0C\x07\x00\x20\x00\x01\x01\x00\x80\x00\x05\x07\x00\x02\x01\x01\x07\x00\x0C\x07\x00\x20\x00\x01\x01\x00\xAD\x00\x05\x07\x00\x02\x01\x01\x07\x00\x0C\x07\x00\x20\x00\x00\x00\xB4\x00\x05\x07\x00\x02\x01\x01\x07\x00\x0C\x07\x00\x20\x00\x00\x00\xBB\x00\x04\x07\x00\x02\x00\x00\x07\x00\x0C\x00\x00'
    .end code
.end method

.method public <init> : ()V
    .code stack 1 locals 1
L0:     aload_0
L1:     invokespecial Method Uf <init> ()V
L4:     return
L5:     
    .end code
.end method

.method public break : (LRg;)Z
    .code stack 6 locals 5
L0:     getstatic Field rg do [I
L3:     aload_1
L4:     getfield Field Rg case LqE;
L7:     invokevirtual Method qE ordinal ()I
L10:    iaload
L11:    tableswitch 1
            L56
            L56
            L186
            L186
            L186
            L186
            L186
            L186
            default : L186
L56:    getstatic Field ZF const Lsb;
L59:    iconst_0
L60:    ifne L183
L63:    astore_2
L64:    aconst_null
L65:    astore_3
L66:    aload_2
L67:    ifnull L76
L70:    aload_2
L71:    aload_1
L72:    invokevirtual Method sb else (LRg;)LLD;
L75:    astore_3
L76:    iconst_0
L77:    iconst_1
L78:    dup
L79:    pop2
L80:    dup
L81:    istore_2
L82:    bipush 28
L84:    iconst_1
L85:    dup
L86:    pop2
L87:    if_icmpge L186
L90:    iconst_0
L91:    iconst_1
L92:    dup
L93:    pop2
L94:    dup
L95:    istore 4
L97:    bipush 10
L99:    iconst_1
L100:   dup
L101:   pop2
L102:   if_icmpge L172
L105:   aload_1
L106:   getfield Field Rg this [[I
L109:   iload 4
L111:   aaload
L112:   iload_2
L113:   iaload
L114:   bipush 31
L116:   iconst_1
L117:   dup
L118:   pop2
L119:   iand
L120:   bipush 12
L122:   iconst_1
L123:   dup
L124:   pop2
L125:   if_icmpne L163
L128:   aload_3
L129:   aload_1
L130:   getfield Field Rg this [[I
L133:   iload 4
L135:   aaload
L136:   iload_2
L137:   bipush 7
L139:   iconst_1
L140:   dup
L141:   pop2
L142:   iastore
L143:   ifnull L163
L146:   aload_3
L147:   getfield Field LD void LlG;
L150:   iload 4
L152:   iload_2
L153:   bipush 16
L155:   iconst_1
L156:   dup
L157:   pop2
L158:   ldc -1.5e0f
L160:   invokevirtual Method lG break (IIIF)V
L163:   iinc 4 1
L166:   iload 4
L168:   goto L97
L171:   athrow
L172:   iinc 2 1
L175:   iload_2
L176:   goto L82
L179:   nop
L180:   nop
L181:   nop
L182:   athrow
L183:   goto L59
L186:   iconst_0
L187:   iconst_1
L188:   dup
L189:   pop2
L190:   ireturn
L191:   
        .attribute StackMap b'\x00\x0B\x00\x38\x00\x02\x07\x00\x02\x07\x00\x0A\x00\x00\x00\x3B\x00\x02\x07\x00\x02\x07\x00\x0A\x00\x01\x07\x00\x1A\x00\x4C\x00\x04\x07\x00\x02\x07\x00\x0A\x07\x00\x1A\x07\x00\x20\x00\x00\x00\x52\x00\x04\x07\x00\x02\x07\x00\x0A\x01\x07\x00\x20\x00\x01\x01\x00\x61\x00\x05\x07\x00\x02\x07\x00\x0A\x01\x07\x00\x20\x01\x00\x01\x01\x00\xA3\x00\x05\x07\x00\x02\x07\x00\x0A\x01\x07\x00\x20\x01\x00\x00\x00\xAB\x00\x00\x00\x01\x07\x00\x12\x00\xAC\x00\x05\x07\x00\x02\x07\x00\x0A\x01\x07\x00\x20\x01\x00\x00\x00\xB3\x00\x00\x00\x01\x07\x00\x12\x00\xB7\x00\x02\x07\x00\x02\x07\x00\x0A\x00\x01\x07\x00\x1A\x00\xBA\x00\x02\x07\x00\x02\x07\x00\x0A\x00\x00'
    .end code
.end method
.innerclasses
    rg Le [0] static synthetic
.end innerclasses
.end class
