.version 49 0
.class public final super lG
.super gB
.field public static final d I = 32
.field private e [[F
.field private g F
.field private k F
.field private a I
.field public static final F I = 1
.field private A F
.field private E [[F
.field private C Z
.field public static final K I = 512
.field private G Z
.field private B Z
.field public static final c I = 1024
.field private field1284 I
.field private i [[I
.field private static final m [F
.field private h I
.field private static final J [F
.field public static final l I = 256
.field private D [[I
.field private f F
.field public static final j I = 4
.field private I [[I
.field private b [[I
.field private field1285 Z
.field public static final return I = 11
.field private field1286 F
.field public static final switch I = 9
.field private field1287 [[F
.field private field1288 [[F
.field private field1289 [[F
.field private field1290 F
.field private field1291 I
.field private field1292 [[I
.field private field1293 F
.field public static final field1294 I = 3840
.field private field1295 I
.field public static final throw I = 12
.field public static final package I = 15
.field private field1296 I
.field private static final field1297 [F
.field private while I
.field private field1298 Z
.field private field1299 F
.field private field1300 F
.field public static final field1301 I = 9
.field public static final field1302 I = 3
.field private field1303 F
.field private field1304 [[I
.field private field1305 I
.field private field1306 F
.field public static final field1307 I = 2
.field public static final field1308 I = 13
.field public static final false I = 31
.field private field1309 [[I
.field public static final field1310 I = 10
.field private true F
.field public static final field1311 I = 8
.field private field1312 I
.field public static final field1313 I = 14
.field private field1314 Z
.field private field1315 F
.field private field163 F
.field public static final field1316 I = 7
.field private field1317 F
.field public static final field1318 I = 0
.field private try [F
.field public static final field1319 I = 5
.field private static final new [F
.field public static final field1320 I = 6
.field private this F
.field public static final field1321 I = 16
.field public static final field1322 I = 2048
.field private field1323 I

.method public <init> : (IIIZ)V
    .code stack 22 locals 5
L0:     aload_0
L1:     dup
L2:     dup2
L3:     dup2
L4:     fconst_0
L5:     aload_0
L6:     dup_x2
L7:     fconst_0
L8:     iload_2
L9:     aload_0
L10:    dup_x1
L11:    dup_x1
L12:    iload_3
L13:    iload_1
L14:    aload_0
L15:    dup_x1
L16:    iload 4
L18:    fconst_0
L19:    aload_0
L20:    dup_x1
L21:    invokespecial Method gB <init> ()V
L24:    putfield Field lG g F
L27:    putfield Field lG G Z
L30:    putfield Field lG field1284 I
L33:    putfield Field lG field1312 I
L36:    putfield Field lG while I
L39:    getfield Field lG field1312 I
L42:    aload_0
L43:    dup_x1
L44:    getfield Field lG while I
L47:    isub
L48:    i2f
L49:    putfield Field lG field163 F
L52:    putfield Field lG field1290 F
L55:    putfield Field lG A F
L58:    getfield Field lG field1284 I
L61:    i2f
L62:    ldc 4e-1f
L64:    fmul
L65:    putfield Field lG field1128 F
L68:    getfield Field lG while I
L71:    i2f
L72:    ldc 4e-1f
L74:    fmul
L75:    putfield Field lG field1137 F
L78:    getfield Field lG field1284 I
L81:    aload_0
L82:    getfield Field lG field1312 I
L85:    multianewarray [[I 2
L89:    putfield Field lG i [[I
L92:    aload_0
L93:    getfield Field lG field1284 I
L96:    aload_0
L97:    dup_x1
L98:    getfield Field lG field1312 I
L101:   multianewarray [[I 2
L105:   putfield Field lG b [[I
L108:   aload_0
L109:   getfield Field lG field1284 I
L112:   aload_0
L113:   dup_x1
L114:   getfield Field lG field1312 I
L117:   multianewarray [[I 2
L121:   putfield Field lG field1292 [[I
L124:   aload_0
L125:   getfield Field lG field1284 I
L128:   aload_0
L129:   dup_x1
L130:   getfield Field lG field1312 I
L133:   multianewarray [[I 2
L137:   putfield Field lG D [[I
L140:   aload_0
L141:   getfield Field lG field1284 I
L144:   aload_0
L145:   dup_x1
L146:   getfield Field lG field1312 I
L149:   multianewarray [[F 2
L153:   putfield Field lG E [[F
L156:   aload_0
L157:   getfield Field lG field1284 I
L160:   aload_0
L161:   dup_x1
L162:   getfield Field lG field1312 I
L165:   multianewarray [[F 2
L169:   putfield Field lG field1288 [[F
L172:   aload_0
L173:   getfield Field lG field1284 I
L176:   aload_0
L177:   dup_x1
L178:   getfield Field lG field1312 I
L181:   multianewarray [[F 2
L185:   putfield Field lG field1289 [[F
L188:   aload_0
L189:   getfield Field lG field1284 I
L192:   aload_0
L193:   dup_x1
L194:   getfield Field lG field1312 I
L197:   multianewarray [[F 2
L201:   putfield Field lG e [[F
L204:   aload_0
L205:   getfield Field lG field1284 I
L208:   aload_0
L209:   dup_x1
L210:   getfield Field lG field1312 I
L213:   multianewarray [[I 2
L217:   putfield Field lG field1309 [[I
L220:   aload_0
L221:   getfield Field lG field1284 I
L224:   aload_0
L225:   dup_x1
L226:   getfield Field lG field1312 I
L229:   multianewarray [[F 2
L233:   putfield Field lG field1287 [[F
L236:   aload_0
L237:   getfield Field lG field1284 I
L240:   aload_0
L241:   dup_x1
L242:   getfield Field lG field1312 I
L245:   multianewarray [[I 2
L249:   putfield Field lG field1304 [[I
L252:   aload_0
L253:   iconst_4
L254:   iconst_1
L255:   dup
L256:   pop2
L257:   iconst_4
L258:   iconst_1
L259:   dup
L260:   pop2
L261:   multianewarray [[I 2
L265:   putfield Field lG I [[I
L268:   iconst_1
L269:   aload_0
L270:   dup_x1
L271:   iconst_1
L272:   fconst_0
L273:   aload_0
L274:   dup_x1
L275:   iconst_0
L276:   fconst_0
L277:   aload_0
L278:   dup_x1
L279:   fconst_0
L280:   dup
L281:   aload_0
L282:   dup_x1
L283:   fconst_1
L284:   aload_0
L285:   dup
L286:   getfield Field lG field1312 I
L289:   newarray float
L291:   iconst_1
L292:   dup
L293:   pop2
L294:   putfield Field lG try [F
L297:   putfield Field lG f F
L300:   putfield Field lG field1306 F
L303:   putfield Field lG field1300 F
L306:   putfield Field lG field1286 F
L309:   iconst_1
L310:   dup
L311:   pop2
L312:   putfield Field lG field1305 I
L315:   putfield Field lG field1303 F
L318:   iconst_1
L319:   dup
L320:   pop2
L321:   invokevirtual Method lG method95 (Z)V
L324:   iconst_1
L325:   dup
L326:   pop2
L327:   invokestatic Method org/lwjgl/opengl/GL11 method3706 (I)I
L330:   putfield Field lG field1295 I
L333:   return
L334:   
    .end code
.end method

.method public method2 : ()V
    .code stack 4 locals 1
L0:     aload_0
L1:     dup
L2:     invokespecial Method gB method2 ()V
L5:     getfield Field lG field1295 I
L8:     iconst_1
L9:     dup
L10:    dup
L11:    pop2
L12:    invokestatic Method org/lwjgl/opengl/GL11 this (II)V
L15:    return
L16:    
    .end code
.end method

.method public method115 : (I)V
    .code stack 8 locals 4
L0:     iload_1
L1:     dup
L2:     istore_2
L3:     ifle L95
L6:     iconst_0
L7:     aload_0
L8:     dup
L9:     getfield Field lG try [F
L12:    swap
L13:    getfield Field lG try [F
L16:    iload_2
L17:    dup_x1
L18:    iconst_1
L19:    dup
L20:    dup
L21:    pop2
L22:    isub
L23:    faload
L24:    fastore
L25:    iconst_1
L26:    dup
L27:    pop2
L28:    dup
L29:    istore_3
L30:    aload_0
L31:    getfield Field lG field1284 I
L34:    if_icmpge L87
L37:    aload_0
L38:    getfield Field lG field1287 [[F
L41:    iload_3
L42:    aaload
L43:    iload_2
L44:    aload_0
L45:    dup_x2
L46:    getfield Field lG field1287 [[F
L49:    iload_3
L50:    aaload
L51:    iload_2
L52:    iconst_1
L53:    dup
L54:    dup
L55:    pop2
L56:    isub
L57:    faload
L58:    fastore
L59:    getfield Field lG field1304 [[I
L62:    iload_3
L63:    aaload
L64:    aload_0
L65:    getfield Field lG field1304 [[I
L68:    iload_3
L69:    aaload
L70:    iload_2
L71:    dup_x1
L72:    iconst_1
L73:    dup
L74:    dup
L75:    pop2
L76:    isub
L77:    iaload
L78:    iinc 3 1
L81:    iastore
L82:    iload_3
L83:    goto L30
L86:    athrow
L87:    iinc 2 -1
L90:    iload_2
L91:    goto L3
L94:    athrow
L95:    iconst_0
L96:    iconst_1
L97:    dup
L98:    pop2
L99:    dup
L100:   istore_2
L101:   iload_1
L102:   if_icmpgt L122
L105:   aload_0
L106:   getfield Field lG try [F
L109:   iload_2
L110:   dup2
L111:   faload
L112:   fconst_1
L113:   fadd
L114:   iinc 2 1
L117:   fastore
L118:   iload_2
L119:   goto L101
L122:   aload_0
L123:   iconst_1
L124:   dup
L125:   aload_0
L126:   dup_x1
L127:   iconst_0
L128:   iconst_1
L129:   dup
L130:   pop2
L131:   putfield Field lG field1314 Z
L134:   iconst_1
L135:   dup
L136:   pop2
L137:   putfield Field lG C Z
L140:   iconst_1
L141:   dup
L142:   pop2
L143:   putfield Field lG B Z
L146:   return
L147:   
        .attribute StackMap b'\x00\x08\x00\x03\x00\x03\x07\x00\x02\x01\x01\x00\x01\x01\x00\x1E\x00\x04\x07\x00\x02\x01\x01\x01\x00\x01\x01\x00\x56\x00\x00\x00\x01\x07\x00\xC4\x00\x57\x00\x04\x07\x00\x02\x01\x01\x01\x00\x00\x00\x5E\x00\x00\x00\x01\x07\x00\xC4\x00\x5F\x00\x03\x07\x00\x02\x01\x01\x00\x00\x00\x65\x00\x03\x07\x00\x02\x01\x01\x00\x01\x01\x00\x7A\x00\x03\x07\x00\x02\x01\x01\x00\x00'
    .end code
.end method

.method public method648 : (I)V
    .code stack 9 locals 4
L0:     iconst_0
L1:     iconst_1
L2:     dup
L3:     pop2
L4:     dup
L5:     istore_2
L6:     aload_0
L7:     getfield Field lG field1312 I
L10:    iload_1
L11:    isub
L12:    if_icmpge L95
L15:    iconst_0
L16:    aload_0
L17:    dup
L18:    getfield Field lG try [F
L21:    swap
L22:    getfield Field lG try [F
L25:    iload_2
L26:    dup_x1
L27:    iload_1
L28:    iadd
L29:    faload
L30:    fastore
L31:    iconst_1
L32:    dup
L33:    pop2
L34:    dup
L35:    istore_3
L36:    aload_0
L37:    getfield Field lG field1284 I
L40:    if_icmpge L87
L43:    aload_0
L44:    getfield Field lG field1287 [[F
L47:    iload_3
L48:    aaload
L49:    iload_2
L50:    aload_0
L51:    dup_x2
L52:    getfield Field lG field1287 [[F
L55:    iload_3
L56:    aaload
L57:    iload_2
L58:    iload_1
L59:    iadd
L60:    faload
L61:    fastore
L62:    getfield Field lG field1304 [[I
L65:    iload_3
L66:    aaload
L67:    aload_0
L68:    getfield Field lG field1304 [[I
L71:    iload_3
L72:    aaload
L73:    iload_2
L74:    dup_x1
L75:    iload_1
L76:    iadd
L77:    iaload
L78:    iinc 3 1
L81:    iastore
L82:    iload_3
L83:    goto L36
L86:    athrow
L87:    iinc 2 1
L90:    iload_2
L91:    goto L6
L94:    athrow
L95:    aload_0
L96:    getfield Field lG field1312 I
L99:    iload_1
L100:   isub
L101:   dup
L102:   istore_2
L103:   aload_0
L104:   getfield Field lG field1312 I
L107:   if_icmpge L153
L110:   iconst_0
L111:   aload_0
L112:   getfield Field lG try [F
L115:   iload_2
L116:   fconst_0
L117:   fastore
L118:   iconst_1
L119:   dup
L120:   pop2
L121:   dup
L122:   istore_3
L123:   aload_0
L124:   getfield Field lG field1284 I
L127:   if_icmpge L146
L130:   aload_0
L131:   getfield Field lG field1287 [[F
L134:   iload_3
L135:   aaload
L136:   iload_2
L137:   fconst_0
L138:   iinc 3 1
L141:   fastore
L142:   iload_3
L143:   goto L123
L146:   iinc 2 1
L149:   iload_2
L150:   goto L103
L153:   aload_0
L154:   iconst_1
L155:   dup
L156:   aload_0
L157:   dup_x1
L158:   iconst_0
L159:   aload_0
L160:   dup
L161:   getfield Field lG field1317 F
L164:   iload_1
L165:   i2f
L166:   fadd
L167:   putfield Field lG field1317 F
L170:   iconst_1
L171:   dup
L172:   pop2
L173:   putfield Field lG field1314 Z
L176:   iconst_1
L177:   dup
L178:   pop2
L179:   putfield Field lG C Z
L182:   iconst_1
L183:   dup
L184:   pop2
L185:   putfield Field lG B Z
L188:   return
L189:   
        .attribute StackMap b'\x00\x0A\x00\x06\x00\x03\x07\x00\x02\x01\x01\x00\x01\x01\x00\x24\x00\x04\x07\x00\x02\x01\x01\x01\x00\x01\x01\x00\x56\x00\x00\x00\x01\x07\x00\xC4\x00\x57\x00\x04\x07\x00\x02\x01\x01\x01\x00\x00\x00\x5E\x00\x00\x00\x01\x07\x00\xC4\x00\x5F\x00\x03\x07\x00\x02\x01\x01\x00\x00\x00\x67\x00\x03\x07\x00\x02\x01\x01\x00\x01\x01\x00\x7B\x00\x04\x07\x00\x02\x01\x01\x01\x00\x01\x01\x00\x92\x00\x04\x07\x00\x02\x01\x01\x01\x00\x00\x00\x99\x00\x03\x07\x00\x02\x01\x01\x00\x00'
    .end code
.end method

.method public method134 : ()I
    .code stack 1 locals 1
L0:     aload_0
L1:     getfield Field lG field1284 I
L4:     ireturn
L5:     
    .end code
.end method

.method public method26 : ()V
    .code stack 9 locals 3
L0:     aload_0
L1:     dup
L2:     dup2
L3:     getfield Field lG field1306 F
L6:     aload_0
L7:     dup_x2
L8:     getfield Field lG field1286 F
L11:    getstatic Field ib field2312 F
L14:    fconst_2
L15:    fmul
L16:    fsub
L17:    aload_0
L18:    getfield Field lG field1286 F
L21:    getstatic Field ib field2312 F
L24:    fconst_2
L25:    fmul
L26:    fadd
L27:    invokestatic Method OC method1001 (FFF)F
L30:    putfield Field lG field1286 F
L33:    getfield Field lG field1305 I
L36:    i2f
L37:    aload_0
L38:    getfield Field lG field1303 F
L41:    getstatic Field ib field2312 F
L44:    ldc 9.6e1f
L46:    fmul
L47:    fsub
L48:    aload_0
L49:    getfield Field lG field1303 F
L52:    getstatic Field ib field2312 F
L55:    ldc 1.2e1f
L57:    fmul
L58:    fadd
L59:    invokestatic Method OC method1001 (FFF)F
L62:    putfield Field lG field1303 F
L65:    getfield Field lG field1300 F
L68:    aload_0
L69:    getfield Field lG f F
L72:    fcmpl
L73:    ifeq L115
L76:    iconst_1
L77:    aload_0
L78:    dup
L79:    dup_x2
L80:    getfield Field lG f F
L83:    aload_0
L84:    getfield Field lG field1300 F
L87:    getstatic Field ib field2312 F
L90:    fconst_2
L91:    fmul
L92:    fsub
L93:    aload_0
L94:    getfield Field lG field1300 F
L97:    getstatic Field ib field2312 F
L100:   fconst_2
L101:   fmul
L102:   fadd
L103:   invokestatic Method OC method1001 (FFF)F
L106:   putfield Field lG field1300 F
L109:   iconst_1
L110:   dup
L111:   pop2
L112:   putfield Field lG C Z
L115:   aload_0
L116:   dup
L117:   dup_x1
L118:   iconst_1
L119:   dup
L120:   dup
L121:   pop2
L122:   putfield Field lG field1314 Z
L125:   dup
L126:   getfield Field lG field1317 F
L129:   aload_0
L130:   getfield Field lG g F
L133:   getstatic Field ib field2312 F
L136:   fmul
L137:   fsub
L138:   putfield Field lG field1317 F
L141:   getfield Field lG field1317 F
L144:   fconst_0
L145:   fcmpg
L146:   ifgt L159
L149:   aload_0
L150:   dup
L151:   fconst_0
L152:   putfield Field lG field1317 F
L155:   goto L176
L158:   athrow
L159:   aload_0
L160:   iconst_1
L161:   aload_0
L162:   dup_x1
L163:   iconst_0
L164:   iconst_1
L165:   dup
L166:   pop2
L167:   putfield Field lG field1314 Z
L170:   iconst_1
L171:   dup
L172:   pop2
L173:   putfield Field lG C Z
L176:   getfield Field lG B Z
L179:   ifne L184
L182:   return
L183:   athrow
L184:   aload_0
L185:   iconst_0
L186:   iconst_1
L187:   dup
L188:   pop2
L189:   putfield Field lG B Z
L192:   iconst_0
L193:   iconst_1
L194:   dup
L195:   pop2
L196:   dup
L197:   istore_1
L198:   aload_0
L199:   getfield Field lG field1312 I
L202:   if_icmpge L471
L205:   aload_0
L206:   dup
L207:   getfield Field lG try [F
L210:   iload_1
L211:   dup2
L212:   faload
L213:   getstatic Field ib field2312 F
L216:   ldc 1.6e1f
L218:   aload_0
L219:   getfield Field lG try [F
L222:   iload_1
L223:   faload
L224:   ldc 4e0f
L226:   fmul
L227:   invokestatic Method java/lang/Math max (FF)F
L230:   fmul
L231:   fsub
L232:   fastore
L233:   getfield Field lG try [F
L236:   iload_1
L237:   faload
L238:   fconst_0
L239:   fcmpg
L240:   aload_0
L241:   swap
L242:   ifge L254
L245:   getfield Field lG try [F
L248:   iload_1
L249:   fconst_0
L250:   fastore
L251:   goto L277
L254:   iconst_0
L255:   iconst_1
L256:   dup
L257:   pop2
L258:   putfield Field lG field1314 Z
L261:   iconst_1
L262:   aload_0
L263:   dup_x1
L264:   iconst_1
L265:   dup
L266:   dup
L267:   pop2
L268:   putfield Field lG C Z
L271:   iconst_1
L272:   dup
L273:   pop2
L274:   putfield Field lG B Z
L277:   iconst_0
L278:   iconst_1
L279:   dup
L280:   pop2
L281:   dup
L282:   istore_2
L283:   aload_0
L284:   getfield Field lG field1284 I
L287:   if_icmpge L464
L290:   aload_0
L291:   getfield Field lG field1304 [[I
L294:   iload_2
L295:   aaload
L296:   iload_1
L297:   iaload
L298:   ifeq L457
L301:   iconst_1
L302:   aload_0
L303:   dup_x1
L304:   dup_x2
L305:   aload_0
L306:   iconst_0
L307:   iconst_1
L308:   dup_x2
L309:   dup
L310:   pop2
L311:   putfield Field lG field1314 Z
L314:   iconst_1
L315:   dup
L316:   pop2
L317:   putfield Field lG C Z
L320:   iconst_1
L321:   dup
L322:   pop2
L323:   putfield Field lG field1298 Z
L326:   getfield Field lG field1287 [[F
L329:   iload_2
L330:   aaload
L331:   iload_1
L332:   faload
L333:   fconst_0
L334:   fcmpl
L335:   ifle L394
L338:   aload_0
L339:   dup
L340:   getfield Field lG field1287 [[F
L343:   iload_2
L344:   aaload
L345:   iload_1
L346:   dup2
L347:   faload
L348:   getstatic Field ib field2312 F
L351:   ldc 1.2e1f
L353:   fmul
L354:   fsub
L355:   fastore
L356:   getfield Field lG field1287 [[F
L359:   iload_2
L360:   aaload
L361:   iload_1
L362:   faload
L363:   fconst_0
L364:   fcmpg
L365:   aload_0
L366:   swap
L367:   ifge L384
L370:   getfield Field lG field1304 [[I
L373:   iload_2
L374:   aaload
L375:   iload_1
L376:   iconst_0
L377:   iconst_1
L378:   dup
L379:   pop2
L380:   iastore
L381:   goto L457
L384:   iconst_1
L385:   dup
L386:   dup
L387:   pop2
L388:   putfield Field lG B Z
L391:   goto L457
L394:   aload_0
L395:   getfield Field lG field1287 [[F
L398:   iload_2
L399:   aaload
L400:   iload_1
L401:   faload
L402:   fconst_0
L403:   fcmpg
L404:   ifge L457
L407:   aload_0
L408:   dup
L409:   getfield Field lG field1287 [[F
L412:   iload_2
L413:   aaload
L414:   iload_1
L415:   dup2
L416:   faload
L417:   getstatic Field ib field2312 F
L420:   fadd
L421:   fastore
L422:   getfield Field lG field1287 [[F
L425:   iload_2
L426:   aaload
L427:   iload_1
L428:   faload
L429:   fconst_0
L430:   fcmpl
L431:   aload_0
L432:   swap
L433:   ifle L450
L436:   getfield Field lG field1304 [[I
L439:   iload_2
L440:   aaload
L441:   iload_1
L442:   iconst_0
L443:   iconst_1
L444:   dup
L445:   pop2
L446:   iastore
L447:   goto L457
L450:   iconst_1
L451:   dup
L452:   dup
L453:   pop2
L454:   putfield Field lG B Z
L457:   iinc 2 1
L460:   iload_2
L461:   goto L283
L464:   iinc 1 1
L467:   iload_1
L468:   goto L198
L471:   return
L472:   
        .attribute StackMap b'\x00\x10\x00\x73\x00\x01\x07\x00\x02\x00\x00\x00\x9E\x00\x00\x00\x01\x07\x00\xC4\x00\x9F\x00\x01\x07\x00\x02\x00\x00\x00\xB0\x00\x01\x07\x00\x02\x00\x01\x07\x00\x02\x00\xB7\x00\x00\x00\x01\x07\x00\xC4\x00\xB8\x00\x01\x07\x00\x02\x00\x00\x00\xC6\x00\x02\x07\x00\x02\x01\x00\x01\x01\x00\xFE\x00\x02\x07\x00\x02\x01\x00\x01\x07\x00\x02\x01\x15\x00\x02\x07\x00\x02\x01\x00\x00\x01\x1B\x00\x03\x07\x00\x02\x01\x01\x00\x01\x01\x01\x80\x00\x03\x07\x00\x02\x01\x01\x00\x01\x07\x00\x02\x01\x8A\x00\x03\x07\x00\x02\x01\x01\x00\x00\x01\xC2\x00\x03\x07\x00\x02\x01\x01\x00\x01\x07\x00\x02\x01\xC9\x00\x03\x07\x00\x02\x01\x01\x00\x00\x01\xD0\x00\x03\x07\x00\x02\x01\x01\x00\x00\x01\xD7\x00\x02\x07\x00\x02\x01\x00\x00'
    .end code
.end method

.method public background : (ZF)V
    .code stack 9 locals 4
L0:     fload_2
L1:     fconst_0
L2:     fcmpl
L3:     ifne L8
L6:     return
L7:     athrow
L8:     aload_0
L9:     getfield Field lG field1315 F
L12:    invokestatic Method java/lang/Math abs (F)F
L15:    f2d
L16:    ldc2_w 1e-4
L19:    dcmpl
L20:    ifle L59
L23:    invokestatic Method org/lwjgl/opengl/GL11 method3672 ()V
L26:    aload_0
L27:    dup
L28:    dup_x1
L29:    getfield Field lG field1124 F
L32:    fconst_2
L33:    fdiv
L34:    fconst_0
L35:    dup
L36:    invokestatic Method org/lwjgl/opengl/GL11 method3807 (FFF)V
L39:    getfield Field lG field1315 F
L42:    fconst_1
L43:    fconst_0
L44:    dup_x1
L45:    invokestatic Method org/lwjgl/opengl/GL11 method3746 (FFFF)V
L48:    getfield Field lG field1124 F
L51:    fneg
L52:    fconst_2
L53:    fdiv
L54:    fconst_0
L55:    dup
L56:    invokestatic Method org/lwjgl/opengl/GL11 method3807 (FFF)V
L59:    aload_0
L60:    getfield Field lG G Z
L63:    ifeq L150
L66:    fconst_0
L67:    dup
L68:    dup_x1
L69:    iload_1
L70:    ifeq L81
L73:    ldc_w 7e-1f
L76:    fload_2
L77:    goto L85
L80:    athrow
L81:    ldc_w 8.5e-1f
L84:    fload_2
L85:    fmul
L86:    invokestatic Method org/lwjgl/opengl/GL11 method3888 (FFFF)V
L89:    bipush 7
L91:    iconst_1
L92:    dup
L93:    pop2
L94:    invokestatic Method org/lwjgl/opengl/GL11 method3664 (I)V
L97:    fconst_0
L98:    aload_0
L99:    getfield Field lG field1132 F
L102:   invokestatic Method org/lwjgl/opengl/GL11 method3848 (FF)V
L105:   fconst_0
L106:   aload_0
L107:   getfield Field lG field1124 F
L110:   aload_0
L111:   dup_x1
L112:   getfield Field lG field1132 F
L115:   invokestatic Method org/lwjgl/opengl/GL11 method3848 (FF)V
L118:   getfield Field lG field1124 F
L121:   aload_0
L122:   dup
L123:   getfield Field lG field1303 F
L126:   swap
L127:   getfield Field lG field1293 F
L130:   fmul
L131:   invokestatic Method org/lwjgl/opengl/GL11 method3848 (FF)V
L134:   aload_0
L135:   dup
L136:   getfield Field lG field1303 F
L139:   swap
L140:   getfield Field lG field1293 F
L143:   fmul
L144:   invokestatic Method org/lwjgl/opengl/GL11 method3848 (FF)V
L147:   invokestatic Method org/lwjgl/opengl/GL11 method3788 ()V
L150:   fload_2
L151:   fstore_3
L152:   iload_1
L153:   ifne L165
L156:   fload_3
L157:   fconst_1
L158:   aload_0
L159:   getfield Field lG field1286 F
L162:   fsub
L163:   fmul
L164:   fstore_3
L165:   fload_3
L166:   fconst_0
L167:   fcmpl
L168:   ifle L238
L171:   invokestatic Method FE method65 ()V
L174:   aload_0
L175:   getfield Field lG field1314 Z
L178:   ifeq L233
L181:   fload_3
L182:   fconst_1
L183:   fcmpl
L184:   ifne L233
L187:   aload_0
L188:   getfield Field lG C Z
L191:   ifeq L223
L194:   fconst_1
L195:   aload_0
L196:   dup
L197:   dup_x2
L198:   iconst_0
L199:   iconst_1
L200:   dup
L201:   pop2
L202:   putfield Field lG C Z
L205:   getfield Field lG field1295 I
L208:   sipush 4864
L211:   iconst_1
L212:   dup
L213:   pop2
L214:   invokestatic Method org/lwjgl/opengl/GL11 method3891 (II)V
L217:   invokespecial Method lG method135 (F)V
L220:   invokestatic Method org/lwjgl/opengl/GL11 try ()V
L223:   aload_0
L224:   getfield Field lG field1295 I
L227:   invokestatic Method org/lwjgl/opengl/GL11 method3901 (I)V
L230:   goto L238
L233:   aload_0
L234:   fload_3
L235:   invokespecial Method lG method135 (F)V
L238:   invokestatic Method FE method10 ()V
L241:   aload_0
L242:   getfield Field lG G Z
L245:   ifeq L452
L248:   aload_0
L249:   dup
L250:   getfield Field lG field1303 F
L253:   swap
L254:   getfield Field lG field1305 I
L257:   i2f
L258:   fcmpg
L259:   ifge L343
L262:   fconst_1
L263:   dup
L264:   dup_x1
L265:   fload_2
L266:   invokestatic Method org/lwjgl/opengl/GL11 method3888 (FFFF)V
L269:   bipush 7
L271:   iconst_1
L272:   dup
L273:   pop2
L274:   invokestatic Method org/lwjgl/opengl/GL11 method3664 (I)V
L277:   fconst_0
L278:   aload_0
L279:   getfield Field lG field1305 I
L282:   i2f
L283:   aload_0
L284:   getfield Field lG field1293 F
L287:   fmul
L288:   invokestatic Method org/lwjgl/opengl/GL11 method3848 (FF)V
L291:   fconst_0
L292:   aload_0
L293:   dup
L294:   getfield Field lG field1124 F
L297:   swap
L298:   getfield Field lG field1305 I
L301:   i2f
L302:   aload_0
L303:   dup_x2
L304:   getfield Field lG field1293 F
L307:   fmul
L308:   invokestatic Method org/lwjgl/opengl/GL11 method3848 (FF)V
L311:   getfield Field lG field1124 F
L314:   aload_0
L315:   dup
L316:   getfield Field lG field1303 F
L319:   swap
L320:   getfield Field lG field1293 F
L323:   fmul
L324:   invokestatic Method org/lwjgl/opengl/GL11 method3848 (FF)V
L327:   aload_0
L328:   dup
L329:   getfield Field lG field1303 F
L332:   swap
L333:   getfield Field lG field1293 F
L336:   fmul
L337:   invokestatic Method org/lwjgl/opengl/GL11 method3848 (FF)V
L340:   invokestatic Method org/lwjgl/opengl/GL11 method3788 ()V
L343:   sipush 770
L346:   iconst_1
L347:   dup
L348:   pop2
L349:   iconst_1
L350:   dup
L351:   dup
L352:   pop2
L353:   invokestatic Method org/lwjgl/opengl/GL11 method3771 (II)V
L356:   fconst_0
L357:   iconst_2
L358:   aload_0
L359:   dup_x1
L360:   dup_x2
L361:   getfield Field lG k F
L364:   aload_0
L365:   dup
L366:   getfield Field lG field1299 F
L369:   swap
L370:   getfield Field lG this F
L373:   ldc_w 2.5e-1f
L376:   fload_2
L377:   fmul
L378:   invokestatic Method org/lwjgl/opengl/GL11 method3888 (FFFF)V
L381:   iconst_1
L382:   dup
L383:   pop2
L384:   invokestatic Method org/lwjgl/opengl/GL11 method3664 (I)V
L387:   fconst_0
L388:   aload_0
L389:   getfield Field lG field1132 F
L392:   invokestatic Method org/lwjgl/opengl/GL11 method3848 (FF)V
L395:   getfield Field lG field1124 F
L398:   aload_0
L399:   getfield Field lG field1132 F
L402:   invokestatic Method org/lwjgl/opengl/GL11 method3848 (FF)V
L405:   getfield Field lG field1124 F
L408:   aload_0
L409:   dup
L410:   getfield Field lG field1303 F
L413:   swap
L414:   getfield Field lG field1293 F
L417:   fmul
L418:   invokestatic Method org/lwjgl/opengl/GL11 method3848 (FF)V
L421:   aload_0
L422:   dup
L423:   getfield Field lG field1303 F
L426:   swap
L427:   getfield Field lG field1293 F
L430:   fmul
L431:   invokestatic Method org/lwjgl/opengl/GL11 method3848 (FF)V
L434:   invokestatic Method org/lwjgl/opengl/GL11 method3788 ()V
L437:   sipush 770
L440:   iconst_1
L441:   dup
L442:   pop2
L443:   sipush 771
L446:   iconst_1
L447:   dup
L448:   pop2
L449:   invokestatic Method org/lwjgl/opengl/GL11 method3771 (II)V
L452:   aload_0
L453:   getfield Field lG field1315 F
L456:   invokestatic Method java/lang/Math abs (F)F
L459:   f2d
L460:   ldc2_w 1e-4
L463:   dcmpl
L464:   ifle L470
L467:   invokestatic Method org/lwjgl/opengl/GL11 method3730 ()V
L470:   return
L471:   
        .attribute StackMap b'\x00\x0E\x00\x07\x00\x00\x00\x01\x07\x00\xC4\x00\x08\x00\x03\x07\x00\x02\x01\x02\x00\x00\x00\x3B\x00\x03\x07\x00\x02\x01\x02\x00\x00\x00\x50\x00\x00\x00\x01\x07\x00\xC4\x00\x51\x00\x03\x07\x00\x02\x01\x02\x00\x03\x02\x02\x02\x00\x55\x00\x03\x07\x00\x02\x01\x02\x00\x05\x02\x02\x02\x02\x02\x00\x96\x00\x03\x07\x00\x02\x01\x02\x00\x00\x00\xA5\x00\x04\x07\x00\x02\x01\x02\x02\x00\x00\x00\xDF\x00\x04\x07\x00\x02\x01\x02\x02\x00\x00\x00\xE9\x00\x04\x07\x00\x02\x01\x02\x02\x00\x00\x00\xEE\x00\x04\x07\x00\x02\x01\x02\x02\x00\x00\x01\x57\x00\x04\x07\x00\x02\x01\x02\x02\x00\x00\x01\xC4\x00\x04\x07\x00\x02\x01\x02\x02\x00\x00\x01\xD6\x00\x04\x07\x00\x02\x01\x02\x02\x00\x00'
    .end code
.end method

.method public this : (FF)V
    .code stack 6 locals 3
L0:     iconst_1
L1:     aload_0
L2:     dup_x1
L3:     fload_2
L4:     aload_0
L5:     fload_1
L6:     putfield Field lG field1290 F
L9:     putfield Field lG A F
L12:    iconst_1
L13:    dup
L14:    pop2
L15:    putfield Field lG C Z
L18:    return
L19:    
    .end code
.end method

.method public method56 : ()V
    .code stack 2 locals 1
L0:     aload_0
L1:     fconst_0
L2:     putfield Field lG field1317 F
L5:     return
L6:     
    .end code
.end method

.method public method649 : (II)V
    .code stack 8 locals 3
L0:     aload_0
L1:     getfield Field lG field1296 I
L4:     iload_1
L5:     if_icmpne L18
L8:     aload_0
L9:     getfield Field lG field1291 I
L12:    iload_2
L13:    if_icmpne L18
L16:    return
L17:    athrow
L18:    aload_0
L19:    iconst_1
L20:    dup
L21:    aload_0
L22:    dup_x1
L23:    iload_2
L24:    aload_0
L25:    iload_1
L26:    putfield Field lG field1296 I
L29:    putfield Field lG field1291 I
L32:    iconst_1
L33:    dup
L34:    pop2
L35:    putfield Field lG C Z
L38:    iconst_1
L39:    dup
L40:    pop2
L41:    putfield Field lG field1298 Z
L44:    return
L45:    
        .attribute StackMap b'\x00\x02\x00\x11\x00\x00\x00\x01\x07\x00\xC4\x00\x12\x00\x03\x07\x00\x02\x01\x01\x00\x00'
    .end code
.end method

.method public method650 : (IIIF)V
    .code stack 6 locals 5
L0:     iconst_1
L1:     aload_0
L2:     dup
L3:     dup_x2
L4:     getfield Field lG field1287 [[F
L7:     iload_1
L8:     aaload
L9:     iload_2
L10:    fload 4
L12:    fastore
L13:    getfield Field lG field1304 [[I
L16:    iload_1
L17:    aaload
L18:    iload_2
L19:    iload_3
L20:    iastore
L21:    iconst_1
L22:    dup
L23:    pop2
L24:    putfield Field lG B Z
L27:    return
L28:    
    .end code
.end method

.method public method651 : (F)V
    .code stack 2 locals 2
L0:     aload_0
L1:     fload_1
L2:     putfield Field lG field1315 F
L5:     return
L6:     
    .end code
.end method

.method public method652 : (F)V
    .code stack 4 locals 2
L0:     aload_0
L1:     getfield Field lG f F
L4:     fload_1
L5:     fcmpl
L6:     ifne L11
L9:     return
L10:    athrow
L11:    aload_0
L12:    fload_1
L13:    fconst_0
L14:    fconst_1
L15:    invokestatic Method OC method1001 (FFF)F
L18:    putfield Field lG f F
L21:    return
L22:    
        .attribute StackMap b'\x00\x02\x00\x0A\x00\x00\x00\x01\x07\x00\xC4\x00\x0B\x00\x02\x07\x00\x02\x02\x00\x00'
    .end code
.end method

.method public static <clinit> : ()V
    .code stack 5 locals 0
L0:     bipush 32
L2:     iconst_1
L3:     dup
L4:     pop2
L5:     newarray float
L7:     iconst_1
L8:     dup
L9:     pop2
L10:    dup
L11:    iconst_0
L12:    iconst_1
L13:    dup
L14:    pop2
L15:    fconst_0
L16:    fastore
L17:    dup
L18:    iconst_1
L19:    dup
L20:    dup
L21:    pop2
L22:    fconst_1
L23:    fastore
L24:    dup
L25:    iconst_2
L26:    iconst_1
L27:    dup
L28:    pop2
L29:    fconst_0
L30:    fastore
L31:    dup
L32:    iconst_3
L33:    iconst_1
L34:    dup
L35:    pop2
L36:    ldc_w 9.5e-1f
L39:    fastore
L40:    dup
L41:    iconst_4
L42:    iconst_1
L43:    dup
L44:    pop2
L45:    ldc_w 2.5e-1f
L48:    fastore
L49:    dup
L50:    iconst_5
L51:    iconst_1
L52:    dup
L53:    pop2
L54:    fconst_1
L55:    fastore
L56:    dup
L57:    bipush 6
L59:    iconst_1
L60:    dup
L61:    pop2
L62:    ldc_w 1e-1f
L65:    fastore
L66:    dup
L67:    bipush 7
L69:    iconst_1
L70:    dup
L71:    pop2
L72:    fconst_1
L73:    fastore
L74:    dup
L75:    bipush 8
L77:    iconst_1
L78:    dup
L79:    pop2
L80:    ldc_w 9e-1f
L83:    fastore
L84:    dup
L85:    bipush 9
L87:    iconst_1
L88:    dup
L89:    pop2
L90:    ldc_w 5e-1f
L93:    fastore
L94:    dup
L95:    bipush 10
L97:    iconst_1
L98:    dup
L99:    pop2
L100:   ldc_w 1.2e0f
L103:   fastore
L104:   dup
L105:   bipush 11
L107:   iconst_1
L108:   dup
L109:   pop2
L110:   ldc_w 1.5e-1f
L113:   fastore
L114:   dup
L115:   bipush 12
L117:   iconst_1
L118:   dup
L119:   pop2
L120:   fconst_0
L121:   fastore
L122:   dup
L123:   bipush 13
L125:   iconst_1
L126:   dup
L127:   pop2
L128:   fconst_1
L129:   fastore
L130:   dup
L131:   bipush 14
L133:   iconst_1
L134:   dup
L135:   pop2
L136:   ldc_w 5.5e-1f
L139:   fastore
L140:   dup
L141:   bipush 15
L143:   iconst_1
L144:   dup
L145:   pop2
L146:   ldc_w 4.5e-1f
L149:   fastore
L150:   dup
L151:   bipush 16
L153:   iconst_1
L154:   dup
L155:   pop2
L156:   ldc_w -6.6e-1f
L159:   fastore
L160:   dup
L161:   bipush 17
L163:   iconst_1
L164:   dup
L165:   pop2
L166:   fconst_0
L167:   fastore
L168:   dup
L169:   bipush 18
L171:   iconst_1
L172:   dup
L173:   pop2
L174:   fconst_0
L175:   fastore
L176:   dup
L177:   bipush 19
L179:   iconst_1
L180:   dup
L181:   pop2
L182:   fconst_0
L183:   fastore
L184:   dup
L185:   bipush 20
L187:   iconst_1
L188:   dup
L189:   pop2
L190:   fconst_0
L191:   fastore
L192:   dup
L193:   bipush 21
L195:   iconst_1
L196:   dup
L197:   pop2
L198:   fconst_0
L199:   fastore
L200:   dup
L201:   bipush 22
L203:   iconst_1
L204:   dup
L205:   pop2
L206:   fconst_0
L207:   fastore
L208:   dup
L209:   bipush 23
L211:   iconst_1
L212:   dup
L213:   pop2
L214:   fconst_0
L215:   fastore
L216:   dup
L217:   bipush 24
L219:   iconst_1
L220:   dup
L221:   pop2
L222:   fconst_0
L223:   fastore
L224:   dup
L225:   bipush 25
L227:   iconst_1
L228:   dup
L229:   pop2
L230:   fconst_0
L231:   fastore
L232:   dup
L233:   bipush 26
L235:   iconst_1
L236:   dup
L237:   pop2
L238:   fconst_0
L239:   fastore
L240:   dup
L241:   bipush 27
L243:   iconst_1
L244:   dup
L245:   pop2
L246:   fconst_0
L247:   fastore
L248:   dup
L249:   bipush 28
L251:   iconst_1
L252:   dup
L253:   pop2
L254:   fconst_0
L255:   fastore
L256:   dup
L257:   bipush 29
L259:   iconst_1
L260:   dup
L261:   pop2
L262:   fconst_0
L263:   fastore
L264:   dup
L265:   bipush 30
L267:   iconst_1
L268:   dup
L269:   pop2
L270:   fconst_0
L271:   fastore
L272:   dup
L273:   bipush 31
L275:   iconst_1
L276:   dup
L277:   pop2
L278:   fconst_0
L279:   fastore
L280:   putstatic Field lG m [F
L283:   bipush 32
L285:   iconst_1
L286:   dup
L287:   pop2
L288:   newarray float
L290:   iconst_1
L291:   dup
L292:   pop2
L293:   dup
L294:   iconst_0
L295:   iconst_1
L296:   dup
L297:   pop2
L298:   fconst_0
L299:   fastore
L300:   dup
L301:   iconst_1
L302:   dup
L303:   dup
L304:   pop2
L305:   ldc_w 1e-1f
L308:   fastore
L309:   dup
L310:   iconst_2
L311:   iconst_1
L312:   dup
L313:   pop2
L314:   fconst_1
L315:   fastore
L316:   dup
L317:   iconst_3
L318:   iconst_1
L319:   dup
L320:   pop2
L321:   fconst_1
L322:   fastore
L323:   dup
L324:   iconst_4
L325:   iconst_1
L326:   dup
L327:   pop2
L328:   ldc_w 2.5e-1f
L331:   fastore
L332:   dup
L333:   iconst_5
L334:   iconst_1
L335:   dup
L336:   pop2
L337:   ldc_w 1e-1f
L340:   fastore
L341:   dup
L342:   bipush 6
L344:   iconst_1
L345:   dup
L346:   pop2
L347:   fconst_1
L348:   fastore
L349:   dup
L350:   bipush 7
L352:   iconst_1
L353:   dup
L354:   pop2
L355:   fconst_1
L356:   fastore
L357:   dup
L358:   bipush 8
L360:   iconst_1
L361:   dup
L362:   pop2
L363:   ldc_w 5e-1f
L366:   fastore
L367:   dup
L368:   bipush 9
L370:   iconst_1
L371:   dup
L372:   pop2
L373:   ldc_w 5e-1f
L376:   fastore
L377:   dup
L378:   bipush 10
L380:   iconst_1
L381:   dup
L382:   pop2
L383:   fconst_1
L384:   fastore
L385:   dup
L386:   bipush 11
L388:   iconst_1
L389:   dup
L390:   pop2
L391:   ldc_w 1.5e-1f
L394:   fastore
L395:   dup
L396:   bipush 12
L398:   iconst_1
L399:   dup
L400:   pop2
L401:   fconst_0
L402:   fastore
L403:   dup
L404:   bipush 13
L406:   iconst_1
L407:   dup
L408:   pop2
L409:   ldc_w 8.5e-1f
L412:   fastore
L413:   dup
L414:   bipush 14
L416:   iconst_1
L417:   dup
L418:   pop2
L419:   ldc_w 8.5e-1f
L422:   fastore
L423:   dup
L424:   bipush 15
L426:   iconst_1
L427:   dup
L428:   pop2
L429:   fconst_0
L430:   fastore
L431:   dup
L432:   bipush 16
L434:   iconst_1
L435:   dup
L436:   pop2
L437:   ldc_w -6.6e-1f
L440:   fastore
L441:   dup
L442:   bipush 17
L444:   iconst_1
L445:   dup
L446:   pop2
L447:   fconst_0
L448:   fastore
L449:   dup
L450:   bipush 18
L452:   iconst_1
L453:   dup
L454:   pop2
L455:   fconst_0
L456:   fastore
L457:   dup
L458:   bipush 19
L460:   iconst_1
L461:   dup
L462:   pop2
L463:   fconst_0
L464:   fastore
L465:   dup
L466:   bipush 20
L468:   iconst_1
L469:   dup
L470:   pop2
L471:   fconst_0
L472:   fastore
L473:   dup
L474:   bipush 21
L476:   iconst_1
L477:   dup
L478:   pop2
L479:   fconst_0
L480:   fastore
L481:   dup
L482:   bipush 22
L484:   iconst_1
L485:   dup
L486:   pop2
L487:   fconst_0
L488:   fastore
L489:   dup
L490:   bipush 23
L492:   iconst_1
L493:   dup
L494:   pop2
L495:   fconst_0
L496:   fastore
L497:   dup
L498:   bipush 24
L500:   iconst_1
L501:   dup
L502:   pop2
L503:   fconst_0
L504:   fastore
L505:   dup
L506:   bipush 25
L508:   iconst_1
L509:   dup
L510:   pop2
L511:   fconst_0
L512:   fastore
L513:   dup
L514:   bipush 26
L516:   iconst_1
L517:   dup
L518:   pop2
L519:   fconst_0
L520:   fastore
L521:   dup
L522:   bipush 27
L524:   iconst_1
L525:   dup
L526:   pop2
L527:   fconst_0
L528:   fastore
L529:   dup
L530:   bipush 28
L532:   iconst_1
L533:   dup
L534:   pop2
L535:   fconst_0
L536:   fastore
L537:   dup
L538:   bipush 29
L540:   iconst_1
L541:   dup
L542:   pop2
L543:   fconst_0
L544:   fastore
L545:   dup
L546:   bipush 30
L548:   iconst_1
L549:   dup
L550:   pop2
L551:   fconst_0
L552:   fastore
L553:   dup
L554:   bipush 31
L556:   iconst_1
L557:   dup
L558:   pop2
L559:   fconst_0
L560:   fastore
L561:   putstatic Field lG new [F
L564:   bipush 32
L566:   iconst_1
L567:   dup
L568:   pop2
L569:   newarray float
L571:   iconst_1
L572:   dup
L573:   pop2
L574:   dup
L575:   iconst_0
L576:   iconst_1
L577:   dup
L578:   pop2
L579:   fconst_0
L580:   fastore
L581:   dup
L582:   iconst_1
L583:   dup
L584:   dup
L585:   pop2
L586:   ldc_w 1e-1f
L589:   fastore
L590:   dup
L591:   iconst_2
L592:   iconst_1
L593:   dup
L594:   pop2
L595:   fconst_0
L596:   fastore
L597:   dup
L598:   iconst_3
L599:   iconst_1
L600:   dup
L601:   pop2
L602:   ldc_w 2.5e-1f
L605:   fastore
L606:   dup
L607:   iconst_4
L608:   iconst_1
L609:   dup
L610:   pop2
L611:   fconst_1
L612:   fastore
L613:   dup
L614:   iconst_5
L615:   iconst_1
L616:   dup
L617:   pop2
L618:   fconst_1
L619:   fastore
L620:   dup
L621:   bipush 6
L623:   iconst_1
L624:   dup
L625:   pop2
L626:   fconst_1
L627:   fastore
L628:   dup
L629:   bipush 7
L631:   iconst_1
L632:   dup
L633:   pop2
L634:   fconst_1
L635:   fastore
L636:   dup
L637:   bipush 8
L639:   iconst_1
L640:   dup
L641:   pop2
L642:   ldc_w 1e-1f
L645:   fastore
L646:   dup
L647:   bipush 9
L649:   iconst_1
L650:   dup
L651:   pop2
L652:   ldc_w 5e-1f
L655:   fastore
L656:   dup
L657:   bipush 10
L659:   iconst_1
L660:   dup
L661:   pop2
L662:   ldc_w 1e-1f
L665:   fastore
L666:   dup
L667:   bipush 11
L669:   iconst_1
L670:   dup
L671:   pop2
L672:   ldc_w 1.5e-1f
L675:   fastore
L676:   dup
L677:   bipush 12
L679:   iconst_1
L680:   dup
L681:   pop2
L682:   fconst_0
L683:   fastore
L684:   dup
L685:   bipush 13
L687:   iconst_1
L688:   dup
L689:   pop2
L690:   ldc_w 1e-1f
L693:   fastore
L694:   dup
L695:   bipush 14
L697:   iconst_1
L698:   dup
L699:   pop2
L700:   ldc_w 5e-2f
L703:   fastore
L704:   dup
L705:   bipush 15
L707:   iconst_1
L708:   dup
L709:   pop2
L710:   ldc_w 5e-2f
L713:   fastore
L714:   dup
L715:   bipush 16
L717:   iconst_1
L718:   dup
L719:   pop2
L720:   ldc_w -6.6e-1f
L723:   fastore
L724:   dup
L725:   bipush 17
L727:   iconst_1
L728:   dup
L729:   pop2
L730:   fconst_0
L731:   fastore
L732:   dup
L733:   bipush 18
L735:   iconst_1
L736:   dup
L737:   pop2
L738:   fconst_0
L739:   fastore
L740:   dup
L741:   bipush 19
L743:   iconst_1
L744:   dup
L745:   pop2
L746:   fconst_0
L747:   fastore
L748:   dup
L749:   bipush 20
L751:   iconst_1
L752:   dup
L753:   pop2
L754:   fconst_0
L755:   fastore
L756:   dup
L757:   bipush 21
L759:   iconst_1
L760:   dup
L761:   pop2
L762:   fconst_0
L763:   fastore
L764:   dup
L765:   bipush 22
L767:   iconst_1
L768:   dup
L769:   pop2
L770:   fconst_0
L771:   fastore
L772:   dup
L773:   bipush 23
L775:   iconst_1
L776:   dup
L777:   pop2
L778:   fconst_0
L779:   fastore
L780:   dup
L781:   bipush 24
L783:   iconst_1
L784:   dup
L785:   pop2
L786:   fconst_0
L787:   fastore
L788:   dup
L789:   bipush 25
L791:   iconst_1
L792:   dup
L793:   pop2
L794:   fconst_0
L795:   fastore
L796:   dup
L797:   bipush 26
L799:   iconst_1
L800:   dup
L801:   pop2
L802:   fconst_0
L803:   fastore
L804:   dup
L805:   bipush 27
L807:   iconst_1
L808:   dup
L809:   pop2
L810:   fconst_0
L811:   fastore
L812:   dup
L813:   bipush 28
L815:   iconst_1
L816:   dup
L817:   pop2
L818:   fconst_0
L819:   fastore
L820:   dup
L821:   bipush 29
L823:   iconst_1
L824:   dup
L825:   pop2
L826:   fconst_0
L827:   fastore
L828:   dup
L829:   bipush 30
L831:   iconst_1
L832:   dup
L833:   pop2
L834:   fconst_0
L835:   fastore
L836:   dup
L837:   bipush 31
L839:   iconst_1
L840:   dup
L841:   pop2
L842:   fconst_0
L843:   fastore
L844:   putstatic Field lG J [F
L847:   bipush 32
L849:   iconst_1
L850:   dup
L851:   pop2
L852:   newarray float
L854:   iconst_1
L855:   dup
L856:   pop2
L857:   dup
L858:   iconst_0
L859:   iconst_1
L860:   dup
L861:   pop2
L862:   fconst_1
L863:   fastore
L864:   dup
L865:   iconst_1
L866:   dup
L867:   dup
L868:   pop2
L869:   fconst_1
L870:   fastore
L871:   dup
L872:   iconst_2
L873:   iconst_1
L874:   dup
L875:   pop2
L876:   fconst_1
L877:   fastore
L878:   dup
L879:   iconst_3
L880:   iconst_1
L881:   dup
L882:   pop2
L883:   fconst_1
L884:   fastore
L885:   dup
L886:   iconst_4
L887:   iconst_1
L888:   dup
L889:   pop2
L890:   fconst_1
L891:   fastore
L892:   dup
L893:   iconst_5
L894:   iconst_1
L895:   dup
L896:   pop2
L897:   fconst_1
L898:   fastore
L899:   dup
L900:   bipush 6
L902:   iconst_1
L903:   dup
L904:   pop2
L905:   fconst_1
L906:   fastore
L907:   dup
L908:   bipush 7
L910:   iconst_1
L911:   dup
L912:   pop2
L913:   fconst_1
L914:   fastore
L915:   dup
L916:   bipush 8
L918:   iconst_1
L919:   dup
L920:   pop2
L921:   fconst_1
L922:   fastore
L923:   dup
L924:   bipush 9
L926:   iconst_1
L927:   dup
L928:   pop2
L929:   fconst_1
L930:   fastore
L931:   dup
L932:   bipush 10
L934:   iconst_1
L935:   dup
L936:   pop2
L937:   fconst_1
L938:   fastore
L939:   dup
L940:   bipush 11
L942:   iconst_1
L943:   dup
L944:   pop2
L945:   fconst_1
L946:   fastore
L947:   dup
L948:   bipush 12
L950:   iconst_1
L951:   dup
L952:   pop2
L953:   fconst_1
L954:   fastore
L955:   dup
L956:   bipush 13
L958:   iconst_1
L959:   dup
L960:   pop2
L961:   fconst_1
L962:   fastore
L963:   dup
L964:   bipush 14
L966:   iconst_1
L967:   dup
L968:   pop2
L969:   fconst_1
L970:   fastore
L971:   dup
L972:   bipush 15
L974:   iconst_1
L975:   dup
L976:   pop2
L977:   fconst_1
L978:   fastore
L979:   dup
L980:   bipush 16
L982:   iconst_1
L983:   dup
L984:   pop2
L985:   fconst_0
L986:   fastore
L987:   dup
L988:   bipush 17
L990:   iconst_1
L991:   dup
L992:   pop2
L993:   fconst_0
L994:   fastore
L995:   dup
L996:   bipush 18
L998:   iconst_1
L999:   dup
L1000:  pop2
L1001:  fconst_0
L1002:  fastore
L1003:  dup
L1004:  bipush 19
L1006:  iconst_1
L1007:  dup
L1008:  pop2
L1009:  fconst_0
L1010:  fastore
L1011:  dup
L1012:  bipush 20
L1014:  iconst_1
L1015:  dup
L1016:  pop2
L1017:  fconst_0
L1018:  fastore
L1019:  dup
L1020:  bipush 21
L1022:  iconst_1
L1023:  dup
L1024:  pop2
L1025:  fconst_0
L1026:  fastore
L1027:  dup
L1028:  bipush 22
L1030:  iconst_1
L1031:  dup
L1032:  pop2
L1033:  fconst_0
L1034:  fastore
L1035:  dup
L1036:  bipush 23
L1038:  iconst_1
L1039:  dup
L1040:  pop2
L1041:  fconst_0
L1042:  fastore
L1043:  dup
L1044:  bipush 24
L1046:  iconst_1
L1047:  dup
L1048:  pop2
L1049:  fconst_0
L1050:  fastore
L1051:  dup
L1052:  bipush 25
L1054:  iconst_1
L1055:  dup
L1056:  pop2
L1057:  fconst_0
L1058:  fastore
L1059:  dup
L1060:  bipush 26
L1062:  iconst_1
L1063:  dup
L1064:  pop2
L1065:  fconst_0
L1066:  fastore
L1067:  dup
L1068:  bipush 27
L1070:  iconst_1
L1071:  dup
L1072:  pop2
L1073:  fconst_0
L1074:  fastore
L1075:  dup
L1076:  bipush 28
L1078:  iconst_1
L1079:  dup
L1080:  pop2
L1081:  fconst_0
L1082:  fastore
L1083:  dup
L1084:  bipush 29
L1086:  iconst_1
L1087:  dup
L1088:  pop2
L1089:  fconst_0
L1090:  fastore
L1091:  dup
L1092:  bipush 30
L1094:  iconst_1
L1095:  dup
L1096:  pop2
L1097:  fconst_0
L1098:  fastore
L1099:  dup
L1100:  bipush 31
L1102:  iconst_1
L1103:  dup
L1104:  pop2
L1105:  fconst_0
L1106:  fastore
L1107:  putstatic Field lG field1297 [F
L1110:  return
L1111:  
    .end code
.end method

.method public method32 : (FF)V
    .code stack 8 locals 3
L0:     iconst_1
L1:     aload_0
L2:     dup
L3:     dup_x2
L4:     aload_0
L5:     dup
L6:     fload_1
L7:     fload_2
L8:     invokespecial Method gB method32 (FF)V
L11:    getfield Field lG field1124 F
L14:    aload_0
L15:    dup_x1
L16:    getfield Field lG field1284 I
L19:    i2f
L20:    fdiv
L21:    putfield Field lG true F
L24:    getfield Field lG field1132 F
L27:    aload_0
L28:    getfield Field lG while I
L31:    i2f
L32:    fdiv
L33:    putfield Field lG field1293 F
L36:    iconst_1
L37:    dup
L38:    pop2
L39:    putfield Field lG C Z
L42:    return
L43:    
    .end code
.end method

.method public method131 : (F)V
    .code stack 3 locals 2
L0:     aload_0
L1:     fconst_1
L2:     fload_1
L3:     fdiv
L4:     putfield Field lG g F
L7:     return
L8:     
    .end code
.end method

.method public method471 : ([[I)V
    .code stack 7 locals 3
L0:     aload_1
L1:     arraylength
L2:     iconst_4
L3:     iconst_1
L4:     dup
L5:     pop2
L6:     if_icmpne L23
L9:     aload_1
L10:    iconst_0
L11:    iconst_1
L12:    dup
L13:    pop2
L14:    aaload
L15:    arraylength
L16:    iconst_4
L17:    iconst_1
L18:    dup
L19:    pop2
L20:    if_icmpeq L86
L23:    aload_0
L24:    iconst_4
L25:    iconst_1
L26:    dup
L27:    pop2
L28:    iconst_4
L29:    iconst_1
L30:    dup
L31:    pop2
L32:    multianewarray [[I 2
L36:    putfield Field lG I [[I
L39:    iconst_0
L40:    iconst_1
L41:    dup
L42:    pop2
L43:    dup
L44:    istore_2
L45:    aload_1
L46:    arraylength
L47:    if_icmpge L130
L50:    aload_1
L51:    iload_2
L52:    aaload
L53:    iconst_1
L54:    dup
L55:    pop2
L56:    aload_0
L57:    getfield Field lG I [[I
L60:    iload_2
L61:    aaload
L62:    iconst_0
L63:    dup_x1
L64:    iconst_1
L65:    dup
L66:    pop2
L67:    aload_1
L68:    iload_2
L69:    iinc 2 1
L72:    aaload
L73:    arraylength
L74:    invokestatic Method java/lang/System arraycopy (Ljava/lang/Object;ILjava/lang/Object;II)V
L77:    iload_2
L78:    goto L45
L81:    nop
L82:    nop
L83:    nop
L84:    nop
L85:    athrow
L86:    iconst_0
L87:    iconst_1
L88:    dup
L89:    pop2
L90:    dup
L91:    istore_2
L92:    iconst_4
L93:    iconst_1
L94:    dup
L95:    pop2
L96:    if_icmpge L130
L99:    aload_1
L100:   iload_2
L101:   aaload
L102:   iconst_1
L103:   dup
L104:   pop2
L105:   aload_0
L106:   getfield Field lG I [[I
L109:   iload_2
L110:   iinc 2 1
L113:   aaload
L114:   iconst_0
L115:   dup_x1
L116:   iconst_1
L117:   dup
L118:   pop2
L119:   iconst_4
L120:   iconst_1
L121:   dup
L122:   pop2
L123:   invokestatic Method java/lang/System arraycopy (Ljava/lang/Object;ILjava/lang/Object;II)V
L126:   iload_2
L127:   goto L92
L130:   aload_0
L131:   aload_0
L132:   iconst_1
L133:   dup
L134:   dup_x2
L135:   dup
L136:   pop2
L137:   putfield Field lG C Z
L140:   iconst_1
L141:   dup
L142:   pop2
L143:   putfield Field lG field1298 Z
L146:   return
L147:   
        .attribute StackMap b'\x00\x06\x00\x17\x00\x02\x07\x00\x02\x07\x00\x87\x00\x00\x00\x2D\x00\x03\x07\x00\x02\x07\x00\x87\x01\x00\x01\x01\x00\x51\x00\x00\x00\x01\x07\x00\xC4\x00\x56\x00\x02\x07\x00\x02\x07\x00\x87\x00\x00\x00\x5C\x00\x03\x07\x00\x02\x07\x00\x87\x01\x00\x01\x01\x00\x82\x00\x03\x07\x00\x02\x07\x00\x87\x01\x00\x00'
    .end code
.end method

.method public method236 : (II)V
    .code stack 8 locals 3
L0:     aload_0
L1:     getfield Field lG a I
L4:     iload_1
L5:     if_icmpne L18
L8:     aload_0
L9:     getfield Field lG h I
L12:    iload_2
L13:    if_icmpne L18
L16:    return
L17:    athrow
L18:    aload_0
L19:    iconst_1
L20:    dup
L21:    aload_0
L22:    dup_x1
L23:    iload_2
L24:    aload_0
L25:    iload_1
L26:    putfield Field lG a I
L29:    putfield Field lG h I
L32:    iconst_1
L33:    dup
L34:    pop2
L35:    putfield Field lG C Z
L38:    iconst_1
L39:    dup
L40:    pop2
L41:    putfield Field lG field1298 Z
L44:    return
L45:    
        .attribute StackMap b'\x00\x02\x00\x11\x00\x00\x00\x01\x07\x00\xC4\x00\x12\x00\x03\x07\x00\x02\x01\x01\x00\x00'
    .end code
.end method

.method private method135 : (F)V
    .code stack 8 locals 16
L0:     aload_0
L1:     getfield Field lG true F
L4:     invokestatic Method java/lang/Math abs (F)F
L7:     f2d
L8:     ldc2_w 1e-4
L11:    dcmpg
L12:    iflt L30
L15:    aload_0
L16:    getfield Field lG field1293 F
L19:    invokestatic Method java/lang/Math abs (F)F
L22:    f2d
L23:    ldc2_w 1e-4
L26:    dcmpg
L27:    ifge L32
L30:    return
L31:    athrow
L32:    aload_0
L33:    getfield Field lG field1290 F
L36:    fconst_0
L37:    fcmpl
L38:    ifne L50
L41:    aload_0
L42:    getfield Field lG A F
L45:    fconst_0
L46:    fcmpl
L47:    ifeq L74
L50:    aload_0
L51:    dup
L52:    getfield Field lG field1290 F
L55:    swap
L56:    getfield Field lG true F
L59:    fmul
L60:    aload_0
L61:    dup
L62:    getfield Field lG A F
L65:    swap
L66:    getfield Field lG field1293 F
L69:    fmul
L70:    fconst_0
L71:    invokestatic Method org/lwjgl/opengl/GL11 method3807 (FFF)V
L74:    sipush 770
L77:    iconst_1
L78:    dup
L79:    pop2
L80:    iconst_1
L81:    dup
L82:    dup
L83:    pop2
L84:    invokestatic Method org/lwjgl/opengl/GL11 method3771 (II)V
L87:    bipush 7
L89:    iconst_1
L90:    dup
L91:    pop2
L92:    invokestatic Method org/lwjgl/opengl/GL11 method3664 (I)V
L95:    aload_0
L96:    getfield Field lG field1305 I
L99:    dup
L100:   istore_2
L101:   aload_0
L102:   getfield Field lG field1312 I
L105:   if_icmpge L1290
L108:   iload_2
L109:   i2f
L110:   aload_0
L111:   getfield Field lG try [F
L114:   iload_2
L115:   faload
L116:   fsub
L117:   aload_0
L118:   getfield Field lG field1317 F
L121:   fadd
L122:   aload_0
L123:   getfield Field lG field163 F
L126:   fsub
L127:   aload_0
L128:   getfield Field lG field1293 F
L131:   fmul
L132:   dup
L133:   fstore_3
L134:   aload_0
L135:   getfield Field lG field1293 F
L138:   fadd
L139:   dup
L140:   fstore 4
L142:   aload_0
L143:   getfield Field lG field1305 I
L146:   i2f
L147:   aload_0
L148:   getfield Field lG field1293 F
L151:   fmul
L152:   fcmpl
L153:   iflt L1283
L156:   fload_3
L157:   aload_0
L158:   getfield Field lG field1132 F
L161:   fcmpg
L162:   ifgt L1283
L165:   fload_3
L166:   aload_0
L167:   getfield Field lG field1305 I
L170:   i2f
L171:   aload_0
L172:   getfield Field lG field1293 F
L175:   fmul
L176:   fcmpg
L177:   ifge L191
L180:   aload_0
L181:   getfield Field lG field1305 I
L184:   i2f
L185:   aload_0
L186:   getfield Field lG field1293 F
L189:   fmul
L190:   fstore_3
L191:   fload 4
L193:   aload_0
L194:   getfield Field lG field1132 F
L197:   fcmpl
L198:   ifle L207
L201:   aload_0
L202:   getfield Field lG field1132 F
L205:   fstore 4
L207:   iconst_0
L208:   iconst_1
L209:   dup
L210:   pop2
L211:   dup
L212:   istore 5
L214:   aload_0
L215:   getfield Field lG field1284 I
L218:   if_icmpge L1283
L221:   aload_0
L222:   dup
L223:   getfield Field lG field1309 [[I
L226:   iload 5
L228:   aaload
L229:   iload_2
L230:   iaload
L231:   istore 6
L233:   getfield Field lG field1304 [[I
L236:   iload 5
L238:   aaload
L239:   iload_2
L240:   iaload
L241:   bipush 31
L243:   iconst_1
L244:   dup
L245:   pop2
L246:   iand
L247:   istore 7
L249:   ldc 4e-1f
L251:   fstore 8
L253:   iload 6
L255:   ifne L323
L258:   iload 5
L260:   aload_0
L261:   getfield Field lG field1296 I
L264:   if_icmplt L323
L267:   iload 5
L269:   aload_0
L270:   getfield Field lG field1296 I
L273:   iconst_4
L274:   iconst_1
L275:   dup
L276:   pop2
L277:   iadd
L278:   if_icmpge L323
L281:   iload_2
L282:   aload_0
L283:   getfield Field lG field1291 I
L286:   if_icmplt L323
L289:   iload_2
L290:   aload_0
L291:   getfield Field lG field1291 I
L294:   iconst_4
L295:   iconst_1
L296:   dup
L297:   pop2
L298:   iadd
L299:   if_icmpge L323
L302:   aload_0
L303:   getfield Field lG I [[I
L306:   iload 5
L308:   aload_0
L309:   getfield Field lG field1296 I
L312:   isub
L313:   aaload
L314:   iload_2
L315:   aload_0
L316:   getfield Field lG field1291 I
L319:   isub
L320:   iaload
L321:   istore 6
L323:   iload 6
L325:   ifne L412
L328:   aload_0
L329:   getfield Field lG field1285 Z
L332:   ifeq L412
L335:   iload 5
L337:   aload_0
L338:   getfield Field lG a I
L341:   if_icmplt L412
L344:   iload 5
L346:   aload_0
L347:   getfield Field lG a I
L350:   iconst_4
L351:   iconst_1
L352:   dup
L353:   pop2
L354:   iadd
L355:   if_icmpge L412
L358:   iload_2
L359:   aload_0
L360:   getfield Field lG h I
L363:   if_icmplt L412
L366:   iload_2
L367:   aload_0
L368:   getfield Field lG h I
L371:   iconst_4
L372:   iconst_1
L373:   dup
L374:   pop2
L375:   iadd
L376:   if_icmpge L412
L379:   iload 6
L381:   aload_0
L382:   getfield Field lG I [[I
L385:   iload 5
L387:   aload_0
L388:   getfield Field lG a I
L391:   isub
L392:   aaload
L393:   iload_2
L394:   aload_0
L395:   getfield Field lG h I
L398:   isub
L399:   iaload
L400:   ior
L401:   dup
L402:   istore 6
L404:   ifeq L412
L407:   ldc_w 1e-1f
L410:   fstore 8
L412:   iload 7
L414:   ifeq L551
L417:   iload 7
L419:   bipush 15
L421:   iconst_1
L422:   dup
L423:   pop2
L424:   if_icmpeq L551
L427:   iload 7
L429:   bipush 16
L431:   iconst_1
L432:   dup
L433:   pop2
L434:   if_icmpeq L551
L437:   getstatic Field lG m [F
L440:   iload 7
L442:   faload
L443:   getstatic Field lG new [F
L446:   iload 7
L448:   faload
L449:   getstatic Field lG J [F
L452:   iload 7
L454:   faload
L455:   getstatic Field lG field1297 [F
L458:   iload 7
L460:   faload
L461:   aload_0
L462:   getfield Field lG field1287 [[F
L465:   iload 5
L467:   aaload
L468:   iload_2
L469:   faload
L470:   fmul
L471:   ldc_w 3e-1f
L474:   fmul
L475:   fload_1
L476:   fmul
L477:   aload_0
L478:   getfield Field lG field1300 F
L481:   fmul
L482:   invokestatic Method org/lwjgl/opengl/GL11 method3888 (FFFF)V
L485:   iload 5
L487:   i2f
L488:   aload_0
L489:   getfield Field lG true F
L492:   fmul
L493:   fload 4
L495:   invokestatic Method org/lwjgl/opengl/GL11 method3848 (FF)V
L498:   iload 5
L500:   iconst_1
L501:   dup
L502:   dup
L503:   pop2
L504:   iadd
L505:   i2f
L506:   aload_0
L507:   getfield Field lG true F
L510:   fmul
L511:   fload 4
L513:   invokestatic Method org/lwjgl/opengl/GL11 method3848 (FF)V
L516:   iload 5
L518:   iconst_1
L519:   dup
L520:   dup
L521:   pop2
L522:   iadd
L523:   i2f
L524:   aload_0
L525:   getfield Field lG true F
L528:   fmul
L529:   fload_3
L530:   invokestatic Method org/lwjgl/opengl/GL11 method3848 (FF)V
L533:   iload 5
L535:   i2f
L536:   aload_0
L537:   getfield Field lG true F
L540:   fmul
L541:   fload_3
L542:   invokestatic Method org/lwjgl/opengl/GL11 method3848 (FF)V
L545:   iconst_0
L546:   iconst_1
L547:   dup
L548:   pop2
L549:   istore 7
L551:   iload 6
L553:   ifeq L1275
L556:   iload 6
L558:   bipush 32
L560:   iconst_1
L561:   dup
L562:   pop2
L563:   iand
L564:   ifeq L1032
L567:   iload 6
L569:   bipush 31
L571:   iconst_1
L572:   dup
L573:   pop2
L574:   iand
L575:   bipush 13
L577:   iconst_1
L578:   dup
L579:   pop2
L580:   if_icmpne L607
L583:   iload_2
L584:   aload_0
L585:   getfield Field lG field1323 I
L588:   if_icmpge L607
L591:   iload 6
L593:   bipush -32
L595:   iconst_1
L596:   dup
L597:   pop2
L598:   iand
L599:   bipush 14
L601:   iconst_1
L602:   dup
L603:   pop2
L604:   ior
L605:   istore 6
L607:   getstatic Field lG m [F
L610:   iload 6
L612:   bipush 31
L614:   iconst_1
L615:   dup
L616:   pop2
L617:   iand
L618:   faload
L619:   fstore 9
L621:   getstatic Field lG new [F
L624:   iload 6
L626:   bipush 31
L628:   iconst_1
L629:   dup
L630:   pop2
L631:   iand
L632:   faload
L633:   fstore 10
L635:   getstatic Field lG J [F
L638:   iload 6
L640:   bipush 31
L642:   iconst_1
L643:   dup
L644:   pop2
L645:   iand
L646:   faload
L647:   fstore 11
L649:   getstatic Field lG field1297 [F
L652:   iload 6
L654:   bipush 31
L656:   iconst_1
L657:   dup
L658:   pop2
L659:   iand
L660:   faload
L661:   fstore 12
L663:   iload 7
L665:   ifeq L731
L668:   fload 9
L670:   getstatic Field lG m [F
L673:   iload 7
L675:   faload
L676:   aload_0
L677:   getfield Field lG field1287 [[F
L680:   iload 5
L682:   aaload
L683:   iload_2
L684:   faload
L685:   fmul
L686:   fsub
L687:   fstore 9
L689:   fload 10
L691:   getstatic Field lG new [F
L694:   iload 7
L696:   faload
L697:   aload_0
L698:   getfield Field lG field1287 [[F
L701:   iload 5
L703:   aaload
L704:   iload_2
L705:   faload
L706:   fmul
L707:   fsub
L708:   fstore 10
L710:   fload 11
L712:   getstatic Field lG J [F
L715:   iload 7
L717:   faload
L718:   aload_0
L719:   getfield Field lG field1287 [[F
L722:   iload 5
L724:   aaload
L725:   iload_2
L726:   faload
L727:   fmul
L728:   fsub
L729:   fstore 11
L731:   ldc_w 1.5e-1f
L734:   ldc2_w 5e-1
L737:   iload 5
L739:   i2f
L740:   fload_3
L741:   aload_0
L742:   getfield Field lG field1293 F
L745:   fdiv
L746:   fadd
L747:   f2d
L748:   dmul
L749:   invokestatic Method java/lang/Math sin (D)D
L752:   d2f
L753:   fmul
L754:   fstore 13
L756:   ldc_w 1.5e-1f
L759:   ldc2_w 5e-1
L762:   iload 5
L764:   i2f
L765:   fload_3
L766:   aload_0
L767:   getfield Field lG field1293 F
L770:   fdiv
L771:   fadd
L772:   fconst_1
L773:   fadd
L774:   f2d
L775:   dmul
L776:   invokestatic Method java/lang/Math sin (D)D
L779:   d2f
L780:   fmul
L781:   fstore 14
L783:   ldc_w 1.5e-1f
L786:   ldc2_w 5e-1
L789:   iload 5
L791:   i2f
L792:   fload_3
L793:   aload_0
L794:   getfield Field lG field1293 F
L797:   fdiv
L798:   fadd
L799:   fconst_2
L800:   fadd
L801:   f2d
L802:   dmul
L803:   invokestatic Method java/lang/Math sin (D)D
L806:   d2f
L807:   fmul
L808:   fstore 15
L810:   invokestatic Method org/lwjgl/opengl/GL11 method3788 ()V
L813:   bipush 6
L815:   iconst_1
L816:   dup
L817:   pop2
L818:   invokestatic Method org/lwjgl/opengl/GL11 method3664 (I)V
L821:   fload 9
L823:   fload 14
L825:   fadd
L826:   fload 10
L828:   fload 14
L830:   fadd
L831:   fload 11
L833:   fload 14
L835:   fadd
L836:   fload 12
L838:   fload 8
L840:   fmul
L841:   fload_1
L842:   fmul
L843:   aload_0
L844:   getfield Field lG field1300 F
L847:   fmul
L848:   ldc_w 1.6e0f
L851:   fmul
L852:   invokestatic Method org/lwjgl/opengl/GL11 method3888 (FFFF)V
L855:   iload 5
L857:   i2f
L858:   aload_0
L859:   getfield Field lG true F
L862:   fmul
L863:   fload 4
L865:   invokestatic Method org/lwjgl/opengl/GL11 method3848 (FF)V
L868:   fload 9
L870:   fload 13
L872:   fadd
L873:   fload 10
L875:   fload 13
L877:   fadd
L878:   fload 11
L880:   fload 13
L882:   fadd
L883:   fload 12
L885:   fload 8
L887:   fmul
L888:   fload_1
L889:   fmul
L890:   aload_0
L891:   getfield Field lG field1300 F
L894:   fmul
L895:   ldc_w 1.6e0f
L898:   fmul
L899:   invokestatic Method org/lwjgl/opengl/GL11 method3888 (FFFF)V
L902:   iload 5
L904:   i2f
L905:   aload_0
L906:   getfield Field lG true F
L909:   fmul
L910:   fload_3
L911:   invokestatic Method org/lwjgl/opengl/GL11 method3848 (FF)V
L914:   fload 9
L916:   fload 14
L918:   fadd
L919:   fload 10
L921:   fload 14
L923:   fadd
L924:   fload 11
L926:   fload 14
L928:   fadd
L929:   fload 12
L931:   fload 8
L933:   fmul
L934:   fload_1
L935:   fmul
L936:   aload_0
L937:   getfield Field lG field1300 F
L940:   fmul
L941:   ldc_w 1.6e0f
L944:   fmul
L945:   invokestatic Method org/lwjgl/opengl/GL11 method3888 (FFFF)V
L948:   iload 5
L950:   iconst_1
L951:   dup
L952:   dup
L953:   pop2
L954:   iadd
L955:   i2f
L956:   aload_0
L957:   getfield Field lG true F
L960:   fmul
L961:   fload_3
L962:   invokestatic Method org/lwjgl/opengl/GL11 method3848 (FF)V
L965:   fload 9
L967:   fload 15
L969:   fadd
L970:   fload 10
L972:   fload 15
L974:   fadd
L975:   fload 11
L977:   fload 15
L979:   fadd
L980:   fload 12
L982:   fload 8
L984:   fmul
L985:   fload_1
L986:   fmul
L987:   aload_0
L988:   getfield Field lG field1300 F
L991:   fmul
L992:   ldc_w 1.6e0f
L995:   fmul
L996:   invokestatic Method org/lwjgl/opengl/GL11 method3888 (FFFF)V
L999:   iload 5
L1001:  iconst_1
L1002:  dup
L1003:  dup
L1004:  pop2
L1005:  iadd
L1006:  i2f
L1007:  aload_0
L1008:  getfield Field lG true F
L1011:  fmul
L1012:  fload 4
L1014:  invokestatic Method org/lwjgl/opengl/GL11 method3848 (FF)V
L1017:  invokestatic Method org/lwjgl/opengl/GL11 method3788 ()V
L1020:  bipush 7
L1022:  iconst_1
L1023:  dup
L1024:  pop2
L1025:  invokestatic Method org/lwjgl/opengl/GL11 method3664 (I)V
L1028:  goto L1275
L1031:  athrow
L1032:  iload 7
L1034:  ifne L1103
L1037:  getstatic Field lG m [F
L1040:  iload 6
L1042:  bipush 31
L1044:  iconst_1
L1045:  dup
L1046:  pop2
L1047:  iand
L1048:  faload
L1049:  getstatic Field lG new [F
L1052:  iload 6
L1054:  bipush 31
L1056:  iconst_1
L1057:  dup
L1058:  pop2
L1059:  iand
L1060:  faload
L1061:  getstatic Field lG J [F
L1064:  iload 6
L1066:  bipush 31
L1068:  iconst_1
L1069:  dup
L1070:  pop2
L1071:  iand
L1072:  faload
L1073:  getstatic Field lG field1297 [F
L1076:  iload 6
L1078:  bipush 31
L1080:  iconst_1
L1081:  dup
L1082:  pop2
L1083:  iand
L1084:  faload
L1085:  fload 8
L1087:  fmul
L1088:  fload_1
L1089:  fmul
L1090:  aload_0
L1091:  getfield Field lG field1300 F
L1094:  fmul
L1095:  invokestatic Method org/lwjgl/opengl/GL11 method3888 (FFFF)V
L1098:  iload 5
L1100:  goto L1217
L1103:  getstatic Field lG m [F
L1106:  iload 6
L1108:  bipush 31
L1110:  iconst_1
L1111:  dup
L1112:  pop2
L1113:  iand
L1114:  faload
L1115:  getstatic Field lG m [F
L1118:  iload 7
L1120:  faload
L1121:  aload_0
L1122:  getfield Field lG field1287 [[F
L1125:  iload 5
L1127:  aaload
L1128:  iload_2
L1129:  faload
L1130:  fmul
L1131:  fsub
L1132:  getstatic Field lG new [F
L1135:  iload 6
L1137:  bipush 31
L1139:  iconst_1
L1140:  dup
L1141:  pop2
L1142:  iand
L1143:  faload
L1144:  getstatic Field lG new [F
L1147:  iload 7
L1149:  faload
L1150:  aload_0
L1151:  getfield Field lG field1287 [[F
L1154:  iload 5
L1156:  aaload
L1157:  iload_2
L1158:  faload
L1159:  fmul
L1160:  fsub
L1161:  getstatic Field lG J [F
L1164:  iload 6
L1166:  bipush 31
L1168:  iconst_1
L1169:  dup
L1170:  pop2
L1171:  iand
L1172:  faload
L1173:  getstatic Field lG J [F
L1176:  iload 7
L1178:  faload
L1179:  aload_0
L1180:  getfield Field lG field1287 [[F
L1183:  iload 5
L1185:  aaload
L1186:  iload_2
L1187:  faload
L1188:  fmul
L1189:  fsub
L1190:  getstatic Field lG field1297 [F
L1193:  iload 6
L1195:  bipush 31
L1197:  iconst_1
L1198:  dup
L1199:  pop2
L1200:  iand
L1201:  faload
L1202:  fload 8
L1204:  fmul
L1205:  fload_1
L1206:  fmul
L1207:  aload_0
L1208:  getfield Field lG field1300 F
L1211:  fmul
L1212:  invokestatic Method org/lwjgl/opengl/GL11 method3888 (FFFF)V
L1215:  iload 5
L1217:  i2f
L1218:  aload_0
L1219:  getfield Field lG true F
L1222:  fmul
L1223:  fload 4
L1225:  invokestatic Method org/lwjgl/opengl/GL11 method3848 (FF)V
L1228:  iload 5
L1230:  iconst_1
L1231:  dup
L1232:  dup
L1233:  pop2
L1234:  iadd
L1235:  i2f
L1236:  aload_0
L1237:  getfield Field lG true F
L1240:  fmul
L1241:  fload 4
L1243:  invokestatic Method org/lwjgl/opengl/GL11 method3848 (FF)V
L1246:  iload 5
L1248:  iconst_1
L1249:  dup
L1250:  dup
L1251:  pop2
L1252:  iadd
L1253:  i2f
L1254:  aload_0
L1255:  getfield Field lG true F
L1258:  fmul
L1259:  fload_3
L1260:  invokestatic Method org/lwjgl/opengl/GL11 method3848 (FF)V
L1263:  iload 5
L1265:  i2f
L1266:  aload_0
L1267:  getfield Field lG true F
L1270:  fmul
L1271:  fload_3
L1272:  invokestatic Method org/lwjgl/opengl/GL11 method3848 (FF)V
L1275:  iinc 5 1
L1278:  iload 5
L1280:  goto L214
L1283:  iinc 2 1
L1286:  iload_2
L1287:  goto L101
L1290:  invokestatic Method org/lwjgl/opengl/GL11 method3788 ()V
L1293:  aload_0
L1294:  getfield Field lG field1298 Z
L1297:  ifeq L1897
L1300:  aload_0
L1301:  iconst_0
L1302:  dup_x1
L1303:  iconst_1
L1304:  dup
L1305:  pop2
L1306:  putfield Field lG field1298 Z
L1309:  iconst_1
L1310:  dup
L1311:  pop2
L1312:  dup
L1313:  istore_2
L1314:  aload_0
L1315:  getfield Field lG field1284 I
L1318:  if_icmpge L1379
L1321:  aload_0
L1322:  dup
L1323:  dup2
L1324:  getfield Field lG field1292 [[I
L1327:  iload_2
L1328:  aaload
L1329:  iconst_0
L1330:  iconst_1
L1331:  dup
L1332:  pop2
L1333:  invokestatic Method java/util/Arrays fill ([II)V
L1336:  getfield Field lG D [[I
L1339:  iload_2
L1340:  aaload
L1341:  iconst_0
L1342:  iconst_1
L1343:  dup
L1344:  pop2
L1345:  invokestatic Method java/util/Arrays fill ([II)V
L1348:  getfield Field lG i [[I
L1351:  iload_2
L1352:  aaload
L1353:  iconst_0
L1354:  iconst_1
L1355:  dup
L1356:  pop2
L1357:  invokestatic Method java/util/Arrays fill ([II)V
L1360:  getfield Field lG b [[I
L1363:  iload_2
L1364:  iinc 2 1
L1367:  aaload
L1368:  iconst_0
L1369:  iconst_1
L1370:  dup
L1371:  pop2
L1372:  invokestatic Method java/util/Arrays fill ([II)V
L1375:  iload_2
L1376:  goto L1314
L1379:  iconst_0
L1380:  iconst_1
L1381:  dup
L1382:  pop2
L1383:  dup
L1384:  istore_2
L1385:  aload_0
L1386:  getfield Field lG field1312 I
L1389:  if_icmpge L1897
L1392:  iconst_0
L1393:  iconst_1
L1394:  dup
L1395:  pop2
L1396:  dup
L1397:  istore_3
L1398:  aload_0
L1399:  getfield Field lG field1284 I
L1402:  if_icmpge L1890
L1405:  aload_0
L1406:  getfield Field lG field1304 [[I
L1409:  iload_3
L1410:  aaload
L1411:  iload_2
L1412:  iaload
L1413:  dup
L1414:  istore 4
L1416:  sipush 2048
L1419:  iconst_1
L1420:  dup
L1421:  pop2
L1422:  iand
L1423:  ifeq L1469
L1426:  iload 4
L1428:  bipush 31
L1430:  iconst_1
L1431:  dup
L1432:  pop2
L1433:  iand
L1434:  ifeq L1469
L1437:  aload_0
L1438:  dup
L1439:  getfield Field lG i [[I
L1442:  iload_3
L1443:  aaload
L1444:  iload_2
L1445:  iload 4
L1447:  bipush 31
L1449:  iconst_1
L1450:  dup
L1451:  pop2
L1452:  iand
L1453:  iastore
L1454:  getfield Field lG E [[F
L1457:  iload_3
L1458:  aaload
L1459:  aload_0
L1460:  getfield Field lG field1287 [[F
L1463:  iload_3
L1464:  aaload
L1465:  iload_2
L1466:  dup_x1
L1467:  faload
L1468:  fastore
L1469:  iload 4
L1471:  sipush 512
L1474:  iconst_1
L1475:  dup
L1476:  pop2
L1477:  iand
L1478:  ifeq L1524
L1481:  iload 4
L1483:  bipush 31
L1485:  iconst_1
L1486:  dup
L1487:  pop2
L1488:  iand
L1489:  ifeq L1524
L1492:  aload_0
L1493:  dup
L1494:  getfield Field lG b [[I
L1497:  iload_3
L1498:  aaload
L1499:  iload_2
L1500:  iload 4
L1502:  bipush 31
L1504:  iconst_1
L1505:  dup
L1506:  pop2
L1507:  iand
L1508:  iastore
L1509:  getfield Field lG field1288 [[F
L1512:  iload_3
L1513:  aaload
L1514:  aload_0
L1515:  getfield Field lG field1287 [[F
L1518:  iload_3
L1519:  aaload
L1520:  iload_2
L1521:  dup_x1
L1522:  faload
L1523:  fastore
L1524:  aload_0
L1525:  getfield Field lG field1309 [[I
L1528:  iload_3
L1529:  aaload
L1530:  iload_2
L1531:  iaload
L1532:  istore 5
L1534:  fconst_1
L1535:  fstore 6
L1537:  iload 5
L1539:  ifne L1604
L1542:  iload_3
L1543:  aload_0
L1544:  getfield Field lG field1296 I
L1547:  if_icmplt L1604
L1550:  iload_3
L1551:  aload_0
L1552:  getfield Field lG field1296 I
L1555:  iconst_4
L1556:  iconst_1
L1557:  dup
L1558:  pop2
L1559:  iadd
L1560:  if_icmpge L1604
L1563:  iload_2
L1564:  aload_0
L1565:  getfield Field lG field1291 I
L1568:  if_icmplt L1604
L1571:  iload_2
L1572:  aload_0
L1573:  getfield Field lG field1291 I
L1576:  iconst_4
L1577:  iconst_1
L1578:  dup
L1579:  pop2
L1580:  iadd
L1581:  if_icmpge L1604
L1584:  aload_0
L1585:  getfield Field lG I [[I
L1588:  iload_3
L1589:  aload_0
L1590:  getfield Field lG field1296 I
L1593:  isub
L1594:  aaload
L1595:  iload_2
L1596:  aload_0
L1597:  getfield Field lG field1291 I
L1600:  isub
L1601:  iaload
L1602:  istore 5
L1604:  iload 5
L1606:  ifne L1687
L1609:  aload_0
L1610:  getfield Field lG field1285 Z
L1613:  ifeq L1687
L1616:  iload_3
L1617:  aload_0
L1618:  getfield Field lG a I
L1621:  if_icmplt L1687
L1624:  iload_3
L1625:  aload_0
L1626:  getfield Field lG a I
L1629:  iconst_4
L1630:  iconst_1
L1631:  dup
L1632:  pop2
L1633:  iadd
L1634:  if_icmpge L1687
L1637:  iload_2
L1638:  aload_0
L1639:  getfield Field lG h I
L1642:  if_icmplt L1687
L1645:  iload_2
L1646:  aload_0
L1647:  getfield Field lG h I
L1650:  iconst_4
L1651:  iconst_1
L1652:  dup
L1653:  pop2
L1654:  iadd
L1655:  if_icmpge L1687
L1658:  aload_0
L1659:  getfield Field lG I [[I
L1662:  iload_3
L1663:  aload_0
L1664:  getfield Field lG a I
L1667:  isub
L1668:  aaload
L1669:  iload_2
L1670:  aload_0
L1671:  getfield Field lG h I
L1674:  isub
L1675:  iaload
L1676:  dup
L1677:  istore 5
L1679:  ifeq L1687
L1682:  ldc_w 3.5e-1f
L1685:  fstore 6
L1687:  iload 5
L1689:  sipush 256
L1692:  iconst_1
L1693:  dup
L1694:  pop2
L1695:  iand
L1696:  ifeq L1736
L1699:  iload 5
L1701:  bipush 31
L1703:  iconst_1
L1704:  dup
L1705:  pop2
L1706:  iand
L1707:  ifeq L1736
L1710:  aload_0
L1711:  dup
L1712:  getfield Field lG field1292 [[I
L1715:  iload_3
L1716:  aaload
L1717:  iload_2
L1718:  iload 5
L1720:  bipush 31
L1722:  iconst_1
L1723:  dup
L1724:  pop2
L1725:  iand
L1726:  iastore
L1727:  getfield Field lG field1289 [[F
L1730:  iload_3
L1731:  aaload
L1732:  iload_2
L1733:  fload 6
L1735:  fastore
L1736:  iload 5
L1738:  sipush 1024
L1741:  iconst_1
L1742:  dup
L1743:  pop2
L1744:  iand
L1745:  ifeq L1785
L1748:  iload 5
L1750:  bipush 31
L1752:  iconst_1
L1753:  dup
L1754:  pop2
L1755:  iand
L1756:  ifeq L1785
L1759:  aload_0
L1760:  dup
L1761:  getfield Field lG D [[I
L1764:  iload_3
L1765:  aaload
L1766:  iload_2
L1767:  iload 5
L1769:  bipush 31
L1771:  iconst_1
L1772:  dup
L1773:  pop2
L1774:  iand
L1775:  iastore
L1776:  getfield Field lG e [[F
L1779:  iload_3
L1780:  aaload
L1781:  iload_2
L1782:  fload 6
L1784:  fastore
L1785:  iload 5
L1787:  sipush 2048
L1790:  iconst_1
L1791:  dup
L1792:  pop2
L1793:  iand
L1794:  ifeq L1834
L1797:  iload 5
L1799:  bipush 31
L1801:  iconst_1
L1802:  dup
L1803:  pop2
L1804:  iand
L1805:  ifeq L1834
L1808:  aload_0
L1809:  dup
L1810:  getfield Field lG i [[I
L1813:  iload_3
L1814:  aaload
L1815:  iload_2
L1816:  iload 5
L1818:  bipush 31
L1820:  iconst_1
L1821:  dup
L1822:  pop2
L1823:  iand
L1824:  iastore
L1825:  getfield Field lG E [[F
L1828:  iload_3
L1829:  aaload
L1830:  iload_2
L1831:  fload 6
L1833:  fastore
L1834:  iload 5
L1836:  sipush 512
L1839:  iconst_1
L1840:  dup
L1841:  pop2
L1842:  iand
L1843:  ifeq L1883
L1846:  iload 5
L1848:  bipush 31
L1850:  iconst_1
L1851:  dup
L1852:  pop2
L1853:  iand
L1854:  ifeq L1883
L1857:  aload_0
L1858:  dup
L1859:  getfield Field lG b [[I
L1862:  iload_3
L1863:  aaload
L1864:  iload_2
L1865:  iload 5
L1867:  bipush 31
L1869:  iconst_1
L1870:  dup
L1871:  pop2
L1872:  iand
L1873:  iastore
L1874:  getfield Field lG field1288 [[F
L1877:  iload_3
L1878:  aaload
L1879:  iload_2
L1880:  fload 6
L1882:  fastore
L1883:  iinc 3 1
L1886:  iload_3
L1887:  goto L1398
L1890:  iinc 2 1
L1893:  iload_2
L1894:  goto L1385
L1897:  iconst_1
L1898:  dup
L1899:  dup
L1900:  pop2
L1901:  invokestatic Method org/lwjgl/opengl/GL11 method3664 (I)V
L1904:  aload_0
L1905:  getfield Field lG field1305 I
L1908:  dup
L1909:  istore_2
L1910:  aload_0
L1911:  getfield Field lG field1312 I
L1914:  if_icmpge L2426
L1917:  iload_2
L1918:  i2f
L1919:  aload_0
L1920:  getfield Field lG try [F
L1923:  iload_2
L1924:  faload
L1925:  fsub
L1926:  aload_0
L1927:  getfield Field lG field1317 F
L1930:  fadd
L1931:  aload_0
L1932:  getfield Field lG field163 F
L1935:  fsub
L1936:  aload_0
L1937:  getfield Field lG field1293 F
L1940:  fmul
L1941:  dup
L1942:  fstore_3
L1943:  aload_0
L1944:  getfield Field lG field1293 F
L1947:  fadd
L1948:  dup
L1949:  fstore 4
L1951:  aload_0
L1952:  getfield Field lG field1305 I
L1955:  i2f
L1956:  aload_0
L1957:  getfield Field lG field1293 F
L1960:  fmul
L1961:  ldc_w 1e-6f
L1964:  fadd
L1965:  fcmpl
L1966:  iflt L2419
L1969:  fload_3
L1970:  aload_0
L1971:  getfield Field lG field1132 F
L1974:  fcmpg
L1975:  ifgt L2419
L1978:  fload_3
L1979:  aload_0
L1980:  getfield Field lG field1305 I
L1983:  i2f
L1984:  aload_0
L1985:  getfield Field lG field1293 F
L1988:  fmul
L1989:  fcmpg
L1990:  ifge L2004
L1993:  aload_0
L1994:  getfield Field lG field1305 I
L1997:  i2f
L1998:  aload_0
L1999:  getfield Field lG field1293 F
L2002:  fmul
L2003:  fstore_3
L2004:  fload 4
L2006:  aload_0
L2007:  getfield Field lG field1132 F
L2010:  fcmpl
L2011:  ifle L2020
L2014:  aload_0
L2015:  getfield Field lG field1132 F
L2018:  fstore 4
L2020:  fconst_0
L2021:  fstore 5
L2023:  iconst_0
L2024:  iconst_1
L2025:  dup
L2026:  pop2
L2027:  istore 6
L2029:  iconst_0
L2030:  iconst_1
L2031:  dup
L2032:  pop2
L2033:  dup
L2034:  istore 7
L2036:  aload_0
L2037:  getfield Field lG field1284 I
L2040:  if_icmpge L2202
L2043:  aload_0
L2044:  getfield Field lG field1292 [[I
L2047:  iload 7
L2049:  aaload
L2050:  iload_2
L2051:  iaload
L2052:  iload 6
L2054:  if_icmpne L2072
L2057:  aload_0
L2058:  getfield Field lG field1289 [[F
L2061:  iload 7
L2063:  aaload
L2064:  iload_2
L2065:  faload
L2066:  fload 5
L2068:  fcmpl
L2069:  ifeq L2194
L2072:  iload 6
L2074:  ifeq L2089
L2077:  iload 7
L2079:  i2f
L2080:  aload_0
L2081:  getfield Field lG true F
L2084:  fmul
L2085:  fload_3
L2086:  invokestatic Method org/lwjgl/opengl/GL11 method3848 (FF)V
L2089:  aload_0
L2090:  dup
L2091:  getfield Field lG field1292 [[I
L2094:  iload 7
L2096:  aaload
L2097:  iload_2
L2098:  iaload
L2099:  istore 6
L2101:  getfield Field lG field1289 [[F
L2104:  iload 7
L2106:  aaload
L2107:  iload_2
L2108:  faload
L2109:  fstore 5
L2111:  iload 6
L2113:  ifeq L2194
L2116:  getstatic Field lG m [F
L2119:  iload 6
L2121:  bipush 31
L2123:  iconst_1
L2124:  dup
L2125:  pop2
L2126:  iand
L2127:  faload
L2128:  getstatic Field lG new [F
L2131:  iload 6
L2133:  bipush 31
L2135:  iconst_1
L2136:  dup
L2137:  pop2
L2138:  iand
L2139:  faload
L2140:  getstatic Field lG J [F
L2143:  iload 6
L2145:  bipush 31
L2147:  iconst_1
L2148:  dup
L2149:  pop2
L2150:  iand
L2151:  faload
L2152:  getstatic Field lG field1297 [F
L2155:  iload 6
L2157:  bipush 31
L2159:  iconst_1
L2160:  dup
L2161:  pop2
L2162:  iand
L2163:  faload
L2164:  fload 5
L2166:  fmul
L2167:  fload_1
L2168:  fmul
L2169:  aload_0
L2170:  getfield Field lG field1300 F
L2173:  fmul
L2174:  aload_0
L2175:  getfield Field lG field1300 F
L2178:  fmul
L2179:  invokestatic Method org/lwjgl/opengl/GL11 method3888 (FFFF)V
L2182:  iload 7
L2184:  i2f
L2185:  aload_0
L2186:  getfield Field lG true F
L2189:  fmul
L2190:  fload_3
L2191:  invokestatic Method org/lwjgl/opengl/GL11 method3848 (FF)V
L2194:  iinc 7 1
L2197:  iload 7
L2199:  goto L2036
L2202:  iload 6
L2204:  ifeq L2221
L2207:  aload_0
L2208:  getfield Field lG field1284 I
L2211:  i2f
L2212:  aload_0
L2213:  getfield Field lG true F
L2216:  fmul
L2217:  fload_3
L2218:  invokestatic Method org/lwjgl/opengl/GL11 method3848 (FF)V
L2221:  fconst_1
L2222:  fstore 5
L2224:  iconst_0
L2225:  iconst_1
L2226:  dup
L2227:  pop2
L2228:  istore 6
L2230:  iconst_0
L2231:  iconst_1
L2232:  dup
L2233:  pop2
L2234:  dup
L2235:  istore 7
L2237:  aload_0
L2238:  getfield Field lG field1284 I
L2241:  if_icmpge L2405
L2244:  aload_0
L2245:  getfield Field lG D [[I
L2248:  iload 7
L2250:  aaload
L2251:  iload_2
L2252:  iaload
L2253:  iload 6
L2255:  if_icmpne L2273
L2258:  aload_0
L2259:  getfield Field lG e [[F
L2262:  iload 7
L2264:  aaload
L2265:  iload_2
L2266:  faload
L2267:  fload 5
L2269:  fcmpl
L2270:  ifeq L2397
L2273:  iload 6
L2275:  ifeq L2291
L2278:  iload 7
L2280:  i2f
L2281:  aload_0
L2282:  getfield Field lG true F
L2285:  fmul
L2286:  fload 4
L2288:  invokestatic Method org/lwjgl/opengl/GL11 method3848 (FF)V
L2291:  aload_0
L2292:  dup
L2293:  getfield Field lG D [[I
L2296:  iload 7
L2298:  aaload
L2299:  iload_2
L2300:  iaload
L2301:  istore 6
L2303:  getfield Field lG e [[F
L2306:  iload 7
L2308:  aaload
L2309:  iload_2
L2310:  faload
L2311:  fstore 5
L2313:  iload 6
L2315:  ifeq L2397
L2318:  getstatic Field lG m [F
L2321:  iload 6
L2323:  bipush 31
L2325:  iconst_1
L2326:  dup
L2327:  pop2
L2328:  iand
L2329:  faload
L2330:  getstatic Field lG new [F
L2333:  iload 6
L2335:  bipush 31
L2337:  iconst_1
L2338:  dup
L2339:  pop2
L2340:  iand
L2341:  faload
L2342:  getstatic Field lG J [F
L2345:  iload 6
L2347:  bipush 31
L2349:  iconst_1
L2350:  dup
L2351:  pop2
L2352:  iand
L2353:  faload
L2354:  getstatic Field lG field1297 [F
L2357:  iload 6
L2359:  bipush 31
L2361:  iconst_1
L2362:  dup
L2363:  pop2
L2364:  iand
L2365:  faload
L2366:  fload 5
L2368:  fmul
L2369:  fload_1
L2370:  fmul
L2371:  aload_0
L2372:  getfield Field lG field1300 F
L2375:  fmul
L2376:  aload_0
L2377:  getfield Field lG field1300 F
L2380:  fmul
L2381:  invokestatic Method org/lwjgl/opengl/GL11 method3888 (FFFF)V
L2384:  iload 7
L2386:  i2f
L2387:  aload_0
L2388:  getfield Field lG true F
L2391:  fmul
L2392:  fload 4
L2394:  invokestatic Method org/lwjgl/opengl/GL11 method3848 (FF)V
L2397:  iinc 7 1
L2400:  iload 7
L2402:  goto L2237
L2405:  iload 6
L2407:  ifeq L2419
L2410:  aload_0
L2411:  getfield Field lG field1124 F
L2414:  fload 4
L2416:  invokestatic Method org/lwjgl/opengl/GL11 method3848 (FF)V
L2419:  iinc 2 1
L2422:  iload_2
L2423:  goto L1910
L2426:  iconst_0
L2427:  iconst_1
L2428:  dup
L2429:  pop2
L2430:  dup
L2431:  istore_2
L2432:  aload_0
L2433:  getfield Field lG field1284 I
L2436:  if_icmpge L3065
L2439:  fconst_1
L2440:  fstore_3
L2441:  iconst_0
L2442:  iconst_1
L2443:  dup
L2444:  pop2
L2445:  istore 4
L2447:  aload_0
L2448:  getfield Field lG field1305 I
L2451:  dup
L2452:  istore 5
L2454:  aload_0
L2455:  getfield Field lG field1312 I
L2458:  if_icmpge L2722
L2461:  iload 5
L2463:  i2f
L2464:  aload_0
L2465:  getfield Field lG try [F
L2468:  iload 5
L2470:  faload
L2471:  fsub
L2472:  aload_0
L2473:  getfield Field lG field1317 F
L2476:  fadd
L2477:  aload_0
L2478:  getfield Field lG field163 F
L2481:  fsub
L2482:  aload_0
L2483:  getfield Field lG field1293 F
L2486:  fmul
L2487:  dup
L2488:  fstore 6
L2490:  aload_0
L2491:  getfield Field lG field1293 F
L2494:  fadd
L2495:  dup
L2496:  fstore 7
L2498:  aload_0
L2499:  getfield Field lG field1305 I
L2502:  i2f
L2503:  aload_0
L2504:  getfield Field lG field1293 F
L2507:  fmul
L2508:  fcmpl
L2509:  iflt L2714
L2512:  fload 6
L2514:  aload_0
L2515:  getfield Field lG field1132 F
L2518:  fcmpg
L2519:  ifgt L2714
L2522:  fload 6
L2524:  aload_0
L2525:  getfield Field lG field1305 I
L2528:  i2f
L2529:  aload_0
L2530:  getfield Field lG field1293 F
L2533:  fmul
L2534:  fcmpg
L2535:  ifge L2550
L2538:  aload_0
L2539:  getfield Field lG field1305 I
L2542:  i2f
L2543:  aload_0
L2544:  getfield Field lG field1293 F
L2547:  fmul
L2548:  fstore 6
L2550:  fload 7
L2552:  aload_0
L2553:  getfield Field lG field1132 F
L2556:  fcmpl
L2557:  ifle L2566
L2560:  aload_0
L2561:  getfield Field lG field1132 F
L2564:  fstore 7
L2566:  aload_0
L2567:  getfield Field lG i [[I
L2570:  iload_2
L2571:  aaload
L2572:  iload 5
L2574:  iaload
L2575:  iload 4
L2577:  if_icmpne L2594
L2580:  aload_0
L2581:  getfield Field lG E [[F
L2584:  iload_2
L2585:  aaload
L2586:  iload 5
L2588:  faload
L2589:  fload_3
L2590:  fcmpl
L2591:  ifeq L2714
L2594:  iload 4
L2596:  ifeq L2611
L2599:  iload_2
L2600:  i2f
L2601:  aload_0
L2602:  getfield Field lG true F
L2605:  fmul
L2606:  fload 6
L2608:  invokestatic Method org/lwjgl/opengl/GL11 method3848 (FF)V
L2611:  aload_0
L2612:  dup
L2613:  getfield Field lG i [[I
L2616:  iload_2
L2617:  aaload
L2618:  iload 5
L2620:  iaload
L2621:  istore 4
L2623:  getfield Field lG E [[F
L2626:  iload_2
L2627:  aaload
L2628:  iload 5
L2630:  faload
L2631:  fstore_3
L2632:  iload 4
L2634:  ifeq L2714
L2637:  getstatic Field lG m [F
L2640:  iload 4
L2642:  bipush 31
L2644:  iconst_1
L2645:  dup
L2646:  pop2
L2647:  iand
L2648:  faload
L2649:  getstatic Field lG new [F
L2652:  iload 4
L2654:  bipush 31
L2656:  iconst_1
L2657:  dup
L2658:  pop2
L2659:  iand
L2660:  faload
L2661:  getstatic Field lG J [F
L2664:  iload 4
L2666:  bipush 31
L2668:  iconst_1
L2669:  dup
L2670:  pop2
L2671:  iand
L2672:  faload
L2673:  getstatic Field lG field1297 [F
L2676:  iload 4
L2678:  bipush 31
L2680:  iconst_1
L2681:  dup
L2682:  pop2
L2683:  iand
L2684:  faload
L2685:  fload_3
L2686:  fmul
L2687:  fload_1
L2688:  fmul
L2689:  aload_0
L2690:  getfield Field lG field1300 F
L2693:  fmul
L2694:  aload_0
L2695:  getfield Field lG field1300 F
L2698:  fmul
L2699:  invokestatic Method org/lwjgl/opengl/GL11 method3888 (FFFF)V
L2702:  iload_2
L2703:  i2f
L2704:  aload_0
L2705:  getfield Field lG true F
L2708:  fmul
L2709:  fload 6
L2711:  invokestatic Method org/lwjgl/opengl/GL11 method3848 (FF)V
L2714:  iinc 5 1
L2717:  iload 5
L2719:  goto L2454
L2722:  iload 4
L2724:  ifeq L2741
L2727:  iload_2
L2728:  i2f
L2729:  aload_0
L2730:  getfield Field lG true F
L2733:  fmul
L2734:  aload_0
L2735:  getfield Field lG field1132 F
L2738:  invokestatic Method org/lwjgl/opengl/GL11 method3848 (FF)V
L2741:  fconst_1
L2742:  fstore_3
L2743:  iconst_0
L2744:  iconst_1
L2745:  dup
L2746:  pop2
L2747:  istore 4
L2749:  aload_0
L2750:  getfield Field lG field1305 I
L2753:  dup
L2754:  istore 5
L2756:  aload_0
L2757:  getfield Field lG field1312 I
L2760:  if_icmpge L3034
L2763:  iload 5
L2765:  i2f
L2766:  aload_0
L2767:  getfield Field lG try [F
L2770:  iload 5
L2772:  faload
L2773:  fsub
L2774:  aload_0
L2775:  getfield Field lG field1317 F
L2778:  fadd
L2779:  aload_0
L2780:  getfield Field lG field163 F
L2783:  fsub
L2784:  aload_0
L2785:  getfield Field lG field1293 F
L2788:  fmul
L2789:  dup
L2790:  fstore 6
L2792:  aload_0
L2793:  getfield Field lG field1293 F
L2796:  fadd
L2797:  dup
L2798:  fstore 7
L2800:  aload_0
L2801:  getfield Field lG field1305 I
L2804:  i2f
L2805:  aload_0
L2806:  getfield Field lG field1293 F
L2809:  fmul
L2810:  fcmpl
L2811:  iflt L3026
L2814:  fload 6
L2816:  aload_0
L2817:  getfield Field lG field1132 F
L2820:  fcmpg
L2821:  ifgt L3026
L2824:  fload 6
L2826:  aload_0
L2827:  getfield Field lG field1305 I
L2830:  i2f
L2831:  aload_0
L2832:  getfield Field lG field1293 F
L2835:  fmul
L2836:  fcmpg
L2837:  ifge L2852
L2840:  aload_0
L2841:  getfield Field lG field1305 I
L2844:  i2f
L2845:  aload_0
L2846:  getfield Field lG field1293 F
L2849:  fmul
L2850:  fstore 6
L2852:  fload 7
L2854:  aload_0
L2855:  getfield Field lG field1132 F
L2858:  fcmpl
L2859:  ifle L2868
L2862:  aload_0
L2863:  getfield Field lG field1132 F
L2866:  fstore 7
L2868:  aload_0
L2869:  getfield Field lG b [[I
L2872:  iload_2
L2873:  aaload
L2874:  iload 5
L2876:  iaload
L2877:  iload 4
L2879:  if_icmpne L2896
L2882:  aload_0
L2883:  getfield Field lG field1288 [[F
L2886:  iload_2
L2887:  aaload
L2888:  iload 5
L2890:  faload
L2891:  fload_3
L2892:  fcmpl
L2893:  ifeq L3026
L2896:  iload 4
L2898:  ifeq L2918
L2901:  iload_2
L2902:  iconst_1
L2903:  dup
L2904:  dup
L2905:  pop2
L2906:  iadd
L2907:  i2f
L2908:  aload_0
L2909:  getfield Field lG true F
L2912:  fmul
L2913:  fload 6
L2915:  invokestatic Method org/lwjgl/opengl/GL11 method3848 (FF)V
L2918:  aload_0
L2919:  dup
L2920:  getfield Field lG b [[I
L2923:  iload_2
L2924:  aaload
L2925:  iload 5
L2927:  iaload
L2928:  istore 4
L2930:  getfield Field lG field1288 [[F
L2933:  iload_2
L2934:  aaload
L2935:  iload 5
L2937:  faload
L2938:  fstore_3
L2939:  iload 4
L2941:  ifeq L3026
L2944:  getstatic Field lG m [F
L2947:  iload 4
L2949:  bipush 31
L2951:  iconst_1
L2952:  dup
L2953:  pop2
L2954:  iand
L2955:  faload
L2956:  getstatic Field lG new [F
L2959:  iload 4
L2961:  bipush 31
L2963:  iconst_1
L2964:  dup
L2965:  pop2
L2966:  iand
L2967:  faload
L2968:  getstatic Field lG J [F
L2971:  iload 4
L2973:  bipush 31
L2975:  iconst_1
L2976:  dup
L2977:  pop2
L2978:  iand
L2979:  faload
L2980:  getstatic Field lG field1297 [F
L2983:  iload 4
L2985:  bipush 31
L2987:  iconst_1
L2988:  dup
L2989:  pop2
L2990:  iand
L2991:  faload
L2992:  fload_3
L2993:  fmul
L2994:  fload_1
L2995:  fmul
L2996:  aload_0
L2997:  getfield Field lG field1300 F
L3000:  fmul
L3001:  aload_0
L3002:  getfield Field lG field1300 F
L3005:  fmul
L3006:  invokestatic Method org/lwjgl/opengl/GL11 method3888 (FFFF)V
L3009:  iload_2
L3010:  iconst_1
L3011:  dup
L3012:  dup
L3013:  pop2
L3014:  iadd
L3015:  i2f
L3016:  aload_0
L3017:  getfield Field lG true F
L3020:  fmul
L3021:  fload 6
L3023:  invokestatic Method org/lwjgl/opengl/GL11 method3848 (FF)V
L3026:  iinc 5 1
L3029:  iload 5
L3031:  goto L2756
L3034:  iload 4
L3036:  ifeq L3058
L3039:  iload_2
L3040:  iconst_1
L3041:  dup
L3042:  dup
L3043:  pop2
L3044:  iadd
L3045:  i2f
L3046:  aload_0
L3047:  getfield Field lG true F
L3050:  fmul
L3051:  aload_0
L3052:  getfield Field lG field1132 F
L3055:  invokestatic Method org/lwjgl/opengl/GL11 method3848 (FF)V
L3058:  iinc 2 1
L3061:  iload_2
L3062:  goto L2432
L3065:  invokestatic Method org/lwjgl/opengl/GL11 method3788 ()V
L3068:  aload_0
L3069:  getfield Field lG field1305 I
L3072:  dup
L3073:  istore_2
L3074:  aload_0
L3075:  getfield Field lG field1312 I
L3078:  if_icmpge L3313
L3081:  iload_2
L3082:  aload_0
L3083:  getfield Field lG field1312 I
L3086:  iconst_1
L3087:  dup
L3088:  dup
L3089:  pop2
L3090:  isub
L3091:  if_icmpne L3100
L3094:  fconst_0
L3095:  fstore_3
L3096:  aload_0
L3097:  goto L3113
L3100:  aload_0
L3101:  dup
L3102:  getfield Field lG try [F
L3105:  iload_2
L3106:  iconst_1
L3107:  dup
L3108:  dup
L3109:  pop2
L3110:  iadd
L3111:  faload
L3112:  fstore_3
L3113:  getfield Field lG try [F
L3116:  iload_2
L3117:  faload
L3118:  fload_3
L3119:  fcmpl
L3120:  ifle L3306
L3123:  iload_2
L3124:  iconst_1
L3125:  dup
L3126:  dup
L3127:  pop2
L3128:  iadd
L3129:  i2f
L3130:  aload_0
L3131:  getfield Field lG try [F
L3134:  iload_2
L3135:  faload
L3136:  fsub
L3137:  aload_0
L3138:  getfield Field lG field1317 F
L3141:  fadd
L3142:  aload_0
L3143:  getfield Field lG field163 F
L3146:  fsub
L3147:  aload_0
L3148:  getfield Field lG field1293 F
L3151:  fmul
L3152:  fstore 4
L3154:  iload_2
L3155:  iconst_1
L3156:  dup
L3157:  dup
L3158:  pop2
L3159:  iadd
L3160:  i2f
L3161:  fload_3
L3162:  fsub
L3163:  aload_0
L3164:  getfield Field lG field1317 F
L3167:  fadd
L3168:  aload_0
L3169:  getfield Field lG field163 F
L3172:  fsub
L3173:  aload_0
L3174:  getfield Field lG field1293 F
L3177:  fmul
L3178:  dup
L3179:  fstore 5
L3181:  aload_0
L3182:  getfield Field lG field1305 I
L3185:  i2f
L3186:  aload_0
L3187:  getfield Field lG field1293 F
L3190:  fmul
L3191:  fcmpl
L3192:  iflt L3306
L3195:  fload 4
L3197:  aload_0
L3198:  getfield Field lG field1132 F
L3201:  fcmpg
L3202:  ifgt L3306
L3205:  fload 4
L3207:  aload_0
L3208:  getfield Field lG field1305 I
L3211:  i2f
L3212:  aload_0
L3213:  getfield Field lG field1293 F
L3216:  fmul
L3217:  fcmpg
L3218:  ifge L3233
L3221:  aload_0
L3222:  getfield Field lG field1305 I
L3225:  i2f
L3226:  aload_0
L3227:  getfield Field lG field1293 F
L3230:  fmul
L3231:  fstore 4
L3233:  fload 5
L3235:  aload_0
L3236:  getfield Field lG field1132 F
L3239:  fcmpl
L3240:  ifle L3249
L3243:  aload_0
L3244:  getfield Field lG field1132 F
L3247:  fstore 5
L3249:  fconst_1
L3250:  dup
L3251:  dup
L3252:  ldc_w 7e-1f
L3255:  fload_1
L3256:  fmul
L3257:  aload_0
L3258:  getfield Field lG field1300 F
L3261:  fmul
L3262:  invokestatic Method org/lwjgl/opengl/GL11 method3888 (FFFF)V
L3265:  bipush 7
L3267:  iconst_1
L3268:  dup
L3269:  pop2
L3270:  invokestatic Method org/lwjgl/opengl/GL11 method3664 (I)V
L3273:  fconst_0
L3274:  fload 4
L3276:  invokestatic Method org/lwjgl/opengl/GL11 method3848 (FF)V
L3279:  fconst_0
L3280:  fload 5
L3282:  invokestatic Method org/lwjgl/opengl/GL11 method3848 (FF)V
L3285:  aload_0
L3286:  dup
L3287:  getfield Field lG field1124 F
L3290:  fload 5
L3292:  invokestatic Method org/lwjgl/opengl/GL11 method3848 (FF)V
L3295:  getfield Field lG field1124 F
L3298:  fload 4
L3300:  invokestatic Method org/lwjgl/opengl/GL11 method3848 (FF)V
L3303:  invokestatic Method org/lwjgl/opengl/GL11 method3788 ()V
L3306:  iinc 2 1
L3309:  iload_2
L3310:  goto L3074
L3313:  aload_0
L3314:  getfield Field lG field1290 F
L3317:  fconst_0
L3318:  fcmpl
L3319:  ifne L3331
L3322:  aload_0
L3323:  getfield Field lG A F
L3326:  fconst_0
L3327:  fcmpl
L3328:  ifeq L3355
L3331:  aload_0
L3332:  getfield Field lG field1290 F
L3335:  fneg
L3336:  aload_0
L3337:  getfield Field lG true F
L3340:  fmul
L3341:  aload_0
L3342:  getfield Field lG A F
L3345:  fneg
L3346:  aload_0
L3347:  getfield Field lG field1293 F
L3350:  fmul
L3351:  fconst_0
L3352:  invokestatic Method org/lwjgl/opengl/GL11 method3807 (FFF)V
L3355:  sipush 770
L3358:  iconst_1
L3359:  dup
L3360:  pop2
L3361:  sipush 771
L3364:  iconst_1
L3365:  dup
L3366:  pop2
L3367:  invokestatic Method org/lwjgl/opengl/GL11 method3771 (II)V
L3370:  return
L3371:  
        .attribute StackMap b'\x00\x4E\x00\x1E\x00\x02\x07\x00\x02\x02\x00\x00\x00\x1F\x00\x00\x00\x01\x07\x00\xC4\x00\x20\x00\x02\x07\x00\x02\x02\x00\x00\x00\x32\x00\x02\x07\x00\x02\x02\x00\x00\x00\x4A\x00\x02\x07\x00\x02\x02\x00\x00\x00\x65\x00\x03\x07\x00\x02\x02\x01\x00\x01\x01\x00\xBF\x00\x05\x07\x00\x02\x02\x01\x02\x02\x00\x00\x00\xCF\x00\x05\x07\x00\x02\x02\x01\x02\x02\x00\x00\x00\xD6\x00\x06\x07\x00\x02\x02\x01\x02\x02\x01\x00\x01\x01\x01\x43\x00\x09\x07\x00\x02\x02\x01\x02\x02\x01\x01\x01\x02\x00\x00\x01\x9C\x00\x09\x07\x00\x02\x02\x01\x02\x02\x01\x01\x01\x02\x00\x00\x02\x27\x00\x09\x07\x00\x02\x02\x01\x02\x02\x01\x01\x01\x02\x00\x00\x02\x5F\x00\x09\x07\x00\x02\x02\x01\x02\x02\x01\x01\x01\x02\x00\x00\x02\xDB\x00\x0D\x07\x00\x02\x02\x01\x02\x02\x01\x01\x01\x02\x02\x02\x02\x02\x00\x00\x04\x07\x00\x00\x00\x01\x07\x00\xC4\x04\x08\x00\x09\x07\x00\x02\x02\x01\x02\x02\x01\x01\x01\x02\x00\x00\x04\x4F\x00\x09\x07\x00\x02\x02\x01\x02\x02\x01\x01\x01\x02\x00\x00\x04\xC1\x00\x09\x07\x00\x02\x02\x01\x02\x02\x01\x01\x01\x02\x00\x01\x01\x04\xFB\x00\x09\x07\x00\x02\x02\x01\x02\x02\x01\x01\x01\x02\x00\x00\x05\x03\x00\x05\x07\x00\x02\x02\x01\x02\x02\x00\x00\x05\x0A\x00\x03\x07\x00\x02\x02\x01\x00\x00\x05\x22\x00\x03\x07\x00\x02\x02\x01\x00\x01\x01\x05\x63\x00\x03\x07\x00\x02\x02\x01\x00\x00\x05\x69\x00\x03\x07\x00\x02\x02\x01\x00\x01\x01\x05\x76\x00\x04\x07\x00\x02\x02\x01\x01\x00\x01\x01\x05\xBD\x00\x05\x07\x00\x02\x02\x01\x01\x01\x00\x00\x05\xF4\x00\x05\x07\x00\x02\x02\x01\x01\x01\x00\x00\x06\x44\x00\x07\x07\x00\x02\x02\x01\x01\x01\x01\x02\x00\x00\x06\x97\x00\x07\x07\x00\x02\x02\x01\x01\x01\x01\x02\x00\x00\x06\xC8\x00\x07\x07\x00\x02\x02\x01\x01\x01\x01\x02\x00\x00\x06\xF9\x00\x07\x07\x00\x02\x02\x01\x01\x01\x01\x02\x00\x00\x07\x2A\x00\x07\x07\x00\x02\x02\x01\x01\x01\x01\x02\x00\x00\x07\x5B\x00\x07\x07\x00\x02\x02\x01\x01\x01\x01\x02\x00\x00\x07\x62\x00\x04\x07\x00\x02\x02\x01\x01\x00\x00\x07\x69\x00\x03\x07\x00\x02\x02\x01\x00\x00\x07\x76\x00\x03\x07\x00\x02\x02\x01\x00\x01\x01\x07\xD4\x00\x05\x07\x00\x02\x02\x01\x02\x02\x00\x00\x07\xE4\x00\x05\x07\x00\x02\x02\x01\x02\x02\x00\x00\x07\xF4\x00\x08\x07\x00\x02\x02\x01\x02\x02\x02\x01\x01\x00\x01\x01\x08\x18\x00\x08\x07\x00\x02\x02\x01\x02\x02\x02\x01\x01\x00\x00\x08\x29\x00\x08\x07\x00\x02\x02\x01\x02\x02\x02\x01\x01\x00\x00\x08\x92\x00\x08\x07\x00\x02\x02\x01\x02\x02\x02\x01\x01\x00\x00\x08\x9A\x00\x08\x07\x00\x02\x02\x01\x02\x02\x02\x01\x01\x00\x00\x08\xAD\x00\x08\x07\x00\x02\x02\x01\x02\x02\x02\x01\x01\x00\x00\x08\xBD\x00\x08\x07\x00\x02\x02\x01\x02\x02\x02\x01\x01\x00\x01\x01\x08\xE1\x00\x08\x07\x00\x02\x02\x01\x02\x02\x02\x01\x01\x00\x00\x08\xF3\x00\x08\x07\x00\x02\x02\x01\x02\x02\x02\x01\x01\x00\x00\x09\x5D\x00\x08\x07\x00\x02\x02\x01\x02\x02\x02\x01\x01\x00\x00\x09\x65\x00\x08\x07\x00\x02\x02\x01\x02\x02\x02\x01\x01\x00\x00\x09\x73\x00\x05\x07\x00\x02\x02\x01\x02\x02\x00\x00\x09\x7A\x00\x03\x07\x00\x02\x02\x01\x00\x00\x09\x80\x00\x03\x07\x00\x02\x02\x01\x00\x01\x01\x09\x96\x00\x06\x07\x00\x02\x02\x01\x02\x01\x01\x00\x01\x01\x09\xF6\x00\x08\x07\x00\x02\x02\x01\x02\x01\x01\x02\x02\x00\x00\x0A\x06\x00\x08\x07\x00\x02\x02\x01\x02\x01\x01\x02\x02\x00\x00\x0A\x22\x00\x08\x07\x00\x02\x02\x01\x02\x01\x01\x02\x02\x00\x00\x0A\x33\x00\x08\x07\x00\x02\x02\x01\x02\x01\x01\x02\x02\x00\x00\x0A\x9A\x00\x08\x07\x00\x02\x02\x01\x02\x01\x01\x02\x02\x00\x00\x0A\xA2\x00\x06\x07\x00\x02\x02\x01\x02\x01\x01\x00\x00\x0A\xB5\x00\x06\x07\x00\x02\x02\x01\x02\x01\x01\x00\x00\x0A\xC4\x00\x06\x07\x00\x02\x02\x01\x02\x01\x01\x00\x01\x01\x0B\x24\x00\x08\x07\x00\x02\x02\x01\x02\x01\x01\x02\x02\x00\x00\x0B\x34\x00\x08\x07\x00\x02\x02\x01\x02\x01\x01\x02\x02\x00\x00\x0B\x50\x00\x08\x07\x00\x02\x02\x01\x02\x01\x01\x02\x02\x00\x00\x0B\x66\x00\x08\x07\x00\x02\x02\x01\x02\x01\x01\x02\x02\x00\x00\x0B\xD2\x00\x08\x07\x00\x02\x02\x01\x02\x01\x01\x02\x02\x00\x00\x0B\xDA\x00\x06\x07\x00\x02\x02\x01\x02\x01\x01\x00\x00\x0B\xF2\x00\x06\x07\x00\x02\x02\x01\x02\x01\x01\x00\x00\x0B\xF9\x00\x03\x07\x00\x02\x02\x01\x00\x00\x0C\x02\x00\x03\x07\x00\x02\x02\x01\x00\x01\x01\x0C\x1C\x00\x03\x07\x00\x02\x02\x01\x00\x00\x0C\x29\x00\x04\x07\x00\x02\x02\x01\x02\x00\x01\x07\x00\x02\x0C\xA1\x00\x06\x07\x00\x02\x02\x01\x02\x02\x02\x00\x00\x0C\xB1\x00\x06\x07\x00\x02\x02\x01\x02\x02\x02\x00\x00\x0C\xEA\x00\x04\x07\x00\x02\x02\x01\x02\x00\x00\x0C\xF1\x00\x03\x07\x00\x02\x02\x01\x00\x00\x0D\x03\x00\x03\x07\x00\x02\x02\x01\x00\x00\x0D\x1B\x00\x03\x07\x00\x02\x02\x01\x00\x00'
    .end code
.end method

.method public method125 : (I)V
    .code stack 4 locals 2
L0:     iconst_1
L1:     aload_0
L2:     dup_x1
L3:     iload_1
L4:     putfield Field lG field1305 I
L7:     iconst_1
L8:     dup
L9:     pop2
L10:    putfield Field lG C Z
L13:    return
L14:    
    .end code
.end method

.method public method247 : ()I
    .code stack 1 locals 1
L0:     aload_0
L1:     getfield Field lG while I
L4:     ireturn
L5:     
    .end code
.end method

.method public method95 : (Z)V
    .code stack 4 locals 2
L0:     iconst_1
L1:     aload_0
L2:     dup_x1
L3:     iload_1
L4:     putfield Field lG field1285 Z
L7:     iconst_1
L8:     dup
L9:     pop2
L10:    putfield Field lG C Z
L13:    return
L14:    
    .end code
.end method

.method public method118 : ([[I)V
    .code stack 6 locals 3
L0:     iconst_0
L1:     iconst_1
L2:     dup
L3:     pop2
L4:     dup
L5:     istore_2
L6:     aload_0
L7:     getfield Field lG field1284 I
L10:    if_icmpge L34
L13:    aload_0
L14:    getfield Field lG field1309 [[I
L17:    iload_2
L18:    iinc 2 1
L21:    aaload
L22:    iconst_0
L23:    iconst_1
L24:    dup
L25:    pop2
L26:    invokestatic Method java/util/Arrays fill ([II)V
L29:    iload_2
L30:    goto L6
L33:    athrow
L34:    iconst_0
L35:    iconst_1
L36:    dup
L37:    pop2
L38:    dup
L39:    istore_2
L40:    aload_1
L41:    arraylength
L42:    if_icmpge L77
L45:    aload_1
L46:    iload_2
L47:    aaload
L48:    iconst_1
L49:    dup
L50:    pop2
L51:    aload_0
L52:    getfield Field lG field1309 [[I
L55:    iload_2
L56:    aaload
L57:    iconst_0
L58:    dup_x1
L59:    iconst_1
L60:    dup
L61:    pop2
L62:    aload_1
L63:    iload_2
L64:    iinc 2 1
L67:    aaload
L68:    arraylength
L69:    invokestatic Method java/lang/System arraycopy (Ljava/lang/Object;ILjava/lang/Object;II)V
L72:    iload_2
L73:    goto L40
L76:    athrow
L77:    aload_0
L78:    aload_0
L79:    iconst_1
L80:    dup
L81:    dup_x2
L82:    dup
L83:    pop2
L84:    putfield Field lG field1298 Z
L87:    iconst_1
L88:    dup
L89:    pop2
L90:    putfield Field lG C Z
L93:    return
L94:    
        .attribute StackMap b'\x00\x06\x00\x06\x00\x03\x07\x00\x02\x07\x00\x87\x01\x00\x01\x01\x00\x21\x00\x00\x00\x01\x07\x00\xC4\x00\x22\x00\x03\x07\x00\x02\x07\x00\x87\x01\x00\x00\x00\x28\x00\x03\x07\x00\x02\x07\x00\x87\x01\x00\x01\x01\x00\x4C\x00\x00\x00\x01\x07\x00\xC4\x00\x4D\x00\x03\x07\x00\x02\x07\x00\x87\x01\x00\x00'
    .end code
.end method

.method public method606 : (FFF)V
    .code stack 6 locals 4
L0:     fload_3
L1:     aload_0
L2:     dup_x1
L3:     fload_2
L4:     aload_0
L5:     fload_1
L6:     putfield Field lG k F
L9:     putfield Field lG field1299 F
L12:    putfield Field lG this F
L15:    return
L16:    
    .end code
.end method

.method public method64 : (I)V
    .code stack 8 locals 6
L0:     aload_0
L1:     getfield Field lG true F
L4:     f2d
L5:     ldc2_w 5e-2
L8:     dcmpg
L9:     ifge L14
L12:    return
L13:    athrow
L14:    iconst_0
L15:    iconst_1
L16:    dup
L17:    pop2
L18:    istore_2
L19:    iconst_0
L20:    iconst_1
L21:    dup
L22:    pop2
L23:    dup
L24:    istore_3
L25:    iconst_4
L26:    iconst_1
L27:    dup
L28:    pop2
L29:    if_icmpge L83
L32:    iconst_0
L33:    iconst_1
L34:    dup
L35:    pop2
L36:    dup
L37:    istore 4
L39:    iconst_4
L40:    iconst_1
L41:    dup
L42:    pop2
L43:    if_icmpge L76
L46:    aload_0
L47:    getfield Field lG I [[I
L50:    iload 4
L52:    aaload
L53:    iload_3
L54:    iaload
L55:    ifeq L67
L58:    iload 4
L60:    iload_2
L61:    if_icmple L67
L64:    iload 4
L66:    istore_2
L67:    iinc 4 1
L70:    iload 4
L72:    goto L39
L75:    athrow
L76:    iinc 3 1
L79:    iload_3
L80:    goto L25
L83:    iconst_0
L84:    iconst_1
L85:    dup
L86:    pop2
L87:    dup
L88:    istore_3
L89:    iconst_4
L90:    iconst_1
L91:    dup
L92:    pop2
L93:    if_icmpge L351
L96:    iconst_0
L97:    iconst_1
L98:    dup
L99:    pop2
L100:   dup
L101:   istore 4
L103:   iconst_4
L104:   iconst_1
L105:   dup
L106:   pop2
L107:   if_icmpge L344
L110:   aload_0
L111:   getfield Field lG I [[I
L114:   iload 4
L116:   aaload
L117:   iload_3
L118:   iaload
L119:   ifeq L336
L122:   iload 4
L124:   aload_0
L125:   getfield Field lG field1296 I
L128:   iadd
L129:   iflt L336
L132:   iload 4
L134:   aload_0
L135:   getfield Field lG field1296 I
L138:   iadd
L139:   bipush 10
L141:   iconst_1
L142:   dup
L143:   pop2
L144:   if_icmpge L336
L147:   aload_0
L148:   getfield Field lG field1291 I
L151:   dup
L152:   istore 5
L154:   iload_1
L155:   if_icmpge L336
L158:   iload_3
L159:   iload 5
L161:   iadd
L162:   ifle L328
L165:   iload_3
L166:   iload 5
L168:   iadd
L169:   aload_0
L170:   getfield Field lG field1312 I
L173:   if_icmpge L328
L176:   iload_3
L177:   iload 5
L179:   iadd
L180:   iload_1
L181:   if_icmplt L201
L184:   aload_0
L185:   getfield Field lG I [[I
L188:   iload 4
L190:   aaload
L191:   iload_3
L192:   iload 5
L194:   iadd
L195:   iload_1
L196:   isub
L197:   iaload
L198:   ifne L328
L201:   aload_0
L202:   dup
L203:   getfield Field lG field1287 [[F
L206:   iload 4
L208:   aload_0
L209:   getfield Field lG field1296 I
L212:   iadd
L213:   aaload
L214:   iload_3
L215:   iload 5
L217:   iadd
L218:   ldc_w 5e-1f
L221:   dup
L222:   iload 5
L224:   i2f
L225:   fmul
L226:   aload_0
L227:   getfield Field lG while I
L230:   i2f
L231:   fdiv
L232:   fadd
L233:   fastore
L234:   getfield Field lG field1304 [[I
L237:   iload 4
L239:   aload_0
L240:   getfield Field lG field1296 I
L243:   iadd
L244:   aaload
L245:   iload_3
L246:   iload 5
L248:   iadd
L249:   aload_0
L250:   getfield Field lG I [[I
L253:   iload 4
L255:   aaload
L256:   iload_3
L257:   iaload
L258:   bipush 31
L260:   iconst_1
L261:   dup
L262:   pop2
L263:   iand
L264:   iastore
L265:   iload 4
L267:   ifne L296
L270:   aload_0
L271:   getfield Field lG field1304 [[I
L274:   iload 4
L276:   aload_0
L277:   getfield Field lG field1296 I
L280:   iadd
L281:   aaload
L282:   iload_3
L283:   iload 5
L285:   iadd
L286:   dup2
L287:   iaload
L288:   sipush 2048
L291:   iconst_1
L292:   dup
L293:   pop2
L294:   ior
L295:   iastore
L296:   iload 4
L298:   iload_2
L299:   if_icmpne L328
L302:   aload_0
L303:   getfield Field lG field1304 [[I
L306:   iload 4
L308:   aload_0
L309:   getfield Field lG field1296 I
L312:   iadd
L313:   aaload
L314:   iload_3
L315:   iload 5
L317:   iadd
L318:   dup2
L319:   iaload
L320:   sipush 512
L323:   iconst_1
L324:   dup
L325:   pop2
L326:   ior
L327:   iastore
L328:   iinc 5 1
L331:   iload 5
L333:   goto L154
L336:   iinc 4 1
L339:   iload 4
L341:   goto L103
L344:   iinc 3 1
L347:   iload_3
L348:   goto L89
L351:   aload_0
L352:   iconst_1
L353:   dup
L354:   aload_0
L355:   dup_x1
L356:   iconst_0
L357:   iconst_1
L358:   dup
L359:   pop2
L360:   putfield Field lG field1314 Z
L363:   iconst_1
L364:   dup
L365:   pop2
L366:   putfield Field lG C Z
L369:   iconst_1
L370:   dup
L371:   pop2
L372:   putfield Field lG B Z
L375:   return
L376:   
        .attribute StackMap b'\x00\x11\x00\x0D\x00\x00\x00\x01\x07\x00\xC4\x00\x0E\x00\x02\x07\x00\x02\x01\x00\x00\x00\x19\x00\x04\x07\x00\x02\x01\x01\x01\x00\x01\x01\x00\x27\x00\x05\x07\x00\x02\x01\x01\x01\x01\x00\x01\x01\x00\x43\x00\x05\x07\x00\x02\x01\x01\x01\x01\x00\x00\x00\x4B\x00\x00\x00\x01\x07\x00\xC4\x00\x4C\x00\x05\x07\x00\x02\x01\x01\x01\x01\x00\x00\x00\x53\x00\x04\x07\x00\x02\x01\x01\x01\x00\x00\x00\x59\x00\x04\x07\x00\x02\x01\x01\x01\x00\x01\x01\x00\x67\x00\x05\x07\x00\x02\x01\x01\x01\x01\x00\x01\x01\x00\x9A\x00\x06\x07\x00\x02\x01\x01\x01\x01\x01\x00\x01\x01\x00\xC9\x00\x06\x07\x00\x02\x01\x01\x01\x01\x01\x00\x00\x01\x28\x00\x06\x07\x00\x02\x01\x01\x01\x01\x01\x00\x00\x01\x48\x00\x06\x07\x00\x02\x01\x01\x01\x01\x01\x00\x00\x01\x50\x00\x05\x07\x00\x02\x01\x01\x01\x01\x00\x00\x01\x58\x00\x05\x07\x00\x02\x01\x01\x01\x01\x00\x00\x01\x5F\x00\x04\x07\x00\x02\x01\x01\x01\x00\x00'
    .end code
.end method

.method public method104 : (F)V
    .code stack 4 locals 2
L0:     aload_0
L1:     fload_1
L2:     fconst_0
L3:     fconst_1
L4:     invokestatic Method OC method1001 (FFF)F
L7:     putfield Field lG field1306 F
L10:    return
L11:    
    .end code
.end method

.method public method14 : (I)V
    .code stack 6 locals 4
L0:     aload_0
L1:     getfield Field lG field1323 I
L4:     dup
L5:     istore_2
L6:     iload_1
L7:     if_icmpge L76
L10:    iconst_0
L11:    iconst_1
L12:    dup
L13:    pop2
L14:    dup
L15:    istore_3
L16:    bipush 10
L18:    iconst_1
L19:    dup
L20:    pop2
L21:    if_icmpge L68
L24:    aload_0
L25:    getfield Field lG field1309 [[I
L28:    iload_3
L29:    aaload
L30:    iload_2
L31:    iaload
L32:    bipush 31
L34:    iconst_1
L35:    dup
L36:    pop2
L37:    iand
L38:    bipush 13
L40:    iconst_1
L41:    dup
L42:    pop2
L43:    if_icmpne L60
L46:    aload_0
L47:    iload_3
L48:    iload_2
L49:    bipush 15
L51:    iconst_1
L52:    dup
L53:    pop2
L54:    ldc_w -1e0f
L57:    invokevirtual Method lG method650 (IIIF)V
L60:    iinc 3 1
L63:    iload_3
L64:    goto L16
L67:    athrow
L68:    iinc 2 1
L71:    iload_2
L72:    goto L6
L75:    athrow
L76:    aload_0
L77:    iconst_1
L78:    dup
L79:    aload_0
L80:    dup_x1
L81:    iload_1
L82:    putfield Field lG field1323 I
L85:    iconst_1
L86:    dup
L87:    pop2
L88:    putfield Field lG field1298 Z
L91:    iconst_1
L92:    dup
L93:    pop2
L94:    putfield Field lG C Z
L97:    return
L98:    
        .attribute StackMap b'\x00\x07\x00\x06\x00\x03\x07\x00\x02\x01\x01\x00\x01\x01\x00\x10\x00\x04\x07\x00\x02\x01\x01\x01\x00\x01\x01\x00\x3C\x00\x04\x07\x00\x02\x01\x01\x01\x00\x00\x00\x43\x00\x00\x00\x01\x07\x00\xC4\x00\x44\x00\x04\x07\x00\x02\x01\x01\x01\x00\x00\x00\x4B\x00\x00\x00\x01\x07\x00\xC4\x00\x4C\x00\x03\x07\x00\x02\x01\x01\x00\x00'
    .end code
.end method
.end class
