.version 49 0
.class public final super lG
.super gB
.field public static final d I = 32
.field private e [[F
.field private g F
.field private k F
.field private a I
.field public static final F I = 1
.field private A F
.field private E [[F
.field private C Z
.field public static final K I = 512
.field private G Z
.field private B Z
.field public static final c I = 1024
.field private "synchronized" I
.field private i [[I
.field private static final m [F
.field private h I
.field private static final J [F
.field public static final l I = 256
.field private D [[I
.field private f F
.field public static final j I = 4
.field private I [[I
.field private b [[I
.field private implements Z
.field public static final return I = 11
.field private default F
.field public static final switch I = 9
.field private "interface" [[F
.field private "private" [[F
.field private assert [[F
.field private boolean F
.field private "strictfp" I
.field private "abstract" [[I
.field private "public" F
.field public static final "volatile" I = 3840
.field private double I
.field public static final throw I = 12
.field public static final package I = 15
.field private finally I
.field private static final "transient" [F
.field private while I
.field private instanceof Z
.field private "protected" F
.field private import F
.field public static final "native" I = 9
.field public static final throws I = 3
.field private "static" F
.field private continue [[I
.field private extends I
.field private float F
.field public static final "final" I = 2
.field public static final catch I = 13
.field public static final false I = 31
.field private class [[I
.field public static final if I = 10
.field private true F
.field public static final for I = 8
.field private case I
.field public static final byte I = 14
.field private "super" Z
.field private short F
.field private goto F
.field public static final break I = 7
.field private long F
.field public static final void I = 0
.field private try [F
.field public static final const I = 5
.field private static final new [F
.field public static final null I = 6
.field private this F
.field public static final else I = 16
.field public static final "enum" I = 2048
.field private do I

.method public <init> : (IIIZ)V
    .code stack 22 locals 5
L0:     aload_0
L1:     dup
L2:     dup2
L3:     dup2
L4:     fconst_0
L5:     aload_0
L6:     dup_x2
L7:     fconst_0
L8:     iload_2
L9:     aload_0
L10:    dup_x1
L11:    dup_x1
L12:    iload_3
L13:    iload_1
L14:    aload_0
L15:    dup_x1
L16:    iload 4
L18:    fconst_0
L19:    aload_0
L20:    dup_x1
L21:    invokespecial Method gB <init> ()V
L24:    putfield Field lG g F
L27:    putfield Field lG G Z
L30:    putfield Field lG "synchronized" I
L33:    putfield Field lG case I
L36:    putfield Field lG while I
L39:    getfield Field lG case I
L42:    aload_0
L43:    dup_x1
L44:    getfield Field lG while I
L47:    isub
L48:    i2f
L49:    putfield Field lG goto F
L52:    putfield Field lG boolean F
L55:    putfield Field lG A F
L58:    getfield Field lG "synchronized" I
L61:    i2f
L62:    ldc 4e-1f
L64:    fmul
L65:    putfield Field lG case F
L68:    getfield Field lG while I
L71:    i2f
L72:    ldc 4e-1f
L74:    fmul
L75:    putfield Field lG char F
L78:    getfield Field lG "synchronized" I
L81:    aload_0
L82:    getfield Field lG case I
L85:    multianewarray [[I 2
L89:    putfield Field lG i [[I
L92:    aload_0
L93:    getfield Field lG "synchronized" I
L96:    aload_0
L97:    dup_x1
L98:    getfield Field lG case I
L101:   multianewarray [[I 2
L105:   putfield Field lG b [[I
L108:   aload_0
L109:   getfield Field lG "synchronized" I
L112:   aload_0
L113:   dup_x1
L114:   getfield Field lG case I
L117:   multianewarray [[I 2
L121:   putfield Field lG "abstract" [[I
L124:   aload_0
L125:   getfield Field lG "synchronized" I
L128:   aload_0
L129:   dup_x1
L130:   getfield Field lG case I
L133:   multianewarray [[I 2
L137:   putfield Field lG D [[I
L140:   aload_0
L141:   getfield Field lG "synchronized" I
L144:   aload_0
L145:   dup_x1
L146:   getfield Field lG case I
L149:   multianewarray [[F 2
L153:   putfield Field lG E [[F
L156:   aload_0
L157:   getfield Field lG "synchronized" I
L160:   aload_0
L161:   dup_x1
L162:   getfield Field lG case I
L165:   multianewarray [[F 2
L169:   putfield Field lG "private" [[F
L172:   aload_0
L173:   getfield Field lG "synchronized" I
L176:   aload_0
L177:   dup_x1
L178:   getfield Field lG case I
L181:   multianewarray [[F 2
L185:   putfield Field lG assert [[F
L188:   aload_0
L189:   getfield Field lG "synchronized" I
L192:   aload_0
L193:   dup_x1
L194:   getfield Field lG case I
L197:   multianewarray [[F 2
L201:   putfield Field lG e [[F
L204:   aload_0
L205:   getfield Field lG "synchronized" I
L208:   aload_0
L209:   dup_x1
L210:   getfield Field lG case I
L213:   multianewarray [[I 2
L217:   putfield Field lG class [[I
L220:   aload_0
L221:   getfield Field lG "synchronized" I
L224:   aload_0
L225:   dup_x1
L226:   getfield Field lG case I
L229:   multianewarray [[F 2
L233:   putfield Field lG "interface" [[F
L236:   aload_0
L237:   getfield Field lG "synchronized" I
L240:   aload_0
L241:   dup_x1
L242:   getfield Field lG case I
L245:   multianewarray [[I 2
L249:   putfield Field lG continue [[I
L252:   aload_0
L253:   iconst_4
L254:   iconst_1
L255:   dup
L256:   pop2
L257:   iconst_4
L258:   iconst_1
L259:   dup
L260:   pop2
L261:   multianewarray [[I 2
L265:   putfield Field lG I [[I
L268:   iconst_1
L269:   aload_0
L270:   dup_x1
L271:   iconst_1
L272:   fconst_0
L273:   aload_0
L274:   dup_x1
L275:   iconst_0
L276:   fconst_0
L277:   aload_0
L278:   dup_x1
L279:   fconst_0
L280:   dup
L281:   aload_0
L282:   dup_x1
L283:   fconst_1
L284:   aload_0
L285:   dup
L286:   getfield Field lG case I
L289:   newarray float
L291:   iconst_1
L292:   dup
L293:   pop2
L294:   putfield Field lG try [F
L297:   putfield Field lG f F
L300:   putfield Field lG float F
L303:   putfield Field lG import F
L306:   putfield Field lG default F
L309:   iconst_1
L310:   dup
L311:   pop2
L312:   putfield Field lG extends I
L315:   putfield Field lG "static" F
L318:   iconst_1
L319:   dup
L320:   pop2
L321:   invokevirtual Method lG else (Z)V
L324:   iconst_1
L325:   dup
L326:   pop2
L327:   invokestatic Method org/lwjgl/opengl/GL11 "super" (I)I
L330:   putfield Field lG double I
L333:   return
L334:   
    .end code
.end method

.method public case : ()V
    .code stack 4 locals 1
L0:     aload_0
L1:     dup
L2:     invokespecial Method gB case ()V
L5:     getfield Field lG double I
L8:     iconst_1
L9:     dup
L10:    dup
L11:    pop2
L12:    invokestatic Method org/lwjgl/opengl/GL11 this (II)V
L15:    return
L16:    
    .end code
.end method

.method public for : (I)V
    .code stack 8 locals 4
L0:     iload_1
L1:     dup
L2:     istore_2
L3:     ifle L95
L6:     iconst_0
L7:     aload_0
L8:     dup
L9:     getfield Field lG try [F
L12:    swap
L13:    getfield Field lG try [F
L16:    iload_2
L17:    dup_x1
L18:    iconst_1
L19:    dup
L20:    dup
L21:    pop2
L22:    isub
L23:    faload
L24:    fastore
L25:    iconst_1
L26:    dup
L27:    pop2
L28:    dup
L29:    istore_3
L30:    aload_0
L31:    getfield Field lG "synchronized" I
L34:    if_icmpge L87
L37:    aload_0
L38:    getfield Field lG "interface" [[F
L41:    iload_3
L42:    aaload
L43:    iload_2
L44:    aload_0
L45:    dup_x2
L46:    getfield Field lG "interface" [[F
L49:    iload_3
L50:    aaload
L51:    iload_2
L52:    iconst_1
L53:    dup
L54:    dup
L55:    pop2
L56:    isub
L57:    faload
L58:    fastore
L59:    getfield Field lG continue [[I
L62:    iload_3
L63:    aaload
L64:    aload_0
L65:    getfield Field lG continue [[I
L68:    iload_3
L69:    aaload
L70:    iload_2
L71:    dup_x1
L72:    iconst_1
L73:    dup
L74:    dup
L75:    pop2
L76:    isub
L77:    iaload
L78:    iinc 3 1
L81:    iastore
L82:    iload_3
L83:    goto L30
L86:    athrow
L87:    iinc 2 -1
L90:    iload_2
L91:    goto L3
L94:    athrow
L95:    iconst_0
L96:    iconst_1
L97:    dup
L98:    pop2
L99:    dup
L100:   istore_2
L101:   iload_1
L102:   if_icmpgt L122
L105:   aload_0
L106:   getfield Field lG try [F
L109:   iload_2
L110:   dup2
L111:   faload
L112:   fconst_1
L113:   fadd
L114:   iinc 2 1
L117:   fastore
L118:   iload_2
L119:   goto L101
L122:   aload_0
L123:   iconst_1
L124:   dup
L125:   aload_0
L126:   dup_x1
L127:   iconst_0
L128:   iconst_1
L129:   dup
L130:   pop2
L131:   putfield Field lG "super" Z
L134:   iconst_1
L135:   dup
L136:   pop2
L137:   putfield Field lG C Z
L140:   iconst_1
L141:   dup
L142:   pop2
L143:   putfield Field lG B Z
L146:   return
L147:   
        .attribute StackMap b'\x00\x08\x00\x03\x00\x03\x07\x00\x02\x01\x01\x00\x01\x01\x00\x1E\x00\x04\x07\x00\x02\x01\x01\x01\x00\x01\x01\x00\x56\x00\x00\x00\x01\x07\x00\xBF\x00\x57\x00\x04\x07\x00\x02\x01\x01\x01\x00\x00\x00\x5E\x00\x00\x00\x01\x07\x00\xBF\x00\x5F\x00\x03\x07\x00\x02\x01\x01\x00\x00\x00\x65\x00\x03\x07\x00\x02\x01\x01\x00\x01\x01\x00\x7A\x00\x03\x07\x00\x02\x01\x01\x00\x00'
    .end code
.end method

.method public catch : (I)V
    .code stack 9 locals 4
L0:     iconst_0
L1:     iconst_1
L2:     dup
L3:     pop2
L4:     dup
L5:     istore_2
L6:     aload_0
L7:     getfield Field lG case I
L10:    iload_1
L11:    isub
L12:    if_icmpge L95
L15:    iconst_0
L16:    aload_0
L17:    dup
L18:    getfield Field lG try [F
L21:    swap
L22:    getfield Field lG try [F
L25:    iload_2
L26:    dup_x1
L27:    iload_1
L28:    iadd
L29:    faload
L30:    fastore
L31:    iconst_1
L32:    dup
L33:    pop2
L34:    dup
L35:    istore_3
L36:    aload_0
L37:    getfield Field lG "synchronized" I
L40:    if_icmpge L87
L43:    aload_0
L44:    getfield Field lG "interface" [[F
L47:    iload_3
L48:    aaload
L49:    iload_2
L50:    aload_0
L51:    dup_x2
L52:    getfield Field lG "interface" [[F
L55:    iload_3
L56:    aaload
L57:    iload_2
L58:    iload_1
L59:    iadd
L60:    faload
L61:    fastore
L62:    getfield Field lG continue [[I
L65:    iload_3
L66:    aaload
L67:    aload_0
L68:    getfield Field lG continue [[I
L71:    iload_3
L72:    aaload
L73:    iload_2
L74:    dup_x1
L75:    iload_1
L76:    iadd
L77:    iaload
L78:    iinc 3 1
L81:    iastore
L82:    iload_3
L83:    goto L36
L86:    athrow
L87:    iinc 2 1
L90:    iload_2
L91:    goto L6
L94:    athrow
L95:    aload_0
L96:    getfield Field lG case I
L99:    iload_1
L100:   isub
L101:   dup
L102:   istore_2
L103:   aload_0
L104:   getfield Field lG case I
L107:   if_icmpge L153
L110:   iconst_0
L111:   aload_0
L112:   getfield Field lG try [F
L115:   iload_2
L116:   fconst_0
L117:   fastore
L118:   iconst_1
L119:   dup
L120:   pop2
L121:   dup
L122:   istore_3
L123:   aload_0
L124:   getfield Field lG "synchronized" I
L127:   if_icmpge L146
L130:   aload_0
L131:   getfield Field lG "interface" [[F
L134:   iload_3
L135:   aaload
L136:   iload_2
L137:   fconst_0
L138:   iinc 3 1
L141:   fastore
L142:   iload_3
L143:   goto L123
L146:   iinc 2 1
L149:   iload_2
L150:   goto L103
L153:   aload_0
L154:   iconst_1
L155:   dup
L156:   aload_0
L157:   dup_x1
L158:   iconst_0
L159:   aload_0
L160:   dup
L161:   getfield Field lG long F
L164:   iload_1
L165:   i2f
L166:   fadd
L167:   putfield Field lG long F
L170:   iconst_1
L171:   dup
L172:   pop2
L173:   putfield Field lG "super" Z
L176:   iconst_1
L177:   dup
L178:   pop2
L179:   putfield Field lG C Z
L182:   iconst_1
L183:   dup
L184:   pop2
L185:   putfield Field lG B Z
L188:   return
L189:   
        .attribute StackMap b'\x00\x0A\x00\x06\x00\x03\x07\x00\x02\x01\x01\x00\x01\x01\x00\x24\x00\x04\x07\x00\x02\x01\x01\x01\x00\x01\x01\x00\x56\x00\x00\x00\x01\x07\x00\xBF\x00\x57\x00\x04\x07\x00\x02\x01\x01\x01\x00\x00\x00\x5E\x00\x00\x00\x01\x07\x00\xBF\x00\x5F\x00\x03\x07\x00\x02\x01\x01\x00\x00\x00\x67\x00\x03\x07\x00\x02\x01\x01\x00\x01\x01\x00\x7B\x00\x04\x07\x00\x02\x01\x01\x01\x00\x01\x01\x00\x92\x00\x04\x07\x00\x02\x01\x01\x01\x00\x00\x00\x99\x00\x03\x07\x00\x02\x01\x01\x00\x00'
    .end code
.end method

.method public const : ()I
    .code stack 1 locals 1
L0:     aload_0
L1:     getfield Field lG "synchronized" I
L4:     ireturn
L5:     
    .end code
.end method

.method public int : ()V
    .code stack 9 locals 3
L0:     aload_0
L1:     dup
L2:     dup2
L3:     getfield Field lG float F
L6:     aload_0
L7:     dup_x2
L8:     getfield Field lG default F
L11:    getstatic Field ib do F
L14:    fconst_2
L15:    fmul
L16:    fsub
L17:    aload_0
L18:    getfield Field lG default F
L21:    getstatic Field ib do F
L24:    fconst_2
L25:    fmul
L26:    fadd
L27:    invokestatic Method OC else (FFF)F
L30:    putfield Field lG default F
L33:    getfield Field lG extends I
L36:    i2f
L37:    aload_0
L38:    getfield Field lG "static" F
L41:    getstatic Field ib do F
L44:    ldc 9.6e1f
L46:    fmul
L47:    fsub
L48:    aload_0
L49:    getfield Field lG "static" F
L52:    getstatic Field ib do F
L55:    ldc 1.2e1f
L57:    fmul
L58:    fadd
L59:    invokestatic Method OC else (FFF)F
L62:    putfield Field lG "static" F
L65:    getfield Field lG import F
L68:    aload_0
L69:    getfield Field lG f F
L72:    fcmpl
L73:    ifeq L115
L76:    iconst_1
L77:    aload_0
L78:    dup
L79:    dup_x2
L80:    getfield Field lG f F
L83:    aload_0
L84:    getfield Field lG import F
L87:    getstatic Field ib do F
L90:    fconst_2
L91:    fmul
L92:    fsub
L93:    aload_0
L94:    getfield Field lG import F
L97:    getstatic Field ib do F
L100:   fconst_2
L101:   fmul
L102:   fadd
L103:   invokestatic Method OC else (FFF)F
L106:   putfield Field lG import F
L109:   iconst_1
L110:   dup
L111:   pop2
L112:   putfield Field lG C Z
L115:   aload_0
L116:   dup
L117:   dup_x1
L118:   iconst_1
L119:   dup
L120:   dup
L121:   pop2
L122:   putfield Field lG "super" Z
L125:   dup
L126:   getfield Field lG long F
L129:   aload_0
L130:   getfield Field lG g F
L133:   getstatic Field ib do F
L136:   fmul
L137:   fsub
L138:   putfield Field lG long F
L141:   getfield Field lG long F
L144:   fconst_0
L145:   fcmpg
L146:   ifgt L159
L149:   aload_0
L150:   dup
L151:   fconst_0
L152:   putfield Field lG long F
L155:   goto L176
L158:   athrow
L159:   aload_0
L160:   iconst_1
L161:   aload_0
L162:   dup_x1
L163:   iconst_0
L164:   iconst_1
L165:   dup
L166:   pop2
L167:   putfield Field lG "super" Z
L170:   iconst_1
L171:   dup
L172:   pop2
L173:   putfield Field lG C Z
L176:   getfield Field lG B Z
L179:   ifne L184
L182:   return
L183:   athrow
L184:   aload_0
L185:   iconst_0
L186:   iconst_1
L187:   dup
L188:   pop2
L189:   putfield Field lG B Z
L192:   iconst_0
L193:   iconst_1
L194:   dup
L195:   pop2
L196:   dup
L197:   istore_1
L198:   aload_0
L199:   getfield Field lG case I
L202:   if_icmpge L471
L205:   aload_0
L206:   dup
L207:   getfield Field lG try [F
L210:   iload_1
L211:   dup2
L212:   faload
L213:   getstatic Field ib do F
L216:   ldc 1.6e1f
L218:   aload_0
L219:   getfield Field lG try [F
L222:   iload_1
L223:   faload
L224:   ldc 4e0f
L226:   fmul
L227:   invokestatic Method java/lang/Math max (FF)F
L230:   fmul
L231:   fsub
L232:   fastore
L233:   getfield Field lG try [F
L236:   iload_1
L237:   faload
L238:   fconst_0
L239:   fcmpg
L240:   aload_0
L241:   swap
L242:   ifge L254
L245:   getfield Field lG try [F
L248:   iload_1
L249:   fconst_0
L250:   fastore
L251:   goto L277
L254:   iconst_0
L255:   iconst_1
L256:   dup
L257:   pop2
L258:   putfield Field lG "super" Z
L261:   iconst_1
L262:   aload_0
L263:   dup_x1
L264:   iconst_1
L265:   dup
L266:   dup
L267:   pop2
L268:   putfield Field lG C Z
L271:   iconst_1
L272:   dup
L273:   pop2
L274:   putfield Field lG B Z
L277:   iconst_0
L278:   iconst_1
L279:   dup
L280:   pop2
L281:   dup
L282:   istore_2
L283:   aload_0
L284:   getfield Field lG "synchronized" I
L287:   if_icmpge L464
L290:   aload_0
L291:   getfield Field lG continue [[I
L294:   iload_2
L295:   aaload
L296:   iload_1
L297:   iaload
L298:   ifeq L457
L301:   iconst_1
L302:   aload_0
L303:   dup_x1
L304:   dup_x2
L305:   aload_0
L306:   iconst_0
L307:   iconst_1
L308:   dup_x2
L309:   dup
L310:   pop2
L311:   putfield Field lG "super" Z
L314:   iconst_1
L315:   dup
L316:   pop2
L317:   putfield Field lG C Z
L320:   iconst_1
L321:   dup
L322:   pop2
L323:   putfield Field lG instanceof Z
L326:   getfield Field lG "interface" [[F
L329:   iload_2
L330:   aaload
L331:   iload_1
L332:   faload
L333:   fconst_0
L334:   fcmpl
L335:   ifle L394
L338:   aload_0
L339:   dup
L340:   getfield Field lG "interface" [[F
L343:   iload_2
L344:   aaload
L345:   iload_1
L346:   dup2
L347:   faload
L348:   getstatic Field ib do F
L351:   ldc 1.2e1f
L353:   fmul
L354:   fsub
L355:   fastore
L356:   getfield Field lG "interface" [[F
L359:   iload_2
L360:   aaload
L361:   iload_1
L362:   faload
L363:   fconst_0
L364:   fcmpg
L365:   aload_0
L366:   swap
L367:   ifge L384
L370:   getfield Field lG continue [[I
L373:   iload_2
L374:   aaload
L375:   iload_1
L376:   iconst_0
L377:   iconst_1
L378:   dup
L379:   pop2
L380:   iastore
L381:   goto L457
L384:   iconst_1
L385:   dup
L386:   dup
L387:   pop2
L388:   putfield Field lG B Z
L391:   goto L457
L394:   aload_0
L395:   getfield Field lG "interface" [[F
L398:   iload_2
L399:   aaload
L400:   iload_1
L401:   faload
L402:   fconst_0
L403:   fcmpg
L404:   ifge L457
L407:   aload_0
L408:   dup
L409:   getfield Field lG "interface" [[F
L412:   iload_2
L413:   aaload
L414:   iload_1
L415:   dup2
L416:   faload
L417:   getstatic Field ib do F
L420:   fadd
L421:   fastore
L422:   getfield Field lG "interface" [[F
L425:   iload_2
L426:   aaload
L427:   iload_1
L428:   faload
L429:   fconst_0
L430:   fcmpl
L431:   aload_0
L432:   swap
L433:   ifle L450
L436:   getfield Field lG continue [[I
L439:   iload_2
L440:   aaload
L441:   iload_1
L442:   iconst_0
L443:   iconst_1
L444:   dup
L445:   pop2
L446:   iastore
L447:   goto L457
L450:   iconst_1
L451:   dup
L452:   dup
L453:   pop2
L454:   putfield Field lG B Z
L457:   iinc 2 1
L460:   iload_2
L461:   goto L283
L464:   iinc 1 1
L467:   iload_1
L468:   goto L198
L471:   return
L472:   
        .attribute StackMap b'\x00\x10\x00\x73\x00\x01\x07\x00\x02\x00\x00\x00\x9E\x00\x00\x00\x01\x07\x00\xBF\x00\x9F\x00\x01\x07\x00\x02\x00\x00\x00\xB0\x00\x01\x07\x00\x02\x00\x01\x07\x00\x02\x00\xB7\x00\x00\x00\x01\x07\x00\xBF\x00\xB8\x00\x01\x07\x00\x02\x00\x00\x00\xC6\x00\x02\x07\x00\x02\x01\x00\x01\x01\x00\xFE\x00\x02\x07\x00\x02\x01\x00\x01\x07\x00\x02\x01\x15\x00\x02\x07\x00\x02\x01\x00\x00\x01\x1B\x00\x03\x07\x00\x02\x01\x01\x00\x01\x01\x01\x80\x00\x03\x07\x00\x02\x01\x01\x00\x01\x07\x00\x02\x01\x8A\x00\x03\x07\x00\x02\x01\x01\x00\x00\x01\xC2\x00\x03\x07\x00\x02\x01\x01\x00\x01\x07\x00\x02\x01\xC9\x00\x03\x07\x00\x02\x01\x01\x00\x00\x01\xD0\x00\x03\x07\x00\x02\x01\x01\x00\x00\x01\xD7\x00\x02\x07\x00\x02\x01\x00\x00'
    .end code
.end method

.method public background : (ZF)V
    .code stack 9 locals 4
L0:     fload_2
L1:     fconst_0
L2:     fcmpl
L3:     ifne L8
L6:     return
L7:     athrow
L8:     aload_0
L9:     getfield Field lG short F
L12:    invokestatic Method java/lang/Math abs (F)F
L15:    f2d
L16:    ldc2_w 1e-4
L19:    dcmpl
L20:    ifle L59
L23:    invokestatic Method org/lwjgl/opengl/GL11 char ()V
L26:    aload_0
L27:    dup
L28:    dup_x1
L29:    getfield Field lG catch F
L32:    fconst_2
L33:    fdiv
L34:    fconst_0
L35:    dup
L36:    invokestatic Method org/lwjgl/opengl/GL11 const (FFF)V
L39:    getfield Field lG short F
L42:    fconst_1
L43:    fconst_0
L44:    dup_x1
L45:    invokestatic Method org/lwjgl/opengl/GL11 for (FFFF)V
L48:    getfield Field lG catch F
L51:    fneg
L52:    fconst_2
L53:    fdiv
L54:    fconst_0
L55:    dup
L56:    invokestatic Method org/lwjgl/opengl/GL11 const (FFF)V
L59:    aload_0
L60:    getfield Field lG G Z
L63:    ifeq L148
L66:    fconst_0
L67:    dup
L68:    dup_x1
L69:    iload_1
L70:    ifeq L80
L73:    ldc 7e-1f
L75:    fload_2
L76:    goto L83
L79:    athrow
L80:    ldc 8.5e-1f
L82:    fload_2
L83:    fmul
L84:    invokestatic Method org/lwjgl/opengl/GL11 else (FFFF)V
L87:    bipush 7
L89:    iconst_1
L90:    dup
L91:    pop2
L92:    invokestatic Method org/lwjgl/opengl/GL11 "strictfp" (I)V
L95:    fconst_0
L96:    aload_0
L97:    getfield Field lG break F
L100:   invokestatic Method org/lwjgl/opengl/GL11 break (FF)V
L103:   fconst_0
L104:   aload_0
L105:   getfield Field lG catch F
L108:   aload_0
L109:   dup_x1
L110:   getfield Field lG break F
L113:   invokestatic Method org/lwjgl/opengl/GL11 break (FF)V
L116:   getfield Field lG catch F
L119:   aload_0
L120:   dup
L121:   getfield Field lG "static" F
L124:   swap
L125:   getfield Field lG "public" F
L128:   fmul
L129:   invokestatic Method org/lwjgl/opengl/GL11 break (FF)V
L132:   aload_0
L133:   dup
L134:   getfield Field lG "static" F
L137:   swap
L138:   getfield Field lG "public" F
L141:   fmul
L142:   invokestatic Method org/lwjgl/opengl/GL11 break (FF)V
L145:   invokestatic Method org/lwjgl/opengl/GL11 float ()V
L148:   fload_2
L149:   fstore_3
L150:   iload_1
L151:   ifne L163
L154:   fload_3
L155:   fconst_1
L156:   aload_0
L157:   getfield Field lG default F
L160:   fsub
L161:   fmul
L162:   fstore_3
L163:   fload_3
L164:   fconst_0
L165:   fcmpl
L166:   ifle L236
L169:   invokestatic Method FE goto ()V
L172:   aload_0
L173:   getfield Field lG "super" Z
L176:   ifeq L231
L179:   fload_3
L180:   fconst_1
L181:   fcmpl
L182:   ifne L231
L185:   aload_0
L186:   getfield Field lG C Z
L189:   ifeq L221
L192:   fconst_1
L193:   aload_0
L194:   dup
L195:   dup_x2
L196:   iconst_0
L197:   iconst_1
L198:   dup
L199:   pop2
L200:   putfield Field lG C Z
L203:   getfield Field lG double I
L206:   sipush 4864
L209:   iconst_1
L210:   dup
L211:   pop2
L212:   invokestatic Method org/lwjgl/opengl/GL11 short (II)V
L215:   invokespecial Method lG const (F)V
L218:   invokestatic Method org/lwjgl/opengl/GL11 try ()V
L221:   aload_0
L222:   getfield Field lG double I
L225:   invokestatic Method org/lwjgl/opengl/GL11 const (I)V
L228:   goto L236
L231:   aload_0
L232:   fload_3
L233:   invokespecial Method lG const (F)V
L236:   invokestatic Method FE "final" ()V
L239:   aload_0
L240:   getfield Field lG G Z
L243:   ifeq L450
L246:   aload_0
L247:   dup
L248:   getfield Field lG "static" F
L251:   swap
L252:   getfield Field lG extends I
L255:   i2f
L256:   fcmpg
L257:   ifge L341
L260:   fconst_1
L261:   dup
L262:   dup_x1
L263:   fload_2
L264:   invokestatic Method org/lwjgl/opengl/GL11 else (FFFF)V
L267:   bipush 7
L269:   iconst_1
L270:   dup
L271:   pop2
L272:   invokestatic Method org/lwjgl/opengl/GL11 "strictfp" (I)V
L275:   fconst_0
L276:   aload_0
L277:   getfield Field lG extends I
L280:   i2f
L281:   aload_0
L282:   getfield Field lG "public" F
L285:   fmul
L286:   invokestatic Method org/lwjgl/opengl/GL11 break (FF)V
L289:   fconst_0
L290:   aload_0
L291:   dup
L292:   getfield Field lG catch F
L295:   swap
L296:   getfield Field lG extends I
L299:   i2f
L300:   aload_0
L301:   dup_x2
L302:   getfield Field lG "public" F
L305:   fmul
L306:   invokestatic Method org/lwjgl/opengl/GL11 break (FF)V
L309:   getfield Field lG catch F
L312:   aload_0
L313:   dup
L314:   getfield Field lG "static" F
L317:   swap
L318:   getfield Field lG "public" F
L321:   fmul
L322:   invokestatic Method org/lwjgl/opengl/GL11 break (FF)V
L325:   aload_0
L326:   dup
L327:   getfield Field lG "static" F
L330:   swap
L331:   getfield Field lG "public" F
L334:   fmul
L335:   invokestatic Method org/lwjgl/opengl/GL11 break (FF)V
L338:   invokestatic Method org/lwjgl/opengl/GL11 float ()V
L341:   sipush 770
L344:   iconst_1
L345:   dup
L346:   pop2
L347:   iconst_1
L348:   dup
L349:   dup
L350:   pop2
L351:   invokestatic Method org/lwjgl/opengl/GL11 char (II)V
L354:   fconst_0
L355:   iconst_2
L356:   aload_0
L357:   dup_x1
L358:   dup_x2
L359:   getfield Field lG k F
L362:   aload_0
L363:   dup
L364:   getfield Field lG "protected" F
L367:   swap
L368:   getfield Field lG this F
L371:   ldc_w 2.5e-1f
L374:   fload_2
L375:   fmul
L376:   invokestatic Method org/lwjgl/opengl/GL11 else (FFFF)V
L379:   iconst_1
L380:   dup
L381:   pop2
L382:   invokestatic Method org/lwjgl/opengl/GL11 "strictfp" (I)V
L385:   fconst_0
L386:   aload_0
L387:   getfield Field lG break F
L390:   invokestatic Method org/lwjgl/opengl/GL11 break (FF)V
L393:   getfield Field lG catch F
L396:   aload_0
L397:   getfield Field lG break F
L400:   invokestatic Method org/lwjgl/opengl/GL11 break (FF)V
L403:   getfield Field lG catch F
L406:   aload_0
L407:   dup
L408:   getfield Field lG "static" F
L411:   swap
L412:   getfield Field lG "public" F
L415:   fmul
L416:   invokestatic Method org/lwjgl/opengl/GL11 break (FF)V
L419:   aload_0
L420:   dup
L421:   getfield Field lG "static" F
L424:   swap
L425:   getfield Field lG "public" F
L428:   fmul
L429:   invokestatic Method org/lwjgl/opengl/GL11 break (FF)V
L432:   invokestatic Method org/lwjgl/opengl/GL11 float ()V
L435:   sipush 770
L438:   iconst_1
L439:   dup
L440:   pop2
L441:   sipush 771
L444:   iconst_1
L445:   dup
L446:   pop2
L447:   invokestatic Method org/lwjgl/opengl/GL11 char (II)V
L450:   aload_0
L451:   getfield Field lG short F
L454:   invokestatic Method java/lang/Math abs (F)F
L457:   f2d
L458:   ldc2_w 1e-4
L461:   dcmpl
L462:   ifle L468
L465:   invokestatic Method org/lwjgl/opengl/GL11 do ()V
L468:   return
L469:   
        .attribute StackMap b'\x00\x0E\x00\x07\x00\x00\x00\x01\x07\x00\xBF\x00\x08\x00\x03\x07\x00\x02\x01\x02\x00\x00\x00\x3B\x00\x03\x07\x00\x02\x01\x02\x00\x00\x00\x4F\x00\x00\x00\x01\x07\x00\xBF\x00\x50\x00\x03\x07\x00\x02\x01\x02\x00\x03\x02\x02\x02\x00\x53\x00\x03\x07\x00\x02\x01\x02\x00\x05\x02\x02\x02\x02\x02\x00\x94\x00\x03\x07\x00\x02\x01\x02\x00\x00\x00\xA3\x00\x04\x07\x00\x02\x01\x02\x02\x00\x00\x00\xDD\x00\x04\x07\x00\x02\x01\x02\x02\x00\x00\x00\xE7\x00\x04\x07\x00\x02\x01\x02\x02\x00\x00\x00\xEC\x00\x04\x07\x00\x02\x01\x02\x02\x00\x00\x01\x55\x00\x04\x07\x00\x02\x01\x02\x02\x00\x00\x01\xC2\x00\x04\x07\x00\x02\x01\x02\x02\x00\x00\x01\xD4\x00\x04\x07\x00\x02\x01\x02\x02\x00\x00'
    .end code
.end method

.method public this : (FF)V
    .code stack 6 locals 3
L0:     iconst_1
L1:     aload_0
L2:     dup_x1
L3:     fload_2
L4:     aload_0
L5:     fload_1
L6:     putfield Field lG boolean F
L9:     putfield Field lG A F
L12:    iconst_1
L13:    dup
L14:    pop2
L15:    putfield Field lG C Z
L18:    return
L19:    
    .end code
.end method

.method public else : ()V
    .code stack 2 locals 1
L0:     aload_0
L1:     fconst_0
L2:     putfield Field lG long F
L5:     return
L6:     
    .end code
.end method

.method public else : (II)V
    .code stack 8 locals 3
L0:     aload_0
L1:     getfield Field lG finally I
L4:     iload_1
L5:     if_icmpne L18
L8:     aload_0
L9:     getfield Field lG "strictfp" I
L12:    iload_2
L13:    if_icmpne L18
L16:    return
L17:    athrow
L18:    aload_0
L19:    iconst_1
L20:    dup
L21:    aload_0
L22:    dup_x1
L23:    iload_2
L24:    aload_0
L25:    iload_1
L26:    putfield Field lG finally I
L29:    putfield Field lG "strictfp" I
L32:    iconst_1
L33:    dup
L34:    pop2
L35:    putfield Field lG C Z
L38:    iconst_1
L39:    dup
L40:    pop2
L41:    putfield Field lG instanceof Z
L44:    return
L45:    
        .attribute StackMap b'\x00\x02\x00\x11\x00\x00\x00\x01\x07\x00\xBF\x00\x12\x00\x03\x07\x00\x02\x01\x01\x00\x00'
    .end code
.end method

.method public break : (IIIF)V
    .code stack 6 locals 5
L0:     iconst_1
L1:     aload_0
L2:     dup
L3:     dup_x2
L4:     getfield Field lG "interface" [[F
L7:     iload_1
L8:     aaload
L9:     iload_2
L10:    fload 4
L12:    fastore
L13:    getfield Field lG continue [[I
L16:    iload_1
L17:    aaload
L18:    iload_2
L19:    iload_3
L20:    iastore
L21:    iconst_1
L22:    dup
L23:    pop2
L24:    putfield Field lG B Z
L27:    return
L28:    
    .end code
.end method

.method public catch : (F)V
    .code stack 2 locals 2
L0:     aload_0
L1:     fload_1
L2:     putfield Field lG short F
L5:     return
L6:     
    .end code
.end method

.method public float : (F)V
    .code stack 4 locals 2
L0:     aload_0
L1:     getfield Field lG f F
L4:     fload_1
L5:     fcmpl
L6:     ifne L11
L9:     return
L10:    athrow
L11:    aload_0
L12:    fload_1
L13:    fconst_0
L14:    fconst_1
L15:    invokestatic Method OC else (FFF)F
L18:    putfield Field lG f F
L21:    return
L22:    
        .attribute StackMap b'\x00\x02\x00\x0A\x00\x00\x00\x01\x07\x00\xBF\x00\x0B\x00\x02\x07\x00\x02\x02\x00\x00'
    .end code
.end method

.method public static <clinit> : ()V
    .code stack 5 locals 0
L0:     bipush 32
L2:     iconst_1
L3:     dup
L4:     pop2
L5:     newarray float
L7:     iconst_1
L8:     dup
L9:     pop2
L10:    dup
L11:    iconst_0
L12:    iconst_1
L13:    dup
L14:    pop2
L15:    fconst_0
L16:    fastore
L17:    dup
L18:    iconst_1
L19:    dup
L20:    dup
L21:    pop2
L22:    fconst_1
L23:    fastore
L24:    dup
L25:    iconst_2
L26:    iconst_1
L27:    dup
L28:    pop2
L29:    fconst_0
L30:    fastore
L31:    dup
L32:    iconst_3
L33:    iconst_1
L34:    dup
L35:    pop2
L36:    ldc_w 9.5e-1f
L39:    fastore
L40:    dup
L41:    iconst_4
L42:    iconst_1
L43:    dup
L44:    pop2
L45:    ldc_w 2.5e-1f
L48:    fastore
L49:    dup
L50:    iconst_5
L51:    iconst_1
L52:    dup
L53:    pop2
L54:    fconst_1
L55:    fastore
L56:    dup
L57:    bipush 6
L59:    iconst_1
L60:    dup
L61:    pop2
L62:    ldc_w 1e-1f
L65:    fastore
L66:    dup
L67:    bipush 7
L69:    iconst_1
L70:    dup
L71:    pop2
L72:    fconst_1
L73:    fastore
L74:    dup
L75:    bipush 8
L77:    iconst_1
L78:    dup
L79:    pop2
L80:    ldc_w 9e-1f
L83:    fastore
L84:    dup
L85:    bipush 9
L87:    iconst_1
L88:    dup
L89:    pop2
L90:    ldc_w 5e-1f
L93:    fastore
L94:    dup
L95:    bipush 10
L97:    iconst_1
L98:    dup
L99:    pop2
L100:   ldc_w 1.2e0f
L103:   fastore
L104:   dup
L105:   bipush 11
L107:   iconst_1
L108:   dup
L109:   pop2
L110:   ldc_w 1.5e-1f
L113:   fastore
L114:   dup
L115:   bipush 12
L117:   iconst_1
L118:   dup
L119:   pop2
L120:   fconst_0
L121:   fastore
L122:   dup
L123:   bipush 13
L125:   iconst_1
L126:   dup
L127:   pop2
L128:   fconst_1
L129:   fastore
L130:   dup
L131:   bipush 14
L133:   iconst_1
L134:   dup
L135:   pop2
L136:   ldc_w 5.5e-1f
L139:   fastore
L140:   dup
L141:   bipush 15
L143:   iconst_1
L144:   dup
L145:   pop2
L146:   ldc_w 4.5e-1f
L149:   fastore
L150:   dup
L151:   bipush 16
L153:   iconst_1
L154:   dup
L155:   pop2
L156:   ldc_w -6.6e-1f
L159:   fastore
L160:   dup
L161:   bipush 17
L163:   iconst_1
L164:   dup
L165:   pop2
L166:   fconst_0
L167:   fastore
L168:   dup
L169:   bipush 18
L171:   iconst_1
L172:   dup
L173:   pop2
L174:   fconst_0
L175:   fastore
L176:   dup
L177:   bipush 19
L179:   iconst_1
L180:   dup
L181:   pop2
L182:   fconst_0
L183:   fastore
L184:   dup
L185:   bipush 20
L187:   iconst_1
L188:   dup
L189:   pop2
L190:   fconst_0
L191:   fastore
L192:   dup
L193:   bipush 21
L195:   iconst_1
L196:   dup
L197:   pop2
L198:   fconst_0
L199:   fastore
L200:   dup
L201:   bipush 22
L203:   iconst_1
L204:   dup
L205:   pop2
L206:   fconst_0
L207:   fastore
L208:   dup
L209:   bipush 23
L211:   iconst_1
L212:   dup
L213:   pop2
L214:   fconst_0
L215:   fastore
L216:   dup
L217:   bipush 24
L219:   iconst_1
L220:   dup
L221:   pop2
L222:   fconst_0
L223:   fastore
L224:   dup
L225:   bipush 25
L227:   iconst_1
L228:   dup
L229:   pop2
L230:   fconst_0
L231:   fastore
L232:   dup
L233:   bipush 26
L235:   iconst_1
L236:   dup
L237:   pop2
L238:   fconst_0
L239:   fastore
L240:   dup
L241:   bipush 27
L243:   iconst_1
L244:   dup
L245:   pop2
L246:   fconst_0
L247:   fastore
L248:   dup
L249:   bipush 28
L251:   iconst_1
L252:   dup
L253:   pop2
L254:   fconst_0
L255:   fastore
L256:   dup
L257:   bipush 29
L259:   iconst_1
L260:   dup
L261:   pop2
L262:   fconst_0
L263:   fastore
L264:   dup
L265:   bipush 30
L267:   iconst_1
L268:   dup
L269:   pop2
L270:   fconst_0
L271:   fastore
L272:   dup
L273:   bipush 31
L275:   iconst_1
L276:   dup
L277:   pop2
L278:   fconst_0
L279:   fastore
L280:   putstatic Field lG m [F
L283:   bipush 32
L285:   iconst_1
L286:   dup
L287:   pop2
L288:   newarray float
L290:   iconst_1
L291:   dup
L292:   pop2
L293:   dup
L294:   iconst_0
L295:   iconst_1
L296:   dup
L297:   pop2
L298:   fconst_0
L299:   fastore
L300:   dup
L301:   iconst_1
L302:   dup
L303:   dup
L304:   pop2
L305:   ldc_w 1e-1f
L308:   fastore
L309:   dup
L310:   iconst_2
L311:   iconst_1
L312:   dup
L313:   pop2
L314:   fconst_1
L315:   fastore
L316:   dup
L317:   iconst_3
L318:   iconst_1
L319:   dup
L320:   pop2
L321:   fconst_1
L322:   fastore
L323:   dup
L324:   iconst_4
L325:   iconst_1
L326:   dup
L327:   pop2
L328:   ldc_w 2.5e-1f
L331:   fastore
L332:   dup
L333:   iconst_5
L334:   iconst_1
L335:   dup
L336:   pop2
L337:   ldc_w 1e-1f
L340:   fastore
L341:   dup
L342:   bipush 6
L344:   iconst_1
L345:   dup
L346:   pop2
L347:   fconst_1
L348:   fastore
L349:   dup
L350:   bipush 7
L352:   iconst_1
L353:   dup
L354:   pop2
L355:   fconst_1
L356:   fastore
L357:   dup
L358:   bipush 8
L360:   iconst_1
L361:   dup
L362:   pop2
L363:   ldc_w 5e-1f
L366:   fastore
L367:   dup
L368:   bipush 9
L370:   iconst_1
L371:   dup
L372:   pop2
L373:   ldc_w 5e-1f
L376:   fastore
L377:   dup
L378:   bipush 10
L380:   iconst_1
L381:   dup
L382:   pop2
L383:   fconst_1
L384:   fastore
L385:   dup
L386:   bipush 11
L388:   iconst_1
L389:   dup
L390:   pop2
L391:   ldc_w 1.5e-1f
L394:   fastore
L395:   dup
L396:   bipush 12
L398:   iconst_1
L399:   dup
L400:   pop2
L401:   fconst_0
L402:   fastore
L403:   dup
L404:   bipush 13
L406:   iconst_1
L407:   dup
L408:   pop2
L409:   ldc 8.5e-1f
L411:   fastore
L412:   dup
L413:   bipush 14
L415:   iconst_1
L416:   dup
L417:   pop2
L418:   ldc 8.5e-1f
L420:   fastore
L421:   dup
L422:   bipush 15
L424:   iconst_1
L425:   dup
L426:   pop2
L427:   fconst_0
L428:   fastore
L429:   dup
L430:   bipush 16
L432:   iconst_1
L433:   dup
L434:   pop2
L435:   ldc_w -6.6e-1f
L438:   fastore
L439:   dup
L440:   bipush 17
L442:   iconst_1
L443:   dup
L444:   pop2
L445:   fconst_0
L446:   fastore
L447:   dup
L448:   bipush 18
L450:   iconst_1
L451:   dup
L452:   pop2
L453:   fconst_0
L454:   fastore
L455:   dup
L456:   bipush 19
L458:   iconst_1
L459:   dup
L460:   pop2
L461:   fconst_0
L462:   fastore
L463:   dup
L464:   bipush 20
L466:   iconst_1
L467:   dup
L468:   pop2
L469:   fconst_0
L470:   fastore
L471:   dup
L472:   bipush 21
L474:   iconst_1
L475:   dup
L476:   pop2
L477:   fconst_0
L478:   fastore
L479:   dup
L480:   bipush 22
L482:   iconst_1
L483:   dup
L484:   pop2
L485:   fconst_0
L486:   fastore
L487:   dup
L488:   bipush 23
L490:   iconst_1
L491:   dup
L492:   pop2
L493:   fconst_0
L494:   fastore
L495:   dup
L496:   bipush 24
L498:   iconst_1
L499:   dup
L500:   pop2
L501:   fconst_0
L502:   fastore
L503:   dup
L504:   bipush 25
L506:   iconst_1
L507:   dup
L508:   pop2
L509:   fconst_0
L510:   fastore
L511:   dup
L512:   bipush 26
L514:   iconst_1
L515:   dup
L516:   pop2
L517:   fconst_0
L518:   fastore
L519:   dup
L520:   bipush 27
L522:   iconst_1
L523:   dup
L524:   pop2
L525:   fconst_0
L526:   fastore
L527:   dup
L528:   bipush 28
L530:   iconst_1
L531:   dup
L532:   pop2
L533:   fconst_0
L534:   fastore
L535:   dup
L536:   bipush 29
L538:   iconst_1
L539:   dup
L540:   pop2
L541:   fconst_0
L542:   fastore
L543:   dup
L544:   bipush 30
L546:   iconst_1
L547:   dup
L548:   pop2
L549:   fconst_0
L550:   fastore
L551:   dup
L552:   bipush 31
L554:   iconst_1
L555:   dup
L556:   pop2
L557:   fconst_0
L558:   fastore
L559:   putstatic Field lG new [F
L562:   bipush 32
L564:   iconst_1
L565:   dup
L566:   pop2
L567:   newarray float
L569:   iconst_1
L570:   dup
L571:   pop2
L572:   dup
L573:   iconst_0
L574:   iconst_1
L575:   dup
L576:   pop2
L577:   fconst_0
L578:   fastore
L579:   dup
L580:   iconst_1
L581:   dup
L582:   dup
L583:   pop2
L584:   ldc_w 1e-1f
L587:   fastore
L588:   dup
L589:   iconst_2
L590:   iconst_1
L591:   dup
L592:   pop2
L593:   fconst_0
L594:   fastore
L595:   dup
L596:   iconst_3
L597:   iconst_1
L598:   dup
L599:   pop2
L600:   ldc_w 2.5e-1f
L603:   fastore
L604:   dup
L605:   iconst_4
L606:   iconst_1
L607:   dup
L608:   pop2
L609:   fconst_1
L610:   fastore
L611:   dup
L612:   iconst_5
L613:   iconst_1
L614:   dup
L615:   pop2
L616:   fconst_1
L617:   fastore
L618:   dup
L619:   bipush 6
L621:   iconst_1
L622:   dup
L623:   pop2
L624:   fconst_1
L625:   fastore
L626:   dup
L627:   bipush 7
L629:   iconst_1
L630:   dup
L631:   pop2
L632:   fconst_1
L633:   fastore
L634:   dup
L635:   bipush 8
L637:   iconst_1
L638:   dup
L639:   pop2
L640:   ldc_w 1e-1f
L643:   fastore
L644:   dup
L645:   bipush 9
L647:   iconst_1
L648:   dup
L649:   pop2
L650:   ldc_w 5e-1f
L653:   fastore
L654:   dup
L655:   bipush 10
L657:   iconst_1
L658:   dup
L659:   pop2
L660:   ldc_w 1e-1f
L663:   fastore
L664:   dup
L665:   bipush 11
L667:   iconst_1
L668:   dup
L669:   pop2
L670:   ldc_w 1.5e-1f
L673:   fastore
L674:   dup
L675:   bipush 12
L677:   iconst_1
L678:   dup
L679:   pop2
L680:   fconst_0
L681:   fastore
L682:   dup
L683:   bipush 13
L685:   iconst_1
L686:   dup
L687:   pop2
L688:   ldc_w 1e-1f
L691:   fastore
L692:   dup
L693:   bipush 14
L695:   iconst_1
L696:   dup
L697:   pop2
L698:   ldc_w 5e-2f
L701:   fastore
L702:   dup
L703:   bipush 15
L705:   iconst_1
L706:   dup
L707:   pop2
L708:   ldc_w 5e-2f
L711:   fastore
L712:   dup
L713:   bipush 16
L715:   iconst_1
L716:   dup
L717:   pop2
L718:   ldc_w -6.6e-1f
L721:   fastore
L722:   dup
L723:   bipush 17
L725:   iconst_1
L726:   dup
L727:   pop2
L728:   fconst_0
L729:   fastore
L730:   dup
L731:   bipush 18
L733:   iconst_1
L734:   dup
L735:   pop2
L736:   fconst_0
L737:   fastore
L738:   dup
L739:   bipush 19
L741:   iconst_1
L742:   dup
L743:   pop2
L744:   fconst_0
L745:   fastore
L746:   dup
L747:   bipush 20
L749:   iconst_1
L750:   dup
L751:   pop2
L752:   fconst_0
L753:   fastore
L754:   dup
L755:   bipush 21
L757:   iconst_1
L758:   dup
L759:   pop2
L760:   fconst_0
L761:   fastore
L762:   dup
L763:   bipush 22
L765:   iconst_1
L766:   dup
L767:   pop2
L768:   fconst_0
L769:   fastore
L770:   dup
L771:   bipush 23
L773:   iconst_1
L774:   dup
L775:   pop2
L776:   fconst_0
L777:   fastore
L778:   dup
L779:   bipush 24
L781:   iconst_1
L782:   dup
L783:   pop2
L784:   fconst_0
L785:   fastore
L786:   dup
L787:   bipush 25
L789:   iconst_1
L790:   dup
L791:   pop2
L792:   fconst_0
L793:   fastore
L794:   dup
L795:   bipush 26
L797:   iconst_1
L798:   dup
L799:   pop2
L800:   fconst_0
L801:   fastore
L802:   dup
L803:   bipush 27
L805:   iconst_1
L806:   dup
L807:   pop2
L808:   fconst_0
L809:   fastore
L810:   dup
L811:   bipush 28
L813:   iconst_1
L814:   dup
L815:   pop2
L816:   fconst_0
L817:   fastore
L818:   dup
L819:   bipush 29
L821:   iconst_1
L822:   dup
L823:   pop2
L824:   fconst_0
L825:   fastore
L826:   dup
L827:   bipush 30
L829:   iconst_1
L830:   dup
L831:   pop2
L832:   fconst_0
L833:   fastore
L834:   dup
L835:   bipush 31
L837:   iconst_1
L838:   dup
L839:   pop2
L840:   fconst_0
L841:   fastore
L842:   putstatic Field lG J [F
L845:   bipush 32
L847:   iconst_1
L848:   dup
L849:   pop2
L850:   newarray float
L852:   iconst_1
L853:   dup
L854:   pop2
L855:   dup
L856:   iconst_0
L857:   iconst_1
L858:   dup
L859:   pop2
L860:   fconst_1
L861:   fastore
L862:   dup
L863:   iconst_1
L864:   dup
L865:   dup
L866:   pop2
L867:   fconst_1
L868:   fastore
L869:   dup
L870:   iconst_2
L871:   iconst_1
L872:   dup
L873:   pop2
L874:   fconst_1
L875:   fastore
L876:   dup
L877:   iconst_3
L878:   iconst_1
L879:   dup
L880:   pop2
L881:   fconst_1
L882:   fastore
L883:   dup
L884:   iconst_4
L885:   iconst_1
L886:   dup
L887:   pop2
L888:   fconst_1
L889:   fastore
L890:   dup
L891:   iconst_5
L892:   iconst_1
L893:   dup
L894:   pop2
L895:   fconst_1
L896:   fastore
L897:   dup
L898:   bipush 6
L900:   iconst_1
L901:   dup
L902:   pop2
L903:   fconst_1
L904:   fastore
L905:   dup
L906:   bipush 7
L908:   iconst_1
L909:   dup
L910:   pop2
L911:   fconst_1
L912:   fastore
L913:   dup
L914:   bipush 8
L916:   iconst_1
L917:   dup
L918:   pop2
L919:   fconst_1
L920:   fastore
L921:   dup
L922:   bipush 9
L924:   iconst_1
L925:   dup
L926:   pop2
L927:   fconst_1
L928:   fastore
L929:   dup
L930:   bipush 10
L932:   iconst_1
L933:   dup
L934:   pop2
L935:   fconst_1
L936:   fastore
L937:   dup
L938:   bipush 11
L940:   iconst_1
L941:   dup
L942:   pop2
L943:   fconst_1
L944:   fastore
L945:   dup
L946:   bipush 12
L948:   iconst_1
L949:   dup
L950:   pop2
L951:   fconst_1
L952:   fastore
L953:   dup
L954:   bipush 13
L956:   iconst_1
L957:   dup
L958:   pop2
L959:   fconst_1
L960:   fastore
L961:   dup
L962:   bipush 14
L964:   iconst_1
L965:   dup
L966:   pop2
L967:   fconst_1
L968:   fastore
L969:   dup
L970:   bipush 15
L972:   iconst_1
L973:   dup
L974:   pop2
L975:   fconst_1
L976:   fastore
L977:   dup
L978:   bipush 16
L980:   iconst_1
L981:   dup
L982:   pop2
L983:   fconst_0
L984:   fastore
L985:   dup
L986:   bipush 17
L988:   iconst_1
L989:   dup
L990:   pop2
L991:   fconst_0
L992:   fastore
L993:   dup
L994:   bipush 18
L996:   iconst_1
L997:   dup
L998:   pop2
L999:   fconst_0
L1000:  fastore
L1001:  dup
L1002:  bipush 19
L1004:  iconst_1
L1005:  dup
L1006:  pop2
L1007:  fconst_0
L1008:  fastore
L1009:  dup
L1010:  bipush 20
L1012:  iconst_1
L1013:  dup
L1014:  pop2
L1015:  fconst_0
L1016:  fastore
L1017:  dup
L1018:  bipush 21
L1020:  iconst_1
L1021:  dup
L1022:  pop2
L1023:  fconst_0
L1024:  fastore
L1025:  dup
L1026:  bipush 22
L1028:  iconst_1
L1029:  dup
L1030:  pop2
L1031:  fconst_0
L1032:  fastore
L1033:  dup
L1034:  bipush 23
L1036:  iconst_1
L1037:  dup
L1038:  pop2
L1039:  fconst_0
L1040:  fastore
L1041:  dup
L1042:  bipush 24
L1044:  iconst_1
L1045:  dup
L1046:  pop2
L1047:  fconst_0
L1048:  fastore
L1049:  dup
L1050:  bipush 25
L1052:  iconst_1
L1053:  dup
L1054:  pop2
L1055:  fconst_0
L1056:  fastore
L1057:  dup
L1058:  bipush 26
L1060:  iconst_1
L1061:  dup
L1062:  pop2
L1063:  fconst_0
L1064:  fastore
L1065:  dup
L1066:  bipush 27
L1068:  iconst_1
L1069:  dup
L1070:  pop2
L1071:  fconst_0
L1072:  fastore
L1073:  dup
L1074:  bipush 28
L1076:  iconst_1
L1077:  dup
L1078:  pop2
L1079:  fconst_0
L1080:  fastore
L1081:  dup
L1082:  bipush 29
L1084:  iconst_1
L1085:  dup
L1086:  pop2
L1087:  fconst_0
L1088:  fastore
L1089:  dup
L1090:  bipush 30
L1092:  iconst_1
L1093:  dup
L1094:  pop2
L1095:  fconst_0
L1096:  fastore
L1097:  dup
L1098:  bipush 31
L1100:  iconst_1
L1101:  dup
L1102:  pop2
L1103:  fconst_0
L1104:  fastore
L1105:  putstatic Field lG "transient" [F
L1108:  return
L1109:  
    .end code
.end method

.method public const : (FF)V
    .code stack 8 locals 3
L0:     iconst_1
L1:     aload_0
L2:     dup
L3:     dup_x2
L4:     aload_0
L5:     dup
L6:     fload_1
L7:     fload_2
L8:     invokespecial Method gB const (FF)V
L11:    getfield Field lG catch F
L14:    aload_0
L15:    dup_x1
L16:    getfield Field lG "synchronized" I
L19:    i2f
L20:    fdiv
L21:    putfield Field lG true F
L24:    getfield Field lG break F
L27:    aload_0
L28:    getfield Field lG while I
L31:    i2f
L32:    fdiv
L33:    putfield Field lG "public" F
L36:    iconst_1
L37:    dup
L38:    pop2
L39:    putfield Field lG C Z
L42:    return
L43:    
    .end code
.end method

.method public short : (F)V
    .code stack 3 locals 2
L0:     aload_0
L1:     fconst_1
L2:     fload_1
L3:     fdiv
L4:     putfield Field lG g F
L7:     return
L8:     
    .end code
.end method

.method public else : ([[I)V
    .code stack 7 locals 3
L0:     aload_1
L1:     arraylength
L2:     iconst_4
L3:     iconst_1
L4:     dup
L5:     pop2
L6:     if_icmpne L23
L9:     aload_1
L10:    iconst_0
L11:    iconst_1
L12:    dup
L13:    pop2
L14:    aaload
L15:    arraylength
L16:    iconst_4
L17:    iconst_1
L18:    dup
L19:    pop2
L20:    if_icmpeq L86
L23:    aload_0
L24:    iconst_4
L25:    iconst_1
L26:    dup
L27:    pop2
L28:    iconst_4
L29:    iconst_1
L30:    dup
L31:    pop2
L32:    multianewarray [[I 2
L36:    putfield Field lG I [[I
L39:    iconst_0
L40:    iconst_1
L41:    dup
L42:    pop2
L43:    dup
L44:    istore_2
L45:    aload_1
L46:    arraylength
L47:    if_icmpge L130
L50:    aload_1
L51:    iload_2
L52:    aaload
L53:    iconst_1
L54:    dup
L55:    pop2
L56:    aload_0
L57:    getfield Field lG I [[I
L60:    iload_2
L61:    aaload
L62:    iconst_0
L63:    dup_x1
L64:    iconst_1
L65:    dup
L66:    pop2
L67:    aload_1
L68:    iload_2
L69:    iinc 2 1
L72:    aaload
L73:    arraylength
L74:    invokestatic Method java/lang/System arraycopy (Ljava/lang/Object;ILjava/lang/Object;II)V
L77:    iload_2
L78:    goto L45
L81:    nop
L82:    nop
L83:    nop
L84:    nop
L85:    athrow
L86:    iconst_0
L87:    iconst_1
L88:    dup
L89:    pop2
L90:    dup
L91:    istore_2
L92:    iconst_4
L93:    iconst_1
L94:    dup
L95:    pop2
L96:    if_icmpge L130
L99:    aload_1
L100:   iload_2
L101:   aaload
L102:   iconst_1
L103:   dup
L104:   pop2
L105:   aload_0
L106:   getfield Field lG I [[I
L109:   iload_2
L110:   iinc 2 1
L113:   aaload
L114:   iconst_0
L115:   dup_x1
L116:   iconst_1
L117:   dup
L118:   pop2
L119:   iconst_4
L120:   iconst_1
L121:   dup
L122:   pop2
L123:   invokestatic Method java/lang/System arraycopy (Ljava/lang/Object;ILjava/lang/Object;II)V
L126:   iload_2
L127:   goto L92
L130:   aload_0
L131:   aload_0
L132:   iconst_1
L133:   dup
L134:   dup_x2
L135:   dup
L136:   pop2
L137:   putfield Field lG C Z
L140:   iconst_1
L141:   dup
L142:   pop2
L143:   putfield Field lG instanceof Z
L146:   return
L147:   
        .attribute StackMap b'\x00\x06\x00\x17\x00\x02\x07\x00\x02\x07\x00\x86\x00\x00\x00\x2D\x00\x03\x07\x00\x02\x07\x00\x86\x01\x00\x01\x01\x00\x51\x00\x00\x00\x01\x07\x00\xBF\x00\x56\x00\x02\x07\x00\x02\x07\x00\x86\x00\x00\x00\x5C\x00\x03\x07\x00\x02\x07\x00\x86\x01\x00\x01\x01\x00\x82\x00\x03\x07\x00\x02\x07\x00\x86\x01\x00\x00'
    .end code
.end method

.method public break : (II)V
    .code stack 8 locals 3
L0:     aload_0
L1:     getfield Field lG a I
L4:     iload_1
L5:     if_icmpne L18
L8:     aload_0
L9:     getfield Field lG h I
L12:    iload_2
L13:    if_icmpne L18
L16:    return
L17:    athrow
L18:    aload_0
L19:    iconst_1
L20:    dup
L21:    aload_0
L22:    dup_x1
L23:    iload_2
L24:    aload_0
L25:    iload_1
L26:    putfield Field lG a I
L29:    putfield Field lG h I
L32:    iconst_1
L33:    dup
L34:    pop2
L35:    putfield Field lG C Z
L38:    iconst_1
L39:    dup
L40:    pop2
L41:    putfield Field lG instanceof Z
L44:    return
L45:    
        .attribute StackMap b'\x00\x02\x00\x11\x00\x00\x00\x01\x07\x00\xBF\x00\x12\x00\x03\x07\x00\x02\x01\x01\x00\x00'
    .end code
.end method

.method private const : (F)V
    .code stack 8 locals 16
L0:     aload_0
L1:     getfield Field lG true F
L4:     invokestatic Method java/lang/Math abs (F)F
L7:     f2d
L8:     ldc2_w 1e-4
L11:    dcmpg
L12:    iflt L30
L15:    aload_0
L16:    getfield Field lG "public" F
L19:    invokestatic Method java/lang/Math abs (F)F
L22:    f2d
L23:    ldc2_w 1e-4
L26:    dcmpg
L27:    ifge L32
L30:    return
L31:    athrow
L32:    aload_0
L33:    getfield Field lG boolean F
L36:    fconst_0
L37:    fcmpl
L38:    ifne L50
L41:    aload_0
L42:    getfield Field lG A F
L45:    fconst_0
L46:    fcmpl
L47:    ifeq L74
L50:    aload_0
L51:    dup
L52:    getfield Field lG boolean F
L55:    swap
L56:    getfield Field lG true F
L59:    fmul
L60:    aload_0
L61:    dup
L62:    getfield Field lG A F
L65:    swap
L66:    getfield Field lG "public" F
L69:    fmul
L70:    fconst_0
L71:    invokestatic Method org/lwjgl/opengl/GL11 const (FFF)V
L74:    sipush 770
L77:    iconst_1
L78:    dup
L79:    pop2
L80:    iconst_1
L81:    dup
L82:    dup
L83:    pop2
L84:    invokestatic Method org/lwjgl/opengl/GL11 char (II)V
L87:    bipush 7
L89:    iconst_1
L90:    dup
L91:    pop2
L92:    invokestatic Method org/lwjgl/opengl/GL11 "strictfp" (I)V
L95:    aload_0
L96:    getfield Field lG extends I
L99:    dup
L100:   istore_2
L101:   aload_0
L102:   getfield Field lG case I
L105:   if_icmpge L1290
L108:   iload_2
L109:   i2f
L110:   aload_0
L111:   getfield Field lG try [F
L114:   iload_2
L115:   faload
L116:   fsub
L117:   aload_0
L118:   getfield Field lG long F
L121:   fadd
L122:   aload_0
L123:   getfield Field lG goto F
L126:   fsub
L127:   aload_0
L128:   getfield Field lG "public" F
L131:   fmul
L132:   dup
L133:   fstore_3
L134:   aload_0
L135:   getfield Field lG "public" F
L138:   fadd
L139:   dup
L140:   fstore 4
L142:   aload_0
L143:   getfield Field lG extends I
L146:   i2f
L147:   aload_0
L148:   getfield Field lG "public" F
L151:   fmul
L152:   fcmpl
L153:   iflt L1283
L156:   fload_3
L157:   aload_0
L158:   getfield Field lG break F
L161:   fcmpg
L162:   ifgt L1283
L165:   fload_3
L166:   aload_0
L167:   getfield Field lG extends I
L170:   i2f
L171:   aload_0
L172:   getfield Field lG "public" F
L175:   fmul
L176:   fcmpg
L177:   ifge L191
L180:   aload_0
L181:   getfield Field lG extends I
L184:   i2f
L185:   aload_0
L186:   getfield Field lG "public" F
L189:   fmul
L190:   fstore_3
L191:   fload 4
L193:   aload_0
L194:   getfield Field lG break F
L197:   fcmpl
L198:   ifle L207
L201:   aload_0
L202:   getfield Field lG break F
L205:   fstore 4
L207:   iconst_0
L208:   iconst_1
L209:   dup
L210:   pop2
L211:   dup
L212:   istore 5
L214:   aload_0
L215:   getfield Field lG "synchronized" I
L218:   if_icmpge L1283
L221:   aload_0
L222:   dup
L223:   getfield Field lG class [[I
L226:   iload 5
L228:   aaload
L229:   iload_2
L230:   iaload
L231:   istore 6
L233:   getfield Field lG continue [[I
L236:   iload 5
L238:   aaload
L239:   iload_2
L240:   iaload
L241:   bipush 31
L243:   iconst_1
L244:   dup
L245:   pop2
L246:   iand
L247:   istore 7
L249:   ldc 4e-1f
L251:   fstore 8
L253:   iload 6
L255:   ifne L323
L258:   iload 5
L260:   aload_0
L261:   getfield Field lG finally I
L264:   if_icmplt L323
L267:   iload 5
L269:   aload_0
L270:   getfield Field lG finally I
L273:   iconst_4
L274:   iconst_1
L275:   dup
L276:   pop2
L277:   iadd
L278:   if_icmpge L323
L281:   iload_2
L282:   aload_0
L283:   getfield Field lG "strictfp" I
L286:   if_icmplt L323
L289:   iload_2
L290:   aload_0
L291:   getfield Field lG "strictfp" I
L294:   iconst_4
L295:   iconst_1
L296:   dup
L297:   pop2
L298:   iadd
L299:   if_icmpge L323
L302:   aload_0
L303:   getfield Field lG I [[I
L306:   iload 5
L308:   aload_0
L309:   getfield Field lG finally I
L312:   isub
L313:   aaload
L314:   iload_2
L315:   aload_0
L316:   getfield Field lG "strictfp" I
L319:   isub
L320:   iaload
L321:   istore 6
L323:   iload 6
L325:   ifne L412
L328:   aload_0
L329:   getfield Field lG implements Z
L332:   ifeq L412
L335:   iload 5
L337:   aload_0
L338:   getfield Field lG a I
L341:   if_icmplt L412
L344:   iload 5
L346:   aload_0
L347:   getfield Field lG a I
L350:   iconst_4
L351:   iconst_1
L352:   dup
L353:   pop2
L354:   iadd
L355:   if_icmpge L412
L358:   iload_2
L359:   aload_0
L360:   getfield Field lG h I
L363:   if_icmplt L412
L366:   iload_2
L367:   aload_0
L368:   getfield Field lG h I
L371:   iconst_4
L372:   iconst_1
L373:   dup
L374:   pop2
L375:   iadd
L376:   if_icmpge L412
L379:   iload 6
L381:   aload_0
L382:   getfield Field lG I [[I
L385:   iload 5
L387:   aload_0
L388:   getfield Field lG a I
L391:   isub
L392:   aaload
L393:   iload_2
L394:   aload_0
L395:   getfield Field lG h I
L398:   isub
L399:   iaload
L400:   ior
L401:   dup
L402:   istore 6
L404:   ifeq L412
L407:   ldc_w 1e-1f
L410:   fstore 8
L412:   iload 7
L414:   ifeq L551
L417:   iload 7
L419:   bipush 15
L421:   iconst_1
L422:   dup
L423:   pop2
L424:   if_icmpeq L551
L427:   iload 7
L429:   bipush 16
L431:   iconst_1
L432:   dup
L433:   pop2
L434:   if_icmpeq L551
L437:   getstatic Field lG m [F
L440:   iload 7
L442:   faload
L443:   getstatic Field lG new [F
L446:   iload 7
L448:   faload
L449:   getstatic Field lG J [F
L452:   iload 7
L454:   faload
L455:   getstatic Field lG "transient" [F
L458:   iload 7
L460:   faload
L461:   aload_0
L462:   getfield Field lG "interface" [[F
L465:   iload 5
L467:   aaload
L468:   iload_2
L469:   faload
L470:   fmul
L471:   ldc_w 3e-1f
L474:   fmul
L475:   fload_1
L476:   fmul
L477:   aload_0
L478:   getfield Field lG import F
L481:   fmul
L482:   invokestatic Method org/lwjgl/opengl/GL11 else (FFFF)V
L485:   iload 5
L487:   i2f
L488:   aload_0
L489:   getfield Field lG true F
L492:   fmul
L493:   fload 4
L495:   invokestatic Method org/lwjgl/opengl/GL11 break (FF)V
L498:   iload 5
L500:   iconst_1
L501:   dup
L502:   dup
L503:   pop2
L504:   iadd
L505:   i2f
L506:   aload_0
L507:   getfield Field lG true F
L510:   fmul
L511:   fload 4
L513:   invokestatic Method org/lwjgl/opengl/GL11 break (FF)V
L516:   iload 5
L518:   iconst_1
L519:   dup
L520:   dup
L521:   pop2
L522:   iadd
L523:   i2f
L524:   aload_0
L525:   getfield Field lG true F
L528:   fmul
L529:   fload_3
L530:   invokestatic Method org/lwjgl/opengl/GL11 break (FF)V
L533:   iload 5
L535:   i2f
L536:   aload_0
L537:   getfield Field lG true F
L540:   fmul
L541:   fload_3
L542:   invokestatic Method org/lwjgl/opengl/GL11 break (FF)V
L545:   iconst_0
L546:   iconst_1
L547:   dup
L548:   pop2
L549:   istore 7
L551:   iload 6
L553:   ifeq L1275
L556:   iload 6
L558:   bipush 32
L560:   iconst_1
L561:   dup
L562:   pop2
L563:   iand
L564:   ifeq L1032
L567:   iload 6
L569:   bipush 31
L571:   iconst_1
L572:   dup
L573:   pop2
L574:   iand
L575:   bipush 13
L577:   iconst_1
L578:   dup
L579:   pop2
L580:   if_icmpne L607
L583:   iload_2
L584:   aload_0
L585:   getfield Field lG do I
L588:   if_icmpge L607
L591:   iload 6
L593:   bipush -32
L595:   iconst_1
L596:   dup
L597:   pop2
L598:   iand
L599:   bipush 14
L601:   iconst_1
L602:   dup
L603:   pop2
L604:   ior
L605:   istore 6
L607:   getstatic Field lG m [F
L610:   iload 6
L612:   bipush 31
L614:   iconst_1
L615:   dup
L616:   pop2
L617:   iand
L618:   faload
L619:   fstore 9
L621:   getstatic Field lG new [F
L624:   iload 6
L626:   bipush 31
L628:   iconst_1
L629:   dup
L630:   pop2
L631:   iand
L632:   faload
L633:   fstore 10
L635:   getstatic Field lG J [F
L638:   iload 6
L640:   bipush 31
L642:   iconst_1
L643:   dup
L644:   pop2
L645:   iand
L646:   faload
L647:   fstore 11
L649:   getstatic Field lG "transient" [F
L652:   iload 6
L654:   bipush 31
L656:   iconst_1
L657:   dup
L658:   pop2
L659:   iand
L660:   faload
L661:   fstore 12
L663:   iload 7
L665:   ifeq L731
L668:   fload 9
L670:   getstatic Field lG m [F
L673:   iload 7
L675:   faload
L676:   aload_0
L677:   getfield Field lG "interface" [[F
L680:   iload 5
L682:   aaload
L683:   iload_2
L684:   faload
L685:   fmul
L686:   fsub
L687:   fstore 9
L689:   fload 10
L691:   getstatic Field lG new [F
L694:   iload 7
L696:   faload
L697:   aload_0
L698:   getfield Field lG "interface" [[F
L701:   iload 5
L703:   aaload
L704:   iload_2
L705:   faload
L706:   fmul
L707:   fsub
L708:   fstore 10
L710:   fload 11
L712:   getstatic Field lG J [F
L715:   iload 7
L717:   faload
L718:   aload_0
L719:   getfield Field lG "interface" [[F
L722:   iload 5
L724:   aaload
L725:   iload_2
L726:   faload
L727:   fmul
L728:   fsub
L729:   fstore 11
L731:   ldc_w 1.5e-1f
L734:   ldc2_w 5e-1
L737:   iload 5
L739:   i2f
L740:   fload_3
L741:   aload_0
L742:   getfield Field lG "public" F
L745:   fdiv
L746:   fadd
L747:   f2d
L748:   dmul
L749:   invokestatic Method java/lang/Math sin (D)D
L752:   d2f
L753:   fmul
L754:   fstore 13
L756:   ldc_w 1.5e-1f
L759:   ldc2_w 5e-1
L762:   iload 5
L764:   i2f
L765:   fload_3
L766:   aload_0
L767:   getfield Field lG "public" F
L770:   fdiv
L771:   fadd
L772:   fconst_1
L773:   fadd
L774:   f2d
L775:   dmul
L776:   invokestatic Method java/lang/Math sin (D)D
L779:   d2f
L780:   fmul
L781:   fstore 14
L783:   ldc_w 1.5e-1f
L786:   ldc2_w 5e-1
L789:   iload 5
L791:   i2f
L792:   fload_3
L793:   aload_0
L794:   getfield Field lG "public" F
L797:   fdiv
L798:   fadd
L799:   fconst_2
L800:   fadd
L801:   f2d
L802:   dmul
L803:   invokestatic Method java/lang/Math sin (D)D
L806:   d2f
L807:   fmul
L808:   fstore 15
L810:   invokestatic Method org/lwjgl/opengl/GL11 float ()V
L813:   bipush 6
L815:   iconst_1
L816:   dup
L817:   pop2
L818:   invokestatic Method org/lwjgl/opengl/GL11 "strictfp" (I)V
L821:   fload 9
L823:   fload 14
L825:   fadd
L826:   fload 10
L828:   fload 14
L830:   fadd
L831:   fload 11
L833:   fload 14
L835:   fadd
L836:   fload 12
L838:   fload 8
L840:   fmul
L841:   fload_1
L842:   fmul
L843:   aload_0
L844:   getfield Field lG import F
L847:   fmul
L848:   ldc_w 1.6e0f
L851:   fmul
L852:   invokestatic Method org/lwjgl/opengl/GL11 else (FFFF)V
L855:   iload 5
L857:   i2f
L858:   aload_0
L859:   getfield Field lG true F
L862:   fmul
L863:   fload 4
L865:   invokestatic Method org/lwjgl/opengl/GL11 break (FF)V
L868:   fload 9
L870:   fload 13
L872:   fadd
L873:   fload 10
L875:   fload 13
L877:   fadd
L878:   fload 11
L880:   fload 13
L882:   fadd
L883:   fload 12
L885:   fload 8
L887:   fmul
L888:   fload_1
L889:   fmul
L890:   aload_0
L891:   getfield Field lG import F
L894:   fmul
L895:   ldc_w 1.6e0f
L898:   fmul
L899:   invokestatic Method org/lwjgl/opengl/GL11 else (FFFF)V
L902:   iload 5
L904:   i2f
L905:   aload_0
L906:   getfield Field lG true F
L909:   fmul
L910:   fload_3
L911:   invokestatic Method org/lwjgl/opengl/GL11 break (FF)V
L914:   fload 9
L916:   fload 14
L918:   fadd
L919:   fload 10
L921:   fload 14
L923:   fadd
L924:   fload 11
L926:   fload 14
L928:   fadd
L929:   fload 12
L931:   fload 8
L933:   fmul
L934:   fload_1
L935:   fmul
L936:   aload_0
L937:   getfield Field lG import F
L940:   fmul
L941:   ldc_w 1.6e0f
L944:   fmul
L945:   invokestatic Method org/lwjgl/opengl/GL11 else (FFFF)V
L948:   iload 5
L950:   iconst_1
L951:   dup
L952:   dup
L953:   pop2
L954:   iadd
L955:   i2f
L956:   aload_0
L957:   getfield Field lG true F
L960:   fmul
L961:   fload_3
L962:   invokestatic Method org/lwjgl/opengl/GL11 break (FF)V
L965:   fload 9
L967:   fload 15
L969:   fadd
L970:   fload 10
L972:   fload 15
L974:   fadd
L975:   fload 11
L977:   fload 15
L979:   fadd
L980:   fload 12
L982:   fload 8
L984:   fmul
L985:   fload_1
L986:   fmul
L987:   aload_0
L988:   getfield Field lG import F
L991:   fmul
L992:   ldc_w 1.6e0f
L995:   fmul
L996:   invokestatic Method org/lwjgl/opengl/GL11 else (FFFF)V
L999:   iload 5
L1001:  iconst_1
L1002:  dup
L1003:  dup
L1004:  pop2
L1005:  iadd
L1006:  i2f
L1007:  aload_0
L1008:  getfield Field lG true F
L1011:  fmul
L1012:  fload 4
L1014:  invokestatic Method org/lwjgl/opengl/GL11 break (FF)V
L1017:  invokestatic Method org/lwjgl/opengl/GL11 float ()V
L1020:  bipush 7
L1022:  iconst_1
L1023:  dup
L1024:  pop2
L1025:  invokestatic Method org/lwjgl/opengl/GL11 "strictfp" (I)V
L1028:  goto L1275
L1031:  athrow
L1032:  iload 7
L1034:  ifne L1103
L1037:  getstatic Field lG m [F
L1040:  iload 6
L1042:  bipush 31
L1044:  iconst_1
L1045:  dup
L1046:  pop2
L1047:  iand
L1048:  faload
L1049:  getstatic Field lG new [F
L1052:  iload 6
L1054:  bipush 31
L1056:  iconst_1
L1057:  dup
L1058:  pop2
L1059:  iand
L1060:  faload
L1061:  getstatic Field lG J [F
L1064:  iload 6
L1066:  bipush 31
L1068:  iconst_1
L1069:  dup
L1070:  pop2
L1071:  iand
L1072:  faload
L1073:  getstatic Field lG "transient" [F
L1076:  iload 6
L1078:  bipush 31
L1080:  iconst_1
L1081:  dup
L1082:  pop2
L1083:  iand
L1084:  faload
L1085:  fload 8
L1087:  fmul
L1088:  fload_1
L1089:  fmul
L1090:  aload_0
L1091:  getfield Field lG import F
L1094:  fmul
L1095:  invokestatic Method org/lwjgl/opengl/GL11 else (FFFF)V
L1098:  iload 5
L1100:  goto L1217
L1103:  getstatic Field lG m [F
L1106:  iload 6
L1108:  bipush 31
L1110:  iconst_1
L1111:  dup
L1112:  pop2
L1113:  iand
L1114:  faload
L1115:  getstatic Field lG m [F
L1118:  iload 7
L1120:  faload
L1121:  aload_0
L1122:  getfield Field lG "interface" [[F
L1125:  iload 5
L1127:  aaload
L1128:  iload_2
L1129:  faload
L1130:  fmul
L1131:  fsub
L1132:  getstatic Field lG new [F
L1135:  iload 6
L1137:  bipush 31
L1139:  iconst_1
L1140:  dup
L1141:  pop2
L1142:  iand
L1143:  faload
L1144:  getstatic Field lG new [F
L1147:  iload 7
L1149:  faload
L1150:  aload_0
L1151:  getfield Field lG "interface" [[F
L1154:  iload 5
L1156:  aaload
L1157:  iload_2
L1158:  faload
L1159:  fmul
L1160:  fsub
L1161:  getstatic Field lG J [F
L1164:  iload 6
L1166:  bipush 31
L1168:  iconst_1
L1169:  dup
L1170:  pop2
L1171:  iand
L1172:  faload
L1173:  getstatic Field lG J [F
L1176:  iload 7
L1178:  faload
L1179:  aload_0
L1180:  getfield Field lG "interface" [[F
L1183:  iload 5
L1185:  aaload
L1186:  iload_2
L1187:  faload
L1188:  fmul
L1189:  fsub
L1190:  getstatic Field lG "transient" [F
L1193:  iload 6
L1195:  bipush 31
L1197:  iconst_1
L1198:  dup
L1199:  pop2
L1200:  iand
L1201:  faload
L1202:  fload 8
L1204:  fmul
L1205:  fload_1
L1206:  fmul
L1207:  aload_0
L1208:  getfield Field lG import F
L1211:  fmul
L1212:  invokestatic Method org/lwjgl/opengl/GL11 else (FFFF)V
L1215:  iload 5
L1217:  i2f
L1218:  aload_0
L1219:  getfield Field lG true F
L1222:  fmul
L1223:  fload 4
L1225:  invokestatic Method org/lwjgl/opengl/GL11 break (FF)V
L1228:  iload 5
L1230:  iconst_1
L1231:  dup
L1232:  dup
L1233:  pop2
L1234:  iadd
L1235:  i2f
L1236:  aload_0
L1237:  getfield Field lG true F
L1240:  fmul
L1241:  fload 4
L1243:  invokestatic Method org/lwjgl/opengl/GL11 break (FF)V
L1246:  iload 5
L1248:  iconst_1
L1249:  dup
L1250:  dup
L1251:  pop2
L1252:  iadd
L1253:  i2f
L1254:  aload_0
L1255:  getfield Field lG true F
L1258:  fmul
L1259:  fload_3
L1260:  invokestatic Method org/lwjgl/opengl/GL11 break (FF)V
L1263:  iload 5
L1265:  i2f
L1266:  aload_0
L1267:  getfield Field lG true F
L1270:  fmul
L1271:  fload_3
L1272:  invokestatic Method org/lwjgl/opengl/GL11 break (FF)V
L1275:  iinc 5 1
L1278:  iload 5
L1280:  goto L214
L1283:  iinc 2 1
L1286:  iload_2
L1287:  goto L101
L1290:  invokestatic Method org/lwjgl/opengl/GL11 float ()V
L1293:  aload_0
L1294:  getfield Field lG instanceof Z
L1297:  ifeq L1897
L1300:  aload_0
L1301:  iconst_0
L1302:  dup_x1
L1303:  iconst_1
L1304:  dup
L1305:  pop2
L1306:  putfield Field lG instanceof Z
L1309:  iconst_1
L1310:  dup
L1311:  pop2
L1312:  dup
L1313:  istore_2
L1314:  aload_0
L1315:  getfield Field lG "synchronized" I
L1318:  if_icmpge L1379
L1321:  aload_0
L1322:  dup
L1323:  dup2
L1324:  getfield Field lG "abstract" [[I
L1327:  iload_2
L1328:  aaload
L1329:  iconst_0
L1330:  iconst_1
L1331:  dup
L1332:  pop2
L1333:  invokestatic Method java/util/Arrays fill ([II)V
L1336:  getfield Field lG D [[I
L1339:  iload_2
L1340:  aaload
L1341:  iconst_0
L1342:  iconst_1
L1343:  dup
L1344:  pop2
L1345:  invokestatic Method java/util/Arrays fill ([II)V
L1348:  getfield Field lG i [[I
L1351:  iload_2
L1352:  aaload
L1353:  iconst_0
L1354:  iconst_1
L1355:  dup
L1356:  pop2
L1357:  invokestatic Method java/util/Arrays fill ([II)V
L1360:  getfield Field lG b [[I
L1363:  iload_2
L1364:  iinc 2 1
L1367:  aaload
L1368:  iconst_0
L1369:  iconst_1
L1370:  dup
L1371:  pop2
L1372:  invokestatic Method java/util/Arrays fill ([II)V
L1375:  iload_2
L1376:  goto L1314
L1379:  iconst_0
L1380:  iconst_1
L1381:  dup
L1382:  pop2
L1383:  dup
L1384:  istore_2
L1385:  aload_0
L1386:  getfield Field lG case I
L1389:  if_icmpge L1897
L1392:  iconst_0
L1393:  iconst_1
L1394:  dup
L1395:  pop2
L1396:  dup
L1397:  istore_3
L1398:  aload_0
L1399:  getfield Field lG "synchronized" I
L1402:  if_icmpge L1890
L1405:  aload_0
L1406:  getfield Field lG continue [[I
L1409:  iload_3
L1410:  aaload
L1411:  iload_2
L1412:  iaload
L1413:  dup
L1414:  istore 4
L1416:  sipush 2048
L1419:  iconst_1
L1420:  dup
L1421:  pop2
L1422:  iand
L1423:  ifeq L1469
L1426:  iload 4
L1428:  bipush 31
L1430:  iconst_1
L1431:  dup
L1432:  pop2
L1433:  iand
L1434:  ifeq L1469
L1437:  aload_0
L1438:  dup
L1439:  getfield Field lG i [[I
L1442:  iload_3
L1443:  aaload
L1444:  iload_2
L1445:  iload 4
L1447:  bipush 31
L1449:  iconst_1
L1450:  dup
L1451:  pop2
L1452:  iand
L1453:  iastore
L1454:  getfield Field lG E [[F
L1457:  iload_3
L1458:  aaload
L1459:  aload_0
L1460:  getfield Field lG "interface" [[F
L1463:  iload_3
L1464:  aaload
L1465:  iload_2
L1466:  dup_x1
L1467:  faload
L1468:  fastore
L1469:  iload 4
L1471:  sipush 512
L1474:  iconst_1
L1475:  dup
L1476:  pop2
L1477:  iand
L1478:  ifeq L1524
L1481:  iload 4
L1483:  bipush 31
L1485:  iconst_1
L1486:  dup
L1487:  pop2
L1488:  iand
L1489:  ifeq L1524
L1492:  aload_0
L1493:  dup
L1494:  getfield Field lG b [[I
L1497:  iload_3
L1498:  aaload
L1499:  iload_2
L1500:  iload 4
L1502:  bipush 31
L1504:  iconst_1
L1505:  dup
L1506:  pop2
L1507:  iand
L1508:  iastore
L1509:  getfield Field lG "private" [[F
L1512:  iload_3
L1513:  aaload
L1514:  aload_0
L1515:  getfield Field lG "interface" [[F
L1518:  iload_3
L1519:  aaload
L1520:  iload_2
L1521:  dup_x1
L1522:  faload
L1523:  fastore
L1524:  aload_0
L1525:  getfield Field lG class [[I
L1528:  iload_3
L1529:  aaload
L1530:  iload_2
L1531:  iaload
L1532:  istore 5
L1534:  fconst_1
L1535:  fstore 6
L1537:  iload 5
L1539:  ifne L1604
L1542:  iload_3
L1543:  aload_0
L1544:  getfield Field lG finally I
L1547:  if_icmplt L1604
L1550:  iload_3
L1551:  aload_0
L1552:  getfield Field lG finally I
L1555:  iconst_4
L1556:  iconst_1
L1557:  dup
L1558:  pop2
L1559:  iadd
L1560:  if_icmpge L1604
L1563:  iload_2
L1564:  aload_0
L1565:  getfield Field lG "strictfp" I
L1568:  if_icmplt L1604
L1571:  iload_2
L1572:  aload_0
L1573:  getfield Field lG "strictfp" I
L1576:  iconst_4
L1577:  iconst_1
L1578:  dup
L1579:  pop2
L1580:  iadd
L1581:  if_icmpge L1604
L1584:  aload_0
L1585:  getfield Field lG I [[I
L1588:  iload_3
L1589:  aload_0
L1590:  getfield Field lG finally I
L1593:  isub
L1594:  aaload
L1595:  iload_2
L1596:  aload_0
L1597:  getfield Field lG "strictfp" I
L1600:  isub
L1601:  iaload
L1602:  istore 5
L1604:  iload 5
L1606:  ifne L1687
L1609:  aload_0
L1610:  getfield Field lG implements Z
L1613:  ifeq L1687
L1616:  iload_3
L1617:  aload_0
L1618:  getfield Field lG a I
L1621:  if_icmplt L1687
L1624:  iload_3
L1625:  aload_0
L1626:  getfield Field lG a I
L1629:  iconst_4
L1630:  iconst_1
L1631:  dup
L1632:  pop2
L1633:  iadd
L1634:  if_icmpge L1687
L1637:  iload_2
L1638:  aload_0
L1639:  getfield Field lG h I
L1642:  if_icmplt L1687
L1645:  iload_2
L1646:  aload_0
L1647:  getfield Field lG h I
L1650:  iconst_4
L1651:  iconst_1
L1652:  dup
L1653:  pop2
L1654:  iadd
L1655:  if_icmpge L1687
L1658:  aload_0
L1659:  getfield Field lG I [[I
L1662:  iload_3
L1663:  aload_0
L1664:  getfield Field lG a I
L1667:  isub
L1668:  aaload
L1669:  iload_2
L1670:  aload_0
L1671:  getfield Field lG h I
L1674:  isub
L1675:  iaload
L1676:  dup
L1677:  istore 5
L1679:  ifeq L1687
L1682:  ldc_w 3.5e-1f
L1685:  fstore 6
L1687:  iload 5
L1689:  sipush 256
L1692:  iconst_1
L1693:  dup
L1694:  pop2
L1695:  iand
L1696:  ifeq L1736
L1699:  iload 5
L1701:  bipush 31
L1703:  iconst_1
L1704:  dup
L1705:  pop2
L1706:  iand
L1707:  ifeq L1736
L1710:  aload_0
L1711:  dup
L1712:  getfield Field lG "abstract" [[I
L1715:  iload_3
L1716:  aaload
L1717:  iload_2
L1718:  iload 5
L1720:  bipush 31
L1722:  iconst_1
L1723:  dup
L1724:  pop2
L1725:  iand
L1726:  iastore
L1727:  getfield Field lG assert [[F
L1730:  iload_3
L1731:  aaload
L1732:  iload_2
L1733:  fload 6
L1735:  fastore
L1736:  iload 5
L1738:  sipush 1024
L1741:  iconst_1
L1742:  dup
L1743:  pop2
L1744:  iand
L1745:  ifeq L1785
L1748:  iload 5
L1750:  bipush 31
L1752:  iconst_1
L1753:  dup
L1754:  pop2
L1755:  iand
L1756:  ifeq L1785
L1759:  aload_0
L1760:  dup
L1761:  getfield Field lG D [[I
L1764:  iload_3
L1765:  aaload
L1766:  iload_2
L1767:  iload 5
L1769:  bipush 31
L1771:  iconst_1
L1772:  dup
L1773:  pop2
L1774:  iand
L1775:  iastore
L1776:  getfield Field lG e [[F
L1779:  iload_3
L1780:  aaload
L1781:  iload_2
L1782:  fload 6
L1784:  fastore
L1785:  iload 5
L1787:  sipush 2048
L1790:  iconst_1
L1791:  dup
L1792:  pop2
L1793:  iand
L1794:  ifeq L1834
L1797:  iload 5
L1799:  bipush 31
L1801:  iconst_1
L1802:  dup
L1803:  pop2
L1804:  iand
L1805:  ifeq L1834
L1808:  aload_0
L1809:  dup
L1810:  getfield Field lG i [[I
L1813:  iload_3
L1814:  aaload
L1815:  iload_2
L1816:  iload 5
L1818:  bipush 31
L1820:  iconst_1
L1821:  dup
L1822:  pop2
L1823:  iand
L1824:  iastore
L1825:  getfield Field lG E [[F
L1828:  iload_3
L1829:  aaload
L1830:  iload_2
L1831:  fload 6
L1833:  fastore
L1834:  iload 5
L1836:  sipush 512
L1839:  iconst_1
L1840:  dup
L1841:  pop2
L1842:  iand
L1843:  ifeq L1883
L1846:  iload 5
L1848:  bipush 31
L1850:  iconst_1
L1851:  dup
L1852:  pop2
L1853:  iand
L1854:  ifeq L1883
L1857:  aload_0
L1858:  dup
L1859:  getfield Field lG b [[I
L1862:  iload_3
L1863:  aaload
L1864:  iload_2
L1865:  iload 5
L1867:  bipush 31
L1869:  iconst_1
L1870:  dup
L1871:  pop2
L1872:  iand
L1873:  iastore
L1874:  getfield Field lG "private" [[F
L1877:  iload_3
L1878:  aaload
L1879:  iload_2
L1880:  fload 6
L1882:  fastore
L1883:  iinc 3 1
L1886:  iload_3
L1887:  goto L1398
L1890:  iinc 2 1
L1893:  iload_2
L1894:  goto L1385
L1897:  iconst_1
L1898:  dup
L1899:  dup
L1900:  pop2
L1901:  invokestatic Method org/lwjgl/opengl/GL11 "strictfp" (I)V
L1904:  aload_0
L1905:  getfield Field lG extends I
L1908:  dup
L1909:  istore_2
L1910:  aload_0
L1911:  getfield Field lG case I
L1914:  if_icmpge L2426
L1917:  iload_2
L1918:  i2f
L1919:  aload_0
L1920:  getfield Field lG try [F
L1923:  iload_2
L1924:  faload
L1925:  fsub
L1926:  aload_0
L1927:  getfield Field lG long F
L1930:  fadd
L1931:  aload_0
L1932:  getfield Field lG goto F
L1935:  fsub
L1936:  aload_0
L1937:  getfield Field lG "public" F
L1940:  fmul
L1941:  dup
L1942:  fstore_3
L1943:  aload_0
L1944:  getfield Field lG "public" F
L1947:  fadd
L1948:  dup
L1949:  fstore 4
L1951:  aload_0
L1952:  getfield Field lG extends I
L1955:  i2f
L1956:  aload_0
L1957:  getfield Field lG "public" F
L1960:  fmul
L1961:  ldc_w 1e-6f
L1964:  fadd
L1965:  fcmpl
L1966:  iflt L2419
L1969:  fload_3
L1970:  aload_0
L1971:  getfield Field lG break F
L1974:  fcmpg
L1975:  ifgt L2419
L1978:  fload_3
L1979:  aload_0
L1980:  getfield Field lG extends I
L1983:  i2f
L1984:  aload_0
L1985:  getfield Field lG "public" F
L1988:  fmul
L1989:  fcmpg
L1990:  ifge L2004
L1993:  aload_0
L1994:  getfield Field lG extends I
L1997:  i2f
L1998:  aload_0
L1999:  getfield Field lG "public" F
L2002:  fmul
L2003:  fstore_3
L2004:  fload 4
L2006:  aload_0
L2007:  getfield Field lG break F
L2010:  fcmpl
L2011:  ifle L2020
L2014:  aload_0
L2015:  getfield Field lG break F
L2018:  fstore 4
L2020:  fconst_0
L2021:  fstore 5
L2023:  iconst_0
L2024:  iconst_1
L2025:  dup
L2026:  pop2
L2027:  istore 6
L2029:  iconst_0
L2030:  iconst_1
L2031:  dup
L2032:  pop2
L2033:  dup
L2034:  istore 7
L2036:  aload_0
L2037:  getfield Field lG "synchronized" I
L2040:  if_icmpge L2202
L2043:  aload_0
L2044:  getfield Field lG "abstract" [[I
L2047:  iload 7
L2049:  aaload
L2050:  iload_2
L2051:  iaload
L2052:  iload 6
L2054:  if_icmpne L2072
L2057:  aload_0
L2058:  getfield Field lG assert [[F
L2061:  iload 7
L2063:  aaload
L2064:  iload_2
L2065:  faload
L2066:  fload 5
L2068:  fcmpl
L2069:  ifeq L2194
L2072:  iload 6
L2074:  ifeq L2089
L2077:  iload 7
L2079:  i2f
L2080:  aload_0
L2081:  getfield Field lG true F
L2084:  fmul
L2085:  fload_3
L2086:  invokestatic Method org/lwjgl/opengl/GL11 break (FF)V
L2089:  aload_0
L2090:  dup
L2091:  getfield Field lG "abstract" [[I
L2094:  iload 7
L2096:  aaload
L2097:  iload_2
L2098:  iaload
L2099:  istore 6
L2101:  getfield Field lG assert [[F
L2104:  iload 7
L2106:  aaload
L2107:  iload_2
L2108:  faload
L2109:  fstore 5
L2111:  iload 6
L2113:  ifeq L2194
L2116:  getstatic Field lG m [F
L2119:  iload 6
L2121:  bipush 31
L2123:  iconst_1
L2124:  dup
L2125:  pop2
L2126:  iand
L2127:  faload
L2128:  getstatic Field lG new [F
L2131:  iload 6
L2133:  bipush 31
L2135:  iconst_1
L2136:  dup
L2137:  pop2
L2138:  iand
L2139:  faload
L2140:  getstatic Field lG J [F
L2143:  iload 6
L2145:  bipush 31
L2147:  iconst_1
L2148:  dup
L2149:  pop2
L2150:  iand
L2151:  faload
L2152:  getstatic Field lG "transient" [F
L2155:  iload 6
L2157:  bipush 31
L2159:  iconst_1
L2160:  dup
L2161:  pop2
L2162:  iand
L2163:  faload
L2164:  fload 5
L2166:  fmul
L2167:  fload_1
L2168:  fmul
L2169:  aload_0
L2170:  getfield Field lG import F
L2173:  fmul
L2174:  aload_0
L2175:  getfield Field lG import F
L2178:  fmul
L2179:  invokestatic Method org/lwjgl/opengl/GL11 else (FFFF)V
L2182:  iload 7
L2184:  i2f
L2185:  aload_0
L2186:  getfield Field lG true F
L2189:  fmul
L2190:  fload_3
L2191:  invokestatic Method org/lwjgl/opengl/GL11 break (FF)V
L2194:  iinc 7 1
L2197:  iload 7
L2199:  goto L2036
L2202:  iload 6
L2204:  ifeq L2221
L2207:  aload_0
L2208:  getfield Field lG "synchronized" I
L2211:  i2f
L2212:  aload_0
L2213:  getfield Field lG true F
L2216:  fmul
L2217:  fload_3
L2218:  invokestatic Method org/lwjgl/opengl/GL11 break (FF)V
L2221:  fconst_1
L2222:  fstore 5
L2224:  iconst_0
L2225:  iconst_1
L2226:  dup
L2227:  pop2
L2228:  istore 6
L2230:  iconst_0
L2231:  iconst_1
L2232:  dup
L2233:  pop2
L2234:  dup
L2235:  istore 7
L2237:  aload_0
L2238:  getfield Field lG "synchronized" I
L2241:  if_icmpge L2405
L2244:  aload_0
L2245:  getfield Field lG D [[I
L2248:  iload 7
L2250:  aaload
L2251:  iload_2
L2252:  iaload
L2253:  iload 6
L2255:  if_icmpne L2273
L2258:  aload_0
L2259:  getfield Field lG e [[F
L2262:  iload 7
L2264:  aaload
L2265:  iload_2
L2266:  faload
L2267:  fload 5
L2269:  fcmpl
L2270:  ifeq L2397
L2273:  iload 6
L2275:  ifeq L2291
L2278:  iload 7
L2280:  i2f
L2281:  aload_0
L2282:  getfield Field lG true F
L2285:  fmul
L2286:  fload 4
L2288:  invokestatic Method org/lwjgl/opengl/GL11 break (FF)V
L2291:  aload_0
L2292:  dup
L2293:  getfield Field lG D [[I
L2296:  iload 7
L2298:  aaload
L2299:  iload_2
L2300:  iaload
L2301:  istore 6
L2303:  getfield Field lG e [[F
L2306:  iload 7
L2308:  aaload
L2309:  iload_2
L2310:  faload
L2311:  fstore 5
L2313:  iload 6
L2315:  ifeq L2397
L2318:  getstatic Field lG m [F
L2321:  iload 6
L2323:  bipush 31
L2325:  iconst_1
L2326:  dup
L2327:  pop2
L2328:  iand
L2329:  faload
L2330:  getstatic Field lG new [F
L2333:  iload 6
L2335:  bipush 31
L2337:  iconst_1
L2338:  dup
L2339:  pop2
L2340:  iand
L2341:  faload
L2342:  getstatic Field lG J [F
L2345:  iload 6
L2347:  bipush 31
L2349:  iconst_1
L2350:  dup
L2351:  pop2
L2352:  iand
L2353:  faload
L2354:  getstatic Field lG "transient" [F
L2357:  iload 6
L2359:  bipush 31
L2361:  iconst_1
L2362:  dup
L2363:  pop2
L2364:  iand
L2365:  faload
L2366:  fload 5
L2368:  fmul
L2369:  fload_1
L2370:  fmul
L2371:  aload_0
L2372:  getfield Field lG import F
L2375:  fmul
L2376:  aload_0
L2377:  getfield Field lG import F
L2380:  fmul
L2381:  invokestatic Method org/lwjgl/opengl/GL11 else (FFFF)V
L2384:  iload 7
L2386:  i2f
L2387:  aload_0
L2388:  getfield Field lG true F
L2391:  fmul
L2392:  fload 4
L2394:  invokestatic Method org/lwjgl/opengl/GL11 break (FF)V
L2397:  iinc 7 1
L2400:  iload 7
L2402:  goto L2237
L2405:  iload 6
L2407:  ifeq L2419
L2410:  aload_0
L2411:  getfield Field lG catch F
L2414:  fload 4
L2416:  invokestatic Method org/lwjgl/opengl/GL11 break (FF)V
L2419:  iinc 2 1
L2422:  iload_2
L2423:  goto L1910
L2426:  iconst_0
L2427:  iconst_1
L2428:  dup
L2429:  pop2
L2430:  dup
L2431:  istore_2
L2432:  aload_0
L2433:  getfield Field lG "synchronized" I
L2436:  if_icmpge L3065
L2439:  fconst_1
L2440:  fstore_3
L2441:  iconst_0
L2442:  iconst_1
L2443:  dup
L2444:  pop2
L2445:  istore 4
L2447:  aload_0
L2448:  getfield Field lG extends I
L2451:  dup
L2452:  istore 5
L2454:  aload_0
L2455:  getfield Field lG case I
L2458:  if_icmpge L2722
L2461:  iload 5
L2463:  i2f
L2464:  aload_0
L2465:  getfield Field lG try [F
L2468:  iload 5
L2470:  faload
L2471:  fsub
L2472:  aload_0
L2473:  getfield Field lG long F
L2476:  fadd
L2477:  aload_0
L2478:  getfield Field lG goto F
L2481:  fsub
L2482:  aload_0
L2483:  getfield Field lG "public" F
L2486:  fmul
L2487:  dup
L2488:  fstore 6
L2490:  aload_0
L2491:  getfield Field lG "public" F
L2494:  fadd
L2495:  dup
L2496:  fstore 7
L2498:  aload_0
L2499:  getfield Field lG extends I
L2502:  i2f
L2503:  aload_0
L2504:  getfield Field lG "public" F
L2507:  fmul
L2508:  fcmpl
L2509:  iflt L2714
L2512:  fload 6
L2514:  aload_0
L2515:  getfield Field lG break F
L2518:  fcmpg
L2519:  ifgt L2714
L2522:  fload 6
L2524:  aload_0
L2525:  getfield Field lG extends I
L2528:  i2f
L2529:  aload_0
L2530:  getfield Field lG "public" F
L2533:  fmul
L2534:  fcmpg
L2535:  ifge L2550
L2538:  aload_0
L2539:  getfield Field lG extends I
L2542:  i2f
L2543:  aload_0
L2544:  getfield Field lG "public" F
L2547:  fmul
L2548:  fstore 6
L2550:  fload 7
L2552:  aload_0
L2553:  getfield Field lG break F
L2556:  fcmpl
L2557:  ifle L2566
L2560:  aload_0
L2561:  getfield Field lG break F
L2564:  fstore 7
L2566:  aload_0
L2567:  getfield Field lG i [[I
L2570:  iload_2
L2571:  aaload
L2572:  iload 5
L2574:  iaload
L2575:  iload 4
L2577:  if_icmpne L2594
L2580:  aload_0
L2581:  getfield Field lG E [[F
L2584:  iload_2
L2585:  aaload
L2586:  iload 5
L2588:  faload
L2589:  fload_3
L2590:  fcmpl
L2591:  ifeq L2714
L2594:  iload 4
L2596:  ifeq L2611
L2599:  iload_2
L2600:  i2f
L2601:  aload_0
L2602:  getfield Field lG true F
L2605:  fmul
L2606:  fload 6
L2608:  invokestatic Method org/lwjgl/opengl/GL11 break (FF)V
L2611:  aload_0
L2612:  dup
L2613:  getfield Field lG i [[I
L2616:  iload_2
L2617:  aaload
L2618:  iload 5
L2620:  iaload
L2621:  istore 4
L2623:  getfield Field lG E [[F
L2626:  iload_2
L2627:  aaload
L2628:  iload 5
L2630:  faload
L2631:  fstore_3
L2632:  iload 4
L2634:  ifeq L2714
L2637:  getstatic Field lG m [F
L2640:  iload 4
L2642:  bipush 31
L2644:  iconst_1
L2645:  dup
L2646:  pop2
L2647:  iand
L2648:  faload
L2649:  getstatic Field lG new [F
L2652:  iload 4
L2654:  bipush 31
L2656:  iconst_1
L2657:  dup
L2658:  pop2
L2659:  iand
L2660:  faload
L2661:  getstatic Field lG J [F
L2664:  iload 4
L2666:  bipush 31
L2668:  iconst_1
L2669:  dup
L2670:  pop2
L2671:  iand
L2672:  faload
L2673:  getstatic Field lG "transient" [F
L2676:  iload 4
L2678:  bipush 31
L2680:  iconst_1
L2681:  dup
L2682:  pop2
L2683:  iand
L2684:  faload
L2685:  fload_3
L2686:  fmul
L2687:  fload_1
L2688:  fmul
L2689:  aload_0
L2690:  getfield Field lG import F
L2693:  fmul
L2694:  aload_0
L2695:  getfield Field lG import F
L2698:  fmul
L2699:  invokestatic Method org/lwjgl/opengl/GL11 else (FFFF)V
L2702:  iload_2
L2703:  i2f
L2704:  aload_0
L2705:  getfield Field lG true F
L2708:  fmul
L2709:  fload 6
L2711:  invokestatic Method org/lwjgl/opengl/GL11 break (FF)V
L2714:  iinc 5 1
L2717:  iload 5
L2719:  goto L2454
L2722:  iload 4
L2724:  ifeq L2741
L2727:  iload_2
L2728:  i2f
L2729:  aload_0
L2730:  getfield Field lG true F
L2733:  fmul
L2734:  aload_0
L2735:  getfield Field lG break F
L2738:  invokestatic Method org/lwjgl/opengl/GL11 break (FF)V
L2741:  fconst_1
L2742:  fstore_3
L2743:  iconst_0
L2744:  iconst_1
L2745:  dup
L2746:  pop2
L2747:  istore 4
L2749:  aload_0
L2750:  getfield Field lG extends I
L2753:  dup
L2754:  istore 5
L2756:  aload_0
L2757:  getfield Field lG case I
L2760:  if_icmpge L3034
L2763:  iload 5
L2765:  i2f
L2766:  aload_0
L2767:  getfield Field lG try [F
L2770:  iload 5
L2772:  faload
L2773:  fsub
L2774:  aload_0
L2775:  getfield Field lG long F
L2778:  fadd
L2779:  aload_0
L2780:  getfield Field lG goto F
L2783:  fsub
L2784:  aload_0
L2785:  getfield Field lG "public" F
L2788:  fmul
L2789:  dup
L2790:  fstore 6
L2792:  aload_0
L2793:  getfield Field lG "public" F
L2796:  fadd
L2797:  dup
L2798:  fstore 7
L2800:  aload_0
L2801:  getfield Field lG extends I
L2804:  i2f
L2805:  aload_0
L2806:  getfield Field lG "public" F
L2809:  fmul
L2810:  fcmpl
L2811:  iflt L3026
L2814:  fload 6
L2816:  aload_0
L2817:  getfield Field lG break F
L2820:  fcmpg
L2821:  ifgt L3026
L2824:  fload 6
L2826:  aload_0
L2827:  getfield Field lG extends I
L2830:  i2f
L2831:  aload_0
L2832:  getfield Field lG "public" F
L2835:  fmul
L2836:  fcmpg
L2837:  ifge L2852
L2840:  aload_0
L2841:  getfield Field lG extends I
L2844:  i2f
L2845:  aload_0
L2846:  getfield Field lG "public" F
L2849:  fmul
L2850:  fstore 6
L2852:  fload 7
L2854:  aload_0
L2855:  getfield Field lG break F
L2858:  fcmpl
L2859:  ifle L2868
L2862:  aload_0
L2863:  getfield Field lG break F
L2866:  fstore 7
L2868:  aload_0
L2869:  getfield Field lG b [[I
L2872:  iload_2
L2873:  aaload
L2874:  iload 5
L2876:  iaload
L2877:  iload 4
L2879:  if_icmpne L2896
L2882:  aload_0
L2883:  getfield Field lG "private" [[F
L2886:  iload_2
L2887:  aaload
L2888:  iload 5
L2890:  faload
L2891:  fload_3
L2892:  fcmpl
L2893:  ifeq L3026
L2896:  iload 4
L2898:  ifeq L2918
L2901:  iload_2
L2902:  iconst_1
L2903:  dup
L2904:  dup
L2905:  pop2
L2906:  iadd
L2907:  i2f
L2908:  aload_0
L2909:  getfield Field lG true F
L2912:  fmul
L2913:  fload 6
L2915:  invokestatic Method org/lwjgl/opengl/GL11 break (FF)V
L2918:  aload_0
L2919:  dup
L2920:  getfield Field lG b [[I
L2923:  iload_2
L2924:  aaload
L2925:  iload 5
L2927:  iaload
L2928:  istore 4
L2930:  getfield Field lG "private" [[F
L2933:  iload_2
L2934:  aaload
L2935:  iload 5
L2937:  faload
L2938:  fstore_3
L2939:  iload 4
L2941:  ifeq L3026
L2944:  getstatic Field lG m [F
L2947:  iload 4
L2949:  bipush 31
L2951:  iconst_1
L2952:  dup
L2953:  pop2
L2954:  iand
L2955:  faload
L2956:  getstatic Field lG new [F
L2959:  iload 4
L2961:  bipush 31
L2963:  iconst_1
L2964:  dup
L2965:  pop2
L2966:  iand
L2967:  faload
L2968:  getstatic Field lG J [F
L2971:  iload 4
L2973:  bipush 31
L2975:  iconst_1
L2976:  dup
L2977:  pop2
L2978:  iand
L2979:  faload
L2980:  getstatic Field lG "transient" [F
L2983:  iload 4
L2985:  bipush 31
L2987:  iconst_1
L2988:  dup
L2989:  pop2
L2990:  iand
L2991:  faload
L2992:  fload_3
L2993:  fmul
L2994:  fload_1
L2995:  fmul
L2996:  aload_0
L2997:  getfield Field lG import F
L3000:  fmul
L3001:  aload_0
L3002:  getfield Field lG import F
L3005:  fmul
L3006:  invokestatic Method org/lwjgl/opengl/GL11 else (FFFF)V
L3009:  iload_2
L3010:  iconst_1
L3011:  dup
L3012:  dup
L3013:  pop2
L3014:  iadd
L3015:  i2f
L3016:  aload_0
L3017:  getfield Field lG true F
L3020:  fmul
L3021:  fload 6
L3023:  invokestatic Method org/lwjgl/opengl/GL11 break (FF)V
L3026:  iinc 5 1
L3029:  iload 5
L3031:  goto L2756
L3034:  iload 4
L3036:  ifeq L3058
L3039:  iload_2
L3040:  iconst_1
L3041:  dup
L3042:  dup
L3043:  pop2
L3044:  iadd
L3045:  i2f
L3046:  aload_0
L3047:  getfield Field lG true F
L3050:  fmul
L3051:  aload_0
L3052:  getfield Field lG break F
L3055:  invokestatic Method org/lwjgl/opengl/GL11 break (FF)V
L3058:  iinc 2 1
L3061:  iload_2
L3062:  goto L2432
L3065:  invokestatic Method org/lwjgl/opengl/GL11 float ()V
L3068:  aload_0
L3069:  getfield Field lG extends I
L3072:  dup
L3073:  istore_2
L3074:  aload_0
L3075:  getfield Field lG case I
L3078:  if_icmpge L3312
L3081:  iload_2
L3082:  aload_0
L3083:  getfield Field lG case I
L3086:  iconst_1
L3087:  dup
L3088:  dup
L3089:  pop2
L3090:  isub
L3091:  if_icmpne L3100
L3094:  fconst_0
L3095:  fstore_3
L3096:  aload_0
L3097:  goto L3113
L3100:  aload_0
L3101:  dup
L3102:  getfield Field lG try [F
L3105:  iload_2
L3106:  iconst_1
L3107:  dup
L3108:  dup
L3109:  pop2
L3110:  iadd
L3111:  faload
L3112:  fstore_3
L3113:  getfield Field lG try [F
L3116:  iload_2
L3117:  faload
L3118:  fload_3
L3119:  fcmpl
L3120:  ifle L3305
L3123:  iload_2
L3124:  iconst_1
L3125:  dup
L3126:  dup
L3127:  pop2
L3128:  iadd
L3129:  i2f
L3130:  aload_0
L3131:  getfield Field lG try [F
L3134:  iload_2
L3135:  faload
L3136:  fsub
L3137:  aload_0
L3138:  getfield Field lG long F
L3141:  fadd
L3142:  aload_0
L3143:  getfield Field lG goto F
L3146:  fsub
L3147:  aload_0
L3148:  getfield Field lG "public" F
L3151:  fmul
L3152:  fstore 4
L3154:  iload_2
L3155:  iconst_1
L3156:  dup
L3157:  dup
L3158:  pop2
L3159:  iadd
L3160:  i2f
L3161:  fload_3
L3162:  fsub
L3163:  aload_0
L3164:  getfield Field lG long F
L3167:  fadd
L3168:  aload_0
L3169:  getfield Field lG goto F
L3172:  fsub
L3173:  aload_0
L3174:  getfield Field lG "public" F
L3177:  fmul
L3178:  dup
L3179:  fstore 5
L3181:  aload_0
L3182:  getfield Field lG extends I
L3185:  i2f
L3186:  aload_0
L3187:  getfield Field lG "public" F
L3190:  fmul
L3191:  fcmpl
L3192:  iflt L3305
L3195:  fload 4
L3197:  aload_0
L3198:  getfield Field lG break F
L3201:  fcmpg
L3202:  ifgt L3305
L3205:  fload 4
L3207:  aload_0
L3208:  getfield Field lG extends I
L3211:  i2f
L3212:  aload_0
L3213:  getfield Field lG "public" F
L3216:  fmul
L3217:  fcmpg
L3218:  ifge L3233
L3221:  aload_0
L3222:  getfield Field lG extends I
L3225:  i2f
L3226:  aload_0
L3227:  getfield Field lG "public" F
L3230:  fmul
L3231:  fstore 4
L3233:  fload 5
L3235:  aload_0
L3236:  getfield Field lG break F
L3239:  fcmpl
L3240:  ifle L3249
L3243:  aload_0
L3244:  getfield Field lG break F
L3247:  fstore 5
L3249:  fconst_1
L3250:  dup
L3251:  dup
L3252:  ldc 7e-1f
L3254:  fload_1
L3255:  fmul
L3256:  aload_0
L3257:  getfield Field lG import F
L3260:  fmul
L3261:  invokestatic Method org/lwjgl/opengl/GL11 else (FFFF)V
L3264:  bipush 7
L3266:  iconst_1
L3267:  dup
L3268:  pop2
L3269:  invokestatic Method org/lwjgl/opengl/GL11 "strictfp" (I)V
L3272:  fconst_0
L3273:  fload 4
L3275:  invokestatic Method org/lwjgl/opengl/GL11 break (FF)V
L3278:  fconst_0
L3279:  fload 5
L3281:  invokestatic Method org/lwjgl/opengl/GL11 break (FF)V
L3284:  aload_0
L3285:  dup
L3286:  getfield Field lG catch F
L3289:  fload 5
L3291:  invokestatic Method org/lwjgl/opengl/GL11 break (FF)V
L3294:  getfield Field lG catch F
L3297:  fload 4
L3299:  invokestatic Method org/lwjgl/opengl/GL11 break (FF)V
L3302:  invokestatic Method org/lwjgl/opengl/GL11 float ()V
L3305:  iinc 2 1
L3308:  iload_2
L3309:  goto L3074
L3312:  aload_0
L3313:  getfield Field lG boolean F
L3316:  fconst_0
L3317:  fcmpl
L3318:  ifne L3330
L3321:  aload_0
L3322:  getfield Field lG A F
L3325:  fconst_0
L3326:  fcmpl
L3327:  ifeq L3354
L3330:  aload_0
L3331:  getfield Field lG boolean F
L3334:  fneg
L3335:  aload_0
L3336:  getfield Field lG true F
L3339:  fmul
L3340:  aload_0
L3341:  getfield Field lG A F
L3344:  fneg
L3345:  aload_0
L3346:  getfield Field lG "public" F
L3349:  fmul
L3350:  fconst_0
L3351:  invokestatic Method org/lwjgl/opengl/GL11 const (FFF)V
L3354:  sipush 770
L3357:  iconst_1
L3358:  dup
L3359:  pop2
L3360:  sipush 771
L3363:  iconst_1
L3364:  dup
L3365:  pop2
L3366:  invokestatic Method org/lwjgl/opengl/GL11 char (II)V
L3369:  return
L3370:  
        .attribute StackMap b'\x00\x4E\x00\x1E\x00\x02\x07\x00\x02\x02\x00\x00\x00\x1F\x00\x00\x00\x01\x07\x00\xBF\x00\x20\x00\x02\x07\x00\x02\x02\x00\x00\x00\x32\x00\x02\x07\x00\x02\x02\x00\x00\x00\x4A\x00\x02\x07\x00\x02\x02\x00\x00\x00\x65\x00\x03\x07\x00\x02\x02\x01\x00\x01\x01\x00\xBF\x00\x05\x07\x00\x02\x02\x01\x02\x02\x00\x00\x00\xCF\x00\x05\x07\x00\x02\x02\x01\x02\x02\x00\x00\x00\xD6\x00\x06\x07\x00\x02\x02\x01\x02\x02\x01\x00\x01\x01\x01\x43\x00\x09\x07\x00\x02\x02\x01\x02\x02\x01\x01\x01\x02\x00\x00\x01\x9C\x00\x09\x07\x00\x02\x02\x01\x02\x02\x01\x01\x01\x02\x00\x00\x02\x27\x00\x09\x07\x00\x02\x02\x01\x02\x02\x01\x01\x01\x02\x00\x00\x02\x5F\x00\x09\x07\x00\x02\x02\x01\x02\x02\x01\x01\x01\x02\x00\x00\x02\xDB\x00\x0D\x07\x00\x02\x02\x01\x02\x02\x01\x01\x01\x02\x02\x02\x02\x02\x00\x00\x04\x07\x00\x00\x00\x01\x07\x00\xBF\x04\x08\x00\x09\x07\x00\x02\x02\x01\x02\x02\x01\x01\x01\x02\x00\x00\x04\x4F\x00\x09\x07\x00\x02\x02\x01\x02\x02\x01\x01\x01\x02\x00\x00\x04\xC1\x00\x09\x07\x00\x02\x02\x01\x02\x02\x01\x01\x01\x02\x00\x01\x01\x04\xFB\x00\x09\x07\x00\x02\x02\x01\x02\x02\x01\x01\x01\x02\x00\x00\x05\x03\x00\x05\x07\x00\x02\x02\x01\x02\x02\x00\x00\x05\x0A\x00\x03\x07\x00\x02\x02\x01\x00\x00\x05\x22\x00\x03\x07\x00\x02\x02\x01\x00\x01\x01\x05\x63\x00\x03\x07\x00\x02\x02\x01\x00\x00\x05\x69\x00\x03\x07\x00\x02\x02\x01\x00\x01\x01\x05\x76\x00\x04\x07\x00\x02\x02\x01\x01\x00\x01\x01\x05\xBD\x00\x05\x07\x00\x02\x02\x01\x01\x01\x00\x00\x05\xF4\x00\x05\x07\x00\x02\x02\x01\x01\x01\x00\x00\x06\x44\x00\x07\x07\x00\x02\x02\x01\x01\x01\x01\x02\x00\x00\x06\x97\x00\x07\x07\x00\x02\x02\x01\x01\x01\x01\x02\x00\x00\x06\xC8\x00\x07\x07\x00\x02\x02\x01\x01\x01\x01\x02\x00\x00\x06\xF9\x00\x07\x07\x00\x02\x02\x01\x01\x01\x01\x02\x00\x00\x07\x2A\x00\x07\x07\x00\x02\x02\x01\x01\x01\x01\x02\x00\x00\x07\x5B\x00\x07\x07\x00\x02\x02\x01\x01\x01\x01\x02\x00\x00\x07\x62\x00\x04\x07\x00\x02\x02\x01\x01\x00\x00\x07\x69\x00\x03\x07\x00\x02\x02\x01\x00\x00\x07\x76\x00\x03\x07\x00\x02\x02\x01\x00\x01\x01\x07\xD4\x00\x05\x07\x00\x02\x02\x01\x02\x02\x00\x00\x07\xE4\x00\x05\x07\x00\x02\x02\x01\x02\x02\x00\x00\x07\xF4\x00\x08\x07\x00\x02\x02\x01\x02\x02\x02\x01\x01\x00\x01\x01\x08\x18\x00\x08\x07\x00\x02\x02\x01\x02\x02\x02\x01\x01\x00\x00\x08\x29\x00\x08\x07\x00\x02\x02\x01\x02\x02\x02\x01\x01\x00\x00\x08\x92\x00\x08\x07\x00\x02\x02\x01\x02\x02\x02\x01\x01\x00\x00\x08\x9A\x00\x08\x07\x00\x02\x02\x01\x02\x02\x02\x01\x01\x00\x00\x08\xAD\x00\x08\x07\x00\x02\x02\x01\x02\x02\x02\x01\x01\x00\x00\x08\xBD\x00\x08\x07\x00\x02\x02\x01\x02\x02\x02\x01\x01\x00\x01\x01\x08\xE1\x00\x08\x07\x00\x02\x02\x01\x02\x02\x02\x01\x01\x00\x00\x08\xF3\x00\x08\x07\x00\x02\x02\x01\x02\x02\x02\x01\x01\x00\x00\x09\x5D\x00\x08\x07\x00\x02\x02\x01\x02\x02\x02\x01\x01\x00\x00\x09\x65\x00\x08\x07\x00\x02\x02\x01\x02\x02\x02\x01\x01\x00\x00\x09\x73\x00\x05\x07\x00\x02\x02\x01\x02\x02\x00\x00\x09\x7A\x00\x03\x07\x00\x02\x02\x01\x00\x00\x09\x80\x00\x03\x07\x00\x02\x02\x01\x00\x01\x01\x09\x96\x00\x06\x07\x00\x02\x02\x01\x02\x01\x01\x00\x01\x01\x09\xF6\x00\x08\x07\x00\x02\x02\x01\x02\x01\x01\x02\x02\x00\x00\x0A\x06\x00\x08\x07\x00\x02\x02\x01\x02\x01\x01\x02\x02\x00\x00\x0A\x22\x00\x08\x07\x00\x02\x02\x01\x02\x01\x01\x02\x02\x00\x00\x0A\x33\x00\x08\x07\x00\x02\x02\x01\x02\x01\x01\x02\x02\x00\x00\x0A\x9A\x00\x08\x07\x00\x02\x02\x01\x02\x01\x01\x02\x02\x00\x00\x0A\xA2\x00\x06\x07\x00\x02\x02\x01\x02\x01\x01\x00\x00\x0A\xB5\x00\x06\x07\x00\x02\x02\x01\x02\x01\x01\x00\x00\x0A\xC4\x00\x06\x07\x00\x02\x02\x01\x02\x01\x01\x00\x01\x01\x0B\x24\x00\x08\x07\x00\x02\x02\x01\x02\x01\x01\x02\x02\x00\x00\x0B\x34\x00\x08\x07\x00\x02\x02\x01\x02\x01\x01\x02\x02\x00\x00\x0B\x50\x00\x08\x07\x00\x02\x02\x01\x02\x01\x01\x02\x02\x00\x00\x0B\x66\x00\x08\x07\x00\x02\x02\x01\x02\x01\x01\x02\x02\x00\x00\x0B\xD2\x00\x08\x07\x00\x02\x02\x01\x02\x01\x01\x02\x02\x00\x00\x0B\xDA\x00\x06\x07\x00\x02\x02\x01\x02\x01\x01\x00\x00\x0B\xF2\x00\x06\x07\x00\x02\x02\x01\x02\x01\x01\x00\x00\x0B\xF9\x00\x03\x07\x00\x02\x02\x01\x00\x00\x0C\x02\x00\x03\x07\x00\x02\x02\x01\x00\x01\x01\x0C\x1C\x00\x03\x07\x00\x02\x02\x01\x00\x00\x0C\x29\x00\x04\x07\x00\x02\x02\x01\x02\x00\x01\x07\x00\x02\x0C\xA1\x00\x06\x07\x00\x02\x02\x01\x02\x02\x02\x00\x00\x0C\xB1\x00\x06\x07\x00\x02\x02\x01\x02\x02\x02\x00\x00\x0C\xE9\x00\x04\x07\x00\x02\x02\x01\x02\x00\x00\x0C\xF0\x00\x03\x07\x00\x02\x02\x01\x00\x00\x0D\x02\x00\x03\x07\x00\x02\x02\x01\x00\x00\x0D\x1A\x00\x03\x07\x00\x02\x02\x01\x00\x00'
    .end code
.end method

.method public float : (I)V
    .code stack 4 locals 2
L0:     iconst_1
L1:     aload_0
L2:     dup_x1
L3:     iload_1
L4:     putfield Field lG extends I
L7:     iconst_1
L8:     dup
L9:     pop2
L10:    putfield Field lG C Z
L13:    return
L14:    
    .end code
.end method

.method public break : ()I
    .code stack 1 locals 1
L0:     aload_0
L1:     getfield Field lG while I
L4:     ireturn
L5:     
    .end code
.end method

.method public else : (Z)V
    .code stack 4 locals 2
L0:     iconst_1
L1:     aload_0
L2:     dup_x1
L3:     iload_1
L4:     putfield Field lG implements Z
L7:     iconst_1
L8:     dup
L9:     pop2
L10:    putfield Field lG C Z
L13:    return
L14:    
    .end code
.end method

.method public break : ([[I)V
    .code stack 6 locals 3
L0:     iconst_0
L1:     iconst_1
L2:     dup
L3:     pop2
L4:     dup
L5:     istore_2
L6:     aload_0
L7:     getfield Field lG "synchronized" I
L10:    if_icmpge L34
L13:    aload_0
L14:    getfield Field lG class [[I
L17:    iload_2
L18:    iinc 2 1
L21:    aaload
L22:    iconst_0
L23:    iconst_1
L24:    dup
L25:    pop2
L26:    invokestatic Method java/util/Arrays fill ([II)V
L29:    iload_2
L30:    goto L6
L33:    athrow
L34:    iconst_0
L35:    iconst_1
L36:    dup
L37:    pop2
L38:    dup
L39:    istore_2
L40:    aload_1
L41:    arraylength
L42:    if_icmpge L77
L45:    aload_1
L46:    iload_2
L47:    aaload
L48:    iconst_1
L49:    dup
L50:    pop2
L51:    aload_0
L52:    getfield Field lG class [[I
L55:    iload_2
L56:    aaload
L57:    iconst_0
L58:    dup_x1
L59:    iconst_1
L60:    dup
L61:    pop2
L62:    aload_1
L63:    iload_2
L64:    iinc 2 1
L67:    aaload
L68:    arraylength
L69:    invokestatic Method java/lang/System arraycopy (Ljava/lang/Object;ILjava/lang/Object;II)V
L72:    iload_2
L73:    goto L40
L76:    athrow
L77:    aload_0
L78:    aload_0
L79:    iconst_1
L80:    dup
L81:    dup_x2
L82:    dup
L83:    pop2
L84:    putfield Field lG instanceof Z
L87:    iconst_1
L88:    dup
L89:    pop2
L90:    putfield Field lG C Z
L93:    return
L94:    
        .attribute StackMap b'\x00\x06\x00\x06\x00\x03\x07\x00\x02\x07\x00\x86\x01\x00\x01\x01\x00\x21\x00\x00\x00\x01\x07\x00\xBF\x00\x22\x00\x03\x07\x00\x02\x07\x00\x86\x01\x00\x00\x00\x28\x00\x03\x07\x00\x02\x07\x00\x86\x01\x00\x01\x01\x00\x4C\x00\x00\x00\x01\x07\x00\xBF\x00\x4D\x00\x03\x07\x00\x02\x07\x00\x86\x01\x00\x00'
    .end code
.end method

.method public else : (FFF)V
    .code stack 6 locals 4
L0:     fload_3
L1:     aload_0
L2:     dup_x1
L3:     fload_2
L4:     aload_0
L5:     fload_1
L6:     putfield Field lG k F
L9:     putfield Field lG "protected" F
L12:    putfield Field lG this F
L15:    return
L16:    
    .end code
.end method

.method public else : (I)V
    .code stack 8 locals 6
L0:     aload_0
L1:     getfield Field lG true F
L4:     f2d
L5:     ldc2_w 5e-2
L8:     dcmpg
L9:     ifge L14
L12:    return
L13:    athrow
L14:    iconst_0
L15:    iconst_1
L16:    dup
L17:    pop2
L18:    istore_2
L19:    iconst_0
L20:    iconst_1
L21:    dup
L22:    pop2
L23:    dup
L24:    istore_3
L25:    iconst_4
L26:    iconst_1
L27:    dup
L28:    pop2
L29:    if_icmpge L83
L32:    iconst_0
L33:    iconst_1
L34:    dup
L35:    pop2
L36:    dup
L37:    istore 4
L39:    iconst_4
L40:    iconst_1
L41:    dup
L42:    pop2
L43:    if_icmpge L76
L46:    aload_0
L47:    getfield Field lG I [[I
L50:    iload 4
L52:    aaload
L53:    iload_3
L54:    iaload
L55:    ifeq L67
L58:    iload 4
L60:    iload_2
L61:    if_icmple L67
L64:    iload 4
L66:    istore_2
L67:    iinc 4 1
L70:    iload 4
L72:    goto L39
L75:    athrow
L76:    iinc 3 1
L79:    iload_3
L80:    goto L25
L83:    iconst_0
L84:    iconst_1
L85:    dup
L86:    pop2
L87:    dup
L88:    istore_3
L89:    iconst_4
L90:    iconst_1
L91:    dup
L92:    pop2
L93:    if_icmpge L351
L96:    iconst_0
L97:    iconst_1
L98:    dup
L99:    pop2
L100:   dup
L101:   istore 4
L103:   iconst_4
L104:   iconst_1
L105:   dup
L106:   pop2
L107:   if_icmpge L344
L110:   aload_0
L111:   getfield Field lG I [[I
L114:   iload 4
L116:   aaload
L117:   iload_3
L118:   iaload
L119:   ifeq L336
L122:   iload 4
L124:   aload_0
L125:   getfield Field lG finally I
L128:   iadd
L129:   iflt L336
L132:   iload 4
L134:   aload_0
L135:   getfield Field lG finally I
L138:   iadd
L139:   bipush 10
L141:   iconst_1
L142:   dup
L143:   pop2
L144:   if_icmpge L336
L147:   aload_0
L148:   getfield Field lG "strictfp" I
L151:   dup
L152:   istore 5
L154:   iload_1
L155:   if_icmpge L336
L158:   iload_3
L159:   iload 5
L161:   iadd
L162:   ifle L328
L165:   iload_3
L166:   iload 5
L168:   iadd
L169:   aload_0
L170:   getfield Field lG case I
L173:   if_icmpge L328
L176:   iload_3
L177:   iload 5
L179:   iadd
L180:   iload_1
L181:   if_icmplt L201
L184:   aload_0
L185:   getfield Field lG I [[I
L188:   iload 4
L190:   aaload
L191:   iload_3
L192:   iload 5
L194:   iadd
L195:   iload_1
L196:   isub
L197:   iaload
L198:   ifne L328
L201:   aload_0
L202:   dup
L203:   getfield Field lG "interface" [[F
L206:   iload 4
L208:   aload_0
L209:   getfield Field lG finally I
L212:   iadd
L213:   aaload
L214:   iload_3
L215:   iload 5
L217:   iadd
L218:   ldc_w 5e-1f
L221:   dup
L222:   iload 5
L224:   i2f
L225:   fmul
L226:   aload_0
L227:   getfield Field lG while I
L230:   i2f
L231:   fdiv
L232:   fadd
L233:   fastore
L234:   getfield Field lG continue [[I
L237:   iload 4
L239:   aload_0
L240:   getfield Field lG finally I
L243:   iadd
L244:   aaload
L245:   iload_3
L246:   iload 5
L248:   iadd
L249:   aload_0
L250:   getfield Field lG I [[I
L253:   iload 4
L255:   aaload
L256:   iload_3
L257:   iaload
L258:   bipush 31
L260:   iconst_1
L261:   dup
L262:   pop2
L263:   iand
L264:   iastore
L265:   iload 4
L267:   ifne L296
L270:   aload_0
L271:   getfield Field lG continue [[I
L274:   iload 4
L276:   aload_0
L277:   getfield Field lG finally I
L280:   iadd
L281:   aaload
L282:   iload_3
L283:   iload 5
L285:   iadd
L286:   dup2
L287:   iaload
L288:   sipush 2048
L291:   iconst_1
L292:   dup
L293:   pop2
L294:   ior
L295:   iastore
L296:   iload 4
L298:   iload_2
L299:   if_icmpne L328
L302:   aload_0
L303:   getfield Field lG continue [[I
L306:   iload 4
L308:   aload_0
L309:   getfield Field lG finally I
L312:   iadd
L313:   aaload
L314:   iload_3
L315:   iload 5
L317:   iadd
L318:   dup2
L319:   iaload
L320:   sipush 512
L323:   iconst_1
L324:   dup
L325:   pop2
L326:   ior
L327:   iastore
L328:   iinc 5 1
L331:   iload 5
L333:   goto L154
L336:   iinc 4 1
L339:   iload 4
L341:   goto L103
L344:   iinc 3 1
L347:   iload_3
L348:   goto L89
L351:   aload_0
L352:   iconst_1
L353:   dup
L354:   aload_0
L355:   dup_x1
L356:   iconst_0
L357:   iconst_1
L358:   dup
L359:   pop2
L360:   putfield Field lG "super" Z
L363:   iconst_1
L364:   dup
L365:   pop2
L366:   putfield Field lG C Z
L369:   iconst_1
L370:   dup
L371:   pop2
L372:   putfield Field lG B Z
L375:   return
L376:   
        .attribute StackMap b'\x00\x11\x00\x0D\x00\x00\x00\x01\x07\x00\xBF\x00\x0E\x00\x02\x07\x00\x02\x01\x00\x00\x00\x19\x00\x04\x07\x00\x02\x01\x01\x01\x00\x01\x01\x00\x27\x00\x05\x07\x00\x02\x01\x01\x01\x01\x00\x01\x01\x00\x43\x00\x05\x07\x00\x02\x01\x01\x01\x01\x00\x00\x00\x4B\x00\x00\x00\x01\x07\x00\xBF\x00\x4C\x00\x05\x07\x00\x02\x01\x01\x01\x01\x00\x00\x00\x53\x00\x04\x07\x00\x02\x01\x01\x01\x00\x00\x00\x59\x00\x04\x07\x00\x02\x01\x01\x01\x00\x01\x01\x00\x67\x00\x05\x07\x00\x02\x01\x01\x01\x01\x00\x01\x01\x00\x9A\x00\x06\x07\x00\x02\x01\x01\x01\x01\x01\x00\x01\x01\x00\xC9\x00\x06\x07\x00\x02\x01\x01\x01\x01\x01\x00\x00\x01\x28\x00\x06\x07\x00\x02\x01\x01\x01\x01\x01\x00\x00\x01\x48\x00\x06\x07\x00\x02\x01\x01\x01\x01\x01\x00\x00\x01\x50\x00\x05\x07\x00\x02\x01\x01\x01\x01\x00\x00\x01\x58\x00\x05\x07\x00\x02\x01\x01\x01\x01\x00\x00\x01\x5F\x00\x04\x07\x00\x02\x01\x01\x01\x00\x00'
    .end code
.end method

.method public else : (F)V
    .code stack 4 locals 2
L0:     aload_0
L1:     fload_1
L2:     fconst_0
L3:     fconst_1
L4:     invokestatic Method OC else (FFF)F
L7:     putfield Field lG float F
L10:    return
L11:    
    .end code
.end method

.method public break : (I)V
    .code stack 6 locals 4
L0:     aload_0
L1:     getfield Field lG do I
L4:     dup
L5:     istore_2
L6:     iload_1
L7:     if_icmpge L76
L10:    iconst_0
L11:    iconst_1
L12:    dup
L13:    pop2
L14:    dup
L15:    istore_3
L16:    bipush 10
L18:    iconst_1
L19:    dup
L20:    pop2
L21:    if_icmpge L68
L24:    aload_0
L25:    getfield Field lG class [[I
L28:    iload_3
L29:    aaload
L30:    iload_2
L31:    iaload
L32:    bipush 31
L34:    iconst_1
L35:    dup
L36:    pop2
L37:    iand
L38:    bipush 13
L40:    iconst_1
L41:    dup
L42:    pop2
L43:    if_icmpne L60
L46:    aload_0
L47:    iload_3
L48:    iload_2
L49:    bipush 15
L51:    iconst_1
L52:    dup
L53:    pop2
L54:    ldc_w -1e0f
L57:    invokevirtual Method lG break (IIIF)V
L60:    iinc 3 1
L63:    iload_3
L64:    goto L16
L67:    athrow
L68:    iinc 2 1
L71:    iload_2
L72:    goto L6
L75:    athrow
L76:    aload_0
L77:    iconst_1
L78:    dup
L79:    aload_0
L80:    dup_x1
L81:    iload_1
L82:    putfield Field lG do I
L85:    iconst_1
L86:    dup
L87:    pop2
L88:    putfield Field lG instanceof Z
L91:    iconst_1
L92:    dup
L93:    pop2
L94:    putfield Field lG C Z
L97:    return
L98:    
        .attribute StackMap b'\x00\x07\x00\x06\x00\x03\x07\x00\x02\x01\x01\x00\x01\x01\x00\x10\x00\x04\x07\x00\x02\x01\x01\x01\x00\x01\x01\x00\x3C\x00\x04\x07\x00\x02\x01\x01\x01\x00\x00\x00\x43\x00\x00\x00\x01\x07\x00\xBF\x00\x44\x00\x04\x07\x00\x02\x01\x01\x01\x00\x00\x00\x4B\x00\x00\x00\x01\x07\x00\xBF\x00\x4C\x00\x03\x07\x00\x02\x01\x01\x00\x00'
    .end code
.end method
.end class
