.version 46 0
.class public final super MA
.super org/xml/sax/helpers/DefaultHandler
.field public final do LDA; .fieldattributes
    .synthetic
.end fieldattributes

.method public endElement : (Ljava/lang/String;Ljava/lang/String;Ljava/lang/String;)V
    .code stack 5 locals 4
L0:     aload_0
L1:     getfield Field MA do LDA;
L4:     dup
L5:     invokestatic Method DA else (LDA;)I
L8:     iconst_1
L9:     dup
L10:    dup
L11:    pop2
L12:    isub
L13:    invokestatic Method DA break (LDA;I)V
L16:    getstatic Field QA short Z
L19:    ifeq L49
L22:    getstatic Field java/lang/System err Ljava/io/PrintStream;
L25:    new java/lang/StringBuffer
L28:    dup
L29:    ldc "</"
L31:    invokespecial Method java/lang/StringBuffer <init> (Ljava/lang/String;)V
L34:    aload_3
L35:    invokevirtual Method java/lang/StringBuffer append (Ljava/lang/String;)Ljava/lang/StringBuffer;
L38:    ldc ">"
L40:    invokevirtual Method java/lang/StringBuffer append (Ljava/lang/String;)Ljava/lang/StringBuffer;
L43:    invokevirtual Method java/lang/StringBuffer toString ()Ljava/lang/String;
L46:    invokevirtual Method java/io/PrintStream println (Ljava/lang/String;)V
L49:    aload_0
L50:    getfield Field MA do LDA;
L53:    invokestatic Method DA for (LDA;)I
L56:    tableswitch 1
            L288
            L288
            L92
            L152
            L208
            default : L288
L92:    aload_3
L93:    iconst_0
L94:    ifne L285
L97:    ldc "jnlp"
L99:    invokevirtual Method java/lang/String equals (Ljava/lang/Object;)Z
L102:   ifeq L288
L105:   aload_0
L106:   getfield Field MA do LDA;
L109:   iconst_2
L110:   iconst_1
L111:   dup
L112:   pop2
L113:   invokestatic Method DA else (LDA;I)V
L116:   getstatic Field QA short Z
L119:   ifeq L288
L122:   getstatic Field java/lang/System err Ljava/io/PrintStream;
L125:   new java/lang/StringBuffer
L128:   dup
L129:   ldc "state = "
L131:   invokespecial Method java/lang/StringBuffer <init> (Ljava/lang/String;)V
L134:   aload_0
L135:   getfield Field MA do LDA;
L138:   invokestatic Method DA for (LDA;)I
L141:   invokevirtual Method java/lang/StringBuffer append (I)Ljava/lang/StringBuffer;
L144:   invokevirtual Method java/lang/StringBuffer toString ()Ljava/lang/String;
L147:   invokevirtual Method java/io/PrintStream println (Ljava/lang/String;)V
L150:   return
L151:   athrow
L152:   aload_3
L153:   ldc "resources"
L155:   invokevirtual Method java/lang/String equals (Ljava/lang/Object;)Z
L158:   ifeq L288
L161:   aload_0
L162:   getfield Field MA do LDA;
L165:   iconst_3
L166:   iconst_1
L167:   dup
L168:   pop2
L169:   invokestatic Method DA else (LDA;I)V
L172:   getstatic Field QA short Z
L175:   ifeq L288
L178:   getstatic Field java/lang/System err Ljava/io/PrintStream;
L181:   new java/lang/StringBuffer
L184:   dup
L185:   ldc "state = "
L187:   invokespecial Method java/lang/StringBuffer <init> (Ljava/lang/String;)V
L190:   aload_0
L191:   getfield Field MA do LDA;
L194:   invokestatic Method DA for (LDA;)I
L197:   invokevirtual Method java/lang/StringBuffer append (I)Ljava/lang/StringBuffer;
L200:   invokevirtual Method java/lang/StringBuffer toString ()Ljava/lang/String;
L203:   invokevirtual Method java/io/PrintStream println (Ljava/lang/String;)V
L206:   return
L207:   athrow
L208:   aload_0
L209:   getfield Field MA do LDA;
L212:   invokestatic Method DA else (LDA;)I
L215:   aload_0
L216:   getfield Field MA do LDA;
L219:   invokestatic Method DA const (LDA;)I
L222:   if_icmpne L288
L225:   aload_0
L226:   getfield Field MA do LDA;
L229:   aload_0
L230:   dup_x1
L231:   getfield Field MA do LDA;
L234:   invokestatic Method DA break (LDA;)I
L237:   invokestatic Method DA else (LDA;I)V
L240:   getfield Field MA do LDA;
L243:   iconst_m1
L244:   iconst_1
L245:   dup
L246:   pop2
L247:   invokestatic Method DA short (LDA;I)V
L250:   getstatic Field QA short Z
L253:   ifeq L288
L256:   getstatic Field java/lang/System err Ljava/io/PrintStream;
L259:   new java/lang/StringBuffer
L262:   dup
L263:   ldc "state = "
L265:   invokespecial Method java/lang/StringBuffer <init> (Ljava/lang/String;)V
L268:   aload_0
L269:   getfield Field MA do LDA;
L272:   invokestatic Method DA for (LDA;)I
L275:   invokevirtual Method java/lang/StringBuffer append (I)Ljava/lang/StringBuffer;
L278:   invokevirtual Method java/lang/StringBuffer toString ()Ljava/lang/String;
L281:   invokevirtual Method java/io/PrintStream println (Ljava/lang/String;)V
L284:   return
L285:   goto L93
L288:   return
L289:   
        .attribute StackMap b'\x00\x09\x00\x31\x00\x04\x07\x00\x02\x07\x00\x3B\x07\x00\x3B\x07\x00\x3B\x00\x00\x00\x5C\x00\x04\x07\x00\x02\x07\x00\x3B\x07\x00\x3B\x07\x00\x3B\x00\x00\x00\x5D\x00\x04\x07\x00\x02\x07\x00\x3B\x07\x00\x3B\x07\x00\x3B\x00\x01\x07\x00\x3B\x00\x97\x00\x00\x00\x01\x07\x00\x4D\x00\x98\x00\x04\x07\x00\x02\x07\x00\x3B\x07\x00\x3B\x07\x00\x3B\x00\x00\x00\xCF\x00\x00\x00\x01\x07\x00\x4D\x00\xD0\x00\x04\x07\x00\x02\x07\x00\x3B\x07\x00\x3B\x07\x00\x3B\x00\x00\x01\x1D\x00\x04\x07\x00\x02\x07\x00\x3B\x07\x00\x3B\x07\x00\x3B\x00\x01\x07\x00\x3B\x01\x20\x00\x04\x07\x00\x02\x07\x00\x3B\x07\x00\x3B\x07\x00\x3B\x00\x00'
    .end code
    .exceptions org/xml/sax/SAXException
.end method

.method public startElement : (Ljava/lang/String;Ljava/lang/String;Ljava/lang/String;Lorg/xml/sax/Attributes;)V
    .code stack 6 locals 8
L0:     aload_0
L1:     getfield Field MA do LDA;
L4:     dup
L5:     invokestatic Method DA else (LDA;)I
L8:     iconst_1
L9:     dup
L10:    dup
L11:    pop2
L12:    iadd
L13:    invokestatic Method DA break (LDA;I)V
L16:    getstatic Field QA short Z
L19:    ifeq L152
L22:    getstatic Field java/lang/System err Ljava/io/PrintStream;
L25:    new java/lang/StringBuffer
L28:    dup
L29:    ldc "<"
L31:    invokespecial Method java/lang/StringBuffer <init> (Ljava/lang/String;)V
L34:    aload_3
L35:    invokevirtual Method java/lang/StringBuffer append (Ljava/lang/String;)Ljava/lang/StringBuffer;
L38:    ldc ">"
L40:    invokevirtual Method java/lang/StringBuffer append (Ljava/lang/String;)Ljava/lang/StringBuffer;
L43:    ldc " : depth="
L45:    invokevirtual Method java/lang/StringBuffer append (Ljava/lang/String;)Ljava/lang/StringBuffer;
L48:    aload_0
L49:    getfield Field MA do LDA;
L52:    invokestatic Method DA else (LDA;)I
L55:    invokevirtual Method java/lang/StringBuffer append (I)Ljava/lang/StringBuffer;
L58:    invokevirtual Method java/lang/StringBuffer toString ()Ljava/lang/String;
L61:    invokevirtual Method java/io/PrintStream println (Ljava/lang/String;)V
L64:    iconst_0
L65:    iconst_1
L66:    dup
L67:    pop2
L68:    dup
L69:    istore 5
L71:    goto L142
L74:    athrow
L75:    getstatic Field java/lang/System err Ljava/io/PrintStream;
L78:    new java/lang/StringBuffer
L81:    dup
L82:    ldc "    ["
L84:    invokespecial Method java/lang/StringBuffer <init> (Ljava/lang/String;)V
L87:    iload 5
L89:    invokevirtual Method java/lang/StringBuffer append (I)Ljava/lang/StringBuffer;
L92:    ldc "]  "
L94:    invokevirtual Method java/lang/StringBuffer append (Ljava/lang/String;)Ljava/lang/StringBuffer;
L97:    aload 4
L99:    iload 5
L101:   invokeinterface InterfaceMethod org/xml/sax/Attributes getQName (I)Ljava/lang/String; 2
L106:   invokevirtual Method java/lang/StringBuffer append (Ljava/lang/String;)Ljava/lang/StringBuffer;
L109:   ldc " = \""
L111:   invokevirtual Method java/lang/StringBuffer append (Ljava/lang/String;)Ljava/lang/StringBuffer;
L114:   aload 4
L116:   iload 5
L118:   invokeinterface InterfaceMethod org/xml/sax/Attributes getValue (I)Ljava/lang/String; 2
L123:   invokevirtual Method java/lang/StringBuffer append (Ljava/lang/String;)Ljava/lang/StringBuffer;
L126:   ldc "\""
L128:   iinc 5 1
L131:   invokevirtual Method java/lang/StringBuffer append (Ljava/lang/String;)Ljava/lang/StringBuffer;
L134:   invokevirtual Method java/lang/StringBuffer toString ()Ljava/lang/String;
L137:   invokevirtual Method java/io/PrintStream println (Ljava/lang/String;)V
L140:   iload 5
L142:   aload 4
L144:   invokeinterface InterfaceMethod org/xml/sax/Attributes getLength ()I 1
L149:   if_icmplt L75
L152:   aload_0
L153:   getfield Field MA do LDA;
L156:   invokestatic Method DA for (LDA;)I
L159:   tableswitch 1
            L1133
            L192
            L404
            L646
            L1133
            default : L1133
L192:   aload_3
L193:   iconst_0
L194:   ifne L643
L197:   ldc "jnlp"
L199:   invokevirtual Method java/lang/String equals (Ljava/lang/Object;)Z
L202:   ifeq L385
L205:   aload_0
L206:   dup
L207:   dup_x1
L208:   getfield Field MA do LDA;
L211:   iconst_3
L212:   iconst_1
L213:   dup
L214:   pop2
L215:   invokestatic Method DA else (LDA;I)V
L218:   getfield Field MA do LDA;
L221:   aload 4
L223:   ldc "codebase"
L225:   invokeinterface InterfaceMethod org/xml/sax/Attributes getValue (Ljava/lang/String;)Ljava/lang/String; 2
L230:   invokestatic Method DA break (LDA;Ljava/lang/String;)V
L233:   getfield Field MA do LDA;
L236:   invokestatic Method DA catch (LDA;)Ljava/lang/String;
L239:   ifnonnull L252
L242:   new org/xml/sax/SAXException
L245:   dup
L246:   ldc "<jnlp> unable to determine codebase"
L248:   invokespecial Method org/xml/sax/SAXException <init> (Ljava/lang/String;)V
L251:   athrow
L252:   aload_0
L253:   getfield Field MA do LDA;
L256:   invokestatic Method DA catch (LDA;)Ljava/lang/String;
L259:   bipush 47
L261:   iconst_1
L262:   dup
L263:   pop2
L264:   invokevirtual Method java/lang/String lastIndexOf (I)I
L267:   aload_0
L268:   getfield Field MA do LDA;
L271:   invokestatic Method DA catch (LDA;)Ljava/lang/String;
L274:   invokevirtual Method java/lang/String length ()I
L277:   iconst_1
L278:   dup
L279:   dup
L280:   pop2
L281:   isub
L282:   if_icmpeq L315
L285:   aload_0
L286:   getfield Field MA do LDA;
L289:   dup
L290:   invokestatic Method DA catch (LDA;)Ljava/lang/String;
L293:   new java/lang/StringBuffer
L296:   dup_x1
L297:   swap
L298:   invokestatic Method java/lang/String valueOf (Ljava/lang/Object;)Ljava/lang/String;
L301:   invokespecial Method java/lang/StringBuffer <init> (Ljava/lang/String;)V
L304:   ldc "/"
L306:   invokevirtual Method java/lang/StringBuffer append (Ljava/lang/String;)Ljava/lang/StringBuffer;
L309:   invokevirtual Method java/lang/StringBuffer toString ()Ljava/lang/String;
L312:   invokestatic Method DA break (LDA;Ljava/lang/String;)V
L315:   getstatic Field QA short Z
L318:   ifeq L349
L321:   getstatic Field java/lang/System err Ljava/io/PrintStream;
L324:   new java/lang/StringBuffer
L327:   dup
L328:   ldc "JNLP : codebase="
L330:   invokespecial Method java/lang/StringBuffer <init> (Ljava/lang/String;)V
L333:   aload_0
L334:   getfield Field MA do LDA;
L337:   invokestatic Method DA catch (LDA;)Ljava/lang/String;
L340:   invokevirtual Method java/lang/StringBuffer append (Ljava/lang/String;)Ljava/lang/StringBuffer;
L343:   invokevirtual Method java/lang/StringBuffer toString ()Ljava/lang/String;
L346:   invokevirtual Method java/io/PrintStream println (Ljava/lang/String;)V
L349:   getstatic Field QA short Z
L352:   ifeq L1133
L355:   getstatic Field java/lang/System err Ljava/io/PrintStream;
L358:   new java/lang/StringBuffer
L361:   dup
L362:   ldc "state = "
L364:   invokespecial Method java/lang/StringBuffer <init> (Ljava/lang/String;)V
L367:   aload_0
L368:   getfield Field MA do LDA;
L371:   invokestatic Method DA for (LDA;)I
L374:   invokevirtual Method java/lang/StringBuffer append (I)Ljava/lang/StringBuffer;
L377:   invokevirtual Method java/lang/StringBuffer toString ()Ljava/lang/String;
L380:   invokevirtual Method java/io/PrintStream println (Ljava/lang/String;)V
L383:   return
L384:   athrow
L385:   aload_3
L386:   ldc "resources"
L388:   invokevirtual Method java/lang/String equals (Ljava/lang/Object;)Z
L391:   ifeq L1133
L394:   new org/xml/sax/SAXException
L397:   dup
L398:   ldc "<resources> tag not within <jnlp> tag"
L400:   invokespecial Method org/xml/sax/SAXException <init> (Ljava/lang/String;)V
L403:   athrow
L404:   aload_3
L405:   ldc "jnlp"
L407:   invokevirtual Method java/lang/String equals (Ljava/lang/Object;)Z
L410:   ifeq L423
L413:   new org/xml/sax/SAXException
L416:   dup
L417:   ldc "Nested <jnlp> tags"
L419:   invokespecial Method org/xml/sax/SAXException <init> (Ljava/lang/String;)V
L422:   athrow
L423:   aload_3
L424:   ldc "resources"
L426:   invokevirtual Method java/lang/String equals (Ljava/lang/Object;)Z
L429:   ifeq L1133
L432:   aload 4
L434:   dup
L435:   ldc "os"
L437:   invokeinterface InterfaceMethod org/xml/sax/Attributes getValue (Ljava/lang/String;)Ljava/lang/String; 2
L442:   astore 5
L444:   ldc "arch"
L446:   invokeinterface InterfaceMethod org/xml/sax/Attributes getValue (Ljava/lang/String;)Ljava/lang/String; 2
L451:   astore 6
L453:   aload 5
L455:   ifnull L472
L458:   invokestatic Method DA const ()Ljava/lang/String;
L461:   aload 5
L463:   invokevirtual Method java/lang/String toLowerCase ()Ljava/lang/String;
L466:   invokevirtual Method java/lang/String startsWith (Ljava/lang/String;)Z
L469:   ifeq L544
L472:   aload 6
L474:   ifnull L491
L477:   invokestatic Method DA break ()Ljava/lang/String;
L480:   aload 6
L482:   invokevirtual Method java/lang/String toLowerCase ()Ljava/lang/String;
L485:   invokevirtual Method java/lang/String startsWith (Ljava/lang/String;)Z
L488:   ifeq L544
L491:   getstatic Field QA short Z
L494:   ifeq L530
L497:   getstatic Field java/lang/System err Ljava/io/PrintStream;
L500:   new java/lang/StringBuffer
L503:   dup
L504:   ldc "Loading resources : os="
L506:   invokespecial Method java/lang/StringBuffer <init> (Ljava/lang/String;)V
L509:   aload 5
L511:   invokevirtual Method java/lang/StringBuffer append (Ljava/lang/String;)Ljava/lang/StringBuffer;
L514:   ldc "  arch="
L516:   invokevirtual Method java/lang/StringBuffer append (Ljava/lang/String;)Ljava/lang/StringBuffer;
L519:   aload 6
L521:   invokevirtual Method java/lang/StringBuffer append (Ljava/lang/String;)Ljava/lang/StringBuffer;
L524:   invokevirtual Method java/lang/StringBuffer toString ()Ljava/lang/String;
L527:   invokevirtual Method java/io/PrintStream println (Ljava/lang/String;)V
L530:   aload_0
L531:   getfield Field MA do LDA;
L534:   iconst_4
L535:   iconst_1
L536:   dup
L537:   pop2
L538:   invokestatic Method DA else (LDA;I)V
L541:   goto L588
L544:   aload_0
L545:   dup
L546:   getfield Field MA do LDA;
L549:   aload_0
L550:   dup_x1
L551:   getfield Field MA do LDA;
L554:   invokestatic Method DA for (LDA;)I
L557:   invokestatic Method DA const (LDA;I)V
L560:   getfield Field MA do LDA;
L563:   aload_0
L564:   getfield Field MA do LDA;
L567:   invokestatic Method DA else (LDA;)I
L570:   iconst_1
L571:   dup
L572:   dup
L573:   pop2
L574:   isub
L575:   invokestatic Method DA short (LDA;I)V
L578:   getfield Field MA do LDA;
L581:   iconst_5
L582:   iconst_1
L583:   dup
L584:   pop2
L585:   invokestatic Method DA else (LDA;I)V
L588:   getstatic Field QA short Z
L591:   ifeq L1133
L594:   getstatic Field java/lang/System err Ljava/io/PrintStream;
L597:   new java/lang/StringBuffer
L600:   dup
L601:   ldc "Resources : os="
L603:   invokespecial Method java/lang/StringBuffer <init> (Ljava/lang/String;)V
L606:   aload 5
L608:   invokevirtual Method java/lang/StringBuffer append (Ljava/lang/String;)Ljava/lang/StringBuffer;
L611:   ldc "  arch="
L613:   invokevirtual Method java/lang/StringBuffer append (Ljava/lang/String;)Ljava/lang/StringBuffer;
L616:   aload 6
L618:   invokevirtual Method java/lang/StringBuffer append (Ljava/lang/String;)Ljava/lang/StringBuffer;
L621:   ldc "  state = "
L623:   invokevirtual Method java/lang/StringBuffer append (Ljava/lang/String;)Ljava/lang/StringBuffer;
L626:   aload_0
L627:   getfield Field MA do LDA;
L630:   invokestatic Method DA for (LDA;)I
L633:   invokevirtual Method java/lang/StringBuffer append (I)Ljava/lang/StringBuffer;
L636:   invokevirtual Method java/lang/StringBuffer toString ()Ljava/lang/String;
L639:   invokevirtual Method java/io/PrintStream println (Ljava/lang/String;)V
L642:   return
L643:   goto L193
        .catch java/io/IOException from L646 to L1112 using L1113
L646:   aload_3
L647:   ldc "jnlp"
L649:   invokevirtual Method java/lang/String equals (Ljava/lang/Object;)Z
L652:   ifeq L665
L655:   new org/xml/sax/SAXException
L658:   dup
L659:   ldc "Nested <jnlp> tags"
L661:   invokespecial Method org/xml/sax/SAXException <init> (Ljava/lang/String;)V
L664:   athrow
L665:   aload_3
L666:   ldc "resources"
L668:   invokevirtual Method java/lang/String equals (Ljava/lang/Object;)Z
L671:   ifeq L684
L674:   new org/xml/sax/SAXException
L677:   dup
L678:   ldc "Nested <resources> tags"
L680:   invokespecial Method org/xml/sax/SAXException <init> (Ljava/lang/String;)V
L683:   athrow
L684:   aload_3
L685:   ldc "jar"
L687:   invokevirtual Method java/lang/String equals (Ljava/lang/Object;)Z
L690:   ifeq L806
L693:   aload 4
L695:   ldc "href"
L697:   invokeinterface InterfaceMethod org/xml/sax/Attributes getValue (Ljava/lang/String;)Ljava/lang/String; 2
L702:   dup
L703:   astore 5
L705:   ifnull L716
L708:   aload 5
L710:   invokevirtual Method java/lang/String length ()I
L713:   ifne L726
L716:   new org/xml/sax/SAXException
L719:   dup
L720:   ldc "<jar> tag missing href attribute"
L722:   invokespecial Method org/xml/sax/SAXException <init> (Ljava/lang/String;)V
L725:   athrow
L726:   new java/lang/StringBuffer
L729:   dup
L730:   aload_0
L731:   getfield Field MA do LDA;
L734:   invokestatic Method DA catch (LDA;)Ljava/lang/String;
L737:   invokestatic Method java/lang/String valueOf (Ljava/lang/Object;)Ljava/lang/String;
L740:   invokespecial Method java/lang/StringBuffer <init> (Ljava/lang/String;)V
L743:   aload 5
L745:   invokevirtual Method java/lang/StringBuffer append (Ljava/lang/String;)Ljava/lang/StringBuffer;
L748:   invokevirtual Method java/lang/StringBuffer toString ()Ljava/lang/String;
L751:   astore 6
L753:   getstatic Field QA short Z
L756:   ifeq L782
L759:   getstatic Field java/lang/System err Ljava/io/PrintStream;
L762:   new java/lang/StringBuffer
L765:   dup
L766:   ldc "Jar: "
L768:   invokespecial Method java/lang/StringBuffer <init> (Ljava/lang/String;)V
L771:   aload 6
L773:   invokevirtual Method java/lang/StringBuffer append (Ljava/lang/String;)Ljava/lang/StringBuffer;
L776:   invokevirtual Method java/lang/StringBuffer toString ()Ljava/lang/String;
L779:   invokevirtual Method java/io/PrintStream println (Ljava/lang/String;)V
L782:   new java/net/URL
L785:   dup
L786:   aload 6
L788:   invokespecial Method java/net/URL <init> (Ljava/lang/String;)V
L791:   astore 7
L793:   aload_0
L794:   getfield Field MA do LDA;
L797:   invokestatic Method DA do (LDA;)LQA;
L800:   aload 7
L802:   invokestatic Method QA else (LQA;Ljava/net/URL;)V
L805:   return
L806:   aload_3
L807:   ldc "nativelib"
L809:   invokevirtual Method java/lang/String equals (Ljava/lang/Object;)Z
L812:   ifeq L928
L815:   aload 4
L817:   ldc "href"
L819:   invokeinterface InterfaceMethod org/xml/sax/Attributes getValue (Ljava/lang/String;)Ljava/lang/String; 2
L824:   dup
L825:   astore 5
L827:   ifnull L838
L830:   aload 5
L832:   invokevirtual Method java/lang/String length ()I
L835:   ifne L848
L838:   new org/xml/sax/SAXException
L841:   dup
L842:   ldc "<nativelib> tag missing href attribute"
L844:   invokespecial Method org/xml/sax/SAXException <init> (Ljava/lang/String;)V
L847:   athrow
L848:   new java/lang/StringBuffer
L851:   dup
L852:   aload_0
L853:   getfield Field MA do LDA;
L856:   invokestatic Method DA catch (LDA;)Ljava/lang/String;
L859:   invokestatic Method java/lang/String valueOf (Ljava/lang/Object;)Ljava/lang/String;
L862:   invokespecial Method java/lang/StringBuffer <init> (Ljava/lang/String;)V
L865:   aload 5
L867:   invokevirtual Method java/lang/StringBuffer append (Ljava/lang/String;)Ljava/lang/StringBuffer;
L870:   invokevirtual Method java/lang/StringBuffer toString ()Ljava/lang/String;
L873:   astore 6
L875:   getstatic Field QA short Z
L878:   ifeq L904
L881:   getstatic Field java/lang/System err Ljava/io/PrintStream;
L884:   new java/lang/StringBuffer
L887:   dup
L888:   ldc "Native Lib: "
L890:   invokespecial Method java/lang/StringBuffer <init> (Ljava/lang/String;)V
L893:   aload 6
L895:   invokevirtual Method java/lang/StringBuffer append (Ljava/lang/String;)Ljava/lang/StringBuffer;
L898:   invokevirtual Method java/lang/StringBuffer toString ()Ljava/lang/String;
L901:   invokevirtual Method java/io/PrintStream println (Ljava/lang/String;)V
L904:   new java/net/URL
L907:   dup
L908:   aload 6
L910:   invokespecial Method java/net/URL <init> (Ljava/lang/String;)V
L913:   astore 7
L915:   aload_0
L916:   getfield Field MA do LDA;
L919:   invokestatic Method DA do (LDA;)LQA;
L922:   aload 7
L924:   invokestatic Method QA break (LQA;Ljava/net/URL;)V
L927:   return
L928:   aload_3
L929:   ldc "extension"
L931:   invokevirtual Method java/lang/String equals (Ljava/lang/Object;)Z
L934:   ifeq L1034
L937:   aload 4
L939:   ldc "href"
L941:   invokeinterface InterfaceMethod org/xml/sax/Attributes getValue (Ljava/lang/String;)Ljava/lang/String; 2
L946:   dup
L947:   astore 5
L949:   ifnull L960
L952:   aload 5
L954:   invokevirtual Method java/lang/String length ()I
L957:   ifne L970
L960:   new org/xml/sax/SAXException
L963:   dup
L964:   ldc "<extension> tag missing href attribute"
L966:   invokespecial Method org/xml/sax/SAXException <init> (Ljava/lang/String;)V
L969:   athrow
L970:   getstatic Field QA short Z
L973:   ifeq L999
L976:   getstatic Field java/lang/System err Ljava/io/PrintStream;
L979:   new java/lang/StringBuffer
L982:   dup
L983:   ldc "Extension: "
L985:   invokespecial Method java/lang/StringBuffer <init> (Ljava/lang/String;)V
L988:   aload 5
L990:   invokevirtual Method java/lang/StringBuffer append (Ljava/lang/String;)Ljava/lang/StringBuffer;
L993:   invokevirtual Method java/lang/StringBuffer toString ()Ljava/lang/String;
L996:   invokevirtual Method java/io/PrintStream println (Ljava/lang/String;)V
L999:   new java/net/URL
L1002:  dup
L1003:  aload 5
L1005:  invokespecial Method java/net/URL <init> (Ljava/lang/String;)V
L1008:  astore 6
L1010:  new DA
L1013:  dup
L1014:  aload_0
L1015:  getfield Field MA do LDA;
L1018:  invokestatic Method DA do (LDA;)LQA;
L1021:  aload 6
L1023:  aconst_null
L1024:  invokespecial Method DA <init> (LQA;Ljava/net/URL;LDA;)V
L1027:  dup
L1028:  astore 7
L1030:  invokestatic Method DA short (LDA;)V
L1033:  return
L1034:  aload_0
L1035:  dup
L1036:  getfield Field MA do LDA;
L1039:  aload_0
L1040:  dup_x1
L1041:  getfield Field MA do LDA;
L1044:  invokestatic Method DA for (LDA;)I
L1047:  invokestatic Method DA const (LDA;I)V
L1050:  getfield Field MA do LDA;
L1053:  aload_0
L1054:  getfield Field MA do LDA;
L1057:  invokestatic Method DA else (LDA;)I
L1060:  iconst_1
L1061:  dup
L1062:  dup
L1063:  pop2
L1064:  isub
L1065:  invokestatic Method DA short (LDA;I)V
L1068:  getfield Field MA do LDA;
L1071:  iconst_5
L1072:  iconst_1
L1073:  dup
L1074:  pop2
L1075:  invokestatic Method DA else (LDA;I)V
L1078:  getstatic Field QA short Z
L1081:  ifeq L1133
L1084:  getstatic Field java/lang/System err Ljava/io/PrintStream;
L1087:  new java/lang/StringBuffer
L1090:  dup
L1091:  ldc "state = "
L1093:  invokespecial Method java/lang/StringBuffer <init> (Ljava/lang/String;)V
L1096:  aload_0
L1097:  getfield Field MA do LDA;
L1100:  invokestatic Method DA for (LDA;)I
L1103:  invokevirtual Method java/lang/StringBuffer append (I)Ljava/lang/StringBuffer;
L1106:  invokevirtual Method java/lang/StringBuffer toString ()Ljava/lang/String;
L1109:  invokevirtual Method java/io/PrintStream println (Ljava/lang/String;)V
L1112:  return
L1113:  astore 5
L1115:  new org/xml/sax/SAXException
L1118:  dup
L1119:  aload 5
L1121:  invokespecial Method org/xml/sax/SAXException <init> (Ljava/lang/Exception;)V
L1124:  aload 5
L1126:  invokevirtual Method org/xml/sax/SAXException initCause (Ljava/lang/Throwable;)Ljava/lang/Throwable;
L1129:  checkcast org/xml/sax/SAXException
L1132:  athrow
L1133:  return
L1134:  
        .attribute StackMap b'\x00\x24\x00\x4A\x00\x00\x00\x01\x07\x00\x4D\x00\x4B\x00\x06\x07\x00\x02\x07\x00\x3B\x07\x00\x3B\x07\x00\x3B\x07\x00\x60\x01\x00\x00\x00\x8E\x00\x06\x07\x00\x02\x07\x00\x3B\x07\x00\x3B\x07\x00\x3B\x07\x00\x60\x01\x00\x01\x01\x00\x98\x00\x05\x07\x00\x02\x07\x00\x3B\x07\x00\x3B\x07\x00\x3B\x07\x00\x60\x00\x00\x00\xC0\x00\x05\x07\x00\x02\x07\x00\x3B\x07\x00\x3B\x07\x00\x3B\x07\x00\x60\x00\x00\x00\xC1\x00\x05\x07\x00\x02\x07\x00\x3B\x07\x00\x3B\x07\x00\x3B\x07\x00\x60\x00\x01\x07\x00\x3B\x00\xFC\x00\x05\x07\x00\x02\x07\x00\x3B\x07\x00\x3B\x07\x00\x3B\x07\x00\x60\x00\x00\x01\x3B\x00\x05\x07\x00\x02\x07\x00\x3B\x07\x00\x3B\x07\x00\x3B\x07\x00\x60\x00\x00\x01\x5D\x00\x05\x07\x00\x02\x07\x00\x3B\x07\x00\x3B\x07\x00\x3B\x07\x00\x60\x00\x00\x01\x80\x00\x00\x00\x01\x07\x00\x4D\x01\x81\x00\x05\x07\x00\x02\x07\x00\x3B\x07\x00\x3B\x07\x00\x3B\x07\x00\x60\x00\x00\x01\x94\x00\x05\x07\x00\x02\x07\x00\x3B\x07\x00\x3B\x07\x00\x3B\x07\x00\x60\x00\x00\x01\xA7\x00\x05\x07\x00\x02\x07\x00\x3B\x07\x00\x3B\x07\x00\x3B\x07\x00\x60\x00\x00\x01\xD8\x00\x07\x07\x00\x02\x07\x00\x3B\x07\x00\x3B\x07\x00\x3B\x07\x00\x60\x07\x00\x3B\x07\x00\x3B\x00\x00\x01\xEB\x00\x07\x07\x00\x02\x07\x00\x3B\x07\x00\x3B\x07\x00\x3B\x07\x00\x60\x07\x00\x3B\x07\x00\x3B\x00\x00\x02\x12\x00\x07\x07\x00\x02\x07\x00\x3B\x07\x00\x3B\x07\x00\x3B\x07\x00\x60\x07\x00\x3B\x07\x00\x3B\x00\x00\x02\x20\x00\x07\x07\x00\x02\x07\x00\x3B\x07\x00\x3B\x07\x00\x3B\x07\x00\x60\x07\x00\x3B\x07\x00\x3B\x00\x00\x02\x4C\x00\x07\x07\x00\x02\x07\x00\x3B\x07\x00\x3B\x07\x00\x3B\x07\x00\x60\x07\x00\x3B\x07\x00\x3B\x00\x00\x02\x83\x00\x05\x07\x00\x02\x07\x00\x3B\x07\x00\x3B\x07\x00\x3B\x07\x00\x60\x00\x01\x07\x00\x3B\x02\x86\x00\x05\x07\x00\x02\x07\x00\x3B\x07\x00\x3B\x07\x00\x3B\x07\x00\x60\x00\x00\x02\x99\x00\x05\x07\x00\x02\x07\x00\x3B\x07\x00\x3B\x07\x00\x3B\x07\x00\x60\x00\x00\x02\xAC\x00\x05\x07\x00\x02\x07\x00\x3B\x07\x00\x3B\x07\x00\x3B\x07\x00\x60\x00\x00\x02\xCC\x00\x06\x07\x00\x02\x07\x00\x3B\x07\x00\x3B\x07\x00\x3B\x07\x00\x60\x07\x00\x3B\x00\x00\x02\xD6\x00\x06\x07\x00\x02\x07\x00\x3B\x07\x00\x3B\x07\x00\x3B\x07\x00\x60\x07\x00\x3B\x00\x00\x03\x0E\x00\x07\x07\x00\x02\x07\x00\x3B\x07\x00\x3B\x07\x00\x3B\x07\x00\x60\x07\x00\x3B\x07\x00\x3B\x00\x00\x03\x26\x00\x05\x07\x00\x02\x07\x00\x3B\x07\x00\x3B\x07\x00\x3B\x07\x00\x60\x00\x00\x03\x46\x00\x06\x07\x00\x02\x07\x00\x3B\x07\x00\x3B\x07\x00\x3B\x07\x00\x60\x07\x00\x3B\x00\x00\x03\x50\x00\x06\x07\x00\x02\x07\x00\x3B\x07\x00\x3B\x07\x00\x3B\x07\x00\x60\x07\x00\x3B\x00\x00\x03\x88\x00\x07\x07\x00\x02\x07\x00\x3B\x07\x00\x3B\x07\x00\x3B\x07\x00\x60\x07\x00\x3B\x07\x00\x3B\x00\x00\x03\xA0\x00\x05\x07\x00\x02\x07\x00\x3B\x07\x00\x3B\x07\x00\x3B\x07\x00\x60\x00\x00\x03\xC0\x00\x06\x07\x00\x02\x07\x00\x3B\x07\x00\x3B\x07\x00\x3B\x07\x00\x60\x07\x00\x3B\x00\x00\x03\xCA\x00\x06\x07\x00\x02\x07\x00\x3B\x07\x00\x3B\x07\x00\x3B\x07\x00\x60\x07\x00\x3B\x00\x00\x03\xE7\x00\x06\x07\x00\x02\x07\x00\x3B\x07\x00\x3B\x07\x00\x3B\x07\x00\x60\x07\x00\x3B\x00\x00\x04\x0A\x00\x05\x07\x00\x02\x07\x00\x3B\x07\x00\x3B\x07\x00\x3B\x07\x00\x60\x00\x00\x04\x59\x00\x05\x07\x00\x02\x07\x00\x3B\x07\x00\x3B\x07\x00\x3B\x07\x00\x60\x00\x01\x07\x00\x5A\x04\x6D\x00\x05\x07\x00\x02\x07\x00\x3B\x07\x00\x3B\x07\x00\x3B\x07\x00\x60\x00\x00'
    .end code
    .exceptions org/xml/sax/SAXException
.end method

.method public <init> : (LDA;)V
    .code stack 3 locals 2
L0:     aload_1
L1:     aload_0
L2:     dup_x1
L3:     invokespecial Method org/xml/sax/helpers/DefaultHandler <init> ()V
L6:     putfield Field MA do LDA;
L9:     return
L10:    
    .end code
.end method

.method public endDocument : ()V
    .code stack 4 locals 1
L0:     getstatic Field QA short Z
L3:     ifeq L14
L6:     getstatic Field java/lang/System err Ljava/io/PrintStream;
L9:     ldc "END DOCUMENT"
L11:    invokevirtual Method java/io/PrintStream println (Ljava/lang/String;)V
L14:    aload_0
L15:    getfield Field MA do LDA;
L18:    iconst_1
L19:    dup
L20:    dup
L21:    pop2
L22:    invokestatic Method DA else (LDA;I)V
L25:    getstatic Field QA short Z
L28:    ifeq L59
L31:    getstatic Field java/lang/System err Ljava/io/PrintStream;
L34:    new java/lang/StringBuffer
L37:    dup
L38:    ldc "state = "
L40:    invokespecial Method java/lang/StringBuffer <init> (Ljava/lang/String;)V
L43:    aload_0
L44:    getfield Field MA do LDA;
L47:    invokestatic Method DA for (LDA;)I
L50:    invokevirtual Method java/lang/StringBuffer append (I)Ljava/lang/StringBuffer;
L53:    invokevirtual Method java/lang/StringBuffer toString ()Ljava/lang/String;
L56:    invokevirtual Method java/io/PrintStream println (Ljava/lang/String;)V
L59:    return
L60:    
        .attribute StackMap b'\x00\x02\x00\x0E\x00\x01\x07\x00\x02\x00\x00\x00\x3B\x00\x01\x07\x00\x02\x00\x00'
    .end code
.end method

.method public startDocument : ()V
    .code stack 4 locals 1
L0:     getstatic Field QA short Z
L3:     ifeq L34
L6:     getstatic Field java/lang/System err Ljava/io/PrintStream;
L9:     new java/lang/StringBuffer
L12:    dup
L13:    ldc "START DOCUMENT: "
L15:    invokespecial Method java/lang/StringBuffer <init> (Ljava/lang/String;)V
L18:    aload_0
L19:    getfield Field MA do LDA;
L22:    invokestatic Method DA float (LDA;)Ljava/net/URL;
L25:    invokevirtual Method java/lang/StringBuffer append (Ljava/lang/Object;)Ljava/lang/StringBuffer;
L28:    invokevirtual Method java/lang/StringBuffer toString ()Ljava/lang/String;
L31:    invokevirtual Method java/io/PrintStream println (Ljava/lang/String;)V
L34:    aload_0
L35:    getfield Field MA do LDA;
L38:    iconst_2
L39:    iconst_1
L40:    dup
L41:    pop2
L42:    invokestatic Method DA else (LDA;I)V
L45:    getstatic Field QA short Z
L48:    ifeq L79
L51:    getstatic Field java/lang/System err Ljava/io/PrintStream;
L54:    new java/lang/StringBuffer
L57:    dup
L58:    ldc "state = "
L60:    invokespecial Method java/lang/StringBuffer <init> (Ljava/lang/String;)V
L63:    aload_0
L64:    getfield Field MA do LDA;
L67:    invokestatic Method DA for (LDA;)I
L70:    invokevirtual Method java/lang/StringBuffer append (I)Ljava/lang/StringBuffer;
L73:    invokevirtual Method java/lang/StringBuffer toString ()Ljava/lang/String;
L76:    invokevirtual Method java/io/PrintStream println (Ljava/lang/String;)V
L79:    return
L80:    
        .attribute StackMap b'\x00\x02\x00\x22\x00\x01\x07\x00\x02\x00\x00\x00\x4F\x00\x01\x07\x00\x02\x00\x00'
    .end code
.end method
.innerclasses
    DA QA [0] private static
    MA DA [0] private
.end innerclasses
.end class
