.version 49 0
.class public final super mC
.super java/lang/Object

.method public <init> : ()V
    .code stack 1 locals 1
L0:     aload_0
L1:     invokespecial Method java/lang/Object <init> ()V
L4:     return
L5:     
    .end code
.end method

.method public static break : ([[LgB;)V
    .code stack 5 locals 7
L0:     iconst_0
L1:     iconst_1
L2:     dup
L3:     pop2
L4:     dup
L5:     istore_1
L6:     aload_0
L7:     arraylength
L8:     if_icmpge L154
L11:    aload_0
L12:    iload_1
L13:    aaload
L14:    arraylength
L15:    iconst_1
L16:    dup
L17:    dup
L18:    pop2
L19:    isub
L20:    dup
L21:    istore_2
L22:    iflt L146
L25:    aload_0
L26:    iload_1
L27:    aaload
L28:    iload_2
L29:    aaload
L30:    ifnull L138
L33:    aconst_null
L34:    astore_3
L35:    aconst_null
L36:    astore 4
L38:    aconst_null
L39:    astore 5
L41:    aconst_null
L42:    astore 6
L44:    iload_2
L45:    ifle L59
L48:    aload_0
L49:    iload_1
L50:    aaload
L51:    iload_2
L52:    iconst_1
L53:    dup
L54:    dup
L55:    pop2
L56:    isub
L57:    aaload
L58:    astore_3
L59:    iload_1
L60:    ifle L75
L63:    aload_0
L64:    iload_1
L65:    iconst_1
L66:    dup
L67:    dup
L68:    pop2
L69:    isub
L70:    aaload
L71:    iload_2
L72:    aaload
L73:    astore 5
L75:    iload_2
L76:    aload_0
L77:    iload_1
L78:    aaload
L79:    arraylength
L80:    iconst_1
L81:    dup
L82:    dup
L83:    pop2
L84:    isub
L85:    if_icmpge L100
L88:    aload_0
L89:    iload_1
L90:    aaload
L91:    iload_2
L92:    iconst_1
L93:    dup
L94:    dup
L95:    pop2
L96:    iadd
L97:    aaload
L98:    astore 4
L100:   iload_1
L101:   aload_0
L102:   arraylength
L103:   iconst_1
L104:   dup
L105:   dup
L106:   pop2
L107:   isub
L108:   if_icmpge L123
L111:   aload_0
L112:   iload_1
L113:   iconst_1
L114:   dup
L115:   dup
L116:   pop2
L117:   iadd
L118:   aaload
L119:   iload_2
L120:   aaload
L121:   astore 6
L123:   aload_0
L124:   iload_1
L125:   aaload
L126:   iload_2
L127:   aaload
L128:   aload 5
L130:   aload 4
L132:   aload 6
L134:   aload_3
L135:   invokevirtual Method gB break (LgB;LgB;LgB;LgB;)V
L138:   iinc 2 -1
L141:   iload_2
L142:   goto L22
L145:   athrow
L146:   iinc 1 1
L149:   iload_1
L150:   goto L6
L153:   athrow
L154:   return
L155:   
        .attribute StackMap b'\x00\x0B\x00\x06\x00\x02\x07\x00\x0C\x01\x00\x01\x01\x00\x16\x00\x03\x07\x00\x0C\x01\x01\x00\x01\x01\x00\x3B\x00\x07\x07\x00\x0C\x01\x01\x07\x00\x0E\x05\x05\x05\x00\x00\x00\x4B\x00\x07\x07\x00\x0C\x01\x01\x07\x00\x0E\x05\x07\x00\x0E\x05\x00\x00\x00\x64\x00\x07\x07\x00\x0C\x01\x01\x07\x00\x0E\x07\x00\x0E\x07\x00\x0E\x05\x00\x00\x00\x7B\x00\x07\x07\x00\x0C\x01\x01\x07\x00\x0E\x07\x00\x0E\x07\x00\x0E\x07\x00\x0E\x00\x00\x00\x8A\x00\x03\x07\x00\x0C\x01\x01\x00\x00\x00\x91\x00\x00\x00\x01\x07\x00\x13\x00\x92\x00\x03\x07\x00\x0C\x01\x01\x00\x00\x00\x99\x00\x00\x00\x01\x07\x00\x13\x00\x9A\x00\x02\x07\x00\x0C\x01\x00\x00'
    .end code
.end method
.end class
