.version 49 0
.class public final super MC
.super qB
.field public field1434 LlG;

.method public method726 : ()D
    .code stack 2 locals 1
L0:     ldc2_w 4e0
L3:     dreturn
L4:     
    .end code
.end method

.method public method725 : ([[I)V
    .code stack 6 locals 8
L0:     iconst_0
L1:     aload_0
L2:     aload_1
L3:     dup_x2
L4:     invokespecial Method qB method725 ([[I)V
L7:     iconst_1
L8:     dup
L9:     pop2
L10:    istore_2
L11:    iconst_0
L12:    iconst_1
L13:    dup
L14:    pop2
L15:    istore_3
L16:    arraylength
L17:    istore 4
L19:    aload_1
L20:    iconst_0
L21:    iconst_1
L22:    dup
L23:    pop2
L24:    aaload
L25:    arraylength
L26:    istore 5
L28:    iconst_0
L29:    iconst_1
L30:    dup
L31:    pop2
L32:    dup
L33:    istore 6
L35:    aload_1
L36:    arraylength
L37:    if_icmpge L123
L40:    iconst_0
L41:    iconst_1
L42:    dup
L43:    pop2
L44:    dup
L45:    istore 7
L47:    aload_1
L48:    iload 6
L50:    aaload
L51:    arraylength
L52:    if_icmpge L114
L55:    aload_1
L56:    iload 6
L58:    aaload
L59:    iload 7
L61:    iaload
L62:    ifeq L105
L65:    iload 6
L67:    iload 4
L69:    if_icmpge L76
L72:    iload 6
L74:    istore 4
L76:    iload 7
L78:    iload 5
L80:    if_icmpge L87
L83:    iload 7
L85:    istore 5
L87:    iload 6
L89:    iload_2
L90:    if_icmple L96
L93:    iload 6
L95:    istore_2
L96:    iload 7
L98:    iload_3
L99:    if_icmple L105
L102:   iload 7
L104:   istore_3
L105:   iinc 7 1
L108:   iload 7
L110:   goto L47
L113:   athrow
L114:   iinc 6 1
L117:   iload 6
L119:   goto L35
L122:   athrow
L123:   aload_0
L124:   dup
L125:   getfield Field MC field1434 LlG;
L128:   iconst_3
L129:   iconst_1
L130:   dup
L131:   pop2
L132:   iload_2
L133:   isub
L134:   iload 4
L136:   isub
L137:   i2f
L138:   fconst_2
L139:   fdiv
L140:   iconst_3
L141:   iconst_1
L142:   dup
L143:   pop2
L144:   iload_3
L145:   isub
L146:   iload 5
L148:   isub
L149:   i2f
L150:   fconst_2
L151:   fdiv
L152:   invokevirtual Method lG this (FF)V
L155:   getfield Field MC field1434 LlG;
L158:   aload_1
L159:   invokevirtual Method lG method118 ([[I)V
L162:   return
L163:   
        .attribute StackMap b'\x00\x0A\x00\x23\x00\x07\x07\x00\x02\x07\x00\x10\x01\x01\x01\x01\x01\x00\x01\x01\x00\x2F\x00\x08\x07\x00\x02\x07\x00\x10\x01\x01\x01\x01\x01\x01\x00\x01\x01\x00\x4C\x00\x08\x07\x00\x02\x07\x00\x10\x01\x01\x01\x01\x01\x01\x00\x00\x00\x57\x00\x08\x07\x00\x02\x07\x00\x10\x01\x01\x01\x01\x01\x01\x00\x00\x00\x60\x00\x08\x07\x00\x02\x07\x00\x10\x01\x01\x01\x01\x01\x01\x00\x00\x00\x69\x00\x08\x07\x00\x02\x07\x00\x10\x01\x01\x01\x01\x01\x01\x00\x00\x00\x71\x00\x00\x00\x01\x07\x00\x12\x00\x72\x00\x08\x07\x00\x02\x07\x00\x10\x01\x01\x01\x01\x01\x01\x00\x00\x00\x7A\x00\x00\x00\x01\x07\x00\x12\x00\x7B\x00\x07\x07\x00\x02\x07\x00\x10\x01\x01\x01\x01\x01\x00\x00'
    .end code
.end method

.method public method717 : (FFF)V
    .code stack 6 locals 4
L0:     aload_0
L1:     dup
L2:     dup_x1
L3:     fload_1
L4:     fload_2
L5:     fload_3
L6:     invokespecial Method qB method717 (FFF)V
L9:     getfield Field MC field1434 LlG;
L12:    fload_1
L13:    fload_2
L14:    fload_3
L15:    fadd
L16:    invokevirtual Method lG method37 (FF)V
L19:    getfield Field MC field1434 LlG;
L22:    fload_3
L23:    ldc 4e0f
L25:    fmul
L26:    fload_3
L27:    ldc 4e0f
L29:    fmul
L30:    invokevirtual Method lG method32 (FF)V
L33:    return
L34:    
    .end code
.end method

.method public <init> : (LLD;)V
    .code stack 10 locals 2
L0:     aload_0
L1:     dup
L2:     aload_1
L3:     ldc "Next piece"
L5:     invokespecial Method qB <init> (LLD;Ljava/lang/String;)V
L8:     new lG
L11:    aload_0
L12:    dup_x2
L13:    dup
L14:    pop2
L15:    dup
L16:    iconst_1
L17:    dup
L18:    pop2
L19:    iconst_4
L20:    iconst_1
L21:    dup
L22:    pop2
L23:    iconst_4
L24:    dup_x1
L25:    iconst_1
L26:    dup
L27:    pop2
L28:    iconst_0
L29:    iconst_1
L30:    dup
L31:    pop2
L32:    invokespecial Method lG <init> (IIIZ)V
L35:    putfield Field MC field1434 LlG;
L38:    getfield Field MC field1430 LLD;
L41:    aload_0
L42:    getfield Field MC field1434 LlG;
L45:    invokevirtual Method LD method36 (LgB;)LgB;
L48:    pop
L49:    return
L50:    
    .end code
.end method
.end class
