.version 49 0
.class public final super Md
.super java/lang/Object
.field private do Ljava/io/DataInputStream;

.method public "enum" : ()F
    .code stack 1 locals 1
L0:     aload_0
L1:     getfield Field Md do Ljava/io/DataInputStream;
L4:     invokevirtual Method java/io/DataInputStream readFloat ()F
L7:     freturn
L8:     
    .end code
    .exceptions java/io/IOException
.end method

.method public long : ()I
    .code stack 4 locals 2
L0:     aload_0
L1:     getfield Field Md do Ljava/io/DataInputStream;
L4:     invokevirtual Method java/io/DataInputStream readByte ()B
L7:     dup
L8:     istore_1
L9:     bipush -128
L11:    iconst_1
L12:    dup
L13:    pop2
L14:    if_icmpne L25
L17:    aload_0
L18:    getfield Field Md do Ljava/io/DataInputStream;
L21:    invokevirtual Method java/io/DataInputStream readInt ()I
L24:    istore_1
L25:    iload_1
L26:    ireturn
L27:    
        .attribute StackMap b'\x00\x01\x00\x19\x00\x02\x07\x00\x02\x01\x00\x00'
    .end code
    .exceptions java/io/IOException
.end method

.method public class : ()[I
    .code stack 3 locals 3
L0:     aload_0
L1:     invokevirtual Method Md long ()I
L4:     dup
L5:     istore_1
L6:     invokestatic Method java/lang/Math abs (I)I
L9:     newarray int
L11:    iconst_1
L12:    dup
L13:    pop2
L14:    astore_2
L15:    iload_1
L16:    ifge L49
L19:    iconst_0
L20:    iconst_1
L21:    dup
L22:    pop2
L23:    dup
L24:    istore_1
L25:    aload_2
L26:    arraylength
L27:    if_icmpge L77
L30:    aload_2
L31:    iload_1
L32:    aload_0
L33:    invokevirtual Method Md long ()I
L36:    iinc 1 1
L39:    iastore
L40:    iload_1
L41:    goto L25
L44:    nop
L45:    nop
L46:    nop
L47:    nop
L48:    athrow
L49:    iconst_0
L50:    iconst_1
L51:    dup
L52:    pop2
L53:    dup
L54:    istore_1
L55:    aload_2
L56:    arraylength
L57:    if_icmpge L77
L60:    aload_2
L61:    iload_1
L62:    aload_0
L63:    getfield Field Md do Ljava/io/DataInputStream;
L66:    invokevirtual Method java/io/DataInputStream readInt ()I
L69:    iinc 1 1
L72:    iastore
L73:    iload_1
L74:    goto L55
L77:    aload_2
L78:    areturn
L79:    
        .attribute StackMap b'\x00\x05\x00\x19\x00\x03\x07\x00\x02\x01\x07\x00\x26\x00\x01\x01\x00\x2C\x00\x00\x00\x01\x07\x00\x28\x00\x31\x00\x03\x07\x00\x02\x01\x07\x00\x26\x00\x00\x00\x37\x00\x03\x07\x00\x02\x01\x07\x00\x26\x00\x01\x01\x00\x4D\x00\x03\x07\x00\x02\x01\x07\x00\x26\x00\x00'
    .end code
    .exceptions java/io/IOException
.end method

.method public if : ()Ljava/util/Map;
    .code stack 3 locals 5
L0:     aload_0
L1:     invokevirtual Method Md long ()I
L4:     istore_1
L5:     new java/util/LinkedHashMap
L8:     dup
L9:     invokespecial Method java/util/LinkedHashMap <init> ()V
L12:    astore_2
L13:    iconst_0
L14:    iconst_1
L15:    dup
L16:    pop2
L17:    dup
L18:    istore_3
L19:    iload_1
L20:    if_icmpge L53
L23:    aload_0
L24:    getfield Field Md do Ljava/io/DataInputStream;
L27:    invokevirtual Method java/io/DataInputStream readUTF ()Ljava/lang/String;
L30:    astore 4
L32:    aload_2
L33:    aload 4
L35:    iinc 3 1
L38:    aload_0
L39:    invokevirtual Method Md try ()Ljava/lang/String;
L42:    invokeinterface InterfaceMethod java/util/Map put (Ljava/lang/Object;Ljava/lang/Object;)Ljava/lang/Object; 3
L47:    pop
L48:    iload_3
L49:    goto L19
L52:    athrow
L53:    aload_2
L54:    areturn
L55:    
        .attribute StackMap b'\x00\x03\x00\x13\x00\x04\x07\x00\x02\x01\x07\x00\x2C\x01\x00\x01\x01\x00\x34\x00\x00\x00\x01\x07\x00\x28\x00\x35\x00\x04\x07\x00\x02\x01\x07\x00\x2C\x01\x00\x00'
    .end code
    .exceptions java/io/IOException
.end method

.method public char : ()I
    .code stack 1 locals 1
L0:     aload_0
L1:     getfield Field Md do Ljava/io/DataInputStream;
L4:     invokevirtual Method java/io/DataInputStream readInt ()I
L7:     ireturn
L8:     
    .end code
    .exceptions java/io/IOException
.end method

.method public new : ()Ljava/lang/String;
    .code stack 1 locals 1
L0:     aload_0
L1:     getfield Field Md do Ljava/io/DataInputStream;
L4:     invokevirtual Method java/io/DataInputStream readUTF ()Ljava/lang/String;
L7:     areturn
L8:     
    .end code
    .exceptions java/io/IOException
.end method

.method public try : ()Ljava/lang/String;
    .code stack 1 locals 1
L0:     aload_0
L1:     invokevirtual Method Md for ()Z
L4:     ifeq L13
L7:     aload_0
L8:     invokevirtual Method Md new ()Ljava/lang/String;
L11:    areturn
L12:    athrow
L13:    aconst_null
L14:    areturn
L15:    
        .attribute StackMap b'\x00\x02\x00\x0C\x00\x00\x00\x01\x07\x00\x28\x00\x0D\x00\x01\x07\x00\x02\x00\x00'
    .end code
    .exceptions java/io/IOException
.end method

.method public this : ()B
    .code stack 1 locals 1
L0:     aload_0
L1:     getfield Field Md do Ljava/io/DataInputStream;
L4:     invokevirtual Method java/io/DataInputStream readByte ()B
L7:     ireturn
L8:     
    .end code
    .exceptions java/io/IOException
.end method

.method public <init> : (Ljava/io/InputStream;)V
    .code stack 4 locals 2
L0:     aload_0
L1:     invokespecial Method java/lang/Object <init> ()V
L4:     new java/io/DataInputStream
L7:     aload_0
L8:     dup_x1
L9:     dup
L10:    pop2
L11:    dup
L12:    aload_1
L13:    invokespecial Method java/io/DataInputStream <init> (Ljava/io/InputStream;)V
L16:    putfield Field Md do Ljava/io/DataInputStream;
L19:    return
L20:    
    .end code
    .exceptions java/io/IOException
.end method

.method public goto : ()[[S
    .code stack 3 locals 3
L0:     aload_0
L1:     invokevirtual Method Md long ()I
L4:     anewarray [S
L7:     iconst_1
L8:     dup
L9:     pop2
L10:    astore_1
L11:    iconst_0
L12:    iconst_1
L13:    dup
L14:    pop2
L15:    dup
L16:    istore_2
L17:    aload_1
L18:    arraylength
L19:    if_icmpge L37
L22:    aload_1
L23:    iload_2
L24:    aload_0
L25:    invokevirtual Method Md float ()[S
L28:    iinc 2 1
L31:    aastore
L32:    iload_2
L33:    goto L17
L36:    athrow
L37:    aload_1
L38:    areturn
L39:    
        .attribute StackMap b'\x00\x03\x00\x11\x00\x03\x07\x00\x02\x07\x00\x50\x01\x00\x01\x01\x00\x24\x00\x00\x00\x01\x07\x00\x28\x00\x25\x00\x03\x07\x00\x02\x07\x00\x50\x01\x00\x00'
    .end code
    .exceptions java/io/IOException
.end method

.method public do : ()[[I
    .code stack 3 locals 3
L0:     aload_0
L1:     invokevirtual Method Md long ()I
L4:     anewarray [I
L7:     iconst_1
L8:     dup
L9:     pop2
L10:    astore_1
L11:    iconst_0
L12:    iconst_1
L13:    dup
L14:    pop2
L15:    dup
L16:    istore_2
L17:    aload_1
L18:    arraylength
L19:    if_icmpge L37
L22:    aload_1
L23:    iload_2
L24:    aload_0
L25:    invokevirtual Method Md class ()[I
L28:    iinc 2 1
L31:    aastore
L32:    iload_2
L33:    goto L17
L36:    athrow
L37:    aload_1
L38:    areturn
L39:    
        .attribute StackMap b'\x00\x03\x00\x11\x00\x03\x07\x00\x02\x07\x00\x57\x01\x00\x01\x01\x00\x24\x00\x00\x00\x01\x07\x00\x28\x00\x25\x00\x03\x07\x00\x02\x07\x00\x57\x01\x00\x00'
    .end code
    .exceptions java/io/IOException
.end method

.method public for : ()Z
    .code stack 4 locals 1
L0:     aload_0
L1:     getfield Field Md do Ljava/io/DataInputStream;
L4:     invokevirtual Method java/io/DataInputStream readByte ()B
L7:     iconst_4
L8:     iconst_1
L9:     dup
L10:    pop2
L11:    iand
L12:    iconst_4
L13:    iconst_1
L14:    dup
L15:    pop2
L16:    if_icmpne L25
L19:    iconst_1
L20:    dup
L21:    dup
L22:    pop2
L23:    ireturn
L24:    athrow
L25:    iconst_0
L26:    iconst_1
L27:    dup
L28:    pop2
L29:    ireturn
L30:    
        .attribute StackMap b'\x00\x02\x00\x18\x00\x00\x00\x01\x07\x00\x28\x00\x19\x00\x01\x07\x00\x02\x00\x00'
    .end code
    .exceptions java/io/IOException
.end method

.method public catch : ()D
    .code stack 2 locals 1
L0:     aload_0
L1:     getfield Field Md do Ljava/io/DataInputStream;
L4:     invokevirtual Method java/io/DataInputStream readDouble ()D
L7:     dreturn
L8:     
    .end code
    .exceptions java/io/IOException
.end method

.method public break : ([B)V
    .code stack 2 locals 2
L0:     aload_0
L1:     getfield Field Md do Ljava/io/DataInputStream;
L4:     aload_1
L5:     invokevirtual Method java/io/DataInputStream readFully ([B)V
L8:     return
L9:     
    .end code
    .exceptions java/io/IOException
.end method

.method public float : ()[S
    .code stack 3 locals 3
L0:     aload_0
L1:     invokevirtual Method Md long ()I
L4:     newarray short
L6:     iconst_1
L7:     dup
L8:     pop2
L9:     astore_1
L10:    iconst_0
L11:    iconst_1
L12:    dup
L13:    pop2
L14:    dup
L15:    istore_2
L16:    aload_1
L17:    arraylength
L18:    if_icmpge L39
L21:    aload_1
L22:    iload_2
L23:    aload_0
L24:    getfield Field Md do Ljava/io/DataInputStream;
L27:    invokevirtual Method java/io/DataInputStream readShort ()S
L30:    iinc 2 1
L33:    sastore
L34:    iload_2
L35:    goto L16
L38:    athrow
L39:    aload_1
L40:    areturn
L41:    
        .attribute StackMap b'\x00\x03\x00\x10\x00\x03\x07\x00\x02\x07\x00\x4E\x01\x00\x01\x01\x00\x26\x00\x00\x00\x01\x07\x00\x28\x00\x27\x00\x03\x07\x00\x02\x07\x00\x4E\x01\x00\x00'
    .end code
    .exceptions java/io/IOException
.end method

.method public short : ()[B
    .code stack 4 locals 2
L0:     aload_0
L1:     dup
L2:     invokevirtual Method Md long ()I
L5:     newarray byte
L7:     iconst_1
L8:     dup
L9:     pop2
L10:    dup
L11:    astore_1
L12:    invokevirtual Method Md break ([B)V
L15:    aload_1
L16:    areturn
L17:    
    .end code
    .exceptions java/io/IOException
.end method

.method public const : ()J
    .code stack 2 locals 1
L0:     aload_0
L1:     getfield Field Md do Ljava/io/DataInputStream;
L4:     invokevirtual Method java/io/DataInputStream readLong ()J
L7:     lreturn
L8:     
    .end code
    .exceptions java/io/IOException
.end method

.method public else : ()Ljava/util/Set;
    .code stack 3 locals 5
L0:     new java/util/LinkedHashSet
L3:     dup
L4:     invokespecial Method java/util/LinkedHashSet <init> ()V
L7:     astore_1
L8:     aload_0
L9:     invokevirtual Method Md long ()I
L12:    istore_2
L13:    iconst_0
L14:    iconst_1
L15:    dup
L16:    pop2
L17:    dup
L18:    istore_3
L19:    iload_2
L20:    if_icmpge L53
L23:    aload_0
L24:    invokevirtual Method Md new ()Ljava/lang/String;
L27:    invokestatic Method xF break (Ljava/lang/String;)LUf;
L30:    dup
L31:    astore 4
L33:    ifnull L45
L36:    aload_1
L37:    aload 4
L39:    invokeinterface InterfaceMethod java/util/Set add (Ljava/lang/Object;)Z 2
L44:    pop
L45:    iinc 3 1
L48:    iload_3
L49:    goto L19
L52:    athrow
L53:    aload_1
L54:    areturn
L55:    
        .attribute StackMap b'\x00\x04\x00\x13\x00\x04\x07\x00\x02\x07\x00\x74\x01\x01\x00\x01\x01\x00\x2D\x00\x05\x07\x00\x02\x07\x00\x74\x01\x01\x07\x00\x82\x00\x00\x00\x34\x00\x00\x00\x01\x07\x00\x28\x00\x35\x00\x04\x07\x00\x02\x07\x00\x74\x01\x01\x00\x00'
    .end code
    .exceptions java/io/IOException
.end method

.method public break : ()S
    .code stack 1 locals 1
L0:     aload_0
L1:     getfield Field Md do Ljava/io/DataInputStream;
L4:     invokevirtual Method java/io/DataInputStream readShort ()S
L7:     ireturn
L8:     
    .end code
    .exceptions java/io/IOException
.end method
.end class
