.version 49 0
.class public final super mD
.super java/lang/Object
.field private static final new I = 20
.field private static final null Ljava/lang/String;
.field private static this LM;
.field private static char I
.field private static final else [[Ljava/nio/ByteBuffer;
.field private static "enum" F
.field private static do Z

.method public static this : ()Ljava/nio/IntBuffer;
    .code stack 12 locals 4
L0:     invokestatic Method java/awt/Toolkit getDefaultToolkit ()Ljava/awt/Toolkit;
L3:     ldc Class mD
L5:     ldc "/data/cursor_hand.png"
L7:     invokevirtual Method java/lang/Class getResource (Ljava/lang/String;)Ljava/net/URL;
L10:    invokevirtual Method java/awt/Toolkit getImage (Ljava/net/URL;)Ljava/awt/Image;
L13:    astore_0
L14:    new java/awt/image/BufferedImage
L17:    dup
L18:    bipush 16
L20:    iconst_1
L21:    dup
L22:    pop2
L23:    bipush 16
L25:    iconst_1
L26:    dup
L27:    pop2
L28:    iconst_2
L29:    iconst_1
L30:    dup
L31:    pop2
L32:    invokespecial Method java/awt/image/BufferedImage <init> (III)V
L35:    dup
L36:    astore_1
L37:    invokevirtual Method java/awt/image/BufferedImage createGraphics ()Ljava/awt/Graphics2D;
L40:    aload_0
L41:    iconst_1
L42:    dup
L43:    pop2
L44:    bipush 15
L46:    iconst_1
L47:    dup
L48:    pop2
L49:    bipush 15
L51:    iconst_1
L52:    dup
L53:    pop2
L54:    iconst_0
L55:    dup_x2
L56:    iconst_1
L57:    dup
L58:    pop2
L59:    iconst_0
L60:    iconst_1
L61:    dup
L62:    pop2
L63:    iconst_0
L64:    iconst_1
L65:    dup
L66:    pop2
L67:    bipush 15
L69:    iconst_1
L70:    dup
L71:    pop2
L72:    bipush 15
L74:    iconst_1
L75:    dup
L76:    pop2
L77:    aconst_null
L78:    invokevirtual Method java/awt/Graphics2D drawImage (Ljava/awt/Image;IIIIIIIILjava/awt/image/ImageObserver;)Z
L81:    ifne L101
        .catch java/lang/InterruptedException from L84 to L90 using L95
L84:    ldc2_w 5L
L87:    invokestatic Method java/lang/Thread sleep (J)V
L90:    aload_1
L91:    goto L37
L94:    athrow
L95:    astore_2
L96:    aload_1
L97:    goto L37
L100:   athrow
L101:   aload_1
L102:   invokevirtual Method java/awt/image/BufferedImage getRaster ()Ljava/awt/image/WritableRaster;
L105:   iconst_0
L106:   iconst_1
L107:   dup
L108:   pop2
L109:   iconst_0
L110:   iconst_1
L111:   dup
L112:   pop2
L113:   bipush 16
L115:   iconst_1
L116:   dup
L117:   pop2
L118:   bipush 16
L120:   iconst_1
L121:   dup
L122:   pop2
L123:   aconst_null
L124:   checkcast [I
L127:   invokevirtual Method java/awt/image/WritableRaster getPixels (IIII[I)[I
L130:   astore_2
L131:   sipush 256
L134:   iconst_1
L135:   dup
L136:   pop2
L137:   invokestatic Method org/lwjgl/BufferUtils createIntBuffer (I)Ljava/nio/IntBuffer;
L140:   astore_1
L141:   iconst_0
L142:   iconst_1
L143:   dup
L144:   pop2
L145:   dup
L146:   istore_3
L147:   aload_2
L148:   arraylength
L149:   if_icmpge L212
L152:   aload_1
L153:   aload_2
L154:   iload_3
L155:   iaload
L156:   aload_2
L157:   iload_3
L158:   iconst_1
L159:   dup
L160:   dup
L161:   pop2
L162:   iadd
L163:   iaload
L164:   bipush 8
L166:   iconst_1
L167:   dup
L168:   pop2
L169:   ishl
L170:   ior
L171:   aload_2
L172:   iload_3
L173:   iconst_2
L174:   iconst_1
L175:   dup
L176:   pop2
L177:   iadd
L178:   iaload
L179:   bipush 16
L181:   iconst_1
L182:   dup
L183:   pop2
L184:   ishl
L185:   ior
L186:   aload_2
L187:   iload_3
L188:   iconst_3
L189:   iconst_1
L190:   dup
L191:   pop2
L192:   iadd
L193:   iinc 3 4
L196:   iaload
L197:   bipush 24
L199:   iconst_1
L200:   dup
L201:   pop2
L202:   ishl
L203:   ior
L204:   invokevirtual Method java/nio/IntBuffer put (I)Ljava/nio/IntBuffer;
L207:   pop
L208:   iload_3
L209:   goto L147
L212:   aload_1
L213:   dup
L214:   invokevirtual Method java/nio/IntBuffer flip ()Ljava/nio/Buffer;
L217:   pop
L218:   areturn
L219:   
        .attribute StackMap b'\x00\x07\x00\x25\x00\x02\x07\x00\x33\x07\x00\x2D\x00\x01\x07\x00\x2D\x00\x5E\x00\x00\x00\x01\x07\x00\x47\x00\x5F\x00\x02\x07\x00\x33\x07\x00\x2D\x00\x01\x07\x00\x19\x00\x64\x00\x00\x00\x01\x07\x00\x47\x00\x65\x00\x02\x07\x00\x33\x07\x00\x2D\x00\x00\x00\x93\x00\x04\x07\x00\x33\x07\x00\x5B\x07\x00\x4D\x01\x00\x01\x01\x00\xD4\x00\x04\x07\x00\x33\x07\x00\x5B\x07\x00\x4D\x01\x00\x00'
    .end code
.end method

.method public static synthetic goto : ()Z
    .code stack 1 locals 0
L0:     getstatic Field mD do Z
L3:     ireturn
L4:     
    .end code
.end method

.method public static synthetic break : (Z)Z
    .code stack 2 locals 1
L0:     iload_0
L1:     dup
L2:     putstatic Field mD do Z
L5:     ireturn
L6:     
    .end code
.end method

.method private static short : ([I)[B
    .code stack 4 locals 3
L0:     aload_0
L1:     arraylength
L2:     newarray byte
L4:     iconst_1
L5:     dup
L6:     pop2
L7:     astore_1
L8:     iconst_0
L9:     iconst_1
L10:    dup
L11:    pop2
L12:    dup
L13:    istore_2
L14:    aload_0
L15:    arraylength
L16:    if_icmpge L34
L19:    aload_1
L20:    aload_0
L21:    iload_2
L22:    dup_x1
L23:    iaload
L24:    i2b
L25:    iinc 2 1
L28:    bastore
L29:    iload_2
L30:    goto L14
L33:    athrow
L34:    aload_1
L35:    areturn
L36:    
        .attribute StackMap b'\x00\x03\x00\x0E\x00\x03\x07\x00\x4D\x07\x00\x6C\x01\x00\x01\x01\x00\x21\x00\x00\x00\x01\x07\x00\x47\x00\x22\x00\x03\x07\x00\x4D\x07\x00\x6C\x01\x00\x00'
    .end code
.end method

.method private static const : ([I)[I
    .code stack 9 locals 5
L0:     sipush 4096
L3:     iconst_1
L4:     dup
L5:     pop2
L6:     newarray int
L8:     iconst_1
L9:     dup
L10:    pop2
L11:    astore_1
L12:    iconst_0
L13:    iconst_1
L14:    dup
L15:    pop2
L16:    dup
L17:    istore_2
L18:    bipush 32
L20:    iconst_1
L21:    dup
L22:    pop2
L23:    if_icmpge L238
L26:    iconst_0
L27:    iconst_1
L28:    dup
L29:    pop2
L30:    dup
L31:    istore_3
L32:    bipush 32
L34:    iconst_1
L35:    dup
L36:    pop2
L37:    if_icmpge L231
L40:    iconst_0
L41:    iconst_1
L42:    dup
L43:    pop2
L44:    dup
L45:    istore 4
L47:    iconst_4
L48:    iconst_1
L49:    dup
L50:    pop2
L51:    if_icmpge L223
L54:    aload_1
L55:    bipush 32
L57:    iconst_1
L58:    dup
L59:    pop2
L60:    iload_2
L61:    imul
L62:    iload_3
L63:    iadd
L64:    iconst_4
L65:    iconst_1
L66:    dup
L67:    pop2
L68:    imul
L69:    iload 4
L71:    iadd
L72:    aload_0
L73:    bipush 64
L75:    iconst_1
L76:    dup
L77:    pop2
L78:    iload_2
L79:    imul
L80:    iconst_2
L81:    iconst_1
L82:    dup
L83:    pop2
L84:    imul
L85:    iload_3
L86:    iconst_2
L87:    iconst_1
L88:    dup
L89:    pop2
L90:    imul
L91:    iadd
L92:    iconst_4
L93:    iconst_1
L94:    dup
L95:    pop2
L96:    imul
L97:    iload 4
L99:    iadd
L100:   iaload
L101:   aload_0
L102:   bipush 64
L104:   iconst_1
L105:   dup
L106:   pop2
L107:   iload_2
L108:   imul
L109:   iconst_2
L110:   iconst_1
L111:   dup
L112:   pop2
L113:   imul
L114:   iload_3
L115:   iconst_2
L116:   iconst_1
L117:   dup
L118:   pop2
L119:   imul
L120:   iadd
L121:   iconst_1
L122:   dup
L123:   dup
L124:   pop2
L125:   iadd
L126:   iconst_4
L127:   iconst_1
L128:   dup
L129:   pop2
L130:   imul
L131:   iload 4
L133:   iadd
L134:   iaload
L135:   iadd
L136:   aload_0
L137:   bipush 64
L139:   iconst_1
L140:   dup
L141:   pop2
L142:   iload_2
L143:   imul
L144:   iconst_2
L145:   iconst_1
L146:   dup
L147:   pop2
L148:   imul
L149:   iload_3
L150:   iconst_2
L151:   iconst_1
L152:   dup
L153:   pop2
L154:   imul
L155:   iadd
L156:   bipush 64
L158:   iconst_1
L159:   dup
L160:   pop2
L161:   iadd
L162:   iconst_4
L163:   iconst_1
L164:   dup
L165:   pop2
L166:   imul
L167:   iload 4
L169:   iadd
L170:   iaload
L171:   iadd
L172:   aload_0
L173:   bipush 64
L175:   iconst_1
L176:   dup
L177:   pop2
L178:   iload_2
L179:   imul
L180:   iconst_2
L181:   iconst_1
L182:   dup
L183:   pop2
L184:   imul
L185:   iload_3
L186:   iconst_2
L187:   iconst_1
L188:   dup
L189:   pop2
L190:   imul
L191:   iadd
L192:   bipush 65
L194:   iconst_1
L195:   dup
L196:   pop2
L197:   iadd
L198:   iconst_4
L199:   iconst_1
L200:   dup
L201:   pop2
L202:   imul
L203:   iload 4
L205:   iadd
L206:   iaload
L207:   iadd
L208:   iconst_4
L209:   iconst_1
L210:   dup
L211:   pop2
L212:   idiv
L213:   iinc 4 1
L216:   iastore
L217:   iload 4
L219:   goto L47
L222:   athrow
L223:   iinc 3 1
L226:   iload_3
L227:   goto L32
L230:   athrow
L231:   iinc 2 1
L234:   iload_2
L235:   goto L18
L238:   aload_1
L239:   areturn
L240:   
        .attribute StackMap b'\x00\x08\x00\x12\x00\x03\x07\x00\x4D\x07\x00\x4D\x01\x00\x01\x01\x00\x20\x00\x04\x07\x00\x4D\x07\x00\x4D\x01\x01\x00\x01\x01\x00\x2F\x00\x05\x07\x00\x4D\x07\x00\x4D\x01\x01\x01\x00\x01\x01\x00\xDE\x00\x00\x00\x01\x07\x00\x47\x00\xDF\x00\x05\x07\x00\x4D\x07\x00\x4D\x01\x01\x01\x00\x00\x00\xE6\x00\x00\x00\x01\x07\x00\x47\x00\xE7\x00\x04\x07\x00\x4D\x07\x00\x4D\x01\x01\x00\x00\x00\xEE\x00\x03\x07\x00\x4D\x07\x00\x4D\x01\x00\x00'
    .end code
.end method

.method public static <clinit> : ()V
    .code stack 3 locals 0
L0:     invokestatic Method mD short ()Ljava/lang/String;
L3:     putstatic Field mD null Ljava/lang/String;
L6:     bipush 20
L8:     iconst_1
L9:     dup
L10:    pop2
L11:    anewarray [Ljava/nio/ByteBuffer;
L14:    iconst_1
L15:    dup
L16:    pop2
L17:    putstatic Field mD else [[Ljava/nio/ByteBuffer;
L20:    iconst_m1
L21:    iconst_1
L22:    dup
L23:    pop2
L24:    putstatic Field mD char I
L27:    fconst_1
L28:    putstatic Field mD "enum" F
L31:    new xb
L34:    dup
L35:    invokespecial Method xb <init> ()V
L38:    putstatic Field mD this LM;
L41:    return
L42:    
    .end code
.end method

.method public static do : ()V
    .code stack 3 locals 0
L0:     getstatic Field mD do Z
L3:     ifeq L8
L6:     return
L7:     athrow
L8:     iconst_1
L9:     dup
L10:    dup
L11:    pop2
L12:    putstatic Field mD do Z
L15:    getstatic Field mD this LM;
L18:    invokestatic Method ib break (LM;)V
L21:    return
L22:    
        .attribute StackMap b'\x00\x02\x00\x07\x00\x00\x00\x01\x07\x00\x47\x00\x08\x00\x00\x00\x00'
    .end code
.end method

.method public static for : ()Ljava/awt/Image;
    .code stack 8 locals 0
L0:     new java/awt/image/BufferedImage
L3:     dup
L4:     bipush 32
L6:     iconst_1
L7:     dup
L8:     pop2
L9:     bipush 32
L11:    iconst_1
L12:    dup
L13:    pop2
L14:    iconst_2
L15:    iconst_1
L16:    dup
L17:    pop2
L18:    invokespecial Method java/awt/image/BufferedImage <init> (III)V
L21:    dup
L22:    invokevirtual Method java/awt/image/BufferedImage getRaster ()Ljava/awt/image/WritableRaster;
L25:    iconst_0
L26:    iconst_1
L27:    dup
L28:    pop2
L29:    iconst_0
L30:    iconst_1
L31:    dup
L32:    pop2
L33:    bipush 32
L35:    iconst_1
L36:    dup
L37:    pop2
L38:    bipush 32
L40:    iconst_1
L41:    dup
L42:    pop2
L43:    fconst_0
L44:    invokestatic Method mD short (F)[I
L47:    invokestatic Method mD break ([I)[I
L50:    invokestatic Method mD const ([I)[I
L53:    invokevirtual Method java/awt/image/WritableRaster setPixels (IIII[I)V
L56:    areturn
L57:    
    .end code
.end method

.method private static else : ([I)[I
    .code stack 9 locals 5
L0:     sipush 1024
L3:     iconst_1
L4:     dup
L5:     pop2
L6:     newarray int
L8:     iconst_1
L9:     dup
L10:    pop2
L11:    astore_1
L12:    iconst_0
L13:    iconst_1
L14:    dup
L15:    pop2
L16:    dup
L17:    istore_2
L18:    bipush 16
L20:    iconst_1
L21:    dup
L22:    pop2
L23:    if_icmpge L238
L26:    iconst_0
L27:    iconst_1
L28:    dup
L29:    pop2
L30:    dup
L31:    istore_3
L32:    bipush 16
L34:    iconst_1
L35:    dup
L36:    pop2
L37:    if_icmpge L231
L40:    iconst_0
L41:    iconst_1
L42:    dup
L43:    pop2
L44:    dup
L45:    istore 4
L47:    iconst_4
L48:    iconst_1
L49:    dup
L50:    pop2
L51:    if_icmpge L223
L54:    aload_1
L55:    bipush 16
L57:    iconst_1
L58:    dup
L59:    pop2
L60:    iload_2
L61:    imul
L62:    iload_3
L63:    iadd
L64:    iconst_4
L65:    iconst_1
L66:    dup
L67:    pop2
L68:    imul
L69:    iload 4
L71:    iadd
L72:    aload_0
L73:    bipush 32
L75:    iconst_1
L76:    dup
L77:    pop2
L78:    iload_2
L79:    imul
L80:    iconst_2
L81:    iconst_1
L82:    dup
L83:    pop2
L84:    imul
L85:    iload_3
L86:    iconst_2
L87:    iconst_1
L88:    dup
L89:    pop2
L90:    imul
L91:    iadd
L92:    iconst_4
L93:    iconst_1
L94:    dup
L95:    pop2
L96:    imul
L97:    iload 4
L99:    iadd
L100:   iaload
L101:   aload_0
L102:   bipush 32
L104:   iconst_1
L105:   dup
L106:   pop2
L107:   iload_2
L108:   imul
L109:   iconst_2
L110:   iconst_1
L111:   dup
L112:   pop2
L113:   imul
L114:   iload_3
L115:   iconst_2
L116:   iconst_1
L117:   dup
L118:   pop2
L119:   imul
L120:   iadd
L121:   iconst_1
L122:   dup
L123:   dup
L124:   pop2
L125:   iadd
L126:   iconst_4
L127:   iconst_1
L128:   dup
L129:   pop2
L130:   imul
L131:   iload 4
L133:   iadd
L134:   iaload
L135:   iadd
L136:   aload_0
L137:   bipush 32
L139:   iconst_1
L140:   dup
L141:   pop2
L142:   iload_2
L143:   imul
L144:   iconst_2
L145:   iconst_1
L146:   dup
L147:   pop2
L148:   imul
L149:   iload_3
L150:   iconst_2
L151:   iconst_1
L152:   dup
L153:   pop2
L154:   imul
L155:   iadd
L156:   bipush 32
L158:   iconst_1
L159:   dup
L160:   pop2
L161:   iadd
L162:   iconst_4
L163:   iconst_1
L164:   dup
L165:   pop2
L166:   imul
L167:   iload 4
L169:   iadd
L170:   iaload
L171:   iadd
L172:   aload_0
L173:   bipush 32
L175:   iconst_1
L176:   dup
L177:   pop2
L178:   iload_2
L179:   imul
L180:   iconst_2
L181:   iconst_1
L182:   dup
L183:   pop2
L184:   imul
L185:   iload_3
L186:   iconst_2
L187:   iconst_1
L188:   dup
L189:   pop2
L190:   imul
L191:   iadd
L192:   bipush 33
L194:   iconst_1
L195:   dup
L196:   pop2
L197:   iadd
L198:   iconst_4
L199:   iconst_1
L200:   dup
L201:   pop2
L202:   imul
L203:   iload 4
L205:   iadd
L206:   iaload
L207:   iadd
L208:   iconst_4
L209:   iconst_1
L210:   dup
L211:   pop2
L212:   idiv
L213:   iinc 4 1
L216:   iastore
L217:   iload 4
L219:   goto L47
L222:   athrow
L223:   iinc 3 1
L226:   iload_3
L227:   goto L32
L230:   athrow
L231:   iinc 2 1
L234:   iload_2
L235:   goto L18
L238:   aload_1
L239:   areturn
L240:   
        .attribute StackMap b'\x00\x08\x00\x12\x00\x03\x07\x00\x4D\x07\x00\x4D\x01\x00\x01\x01\x00\x20\x00\x04\x07\x00\x4D\x07\x00\x4D\x01\x01\x00\x01\x01\x00\x2F\x00\x05\x07\x00\x4D\x07\x00\x4D\x01\x01\x01\x00\x01\x01\x00\xDE\x00\x00\x00\x01\x07\x00\x47\x00\xDF\x00\x05\x07\x00\x4D\x07\x00\x4D\x01\x01\x01\x00\x00\x00\xE6\x00\x00\x00\x01\x07\x00\x47\x00\xE7\x00\x04\x07\x00\x4D\x07\x00\x4D\x01\x01\x00\x00\x00\xEE\x00\x03\x07\x00\x4D\x07\x00\x4D\x01\x00\x00'
    .end code
.end method

.method public static synthetic float : (F)F
    .code stack 2 locals 1
L0:     getstatic Field mD "enum" F
L3:     fload_0
L4:     fadd
L5:     dup
L6:     putstatic Field mD "enum" F
L9:     freturn
L10:    
    .end code
.end method

.method public static catch : ()V
    .code stack 2 locals 1
L0:     fconst_1
L1:     getstatic Field mD "enum" F
L4:     fsub
L5:     ldc 1.9e1f
L7:     fmul
L8:     f2i
L9:     dup
L10:    istore_0
L11:    getstatic Field mD char I
L14:    if_icmpeq L30
L17:    getstatic Field mD else [[Ljava/nio/ByteBuffer;
L20:    iload_0
L21:    aaload
L22:    invokestatic Method org/lwjgl/opengl/Display else ([Ljava/nio/ByteBuffer;)I
L25:    iload_0
L26:    putstatic Field mD char I
L29:    pop
L30:    return
L31:    
        .attribute StackMap b'\x00\x01\x00\x1E\x00\x01\x01\x00\x00'
    .end code
.end method

.method private static short : (F)[I
    .code stack 10 locals 9
L0:     ldc 65536
L2:     newarray int
L4:     iconst_1
L5:     dup
L6:     pop2
L7:     astore_1
L8:     iconst_0
L9:     iconst_1
L10:    dup
L11:    pop2
L12:    istore_2
L13:    iconst_0
L14:    iconst_1
L15:    dup
L16:    pop2
L17:    istore_3
L18:    iconst_0
L19:    iconst_1
L20:    dup
L21:    pop2
L22:    dup
L23:    istore 4
L25:    sipush 128
L28:    iconst_1
L29:    dup
L30:    pop2
L31:    if_icmpge L298
L34:    iconst_0
L35:    iconst_1
L36:    dup
L37:    pop2
L38:    dup
L39:    istore 5
L41:    sipush 128
L44:    iconst_1
L45:    dup
L46:    pop2
L47:    if_icmpge L289
L50:    getstatic Field mD null Ljava/lang/String;
L53:    iload_2
L54:    iconst_0
L55:    iconst_1
L56:    dup
L57:    pop2
L58:    iadd
L59:    iload_2
L60:    iconst_2
L61:    iconst_1
L62:    dup
L63:    pop2
L64:    iadd
L65:    invokevirtual Method java/lang/String substring (II)Ljava/lang/String;
L68:    bipush 16
L70:    iconst_1
L71:    dup
L72:    pop2
L73:    invokestatic Method java/lang/Integer parseInt (Ljava/lang/String;I)I
L76:    i2f
L77:    ldc 2.55e2f
L79:    fdiv
L80:    fstore 6
L82:    getstatic Field mD null Ljava/lang/String;
L85:    iload_2
L86:    iconst_2
L87:    iconst_1
L88:    dup
L89:    pop2
L90:    iadd
L91:    iload_2
L92:    iconst_4
L93:    iconst_1
L94:    dup
L95:    pop2
L96:    iadd
L97:    invokevirtual Method java/lang/String substring (II)Ljava/lang/String;
L100:   bipush 16
L102:   iconst_1
L103:   dup
L104:   pop2
L105:   invokestatic Method java/lang/Integer parseInt (Ljava/lang/String;I)I
L108:   i2f
L109:   ldc 2.55e2f
L111:   fdiv
L112:   fstore 7
L114:   getstatic Field mD null Ljava/lang/String;
L117:   iload_2
L118:   iconst_4
L119:   iconst_1
L120:   dup
L121:   pop2
L122:   iadd
L123:   iload_2
L124:   bipush 6
L126:   iconst_1
L127:   dup
L128:   pop2
L129:   iadd
L130:   invokevirtual Method java/lang/String substring (II)Ljava/lang/String;
L133:   bipush 16
L135:   iconst_1
L136:   dup
L137:   pop2
L138:   invokestatic Method java/lang/Integer parseInt (Ljava/lang/String;I)I
L141:   i2f
L142:   ldc 2.55e2f
L144:   fdiv
L145:   fstore 8
L147:   aload_1
L148:   dup
L149:   dup2
L150:   iload_3
L151:   ldc 2.55e2f
L153:   fload 8
L155:   fload 6
L157:   ldc 2.5e0f
L159:   fmul
L160:   fload_0
L161:   fmul
L162:   fadd
L163:   fmul
L164:   f2i
L165:   iconst_0
L166:   iconst_1
L167:   dup
L168:   pop2
L169:   sipush 255
L172:   iconst_1
L173:   dup
L174:   pop2
L175:   invokestatic Method OC break (III)I
L178:   iinc 3 1
L181:   iastore
L182:   iload_3
L183:   ldc 2.55e2f
L185:   fload 7
L187:   fload 6
L189:   fconst_2
L190:   fmul
L191:   fload_0
L192:   fmul
L193:   fadd
L194:   fmul
L195:   f2i
L196:   iconst_0
L197:   iconst_1
L198:   dup
L199:   pop2
L200:   sipush 255
L203:   iconst_1
L204:   dup
L205:   pop2
L206:   invokestatic Method OC break (III)I
L209:   iinc 3 1
L212:   iastore
L213:   iload_3
L214:   ldc 2.55e2f
L216:   fload 6
L218:   dup
L219:   ldc 5e-1f
L221:   fmul
L222:   fload_0
L223:   fmul
L224:   fadd
L225:   fmul
L226:   f2i
L227:   iconst_0
L228:   iconst_1
L229:   dup
L230:   pop2
L231:   sipush 255
L234:   iconst_1
L235:   dup
L236:   pop2
L237:   invokestatic Method OC break (III)I
L240:   iinc 3 1
L243:   iastore
L244:   iload_3
L245:   getstatic Field mD null Ljava/lang/String;
L248:   iload_2
L249:   bipush 6
L251:   iconst_1
L252:   dup
L253:   pop2
L254:   iadd
L255:   iload_2
L256:   bipush 8
L258:   iconst_1
L259:   dup
L260:   pop2
L261:   iadd
L262:   invokevirtual Method java/lang/String substring (II)Ljava/lang/String;
L265:   bipush 16
L267:   iconst_1
L268:   dup
L269:   pop2
L270:   invokestatic Method java/lang/Integer parseInt (Ljava/lang/String;I)I
L273:   iinc 3 1
L276:   iinc 2 8
L279:   iastore
L280:   iinc 5 1
L283:   iload 5
L285:   goto L41
L288:   athrow
L289:   iinc 4 1
L292:   iload 4
L294:   goto L25
L297:   athrow
L298:   aload_1
L299:   areturn
L300:   
        .attribute StackMap b'\x00\x06\x00\x19\x00\x05\x02\x07\x00\x4D\x01\x01\x01\x00\x01\x01\x00\x29\x00\x06\x02\x07\x00\x4D\x01\x01\x01\x01\x00\x01\x01\x01\x20\x00\x00\x00\x01\x07\x00\x47\x01\x21\x00\x06\x02\x07\x00\x4D\x01\x01\x01\x01\x00\x00\x01\x29\x00\x00\x00\x01\x07\x00\x47\x01\x2A\x00\x05\x02\x07\x00\x4D\x01\x01\x01\x00\x00'
    .end code
.end method

.method public <init> : ()V
    .code stack 1 locals 1
L0:     aload_0
L1:     invokespecial Method java/lang/Object <init> ()V
L4:     return
L5:     
    .end code
.end method

.method public static synthetic const : (F)[Ljava/nio/ByteBuffer;
    .code stack 1 locals 1
L0:     fload_0
L1:     invokestatic Method mD break (F)[Ljava/nio/ByteBuffer;
L4:     areturn
L5:     
    .end code
.end method

.method public static synthetic float : ()F
    .code stack 3 locals 0
L0:     getstatic Field mD "enum" F
L3:     dup
L4:     fconst_1
L5:     fsub
L6:     putstatic Field mD "enum" F
L9:     freturn
L10:    
    .end code
.end method

.method private static short : ()Ljava/lang/String;
    .code stack 3 locals 4
L0:     ldc [_184]
L2:     astore_0
L3:     ldc [_186]
L5:     astore_1
L6:     ldc [_188]
L8:     astore_2
L9:     ldc [_190]
L11:    astore_3
L12:    new java/lang/StringBuilder
L15:    dup
L16:    invokespecial Method java/lang/StringBuilder <init> ()V
L19:    iconst_0
L20:    aload_0
L21:    invokevirtual Method java/lang/StringBuilder insert (ILjava/lang/String;)Ljava/lang/StringBuilder;
L24:    aload_1
L25:    invokevirtual Method java/lang/StringBuilder append (Ljava/lang/String;)Ljava/lang/StringBuilder;
L28:    aload_2
L29:    invokevirtual Method java/lang/StringBuilder append (Ljava/lang/String;)Ljava/lang/StringBuilder;
L32:    aload_3
L33:    invokevirtual Method java/lang/StringBuilder append (Ljava/lang/String;)Ljava/lang/StringBuilder;
L36:    invokevirtual Method java/lang/StringBuilder toString ()Ljava/lang/String;
L39:    areturn
L40:    
    .end code
.end method

.method private static break : ([I)[I
    .code stack 9 locals 5
L0:     sipush 16384
L3:     iconst_1
L4:     dup
L5:     pop2
L6:     newarray int
L8:     iconst_1
L9:     dup
L10:    pop2
L11:    astore_1
L12:    iconst_0
L13:    iconst_1
L14:    dup
L15:    pop2
L16:    dup
L17:    istore_2
L18:    bipush 64
L20:    iconst_1
L21:    dup
L22:    pop2
L23:    if_icmpge L244
L26:    iconst_0
L27:    iconst_1
L28:    dup
L29:    pop2
L30:    dup
L31:    istore_3
L32:    bipush 64
L34:    iconst_1
L35:    dup
L36:    pop2
L37:    if_icmpge L237
L40:    iconst_0
L41:    iconst_1
L42:    dup
L43:    pop2
L44:    dup
L45:    istore 4
L47:    iconst_4
L48:    iconst_1
L49:    dup
L50:    pop2
L51:    if_icmpge L229
L54:    aload_1
L55:    bipush 64
L57:    iconst_1
L58:    dup
L59:    pop2
L60:    iload_2
L61:    imul
L62:    iload_3
L63:    iadd
L64:    iconst_4
L65:    iconst_1
L66:    dup
L67:    pop2
L68:    imul
L69:    iload 4
L71:    iadd
L72:    aload_0
L73:    sipush 128
L76:    iconst_1
L77:    dup
L78:    pop2
L79:    iload_2
L80:    imul
L81:    iconst_2
L82:    iconst_1
L83:    dup
L84:    pop2
L85:    imul
L86:    iload_3
L87:    iconst_2
L88:    iconst_1
L89:    dup
L90:    pop2
L91:    imul
L92:    iadd
L93:    iconst_4
L94:    iconst_1
L95:    dup
L96:    pop2
L97:    imul
L98:    iload 4
L100:   iadd
L101:   iaload
L102:   aload_0
L103:   sipush 128
L106:   iconst_1
L107:   dup
L108:   pop2
L109:   iload_2
L110:   imul
L111:   iconst_2
L112:   iconst_1
L113:   dup
L114:   pop2
L115:   imul
L116:   iload_3
L117:   iconst_2
L118:   iconst_1
L119:   dup
L120:   pop2
L121:   imul
L122:   iadd
L123:   iconst_1
L124:   dup
L125:   dup
L126:   pop2
L127:   iadd
L128:   iconst_4
L129:   iconst_1
L130:   dup
L131:   pop2
L132:   imul
L133:   iload 4
L135:   iadd
L136:   iaload
L137:   iadd
L138:   aload_0
L139:   sipush 128
L142:   iconst_1
L143:   dup
L144:   pop2
L145:   iload_2
L146:   imul
L147:   iconst_2
L148:   iconst_1
L149:   dup
L150:   pop2
L151:   imul
L152:   iload_3
L153:   iconst_2
L154:   iconst_1
L155:   dup
L156:   pop2
L157:   imul
L158:   iadd
L159:   sipush 128
L162:   iconst_1
L163:   dup
L164:   pop2
L165:   iadd
L166:   iconst_4
L167:   iconst_1
L168:   dup
L169:   pop2
L170:   imul
L171:   iload 4
L173:   iadd
L174:   iaload
L175:   iadd
L176:   aload_0
L177:   sipush 128
L180:   iconst_1
L181:   dup
L182:   pop2
L183:   iload_2
L184:   imul
L185:   iconst_2
L186:   iconst_1
L187:   dup
L188:   pop2
L189:   imul
L190:   iload_3
L191:   iconst_2
L192:   iconst_1
L193:   dup
L194:   pop2
L195:   imul
L196:   iadd
L197:   sipush 129
L200:   iconst_1
L201:   dup
L202:   pop2
L203:   iadd
L204:   iconst_4
L205:   iconst_1
L206:   dup
L207:   pop2
L208:   imul
L209:   iload 4
L211:   iadd
L212:   iaload
L213:   iadd
L214:   iconst_4
L215:   iconst_1
L216:   dup
L217:   pop2
L218:   idiv
L219:   iinc 4 1
L222:   iastore
L223:   iload 4
L225:   goto L47
L228:   athrow
L229:   iinc 3 1
L232:   iload_3
L233:   goto L32
L236:   athrow
L237:   iinc 2 1
L240:   iload_2
L241:   goto L18
L244:   aload_1
L245:   areturn
L246:   
        .attribute StackMap b'\x00\x08\x00\x12\x00\x03\x07\x00\x4D\x07\x00\x4D\x01\x00\x01\x01\x00\x20\x00\x04\x07\x00\x4D\x07\x00\x4D\x01\x01\x00\x01\x01\x00\x2F\x00\x05\x07\x00\x4D\x07\x00\x4D\x01\x01\x01\x00\x01\x01\x00\xE4\x00\x00\x00\x01\x07\x00\x47\x00\xE5\x00\x05\x07\x00\x4D\x07\x00\x4D\x01\x01\x01\x00\x00\x00\xEC\x00\x00\x00\x01\x07\x00\x47\x00\xED\x00\x04\x07\x00\x4D\x07\x00\x4D\x01\x01\x00\x00\x00\xF4\x00\x03\x07\x00\x4D\x07\x00\x4D\x01\x00\x00'
    .end code
.end method

.method public static synthetic else : (F)F
    .code stack 2 locals 1
L0:     fload_0
L1:     dup
L2:     putstatic Field mD "enum" F
L5:     freturn
L6:     
    .end code
.end method

.method public static const : ()V
    .code stack 6 locals 4
L0:     invokestatic Method java/lang/Runtime getRuntime ()Ljava/lang/Runtime;
L3:     invokevirtual Method java/lang/Runtime availableProcessors ()I
L6:     invokestatic Method java/util/concurrent/Executors newFixedThreadPool (I)Ljava/util/concurrent/ExecutorService;
L9:     astore_0
L10:    bipush 20
L12:    iconst_1
L13:    dup
L14:    pop2
L15:    anewarray java/util/concurrent/Future
L18:    iconst_1
L19:    dup
L20:    pop2
L21:    astore_1
L22:    iconst_0
L23:    iconst_1
L24:    dup
L25:    pop2
L26:    dup
L27:    istore_2
L28:    bipush 20
L30:    iconst_1
L31:    dup
L32:    pop2
L33:    if_icmpge L66
L36:    iload_2
L37:    istore_3
L38:    aload_1
L39:    iload_2
L40:    new Bc
L43:    aload_0
L44:    dup_x1
L45:    dup
L46:    pop2
L47:    dup
L48:    iload_3
L49:    invokespecial Method Bc <init> (I)V
L52:    invokeinterface InterfaceMethod java/util/concurrent/ExecutorService submit (Ljava/util/concurrent/Callable;)Ljava/util/concurrent/Future; 2
L57:    iinc 2 1
L60:    aastore
L61:    iload_2
L62:    goto L28
L65:    athrow
L66:    iconst_0
L67:    iconst_1
L68:    dup
L69:    pop2
L70:    dup
L71:    istore_2
L72:    bipush 20
L74:    iconst_1
L75:    dup
L76:    pop2
L77:    if_icmpge L104
L80:    getstatic Field mD else [[Ljava/nio/ByteBuffer;
L83:    aload_1
L84:    iload_2
L85:    dup_x1
L86:    aaload
L87:    invokeinterface InterfaceMethod java/util/concurrent/Future get ()Ljava/lang/Object; 1
L92:    checkcast [Ljava/nio/ByteBuffer;
L95:    iinc 2 1
L98:    aastore
L99:    iload_2
L100:   goto L72
L103:   athrow
L104:   aload_0
L105:   invokeinterface InterfaceMethod java/util/concurrent/ExecutorService shutdown ()V 1
L110:   invokestatic Method mD catch ()V
L113:   return
L114:   
        .attribute StackMap b'\x00\x06\x00\x1C\x00\x03\x07\x00\xE2\x07\x00\xE4\x01\x00\x01\x01\x00\x41\x00\x00\x00\x01\x07\x00\x47\x00\x42\x00\x03\x07\x00\xE2\x07\x00\xE4\x01\x00\x00\x00\x48\x00\x03\x07\x00\xE2\x07\x00\xE4\x01\x00\x01\x01\x00\x67\x00\x00\x00\x01\x07\x00\x47\x00\x68\x00\x03\x07\x00\xE2\x07\x00\xE4\x01\x00\x00'
    .end code
    .exceptions java/lang/Exception
.end method

.method public static synthetic else : ()F
    .code stack 1 locals 0
L0:     getstatic Field mD "enum" F
L3:     freturn
L4:     
    .end code
.end method

.method public static break : ()V
    .code stack 3 locals 0
L0:     iconst_0
L1:     iconst_1
L2:     dup
L3:     pop2
L4:     putstatic Field mD do Z
L7:     return
L8:     
    .end code
.end method

.method private static break : (F)[Ljava/nio/ByteBuffer;
    .code stack 6 locals 5
L0:     fload_0
L1:     invokestatic Method mD short (F)[I
L4:     dup
L5:     invokestatic Method mD break ([I)[I
L8:     dup
L9:     astore_1
L10:    invokestatic Method mD const ([I)[I
L13:    dup
L14:    astore_2
L15:    invokestatic Method mD else ([I)[I
L18:    astore_3
L19:    invokestatic Method mD short ([I)[B
L22:    astore 4
L24:    aload_1
L25:    invokestatic Method mD short ([I)[B
L28:    astore_1
L29:    aload_2
L30:    invokestatic Method mD short ([I)[B
L33:    astore_2
L34:    aload_3
L35:    invokestatic Method mD short ([I)[B
L38:    astore_3
L39:    iconst_4
L40:    iconst_1
L41:    dup
L42:    pop2
L43:    anewarray java/nio/ByteBuffer
L46:    iconst_1
L47:    dup
L48:    pop2
L49:    dup
L50:    iconst_0
L51:    iconst_1
L52:    dup
L53:    pop2
L54:    ldc 65536
L56:    invokestatic Method java/nio/ByteBuffer allocateDirect (I)Ljava/nio/ByteBuffer;
L59:    aload 4
L61:    invokevirtual Method java/nio/ByteBuffer put ([B)Ljava/nio/ByteBuffer;
L64:    invokevirtual Method java/nio/ByteBuffer rewind ()Ljava/nio/Buffer;
L67:    checkcast java/nio/ByteBuffer
L70:    aastore
L71:    dup
L72:    iconst_1
L73:    dup
L74:    pop2
L75:    sipush 16384
L78:    iconst_1
L79:    dup_x1
L80:    dup
L81:    pop2
L82:    invokestatic Method java/nio/ByteBuffer allocateDirect (I)Ljava/nio/ByteBuffer;
L85:    aload_1
L86:    invokevirtual Method java/nio/ByteBuffer put ([B)Ljava/nio/ByteBuffer;
L89:    invokevirtual Method java/nio/ByteBuffer rewind ()Ljava/nio/Buffer;
L92:    checkcast java/nio/ByteBuffer
L95:    aastore
L96:    dup
L97:    iconst_2
L98:    iconst_1
L99:    dup
L100:   pop2
L101:   sipush 4096
L104:   iconst_1
L105:   dup
L106:   pop2
L107:   invokestatic Method java/nio/ByteBuffer allocateDirect (I)Ljava/nio/ByteBuffer;
L110:   aload_2
L111:   invokevirtual Method java/nio/ByteBuffer put ([B)Ljava/nio/ByteBuffer;
L114:   invokevirtual Method java/nio/ByteBuffer rewind ()Ljava/nio/Buffer;
L117:   checkcast java/nio/ByteBuffer
L120:   aastore
L121:   dup
L122:   iconst_3
L123:   iconst_1
L124:   dup
L125:   pop2
L126:   sipush 1024
L129:   iconst_1
L130:   dup
L131:   pop2
L132:   invokestatic Method java/nio/ByteBuffer allocateDirect (I)Ljava/nio/ByteBuffer;
L135:   aload_3
L136:   invokevirtual Method java/nio/ByteBuffer put ([B)Ljava/nio/ByteBuffer;
L139:   invokevirtual Method java/nio/ByteBuffer rewind ()Ljava/nio/Buffer;
L142:   checkcast java/nio/ByteBuffer
L145:   aastore
L146:   areturn
L147:   
    .end code
.end method
.innerclasses
    Bc [0] [0] static
    xb [0] [0] static
.end innerclasses
.const [_184] = String [_183]
.const [_186] = String [_185]
.const [_188] = String [_187]
.const [_190] = String [_189]
.const [_183] = Utf8 "000000000000000000000000000000000000000000000000000000000000000000000000000000000000000000000000000000000000000000000000000000000000000000000000000000000000000000000000000000000000000000000000000000000000000000000000000000000000000000000000000000000000000000000000000000000000000000000000000000000000000000000000000000000000000000000000000000000000000000000000000000000000000000000000000000000000000000000000000000000000000000000000000000000000000000000000000000000000000000000000000000000000000000000000000000000000000000000000000000000000000000000000000000000000000000000000000000000000000000000000000000000000000000000000000000000000000000000000000000000000000000000000000000000000000000000000000000000000000000000000000000000000000000000000000000000000000000000000000000000000000000000000000000000000000000000000000000000000000000000000000000000000000000000000000000000000000000000000000000000000000000000000000000000000000000000000000000000000000000000000000000000000000000000000000000000000000000000000000000000000000000000000000000000000000000000000000000000000000000000000000000000000000000000000000000000000000000000000000000000000000000000000000000000000000000000000000000000000000000000000000000010000000100000001000000010000000100000001000000010000000100000001000000010000000100000001000000010000000100000001000000010000000100000001000000010000000100000001000000010000000100000001000000010000000100000001000000010000000100000001000000010000000100000001000000010000000100000001000000010000000100000001000000010000000100000001000000010000000100000001000000010000000100000001000000010000000100000001000000010000000100000001000000010000000100000001000000010000000100000001000000010000000100000001000000010000000100000001000000010000000100000001000000010000000100000001000000010000000100000001000000010000000100000001000000010000000100000001000000010000000100000001000000010000000000000000000000000000000000000000000000000000000000000000000000000000000000000000000000000000000000000000000000000000000000000000000000000000000000000000000000000000000000000000000000000000000000000000000000000000000000000000000000000000000000000000000000000000000100000001000000020000000300000004000000040000000400000004000000040000000400000004000000050000000500000005000000050000000500000005000000050000000500000005000000050000000500000005000000050000000500000005000000050000000500000005000000050000000500000005000000050000000500000005000000050000000500000005000000050000000500000005000000050000000500000005000000050000000500000005000000050000000500000005000000050000000500000005000000050000000500000005000000050000000500000005000000050000000500000005000000050000000500000005000000050000000500000005000000050000000500000005000000050000000500000005000000050000000500000005000000050000000500000005000000050000000500000005000000050000000500000005000000050000000500000005000000050000000500000005000000050000000500000004000000040000000400000004000000040000000400000004000000030000000300000002000000010000000000000000000000000000000000000000000000000000000000000000000000000000000000000000000000000000000000000000000000000000000000000000000000000000000000000000000000000000000100000002000000040000000600000007000000090000000b0000000b0000000c0000000d0000000d0000000d0000000d0000000d0000000e0000000e0000000e0000000e0000000e0000000e0000000e0000000e0000000e0000000e0000000e0000000e0000000e0000000e0000000e0000000e0000000e0000000e0000000e0000000e0000000e0000000e0000000e0000000e0000000e0000000e0000000e0000000e0000000e0000000e0000000e0000000e0000000e0000000e0000000e0000000e0000000e0000000e0000000e0000000e0000000e0000000e0000000e0000000e0000000e0000000e0000000e0000000e0000000e0000000e0000000e0000000e0000000e0000000e0000000e0000000e0000000e0000000e0000000e0000000e0000000e0000000e0000000e0000000e0000000e0000000e0000000e0000000e0000000e0000000e0000000e0000000e0000000e0000000e0000000e0000000e0000000e0000000e0000000e0000000e0000000e0000000d0000000d0000000d0000000d0000000d0000000d0000000c0000000b0000000a00000008000000060000000500000003000000010000000100000000000000000000000000000000000000000000000000000000000000000000000000000000000000000000000000000000000000000000000000000000000000010000000200000004000000070000000a0000000e000000110000001500000017000000190000001a0000001b0000001b0000001b0000001b0000001b0000001c0000001c0000001c0000001c0000001c0000001c0000001c0000001c0000001c0000001c0000001c0000001c0000001c0000001c0000001c0000001c0000001c0000001c0000001c0000001c0000001c0000001c0000001c0000001c0000001c0000001c0000001c0000001c0000001c0000001c0000001c0000001c0000001c0000001c0000001c0000001c0000001c0000001c0000001c0000001c0000001c0000001c0000001c0000001c0000001c0000001c0000001c0000001c0000001c0000001c0000001c0000001c0000001c0000001c0000001c0000001c0000001c0000001c0000001c0000001c0000001c0000001c0000001c0000001c0000001c0000001c0000001c0000001c0000001c0000001c0000001c0000001c0000001c0000001c0000001c0000001c0000001c0000001c0000001c0000001c0000001c0000001c0000001b0000001b0000001b0000001b0000001b0000001a000000180000001600000013000000100000000b0000000800000005000000030000000100000000000000000000000000000000000000000000000000000000000000000000000000000000000000000000000000000000000000000000000100000003000000060000000a0000000f000000160000001c00000022000000270000002c0000002f000000310000003200000033000000330000003300000033000000340000003400000034000000340000003400000034000000340000003400000034000000340000003400000034000000340000003400000034000000340000003400000034000000340000003400000034000000340000003400000034000000340000003400000034000000340000003400000034000000340000003400000034000000340000003400000034000000340000003400000034000000340000003400000034000000340000003400000034000000340000003400000034000000340000003400000034000000340000003400000034000000340000003400000034000000340000003400000034000000340000003400000034000000340000003400000034000000340000003400000034000000340000003400000034000000340000003400000034000000340000003400000034000000340000003400000034000000330000003300000033000000330000003300000031000000300000002d0000002a000000250000001f00000018000000120000000c0000000800000004000000020000000000000000000000000000000000000000000000000000000000000000000000000000000000000000000000000000000200000004000000080000000d000000150000001d0000002700000033120c09531810096a17110a7517110a7717110a7817100a7916100a7a16100a7a16100a7a16100a7a16100a7a16100a7a16100a7a16100a7a16100a7a16100a7a16100a7a16100a7a16100a7a16100a7a16100a7a16100a7a16100a7a16100a7a16100a7a16100a7a16100a7a16100a7a16100a7a16100a7a16100a7a16100a7a16100a7a16100a7a16100a7a16100a7a16100a7a16100a7a16100a7a16100a7a16100a7a16100a7a16100a7a16100a7a16100a7a16100a7a16100a7a16100a7a16100a7a16100a7a16100a7a16100a7a16100a7a16100a7a16100a7a16100a7a16100a7a16100a7a16100a7a16100a7a16100a7a16100a7a16100a7a16100a7a16100a7a16100a7a16100a7a16100a7a16100a7a16100a7a16100a7a16100a7a16100a7a16100a7a16100a7a16100a7a16100a7a16100a7a16100a7a16100a7a16100a7a16100a7a16100a7a16100a7a16100a7a16100a7a16100a7a16100a7a16100a7a16100a7a16100a7a16100a7a16100a7a16100a7a16100a7a16100a7a17100a7917110a78110c07650603034d0000003e000000350000002b000000210000001800000010000000090000000500000002000000010000000000000000000000000000000000000000000000000000000000000000000000000000000200000004000000080000000f0000001800000024000000341f170d81291e13d92b2015fd2c2015ff2c2015ff2c2015ff2c2015ff2c2015ff2c2015ff2c2015ff2c2015ff2c2015ff2c2015ff2c2015ff2c2015ff2c2015ff2c2015ff2c2015ff2c2015ff2c2015ff2c2015ff2c2015ff2c2015ff2c2015ff2c2015ff2c2015ff2c2015ff2c2015ff2c2015ff2c2015ff2c2015ff2c2015ff2c2015ff2c2015ff2c2015ff2c2015ff2c2015ff2c2015ff2c2015ff2c2015ff2c2015ff2c2015ff2c2015ff2c2015ff2c2015ff2c2015ff2c2015ff2c2015ff2c2015ff2c2015ff2c2015ff2c2015ff2c2015ff2c2015ff2c2015ff2c2015ff2c2015ff2c2015ff2c2015ff2c2015ff2c2015ff2c2015ff2c2015ff2c2015ff2c2015ff2c2015ff2c2015ff2c2015ff2c2015ff2c2015ff2c2015ff2c2015ff2c2015ff2c2015ff2c2015ff2c2015ff2c2015ff2c2015ff2c2015ff2c2015ff2c2015ff2c2015ff2c2015ff2c2015ff2c2015ff2c2015ff2c2015ff2c2015ff2c2015ff2c2015ff2c2015ff2c2015ff2c2015ff2c2015ff2c2015ff2c2015ff2c2015ff2c2015ff2c2015ff2c2015ff2c2015ff291f14ed221a10af0805025e0000004500000037000000280000001c000000120000000b000000050000000200000000000000000000000000000000000000000000000000000000000000000000000100000003000000080000000f0000001900000027100c064f281e12ca2c2115fe2c2115ff2c2115ff2c2115ff2c2115ff2c2115ff2c2115ff2c2115ff2c2115ff2c2115ff2c2115ff2c2115ff2c2115ff2c2115ff2c2115ff2c2115ff2c2115ff2c2115ff2c2115ff2c2115ff2c2115ff2c2115ff2c2115ff2c2115ff2c2115ff2c2115ff2c2115ff2c2115ff2c2115ff2c2115ff2c2115ff2c2115ff2c2115ff2c2115ff2c2115ff2c2115ff2c2115ff2c2115ff2c2115ff2c2115ff2c2115ff2c2115ff2c2115ff2c2115ff2c2115ff2c2115ff2c2115ff2c2115ff2c2115ff2c2115ff2c2115ff2c2115ff2c2115ff2c2115ff2c2115ff2c2115ff2c2115ff2c2115ff2c2115ff2c2115ff2c2115ff2c2115ff2c2115ff2c2115ff2c2115ff2c2115ff2c2115ff2c2115ff2c2115ff2c2115ff2c2115ff2c2115ff2c2115ff2c2115ff2c2115ff2c2115ff2c2115ff2c2115ff2c2115ff2c2115ff2c2115ff2c2115ff2c2115ff2c2115ff2c2115ff2c2115ff2c2115ff2c2115ff2c2115ff2c2115ff2c2115ff2c2115ff2c2115ff2c2115ff2c2115ff2c2115ff2c2115ff2c2115ff2c2115ff2c2115ff2c2115ff2c2115ff2c2115ff2a1f13eb18130c90000000520000003f0000002d0000001e000000120000000a00000005000000020000000000000000000000000000000000000000000000000000000000000002000000060000000d00000018000000271e140d6e2b2015ed2d2116ff2d2116ff2d2116ff2d2116ff2d2116ff2d2116ff2d2116ff2d2116ff2d2116ff2d2116ff2d2116ff2d2116ff2d2116ff2d2116ff2d2116ff2d2116ff2d2116ff2d2116ff2d2116ff2d2116ff2d2116ff2d2116ff2d2116ff2d2116ff2d2116ff2d2116ff2d2116ff2d2116ff2d2116ff2d2116ff2d2116ff2d2116ff2d2116ff2d2116ff2d2116ff2d2116ff2d2116ff2d2116ff2d2116ff2d2116ff2d2116ff2d2116ff2d2116ff2d2116ff2d2116ff2d2116ff2d2116ff2d2116ff2d2116ff2d2116ff2d2116ff2d2116ff2d2116ff2d2116ff2d2116ff2d2116ff2d2116ff2d2116ff2d2116ff2d2116ff2d2116ff2d2116ff2d2116ff2d2116ff2d2116ff2d2116ff2d2116ff2d2116ff2d2116ff2d2116ff2d2116ff2d2116ff2d2116ff2d2116ff2d2116ff2d2116ff2d2116ff2d2116ff2d2116ff2d2116ff2d2116ff2d2116ff2d2116ff2d2116ff2d2116ff2d2116ff2d2116ff2d2116ff2d2116ff2d2116ff2d2116ff2d2116ff2d2116ff2d2116ff2d2116ff2d2116ff2d2116ff2d2116ff2d2116ff2d2116ff2d2116ff2d2116ff2d2116ff2d2116ff2d2116ff2c2015fd231910b500000059000000420000002e0000001d00000011000000080000000400000001000000000000000000000000000000000000000000000001000000040000000b0000001500000024120f09532b2115ef2d2116ff2d2116ff2d2116ff2d2116ff2d2116ff2d2116ff2d2116ff2d2116ff2d2116ff2d2116ff2d2116ff2d2116ff2d2116ff2d2116ff2d2116ff2d2116ff2d2116ff2d2116ff2d2116ff2d2116ff2d2116ff2d2116ff2d2116ff2d2116ff2d2116ff2d2116ff2d2116ff2d2116ff2d2116ff2d2116ff2d2116ff2d2116ff2d2116ff2d2116ff2d2116ff2d2116ff2d2116ff2d2116ff2d2116ff2d2116ff2d2116ff2d2116ff2d2116ff2d2116ff2d2116ff2d2116ff2d2116ff2d2116ff2d2116ff2d2116ff2d2116ff2d2116ff2d2116ff2d2116ff2d2116ff2d2116ff2d2116ff2d2116ff2d2116ff2d2116ff2d2116ff2d2116ff2d2116ff2d2116ff2d2116ff2d2116ff2d2116ff2d2116ff2d2116ff2d2116ff2d2116ff2d2116ff2d2116ff2d2116ff2d2116ff2d2116ff2d2116ff2d2116ff2d2116ff2d2116ff2d2116ff2d2116ff2d2116ff2d2116ff2d2116ff2d2116ff2d2116ff2d2116ff2d2116ff2d2116ff2d2116ff2d2116ff2d2116ff2d2116ff2d2116ff2d2116ff2d2116ff2d2116ff2d2116ff2d2116ff2d2116ff2d2116ff2d2116ff2d2116ff2d2116ff2d2116ff2d2116ff2c2116fe1c140ca000000059000000400000002b0000001a0000000e000000060000000200000000000000000000000000000000000000000000000200000007000000100000001e00000034291f14cb2d2216ff2d2216ff2d2216ff2d2216ff2d2216ff2d2216ff2d2216ff2d2216ff2d2216ff2d2216ff2d2216ff2d2216ff2d2216ff2d2216ff2d2216ff2d2216ff2d2216ff2d2216ff2d2216ff2d2216ff2d2216ff2d2216ff2d2216ff2d2216ff2d2216ff2d2216ff2d2216ff2d2216ff2d2216ff2d2216ff2d2216ff2d2216ff2d2216ff2d2216ff2d2216ff2d2216ff2d2216ff2d2216ff2d2216ff2d2216ff2d2216ff2d2216ff2d2216ff2d2216ff2d2216ff2d2216ff2d2216ff2d2216ff2d2216ff2d2216ff2d2216ff2d2216ff2d2216ff2d2216ff2d2216ff2d2216ff2d2216ff2d2216ff2d2216ff2d2216ff2d2216ff2d2216ff2d2216ff2d2216ff2d2216ff2d2216ff2d2216ff2d2216ff2d2216ff2d2216ff2d2216ff2d2216ff2d2216ff2d2216ff2d2216ff2d2216ff2d2216ff2d2216ff2d2216ff2d2216ff2d2216ff2d2216ff2d2216ff2d2216ff2d2216ff2d2216ff2d2216ff2d2216ff2d2216ff2d2216ff2d2216ff2d2216ff2d2216ff2d2216ff2d2216ff2d2216ff2d2216ff2d2216ff2d2216ff2d2216ff2d2216ff2d2216ff2d2216ff2d2216ff2d2216ff2d2216ff2d2216ff2d2216ff2d2216ff2c2114f60c08067f000000550000003a00000025000000140000000a000000040000000100000000000000000000000000000001000000040000000b00000016000000281f170f812e2216fe2e2216ff2e2216ff2e2216ff2e2216ff2e2216ff2e2216ff2e2216ff2e2216ff2e2216ff2e2216ff2e2216ff2e2216ff2e2216ff2e2216ff2e2216ff2e2216ff2e2216ff2e2216ff2e2216ff2e2216ff2e2216ff2e2216ff2e2216ff2e2216ff2e2216ff2e2216ff2e2216ff2e2216ff2e2216ff2e2216ff2e2216ff2e2216ff2e2216ff2e2216ff2e2216ff2e2216ff2e2216ff2e2216ff2e2216ff2e2216ff2e2216ff2e2216ff2e2216ff2e2216ff2e2216ff2e2216ff2e2216ff2e2216ff2e2216ff2e2216ff2e2216ff2e2216ff2e2216ff2e2216ff2e2216ff2e2216ff2e2216ff2e2216ff2e2216ff2e2216ff2e2216ff2e2216ff2e2216ff2e2216ff2e2216ff2e2216ff2e2216ff2e2216ff2e2216ff2e2216ff2e2216ff2e2216ff2e2216ff2e2216ff2e2216ff2e2216ff2e2216ff2e2216ff2e2216ff2e2216ff2e2216ff2e2216ff2e2216ff2e2216ff2e2216ff2e2216ff2e2216ff2e2216ff2e2216ff2e2216ff2e2216ff2e2216ff2e2216ff2e2216ff2e2216ff2e2216ff2e2216ff2e2216ff2e2216ff2e2216ff2e2216ff2e2216ff2e2216ff2e2216ff2e2216ff2e2216ff2e2216ff2e2216ff2e2216ff2e2216ff271d12d1000000690000004a000000300000001c0000000e000000060000000200000000000000000000000000000002000000060000000e0000001c000000342b2015d92e2217ff2e2217ff2e2217ff2e2217ff2e2217ff2e2217ff2e2217ff2e2217ff2e2217ff2e2217ff2e2217ff2e2217ff2e2217ff2e2217ff2e2217ff2e2217ff2e2217ff2e2217ff2e2217ff2e2217ff2e2217ff2e2217ff2e2217ff2e2217ff2e2217ff2e2217ff2e2217ff2e2217ff2e2217ff2e2217ff2e2217ff2e2217ff2e2217ff2e2217ff2e2217ff2e2217ff2e2217ff2e2217ff2e2217ff2e2217ff2e2217ff2e2217ff2e2217ff2e2217ff2e2217ff2e2217ff2e2217ff2e2217ff2e2217ff2e2217ff2e2217ff2e2217ff2e2217ff2e2217ff2e2217ff2e2217ff2e2217ff2e2217ff2e2217ff2e2217ff2e2217ff2e2217ff2e2217ff2e2217ff2e2217ff2e2217ff2e2217ff2e2217ff2e2217ff2e2217ff2e2217ff2e2217ff2e2217ff2e2217ff2e2217ff2e2217ff2e2217ff2e2217ff2e2217ff2e2217ff2e2217ff2e2217ff2e2217ff2e2217ff2e2217ff2e2217ff2e2217ff2e2217ff2e2217ff2e2217ff2e2217ff2e2217ff2e2217ff2e2217ff2e2217ff2e2217ff2e2217ff2e2217ff2e2217ff2e2217ff2e2217ff2e2217ff2e2217ff2e2217ff2e2217ff2e2217ff2e2217ff2e2217ff2e2217ff2e2217ff2e2217ff2e2216fd0e0b07890000005a0000003c0000002400000013000000090000000300000000000000000000000000000003000000080000001200000023120c09532e2216fd2f2317ff2f2317ff2f2317ff2f2317ff2f2317ff2f2317ff2f2317ff2f2317ff2f2317ff2f2317ff2f2317ff2f2317ff2f2317ff2f2317ff2f2317ff2f2317ff2f2317ff2f2317ff2f2317ff2f2317ff2f2317ff2f2317ff2f2317ff2f2317ff2f2317ff2f2317ff2f2317ff2f2317ff2f2317ff2f2317ff2f2317ff2f2317ff2f2317ff2f2317ff2f2317ff2f2317ff2f2317ff2f2317ff2f2317ff2f2317ff2f2317ff2f2317ff2f2317ff2f2317ff2f2317ff2f2317ff2f2317ff2f2317ff2f2317ff2f2317ff2f2317ff2f2317ff2f2317ff2f2317ff2f2317ff2f2317ff2f2317ff2f2317ff2f2317ff2f2317ff2f2317ff2f2317ff2f2317ff2f2317ff2f2317ff2f2317ff2f2317ff2f2317ff2f2317ff2f2317ff2f2317ff2f2317ff2f2317ff2f2317ff2f2317ff2f2317ff2f2317ff2f2317ff2f2317ff2f2317ff2f2317ff2f2317ff2f2317ff2f2317ff2f2317ff2f2317ff2f2317ff2f2317ff2f2317ff2f2317ff2f2317ff2f2317ff2f2317ff2f2317ff2f2317ff2f2317ff2f2317ff2f2317ff2f2317ff2f2317ff2f2317ff2f2317ff2f2317ff2f2317ff2f2317ff2f2317ff2f2317ff2f2317ff2f2317ff2f2317ff2f2317ff2f2317ff20170fba00000067000000470000002c000000180000000b00000004000000010000000000000000000000030000000900000015000000281a130b6b2f2317ff2f2317ff2f2317ff2f2317ff2f2317ff2f2317ff2f2317ff2f2317ff2f2317ff2f2317ff2f2317ff2f2317ff2f2317ff2f2317ff2f2317ff2f2317ff2f2317ff2f2317ff2f2317ff2f2317ff2f2317ff2f2317ff2f2317ff2f2317ff2f2317ff2f2317ff2f2317ff2f2317ff2f2317ff2f2317ff2f2317ff2f2317ff2f2317ff2f2317ff2f2317ff2f2317ff2f2317ff2f2317ff2f2317ff2f2317ff2f2317ff2f2317ff2f2317ff2f2317ff2f2317ff2f2317ff2f2317ff2f2317ff2f2317ff2f2317ff2f2317ff2f2317ff2f2317ff2f2317ff2f2317ff2f2317ff2f2317ff2f2317ff2f2317ff2f2317ff2f2317ff2f2317ff2f2317ff2f2317ff2f2317ff2f2317ff2f2317ff2f2317ff2f2317ff2f2317ff2f2317ff2f2317ff2f2317ff2f2317ff2f2317ff2f2317ff2f2317ff2f2317ff2f2317ff2f2317ff2f2317ff2f2317ff2f2317ff2f2317ff2f2317ff2f2317ff2f2317ff2f2317ff2f2317ff2f2317ff2f2317ff2f2317ff2f2317ff2f2317ff2f2317ff2f2317ff2f2317ff2f2317ff2f2317ff2f2317ff2f2317ff2f2317ff2f2317ff2f2317ff2f2317ff2f2317ff2f2317ff2f2317ff2f2317ff2f2317ff2f2317ff2f2317ff2f2317ff251b12cd0000007300000050000000330000001c0000000e00000006000000010000000000000001000000040000000b000000170000002c1c130d75302317ff302317ff302317ff302317ff302317ff302317ff302317ff302317ff302317ff302317ff302317ff302317ff302317ff302317ff302317ff302317ff302317ff302317ff302317ff302317ff302317ff302317ff302317ff302317ff302317ff302317ff302317ff302317ff302317ff302317ff302317ff302317ff302317ff302317ff302317ff302317ff302317ff302317ff302317ff302317ff302317ff302317ff302317ff302317ff302317ff302317ff302317ff302317ff302317ff302317ff302317ff302317ff302317ff302317ff302317ff302317ff302317ff302317ff302317ff302317ff302317ff302317ff302317ff302317ff302317ff302317ff302317ff302317ff302317ff302317ff302317ff302317ff302317ff302317ff302317ff302317ff302317ff302317ff302317ff302317ff302317ff302317ff302317ff302317ff302317ff302317ff302317ff302317ff302317ff302317ff302317ff302317ff302317ff302317ff302317ff302317ff302317ff302317ff302317ff302317ff302317ff302317ff302317ff302317ff302317ff302317ff302317ff302317ff302317ff302317ff302317ff302317ff302317ff291e13d90000007c0000005800000038000000200000001000000006000000010000000000000001000000040000000c0000001a0000002f1b130c77302417ff302417ff302417ff302417ff302417ff302417ff302417ff302417ff302417ff302417ff302417ff302417ff302417ff302417ff302417ff302417ff302417ff302417ff302417ff302417ff302417ff302417ff302417ff302417ff302417ff302417ff302417ff302417ff302417ff302417ff302417ff302417ff302417ff302417ff302417ff302417ff302417ff302417ff302417ff302417ff302417ff302417ff302417ff302417ff302417ff302417ff302417ff302417ff302417ff302417ff302417ff302417ff302417ff302417ff302417ff302417ff302417ff302417ff302417ff302417ff302417ff302417ff302417ff302417ff302417ff302417ff302417ff302417ff302417ff302417ff302417ff302417ff302417ff302417ff302417ff302417ff302417ff302417ff302417ff302417ff302417ff302417ff302417ff302417ff302417ff302417ff302417ff302417ff302417ff302417ff302417ff302417ff302417ff302417ff302417ff302417ff302417ff302417ff302417ff302417ff302417ff302417ff302417ff302417ff302417ff302417ff302417ff302417ff302417ff302417ff302417ff302417ff302417ff281e13da000000820000005d0000003c000000230000001100000007000000010000000000000001000000050000000c0000001b000000311b120c79312418ff312418ff312418ff312418ff312418ff312418ff312418ff312418ff312418ff312418ff312418ff312418ff312418ff312418ff312418ff312418ff312418ff312418ff312418ff312418ff312418ff312418ff312418ff312418ff312418ff312418ff312418ff312418ff312418ff312418ff312418ff312418ff312418ff312418ff312418ff312418ff312418ff312418ff312418ff312418ff312418ff312418ff312418ff312418ff312418ff312418ff312418ff312418ff312418ff312418ff312418ff312418ff312418ff312418ff312418ff312418ff312418ff312418ff312418ff312418ff312418ff312418ff312418ff312418ff312418ff312418ff312418ff312418ff312418ff312418ff312418ff312418ff312418ff312418ff312418ff312418ff312418ff312418ff312418ff312418ff312418ff312418ff312418ff312418ff312418ff312418ff312418ff312418ff312418ff312418ff312418ff312418ff312418ff312418ff312418ff312418ff312418ff312418ff312418ff312418ff312418ff312418ff312418ff312418ff312418ff312418ff312418ff312418ff312418ff312418ff312418ff312418ff312418ff2a1e13da00000086000000600000003f000000240000001300000008000000020000000000000001000000050000000d0000001b000000321b120c7a312418ff312418ff312418ff312418ff312418ff312418ff312418ff312418ff312418ff312418ff312418ff312418ff312418ff312418ff312418ff312418ff312418ff312418ff312418ff312418ff312418ff312418ff312418ff312418ff312418ff312418ff312418ff312418ff312418ff312418ff312418ff312418ff312418ff312418ff312418ff312418ff312418ff312418ff312418ff312418ff312418ff312418ff312418ff312418ff312418ff312418ff312418ff312418ff312418ff312418ff312418ff312418ff312418ff312418ff312418ff312418ff312418ff312418ff312418ff312418ff312418ff312418ff312418ff312418ff312418ff312418ff312418ff312418ff312418ff312418ff312418ff312418ff312418ff312418ff312418ff312418ff312418ff312418ff312418ff312418ff312418ff312418ff312418ff312418ff312418ff312418ff312418ff312418ff312418ff312418ff312418ff312418ff312418ff312418ff312418ff312418ff312418ff312418ff312418ff312418ff312418ff312418ff312418ff312418ff312418ff312418ff312418ff312418ff312418ff312418ff312418ff312418ff312418ff2a1e13da000000880000006200000040000000250000001300000008000000020000000000000001000000050000000d0000001c000000331b120c7a322518ff322518ff322518ff322518ff322518ff322518ff322518ff322518ff322518ff322518ff322518ff322518ff322518ff322518ff322518ff322518ff322518ff322518ff322518ff322518ff322518ff322518ff322518ff322518ff322518ff322518ff322518ff322518ff322518ff322518ff322518ff322518ff322518ff322518ff322518ff322518ff322518ff322518ff322518ff322518ff322518ff322518ff322518ff322518ff322518ff322518ff322518ff322518ff322518ff322518ff322518ff322518ff322518ff322518ff322518ff322518ff322518ff322518ff322518ff322518ff322518ff322518ff322518ff322518ff322518ff322518ff322518ff322518ff322518ff322518ff322518ff322518ff322518ff322518ff322518ff322518ff322518ff322518ff322518ff322518ff322518ff322518ff322518ff322518ff322518ff322518ff322518ff322518ff322518ff322518ff322518ff322518ff322518ff322518ff322518ff322518ff322518ff322518ff322518ff322518ff322518ff322518ff322518ff322518ff322518ff322518ff322518ff322518ff322518ff322518ff322518ff322518ff322518ff2b1f13da000000890000006300000041000000260000001300000009000000020000000000000001000000050000000d0000001c000000331b120c7a322518ff322518ff322518ff322518ff322518ff322518ff322518ff322518ff322518ff322518ff322518ff322518ff322518ff322518ff322518ff322518ff322518ff322518ff322518ff322518ff322518ff322518ff322518ff322518ff322518ff322518ff322518ff322518ff322518ff322518ff322518ff322518ff322518ff322518ff322518ff322518ff322518ff322518ff322518ff322518ff322518ff322518ff322518ff322518ff322518ff322518ff322518ff322518ff322518ff322518ff322518ff322518ff322518ff322518ff322518ff322518ff322518ff322518ff322518ff322518ff33261aff372a1eff372a1eff372a1eff35281cff322518ff322518ff322518ff322518ff322518ff322518ff322518ff322518ff322518ff322518ff322518ff322518ff322518ff322518ff322518ff322518ff322518ff322518ff322518ff322518ff322518ff322518ff322518ff322518ff322518ff322518ff322518ff322518ff322518ff322518ff322518ff322518ff322518ff322518ff322518ff322518ff322518ff322518ff322518ff322518ff322518ff322518ff322518ff322518ff322518ff322518ff322518ff322518ff2b1f13da0000008a0000006400000042000000260000001400000009000000020000000000000001000000050000000e0000001c000000331b120c7a332519ff332519ff332519ff332519ff332519ff332519ff332519ff332519ff332519ff332519ff332519ff332519ff332519ff332519ff332519ff332519ff332519ff332519ff332519ff332519ff332519ff332519ff332519ff332519ff332519ff332519ff332519ff332519ff332519ff332519ff332519ff332519ff332519ff332519ff332519ff332519ff332519ff332519ff332519ff332519ff332519ff332519ff332519ff332519ff332519ff332519ff332519ff332519ff332519ff332519ff332519ff332519ff35281cff4d4136ff6c635aff908882ffaba5a0ffc0bbb7ffcdcac7ffd8d5d3ffdedcdaffecebeaffecebeaffecebeaffe6e4e3ffd8d5d3ffcac7c4ffbfbab7ffa8a29dff938c86ff766c65ff584d42ff3f3227ff332519ff332519ff332519ff332519ff332519ff332519ff332519ff332519ff332519ff332519ff332519ff332519ff332519ff332519ff332519ff332519ff332519ff332519ff332519ff332519ff332519ff332519ff332519ff332519ff332519ff332519ff332519ff332519ff332519ff332519ff332519ff332519ff332519ff332519ff332519ff332519ff332519ff332519ff332519ff332519ff2b1f15da0000008a0000006400000042000000270000001400000009000000020000000000000001000000050000000e0000001c000000331b140c7a332619ff332619ff332619ff332619ff332619ff332619ff332619ff332619ff332619ff332619ff332619ff332619ff332619ff332619ff332619ff332619ff332619ff332619ff332619ff332619ff332619ff332619ff332619ff332619ff332619ff332619ff332619ff332619ff332619ff332619ff332619ff332619ff332619ff332619ff332619ff332619ff332619ff332619ff332619ff332619ff332619ff332619ff332619ff332619ff332619ff332619ff332619ff332619ff33261aff4c4135ff7b736bffafaaa5ffdfdddbfffbfafafffffffffffffffffffffffffffffffffffffffffffffffffffffffffffefefefff9f9f9fffbfbfbfffffffffffffffffffffffffffffffffffffffffffffffffffffffffffefefefff3f2f2ffcfccc9ffa39d97ff6f665dff43372bff332619ff332619ff332619ff332619ff332619ff332619ff332619ff332619ff332619ff332619ff332619ff332619ff332619ff332619ff332619ff332619ff332619ff332619ff332619ff332619ff332619ff332619ff332619ff332619ff332619ff332619ff332619ff332619ff332619ff332619ff332619ff332619ff332619ff332619ff332619ff332619ff2b2015da0000008a0000006400000042000000270000001400000009000000020000000000000001000000050000000e0000001c000000341b140c7a332619ff332619ff332619ff332619ff332619ff332619ff332619ff332619ff332619ff332619ff332619ff332619ff332619ff332619ff332619ff332619ff332619ff332619ff332619ff332619ff332619ff332619ff332619ff332619ff332619ff332619ff332619ff332619ff332619ff332619ff332619ff332619ff332619ff332619ff332619ff332619ff332619ff332619ff332619ff332619ff332619ff332619ff332619ff332619ff332619ff332619ff4a3e32ff8b847dffcfccc9fff9f9f9fffffffffffffffffffffffffff6f6f6ffe2e1e1ffb4b3b2ff979593ff747270ff5a5654ff514d4bff3d3936ff383432ff25211eff2f2b28ff3d3936ff514d4bff5c5956ff777472ff817f7cffafadacffd3d2d1ffececebfffefefefffffffffffffffffffffffffff3f2f1ffbab6b2ff665c52ff392c1fff332619ff332619ff332619ff332619ff332619ff332619ff332619ff332619ff332619ff332619ff332619ff332619ff332619ff332619ff332619ff332619ff332619ff332619ff332619ff332619ff332619ff332619ff332619ff332619ff332619ff332619ff332619ff332619ff332619ff332619ff332619ff332619ff332619ff2b2015da0000008a0000006400000042000000270000001400000009000000020000000000000001000000050000000e0000001c000000341b140c7a342619ff342619ff342619ff342619ff342619ff342619ff342619ff342619ff342619ff342619ff342619ff342619ff342619ff342619ff342619ff342619ff342619ff342619ff342619ff342619ff342619ff342619ff342619ff342619ff342619ff342619ff342619ff342619ff342619ff342619ff342619ff342619ff342619ff342619ff342619ff342619ff342619ff342619ff342619ff342619ff342619ff342619ff342619ff36291cff6c6259ffc2bebafff7f6f6fffffffffffffffffff8f7f7ffcac9c8ff868482ff514e4bff272420ff14100cff100b08ff100b08ff100b08ff100b08ff100b08ff100b08ff100b08ff100b08ff100b08ff100b08ff100b08ff100b08ff100b08ff100b08ff100b08ff110d09ff181411ff413e3bff706e6bffaeadabffe8e8e7fffcfcfcfffffffffffefefeffe8e6e5ffaba5a0ff5a4f44ff35271aff342619ff342619ff342619ff342619ff342619ff342619ff342619ff342619ff342619ff342619ff342619ff342619ff342619ff342619ff342619ff342619ff342619ff342619ff342619ff342619ff342619ff342619ff342619ff342619ff342619ff342619ff342619ff342619ff342619ff342619ff2c2015da0000008a0000006500000042000000270000001400000009000000020000000000000001000000050000000e0000001c000000341b140e7a34271aff34271aff34271aff34271aff34271aff34271aff34271aff34271aff34271aff34271aff34271aff34271aff34271aff34271aff34271aff34271aff34271aff34271aff34271aff34271aff34271aff34271aff34271aff34271aff34271aff34271aff34271aff34271aff34271aff34271aff34271aff34271aff34271aff34271aff34271aff34271aff34271aff34271aff34271aff34271aff34271aff372a1dff6e655bffcfccc9fffdfdfdfffffffffffcfcfcffd3d2d2ff7e7c79ff322e2bff100c08ff100c08ff100c08ff100c08ff100c08ff100c08ff100c08ff100c08ff100c08ff100c08ff100c08ff100c08ff100c08ff100c08ff100c08ff100c08ff100c08ff100c08ff100c08ff100c08ff100c08ff100c08ff100c08ff100c08ff100c08ff191511ff3e3b38ff9c9b99ffebeaeafffffffffffffffffffbfbfbffc4c0bdff63594fff35281bff34271aff34271aff34271aff34271aff34271aff34271aff34271aff34271aff34271aff34271aff34271aff34271aff34271aff34271aff34271aff34271aff34271aff34271aff34271aff34271aff34271aff34271aff34271aff34271aff34271aff34271aff34271aff34271aff2c2016da0000008a0000006500000042000000270000001400000009000000020000000000000001000000050000000e0000001c000000341d140e7a35271aff35271aff35271aff35271aff35271aff35271aff35271aff35271aff35271aff35271aff35271aff35271aff35271aff35271aff35271aff35271aff35271aff35271aff35271aff35271aff35271aff35271aff35271aff35271aff35271aff35271aff35271aff35271aff35271aff35271aff35271aff35271aff35271aff35271aff35271aff35271aff35271aff35271aff35271aff35271aff54483effc5c1bdfffdfdfdfffffffffff4f4f4ffaaa9a7ff3e3a37ff14100cff100c08ff100c08ff100c08ff100c08ff100c08ff100c08ff100c08ff100c08ff100c08ff100c08ff100c08ff100c08ff100c08ff100c08ff100c08ff100c08ff100c08ff100c08ff100c08ff100c08ff100c08ff100c08ff100c08ff100c08ff100c08ff100c08ff100c08ff100c08ff100c08ff100c08ff1e1a16ff585553ffc3c2c1fffbfbfbfffffffffffcfcfbffc1bdb9ff51453aff35271aff35271aff35271aff35271aff35271aff35271aff35271aff35271aff35271aff35271aff35271aff"
.const [_185] = Utf8 "35271aff35271aff35271aff35271aff35271aff35271aff35271aff35271aff35271aff35271aff35271aff35271aff35271aff35271aff35271aff35271aff2c2016da0000008a0000006500000042000000270000001400000009000000020000000000000001000000050000000e0000001c000000341d140e7a35271aff35271aff35271aff35271aff35271aff35271aff35271aff35271aff35271aff35271aff35271aff35271aff35271aff35271aff35271aff35271aff35271aff35271aff35271aff35271aff35271aff35271aff35271aff35271aff35271aff35271aff35271aff35271aff35271aff35271aff35271aff35271aff35271aff35271aff35271aff35271aff35271aff35271aff382b1dff8d867efff3f2f2fffffffffff7f7f6ff9a9896ff302d29ff100c08ff100c08ff100c08ff100c08ff100c08ff100c08ff100c08ff100c08ff100c08ff100c08ff100c08ff100c08ff100c08ff100c08ff100c08ff100c08ff100c08ff100c08ff100c08ff100c08ff100c08ff100c08ff100c08ff100c08ff100c08ff100c08ff100c08ff100c08ff100c08ff100c08ff100c08ff100c08ff100c08ff100c08ff100c08ff110d09ff403d3affa8a7a6fff8f8f8fffffffffff3f2f2ff8f8780ff3c2e21ff35271aff35271aff35271aff35271aff35271aff35271aff35271aff35271aff35271aff35271aff35271aff35271aff35271aff35271aff35271aff35271aff35271aff35271aff35271aff35271aff35271aff35271aff35271aff35271aff35271aff2d2116da0000008a0000006500000042000000270000001400000009000000020000000000000001000000050000000e0000001c000000341d140e7a36281aff36281aff36281aff36281aff36281aff36281aff36281aff36281aff36281aff36281aff36281aff36281aff36281aff36281aff36281aff36281aff36281aff36281aff36281aff36281aff36281aff36281aff36281aff36281aff36281aff36281aff36281aff36281aff36281aff36281aff36281aff36281aff36281aff36281aff36281aff36281aff36281aff473b2effbfbbb6fffefefeffffffffffcfcfceff44413eff100c08ff100c08ff100c08ff100c08ff100c08ff100c08ff100c08ff100c08ff100c08ff100c08ff100c08ff100c08ff100c08ff100c08ff100c08ff100c08ff100c08ff100c08ff100c08ff100c08ff100c08ff100c08ff100c08ff100c08ff100c08ff100c08ff100c08ff100c08ff100c08ff100c08ff100c08ff100c08ff100c08ff100c08ff100c08ff100c08ff100c08ff100c08ff100c08ff100c08ff3f3c38ffc7c6c5fffefefeffffffffffd3d0ccff62574cff36281aff36281aff36281aff36281aff36281aff36281aff36281aff36281aff36281aff36281aff36281aff36281aff36281aff36281aff36281aff36281aff36281aff36281aff36281aff36281aff36281aff36281aff36281aff36281aff2d2116da0000008a0000006500000042000000270000001400000009000000020000000000000001000000050000000e0000001c000000341d140e7a36281bff36281bff36281bff36281bff36281bff36281bff36281bff36281bff36281bff36281bff36281bff36281bff36281bff36281bff36281bff36281bff36281bff36281bff36281bff36281bff36281bff36281bff36281bff36281bff36281bff36281bff36281bff36281bff36281bff36281bff36281bff36281bff36281bff36281bff36281bff36281bff564a3fffdddad8fffffffffff2f1f1ff767472ff181410ff100c08ff100c08ff100c08ff100c08ff100c08ff100c08ff100c08ff100c08ff100c08ff100c08ff100c08ff100c08ff100c08ff100c08ff100c08ff120e0aff1d1915ff25221eff393532ff433f3cff5a5754ff5a5754ff5a5754ff433f3cff3b3734ff26221fff181410ff100c08ff100c08ff100c08ff100c08ff100c08ff100c08ff100c08ff100c08ff100c08ff100c08ff100c08ff100c08ff100c08ff100c08ff100c08ff15110dff6f6c6affe1e1e1ffffffffffd8d5d2ff36281bff36281bff36281bff36281bff36281bff36281bff36281bff36281bff36281bff36281bff36281bff36281bff36281bff36281bff36281bff36281bff36281bff36281bff36281bff36281bff36281bff36281bff36281bff36281bff2d2117da0000008a0000006500000042000000270000001400000009000000020000000000000001000000050000000e0000001c000000341f160e7a37291bff37291bff37291bff37291bff37291bff37291bff37291bff37291bff37291bff37291bff37291bff37291bff37291bff37291bff37291bff37291bff37291bff37291bff37291bff37291bff37291bff37291bff37291bff37291bff37291bff37291bff37291bff37291bff37291bff37291bff37291bff37291bff37291bff37291bff37291bff594d42ffe9e7e5ffffffffffe2e2e1ff474340ff110c08ff110c08ff110c08ff110c08ff110c08ff110c08ff110c08ff110c08ff110c08ff110c08ff110c08ff110c08ff110c08ff1d1814ff484441ff757270ffa4a3a1ffd9d9d8fff0f0effff9f9f9fffefefefffffffffffffffffffffffffffffffffffffffffffefefefff9f9f9ffeaeae9ffc9c8c7ff9a9896ff64625fff302c28ff130e0aff110c08ff110c08ff110c08ff110c08ff110c08ff110c08ff110c08ff110c08ff110c08ff110c08ff110c08ff110c08ff5d5a58ffffffffffd9d6d3ff37291bff37291bff37291bff37291bff37291bff37291bff37291bff37291bff37291bff37291bff37291bff37291bff37291bff37291bff37291bff37291bff37291bff37291bff37291bff37291bff37291bff37291bff37291bff37291bff2e2317da0000008a0000006500000042000000270000001400000009000000020000000000000001000000050000000e0000001c000000341f160e7a37291bff37291bff37291bff37291bff37291bff37291bff37291bff37291bff37291bff37291bff37291bff37291bff37291bff37291bff37291bff37291bff37291bff37291bff37291bff37291bff37291bff37291bff37291bff37291bff37291bff37291bff37291bff37291bff37291bff37291bff37291bff37291bff37291bff37291bff5b5045ffe9e7e5ffffffffffc8c7c6ff2b2723ff110c08ff110c08ff110c08ff110c08ff110c08ff110c08ff110c08ff110c08ff110c08ff110c08ff110c08ff16110dff4f4b48ffa3a2a0ffebebebfffefefefffffffffffffffffffffffffffafaf9fff4f3f2ffedebeaffdddad8ffd1cecbffc1bcb8ffd4d1ceffdddad8ffedebeafff4f3f3fffffffffffffffffffffffffffffffffffafafaffd4d3d2ff8d8b88ff403c39ff15100cff110c08ff110c08ff110c08ff110c08ff110c08ff110c08ff110c08ff110c08ff110c08ff5a5754ffffffffffd9d6d3ff37291bff37291bff37291bff37291bff37291bff37291bff37291bff37291bff37291bff37291bff37291bff37291bff37291bff37291bff37291bff37291bff37291bff37291bff37291bff37291bff37291bff37291bff37291bff37291bff2e2317da0000008a0000006500000042000000270000001400000009000000020000000000000001000000050000000e0000001c000000341f160e7a38291bff38291bff38291bff38291bff38291bff38291bff38291bff38291bff38291bff38291bff38291bff38291bff38291bff38291bff38291bff38291bff38291bff38291bff38291bff38291bff38291bff38291bff38291bff38291bff38291bff38291bff38291bff38291bff38291bff38291bff38291bff38291bff38291bff62564bfff1f0efffffffffffc2c1c0ff201b18ff110c08ff110c08ff110c08ff110c08ff110c08ff110c08ff110c08ff110c08ff110c08ff110c08ff17120eff63605dffd3d2d2fffefefefffffffffffefefefff3f3f2ffc8c4c0ff928a82ff6d6258ff4c3e31ff443629ff3d2e21ff38291cff38291bff38291bff38291bff38291cff3d2e21ff46382bff5e5246ff7e746bff9c948effcecac7fff1f0effffffffffffffffffffcfcfcffdadad9ff807e7cff211c18ff110c08ff110c08ff110c08ff110c08ff110c08ff110c08ff110c08ff5a5754ffffffffffd9d6d3ff38291bff38291bff38291bff38291bff38291bff38291bff38291bff38291bff38291bff38291bff38291bff38291bff38291bff38291bff38291bff38291bff38291bff38291bff38291bff38291bff38291bff38291bff38291bff38291bff2f2317da0000008a0000006500000042000000270000001400000009000000020000000000000001000000050000000e0000001c000000341f160e7a382a1cff382a1cff382a1cff382a1cff382a1cff382a1cff382a1cff382a1cff382a1cff382a1cff382a1cff382a1cff382a1cff382a1cff382a1cff382a1cff382a1cff382a1cff382a1cff382a1cff382a1cff382a1cff382a1cff382a1cff382a1cff382a1cff382a1cff382a1cff382a1cff382a1cff382a1cff382a1cff52463affe9e7e6ffffffffffc2c1c0ff201c18ff110d08ff110d08ff110d08ff110d08ff110d08ff110d08ff110d08ff110d08ff110d08ff130f0aff5c5957ffd3d2d2fffefefeffffffffffefeeedffb0aaa5ff736a60ff45372aff382a1cff382a1cff382a1cff382a1cff382a1cff382a1cff382a1cff382a1cff382a1cff382a1cff382a1cff382a1cff382a1cff382a1cff382a1cff382a1cff382a1cff473a2dff7b7268ffc0bcb7fff1f0efffffffffffffffffffe7e7e6ff807e7cff201c18ff110d08ff110d08ff110d08ff110d08ff110d08ff5a5854ffffffffffd9d6d4ff382a1cff382a1cff382a1cff382a1cff382a1cff382a1cff382a1cff382a1cff382a1cff382a1cff382a1cff382a1cff382a1cff382a1cff382a1cff382a1cff382a1cff382a1cff382a1cff382a1cff382a1cff382a1cff382a1cff382a1cff2f2317da0000008a0000006500000042000000270000001400000009000000020000000000000001000000050000000e0000001c000000341f160e7a382a1cff382a1cff382a1cff382a1cff382a1cff382a1cff382a1cff382a1cff382a1cff382a1cff382a1cff382a1cff382a1cff382a1cff382a1cff382a1cff382a1cff382a1cff382a1cff382a1cff382a1cff382a1cff382a1cff382a1cff382a1cff382a1cff382a1cff382a1cff382a1cff382a1cff382a1cff473a2dffdcd9d6ffffffffffcfcfceff201c18ff110d08ff110d08ff110d08ff110d08ff110d08ff110d08ff110d08ff110d08ff110d08ff1f1c17ffa7a5a4fffdfdfdffffffffffebe9e8ff928a82ff46392cff382a1cff382a1cff382a1cff382a1cff382a1cff382a1cff382a1cff382a1cff382a1cff382a1cff382a1cff382a1cff382a1cff382a1cff382a1cff382a1cff382a1cff382a1cff382a1cff382a1cff382a1cff382a1cff382a1cff483b2eff958d86ffe6e4e2fffefefeffffffffffe0e0e0ff686563ff15110cff110d08ff110d08ff110d08ff5a5854ffffffffffd9d6d4ff382a1cff382a1cff382a1cff382a1cff382a1cff382a1cff382a1cff382a1cff382a1cff382a1cff382a1cff382a1cff382a1cff382a1cff382a1cff382a1cff382a1cff382a1cff382a1cff382a1cff382a1cff382a1cff382a1cff382a1cff2f2317da0000008a0000006500000042000000270000001400000009000000020000000000000001000000050000000e0000001c000000341f160e7a392a1cff392a1cff392a1cff392a1cff392a1cff392a1cff392a1cff392a1cff392a1cff392a1cff392a1cff392a1cff392a1cff392a1cff392a1cff392a1cff392a1cff392a1cff392a1cff392a1cff392a1cff392a1cff392a1cff392a1cff392a1cff392a1cff392a1cff392a1cff392a1cff392a1cff3b2c1effbbb6b1ffffffffffe7e7e6ff302d29ff110d08ff110d08ff110d08ff110d08ff110d08ff110d08ff110d08ff110d08ff110d08ff373430ffd0cfcefffffffffffbfbfbffb0a9a4ff483a2dff392a1cff392a1cff392a1cff392a1cff392a1cff392a1cff392a1cff392a1cff392a1cff392a1cff392a1cff392a1cff392a1cff392a1cff392a1cff392a1cff392a1cff392a1cff392a1cff392a1cff392a1cff392a1cff392a1cff392a1cff392a1cff392a1cff392a1cff403124ff887f76ffe6e4e2fffffffffffefefeffbbb9b8ff302d29ff110d08ff110d08ff5a5854ffffffffffd9d6d4ff392a1cff392a1cff392a1cff392a1cff392a1cff392a1cff392a1cff392a1cff392a1cff392a1cff392a1cff392a1cff392a1cff392a1cff392a1cff392a1cff392a1cff392a1cff392a1cff392a1cff392a1cff392a1cff392a1cff392a1cff2f2317da0000008a0000006500000042000000270000001400000009000000020000000000000001000000050000000e0000001c000000341f160e7a392b1cff392b1cff392b1cff392b1cff392b1cff392b1cff392b1cff392b1cff392b1cff392b1cff392b1cff392b1cff392b1cff392b1cff392b1cff392b1cff392b1cff392b1cff392b1cff392b1cff392b1cff392b1cff392b1cff392b1cff392b1cff392b1cff392b1cff392b1cff392b1cff392b1cff837a70fffdfdfdfff9f9f9ff56534fff110d08ff110d08ff110d08ff110d08ff110d08ff110d08ff110d08ff110d08ff110d08ff4c4945ffe7e7e6ffffffffffe8e7e5ff6f655aff3a2b1cff392b1cff392b1cff392b1cff392b1cff392b1cff392b1cff392b1cff392b1cff392b1cff392b1cff392b1cff392b1cff392b1cff392b1cff392b1cff392b1cff392b1cff392b1cff392b1cff392b1cff392b1cff392b1cff392b1cff392b1cff392b1cff392b1cff392b1cff392b1cff392b1cff392b1cff46382aff9e9790fff6f5f5ffffffffffedececff625f5cff120d08ff5a5854ffffffffffd9d6d4ff392b1cff392b1cff392b1cff392b1cff392b1cff392b1cff392b1cff392b1cff392b1cff392b1cff392b1cff392b1cff392b1cff392b1cff392b1cff392b1cff392b1cff392b1cff392b1cff392b1cff392b1cff392b1cff392b1cff392b1cff312417da0000008a0000006500000042000000270000001400000009000000020000000000000001000000050000000e0000001c000000341f160e7a3a2b1cff3a2b1cff3a2b1cff3a2b1cff3a2b1cff3a2b1cff3a2b1cff3a2b1cff3a2b1cff3a2b1cff3a2b1cff3a2b1cff3a2b1cff3a2b1cff3a2b1cff3a2b1cff3a2b1cff3a2b1cff3a2b1cff3a2b1cff3a2b1cff3a2b1cff3a2b1cff3a2b1cff3a2b1cff3a2b1cff3a2b1cff3a2b1cff3a2b1cff534539fff0efeeffffffffff969492ff120d08ff120d08ff120d08ff120d08ff120d08ff120d08ff120d08ff120d08ff120d08ff4c4945ffefefefffffffffffdad7d5ff514438ff3a2b1cff3a2b1cff3a2b1cff3a2b1cff3a2b1cff3a2b1cff3a2b1cff3a2b1cff3a2b1cff3a2b1cff3a2b1cff3a2b1cff3a2b1cff3a2b1cff3a2b1cff3a2b1cff3a2b1cff3a2b1cff3a2b1cff3a2b1cff3a2b1cff3a2b1cff3a2b1cff3a2b1cff3a2b1cff3a2b1cff3a2b1cff3a2b1cff3a2b1cff3a2b1cff3a2b1cff3a2b1cff3a2b1cff3a2b1cff5c5044ffcdc9c6fffffffffffcfcfcff93918fff625f5cffffffffffd9d6d4ff3a2b1cff3a2b1cff3a2b1cff3a2b1cff3a2b1cff3a2b1cff3a2b1cff3a2b1cff3a2b1cff3a2b1cff3a2b1cff3a2b1cff3a2b1cff3a2b1cff3a2b1cff3a2b1cff3a2b1cff3a2b1cff3a2b1cff3a2b1cff3a2b1cff3a2b1cff3a2b1cff3a2b1cff312418da0000008a0000006500000042000000270000001400000009000000020000000000000001000000050000000e0000001c000000341f160e7a3a2b1dff3a2b1dff3a2b1dff3a2b1dff3a2b1dff3a2b1dff3a2b1dff3a2b1dff3a2b1dff3a2b1dff3a2b1dff3a2b1dff3a2b1dff3a2b1dff3a2b1dff3a2b1dff3a2b1dff3a2b1dff3a2b1dff3a2b1dff3a2b1dff3a2b1dff3a2b1dff3a2b1dff3a2b1dff3a2b1dff3a2b1dff3a2b1dff3a2b1dffafa8a3ffffffffffd9d9d8ff1f1a16ff120d09ff120d09ff120d09ff120d09ff120d09ff120d09ff120d09ff120d09ff3f3c38ffecececffffffffffcdc9c5ff48392cff3a2b1dff3a2b1dff3a2b1dff3a2b1dff3a2b1dff3a2b1dff3a2b1dff3a2b1dff3a2b1dff3a2b1dff3a2b1dff3a2b1dff3a2b1dff3a2b1dff3a2b1dff3a2b1dff3a2b1dff3a2b1dff3a2b1dff3a2b1dff3a2b1dff3a2b1dff3a2b1dff3a2b1dff3a2b1dff3a2b1dff3a2b1dff3a2b1dff3a2b1dff3a2b1dff3a2b1dff3a2b1dff3a2b1dff3a2b1dff3a2b1dff3a2b1dff403123ff9f9891fffafaf9ffffffffffe7e6e6ffffffffffd9d6d4ff3a2b1dff3a2b1dff3a2b1dff3a2b1dff3a2b1dff3a2b1dff3a2b1dff3a2b1dff3a2b1dff3a2b1dff3a2b1dff3a2b1dff3a2b1dff3a2b1dff3a2b1dff3a2b1dff3a2b1dff3a2b1dff3a2b1dff3a2b1dff3a2b1dff3a2b1dff3a2b1dff3a2b1dff312418da0000008a0000006500000042000000270000001400000009000000020000000000000001000000050000000e0000001c0000003421160e7a3b2c1dff3b2c1dff3b2c1dff3b2c1dff3b2c1dff3b2c1dff3b2c1dff3b2c1dff3b2c1dff3b2c1dff3b2c1dff3b2c1dff3b2c1dff3b2c1dff3b2c1dff3b2c1dff3b2c1dff3b2c1dff3b2c1dff3b2c1dff3b2c1dff3b2c1dff3b2c1dff3b2c1dff3b2c1dff3b2c1dff3b2c1dff3b2c1dff5f5246fff8f8f7fffdfdfdff595653ff120d09ff120d09ff120d09ff120d09ff120d09ff120d09ff120d09ff120d09ff211c18ffd6d5d4ffffffffffd2cecbff47392bff3b2c1dff3b2c1dff3b2c1dff3b2c1dff3b2c1dff3b2c1dff3b2c1dff3b2c1dff3b2c1dff3b2c1dff3b2c1dff3b2c1dff3b2c1dff3b2c1dff3b2c1dff3b2c1dff3b2c1dff3b2c1dff3b2c1dff3b2c1dff3b2c1dff3b2c1dff3b2c1dff3b2c1dff3b2c1dff3b2c1dff3b2c1dff3b2c1dff3b2c1dff3b2c1dff3b2c1dff3b2c1dff3b2c1dff3b2c1dff3b2c1dff3b2c1dff3b2c1dff3b2c1dff3b2c1dff776d63fff0efedffffffffffffffffffd9d7d4ff3b2c1dff3b2c1dff3b2c1dff3b2c1dff3b2c1dff3b2c1dff3b2c1dff3b2c1dff3b2c1dff3b2c1dff3b2c1dff3b2c1dff3b2c1dff3b2c1dff3b2c1dff3b2c1dff3b2c1dff3b2c1dff3b2c1dff3b2c1dff3b2c1dff3b2c1dff3b2c1dff3b2c1dff322518da0000008a0000006500000042000000270000001400000009000000020000000000000001000000050000000e0000001c0000003421160e7a3b2c1dff3b2c1dff3b2c1dff3b2c1dff3b2c1dff3b2c1dff3b2c1dff3b2c1dff3b2c1dff3b2c1dff3b2c1dff3b2c1dff3b2c1dff3b2c1dff3b2c1dff3b2c1dff3b2c1dff3b2c1dff3b2c1dff3b2c1dff3b2c1dff3b2c1dff3b2c1dff3b2c1dff3b2c1dff3b2c1dff3b2c1dff3c2d1effc6c1bdffffffffffbcbab9ff140f0bff120d09ff120d09ff120d09ff120d09ff120d09ff120d09ff120d09ff130e0affa6a4a3ffffffffffebe9e8ff524538ff3b2c1dff3b2c1dff3b2c1dff3b2c1dff3b2c1dff3b2c1dff3b2c1dff3b2c1dff3b2c1dff3b2c1dff3b2c1dff3b2c1dff3b2c1dff3b2c1dff3b2c1dff3b2c1dff3b2c1dff3b2c1dff3b2c1dff3b2c1dff3b2c1dff3b2c1dff3b2c1dff3b2c1dff3b2c1dff3b2c1dff3b2c1dff3b2c1dff3b2c1dff3b2c1dff3b2c1dff3b2c1dff3b2c1dff3b2c1dff3b2c1dff3b2c1dff3b2c1dff3b2c1dff3b2c1dff3b2c1dff3b2c1dff5d5044ffdfdddaffffffffffd9d7d4ff3b2c1dff3b2c1dff3b2c1dff3b2c1dff3b2c1dff3b2c1dff3b2c1dff3b2c1dff3b2c1dff3b2c1dff3b2c1dff3b2c1dff3b2c1dff3b2c1dff3b2c1dff3b2c1dff3b2c1dff3b2c1dff3b2c1dff3b2c1dff3b2c1dff3b2c1dff3b2c1dff3b2c1dff322518da0000008a0000006500000042000000270000001400000009000000020000000000000001000000050000000e0000001c0000003421160e7a3c2c1dff3c2c1dff3c2c1dff3c2c1dff3c2c1dff3c2c1dff3c2c1dff3c2c1dff3c2c1dff3c2c1dff3c2c1dff3c2c1dff3c2c1dff3c2c1dff3c2c1dff3c2c1dff3c2c1dff3c2c1dff3c2c1dff3c2c1dff3c2c1dff3c2c1dff3c2c1dff3c2c1dff3c2c1dff3c2c1dff3c2c1dff66594efffcfcfcfffbfbfbff494542ff120d09ff120d09ff120d09ff120d09ff120d09ff120d09ff120d09ff120d09ff585552fffcfcfcfffafaf9ff74695eff3c2c1dff3c2c1dff3c2c1dff3c2c1dff3c2c1dff3c2c1dff3c2c1dff3c2c1dff3c2c1dff3c2c1dff3c2c1dff3c2c1dff3c2c1dff3c2c1dff3c2c1dff3c2c1dff3c2c1dff3c2c1dff3c2c1dff3c2c1dff3c2c1dff3c2c1dff3c2c1dff3c2c1dff3c2c1dff3c2c1dff3c2c1dff3c2c1dff3c2c1dff3c2c1dff3c2c1dff3c2c1dff3c2c1dff3c2c1dff3c2c1dff3c2c1dff3c2c1dff3c2c1dff3c2c1dff3c2c1dff3c2c1dff3c2c1dff3c2c1dff514236ffd8d5d2ffdad7d4ff3c2c1dff3c2c1dff3c2c1dff3c2c1dff3c2c1dff3c2c1dff3c2c1dff3c2c1dff3c2c1dff3c2c1dff3c2c1dff3c2c1dff3c2c1dff3c2c1dff3c2c1dff3c2c1dff3c2c1dff3c2c1dff3c2c1dff3c2c1dff3c2c1dff3c2c1dff3c2c1dff3c2c1dff332518da0000008a0000006500000042000000270000001400000009000000020000000000000001000000050000000e0000001c000000342119107a3c2d1eff3c2d1eff3c2d1eff3c2d1eff3c2d1eff3c2d1eff3c2d1eff3c2d1eff3c2d1eff3c2d1eff3c2d1eff3c2d1eff3c2d1eff3c2d1eff3c2d1eff3c2d1eff3c2d1eff3c2d1eff3c2d1eff3c2d1eff3c2d1eff3c2d1eff3c2d1eff3c2d1eff3c2d1eff3c2d1eff3c2d1effb7b2acffffffffffbbbab8ff130f0aff120e09ff120e09ff120e09ff120e09ff120e09ff120e09ff120e09ff1c1813ffd9d8d7ffffffffffada7a1ff3c2d1eff3c2d1eff3c2d1eff3c2d1eff3c2d1eff3c2d1eff3c2d1eff3c2d1eff3c2d1eff3c2d1eff3c2d1eff3c2d1eff3c2d1eff3c2d1eff3c2d1eff3c2d1eff3c2d1eff3c2d1eff3c2d1eff3c2d1eff3c2d1eff3c2d1eff3c2d1eff3c2d1eff3c2d1eff3c2d1eff3c2d1eff3c2d1eff3c2d1eff3c2d1eff3c2d1eff3c2d1eff3c2d1eff3c2d1eff3c2d1eff3c2d1eff3c2d1eff3c2d1eff3c2d1eff3c2d1eff3c2d1eff3c2d1eff3c2d1eff3c2d1eff3c2d1eff483a2cff9c948cff3c2d1eff3c2d1eff3c2d1eff3c2d1eff3c2d1eff3c2d1eff3c2d1eff3c2d1eff3c2d1eff3c2d1eff3c2d1eff3c2d1eff3c2d1eff3c2d1eff3c2d1eff3c2d1eff3c2d1eff3c2d1eff3c2d1eff3c2d1eff3c2d1eff3c2d1eff3c2d1eff3c2d1eff332619da0000008a0000006500000042000000270000001400000009000000020000000000000001000000050000000e0000001c000000342119107a3d2d1eff3d2d1eff3d2d1eff3d2d1eff3d2d1eff3d2d1eff3d2d1eff3d2d1eff3d2d1eff3d2d1eff3d2d1eff3d2d1eff3d2d1eff3d2d1eff3d2d1eff3d2d1eff3d2d1eff3d2d1eff3d2d1eff3d2d1eff3d2d1eff3d2d1eff3d2d1eff3d2d1eff3d2d1eff3d2d1eff4f4033fff4f3f2fffdfdfdff504d4aff120e09ff120e09ff120e09ff120e09ff120e09ff120e09ff120e09ff120e09ff6d6a67ffffffffffecebe9ff4e3f31ff3d2d1eff3d2d1eff3d2d1eff3d2d1eff3d2d1eff3d2d1eff3d2d1eff3d2d1eff3d2d1eff3d2d1eff3d2d1eff3d2d1eff3d2d1eff3d2d1eff3d2d1eff3d2d1eff3d2d1eff3d2d1eff3d2d1eff3d2d1eff3d2d1eff3d2d1eff3d2d1eff3d2d1eff3d2d1eff3d2d1eff3d2d1eff3d2d1eff3d2d1eff3d2d1eff3d2d1eff3d2d1eff3d2d1eff3d2d1eff3d2d1eff3d2d1eff3d2d1eff3d2d1eff3d2d1eff3d2d1eff3d2d1eff3d2d1eff3d2d1eff3d2d1eff3d2d1eff3d2d1eff3d2d1eff3d2d1eff3d2d1eff3d2d1eff3d2d1eff3d2d1eff3d2d1eff3d2d1eff3d2d1eff3d2d1eff3d2d1eff3d2d1eff3d2d1eff3d2d1eff3d2d1eff3d2d1eff3d2d1eff3d2d1eff3d2d1eff3d2d1eff3d2d1eff3d2d1eff3d2d1eff3d2d1eff3d2d1eff342619da0000008a0000006500000042000000270000001400000009000000020000000000000001000000050000000e0000001c000000342119107a3d2d1eff3d2d1eff3d2d1eff3d2d1eff3d2d1eff3d2d1eff3d2d1eff3d2d1eff3d2d1eff3d2d1eff3d2d1eff3d2d1eff3d2d1eff3d2d1eff3d2d1eff3d2d1eff3d2d1eff3d2d1eff3d2d1eff3d2d1eff3d2d1eff3d2d1eff3d2d1eff3d2d1eff3d2d1eff3d2d1eff8f867effffffffffd2d1d0ff16120dff120e09ff120e09ff120e09ff120e09ff120e09ff120e09ff120e09ff17130effd3d3d2ffffffffff928980ff3d2d1eff3d2d1eff3d2d1eff3d2d1eff3d2d1eff3d2d1eff3d2d1eff3d2d1eff3d2d1eff3d2d1eff3d2d1eff3d2d1eff3d2d1eff3d2d1eff3d2d1eff3d2d1eff3d2d1eff3d2d1eff3d2d1eff3d2d1eff3d2d1eff3d2d1eff3d2d1eff3d2d1eff3d2d1eff3d2d1eff3d2d1eff3d2d1eff3d2d1eff3d2d1eff3d2d1eff3d2d1eff3d2d1eff3d2d1eff3d2d1eff3d2d1eff3d2d1eff3d2d1eff3d2d1eff3d2d1eff3d2d1eff3d2d1eff3d2d1eff3d2d1eff3d2d1eff3d2d1eff3d2d1eff3d2d1eff3d2d1eff3d2d1eff3d2d1eff3d2d1eff3d2d1eff3d2d1eff3d2d1eff3d2d1eff3d2d1eff3d2d1eff3d2d1eff3d2d1eff3d2d1eff3d2d1eff3d2d1eff3d2d1eff3d2d1eff3d2d1eff3d2d1eff3d2d1eff3d2d1eff3d2d1eff3d2d1eff3d2d1eff342619da0000008a0000006500000042000000270000001400000009000000020000000000000001000000050000000e0000001c000000342119107a3e2e1eff3e2e1eff3e2e1eff3e2e1eff3e2e1eff3e2e1eff3e2e1eff3e2e1eff3e2e1eff3e2e1eff3e2e1eff3e2e1eff3e2e1eff3e2e1eff3e2e1eff3e2e1eff3e2e1eff3e2e1eff3e2e1eff3e2e1eff3e2e1eff3e2e1eff3e2e1eff3e2e1eff3e2e1eff3e2e1fffd1cecaffffffffff797674ff130e09ff130e09ff130e09ff130e09ff130e09ff130e09ff130e09ff130e09ff565350fffefefeffe7e5e3ff463727ff3e2e1eff3e2e1eff3e2e1eff3e2e1eff3e2e1eff3e2e1eff3e2e1eff3e2e1eff3e2e1eff3e2e1eff3e2e1eff3e2e1eff3e2e1eff3e2e1eff3e2e1eff3e2e1eff3e2e1eff3e2e1eff3e2e1eff3e2e1eff3e2e1eff3e2e1eff3e2e1eff3e2e1eff3e2e1eff3e2e1eff3e2e1eff3e2e1eff3e2e1eff3e2e1eff3e2e1eff3e2e1eff3e2e1eff3e2e1eff3e2e1eff3e2e1eff3e2e1eff3e2e1eff3e2e1eff3e2e1eff3e2e1eff3e2e1eff3e2e1eff3e2e1eff3e2e1eff3e2e1eff3e2e1eff3e2e1eff3e2e1eff3e2e1eff3e2e1eff3e2e1eff3e2e1eff3e2e1eff3e2e1eff3e2e1eff3e2e1eff3e2e1eff3e2e1eff3e2e1eff3e2e1eff3e2e1eff3e2e1eff3e2e1eff3e2e1eff3e2e1eff3e2e1eff3e2e1eff3e2e1eff3e2e1eff3e2e1eff3e2e1eff342619da0000008a0000006500000042000000270000001400000009000000020000000000000001000000050000000e0000001c000000342119107a3e2e1fff3e2e1fff3e2e1fff3e2e1fff3e2e1fff3e2e1fff3e2e1fff3e2e1fff3e2e1fff3e2e1fff3e2e1fff3e2e1fff3e2e1fff3e2e1fff3e2e1fff3e2e1fff3e2e1fff3e2e1fff3e2e1fff3e2e1fff3e2e1fff3e2e1fff3e2e1fff3e2e1fff3e2e1fff57493cfff9f9f9fff8f8f8ff312d29ff130e09ff130e09ff130e09ff130e09ff130e09ff130e09ff130e09ff130e09ffbebcbbffffffffffa69e97ff3e2e1fff3e2e1fff3e2e1fff3e2e1fff3e2e1fff3e2e1fff3e2e1fff3e2e1fff3e2e1fff3e2e1fff3e2e1fff3e2e1fff3e2e1fff3e2e1fff3e2e1fff3e2e1fff3e2e1fff3e2e1fff3e2e1fff3e2e1fff3e2e1fff3e2e1fff3e2e1fff3e2e1fff3e2e1fff3e2e1fff3e2e1fff3e2e1fff3e2e1fff3e2e1fff3e2e1fff3e2e1fff3e2e1fff3e2e1fff3e2e1fff3e2e1fff3e2e1fff3e2e1fff3e2e1fff3e2e1fff3e2e1fff3e2e1fff3e2e1fff3e2e1fff3e2e1fff3e2e1fff3e2e1fff3e2e1fff3e2e1fff3e2e1fff3e2e1fff3e2e1fff3e2e1fff3e2e1fff3e2e1fff3e2e1fff3e2e1fff3e2e1fff3e2e1fff3e2e1fff3e2e1fff3e2e1fff3e2e1fff3e2e1fff3e2e1fff3e2e1fff3e2e1fff3e2e1fff3e2e1fff3e2e1fff3e2e1fff3e2e1fff3e2e1fff342619da0000008a0000006500000042000000270000001400000009000000020000000000000001000000050000000e0000001c000000342119107a3e2e1fff3e2e1fff3e2e1fff3e2e1fff3e2e1fff3e2e1fff3e2e1fff3e2e1fff3e2e1fff3e2e1fff3e2e1fff3e2e1fff3e2e1fff3e2e1fff3e2e1fff3e2e1fff3e2e1fff3e2e1fff3e2e1fff3e2e1fff3e2e1fff3e2e1fff3e2e1fff3e2e1fff3e2e1fff928980ffffffffffcdcccbff140f0aff130e09ff130e09ff130e09ff130e09ff130e09ff130e09ff130e09ff2b2622fff5f5f5fffcfcfcff63564aff3e2e1fff3e2e1fff3e2e1fff3e2e1fff3e2e1fff3e2e1fff3e2e1fff3e2e1fff3e2e1fff3e2e1fff3e2e1fff3e2e1fff3e2e1fff3e2e1fff3e2e1fff3e2e1fff3e2e1fff3e2e1fff3e2e1fff3e2e1fff3e2e1fff3e2e1fff3e2e1fff3e2e1fff3e2e1fff3e2e1fff3e2e1fff3e2e1fff3e2e1fff3e2e1fff3e2e1fff3e2e1fff3e2e1fff3e2e1fff3e2e1fff3e2e1fff3e2e1fff3e2e1fff3e2e1fff3e2e1fff3e2e1fff3e2e1fff3e2e1fff3e2e1fff3e2e1fff3e2e1fff3e2e1fff3e2e1fff3e2e1fff3e2e1fff3e2e1fff3e2e1fff3e2e1fff3e2e1fff3e2e1fff3e2e1fff3e2e1fff3e2e1fff3e2e1fff3e2e1fff3e2e1fff3e2e1fff3e2e1fff3e2e1fff3e2e1fff3e2e1fff3e2e1fff3e2e1fff3e2e1fff3e2e1fff3e2e1fff3e2e1fff3e2e1fff342619da0000008a0000006500000042000000270000001400000009000000020000000000000001000000050000000e0000001c000000342319107a3f2f1fff3f2f1fff3f2f1fff3f2f1fff3f2f1fff3f2f1fff3f2f1fff3f2f1fff3f2f1fff3f2f1fff3f2f1fff3f2f1fff3f2f1fff3f2f1fff3f2f1fff3f2f1fff3f2f1fff3f2f1fff3f2f1fff3f2f1fff3f2f1fff3f2f1fff3f2f1fff3f2f1fff3f2f1fffd0ccc8ffffffffff8b8886ff130e09ff130e09ff130e09ff130e09ff130e09ff130e09ff130e09ff130e09ff706d69ffffffffffd9d6d3ff413121ff3f2f1fff3f2f1fff3f2f1fff3f2f1fff3f2f1fff3f2f1fff3f2f1fff3f2f1fff3f2f1fff3f2f1fff3f2f1fff3f2f1fff3f2f1fff3f2f1fff3f2f1fff3f2f1fff3f2f1fff3f2f1fff3f2f1fff3f2f1fff3f2f1fff3f2f1fff3f2f1fff3f2f1fff3f2f1fff3f2f1fff3f2f1fff3f2f1fff3f2f1fff3f2f1fff3f2f1fff3f2f1fff3f2f1fff3f2f1fff3f2f1fff3f2f1fff3f2f1fff3f2f1fff3f2f1fff3f2f1fff3f2f1fff3f2f1fff3f2f1fff3f2f1fff3f2f1fff3f2f1fff3f2f1fff3f2f1fff3f2f1fff3f2f1fff3f2f1fff3f2f1fff3f2f1fff3f2f1fff3f2f1fff3f2f1fff3f2f1fff3f2f1fff3f2f1fff3f2f1fff3f2f1fff3f2f1fff3f2f1fff3f2f1fff3f2f1fff3f2f1fff3f2f1fff3f2f1fff3f2f1fff3f2f1fff3f2f1fff3f2f1fff3f2f1fff352719da0000008a0000006500000042000000270000001400000009000000020000000000000001000000050000000e0000001c000000342319107a3f2f1fff3f2f1fff3f2f1fff3f2f1fff3f2f1fff3f2f1fff3f2f1fff3f2f1fff3f2f1fff3f2f1fff3f2f1fff3f2f1fff3f2f1fff3f2f1fff3f2f1fff3f2f1fff3f2f1fff3f2f1fff3f2f1fff3f2f1fff3f2f1fff3f2f1fff3f2f1fff3f2f1fff4d3d2ffff4f3f2fffefefeff4a4743ff130e09ff130e09ff130e09ff130e09ff130e09ff130e09ff130e09ff130e09ffbdbcbaffffffffffa8a099ff3f2f1fff3f2f1fff3f2f1fff3f2f1fff3f2f1fff3f2f1fff3f2f1fff3f2f1fff3f2f1fff3f2f1fff3f2f1fff3f2f1fff3f2f1fff3f2f1fff3f2f1fff3f2f1fff3f2f1fff3f2f1fff3f2f1fff3f2f1fff3f2f1fff3f2f1fff3f2f1fff3f2f1fff3f2f1fff3f2f1fff3f2f1fff3f2f1fff3f2f1fff3f2f1fff3f2f1fff3f2f1fff3f2f1fff3f2f1fff3f2f1fff3f2f1fff3f2f1fff3f2f1fff3f2f1fff3f2f1fff3f2f1fff3f2f1fff3f2f1fff3f2f1fff3f2f1fff3f2f1fff3f2f1fff3f2f1fff3f2f1fff3f2f1fff3f2f1fff3f2f1fff3f2f1fff3f2f1fff3f2f1fff3f2f1fff3f2f1fff3f2f1fff3f2f1fff3f2f1fff3f2f1fff3f2f1fff3f2f1fff3f2f1fff3f2f1fff3f2f1fff3f2f1fff3f2f1fff3f2f1fff3f2f1fff3f2f1fff3f2f1fff3f2f1fff3f2f1fff352719da0000008a0000006500000042000000270000001400000009000000020000000000000001000000050000000e0000001c000000342319107a402f20ff402f20ff402f20ff402f20ff402f20ff402f20ff402f20ff402f20ff402f20ff402f20ff402f20ff402f20ff402f20ff402f20ff402f20ff402f20ff402f20ff402f20ff402f20ff402f20ff402f20ff402f20ff402f20ff402f20ff6d6155ffffffffffefefefff201b17ff130e0aff130e0aff130e0aff130e0aff130e0aff130e0aff130e0aff1f1a16ffeeededffffffffff72665bff402f20ff402f20ff402f20ff402f20ff402f20ff402f20ff402f20ff402f20ff402f20ff402f20ff402f20ff402f20ff402f20ff402f20ff402f20ff402f20ff402f20ff402f20ff402f20ff402f20ff402f20ff402f20ff402f20ff402f20ff402f20ff402f20ff402f20ff402f20ff402f20ff402f20ff402f20ff402f20ff402f20ff402f20ff402f20ff402f20ff402f20ff402f20ff402f20ff402f20ff402f20ff402f20ff402f20ff402f20ff402f20ff402f20ff402f20ff402f20ff402f20ff402f20ff402f20ff402f20ff402f20ff402f20ff402f20ff402f20ff402f20ff402f20ff402f20ff402f20ff402f20ff402f20ff402f20ff402f20ff402f20ff402f20ff402f20ff402f20ff402f20ff402f20ff402f20ff402f20ff402f20ff402f20ff35271ada0000008a0000006500000042000000270000001400000009000000020000000000000001000000050000000e0000001c000000342319107a403020ff403020ff403020ff403020ff403020ff403020ff403020ff403020ff403020ff403020ff403020ff403020ff403020ff403020ff403020ff403020ff403020ff403020ff403020ff403020ff403020ff403020ff403020ff403020ff8c8279ffffffffffcbcac9ff130e0aff130e0aff130e0aff130e0aff130e0aff130e0aff130e0aff130e0aff44403cfffefefefff4f3f2ff4e3e30ff403020ff403020ff403020ff403020ff403020ff403020ff403020ff403020ff403020ff403020ff403020ff403020ff403020ff403020ff403020ff403020ff403020ff403020ff403020ff403020ff403020ff403020ff403020ff403020ff403020ff403020ff403020ff403020ff403020ff403020ff403020ff403020ff403020ff403020ff403020ff403020ff403020ff403020ff403020ff403020ff403020ff403020ff403020ff403020ff403020ff403020ff403020ff403020ff403020ff403020ff403020ff403020ff403020ff403020ff403020ff403020ff403020ff403020ff403020ff403020ff403020ff403020ff403020ff403020ff403020ff403020ff403020ff403020ff403020ff403020ff403020ff403020ff403020ff403020ff36281ada0000008a0000006500000042000000270000001400000009000000020000000000000001000000050000000e0000001c000000342319107a413020ff413020ff413020ff413020ff413020ff413020ff413020ff413020ff413020ff413020ff413020ff413020ff413020ff413020ff413020ff413020ff413020ff413020ff413020ff413020ff413020ff413020ff413020ff413020ffb1aaa4ffffffffffa4a3a1ff140e0aff140e0aff140e0aff140e0aff140e0aff140e0aff140e0aff140e0aff777471ffffffffffd2cecaff413020ff413020ff413020ff413020ff413020ff413020ff413020ff413020ff413020ff413020ff413020ff413020ff413020ff413020ff413020ff413020ff413020ff413020ff413020ff413020ff413020ff413020ff413020ff413020ff413020ff413020ff413020ff413020ff413020ff413020ff413020ff413020ff413020ff413020ff413020ff413020ff413020ff413020ff413020ff413020ff413020ff413020ff413020ff413020ff413020ff413020ff413020ff413020ff413020ff413020ff413020ff413020ff413020ff413020ff413020ff413020ff413020ff413020ff413020ff413020ff413020ff413020ff413020ff413020ff413020ff413020ff413020ff413020ff413020ff413020ff413020ff413020ff413020ff413020ff413020ff36281ada0000008a0000006500000042000000270000001400000009000000020000000000000001000000050000000e0000001c000000342319107a413020ff413020ff413020ff413020ff413020ff413020ff413020ff413020ff413020ff413020ff413020ff413020ff413020ff413020ff413020ff413020ff413020ff413020ff413020ff413020ff413020ff413020ff413020ff413020ffd0ccc8ffffffffff73716eff140e0aff140e0aff140e0aff140e0aff140e0aff140e0aff140e0aff140e0aff9e9b99ffffffffffb3aca6ff413020ff413020ff413020ff413020ff413020ff413020ff413020ff413020ff413020ff413020ff413020ff413020ff413020ff413020ff413020ff413020ff413020ff413020ff413020ff413020ff413020ff413020ff413020ff413020ff413020ff413020ff413020ff413020ff413020ff413020ff413020ff413020ff413020ff413020ff413020ff413020ff413020ff413020ff413020ff413020ff413020ff413020ff413020ff413020ff413020ff413020ff413020ff413020ff413020ff413020ff413020ff413020ff413020ff413020ff413020ff413020ff413020ff413020ff413020ff413020ff413020ff413020ff413020ff413020ff413020ff413020ff413020ff413020ff413020ff413020ff413020ff413020ff413020ff413020ff413020ff36281ada0000008a0000006500000042000000270000001400000009000000020000000000000001000000050000000e0000001c00000034231b107a423121ff423121ff423121ff423121ff423121ff423121ff423121ff423121ff423121ff423121ff423121ff423121ff423121ff423121ff423121ff423121ff423121ff423121ff423121ff423121ff423121ff423121ff423121ff463525ffeae8e7ffffffffff4d4945ff140f0aff140f0aff140f0aff140f0aff140f0aff140f0aff140f0aff140f0affbebdbcffffffffff948a81ff423121ff423121ff423121ff423121ff423121ff423121ff423121ff423121ff423121ff423121ff423121ff423121ff423121ff423121ff423121ff423121ff423121ff423121ff423121ff423121ff423121ff423121ff423121ff423121ff423121ff423121ff423121ff423121ff423121ff423121ff423121ff423121ff423121ff423121ff423121ff423121ff423121ff423121ff423121ff423121ff423121ff423121ff423121ff423121ff423121ff423121ff423121ff423121ff423121ff423121ff423121ff423121ff423121ff423121ff423121ff423121ff423121ff423121ff423121ff423121ff423121ff423121ff423121ff423121ff423121ff423121ff423121ff423121ff423121ff423121ff423121ff423121ff423121ff423121ff423121ff382a1cda0000008a0000006500000042000000270000001400000009000000020000000000000001000000050000000e0000001c00000034231b107a423121ff423121ff423121ff423121ff423121ff423121ff423121ff423121ff423121ff423121ff423121ff423121ff423121ff423121ff423121ff423121ff423121ff423121ff423121ff423121ff423121ff423121ff423121ff524233fff9f8f8fffbfbfbff302c27ff140f0aff140f0aff140f0aff140f0aff140f0aff140f0aff140f0aff16110cffdcdbdbffffffffff76695eff423121ff423121ff423121ff423121ff423121ff423121ff423121ff423121ff423121ff423121ff423121ff423121ff423121ff423121ff423121ff423121ff423121ff423121ff423121ff423121ff423121ff423121ff423121ff423121ff423121ff423121ff423121ff423121ff423121ff423121ff423121ff423121ff423121ff423121ff423121ff423121ff423121ff423121ff423121ff423121ff423121ff423121ff423121ff423121ff423121ff423121ff423121ff423121ff423121ff423121ff423121ff423121ff423121ff423121ff423121ff423121ff423121ff423121ff423121ff423121ff423121ff423121ff423121ff423121ff423121ff423121ff423121ff423121ff423121ff423121ff423121ff423121ff423121ff423121ff423121ff382a1cda0000008a0000006500000042000000270000001400000009000000020000000000000001000000050000000e0000001c00000034251b107a433121ff433121ff433121ff433121ff433121ff433121ff433121ff433121ff433121ff433121ff433121ff433121ff433121ff433121ff433121ff433121ff433121ff433121ff433121ff433121ff433121ff433121ff433121ff635446fffefefeffeeeeedff1e1915ff140f0aff140f0aff140f0aff140f0aff140f0aff140f0aff140f0aff1c1713ffedececfffefefeff655649ff433121ff433121ff433121ff433121ff433121ff433121ff433121ff433121ff433121ff433121ff433121ff433121ff433121ff433121ff433121ff433121ff433121ff433121ff433121ff433121ff433121ff433121ff433121ff433121ff433121ff433121ff433121ff433121ff433121ff433121ff433121ff433121ff433121ff433121ff433121ff433121ff433121ff433121ff433121ff433121ff433121ff433121ff433121ff433121ff433121ff433121ff433121ff433121ff433121ff433121ff433121ff433121ff433121ff433121ff433121ff433121ff433121ff433121ff433121ff433121ff433121ff433121ff433121ff433121ff433121ff433121ff433121ff433121ff433121ff433121ff433121ff433121ff433121ff433121ff433121ff392a1cda0000008a0000006500000042000000270000001400000009000000020000000000000001000000050000000e0000001c00000034251b107a433221ff433221ff433221ff433221ff433221ff433221ff433221ff433221ff433221ff433221ff433221ff433221ff433221ff433221ff433221ff433221ff433221ff433221ff433221ff433221ff433221ff433221ff433221ff6b5d50ffffffffffe7e7e6ff19140fff140f0aff140f0aff140f0aff140f0aff140f0aff140f0aff140f0aff292420fff9f9f9fffafaf9ff544535ff433221ff433221ff433221ff433221ff433221ff433221ff433221ff433221ff433221ff433221ff433221ff433221ff433221ff433221ff433221ff433221ff433221ff433221ff433221ff433221ff433221ff433221ff433221ff433221ff433221ff433221ff433221ff433221ff433221ff433221ff433221ff433221ff433221ff433221ff433221ff433221ff433221ff433221ff433221ff433221ff433221ff433221ff433221ff433221ff433221ff433221ff433221ff433221ff433221ff433221ff433221ff433221ff433221ff433221ff433221ff433221ff433221ff433221ff433221ff433221ff433221ff433221ff433221ff433221ff433221ff433221ff433221ff433221ff433221ff433221ff433221ff433221ff433221ff433221ff433221ff392a1cda0000008a0000006500000042000000270000001400000009000000020000000000000001000000050000000e0000001c00000034251b107a443221ff443221ff443221ff443221ff443221ff443221ff443221ff443221ff443221ff443221ff443221ff443221ff443221ff443221ff443221ff443221ff443221ff443221ff443221ff443221ff443221ff443221ff443221ff7e7166ffffffffffd3d2d1ff150f0aff150f0aff150f0aff150f0aff150f0aff150f0aff150f0aff150f0aff312c27fffbfbfbfff6f5f5ff514031ff443221ff443221ff443221ff443221ff443221ff443221ff443221ff443221ff443221ff443221ff443221ff443221ff443221ff443221ff443221ff443221ff443221ff443221ff443221ff443221ff443221ff443221ff443221ff"
.const [_187] = Utf8 "443221ff443221ff443221ff443221ff443221ff443221ff443221ff443221ff443221ff443221ff443221ff443221ff443221ff443221ff443221ff443221ff443221ff443221ff443221ff443221ff443221ff443221ff443221ff443221ff443221ff443221ff443221ff443221ff443221ff443221ff443221ff443221ff443221ff443221ff443221ff443221ff443221ff443221ff443221ff443221ff443221ff443221ff443221ff443221ff443221ff443221ff443221ff443221ff443221ff443221ff443221ff443221ff392a1cda0000008a0000006500000042000000270000001400000009000000020000000000000001000000050000000e0000001c00000034251b127a443222ff443222ff443222ff443222ff443222ff443222ff443222ff443222ff443222ff443222ff443222ff443222ff443222ff443222ff443222ff443222ff443222ff443222ff443222ff443222ff443222ff443222ff443222ff7e7267ffffffffffd2d1d0ff150f0aff150f0aff150f0aff150f0aff150f0aff150f0aff150f0aff150f0aff413c38ffffffffffeeecebff493727ff443222ff443222ff443222ff443222ff443222ff443222ff443222ff443222ff443222ff443222ff443222ff443222ff443222ff443222ff443222ff443222ff443222ff443222ff443222ff443222ff443222ff443222ff443222ff443222ff443222ff443222ff443222ff443222ff443222ff443222ff443222ff443222ff443222ff443222ff443222ff443222ff443222ff443222ff443222ff443222ff443222ff443222ff443222ff443222ff443222ff443222ff443222ff443222ff443222ff443222ff443222ff443222ff443222ff443222ff443222ff443222ff443222ff443222ff443222ff443222ff443222ff443222ff443222ff443222ff443222ff443222ff443222ff443222ff443222ff443222ff443222ff443222ff443222ff443222ff443222ff392b1dda0000008a0000006500000042000000270000001400000009000000020000000000000001000000050000000e0000001c00000034251b127a443322ff443322ff443322ff443322ff443322ff443322ff443322ff443322ff443322ff443322ff443322ff443322ff443322ff443322ff443322ff443322ff443322ff443322ff443322ff443322ff443322ff443322ff443322ff93897fffffffffffbbbab8ff150f0aff150f0aff150f0aff150f0aff150f0aff150f0aff150f0aff150f0aff413c38ffffffffffeeecebff493827ff443322ff443322ff443322ff443322ff443322ff443322ff443322ff443322ff443322ff443322ff443322ff443322ff443322ff443322ff443322ff443322ff443322ff443322ff443322ff443322ff443322ff443322ff443322ff443322ff443322ff443322ff443322ff443322ff443322ff443322ff443322ff443322ff443322ff443322ff443322ff443322ff443322ff443322ff443322ff443322ff443322ff443322ff443322ff443322ff443322ff443322ff443322ff443322ff443322ff443322ff443322ff443322ff443322ff443322ff443322ff443322ff443322ff443322ff443322ff443322ff443322ff443322ff443322ff443322ff443322ff443322ff443322ff443322ff443322ff443322ff443322ff443322ff443322ff443322ff443322ff3a2b1dda0000008a0000006500000042000000270000001400000009000000020000000000000001000000050000000e0000001c00000034251b127a453322ff453322ff453322ff453322ff453322ff453322ff453322ff453322ff453322ff453322ff453322ff453322ff453322ff453322ff453322ff453322ff453322ff453322ff453322ff453322ff453322ff453322ff453322ff958b82ffffffffffb6b4b3ff150f0aff150f0aff150f0aff150f0aff150f0aff150f0aff150f0aff150f0aff413c38ffffffffffeeecebff493827ff453322ff453322ff453322ff453322ff453322ff453322ff453322ff453322ff453322ff453322ff453322ff453322ff453322ff453322ff453322ff453322ff453322ff453322ff453322ff453322ff453322ff453322ff453322ff453322ff453322ff453322ff453322ff453322ff453322ff453322ff453322ff453322ff453322ff453322ff453322ff453322ff453322ff453322ff453322ff453322ff453322ff453322ff453322ff453322ff453322ff453322ff453322ff453322ff453322ff453322ff453322ff453322ff453322ff453322ff453322ff453322ff453322ff453322ff453322ff453322ff453322ff453322ff453322ff453322ff453322ff453322ff453322ff453322ff453322ff453322ff453322ff453322ff453322ff453322ff453322ff3a2b1dda0000008a0000006500000042000000270000001400000009000000020000000000000001000000050000000e0000001c00000034251b127a453322ff453322ff453322ff453322ff453322ff453322ff453322ff453322ff453322ff453322ff453322ff453322ff453322ff453322ff453322ff453322ff453322ff453322ff453322ff453322ff453322ff453322ff453322ff968b82ffffffffffb6b4b3ff150f0aff150f0aff150f0aff150f0aff150f0aff150f0aff150f0aff150f0aff413c38ffffffffffeeecebff4a3828ff453322ff453322ff453322ff453322ff453322ff453322ff453322ff453322ff453322ff453322ff453322ff453322ff453322ff453322ff453322ff453322ff453322ff453322ff453322ff453322ff453322ff453322ff453322ff453322ff453322ff453322ff453322ff453322ff453322ff453322ff453322ff453322ff453322ff453322ff453322ff453322ff453322ff453322ff453322ff453322ff453322ff453322ff453322ff453322ff453322ff453322ff453322ff453322ff453322ff453322ff453322ff453322ff453322ff453322ff453322ff453322ff453322ff453322ff453322ff453322ff453322ff453322ff453322ff453322ff453322ff453322ff453322ff453322ff453322ff453322ff453322ff453322ff453322ff453322ff453322ff3a2b1dda0000008a0000006500000042000000270000001400000009000000020000000000000001000000050000000e0000001c00000034271b127a463423ff463423ff463423ff463423ff463423ff463423ff463423ff463423ff463423ff463423ff463423ff463423ff463423ff463423ff463423ff463423ff463423ff463423ff463423ff463423ff463423ff463423ff463423ff968c82ffffffffffb6b4b3ff15100bff15100bff15100bff15100bff15100bff15100bff15100bff15100bff413d39ffffffffffeeecebff4a3928ff463423ff463423ff463423ff463423ff463423ff463423ff463423ff463423ff463423ff463423ff463423ff463423ff463423ff463423ff463423ff463423ff463423ff463423ff463423ff463423ff463423ff463423ff463423ff463423ff463423ff463423ff463423ff463423ff463423ff463423ff463423ff463423ff463423ff463423ff463423ff463423ff463423ff463423ff463423ff463423ff463423ff463423ff463423ff463423ff463423ff463423ff463423ff463423ff463423ff463423ff463423ff463423ff463423ff463423ff463423ff463423ff463423ff463423ff463423ff463423ff463423ff463423ff463423ff463423ff463423ff463423ff463423ff463423ff463423ff463423ff463423ff463423ff463423ff463423ff463423ff3b2c1dda0000008a0000006500000042000000270000001400000009000000020000000000000001000000050000000e0000001c00000034271b127a463423ff463423ff463423ff463423ff463423ff463423ff463423ff463423ff463423ff463423ff463423ff463423ff463423ff463423ff463423ff463423ff463423ff463423ff463423ff463423ff463423ff463423ff463423ff92877dffffffffffbbbab8ff15100bff15100bff15100bff15100bff15100bff15100bff15100bff15100bff413d39ffffffffffeeecebff4a3928ff463423ff463423ff463423ff463423ff463423ff463423ff463423ff463423ff463423ff463423ff463423ff463423ff463423ff463423ff463423ff463423ff463423ff463423ff463423ff463423ff463423ff463423ff463423ff463423ff463423ff463423ff463423ff463423ff463423ff463423ff463423ff463423ff463423ff463423ff463423ff463423ff463423ff463423ff463423ff463423ff463423ff463423ff463423ff463423ff463423ff463423ff463423ff463423ff463423ff463423ff463423ff463423ff463423ff463423ff463423ff463423ff463423ff463423ff463423ff463423ff463423ff463423ff463423ff463423ff463423ff463423ff463423ff463423ff463423ff463423ff463423ff463423ff463423ff463423ff463423ff3b2c1dda0000008a0000006500000042000000270000001400000009000000020000000000000001000000050000000e0000001c00000034271b127a473423ff473423ff473423ff473423ff473423ff473423ff473423ff473423ff473423ff473423ff473423ff473423ff473423ff473423ff473423ff473423ff473423ff473423ff473423ff473423ff473423ff473423ff473423ff807367ffffffffffd2d1d0ff15100bff15100bff15100bff15100bff15100bff15100bff15100bff15100bff413d39ffffffffffeeecebff4b3928ff473423ff473423ff473423ff473423ff473423ff473423ff473423ff473423ff473423ff473423ff473423ff473423ff473423ff473423ff473423ff473423ff473423ff473423ff473423ff473423ff473423ff473423ff473423ff473423ff473423ff473423ff473423ff473423ff473423ff473423ff473423ff473423ff473423ff473423ff473423ff473423ff473423ff473423ff473423ff473423ff473423ff473423ff473423ff473423ff473423ff473423ff473423ff473423ff473423ff473423ff473423ff473423ff473423ff473423ff473423ff473423ff473423ff473423ff473423ff473423ff473423ff473423ff473423ff473423ff473423ff473423ff473423ff473423ff473423ff473423ff473423ff473423ff473423ff473423ff473423ff3c2c1dda0000008a0000006500000042000000270000001400000009000000020000000000000001000000050000000e0000001c00000034271d127a473523ff473523ff473523ff473523ff473523ff473523ff473523ff473523ff473523ff473523ff473523ff473523ff473523ff473523ff473523ff473523ff473523ff473523ff473523ff473523ff473523ff473523ff473523ff7f7266ffffffffffd4d3d3ff15100bff15100bff15100bff15100bff15100bff15100bff15100bff15100bff2e2a25fffafafafff8f7f6ff554434ff473523ff473523ff473523ff473523ff473523ff473523ff473523ff473523ff473523ff473523ff473523ff473523ff473523ff473523ff473523ff473523ff473523ff473523ff473523ff473523ff473523ff473523ff473523ff473523ff473523ff473523ff473523ff473523ff473523ff473523ff473523ff473523ff473523ff473523ff473523ff473523ff473523ff473523ff473523ff473523ff473523ff473523ff473523ff473523ff473523ff473523ff473523ff473523ff473523ff473523ff473523ff473523ff473523ff473523ff473523ff473523ff473523ff473523ff473523ff473523ff473523ff473523ff473523ff473523ff473523ff473523ff473523ff473523ff473523ff473523ff473523ff473523ff473523ff473523ff473523ff3c2c1dda0000008a0000006500000042000000270000001400000009000000020000000000000001000000050000000e0000001c00000034271d127a483524ff483524ff483524ff483524ff483524ff483524ff483524ff483524ff483524ff483524ff483524ff483524ff483524ff483524ff483524ff483524ff483524ff483524ff483524ff483524ff483524ff483524ff483524ff6d5d50ffffffffffe9e8e8ff1b1611ff16100bff16100bff16100bff16100bff16100bff16100bff16100bff2a2520fff8f8f8fffafafaff5a493aff483524ff483524ff483524ff483524ff483524ff483524ff483524ff483524ff483524ff483524ff483524ff483524ff483524ff483524ff483524ff483524ff483524ff483524ff483524ff483524ff483524ff483524ff483524ff483524ff483524ff483524ff483524ff483524ff483524ff483524ff483524ff483524ff483524ff483524ff483524ff483524ff483524ff483524ff483524ff483524ff483524ff483524ff483524ff483524ff483524ff483524ff483524ff483524ff483524ff483524ff483524ff483524ff483524ff483524ff483524ff483524ff483524ff483524ff483524ff483524ff483524ff483524ff483524ff483524ff483524ff483524ff483524ff483524ff483524ff483524ff483524ff483524ff483524ff483524ff483524ff3d2c1eda0000008a0000006500000042000000270000001400000009000000020000000000000001000000050000000e0000001c00000034271d127a483524ff483524ff483524ff483524ff483524ff483524ff483524ff483524ff483524ff483524ff483524ff483524ff483524ff483524ff483524ff483524ff483524ff483524ff483524ff483524ff483524ff483524ff483524ff655547fffdfdfdfff0f0f0ff221c18ff16100bff16100bff16100bff16100bff16100bff16100bff16100bff1d1712ffebebeaffffffffff6a5b4dff483524ff483524ff483524ff483524ff483524ff483524ff483524ff483524ff483524ff483524ff483524ff483524ff483524ff483524ff483524ff483524ff483524ff483524ff483524ff483524ff483524ff483524ff483524ff483524ff483524ff483524ff483524ff483524ff483524ff483524ff483524ff483524ff483524ff483524ff483524ff483524ff483524ff483524ff483524ff483524ff483524ff483524ff483524ff483524ff483524ff483524ff483524ff483524ff483524ff483524ff483524ff483524ff483524ff483524ff483524ff483524ff483524ff483524ff483524ff483524ff483524ff483524ff483524ff483524ff483524ff483524ff483524ff483524ff483524ff483524ff483524ff483524ff483524ff483524ff483524ff3d2d1eda0000008a0000006500000042000000270000001400000009000000020000000000000001000000050000000e0000001c00000034271d127a493624ff493624ff493624ff493624ff493624ff493624ff493624ff493624ff493624ff493624ff493624ff493624ff493624ff493624ff493624ff493624ff493624ff493624ff493624ff493624ff493624ff493624ff493624ff574535fff8f7f6fffbfbfbff35302bff16100bff16100bff16100bff16100bff16100bff16100bff16100bff17120cffd9d8d8ffffffffff7f7165ff493624ff493624ff493624ff493624ff493624ff493624ff493624ff493624ff493624ff493624ff493624ff493624ff493624ff493624ff493624ff493624ff493624ff493624ff493624ff493624ff493624ff493624ff493624ff493624ff493624ff493624ff493624ff493624ff493624ff493624ff493624ff493624ff493624ff493624ff493624ff493624ff493624ff493624ff493624ff493624ff493624ff493624ff493624ff493624ff493624ff493624ff493624ff493624ff493624ff493624ff493624ff493624ff493624ff493624ff493624ff493624ff493624ff493624ff493624ff493624ff493624ff493624ff493624ff493624ff493624ff493624ff493624ff493624ff493624ff493624ff493624ff493624ff493624ff493624ff493624ff3d2d1eda0000008a0000006500000042000000270000001400000009000000020000000000000001000000050000000e0000001c00000034271d127a493624ff493624ff493624ff493624ff493624ff493624ff493624ff493624ff493624ff493624ff493624ff493624ff493624ff493624ff493624ff493624ff493624ff493624ff493624ff493624ff493624ff493624ff493624ff4c3927ffe9e6e4ffffffffff524d4aff16100bff16100bff16100bff16100bff16100bff16100bff16100bff16100bffbbb9b8ffffffffff9c9188ff493624ff493624ff493624ff493624ff493624ff493624ff493624ff493624ff493624ff493624ff493624ff493624ff493624ff493624ff493624ff493624ff493624ff493624ff493624ff493624ff493624ff493624ff493624ff493624ff493624ff493624ff493624ff493624ff493624ff493624ff493624ff493624ff493624ff493624ff493624ff493624ff493624ff493624ff493624ff493624ff493624ff493624ff493624ff493624ff493624ff493624ff493624ff493624ff493624ff493624ff493624ff493624ff493624ff493624ff493624ff493624ff493624ff493624ff493624ff493624ff493624ff493624ff493624ff493624ff493624ff493624ff493624ff493624ff493624ff493624ff493624ff493624ff493624ff493624ff493624ff3d2d1eda0000008a0000006500000042000000270000001400000009000000020000000000000001000000050000000e0000001c00000034271d127a493625ff493625ff493625ff493625ff493625ff493625ff493625ff493625ff493625ff493625ff493625ff493625ff493625ff493625ff493625ff493625ff493625ff493625ff493625ff493625ff493625ff493625ff493625ff493625ffd0cbc7ffffffffff7b7875ff16100bff16100bff16100bff16100bff16100bff16100bff16100bff16100bff999795ffffffffffbab2acff493625ff493625ff493625ff493625ff493625ff493625ff493625ff493625ff493625ff493625ff493625ff493625ff493625ff493625ff493625ff493625ff493625ff493625ff493625ff493625ff493625ff493625ff493625ff493625ff493625ff493625ff493625ff493625ff493625ff493625ff493625ff493625ff493625ff493625ff493625ff493625ff493625ff493625ff493625ff493625ff493625ff493625ff493625ff493625ff493625ff493625ff493625ff493625ff493625ff493625ff493625ff493625ff493625ff493625ff493625ff493625ff493625ff493625ff493625ff493625ff493625ff493625ff493625ff493625ff493625ff493625ff493625ff493625ff493625ff493625ff493625ff493625ff493625ff493625ff493625ff3d2e1fda0000008a0000006500000042000000270000001400000009000000020000000000000001000000050000000e0000001c00000034291f127a4a3725ff4a3725ff4a3725ff4a3725ff4a3725ff4a3725ff4a3725ff4a3725ff4a3725ff4a3725ff4a3725ff4a3725ff4a3725ff4a3725ff4a3725ff4a3725ff4a3725ff4a3725ff4a3725ff4a3725ff4a3725ff4a3725ff4a3725ff4a3725ffb0a89fffffffffffaaa8a6ff16110bff16110bff16110bff16110bff16110bff16110bff16110bff16110bff736f6cffffffffffd9d5d1ff4a3725ff4a3725ff4a3725ff4a3725ff4a3725ff4a3725ff4a3725ff4a3725ff4a3725ff4a3725ff4a3725ff4a3725ff4a3725ff4a3725ff4a3725ff4a3725ff4a3725ff4a3725ff4a3725ff4a3725ff4a3725ff4a3725ff4a3725ff4a3725ff4a3725ff4a3725ff4a3725ff4a3725ff4a3725ff4a3725ff4a3725ff4a3725ff4a3725ff4a3725ff4a3725ff4a3725ff4a3725ff4a3725ff4a3725ff4a3725ff4a3725ff4a3725ff4a3725ff4a3725ff4a3725ff4a3725ff4a3725ff4a3725ff4a3725ff4a3725ff4a3725ff4a3725ff4a3725ff4a3725ff4a3725ff4a3725ff4a3725ff4a3725ff4a3725ff4a3725ff4a3725ff4a3725ff4a3725ff4a3725ff4a3725ff4a3725ff4a3725ff4a3725ff4a3725ff4a3725ff4a3725ff4a3725ff4a3725ff4a3725ff4a3725ff3f2e1fda0000008a0000006500000042000000270000001400000009000000020000000000000001000000050000000e0000001c00000034291f127a4a3725ff4a3725ff4a3725ff4a3725ff4a3725ff4a3725ff4a3725ff4a3725ff4a3725ff4a3725ff4a3725ff4a3725ff4a3725ff4a3725ff4a3725ff4a3725ff4a3725ff4a3725ff4a3725ff4a3725ff4a3725ff4a3725ff4a3725ff4a3725ff8f8378ffffffffffd2d1d0ff17120cff16110bff16110bff16110bff16110bff16110bff16110bff16110bff413c37fffdfdfdfff7f7f6ff5a4938ff4a3725ff4a3725ff4a3725ff4a3725ff4a3725ff4a3725ff4a3725ff4a3725ff4a3725ff4a3725ff4a3725ff4a3725ff4a3725ff4a3725ff4a3725ff4a3725ff4a3725ff4a3725ff4a3725ff4a3725ff4a3725ff4a3725ff4a3725ff4a3725ff4a3725ff4a3725ff4a3725ff4a3725ff4a3725ff4a3725ff4a3725ff4a3725ff4a3725ff4a3725ff4a3725ff4a3725ff4a3725ff4a3725ff4a3725ff4a3725ff4a3725ff4a3725ff4a3725ff4a3725ff4a3725ff4a3725ff4a3725ff4a3725ff4a3725ff4a3725ff4a3725ff4a3725ff4a3725ff4a3725ff4a3725ff4a3725ff4a3725ff4a3725ff4a3725ff4a3725ff4a3725ff4a3725ff4a3725ff4a3725ff4a3725ff4a3725ff4a3725ff4a3725ff4a3725ff4a3725ff4a3725ff4a3725ff4a3725ff4a3725ff3f2e1fda0000008a0000006500000042000000270000001400000009000000020000000000000001000000050000000e0000001c00000034291f127a4b3725ff4b3725ff4b3725ff4b3725ff4b3725ff4b3725ff4b3725ff4b3725ff4b3725ff4b3725ff4b3725ff4b3725ff4b3725ff4b3725ff4b3725ff4b3725ff4b3725ff4b3725ff4b3725ff4b3725ff4b3725ff4b3725ff4b3725ff4b3725ff6d5e4ffffefefefff5f5f5ff2b2620ff17110bff17110bff17110bff17110bff17110bff17110bff17110bff201a15ffeae9e9ffffffffff807265ff4b3725ff4b3725ff4b3725ff4b3725ff4b3725ff4b3725ff4b3725ff4b3725ff4b3725ff4b3725ff4b3725ff4b3725ff4b3725ff4b3725ff4b3725ff4b3725ff4b3725ff4b3725ff4b3725ff4b3725ff4b3725ff4b3725ff4b3725ff4b3725ff4b3725ff4b3725ff4b3725ff4b3725ff4b3725ff4b3725ff4b3725ff4b3725ff4b3725ff4b3725ff4b3725ff4b3725ff4b3725ff4b3725ff4b3725ff4b3725ff4b3725ff4b3725ff4b3725ff4b3725ff4b3725ff4b3725ff4b3725ff4b3725ff4b3725ff4b3725ff4b3725ff4b3725ff4b3725ff4b3725ff4b3725ff4b3725ff4b3725ff4b3725ff4b3725ff4b3725ff4b3725ff4b3725ff4b3725ff4b3725ff4b3725ff4b3725ff4b3725ff4b3725ff4b3725ff4b3725ff4b3725ff4b3725ff4b3725ff4b3725ff402e1fda0000008a0000006500000042000000270000001400000009000000020000000000000001000000050000000e0000001c00000034291f147a4b3826ff4b3826ff4b3826ff4b3826ff4b3826ff4b3826ff4b3826ff4b3826ff4b3826ff4b3826ff4b3826ff4b3826ff4b3826ff4b3826ff4b3826ff4b3826ff4b3826ff4b3826ff4b3826ff4b3826ff4b3826ff4b3826ff4b3826ff4b3826ff52402effefedebffffffffff5b5753ff17110bff17110bff17110bff17110bff17110bff17110bff17110bff17110bffb5b4b2ffffffffffb3aba3ff4b3826ff4b3826ff4b3826ff4b3826ff4b3826ff4b3826ff4b3826ff4b3826ff4b3826ff4b3826ff4b3826ff4b3826ff4b3826ff4b3826ff4b3826ff4b3826ff4b3826ff4b3826ff4b3826ff4b3826ff4b3826ff4b3826ff4b3826ff4b3826ff4b3826ff4b3826ff4b3826ff4b3826ff4b3826ff4b3826ff4b3826ff4b3826ff4b3826ff4b3826ff4b3826ff4b3826ff4b3826ff4b3826ff4b3826ff4b3826ff4b3826ff4b3826ff4b3826ff4b3826ff4b3826ff4b3826ff4b3826ff4b3826ff4b3826ff4b3826ff4b3826ff4b3826ff4b3826ff4b3826ff4b3826ff4b3826ff4b3826ff4b3826ff4b3826ff4b3826ff4b3826ff4b3826ff4b3826ff4b3826ff4b3826ff4b3826ff4b3826ff4b3826ff4b3826ff4b3826ff4b3826ff4b3826ff4b3826ff4b3826ff402f20da0000008a0000006500000042000000270000001400000009000000020000000000000001000000050000000e0000001c00000034291f147a4c3826ff4c3826ff4c3826ff4c3826ff4c3826ff4c3826ff4c3826ff4c3826ff4c3826ff4c3826ff4c3826ff4c3826ff4c3826ff4c3826ff4c3826ff4c3826ff4c3826ff4c3826ff4c3826ff4c3826ff4c3826ff4c3826ff4c3826ff4c3826ff4c3826ffcac4bfffffffffff9d9a98ff17110bff17110bff17110bff17110bff17110bff17110bff17110bff17110bff696561ffffffffffe1dedbff4f3b29ff4c3826ff4c3826ff4c3826ff4c3826ff4c3826ff4c3826ff4c3826ff4c3826ff4c3826ff4c3826ff4c3826ff4c3826ff4c3826ff4c3826ff4c3826ff4c3826ff4c3826ff4c3826ff4c3826ff4c3826ff4c3826ff4c3826ff4c3826ff4c3826ff4c3826ff4c3826ff4c3826ff4c3826ff4c3826ff4c3826ff4c3826ff4c3826ff4c3826ff4c3826ff4c3826ff4c3826ff4c3826ff4c3826ff4c3826ff4c3826ff4c3826ff4c3826ff4c3826ff4c3826ff4c3826ff4c3826ff4c3826ff4c3826ff4c3826ff4c3826ff4c3826ff4c3826ff4c3826ff4c3826ff4c3826ff4c3826ff4c3826ff4c3826ff4c3826ff4c3826ff4c3826ff4c3826ff4c3826ff4c3826ff4c3826ff4c3826ff4c3826ff4c3826ff4c3826ff4c3826ff4c3826ff4c3826ff4c3826ff402f20da0000008a0000006500000042000000270000001400000009000000020000000000000001000000050000000e0000001c00000034291f147a4c3926ff4c3926ff4c3926ff4c3926ff4c3926ff4c3926ff4c3926ff4c3926ff4c3926ff4c3926ff4c3926ff4c3926ff4c3926ff4c3926ff4c3926ff4c3926ff4c3926ff4c3926ff4c3926ff4c3926ff4c3926ff4c3926ff4c3926ff4c3926ff4c3926ff92867bffffffffffd5d4d2ff19130dff17110bff17110bff17110bff17110bff17110bff17110bff17110bff29241efff1f1f0fffefdfdff756658ff4c3926ff4c3926ff4c3926ff4c3926ff4c3926ff4c3926ff4c3926ff4c3926ff4c3926ff4c3926ff4c3926ff4c3926ff4c3926ff4c3926ff4c3926ff4c3926ff4c3926ff4c3926ff4c3926ff4c3926ff4c3926ff4c3926ff4c3926ff4c3926ff4c3926ff4c3926ff4c3926ff4c3926ff4c3926ff4c3926ff4c3926ff4c3926ff4c3926ff4c3926ff4c3926ff4c3926ff4c3926ff4c3926ff4c3926ff4c3926ff4c3926ff4c3926ff4c3926ff4c3926ff4c3926ff4c3926ff4c3926ff4c3926ff4c3926ff4c3926ff4c3926ff4c3926ff4c3926ff4c3926ff4c3926ff4c3926ff4c3926ff4c3926ff4c3926ff4c3926ff4c3926ff4c3926ff4c3926ff4c3926ff4c3926ff4c3926ff4c3926ff4c3926ff4c3926ff4c3926ff4c3926ff4c3926ff4c3926ff402f20da0000008a0000006500000042000000270000001400000009000000020000000000000001000000050000000e0000001c00000034291f147a4d3926ff4d3926ff4d3926ff4d3926ff4d3926ff4d3926ff4d3926ff4d3926ff4d3926ff4d3926ff4d3926ff4d3926ff4d3926ff4d3926ff4d3926ff4d3926ff4d3926ff4d3926ff4d3926ff4d3926ff4d3926ff4d3926ff4d3926ff4d3926ff4d3926ff5f4d3cfff8f7f6fffbfbfbff3d3833ff17110bff17110bff17110bff17110bff17110bff17110bff17110bff17110bffb5b3b1ffffffffffb5ada5ff4d3926ff4d3926ff4d3926ff4d3926ff4d3926ff4d3926ff4d3926ff4d3926ff4d3926ff4d3926ff4d3926ff4d3926ff4d3926ff4d3926ff4d3926ff4d3926ff4d3926ff4d3926ff4d3926ff4d3926ff4d3926ff4d3926ff4d3926ff4d3926ff4d3926ff4d3926ff4d3926ff4d3926ff4d3926ff4d3926ff4d3926ff4d3926ff4d3926ff4d3926ff4d3926ff4d3926ff4d3926ff4d3926ff4d3926ff4d3926ff4d3926ff4d3926ff4d3926ff4d3926ff4d3926ff4d3926ff4d3926ff4d3926ff4d3926ff4d3926ff4d3926ff4d3926ff4d3926ff4d3926ff4d3926ff4d3926ff4d3926ff4d3926ff4d3926ff4d3926ff4d3926ff4d3926ff4d3926ff4d3926ff4d3926ff4d3926ff4d3926ff4d3926ff4d3926ff4d3926ff4d3926ff4d3926ff4d3926ff412f20da0000008a0000006500000042000000270000001400000009000000020000000000000001000000050000000e0000001c00000034291f147a4d3926ff4d3926ff4d3926ff4d3926ff4d3926ff4d3926ff4d3926ff4d3926ff4d3926ff4d3926ff4d3926ff4d3926ff4d3926ff4d3926ff4d3926ff4d3926ff4d3926ff4d3926ff4d3926ff4d3926ff4d3926ff4d3926ff4d3926ff4d3926ff4d3926ff4d3926ffcec9c4ffffffffff868380ff17110bff17110bff17110bff17110bff17110bff17110bff17110bff17110bff4e4945fffcfcfcffeeedebff594635ff4d3926ff4d3926ff4d3926ff4d3926ff4d3926ff4d3926ff4d3926ff4d3926ff4d3926ff4d3926ff4d3926ff4d3926ff4d3926ff4d3926ff4d3926ff4d3926ff4d3926ff4d3926ff4d3926ff4d3926ff4d3926ff4d3926ff4d3926ff4d3926ff4d3926ff4d3926ff4d3926ff4d3926ff4d3926ff4d3926ff4d3926ff4d3926ff4d3926ff4d3926ff4d3926ff4d3926ff4d3926ff4d3926ff4d3926ff4d3926ff4d3926ff4d3926ff4d3926ff4d3926ff4d3926ff4d3926ff4d3926ff4d3926ff4d3926ff4d3926ff4d3926ff4d3926ff4d3926ff4d3926ff4d3926ff4d3926ff4d3926ff4d3926ff4d3926ff4d3926ff4d3926ff4d3926ff4d3926ff4d3926ff4d3926ff4d3926ff4d3926ff4d3926ff4d3926ff4d3926ff4d3926ff4d3926ff412f20da0000008a0000006500000042000000270000001400000009000000020000000000000001000000050000000e0000001c000000342b1f147a4e3a27ff4e3a27ff4e3a27ff4e3a27ff4e3a27ff4e3a27ff4e3a27ff4e3a27ff4e3a27ff4e3a27ff4e3a27ff4e3a27ff4e3a27ff4e3a27ff4e3a27ff4e3a27ff4e3a27ff4e3a27ff4e3a27ff4e3a27ff4e3a27ff4e3a27ff4e3a27ff4e3a27ff4e3a27ff4e3a27ff918579ffffffffffdfdeddff211b16ff18120cff18120cff18120cff18120cff18120cff18120cff18120cff1b150fffc9c7c6ffffffffffa79e94ff4e3a27ff4e3a27ff4e3a27ff4e3a27ff4e3a27ff4e3a27ff4e3a27ff4e3a27ff4e3a27ff4e3a27ff4e3a27ff4e3a27ff4e3a27ff4e3a27ff4e3a27ff4e3a27ff4e3a27ff4e3a27ff4e3a27ff4e3a27ff4e3a27ff4e3a27ff4e3a27ff4e3a27ff4e3a27ff4e3a27ff4e3a27ff4e3a27ff4e3a27ff4e3a27ff4e3a27ff4e3a27ff4e3a27ff4e3a27ff4e3a27ff4e3a27ff4e3a27ff4e3a27ff4e3a27ff4e3a27ff4e3a27ff4e3a27ff4e3a27ff4e3a27ff4e3a27ff4e3a27ff4e3a27ff4e3a27ff4e3a27ff4e3a27ff4e3a27ff4e3a27ff4e3a27ff4e3a27ff4e3a27ff4e3a27ff4e3a27ff4e3a27ff4e3a27ff4e3a27ff4e3a27ff4e3a27ff4e3a27ff4e3a27ff4e3a27ff4e3a27ff4e3a27ff4e3a27ff4e3a27ff4e3a27ff4e3a27ff4e3a27ff423120da0000008a0000006500000042000000270000001400000009000000020000000000000001000000050000000e0000001c000000342b1f147a4e3a27ff4e3a27ff4e3a27ff4e3a27ff4e3a27ff4e3a27ff4e3a27ff4e3a27ff4e3a27ff4e3a27ff4e3a27ff4e3a27ff4e3a27ff4e3a27ff4e3a27ff4e3a27ff4e3a27ff4e3a27ff4e3a27ff4e3a27ff4e3a27ff4e3a27ff4e3a27ff4e3a27ff4e3a27ff4e3a27ff5a4735fff0efedffffffffff6c6865ff18120cff18120cff18120cff18120cff18120cff18120cff18120cff18120cff63605bfffefefefff3f2f0ff655443ff4e3a27ff4e3a27ff4e3a27ff4e3a27ff4e3a27ff4e3a27ff4e3a27ff4e3a27ff4e3a27ff4e3a27ff4e3a27ff4e3a27ff4e3a27ff4e3a27ff4e3a27ff4e3a27ff4e3a27ff4e3a27ff4e3a27ff4e3a27ff4e3a27ff4e3a27ff4e3a27ff4e3a27ff4e3a27ff4e3a27ff4e3a27ff4e3a27ff4e3a27ff4e3a27ff4e3a27ff4e3a27ff4e3a27ff4e3a27ff4e3a27ff4e3a27ff4e3a27ff4e3a27ff4e3a27ff4e3a27ff4e3a27ff4e3a27ff4e3a27ff4e3a27ff4e3a27ff4e3a27ff503c2aff4e3a27ff4e3a27ff4e3a27ff4e3a27ff4e3a27ff4e3a27ff4e3a27ff4e3a27ff4e3a27ff4e3a27ff4e3a27ff4e3a27ff4e3a27ff4e3a27ff4e3a27ff4e3a27ff4e3a27ff4e3a27ff4e3a27ff4e3a27ff4e3a27ff4e3a27ff4e3a27ff4e3a27ff423120da0000008a0000006500000042000000270000001400000009000000020000000000000001000000050000000e0000001c000000342b1f147a4f3a27ff4f3a27ff4f3a27ff4f3a27ff4f3a27ff4f3a27ff4f3a27ff4f3a27ff4f3a27ff4f3a27ff4f3a27ff4f3a27ff4f3a27ff4f3a27ff4f3a27ff4f3a27ff4f3a27ff4f3a27ff4f3a27ff4f3a27ff4f3a27ff4f3a27ff4f3a27ff4f3a27ff4f3a27ff4f3a27ff4f3a27ffb5aca4ffffffffffcccbcaff1b150fff18120cff18120cff18120cff18120cff18120cff18120cff18120cff1e1812ffcdcccbffffffffffccc6c1ff523d2aff4f3a27ff4f3a27ff4f3a27ff4f3a27ff4f3a27ff4f3a27ff4f3a27ff4f3a27ff4f3a27ff4f3a27ff4f3a27ff4f3a27ff4f3a27ff4f3a27ff4f3a27ff4f3a27ff4f3a27ff4f3a27ff4f3a27ff4f3a27ff4f3a27ff4f3a27ff4f3a27ff4f3a27ff4f3a27ff4f3a27ff4f3a27ff4f3a27ff4f3a27ff4f3a27ff4f3a27ff4f3a27ff4f3a27ff4f3a27ff4f3a27ff4f3a27ff4f3a27ff4f3a27ff4f3a27ff4f3a27ff4f3a27ff4f3a27ff4f3a27ff4f3a27ff62503fffb8afa8ff4f3a27ff4f3a27ff4f3a27ff4f3a27ff4f3a27ff4f3a27ff4f3a27ff4f3a27ff4f3a27ff4f3a27ff4f3a27ff4f3a27ff4f3a27ff4f3a27ff4f3a27ff4f3a27ff4f3a27ff4f3a27ff4f3a27ff4f3a27ff4f3a27ff4f3a27ff4f3a27ff4f3a27ff423120da0000008a0000006500000042000000270000001400000009000000020000000000000001000000050000000e0000001c000000342b21147a4f3b27ff4f3b27ff4f3b27ff4f3b27ff4f3b27ff4f3b27ff4f3b27ff4f3b27ff4f3b27ff4f3b27ff4f3b27ff4f3b27ff4f3b27ff4f3b27ff4f3b27ff4f3b27ff4f3b27ff4f3b27ff4f3b27ff4f3b27ff4f3b27ff4f3b27ff4f3b27ff4f3b27ff4f3b27ff4f3b27ff4f3b27ff6d5d4dfffaf9f9fffdfdfdff5a5551ff18120cff18120cff18120cff18120cff18120cff18120cff18120cff18120cff4d4944fff8f7f7fffefefeff95897dff4f3b27ff4f3b27ff4f3b27ff4f3b27ff4f3b27ff4f3b27ff4f3b27ff4f3b27ff4f3b27ff4f3b27ff4f3b27ff4f3b27ff4f3b27ff4f3b27ff4f3b27ff4f3b27ff4f3b27ff4f3b27ff4f3b27ff4f3b27ff4f3b27ff4f3b27ff4f3b27ff4f3b27ff4f3b27ff4f3b27ff4f3b27ff4f3b27ff4f3b27ff4f3b27ff4f3b27ff4f3b27ff4f3b27ff4f3b27ff4f3b27ff4f3b27ff4f3b27ff4f3b27ff4f3b27ff4f3b27ff4f3b27ff4f3b27ff4f3b27ff6d5c4cffe9e7e5ffddd9d6ff4f3b27ff4f3b27ff4f3b27ff4f3b27ff4f3b27ff4f3b27ff4f3b27ff4f3b27ff4f3b27ff4f3b27ff4f3b27ff4f3b27ff4f3b27ff4f3b27ff4f3b27ff4f3b27ff4f3b27ff4f3b27ff4f3b27ff4f3b27ff4f3b27ff4f3b27ff4f3b27ff4f3b27ff423221da0000008a0000006500000042000000270000001400000009000000020000000000000001000000050000000e0000001c000000342b21147a4f3b28ff4f3b28ff4f3b28ff4f3b28ff4f3b28ff4f3b28ff4f3b28ff4f3b28ff4f3b28ff4f3b28ff4f3b28ff4f3b28ff4f3b28ff4f3b28ff4f3b28ff4f3b28ff4f3b28ff4f3b28ff4f3b28ff4f3b28ff4f3b28ff4f3b28ff4f3b28ff4f3b28ff4f3b28ff4f3b28ff4f3b28ff4f3b28ffc1b9b3ffffffffffcac9c8ff1d1711ff18120cff18120cff18120cff18120cff18120cff18120cff18120cff18120cff878481fffefefefff3f2f1ff705f4fff4f3b28ff4f3b28ff4f3b28ff4f3b28ff4f3b28ff4f3b28ff4f3b28ff4f3b28ff4f3b28ff4f3b28ff4f3b28ff4f3b28ff4f3b28ff4f3b28ff4f3b28ff4f3b28ff4f3b28ff4f3b28ff4f3b28ff4f3b28ff4f3b28ff4f3b28ff4f3b28ff4f3b28ff4f3b28ff4f3b28ff4f3b28ff4f3b28ff4f3b28ff4f3b28ff4f3b28ff4f3b28ff4f3b28ff4f3b28ff4f3b28ff4f3b28ff4f3b28ff4f3b28ff4f3b28ff4f3b28ff4f3b28ff7d6e5fffedebe9ffffffffffddd9d6ff4f3b28ff4f3b28ff4f3b28ff4f3b28ff4f3b28ff4f3b28ff4f3b28ff4f3b28ff4f3b28ff4f3b28ff4f3b28ff4f3b28ff4f3b28ff4f3b28ff4f3b28ff4f3b28ff4f3b28ff4f3b28ff4f3b28ff4f3b28ff4f3b28ff4f3b28ff4f3b28ff4f3b28ff433221da0000008a0000006500000042000000270000001400000009000000020000000000000001000000050000000e0000001c000000342b21147a503b28ff503b28ff503b28ff503b28ff503b28ff503b28ff503b28ff503b28ff503b28ff503b28ff503b28ff503b28ff503b28ff503b28ff503b28ff503b28ff503b28ff503b28ff503b28ff503b28ff503b28ff503b28ff503b28ff503b28ff503b28ff503b28ff503b28ff503b28ff675544fff5f3f2fffefefeff6d6965ff18120cff18120cff18120cff18120cff18120cff18120cff18120cff18120cff1c1610ffb6b4b2ffffffffffe5e2dfff63503fff503b28ff503b28ff503b28ff503b28ff503b28ff503b28ff503b28ff503b28ff503b28ff503b28ff503b28ff503b28ff503b28ff503b28ff503b28ff503b28ff503b28ff503b28ff503b28ff503b28ff503b28ff503b28ff503b28ff503b28ff503b28ff503b28ff503b28ff503b28ff503b28ff503b28ff503b28ff503b28ff503b28ff503b28ff503b28ff503b28ff503b28ff503b28ff513d2aff988c81fff8f7f7ffffffffffffffffffddd9d6ff503b28ff503b28ff503b28ff503b28ff503b28ff503b28ff503b28ff503b28ff503b28ff503b28ff503b28ff503b28ff503b28ff503b28ff503b28ff503b28ff503b28ff503b28ff503b28ff503b28ff503b28ff503b28ff503b28ff503b28ff433221da0000008a0000006500000042000000270000001400000009000000020000000000000001000000050000000e0000001c000000342b21147a503c28ff503c28ff503c28ff503c28ff503c28ff503c28ff503c28ff503c28ff503c28ff503c28ff503c28ff503c28ff503c28ff503c28ff503c28ff503c28ff503c28ff503c28ff503c28ff503c28ff503c28ff503c28ff503c28ff503c28ff503c28ff503c28ff503c28ff503c28ff503c28ffada39affffffffffe5e5e4ff2d2722ff18120cff18120cff18120cff18120cff18120cff18120cff18120cff18120cff2c2621ffdcdcdbffffffffffe0dddaff655342ff503c28ff503c28ff503c28ff503c28ff503c28ff503c28ff503c28ff503c28ff503c28ff503c28ff503c28ff503c28ff503c28ff503c28ff503c28ff503c28ff503c28ff503c28ff503c28ff503c28ff503c28ff503c28ff503c28ff503c28ff503c28ff503c28ff503c28ff503c28ff503c28ff503c28ff503c28ff503c28ff503c28ff503c28ff503c28ff503c28ff5b4835ffbeb7affffefdfdfffdfdfdffd8d7d6ffffffffffdddad6ff503c28ff503c28ff503c28ff503c28ff503c28ff503c28ff503c28ff503c28ff503c28ff503c28ff503c28ff503c28ff503c28ff503c28ff503c28ff503c28ff503c28ff503c28ff503c28ff503c28ff503c28ff503c28ff503c28ff503c28ff453321da0000008a0000006500000042000000270000001400000009000000020000000000000001000000050000000e0000001c000000342b21147a513c28ff513c28ff513c28ff513c28ff513c28ff513c28ff513c28ff513c28ff513c28ff513c28ff513c28ff513c28ff513c28ff513c28ff513c28ff513c28ff513c28ff513c28ff513c28ff513c28ff513c28ff513c28ff513c28ff513c28ff513c28ff513c28ff513c28ff513c28ff513c28ff604d3bffeae8e6ffffffffffacaaa8ff1a140eff18120cff18120cff18120cff18120cff18120cff18120cff18120cff18120cff3f3a35ffe5e4e4ffffffffffebe9e6ff7a6a5bff513c28ff513c28ff513c28ff513c28ff513c28ff513c28ff513c28ff513c28ff513c28ff513c28ff513c28ff513c28ff513c28ff513c28ff513c28ff513c28ff513c28ff513c28ff513c28ff513c28ff513c28ff513c28ff513c28ff513c28ff513c28ff513c28ff513c28ff513c28ff513c28ff513c28ff513c28ff513c28ff513c28ff513c29ff807163ffe3dfdcfffffffffff6f6f6ff7c7875ff615d59ffffffffffdedad6ff513c28ff513c28ff513c28ff513c28ff513c28ff513c28ff513c28ff513c28ff513c28ff513c28ff513c28ff513c28ff513c28ff513c28ff513c28ff513c28ff513c28ff513c28ff513c28ff513c28ff513c28ff513c28ff513c28ff513c28ff453321da0000008a0000006500000042000000270000001400000009000000020000000000000001000000050000000e0000001c000000342b21167a513c29ff513c29ff513c29ff513c29ff513c29ff513c29ff513c29ff513c29ff513c29ff513c29ff513c29ff513c29ff513c29ff513c29ff513c29ff513c29ff513c29ff513c29ff513c29ff513c29ff513c29ff513c29ff513c29ff513c29ff513c29ff513c29ff513c29ff513c29ff513c29ff513c29ff7f6f61fff9f9f8fffdfdfdff7c7875ff18120cff18120cff18120cff18120cff18120cff18120cff18120cff18120cff18120cff3f3935ffdad9d8fffffffffff8f7f7ffa0958aff543f2cff513c29ff513c29ff513c29ff513c29ff513c29ff513c29ff513c29ff513c29ff513c29ff513c29ff513c29ff513c29ff513c29ff513c29ff513c29ff513c29ff513c29ff513c29ff513c29ff513c29ff513c29ff513c29ff513c29ff513c29ff513c29ff513c29ff513c29ff513c29ff513c29ff513c29ff675444ffbfb7b0fffcfbfbffffffffffdfdeddff4f4a46ff18120cff5f5b57ffffffffffdedad6ff513c29ff513c29ff513c29ff513c29ff513c29ff513c29ff513c29ff513c29ff513c29ff513c29ff513c29ff513c29ff513c29ff513c29ff513c29ff513c29ff513c29ff513c29ff513c29ff513c29ff513c29ff513c29ff513c29ff513c29ff453323da0000008a0000006500000042000000270000001400000009000000020000000000000001000000050000000e0000001c000000342d21167a523d29ff523d29ff523d29ff523d29ff523d29ff523d29ff523d29ff523d29ff523d29ff523d29ff523d29ff523d29ff523d29ff523d29ff523d29ff523d29ff523d29ff523d29ff523d29ff523d29ff523d29ff523d29ff523d29ff523d29ff523d29ff523d29ff523d29ff523d29ff523d29ff523d29ff523d29ffa59b90fffefefefff7f7f6ff58534fff19120cff19120cff19120cff19120cff19120cff19120cff19120cff19120cff19120cff2f2923ffbcbab8fffefefefffefefeffd6d1cdff7b6b5cff533e2aff523d29ff523d29ff523d29ff523d29ff523d29ff523d29ff523d29ff523d29ff523d29ff523d29ff523d29ff523d29ff523d29ff523d29ff523d29ff523d29ff523d29ff523d29ff523d29ff523d29ff523d29ff523d29ff523d29ff523d29ff523d29ff523d29ff63503effada39afff3f2f0fffffffffffbfbfbffa3a09eff29231dff19120cff19120cff605b57ffffffffffdedad6ff523d29ff523d29ff523d29ff523d29ff523d29ff523d29ff523d29ff523d29ff523d29ff523d29ff523d29ff523d29ff523d29ff523d29ff523d29ff523d29ff523d29ff523d29ff523d29ff523d29ff523d29ff523d29ff523d29ff523d29ff463423da0000008a0000006500000042000000270000001400000009000000020000000000000001000000050000000e0000001c000000342d21167a523d29ff523d29ff523d29ff523d29ff523d29ff523d29ff523d29ff523d29ff523d29ff523d29ff523d29ff523d29ff523d29ff523d29ff523d29ff523d29ff523d29ff523d29ff523d29ff523d29ff523d29ff523d29ff523d29ff523d29ff523d29ff523d29ff523d29ff523d29ff523d29ff523d29ff523d29ff56412effc9c2bcffffffffffeaeae9ff3a3530ff19120cff19120cff19120cff19120cff19120cff19120cff19120cff19120cff19120cff1e1711ff7e7a77ffefefeffffffffffffcfcfcffc5beb7ff716050ff523d29ff523d29ff523d29ff523d29ff523d29ff523d29ff523d29ff523d29ff523d29ff523d29ff523d29ff523d29ff523d29ff"
.const [_189] = Utf8 "523d29ff523d29ff523d29ff523d29ff523d29ff523d29ff523d29ff523d29ff523d29ff533f2bff726151ffbab2aafff5f4f3fffffffffffefefeffcdcccbff544f4aff19120cff19120cff19120cff19120cff605b57ffffffffffdedad6ff523d29ff523d29ff523d29ff523d29ff523d29ff523d29ff523d29ff523d29ff523d29ff523d29ff523d29ff523d29ff523d29ff523d29ff523d29ff523d29ff523d29ff523d29ff523d29ff523d29ff523d29ff523d29ff523d29ff523d29ff463423da0000008a0000006500000042000000270000001400000009000000020000000000000001000000050000000e0000001c000000342d21167a533d29ff533d29ff533d29ff533d29ff533d29ff533d29ff533d29ff533d29ff533d29ff533d29ff533d29ff533d29ff533d29ff533d29ff533d29ff533d29ff533d29ff533d29ff533d29ff533d29ff533d29ff533d29ff533d29ff533d29ff533d29ff533d29ff533d29ff533d29ff533d29ff533d29ff533d29ff533d29ff5e4a37ffdfdbd7ffffffffffd7d6d5ff322c26ff19120cff19120cff19120cff19120cff19120cff19120cff19120cff19120cff19120cff19120cff36302bffb0adacfffbfbfbfffffffffffbfafaffd2ccc7ff9d9085ff6d5b4aff56402dff533d29ff533d29ff533d29ff533d29ff533d29ff533d29ff533d29ff533d29ff533d29ff533d29ff533d29ff533d29ff533d29ff533d29ff533d29ff5f4a38ff7c6c5dffa89c92ffddd8d4fffcfbfbfffffffffffefefeffd4d3d2ff65605dff1f1812ff19120cff19120cff19120cff19120cff19120cff605b57ffffffffffdedad6ff533d29ff533d29ff533d29ff533d29ff533d29ff533d29ff533d29ff533d29ff533d29ff533d29ff533d29ff533d29ff533d29ff533d29ff533d29ff533d29ff533d29ff533d29ff533d29ff533d29ff533d29ff533d29ff533d29ff533d29ff473423da0000008a0000006500000042000000270000001400000009000000020000000000000001000000050000000e0000001c000000342d21167a533e2aff533e2aff533e2aff533e2aff533e2aff533e2aff533e2aff533e2aff533e2aff533e2aff533e2aff533e2aff533e2aff533e2aff533e2aff533e2aff533e2aff533e2aff533e2aff533e2aff533e2aff533e2aff533e2aff533e2aff533e2aff533e2aff533e2aff533e2aff533e2aff533e2aff533e2aff533e2aff533e2aff6c5a49ffeae7e5ffffffffffd7d6d5ff322c27ff19130dff19130dff19130dff19130dff19130dff19130dff19130dff19130dff19130dff19130dff1a140eff4d4944ffa7a5a2fff5f4f4fffffffffffffffffffcfcfcffe9e6e3ffcec8c2ffada39aff918477ff776757ff675543ff624f3dff624f3cff5a4633ff624f3dff624f3dff675543ff756454ff8e8073ffaca298ffd6d1ccfff5f4f3fffffffffffffffffffffffffff4f4f3ffaba8a6ff5a5652ff1f1913ff19130dff19130dff19130dff19130dff19130dff19130dff19130dff605c58ffffffffffdedad6ff533e2aff533e2aff533e2aff533e2aff533e2aff533e2aff533e2aff533e2aff533e2aff533e2aff533e2aff533e2aff533e2aff533e2aff533e2aff533e2aff533e2aff533e2aff533e2aff533e2aff533e2aff533e2aff533e2aff533e2aff473423da0000008a0000006500000042000000270000001400000009000000020000000000000001000000050000000e0000001c000000342d21167a543e2aff543e2aff543e2aff543e2aff543e2aff543e2aff543e2aff543e2aff543e2aff543e2aff543e2aff543e2aff543e2aff543e2aff543e2aff543e2aff543e2aff543e2aff543e2aff543e2aff543e2aff543e2aff543e2aff543e2aff543e2aff543e2aff543e2aff543e2aff543e2aff543e2aff543e2aff543e2aff543e2aff543e2aff675342ffe1dddaffffffffffdddcdbff433e39ff19130dff19130dff19130dff19130dff19130dff19130dff19130dff19130dff19130dff19130dff19130dff19130dff352f2aff7f7c78ffbdbbb9fff7f7f7fffffffffffffffffffffffffffffffffffffffffffcfbfbfffafaf9fffaf9f9fff2f1effffafaf9fffafaf9fffcfbfbfffffffffffffffffffffffffffffffffffefefeffecebebffbbb9b7ff706c68ff302b25ff19130dff19130dff19130dff19130dff19130dff19130dff19130dff19130dff19130dff19130dff605c58ffffffffffdedad6ff543e2aff543e2aff543e2aff543e2aff543e2aff543e2aff543e2aff543e2aff543e2aff543e2aff543e2aff543e2aff543e2aff543e2aff543e2aff543e2aff543e2aff543e2aff543e2aff543e2aff543e2aff543e2aff543e2aff543e2aff473423da0000008a0000006500000042000000270000001400000009000000020000000000000001000000050000000e0000001c000000342d21167a543e2aff543e2aff543e2aff543e2aff543e2aff543e2aff543e2aff543e2aff543e2aff543e2aff543e2aff543e2aff543e2aff543e2aff543e2aff543e2aff543e2aff543e2aff543e2aff543e2aff543e2aff543e2aff543e2aff543e2aff543e2aff543e2aff543e2aff543e2aff543e2aff543e2aff543e2aff543e2aff543e2aff543e2aff543e2aff665241ffdfdbd7fffffffffff0efefff6d6966ff1a140eff19130dff19130dff19130dff19130dff19130dff19130dff19130dff19130dff19130dff19130dff19130dff19130dff19130dff322c27ff5b5652ff807d79ffa4a19fffcecccbffe3e2e1ffeae9e9ffeae9e9ffeae9e9ffececebffeae9e9ffeae9e9ffeae9e9ffd5d4d2ffb7b5b4ffa7a5a3ff807d79ff48433eff251f19ff19130dff19130dff19130dff19130dff19130dff19130dff19130dff19130dff19130dff19130dff19130dff19130dff19130dff75716effffffffffdedad6ff543e2aff543e2aff543e2aff543e2aff543e2aff543e2aff543e2aff543e2aff543e2aff543e2aff543e2aff543e2aff543e2aff543e2aff543e2aff543e2aff543e2aff543e2aff543e2aff543e2aff543e2aff543e2aff543e2aff543e2aff473423da0000008a0000006500000042000000270000001400000009000000020000000000000001000000050000000e0000001c000000343023167a553f2aff553f2aff553f2aff553f2aff553f2aff553f2aff553f2aff553f2aff553f2aff553f2aff553f2aff553f2aff553f2aff553f2aff553f2aff553f2aff553f2aff553f2aff553f2aff553f2aff553f2aff553f2aff553f2aff553f2aff553f2aff553f2aff553f2aff553f2aff553f2aff553f2aff553f2aff553f2aff553f2aff553f2aff553f2aff553f2aff604c38ffc9c2bbfffefefefffcfcfcffaca9a7ff2e2823ff1a130dff1a130dff1a130dff1a130dff1a130dff1a130dff1a130dff1a130dff1a130dff1a130dff1a130dff1a130dff1a130dff1a130dff1a130dff1a130dff1a130dff1d1711ff1f1913ff1f1913ff1f1913ff211b15ff1f1913ff1f1913ff1f1913ff1b140eff1a130dff1a130dff1a130dff1a130dff1a130dff1a130dff1a130dff1a130dff1a130dff1a130dff1a130dff1a130dff1a130dff1a130dff1a130dff1a130dff37312bffadaba9fff8f8f8ffffffffffd4cfc9ff553f2aff553f2aff553f2aff553f2aff553f2aff553f2aff553f2aff553f2aff553f2aff553f2aff553f2aff553f2aff553f2aff553f2aff553f2aff553f2aff553f2aff553f2aff553f2aff553f2aff553f2aff553f2aff553f2aff553f2aff483523da0000008a0000006500000042000000270000001400000009000000020000000000000001000000050000000e0000001c000000343023167a553f2bff553f2bff553f2bff553f2bff553f2bff553f2bff553f2bff553f2bff553f2bff553f2bff553f2bff553f2bff553f2bff553f2bff553f2bff553f2bff553f2bff553f2bff553f2bff553f2bff553f2bff553f2bff553f2bff553f2bff553f2bff553f2bff553f2bff553f2bff553f2bff553f2bff553f2bff553f2bff553f2bff553f2bff553f2bff553f2bff553f2bff57422effa2968bfff8f7f7ffffffffffe5e5e4ff716d69ff1f1812ff1a130dff1a130dff1a130dff1a130dff1a130dff1a130dff1a130dff1a130dff1a130dff1a130dff1a130dff1a130dff1a130dff1a130dff1a130dff1a130dff1a130dff1a130dff1a130dff1a130dff1a130dff1a130dff1a130dff1a130dff1a130dff1a130dff1a130dff1a130dff1a130dff1a130dff1a130dff1a130dff1a130dff1a130dff1a130dff1a130dff1a130dff1a130dff29231dff8a8784ffefefeffffffffffffafaf9ffb4aaa1ff5f4a37ff553f2bff553f2bff553f2bff553f2bff553f2bff553f2bff553f2bff553f2bff553f2bff553f2bff553f2bff553f2bff553f2bff553f2bff553f2bff553f2bff553f2bff553f2bff553f2bff553f2bff553f2bff553f2bff553f2bff553f2bff483524da0000008a0000006500000042000000270000001400000009000000020000000000000001000000050000000e0000001c000000343023167a553f2bff553f2bff553f2bff553f2bff553f2bff553f2bff553f2bff553f2bff553f2bff553f2bff553f2bff553f2bff553f2bff553f2bff553f2bff553f2bff553f2bff553f2bff553f2bff553f2bff553f2bff553f2bff553f2bff553f2bff553f2bff553f2bff553f2bff553f2bff553f2bff553f2bff553f2bff553f2bff553f2bff553f2bff553f2bff553f2bff553f2bff553f2bff553f2bff7e6c5dffe8e5e2fffffffffffefefeffcbc9c8ff5b5652ff1d1610ff1a130dff1a130dff1a130dff1a130dff1a130dff1a130dff1a130dff1a130dff1a130dff1a130dff1a130dff1a130dff1a130dff1a130dff1a130dff1a130dff1a130dff1a130dff1a130dff1a130dff1a130dff1a130dff1a130dff1a130dff1a130dff1a130dff1a130dff1a130dff1a130dff1a130dff1a130dff1a130dff1a130dff1a130dff2f2823ff85817effe8e7e7fffffffffffefefeffdbd6d1ff7b695aff553f2bff553f2bff553f2bff553f2bff553f2bff553f2bff553f2bff553f2bff553f2bff553f2bff553f2bff553f2bff553f2bff553f2bff553f2bff553f2bff553f2bff553f2bff553f2bff553f2bff553f2bff553f2bff553f2bff553f2bff553f2bff553f2bff483524da0000008a0000006500000042000000270000001400000009000000020000000000000001000000050000000e0000001c000000343023167a56402bff56402bff56402bff56402bff56402bff56402bff56402bff56402bff56402bff56402bff56402bff56402bff56402bff56402bff56402bff56402bff56402bff56402bff56402bff56402bff56402bff56402bff56402bff56402bff56402bff56402bff56402bff56402bff56402bff56402bff56402bff56402bff56402bff56402bff56402bff56402bff56402bff56402bff56402bff56402bff64503cffafa59bfff3f2f0fffffffffffdfdfdffc9c8c6ff635e5aff26201aff1a130dff1a130dff1a130dff1a130dff1a130dff1a130dff1a130dff1a130dff1a130dff1a130dff1a130dff1a130dff1a130dff1a130dff1a130dff1a130dff1a130dff1a130dff1a130dff1a130dff1a130dff1a130dff1a130dff1a130dff1a130dff1a130dff1a130dff1a130dff1a130dff1c150fff48433effa6a4a1fff0f0efffffffffffffffffffe6e3e0ff97897cff5a4530ff56402bff56402bff56402bff56402bff56402bff56402bff56402bff56402bff56402bff56402bff56402bff56402bff56402bff56402bff56402bff56402bff56402bff56402bff56402bff56402bff56402bff56402bff56402bff56402bff56402bff56402bff56402bff493524da0000008a0000006500000042000000270000001400000009000000020000000000000001000000050000000e0000001c000000343023167a56402bff56402bff56402bff56402bff56402bff56402bff56402bff56402bff56402bff56402bff56402bff56402bff56402bff56402bff56402bff56402bff56402bff56402bff56402bff56402bff56402bff56402bff56402bff56402bff56402bff56402bff56402bff56402bff56402bff56402bff56402bff56402bff56402bff56402bff56402bff56402bff56402bff56402bff56402bff56402bff56402bff56402bff675240ffb0a59bfff3f2f0ffffffffffffffffffe9e8e8ffa4a29fff524d48ff201913ff1a130dff1a130dff1a130dff1a130dff1a130dff1a130dff1a130dff1a130dff1a130dff1a130dff1a130dff1a130dff1a130dff1a130dff1a130dff1a130dff1a130dff1a130dff1a130dff1a130dff1a130dff1a130dff1a130dff1c150fff3f3934ff878480ffd1d0cffffcfbfbfffffffffffefefeffe1dddaff9b8d81ff5c4632ff56402bff56402bff56402bff56402bff56402bff56402bff56402bff56402bff56402bff56402bff56402bff56402bff56402bff56402bff56402bff56402bff56402bff56402bff56402bff56402bff56402bff56402bff56402bff56402bff56402bff56402bff56402bff56402bff56402bff493524da0000008a0000006500000042000000270000001400000009000000020000000000000001000000050000000e0000001c000000343023167a57402bff57402bff57402bff57402bff57402bff57402bff57402bff57402bff57402bff57402bff57402bff57402bff57402bff57402bff57402bff57402bff57402bff57402bff57402bff57402bff57402bff57402bff57402bff57402bff57402bff57402bff57402bff57402bff57402bff57402bff57402bff57402bff57402bff57402bff57402bff57402bff57402bff57402bff57402bff57402bff57402bff57402bff57402bff57402bff675340ffb0a59cffedebe9fffffffffffffffffffefefeffe5e4e4ffadaba8ff77736fff4e4844ff332d27ff221b16ff1b140eff1a130dff1a130dff1a130dff1a130dff1a130dff1a130dff1a130dff1a130dff1a130dff1a130dff1a130dff1a130dff1b140eff241d18ff3c3631ff6b6763ffa19f9cffd5d4d3fffbfbfbfffffffffffffffffff8f8f7ffcdc6bfff857465ff5b4531ff57402bff57402bff57402bff57402bff57402bff57402bff57402bff57402bff57402bff57402bff57402bff57402bff57402bff57402bff57402bff57402bff57402bff57402bff57402bff57402bff57402bff57402bff57402bff57402bff57402bff57402bff57402bff57402bff57402bff57402bff57402bff493625da0000008a0000006500000042000000270000001400000009000000020000000000000001000000050000000e0000001c000000343023167a57412cff57412cff57412cff57412cff57412cff57412cff57412cff57412cff57412cff57412cff57412cff57412cff57412cff57412cff57412cff57412cff57412cff57412cff57412cff57412cff57412cff57412cff57412cff57412cff57412cff57412cff57412cff57412cff57412cff57412cff57412cff57412cff57412cff57412cff57412cff57412cff57412cff57412cff57412cff57412cff57412cff57412cff57412cff57412cff57412cff57412cff5f4935ff89796affc4bbb4ffefedebfffefefefffffffffffffffffffffffffffafafaffedececffd8d6d5ffbdbbb9ffa19e9bff837f7cff7e7976ff7e7976ff696561ff75706cff7e7976ff7e7976ff95928fffa19e9bffb9b7b5ffd5d4d3ffeeeeedfffcfcfcfffffffffffffffffffffffffff5f3f2ffcec8c2ff988a7eff6c5846ff57412cff57412cff57412cff57412cff57412cff57412cff57412cff57412cff57412cff57412cff57412cff57412cff57412cff57412cff57412cff57412cff57412cff57412cff57412cff57412cff57412cff57412cff57412cff57412cff57412cff57412cff57412cff57412cff57412cff57412cff57412cff57412cff57412cff57412cff4a3625da0000008a0000006500000042000000270000001400000009000000020000000000000001000000050000000e0000001c000000343023167a58412cff58412cff58412cff58412cff58412cff58412cff58412cff58412cff58412cff58412cff58412cff58412cff58412cff58412cff58412cff58412cff58412cff58412cff58412cff58412cff58412cff58412cff58412cff58412cff58412cff58412cff58412cff58412cff58412cff58412cff58412cff58412cff58412cff58412cff58412cff58412cff58412cff58412cff58412cff58412cff58412cff58412cff58412cff58412cff58412cff58412cff58412cff58412cff58412cff604a36ff7f6d5dffa69a8fffd2ccc6ffeeeceafffafaf9fffefefefffffffffffffffffffffffffffffffffffffffffffffffffffffffffffffffffffffffffffffffffffffffffffffffffffffffffffffffffffdfdfcfff3f1efffd1cbc5ffaca197ff867566ff644e3bff58412cff58412cff58412cff58412cff58412cff58412cff58412cff58412cff58412cff58412cff58412cff58412cff58412cff58412cff58412cff58412cff58412cff58412cff58412cff58412cff58412cff58412cff58412cff58412cff58412cff58412cff58412cff58412cff58412cff58412cff58412cff58412cff58412cff58412cff58412cff58412cff58412cff4a3625da0000008a0000006500000042000000270000001400000009000000020000000000000001000000050000000e0000001c000000343023167a58412cff58412cff58412cff58412cff58412cff58412cff58412cff58412cff58412cff58412cff58412cff58412cff58412cff58412cff58412cff58412cff58412cff58412cff58412cff58412cff58412cff58412cff58412cff58412cff58412cff58412cff58412cff58412cff58412cff58412cff58412cff58412cff58412cff58412cff58412cff58412cff58412cff58412cff58412cff58412cff58412cff58412cff58412cff58412cff58412cff58412cff58412cff58412cff58412cff58412cff58412cff58412cff58412cff5d4733ff67523fff786654ff8b7c6dff9c8f82ffb5aca2ffb6aca3ffb6aca3ffbcb4abffcbc4bdffc7c0b8ffb6aca3ffb6aca3ffb6aca3ffa4998dff9e9285ff8b7c6dff725f4dff604b37ff58412cff58412cff58412cff58412cff58412cff58412cff58412cff58412cff58412cff58412cff58412cff58412cff58412cff58412cff58412cff58412cff58412cff58412cff58412cff58412cff58412cff58412cff58412cff58412cff58412cff58412cff58412cff58412cff58412cff58412cff58412cff58412cff58412cff58412cff58412cff58412cff58412cff58412cff58412cff58412cff58412cff4a3825da0000008a0000006500000042000000270000001400000009000000020000000000000001000000050000000e0000001c000000333223167a59422cff59422cff59422cff59422cff59422cff59422cff59422cff59422cff59422cff59422cff59422cff59422cff59422cff59422cff59422cff59422cff59422cff59422cff59422cff59422cff59422cff59422cff59422cff59422cff59422cff59422cff59422cff59422cff59422cff59422cff59422cff59422cff59422cff59422cff59422cff59422cff59422cff59422cff59422cff59422cff59422cff59422cff59422cff59422cff59422cff59422cff59422cff59422cff59422cff59422cff59422cff59422cff59422cff59422cff59422cff59422cff59422cff59422cff59422cff59422cff59422cff59422cff59422cff59422cff59422cff59422cff59422cff59422cff59422cff59422cff59422cff59422cff59422cff59422cff59422cff59422cff59422cff59422cff59422cff59422cff59422cff59422cff59422cff59422cff59422cff59422cff59422cff59422cff59422cff59422cff59422cff59422cff59422cff59422cff59422cff59422cff59422cff59422cff59422cff59422cff59422cff59422cff59422cff59422cff59422cff59422cff59422cff59422cff59422cff59422cff59422cff59422cff59422cff4c3825da0000008a0000006400000042000000270000001400000009000000020000000000000001000000050000000e0000001c000000333223197a59422dff59422dff59422dff59422dff59422dff59422dff59422dff59422dff59422dff59422dff59422dff59422dff59422dff59422dff59422dff59422dff59422dff59422dff59422dff59422dff59422dff59422dff59422dff59422dff59422dff59422dff59422dff59422dff59422dff59422dff59422dff59422dff59422dff59422dff59422dff59422dff59422dff59422dff59422dff59422dff59422dff59422dff59422dff59422dff59422dff59422dff59422dff59422dff59422dff59422dff59422dff59422dff59422dff59422dff59422dff59422dff59422dff59422dff59422dff59422dff59422dff59422dff59422dff59422dff59422dff59422dff59422dff59422dff59422dff59422dff59422dff59422dff59422dff59422dff59422dff59422dff59422dff59422dff59422dff59422dff59422dff59422dff59422dff59422dff59422dff59422dff59422dff59422dff59422dff59422dff59422dff59422dff59422dff59422dff59422dff59422dff59422dff59422dff59422dff59422dff59422dff59422dff59422dff59422dff59422dff59422dff59422dff59422dff59422dff59422dff59422dff59422dff59422dff4c3826da0000008a0000006400000042000000270000001400000009000000020000000000000001000000050000000d0000001c000000333223197a5a422dff5a422dff5a422dff5a422dff5a422dff5a422dff5a422dff5a422dff5a422dff5a422dff5a422dff5a422dff5a422dff5a422dff5a422dff5a422dff5a422dff5a422dff5a422dff5a422dff5a422dff5a422dff5a422dff5a422dff5a422dff5a422dff5a422dff5a422dff5a422dff5a422dff5a422dff5a422dff5a422dff5a422dff5a422dff5a422dff5a422dff5a422dff5a422dff5a422dff5a422dff5a422dff5a422dff5a422dff5a422dff5a422dff5a422dff5a422dff5a422dff5a422dff5a422dff5a422dff5a422dff5a422dff5a422dff5a422dff5a422dff5a422dff5a422dff5a422dff5a422dff5a422dff5a422dff5a422dff5a422dff5a422dff5a422dff5a422dff5a422dff5a422dff5a422dff5a422dff5a422dff5a422dff5a422dff5a422dff5a422dff5a422dff5a422dff5a422dff5a422dff5a422dff5a422dff5a422dff5a422dff5a422dff5a422dff5a422dff5a422dff5a422dff5a422dff5a422dff5a422dff5a422dff5a422dff5a422dff5a422dff5a422dff5a422dff5a422dff5a422dff5a422dff5a422dff5a422dff5a422dff5a422dff5a422dff5a422dff5a422dff5a422dff5a422dff5a422dff5a422dff4c3826da0000008a0000006400000042000000270000001400000009000000020000000000000001000000050000000d0000001c000000333225197a5a432dff5a432dff5a432dff5a432dff5a432dff5a432dff5a432dff5a432dff5a432dff5a432dff5a432dff5a432dff5a432dff5a432dff5a432dff5a432dff5a432dff5a432dff5a432dff5a432dff5a432dff5a432dff5a432dff5a432dff5a432dff5a432dff5a432dff5a432dff5a432dff5a432dff5a432dff5a432dff5a432dff5a432dff5a432dff5a432dff5a432dff5a432dff5a432dff5a432dff5a432dff5a432dff5a432dff5a432dff5a432dff5a432dff5a432dff5a432dff5a432dff5a432dff5a432dff5a432dff5a432dff5a432dff5a432dff5a432dff5a432dff5a432dff5a432dff5a432dff5a432dff5a432dff5a432dff5a432dff5a432dff5a432dff5a432dff5a432dff5a432dff5a432dff5a432dff5a432dff5a432dff5a432dff5a432dff5a432dff5a432dff5a432dff5a432dff5a432dff5a432dff5a432dff5a432dff5a432dff5a432dff5a432dff5a432dff5a432dff5a432dff5a432dff5a432dff5a432dff5a432dff5a432dff5a432dff5a432dff5a432dff5a432dff5a432dff5a432dff5a432dff5a432dff5a432dff5a432dff5a432dff5a432dff5a432dff5a432dff5a432dff5a432dff5a432dff5a432dff5a432dff4d3926da0000008a0000006400000041000000260000001400000009000000020000000000000001000000050000000d0000001c000000333225197a5b432dff5b432dff5b432dff5b432dff5b432dff5b432dff5b432dff5b432dff5b432dff5b432dff5b432dff5b432dff5b432dff5b432dff5b432dff5b432dff5b432dff5b432dff5b432dff5b432dff5b432dff5b432dff5b432dff5b432dff5b432dff5b432dff5b432dff5b432dff5b432dff5b432dff5b432dff5b432dff5b432dff5b432dff5b432dff5b432dff5b432dff5b432dff5b432dff5b432dff5b432dff5b432dff5b432dff5b432dff5b432dff5b432dff5b432dff5b432dff5b432dff5b432dff5b432dff5b432dff5b432dff5b432dff5b432dff5b432dff5b432dff5b432dff5b432dff5b432dff5b432dff5b432dff5b432dff5b432dff5b432dff5b432dff5b432dff5b432dff5b432dff5b432dff5b432dff5b432dff5b432dff5b432dff5b432dff5b432dff5b432dff5b432dff5b432dff5b432dff5b432dff5b432dff5b432dff5b432dff5b432dff5b432dff5b432dff5b432dff5b432dff5b432dff5b432dff5b432dff5b432dff5b432dff5b432dff5b432dff5b432dff5b432dff5b432dff5b432dff5b432dff5b432dff5b432dff5b432dff5b432dff5b432dff5b432dff5b432dff5b432dff5b432dff5b432dff5b432dff5b432dff4e3926da000000890000006300000041000000260000001300000009000000020000000000000001000000050000000d0000001b00000032322519795b432eff5b432eff5b432eff5b432eff5b432eff5b432eff5b432eff5b432eff5b432eff5b432eff5b432eff5b432eff5b432eff5b432eff5b432eff5b432eff5b432eff5b432eff5b432eff5b432eff5b432eff5b432eff5b432eff5b432eff5b432eff5b432eff5b432eff5b432eff5b432eff5b432eff5b432eff5b432eff5b432eff5b432eff5b432eff5b432eff5b432eff5b432eff5b432eff5b432eff5b432eff5b432eff5b432eff5b432eff5b432eff5b432eff5b432eff5b432eff5b432eff5b432eff5b432eff5b432eff5b432eff5b432eff5b432eff5b432eff5b432eff5b432eff5b432eff5b432eff5b432eff5b432eff5b432eff5b432eff5b432eff5b432eff5b432eff5b432eff5b432eff5b432eff5b432eff5b432eff5b432eff5b432eff5b432eff5b432eff5b432eff5b432eff5b432eff5b432eff5b432eff5b432eff5b432eff5b432eff5b432eff5b432eff5b432eff5b432eff5b432eff5b432eff5b432eff5b432eff5b432eff5b432eff5b432eff5b432eff5b432eff5b432eff5b432eff5b432eff5b432eff5b432eff5b432eff5b432eff5b432eff5b432eff5b432eff5b432eff5b432eff5b432eff5b432eff5b432eff5b432eff4e3926da000000870000006100000040000000250000001300000008000000020000000000000001000000050000000c0000001a00000030332619785b442eff5b442eff5b442eff5b442eff5b442eff5b442eff5b442eff5b442eff5b442eff5b442eff5b442eff5b442eff5b442eff5b442eff5b442eff5b442eff5b442eff5b442eff5b442eff5b442eff5b442eff5b442eff5b442eff5b442eff5b442eff5b442eff5b442eff5b442eff5b442eff5b442eff5b442eff5b442eff5b442eff5b442eff5b442eff5b442eff5b442eff5b442eff5b442eff5b442eff5b442eff5b442eff5b442eff5b442eff5b442eff5b442eff5b442eff5b442eff5b442eff5b442eff5b442eff5b442eff5b442eff5b442eff5b442eff5b442eff5b442eff5b442eff5b442eff5b442eff5b442eff5b442eff5b442eff5b442eff5b442eff5b442eff5b442eff5b442eff5b442eff5b442eff5b442eff5b442eff5b442eff5b442eff5b442eff5b442eff5b442eff5b442eff5b442eff5b442eff5b442eff5b442eff5b442eff5b442eff5b442eff5b442eff5b442eff5b442eff5b442eff5b442eff5b442eff5b442eff5b442eff5b442eff5b442eff5b442eff5b442eff5b442eff5b442eff5b442eff5b442eff5b442eff5b442eff5b442eff5b442eff5b442eff5b442eff5b442eff5b442eff5b442eff5b442eff5b442eff5b442eff4b3825d5000000840000005f0000003d000000240000001200000008000000010000000000000001000000040000000b000000180000002d281b14655c442eff5c442eff5c442eff5c442eff5c442eff5c442eff5c442eff5c442eff5c442eff5c442eff5c442eff5c442eff5c442eff5c442eff5c442eff5c442eff5c442eff5c442eff5c442eff5c442eff5c442eff5c442eff5c442eff5c442eff5c442eff5c442eff5c442eff5c442eff5c442eff5c442eff5c442eff5c442eff5c442eff5c442eff5c442eff5c442eff5c442eff5c442eff5c442eff5c442eff5c442eff5c442eff5c442eff5c442eff5c442eff5c442eff5c442eff5c442eff5c442eff5c442eff5c442eff5c442eff5c442eff5c442eff5c442eff5c442eff5c442eff5c442eff5c442eff5c442eff5c442eff5c442eff5c442eff5c442eff5c442eff5c442eff5c442eff5c442eff5c442eff5c442eff5c442eff5c442eff5c442eff5c442eff5c442eff5c442eff5c442eff5c442eff5c442eff5c442eff5c442eff5c442eff5c442eff5c442eff5c442eff5c442eff5c442eff5c442eff5c442eff5c442eff5c442eff5c442eff5c442eff5c442eff5c442eff5c442eff5c442eff5c442eff5c442eff5c442eff5c442eff5c442eff5c442eff5c442eff5c442eff5c442eff5c442eff5c442eff5c442eff5c442eff5c442eff5c442eff5c442eff413020c90000007f0000005a0000003a000000210000001100000007000000010000000000000000000000040000000a000000160000002a1009064d59412ced5c442eff5c442eff5c442eff5c442eff5c442eff5c442eff5c442eff5c442eff5c442eff5c442eff5c442eff5c442eff5c442eff5c442eff5c442eff5c442eff5c442eff5c442eff5c442eff5c442eff5c442eff5c442eff5c442eff5c442eff5c442eff5c442eff5c442eff5c442eff5c442eff5c442eff5c442eff5c442eff5c442eff5c442eff5c442eff5c442eff5c442eff5c442eff5c442eff5c442eff5c442eff5c442eff5c442eff5c442eff5c442eff5c442eff5c442eff5c442eff5c442eff5c442eff5c442eff5c442eff5c442eff5c442eff5c442eff5c442eff5c442eff5c442eff5c442eff5c442eff5c442eff5c442eff5c442eff5c442eff5c442eff5c442eff5c442eff5c442eff5c442eff5c442eff5c442eff5c442eff5c442eff5c442eff5c442eff5c442eff5c442eff5c442eff5c442eff5c442eff5c442eff5c442eff5c442eff5c442eff5c442eff5c442eff5c442eff5c442eff5c442eff5c442eff5c442eff5c442eff5c442eff5c442eff5c442eff5c442eff5c442eff5c442eff5c442eff5c442eff5c442eff5c442eff5c442eff5c442eff5c442eff5c442eff5c442eff5c442eff5c442eff5c442eff5c442eff5c442eff281c13a90000007700000053000000350000001e0000000f00000006000000010000000000000000000000030000000800000013000000250000003e4a3724af5d452fff5d452fff5d452fff5d452fff5d452fff5d452fff5d452fff5d452fff5d452fff5d452fff5d452fff5d452fff5d452fff5d452fff5d452fff5d452fff5d452fff5d452fff5d452fff5d452fff5d452fff5d452fff5d452fff5d452fff5d452fff5d452fff5d452fff5d452fff5d452fff5d452fff5d452fff5d452fff5d452fff5d452fff5d452fff5d452fff5d452fff5d452fff5d452fff5d452fff5d452fff5d452fff5d452fff5d452fff5d452fff5d452fff5d452fff5d452fff5d452fff5d452fff5d452fff5d452fff5d452fff5d452fff5d452fff5d452fff5d452fff5d452fff5d452fff5d452fff5d452fff5d452fff5d452fff5d452fff5d452fff5d452fff5d452fff5d452fff5d452fff5d452fff5d452fff5d452fff5d452fff5d452fff5d452fff5d452fff5d452fff5d452fff5d452fff5d452fff5d452fff5d452fff5d452fff5d452fff5d452fff5d452fff5d452fff5d452fff5d452fff5d452fff5d452fff5d452fff5d452fff5d452fff5d452fff5d452fff5d452fff5d452fff5d452fff5d452fff5d452fff5d452fff5d452fff5d452fff5d452fff5d452fff5d452fff5d452fff5d452fff5d452fff5d452fff56402bea0503018e0000006c0000004a0000002e0000001a0000000d000000050000000100000000000000000000000200000007000000100000001f0000003515100a5e5a422ceb5d452fff5d452fff5d452fff5d452fff5d452fff5d452fff5d452fff5d452fff5d452fff5d452fff5d452fff5d452fff5d452fff5d452fff5d452fff5d452fff5d452fff5d452fff5d452fff5d452fff5d452fff5d452fff5d452fff5d452fff5d452fff5d452fff5d452fff5d452fff5d452fff5d452fff5d452fff5d452fff5d452fff5d452fff5d452fff5d452fff5d452fff5d452fff5d452fff5d452fff5d452fff5d452fff5d452fff5d452fff5d452fff5d452fff5d452fff5d452fff5d452fff5d452fff5d452fff5d452fff5d452fff5d452fff5d452fff5d452fff5d452fff5d452fff5d452fff5d452fff5d452fff5d452fff5d452fff5d452fff5d452fff5d452fff5d452fff5d452fff5d452fff5d452fff5d452fff5d452fff5d452fff5d452fff5d452fff5d452fff5d452fff5d452fff5d452fff5d452fff5d452fff5d452fff5d452fff5d452fff5d452fff5d452fff5d452fff5d452fff5d452fff5d452fff5d452fff5d452fff5d452fff5d452fff5d452fff5d452fff5d452fff5d452fff5d452fff5d452fff5d452fff5d452fff5d452fff5d452fff5d452fff5d452fff5d452fff5d452fff5d452fff5d452ffe2a2014af000000810000005f0000004000000027000000150000000a0000000400000000000000000000000000000001000000050000000c000000190000002b0000004538281a905d442efd5e452fff5e452fff5e452fff5e452fff5e452fff5e452fff5e452fff5e452fff5e452fff5e452fff5e452fff5e452fff5e452fff5e452fff5e452fff5e452fff5e452fff5e452fff5e452fff5e452fff5e452fff5e452fff5e452fff5e452fff5e452fff5e452fff5e452fff5e452fff5e452fff5e452fff5e452fff5e452fff5e452fff5e452fff5e452fff5e452fff5e452fff5e452fff5e452fff5e452fff5e452fff5e452fff5e452fff5e452fff5e452fff5e452fff5e452fff5e452fff5e452fff5e452fff5e452fff5e452fff5e452fff5e452fff5e452fff5e452fff5e452fff5e452fff5e452fff5e452fff5e452fff5e452fff5e452fff5e452fff5e452fff5e452fff5e452fff5e452fff5e452fff5e452fff5e452fff5e452fff5e452fff5e452fff5e452fff5e452fff5e452fff5e452fff5e452fff5e452fff5e452fff5e452fff5e452fff5e452fff5e452fff5e452fff5e452fff5e452fff5e452fff5e452fff5e452fff5e452fff5e452fff5e452fff5e452fff5e452fff5e452fff5e452fff5e452fff5e452fff5e452fff5e452fff5e452fff5e452fff5e452fff5e452fff5e452fff5e452fff473523d10100008f0000006f00000050000000350000001f00000010000000070000000200000000000000000000000000000001000000030000000900000012000000210000003700000052493624b55d452efe5e462fff5e462fff5e462fff5e462fff5e462fff5e462fff5e462fff5e462fff5e462fff5e462fff5e462fff5e462fff5e462fff5e462fff5e462fff5e462fff5e462fff5e462fff5e462fff5e462fff5e462fff5e462fff5e462fff5e462fff5e462fff5e462fff5e462fff5e462fff5e462fff5e462fff5e462fff5e462fff5e462fff5e462fff5e462fff5e462fff5e462fff5e462fff5e462fff5e462fff5e462fff5e462fff5e462fff5e462fff5e462fff5e462fff5e462fff5e462fff5e462fff5e462fff5e462fff5e462fff5e462fff5e462fff5e462fff5e462fff5e462fff5e462fff5e462fff5e462fff5e462fff5e462fff5e462fff5e462fff5e462fff5e462fff5e462fff5e462fff5e462fff5e462fff5e462fff5e462fff5e462fff5e462fff5e462fff5e462fff5e462fff5e462fff5e462fff5e462fff5e462fff5e462fff5e462fff5e462fff5e462fff5e462fff5e462fff5e462fff5e462fff5e462fff5e462fff5e462fff5e462fff5e462fff5e462fff5e462fff5e462fff5e462fff5e462fff5e462fff5e462fff5e462fff5e462fff5e462fff5e462fff5e462fff553e29e7080605960000007a0000005c0000004000000029000000170000000c00000005000000010000000000000000000000000000000000000002000000050000000d00000018000000290000003f020000593a2b1ea05d442ef65f4630ff5f4630ff5f4630ff5f4630ff5f4630ff5f4630ff5f4630ff5f4630ff5f4630ff5f4630ff5f4630ff5f4630ff5f4630ff5f4630ff5f4630ff5f4630ff5f4630ff5f4630ff5f4630ff5f4630ff5f4630ff5f4630ff5f4630ff5f4630ff5f4630ff5f4630ff5f4630ff5f4630ff5f4630ff5f4630ff5f4630ff5f4630ff5f4630ff5f4630ff5f4630ff5f4630ff5f4630ff5f4630ff5f4630ff5f4630ff5f4630ff5f4630ff5f4630ff5f4630ff5f4630ff5f4630ff5f4630ff5f4630ff5f4630ff5f4630ff5f4630ff5f4630ff5f4630ff5f4630ff5f4630ff5f4630ff5f4630ff5f4630ff5f4630ff5f4630ff5f4630ff5f4630ff5f4630ff5f4630ff5f4630ff5f4630ff5f4630ff5f4630ff5f4630ff5f4630ff5f4630ff5f4630ff5f4630ff5f4630ff5f4630ff5f4630ff5f4630ff5f4630ff5f4630ff5f4630ff5f4630ff5f4630ff5f4630ff5f4630ff5f4630ff5f4630ff5f4630ff5f4630ff5f4630ff5f4630ff5f4630ff5f4630ff5f4630ff5f4630ff5f4630ff5f4630ff5f4630ff5f4630ff5f4630ff5f4630ff5f4630ff5f4630ff5f4630ff5f4630fe4a3726d40b0805960000007e0000006200000048000000300000001e0000001000000008000000030000000000000000000000000000000000000000000000010000000300000008000000100000001c0000002d00000042000000591c140e7e503b28d15e452ffd5f4630ff5f4630ff5f4630ff5f4630ff5f4630ff5f4630ff5f4630ff5f4630ff5f4630ff5f4630ff5f4630ff5f4630ff5f4630ff5f4630ff5f4630ff5f4630ff5f4630ff5f4630ff5f4630ff5f4630ff5f4630ff5f4630ff5f4630ff5f4630ff5f4630ff5f4630ff5f4630ff5f4630ff5f4630ff5f4630ff5f4630ff5f4630ff5f4630ff5f4630ff5f4630ff5f4630ff5f4630ff5f4630ff5f4630ff5f4630ff5f4630ff5f4630ff5f4630ff5f4630ff5f4630ff5f4630ff5f4630ff5f4630ff5f4630ff5f4630ff5f4630ff5f4630ff5f4630ff5f4630ff5f4630ff5f4630ff5f4630ff5f4630ff5f4630ff5f4630ff5f4630ff5f4630ff5f4630ff5f4630ff5f4630ff5f4630ff5f4630ff5f4630ff5f4630ff5f4630ff5f4630ff5f4630ff5f4630ff5f4630ff5f4630ff5f4630ff5f4630ff5f4630ff5f4630ff5f4630ff5f4630ff5f4630ff5f4630ff5f4630ff5f4630ff5f4630ff5f4630ff5f4630ff5f4630ff5f4630ff5f4630ff5f4630ff5f4630ff5f4630ff5f4630ff5f4630ff5f4630ff5f4630ff5f4630ff5f4630ff58412cea2b2015af0100008f0000007a000000620000004b0000003400000022000000140000000a0000000400000002000000000000000000000000000000000000000000000000000000020000000400000009000000120000001e0000002e0000004000000054000000681e160f8841301fb84b3725cb493724cc493624cd493623ce493623ce483423cf483423cf483423cf483423cf483423cf483423cf483423cf483423cf483423cf483423cf483423cf483423cf483423cf483423cf483423cf483423cf483423cf483423cf483423cf483423cf483423cf483423cf483423cf483423cf483423cf483423cf483423cf483423cf483423cf483423cf483423cf483423cf483423cf483423cf483423cf483423cf483423cf483423cf483423cf483423cf483423cf483423cf483423cf483423cf483423cf483423cf483423cf483423cf483423cf483423cf483423cf483423cf483423cf483423cf483423cf483423cf483423cf483423cf483423cf483423cf483423cf483423cf483423cf483423cf483423cf483423cf483423cf483423cf483423cf483423cf483423cf483423cf483423cf483423cf483423cf483423cf483423cf483423cf483423cf483423cf483423cf483423cf483423cf483423cf483423cf483423cf483423cf483423cf483423cf493523ce493623ce493623ce453322c7271d13a70503018d000000800000006f0000005c000000480000003400000024000000160000000c0000000600000002000000000000000000000000000000000000000000000000000000000000000000000002000000050000000b000000120000001d0000002b0000003a0000004a0000005900000066000000710000007a0000007f000000830000008400000085000000850000008500000086000000860000008600000086000000860000008600000086000000860000008600000086000000860000008600000086000000860000008600000086000000860000008600000086000000860000008600000086000000860000008600000086000000860000008600000086000000860000008600000086000000860000008600000086000000860000008600000086000000860000008600000086000000860000008600000086000000860000008600000086000000860000008600000086000000860000008600000086000000860000008600000086000000860000008600000086000000860000008600000086000000860000008600000086000000860000008600000086000000860000008600000086000000860000008600000086000000860000008600000086000000860000008600000086000000860000008600000086000000860000008500000085000000850000008500000084000000800000007c000000750000006b0000005e00000050000000400000003000000022000000160000000d00000007000000030000000100000000000000000000000000000000000000000000000000000000000000000000000000000002000000050000000a000000110000001a00000024000000300000003b000000460000004e000000550000005a0000005d0000005e0000005f0000005f0000005f00000060000000600000006000000060000000600000006000000060000000600000006000000060000000600000006000000060000000600000006000000060000000600000006000000060000000600000006000000060000000600000006000000060000000600000006000000060000000600000006000000060000000600000006000000060000000600000006000000060000000600000006000000060000000600000006000000060000000600000006000000060000000600000006000000060000000600000006000000060000000600000006000000060000000600000006000000060000000600000006000000060000000600000006000000060000000600000006000000060000000600000006000000060000000600000006000000060000000600000006000000060000000600000006000000060000000600000006000000060000000600000005f0000005f0000005f0000005f0000005e0000005b0000005700000051000000490000003f00000034000000280000001d000000140000000c00000007000000030000000100000000000000000000000000000000000000000000000000000000000000000000000000000000000000000000000200000005000000080000000e000000140000001b000000230000002b0000003100000036000000390000003c0000003d0000003d0000003d0000003d0000003e0000003e0000003e0000003e0000003e0000003e0000003e0000003e0000003e0000003e0000003e0000003e0000003e0000003e0000003e0000003e0000003e0000003e0000003e0000003e0000003e0000003e0000003e0000003e0000003e0000003e0000003e0000003e0000003e0000003e0000003e0000003e0000003e0000003e0000003e0000003e0000003e0000003e0000003e0000003e0000003e0000003e0000003e0000003e0000003e0000003e0000003e0000003e0000003e0000003e0000003e0000003e0000003e0000003e0000003e0000003e0000003e0000003e0000003e0000003e0000003e0000003e0000003e0000003e0000003e0000003e0000003e0000003e0000003e0000003e0000003e0000003e0000003e0000003e0000003e0000003e0000003e0000003e0000003e0000003e0000003e0000003e0000003e0000003d0000003d0000003d0000003d0000003c0000003a00000037000000330000002d000000260000001f00000017000000100000000a000000060000000300000001000000000000000000000000000000000000000000000000000000000000000000000000000000000000000000000000000000000000000200000003000000060000000a0000000e00000013000000170000001b0000001e00000021000000220000002300000023000000230000002300000024000000240000002400000024000000240000002400000024000000240000002400000024000000240000002400000024000000240000002400000024000000240000002400000024000000240000002400000024000000240000002400000024000000240000002400000024000000240000002400000024000000240000002400000024000000240000002400000024000000240000002400000024000000240000002400000024000000240000002400000024000000240000002400000024000000240000002400000024000000240000002400000024000000240000002400000024000000240000002400000024000000240000002400000024000000240000002400000024000000240000002400000024000000240000002400000024000000240000002400000024000000240000002400000024000000240000002400000024000000240000002300000023000000230000002300000022000000210000001f0000001c0000001900000014000000100000000b0000000700000004000000020000000100000000000000000000000000000000000000000000000000000000000000000000000000000000000000000000000000000000000000000000000000000001000000020000000400000006000000080000000b0000000d0000000f00000010000000110000001100000011000000110000001100000012000000120000001200000012000000120000001200000012000000120000001200000012000000120000001200000012000000120000001200000012000000120000001200000012000000120000001200000012000000120000001200000012000000120000001200000012000000120000001200000012000000120000001200000012000000120000001200000012000000120000001200000012000000120000001200000012000000120000001200000012000000120000001200000012000000120000001200000012000000120000001200000012000000120000001200000012000000120000001200000012000000120000001200000012000000120000001200000012000000120000001200000012000000120000001200000012000000120000001200000012000000120000001200000012000000120000001200000012000000120000001100000011000000110000001100000011000000100000000f0000000d0000000c0000000900000007000000040000000300000001000000000000000000000000000000000000000000000000000000000000000000000000000000000000000000000000000000000000000000000000000000000000000000000000000000000000000100000001000000030000000400000005000000050000000600000007000000070000000700000007000000070000000700000008000000080000000800000008000000080000000800000008000000080000000800000008000000080000000800000008000000080000000800000008000000080000000800000008000000080000000800000008000000080000000800000008000000080000000800000008000000080000000800000008000000080000000800000008000000080000000800000008000000080000000800000008000000080000000800000008000000080000000800000008000000080000000800000008000000080000000800000008000000080000000800000008000000080000000800000008000000080000000800000008000000080000000800000008000000080000000800000008000000080000000800000008000000080000000800000008000000080000000800000008000000080000000800000008000000080000000800000008000000070000000700000007000000070000000700000007000000060000000500000004000000030000000200000001000000000000000000000000000000000000000000000000000000000000000000000000000000000000000000000000000000000000000000000000000000000000000000000000000000000000000000000000000000000000000000000000000000000000000100000001000000010000000100000001000000010000000100000001000000010000000200000002000000020000000200000002000000020000000200000002000000020000000200000002000000020000000200000002000000020000000200000002000000020000000200000002000000020000000200000002000000020000000200000002000000020000000200000002000000020000000200000002000000020000000200000002000000020000000200000002000000020000000200000002000000020000000200000002000000020000000200000002000000020000000200000002000000020000000200000002000000020000000200000002000000020000000200000002000000020000000200000002000000020000000200000002000000020000000200000002000000020000000200000002000000020000000200000002000000020000000200000002000000020000000200000002000000020000000200000001000000010000000100000001000000010000000100000001000000010000000100000000000000000000000000000000000000000000000000000000000000000000000000000000000000000000000000000000"
.end class
