.version 49 0
.class public final super Me
.super sg

.method public <init> : ()V
    .code stack 1 locals 1
L0:     aload_0
L1:     invokespecial Method sg <init> ()V
L4:     return
L5:     
    .end code
.end method

.method public method754 : (LRg;)V
    .code stack 5 locals 6
L0:     aload_1
L1:     bipush 10
L3:     iconst_1
L4:     dup
L5:     pop2
L6:     bipush 28
L8:     iconst_1
L9:     dup
L10:    pop2
L11:    multianewarray [[I 2
L15:    putfield Field Rg this [[I
L18:    new java/util/Random
L21:    dup
L22:    aload_1
L23:    getfield Field Rg field239 Lqd;
L26:    getfield Field qd field756 J
L29:    invokespecial Method java/util/Random <init> (J)V
L32:    astore_2
L33:    bipush 19
L35:    iconst_1
L36:    dup
L37:    pop2
L38:    dup
L39:    istore_3
L40:    bipush 28
L42:    iconst_1
L43:    dup
L44:    pop2
L45:    if_icmpge L122
L48:    iconst_0
L49:    iconst_1
L50:    dup
L51:    pop2
L52:    dup
L53:    istore 4
L55:    iconst_2
L56:    iconst_1
L57:    dup
L58:    pop2
L59:    if_icmpge L115
L62:    aload_2
L63:    bipush 10
L65:    iconst_1
L66:    dup
L67:    pop2
L68:    invokevirtual Method java/util/Random nextInt (I)I
L71:    istore 5
L73:    aload_1
L74:    getfield Field Rg this [[I
L77:    iload 5
L79:    aaload
L80:    iload_3
L81:    iaload
L82:    ifne L62
L85:    aload_1
L86:    getfield Field Rg this [[I
L89:    iload 5
L91:    aaload
L92:    iload_3
L93:    bipush 45
L95:    iconst_1
L96:    dup
L97:    pop2
L98:    iastore
L99:    goto L107
L102:   nop
L103:   nop
L104:   nop
L105:   nop
L106:   athrow
L107:   iinc 4 1
L110:   iload 4
L112:   goto L55
L115:   iinc 3 1
L118:   iload_3
L119:   goto L40
L122:   aload_1
L123:   getfield Field Rg this [[I
L126:   invokestatic Method hE method1143 ([[I)V
L129:   return
L130:   
        .attribute StackMap b'\x00\x07\x00\x28\x00\x04\x07\x00\x02\x07\x00\x13\x07\x00\x18\x01\x00\x01\x01\x00\x37\x00\x05\x07\x00\x02\x07\x00\x13\x07\x00\x18\x01\x01\x00\x01\x01\x00\x3E\x00\x05\x07\x00\x02\x07\x00\x13\x07\x00\x18\x01\x01\x00\x00\x00\x66\x00\x00\x00\x01\x07\x00\x2B\x00\x6B\x00\x06\x07\x00\x02\x07\x00\x13\x07\x00\x18\x01\x01\x01\x00\x00\x00\x73\x00\x05\x07\x00\x02\x07\x00\x13\x07\x00\x18\x01\x01\x00\x00\x00\x7A\x00\x04\x07\x00\x02\x07\x00\x13\x07\x00\x18\x01\x00\x00'
    .end code
.end method

.method public method750 : (LRg;)F
    .code stack 1 locals 2
L0:     ldc 6e-1f
L2:     freturn
L3:     
    .end code
.end method

.method public method761 : ()F
    .code stack 1 locals 1
L0:     fconst_0
L1:     freturn
L2:     
    .end code
.end method
.innerclasses
    Me [0] [0] static
.end innerclasses
.enclosing method SE winterbottom ([LTe;)LTe;
.end class
