.version 46 0
.class public final super MF
.super java/lang/Object
.field private final field1971 I
.field public static final field1972 I = 8
.field private final field1973 [B

.method public method881 : (Ljava/nio/ByteBuffer;)V
    .code stack 3 locals 2
L0:     aload_1
L1:     aload_0
L2:     getfield Field MF field1973 [B
L5:     invokevirtual Method java/nio/ByteBuffer put ([B)Ljava/nio/ByteBuffer;
L8:     aload_1
L9:     aload_0
L10:    getfield Field MF field1971 I
L13:    invokevirtual Method java/nio/ByteBuffer putInt (I)Ljava/nio/ByteBuffer;
L16:    pop2
L17:    return
L18:    
    .end code
.end method

.method public method882 : ()I
    .code stack 1 locals 1
L0:     aload_0
L1:     getfield Field MF field1971 I
L4:     ireturn
L5:     
    .end code
.end method

.method public method883 : ()[B
    .code stack 1 locals 1
L0:     aload_0
L1:     getfield Field MF field1973 [B
L4:     areturn
L5:     
    .end code
.end method

.method public <init> : ([BI)V
    .code stack 5 locals 3
L0:     iload_2
L1:     aload_0
L2:     dup_x1
L3:     aload_1
L4:     aload_0
L5:     invokespecial Method java/lang/Object <init> ()V
L8:     putfield Field MF field1973 [B
L11:    putfield Field MF field1971 I
L14:    return
L15:    
    .end code
.end method

.method public method884 : (Ljava/io/RandomAccessFile;Ljouvieje/bass/utils/D;)V
    .code stack 6 locals 3
L0:     aload_1
L1:     aload_0
L2:     aload_2
L3:     dup_x2
L4:     aload_1
L5:     aload_0
L6:     getfield Field MF field1973 [B
L9:     invokevirtual Method jouvieje/bass/utils/D method1656 (Ljava/io/RandomAccessFile;[B)V
L12:    getfield Field MF field1971 I
L15:    invokevirtual Method jouvieje/bass/utils/D method1665 (Ljava/io/RandomAccessFile;I)V
L18:    return
L19:    
    .end code
    .exceptions java/io/IOException
.end method
.end class
