.version 49 0
.class public final super mf
.super java/lang/Object
.implements K
.field public final synthetic field1753 LZF;

.method public method736 : (LRg;LKD;)V
    .code stack 0 locals 3
L0:     return
L1:     
    .end code
.end method

.method public method737 : (LRg;)V
    .code stack 5 locals 2
L0:     aload_1
L1:     aload_0
L2:     dup_x1
L3:     aload_1
L4:     getstatic Field qE field628 LqE;
L7:     invokevirtual Method Rg method226 (LqE;)V
L10:    getfield Field mf field1753 LZF;
L13:    invokevirtual Method Rg method235 (LF;)V
L16:    getfield Field mf field1753 LZF;
L19:    invokestatic Method ZF method110 (LZF;)V
L22:    return
L23:    
    .end code
.end method

.method public bridge synthetic method734 : (Ljava/lang/Object;)V
    .code stack 2 locals 2
L0:     aload_0
L1:     aload_1
L2:     checkcast Rg
L5:     invokevirtual Method mf method737 (LRg;)V
L8:     return
L9:     
    .end code
.end method

.method public <init> : (LZF;)V
    .code stack 3 locals 2
L0:     aload_0
L1:     dup
L2:     aload_1
L3:     putfield Field mf field1753 LZF;
L6:     invokespecial Method java/lang/Object <init> ()V
L9:     return
L10:    
    .end code
.end method

.method public bridge synthetic method735 : (Ljava/lang/Object;LKD;)V
    .code stack 3 locals 3
L0:     aload_0
L1:     aload_1
L2:     checkcast Rg
L5:     aload_2
L6:     invokevirtual Method mf method736 (LRg;LKD;)V
L9:     return
L10:    
    .end code
.end method
.innerclasses
    mf [0] [0]
    KD K [0] public static final enum
.end innerclasses
.enclosing method ZF method49 ()V
.end class
