.version 49 0
.class public final super Nb
.super java/lang/Object
.implements java/util/Comparator
.field public final synthetic field1344 LCC;

.method public method692 : (LUf;LUf;)I
    .code stack 3 locals 5
L0:     aload_0
L1:     dup
L2:     getfield Field Nb field1344 LCC;
L5:     invokestatic Method CC try (LCC;)Led;
L8:     getfield Field ed field704 Ljava/util/Set;
L11:    aload_1
L12:    invokeinterface InterfaceMethod java/util/Set contains (Ljava/lang/Object;)Z 2
L17:    istore_3
L18:    getfield Field Nb field1344 LCC;
L21:    invokestatic Method CC try (LCC;)Led;
L24:    getfield Field ed field704 Ljava/util/Set;
L27:    aload_2
L28:    invokeinterface InterfaceMethod java/util/Set contains (Ljava/lang/Object;)Z 2
L33:    istore 4
L35:    iload_3
L36:    iload 4
L38:    if_icmpeq L57
L41:    iload_3
L42:    ifeq L51
L45:    iconst_m1
L46:    iconst_1
L47:    dup
L48:    pop2
L49:    ireturn
L50:    athrow
L51:    iconst_1
L52:    dup
L53:    dup
L54:    pop2
L55:    ireturn
L56:    athrow
L57:    iload_3
L58:    ifeq L87
L61:    iload 4
L63:    ifeq L87
L66:    aload_1
L67:    getfield Field Uf field1349 I
L70:    aload_2
L71:    getfield Field Uf field1349 I
L74:    if_icmpeq L87
L77:    aload_2
L78:    getfield Field Uf field1349 I
L81:    aload_1
L82:    getfield Field Uf field1349 I
L85:    isub
L86:    ireturn
L87:    aload_1
L88:    getfield Field Uf field1351 Ljava/lang/String;
L91:    aload_2
L92:    getfield Field Uf field1351 Ljava/lang/String;
L95:    invokevirtual Method java/lang/String compareTo (Ljava/lang/String;)I
L98:    ireturn
L99:    
        .attribute StackMap b'\x00\x05\x00\x32\x00\x00\x00\x01\x07\x00\x23\x00\x33\x00\x05\x07\x00\x02\x07\x00\x25\x07\x00\x25\x01\x01\x00\x00\x00\x38\x00\x00\x00\x01\x07\x00\x23\x00\x39\x00\x05\x07\x00\x02\x07\x00\x25\x07\x00\x25\x01\x01\x00\x00\x00\x57\x00\x05\x07\x00\x02\x07\x00\x25\x07\x00\x25\x01\x01\x00\x00'
    .end code
.end method

.method public <init> : (LCC;)V
    .code stack 3 locals 2
L0:     aload_0
L1:     dup
L2:     aload_1
L3:     putfield Field Nb field1344 LCC;
L6:     invokespecial Method java/lang/Object <init> ()V
L9:     return
L10:    
    .end code
.end method

.method public bridge synthetic compare : (Ljava/lang/Object;Ljava/lang/Object;)I
    .code stack 3 locals 3
L0:     aload_0
L1:     aload_1
L2:     checkcast Uf
L5:     aload_2
L6:     checkcast Uf
L9:     invokevirtual Method Nb method692 (LUf;LUf;)I
L12:    ireturn
L13:    
    .end code
.end method
.innerclasses
    Nb [0] [0]
.end innerclasses
.enclosing method CC method177 ()Lqc;
.end class
