.version 49 0
.class public final super synthetic nD
.super java/lang/Object
.field public static final synthetic field2391 [I
.field public static final synthetic field2392 [I

.method public static <clinit> : ()V
    .code stack 5 locals 1
L0:     invokestatic Method QB values ()[LQB;
L3:     arraylength
L4:     newarray int
L6:     iconst_1
L7:     dup
L8:     pop2
L9:     putstatic Field nD field2391 [I
        .catch java/lang/NoSuchFieldError from L12 to L26 using L30
L12:    getstatic Field nD field2391 [I
L15:    getstatic Field QB field368 LQB;
L18:    invokevirtual Method QB ordinal ()I
L21:    iconst_1
L22:    dup
L23:    dup
L24:    pop2
L25:    iastore
L26:    goto L31
L29:    athrow
L30:    astore_0
        .catch java/lang/NoSuchFieldError from L31 to L45 using L49
L31:    getstatic Field nD field2391 [I
L34:    getstatic Field QB field366 LQB;
L37:    invokevirtual Method QB ordinal ()I
L40:    iconst_2
L41:    iconst_1
L42:    dup
L43:    pop2
L44:    iastore
L45:    goto L50
L48:    athrow
L49:    astore_0
        .catch java/lang/NoSuchFieldError from L50 to L64 using L67
L50:    getstatic Field nD field2391 [I
L53:    getstatic Field QB field367 LQB;
L56:    invokevirtual Method QB ordinal ()I
L59:    iconst_3
L60:    iconst_1
L61:    dup
L62:    pop2
L63:    iastore
L64:    goto L68
L67:    astore_0
        .catch java/lang/NoSuchFieldError from L68 to L82 using L85
L68:    getstatic Field nD field2391 [I
L71:    getstatic Field QB field369 LQB;
L74:    invokevirtual Method QB ordinal ()I
L77:    iconst_4
L78:    iconst_1
L79:    dup
L80:    pop2
L81:    iastore
L82:    goto L86
L85:    astore_0
L86:    invokestatic Method oc values ()[Loc;
L89:    arraylength
L90:    newarray int
L92:    iconst_1
L93:    dup
L94:    pop2
L95:    putstatic Field nD field2392 [I
        .catch java/lang/NoSuchFieldError from L98 to L112 using L115
L98:    getstatic Field nD field2392 [I
L101:   getstatic Field oc field381 Loc;
L104:   invokevirtual Method oc ordinal ()I
L107:   iconst_1
L108:   dup
L109:   dup
L110:   pop2
L111:   iastore
L112:   goto L116
L115:   astore_0
        .catch java/lang/NoSuchFieldError from L116 to L130 using L133
L116:   getstatic Field nD field2392 [I
L119:   getstatic Field oc field377 Loc;
L122:   invokevirtual Method oc ordinal ()I
L125:   iconst_2
L126:   iconst_1
L127:   dup
L128:   pop2
L129:   iastore
L130:   goto L134
L133:   astore_0
        .catch java/lang/NoSuchFieldError from L134 to L148 using L151
L134:   getstatic Field nD field2392 [I
L137:   getstatic Field oc field378 Loc;
L140:   invokevirtual Method oc ordinal ()I
L143:   iconst_3
L144:   iconst_1
L145:   dup
L146:   pop2
L147:   iastore
L148:   goto L152
L151:   astore_0
        .catch java/lang/NoSuchFieldError from L152 to L166 using L169
L152:   getstatic Field nD field2392 [I
L155:   getstatic Field oc try Loc;
L158:   invokevirtual Method oc ordinal ()I
L161:   iconst_4
L162:   iconst_1
L163:   dup
L164:   pop2
L165:   iastore
L166:   goto L170
L169:   astore_0
        .catch java/lang/NoSuchFieldError from L170 to L184 using L187
L170:   getstatic Field nD field2392 [I
L173:   getstatic Field oc this Loc;
L176:   invokevirtual Method oc ordinal ()I
L179:   iconst_5
L180:   iconst_1
L181:   dup
L182:   pop2
L183:   iastore
L184:   goto L188
L187:   astore_0
        .catch java/lang/NoSuchFieldError from L188 to L203 using L206
L188:   getstatic Field nD field2392 [I
L191:   getstatic Field oc field375 Loc;
L194:   invokevirtual Method oc ordinal ()I
L197:   bipush 6
L199:   iconst_1
L200:   dup
L201:   pop2
L202:   iastore
L203:   goto L207
L206:   astore_0
        .catch java/lang/NoSuchFieldError from L207 to L222 using L225
L207:   getstatic Field nD field2392 [I
L210:   getstatic Field oc field379 Loc;
L213:   invokevirtual Method oc ordinal ()I
L216:   bipush 7
L218:   iconst_1
L219:   dup
L220:   pop2
L221:   iastore
L222:   goto L226
L225:   astore_0
        .catch java/lang/NoSuchFieldError from L226 to L241 using L244
L226:   getstatic Field nD field2392 [I
L229:   getstatic Field oc field376 Loc;
L232:   invokevirtual Method oc ordinal ()I
L235:   bipush 8
L237:   iconst_1
L238:   dup
L239:   pop2
L240:   iastore
L241:   goto L245
L244:   astore_0
        .catch java/lang/NoSuchFieldError from L245 to L260 using L263
L245:   getstatic Field nD field2392 [I
L248:   getstatic Field oc new Loc;
L251:   invokevirtual Method oc ordinal ()I
L254:   bipush 9
L256:   iconst_1
L257:   dup
L258:   pop2
L259:   iastore
L260:   goto L264
L263:   astore_0
        .catch java/lang/NoSuchFieldError from L264 to L279 using L280
L264:   getstatic Field nD field2392 [I
L267:   getstatic Field oc field380 Loc;
L270:   invokevirtual Method oc ordinal ()I
L273:   bipush 10
L275:   iconst_1
L276:   dup
L277:   pop2
L278:   iastore
L279:   return
L280:   astore_0
L281:   return
L282:   
        .attribute StackMap b'\x00\x1D\x00\x1D\x00\x00\x00\x01\x07\x00\x25\x00\x1E\x00\x00\x00\x01\x07\x00\x15\x00\x1F\x00\x00\x00\x00\x00\x30\x00\x00\x00\x01\x07\x00\x25\x00\x31\x00\x00\x00\x01\x07\x00\x15\x00\x32\x00\x00\x00\x00\x00\x43\x00\x00\x00\x01\x07\x00\x15\x00\x44\x00\x00\x00\x00\x00\x55\x00\x00\x00\x01\x07\x00\x15\x00\x56\x00\x00\x00\x00\x00\x73\x00\x00\x00\x01\x07\x00\x15\x00\x74\x00\x00\x00\x00\x00\x85\x00\x00\x00\x01\x07\x00\x15\x00\x86\x00\x00\x00\x00\x00\x97\x00\x00\x00\x01\x07\x00\x15\x00\x98\x00\x00\x00\x00\x00\xA9\x00\x00\x00\x01\x07\x00\x15\x00\xAA\x00\x00\x00\x00\x00\xBB\x00\x00\x00\x01\x07\x00\x15\x00\xBC\x00\x00\x00\x00\x00\xCE\x00\x00\x00\x01\x07\x00\x15\x00\xCF\x00\x00\x00\x00\x00\xE1\x00\x00\x00\x01\x07\x00\x15\x00\xE2\x00\x00\x00\x00\x00\xF4\x00\x00\x00\x01\x07\x00\x15\x00\xF5\x00\x00\x00\x00\x01\x07\x00\x00\x00\x01\x07\x00\x15\x01\x08\x00\x00\x00\x00\x01\x18\x00\x00\x00\x01\x07\x00\x15'
    .end code
.end method
.innerclasses
    QB qd [0] public static final enum
    nD jb [0] static synthetic
    oc fc [0] public static final enum
.end innerclasses
.enclosing method jb [0]
.end class
