.version 49 0
.class public final super NE
.super java/lang/Object
.implements M
.field public new LAC;
.field public field809 [LwF;
.field public this Ljava/io/ByteArrayOutputStream;
.field public field810 I
.field public field811 Lqd;
.field public field812 Z
.field public field813 [B

.method public method440 : (Led;)I
    .code stack 3 locals 3
L0:     iconst_0
L1:     iconst_1
L2:     dup
L3:     pop2
L4:     dup
L5:     istore_2
L6:     aload_0
L7:     getfield Field NE field809 [LwF;
L10:    arraylength
L11:    if_icmpge L41
L14:    aload_0
L15:    getfield Field NE field809 [LwF;
L18:    iload_2
L19:    aaload
L20:    getfield Field wF new LRg;
L23:    getfield Field Rg false Led;
L26:    aload_1
L27:    if_acmpne L33
L30:    iload_2
L31:    ireturn
L32:    athrow
L33:    iinc 2 1
L36:    iload_2
L37:    goto L6
L40:    athrow
L41:    iconst_m1
L42:    iconst_1
L43:    dup
L44:    pop2
L45:    ireturn
L46:    
        .attribute StackMap b'\x00\x05\x00\x06\x00\x03\x07\x00\x02\x07\x00\x20\x01\x00\x01\x01\x00\x20\x00\x00\x00\x01\x07\x00\x2F\x00\x21\x00\x03\x07\x00\x02\x07\x00\x20\x01\x00\x00\x00\x28\x00\x00\x00\x01\x07\x00\x2F\x00\x29\x00\x03\x07\x00\x02\x07\x00\x20\x01\x00\x00'
    .end code
.end method

.method public <init> : (Lqd;)V
    .code stack 7 locals 5
L0:     aload_1
L1:     aload_0
L2:     dup_x1
L3:     dup_x2
L4:     invokespecial Method java/lang/Object <init> ()V
L7:     putfield Field NE field811 Lqd;
L10:    getfield Field NE field811 Lqd;
L13:    getfield Field qd field763 LQB;
L16:    getstatic Field QB field369 LQB;
L19:    if_acmpeq L30
L22:    new java/lang/RuntimeException
L25:    dup
L26:    invokespecial Method java/lang/RuntimeException <init> ()V
L29:    athrow
        .catch java/io/IOException from L30 to L123 using L279
L30:    aload_0
L31:    dup
L32:    dup2
L33:    new java/io/ByteArrayOutputStream
L36:    dup
L37:    invokespecial Method java/io/ByteArrayOutputStream <init> ()V
L40:    putfield Field NE this Ljava/io/ByteArrayOutputStream;
L43:    new AC
L46:    aload_0
L47:    dup_x2
L48:    dup
L49:    pop2
L50:    dup
L51:    aload_0
L52:    getfield Field NE this Ljava/io/ByteArrayOutputStream;
L55:    invokespecial Method AC <init> (Ljava/io/OutputStream;)V
L58:    putfield Field NE new LAC;
L61:    getfield Field NE new LAC;
L64:    aload_0
L65:    getfield Field NE field811 Lqd;
L68:    getfield Field qd field742 Z
L71:    invokevirtual Method AC method684 (Z)V
L74:    getfield Field NE field811 Lqd;
L77:    getfield Field qd field761 Leb;
L80:    invokevirtual Method eb method751 ()[LEF;
L83:    astore_1
L84:    getfield Field NE new LAC;
L87:    aload_1
L88:    arraylength
L89:    invokevirtual Method AC method691 (I)V
L92:    iconst_0
L93:    iconst_1
L94:    dup
L95:    pop2
L96:    dup
L97:    istore_2
L98:    aload_1
L99:    arraylength
L100:   if_icmpge L124
L103:   aload_0
L104:   getfield Field NE new LAC;
L107:   aload_1
L108:   iload_2
L109:   iinc 2 1
L112:   aaload
L113:   invokevirtual Method EF ordinal ()I
L116:   invokevirtual Method AC method691 (I)V
L119:   iload_2
L120:   goto L98
L123:   athrow
        .catch java/io/IOException from L124 to L275 using L279
L124:   aload_0
L125:   dup
L126:   getfield Field NE field811 Lqd;
L129:   getfield Field qd field766 Ljava/util/Map;
L132:   invokeinterface InterfaceMethod java/util/Map size ()I 1
L137:   anewarray wF
L140:   iconst_1
L141:   dup
L142:   pop2
L143:   putfield Field NE field809 [LwF;
L146:   aload_0
L147:   dup
L148:   getfield Field NE new LAC;
L151:   swap
L152:   getfield Field NE field809 [LwF;
L155:   arraylength
L156:   invokevirtual Method AC method691 (I)V
L159:   iconst_0
L160:   iconst_1
L161:   dup
L162:   pop2
L163:   istore_2
L164:   aload_0
L165:   getfield Field NE field811 Lqd;
L168:   getfield Field qd field766 Ljava/util/Map;
L171:   invokeinterface InterfaceMethod java/util/Map keySet ()Ljava/util/Set; 1
L176:   invokeinterface InterfaceMethod java/util/Set iterator ()Ljava/util/Iterator; 1
L181:   astore_3
L182:   aload_3
L183:   invokeinterface InterfaceMethod java/util/Iterator hasNext ()Z 1
L188:   ifeq L289
L191:   aload_3
L192:   invokeinterface InterfaceMethod java/util/Iterator next ()Ljava/lang/Object; 1
L197:   checkcast Rg
L200:   astore 4
L202:   aload_0
L203:   dup
L204:   dup2
L205:   getfield Field NE new LAC;
L208:   aload 4
L210:   getfield Field Rg false Led;
L213:   getfield Field ed field701 Ljava/lang/String;
L216:   invokevirtual Method AC method683 (Ljava/lang/String;)V
L219:   getfield Field NE new LAC;
L222:   aload 4
L224:   getfield Field Rg false Led;
L227:   getfield Field ed field712 I
L230:   invokevirtual Method AC method674 (I)V
L233:   getfield Field NE new LAC;
L236:   aload 4
L238:   getfield Field Rg false Led;
L241:   getfield Field ed new Ljava/lang/String;
L244:   invokevirtual Method AC method683 (Ljava/lang/String;)V
L247:   getfield Field NE field809 [LwF;
L250:   new wF
L253:   iload_2
L254:   dup_x1
L255:   dup
L256:   pop2
L257:   dup
L258:   aload 4
L260:   aload_0
L261:   dup_x1
L262:   getfield Field NE new LAC;
L265:   invokespecial Method wF <init> (LNE;LRg;LAC;)V
L268:   iinc 2 1
L271:   aastore
L272:   goto L182
L275:   nop
L276:   nop
L277:   nop
L278:   athrow
L279:   astore_1
L280:   new java/lang/RuntimeException
L283:   dup
L284:   aload_1
L285:   invokespecial Method java/lang/RuntimeException <init> (Ljava/lang/Throwable;)V
L288:   athrow
L289:   aload_0
L290:   invokestatic Method ib method1156 (LM;)V
L293:   return
L294:   
        .attribute StackMap b'\x00\x08\x00\x1E\x00\x02\x07\x00\x02\x07\x00\x0E\x00\x00\x00\x62\x00\x03\x07\x00\x02\x07\x00\x63\x01\x00\x01\x01\x00\x7B\x00\x00\x00\x01\x07\x00\x2F\x00\x7C\x00\x03\x07\x00\x02\x07\x00\x63\x01\x00\x00\x00\xB6\x00\x04\x07\x00\x02\x07\x00\x63\x01\x07\x00\x7C\x00\x00\x01\x13\x00\x00\x00\x01\x07\x00\x2F\x01\x17\x00\x02\x07\x00\x02\x07\x00\x04\x00\x01\x07\x00\x33\x01\x21\x00\x04\x07\x00\x02\x07\x00\x63\x01\x07\x00\x7C\x00\x00'
    .end code
    .exceptions java/io/IOException
.end method

.method public fpsfoundhere : (F)Z
    .code stack 3 locals 2
L0:     iconst_0
L1:     iconst_1
L2:     dup
L3:     pop2
L4:     ireturn
L5:     
    .end code
    .exceptions java/lang/Exception
.end method

.method public method227 : ()Z
    .code stack 14 locals 4
L0:     aload_0
L1:     getfield Field NE field812 Z
L4:     ifeq L13
L7:     iconst_0
L8:     iconst_1
L9:     dup
L10:    pop2
L11:    ireturn
L12:    athrow
L13:    aload_0
L14:    getfield Field NE field809 [LwF;
L17:    dup
L18:    astore_1
L19:    arraylength
L20:    istore_2
L21:    iconst_0
L22:    iconst_1
L23:    dup
L24:    pop2
L25:    dup
L26:    istore_3
L27:    iload_2
L28:    if_icmpge L45
L31:    aload_1
L32:    iload_3
L33:    iinc 3 1
L36:    aaload
L37:    invokevirtual Method wF method113 ()V
L40:    iload_3
L41:    goto L27
L44:    athrow
L45:    aload_0
L46:    dup
L47:    dup
L48:    getfield Field NE field810 I
L51:    iconst_1
L52:    dup
L53:    dup
L54:    pop2
L55:    iadd
L56:    putfield Field NE field810 I
L59:    getfield Field NE field811 Lqd;
L62:    getfield Field qd field763 LQB;
L65:    getstatic Field QB field369 LQB;
L68:    if_acmpeq L226
L71:    aload_0
L72:    dup
L73:    dup2
L74:    getfield Field NE new LAC;
L77:    invokevirtual Method AC method689 ()V
L80:    new java/io/ByteArrayOutputStream
L83:    dup
L84:    invokespecial Method java/io/ByteArrayOutputStream <init> ()V
L87:    astore_1
L88:    new AC
L91:    dup
L92:    new java/util/zip/DeflaterOutputStream
L95:    dup
L96:    new java/util/zip/Deflater
L99:    aload_1
L100:   dup_x1
L101:   dup
L102:   pop2
L103:   dup
L104:   bipush 9
L106:   iconst_1
L107:   dup
L108:   pop2
L109:   iconst_1
L110:   dup
L111:   dup
L112:   pop2
L113:   invokespecial Method java/util/zip/Deflater <init> (IZ)V
L116:   invokespecial Method java/util/zip/DeflaterOutputStream <init> (Ljava/io/OutputStream;Ljava/util/zip/Deflater;)V
L119:   invokespecial Method AC <init> (Ljava/io/OutputStream;)V
L122:   astore_2
L123:   aload_0
L124:   aload_2
L125:   dup_x1
L126:   dup_x1
L127:   aload_0
L128:   aload_2
L129:   dup
L130:   iconst_1
L131:   dup
L132:   dup
L133:   pop2
L134:   invokevirtual Method AC method691 (I)V
L137:   getstatic Field ib field2312 F
L140:   invokevirtual Method AC method685 (F)V
L143:   getfield Field NE field810 I
L146:   invokevirtual Method AC method674 (I)V
L149:   getfield Field NE this Ljava/io/ByteArrayOutputStream;
L152:   invokevirtual Method java/io/ByteArrayOutputStream toByteArray ()[B
L155:   invokevirtual Method AC method677 ([B)V
L158:   invokevirtual Method AC method689 ()V
L161:   getstatic Field java/lang/System out Ljava/io/PrintStream;
L164:   new java/lang/StringBuilder
L167:   dup
L168:   invokespecial Method java/lang/StringBuilder <init> ()V
L171:   aload_1
L172:   dup_x2
L173:   invokevirtual Method java/io/ByteArrayOutputStream size ()I
L176:   invokevirtual Method java/lang/StringBuilder append (I)Ljava/lang/StringBuilder;
L179:   ldc " bytes, "
L181:   invokevirtual Method java/lang/StringBuilder append (Ljava/lang/String;)Ljava/lang/StringBuilder;
L184:   aload_0
L185:   getfield Field NE this Ljava/io/ByteArrayOutputStream;
L188:   invokevirtual Method java/io/ByteArrayOutputStream size ()I
L191:   invokevirtual Method java/lang/StringBuilder append (I)Ljava/lang/StringBuilder;
L194:   ldc " bytes uncompressed"
L196:   invokevirtual Method java/lang/StringBuilder append (Ljava/lang/String;)Ljava/lang/StringBuilder;
L199:   invokevirtual Method java/lang/StringBuilder toString ()Ljava/lang/String;
L202:   invokevirtual Method java/io/PrintStream println (Ljava/lang/String;)V
L205:   invokevirtual Method java/io/ByteArrayOutputStream toByteArray ()[B
L208:   putfield Field NE field813 [B
L211:   iconst_1
L212:   dup
L213:   dup
L214:   pop2
L215:   putfield Field NE field812 Z
L218:   invokestatic Method ib method1153 (LM;)V
L221:   iconst_0
L222:   iconst_1
L223:   dup
L224:   pop2
L225:   ireturn
L226:   iconst_0
L227:   iconst_1
L228:   dup
L229:   pop2
L230:   ireturn
L231:   
        .attribute StackMap b'\x00\x06\x00\x0C\x00\x00\x00\x01\x07\x00\x2F\x00\x0D\x00\x01\x07\x00\x02\x00\x00\x00\x1B\x00\x04\x07\x00\x02\x07\x00\xA8\x01\x01\x00\x01\x01\x00\x2C\x00\x00\x00\x01\x07\x00\x2F\x00\x2D\x00\x04\x07\x00\x02\x07\x00\xA8\x01\x01\x00\x00\x00\xE2\x00\x04\x07\x00\x02\x07\x00\xA8\x01\x01\x00\x00'
    .end code
    .exceptions java/lang/Exception
.end method

.method public method441 : ()[B
    .code stack 2 locals 1
L0:     aload_0
L1:     getfield Field NE field812 Z
L4:     ifne L15
L7:     new java/lang/RuntimeException
L10:    dup
L11:    invokespecial Method java/lang/RuntimeException <init> ()V
L14:    athrow
L15:    aload_0
L16:    getfield Field NE field813 [B
L19:    areturn
L20:    
        .attribute StackMap b'\x00\x01\x00\x0F\x00\x01\x07\x00\x02\x00\x00'
    .end code
.end method
.innerclasses
    EF eb [0] public static final enum
    QB qd [0] public static final enum
.end innerclasses
.end class
