.version 49 0
.class public final super Nf
.super java/lang/Object
.implements D
.field public field907 F
.field public field908 LRC;
.field public field909 LTe;
.field public field910 Ljava/lang/String;
.field public field911 F
.field public field912 Ljava/lang/String;
.field public try I
.field public field913 I
.field public new Ljava/lang/String;
.field public field914 F
.field public this I
.field public field915 Ljava/lang/String;
.field public field916 J
.field public field917 I
.field public field918 I

.method public <init> : (IFIIIIFFLjava/lang/String;Ljava/lang/String;Ljava/lang/String;Ljava/lang/String;LRC;LTe;J)V
    .code stack 32 locals 17
L0:     lload 15
L2:     aload_0
L3:     dup_x2
L4:     aload 14
L6:     aload 13
L8:     aload_0
L9:     dup_x1
L10:    aload 12
L12:    aload 11
L14:    aload_0
L15:    dup_x1
L16:    aload 10
L18:    aload 9
L20:    aload_0
L21:    dup_x1
L22:    fload 8
L24:    fload 7
L26:    aload_0
L27:    dup_x1
L28:    iload 6
L30:    iload 5
L32:    aload_0
L33:    dup_x1
L34:    iload 4
L36:    iload_3
L37:    aload_0
L38:    dup_x1
L39:    fload_2
L40:    iload_1
L41:    aload_0
L42:    dup_x1
L43:    invokespecial Method java/lang/Object <init> ()V
L46:    putfield Field Nf this I
L49:    putfield Field Nf field907 F
L52:    putfield Field Nf field918 I
L55:    putfield Field Nf field917 I
L58:    putfield Field Nf field913 I
L61:    putfield Field Nf try I
L64:    putfield Field Nf field911 F
L67:    putfield Field Nf field914 F
L70:    putfield Field Nf field915 Ljava/lang/String;
L73:    putfield Field Nf new Ljava/lang/String;
L76:    putfield Field Nf field912 Ljava/lang/String;
L79:    putfield Field Nf field910 Ljava/lang/String;
L82:    putfield Field Nf field908 LRC;
L85:    putfield Field Nf field909 LTe;
L88:    putfield Field Nf field916 J
L91:    return
L92:    
    .end code
.end method

.method public <init> : (LMd;)V
    .code stack 22 locals 6
L0:     aload_0
L1:     aload_1
L2:     dup_x1
L3:     aload_1
L4:     aload_0
L5:     dup_x1
L6:     aload_0
L7:     aload_1
L8:     dup_x1
L9:     aload_1
L10:    aload_0
L11:    dup_x1
L12:    aload_0
L13:    aload_1
L14:    dup_x1
L15:    aload_1
L16:    aload_0
L17:    dup_x1
L18:    aload_0
L19:    aload_1
L20:    dup_x1
L21:    aload_0
L22:    invokespecial Method java/lang/Object <init> ()V
L25:    invokevirtual Method Md method886 ()I
L28:    putfield Field Nf this I
L31:    invokevirtual Method Md method885 ()F
L34:    putfield Field Nf field907 F
L37:    invokevirtual Method Md method889 ()I
L40:    putfield Field Nf field918 I
L43:    invokevirtual Method Md method886 ()I
L46:    putfield Field Nf field917 I
L49:    invokevirtual Method Md method886 ()I
L52:    putfield Field Nf field913 I
L55:    invokevirtual Method Md method886 ()I
L58:    putfield Field Nf try I
L61:    invokevirtual Method Md method885 ()F
L64:    putfield Field Nf field911 F
L67:    invokevirtual Method Md method885 ()F
L70:    putfield Field Nf field914 F
L73:    invokevirtual Method Md new ()Ljava/lang/String;
L76:    putfield Field Nf field915 Ljava/lang/String;
L79:    invokevirtual Method Md new ()Ljava/lang/String;
L82:    putfield Field Nf new Ljava/lang/String;
L85:    invokevirtual Method Md method892 ()Z
L88:    ifeq L99
L91:    aload_0
L92:    aload_1
L93:    invokevirtual Method Md new ()Ljava/lang/String;
L96:    putfield Field Nf field912 Ljava/lang/String;
L99:    aload_0
L100:   aload_1
L101:   invokevirtual Method Md new ()Ljava/lang/String;
L104:   putfield Field Nf field910 Ljava/lang/String;
L107:   aload_1
L108:   invokevirtual Method Md method892 ()Z
L111:   istore_2
L112:   iconst_0
L113:   iconst_1
L114:   dup
L115:   pop2
L116:   istore_3
L117:   iload_2
L118:   ifeq L126
L121:   aload_1
L122:   invokevirtual Method Md method886 ()I
L125:   istore_3
L126:   aload_1
L127:   invokevirtual Method Md method892 ()Z
L130:   istore 4
L132:   ldc ""
L134:   astore 5
L136:   iload 4
L138:   ifeq L147
L141:   aload_1
L142:   invokevirtual Method Md new ()Ljava/lang/String;
L145:   astore 5
L147:   aload_0
L148:   aload_1
L149:   invokevirtual Method Md method897 ()J
L152:   putfield Field Nf field916 J
L155:   iload_2
L156:   ifeq L179
L159:   aload_0
L160:   getstatic Field Kc field1931 LKc;
L163:   invokevirtual Method Kc method850 ()Ljava/util/LinkedHashMap;
L166:   iload_3
L167:   invokestatic Method java/lang/Integer valueOf (I)Ljava/lang/Integer;
L170:   invokevirtual Method java/util/LinkedHashMap get (Ljava/lang/Object;)Ljava/lang/Object;
L173:   checkcast RC
L176:   putfield Field Nf field908 LRC;
L179:   iload 4
L181:   ifeq L201
L184:   aload_0
L185:   getstatic Field SE field2069 Ljava/util/Map;
L188:   aload 5
L190:   invokeinterface InterfaceMethod java/util/Map get (Ljava/lang/Object;)Ljava/lang/Object; 2
L195:   checkcast Te
L198:   putfield Field Nf field909 LTe;
L201:   return
L202:   
        .attribute StackMap b'\x00\x05\x00\x63\x00\x02\x07\x00\x02\x07\x00\x43\x00\x00\x00\x7E\x00\x04\x07\x00\x02\x07\x00\x43\x01\x01\x00\x00\x00\x93\x00\x06\x07\x00\x02\x07\x00\x43\x01\x01\x01\x07\x00\x59\x00\x00\x00\xB3\x00\x06\x07\x00\x02\x07\x00\x43\x01\x01\x01\x07\x00\x59\x00\x00\x00\xC9\x00\x06\x07\x00\x02\x07\x00\x43\x01\x01\x01\x07\x00\x59\x00\x00'
    .end code
    .exceptions java/io/IOException
.end method

.method public method384 : (LAC;)V
    .code stack 22 locals 2
L0:     aload_0
L1:     aload_1
L2:     dup_x1
L3:     aload_1
L4:     aload_0
L5:     dup_x1
L6:     aload_0
L7:     aload_1
L8:     dup_x1
L9:     aload_1
L10:    aload_0
L11:    dup_x1
L12:    aload_0
L13:    aload_1
L14:    dup_x1
L15:    aload_1
L16:    aload_0
L17:    dup_x1
L18:    aload_0
L19:    aload_1
L20:    dup_x1
L21:    aload_0
L22:    getfield Field Nf this I
L25:    invokevirtual Method AC method691 (I)V
L28:    getfield Field Nf field907 F
L31:    invokevirtual Method AC method685 (F)V
L34:    getfield Field Nf field918 I
L37:    invokevirtual Method AC method674 (I)V
L40:    getfield Field Nf field917 I
L43:    invokevirtual Method AC method691 (I)V
L46:    getfield Field Nf field913 I
L49:    invokevirtual Method AC method691 (I)V
L52:    getfield Field Nf try I
L55:    invokevirtual Method AC method691 (I)V
L58:    getfield Field Nf field911 F
L61:    invokevirtual Method AC method685 (F)V
L64:    getfield Field Nf field914 F
L67:    invokevirtual Method AC method685 (F)V
L70:    getfield Field Nf field915 Ljava/lang/String;
L73:    invokevirtual Method AC method683 (Ljava/lang/String;)V
L76:    getfield Field Nf new Ljava/lang/String;
L79:    invokevirtual Method AC method683 (Ljava/lang/String;)V
L82:    getfield Field Nf field912 Ljava/lang/String;
L85:    ifnull L96
L88:    iconst_1
L89:    dup
L90:    dup
L91:    pop2
L92:    goto L100
L95:    athrow
L96:    iconst_0
L97:    iconst_1
L98:    dup
L99:    pop2
L100:   invokevirtual Method AC method684 (Z)V
L103:   aload_0
L104:   getfield Field Nf field912 Ljava/lang/String;
L107:   ifnull L118
L110:   aload_1
L111:   aload_0
L112:   getfield Field Nf field912 Ljava/lang/String;
L115:   invokevirtual Method AC method683 (Ljava/lang/String;)V
L118:   aload_1
L119:   dup
L120:   aload_0
L121:   dup_x1
L122:   getfield Field Nf field910 Ljava/lang/String;
L125:   invokevirtual Method AC method683 (Ljava/lang/String;)V
L128:   getfield Field Nf field908 LRC;
L131:   ifnull L142
L134:   iconst_1
L135:   dup
L136:   dup
L137:   pop2
L138:   goto L146
L141:   athrow
L142:   iconst_0
L143:   iconst_1
L144:   dup
L145:   pop2
L146:   invokevirtual Method AC method684 (Z)V
L149:   aload_0
L150:   getfield Field Nf field908 LRC;
L153:   ifnull L167
L156:   aload_1
L157:   aload_0
L158:   getfield Field Nf field908 LRC;
L161:   getfield Field RC field735 I
L164:   invokevirtual Method AC method691 (I)V
L167:   aload_1
L168:   aload_0
L169:   getfield Field Nf field909 LTe;
L172:   ifnull L182
L175:   iconst_1
L176:   dup
L177:   dup
L178:   pop2
L179:   goto L186
L182:   iconst_0
L183:   iconst_1
L184:   dup
L185:   pop2
L186:   invokevirtual Method AC method684 (Z)V
L189:   aload_0
L190:   getfield Field Nf field909 LTe;
L193:   ifnull L207
L196:   aload_1
L197:   aload_0
L198:   getfield Field Nf field909 LTe;
L201:   getfield Field Te field2117 Ljava/lang/String;
L204:   invokevirtual Method AC method683 (Ljava/lang/String;)V
L207:   aload_1
L208:   aload_0
L209:   getfield Field Nf field916 J
L212:   invokevirtual Method AC method690 (J)V
L215:   return
L216:   
        .attribute StackMap b'\x00\x0B\x00\x5F\x00\x00\x00\x01\x07\x00\x95\x00\x60\x00\x02\x07\x00\x02\x07\x00\x84\x00\x01\x07\x00\x84\x00\x64\x00\x02\x07\x00\x02\x07\x00\x84\x00\x02\x07\x00\x84\x01\x00\x76\x00\x02\x07\x00\x02\x07\x00\x84\x00\x00\x00\x8D\x00\x00\x00\x01\x07\x00\x95\x00\x8E\x00\x02\x07\x00\x02\x07\x00\x84\x00\x01\x07\x00\x84\x00\x92\x00\x02\x07\x00\x02\x07\x00\x84\x00\x02\x07\x00\x84\x01\x00\xA7\x00\x02\x07\x00\x02\x07\x00\x84\x00\x00\x00\xB6\x00\x02\x07\x00\x02\x07\x00\x84\x00\x01\x07\x00\x84\x00\xBA\x00\x02\x07\x00\x02\x07\x00\x84\x00\x02\x07\x00\x84\x01\x00\xCF\x00\x02\x07\x00\x02\x07\x00\x84\x00\x00'
    .end code
    .exceptions java/io/IOException
.end method
.end class
