.version 49 0
.class public final super ng
.super td
.field public final synthetic field100 LRg;

.method public method73 : (IIF)V
    .code stack 6 locals 4
L0:     aload_0
L1:     getfield Field ng field100 LRg;
L4:     getfield Field Rg field239 Lqd;
L7:     new Wf
L10:    dup
L11:    aload_0
L12:    getfield Field ng field100 LRg;
L15:    getfield Field Rg false Led;
L18:    iload_1
L19:    iload_2
L20:    invokespecial Method Wf <init> (Led;II)V
L23:    invokevirtual Method qd method394 (LD;)V
L26:    return
L27:    
    .end code
.end method

.method public method56 : ()V
    .code stack 4 locals 1
L0:     aload_0
L1:     getfield Field ng field100 LRg;
L4:     getfield Field Rg field239 Lqd;
L7:     new RF
L10:    dup
L11:    aload_0
L12:    getfield Field ng field100 LRg;
L15:    getfield Field Rg false Led;
L18:    invokespecial Method RF <init> (Led;)V
L21:    invokevirtual Method qd method394 (LD;)V
L24:    return
L25:    
    .end code
.end method

.method public method65 : ()V
    .code stack 7 locals 1
L0:     getstatic Field XE field2166 [I
L3:     aload_0
L4:     getfield Field ng field100 LRg;
L7:     getfield Field Rg field227 LqE;
L10:    invokevirtual Method qE ordinal ()I
L13:    iaload
L14:    lookupswitch
            1 : L40
            2 : L91
            default : L128
L40:    aload_0
L41:    iconst_0
L42:    ifne L41
L45:    getfield Field ng field100 LRg;
L48:    getfield Field Rg field239 Lqd;
L51:    new ag
L54:    dup
L55:    aload_0
L56:    getfield Field ng field100 LRg;
L59:    getfield Field Rg false Led;
L62:    aload_0
L63:    getfield Field ng field100 LRg;
L66:    getfield Field Rg field227 LqE;
L69:    aload_0
L70:    getfield Field ng field100 LRg;
L73:    getfield Field Rg field221 Lff;
L76:    aload_0
L77:    getfield Field ng field100 LRg;
L80:    getfield Field Rg field238 Lff;
L83:    invokespecial Method ag <init> (Led;LqE;Lff;Lff;)V
L86:    invokevirtual Method qd method394 (LD;)V
L89:    return
L90:    athrow
L91:    aload_0
L92:    getfield Field ng field100 LRg;
L95:    getfield Field Rg field239 Lqd;
L98:    new ag
L101:   dup
L102:   aload_0
L103:   getfield Field ng field100 LRg;
L106:   getfield Field Rg false Led;
L109:   aload_0
L110:   getfield Field ng field100 LRg;
L113:   getfield Field Rg field227 LqE;
L116:   aload_0
L117:   getfield Field ng field100 LRg;
L120:   invokespecial Method ag <init> (Led;LqE;LRg;)V
L123:   invokevirtual Method qd method394 (LD;)V
L126:   return
L127:   athrow
L128:   aload_0
L129:   getfield Field ng field100 LRg;
L132:   getfield Field Rg field239 Lqd;
L135:   new ag
L138:   dup
L139:   aload_0
L140:   getfield Field ng field100 LRg;
L143:   getfield Field Rg false Led;
L146:   aload_0
L147:   getfield Field ng field100 LRg;
L150:   getfield Field Rg field227 LqE;
L153:   invokespecial Method ag <init> (Led;LqE;)V
L156:   invokevirtual Method qd method394 (LD;)V
L159:   return
L160:   
        .attribute StackMap b'\x00\x06\x00\x28\x00\x01\x07\x00\x02\x00\x00\x00\x29\x00\x01\x07\x00\x02\x00\x01\x07\x00\x02\x00\x5A\x00\x00\x00\x01\x07\x00\x48\x00\x5B\x00\x01\x07\x00\x02\x00\x00\x00\x7F\x00\x00\x00\x01\x07\x00\x48\x00\x80\x00\x01\x07\x00\x02\x00\x00'
    .end code
.end method

.method public this : ()V
    .code stack 4 locals 1
L0:     aload_0
L1:     getfield Field ng field100 LRg;
L4:     getfield Field Rg field239 Lqd;
L7:     new hf
L10:    dup
L11:    aload_0
L12:    getfield Field ng field100 LRg;
L15:    getfield Field Rg false Led;
L18:    invokespecial Method hf <init> (Led;)V
L21:    invokevirtual Method qd method394 (LD;)V
L24:    return
L25:    
    .end code
.end method

.method public method76 : ()V
    .code stack 5 locals 1
L0:     aload_0
L1:     getfield Field ng field100 LRg;
L4:     getfield Field Rg field239 Lqd;
L7:     new LF
L10:    dup
L11:    aload_0
L12:    getfield Field ng field100 LRg;
L15:    getfield Field Rg false Led;
L18:    aload_0
L19:    getfield Field ng field100 LRg;
L22:    getfield Field Rg field231 LsE;
L25:    invokespecial Method LF <init> (Led;LsE;)V
L28:    invokevirtual Method qd method394 (LD;)V
L31:    return
L32:    
    .end code
.end method

.method public method69 : ()V
    .code stack 4 locals 1
L0:     aload_0
L1:     getfield Field ng field100 LRg;
L4:     getfield Field Rg field239 Lqd;
L7:     new aF
L10:    dup
L11:    aload_0
L12:    getfield Field ng field100 LRg;
L15:    getfield Field Rg false Led;
L18:    invokespecial Method aF <init> (Led;)V
L21:    invokevirtual Method qd method394 (LD;)V
L24:    return
L25:    
    .end code
.end method

.method public method87 : (Led;I[I)V
    .code stack 7 locals 4
L0:     aload_0
L1:     getfield Field ng field100 LRg;
L4:     getfield Field Rg field239 Lqd;
L7:     new uE
L10:    dup
L11:    aload_0
L12:    getfield Field ng field100 LRg;
L15:    getfield Field Rg false Led;
L18:    aload_1
L19:    iload_2
L20:    aload_3
L21:    invokespecial Method uE <init> (Led;Led;I[I)V
L24:    invokevirtual Method qd method394 (LD;)V
L27:    return
L28:    
    .end code
.end method

.method public method67 : ()V
    .code stack 6 locals 1
L0:     aload_0
L1:     getfield Field ng field100 LRg;
L4:     getfield Field Rg field239 Lqd;
L7:     new dG
L10:    dup
L11:    aload_0
L12:    getfield Field ng field100 LRg;
L15:    getfield Field Rg false Led;
L18:    aload_0
L19:    getfield Field ng field100 LRg;
L22:    getfield Field Rg field221 Lff;
L25:    getfield Field ff field879 I
L28:    aload_0
L29:    getfield Field ng field100 LRg;
L32:    getfield Field Rg field221 Lff;
L35:    getfield Field ff field881 I
L38:    invokespecial Method dG <init> (Led;II)V
L41:    invokevirtual Method qd method394 (LD;)V
L44:    return
L45:    
    .end code
.end method

.method public method68 : ()V
    .code stack 4 locals 1
L0:     aload_0
L1:     getfield Field ng field100 LRg;
L4:     getfield Field Rg field239 Lqd;
L7:     new LG
L10:    dup
L11:    aload_0
L12:    getfield Field ng field100 LRg;
L15:    getfield Field Rg false Led;
L18:    invokespecial Method LG <init> (Led;)V
L21:    invokevirtual Method qd method394 (LD;)V
L24:    return
L25:    
    .end code
.end method

.method public method60 : (LUf;)V
    .code stack 5 locals 2
L0:     aload_1
L1:     getfield Field Uf field1348 Ljava/lang/String;
L4:     ifnull L28
L7:     getstatic Field Kc field1931 LKc;
L10:    new hG
L13:    dup
L14:    aload_0
L15:    getfield Field ng field100 LRg;
L18:    getfield Field Rg false Led;
L21:    aload_1
L22:    invokespecial Method hG <init> (Led;LUf;)V
L25:    invokevirtual Method Kc method846 (LD;)V
L28:    return
L29:    
        .attribute StackMap b'\x00\x01\x00\x1C\x00\x02\x07\x00\x02\x07\x00\x7B\x00\x00'
    .end code
.end method

.method public method91 : (Lff;)V
    .code stack 5 locals 2
L0:     aload_0
L1:     getfield Field ng field100 LRg;
L4:     getfield Field Rg field239 Lqd;
L7:     new Re
L10:    dup
L11:    aload_0
L12:    getfield Field ng field100 LRg;
L15:    getfield Field Rg false Led;
L18:    aload_0
L19:    getfield Field ng field100 LRg;
L22:    getfield Field Rg field238 Lff;
L25:    invokespecial Method Re <init> (Led;Lff;)V
L28:    invokevirtual Method qd method394 (LD;)V
L31:    return
L32:    
    .end code
.end method

.method public <init> : (LRg;)V
    .code stack 3 locals 2
L0:     aload_0
L1:     dup
L2:     aload_1
L3:     putfield Field ng field100 LRg;
L6:     invokespecial Method td <init> ()V
L9:     return
L10:    
    .end code
.end method
.innerclasses
    XE Rg [0] static synthetic
    ng [0] [0]
.end innerclasses
.enclosing method Rg this ()V
.end class
