.version 49 0
.class public final super OC
.super java/lang/Object
.field private static final field2026 Ljava/util/regex/Pattern;
.field private static field2027 Ljava/lang/Object;
.field public static field2028 J
.field private static final field2029 Ljava/util/regex/Pattern;
.field private static final field2030 Ljava/util/regex/Pattern;
.field private static final field2031 Ljava/util/regex/Pattern;
.field private static final field2032 Ljava/util/regex/Pattern;
.field private static field2033 Ljava/security/MessageDigest;
.field private static final try Ljava/util/regex/Pattern;
.field public static field2034 D
.field public static new Z
.field private static final field2035 Ljava/util/regex/Pattern;
.field private static final this Ljava/util/regex/Pattern;
.field private static final field2036 [Ljava/lang/String;
.field private static field2037 D
.field private static final field2038 Ljava/util/regex/Pattern;
.field private static final field2039 Ljava/util/regex/Pattern;

.method public static method988 : (DDD)D
    .code stack 4 locals 6
L0:     dload_0
L1:     dload_2
L2:     dcmpg
L3:     ifge L9
L6:     dload_2
L7:     dreturn
L8:     athrow
L9:     dload_0
L10:    dload 4
L12:    dcmpl
L13:    ifle L20
L16:    dload 4
L18:    dreturn
L19:    athrow
L20:    dload_0
L21:    dreturn
L22:    
        .attribute StackMap b'\x00\x04\x00\x08\x00\x00\x00\x01\x07\x00\x28\x00\x09\x00\x03\x03\x03\x03\x00\x00\x00\x13\x00\x00\x00\x01\x07\x00\x28\x00\x14\x00\x03\x03\x03\x03\x00\x00'
    .end code
.end method

.method public static method989 : (Ljava/lang/String;)[B
    .code stack 5 locals 5
        .catch java/io/IOException from L0 to L61 using L83
L0:     ldc Class OC
L2:     new java/lang/StringBuilder
L5:     dup
L6:     invokespecial Method java/lang/StringBuilder <init> ()V
L9:     iconst_0
L10:    ldc "/data/"
L12:    invokevirtual Method java/lang/StringBuilder insert (ILjava/lang/String;)Ljava/lang/StringBuilder;
L15:    aload_0
L16:    invokevirtual Method java/lang/StringBuilder append (Ljava/lang/String;)Ljava/lang/StringBuilder;
L19:    invokevirtual Method java/lang/StringBuilder toString ()Ljava/lang/String;
L22:    invokevirtual Method java/lang/Class getResourceAsStream (Ljava/lang/String;)Ljava/io/InputStream;
L25:    astore_1
L26:    new java/io/ByteArrayOutputStream
L29:    dup
L30:    invokespecial Method java/io/ByteArrayOutputStream <init> ()V
L33:    astore_2
L34:    ldc 65536
L36:    newarray byte
L38:    iconst_1
L39:    dup
L40:    pop2
L41:    astore_3
L42:    aload_1
L43:    aload_3
L44:    invokevirtual Method java/io/InputStream read ([B)I
L47:    dup
L48:    istore 4
L50:    iconst_m1
L51:    iconst_1
L52:    dup
L53:    pop2
L54:    if_icmpne L62
L57:    aload_2
L58:    goto L79
L61:    athrow
        .catch java/io/IOException from L62 to L77 using L83
L62:    aload_2
L63:    aload_3
L64:    iconst_0
L65:    iconst_1
L66:    dup
L67:    pop2
L68:    iload 4
L70:    invokevirtual Method java/io/ByteArrayOutputStream write ([BII)V
L73:    aload_1
L74:    goto L43
L77:    nop
L78:    athrow
        .catch java/io/IOException from L79 to L82 using L83
L79:    invokevirtual Method java/io/ByteArrayOutputStream toByteArray ()[B
L82:    areturn
L83:    astore_1
L84:    new java/lang/RuntimeException
L87:    dup
L88:    aload_1
L89:    invokespecial Method java/lang/RuntimeException <init> (Ljava/lang/Throwable;)V
L92:    athrow
L93:    
        .attribute StackMap b'\x00\x06\x00\x2B\x00\x04\x07\x00\x4C\x07\x00\x4E\x07\x00\x48\x07\x00\x50\x00\x01\x07\x00\x4E\x00\x3D\x00\x00\x00\x01\x07\x00\x28\x00\x3E\x00\x05\x07\x00\x4C\x07\x00\x4E\x07\x00\x48\x07\x00\x50\x01\x00\x00\x00\x4D\x00\x00\x00\x01\x07\x00\x28\x00\x4F\x00\x05\x07\x00\x4C\x07\x00\x4E\x07\x00\x48\x07\x00\x50\x01\x00\x01\x07\x00\x48\x00\x53\x00\x01\x07\x00\x4C\x00\x01\x07\x00\x2C'
    .end code
.end method

.method public static method990 : (Ljava/lang/String;)Ljava/nio/ByteBuffer;
    .code stack 4 locals 6
        .catch java/io/IOException from L0 to L65 using L159
L0:     ldc Class OC
L2:     new java/lang/StringBuilder
L5:     dup
L6:     invokespecial Method java/lang/StringBuilder <init> ()V
L9:     iconst_0
L10:    ldc "/data/"
L12:    invokevirtual Method java/lang/StringBuilder insert (ILjava/lang/String;)Ljava/lang/StringBuilder;
L15:    aload_0
L16:    invokevirtual Method java/lang/StringBuilder append (Ljava/lang/String;)Ljava/lang/StringBuilder;
L19:    invokevirtual Method java/lang/StringBuilder toString ()Ljava/lang/String;
L22:    invokevirtual Method java/lang/Class getResourceAsStream (Ljava/lang/String;)Ljava/io/InputStream;
L25:    astore_1
L26:    new java/util/ArrayList
L29:    dup
L30:    invokespecial Method java/util/ArrayList <init> ()V
L33:    astore_2
L34:    sipush 8192
L37:    iconst_1
L38:    dup
L39:    pop2
L40:    newarray byte
L42:    iconst_1
L43:    dup
L44:    pop2
L45:    astore_3
L46:    aload_1
L47:    aload_3
L48:    invokevirtual Method java/io/InputStream read ([B)I
L51:    dup
L52:    istore 4
L54:    iconst_m1
L55:    iconst_1
L56:    dup
L57:    pop2
L58:    if_icmpne L66
L61:    aload_2
L62:    goto L103
L65:    athrow
        .catch java/io/IOException from L66 to L98 using L159
L66:    iconst_0
L67:    iconst_1
L68:    dup
L69:    pop2
L70:    dup
L71:    istore 5
L73:    iload 4
L75:    if_icmpge L34
L78:    aload_2
L79:    aload_3
L80:    iload 5
L82:    iinc 5 1
L85:    baload
L86:    invokestatic Method java/lang/Byte valueOf (B)Ljava/lang/Byte;
L89:    invokevirtual Method java/util/ArrayList add (Ljava/lang/Object;)Z
L92:    pop
L93:    iload 5
L95:    goto L73
L98:    nop
L99:    nop
L100:   nop
L101:   nop
L102:   athrow
        .catch java/io/IOException from L103 to L158 using L159
L103:   invokevirtual Method java/util/ArrayList size ()I
L106:   invokestatic Method jouvieje/bass/utils/e method1679 (I)Ljava/nio/ByteBuffer;
L109:   astore_3
L110:   aload_2
L111:   invokevirtual Method java/util/ArrayList iterator ()Ljava/util/Iterator;
L114:   dup
L115:   astore 4
L117:   invokeinterface InterfaceMethod java/util/Iterator hasNext ()Z 1
L122:   ifeq L152
L125:   aload 4
L127:   invokeinterface InterfaceMethod java/util/Iterator next ()Ljava/lang/Object; 1
L132:   checkcast java/lang/Byte
L135:   invokevirtual Method java/lang/Byte byteValue ()B
L138:   istore 5
L140:   aload 4
L142:   aload_3
L143:   iload 5
L145:   invokevirtual Method java/nio/ByteBuffer put (B)Ljava/nio/ByteBuffer;
L148:   pop
L149:   goto L117
L152:   aload_3
L153:   invokevirtual Method java/nio/ByteBuffer flip ()Ljava/nio/Buffer;
L156:   pop
L157:   aload_3
L158:   areturn
L159:   astore_1
L160:   new java/lang/RuntimeException
L163:   dup
L164:   aload_1
L165:   invokespecial Method java/lang/RuntimeException <init> (Ljava/lang/Throwable;)V
L168:   athrow
L169:   
        .attribute StackMap b'\x00\x09\x00\x22\x00\x03\x07\x00\x4C\x07\x00\x4E\x07\x00\x65\x00\x00\x00\x41\x00\x00\x00\x01\x07\x00\x28\x00\x42\x00\x05\x07\x00\x4C\x07\x00\x4E\x07\x00\x65\x07\x00\x50\x01\x00\x00\x00\x49\x00\x06\x07\x00\x4C\x07\x00\x4E\x07\x00\x65\x07\x00\x50\x01\x01\x00\x01\x01\x00\x62\x00\x00\x00\x01\x07\x00\x28\x00\x67\x00\x05\x07\x00\x4C\x07\x00\x4E\x07\x00\x65\x07\x00\x50\x01\x00\x01\x07\x00\x65\x00\x75\x00\x05\x07\x00\x4C\x07\x00\x4E\x07\x00\x65\x07\x00\x80\x07\x00\x82\x00\x01\x07\x00\x82\x00\x98\x00\x05\x07\x00\x4C\x07\x00\x4E\x07\x00\x65\x07\x00\x80\x07\x00\x82\x00\x00\x00\x9F\x00\x01\x07\x00\x4C\x00\x01\x07\x00\x2C'
    .end code
.end method

.method public static <clinit> : ()V
    .code stack 5 locals 0
L0:     new java/lang/Object
L3:     dup
L4:     invokespecial Method java/lang/Object <init> ()V
L7:     putstatic Field OC field2027 Ljava/lang/Object;
L10:    aconst_null
L11:    putstatic Field OC field2033 Ljava/security/MessageDigest;
L14:    sipush 269
L17:    iconst_1
L18:    dup
L19:    pop2
L20:    anewarray java/lang/String
L23:    iconst_1
L24:    dup
L25:    pop2
L26:    dup
L27:    iconst_0
L28:    iconst_1
L29:    dup
L30:    pop2
L31:    ldc "MUSEUM"
L33:    aastore
L34:    dup
L35:    iconst_1
L36:    dup
L37:    dup
L38:    pop2
L39:    ldc "TRAVEL"
L41:    aastore
L42:    dup
L43:    iconst_2
L44:    iconst_1
L45:    dup
L46:    pop2
L47:    ldc "COOP"
L49:    aastore
L50:    dup
L51:    iconst_3
L52:    iconst_1
L53:    dup
L54:    pop2
L55:    ldc "INFO"
L57:    aastore
L58:    dup
L59:    iconst_4
L60:    iconst_1
L61:    dup
L62:    pop2
L63:    ldc "AERO"
L65:    aastore
L66:    dup
L67:    iconst_5
L68:    iconst_1
L69:    dup
L70:    pop2
L71:    ldc "JOBS"
L73:    aastore
L74:    dup
L75:    bipush 6
L77:    iconst_1
L78:    dup
L79:    pop2
L80:    ldc "MOBI"
L82:    aastore
L83:    dup
L84:    bipush 7
L86:    iconst_1
L87:    dup
L88:    pop2
L89:    ldc "NAME"
L91:    aastore
L92:    dup
L93:    bipush 8
L95:    iconst_1
L96:    dup
L97:    pop2
L98:    ldc "ARPA"
L100:   aastore
L101:   dup
L102:   bipush 9
L104:   iconst_1
L105:   dup
L106:   pop2
L107:   ldc "ASIA"
L109:   aastore
L110:   dup
L111:   bipush 10
L113:   iconst_1
L114:   dup
L115:   pop2
L116:   ldc "GOV"
L118:   aastore
L119:   dup
L120:   bipush 11
L122:   iconst_1
L123:   dup
L124:   pop2
L125:   ldc "ORG"
L127:   aastore
L128:   dup
L129:   bipush 12
L131:   iconst_1
L132:   dup
L133:   pop2
L134:   ldc "TEL"
L136:   aastore
L137:   dup
L138:   bipush 13
L140:   iconst_1
L141:   dup
L142:   pop2
L143:   ldc "MIL"
L145:   aastore
L146:   dup
L147:   bipush 14
L149:   iconst_1
L150:   dup
L151:   pop2
L152:   ldc "COM"
L154:   aastore
L155:   dup
L156:   bipush 15
L158:   iconst_1
L159:   dup
L160:   pop2
L161:   ldc "PRO"
L163:   aastore
L164:   dup
L165:   bipush 16
L167:   iconst_1
L168:   dup
L169:   pop2
L170:   ldc "CAT"
L172:   aastore
L173:   dup
L174:   bipush 17
L176:   iconst_1
L177:   dup
L178:   pop2
L179:   ldc "INT"
L181:   aastore
L182:   dup
L183:   bipush 18
L185:   iconst_1
L186:   dup
L187:   pop2
L188:   ldc "NET"
L190:   aastore
L191:   dup
L192:   bipush 19
L194:   iconst_1
L195:   dup
L196:   pop2
L197:   ldc "EDU"
L199:   aastore
L200:   dup
L201:   bipush 20
L203:   iconst_1
L204:   dup
L205:   pop2
L206:   ldc "BIZ"
L208:   aastore
L209:   dup
L210:   bipush 21
L212:   iconst_1
L213:   dup
L214:   pop2
L215:   ldc "XXX"
L217:   aastore
L218:   dup
L219:   bipush 22
L221:   iconst_1
L222:   dup
L223:   pop2
L224:   ldc "KZ"
L226:   aastore
L227:   dup
L228:   bipush 23
L230:   iconst_1
L231:   dup
L232:   pop2
L233:   ldc "LY"
L235:   aastore
L236:   dup
L237:   bipush 24
L239:   iconst_1
L240:   dup
L241:   pop2
L242:   ldc "SY"
L244:   aastore
L245:   dup
L246:   bipush 25
L248:   iconst_1
L249:   dup
L250:   pop2
L251:   ldc "CY"
L253:   aastore
L254:   dup
L255:   bipush 26
L257:   iconst_1
L258:   dup
L259:   pop2
L260:   ldc "KY"
L262:   aastore
L263:   dup
L264:   bipush 27
L266:   iconst_1
L267:   dup
L268:   pop2
L269:   ldc "GY"
L271:   aastore
L272:   dup
L273:   bipush 28
L275:   iconst_1
L276:   dup
L277:   pop2
L278:   ldc "MY"
L280:   aastore
L281:   dup
L282:   bipush 29
L284:   iconst_1
L285:   dup
L286:   pop2
L287:   ldc "PY"
L289:   aastore
L290:   dup
L291:   bipush 30
L293:   iconst_1
L294:   dup
L295:   pop2
L296:   ldc "UY"
L298:   aastore
L299:   dup
L300:   bipush 31
L302:   iconst_1
L303:   dup
L304:   pop2
L305:   ldc "CX"
L307:   aastore
L308:   dup
L309:   bipush 32
L311:   iconst_1
L312:   dup
L313:   pop2
L314:   ldc "AX"
L316:   aastore
L317:   dup
L318:   bipush 33
L320:   iconst_1
L321:   dup
L322:   pop2
L323:   ldc "MX"
L325:   aastore
L326:   dup
L327:   bipush 34
L329:   iconst_1
L330:   dup
L331:   pop2
L332:   ldc "ZW"
L334:   aastore
L335:   dup
L336:   bipush 35
L338:   iconst_1
L339:   dup
L340:   pop2
L341:   ldc "BW"
L343:   aastore
L344:   dup
L345:   bipush 36
L347:   iconst_1
L348:   dup
L349:   pop2
L350:   ldc "AW"
L352:   aastore
L353:   dup
L354:   bipush 37
L356:   iconst_1
L357:   dup
L358:   pop2
L359:   ldc "TW"
L361:   aastore
L362:   dup
L363:   bipush 38
L365:   iconst_1
L366:   dup
L367:   pop2
L368:   ldc "PW"
L370:   aastore
L371:   dup
L372:   bipush 39
L374:   iconst_1
L375:   dup
L376:   pop2
L377:   ldc "KW"
L379:   aastore
L380:   dup
L381:   bipush 40
L383:   iconst_1
L384:   dup
L385:   pop2
L386:   ldc "RW"
L388:   aastore
L389:   dup
L390:   bipush 41
L392:   iconst_1
L393:   dup
L394:   pop2
L395:   ldc "GW"
L397:   aastore
L398:   dup
L399:   bipush 42
L401:   iconst_1
L402:   dup
L403:   pop2
L404:   ldc "MW"
L406:   aastore
L407:   dup
L408:   bipush 43
L410:   iconst_1
L411:   dup
L412:   pop2
L413:   ldc "MV"
L415:   aastore
L416:   dup
L417:   bipush 44
L419:   iconst_1
L420:   dup
L421:   pop2
L422:   ldc "BV"
L424:   aastore
L425:   dup
L426:   bipush 45
L428:   iconst_1
L429:   dup
L430:   pop2
L431:   ldc "CV"
L433:   aastore
L434:   dup
L435:   bipush 46
L437:   iconst_1
L438:   dup
L439:   pop2
L440:   ldc "LV"
L442:   aastore
L443:   dup
L444:   bipush 47
L446:   iconst_1
L447:   dup
L448:   pop2
L449:   ldc "TV"
L451:   aastore
L452:   dup
L453:   bipush 48
L455:   iconst_1
L456:   dup
L457:   pop2
L458:   ldc "SV"
L460:   aastore
L461:   dup
L462:   bipush 49
L464:   iconst_1
L465:   dup
L466:   pop2
L467:   ldc_w "BA"
L470:   aastore
L471:   dup
L472:   bipush 50
L474:   iconst_1
L475:   dup
L476:   pop2
L477:   ldc_w "LU"
L480:   aastore
L481:   dup
L482:   bipush 51
L484:   iconst_1
L485:   dup
L486:   pop2
L487:   ldc_w "EU"
L490:   aastore
L491:   dup
L492:   bipush 52
L494:   iconst_1
L495:   dup
L496:   pop2
L497:   ldc_w "RU"
L500:   aastore
L501:   dup
L502:   bipush 53
L504:   iconst_1
L505:   dup
L506:   pop2
L507:   ldc_w "VU"
L510:   aastore
L511:   dup
L512:   bipush 54
L514:   iconst_1
L515:   dup
L516:   pop2
L517:   ldc_w "HU"
L520:   aastore
L521:   dup
L522:   bipush 55
L524:   iconst_1
L525:   dup
L526:   pop2
L527:   ldc_w "AU"
L530:   aastore
L531:   dup
L532:   bipush 56
L534:   iconst_1
L535:   dup
L536:   pop2
L537:   ldc_w "GU"
L540:   aastore
L541:   dup
L542:   bipush 57
L544:   iconst_1
L545:   dup
L546:   pop2
L547:   ldc_w "CU"
L550:   aastore
L551:   dup
L552:   bipush 58
L554:   iconst_1
L555:   dup
L556:   pop2
L557:   ldc_w "MU"
L560:   aastore
L561:   dup
L562:   bipush 59
L564:   iconst_1
L565:   dup
L566:   pop2
L567:   ldc_w "SU"
L570:   aastore
L571:   dup
L572:   bipush 60
L574:   iconst_1
L575:   dup
L576:   pop2
L577:   ldc_w "NU"
L580:   aastore
L581:   dup
L582:   bipush 61
L584:   iconst_1
L585:   dup
L586:   pop2
L587:   ldc_w "BT"
L590:   aastore
L591:   dup
L592:   bipush 62
L594:   iconst_1
L595:   dup
L596:   pop2
L597:   ldc_w "MT"
L600:   aastore
L601:   dup
L602:   bipush 63
L604:   iconst_1
L605:   dup
L606:   pop2
L607:   ldc_w "ET"
L610:   aastore
L611:   dup
L612:   bipush 64
L614:   iconst_1
L615:   dup
L616:   pop2
L617:   ldc_w "GT"
L620:   aastore
L621:   dup
L622:   bipush 65
L624:   iconst_1
L625:   dup
L626:   pop2
L627:   ldc_w "ST"
L630:   aastore
L631:   dup
L632:   bipush 66
L634:   iconst_1
L635:   dup
L636:   pop2
L637:   ldc_w "IT"
L640:   aastore
L641:   dup
L642:   bipush 67
L644:   iconst_1
L645:   dup
L646:   pop2
L647:   ldc_w "TT"
L650:   aastore
L651:   dup
L652:   bipush 68
L654:   iconst_1
L655:   dup
L656:   pop2
L657:   ldc_w "AT"
L660:   aastore
L661:   dup
L662:   bipush 69
L664:   iconst_1
L665:   dup
L666:   pop2
L667:   ldc_w "HT"
L670:   aastore
L671:   dup
L672:   bipush 70
L674:   iconst_1
L675:   dup
L676:   pop2
L677:   ldc_w "PT"
L680:   aastore
L681:   dup
L682:   bipush 71
L684:   iconst_1
L685:   dup
L686:   pop2
L687:   ldc_w "YT"
L690:   aastore
L691:   dup
L692:   bipush 72
L694:   iconst_1
L695:   dup
L696:   pop2
L697:   ldc_w "LT"
L700:   aastore
L701:   dup
L702:   bipush 73
L704:   iconst_1
L705:   dup
L706:   pop2
L707:   ldc_w "ZA"
L710:   aastore
L711:   dup
L712:   bipush 74
L714:   iconst_1
L715:   dup
L716:   pop2
L717:   ldc_w "US"
L720:   aastore
L721:   dup
L722:   bipush 75
L724:   iconst_1
L725:   dup
L726:   pop2
L727:   ldc_w "MS"
L730:   aastore
L731:   dup
L732:   bipush 76
L734:   iconst_1
L735:   dup
L736:   pop2
L737:   ldc_w "WS"
L740:   aastore
L741:   dup
L742:   bipush 77
L744:   iconst_1
L745:   dup
L746:   pop2
L747:   ldc_w "BS"
L750:   aastore
L751:   dup
L752:   bipush 78
L754:   iconst_1
L755:   dup
L756:   pop2
L757:   ldc_w "RS"
L760:   aastore
L761:   dup
L762:   bipush 79
L764:   iconst_1
L765:   dup
L766:   pop2
L767:   ldc_w "LS"
L770:   aastore
L771:   dup
L772:   bipush 80
L774:   iconst_1
L775:   dup
L776:   pop2
L777:   ldc_w "AS"
L780:   aastore
L781:   dup
L782:   bipush 81
L784:   iconst_1
L785:   dup
L786:   pop2
L787:   ldc_w "GS"
L790:   aastore
L791:   dup
L792:   bipush 82
L794:   iconst_1
L795:   dup
L796:   pop2
L797:   ldc_w "ES"
L800:   aastore
L801:   dup
L802:   bipush 83
L804:   iconst_1
L805:   dup
L806:   pop2
L807:   ldc_w "PS"
L810:   aastore
L811:   dup
L812:   bipush 84
L814:   iconst_1
L815:   dup
L816:   pop2
L817:   ldc_w "IS"
L820:   aastore
L821:   dup
L822:   bipush 85
L824:   iconst_1
L825:   dup
L826:   pop2
L827:   ldc_w "CA"
L830:   aastore
L831:   dup
L832:   bipush 86
L834:   iconst_1
L835:   dup
L836:   pop2
L837:   ldc_w "SA"
L840:   aastore
L841:   dup
L842:   bipush 87
L844:   iconst_1
L845:   dup
L846:   pop2
L847:   ldc_w "GA"
L850:   aastore
L851:   dup
L852:   bipush 88
L854:   iconst_1
L855:   dup
L856:   pop2
L857:   ldc_w "QA"
L860:   aastore
L861:   dup
L862:   bipush 89
L864:   iconst_1
L865:   dup
L866:   pop2
L867:   ldc_w "KR"
L870:   aastore
L871:   dup
L872:   bipush 90
L874:   iconst_1
L875:   dup
L876:   pop2
L877:   ldc_w "ER"
L880:   aastore
L881:   dup
L882:   bipush 91
L884:   iconst_1
L885:   dup
L886:   pop2
L887:   ldc_w "AR"
L890:   aastore
L891:   dup
L892:   bipush 92
L894:   iconst_1
L895:   dup
L896:   pop2
L897:   ldc_w "IR"
L900:   aastore
L901:   dup
L902:   bipush 93
L904:   iconst_1
L905:   dup
L906:   pop2
L907:   ldc_w "LR"
L910:   aastore
L911:   dup
L912:   bipush 94
L914:   iconst_1
L915:   dup
L916:   pop2
L917:   ldc_w "FR"
L920:   aastore
L921:   dup
L922:   bipush 95
L924:   iconst_1
L925:   dup
L926:   pop2
L927:   ldc_w "MR"
L930:   aastore
L931:   dup
L932:   bipush 96
L934:   iconst_1
L935:   dup
L936:   pop2
L937:   ldc_w "CR"
L940:   aastore
L941:   dup
L942:   bipush 97
L944:   iconst_1
L945:   dup
L946:   pop2
L947:   ldc_w "HR"
L950:   aastore
L951:   dup
L952:   bipush 98
L954:   iconst_1
L955:   dup
L956:   pop2
L957:   ldc_w "NR"
L960:   aastore
L961:   dup
L962:   bipush 99
L964:   iconst_1
L965:   dup
L966:   pop2
L967:   ldc_w "PR"
L970:   aastore
L971:   dup
L972:   bipush 100
L974:   iconst_1
L975:   dup
L976:   pop2
L977:   ldc_w "BR"
L980:   aastore
L981:   dup
L982:   bipush 101
L984:   iconst_1
L985:   dup
L986:   pop2
L987:   ldc_w "SR"
L990:   aastore
L991:   dup
L992:   bipush 102
L994:   iconst_1
L995:   dup
L996:   pop2
L997:   ldc_w "TR"
L1000:  aastore
L1001:  dup
L1002:  bipush 103
L1004:  iconst_1
L1005:  dup
L1006:  pop2
L1007:  ldc_w "GR"
L1010:  aastore
L1011:  dup
L1012:  bipush 104
L1014:  iconst_1
L1015:  dup
L1016:  pop2
L1017:  ldc_w "GQ"
L1020:  aastore
L1021:  dup
L1022:  bipush 105
L1024:  iconst_1
L1025:  dup
L1026:  pop2
L1027:  ldc_w "MQ"
L1030:  aastore
L1031:  dup
L1032:  bipush 106
L1034:  iconst_1
L1035:  dup
L1036:  pop2
L1037:  ldc_w "AQ"
L1040:  aastore
L1041:  dup
L1042:  bipush 107
L1044:  iconst_1
L1045:  dup
L1046:  pop2
L1047:  ldc_w "IQ"
L1050:  aastore
L1051:  dup
L1052:  bipush 108
L1054:  iconst_1
L1055:  dup
L1056:  pop2
L1057:  ldc_w "KP"
L1060:  aastore
L1061:  dup
L1062:  bipush 109
L1064:  iconst_1
L1065:  dup
L1066:  pop2
L1067:  ldc_w "TP"
L1070:  aastore
L1071:  dup
L1072:  bipush 110
L1074:  iconst_1
L1075:  dup
L1076:  pop2
L1077:  ldc_w "JP"
L1080:  aastore
L1081:  dup
L1082:  bipush 111
L1084:  iconst_1
L1085:  dup
L1086:  pop2
L1087:  ldc_w "MP"
L1090:  aastore
L1091:  dup
L1092:  bipush 112
L1094:  iconst_1
L1095:  dup
L1096:  pop2
L1097:  ldc_w "GP"
L1100:  aastore
L1101:  dup
L1102:  bipush 113
L1104:  iconst_1
L1105:  dup
L1106:  pop2
L1107:  ldc_w "NP"
L1110:  aastore
L1111:  dup
L1112:  bipush 114
L1114:  iconst_1
L1115:  dup
L1116:  pop2
L1117:  ldc_w "LA"
L1120:  aastore
L1121:  dup
L1122:  bipush 115
L1124:  iconst_1
L1125:  dup
L1126:  pop2
L1127:  ldc_w "PA"
L1130:  aastore
L1131:  dup
L1132:  bipush 116
L1134:  iconst_1
L1135:  dup
L1136:  pop2
L1137:  ldc_w "UA"
L1140:  aastore
L1141:  dup
L1142:  bipush 117
L1144:  iconst_1
L1145:  dup
L1146:  pop2
L1147:  ldc_w "MA"
L1150:  aastore
L1151:  dup
L1152:  bipush 118
L1154:  iconst_1
L1155:  dup
L1156:  pop2
L1157:  ldc_w "NA"
L1160:  aastore
L1161:  dup
L1162:  bipush 119
L1164:  iconst_1
L1165:  dup
L1166:  pop2
L1167:  ldc_w "AO"
L1170:  aastore
L1171:  dup
L1172:  bipush 120
L1174:  iconst_1
L1175:  dup
L1176:  pop2
L1177:  ldc_w "FO"
L1180:  aastore
L1181:  dup
L1182:  bipush 121
L1184:  iconst_1
L1185:  dup
L1186:  pop2
L1187:  ldc_w "NO"
L1190:  aastore
L1191:  dup
L1192:  bipush 122
L1194:  iconst_1
L1195:  dup
L1196:  pop2
L1197:  ldc_w "TO"
L1200:  aastore
L1201:  dup
L1202:  bipush 123
L1204:  iconst_1
L1205:  dup
L1206:  pop2
L1207:  ldc_w "CO"
L1210:  aastore
L1211:  dup
L1212:  bipush 124
L1214:  iconst_1
L1215:  dup
L1216:  pop2
L1217:  ldc_w "BO"
L1220:  aastore
L1221:  dup
L1222:  bipush 125
L1224:  iconst_1
L1225:  dup
L1226:  pop2
L1227:  ldc_w "DO"
L1230:  aastore
L1231:  dup
L1232:  bipush 126
L1234:  iconst_1
L1235:  dup
L1236:  pop2
L1237:  ldc_w "RO"
L1240:  aastore
L1241:  dup
L1242:  bipush 127
L1244:  iconst_1
L1245:  dup
L1246:  pop2
L1247:  ldc_w "SO"
L1250:  aastore
L1251:  dup
L1252:  sipush 128
L1255:  iconst_1
L1256:  dup
L1257:  pop2
L1258:  ldc_w "MO"
L1261:  aastore
L1262:  dup
L1263:  sipush 129
L1266:  iconst_1
L1267:  dup
L1268:  pop2
L1269:  ldc_w "IO"
L1272:  aastore
L1273:  dup
L1274:  sipush 130
L1277:  iconst_1
L1278:  dup
L1279:  pop2
L1280:  ldc_w "JO"
L1283:  aastore
L1284:  dup
L1285:  sipush 131
L1288:  iconst_1
L1289:  dup
L1290:  pop2
L1291:  ldc_w "VA"
L1294:  aastore
L1295:  dup
L1296:  sipush 132
L1299:  iconst_1
L1300:  dup
L1301:  pop2
L1302:  ldc_w "GB"
L1305:  aastore
L1306:  dup
L1307:  sipush 133
L1310:  iconst_1
L1311:  dup
L1312:  pop2
L1313:  ldc_w "TN"
L1316:  aastore
L1317:  dup
L1318:  sipush 134
L1321:  iconst_1
L1322:  dup
L1323:  pop2
L1324:  ldc_w "SN"
L1327:  aastore
L1328:  dup
L1329:  sipush 135
L1332:  iconst_1
L1333:  dup
L1334:  pop2
L1335:  ldc_w "BN"
L1338:  aastore
L1339:  dup
L1340:  sipush 136
L1343:  iconst_1
L1344:  dup
L1345:  pop2
L1346:  ldc_w "IN"
L1349:  aastore
L1350:  dup
L1351:  sipush 137
L1354:  iconst_1
L1355:  dup
L1356:  pop2
L1357:  ldc_w "CN"
L1360:  aastore
L1361:  dup
L1362:  sipush 138
L1365:  iconst_1
L1366:  dup
L1367:  pop2
L1368:  ldc_w "MN"
L1371:  aastore
L1372:  dup
L1373:  sipush 139
L1376:  iconst_1
L1377:  dup
L1378:  pop2
L1379:  ldc_w "PN"
L1382:  aastore
L1383:  dup
L1384:  sipush 140
L1387:  iconst_1
L1388:  dup
L1389:  pop2
L1390:  ldc_w "HN"
L1393:  aastore
L1394:  dup
L1395:  sipush 141
L1398:  iconst_1
L1399:  dup
L1400:  pop2
L1401:  ldc_w "VN"
L1404:  aastore
L1405:  dup
L1406:  sipush 142
L1409:  iconst_1
L1410:  dup
L1411:  pop2
L1412:  ldc_w "GN"
L1415:  aastore
L1416:  dup
L1417:  sipush 143
L1420:  iconst_1
L1421:  dup
L1422:  pop2
L1423:  ldc_w "KN"
L1426:  aastore
L1427:  dup
L1428:  sipush 144
L1431:  iconst_1
L1432:  dup
L1433:  pop2
L1434:  ldc_w "AN"
L1437:  aastore
L1438:  dup
L1439:  sipush 145
L1442:  iconst_1
L1443:  dup
L1444:  pop2
L1445:  ldc_w "JM"
L1448:  aastore
L1449:  dup
L1450:  sipush 146
L1453:  iconst_1
L1454:  dup
L1455:  pop2
L1456:  ldc_w "CM"
L1459:  aastore
L1460:  dup
L1461:  sipush 147
L1464:  iconst_1
L1465:  dup
L1466:  pop2
L1467:  ldc_w "MM"
L1470:  aastore
L1471:  dup
L1472:  sipush 148
L1475:  iconst_1
L1476:  dup
L1477:  pop2
L1478:  ldc_w "KM"
L1481:  aastore
L1482:  dup
L1483:  sipush 149
L1486:  iconst_1
L1487:  dup
L1488:  pop2
L1489:  ldc_w "BM"
L1492:  aastore
L1493:  dup
L1494:  sipush 150
L1497:  iconst_1
L1498:  dup
L1499:  pop2
L1500:  ldc_w "PM"
L1503:  aastore
L1504:  dup
L1505:  sipush 151
L1508:  iconst_1
L1509:  dup
L1510:  pop2
L1511:  ldc_w "OM"
L1514:  aastore
L1515:  dup
L1516:  sipush 152
L1519:  iconst_1
L1520:  dup
L1521:  pop2
L1522:  ldc_w "AM"
L1525:  aastore
L1526:  dup
L1527:  sipush 153
L1530:  iconst_1
L1531:  dup
L1532:  pop2
L1533:  ldc_w "GM"
L1536:  aastore
L1537:  dup
L1538:  sipush 154
L1541:  iconst_1
L1542:  dup
L1543:  pop2
L1544:  ldc_w "TM"
L1547:  aastore
L1548:  dup
L1549:  sipush 155
L1552:  iconst_1
L1553:  dup
L1554:  pop2
L1555:  ldc_w "SM"
L1558:  aastore
L1559:  dup
L1560:  sipush 156
L1563:  iconst_1
L1564:  dup
L1565:  pop2
L1566:  ldc_w "DM"
L1569:  aastore
L1570:  dup
L1571:  sipush 157
L1574:  iconst_1
L1575:  dup
L1576:  pop2
L1577:  ldc_w "HM"
L1580:  aastore
L1581:  dup
L1582:  sipush 158
L1585:  iconst_1
L1586:  dup
L1587:  pop2
L1588:  ldc_w "FM"
L1591:  aastore
L1592:  dup
L1593:  sipush 159
L1596:  iconst_1
L1597:  dup
L1598:  pop2
L1599:  ldc_w "IM"
L1602:  aastore
L1603:  dup
L1604:  sipush 160
L1607:  iconst_1
L1608:  dup
L1609:  pop2
L1610:  ldc_w "ZM"
L1613:  aastore
L1614:  dup
L1615:  sipush 161
L1618:  iconst_1
L1619:  dup
L1620:  pop2
L1621:  ldc_w "IL"
L1624:  aastore
L1625:  dup
L1626:  sipush 162
L1629:  iconst_1
L1630:  dup
L1631:  pop2
L1632:  ldc_w "NL"
L1635:  aastore
L1636:  dup
L1637:  sipush 163
L1640:  iconst_1
L1641:  dup
L1642:  pop2
L1643:  ldc_w "SL"
L1646:  aastore
L1647:  dup
L1648:  sipush 164
L1651:  iconst_1
L1652:  dup
L1653:  pop2
L1654:  ldc_w "TL"
L1657:  aastore
L1658:  dup
L1659:  sipush 165
L1662:  iconst_1
L1663:  dup
L1664:  pop2
L1665:  ldc_w "AL"
L1668:  aastore
L1669:  dup
L1670:  sipush 166
L1673:  iconst_1
L1674:  dup
L1675:  pop2
L1676:  ldc_w "CL"
L1679:  aastore
L1680:  dup
L1681:  sipush 167
L1684:  iconst_1
L1685:  dup
L1686:  pop2
L1687:  ldc_w "PL"
L1690:  aastore
L1691:  dup
L1692:  sipush 168
L1695:  iconst_1
L1696:  dup
L1697:  pop2
L1698:  ldc_w "ML"
L1701:  aastore
L1702:  dup
L1703:  sipush 169
L1706:  iconst_1
L1707:  dup
L1708:  pop2
L1709:  ldc_w "GL"
L1712:  aastore
L1713:  dup
L1714:  sipush 170
L1717:  iconst_1
L1718:  dup
L1719:  pop2
L1720:  ldc_w "FK"
L1723:  aastore
L1724:  dup
L1725:  sipush 171
L1728:  iconst_1
L1729:  dup
L1730:  pop2
L1731:  ldc_w "TK"
L1734:  aastore
L1735:  dup
L1736:  sipush 172
L1739:  iconst_1
L1740:  dup
L1741:  pop2
L1742:  ldc_w "MK"
L1745:  aastore
L1746:  dup
L1747:  sipush 173
L1750:  iconst_1
L1751:  dup
L1752:  pop2
L1753:  ldc_w "SK"
L1756:  aastore
L1757:  dup
L1758:  sipush 174
L1761:  iconst_1
L1762:  dup
L1763:  pop2
L1764:  ldc_w "UK"
L1767:  aastore
L1768:  dup
L1769:  sipush 175
L1772:  iconst_1
L1773:  dup
L1774:  pop2
L1775:  ldc_w "PK"
L1778:  aastore
L1779:  dup
L1780:  sipush 176
L1783:  iconst_1
L1784:  dup
L1785:  pop2
L1786:  ldc_w "CK"
L1789:  aastore
L1790:  dup
L1791:  sipush 177
L1794:  iconst_1
L1795:  dup
L1796:  pop2
L1797:  ldc_w "HK"
L1800:  aastore
L1801:  dup
L1802:  sipush 178
L1805:  iconst_1
L1806:  dup
L1807:  pop2
L1808:  ldc_w "LK"
L1811:  aastore
L1812:  dup
L1813:  sipush 179
L1816:  iconst_1
L1817:  dup
L1818:  pop2
L1819:  ldc_w "DK"
L1822:  aastore
L1823:  dup
L1824:  sipush 180
L1827:  iconst_1
L1828:  dup
L1829:  pop2
L1830:  ldc_w "BJ"
L1833:  aastore
L1834:  dup
L1835:  sipush 181
L1838:  iconst_1
L1839:  dup
L1840:  pop2
L1841:  ldc_w "TJ"
L1844:  aastore
L1845:  dup
L1846:  sipush 182
L1849:  iconst_1
L1850:  dup
L1851:  pop2
L1852:  ldc_w "SJ"
L1855:  aastore
L1856:  dup
L1857:  sipush 183
L1860:  iconst_1
L1861:  dup
L1862:  pop2
L1863:  ldc_w "FJ"
L1866:  aastore
L1867:  dup
L1868:  sipush 184
L1871:  iconst_1
L1872:  dup
L1873:  pop2
L1874:  ldc_w "DJ"
L1877:  aastore
L1878:  dup
L1879:  sipush 185
L1882:  iconst_1
L1883:  dup
L1884:  pop2
L1885:  ldc_w "SB"
L1888:  aastore
L1889:  dup
L1890:  sipush 186
L1893:  iconst_1
L1894:  dup
L1895:  pop2
L1896:  ldc_w "BB"
L1899:  aastore
L1900:  dup
L1901:  sipush 187
L1904:  iconst_1
L1905:  dup
L1906:  pop2
L1907:  ldc_w "SI"
L1910:  aastore
L1911:  dup
L1912:  sipush 188
L1915:  iconst_1
L1916:  dup
L1917:  pop2
L1918:  ldc_w "LI"
L1921:  aastore
L1922:  dup
L1923:  sipush 189
L1926:  iconst_1
L1927:  dup
L1928:  pop2
L1929:  ldc_w "FI"
L1932:  aastore
L1933:  dup
L1934:  sipush 190
L1937:  iconst_1
L1938:  dup
L1939:  pop2
L1940:  ldc_w "GI"
L1943:  aastore
L1944:  dup
L1945:  sipush 191
L1948:  iconst_1
L1949:  dup
L1950:  pop2
L1951:  ldc_w "BI"
L1954:  aastore
L1955:  dup
L1956:  sipush 192
L1959:  iconst_1
L1960:  dup
L1961:  pop2
L1962:  ldc_w "NI"
L1965:  aastore
L1966:  dup
L1967:  sipush 193
L1970:  iconst_1
L1971:  dup
L1972:  pop2
L1973:  ldc_w "KI"
L1976:  aastore
L1977:  dup
L1978:  sipush 194
L1981:  iconst_1
L1982:  dup
L1983:  pop2
L1984:  ldc_w "VI"
L1987:  aastore
L1988:  dup
L1989:  sipush 195
L1992:  iconst_1
L1993:  dup
L1994:  pop2
L1995:  ldc_w "CI"
L1998:  aastore
L1999:  dup
L2000:  sipush 196
L2003:  iconst_1
L2004:  dup
L2005:  pop2
L2006:  ldc_w "AI"
L2009:  aastore
L2010:  dup
L2011:  sipush 197
L2014:  iconst_1
L2015:  dup
L2016:  pop2
L2017:  ldc_w "SH"
L2020:  aastore
L2021:  dup
L2022:  sipush 198
L2025:  iconst_1
L2026:  dup
L2027:  pop2
L2028:  ldc_w "KH"
L2031:  aastore
L2032:  dup
L2033:  sipush 199
L2036:  iconst_1
L2037:  dup
L2038:  pop2
L2039:  ldc_w "GH"
L2042:  aastore
L2043:  dup
L2044:  sipush 200
L2047:  iconst_1
L2048:  dup
L2049:  pop2
L2050:  ldc_w "CH"
L2053:  aastore
L2054:  dup
L2055:  sipush 201
L2058:  iconst_1
L2059:  dup
L2060:  pop2
L2061:  ldc_w "TH"
L2064:  aastore
L2065:  dup
L2066:  sipush 202
L2069:  iconst_1
L2070:  dup
L2071:  pop2
L2072:  ldc_w "MH"
L2075:  aastore
L2076:  dup
L2077:  sipush 203
L2080:  iconst_1
L2081:  dup
L2082:  pop2
L2083:  ldc_w "BH"
L2086:  aastore
L2087:  dup
L2088:  sipush 204
L2091:  iconst_1
L2092:  dup
L2093:  pop2
L2094:  ldc_w "PH"
L2097:  aastore
L2098:  dup
L2099:  sipush 205
L2102:  iconst_1
L2103:  dup
L2104:  pop2
L2105:  ldc_w "PG"
L2108:  aastore
L2109:  dup
L2110:  sipush 206
L2113:  iconst_1
L2114:  dup
L2115:  pop2
L2116:  ldc_w "UG"
L2119:  aastore
L2120:  dup
L2121:  sipush 207
L2124:  iconst_1
L2125:  dup
L2126:  pop2
L2127:  ldc_w "NG"
L2130:  aastore
L2131:  dup
L2132:  sipush 208
L2135:  iconst_1
L2136:  dup
L2137:  pop2
L2138:  ldc_w "BG"
L2141:  aastore
L2142:  dup
L2143:  sipush 209
L2146:  iconst_1
L2147:  dup
L2148:  pop2
L2149:  ldc_w "EG"
L2152:  aastore
L2153:  dup
L2154:  sipush 210
L2157:  iconst_1
L2158:  dup
L2159:  pop2
L2160:  ldc_w "KG"
L2163:  aastore
L2164:  dup
L2165:  sipush 211
L2168:  iconst_1
L2169:  dup
L2170:  pop2
L2171:  ldc_w "CG"
L2174:  aastore
L2175:  dup
L2176:  sipush 212
L2179:  iconst_1
L2180:  dup
L2181:  pop2
L2182:  ldc_w "VG"
L2185:  aastore
L2186:  dup
L2187:  sipush 213
L2190:  iconst_1
L2191:  dup
L2192:  pop2
L2193:  ldc_w "TG"
L2196:  aastore
L2197:  dup
L2198:  sipush 214
L2201:  iconst_1
L2202:  dup
L2203:  pop2
L2204:  ldc_w "MG"
L2207:  aastore
L2208:  dup
L2209:  sipush 215
L2212:  iconst_1
L2213:  dup
L2214:  pop2
L2215:  ldc_w "AG"
L2218:  aastore
L2219:  dup
L2220:  sipush 216
L2223:  iconst_1
L2224:  dup
L2225:  pop2
L2226:  ldc_w "GG"
L2229:  aastore
L2230:  dup
L2231:  sipush 217
L2234:  iconst_1
L2235:  dup
L2236:  pop2
L2237:  ldc_w "SG"
L2240:  aastore
L2241:  dup
L2242:  sipush 218
L2245:  iconst_1
L2246:  dup
L2247:  pop2
L2248:  ldc_w "PF"
L2251:  aastore
L2252:  dup
L2253:  sipush 219
L2256:  iconst_1
L2257:  dup
L2258:  pop2
L2259:  ldc_w "AF"
L2262:  aastore
L2263:  dup
L2264:  sipush 220
L2267:  iconst_1
L2268:  dup
L2269:  pop2
L2270:  ldc_w "BF"
L2273:  aastore
L2274:  dup
L2275:  sipush 221
L2278:  iconst_1
L2279:  dup
L2280:  pop2
L2281:  ldc_w "NF"
L2284:  aastore
L2285:  dup
L2286:  sipush 222
L2289:  iconst_1
L2290:  dup
L2291:  pop2
L2292:  ldc_w "WF"
L2295:  aastore
L2296:  dup
L2297:  sipush 223
L2300:  iconst_1
L2301:  dup
L2302:  pop2
L2303:  ldc_w "GF"
L2306:  aastore
L2307:  dup
L2308:  sipush 224
L2311:  iconst_1
L2312:  dup
L2313:  pop2
L2314:  ldc_w "CF"
L2317:  aastore
L2318:  dup
L2319:  sipush 225
L2322:  iconst_1
L2323:  dup
L2324:  pop2
L2325:  ldc_w "TF"
L2328:  aastore
L2329:  dup
L2330:  sipush 226
L2333:  iconst_1
L2334:  dup
L2335:  pop2
L2336:  ldc_w "LB"
L2339:  aastore
L2340:  dup
L2341:  sipush 227
L2344:  iconst_1
L2345:  dup
L2346:  pop2
L2347:  ldc_w "NC"
L2350:  aastore
L2351:  dup
L2352:  sipush 228
L2355:  iconst_1
L2356:  dup
L2357:  pop2
L2358:  ldc_w "VC"
L2361:  aastore
L2362:  dup
L2363:  sipush 229
L2366:  iconst_1
L2367:  dup
L2368:  pop2
L2369:  ldc_w "PE"
L2372:  aastore
L2373:  dup
L2374:  sipush 230
L2377:  iconst_1
L2378:  dup
L2379:  pop2
L2380:  ldc_w "AE"
L2383:  aastore
L2384:  dup
L2385:  sipush 231
L2388:  iconst_1
L2389:  dup
L2390:  pop2
L2391:  ldc_w "VE"
L2394:  aastore
L2395:  dup
L2396:  sipush 232
L2399:  iconst_1
L2400:  dup
L2401:  pop2
L2402:  ldc_w "IE"
L2405:  aastore
L2406:  dup
L2407:  sipush 233
L2410:  iconst_1
L2411:  dup
L2412:  pop2
L2413:  ldc_w "DE"
L2416:  aastore
L2417:  dup
L2418:  sipush 234
L2421:  iconst_1
L2422:  dup
L2423:  pop2
L2424:  ldc_w "NE"
L2427:  aastore
L2428:  dup
L2429:  sipush 235
L2432:  iconst_1
L2433:  dup
L2434:  pop2
L2435:  ldc_w "BE"
L2438:  aastore
L2439:  dup
L2440:  sipush 236
L2443:  iconst_1
L2444:  dup
L2445:  pop2
L2446:  ldc_w "JE"
L2449:  aastore
L2450:  dup
L2451:  sipush 237
L2454:  iconst_1
L2455:  dup
L2456:  pop2
L2457:  ldc_w "KE"
L2460:  aastore
L2461:  dup
L2462:  sipush 238
L2465:  iconst_1
L2466:  dup
L2467:  pop2
L2468:  ldc_w "EE"
L2471:  aastore
L2472:  dup
L2473:  sipush 239
L2476:  iconst_1
L2477:  dup
L2478:  pop2
L2479:  ldc_w "ME"
L2482:  aastore
L2483:  dup
L2484:  sipush 240
L2487:  iconst_1
L2488:  dup
L2489:  pop2
L2490:  ldc_w "YE"
L2493:  aastore
L2494:  dup
L2495:  sipush 241
L2498:  iconst_1
L2499:  dup
L2500:  pop2
L2501:  ldc_w "RE"
L2504:  aastore
L2505:  dup
L2506:  sipush 242
L2509:  iconst_1
L2510:  dup
L2511:  pop2
L2512:  ldc_w "SE"
L2515:  aastore
L2516:  dup
L2517:  sipush 243
L2520:  iconst_1
L2521:  dup
L2522:  pop2
L2523:  ldc_w "GE"
L2526:  aastore
L2527:  dup
L2528:  sipush 244
L2531:  iconst_1
L2532:  dup
L2533:  pop2
L2534:  ldc_w "SC"
L2537:  aastore
L2538:  dup
L2539:  sipush 245
L2542:  iconst_1
L2543:  dup
L2544:  pop2
L2545:  ldc_w "SD"
L2548:  aastore
L2549:  dup
L2550:  sipush 246
L2553:  iconst_1
L2554:  dup
L2555:  pop2
L2556:  ldc_w "CD"
L2559:  aastore
L2560:  dup
L2561:  sipush 247
L2564:  iconst_1
L2565:  dup
L2566:  pop2
L2567:  ldc_w "MD"
L2570:  aastore
L2571:  dup
L2572:  sipush 248
L2575:  iconst_1
L2576:  dup
L2577:  pop2
L2578:  ldc_w "GD"
L2581:  aastore
L2582:  dup
L2583:  sipush 249
L2586:  iconst_1
L2587:  dup
L2588:  pop2
L2589:  ldc_w "ID"
L2592:  aastore
L2593:  dup
L2594:  sipush 250
L2597:  iconst_1
L2598:  dup
L2599:  pop2
L2600:  ldc_w "BD"
L2603:  aastore
L2604:  dup
L2605:  sipush 251
L2608:  iconst_1
L2609:  dup
L2610:  pop2
L2611:  ldc_w "TD"
L2614:  aastore
L2615:  dup
L2616:  sipush 252
L2619:  iconst_1
L2620:  dup
L2621:  pop2
L2622:  ldc_w "AD"
L2625:  aastore
L2626:  dup
L2627:  sipush 253
L2630:  iconst_1
L2631:  dup
L2632:  pop2
L2633:  ldc_w "MC"
L2636:  aastore
L2637:  dup
L2638:  sipush 254
L2641:  iconst_1
L2642:  dup
L2643:  pop2
L2644:  ldc_w "CC"
L2647:  aastore
L2648:  dup
L2649:  sipush 255
L2652:  iconst_1
L2653:  dup
L2654:  pop2
L2655:  ldc_w "TC"
L2658:  aastore
L2659:  dup
L2660:  sipush 256
L2663:  iconst_1
L2664:  dup
L2665:  pop2
L2666:  ldc_w "AC"
L2669:  aastore
L2670:  dup
L2671:  sipush 257
L2674:  iconst_1
L2675:  dup
L2676:  pop2
L2677:  ldc_w "LC"
L2680:  aastore
L2681:  dup
L2682:  sipush 258
L2685:  iconst_1
L2686:  dup
L2687:  pop2
L2688:  ldc_w "EC"
L2691:  aastore
L2692:  dup
L2693:  sipush 259
L2696:  iconst_1
L2697:  dup
L2698:  pop2
L2699:  ldc_w "BY"
L2702:  aastore
L2703:  dup
L2704:  sipush 260
L2707:  iconst_1
L2708:  dup
L2709:  pop2
L2710:  ldc_w "DZ"
L2713:  aastore
L2714:  dup
L2715:  sipush 261
L2718:  iconst_1
L2719:  dup
L2720:  pop2
L2721:  ldc_w "MZ"
L2724:  aastore
L2725:  dup
L2726:  sipush 262
L2729:  iconst_1
L2730:  dup
L2731:  pop2
L2732:  ldc_w "NZ"
L2735:  aastore
L2736:  dup
L2737:  sipush 263
L2740:  iconst_1
L2741:  dup
L2742:  pop2
L2743:  ldc_w "CZ"
L2746:  aastore
L2747:  dup
L2748:  sipush 264
L2751:  iconst_1
L2752:  dup
L2753:  pop2
L2754:  ldc_w "BZ"
L2757:  aastore
L2758:  dup
L2759:  sipush 265
L2762:  iconst_1
L2763:  dup
L2764:  pop2
L2765:  ldc_w "SZ"
L2768:  aastore
L2769:  dup
L2770:  sipush 266
L2773:  iconst_1
L2774:  dup
L2775:  pop2
L2776:  ldc_w "TZ"
L2779:  aastore
L2780:  dup
L2781:  sipush 267
L2784:  iconst_1
L2785:  dup
L2786:  pop2
L2787:  ldc_w "AZ"
L2790:  aastore
L2791:  dup
L2792:  sipush 268
L2795:  iconst_1
L2796:  dup
L2797:  pop2
L2798:  ldc_w "UZ"
L2801:  aastore
L2802:  putstatic Field OC field2036 [Ljava/lang/String;
L2805:  ldc_w "[a-zA-Z0-9\\+]*://"
L2808:  invokestatic Method java/util/regex/Pattern compile (Ljava/lang/String;)Ljava/util/regex/Pattern;
L2811:  putstatic Field OC field2039 Ljava/util/regex/Pattern;
L2814:  ldc_w "[a-zA-Z0-9\\+\\-]{2,}://"
L2817:  invokestatic Method java/util/regex/Pattern compile (Ljava/lang/String;)Ljava/util/regex/Pattern;
L2820:  putstatic Field OC this Ljava/util/regex/Pattern;
L2823:  ldc_w "[a-zA-Z0-9\\-\\_\\.]+@([a-zA-Z0-9\\-]+\\.)+[a-zA-Z0-9\\-]{2,}"
L2826:  invokestatic Method java/util/regex/Pattern compile (Ljava/lang/String;)Ljava/util/regex/Pattern;
L2829:  putstatic Field OC field2032 Ljava/util/regex/Pattern;
L2832:  ldc_w "[\\p{L}0-9\\.\\_\\-\\+@%\\:]*"
L2835:  invokestatic Method java/util/regex/Pattern compile (Ljava/lang/String;)Ljava/util/regex/Pattern;
L2838:  putstatic Field OC field2035 Ljava/util/regex/Pattern;
L2841:  ldc_w "([a-zA-Z0-9%]+\\:[a-zA-Z0-9%]*@)?([\\p{L}0-9\\-]+\\.)+[a-zA-Z0-9\\-]{2,}"
L2844:  invokestatic Method java/util/regex/Pattern compile (Ljava/lang/String;)Ljava/util/regex/Pattern;
L2847:  putstatic Field OC field2030 Ljava/util/regex/Pattern;
L2850:  ldc_w ":[0-9]{0,5}"
L2853:  invokestatic Method java/util/regex/Pattern compile (Ljava/lang/String;)Ljava/util/regex/Pattern;
L2856:  putstatic Field OC try Ljava/util/regex/Pattern;
L2859:  ldc_w ":[0-9]{1,5}"
L2862:  invokestatic Method java/util/regex/Pattern compile (Ljava/lang/String;)Ljava/util/regex/Pattern;
L2865:  putstatic Field OC field2029 Ljava/util/regex/Pattern;
L2868:  ldc_w "[\\p{L}0-9\\-]"
L2871:  invokestatic Method java/util/regex/Pattern compile (Ljava/lang/String;)Ljava/util/regex/Pattern;
L2874:  putstatic Field OC field2026 Ljava/util/regex/Pattern;
L2877:  ldc_w "/[/a-zA-Z0-9#\\?%\\(\\)\\+\\-\\_\\.\\,\\=\\&\\;@]*"
L2880:  invokestatic Method java/util/regex/Pattern compile (Ljava/lang/String;)Ljava/util/regex/Pattern;
L2883:  putstatic Field OC field2038 Ljava/util/regex/Pattern;
L2886:  ldc_w "[\\.\\,\\!\\;\\:\\?]"
L2889:  invokestatic Method java/util/regex/Pattern compile (Ljava/lang/String;)Ljava/util/regex/Pattern;
L2892:  putstatic Field OC field2031 Ljava/util/regex/Pattern;
L2895:  return
L2896:  
    .end code
.end method

.method public static method991 : (J)Ljava/lang/String;
    .code stack 6 locals 2
L0:     new java/lang/StringBuilder
L3:     dup
L4:     invokespecial Method java/lang/StringBuilder <init> ()V
L7:     lload_0
L8:     bipush 24
L10:    iconst_1
L11:    dup
L12:    pop2
L13:    lshr
L14:    ldc2_w 255L
L17:    land
L18:    invokevirtual Method java/lang/StringBuilder append (J)Ljava/lang/StringBuilder;
L21:    ldc_w "."
L24:    invokevirtual Method java/lang/StringBuilder append (Ljava/lang/String;)Ljava/lang/StringBuilder;
L27:    lload_0
L28:    bipush 16
L30:    iconst_1
L31:    dup
L32:    pop2
L33:    lshr
L34:    ldc2_w 255L
L37:    land
L38:    invokevirtual Method java/lang/StringBuilder append (J)Ljava/lang/StringBuilder;
L41:    ldc_w "."
L44:    invokevirtual Method java/lang/StringBuilder append (Ljava/lang/String;)Ljava/lang/StringBuilder;
L47:    lload_0
L48:    bipush 8
L50:    iconst_1
L51:    dup
L52:    pop2
L53:    lshr
L54:    ldc2_w 255L
L57:    land
L58:    invokevirtual Method java/lang/StringBuilder append (J)Ljava/lang/StringBuilder;
L61:    ldc_w "."
L64:    invokevirtual Method java/lang/StringBuilder append (Ljava/lang/String;)Ljava/lang/StringBuilder;
L67:    lload_0
L68:    ldc2_w 255L
L71:    land
L72:    invokevirtual Method java/lang/StringBuilder append (J)Ljava/lang/StringBuilder;
L75:    invokevirtual Method java/lang/StringBuilder toString ()Ljava/lang/String;
L78:    areturn
L79:    
    .end code
.end method

.method public static varargs method992 : ([[LYg;)[LYg;
    .code stack 4 locals 9
L0:     new java/util/ArrayList
L3:     dup
L4:     invokespecial Method java/util/ArrayList <init> ()V
L7:     astore_1
L8:     aload_0
L9:     dup
L10:    astore_2
L11:    arraylength
L12:    istore_3
L13:    iconst_0
L14:    iconst_1
L15:    dup
L16:    pop2
L17:    dup
L18:    istore 4
L20:    iload_3
L21:    if_icmpge L78
L24:    aload_2
L25:    iload 4
L27:    aaload
L28:    dup
L29:    astore 5
L31:    arraylength
L32:    istore 6
L34:    iconst_0
L35:    iconst_1
L36:    dup
L37:    pop2
L38:    dup
L39:    istore 7
L41:    iload 6
L43:    if_icmpge L69
L46:    aload 5
L48:    iload 7
L50:    iinc 7 1
L53:    aaload
L54:    astore 8
L56:    aload_1
L57:    aload 8
L59:    invokevirtual Method java/util/ArrayList add (Ljava/lang/Object;)Z
L62:    pop
L63:    iload 7
L65:    goto L41
L68:    athrow
L69:    iinc 4 1
L72:    iload 4
L74:    goto L20
L77:    athrow
L78:    aload_1
L79:    iconst_0
L80:    iconst_1
L81:    dup
L82:    pop2
L83:    anewarray Yg
L86:    iconst_1
L87:    dup
L88:    pop2
L89:    invokevirtual Method java/util/ArrayList toArray ([Ljava/lang/Object;)[Ljava/lang/Object;
L92:    checkcast [LYg;
L95:    areturn
L96:    
        .attribute StackMap b'\x00\x06\x00\x14\x00\x05\x07\x02\xF3\x07\x00\x65\x07\x02\xF3\x01\x01\x00\x01\x01\x00\x29\x00\x08\x07\x02\xF3\x07\x00\x65\x07\x02\xF3\x01\x01\x07\x02\xF5\x01\x01\x00\x01\x01\x00\x44\x00\x00\x00\x01\x07\x00\x28\x00\x45\x00\x08\x07\x02\xF3\x07\x00\x65\x07\x02\xF3\x01\x01\x07\x02\xF5\x01\x01\x00\x00\x00\x4D\x00\x00\x00\x01\x07\x00\x28\x00\x4E\x00\x05\x07\x02\xF3\x07\x00\x65\x07\x02\xF3\x01\x01\x00\x00'
    .end code
.end method

.method public static method993 : (III)I
    .code stack 2 locals 3
L0:     iload_0
L1:     iload_1
L2:     if_icmpge L8
L5:     iload_1
L6:     ireturn
L7:     athrow
L8:     iload_0
L9:     iload_2
L10:    if_icmple L16
L13:    iload_2
L14:    ireturn
L15:    athrow
L16:    iload_0
L17:    ireturn
L18:    
        .attribute StackMap b'\x00\x04\x00\x07\x00\x00\x00\x01\x07\x00\x28\x00\x08\x00\x03\x01\x01\x01\x00\x00\x00\x0F\x00\x00\x00\x01\x07\x00\x28\x00\x10\x00\x03\x01\x01\x01\x00\x00'
    .end code
.end method

.method public static method994 : (Ljava/lang/String;)V
    .code stack 4 locals 2
        .catch java/lang/Exception from L0 to L18 using L20
L0:     invokestatic Method java/awt/Toolkit getDefaultToolkit ()Ljava/awt/Toolkit;
L3:     invokevirtual Method java/awt/Toolkit getSystemClipboard ()Ljava/awt/datatransfer/Clipboard;
L6:     new java/awt/datatransfer/StringSelection
L9:     dup
L10:    aload_0
L11:    invokespecial Method java/awt/datatransfer/StringSelection <init> (Ljava/lang/String;)V
L14:    aconst_null
L15:    invokevirtual Method java/awt/datatransfer/Clipboard setContents (Ljava/awt/datatransfer/Transferable;Ljava/awt/datatransfer/ClipboardOwner;)V
L18:    return
L19:    athrow
L20:    astore_1
L21:    aload_1
L22:    invokevirtual Method java/lang/Exception printStackTrace ()V
L25:    return
L26:    
        .attribute StackMap b'\x00\x02\x00\x13\x00\x00\x00\x01\x07\x00\x28\x00\x14\x00\x01\x07\x00\x4C\x00\x01\x07\x03\x01'
    .end code
.end method

.method public static method995 : (Ljava/lang/String;)Ljava/lang/String;
    .code stack 2 locals 2
        .catch java/io/UnsupportedEncodingException from L0 to L10 using L12
L0:     aload_0
L1:     ldc_w "UTF-8"
L4:     invokevirtual Method java/lang/String getBytes (Ljava/lang/String;)[B
L7:     invokestatic Method OC method1010 ([B)Ljava/lang/String;
L10:    areturn
L11:    athrow
L12:    astore_1
L13:    aconst_null
L14:    aload_1
L15:    invokevirtual Method java/io/UnsupportedEncodingException printStackTrace ()V
L18:    areturn
L19:    
        .attribute StackMap b'\x00\x02\x00\x0B\x00\x00\x00\x01\x07\x00\x28\x00\x0C\x00\x01\x07\x00\x4C\x00\x01\x07\x03\x1C'
    .end code
.end method

.method public static method996 : (I)Ljava/lang/String;
    .code stack 4 locals 1
L0:     iload_0
L1:     bipush 100
L3:     iconst_1
L4:     dup
L5:     pop2
L6:     irem
L7:     tableswitch 1
            L392
            L418
            L440
            L464
            L464
            L464
            L464
            L464
            L464
            L464
            L464
            L464
            L464
            L464
            L464
            L464
            L464
            L464
            L464
            L464
            L392
            L418
            L440
            L464
            L464
            L464
            L464
            L464
            L464
            L464
            L392
            L418
            L440
            L464
            L464
            L464
            L464
            L464
            L464
            L464
            L392
            L418
            L440
            L464
            L464
            L464
            L464
            L464
            L464
            L464
            L392
            L418
            L440
            L464
            L464
            L464
            L464
            L464
            L464
            L464
            L392
            L418
            L440
            L464
            L464
            L464
            L464
            L464
            L464
            L464
            L392
            L418
            L440
            L464
            L464
            L464
            L464
            L464
            L464
            L464
            L392
            L418
            L440
            L464
            L464
            L464
            L464
            L464
            L464
            L464
            L392
            L418
            L440
            default : L464
L392:   new java/lang/StringBuilder
L395:   iconst_0
L396:   ifne L461
L399:   dup
L400:   invokespecial Method java/lang/StringBuilder <init> ()V
L403:   iload_0
L404:   invokevirtual Method java/lang/StringBuilder append (I)Ljava/lang/StringBuilder;
L407:   ldc_w "st"
L410:   invokevirtual Method java/lang/StringBuilder append (Ljava/lang/String;)Ljava/lang/StringBuilder;
L413:   invokevirtual Method java/lang/StringBuilder toString ()Ljava/lang/String;
L416:   areturn
L417:   athrow
L418:   new java/lang/StringBuilder
L421:   dup
L422:   invokespecial Method java/lang/StringBuilder <init> ()V
L425:   iload_0
L426:   invokevirtual Method java/lang/StringBuilder append (I)Ljava/lang/StringBuilder;
L429:   ldc_w "nd"
L432:   invokevirtual Method java/lang/StringBuilder append (Ljava/lang/String;)Ljava/lang/StringBuilder;
L435:   invokevirtual Method java/lang/StringBuilder toString ()Ljava/lang/String;
L438:   areturn
L439:   athrow
L440:   new java/lang/StringBuilder
L443:   dup
L444:   invokespecial Method java/lang/StringBuilder <init> ()V
L447:   iload_0
L448:   invokevirtual Method java/lang/StringBuilder append (I)Ljava/lang/StringBuilder;
L451:   ldc_w "rd"
L454:   invokevirtual Method java/lang/StringBuilder append (Ljava/lang/String;)Ljava/lang/StringBuilder;
L457:   invokevirtual Method java/lang/StringBuilder toString ()Ljava/lang/String;
L460:   areturn
L461:   goto L395
L464:   new java/lang/StringBuilder
L467:   dup
L468:   invokespecial Method java/lang/StringBuilder <init> ()V
L471:   iload_0
L472:   invokevirtual Method java/lang/StringBuilder append (I)Ljava/lang/StringBuilder;
L475:   ldc_w "th"
L478:   invokevirtual Method java/lang/StringBuilder append (Ljava/lang/String;)Ljava/lang/StringBuilder;
L481:   invokevirtual Method java/lang/StringBuilder toString ()Ljava/lang/String;
L484:   areturn
L485:   
        .attribute StackMap b'\x00\x08\x01\x88\x00\x01\x01\x00\x00\x01\x8B\x00\x01\x01\x00\x01\x08\x01\x88\x01\xA1\x00\x00\x00\x01\x07\x00\x28\x01\xA2\x00\x01\x01\x00\x00\x01\xB7\x00\x00\x00\x01\x07\x00\x28\x01\xB8\x00\x01\x01\x00\x00\x01\xCD\x00\x01\x01\x00\x01\x08\x01\x88\x01\xD0\x00\x01\x01\x00\x00'
    .end code
.end method

.method public static method997 : (Ljava/util/LinkedHashMap;Z)V
    .code stack 5 locals 6
L0:     aload_0
L1:     invokevirtual Method java/util/LinkedHashMap size ()I
L4:     anewarray java/lang/Object
L7:     iconst_1
L8:     dup
L9:     pop2
L10:    astore_2
L11:    iconst_0
L12:    iconst_1
L13:    dup
L14:    pop2
L15:    istore_3
L16:    aload_0
L17:    invokevirtual Method java/util/LinkedHashMap keySet ()Ljava/util/Set;
L20:    invokeinterface InterfaceMethod java/util/Set iterator ()Ljava/util/Iterator; 1
L25:    dup
L26:    astore 4
L28:    invokeinterface InterfaceMethod java/util/Iterator hasNext ()Z 1
L33:    ifeq L58
L36:    aload 4
L38:    dup
L39:    invokeinterface InterfaceMethod java/util/Iterator next ()Ljava/lang/Object; 1
L44:    astore 5
L46:    aload_2
L47:    iload_3
L48:    aload 5
L50:    iinc 3 1
L53:    aastore
L54:    goto L28
L57:    athrow
L58:    iload_1
L59:    ifeq L82
L62:    new jc
L65:    aload_2
L66:    dup_x1
L67:    dup_x2
L68:    dup
L69:    pop2
L70:    dup
L71:    aload_0
L72:    invokespecial Method jc <init> (Ljava/util/LinkedHashMap;)V
L75:    invokestatic Method java/util/Arrays sort ([Ljava/lang/Object;Ljava/util/Comparator;)V
L78:    goto L95
L81:    athrow
L82:    aload_2
L83:    dup
L84:    new Zc
L87:    dup
L88:    aload_0
L89:    invokespecial Method Zc <init> (Ljava/util/LinkedHashMap;)V
L92:    invokestatic Method java/util/Arrays sort ([Ljava/lang/Object;Ljava/util/Comparator;)V
L95:    astore 4
L97:    aload 4
L99:    arraylength
L100:   istore 5
L102:   iconst_0
L103:   iconst_1
L104:   dup
L105:   pop2
L106:   dup
L107:   istore_1
L108:   iload 5
L110:   if_icmpge L141
L113:   aload 4
L115:   iload_1
L116:   iinc 1 1
L119:   aaload
L120:   astore_2
L121:   aload_0
L122:   aload_2
L123:   invokevirtual Method java/util/LinkedHashMap remove (Ljava/lang/Object;)Ljava/lang/Object;
L126:   checkcast java/lang/Integer
L129:   astore_3
L130:   aload_0
L131:   aload_2
L132:   aload_3
L133:   invokevirtual Method java/util/LinkedHashMap put (Ljava/lang/Object;Ljava/lang/Object;)Ljava/lang/Object;
L136:   pop
L137:   iload_1
L138:   goto L108
L141:   return
L142:   
        .attribute StackMap b'\x00\x08\x00\x1C\x00\x05\x07\x03\x37\x01\x07\x03\x41\x01\x07\x00\x82\x00\x01\x07\x00\x82\x00\x39\x00\x00\x00\x01\x07\x00\x28\x00\x3A\x00\x05\x07\x03\x37\x01\x07\x03\x41\x01\x07\x00\x82\x00\x00\x00\x51\x00\x00\x00\x01\x07\x00\x28\x00\x52\x00\x05\x07\x03\x37\x01\x07\x03\x41\x01\x07\x00\x82\x00\x00\x00\x5F\x00\x05\x07\x03\x37\x01\x07\x03\x41\x01\x07\x00\x82\x00\x01\x07\x03\x41\x00\x6C\x00\x06\x07\x03\x37\x01\x07\x00\x04\x00\x07\x03\x41\x01\x00\x01\x01\x00\x8D\x00\x06\x07\x03\x37\x01\x07\x00\x04\x00\x07\x03\x41\x01\x00\x00'
    .end code
.end method

.method public static method998 : ([[S)[[S
    .code stack 6 locals 3
L0:     aload_0
L1:     arraylength
L2:     anewarray [S
L5:     iconst_1
L6:     dup
L7:     pop2
L8:     astore_1
L9:     iconst_0
L10:    iconst_1
L11:    dup
L12:    pop2
L13:    dup
L14:    istore_2
L15:    aload_0
L16:    arraylength
L17:    if_icmpge L61
L20:    aload_1
L21:    aload_0
L22:    iload_2
L23:    dup_x1
L24:    aaload
L25:    arraylength
L26:    newarray short
L28:    iconst_1
L29:    dup
L30:    pop2
L31:    aastore
L32:    aload_0
L33:    iload_2
L34:    aaload
L35:    iconst_1
L36:    dup
L37:    pop2
L38:    aload_1
L39:    iload_2
L40:    aaload
L41:    iconst_0
L42:    dup_x1
L43:    iconst_1
L44:    dup
L45:    pop2
L46:    aload_0
L47:    iload_2
L48:    iinc 2 1
L51:    aaload
L52:    arraylength
L53:    invokestatic Method java/lang/System arraycopy (Ljava/lang/Object;ILjava/lang/Object;II)V
L56:    iload_2
L57:    goto L15
L60:    athrow
L61:    aload_1
L62:    areturn
L63:    
        .attribute StackMap b'\x00\x03\x00\x0F\x00\x03\x07\x03\x5A\x07\x03\x5A\x01\x00\x01\x01\x00\x3C\x00\x00\x00\x01\x07\x00\x28\x00\x3D\x00\x03\x07\x03\x5A\x07\x03\x5A\x01\x00\x00'
    .end code
.end method

.method public static method999 : (Ljava/lang/String;)[B
    .code stack 8 locals 5
L0:     new java/net/URL
L3:     dup
L4:     aload_0
L5:     invokespecial Method java/net/URL <init> (Ljava/lang/String;)V
L8:     invokevirtual Method java/net/URL openConnection ()Ljava/net/URLConnection;
L11:    checkcast java/net/HttpURLConnection
L14:    astore_1
L15:    sipush 8000
L18:    aload_1
L19:    dup_x1
L20:    sipush 8000
L23:    aload_1
L24:    iconst_0
L25:    iconst_1
L26:    dup
L27:    pop2
L28:    invokevirtual Method java/net/HttpURLConnection setAllowUserInteraction (Z)V
L31:    iconst_1
L32:    dup
L33:    pop2
L34:    invokevirtual Method java/net/HttpURLConnection setConnectTimeout (I)V
L37:    iconst_1
L38:    dup
L39:    pop2
L40:    invokevirtual Method java/net/HttpURLConnection setReadTimeout (I)V
        .catch [0] from L43 to L132 using L183
L43:    aload_1
L44:    invokevirtual Method java/net/HttpURLConnection getResponseCode ()I
L47:    lookupswitch
            200 : L110
            307 : L80
            404 : L140
            default : L151
L80:    aload_1
L81:    invokevirtual Method java/net/HttpURLConnection disconnect ()V
L84:    aload_1
L85:    ldc_w "Location"
L88:    invokevirtual Method java/net/HttpURLConnection getHeaderField (Ljava/lang/String;)Ljava/lang/String;
L91:    astore_2
L92:    new java/net/URL
L95:    dup
L96:    aload_2
L97:    invokespecial Method java/net/URL <init> (Ljava/lang/String;)V
L100:   invokevirtual Method java/net/URL openConnection ()Ljava/net/URLConnection;
L103:   checkcast java/net/HttpURLConnection
L106:   astore_1
L107:   goto L110
L110:   new java/io/ByteArrayOutputStream
L113:   dup
L114:   invokespecial Method java/io/ByteArrayOutputStream <init> ()V
L117:   astore_3
L118:   aload_1
L119:   invokevirtual Method java/net/HttpURLConnection getInputStream ()Ljava/io/InputStream;
L122:   aload_3
L123:   dup_x1
L124:   invokestatic Method OC method1018 (Ljava/io/InputStream;Ljava/io/OutputStream;)V
L127:   invokevirtual Method java/io/ByteArrayOutputStream toByteArray ()[B
L130:   astore 4
L132:   aload 4
L134:   aload_1
L135:   invokevirtual Method java/net/HttpURLConnection disconnect ()V
L138:   areturn
L139:   athrow
        .catch [0] from L140 to L143 using L183
L140:   aconst_null
L141:   astore 4
L143:   aload 4
L145:   aload_1
L146:   invokevirtual Method java/net/HttpURLConnection disconnect ()V
L149:   areturn
L150:   athrow
        .catch [0] from L151 to L185 using L183
L151:   new java/io/IOException
L154:   dup
L155:   new java/lang/StringBuilder
L158:   dup
L159:   invokespecial Method java/lang/StringBuilder <init> ()V
L162:   iconst_0
L163:   ldc_w "HTTP error "
L166:   invokevirtual Method java/lang/StringBuilder insert (ILjava/lang/String;)Ljava/lang/StringBuilder;
L169:   aload_1
L170:   invokevirtual Method java/net/HttpURLConnection getResponseCode ()I
L173:   invokevirtual Method java/lang/StringBuilder append (I)Ljava/lang/StringBuilder;
L176:   invokevirtual Method java/lang/StringBuilder toString ()Ljava/lang/String;
L179:   invokespecial Method java/io/IOException <init> (Ljava/lang/String;)V
L182:   athrow
L183:   astore 4
L185:   aload 4
L187:   aload_1
L188:   invokevirtual Method java/net/HttpURLConnection disconnect ()V
L191:   athrow
L192:   
        .attribute StackMap b'\x00\x07\x00\x50\x00\x02\x07\x00\x4C\x07\x03\x81\x00\x00\x00\x6E\x00\x02\x07\x00\x4C\x07\x03\x81\x00\x00\x00\x8B\x00\x00\x00\x01\x07\x00\x28\x00\x8C\x00\x02\x07\x00\x4C\x07\x03\x81\x00\x00\x00\x96\x00\x00\x00\x01\x07\x00\x28\x00\x97\x00\x02\x07\x00\x4C\x07\x03\x81\x00\x00\x00\xB7\x00\x02\x07\x00\x4C\x07\x03\x81\x00\x01\x07\x00\x28'
    .end code
    .exceptions java/io/IOException java/net/MalformedURLException
    .runtime visible annotations
        .annotation Lme/coley/recaf/metadata/InsnComment;
            At_1 = string "Create a new URL object"
        .end annotation
        .annotation Lme/coley/recaf/metadata/InsnComment;
            At_5 = string "Open a connection to the URL"
        .end annotation
        .annotation Lme/coley/recaf/metadata/InsnComment;
            At_8 = string "Set connection parameters"
        .end annotation
        .annotation Lme/coley/recaf/metadata/InsnComment;
            At_27 = string "Get the response code"
        .end annotation
        .annotation Lme/coley/recaf/metadata/InsnComment;
            At_29 = string "Switch based on the response code"
        .end annotation
        .annotation Lme/coley/recaf/metadata/InsnComment;
            At_31 = string "Close the current connection"
        .end annotation
        .annotation Lme/coley/recaf/metadata/InsnComment;
            At_33 = string "Get the redirection URL from the 'Location' header"
        .end annotation
        .annotation Lme/coley/recaf/metadata/InsnComment;
            At_37 = string "Create a new URL connection with the redirection URL"
        .end annotation
        .annotation Lme/coley/recaf/metadata/InsnComment;
            At_44 = string "Continue to handle the new connection"
        .end annotation
        .annotation Lme/coley/recaf/metadata/InsnComment;
            At_46 = string "For example: Handling the response data"
        .end annotation
    .end runtime
.end method

.method public static method1000 : (D)D
    .code stack 6 locals 2
L0:     dload_0
L1:     dconst_0
L2:     dcmpg
L3:     ifge L9
L6:     dconst_0
L7:     dreturn
L8:     athrow
L9:     dload_0
L10:    dconst_1
L11:    dcmpl
L12:    ifle L18
L15:    dconst_1
L16:    dreturn
L17:    athrow
L18:    ldc2_w 5e-1
L21:    dload_0
L22:    ldc2_w 3.141592653589793e0
L25:    dmul
L26:    invokestatic Method java/lang/Math cos (D)D
L29:    ldc2_w 5e-1
L32:    dmul
L33:    dsub
L34:    dreturn
L35:    
        .attribute StackMap b'\x00\x04\x00\x08\x00\x00\x00\x01\x07\x00\x28\x00\x09\x00\x01\x03\x00\x00\x00\x11\x00\x00\x00\x01\x07\x00\x28\x00\x12\x00\x01\x03\x00\x00'
    .end code
.end method

.method public static method1001 : (FFF)F
    .code stack 2 locals 3
L0:     fload_0
L1:     fload_1
L2:     fcmpg
L3:     ifge L9
L6:     fload_1
L7:     freturn
L8:     athrow
L9:     fload_0
L10:    fload_2
L11:    fcmpl
L12:    ifle L18
L15:    fload_2
L16:    freturn
L17:    athrow
L18:    fload_0
L19:    freturn
L20:    
        .attribute StackMap b'\x00\x04\x00\x08\x00\x00\x00\x01\x07\x00\x28\x00\x09\x00\x03\x02\x02\x02\x00\x00\x00\x11\x00\x00\x00\x01\x07\x00\x28\x00\x12\x00\x03\x02\x02\x02\x00\x00'
    .end code
.end method

.method public static varargs method1002 : (II[Ljava/util/List;)V
    .code stack 6 locals 9
L0:     new java/util/Random
L3:     dup
L4:     invokespecial Method java/util/Random <init> ()V
L7:     astore_3
L8:     iload_1
L9:     dup
L10:    istore_1
L11:    iload_0
L12:    if_icmple L99
L15:    aload_3
L16:    iload_1
L17:    iconst_1
L18:    dup
L19:    dup
L20:    pop2
L21:    iadd
L22:    iload_0
L23:    dup_x2
L24:    isub
L25:    invokevirtual Method java/util/Random nextInt (I)I
L28:    iadd
L29:    istore 4
L31:    aload_2
L32:    dup
L33:    astore 5
L35:    arraylength
L36:    istore 6
L38:    iconst_0
L39:    iconst_1
L40:    dup
L41:    pop2
L42:    dup
L43:    istore 7
L45:    iload 6
L47:    if_icmpge L91
L50:    aload 5
L52:    iload 7
L54:    iinc 7 1
L57:    aaload
L58:    astore 8
L60:    iload_1
L61:    aload 8
L63:    dup_x1
L64:    iload 4
L66:    aload 8
L68:    iload_1
L69:    invokeinterface InterfaceMethod java/util/List get (I)Ljava/lang/Object; 2
L74:    invokeinterface InterfaceMethod java/util/List set (ILjava/lang/Object;)Ljava/lang/Object; 3
L79:    invokeinterface InterfaceMethod java/util/List set (ILjava/lang/Object;)Ljava/lang/Object; 3
L84:    pop
L85:    iload 7
L87:    goto L45
L90:    athrow
L91:    iinc 1 -1
L94:    iload_1
L95:    goto L11
L98:    athrow
L99:    return
L100:   
        .attribute StackMap b'\x00\x06\x00\x0B\x00\x04\x01\x01\x07\x03\xB6\x07\x03\xB3\x00\x01\x01\x00\x2D\x00\x08\x01\x01\x07\x03\xB6\x07\x03\xB3\x01\x07\x03\xB6\x01\x01\x00\x01\x01\x00\x5A\x00\x00\x00\x01\x07\x00\x28\x00\x5B\x00\x08\x01\x01\x07\x03\xB6\x07\x03\xB3\x01\x07\x03\xB6\x01\x01\x00\x00\x00\x62\x00\x00\x00\x01\x07\x00\x28\x00\x63\x00\x04\x01\x01\x07\x03\xB6\x07\x03\xB3\x00\x00'
    .end code
.end method

.method public static method1003 : (LFE;)V
    .code stack 3 locals 1
L0:     getstatic Field net/gewaltig/cultris/Cultris field2396 Z
L3:     ifne L8
L6:     return
L7:     athrow
L8:     aload_0
L9:     getstatic Field Ae field347 LAe;
L12:    ldc_w "Please note that this is a beta version (1.4c).\u000AThe quality of this preview does not neccessarily\u000Areflect the final product.\u000A\u000ACheck http://gewaltig.net/ for updates."
L15:    invokevirtual Method FE method445 (LAe;Ljava/lang/String;)LjC;
L18:    pop
L19:    return
L20:    
        .attribute StackMap b'\x00\x02\x00\x07\x00\x00\x00\x01\x07\x00\x28\x00\x08\x00\x01\x07\x03\xCD\x00\x00'
    .end code
.end method

.method public static varargs method1004 : ([[C)[C
    .code stack 5 locals 7
L0:     iconst_0
L1:     iconst_1
L2:     dup
L3:     pop2
L4:     istore_1
L5:     aload_0
L6:     dup
L7:     astore_2
L8:     arraylength
L9:     istore_3
L10:    iconst_0
L11:    iconst_1
L12:    dup
L13:    pop2
L14:    dup
L15:    istore 4
L17:    iload_3
L18:    if_icmpge L42
L21:    aload_2
L22:    iload 4
L24:    iinc 4 1
L27:    aaload
L28:    astore 5
L30:    iload_1
L31:    aload 5
L33:    arraylength
L34:    iadd
L35:    istore_1
L36:    iload 4
L38:    goto L17
L41:    athrow
L42:    iload_1
L43:    newarray char
L45:    iconst_1
L46:    dup
L47:    pop2
L48:    astore_2
L49:    iconst_0
L50:    iconst_1
L51:    dup
L52:    pop2
L53:    istore_3
L54:    aload_0
L55:    dup
L56:    astore 4
L58:    arraylength
L59:    istore 5
L61:    iconst_0
L62:    iconst_1
L63:    dup
L64:    pop2
L65:    dup
L66:    istore_1
L67:    iload 5
L69:    if_icmpge L105
L72:    aload 4
L74:    iload_1
L75:    iinc 1 1
L78:    aaload
L79:    dup
L80:    astore 6
L82:    iconst_0
L83:    iconst_1
L84:    dup
L85:    pop2
L86:    aload_2
L87:    iload_3
L88:    aload 6
L90:    arraylength
L91:    invokestatic Method java/lang/System arraycopy (Ljava/lang/Object;ILjava/lang/Object;II)V
L94:    iload_3
L95:    aload 6
L97:    arraylength
L98:    iadd
L99:    istore_3
L100:   iload_1
L101:   goto L67
L104:   athrow
L105:   aload_2
L106:   areturn
L107:   
        .attribute StackMap b'\x00\x06\x00\x11\x00\x05\x07\x03\xDB\x01\x07\x03\xDB\x01\x01\x00\x01\x01\x00\x29\x00\x00\x00\x01\x07\x00\x28\x00\x2A\x00\x05\x07\x03\xDB\x01\x07\x03\xDB\x01\x01\x00\x00\x00\x43\x00\x06\x07\x03\xDB\x01\x07\x03\xDD\x01\x07\x03\xDB\x01\x00\x01\x01\x00\x68\x00\x00\x00\x01\x07\x00\x28\x00\x69\x00\x06\x07\x03\xDB\x01\x07\x03\xDD\x01\x07\x03\xDB\x01\x00\x00'
    .end code
.end method

.method public static method1005 : (J)Ljava/lang/String;
    .code stack 4 locals 16
L0:     lload_0
L1:     ldc2_w 1000L
L4:     ldiv
L5:     dup2
L6:     lstore_2
L7:     ldc2_w 60L
L10:    ldiv
L11:    dup2
L12:    lstore 4
L14:    ldc2_w 60L
L17:    ldiv
L18:    dup2
L19:    lstore 6
L21:    ldc2_w 24L
L24:    ldiv
L25:    dup2
L26:    lstore 8
L28:    ldc2_w 7L
L31:    ldiv
L32:    lstore 10
L34:    lload 8
L36:    ldc2_w 30L
L39:    ldiv
L40:    lstore 12
L42:    lload 8
L44:    ldc2_w 365L
L47:    ldiv
L48:    lstore 14
L50:    lload_0
L51:    ldc2_w 1000L
L54:    lcmp
L55:    ifge L63
L58:    ldc_w "moments"
L61:    areturn
L62:    athrow
L63:    lload_2
L64:    ldc2_w 20L
L67:    lcmp
L68:    ifge L76
L71:    ldc_w "some seconds"
L74:    areturn
L75:    athrow
L76:    lload_2
L77:    ldc2_w 50L
L80:    lcmp
L81:    ifge L88
L84:    ldc_w "half a minute"
L87:    areturn
L88:    lload_2
L89:    ldc2_w 90L
L92:    lcmp
L93:    ifge L100
L96:    ldc_w "a minute"
L99:    areturn
L100:   lload 4
L102:   ldc2_w 4L
L105:   lcmp
L106:   ifge L113
L109:   ldc_w "two minutes"
L112:   areturn
L113:   lload 4
L115:   ldc2_w 8L
L118:   lcmp
L119:   ifge L126
L122:   ldc_w "five minutes"
L125:   areturn
L126:   lload 4
L128:   ldc2_w 13L
L131:   lcmp
L132:   ifge L139
L135:   ldc_w "ten minutes"
L138:   areturn
L139:   lload 4
L141:   ldc2_w 18L
L144:   lcmp
L145:   ifge L152
L148:   ldc_w "15 minutes"
L151:   areturn
L152:   lload 4
L154:   ldc2_w 25L
L157:   lcmp
L158:   ifge L165
L161:   ldc_w "20 minutes"
L164:   areturn
L165:   lload 4
L167:   ldc2_w 45L
L170:   lcmp
L171:   ifge L178
L174:   ldc_w "half an hour"
L177:   areturn
L178:   lload 4
L180:   ldc2_w 90L
L183:   lcmp
L184:   ifge L191
L187:   ldc_w "an hour"
L190:   areturn
L191:   lload 6
L193:   ldc2_w 3L
L196:   lcmp
L197:   ifge L204
L200:   ldc_w "two hours"
L203:   areturn
L204:   lload 6
L206:   ldc2_w 11L
L209:   lcmp
L210:   ifge L217
L213:   ldc_w "a couple hours"
L216:   areturn
L217:   lload 6
L219:   ldc2_w 23L
L222:   lcmp
L223:   ifge L230
L226:   ldc_w "half a day"
L229:   areturn
L230:   lload 8
L232:   ldc2_w 2L
L235:   lcmp
L236:   ifge L243
L239:   ldc_w "a day"
L242:   areturn
L243:   lload 8
L245:   ldc2_w 3L
L248:   lcmp
L249:   ifge L256
L252:   ldc_w "two days"
L255:   areturn
L256:   lload 8
L258:   ldc2_w 4L
L261:   lcmp
L262:   ifge L269
L265:   ldc_w "three days"
L268:   areturn
L269:   lload 8
L271:   ldc2_w 5L
L274:   lcmp
L275:   ifge L282
L278:   ldc_w "four days"
L281:   areturn
L282:   lload 8
L284:   ldc2_w 6L
L287:   lcmp
L288:   ifge L295
L291:   ldc_w "five days"
L294:   areturn
L295:   lload 8
L297:   ldc2_w 7L
L300:   lcmp
L301:   ifge L308
L304:   ldc_w "six days"
L307:   areturn
L308:   lload 10
L310:   ldc2_w 2L
L313:   lcmp
L314:   ifge L321
L317:   ldc_w "a week"
L320:   areturn
L321:   lload 10
L323:   ldc2_w 3L
L326:   lcmp
L327:   ifge L334
L330:   ldc_w "two weeks"
L333:   areturn
L334:   lload 10
L336:   ldc2_w 4L
L339:   lcmp
L340:   ifge L347
L343:   ldc_w "three weeks"
L346:   areturn
L347:   lload 12
L349:   ldc2_w 2L
L352:   lcmp
L353:   ifge L360
L356:   ldc_w "a month"
L359:   areturn
L360:   lload 12
L362:   ldc2_w 3L
L365:   lcmp
L366:   ifge L373
L369:   ldc_w "two months"
L372:   areturn
L373:   lload 12
L375:   ldc2_w 5L
L378:   lcmp
L379:   ifge L386
L382:   ldc_w "a couple of months"
L385:   areturn
L386:   lload 12
L388:   ldc2_w 11L
L391:   lcmp
L392:   ifge L399
L395:   ldc_w "half a year"
L398:   areturn
L399:   lload 14
L401:   ldc2_w 2L
L404:   lcmp
L405:   ifge L412
L408:   ldc_w "a year"
L411:   areturn
L412:   lload 14
L414:   ldc2_w 3L
L417:   lcmp
L418:   ifge L425
L421:   ldc_w "two years"
L424:   areturn
L425:   lload 14
L427:   ldc2_w 4L
L430:   lcmp
L431:   ifge L438
L434:   ldc_w "three years"
L437:   areturn
L438:   lload 14
L440:   ldc2_w 5L
L443:   lcmp
L444:   ifge L451
L447:   ldc_w "four years"
L450:   areturn
L451:   lload 14
L453:   ldc2_w 6L
L456:   lcmp
L457:   ifge L464
L460:   ldc_w "five years"
L463:   areturn
L464:   ldc_w "a long time"
L467:   areturn
L468:   
        .attribute StackMap b'\x00\x22\x00\x3E\x00\x00\x00\x01\x07\x00\x28\x00\x3F\x00\x08\x04\x04\x04\x04\x04\x04\x04\x04\x00\x00\x00\x4B\x00\x00\x00\x01\x07\x00\x28\x00\x4C\x00\x08\x04\x04\x04\x04\x04\x04\x04\x04\x00\x00\x00\x58\x00\x08\x04\x04\x04\x04\x04\x04\x04\x04\x00\x00\x00\x64\x00\x08\x04\x04\x04\x04\x04\x04\x04\x04\x00\x00\x00\x71\x00\x08\x04\x04\x04\x04\x04\x04\x04\x04\x00\x00\x00\x7E\x00\x08\x04\x04\x04\x04\x04\x04\x04\x04\x00\x00\x00\x8B\x00\x08\x04\x04\x04\x04\x04\x04\x04\x04\x00\x00\x00\x98\x00\x08\x04\x04\x04\x04\x04\x04\x04\x04\x00\x00\x00\xA5\x00\x08\x04\x04\x04\x04\x04\x04\x04\x04\x00\x00\x00\xB2\x00\x08\x04\x04\x04\x04\x04\x04\x04\x04\x00\x00\x00\xBF\x00\x08\x04\x04\x04\x04\x04\x04\x04\x04\x00\x00\x00\xCC\x00\x08\x04\x04\x04\x04\x04\x04\x04\x04\x00\x00\x00\xD9\x00\x08\x04\x04\x04\x04\x04\x04\x04\x04\x00\x00\x00\xE6\x00\x08\x04\x04\x04\x04\x04\x04\x04\x04\x00\x00\x00\xF3\x00\x08\x04\x04\x04\x04\x04\x04\x04\x04\x00\x00\x01\x00\x00\x08\x04\x04\x04\x04\x04\x04\x04\x04\x00\x00\x01\x0D\x00\x08\x04\x04\x04\x04\x04\x04\x04\x04\x00\x00\x01\x1A\x00\x08\x04\x04\x04\x04\x04\x04\x04\x04\x00\x00\x01\x27\x00\x08\x04\x04\x04\x04\x04\x04\x04\x04\x00\x00\x01\x34\x00\x08\x04\x04\x04\x04\x04\x04\x04\x04\x00\x00\x01\x41\x00\x08\x04\x04\x04\x04\x04\x04\x04\x04\x00\x00\x01\x4E\x00\x08\x04\x04\x04\x04\x04\x04\x04\x04\x00\x00\x01\x5B\x00\x08\x04\x04\x04\x04\x04\x04\x04\x04\x00\x00\x01\x68\x00\x08\x04\x04\x04\x04\x04\x04\x04\x04\x00\x00\x01\x75\x00\x08\x04\x04\x04\x04\x04\x04\x04\x04\x00\x00\x01\x82\x00\x08\x04\x04\x04\x04\x04\x04\x04\x04\x00\x00\x01\x8F\x00\x08\x04\x04\x04\x04\x04\x04\x04\x04\x00\x00\x01\x9C\x00\x08\x04\x04\x04\x04\x04\x04\x04\x04\x00\x00\x01\xA9\x00\x08\x04\x04\x04\x04\x04\x04\x04\x04\x00\x00\x01\xB6\x00\x08\x04\x04\x04\x04\x04\x04\x04\x04\x00\x00\x01\xC3\x00\x08\x04\x04\x04\x04\x04\x04\x04\x04\x00\x00\x01\xD0\x00\x08\x04\x04\x04\x04\x04\x04\x04\x04\x00\x00'
    .end code
.end method

.method public static method1006 : (FZ)F
    .code stack 3 locals 2
L0:     iload_1
L1:     ifeq L9
L4:     ldc_w 3.5e-1f
L7:     freturn
L8:     athrow
L9:     ldc_w 8e-2f
L12:    fload_0
L13:    ldc_w 1.7e-1f
L16:    fmul
L17:    fadd
L18:    freturn
L19:    
        .attribute StackMap b'\x00\x02\x00\x08\x00\x00\x00\x01\x07\x00\x28\x00\x09\x00\x02\x02\x01\x00\x00'
    .end code
.end method

.method public static method1007 : (Ljava/lang/String;)J
    .code stack 4 locals 7
L0:     lconst_0
L1:     lstore_1
L2:     aload_0
L3:     ldc_w "\\."
L6:     invokevirtual Method java/lang/String split (Ljava/lang/String;)[Ljava/lang/String;
L9:     dup
L10:    astore_3
L11:    arraylength
L12:    istore 4
L14:    iconst_0
L15:    iconst_1
L16:    dup
L17:    pop2
L18:    dup
L19:    istore 5
L21:    iload 4
L23:    if_icmpge L54
L26:    aload_3
L27:    iload 5
L29:    iinc 5 1
L32:    aaload
L33:    astore 6
L35:    lload_1
L36:    ldc2_w 256L
L39:    lmul
L40:    aload 6
L42:    invokestatic Method java/lang/Integer parseInt (Ljava/lang/String;)I
L45:    i2l
L46:    ladd
L47:    lstore_1
L48:    iload 5
L50:    goto L21
L53:    athrow
L54:    lload_1
L55:    lreturn
L56:    
        .attribute StackMap b'\x00\x03\x00\x15\x00\x05\x07\x00\x4C\x04\x07\x04\x58\x01\x01\x00\x01\x01\x00\x35\x00\x00\x00\x01\x07\x00\x28\x00\x36\x00\x05\x07\x00\x4C\x04\x07\x04\x58\x01\x01\x00\x00'
    .end code
.end method

.method public static method1008 : (Ljava/lang/String;)Ljava/util/List;
    .code stack 7 locals 18
L0:     new java/util/ArrayList
L3:     dup
L4:     iconst_1
L5:     dup
L6:     dup
L7:     pop2
L8:     invokespecial Method java/util/ArrayList <init> (I)V
L11:    astore_1
L12:    aload_0
L13:    ldc_w "."
L16:    new Dc
L19:    aload_1
L20:    dup_x1
L21:    dup
L22:    pop2
L23:    dup
L24:    aload_0
L25:    aconst_null
L26:    invokespecial Method Dc <init> (Ljava/lang/Object;Ljava/lang/Object;)V
L29:    invokeinterface InterfaceMethod java/util/List add (Ljava/lang/Object;)Z 2
L34:    pop
L35:    invokevirtual Method java/lang/String contains (Ljava/lang/CharSequence;)Z
L38:    ifne L44
L41:    aload_1
L42:    areturn
L43:    athrow
L44:    getstatic Field OC field2036 [Ljava/lang/String;
L47:    dup
L48:    astore_2
L49:    arraylength
L50:    istore_3
L51:    iconst_0
L52:    iconst_1
L53:    dup
L54:    pop2
L55:    dup
L56:    istore 4
L58:    iload_3
L59:    if_icmpge L1383
L62:    aload_2
L63:    iload 4
L65:    aaload
L66:    astore 5
L68:    iconst_0
L69:    iconst_1
L70:    dup
L71:    pop2
L72:    dup
L73:    istore 6
L75:    aload_1
L76:    invokeinterface InterfaceMethod java/util/List size ()I 1
L81:    if_icmpge L1375
L84:    aload_1
L85:    iload 6
L87:    invokeinterface InterfaceMethod java/util/List get (I)Ljava/lang/Object; 2
L92:    checkcast Dc
L95:    getfield Field Dc field1794 Ljava/lang/Object;
L98:    ifnonnull L1367
L101:   aload_1
L102:   iload 6
L104:   invokeinterface InterfaceMethod java/util/List get (I)Ljava/lang/Object; 2
L109:   checkcast Dc
L112:   getfield Field Dc field1793 Ljava/lang/Object;
L115:   checkcast java/lang/String
L118:   astore 7
L120:   new java/lang/StringBuilder
L123:   dup
L124:   aload 7
L126:   invokevirtual Method java/lang/String length ()I
L129:   invokespecial Method java/lang/StringBuilder <init> (I)V
L132:   astore 8
L134:   iconst_0
L135:   iconst_1
L136:   dup
L137:   pop2
L138:   dup
L139:   istore 9
L141:   aload 7
L143:   invokevirtual Method java/lang/String length ()I
L146:   if_icmpge L174
L149:   aload 8
L151:   aload 7
L153:   iload 9
L155:   iinc 9 1
L158:   invokevirtual Method java/lang/String codePointAt (I)I
L161:   invokestatic Method java/lang/Character toUpperCase (I)I
L164:   invokevirtual Method java/lang/StringBuilder appendCodePoint (I)Ljava/lang/StringBuilder;
L167:   pop
L168:   iload 9
L170:   goto L141
L173:   athrow
L174:   aload 8
L176:   invokevirtual Method java/lang/StringBuilder toString ()Ljava/lang/String;
L179:   astore 9
L181:   new java/lang/StringBuilder
L184:   aload 9
L186:   dup_x1
L187:   dup
L188:   pop2
L189:   dup
L190:   invokespecial Method java/lang/StringBuilder <init> ()V
L193:   ldc_w "."
L196:   invokevirtual Method java/lang/StringBuilder append (Ljava/lang/String;)Ljava/lang/StringBuilder;
L199:   aload 5
L201:   invokevirtual Method java/lang/StringBuilder append (Ljava/lang/String;)Ljava/lang/StringBuilder;
L204:   invokevirtual Method java/lang/StringBuilder toString ()Ljava/lang/String;
L207:   invokevirtual Method java/lang/String indexOf (Ljava/lang/String;)I
L210:   dup
L211:   istore 8
L213:   iconst_m1
L214:   iconst_1
L215:   dup
L216:   pop2
L217:   if_icmpeq L1367
L220:   iload 8
L222:   istore 10
L224:   iload 8
L226:   aload 5
L228:   invokevirtual Method java/lang/String length ()I
L231:   iadd
L232:   iconst_1
L233:   dup
L234:   dup
L235:   pop2
L236:   iadd
L237:   istore 11
L239:   iconst_1
L240:   dup
L241:   dup
L242:   pop2
L243:   istore 12
L245:   iconst_0
L246:   iconst_1
L247:   dup
L248:   pop2
L249:   istore 13
L251:   iload 11
L253:   aload 7
L255:   invokevirtual Method java/lang/String length ()I
L258:   if_icmpge L305
L261:   getstatic Field OC field2026 Ljava/util/regex/Pattern;
L264:   new java/lang/StringBuilder
L267:   dup
L268:   invokespecial Method java/lang/StringBuilder <init> ()V
L271:   aload 7
L273:   iload 11
L275:   invokevirtual Method java/lang/String charAt (I)C
L278:   invokevirtual Method java/lang/StringBuilder append (C)Ljava/lang/StringBuilder;
L281:   ldc_w ""
L284:   invokevirtual Method java/lang/StringBuilder append (Ljava/lang/String;)Ljava/lang/StringBuilder;
L287:   invokevirtual Method java/lang/StringBuilder toString ()Ljava/lang/String;
L290:   invokevirtual Method java/util/regex/Pattern matcher (Ljava/lang/CharSequence;)Ljava/util/regex/Matcher;
L293:   invokevirtual Method java/util/regex/Matcher matches ()Z
L296:   ifeq L305
L299:   iconst_0
L300:   iconst_1
L301:   dup
L302:   pop2
L303:   istore 12
L305:   iload 12
L307:   ifeq L406
L310:   iload 10
L312:   ifle L349
L315:   getstatic Field OC field2035 Ljava/util/regex/Pattern;
L318:   aload 7
L320:   iload 10
L322:   iconst_1
L323:   dup
L324:   dup
L325:   pop2
L326:   isub
L327:   iload 11
L329:   invokevirtual Method java/lang/String substring (II)Ljava/lang/String;
L332:   invokevirtual Method java/util/regex/Pattern matcher (Ljava/lang/CharSequence;)Ljava/util/regex/Matcher;
L335:   invokevirtual Method java/util/regex/Matcher matches ()Z
L338:   ifeq L349
L341:   iinc 10 -1
L344:   iload 10
L346:   goto L312
L349:   getstatic Field OC field2030 Ljava/util/regex/Pattern;
L352:   aload 7
L354:   iload 10
L356:   iload 11
L358:   invokevirtual Method java/lang/String substring (II)Ljava/lang/String;
L361:   invokevirtual Method java/util/regex/Pattern matcher (Ljava/lang/CharSequence;)Ljava/util/regex/Matcher;
L364:   invokevirtual Method java/util/regex/Matcher matches ()Z
L367:   ifne L406
L370:   getstatic Field OC field2032 Ljava/util/regex/Pattern;
L373:   aload 7
L375:   iload 10
L377:   iload 11
L379:   invokevirtual Method java/lang/String substring (II)Ljava/lang/String;
L382:   invokevirtual Method java/util/regex/Pattern matcher (Ljava/lang/CharSequence;)Ljava/util/regex/Matcher;
L385:   invokevirtual Method java/util/regex/Matcher matches ()Z
L388:   ifeq L400
L391:   iconst_1
L392:   dup
L393:   dup
L394:   pop2
L395:   istore 13
L397:   goto L406
L400:   iconst_0
L401:   iconst_1
L402:   dup
L403:   pop2
L404:   istore 12
L406:   iconst_0
L407:   iconst_1
L408:   dup
L409:   pop2
L410:   istore 14
L412:   iload 12
L414:   ifeq L538
L417:   iload 10
L419:   iconst_4
L420:   iconst_1
L421:   dup
L422:   pop2
L423:   if_icmplt L538
L426:   ldc_w "://"
L429:   aload 7
L431:   iload 10
L433:   iconst_3
L434:   iconst_1
L435:   dup
L436:   pop2
L437:   isub
L438:   iload 10
L440:   invokevirtual Method java/lang/String substring (II)Ljava/lang/String;
L443:   invokevirtual Method java/lang/String equals (Ljava/lang/Object;)Z
L446:   ifeq L538
L449:   iload 10
L451:   iconst_2
L452:   iconst_1
L453:   dup
L454:   pop2
L455:   isub
L456:   dup
L457:   istore 15
L459:   ifle L496
L462:   getstatic Field OC field2039 Ljava/util/regex/Pattern;
L465:   aload 7
L467:   iload 15
L469:   iconst_1
L470:   dup
L471:   dup
L472:   pop2
L473:   isub
L474:   iload 10
L476:   invokevirtual Method java/lang/String substring (II)Ljava/lang/String;
L479:   invokevirtual Method java/util/regex/Pattern matcher (Ljava/lang/CharSequence;)Ljava/util/regex/Matcher;
L482:   invokevirtual Method java/util/regex/Matcher matches ()Z
L485:   ifeq L496
L488:   iinc 15 -1
L491:   iload 15
L493:   goto L459
L496:   getstatic Field OC this Ljava/util/regex/Pattern;
L499:   aload 7
L501:   iload 15
L503:   iload 10
L505:   invokevirtual Method java/lang/String substring (II)Ljava/lang/String;
L508:   invokevirtual Method java/util/regex/Pattern matcher (Ljava/lang/CharSequence;)Ljava/util/regex/Matcher;
L511:   invokevirtual Method java/util/regex/Matcher matches ()Z
L514:   ifeq L538
L517:   iload 15
L519:   istore 10
L521:   iconst_1
L522:   dup
L523:   dup
L524:   pop2
L525:   istore 14
L527:   iload 13
L529:   ifeq L538
L532:   iconst_0
L533:   iconst_1
L534:   dup
L535:   pop2
L536:   istore 12
L538:   iload 12
L540:   ifeq L633
L543:   iload 11
L545:   dup
L546:   istore 15
L548:   aload 7
L550:   invokevirtual Method java/lang/String length ()I
L553:   if_icmpge L590
L556:   getstatic Field OC try Ljava/util/regex/Pattern;
L559:   aload 7
L561:   iload 11
L563:   iload 15
L565:   iconst_1
L566:   dup
L567:   dup
L568:   pop2
L569:   iadd
L570:   invokevirtual Method java/lang/String substring (II)Ljava/lang/String;
L573:   invokevirtual Method java/util/regex/Pattern matcher (Ljava/lang/CharSequence;)Ljava/util/regex/Matcher;
L576:   invokevirtual Method java/util/regex/Matcher matches ()Z
L579:   ifeq L590
L582:   iinc 15 1
L585:   iload 15
L587:   goto L548
L590:   getstatic Field OC field2029 Ljava/util/regex/Pattern;
L593:   aload 7
L595:   iload 11
L597:   iload 15
L599:   invokevirtual Method java/lang/String substring (II)Ljava/lang/String;
L602:   invokevirtual Method java/util/regex/Pattern matcher (Ljava/lang/CharSequence;)Ljava/util/regex/Matcher;
L605:   invokevirtual Method java/util/regex/Matcher matches ()Z
L608:   ifeq L633
L611:   iload 11
L613:   iload 15
L615:   if_icmpeq L629
L618:   iload 13
L620:   ifeq L629
L623:   iconst_0
L624:   iconst_1
L625:   dup
L626:   pop2
L627:   istore 12
L629:   iload 15
L631:   istore 11
L633:   iload 12
L635:   ifeq L850
L638:   iload 13
L640:   ifne L850
L643:   iload 11
L645:   dup
L646:   istore 15
L648:   aload 7
L650:   invokevirtual Method java/lang/String length ()I
L653:   if_icmpge L690
L656:   getstatic Field OC field2038 Ljava/util/regex/Pattern;
L659:   aload 7
L661:   iload 11
L663:   iload 15
L665:   iconst_1
L666:   dup
L667:   dup
L668:   pop2
L669:   iadd
L670:   invokevirtual Method java/lang/String substring (II)Ljava/lang/String;
L673:   invokevirtual Method java/util/regex/Pattern matcher (Ljava/lang/CharSequence;)Ljava/util/regex/Matcher;
L676:   invokevirtual Method java/util/regex/Matcher matches ()Z
L679:   ifeq L690
L682:   iinc 15 1
L685:   iload 15
L687:   goto L648
L690:   getstatic Field OC field2031 Ljava/util/regex/Pattern;
L693:   new java/lang/StringBuilder
L696:   dup
L697:   invokespecial Method java/lang/StringBuilder <init> ()V
L700:   aload 7
L702:   iload 15
L704:   iconst_1
L705:   dup
L706:   dup
L707:   pop2
L708:   isub
L709:   invokevirtual Method java/lang/String charAt (I)C
L712:   invokevirtual Method java/lang/StringBuilder append (C)Ljava/lang/StringBuilder;
L715:   ldc_w ""
L718:   invokevirtual Method java/lang/StringBuilder append (Ljava/lang/String;)Ljava/lang/StringBuilder;
L721:   invokevirtual Method java/lang/StringBuilder toString ()Ljava/lang/String;
L724:   invokevirtual Method java/util/regex/Pattern matcher (Ljava/lang/CharSequence;)Ljava/util/regex/Matcher;
L727:   invokevirtual Method java/util/regex/Matcher matches ()Z
L730:   ifeq L736
L733:   iinc 15 -1
L736:   iload 10
L738:   ifle L846
L741:   iload 15
L743:   iconst_1
L744:   dup
L745:   dup
L746:   pop2
L747:   isub
L748:   aload 7
L750:   invokevirtual Method java/lang/String length ()I
L753:   if_icmpge L846
L756:   aload 7
L758:   dup
L759:   iload 10
L761:   iconst_1
L762:   dup
L763:   dup
L764:   pop2
L765:   isub
L766:   invokevirtual Method java/lang/String charAt (I)C
L769:   istore 16
L771:   iload 15
L773:   iconst_1
L774:   dup
L775:   dup
L776:   pop2
L777:   isub
L778:   invokevirtual Method java/lang/String charAt (I)C
L781:   istore 17
L783:   iload 16
L785:   bipush 40
L787:   iconst_1
L788:   dup
L789:   pop2
L790:   if_icmpne L803
L793:   iload 17
L795:   bipush 41
L797:   iconst_1
L798:   dup
L799:   pop2
L800:   if_icmpeq L843
L803:   iload 16
L805:   bipush 91
L807:   iconst_1
L808:   dup
L809:   pop2
L810:   if_icmpne L823
L813:   iload 17
L815:   bipush 93
L817:   iconst_1
L818:   dup
L819:   pop2
L820:   if_icmpeq L843
L823:   iload 16
L825:   bipush 123
L827:   iconst_1
L828:   dup
L829:   pop2
L830:   if_icmpne L846
L833:   iload 17
L835:   bipush 125
L837:   iconst_1
L838:   dup
L839:   pop2
L840:   if_icmpne L846
L843:   iinc 15 -1
L846:   iload 15
L848:   istore 11
L850:   iload 12
L852:   ifeq L1327
L855:   aload 7
L857:   dup
L858:   dup_x1
L859:   iconst_0
L860:   iconst_1
L861:   dup
L862:   pop2
L863:   iload 10
L865:   invokevirtual Method java/lang/String substring (II)Ljava/lang/String;
L868:   astore 15
L870:   iload 10
L872:   iload 11
L874:   invokevirtual Method java/lang/String substring (II)Ljava/lang/String;
L877:   astore 16
L879:   iload 11
L881:   invokevirtual Method java/lang/String substring (I)Ljava/lang/String;
L884:   astore 17
L886:   iload 14
L888:   ifne L911
L891:   aload 16
L893:   invokevirtual Method java/lang/String toLowerCase ()Ljava/lang/String;
L896:   ldc_w "mailto:"
L899:   invokevirtual Method java/lang/String startsWith (Ljava/lang/String;)Z
L902:   ifeq L911
L905:   iconst_0
L906:   iconst_1
L907:   dup
L908:   pop2
L909:   istore 12
L911:   iload 12
L913:   ifeq L974
L916:   iload 13
L918:   ifne L974
        .catch java/net/MalformedURLException from L921 to L961 using L966
        .catch java/lang/Exception from L0 to L42 using L1385
        .catch java/lang/Exception from L44 to L173 using L1385
        .catch java/lang/Exception from L174 to L1384 using L1385
L921:   new java/net/URL
L924:   dup
L925:   iload 14
L927:   ifeq L935
L930:   aload 16
L932:   goto L957
L935:   new java/lang/StringBuilder
L938:   dup
L939:   invokespecial Method java/lang/StringBuilder <init> ()V
L942:   iconst_0
L943:   ldc_w "http://"
L946:   invokevirtual Method java/lang/StringBuilder insert (ILjava/lang/String;)Ljava/lang/StringBuilder;
L949:   aload 16
L951:   invokevirtual Method java/lang/StringBuilder append (Ljava/lang/String;)Ljava/lang/StringBuilder;
L954:   invokevirtual Method java/lang/StringBuilder toString ()Ljava/lang/String;
L957:   invokespecial Method java/net/URL <init> (Ljava/lang/String;)V
L960:   pop
L961:   iload 12
L963:   goto L976
L966:   astore 10
L968:   iconst_0
L969:   iconst_1
L970:   dup
L971:   pop2
L972:   istore 12
L974:   iload 12
L976:   ifeq L1327
L979:   aload_1
L980:   iload 6
L982:   invokeinterface InterfaceMethod java/util/List get (I)Ljava/lang/Object; 2
L987:   checkcast Dc
L990:   aload 16
L992:   putfield Field Dc field1793 Ljava/lang/Object;
L995:   iload 13
L997:   aload_1
L998:   swap
L999:   ifeq L1042
L1002:  iload 6
L1004:  invokeinterface InterfaceMethod java/util/List get (I)Ljava/lang/Object; 2
L1009:  checkcast Dc
L1012:  new java/lang/StringBuilder
L1015:  dup
L1016:  invokespecial Method java/lang/StringBuilder <init> ()V
L1019:  iconst_0
L1020:  ldc_w "mailto:"
L1023:  invokevirtual Method java/lang/StringBuilder insert (ILjava/lang/String;)Ljava/lang/StringBuilder;
L1026:  aload 16
L1028:  invokevirtual Method java/lang/StringBuilder append (Ljava/lang/String;)Ljava/lang/StringBuilder;
L1031:  invokevirtual Method java/lang/StringBuilder toString ()Ljava/lang/String;
L1034:  putfield Field Dc field1794 Ljava/lang/Object;
L1037:  aload 17
L1039:  goto L1089
L1042:  iload 6
L1044:  invokeinterface InterfaceMethod java/util/List get (I)Ljava/lang/Object; 2
L1049:  checkcast Dc
L1052:  iload 14
L1054:  ifeq L1062
L1057:  aload 16
L1059:  goto L1084
L1062:  new java/lang/StringBuilder
L1065:  dup
L1066:  invokespecial Method java/lang/StringBuilder <init> ()V
L1069:  iconst_0
L1070:  ldc_w "http://"
L1073:  invokevirtual Method java/lang/StringBuilder insert (ILjava/lang/String;)Ljava/lang/StringBuilder;
L1076:  aload 16
L1078:  invokevirtual Method java/lang/StringBuilder append (Ljava/lang/String;)Ljava/lang/StringBuilder;
L1081:  invokevirtual Method java/lang/StringBuilder toString ()Ljava/lang/String;
L1084:  putfield Field Dc field1794 Ljava/lang/Object;
L1087:  aload 17
L1089:  invokevirtual Method java/lang/String length ()I
L1092:  ifle L1221
L1095:  iload 6
L1097:  aload_1
L1098:  invokeinterface InterfaceMethod java/util/List size ()I 1
L1103:  iconst_1
L1104:  dup
L1105:  dup
L1106:  pop2
L1107:  isub
L1108:  if_icmpeq L1133
L1111:  aload_1
L1112:  iload 6
L1114:  iconst_1
L1115:  dup
L1116:  dup
L1117:  pop2
L1118:  iadd
L1119:  invokeinterface InterfaceMethod java/util/List get (I)Ljava/lang/Object; 2
L1124:  checkcast Dc
L1127:  getfield Field Dc field1794 Ljava/lang/Object;
L1130:  ifnull L1161
L1133:  aload_1
L1134:  iload 6
L1136:  iconst_1
L1137:  dup
L1138:  dup
L1139:  pop2
L1140:  iadd
L1141:  new Dc
L1144:  dup
L1145:  aload 17
L1147:  aconst_null
L1148:  invokespecial Method Dc <init> (Ljava/lang/Object;Ljava/lang/Object;)V
L1151:  invokeinterface InterfaceMethod java/util/List add (ILjava/lang/Object;)V 3
L1156:  aload 15
L1158:  goto L1223
L1161:  aload_1
L1162:  iload 6
L1164:  iconst_1
L1165:  dup
L1166:  dup
L1167:  pop2
L1168:  iadd
L1169:  invokeinterface InterfaceMethod java/util/List get (I)Ljava/lang/Object; 2
L1174:  checkcast Dc
L1177:  new java/lang/StringBuilder
L1180:  dup
L1181:  invokespecial Method java/lang/StringBuilder <init> ()V
L1184:  iconst_0
L1185:  aload 17
L1187:  invokevirtual Method java/lang/StringBuilder insert (ILjava/lang/String;)Ljava/lang/StringBuilder;
L1190:  aload_1
L1191:  iload 6
L1193:  iconst_1
L1194:  dup
L1195:  dup
L1196:  pop2
L1197:  iadd
L1198:  invokeinterface InterfaceMethod java/util/List get (I)Ljava/lang/Object; 2
L1203:  checkcast Dc
L1206:  getfield Field Dc field1793 Ljava/lang/Object;
L1209:  checkcast java/lang/String
L1212:  invokevirtual Method java/lang/StringBuilder append (Ljava/lang/String;)Ljava/lang/StringBuilder;
L1215:  invokevirtual Method java/lang/StringBuilder toString ()Ljava/lang/String;
L1218:  putfield Field Dc field1793 Ljava/lang/Object;
L1221:  aload 15
L1223:  invokevirtual Method java/lang/String length ()I
L1226:  ifle L1321
L1229:  iload 6
L1231:  ifeq L1256
L1234:  aload_1
L1235:  iload 6
L1237:  iconst_1
L1238:  dup
L1239:  dup
L1240:  pop2
L1241:  isub
L1242:  invokeinterface InterfaceMethod java/util/List get (I)Ljava/lang/Object; 2
L1247:  checkcast Dc
L1250:  getfield Field Dc field1794 Ljava/lang/Object;
L1253:  ifnull L1280
L1256:  aload_1
L1257:  new Dc
L1260:  iload 6
L1262:  dup_x1
L1263:  dup
L1264:  pop2
L1265:  dup
L1266:  aload 15
L1268:  aconst_null
L1269:  invokespecial Method Dc <init> (Ljava/lang/Object;Ljava/lang/Object;)V
L1272:  invokeinterface InterfaceMethod java/util/List add (ILjava/lang/Object;)V 3
L1277:  goto L1321
L1280:  new java/lang/StringBuilder
L1283:  dup
L1284:  invokespecial Method java/lang/StringBuilder <init> ()V
L1287:  aload_1
L1288:  iload 6
L1290:  iconst_1
L1291:  dup
L1292:  dup
L1293:  pop2
L1294:  isub
L1295:  invokeinterface InterfaceMethod java/util/List get (I)Ljava/lang/Object; 2
L1300:  checkcast Dc
L1303:  dup_x1
L1304:  getfield Field Dc field1793 Ljava/lang/Object;
L1307:  invokevirtual Method java/lang/StringBuilder append (Ljava/lang/Object;)Ljava/lang/StringBuilder;
L1310:  aload 15
L1312:  invokevirtual Method java/lang/StringBuilder append (Ljava/lang/String;)Ljava/lang/StringBuilder;
L1315:  invokevirtual Method java/lang/StringBuilder toString ()Ljava/lang/String;
L1318:  putfield Field Dc field1793 Ljava/lang/Object;
L1321:  iinc 6 -1
L1324:  goto L1367
L1327:  aload 9
L1329:  new java/lang/StringBuilder
L1332:  dup
L1333:  invokespecial Method java/lang/StringBuilder <init> ()V
L1336:  iconst_0
L1337:  ldc_w "."
L1340:  invokevirtual Method java/lang/StringBuilder insert (ILjava/lang/String;)Ljava/lang/StringBuilder;
L1343:  aload 5
L1345:  invokevirtual Method java/lang/StringBuilder append (Ljava/lang/String;)Ljava/lang/StringBuilder;
L1348:  invokevirtual Method java/lang/StringBuilder toString ()Ljava/lang/String;
L1351:  iload 8
L1353:  iconst_1
L1354:  dup
L1355:  dup
L1356:  pop2
L1357:  iadd
L1358:  invokevirtual Method java/lang/String indexOf (Ljava/lang/String;I)I
L1361:  dup
L1362:  istore 8
L1364:  goto L213
L1367:  iinc 6 1
L1370:  iload 6
L1372:  goto L75
L1375:  iinc 4 1
L1378:  iload 4
L1380:  goto L58
L1383:  aload_1
L1384:  areturn
L1385:  astore_1
L1386:  new java/lang/RuntimeException
L1389:  dup
L1390:  aload_0
L1391:  aload_1
L1392:  invokespecial Method java/lang/RuntimeException <init> (Ljava/lang/String;Ljava/lang/Throwable;)V
L1395:  athrow
L1396:  
        .attribute StackMap b'\x00\x32\x00\x2B\x00\x00\x00\x01\x07\x00\x28\x00\x2C\x00\x02\x07\x00\x4C\x07\x00\x65\x00\x00\x00\x3A\x00\x05\x07\x00\x4C\x07\x00\x65\x07\x04\x58\x01\x01\x00\x01\x01\x00\x4B\x00\x07\x07\x00\x4C\x07\x00\x65\x07\x04\x58\x01\x01\x07\x00\x4C\x01\x00\x01\x01\x00\x8D\x00\x0A\x07\x00\x4C\x07\x00\x65\x07\x04\x58\x01\x01\x07\x00\x4C\x01\x07\x00\x4C\x07\x00\x2E\x01\x00\x01\x01\x00\xAD\x00\x00\x00\x01\x07\x00\x28\x00\xAE\x00\x0A\x07\x00\x4C\x07\x00\x65\x07\x04\x58\x01\x01\x07\x00\x4C\x01\x07\x00\x4C\x07\x00\x2E\x01\x00\x00\x00\xD5\x00\x0A\x07\x00\x4C\x07\x00\x65\x07\x04\x58\x01\x01\x07\x00\x4C\x01\x07\x00\x4C\x01\x07\x00\x4C\x00\x01\x01\x01\x31\x00\x0E\x07\x00\x4C\x07\x00\x65\x07\x04\x58\x01\x01\x07\x00\x4C\x01\x07\x00\x4C\x01\x07\x00\x4C\x01\x01\x01\x01\x00\x00\x01\x38\x00\x0E\x07\x00\x4C\x07\x00\x65\x07\x04\x58\x01\x01\x07\x00\x4C\x01\x07\x00\x4C\x01\x07\x00\x4C\x01\x01\x01\x01\x00\x01\x01\x01\x5D\x00\x0E\x07\x00\x4C\x07\x00\x65\x07\x04\x58\x01\x01\x07\x00\x4C\x01\x07\x00\x4C\x01\x07\x00\x4C\x01\x01\x01\x01\x00\x00\x01\x90\x00\x0E\x07\x00\x4C\x07\x00\x65\x07\x04\x58\x01\x01\x07\x00\x4C\x01\x07\x00\x4C\x01\x07\x00\x4C\x01\x01\x01\x01\x00\x00\x01\x96\x00\x0E\x07\x00\x4C\x07\x00\x65\x07\x04\x58\x01\x01\x07\x00\x4C\x01\x07\x00\x4C\x01\x07\x00\x4C\x01\x01\x01\x01\x00\x00\x01\xCB\x00\x10\x07\x00\x4C\x07\x00\x65\x07\x04\x58\x01\x01\x07\x00\x4C\x01\x07\x00\x4C\x01\x07\x00\x4C\x01\x01\x01\x01\x01\x01\x00\x01\x01\x01\xF0\x00\x10\x07\x00\x4C\x07\x00\x65\x07\x04\x58\x01\x01\x07\x00\x4C\x01\x07\x00\x4C\x01\x07\x00\x4C\x01\x01\x01\x01\x01\x01\x00\x00\x02\x1A\x00\x0F\x07\x00\x4C\x07\x00\x65\x07\x04\x58\x01\x01\x07\x00\x4C\x01\x07\x00\x4C\x01\x07\x00\x4C\x01\x01\x01\x01\x01\x00\x00\x02\x24\x00\x10\x07\x00\x4C\x07\x00\x65\x07\x04\x58\x01\x01\x07\x00\x4C\x01\x07\x00\x4C\x01\x07\x00\x4C\x01\x01\x01\x01\x01\x01\x00\x01\x01\x02\x4E\x00\x10\x07\x00\x4C\x07\x00\x65\x07\x04\x58\x01\x01\x07\x00\x4C\x01\x07\x00\x4C\x01\x07\x00\x4C\x01\x01\x01\x01\x01\x01\x00\x00\x02\x75\x00\x10\x07\x00\x4C\x07\x00\x65\x07\x04\x58\x01\x01\x07\x00\x4C\x01\x07\x00\x4C\x01\x07\x00\x4C\x01\x01\x01\x01\x01\x01\x00\x00\x02\x79\x00\x0F\x07\x00\x4C\x07\x00\x65\x07\x04\x58\x01\x01\x07\x00\x4C\x01\x07\x00\x4C\x01\x07\x00\x4C\x01\x01\x01\x01\x01\x00\x00\x02\x88\x00\x10\x07\x00\x4C\x07\x00\x65\x07\x04\x58\x01\x01\x07\x00\x4C\x01\x07\x00\x4C\x01\x07\x00\x4C\x01\x01\x01\x01\x01\x01\x00\x01\x01\x02\xB2\x00\x10\x07\x00\x4C\x07\x00\x65\x07\x04\x58\x01\x01\x07\x00\x4C\x01\x07\x00\x4C\x01\x07\x00\x4C\x01\x01\x01\x01\x01\x01\x00\x00\x02\xE0\x00\x10\x07\x00\x4C\x07\x00\x65\x07\x04\x58\x01\x01\x07\x00\x4C\x01\x07\x00\x4C\x01\x07\x00\x4C\x01\x01\x01\x01\x01\x01\x00\x00\x03\x23\x00\x12\x07\x00\x4C\x07\x00\x65\x07\x04\x58\x01\x01\x07\x00\x4C\x01\x07\x00\x4C\x01\x07\x00\x4C\x01\x01\x01\x01\x01\x01\x01\x01\x00\x00\x03\x37\x00\x12\x07\x00\x4C\x07\x00\x65\x07\x04\x58\x01\x01\x07\x00\x4C\x01\x07\x00\x4C\x01\x07\x00\x4C\x01\x01\x01\x01\x01\x01\x01\x01\x00\x00\x03\x4B\x00\x12\x07\x00\x4C\x07\x00\x65\x07\x04\x58\x01\x01\x07\x00\x4C\x01\x07\x00\x4C\x01\x07\x00\x4C\x01\x01\x01\x01\x01\x01\x01\x01\x00\x00\x03\x4E\x00\x10\x07\x00\x4C\x07\x00\x65\x07\x04\x58\x01\x01\x07\x00\x4C\x01\x07\x00\x4C\x01\x07\x00\x4C\x01\x01\x01\x01\x01\x01\x00\x00\x03\x52\x00\x0F\x07\x00\x4C\x07\x00\x65\x07\x04\x58\x01\x01\x07\x00\x4C\x01\x07\x00\x4C\x01\x07\x00\x4C\x01\x01\x01\x01\x01\x00\x00\x03\x8F\x00\x12\x07\x00\x4C\x07\x00\x65\x07\x04\x58\x01\x01\x07\x00\x4C\x01\x07\x00\x4C\x01\x07\x00\x4C\x01\x01\x01\x01\x01\x07\x00\x4C\x07\x00\x4C\x07\x00\x4C\x00\x00\x03\xA7\x00\x12\x07\x00\x4C\x07\x00\x65\x07\x04\x58\x01\x01\x07\x00\x4C\x01\x07\x00\x4C\x01\x07\x00\x4C\x01\x01\x01\x01\x01\x07\x00\x4C\x07\x00\x4C\x07\x00\x4C\x00\x02\x08\x03\x99\x08\x03\x99\x03\xBD\x00\x12\x07\x00\x4C\x07\x00\x65\x07\x04\x58\x01\x01\x07\x00\x4C\x01\x07\x00\x4C\x01\x07\x00\x4C\x01\x01\x01\x01\x01\x07\x00\x4C\x07\x00\x4C\x07\x00\x4C\x00\x03\x08\x03\x99\x08\x03\x99\x07\x00\x4C\x03\xC6\x00\x12\x07\x00\x4C\x07\x00\x65\x07\x04\x58\x01\x01\x07\x00\x4C\x01\x07\x00\x4C\x01\x07\x00\x4C\x01\x01\x01\x01\x01\x07\x00\x4C\x07\x00\x4C\x07\x00\x4C\x00\x01\x07\x03\x63\x03\xCE\x00\x12\x07\x00\x4C\x07\x00\x65\x07\x04\x58\x01\x01\x07\x00\x4C\x01\x07\x00\x4C\x01\x07\x00\x4C\x00\x01\x01\x01\x01\x07\x00\x4C\x07\x00\x4C\x07\x00\x4C\x00\x00\x03\xD0\x00\x12\x07\x00\x4C\x07\x00\x65\x07\x04\x58\x01\x01\x07\x00\x4C\x01\x07\x00\x4C\x01\x07\x00\x4C\x00\x01\x01\x01\x01\x07\x00\x4C\x07\x00\x4C\x07\x00\x4C\x00\x01\x01\x04\x12\x00\x12\x07\x00\x4C\x07\x00\x65\x07\x04\x58\x01\x01\x07\x00\x4C\x01\x07\x00\x4C\x01\x07\x00\x4C\x00\x01\x01\x01\x01\x07\x00\x4C\x07\x00\x4C\x07\x00\x4C\x00\x01\x07\x00\x65\x04\x26\x00\x12\x07\x00\x4C\x07\x00\x65\x07\x04\x58\x01\x01\x07\x00\x4C\x01\x07\x00\x4C\x01\x07\x00\x4C\x00\x01\x01\x01\x01\x07\x00\x4C\x07\x00\x4C\x07\x00\x4C\x00\x01\x07\x04\x64\x04\x3C\x00\x12\x07\x00\x4C\x07\x00\x65\x07\x04\x58\x01\x01\x07\x00\x4C\x01\x07\x00\x4C\x01\x07\x00\x4C\x00\x01\x01\x01\x01\x07\x00\x4C\x07\x00\x4C\x07\x00\x4C\x00\x02\x07\x04\x64\x07\x00\x4C\x04\x41\x00\x12\x07\x00\x4C\x07\x00\x65\x07\x04\x58\x01\x01\x07\x00\x4C\x01\x07\x00\x4C\x01\x07\x00\x4C\x00\x01\x01\x01\x01\x07\x00\x4C\x07\x00\x4C\x07\x00\x4C\x00\x01\x07\x00\x4C\x04\x6D\x00\x12\x07\x00\x4C\x07\x00\x65\x07\x04\x58\x01\x01\x07\x00\x4C\x01\x07\x00\x4C\x01\x07\x00\x4C\x00\x01\x01\x01\x01\x07\x00\x4C\x07\x00\x4C\x07\x00\x4C\x00\x00\x04\x89\x00\x12\x07\x00\x4C\x07\x00\x65\x07\x04\x58\x01\x01\x07\x00\x4C\x01\x07\x00\x4C\x01\x07\x00\x4C\x00\x01\x01\x01\x01\x07\x00\x4C\x07\x00\x4C\x07\x00\x4C\x00\x00\x04\xC5\x00\x12\x07\x00\x4C\x07\x00\x65\x07\x04\x58\x01\x01\x07\x00\x4C\x01\x07\x00\x4C\x01\x07\x00\x4C\x00\x01\x01\x01\x01\x07\x00\x4C\x07\x00\x4C\x07\x00\x4C\x00\x00\x04\xC7\x00\x12\x07\x00\x4C\x07\x00\x65\x07\x04\x58\x01\x01\x07\x00\x4C\x01\x07\x00\x4C\x01\x07\x00\x4C\x00\x01\x01\x01\x01\x07\x00\x4C\x07\x00\x4C\x07\x00\x4C\x00\x01\x07\x00\x4C\x04\xE8\x00\x12\x07\x00\x4C\x07\x00\x65\x07\x04\x58\x01\x01\x07\x00\x4C\x01\x07\x00\x4C\x01\x07\x00\x4C\x00\x01\x01\x01\x01\x07\x00\x4C\x07\x00\x4C\x07\x00\x4C\x00\x00\x05\x00\x00\x12\x07\x00\x4C\x07\x00\x65\x07\x04\x58\x01\x01\x07\x00\x4C\x01\x07\x00\x4C\x01\x07\x00\x4C\x00\x01\x01\x01\x01\x07\x00\x4C\x07\x00\x4C\x07\x00\x4C\x00\x00\x05\x29\x00\x12\x07\x00\x4C\x07\x00\x65\x07\x04\x58\x01\x01\x07\x00\x4C\x01\x07\x00\x4C\x01\x07\x00\x4C\x00\x01\x01\x01\x01\x07\x00\x4C\x07\x00\x4C\x07\x00\x4C\x00\x00\x05\x2F\x00\x0F\x07\x00\x4C\x07\x00\x65\x07\x04\x58\x01\x01\x07\x00\x4C\x01\x07\x00\x4C\x01\x07\x00\x4C\x00\x01\x01\x01\x01\x00\x00\x05\x57\x00\x07\x07\x00\x4C\x07\x00\x65\x07\x04\x58\x01\x01\x07\x00\x4C\x01\x00\x00\x05\x5F\x00\x07\x07\x00\x4C\x07\x00\x65\x07\x04\x58\x01\x01\x07\x00\x4C\x01\x00\x00\x05\x67\x00\x05\x07\x00\x4C\x07\x00\x65\x07\x04\x58\x01\x01\x00\x00\x05\x69\x00\x01\x07\x00\x4C\x00\x01\x07\x03\x01'
    .end code
.end method

.method public static method1009 : (I)Ljava/lang/String;
    .code stack 6 locals 4
L0:     new java/lang/StringBuilder
L3:     dup
L4:     iload_0
L5:     invokespecial Method java/lang/StringBuilder <init> (I)V
L8:     astore_1
L9:     new java/util/Random
L12:    dup
L13:    invokespecial Method java/util/Random <init> ()V
L16:    astore_2
L17:    iconst_0
L18:    iconst_1
L19:    dup
L20:    pop2
L21:    dup
L22:    istore_3
L23:    iload_0
L24:    if_icmpge L55
L27:    aload_1
L28:    ldc_w "0123456789abcdef"
L31:    aload_2
L32:    bipush 16
L34:    iconst_1
L35:    dup
L36:    pop2
L37:    iinc 3 1
L40:    invokevirtual Method java/util/Random nextInt (I)I
L43:    invokevirtual Method java/lang/String charAt (I)C
L46:    invokevirtual Method java/lang/StringBuilder append (C)Ljava/lang/StringBuilder;
L49:    pop
L50:    iload_3
L51:    goto L23
L54:    athrow
L55:    aload_1
L56:    invokevirtual Method java/lang/StringBuilder toString ()Ljava/lang/String;
L59:    areturn
L60:    
        .attribute StackMap b'\x00\x03\x00\x17\x00\x04\x01\x07\x00\x2E\x07\x03\xB3\x01\x00\x01\x01\x00\x36\x00\x00\x00\x01\x07\x00\x28\x00\x37\x00\x04\x01\x07\x00\x2E\x07\x03\xB3\x01\x00\x00'
    .end code
.end method

.method public <init> : ()V
    .code stack 1 locals 1
L0:     aload_0
L1:     invokespecial Method java/lang/Object <init> ()V
L4:     return
L5:     
    .end code
.end method

.method public static method1010 : ([B)Ljava/lang/String;
    .code stack 9 locals 4
L0:     getstatic Field OC field2027 Ljava/lang/Object;
L3:     dup
L4:     astore_1
L5:     monitorenter
        .catch java/lang/Exception from L6 to L61 using L65
        .catch [0] from L6 to L63 using L75
L6:     getstatic Field OC field2033 Ljava/security/MessageDigest;
L9:     ifnonnull L21
L12:    ldc_w "MD5"
L15:    invokestatic Method java/security/MessageDigest getInstance (Ljava/lang/String;)Ljava/security/MessageDigest;
L18:    putstatic Field OC field2033 Ljava/security/MessageDigest;
L21:    ldc_w "%1$032x"
L24:    iconst_1
L25:    dup
L26:    dup
L27:    pop2
L28:    anewarray java/lang/Object
L31:    iconst_1
L32:    dup
L33:    pop2
L34:    dup
L35:    iconst_0
L36:    iconst_1
L37:    dup
L38:    pop2
L39:    new java/math/BigInteger
L42:    dup
L43:    iconst_1
L44:    dup
L45:    dup
L46:    pop2
L47:    getstatic Field OC field2033 Ljava/security/MessageDigest;
L50:    aload_0
L51:    invokevirtual Method java/security/MessageDigest digest ([B)[B
L54:    invokespecial Method java/math/BigInteger <init> (I[B)V
L57:    aastore
L58:    invokestatic Method java/lang/String format (Ljava/lang/String;[Ljava/lang/Object;)Ljava/lang/String;
L61:    aload_1
L62:    monitorexit
L63:    areturn
L64:    athrow
        .catch [0] from L65 to L73 using L75
L65:    astore_2
L66:    aconst_null
L67:    aload_2
L68:    invokevirtual Method java/lang/Exception printStackTrace ()V
L71:    aload_1
L72:    monitorexit
L73:    areturn
L74:    athrow
        .catch [0] from L75 to L78 using L75
L75:    astore_3
L76:    aload_1
L77:    monitorexit
L78:    aload_3
L79:    athrow
L80:    
        .attribute StackMap b'\x00\x05\x00\x15\x00\x02\x07\x00\x50\x07\x00\x04\x00\x00\x00\x40\x00\x00\x00\x01\x07\x00\x28\x00\x41\x00\x02\x07\x00\x50\x07\x00\x04\x00\x01\x07\x03\x01\x00\x4A\x00\x00\x00\x01\x07\x00\x28\x00\x4B\x00\x02\x07\x00\x50\x07\x00\x04\x00\x01\x07\x00\x28'
    .end code
.end method

.method public static method1011 : (FFF)F
    .code stack 3 locals 3
L0:     fload_1
L1:     fconst_1
L2:     fload_0
L3:     fsub
L4:     fmul
L5:     fload_2
L6:     fload_0
L7:     fmul
L8:     fadd
L9:     freturn
L10:    
    .end code
.end method

.method public static method1012 : ([[I)[[I
    .code stack 4 locals 3
L0:     aload_0
L1:     arraylength
L2:     anewarray [I
L5:     iconst_1
L6:     dup
L7:     pop2
L8:     astore_1
L9:     iconst_0
L10:    iconst_1
L11:    dup
L12:    pop2
L13:    dup
L14:    istore_2
L15:    aload_0
L16:    arraylength
L17:    if_icmpge L37
L20:    aload_1
L21:    aload_0
L22:    iload_2
L23:    dup_x1
L24:    aaload
L25:    invokestatic Method OC method1013 ([I)[I
L28:    iinc 2 1
L31:    aastore
L32:    iload_2
L33:    goto L15
L36:    athrow
L37:    aload_1
L38:    areturn
L39:    
        .attribute StackMap b'\x00\x03\x00\x0F\x00\x03\x07\x04\xDA\x07\x04\xDA\x01\x00\x01\x01\x00\x24\x00\x00\x00\x01\x07\x00\x28\x00\x25\x00\x03\x07\x04\xDA\x07\x04\xDA\x01\x00\x00'
    .end code
.end method

.method public static method1013 : ([I)[I
    .code stack 6 locals 2
L0:     aload_0
L1:     arraylength
L2:     newarray int
L4:     iconst_1
L5:     dup
L6:     pop2
L7:     astore_1
L8:     aload_0
L9:     iconst_1
L10:    dup
L11:    pop2
L12:    aload_1
L13:    iconst_0
L14:    dup_x1
L15:    iconst_1
L16:    dup
L17:    pop2
L18:    aload_0
L19:    arraylength
L20:    invokestatic Method java/lang/System arraycopy (Ljava/lang/Object;ILjava/lang/Object;II)V
L23:    aload_1
L24:    areturn
L25:    
    .end code
.end method

.method public static method1014 : (I)I
    .code stack 4 locals 2
L0:     iconst_1
L1:     dup
L2:     dup
L3:     pop2
L4:     dup
L5:     istore_1
L6:     iload_0
L7:     if_icmpge L22
L10:    iload_1
L11:    iconst_1
L12:    dup
L13:    dup
L14:    pop2
L15:    ishl
L16:    dup
L17:    istore_1
L18:    goto L6
L21:    athrow
L22:    iload_1
L23:    ireturn
L24:    
        .attribute StackMap b'\x00\x03\x00\x06\x00\x02\x01\x01\x00\x01\x01\x00\x15\x00\x00\x00\x01\x07\x00\x28\x00\x16\x00\x02\x01\x01\x00\x00'
    .end code
.end method

.method public static method1015 : ()D
    .code stack 6 locals 2
L0:     invokestatic Method java/lang/System currentTimeMillis ()J
L3:     getstatic Field OC field2028 J
L6:     lsub
L7:     l2d
L8:     ldc2_w 1e3
L11:    ddiv
L12:    getstatic Field OC field2034 D
L15:    dadd
L16:    dstore_0
L17:    getstatic Field OC field2037 D
L20:    dload_0
L21:    dcmpl
L22:    ifle L78
L25:    getstatic Field java/lang/System out Ljava/io/PrintStream;
L28:    new java/lang/StringBuilder
L31:    dup
L32:    invokespecial Method java/lang/StringBuilder <init> ()V
L35:    iconst_0
L36:    ldc_w "Flux capacitor engaged! DeLorean went "
L39:    invokevirtual Method java/lang/StringBuilder insert (ILjava/lang/String;)Ljava/lang/StringBuilder;
L42:    getstatic Field OC field2037 D
L45:    dload_0
L46:    dsub
L47:    invokevirtual Method java/lang/StringBuilder append (D)Ljava/lang/StringBuilder;
L50:    ldc_w " backwards."
L53:    invokevirtual Method java/lang/StringBuilder append (Ljava/lang/String;)Ljava/lang/StringBuilder;
L56:    invokevirtual Method java/lang/StringBuilder toString ()Ljava/lang/String;
L59:    invokevirtual Method java/io/PrintStream println (Ljava/lang/String;)V
L62:    getstatic Field OC field2034 D
L65:    getstatic Field OC field2037 D
L68:    dload_0
L69:    dsub
L70:    dadd
L71:    putstatic Field OC field2034 D
L74:    getstatic Field OC field2037 D
L77:    dstore_0
L78:    dload_0
L79:    getstatic Field OC field2037 D
L82:    dconst_1
L83:    dadd
L84:    dcmpl
L85:    ifle L147
L88:    getstatic Field java/lang/System out Ljava/io/PrintStream;
L91:    new java/lang/StringBuilder
L94:    dup
L95:    invokespecial Method java/lang/StringBuilder <init> ()V
L98:    iconst_0
L99:    ldc_w "Flux capacitor engaged! DeLorean went "
L102:   invokevirtual Method java/lang/StringBuilder insert (ILjava/lang/String;)Ljava/lang/StringBuilder;
L105:   dload_0
L106:   getstatic Field OC field2037 D
L109:   dsub
L110:   invokevirtual Method java/lang/StringBuilder append (D)Ljava/lang/StringBuilder;
L113:   ldc_w " forwards."
L116:   invokevirtual Method java/lang/StringBuilder append (Ljava/lang/String;)Ljava/lang/StringBuilder;
L119:   invokevirtual Method java/lang/StringBuilder toString ()Ljava/lang/String;
L122:   invokevirtual Method java/io/PrintStream println (Ljava/lang/String;)V
L125:   getstatic Field OC new Z
L128:   ifeq L147
L131:   getstatic Field OC field2034 D
L134:   dload_0
L135:   getstatic Field OC field2037 D
L138:   dsub
L139:   dsub
L140:   putstatic Field OC field2034 D
L143:   getstatic Field OC field2037 D
L146:   dstore_0
L147:   dload_0
L148:   putstatic Field OC field2037 D
L151:   dload_0
L152:   dreturn
L153:   
        .attribute StackMap b'\x00\x02\x00\x4E\x00\x01\x03\x00\x00\x00\x93\x00\x01\x03\x00\x00'
    .end code
.end method

.method public static method1016 : ()J
    .code stack 6 locals 8
        .catch java/lang/Exception from L0 to L126 using L146
L0:     ldc_w Class org/lwjgl/opengl/Display
L3:     invokevirtual Method java/lang/Class getDeclaredMethods ()[Ljava/lang/reflect/Method;
L6:     dup
L7:     astore_0
L8:     arraylength
L9:     istore_1
L10:    iconst_0
L11:    iconst_1
L12:    dup
L13:    pop2
L14:    istore_2
L15:    iload_2
L16:    iload_1
L17:    if_icmpge L151
L20:    aload_0
L21:    iload_2
L22:    aaload
L23:    dup
L24:    astore_3
L25:    invokevirtual Method java/lang/reflect/Method getName ()Ljava/lang/String;
L28:    ldc_w "getImplementation"
L31:    invokevirtual Method java/lang/String equals (Ljava/lang/Object;)Z
L34:    ifeq L137
L37:    aconst_null
L38:    aload_3
L39:    dup_x1
L40:    iconst_1
L41:    dup
L42:    dup
L43:    pop2
L44:    invokevirtual Method java/lang/reflect/Method setAccessible (Z)V
L47:    iconst_0
L48:    iconst_1
L49:    dup
L50:    pop2
L51:    anewarray java/lang/Object
L54:    iconst_1
L55:    dup
L56:    pop2
L57:    invokevirtual Method java/lang/reflect/Method invoke (Ljava/lang/Object;[Ljava/lang/Object;)Ljava/lang/Object;
L60:    dup
L61:    astore_3
L62:    invokevirtual Method java/lang/Object getClass ()Ljava/lang/Class;
L65:    invokevirtual Method java/lang/Class getDeclaredFields ()[Ljava/lang/reflect/Field;
L68:    dup
L69:    astore 4
L71:    arraylength
L72:    istore 5
L74:    iconst_0
L75:    iconst_1
L76:    dup
L77:    pop2
L78:    dup
L79:    istore 6
L81:    iload 5
L83:    if_icmpge L137
L86:    aload 4
L88:    iload 6
L90:    aaload
L91:    dup
L92:    astore 7
L94:    invokevirtual Method java/lang/reflect/Field getName ()Ljava/lang/String;
L97:    ldc_w "hwnd"
L100:   invokevirtual Method java/lang/String equals (Ljava/lang/Object;)Z
L103:   ifeq L128
L106:   aload_3
L107:   aload 7
L109:   dup_x1
L110:   iconst_1
L111:   dup
L112:   dup
L113:   pop2
L114:   invokevirtual Method java/lang/reflect/Field setAccessible (Z)V
L117:   invokevirtual Method java/lang/reflect/Field get (Ljava/lang/Object;)Ljava/lang/Object;
L120:   checkcast java/lang/Long
L123:   invokevirtual Method java/lang/Long longValue ()J
L126:   lreturn
L127:   athrow
        .catch java/lang/Exception from L128 to L136 using L146
L128:   iinc 6 1
L131:   iload 6
L133:   goto L81
L136:   athrow
        .catch java/lang/Exception from L137 to L143 using L146
L137:   iinc 2 1
L140:   goto L15
L143:   nop
L144:   nop
L145:   athrow
L146:   astore_0
L147:   aload_0
L148:   invokevirtual Method java/lang/Exception printStackTrace ()V
L151:   lconst_0
L152:   lreturn
L153:   
        .attribute StackMap b'\x00\x09\x00\x0F\x00\x03\x07\x05\x0A\x01\x01\x00\x00\x00\x51\x00\x07\x07\x05\x0A\x01\x01\x07\x00\x04\x07\x05\x22\x01\x01\x00\x01\x01\x00\x7F\x00\x00\x00\x01\x07\x00\x28\x00\x80\x00\x08\x07\x05\x0A\x01\x01\x07\x00\x04\x07\x05\x22\x01\x01\x07\x05\x24\x00\x00\x00\x88\x00\x00\x00\x01\x07\x00\x28\x00\x89\x00\x04\x07\x05\x0A\x01\x01\x07\x00\x04\x00\x00\x00\x8F\x00\x00\x00\x01\x07\x00\x28\x00\x92\x00\x00\x00\x01\x07\x03\x01\x00\x97\x00\x01\x07\x00\x04\x00\x00'
    .end code
.end method

.method public static method1017 : (DDD)D
    .code stack 6 locals 6
L0:     dload_2
L1:     dconst_1
L2:     dload_0
L3:     dsub
L4:     dmul
L5:     dload 4
L7:     dload_0
L8:     dmul
L9:     dadd
L10:    dreturn
L11:    
    .end code
.end method

.method public static method1018 : (Ljava/io/InputStream;Ljava/io/OutputStream;)V
    .code stack 5 locals 4
L0:     ldc 65536
L2:     newarray byte
L4:     iconst_1
L5:     dup
L6:     pop2
L7:     astore_2
L8:     aload_0
L9:     aload_2
L10:    invokevirtual Method java/io/InputStream read ([B)I
L13:    dup
L14:    istore_3
L15:    ifge L20
L18:    return
L19:    athrow
L20:    aload_1
L21:    aload_2
L22:    iconst_0
L23:    iconst_1
L24:    dup
L25:    pop2
L26:    iload_3
L27:    invokevirtual Method java/io/OutputStream write ([BII)V
L30:    aload_0
L31:    goto L9
L34:    
        .attribute StackMap b'\x00\x03\x00\x09\x00\x03\x07\x00\x4E\x07\x05\x32\x07\x00\x50\x00\x01\x07\x00\x4E\x00\x13\x00\x00\x00\x01\x07\x00\x28\x00\x14\x00\x04\x07\x00\x4E\x07\x05\x32\x07\x00\x50\x01\x00\x00'
    .end code
    .exceptions java/io/IOException
.end method
.innerclasses
    Ae ig [0] public static final enum
    Zc [0] [0] static
    jc [0] [0] static
.end innerclasses
.end class
