.version 49 0
.class public final super od
.super qc
.implements G
.field public field970 Lqd;
.field private field971 F
.field private field972 Ljava/util/LinkedHashMap;
.field private try F
.field private field973 LLD;
.field private static final new Ljava/util/HashMap;
.field private field974 LmB;
.field private this F
.field private field975 LId;
.field private field976 Ljava/util/HashMap;
.field private field977 F
.field public field978 Ljava/util/LinkedList;

.method public method476 : (FF)V
    .code stack 5 locals 3
L0:     fload_2
L1:     aload_0
L2:     dup_x1
L3:     dup_x2
L4:     fload_1
L5:     putfield Field od field977 F
L8:     putfield Field od try F
L11:    invokespecial Method od method94 ()Z
L14:    ifeq L30
L17:    aload_0
L18:    dup
L19:    invokespecial Method od method71 ()V
L22:    getfield Field od field974 LmB;
L25:    ldc 5e-1f
L27:    invokevirtual Method mB method104 (F)V
L30:    return
L31:    
        .attribute StackMap b'\x00\x01\x00\x1E\x00\x03\x07\x00\x02\x02\x02\x00\x00'
    .end code
.end method

.method private method71 : ()V
    .code stack 8 locals 5
L0:     aload_0
L1:     getfield Field od field1124 F
L4:     invokestatic Method java/lang/Math abs (F)F
L7:     f2d
L8:     ldc2_w 1e-3
L11:    dcmpg
L12:    iflt L30
L15:    aload_0
L16:    getfield Field od field1132 F
L19:    invokestatic Method java/lang/Math abs (F)F
L22:    f2d
L23:    ldc2_w 1e-3
L26:    dcmpg
L27:    ifge L32
L30:    return
L31:    athrow
L32:    aload_0
L33:    getfield Field od field970 Lqd;
L36:    getfield Field qd field742 Z
L39:    ifeq L169
L42:    new java/util/LinkedHashSet
L45:    dup
L46:    invokespecial Method java/util/LinkedHashSet <init> ()V
L49:    astore_1
L50:    aload_0
L51:    getfield Field od field978 Ljava/util/LinkedList;
L54:    invokevirtual Method java/util/LinkedList iterator ()Ljava/util/Iterator;
L57:    dup
L58:    astore_2
L59:    invokeinterface InterfaceMethod java/util/Iterator hasNext ()Z 1
L64:    ifeq L94
L67:    aload_2
L68:    invokeinterface InterfaceMethod java/util/Iterator next ()Ljava/lang/Object; 1
L73:    checkcast LD
L76:    astore_3
L77:    aload_2
L78:    aload_1
L79:    aload_3
L80:    getfield Field LD field137 LRg;
L83:    getfield Field Rg field231 LsE;
L86:    invokevirtual Method java/util/LinkedHashSet add (Ljava/lang/Object;)Z
L89:    pop
L90:    goto L59
L93:    athrow
L94:    iconst_0
L95:    iconst_1
L96:    dup
L97:    pop2
L98:    istore_2
L99:    aload_1
L100:   invokevirtual Method java/util/LinkedHashSet iterator ()Ljava/util/Iterator;
L103:   dup
L104:   astore_3
L105:   invokeinterface InterfaceMethod java/util/Iterator hasNext ()Z 1
L110:   ifeq L185
L113:   aload_3
L114:   invokeinterface InterfaceMethod java/util/Iterator next ()Ljava/lang/Object; 1
L119:   checkcast sE
L122:   astore 4
L124:   aload_3
L125:   aload_0
L126:   aload 4
L128:   fconst_0
L129:   iload_2
L130:   i2f
L131:   aload_0
L132:   getfield Field od field1132 F
L135:   iinc 2 1
L138:   fmul
L139:   aload_1
L140:   invokevirtual Method java/util/LinkedHashSet size ()I
L143:   i2f
L144:   fdiv
L145:   aload_0
L146:   dup
L147:   getfield Field od field1124 F
L150:   swap
L151:   getfield Field od field1132 F
L154:   aload_1
L155:   invokevirtual Method java/util/LinkedHashSet size ()I
L158:   i2f
L159:   fdiv
L160:   invokespecial Method od method480 (LsE;FFFF)V
L163:   goto L105
L166:   nop
L167:   nop
L168:   athrow
L169:   aload_0
L170:   aconst_null
L171:   fconst_0
L172:   dup
L173:   aload_0
L174:   dup
L175:   getfield Field od field1124 F
L178:   swap
L179:   getfield Field od field1132 F
L182:   invokespecial Method od method480 (LsE;FFFF)V
L185:   aload_0
L186:   getfield Field od field978 Ljava/util/LinkedList;
L189:   invokevirtual Method java/util/LinkedList iterator ()Ljava/util/Iterator;
L192:   dup
L193:   astore_1
L194:   invokeinterface InterfaceMethod java/util/Iterator hasNext ()Z 1
L199:   ifeq L221
L202:   aload_1
L203:   invokeinterface InterfaceMethod java/util/Iterator next ()Ljava/lang/Object; 1
L208:   checkcast LD
L211:   astore_2
L212:   aload_1
L213:   aload_2
L214:   fconst_1
L215:   invokevirtual Method LD method102 (F)V
L218:   goto L194
L221:   aload_0
L222:   getfield Field od field972 Ljava/util/LinkedHashMap;
L225:   invokevirtual Method java/util/LinkedHashMap keySet ()Ljava/util/Set;
L228:   invokeinterface InterfaceMethod java/util/Set iterator ()Ljava/util/Iterator; 1
L233:   dup
L234:   astore_1
L235:   invokeinterface InterfaceMethod java/util/Iterator hasNext ()Z 1
L240:   ifeq L290
L243:   aload_1
L244:   invokeinterface InterfaceMethod java/util/Iterator next ()Ljava/lang/Object; 1
L249:   checkcast LD
L252:   astore_2
L253:   aload_0
L254:   dup
L255:   getfield Field od field1134 F
L258:   swap
L259:   getfield Field od field1124 F
L262:   fadd
L263:   aload_0
L264:   getfield Field od field972 Ljava/util/LinkedHashMap;
L267:   aload_2
L268:   dup_x2
L269:   invokevirtual Method java/util/LinkedHashMap get (Ljava/lang/Object;)Ljava/lang/Object;
L272:   checkcast java/lang/Float
L275:   invokevirtual Method java/lang/Float floatValue ()F
L278:   invokevirtual Method LD method37 (FF)V
L281:   aload_1
L282:   aload_2
L283:   fconst_0
L284:   invokevirtual Method LD method102 (F)V
L287:   goto L235
L290:   aload_0
L291:   getfield Field od field973 LLD;
L294:   ifnull L305
L297:   aload_0
L298:   dup
L299:   getfield Field od field973 LLD;
L302:   invokevirtual Method od method25 (LgB;)V
L305:   return
L306:   
        .attribute StackMap b'\x00\x0F\x00\x1E\x00\x01\x07\x00\x02\x00\x00\x00\x1F\x00\x00\x00\x01\x07\x00\xAA\x00\x20\x00\x01\x07\x00\x02\x00\x00\x00\x3B\x00\x03\x07\x00\x02\x07\x00\x55\x07\x00\x62\x00\x01\x07\x00\x62\x00\x5D\x00\x00\x00\x01\x07\x00\xAA\x00\x5E\x00\x03\x07\x00\x02\x07\x00\x55\x07\x00\x62\x00\x00\x00\x69\x00\x04\x07\x00\x02\x07\x00\x55\x01\x07\x00\x62\x00\x01\x07\x00\x62\x00\xA6\x00\x00\x00\x01\x07\x00\xAA\x00\xA9\x00\x01\x07\x00\x02\x00\x00\x00\xB9\x00\x01\x07\x00\x02\x00\x00\x00\xC2\x00\x02\x07\x00\x02\x07\x00\x62\x00\x01\x07\x00\x62\x00\xDD\x00\x02\x07\x00\x02\x07\x00\x62\x00\x00\x00\xEB\x00\x02\x07\x00\x02\x07\x00\x62\x00\x01\x07\x00\x62\x01\x22\x00\x02\x07\x00\x02\x07\x00\x62\x00\x00\x01\x31\x00\x02\x07\x00\x02\x07\x00\x62\x00\x00'
    .end code
.end method

.method public background : (ZF)V
    .code stack 8 locals 3
L0:     aload_0
L1:     getfield Field od field973 LLD;
L4:     ifnull L37
L7:     aload_0
L8:     getfield Field od field1136 LFE;
L11:    getfield Field FE field825 Z
L14:    ifne L37
L17:    aload_0
L18:    invokespecial Method od method94 ()Z
L21:    ifeq L37
L24:    aload_0
L25:    dup
L26:    invokespecial Method od method71 ()V
L29:    getfield Field od field974 LmB;
L32:    ldc 5e-1f
L34:    invokevirtual Method mB method104 (F)V
L37:    invokestatic Method FE method10 ()V
L40:    iload_1
L41:    aload_0
L42:    dup_x1
L43:    dup_x2
L44:    fconst_0
L45:    ldc -Infinityf
L47:    aload_0
L48:    getfield Field od field1124 F
L51:    ldc +Infinityf
L53:    invokevirtual Method od method464 (FFFF)V
L56:    fload_2
L57:    invokespecial Method qc background (ZF)V
L60:    invokevirtual Method od method417 ()V
L63:    return
L64:    
        .attribute StackMap b'\x00\x01\x00\x25\x00\x03\x07\x00\x02\x01\x02\x00\x00'
    .end code
.end method

.method public method2 : ()V
    .code stack 2 locals 1
L0:     aload_0
L1:     dup
L2:     invokespecial Method qc method2 ()V
L5:     getfield Field od field970 Lqd;
L8:     ifnull L19
L11:    aload_0
L12:    getfield Field od field970 Lqd;
L15:    aload_0
L16:    invokevirtual Method qd method401 (LG;)V
L19:    return
L20:    
        .attribute StackMap b'\x00\x01\x00\x13\x00\x01\x07\x00\x02\x00\x00'
    .end code
.end method

.method private method477 : (LRg;)V
    .code stack 7 locals 2
L0:     aload_1
L1:     ifnonnull L6
L4:     return
L5:     athrow
L6:     aload_1
L7:     instanceof oF
L10:    ifeq L15
L13:    return
L14:    athrow
L15:    aload_0
L16:    aload_1
L17:    invokevirtual Method od method479 (LRg;)LLD;
L20:    ifnull L24
L23:    return
L24:    new LD
L27:    dup
L28:    aload_1
L29:    ldc 1e-1f
L31:    getstatic Field net/gewaltig/cultris/Cultris enable_enemy_sounds I
L34:    i2f
L35:    fmul
L36:    invokespecial Method LD <init> (LRg;F)V
L39:    astore_1
L40:    aload_0
L41:    getfield Field od field978 Ljava/util/LinkedList;
L44:    aload_1
L45:    invokevirtual Method java/util/LinkedList add (Ljava/lang/Object;)Z
L48:    aload_0
L49:    dup_x1
L50:    aload_1
L51:    invokevirtual Method od method36 (LgB;)LgB;
L54:    aload_1
L55:    aload_0
L56:    invokespecial Method od method71 ()V
L59:    aload_0
L60:    dup
L61:    getfield Field od field1134 F
L64:    swap
L65:    getfield Field od field1124 F
L68:    fadd
L69:    aload_1
L70:    dup_x2
L71:    getfield Field LD field1126 F
L74:    invokevirtual Method LD method37 (FF)V
L77:    fconst_0
L78:    invokevirtual Method LD method102 (F)V
L81:    pop2
L82:    getfield Field od field974 LmB;
L85:    ifnull L97
L88:    aload_0
L89:    getfield Field od field974 LmB;
L92:    aload_1
L93:    invokevirtual Method mB method438 (LgB;)LbB;
L96:    pop
L97:    aload_0
L98:    dup
L99:    invokespecial Method od method71 ()V
L102:   invokespecial Method od method94 ()Z
L105:   ifeq L112
L108:   aload_0
L109:   invokespecial Method od method71 ()V
L112:   aload_0
L113:   getfield Field od field974 LmB;
L116:   ifnull L127
L119:   aload_0
L120:   getfield Field od field974 LmB;
L123:   fconst_1
L124:   invokevirtual Method mB method104 (F)V
L127:   return
L128:   
        .attribute StackMap b'\x00\x08\x00\x05\x00\x00\x00\x01\x07\x00\xAA\x00\x06\x00\x02\x07\x00\x02\x07\x00\x71\x00\x00\x00\x0E\x00\x00\x00\x01\x07\x00\xAA\x00\x0F\x00\x02\x07\x00\x02\x07\x00\x71\x00\x00\x00\x18\x00\x02\x07\x00\x02\x07\x00\x71\x00\x00\x00\x61\x00\x02\x07\x00\x02\x07\x00\x6B\x00\x00\x00\x70\x00\x02\x07\x00\x02\x07\x00\x6B\x00\x00\x00\x7F\x00\x02\x07\x00\x02\x07\x00\x6B\x00\x00'
    .end code
.end method

.method public method29 : ()V
    .code stack 6 locals 1
L0:     aload_0
L1:     dup
L2:     invokespecial Method od method71 ()V
L5:     new mB
L8:     aload_0
L9:     dup_x2
L10:    dup
L11:    pop2
L12:    dup
L13:    getstatic Field xc field436 Lxc;
L16:    aload_0
L17:    invokespecial Method mB <init> (Lxc;Lqc;)V
L20:    putfield Field od field974 LmB;
L23:    getfield Field od field974 LmB;
L26:    invokevirtual Method mB method56 ()V
L29:    return
L30:    
    .end code
.end method

.method public method8 : (LD;)V
    .code stack 3 locals 4
L0:     aload_1
L1:     instanceof ag
L4:     ifeq L87
L7:     aload_1
L8:     checkcast ag
L11:    astore_2
L12:    aload_0
L13:    getfield Field od field970 Lqd;
L16:    getfield Field qd new Ljava/util/LinkedHashMap;
L19:    aload_2
L20:    getfield Field ag field720 Led;
L23:    invokevirtual Method java/util/LinkedHashMap get (Ljava/lang/Object;)Ljava/lang/Object;
L26:    checkcast Rg
L29:    astore_3
L30:    aload_2
L31:    getfield Field ag try LqE;
L34:    getstatic Field qE field627 LqE;
L37:    if_acmpeq L70
L40:    aload_2
L41:    getfield Field ag try LqE;
L44:    getstatic Field qE try LqE;
L47:    if_acmpeq L70
L50:    aload_2
L51:    getfield Field ag try LqE;
L54:    getstatic Field qE field630 LqE;
L57:    if_acmpeq L70
L60:    aload_2
L61:    getfield Field ag try LqE;
L64:    getstatic Field qE field628 LqE;
L67:    if_acmpne L80
L70:    aload_0
L71:    aload_2
L72:    getfield Field ag field720 Led;
L75:    invokevirtual Method od method410 (Led;)V
L78:    return
L79:    athrow
L80:    aload_0
L81:    aload_3
L82:    invokespecial Method od method477 (LRg;)V
L85:    return
L86:    athrow
L87:    aload_1
L88:    instanceof LF
L91:    ifeq L170
L94:    aload_1
L95:    checkcast LF
L98:    astore_2
L99:    aload_0
L100:   getfield Field od field970 Lqd;
L103:   getfield Field qd new Ljava/util/LinkedHashMap;
L106:   aload_2
L107:   getfield Field LF field953 Led;
L110:   invokevirtual Method java/util/LinkedHashMap get (Ljava/lang/Object;)Ljava/lang/Object;
L113:   checkcast Rg
L116:   getfield Field Rg field227 LqE;
L119:   dup
L120:   astore_3
L121:   getstatic Field qE field627 LqE;
L124:   if_acmpeq L368
L127:   aload_3
L128:   getstatic Field qE try LqE;
L131:   if_acmpeq L368
L134:   aload_3
L135:   getstatic Field qE field630 LqE;
L138:   if_acmpeq L368
L141:   aload_3
L142:   getstatic Field qE field628 LqE;
L145:   if_acmpeq L368
L148:   aload_0
L149:   dup
L150:   getfield Field od field970 Lqd;
L153:   getfield Field qd new Ljava/util/LinkedHashMap;
L156:   aload_2
L157:   getfield Field LF field953 Led;
L160:   invokevirtual Method java/util/LinkedHashMap get (Ljava/lang/Object;)Ljava/lang/Object;
L163:   checkcast Rg
L166:   invokespecial Method od method477 (LRg;)V
L169:   return
L170:   aload_1
L171:   instanceof fc
L174:   ifeq L223
L177:   aload_1
L178:   checkcast fc
L181:   dup
L182:   astore_2
L183:   getfield Field fc field876 Loc;
L186:   getstatic Field oc new Loc;
L189:   if_acmpne L368
L192:   aload_0
L193:   dup
L194:   invokespecial Method od method71 ()V
L197:   invokespecial Method od method94 ()Z
L200:   ifeq L207
L203:   aload_0
L204:   invokespecial Method od method71 ()V
L207:   aload_0
L208:   getfield Field od field974 LmB;
L211:   ifnull L368
L214:   aload_0
L215:   getfield Field od field974 LmB;
L218:   fconst_1
L219:   invokevirtual Method mB method104 (F)V
L222:   return
L223:   aload_1
L224:   instanceof pc
L227:   ifeq L306
L230:   aload_1
L231:   checkcast pc
L234:   astore_2
L235:   aload_0
L236:   getfield Field od field970 Lqd;
L239:   getfield Field qd new Ljava/util/LinkedHashMap;
L242:   aload_2
L243:   getfield Field pc field943 Led;
L246:   invokevirtual Method java/util/LinkedHashMap get (Ljava/lang/Object;)Ljava/lang/Object;
L249:   checkcast Rg
L252:   getfield Field Rg field227 LqE;
L255:   dup
L256:   astore_3
L257:   getstatic Field qE field627 LqE;
L260:   if_acmpeq L368
L263:   aload_3
L264:   getstatic Field qE try LqE;
L267:   if_acmpeq L368
L270:   aload_3
L271:   getstatic Field qE field630 LqE;
L274:   if_acmpeq L368
L277:   aload_3
L278:   getstatic Field qE field628 LqE;
L281:   if_acmpeq L368
L284:   aload_0
L285:   dup
L286:   getfield Field od field970 Lqd;
L289:   getfield Field qd new Ljava/util/LinkedHashMap;
L292:   aload_2
L293:   getfield Field pc field943 Led;
L296:   invokevirtual Method java/util/LinkedHashMap get (Ljava/lang/Object;)Ljava/lang/Object;
L299:   checkcast Rg
L302:   invokespecial Method od method477 (LRg;)V
L305:   return
L306:   aload_1
L307:   instanceof gC
L310:   aload_1
L311:   swap
L312:   ifeq L328
L315:   checkcast gC
L318:   astore_2
L319:   aload_0
L320:   aload_2
L321:   getfield Field gC field872 Led;
L324:   invokevirtual Method od method410 (Led;)V
L327:   return
L328:   instanceof tc
L331:   ifeq L368
L334:   aload_0
L335:   getfield Field od field978 Ljava/util/LinkedList;
L338:   invokevirtual Method java/util/LinkedList isEmpty ()Z
L341:   ifne L368
L344:   aload_0
L345:   dup
L346:   getfield Field od field978 Ljava/util/LinkedList;
L349:   invokevirtual Method java/util/LinkedList getLast ()Ljava/lang/Object;
L352:   checkcast LD
L355:   getfield Field LD field137 LRg;
L358:   getfield Field Rg false Led;
L361:   invokevirtual Method od method410 (Led;)V
L364:   aload_0
L365:   goto L335
L368:   return
L369:   
        .attribute StackMap b'\x00\x0C\x00\x46\x00\x04\x07\x00\x02\x07\x01\x37\x07\x00\xF7\x07\x00\x71\x00\x00\x00\x4F\x00\x00\x00\x01\x07\x00\xAA\x00\x50\x00\x04\x07\x00\x02\x07\x01\x37\x07\x00\xF7\x07\x00\x71\x00\x00\x00\x56\x00\x00\x00\x01\x07\x00\xAA\x00\x57\x00\x02\x07\x00\x02\x07\x01\x37\x00\x00\x00\xAA\x00\x02\x07\x00\x02\x07\x01\x37\x00\x00\x00\xCF\x00\x03\x07\x00\x02\x07\x01\x37\x07\x00\x0E\x00\x00\x00\xDF\x00\x02\x07\x00\x02\x07\x01\x37\x00\x00\x01\x32\x00\x02\x07\x00\x02\x07\x01\x37\x00\x00\x01\x48\x00\x02\x07\x00\x02\x07\x01\x37\x00\x01\x07\x01\x37\x01\x4F\x00\x02\x07\x00\x02\x07\x01\x37\x00\x01\x07\x00\x02\x01\x70\x00\x02\x07\x00\x02\x07\x01\x37\x00\x00'
    .end code
.end method

.method public method30 : (FF)V
    .code stack 3 locals 5
L0:     aload_0
L1:     getfield Field od field978 Ljava/util/LinkedList;
L4:     invokevirtual Method java/util/LinkedList iterator ()Ljava/util/Iterator;
L7:     astore_3
L8:     aload_3
L9:     invokeinterface InterfaceMethod java/util/Iterator hasNext ()Z 1
L14:    ifeq L113
L17:    aload_3
L18:    invokeinterface InterfaceMethod java/util/Iterator next ()Ljava/lang/Object; 1
L23:    checkcast LD
L26:    astore 4
L28:    fload_1
L29:    aload_0
L30:    getfield Field od field1134 F
L33:    fadd
L34:    aload 4
L36:    getfield Field LD field1134 F
L39:    fcmpl
L40:    iflt L8
L43:    fload_1
L44:    aload_0
L45:    getfield Field od field1134 F
L48:    fadd
L49:    aload 4
L51:    dup
L52:    getfield Field LD field1134 F
L55:    swap
L56:    getfield Field LD field1124 F
L59:    fadd
L60:    fcmpg
L61:    ifgt L8
L64:    fload_2
L65:    aload_0
L66:    getfield Field od field1126 F
L69:    fadd
L70:    aload 4
L72:    getfield Field LD field1126 F
L75:    fcmpl
L76:    iflt L8
L79:    fload_2
L80:    aload_0
L81:    getfield Field od field1126 F
L84:    fadd
L85:    aload 4
L87:    dup
L88:    getfield Field LD field1126 F
L91:    swap
L92:    getfield Field LD field1132 F
L95:    fadd
L96:    fcmpg
L97:    ifgt L8
L100:   aload 4
L102:   fload_1
L103:   fload_2
L104:   invokevirtual Method LD method30 (FF)V
L107:   return
L108:   nop
L109:   nop
L110:   nop
L111:   nop
L112:   athrow
L113:   return
L114:   
        .attribute StackMap b'\x00\x03\x00\x08\x00\x04\x07\x00\x02\x02\x02\x07\x00\x62\x00\x00\x00\x6C\x00\x00\x00\x01\x07\x00\xAA\x00\x71\x00\x04\x07\x00\x02\x02\x02\x07\x00\x62\x00\x00'
    .end code
.end method

.method public method263 : ()Z
    .code stack 3 locals 1
L0:     aload_0
L1:     getfield Field od field973 LLD;
L4:     ifnull L13
L7:     iconst_1
L8:     dup
L9:     dup
L10:    pop2
L11:    ireturn
L12:    athrow
L13:    iconst_0
L14:    iconst_1
L15:    dup
L16:    pop2
L17:    ireturn
L18:    
        .attribute StackMap b'\x00\x02\x00\x0C\x00\x00\x00\x01\x07\x00\xAA\x00\x0D\x00\x01\x07\x00\x02\x00\x00'
    .end code
.end method

.method public false : ()Z
    .code stack 3 locals 1
L0:     iconst_1
L1:     dup
L2:     dup
L3:     pop2
L4:     ireturn
L5:     
    .end code
.end method

.method public method32 : (FF)V
    .code stack 8 locals 3
L0:     aload_0
L1:     getfield Field od field1124 F
L4:     fload_1
L5:     fcmpl
L6:     ifne L20
L9:     aload_0
L10:    getfield Field od field1132 F
L13:    fload_2
L14:    fcmpl
L15:    ifne L20
L18:    return
L19:    athrow
L20:    aload_0
L21:    dup
L22:    dup2
L23:    dup2
L24:    fload_1
L25:    fload_2
L26:    invokespecial Method qc method32 (FF)V
L29:    getfield Field od field1124 F
L32:    ldc_w 7.5e-1f
L35:    fmul
L36:    aload_0
L37:    dup_x1
L38:    getfield Field od field1132 F
L41:    invokestatic Method LD method124 ()F
L44:    fmul
L45:    ldc_w 7.5e-1f
L48:    fmul
L49:    invokestatic Method java/lang/Math min (FF)F
L52:    putfield Field od this F
L55:    getfield Field od this F
L58:    invokestatic Method LD method124 ()F
L61:    fdiv
L62:    putfield Field od field971 F
L65:    invokespecial Method od method71 ()V
L68:    invokespecial Method od method94 ()Z
L71:    ifeq L78
L74:    aload_0
L75:    invokespecial Method od method71 ()V
L78:    aload_0
L79:    getfield Field od field974 LmB;
L82:    ifnull L92
L85:    aload_0
L86:    getfield Field od field974 LmB;
L89:    invokevirtual Method mB method56 ()V
L92:    return
L93:    
        .attribute StackMap b'\x00\x04\x00\x13\x00\x00\x00\x01\x07\x00\xAA\x00\x14\x00\x03\x07\x00\x02\x02\x02\x00\x00\x00\x4E\x00\x03\x07\x00\x02\x02\x02\x00\x00\x00\x5C\x00\x03\x07\x00\x02\x02\x02\x00\x00'
    .end code
.end method

.method public method478 : ()V
    .code stack 2 locals 1
L0:     aload_0
L1:     dup
L2:     invokespecial Method qc method478 ()V
L5:     invokespecial Method od method94 ()Z
L8:     ifeq L24
L11:    aload_0
L12:    dup
L13:    invokespecial Method od method71 ()V
L16:    getfield Field od field974 LmB;
L19:    ldc 5e-1f
L21:    invokevirtual Method mB method104 (F)V
L24:    return
L25:    
        .attribute StackMap b'\x00\x01\x00\x18\x00\x01\x07\x00\x02\x00\x00'
    .end code
.end method

.method private method94 : ()Z
    .code stack 6 locals 7
L0:     aload_0
L1:     getfield Field od field1124 F
L4:     invokestatic Method java/lang/Math abs (F)F
L7:     f2d
L8:     ldc2_w 1e-3
L11:    dcmpg
L12:    iflt L37
L15:    aload_0
L16:    getfield Field od field1132 F
L19:    invokestatic Method java/lang/Math abs (F)F
L22:    f2d
L23:    ldc2_w 1e-3
L26:    dcmpg
L27:    iflt L37
L30:    aload_0
L31:    getfield Field od field1131 Z
L34:    ifne L82
L37:    aload_0
L38:    getfield Field od field973 LLD;
L41:    ifnonnull L50
L44:    iconst_0
L45:    iconst_1
L46:    dup
L47:    pop2
L48:    ireturn
L49:    athrow
L50:    aload_0
L51:    aconst_null
L52:    aload_0
L53:    dup_x1
L54:    getfield Field od field973 LLD;
L57:    invokevirtual Method LD method46 ()V
L60:    putfield Field od field973 LLD;
L63:    getfield Field od field1127 Lqc;
L66:    ifnull L76
L69:    aload_0
L70:    getfield Field od field1127 Lqc;
L73:    invokevirtual Method qc method21 ()V
L76:    iconst_1
L77:    dup
L78:    dup
L79:    pop2
L80:    ireturn
L81:    athrow
L82:    aload_0
L83:    dup
L84:    dup2
L85:    getfield Field od field977 F
L88:    aload_0
L89:    dup_x2
L90:    getfield Field od field1134 F
L93:    fadd
L94:    fstore_1
L95:    getfield Field od try F
L98:    aload_0
L99:    getfield Field od field1126 F
L102:   fadd
L103:   fstore_2
L104:   getfield Field od field973 LLD;
L107:   astore_3
L108:   aconst_null
L109:   putfield Field od field973 LLD;
L112:   getfield Field od field1136 LFE;
L115:   getfield Field FE field825 Z
L118:   ifeq L287
L121:   aload_0
L122:   getfield Field od field978 Ljava/util/LinkedList;
L125:   invokevirtual Method java/util/LinkedList iterator ()Ljava/util/Iterator;
L128:   astore 4
L130:   aload 4
L132:   invokeinterface InterfaceMethod java/util/Iterator hasNext ()Z 1
L137:   ifeq L287
L140:   aload 4
L142:   invokeinterface InterfaceMethod java/util/Iterator next ()Ljava/lang/Object; 1
L147:   checkcast LD
L150:   dup
L151:   astore 5
L153:   getfield Field LD field137 LRg;
L156:   instanceof oF
L159:   ifne L130
L162:   aload_0
L163:   getfield Field od field976 Ljava/util/HashMap;
L166:   aload 5
L168:   invokevirtual Method java/util/HashMap get (Ljava/lang/Object;)Ljava/lang/Object;
L171:   checkcast [F
L174:   dup
L175:   astore 6
L177:   ifnull L130
L180:   fload_1
L181:   aload 6
L183:   iconst_0
L184:   iconst_1
L185:   dup
L186:   pop2
L187:   faload
L188:   fcmpl
L189:   iflt L130
L192:   fload_2
L193:   aload 6
L195:   iconst_1
L196:   dup
L197:   dup
L198:   pop2
L199:   faload
L200:   fcmpl
L201:   iflt L130
L204:   fload_1
L205:   aload 6
L207:   iconst_0
L208:   iconst_1
L209:   dup
L210:   pop2
L211:   faload
L212:   aload 6
L214:   iconst_2
L215:   iconst_1
L216:   dup
L217:   pop2
L218:   faload
L219:   fadd
L220:   fcmpg
L221:   ifgt L130
L224:   fload_2
L225:   aload 6
L227:   iconst_1
L228:   dup
L229:   dup
L230:   pop2
L231:   faload
L232:   aload 6
L234:   iconst_3
L235:   iconst_1
L236:   dup
L237:   pop2
L238:   faload
L239:   fadd
L240:   fcmpg
L241:   ifgt L130
L244:   aload_0
L245:   getfield Field od this F
L248:   aload 6
L250:   iconst_2
L251:   iconst_1
L252:   dup
L253:   pop2
L254:   faload
L255:   fcmpl
L256:   ifle L287
L259:   aload_0
L260:   getfield Field od field971 F
L263:   aload 6
L265:   iconst_3
L266:   iconst_1
L267:   dup
L268:   pop2
L269:   faload
L270:   fcmpl
L271:   ifle L287
L274:   aload_3
L275:   aload_0
L276:   aload 5
L278:   putfield Field od field973 LLD;
L281:   goto L288
L284:   nop
L285:   nop
L286:   athrow
L287:   aload_3
L288:   ifnull L295
L291:   aload_3
L292:   invokevirtual Method LD method46 ()V
L295:   aload_0
L296:   getfield Field od field973 LLD;
L299:   ifnull L309
L302:   aload_0
L303:   getfield Field od field973 LLD;
L306:   invokevirtual Method LD while ()V
L309:   aload_0
L310:   getfield Field od field973 LLD;
L313:   aload_3
L314:   if_acmpeq L331
L317:   aload_0
L318:   getfield Field od field1127 Lqc;
L321:   ifnull L331
L324:   aload_0
L325:   getfield Field od field1127 Lqc;
L328:   invokevirtual Method qc method21 ()V
L331:   aload_0
L332:   getfield Field od field973 LLD;
L335:   aload_3
L336:   if_acmpeq L344
L339:   iconst_1
L340:   dup
L341:   dup
L342:   pop2
L343:   ireturn
L344:   iconst_0
L345:   iconst_1
L346:   dup
L347:   pop2
L348:   ireturn
L349:   
        .attribute StackMap b'\x00\x0E\x00\x25\x00\x01\x07\x00\x02\x00\x00\x00\x31\x00\x00\x00\x01\x07\x00\xAA\x00\x32\x00\x01\x07\x00\x02\x00\x00\x00\x4C\x00\x01\x07\x00\x02\x00\x00\x00\x51\x00\x00\x00\x01\x07\x00\xAA\x00\x52\x00\x01\x07\x00\x02\x00\x00\x00\x82\x00\x05\x07\x00\x02\x02\x02\x07\x00\x6B\x07\x00\x62\x00\x00\x01\x1C\x00\x00\x00\x01\x07\x00\xAA\x01\x1F\x00\x04\x07\x00\x02\x02\x02\x07\x00\x6B\x00\x00\x01\x20\x00\x04\x07\x00\x02\x02\x02\x07\x00\x6B\x00\x01\x07\x00\x6B\x01\x27\x00\x04\x07\x00\x02\x02\x02\x07\x00\x6B\x00\x00\x01\x35\x00\x04\x07\x00\x02\x02\x02\x07\x00\x6B\x00\x00\x01\x4B\x00\x04\x07\x00\x02\x02\x02\x07\x00\x6B\x00\x00\x01\x58\x00\x04\x07\x00\x02\x02\x02\x07\x00\x6B\x00\x00'
    .end code
.end method

.method public method37 : (FF)V
    .code stack 8 locals 3
L0:     aload_0
L1:     getfield Field od field1134 F
L4:     fload_1
L5:     fcmpl
L6:     ifne L20
L9:     aload_0
L10:    getfield Field od field1126 F
L13:    fload_2
L14:    fcmpl
L15:    ifne L20
L18:    return
L19:    athrow
L20:    aload_0
L21:    dup
L22:    fload_1
L23:    aload_0
L24:    dup_x2
L25:    aload_0
L26:    ldc -Infinityf
L28:    dup_x1
L29:    putfield Field od field977 F
L32:    putfield Field od try F
L35:    fload_2
L36:    invokespecial Method qc method37 (FF)V
L39:    invokespecial Method od method71 ()V
L42:    invokespecial Method od method94 ()Z
L45:    ifeq L52
L48:    aload_0
L49:    invokespecial Method od method71 ()V
L52:    aload_0
L53:    getfield Field od field974 LmB;
L56:    ifnull L66
L59:    aload_0
L60:    getfield Field od field974 LmB;
L63:    invokevirtual Method mB method56 ()V
L66:    return
L67:    
        .attribute StackMap b'\x00\x04\x00\x13\x00\x00\x00\x01\x07\x00\xAA\x00\x14\x00\x03\x07\x00\x02\x02\x02\x00\x00\x00\x34\x00\x03\x07\x00\x02\x02\x02\x00\x00\x00\x42\x00\x03\x07\x00\x02\x02\x02\x00\x00'
    .end code
.end method

.method public true : ()V
    .code stack 2 locals 1
L0:     aload_0
L1:     dup
L2:     invokespecial Method qc true ()V
L5:     invokespecial Method od method94 ()Z
L8:     ifeq L24
L11:    aload_0
L12:    dup
L13:    invokespecial Method od method71 ()V
L16:    getfield Field od field974 LmB;
L19:    ldc 5e-1f
L21:    invokevirtual Method mB method104 (F)V
L24:    return
L25:    
        .attribute StackMap b'\x00\x01\x00\x18\x00\x01\x07\x00\x02\x00\x00'
    .end code
.end method

.method public <init> : (Lqd;LId;)V
    .code stack 22 locals 3
L0:     aload_2
L1:     aload_0
L2:     dup_x1
L3:     dup_x2
L4:     ldc -Infinityf
L6:     aload_0
L7:     dup_x1
L8:     ldc -Infinityf
L10:    aconst_null
L11:    aload_0
L12:    dup
L13:    dup_x2
L14:    ldc_w 1.6e1f
L17:    aload_1
L18:    aload_0
L19:    dup_x1
L20:    dup_x2
L21:    new sF
L24:    aload_0
L25:    dup_x1
L26:    dup_x2
L27:    dup
L28:    pop2
L29:    dup
L30:    invokespecial Method sF <init> ()V
L33:    invokespecial Method qc <init> (Ld;)V
L36:    new java/util/LinkedHashMap
L39:    aload_0
L40:    dup
L41:    pop2
L42:    dup
L43:    invokespecial Method java/util/LinkedHashMap <init> ()V
L46:    putfield Field od field972 Ljava/util/LinkedHashMap;
L49:    new java/util/LinkedList
L52:    aload_0
L53:    dup
L54:    pop2
L55:    dup
L56:    invokespecial Method java/util/LinkedList <init> ()V
L59:    putfield Field od field978 Ljava/util/LinkedList;
L62:    putfield Field od field970 Lqd;
L65:    getfield Field od field970 Lqd;
L68:    aload_0
L69:    getstatic Field mc field387 Lmc;
L72:    invokevirtual Method qd method408 (LG;Lmc;)V
L75:    putfield Field od field1128 F
L78:    getstatic Field FE field822 F
L81:    putfield Field od field1137 F
L84:    putfield Field od field973 LLD;
L87:    putfield Field od field977 F
L90:    putfield Field od try F
L93:    new java/util/HashMap
L96:    aload_0
L97:    dup
L98:    pop2
L99:    dup
L100:   invokespecial Method java/util/HashMap <init> ()V
L103:   putfield Field od field976 Ljava/util/HashMap;
L106:   putfield Field od field975 LId;
L109:   invokespecial Method od method74 ()V
L112:   return
L113:   
    .end code
.end method

.method public method479 : (LRg;)LLD;
    .code stack 2 locals 4
L0:     aload_0
L1:     getfield Field od field978 Ljava/util/LinkedList;
L4:     invokevirtual Method java/util/LinkedList iterator ()Ljava/util/Iterator;
L7:     astore_2
L8:     aload_2
L9:     invokeinterface InterfaceMethod java/util/Iterator hasNext ()Z 1
L14:    ifeq L42
L17:    aload_2
L18:    invokeinterface InterfaceMethod java/util/Iterator next ()Ljava/lang/Object; 1
L23:    checkcast LD
L26:    dup
L27:    astore_3
L28:    getfield Field LD field137 LRg;
L31:    aload_1
L32:    if_acmpne L8
L35:    aload_3
L36:    areturn
L37:    nop
L38:    nop
L39:    nop
L40:    nop
L41:    athrow
L42:    aconst_null
L43:    areturn
L44:    
        .attribute StackMap b'\x00\x03\x00\x08\x00\x03\x07\x00\x02\x07\x00\x71\x07\x00\x62\x00\x00\x00\x25\x00\x00\x00\x01\x07\x00\xAA\x00\x2A\x00\x03\x07\x00\x02\x07\x00\x71\x07\x00\x62\x00\x00'
    .end code
.end method

.method private method480 : (LsE;FFFF)V
    .code stack 8 locals 19
L0:     new java/util/ArrayList
L3:     dup
L4:     invokespecial Method java/util/ArrayList <init> ()V
L7:     astore 6
L9:     aload_0
L10:    getfield Field od field978 Ljava/util/LinkedList;
L13:    invokevirtual Method java/util/LinkedList iterator ()Ljava/util/Iterator;
L16:    astore 7
L18:    aload 7
L20:    invokeinterface InterfaceMethod java/util/Iterator hasNext ()Z 1
L25:    ifeq L63
L28:    aload 7
L30:    invokeinterface InterfaceMethod java/util/Iterator next ()Ljava/lang/Object; 1
L35:    checkcast LD
L38:    dup
L39:    astore 8
L41:    getfield Field LD field137 LRg;
L44:    getfield Field Rg field231 LsE;
L47:    aload_1
L48:    if_acmpne L18
L51:    aload 6
L53:    aload 8
L55:    invokevirtual Method java/util/ArrayList add (Ljava/lang/Object;)Z
L58:    pop
L59:    goto L18
L62:    athrow
L63:    aload 6
L65:    invokevirtual Method java/util/ArrayList size ()I
L68:    ifne L73
L71:    return
L72:    athrow
L73:    fload 5
L75:    fload 4
L77:    fdiv
L78:    fstore 7
L80:    aload_0
L81:    aload 6
L83:    invokevirtual Method java/util/ArrayList size ()I
L86:    fload 7
L88:    invokespecial Method od method481 (IF)LDc;
L91:    astore 8
L93:    iconst_0
L94:    iconst_1
L95:    dup
L96:    pop2
L97:    istore_1
L98:    iconst_0
L99:    iconst_1
L100:   dup
L101:   pop2
L102:   istore 9
L104:   fload 4
L106:   aload 8
L108:   getfield Field Dc field1793 Ljava/lang/Object;
L111:   checkcast java/lang/Integer
L114:   invokevirtual Method java/lang/Integer intValue ()I
L117:   i2f
L118:   fdiv
L119:   fstore 4
L121:   fload 5
L123:   aload 8
L125:   getfield Field Dc field1794 Ljava/lang/Object;
L128:   checkcast java/lang/Integer
L131:   invokevirtual Method java/lang/Integer intValue ()I
L134:   i2f
L135:   fdiv
L136:   fstore 5
L138:   fload 4
L140:   fload 5
L142:   invokestatic Method LD method124 ()F
L145:   fmul
L146:   invokestatic Method java/lang/Math min (FF)F
L149:   dup
L150:   fstore 10
L152:   invokestatic Method LD method124 ()F
L155:   fdiv
L156:   fstore 11
L158:   fload_2
L159:   fstore 12
L161:   fload_3
L162:   fstore_3
L163:   fload 4
L165:   fload 5
L167:   invokestatic Method LD method124 ()F
L170:   fmul
L171:   fcmpl
L172:   ifle L196
L175:   fload 12
L177:   fload 4
L179:   fload 5
L181:   invokestatic Method LD method124 ()F
L184:   fmul
L185:   fsub
L186:   fconst_2
L187:   fdiv
L188:   fadd
L189:   fstore 12
L191:   aload 6
L193:   goto L212
L196:   fload_3
L197:   fload 5
L199:   fload 4
L201:   invokestatic Method LD method124 ()F
L204:   fdiv
L205:   fsub
L206:   fconst_2
L207:   fdiv
L208:   fadd
L209:   fstore_3
L210:   aload 6
L212:   invokevirtual Method java/util/ArrayList size ()I
L215:   iconst_1
L216:   dup
L217:   dup
L218:   pop2
L219:   if_icmpne L237
L222:   fload 12
L224:   aload_0
L225:   getfield Field od field1124 F
L228:   fload 4
L230:   fsub
L231:   ldc 5e-1f
L233:   fmul
L234:   fadd
L235:   fstore 12
L237:   aload 8
L239:   getfield Field Dc field1793 Ljava/lang/Object;
L242:   checkcast java/lang/Integer
L245:   invokevirtual Method java/lang/Integer intValue ()I
L248:   iconst_1
L249:   dup
L250:   dup
L251:   pop2
L252:   if_icmpne L301
L255:   aload 8
L257:   getfield Field Dc field1794 Ljava/lang/Object;
L260:   checkcast java/lang/Integer
L263:   invokevirtual Method java/lang/Integer intValue ()I
L266:   aload 6
L268:   invokevirtual Method java/util/ArrayList size ()I
L271:   if_icmple L301
L274:   fload_3
L275:   aload 8
L277:   getfield Field Dc field1794 Ljava/lang/Object;
L280:   checkcast java/lang/Integer
L283:   invokevirtual Method java/lang/Integer intValue ()I
L286:   aload 6
L288:   invokevirtual Method java/util/ArrayList size ()I
L291:   isub
L292:   i2f
L293:   fload 5
L295:   fmul
L296:   ldc 5e-1f
L298:   fmul
L299:   fadd
L300:   fstore_3
L301:   iconst_0
L302:   iconst_1
L303:   dup
L304:   pop2
L305:   istore 8
L307:   iconst_0
L308:   iconst_1
L309:   dup
L310:   pop2
L311:   istore 13
L313:   iconst_1
L314:   dup
L315:   dup
L316:   pop2
L317:   istore 14
L319:   iconst_1
L320:   dup
L321:   dup
L322:   pop2
L323:   istore 15
L325:   aload 6
L327:   invokevirtual Method java/util/ArrayList iterator ()Ljava/util/Iterator;
L330:   astore 6
L332:   aload 6
L334:   invokeinterface InterfaceMethod java/util/Iterator hasNext ()Z 1
L339:   ifeq L710
L342:   aload 6
L344:   invokeinterface InterfaceMethod java/util/Iterator next ()Ljava/lang/Object; 1
L349:   checkcast LD
L352:   dup
L353:   astore 16
L355:   aload_0
L356:   dup
L357:   getfield Field od field1134 F
L360:   fload 12
L362:   fadd
L363:   iload_1
L364:   i2f
L365:   fload 4
L367:   fmul
L368:   fadd
L369:   fstore 17
L371:   getfield Field od field1126 F
L374:   fload_3
L375:   fadd
L376:   iload 9
L378:   i2f
L379:   fload 5
L381:   fmul
L382:   fadd
L383:   fstore 18
L385:   aload_0
L386:   getfield Field od field973 LLD;
L389:   if_acmpne L523
L392:   fload 17
L394:   aload 16
L396:   dup_x1
L397:   aload_0
L398:   dup
L399:   getfield Field od this F
L402:   swap
L403:   getfield Field od field971 F
L406:   invokevirtual Method LD method32 (FF)V
L409:   aload_0
L410:   getfield Field od this F
L413:   fload 10
L415:   fsub
L416:   fconst_2
L417:   fdiv
L418:   fsub
L419:   aload_0
L420:   getfield Field od field1134 F
L423:   ldc_w 1e-2f
L426:   aload_0
L427:   getfield Field od field1124 F
L430:   fmul
L431:   fadd
L432:   fload_2
L433:   fadd
L434:   ldc 1e-1f
L436:   aload_0
L437:   getfield Field od this F
L440:   fmul
L441:   fadd
L442:   aload_0
L443:   dup
L444:   getfield Field od field1134 F
L447:   swap
L448:   getfield Field od field1124 F
L451:   fadd
L452:   ldc_w 4.5e-2f
L455:   aload_0
L456:   getfield Field od field1124 F
L459:   fmul
L460:   fsub
L461:   aload_0
L462:   getfield Field od this F
L465:   fsub
L466:   invokestatic Method OC method1001 (FFF)F
L469:   fstore 17
L471:   fload 18
L473:   aload_0
L474:   getfield Field od field971 F
L477:   fload 11
L479:   fsub
L480:   fconst_2
L481:   fdiv
L482:   fsub
L483:   aload_0
L484:   getfield Field od field1126 F
L487:   ldc_w 7e-2f
L490:   aload_0
L491:   getfield Field od field971 F
L494:   fmul
L495:   fadd
L496:   aload_0
L497:   dup
L498:   getfield Field od field1126 F
L501:   swap
L502:   getfield Field od field1132 F
L505:   fadd
L506:   aload_0
L507:   getfield Field od field971 F
L510:   ldc_w 1.07e0f
L513:   fmul
L514:   fsub
L515:   invokestatic Method OC method1001 (FFF)F
L518:   fstore 18
L520:   goto L533
L523:   aload 16
L525:   dup
L526:   fload 10
L528:   fload 11
L530:   invokevirtual Method LD method32 (FF)V
L533:   fload 17
L535:   fload 18
L537:   invokevirtual Method LD method37 (FF)V
L540:   aload_0
L541:   getfield Field od field976 Ljava/util/HashMap;
L544:   aload 16
L546:   iconst_4
L547:   iconst_1
L548:   dup
L549:   pop2
L550:   newarray float
L552:   iconst_1
L553:   dup
L554:   pop2
L555:   dup
L556:   iconst_0
L557:   iconst_1
L558:   dup
L559:   pop2
L560:   aload_0
L561:   getfield Field od field1134 F
L564:   fload 12
L566:   fadd
L567:   iload_1
L568:   i2f
L569:   fload 4
L571:   fmul
L572:   fadd
L573:   fastore
L574:   dup
L575:   iconst_1
L576:   dup
L577:   dup
L578:   pop2
L579:   aload_0
L580:   getfield Field od field1126 F
L583:   fload_3
L584:   fadd
L585:   iload 9
L587:   i2f
L588:   fload 5
L590:   fmul
L591:   fadd
L592:   fastore
L593:   dup
L594:   iconst_2
L595:   iconst_1
L596:   dup
L597:   pop2
L598:   fload 10
L600:   fastore
L601:   dup
L602:   iconst_3
L603:   iconst_1
L604:   dup
L605:   pop2
L606:   fload 11
L608:   fastore
L609:   invokevirtual Method java/util/HashMap put (Ljava/lang/Object;Ljava/lang/Object;)Ljava/lang/Object;
L612:   pop
L613:   iinc 1 1
L616:   iload_1
L617:   iload 15
L619:   if_icmpne L694
L622:   iconst_0
L623:   iconst_1
L624:   iinc 9 1
L627:   dup
L628:   pop2
L629:   istore_1
L630:   iload 9
L632:   iload 14
L634:   if_icmpne L694
L637:   iconst_0
L638:   iconst_1
L639:   dup
L640:   pop2
L641:   istore 9
L643:   iload 15
L645:   istore 13
L647:   iload 14
L649:   istore 8
L651:   aload_0
L652:   iload 15
L654:   iload 14
L656:   imul
L657:   iconst_1
L658:   dup
L659:   dup
L660:   pop2
L661:   iadd
L662:   fload 7
L664:   invokespecial Method od method481 (IF)LDc;
L667:   dup
L668:   astore 16
L670:   getfield Field Dc field1793 Ljava/lang/Object;
L673:   checkcast java/lang/Integer
L676:   invokevirtual Method java/lang/Integer intValue ()I
L679:   istore 15
L681:   aload 16
L683:   getfield Field Dc field1794 Ljava/lang/Object;
L686:   checkcast java/lang/Integer
L689:   invokevirtual Method java/lang/Integer intValue ()I
L692:   istore 14
L694:   iload_1
L695:   iload 13
L697:   if_icmpge L332
L700:   iload 9
L702:   iload 8
L704:   if_icmplt L613
L707:   goto L332
L710:   return
L711:   
        .attribute StackMap b'\x00\x0F\x00\x12\x00\x08\x07\x00\x02\x07\x00\x7C\x02\x02\x02\x02\x07\x01\x91\x07\x00\x62\x00\x00\x00\x3E\x00\x00\x00\x01\x07\x00\xAA\x00\x3F\x00\x08\x07\x00\x02\x07\x00\x7C\x02\x02\x02\x02\x07\x01\x91\x07\x00\x62\x00\x00\x00\x48\x00\x00\x00\x01\x07\x00\xAA\x00\x49\x00\x08\x07\x00\x02\x07\x00\x7C\x02\x02\x02\x02\x07\x01\x91\x07\x00\x62\x00\x00\x00\xC4\x00\x0D\x07\x00\x02\x01\x02\x02\x02\x02\x07\x01\x91\x02\x07\x01\x9A\x01\x02\x02\x02\x00\x00\x00\xD4\x00\x0D\x07\x00\x02\x01\x02\x02\x02\x02\x07\x01\x91\x02\x07\x01\x9A\x01\x02\x02\x02\x00\x01\x07\x01\x91\x00\xED\x00\x0D\x07\x00\x02\x01\x02\x02\x02\x02\x07\x01\x91\x02\x07\x01\x9A\x01\x02\x02\x02\x00\x00\x01\x2D\x00\x0D\x07\x00\x02\x01\x02\x02\x02\x02\x07\x01\x91\x02\x07\x01\x9A\x01\x02\x02\x02\x00\x00\x01\x4C\x00\x10\x07\x00\x02\x01\x02\x02\x02\x02\x07\x00\x62\x02\x01\x01\x02\x02\x02\x01\x01\x01\x00\x00\x02\x0B\x00\x13\x07\x00\x02\x01\x02\x02\x02\x02\x07\x00\x62\x02\x01\x01\x02\x02\x02\x01\x01\x01\x07\x00\x6B\x02\x02\x00\x00\x02\x15\x00\x13\x07\x00\x02\x01\x02\x02\x02\x02\x07\x00\x62\x02\x01\x01\x02\x02\x02\x01\x01\x01\x07\x00\x6B\x02\x02\x00\x01\x07\x00\x6B\x02\x65\x00\x13\x07\x00\x02\x01\x02\x02\x02\x02\x07\x00\x62\x02\x01\x01\x02\x02\x02\x01\x01\x01\x07\x01\xB8\x02\x02\x00\x00\x02\xB6\x00\x13\x07\x00\x02\x01\x02\x02\x02\x02\x07\x00\x62\x02\x01\x01\x02\x02\x02\x01\x01\x01\x07\x01\xB8\x02\x02\x00\x00\x02\xC6\x00\x10\x07\x00\x02\x01\x02\x02\x02\x02\x07\x00\x62\x02\x01\x01\x02\x02\x02\x01\x01\x01\x00\x00'
    .end code
.end method

.method private method481 : (IF)LDc;
    .code stack 6 locals 9
L0:     new Dc
L3:     dup
L4:     iload_1
L5:     invokestatic Method java/lang/Integer valueOf (I)Ljava/lang/Integer;
L8:     fload_2
L9:     invokestatic Method java/lang/Float valueOf (F)Ljava/lang/Float;
L12:    invokespecial Method Dc <init> (Ljava/lang/Object;Ljava/lang/Object;)V
L15:    astore_3
L16:    getstatic Field od new Ljava/util/HashMap;
L19:    aload_3
L20:    invokevirtual Method java/util/HashMap get (Ljava/lang/Object;)Ljava/lang/Object;
L23:    checkcast Dc
L26:    dup
L27:    astore 4
L29:    ifnull L36
L32:    aload 4
L34:    areturn
L35:    athrow
L36:    iload_1
L37:    iconst_2
L38:    iconst_1
L39:    dup
L40:    pop2
L41:    if_icmpgt L88
L44:    aload_0
L45:    getfield Field od field975 LId;
L48:    getstatic Field Id field639 LId;
L51:    if_acmpeq L88
L54:    aload_0
L55:    getfield Field od field975 LId;
L58:    getstatic Field Id field636 LId;
L61:    if_acmpeq L88
L64:    new Dc
L67:    dup
L68:    iload_1
L69:    invokestatic Method java/lang/Integer valueOf (I)Ljava/lang/Integer;
L72:    iconst_1
L73:    dup
L74:    dup
L75:    pop2
L76:    invokestatic Method java/lang/Integer valueOf (I)Ljava/lang/Integer;
L79:    invokespecial Method Dc <init> (Ljava/lang/Object;Ljava/lang/Object;)V
L82:    astore 4
L84:    goto L256
L87:    athrow
L88:    iconst_1
L89:    dup
L90:    dup
L91:    pop2
L92:    dup
L93:    istore 5
L95:    i2f
L96:    fload_2
L97:    fdiv
L98:    f2i
L99:    istore 6
L101:   iload 5
L103:   iload 6
L105:   imul
L106:   iload_1
L107:   if_icmpge L126
L110:   iinc 5 1
L113:   iload 5
L115:   i2f
L116:   fload_2
L117:   fdiv
L118:   f2i
L119:   istore 6
L121:   iload 5
L123:   goto L103
L126:   iconst_1
L127:   dup
L128:   dup
L129:   pop2
L130:   dup
L131:   istore 7
L133:   i2f
L134:   fload_2
L135:   fmul
L136:   f2i
L137:   dup
L138:   istore 8
L140:   iload 7
L142:   imul
L143:   iload_1
L144:   if_icmpge L162
L147:   iinc 7 1
L150:   iload 7
L152:   i2f
L153:   fload_2
L154:   fmul
L155:   f2i
L156:   dup
L157:   istore 8
L159:   goto L140
L162:   iload 6
L164:   iload 5
L166:   imul
L167:   iload 7
L169:   iload 8
L171:   imul
L172:   if_icmpge L180
L175:   iload 6
L177:   goto L182
L180:   iload 7
L182:   istore_2
L183:   iload 6
L185:   iload 5
L187:   imul
L188:   iload 7
L190:   iload 8
L192:   imul
L193:   if_icmpge L201
L196:   iload 5
L198:   goto L203
L201:   iload 8
L203:   istore 6
L205:   iload_2
L206:   iconst_1
L207:   dup
L208:   dup
L209:   pop2
L210:   if_icmpne L222
L213:   iload 6
L215:   iload_1
L216:   if_icmple L222
L219:   iload_1
L220:   istore 6
L222:   iload 6
L224:   iconst_1
L225:   dup
L226:   dup
L227:   pop2
L228:   if_icmpne L238
L231:   iload_2
L232:   iload_1
L233:   if_icmple L238
L236:   iload_1
L237:   istore_2
L238:   new Dc
L241:   dup
L242:   iload_2
L243:   invokestatic Method java/lang/Integer valueOf (I)Ljava/lang/Integer;
L246:   iload 6
L248:   invokestatic Method java/lang/Integer valueOf (I)Ljava/lang/Integer;
L251:   invokespecial Method Dc <init> (Ljava/lang/Object;Ljava/lang/Object;)V
L254:   astore 4
L256:   getstatic Field od new Ljava/util/HashMap;
L259:   aload_3
L260:   aload 4
L262:   invokevirtual Method java/util/HashMap put (Ljava/lang/Object;Ljava/lang/Object;)Ljava/lang/Object;
L265:   pop
L266:   aload 4
L268:   areturn
L269:   
        .attribute StackMap b'\x00\x0F\x00\x23\x00\x00\x00\x01\x07\x00\xAA\x00\x24\x00\x05\x07\x00\x02\x01\x02\x07\x01\x9A\x07\x01\x9A\x00\x00\x00\x57\x00\x00\x00\x01\x07\x00\xAA\x00\x58\x00\x05\x07\x00\x02\x01\x02\x07\x01\x9A\x07\x01\x9A\x00\x00\x00\x67\x00\x07\x07\x00\x02\x01\x02\x07\x01\x9A\x07\x01\x9A\x01\x01\x00\x01\x01\x00\x7E\x00\x07\x07\x00\x02\x01\x02\x07\x01\x9A\x07\x01\x9A\x01\x01\x00\x00\x00\x8C\x00\x09\x07\x00\x02\x01\x02\x07\x01\x9A\x07\x01\x9A\x01\x01\x01\x01\x00\x01\x01\x00\xA2\x00\x09\x07\x00\x02\x01\x02\x07\x01\x9A\x07\x01\x9A\x01\x01\x01\x01\x00\x00\x00\xB4\x00\x09\x07\x00\x02\x01\x02\x07\x01\x9A\x07\x01\x9A\x01\x01\x01\x01\x00\x00\x00\xB6\x00\x09\x07\x00\x02\x01\x02\x07\x01\x9A\x07\x01\x9A\x01\x01\x01\x01\x00\x01\x01\x00\xC9\x00\x09\x07\x00\x02\x01\x01\x07\x01\x9A\x07\x01\x9A\x01\x01\x01\x01\x00\x00\x00\xCB\x00\x09\x07\x00\x02\x01\x01\x07\x01\x9A\x07\x01\x9A\x01\x01\x01\x01\x00\x01\x01\x00\xDE\x00\x09\x07\x00\x02\x01\x01\x07\x01\x9A\x07\x01\x9A\x01\x01\x01\x01\x00\x00\x00\xEE\x00\x09\x07\x00\x02\x01\x01\x07\x01\x9A\x07\x01\x9A\x01\x01\x01\x01\x00\x00\x01\x00\x00\x05\x07\x00\x02\x01\x00\x07\x01\x9A\x07\x01\x9A\x00\x00'
    .end code
.end method

.method private method74 : ()V
    .code stack 2 locals 3
L0:     aload_0
L1:     getfield Field od field970 Lqd;
L4:     getfield Field qd new Ljava/util/LinkedHashMap;
L7:     invokevirtual Method java/util/LinkedHashMap values ()Ljava/util/Collection;
L10:    invokeinterface InterfaceMethod java/util/Collection iterator ()Ljava/util/Iterator; 1
L15:    astore_1
L16:    aload_1
L17:    invokeinterface InterfaceMethod java/util/Iterator hasNext ()Z 1
L22:    ifeq L84
L25:    aload_1
L26:    invokeinterface InterfaceMethod java/util/Iterator next ()Ljava/lang/Object; 1
L31:    checkcast Rg
L34:    dup
L35:    astore_2
L36:    getfield Field Rg field227 LqE;
L39:    getstatic Field qE field627 LqE;
L42:    if_acmpeq L16
L45:    aload_2
L46:    getfield Field Rg field227 LqE;
L49:    getstatic Field qE try LqE;
L52:    if_acmpeq L16
L55:    aload_2
L56:    getfield Field Rg field227 LqE;
L59:    getstatic Field qE field630 LqE;
L62:    if_acmpeq L16
L65:    aload_2
L66:    getfield Field Rg field227 LqE;
L69:    getstatic Field qE field628 LqE;
L72:    if_acmpeq L16
L75:    aload_0
L76:    aload_2
L77:    invokespecial Method od method477 (LRg;)V
L80:    goto L16
L83:    athrow
L84:    return
L85:    
        .attribute StackMap b'\x00\x03\x00\x10\x00\x02\x07\x00\x02\x07\x00\x62\x00\x00\x00\x53\x00\x00\x00\x01\x07\x00\xAA\x00\x54\x00\x02\x07\x00\x02\x07\x00\x62\x00\x00'
    .end code
.end method

.method public method26 : ()V
    .code stack 4 locals 3
L0:     aload_0
L1:     dup
L2:     invokespecial Method qc method26 ()V
L5:     getfield Field od field972 Ljava/util/LinkedHashMap;
L8:     invokevirtual Method java/util/LinkedHashMap keySet ()Ljava/util/Set;
L11:    invokeinterface InterfaceMethod java/util/Set iterator ()Ljava/util/Iterator; 1
L16:    astore_1
L17:    aload_1
L18:    invokeinterface InterfaceMethod java/util/Iterator hasNext ()Z 1
L23:    ifeq L71
L26:    aload_1
L27:    invokeinterface InterfaceMethod java/util/Iterator next ()Ljava/lang/Object; 1
L32:    checkcast LD
L35:    astore_2
L36:    aload_0
L37:    getfield Field od field974 LmB;
L40:    aload_2
L41:    invokevirtual Method mB method439 (LgB;)Z
L44:    ifne L17
L47:    aload_0
L48:    getfield Field od field976 Ljava/util/HashMap;
L51:    aload_2
L52:    invokevirtual Method java/util/HashMap remove (Ljava/lang/Object;)Ljava/lang/Object;
L55:    aload_1
L56:    aload_0
L57:    aload_2
L58:    invokevirtual Method od method23 (LgB;)V
L61:    invokeinterface InterfaceMethod java/util/Iterator remove ()V 1
L66:    pop
L67:    goto L17
L70:    athrow
L71:    return
L72:    
        .attribute StackMap b'\x00\x03\x00\x11\x00\x02\x07\x00\x02\x07\x00\x62\x00\x00\x00\x46\x00\x00\x00\x01\x07\x00\xAA\x00\x47\x00\x02\x07\x00\x02\x07\x00\x62\x00\x00'
    .end code
.end method

.method public method410 : (Led;)V
    .code stack 6 locals 2
L0:     aload_0
L1:     aload_1
L2:     invokevirtual Method od method138 (Led;)LLD;
L5:     dup
L6:     astore_1
L7:     ifnonnull L12
L10:    return
L11:    athrow
L12:    aload_0
L13:    dup
L14:    dup_x1
L15:    getfield Field od field978 Ljava/util/LinkedList;
L18:    swap
L19:    getfield Field od field978 Ljava/util/LinkedList;
L22:    aload_1
L23:    invokevirtual Method java/util/LinkedList indexOf (Ljava/lang/Object;)I
L26:    aload_0
L27:    getfield Field od field978 Ljava/util/LinkedList;
L30:    invokevirtual Method java/util/LinkedList getLast ()Ljava/lang/Object;
L33:    invokevirtual Method java/util/LinkedList set (ILjava/lang/Object;)Ljava/lang/Object;
L36:    aload_0
L37:    getfield Field od field978 Ljava/util/LinkedList;
L40:    invokevirtual Method java/util/LinkedList removeLast ()Ljava/lang/Object;
L43:    aload_0
L44:    getfield Field od field972 Ljava/util/LinkedHashMap;
L47:    aload_1
L48:    dup
L49:    getfield Field LD field1126 F
L52:    invokestatic Method java/lang/Float valueOf (F)Ljava/lang/Float;
L55:    invokevirtual Method java/util/LinkedHashMap put (Ljava/lang/Object;Ljava/lang/Object;)Ljava/lang/Object;
L58:    pop
L59:    pop2
L60:    getfield Field od field974 LmB;
L63:    ifnull L75
L66:    aload_0
L67:    getfield Field od field974 LmB;
L70:    aload_1
L71:    invokevirtual Method mB method438 (LgB;)LbB;
L74:    pop
L75:    aload_0
L76:    dup
L77:    invokespecial Method od method71 ()V
L80:    invokespecial Method od method94 ()Z
L83:    ifeq L90
L86:    aload_0
L87:    invokespecial Method od method71 ()V
L90:    aload_0
L91:    getfield Field od field974 LmB;
L94:    ifnull L105
L97:    aload_0
L98:    getfield Field od field974 LmB;
L101:   fconst_1
L102:   invokevirtual Method mB method104 (F)V
L105:   return
L106:   
        .attribute StackMap b'\x00\x05\x00\x0B\x00\x00\x00\x01\x07\x00\xAA\x00\x0C\x00\x02\x07\x00\x02\x07\x00\x6B\x00\x00\x00\x4B\x00\x02\x07\x00\x02\x07\x00\x6B\x00\x00\x00\x5A\x00\x02\x07\x00\x02\x07\x00\x6B\x00\x00\x00\x69\x00\x02\x07\x00\x02\x07\x00\x6B\x00\x00'
    .end code
.end method

.method public method142 : (Lqd;)V
    .code stack 7 locals 4
L0:     aload_0
L1:     getfield Field od field970 Lqd;
L4:     aload_0
L5:     dup_x1
L6:     invokevirtual Method qd method401 (LG;)V
L9:     getfield Field od field978 Ljava/util/LinkedList;
L12:    invokevirtual Method java/util/LinkedList iterator ()Ljava/util/Iterator;
L15:    dup
L16:    astore_2
L17:    invokeinterface InterfaceMethod java/util/Iterator hasNext ()Z 1
L22:    ifeq L56
L25:    aload_2
L26:    invokeinterface InterfaceMethod java/util/Iterator next ()Ljava/lang/Object; 1
L31:    checkcast LD
L34:    astore_3
L35:    aload_2
L36:    aload_0
L37:    getfield Field od field972 Ljava/util/LinkedHashMap;
L40:    aload_3
L41:    dup
L42:    getfield Field LD field1126 F
L45:    invokestatic Method java/lang/Float valueOf (F)Ljava/lang/Float;
L48:    invokevirtual Method java/util/LinkedHashMap put (Ljava/lang/Object;Ljava/lang/Object;)Ljava/lang/Object;
L51:    pop
L52:    goto L17
L55:    athrow
L56:    aload_0
L57:    dup
L58:    aload_1
L59:    aload_0
L60:    dup_x2
L61:    aload_0
L62:    dup
L63:    getfield Field od field978 Ljava/util/LinkedList;
L66:    invokevirtual Method java/util/LinkedList clear ()V
L69:    invokespecial Method od method71 ()V
L72:    getfield Field od field974 LmB;
L75:    fconst_1
L76:    invokevirtual Method mB method104 (F)V
L79:    putfield Field od field970 Lqd;
L82:    getfield Field od field970 Lqd;
L85:    aload_0
L86:    getstatic Field mc field387 Lmc;
L89:    invokevirtual Method qd method408 (LG;Lmc;)V
L92:    invokespecial Method od method74 ()V
L95:    return
L96:    
        .attribute StackMap b'\x00\x03\x00\x11\x00\x03\x07\x00\x02\x07\x00\x4F\x07\x00\x62\x00\x01\x07\x00\x62\x00\x37\x00\x00\x00\x01\x07\x00\xAA\x00\x38\x00\x03\x07\x00\x02\x07\x00\x4F\x07\x00\x62\x00\x00'
    .end code
.end method

.method public method138 : (Led;)LLD;
    .code stack 2 locals 4
L0:     aload_0
L1:     getfield Field od field978 Ljava/util/LinkedList;
L4:     invokevirtual Method java/util/LinkedList iterator ()Ljava/util/Iterator;
L7:     astore_2
L8:     aload_2
L9:     invokeinterface InterfaceMethod java/util/Iterator hasNext ()Z 1
L14:    ifeq L45
L17:    aload_2
L18:    invokeinterface InterfaceMethod java/util/Iterator next ()Ljava/lang/Object; 1
L23:    checkcast LD
L26:    dup
L27:    astore_3
L28:    getfield Field LD field137 LRg;
L31:    getfield Field Rg false Led;
L34:    aload_1
L35:    if_acmpne L8
L38:    aload_3
L39:    areturn
L40:    nop
L41:    nop
L42:    nop
L43:    nop
L44:    athrow
L45:    aconst_null
L46:    areturn
L47:    
        .attribute StackMap b'\x00\x03\x00\x08\x00\x03\x07\x00\x02\x07\x01\xF7\x07\x00\x62\x00\x00\x00\x28\x00\x00\x00\x01\x07\x00\xAA\x00\x2D\x00\x03\x07\x00\x02\x07\x01\xF7\x07\x00\x62\x00\x00'
    .end code
.end method

.method public static <clinit> : ()V
    .code stack 2 locals 0
L0:     new java/util/HashMap
L3:     dup
L4:     invokespecial Method java/util/HashMap <init> ()V
L7:     putstatic Field od new Ljava/util/HashMap;
L10:    return
L11:    
    .end code
.end method

.method public static readenemySFXtoggle : ()I
    .code stack 5 locals 3
L0:     iconst_1
L1:     istore_0
        .catch java/io/IOException from L2 to L30 using L33
L2:     new java/io/BufferedReader
L5:     dup
L6:     new java/io/FileReader
L9:     dup
L10:    ldc_w "settings/od-enable-enemy-sounds.txt"
L13:    invokespecial Method java/io/FileReader <init> (Ljava/lang/String;)V
L16:    invokespecial Method java/io/BufferedReader <init> (Ljava/io/Reader;)V
L19:    astore_1
L20:    aload_1
L21:    invokevirtual Method java/io/BufferedReader readLine ()Ljava/lang/String;
L24:    astore_2
L25:    aload_2
L26:    invokestatic Method java/lang/Integer parseInt (Ljava/lang/String;)I
L29:    istore_0
L30:    goto L38
L33:    astore_1
L34:    aload_1
L35:    invokevirtual Method java/io/IOException printStackTrace ()V
L38:    iload_0
L39:    ireturn
L40:    
        .attribute StackMap b'\x00\x02\x00\x21\x00\x01\x01\x00\x01\x07\x01\xFB\x00\x26\x00\x02\x01\x07\x01\xB8\x00\x00'
        .linenumbertable
            L0 13
            L2 15
            L20 16
            L25 17
            L30 22
            L33 20
            L34 21
            L38 23
        .end linenumbertable
    .end code
.end method
.innerclasses
    Id sb [0] public static final enum
    oc fc [0] public static final enum
    xc mB [0] public static final enum
    bB mB [0] private static
.end innerclasses
.end class
