.version 49 0
.class public final super pB
.super java/lang/Object
.implements h
.field public final synthetic field1589 LFE;
.field public final synthetic field1590 Led;
.field public final synthetic field1591 Lqc;
.field public final synthetic field1592 Led;

.method public <init> : (LFE;Lqc;Led;Led;)V
    .code stack 9 locals 5
L0:     aload 4
L2:     aload_0
L3:     dup_x1
L4:     dup_x2
L5:     aload_3
L6:     aload_2
L7:     aload_0
L8:     dup_x1
L9:     aload_1
L10:    putfield Field pB field1589 LFE;
L13:    putfield Field pB field1591 Lqc;
L16:    putfield Field pB field1590 Led;
L19:    putfield Field pB field1592 Led;
L22:    invokespecial Method java/lang/Object <init> ()V
L25:    return
L26:    
    .end code
.end method

.method public method728 : (LgB;)V
    .code stack 5 locals 2
L0:     aload_0
L1:     getfield Field pB field1589 LFE;
L4:     aload_0
L5:     dup_x1
L6:     getfield Field pB field1591 Lqc;
L9:     invokevirtual Method qc method51 ()LbC;
L12:    invokevirtual Method FE method203 (LbC;)V
L15:    getfield Field pB field1589 LFE;
L18:    new HD
L21:    dup
L22:    aload_0
L23:    dup
L24:    getfield Field pB field1590 Led;
L27:    swap
L28:    getfield Field pB field1592 Led;
L31:    invokespecial Method HD <init> (Led;Led;)V
L34:    invokevirtual Method FE method444 (LbC;)V
L37:    return
L38:    
    .end code
.end method
.innerclasses
    pB [0] [0] static
.end innerclasses
.enclosing method eD method1130 (LFE;Led;Lqd;)Ljava/util/List;
.end class
