.version 49 0
.class public final super enum Pc
.super java/lang/Enum
.field public char Ljava/lang/String;
.field public static final enum else LPc;
.field private static final synthetic "enum" [LPc;
.field public static final enum do LPc;

.method private <init> : (Ljava/lang/String;ILjava/lang/String;)V
    .code stack 5 locals 4
L0:     aload_3
L1:     aload_0
L2:     dup_x1
L3:     aload_1
L4:     iload_2
L5:     invokespecial Method java/lang/Enum <init> (Ljava/lang/String;I)V
L8:     putfield Field Pc char Ljava/lang/String;
L11:    return
L12:    
    .end code
.end method

.method public static <clinit> : ()V
    .code stack 6 locals 0
L0:     new Pc
L3:     dup
L4:     ldc "PLAYER_1"
L6:     iconst_0
L7:     iconst_1
L8:     dup
L9:     pop2
L10:    ldc "p1"
L12:    invokespecial Method Pc <init> (Ljava/lang/String;ILjava/lang/String;)V
L15:    putstatic Field Pc do LPc;
L18:    new Pc
L21:    dup
L22:    ldc "PLAYER_2"
L24:    iconst_1
L25:    dup
L26:    dup
L27:    pop2
L28:    ldc "p2"
L30:    invokespecial Method Pc <init> (Ljava/lang/String;ILjava/lang/String;)V
L33:    putstatic Field Pc else LPc;
L36:    iconst_2
L37:    iconst_1
L38:    dup
L39:    pop2
L40:    anewarray Pc
L43:    iconst_1
L44:    dup
L45:    pop2
L46:    dup
L47:    iconst_0
L48:    iconst_1
L49:    dup
L50:    pop2
L51:    getstatic Field Pc do LPc;
L54:    aastore
L55:    dup
L56:    iconst_1
L57:    dup
L58:    dup
L59:    pop2
L60:    getstatic Field Pc else LPc;
L63:    aastore
L64:    putstatic Field Pc "enum" [LPc;
L67:    return
L68:    
    .end code
.end method

.method public static values : ()[LPc;
    .code stack 1 locals 0
L0:     getstatic Field Pc "enum" [LPc;
L3:     invokevirtual Method [LPc; clone ()Ljava/lang/Object;
L6:     checkcast [LPc;
L9:     areturn
L10:    
    .end code
.end method

.method public static valueOf : (Ljava/lang/String;)LPc;
    .code stack 2 locals 1
L0:     ldc Class Pc
L2:     aload_0
L3:     invokestatic Method java/lang/Enum valueOf (Ljava/lang/Class;Ljava/lang/String;)Ljava/lang/Enum;
L6:     checkcast Pc
L9:     areturn
L10:    
    .end code
.end method
.innerclasses
    Pc JB [0] public static final enum
.end innerclasses
.end class
