.version 49 0
.class public final super pd
.super java/lang/Object
.implements h
.field public final synthetic field1616 Lqc;
.field public final synthetic field1617 LzD;
.field public final synthetic field1618 LGd;
.field public final synthetic field1619 LDF;

.method public method728 : (LgB;)V
    .code stack 5 locals 2
L0:     ldc "t"
L2:     aload_0
L3:     getfield Field pd field1619 LDF;
L6:     new java/lang/StringBuilder
L9:     dup
L10:    invokespecial Method java/lang/StringBuilder <init> ()V
L13:    iconst_0
L14:    ldc ""
L16:    invokevirtual Method java/lang/StringBuilder insert (ILjava/lang/String;)Ljava/lang/StringBuilder;
L19:    aload_0
L20:    getfield Field pd field1617 LzD;
L23:    invokevirtual Method zD method183 ()I
L26:    invokevirtual Method java/lang/StringBuilder append (I)Ljava/lang/StringBuilder;
L29:    invokevirtual Method java/lang/StringBuilder toString ()Ljava/lang/String;
L32:    invokevirtual Method DF method12 (Ljava/lang/String;)V
L35:    aload_0
L36:    dup_x1
L37:    getfield Field pd field1617 LzD;
L40:    invokevirtual Method zD method183 ()I
L43:    invokestatic Method JB method827 (Ljava/lang/String;I)V
L46:    getfield Field pd field1616 Lqc;
L49:    invokevirtual Method qc method21 ()V
L52:    return
L53:    
    .end code
.end method

.method public <init> : (LGd;LDF;LzD;Lqc;)V
    .code stack 9 locals 5
L0:     aload 4
L2:     aload_0
L3:     dup_x1
L4:     dup_x2
L5:     aload_3
L6:     aload_2
L7:     aload_0
L8:     dup_x1
L9:     aload_1
L10:    putfield Field pd field1618 LGd;
L13:    putfield Field pd field1619 LDF;
L16:    putfield Field pd field1617 LzD;
L19:    putfield Field pd field1616 Lqc;
L22:    invokespecial Method java/lang/Object <init> ()V
L25:    return
L26:    
    .end code
.end method
.innerclasses
    pd [0] [0]
.end innerclasses
.enclosing method Gd method205 ()Lqc;
.end class
