.version 49 0
.class public final super pD
.super SB
.field public final synthetic try Led;
.field public final synthetic const Lqc;
.field public final synthetic new LDF;
.field public final synthetic null LxD;
.field public final synthetic this LDF;
.field public char Z
.field public final synthetic else Led;
.field public final synthetic "enum" LDF;
.field public final synthetic do LDF;

.method public <init> : (LgB;FLed;LxD;LDF;LDF;LDF;LDF;Led;Lqc;)V
    .code stack 21 locals 11
L0:     iconst_0
L1:     aload_0
L2:     dup_x1
L3:     aload_1
L4:     fload_2
L5:     aload 10
L7:     aload_0
L8:     dup_x1
L9:     aload 9
L11:    aload 8
L13:    aload_0
L14:    dup_x1
L15:    aload 7
L17:    aload 6
L19:    aload_0
L20:    dup_x1
L21:    aload 5
L23:    aload 4
L25:    aload_0
L26:    dup_x1
L27:    aload_3
L28:    putfield Field pD try Led;
L31:    putfield Field pD null LxD;
L34:    putfield Field pD do LDF;
L37:    putfield Field pD "enum" LDF;
L40:    putfield Field pD new LDF;
L43:    putfield Field pD this LDF;
L46:    putfield Field pD else Led;
L49:    putfield Field pD const Lqc;
L52:    invokespecial Method SB <init> (LgB;F)V
L55:    iconst_1
L56:    dup
L57:    pop2
L58:    putfield Field pD char Z
L61:    return
L62:    
    .end code
.end method

.method public background : (ZF)V
    .code stack 5 locals 3
L0:     aload_0
L1:     dup
L2:     iload_1
L3:     fload_2
L4:     invokespecial Method SB background (ZF)V
L7:     getfield Field pD char Z
L10:    ifne L39
L13:    getstatic Field Kc else LKc;
L16:    aload_0
L17:    getfield Field pD try Led;
L20:    new rD
L23:    dup
L24:    aload_0
L25:    invokespecial Method rD <init> (LpD;)V
L28:    invokevirtual Method Kc break (Led;LK;)V
L31:    aload_0
L32:    iconst_1
L33:    dup
L34:    dup
L35:    pop2
L36:    putfield Field pD char Z
L39:    return
L40:    
        .attribute StackMap b'\x00\x01\x00\x27\x00\x03\x07\x00\x02\x01\x02\x00\x00'
    .end code
.end method
.innerclasses
    pD [0] [0] static
    rD [0] [0]
.end innerclasses
.enclosing method eD break (LFE;Led;Lqd;)Ljava/util/List;
.end class
