.version 46 0
.class public final super QA
.super java/applet/Applet
.field private static throws Ljava/io/File;
.field private static "static" Ljava/util/Set;
.field private static final continue Ljava/lang/String;
.field private extends Ljava/lang/String;
.field private static float Ljava/io/File;
.field private static "final" Ljava/util/Map;
.field private static catch Ljava/io/File;
.field private static false Z
.field public static class Ljava/lang/Class; .fieldattributes
    .synthetic
.end fieldattributes
.field private static final if Ljava/lang/String;
.field private true Ljavax/swing/JPanel;
.field private for Ljava/applet/Applet;
.field private static case Ljava/util/List;
.field private byte Ljava/lang/String;
.field private static final "super" Ljava/lang/String;
.field private static int Ljava/lang/String;
.field public static short Z
.field private goto Ljavax/swing/JProgressBar;
.field private static break Ljava/io/File;
.field private static long Z
.field private static void Ljava/net/URL;
.field private try Z
.field private static const Ljava/lang/String;
.field private static new Ljava/lang/String;
.field private null Z
.field private static this Ljava/lang/String;
.field private char Z
.field private else Ljava/net/URL;
.field public static "enum" Z
.field private static do Ljava/util/Set;

.method public class : ()Ljava/applet/Applet;
    .code stack 1 locals 1
L0:     aload_0
L1:     getfield Field QA for Ljava/applet/Applet;
L4:     areturn
L5:     
    .end code
.end method

.method public destroy : ()V
    .code stack 1 locals 1
L0:     aload_0
L1:     getfield Field QA for Ljava/applet/Applet;
L4:     ifnull L14
L7:     aload_0
L8:     getfield Field QA for Ljava/applet/Applet;
L11:    invokevirtual Method java/applet/Applet destroy ()V
L14:    return
L15:    
        .attribute StackMap b'\x00\x01\x00\x0E\x00\x01\x07\x00\x02\x00\x00'
    .end code
.end method

.method private break : (Ljava/net/URLConnection;Ljava/io/File;)I
    .code stack 5 locals 5
L0:     iconst_0
L1:     iconst_1
L2:     dup
L3:     pop2
L4:     istore_3
L5:     new java/io/BufferedInputStream
L8:     dup
L9:     aload_1
L10:    invokevirtual Method java/net/URLConnection getInputStream ()Ljava/io/InputStream;
L13:    invokespecial Method java/io/BufferedInputStream <init> (Ljava/io/InputStream;)V
L16:    astore 4
L18:    new java/io/BufferedOutputStream
L21:    dup
L22:    new java/io/FileOutputStream
L25:    dup
L26:    aload_2
L27:    invokespecial Method java/io/FileOutputStream <init> (Ljava/io/File;)V
L30:    invokespecial Method java/io/BufferedOutputStream <init> (Ljava/io/OutputStream;)V
L33:    astore_2
        .catch [0] from L34 to L49 using L50
        .catch [0] from L18 to L49 using L65
L34:    aload_0
L35:    aload 4
L37:    aload_2
L38:    aload_1
L39:    invokevirtual Method java/net/URLConnection getContentLength ()I
L42:    invokespecial Method QA break (Ljava/io/InputStream;Ljava/io/OutputStream;I)I
L45:    istore_3
L46:    goto L57
L49:    athrow
        .catch [0] from L50 to L64 using L65
L50:    astore_1
L51:    aload_1
L52:    aload_2
L53:    invokevirtual Method java/io/OutputStream close ()V
L56:    athrow
L57:    aload_2
L58:    invokevirtual Method java/io/OutputStream close ()V
L61:    goto L73
L64:    athrow
L65:    astore_1
L66:    aload_1
L67:    aload 4
L69:    invokevirtual Method java/io/InputStream close ()V
L72:    athrow
L73:    aload 4
L75:    invokevirtual Method java/io/InputStream close ()V
L78:    iload_3
L79:    ireturn
L80:    
        .attribute StackMap b'\x00\x06\x00\x31\x00\x00\x00\x01\x07\x00\x73\x00\x32\x00\x05\x07\x00\x02\x07\x00\x58\x07\x00\x62\x01\x07\x00\x56\x00\x01\x07\x00\x73\x00\x39\x00\x05\x07\x00\x02\x07\x00\x58\x07\x00\x62\x01\x07\x00\x56\x00\x00\x00\x40\x00\x00\x00\x01\x07\x00\x73\x00\x41\x00\x05\x07\x00\x02\x07\x00\x7A\x07\x00\x7A\x01\x07\x00\x56\x00\x01\x07\x00\x73\x00\x49\x00\x05\x07\x00\x02\x07\x00\x58\x07\x00\x62\x01\x07\x00\x56\x00\x00'
    .end code
    .exceptions java/io/IOException
.end method

.method public static short : (LQA;)V
    .code stack 1 locals 1
L0:     aload_0
L1:     invokespecial Method QA const ()V
L4:     return
L5:     
    .end code
    .synthetic
.end method

.method private const : (Ljava/net/URL;)V
    .code stack 7 locals 9
L0:     aload_1
L1:     invokevirtual Method java/net/URL toExternalForm ()Ljava/lang/String;
L4:     bipush 92
L6:     iconst_1
L7:     dup
L8:     pop2
L9:     bipush 47
L11:    iconst_1
L12:    dup
L13:    pop2
L14:    invokevirtual Method java/lang/String replace (CC)Ljava/lang/String;
L17:    dup
L18:    ldc "/"
L20:    invokevirtual Method java/lang/String lastIndexOf (Ljava/lang/String;)I
L23:    iconst_1
L24:    dup
L25:    dup
L26:    pop2
L27:    iadd
L28:    invokevirtual Method java/lang/String substring (I)Ljava/lang/String;
L31:    astore_2
L32:    new java/io/File
L35:    dup
L36:    getstatic Field QA catch Ljava/io/File;
L39:    aload_2
L40:    invokespecial Method java/io/File <init> (Ljava/io/File;Ljava/lang/String;)V
L43:    dup
L44:    astore_3
L45:    invokevirtual Method java/io/File isDirectory ()Z
L48:    ifeq L78
L51:    new java/io/IOException
L54:    dup
L55:    new java/lang/StringBuffer
L58:    dup
L59:    invokespecial Method java/lang/StringBuffer <init> ()V
L62:    aload_3
L63:    invokevirtual Method java/lang/StringBuffer append (Ljava/lang/Object;)Ljava/lang/StringBuffer;
L66:    ldc " is a directory"
L68:    invokevirtual Method java/lang/StringBuffer append (Ljava/lang/String;)Ljava/lang/StringBuffer;
L71:    invokevirtual Method java/lang/StringBuffer toString ()Ljava/lang/String;
L74:    invokespecial Method java/io/IOException <init> (Ljava/lang/String;)V
L77:    athrow
L78:    aload_2
L79:    dup
L80:    astore 4
L82:    ldc "."
L84:    invokevirtual Method java/lang/String lastIndexOf (Ljava/lang/String;)I
L87:    dup
L88:    istore 5
L90:    ifle L105
L93:    aload_2
L94:    iconst_0
L95:    iconst_1
L96:    dup
L97:    pop2
L98:    iload 5
L100:   invokevirtual Method java/lang/String substring (II)Ljava/lang/String;
L103:   astore 4
L105:   new java/lang/StringBuffer
L108:   dup
L109:   aload 4
L111:   invokestatic Method java/lang/String valueOf (Ljava/lang/Object;)Ljava/lang/String;
L114:   invokespecial Method java/lang/StringBuffer <init> (Ljava/lang/String;)V
L117:   ldc ".idx"
L119:   invokevirtual Method java/lang/StringBuffer append (Ljava/lang/String;)Ljava/lang/StringBuffer;
L122:   invokevirtual Method java/lang/StringBuffer toString ()Ljava/lang/String;
L125:   astore 4
L127:   new java/io/File
L130:   dup
L131:   getstatic Field QA catch Ljava/io/File;
L134:   aload 4
L136:   invokespecial Method java/io/File <init> (Ljava/io/File;Ljava/lang/String;)V
L139:   astore 4
L141:   getstatic Field QA short Z
L144:   ifeq L192
L147:   getstatic Field java/lang/System err Ljava/io/PrintStream;
L150:   new java/lang/StringBuffer
L153:   dup
L154:   ldc "nativeFile = "
L156:   invokespecial Method java/lang/StringBuffer <init> (Ljava/lang/String;)V
L159:   aload_3
L160:   invokevirtual Method java/lang/StringBuffer append (Ljava/lang/Object;)Ljava/lang/StringBuffer;
L163:   invokevirtual Method java/lang/StringBuffer toString ()Ljava/lang/String;
L166:   invokevirtual Method java/io/PrintStream println (Ljava/lang/String;)V
L169:   getstatic Field java/lang/System err Ljava/io/PrintStream;
L172:   new java/lang/StringBuffer
L175:   dup
L176:   ldc "indexFile = "
L178:   invokespecial Method java/lang/StringBuffer <init> (Ljava/lang/String;)V
L181:   aload 4
L183:   invokevirtual Method java/lang/StringBuffer append (Ljava/lang/Object;)Ljava/lang/StringBuffer;
L186:   invokevirtual Method java/lang/StringBuffer toString ()Ljava/lang/String;
L189:   invokevirtual Method java/io/PrintStream println (Ljava/lang/String;)V
L192:   aload_0
L193:   iconst_0
L194:   aload_0
L195:   new java/lang/StringBuffer
L198:   dup
L199:   ldc "Loading: "
L201:   invokespecial Method java/lang/StringBuffer <init> (Ljava/lang/String;)V
L204:   aload_2
L205:   invokevirtual Method java/lang/StringBuffer append (Ljava/lang/String;)Ljava/lang/StringBuffer;
L208:   invokevirtual Method java/lang/StringBuffer toString ()Ljava/lang/String;
L211:   invokespecial Method QA const (Ljava/lang/String;)V
L214:   iconst_1
L215:   dup
L216:   pop2
L217:   invokespecial Method QA break (I)V
L220:   aload_1
L221:   invokevirtual Method java/net/URL openConnection ()Ljava/net/URLConnection;
L224:   dup
L225:   astore_1
L226:   dup
L227:   invokevirtual Method java/net/URLConnection connect ()V
L230:   invokevirtual Method java/net/URLConnection getHeaderFields ()Ljava/util/Map;
L233:   astore 5
L235:   getstatic Field QA short Z
L238:   ifeq L405
L241:   aload 5
L243:   invokeinterface InterfaceMethod java/util/Map entrySet ()Ljava/util/Set; 1
L248:   invokeinterface InterfaceMethod java/util/Set iterator ()Ljava/util/Iterator; 1
L253:   dup
L254:   astore 6
L256:   goto L391
L259:   athrow
L260:   aload 6
L262:   invokeinterface InterfaceMethod java/util/Iterator next ()Ljava/lang/Object; 1
L267:   checkcast java/util/Map$Entry
L270:   dup
L271:   astore 7
L273:   invokeinterface InterfaceMethod java/util/Map$Entry getValue ()Ljava/lang/Object; 1
L278:   checkcast java/util/List
L281:   invokeinterface InterfaceMethod java/util/List iterator ()Ljava/util/Iterator; 1
L286:   dup
L287:   astore 5
L289:   goto L375
L292:   athrow
L293:   aload 5
L295:   invokeinterface InterfaceMethod java/util/Iterator next ()Ljava/lang/Object; 1
L300:   checkcast java/lang/String
L303:   astore 8
L305:   aload 7
L307:   invokeinterface InterfaceMethod java/util/Map$Entry getKey ()Ljava/lang/Object; 1
L312:   ifnull L346
L315:   getstatic Field java/lang/System err Ljava/io/PrintStream;
L318:   new java/lang/StringBuffer
L321:   dup
L322:   invokespecial Method java/lang/StringBuffer <init> ()V
L325:   aload 7
L327:   invokeinterface InterfaceMethod java/util/Map$Entry getKey ()Ljava/lang/Object; 1
L332:   invokevirtual Method java/lang/StringBuffer append (Ljava/lang/Object;)Ljava/lang/StringBuffer;
L335:   ldc ": "
L337:   invokevirtual Method java/lang/StringBuffer append (Ljava/lang/String;)Ljava/lang/StringBuffer;
L340:   invokevirtual Method java/lang/StringBuffer toString ()Ljava/lang/String;
L343:   invokevirtual Method java/io/PrintStream print (Ljava/lang/String;)V
L346:   getstatic Field java/lang/System err Ljava/io/PrintStream;
L349:   new java/lang/StringBuffer
L352:   dup
L353:   aload 8
L355:   invokestatic Method java/lang/String valueOf (Ljava/lang/Object;)Ljava/lang/String;
L358:   invokespecial Method java/lang/StringBuffer <init> (Ljava/lang/String;)V
L361:   ldc_w " "
L364:   invokevirtual Method java/lang/StringBuffer append (Ljava/lang/String;)Ljava/lang/StringBuffer;
L367:   invokevirtual Method java/lang/StringBuffer toString ()Ljava/lang/String;
L370:   invokevirtual Method java/io/PrintStream print (Ljava/lang/String;)V
L373:   aload 5
L375:   invokeinterface InterfaceMethod java/util/Iterator hasNext ()Z 1
L380:   ifne L293
L383:   getstatic Field java/lang/System err Ljava/io/PrintStream;
L386:   invokevirtual Method java/io/PrintStream println ()V
L389:   aload 6
L391:   invokeinterface InterfaceMethod java/util/Iterator hasNext ()Z 1
L396:   ifne L260
L399:   getstatic Field java/lang/System err Ljava/io/PrintStream;
L402:   invokevirtual Method java/io/PrintStream println ()V
L405:   getstatic Field java/lang/System out Ljava/io/PrintStream;
L408:   dup
L409:   astore 6
L411:   monitorenter
        .catch [0] from L412 to L423 using L427
L412:   aload_0
L413:   aload_1
L414:   aload_3
L415:   aload 4
L417:   invokespecial Method QA break (Ljava/net/URLConnection;Ljava/io/File;Ljava/io/File;)V
L420:   aload 6
L422:   monitorexit
L423:   aload_0
L424:   goto L432
        .catch [0] from L427 to L430 using L427
L427:   aload 6
L429:   monitorexit
L430:   athrow
L431:   athrow
L432:   new java/lang/StringBuffer
L435:   dup
L436:   ldc_w "Unpacking: "
L439:   invokespecial Method java/lang/StringBuffer <init> (Ljava/lang/String;)V
L442:   aload_2
L443:   invokevirtual Method java/lang/StringBuffer append (Ljava/lang/String;)Ljava/lang/StringBuffer;
L446:   invokevirtual Method java/lang/StringBuffer toString ()Ljava/lang/String;
L449:   invokespecial Method QA const (Ljava/lang/String;)V
L452:   aload_0
L453:   dup
L454:   dup2
L455:   iconst_0
L456:   iconst_1
L457:   dup
L458:   pop2
L459:   invokespecial Method QA break (I)V
L462:   new java/util/jar/JarFile
L465:   dup
L466:   aload_3
L467:   invokespecial Method java/util/jar/JarFile <init> (Ljava/io/File;)V
L470:   dup
L471:   astore 6
L473:   invokespecial Method QA break (Ljava/util/jar/JarFile;)Ljava/util/Set;
L476:   astore 7
L478:   aload 6
L480:   aload 7
L482:   invokespecial Method QA break (Ljava/util/jar/JarFile;Ljava/util/Set;)V
L485:   aload 6
L487:   aload 7
L489:   invokespecial Method QA else (Ljava/util/jar/JarFile;Ljava/util/Set;)V
L492:   getstatic Field QA short Z
L495:   ifeq L504
L498:   getstatic Field java/lang/System err Ljava/io/PrintStream;
L501:   invokevirtual Method java/io/PrintStream println ()V
L504:   return
L505:   
        .attribute StackMap b'\x00\x0F\x00\x4E\x00\x04\x07\x00\x02\x07\x00\x83\x07\x00\x89\x07\x00\x99\x00\x00\x00\x69\x00\x06\x07\x00\x02\x07\x00\x83\x07\x00\x89\x07\x00\x99\x07\x00\x89\x01\x00\x00\x00\xC0\x00\x06\x07\x00\x02\x07\x00\x83\x07\x00\x89\x07\x00\x99\x07\x00\x99\x01\x00\x00\x01\x03\x00\x00\x00\x01\x07\x00\x73\x01\x04\x00\x07\x07\x00\x02\x07\x00\x58\x07\x00\x89\x07\x00\x99\x07\x00\x99\x07\x00\x7A\x07\x00\xF0\x00\x00\x01\x24\x00\x00\x00\x01\x07\x00\x73\x01\x25\x00\x08\x07\x00\x02\x07\x00\x58\x07\x00\x89\x07\x00\x99\x07\x00\x99\x07\x00\xF0\x07\x00\xF0\x07\x00\x1A\x00\x00\x01\x5A\x00\x09\x07\x00\x02\x07\x00\x58\x07\x00\x89\x07\x00\x99\x07\x00\x99\x07\x00\xF0\x07\x00\xF0\x07\x00\x1A\x07\x00\x89\x00\x00\x01\x77\x00\x08\x07\x00\x02\x07\x00\x58\x07\x00\x89\x07\x00\x99\x07\x00\x99\x07\x00\xF0\x07\x00\xF0\x07\x00\x1A\x00\x01\x07\x00\xF0\x01\x87\x00\x07\x07\x00\x02\x07\x00\x58\x07\x00\x89\x07\x00\x99\x07\x00\x99\x07\x00\x7A\x07\x00\xF0\x00\x01\x07\x00\xF0\x01\x95\x00\x06\x07\x00\x02\x07\x00\x58\x07\x00\x89\x07\x00\x99\x07\x00\x99\x07\x00\x7A\x00\x00\x01\xAB\x00\x07\x07\x00\x02\x07\x00\x58\x07\x00\x89\x07\x00\x99\x07\x00\x99\x07\x00\x7A\x07\x00\xCD\x00\x01\x07\x00\x73\x01\xAF\x00\x00\x00\x01\x07\x00\x73\x01\xB0\x00\x07\x07\x00\x02\x07\x00\x58\x07\x00\x89\x07\x00\x99\x07\x00\x99\x07\x00\x7A\x07\x00\xCD\x00\x01\x07\x00\x02\x01\xF8\x00\x08\x07\x00\x02\x07\x00\x58\x07\x00\x89\x07\x00\x99\x07\x00\x99\x07\x00\x7A\x07\x01\x13\x07\x00\xEA\x00\x00'
    .end code
    .exceptions java/io/IOException
.end method

.method public static const : (LQA;)V
    .code stack 1 locals 1
L0:     aload_0
L1:     invokespecial Method QA char ()V
L4:     return
L5:     
    .end code
    .synthetic
.end method

.method private else : (Ljava/util/jar/JarFile;Ljava/util/Set;)V
    .code stack 6 locals 8
L0:     getstatic Field QA "enum" Z
L3:     ifeq L15
L6:     getstatic Field java/lang/System err Ljava/io/PrintStream;
L9:     ldc_w "extractNativeLibs:"
L12:    invokevirtual Method java/io/PrintStream println (Ljava/lang/String;)V
L15:    aload_1
L16:    invokevirtual Method java/util/jar/JarFile entries ()Ljava/util/Enumeration;
L19:    dup
L20:    astore_3
L21:    goto L240
L24:    athrow
L25:    aload_3
L26:    invokeinterface InterfaceMethod java/util/Enumeration nextElement ()Ljava/lang/Object; 1
L31:    checkcast java/util/jar/JarEntry
L34:    dup
L35:    astore 4
L37:    invokevirtual Method java/util/jar/JarEntry getName ()Ljava/lang/String;
L40:    astore 5
L42:    getstatic Field QA short Z
L45:    ifeq L72
L48:    getstatic Field java/lang/System err Ljava/io/PrintStream;
L51:    new java/lang/StringBuffer
L54:    dup
L55:    ldc_w "JarEntry : "
L58:    invokespecial Method java/lang/StringBuffer <init> (Ljava/lang/String;)V
L61:    aload 5
L63:    invokevirtual Method java/lang/StringBuffer append (Ljava/lang/String;)Ljava/lang/StringBuffer;
L66:    invokevirtual Method java/lang/StringBuffer toString ()Ljava/lang/String;
L69:    invokevirtual Method java/io/PrintStream println (Ljava/lang/String;)V
L72:    aload_2
L73:    aload 5
L75:    invokeinterface InterfaceMethod java/util/Set contains (Ljava/lang/Object;)Z 2
L80:    ifeq L239
L83:    getstatic Field QA const Ljava/lang/String;
L86:    invokevirtual Method java/lang/String length ()I
L89:    aload 5
L91:    dup_x1
L92:    invokevirtual Method java/lang/String length ()I
L95:    getstatic Field QA this Ljava/lang/String;
L98:    invokevirtual Method java/lang/String length ()I
L101:   isub
L102:   invokevirtual Method java/lang/String substring (II)Ljava/lang/String;
L105:   astore 6
L107:   getstatic Field QA "enum" Z
L110:   ifeq L154
L113:   getstatic Field java/lang/System err Ljava/io/PrintStream;
L116:   new java/lang/StringBuffer
L119:   dup
L120:   ldc_w "EXTRACT: "
L123:   invokespecial Method java/lang/StringBuffer <init> (Ljava/lang/String;)V
L126:   aload 5
L128:   invokevirtual Method java/lang/StringBuffer append (Ljava/lang/String;)Ljava/lang/StringBuffer;
L131:   ldc_w "("
L134:   invokevirtual Method java/lang/StringBuffer append (Ljava/lang/String;)Ljava/lang/StringBuffer;
L137:   aload 6
L139:   invokevirtual Method java/lang/StringBuffer append (Ljava/lang/String;)Ljava/lang/StringBuffer;
L142:   ldc_w ")"
L145:   invokevirtual Method java/lang/StringBuffer append (Ljava/lang/String;)Ljava/lang/StringBuffer;
L148:   invokevirtual Method java/lang/StringBuffer toString ()Ljava/lang/String;
L151:   invokevirtual Method java/io/PrintStream println (Ljava/lang/String;)V
L154:   new java/io/File
L157:   dup
L158:   getstatic Field QA throws Ljava/io/File;
L161:   aload 5
L163:   invokespecial Method java/io/File <init> (Ljava/io/File;Ljava/lang/String;)V
L166:   astore 5
L168:   new java/io/BufferedInputStream
L171:   dup
L172:   aload_1
L173:   aload 4
L175:   invokevirtual Method java/util/jar/JarFile getInputStream (Ljava/util/zip/ZipEntry;)Ljava/io/InputStream;
L178:   invokespecial Method java/io/BufferedInputStream <init> (Ljava/io/InputStream;)V
L181:   astore 4
L183:   new java/io/BufferedOutputStream
L186:   dup
L187:   new java/io/FileOutputStream
L190:   dup
L191:   aload 5
L193:   invokespecial Method java/io/FileOutputStream <init> (Ljava/io/File;)V
L196:   invokespecial Method java/io/BufferedOutputStream <init> (Ljava/io/OutputStream;)V
L199:   astore 7
L201:   aload_0
L202:   aload 4
L204:   aload 7
L206:   iconst_m1
L207:   iconst_1
L208:   dup
L209:   pop2
L210:   invokespecial Method QA break (Ljava/io/InputStream;Ljava/io/OutputStream;I)I
L213:   aload 7
L215:   aload 4
L217:   invokevirtual Method java/io/InputStream close ()V
L220:   invokevirtual Method java/io/OutputStream close ()V
L223:   getstatic Field QA "final" Ljava/util/Map;
L226:   aload 6
L228:   aload 5
L230:   invokevirtual Method java/io/File getAbsolutePath ()Ljava/lang/String;
L233:   invokeinterface InterfaceMethod java/util/Map put (Ljava/lang/Object;Ljava/lang/Object;)Ljava/lang/Object; 3
L238:   pop2
L239:   aload_3
L240:   invokeinterface InterfaceMethod java/util/Enumeration hasMoreElements ()Z 1
L245:   ifne L25
L248:   return
L249:   
        .attribute StackMap b'\x00\x07\x00\x0F\x00\x03\x07\x00\x02\x07\x01\x13\x07\x00\xEA\x00\x00\x00\x18\x00\x00\x00\x01\x07\x00\x73\x00\x19\x00\x04\x07\x00\x02\x07\x01\x13\x07\x00\xEA\x07\x01\x28\x00\x00\x00\x48\x00\x06\x07\x00\x02\x07\x01\x13\x07\x00\xEA\x07\x01\x28\x07\x01\x2D\x07\x00\x89\x00\x00\x00\x9A\x00\x07\x07\x00\x02\x07\x01\x13\x07\x00\xEA\x07\x01\x28\x07\x01\x2D\x07\x00\x89\x07\x00\x89\x00\x00\x00\xEF\x00\x06\x07\x00\x02\x07\x01\x13\x07\x00\xEA\x07\x01\x28\x07\x00\x7A\x07\x00\x7A\x00\x00\x00\xF0\x00\x04\x07\x00\x02\x07\x01\x13\x07\x00\xEA\x07\x01\x28\x00\x01\x07\x01\x28'
    .end code
    .exceptions java/io/IOException
.end method

.method private break : (Ljava/util/List;)V
    .code stack 5 locals 3
L0:     aload_1
L1:     invokeinterface InterfaceMethod java/util/List iterator ()Ljava/util/Iterator; 1
L6:     dup
L7:     astore_1
L8:     goto L36
L11:    athrow
L12:    aload_1
L13:    invokeinterface InterfaceMethod java/util/Iterator next ()Ljava/lang/Object; 1
L18:    checkcast java/net/URL
L21:    astore_2
L22:    new DA
L25:    dup
L26:    aload_0
L27:    aload_2
L28:    aconst_null
L29:    invokespecial Method DA <init> (LQA;Ljava/net/URL;LDA;)V
L32:    invokestatic Method DA short (LDA;)V
L35:    aload_1
L36:    invokeinterface InterfaceMethod java/util/Iterator hasNext ()Z 1
L41:    ifne L12
L44:    return
L45:    
        .attribute StackMap b'\x00\x03\x00\x0B\x00\x00\x00\x01\x07\x00\x73\x00\x0C\x00\x02\x07\x00\x02\x07\x00\xF0\x00\x00\x00\x24\x00\x02\x07\x00\x02\x07\x00\xF0\x00\x01\x07\x00\xF0'
    .end code
    .exceptions java/io/IOException
.end method

.method private break : (Ljava/net/URLConnection;Ljava/io/File;Ljava/io/File;)V
    .code stack 4 locals 8
L0:     new java/io/File
L3:     dup
L4:     getstatic Field QA catch Ljava/io/File;
L7:     ldc_w "cache.lck"
L10:    invokespecial Method java/io/File <init> (Ljava/io/File;Ljava/lang/String;)V
L13:    dup
L14:    astore 4
L16:    invokevirtual Method java/io/File createNewFile ()Z
L19:    new java/io/FileOutputStream
L22:    dup
L23:    aload 4
L25:    invokespecial Method java/io/FileOutputStream <init> (Ljava/io/File;)V
L28:    invokevirtual Method java/io/FileOutputStream getChannel ()Ljava/nio/channels/FileChannel;
L31:    invokevirtual Method java/nio/channels/FileChannel lock ()Ljava/nio/channels/FileLock;
L34:    astore 4
L36:    pop
        .catch [0] from L37 to L253 using L290
L37:    iconst_0
L38:    iconst_1
L39:    dup
L40:    pop2
L41:    istore 5
L43:    aload_2
L44:    aload_1
L45:    invokevirtual Method java/net/URLConnection getLastModified ()J
L48:    lstore 6
L50:    invokevirtual Method java/io/File exists ()Z
L53:    ifeq L80
L56:    lload 6
L58:    lconst_0
L59:    lcmp
L60:    ifle L80
L63:    lload 6
L65:    aload_0
L66:    aload_3
L67:    invokespecial Method QA else (Ljava/io/File;)J
L70:    lcmp
L71:    ifne L80
L74:    iconst_1
L75:    dup
L76:    dup
L77:    pop2
L78:    istore 5
L80:    iload 5
L82:    ifne L254
L85:    getstatic Field QA short Z
L88:    ifeq L117
L91:    getstatic Field java/lang/System err Ljava/io/PrintStream;
L94:    new java/lang/StringBuffer
L97:    dup
L98:    ldc_w "processNativeJar: downloading "
L101:   invokespecial Method java/lang/StringBuffer <init> (Ljava/lang/String;)V
L104:   aload_2
L105:   invokevirtual Method java/io/File getAbsolutePath ()Ljava/lang/String;
L108:   invokevirtual Method java/lang/StringBuffer append (Ljava/lang/String;)Ljava/lang/StringBuffer;
L111:   invokevirtual Method java/lang/StringBuffer toString ()Ljava/lang/String;
L114:   invokevirtual Method java/io/PrintStream println (Ljava/lang/String;)V
L117:   aload_3
L118:   invokevirtual Method java/io/File delete ()Z
L121:   aload_2
L122:   invokevirtual Method java/io/File delete ()Z
L125:   aload_1
L126:   invokevirtual Method java/net/URLConnection getContentLength ()I
L129:   istore 5
L131:   pop2
L132:   getstatic Field QA short Z
L135:   ifeq L168
L138:   getstatic Field java/lang/System err Ljava/io/PrintStream;
L141:   new java/lang/StringBuffer
L144:   dup
L145:   ldc_w "Content length = "
L148:   invokespecial Method java/lang/StringBuffer <init> (Ljava/lang/String;)V
L151:   iload 5
L153:   invokevirtual Method java/lang/StringBuffer append (I)Ljava/lang/StringBuffer;
L156:   ldc_w " bytes"
L159:   invokevirtual Method java/lang/StringBuffer append (Ljava/lang/String;)Ljava/lang/StringBuffer;
L162:   invokevirtual Method java/lang/StringBuffer toString ()Ljava/lang/String;
L165:   invokevirtual Method java/io/PrintStream println (Ljava/lang/String;)V
L168:   aload_0
L169:   aload_1
L170:   aload_2
L171:   invokespecial Method QA break (Ljava/net/URLConnection;Ljava/io/File;)I
L174:   istore 5
L176:   getstatic Field QA "enum" Z
L179:   ifeq L241
L182:   getstatic Field java/lang/System err Ljava/io/PrintStream;
L185:   new java/lang/StringBuffer
L188:   dup
L189:   ldc_w "processNativeJar: "
L192:   invokespecial Method java/lang/StringBuffer <init> (Ljava/lang/String;)V
L195:   aload_1
L196:   invokevirtual Method java/net/URLConnection getURL ()Ljava/net/URL;
L199:   invokevirtual Method java/net/URL toString ()Ljava/lang/String;
L202:   invokevirtual Method java/lang/StringBuffer append (Ljava/lang/String;)Ljava/lang/StringBuffer;
L205:   ldc_w " --> "
L208:   invokevirtual Method java/lang/StringBuffer append (Ljava/lang/String;)Ljava/lang/StringBuffer;
L211:   aload_2
L212:   invokevirtual Method java/io/File getAbsolutePath ()Ljava/lang/String;
L215:   invokevirtual Method java/lang/StringBuffer append (Ljava/lang/String;)Ljava/lang/StringBuffer;
L218:   ldc_w " : "
L221:   invokevirtual Method java/lang/StringBuffer append (Ljava/lang/String;)Ljava/lang/StringBuffer;
L224:   iload 5
L226:   invokevirtual Method java/lang/StringBuffer append (I)Ljava/lang/StringBuffer;
L229:   ldc_w " bytes written"
L232:   invokevirtual Method java/lang/StringBuffer append (Ljava/lang/String;)Ljava/lang/StringBuffer;
L235:   invokevirtual Method java/lang/StringBuffer toString ()Ljava/lang/String;
L238:   invokevirtual Method java/io/PrintStream println (Ljava/lang/String;)V
L241:   aload_0
L242:   aload_3
L243:   lload 6
L245:   invokespecial Method QA break (Ljava/io/File;J)V
L248:   aload 4
L250:   goto L300
L253:   athrow
        .catch [0] from L254 to L289 using L290
L254:   getstatic Field QA "enum" Z
L257:   ifeq L298
L260:   getstatic Field java/lang/System err Ljava/io/PrintStream;
L263:   new java/lang/StringBuffer
L266:   dup
L267:   ldc_w "processNativeJar: using previously cached: "
L270:   invokespecial Method java/lang/StringBuffer <init> (Ljava/lang/String;)V
L273:   aload_2
L274:   invokevirtual Method java/io/File getAbsolutePath ()Ljava/lang/String;
L277:   invokevirtual Method java/lang/StringBuffer append (Ljava/lang/String;)Ljava/lang/StringBuffer;
L280:   invokevirtual Method java/lang/StringBuffer toString ()Ljava/lang/String;
L283:   invokevirtual Method java/io/PrintStream println (Ljava/lang/String;)V
L286:   goto L298
L289:   athrow
L290:   astore_1
L291:   aload_1
L292:   aload 4
L294:   invokevirtual Method java/nio/channels/FileLock release ()V
L297:   athrow
L298:   aload 4
L300:   invokevirtual Method java/nio/channels/FileLock release ()V
L303:   return
L304:   
        .attribute StackMap b'\x00\x0A\x00\x50\x00\x07\x07\x00\x02\x07\x00\x58\x07\x00\x99\x07\x00\x99\x07\x01\x76\x01\x04\x00\x00\x00\x75\x00\x07\x07\x00\x02\x07\x00\x58\x07\x00\x99\x07\x00\x99\x07\x01\x76\x01\x04\x00\x00\x00\xA8\x00\x07\x07\x00\x02\x07\x00\x58\x07\x00\x99\x07\x00\x99\x07\x01\x76\x01\x04\x00\x00\x00\xF1\x00\x07\x07\x00\x02\x07\x00\x58\x07\x00\x99\x07\x00\x99\x07\x01\x76\x01\x04\x00\x00\x00\xFD\x00\x00\x00\x01\x07\x00\x73\x00\xFE\x00\x07\x07\x00\x02\x07\x00\x58\x07\x00\x99\x07\x00\x99\x07\x01\x76\x01\x04\x00\x00\x01\x21\x00\x00\x00\x01\x07\x00\x73\x01\x22\x00\x05\x07\x00\x02\x07\x00\x58\x07\x00\x99\x07\x00\x99\x07\x01\x76\x00\x01\x07\x00\x73\x01\x2A\x00\x07\x07\x00\x02\x07\x00\x58\x07\x00\x99\x07\x00\x99\x07\x01\x76\x01\x04\x00\x00\x01\x2C\x00\x07\x07\x00\x02\x07\x00\x58\x07\x00\x99\x07\x00\x99\x07\x01\x76\x01\x04\x00\x01\x07\x01\x76'
    .end code
    .exceptions java/io/IOException
.end method

.method private if : ()V
    .code stack 10 locals 3
L0:     ldc_w "progressbar"
L3:     aload_0
L4:     dup
L5:     dup_x2
L6:     new java/awt/BorderLayout
L9:     aload_0
L10:    dup
L11:    pop2
L12:    dup
L13:    invokespecial Method java/awt/BorderLayout <init> ()V
L16:    invokevirtual Method QA setLayout (Ljava/awt/LayoutManager;)V
L19:    new javax/swing/JPanel
L22:    aload_0
L23:    dup
L24:    pop2
L25:    dup
L26:    new java/awt/BorderLayout
L29:    dup
L30:    invokespecial Method java/awt/BorderLayout <init> ()V
L33:    invokespecial Method javax/swing/JPanel <init> (Ljava/awt/LayoutManager;)V
L36:    putfield Field QA true Ljavax/swing/JPanel;
L39:    invokespecial Method QA short (Ljava/lang/String;)Z
L42:    ifeq L100
L45:    aload_0
L46:    dup
L47:    dup_x1
L48:    new javax/swing/JProgressBar
L51:    aload_0
L52:    dup_x2
L53:    dup
L54:    pop2
L55:    dup
L56:    iconst_0
L57:    iconst_1
L58:    dup
L59:    pop2
L60:    bipush 100
L62:    iconst_1
L63:    dup
L64:    pop2
L65:    invokespecial Method javax/swing/JProgressBar <init> (II)V
L68:    putfield Field QA goto Ljavax/swing/JProgressBar;
L71:    getfield Field QA goto Ljavax/swing/JProgressBar;
L74:    iconst_1
L75:    dup
L76:    dup
L77:    pop2
L78:    invokevirtual Method javax/swing/JProgressBar setBorderPainted (Z)V
L81:    getfield Field QA goto Ljavax/swing/JProgressBar;
L84:    iconst_1
L85:    dup
L86:    dup
L87:    pop2
L88:    invokevirtual Method javax/swing/JProgressBar setStringPainted (Z)V
L91:    getfield Field QA goto Ljavax/swing/JProgressBar;
L94:    ldc_w "Loading..."
L97:    invokevirtual Method javax/swing/JProgressBar setString (Ljava/lang/String;)V
L100:   iconst_0
L101:   iconst_1
L102:   dup
L103:   pop2
L104:   istore_1
L105:   aconst_null
L106:   astore_2
L107:   aload_0
L108:   getfield Field QA else Ljava/net/URL;
L111:   ifnull L131
L114:   new javax/swing/ImageIcon
L117:   dup
L118:   aload_0
L119:   getfield Field QA else Ljava/net/URL;
L122:   invokespecial Method javax/swing/ImageIcon <init> (Ljava/net/URL;)V
L125:   astore_2
L126:   iconst_1
L127:   dup
L128:   dup
L129:   pop2
L130:   istore_1
L131:   aload_0
L132:   dup
L133:   getfield Field QA true Ljavax/swing/JPanel;
L136:   ldc_w "South"
L139:   invokevirtual Method QA add (Ljava/awt/Component;Ljava/lang/Object;)V
L142:   iload_1
L143:   ifeq L188
L146:   aload_0
L147:   dup
L148:   getfield Field QA true Ljavax/swing/JPanel;
L151:   new javax/swing/JLabel
L154:   dup
L155:   aload_2
L156:   invokespecial Method javax/swing/JLabel <init> (Ljavax/swing/Icon;)V
L159:   ldc_w "Center"
L162:   invokevirtual Method javax/swing/JPanel add (Ljava/awt/Component;Ljava/lang/Object;)V
L165:   getfield Field QA goto Ljavax/swing/JProgressBar;
L168:   ifnull L210
L171:   aload_0
L172:   dup
L173:   getfield Field QA true Ljavax/swing/JPanel;
L176:   swap
L177:   getfield Field QA goto Ljavax/swing/JProgressBar;
L180:   ldc_w "South"
L183:   invokevirtual Method javax/swing/JPanel add (Ljava/awt/Component;Ljava/lang/Object;)V
L186:   return
L187:   athrow
L188:   aload_0
L189:   getfield Field QA goto Ljavax/swing/JProgressBar;
L192:   ifnull L210
L195:   aload_0
L196:   dup
L197:   getfield Field QA true Ljavax/swing/JPanel;
L200:   swap
L201:   getfield Field QA goto Ljavax/swing/JProgressBar;
L204:   ldc_w "Center"
L207:   invokevirtual Method javax/swing/JPanel add (Ljava/awt/Component;Ljava/lang/Object;)V
L210:   return
L211:   
        .attribute StackMap b'\x00\x05\x00\x64\x00\x01\x07\x00\x02\x00\x00\x00\x83\x00\x03\x07\x00\x02\x01\x07\x01\xC2\x00\x00\x00\xBB\x00\x00\x00\x01\x07\x00\x73\x00\xBC\x00\x03\x07\x00\x02\x01\x07\x01\xC2\x00\x00\x00\xD2\x00\x03\x07\x00\x02\x01\x07\x01\xC2\x00\x00'
    .end code
.end method

.method public init : ()V
    .code stack 4 locals 2
L0:     getstatic Field QA short Z
L3:     ifeq L21
L6:     getstatic Field java/lang/System err Ljava/io/PrintStream;
L9:     invokevirtual Method java/io/PrintStream println ()V
L12:    getstatic Field java/lang/System err Ljava/io/PrintStream;
L15:    ldc_w "==========================================================================="
L18:    invokevirtual Method java/io/PrintStream println (Ljava/lang/String;)V
L21:    getstatic Field QA "enum" Z
L24:    ifeq L36
L27:    getstatic Field java/lang/System err Ljava/io/PrintStream;
L30:    ldc_w "Applet.init"
L33:    invokevirtual Method java/io/PrintStream println (Ljava/lang/String;)V
L36:    getstatic Field QA false Z
L39:    ifeq L44
L42:    return
L43:    athrow
L44:    aload_0
L45:    dup
L46:    dup_x1
L47:    ldc_w "subapplet.classname"
L50:    invokevirtual Method QA getParameter (Ljava/lang/String;)Ljava/lang/String;
L53:    putfield Field QA extends Ljava/lang/String;
L56:    getfield Field QA extends Ljava/lang/String;
L59:    ifnonnull L71
L62:    aload_0
L63:    ldc_w "Init failed : Missing subapplet.classname parameter"
L66:    invokespecial Method QA break (Ljava/lang/String;)V
L69:    return
L70:    athrow
L71:    aload_0
L72:    dup
L73:    dup_x1
L74:    ldc_w "subapplet.displayname"
L77:    invokevirtual Method QA getParameter (Ljava/lang/String;)Ljava/lang/String;
L80:    putfield Field QA byte Ljava/lang/String;
L83:    getfield Field QA byte Ljava/lang/String;
L86:    ifnonnull L96
L89:    aload_0
L90:    ldc_w "Applet"
L93:    putfield Field QA byte Ljava/lang/String;
L96:    aload_0
L97:    aconst_null
L98:    putfield Field QA else Ljava/net/URL;
        .catch java/io/IOException from L101 to L135 using L138
L101:   aload_0
L102:   ldc_w "subapplet.image"
L105:   invokevirtual Method QA getParameter (Ljava/lang/String;)Ljava/lang/String;
L108:   dup
L109:   astore_1
L110:   ifnull L143
L113:   aload_1
L114:   invokevirtual Method java/lang/String length ()I
L117:   ifle L143
L120:   new java/net/URL
L123:   aload_0
L124:   dup_x1
L125:   dup
L126:   pop2
L127:   dup
L128:   aload_1
L129:   invokespecial Method java/net/URL <init> (Ljava/lang/String;)V
L132:   putfield Field QA else Ljava/net/URL;
L135:   goto L143
L138:   astore_1
L139:   aload_1
L140:   invokevirtual Method java/io/IOException printStackTrace ()V
L143:   getstatic Field QA "enum" Z
L146:   ifeq L237
L149:   getstatic Field java/lang/System err Ljava/io/PrintStream;
L152:   new java/lang/StringBuffer
L155:   dup
L156:   ldc_w "subapplet.classname = "
L159:   invokespecial Method java/lang/StringBuffer <init> (Ljava/lang/String;)V
L162:   aload_0
L163:   getfield Field QA extends Ljava/lang/String;
L166:   invokevirtual Method java/lang/StringBuffer append (Ljava/lang/String;)Ljava/lang/StringBuffer;
L169:   invokevirtual Method java/lang/StringBuffer toString ()Ljava/lang/String;
L172:   invokevirtual Method java/io/PrintStream println (Ljava/lang/String;)V
L175:   getstatic Field java/lang/System err Ljava/io/PrintStream;
L178:   new java/lang/StringBuffer
L181:   dup
L182:   ldc_w "subapplet.displayname = "
L185:   invokespecial Method java/lang/StringBuffer <init> (Ljava/lang/String;)V
L188:   aload_0
L189:   getfield Field QA byte Ljava/lang/String;
L192:   invokevirtual Method java/lang/StringBuffer append (Ljava/lang/String;)Ljava/lang/StringBuffer;
L195:   invokevirtual Method java/lang/StringBuffer toString ()Ljava/lang/String;
L198:   invokevirtual Method java/io/PrintStream println (Ljava/lang/String;)V
L201:   aload_0
L202:   getfield Field QA else Ljava/net/URL;
L205:   ifnull L237
L208:   getstatic Field java/lang/System err Ljava/io/PrintStream;
L211:   new java/lang/StringBuffer
L214:   dup
L215:   ldc_w "subapplet.image = "
L218:   invokespecial Method java/lang/StringBuffer <init> (Ljava/lang/String;)V
L221:   aload_0
L222:   getfield Field QA else Ljava/net/URL;
L225:   invokevirtual Method java/net/URL toExternalForm ()Ljava/lang/String;
L228:   invokevirtual Method java/lang/StringBuffer append (Ljava/lang/String;)Ljava/lang/StringBuffer;
L231:   invokevirtual Method java/lang/StringBuffer toString ()Ljava/lang/String;
L234:   invokevirtual Method java/io/PrintStream println (Ljava/lang/String;)V
L237:   aload_0
L238:   iconst_1
L239:   aload_0
L240:   invokespecial Method QA if ()V
L243:   iconst_1
L244:   dup
L245:   pop2
L246:   putfield Field QA char Z
L249:   return
L250:   
        .attribute StackMap b'\x00\x0A\x00\x15\x00\x01\x07\x00\x02\x00\x00\x00\x24\x00\x01\x07\x00\x02\x00\x00\x00\x2B\x00\x00\x00\x01\x07\x00\x73\x00\x2C\x00\x01\x07\x00\x02\x00\x00\x00\x46\x00\x00\x00\x01\x07\x00\x73\x00\x47\x00\x01\x07\x00\x02\x00\x00\x00\x60\x00\x01\x07\x00\x02\x00\x00\x00\x8A\x00\x01\x07\x00\x02\x00\x01\x07\x00\x54\x00\x8F\x00\x02\x07\x00\x02\x07\x00\x7A\x00\x00\x00\xED\x00\x02\x07\x00\x02\x07\x00\x7A\x00\x00'
    .end code
.end method

.method private short : (Ljava/lang/String;)Z
    .code stack 2 locals 2
L0:     aload_0
L1:     aload_1
L2:     invokevirtual Method QA getParameter (Ljava/lang/String;)Ljava/lang/String;
L5:     invokestatic Method java/lang/Boolean valueOf (Ljava/lang/String;)Ljava/lang/Boolean;
L8:     invokevirtual Method java/lang/Boolean booleanValue ()Z
L11:    ireturn
L12:    
    .end code
.end method

.method public static else : (LQA;)V
    .code stack 1 locals 1
L0:     aload_0
L1:     invokespecial Method QA this ()V
L4:     return
L5:     
    .end code
    .synthetic
.end method

.method private char : ()V
    .code stack 11 locals 9
L0:     ldc_w "user.home"
L3:     invokestatic Method java/lang/System getProperty (Ljava/lang/String;)Ljava/lang/String;
L6:     astore_1
L7:     new java/io/File
L10:    dup
L11:    new java/lang/StringBuffer
L14:    dup
L15:    aload_1
L16:    invokestatic Method java/lang/String valueOf (Ljava/lang/Object;)Ljava/lang/String;
L19:    invokespecial Method java/lang/StringBuffer <init> (Ljava/lang/String;)V
L22:    getstatic Field java/io/File separator Ljava/lang/String;
L25:    invokevirtual Method java/lang/StringBuffer append (Ljava/lang/String;)Ljava/lang/StringBuffer;
L28:    ldc_w ".jnlp-applet"
L31:    invokevirtual Method java/lang/StringBuffer append (Ljava/lang/String;)Ljava/lang/StringBuffer;
L34:    getstatic Field java/io/File separator Ljava/lang/String;
L37:    invokevirtual Method java/lang/StringBuffer append (Ljava/lang/String;)Ljava/lang/StringBuffer;
L40:    ldc_w ".dont_ask"
L43:    invokevirtual Method java/lang/StringBuffer append (Ljava/lang/String;)Ljava/lang/StringBuffer;
L46:    invokevirtual Method java/lang/StringBuffer toString ()Ljava/lang/String;
L49:    invokespecial Method java/io/File <init> (Ljava/lang/String;)V
L52:    dup
L53:    astore_1
L54:    invokevirtual Method java/io/File exists ()Z
L57:    ifeq L62
L60:    return
L61:    athrow
L62:    iconst_0
L63:    iconst_1
L64:    dup
L65:    pop2
L66:    istore_2
L67:    aload_0
L68:    ldc_w "noddraw.check.silent"
L71:    invokespecial Method QA short (Ljava/lang/String;)Z
L74:    ifne L137
L77:    aconst_null
L78:    ldc_w [_534]
L81:    ldc_w "Update deployment.properties?"
L84:    iconst_1
L85:    dup
L86:    pop2
L87:    iconst_3
L88:    iconst_1
L89:    dup_x1
L90:    dup
L91:    pop2
L92:    aconst_null
L93:    iconst_3
L94:    iconst_1
L95:    dup
L96:    pop2
L97:    anewarray java/lang/Object
L100:   iconst_1
L101:   dup
L102:   pop2
L103:   dup
L104:   iconst_0
L105:   iconst_1
L106:   dup
L107:   pop2
L108:   ldc_w "Yes"
L111:   aastore
L112:   dup
L113:   iconst_1
L114:   dup
L115:   dup
L116:   pop2
L117:   ldc_w "No"
L120:   aastore
L121:   dup
L122:   iconst_2
L123:   iconst_1
L124:   dup
L125:   pop2
L126:   ldc_w "No, Don't Ask Again"
L129:   aastore
L130:   ldc_w "Yes"
L133:   invokestatic Method javax/swing/JOptionPane showOptionDialog (Ljava/awt/Component;Ljava/lang/Object;Ljava/lang/String;IILjavax/swing/Icon;[Ljava/lang/Object;Ljava/lang/Object;)I
L136:   istore_2
L137:   iload_2
L138:   iflt L149
L141:   iload_2
L142:   iconst_1
L143:   dup
L144:   dup
L145:   pop2
L146:   if_icmpne L151
L149:   return
L150:   athrow
L151:   iload_2
L152:   iconst_2
L153:   iconst_1
L154:   dup
L155:   pop2
L156:   if_icmpne L167
        .catch java/io/IOException from L159 to L164 using L165
L159:   aload_1
L160:   invokevirtual Method java/io/File createNewFile ()Z
L163:   pop
L164:   return
L165:   pop
L166:   return
        .catch java/io/IOException from L167 to L186 using L546
L167:   new java/io/File
L170:   dup
L171:   aload_0
L172:   invokespecial Method QA float ()Ljava/lang/String;
L175:   invokespecial Method java/io/File <init> (Ljava/lang/String;)V
L178:   dup
L179:   astore_1
L180:   invokevirtual Method java/io/File exists ()Z
L183:   ifne L187
L186:   return
        .catch java/io/IOException from L187 to L206 using L546
L187:   new java/io/File
L190:   dup
L191:   aload_1
L192:   ldc_w "deployment.properties"
L195:   invokespecial Method java/io/File <init> (Ljava/io/File;Ljava/lang/String;)V
L198:   dup
L199:   astore_2
L200:   invokevirtual Method java/io/File exists ()Z
L203:   ifne L207
L206:   return
        .catch java/io/IOException from L207 to L545 using L546
L207:   new java/util/Properties
L210:   dup
L211:   invokespecial Method java/util/Properties <init> ()V
L214:   astore_3
L215:   new java/io/BufferedInputStream
L218:   dup
L219:   new java/io/FileInputStream
L222:   dup
L223:   aload_2
L224:   invokespecial Method java/io/FileInputStream <init> (Ljava/io/File;)V
L227:   invokespecial Method java/io/BufferedInputStream <init> (Ljava/io/InputStream;)V
L230:   dup
L231:   astore 4
L233:   aload_3
L234:   dup_x1
L235:   aload 4
L237:   invokevirtual Method java/util/Properties load (Ljava/io/InputStream;)V
L240:   invokevirtual Method java/io/InputStream close ()V
L243:   new java/util/HashSet
L246:   dup
L247:   invokespecial Method java/util/HashSet <init> ()V
L250:   astore 4
L252:   invokevirtual Method java/util/Properties keySet ()Ljava/util/Set;
L255:   invokeinterface InterfaceMethod java/util/Set iterator ()Ljava/util/Iterator; 1
L260:   dup
L261:   astore 5
L263:   goto L339
L266:   aload 5
L268:   invokeinterface InterfaceMethod java/util/Iterator next ()Ljava/lang/Object; 1
L273:   checkcast java/lang/String
L276:   dup
L277:   astore 6
L279:   ldc_w "deployment.javapi.jre."
L282:   invokevirtual Method java/lang/String startsWith (Ljava/lang/String;)Z
L285:   ifeq L337
L288:   aload 6
L290:   ldc "."
L292:   invokevirtual Method java/lang/String lastIndexOf (Ljava/lang/String;)I
L295:   dup
L296:   istore 7
L298:   iflt L337
L301:   iload 7
L303:   ldc_w "deployment.javapi.jre."
L306:   invokevirtual Method java/lang/String length ()I
L309:   if_icmple L337
L312:   aload 6
L314:   ldc_w "deployment.javapi.jre."
L317:   invokevirtual Method java/lang/String length ()I
L320:   iload 7
L322:   invokevirtual Method java/lang/String substring (II)Ljava/lang/String;
L325:   astore 8
L327:   aload 4
L329:   aload 8
L331:   invokeinterface InterfaceMethod java/util/Set add (Ljava/lang/Object;)Z 2
L336:   pop
L337:   aload 5
L339:   invokeinterface InterfaceMethod java/util/Iterator hasNext ()Z 1
L344:   ifne L266
L347:   aload 4
L349:   ldc_w "java.version"
L352:   invokestatic Method java/lang/System getProperty (Ljava/lang/String;)Ljava/lang/String;
L355:   invokeinterface InterfaceMethod java/util/Set add (Ljava/lang/Object;)Z 2
L360:   aload 4
L362:   invokeinterface InterfaceMethod java/util/Set iterator ()Ljava/util/Iterator; 1
L367:   astore 5
L369:   pop
L370:   aload 5
L372:   goto L485
L375:   aload 5
L377:   invokeinterface InterfaceMethod java/util/Iterator next ()Ljava/lang/Object; 1
L382:   checkcast java/lang/String
L385:   astore 6
L387:   new java/lang/StringBuffer
L390:   dup
L391:   ldc_w "deployment.javapi.jre."
L394:   invokespecial Method java/lang/StringBuffer <init> (Ljava/lang/String;)V
L397:   aload 6
L399:   invokevirtual Method java/lang/StringBuffer append (Ljava/lang/String;)Ljava/lang/StringBuffer;
L402:   ldc_w ".args"
L405:   invokevirtual Method java/lang/StringBuffer append (Ljava/lang/String;)Ljava/lang/StringBuffer;
L408:   invokevirtual Method java/lang/StringBuffer toString ()Ljava/lang/String;
L411:   astore 7
L413:   aload_3
L414:   aload 7
L416:   invokevirtual Method java/util/Properties getProperty (Ljava/lang/String;)Ljava/lang/String;
L419:   dup
L420:   astore 8
L422:   ifnonnull L434
L425:   ldc_w "-Dsun.java2d.noddraw=true"
L428:   astore 8
L430:   aload_3
L431:   goto L475
L434:   aload 8
L436:   ldc_w "-Dsun.java2d.noddraw=true"
L439:   invokevirtual Method java/lang/String indexOf (Ljava/lang/String;)I
L442:   ifge L474
L445:   new java/lang/StringBuffer
L448:   dup
L449:   aload 8
L451:   invokestatic Method java/lang/String valueOf (Ljava/lang/Object;)Ljava/lang/String;
L454:   invokespecial Method java/lang/StringBuffer <init> (Ljava/lang/String;)V
L457:   ldc_w " "
L460:   invokevirtual Method java/lang/StringBuffer append (Ljava/lang/String;)Ljava/lang/StringBuffer;
L463:   ldc_w "-Dsun.java2d.noddraw=true"
L466:   invokevirtual Method java/lang/StringBuffer append (Ljava/lang/String;)Ljava/lang/StringBuffer;
L469:   invokevirtual Method java/lang/StringBuffer toString ()Ljava/lang/String;
L472:   astore 8
L474:   aload_3
L475:   aload 7
L477:   aload 8
L479:   invokevirtual Method java/util/Properties setProperty (Ljava/lang/String;Ljava/lang/String;)Ljava/lang/Object;
L482:   pop
L483:   aload 5
L485:   invokeinterface InterfaceMethod java/util/Iterator hasNext ()Z 1
L490:   ifne L375
L493:   new java/io/BufferedOutputStream
L496:   dup
L497:   new java/io/FileOutputStream
L500:   dup
L501:   aload_2
L502:   invokespecial Method java/io/FileOutputStream <init> (Ljava/io/File;)V
L505:   invokespecial Method java/io/BufferedOutputStream <init> (Ljava/io/OutputStream;)V
L508:   astore 5
L510:   aload_0
L511:   ldc_w "noddraw.check.silent"
L514:   aload_3
L515:   aload 5
L517:   dup_x1
L518:   aconst_null
L519:   invokevirtual Method java/util/Properties store (Ljava/io/OutputStream;Ljava/lang/String;)V
L522:   invokevirtual Method java/io/OutputStream close ()V
L525:   invokespecial Method QA short (Ljava/lang/String;)Z
L528:   ifne L551
L531:   aconst_null
L532:   ldc_w "For best robustness, we recommend you now exit and\u000Arestart your web browser. (Note: clicking \"OK\" will\u000Anot exit your browser.)"
L535:   ldc_w "Browser Restart Recommended"
L538:   iconst_1
L539:   dup
L540:   dup
L541:   pop2
L542:   invokestatic Method javax/swing/JOptionPane showMessageDialog (Ljava/awt/Component;Ljava/lang/Object;Ljava/lang/String;I)V
L545:   return
L546:   astore_1
L547:   aload_1
L548:   invokevirtual Method java/io/IOException printStackTrace ()V
L551:   return
L552:   
        .attribute StackMap b'\x00\x14\x00\x3D\x00\x00\x00\x01\x07\x00\x73\x00\x3E\x00\x02\x07\x00\x02\x07\x00\x99\x00\x00\x00\x89\x00\x03\x07\x00\x02\x07\x00\x99\x01\x00\x00\x00\x95\x00\x03\x07\x00\x02\x07\x00\x99\x01\x00\x00\x00\x96\x00\x00\x00\x01\x07\x00\x73\x00\x97\x00\x03\x07\x00\x02\x07\x00\x99\x01\x00\x00\x00\xA5\x00\x03\x07\x00\x02\x07\x00\x99\x01\x00\x01\x07\x00\x54\x00\xA7\x00\x03\x07\x00\x02\x07\x00\x99\x01\x00\x00\x00\xBB\x00\x03\x07\x00\x02\x07\x00\x99\x01\x00\x00\x00\xCF\x00\x03\x07\x00\x02\x07\x00\x99\x07\x00\x99\x00\x00\x01\x0A\x00\x06\x07\x00\x02\x07\x00\x99\x07\x00\x99\x07\x02\x2A\x07\x02\x33\x07\x00\xF0\x00\x00\x01\x51\x00\x07\x07\x00\x02\x07\x00\x99\x07\x00\x99\x07\x02\x2A\x07\x02\x33\x07\x00\xF0\x07\x00\x89\x00\x00\x01\x53\x00\x06\x07\x00\x02\x07\x00\x99\x07\x00\x99\x07\x02\x2A\x07\x02\x33\x07\x00\xF0\x00\x01\x07\x00\xF0\x01\x77\x00\x06\x07\x00\x02\x07\x00\x99\x07\x00\x99\x07\x02\x2A\x07\x02\x33\x07\x00\xF0\x00\x00\x01\xB2\x00\x09\x07\x00\x02\x07\x00\x99\x07\x00\x99\x07\x02\x2A\x07\x02\x33\x07\x00\xF0\x07\x00\x89\x07\x00\x89\x07\x00\x89\x00\x00\x01\xDA\x00\x09\x07\x00\x02\x07\x00\x99\x07\x00\x99\x07\x02\x2A\x07\x02\x33\x07\x00\xF0\x07\x00\x89\x07\x00\x89\x07\x00\x89\x00\x00\x01\xDB\x00\x09\x07\x00\x02\x07\x00\x99\x07\x00\x99\x07\x02\x2A\x07\x02\x33\x07\x00\xF0\x07\x00\x89\x07\x00\x89\x07\x00\x89\x00\x01\x07\x02\x2A\x01\xE5\x00\x06\x07\x00\x02\x07\x00\x99\x07\x00\x99\x07\x02\x2A\x07\x02\x33\x07\x00\xF0\x00\x01\x07\x00\xF0\x02\x22\x00\x02\x07\x00\x02\x07\x00\x99\x00\x01\x07\x00\x54\x02\x27\x00\x02\x07\x00\x02\x07\x00\x7A\x00\x00'
    .end code
.end method

.method private new : ()Ljava/lang/String;
    .code stack 5 locals 5
L0:     aload_0
L1:     invokevirtual Method QA getCodeBase ()Ljava/net/URL;
L4:     invokevirtual Method java/net/URL toExternalForm ()Ljava/lang/String;
L7:     astore_1
L8:     iconst_m1
L9:     iconst_1
L10:    dup
L11:    pop2
L12:    istore_2
L13:    iconst_m1
L14:    iconst_1
L15:    dup
L16:    pop2
L17:    istore_3
L18:    ldc_w "UNKNOWN"
L21:    astore 4
L23:    aload_1
L24:    ldc_w "://"
L27:    invokevirtual Method java/lang/String indexOf (Ljava/lang/String;)I
L30:    dup
L31:    istore_2
L32:    iflt L148
L35:    iinc 2 3
L38:    iload_2
L39:    aload_1
L40:    invokevirtual Method java/lang/String length ()I
L43:    if_icmpge L148
L46:    aload_1
L47:    iload_2
L48:    invokevirtual Method java/lang/String charAt (I)C
L51:    bipush 47
L53:    iconst_1
L54:    dup
L55:    pop2
L56:    if_icmpeq L148
L59:    aload_1
L60:    bipush 47
L62:    iconst_1
L63:    dup
L64:    pop2
L65:    iload_2
L66:    invokevirtual Method java/lang/String indexOf (II)I
L69:    dup
L70:    istore_3
L71:    iload_2
L72:    if_icmple L148
L75:    aload_1
L76:    iload_2
L77:    iload_3
L78:    invokevirtual Method java/lang/String substring (II)Ljava/lang/String;
L81:    bipush 46
L83:    iconst_1
L84:    dup
L85:    pop2
L86:    bipush 95
L88:    iconst_1
L89:    dup
L90:    pop2
L91:    invokevirtual Method java/lang/String replace (CC)Ljava/lang/String;
L94:    bipush 58
L96:    iconst_1
L97:    dup
L98:    pop2
L99:    bipush 95
L101:   iconst_1
L102:   dup
L103:   pop2
L104:   invokevirtual Method java/lang/String replace (CC)Ljava/lang/String;
L107:   bipush 92
L109:   iconst_1
L110:   dup
L111:   pop2
L112:   bipush 95
L114:   iconst_1
L115:   dup
L116:   pop2
L117:   invokevirtual Method java/lang/String replace (CC)Ljava/lang/String;
L120:   bipush 91
L122:   iconst_1
L123:   dup
L124:   pop2
L125:   bipush 95
L127:   iconst_1
L128:   dup
L129:   pop2
L130:   invokevirtual Method java/lang/String replace (CC)Ljava/lang/String;
L133:   bipush 93
L135:   iconst_1
L136:   dup
L137:   pop2
L138:   bipush 95
L140:   iconst_1
L141:   dup
L142:   pop2
L143:   invokevirtual Method java/lang/String replace (CC)Ljava/lang/String;
L146:   astore 4
L148:   new java/lang/StringBuffer
L151:   dup
L152:   invokespecial Method java/lang/StringBuffer <init> ()V
L155:   dup
L156:   astore_2
L157:   aload_1
L158:   invokevirtual Method java/lang/StringBuffer append (Ljava/lang/String;)Ljava/lang/StringBuffer;
L161:   ldc_w "\u000A"
L164:   invokevirtual Method java/lang/StringBuffer append (Ljava/lang/String;)Ljava/lang/StringBuffer;
L167:   aload_0
L168:   ldc_w "archive"
L171:   invokevirtual Method QA getParameter (Ljava/lang/String;)Ljava/lang/String;
L174:   invokevirtual Method java/lang/StringBuffer append (Ljava/lang/String;)Ljava/lang/StringBuffer;
L177:   pop
L178:   getstatic Field QA short Z
L181:   ifeq L207
L184:   getstatic Field java/lang/System err Ljava/io/PrintStream;
L187:   new java/lang/StringBuffer
L190:   dup
L191:   ldc_w "key = "
L194:   invokespecial Method java/lang/StringBuffer <init> (Ljava/lang/String;)V
L197:   aload_2
L198:   invokevirtual Method java/lang/StringBuffer append (Ljava/lang/Object;)Ljava/lang/StringBuffer;
L201:   invokevirtual Method java/lang/StringBuffer toString ()Ljava/lang/String;
L204:   invokevirtual Method java/io/PrintStream println (Ljava/lang/String;)V
L207:   new java/lang/StringBuffer
L210:   dup
L211:   invokespecial Method java/lang/StringBuffer <init> ()V
L214:   dup
L215:   astore_1
L216:   aload 4
L218:   invokevirtual Method java/lang/StringBuffer append (Ljava/lang/String;)Ljava/lang/StringBuffer;
L221:   getstatic Field java/io/File separator Ljava/lang/String;
L224:   invokevirtual Method java/lang/StringBuffer append (Ljava/lang/String;)Ljava/lang/StringBuffer;
L227:   aload_2
L228:   invokevirtual Method java/lang/StringBuffer toString ()Ljava/lang/String;
L231:   invokestatic Method QA else (Ljava/lang/String;)Ljava/lang/String;
L234:   invokevirtual Method java/lang/StringBuffer append (Ljava/lang/String;)Ljava/lang/StringBuffer;
L237:   pop
L238:   getstatic Field QA short Z
L241:   ifeq L267
L244:   getstatic Field java/lang/System err Ljava/io/PrintStream;
L247:   new java/lang/StringBuffer
L250:   dup
L251:   ldc_w "result = "
L254:   invokespecial Method java/lang/StringBuffer <init> (Ljava/lang/String;)V
L257:   aload_1
L258:   invokevirtual Method java/lang/StringBuffer append (Ljava/lang/Object;)Ljava/lang/StringBuffer;
L261:   invokevirtual Method java/lang/StringBuffer toString ()Ljava/lang/String;
L264:   invokevirtual Method java/io/PrintStream println (Ljava/lang/String;)V
L267:   aload_1
L268:   invokevirtual Method java/lang/StringBuffer toString ()Ljava/lang/String;
L271:   areturn
L272:   
        .attribute StackMap b'\x00\x03\x00\x94\x00\x05\x07\x00\x02\x07\x00\x89\x01\x01\x07\x00\x89\x00\x00\x00\xCF\x00\x05\x07\x00\x02\x07\x00\x89\x07\x00\xA4\x01\x07\x00\x89\x00\x00\x01\x0B\x00\x05\x07\x00\x02\x07\x00\xA4\x07\x00\xA4\x01\x07\x00\x89\x00\x00'
    .end code
.end method

.method private static break : (Ljava/lang/Throwable;)Ljava/lang/String;
    .code stack 3 locals 3
L0:     new java/lang/StringBuffer
L3:     dup
L4:     aload_0
L5:     invokevirtual Method java/lang/Throwable toString ()Ljava/lang/String;
L8:     invokespecial Method java/lang/StringBuffer <init> (Ljava/lang/String;)V
L11:    astore_1
L12:    aload_0
L13:    invokevirtual Method java/lang/Throwable getCause ()Ljava/lang/Throwable;
L16:    dup
L17:    astore_2
L18:    goto L39
L21:    athrow
L22:    aload_1
L23:    ldc ": "
L25:    invokevirtual Method java/lang/StringBuffer append (Ljava/lang/String;)Ljava/lang/StringBuffer;
L28:    aload_2
L29:    invokevirtual Method java/lang/StringBuffer append (Ljava/lang/Object;)Ljava/lang/StringBuffer;
L32:    aload_2
L33:    invokevirtual Method java/lang/Throwable getCause ()Ljava/lang/Throwable;
L36:    astore_2
L37:    pop
L38:    aload_2
L39:    ifnonnull L22
L42:    aload_1
L43:    invokevirtual Method java/lang/StringBuffer toString ()Ljava/lang/String;
L46:    areturn
L47:    
        .attribute StackMap b'\x00\x03\x00\x15\x00\x00\x00\x01\x07\x00\x73\x00\x16\x00\x03\x07\x00\x73\x07\x00\xA4\x07\x00\x73\x00\x00\x00\x27\x00\x03\x07\x00\x73\x07\x00\xA4\x07\x00\x73\x00\x01\x07\x00\x73'
    .end code
.end method

.method private else : (Ljava/net/URL;)V
    .code stack 2 locals 2
L0:     getstatic Field QA do Ljava/util/Set;
L3:     aload_1
L4:     invokeinterface InterfaceMethod java/util/Set add (Ljava/lang/Object;)Z 2
L9:     pop
L10:    return
L11:    
    .end code
.end method

.method private break : (Ljava/util/jar/JarFile;Ljava/util/Set;)V
    .code stack 5 locals 7
L0:     getstatic Field QA "enum" Z
L3:     ifeq L15
L6:     getstatic Field java/lang/System err Ljava/io/PrintStream;
L9:     ldc_w "validateCertificates:"
L12:    invokevirtual Method java/io/PrintStream println (Ljava/lang/String;)V
L15:    sipush 1000
L18:    iconst_1
L19:    dup
L20:    pop2
L21:    newarray byte
L23:    iconst_1
L24:    dup
L25:    pop2
L26:    astore_3
L27:    aload_1
L28:    invokevirtual Method java/util/jar/JarFile entries ()Ljava/util/Enumeration;
L31:    dup
L32:    astore 4
L34:    goto L166
L37:    athrow
L38:    aload 4
L40:    invokeinterface InterfaceMethod java/util/Enumeration nextElement ()Ljava/lang/Object; 1
L45:    checkcast java/util/jar/JarEntry
L48:    dup
L49:    astore 5
L51:    invokevirtual Method java/util/jar/JarEntry getName ()Ljava/lang/String;
L54:    astore 6
L56:    getstatic Field QA short Z
L59:    ifeq L86
L62:    getstatic Field java/lang/System err Ljava/io/PrintStream;
L65:    new java/lang/StringBuffer
L68:    dup
L69:    ldc_w "JarEntry : "
L72:    invokespecial Method java/lang/StringBuffer <init> (Ljava/lang/String;)V
L75:    aload 6
L77:    invokevirtual Method java/lang/StringBuffer append (Ljava/lang/String;)Ljava/lang/StringBuffer;
L80:    invokevirtual Method java/lang/StringBuffer toString ()Ljava/lang/String;
L83:    invokevirtual Method java/io/PrintStream println (Ljava/lang/String;)V
L86:    aload_2
L87:    aload 6
L89:    invokeinterface InterfaceMethod java/util/Set contains (Ljava/lang/Object;)Z 2
L94:    ifeq L164
L97:    getstatic Field QA "enum" Z
L100:   ifeq L127
L103:   getstatic Field java/lang/System err Ljava/io/PrintStream;
L106:   new java/lang/StringBuffer
L109:   dup
L110:   ldc_w "VALIDATE: "
L113:   invokespecial Method java/lang/StringBuffer <init> (Ljava/lang/String;)V
L116:   aload 6
L118:   invokevirtual Method java/lang/StringBuffer append (Ljava/lang/String;)Ljava/lang/StringBuffer;
L121:   invokevirtual Method java/lang/StringBuffer toString ()Ljava/lang/String;
L124:   invokevirtual Method java/io/PrintStream println (Ljava/lang/String;)V
L127:   aload_0
L128:   aload_1
L129:   aload 5
L131:   aload_3
L132:   invokespecial Method QA break (Ljava/util/jar/JarFile;Ljava/util/jar/JarEntry;[B)Z
L135:   ifne L164
L138:   new java/io/IOException
L141:   dup
L142:   new java/lang/StringBuffer
L145:   dup
L146:   ldc_w "Cannot validate certificate for "
L149:   invokespecial Method java/lang/StringBuffer <init> (Ljava/lang/String;)V
L152:   aload 6
L154:   invokevirtual Method java/lang/StringBuffer append (Ljava/lang/String;)Ljava/lang/StringBuffer;
L157:   invokevirtual Method java/lang/StringBuffer toString ()Ljava/lang/String;
L160:   invokespecial Method java/io/IOException <init> (Ljava/lang/String;)V
L163:   athrow
L164:   aload 4
L166:   invokeinterface InterfaceMethod java/util/Enumeration hasMoreElements ()Z 1
L171:   ifne L38
L174:   return
L175:   
        .attribute StackMap b'\x00\x07\x00\x0F\x00\x03\x07\x00\x02\x07\x01\x13\x07\x00\xEA\x00\x00\x00\x25\x00\x00\x00\x01\x07\x00\x73\x00\x26\x00\x05\x07\x00\x02\x07\x01\x13\x07\x00\xEA\x07\x02\x7C\x07\x01\x28\x00\x00\x00\x56\x00\x07\x07\x00\x02\x07\x01\x13\x07\x00\xEA\x07\x02\x7C\x07\x01\x28\x07\x01\x2D\x07\x00\x89\x00\x00\x00\x7F\x00\x07\x07\x00\x02\x07\x01\x13\x07\x00\xEA\x07\x02\x7C\x07\x01\x28\x07\x01\x2D\x07\x00\x89\x00\x00\x00\xA4\x00\x07\x07\x00\x02\x07\x01\x13\x07\x00\xEA\x07\x02\x7C\x07\x01\x28\x07\x01\x2D\x07\x00\x89\x00\x00\x00\xA6\x00\x05\x07\x00\x02\x07\x01\x13\x07\x00\xEA\x07\x02\x7C\x07\x01\x28\x00\x01\x07\x01\x28'
    .end code
    .exceptions java/io/IOException
.end method

.method private try : ()V
    .code stack 5 locals 3
L0:     getstatic Field QA short Z
L3:     ifeq L15
L6:     getstatic Field java/lang/System err Ljava/io/PrintStream;
L9:     ldc_w "---------------------------------------------------"
L12:    invokevirtual Method java/io/PrintStream println (Ljava/lang/String;)V
L15:    ldc_w "jln"
L18:    ldc_w ".tmp"
L21:    getstatic Field QA float Ljava/io/File;
L24:    invokestatic Method java/io/File createTempFile (Ljava/lang/String;Ljava/lang/String;Ljava/io/File;)Ljava/io/File;
L27:    dup
L28:    astore_1
L29:    invokevirtual Method java/io/File getAbsolutePath ()Ljava/lang/String;
L32:    astore_2
L33:    iconst_0
L34:    iconst_1
L35:    dup
L36:    pop2
L37:    aload_2
L38:    dup_x1
L39:    ldc_w ".tmp"
L42:    invokevirtual Method java/lang/String lastIndexOf (Ljava/lang/String;)I
L45:    invokevirtual Method java/lang/String substring (II)Ljava/lang/String;
L48:    astore_2
L49:    new java/io/File
L52:    dup
L53:    aload_2
L54:    invokespecial Method java/io/File <init> (Ljava/lang/String;)V
L57:    putstatic Field QA throws Ljava/io/File;
L60:    getstatic Field QA short Z
L63:    ifeq L107
L66:    getstatic Field java/lang/System err Ljava/io/PrintStream;
L69:    new java/lang/StringBuffer
L72:    dup
L73:    ldc_w "tmpFile = "
L76:    invokespecial Method java/lang/StringBuffer <init> (Ljava/lang/String;)V
L79:    aload_1
L80:    invokevirtual Method java/io/File getAbsolutePath ()Ljava/lang/String;
L83:    invokevirtual Method java/lang/StringBuffer append (Ljava/lang/String;)Ljava/lang/StringBuffer;
L86:    ldc_w "  tmpDir = "
L89:    invokevirtual Method java/lang/StringBuffer append (Ljava/lang/String;)Ljava/lang/StringBuffer;
L92:    getstatic Field QA throws Ljava/io/File;
L95:    invokevirtual Method java/io/File getAbsolutePath ()Ljava/lang/String;
L98:    invokevirtual Method java/lang/StringBuffer append (Ljava/lang/String;)Ljava/lang/StringBuffer;
L101:   invokevirtual Method java/lang/StringBuffer toString ()Ljava/lang/String;
L104:   invokevirtual Method java/io/PrintStream println (Ljava/lang/String;)V
L107:   getstatic Field QA throws Ljava/io/File;
L110:   invokevirtual Method java/io/File mkdir ()Z
L113:   ifne L143
L116:   new java/io/IOException
L119:   dup
L120:   new java/lang/StringBuffer
L123:   dup
L124:   ldc_w "Cannot create "
L127:   invokespecial Method java/lang/StringBuffer <init> (Ljava/lang/String;)V
L130:   getstatic Field QA throws Ljava/io/File;
L133:   invokevirtual Method java/lang/StringBuffer append (Ljava/lang/Object;)Ljava/lang/StringBuffer;
L136:   invokevirtual Method java/lang/StringBuffer toString ()Ljava/lang/String;
L139:   invokespecial Method java/io/IOException <init> (Ljava/lang/String;)V
L142:   athrow
L143:   return
L144:   
        .attribute StackMap b'\x00\x03\x00\x0F\x00\x01\x07\x00\x02\x00\x00\x00\x6B\x00\x03\x07\x00\x02\x07\x00\x99\x07\x00\x89\x00\x00\x00\x8F\x00\x03\x07\x00\x02\x07\x00\x99\x07\x00\x89\x00\x00'
    .end code
    .exceptions java/io/IOException
.end method

.method private this : ()V
    .code stack 4 locals 2
        .catch java/lang/Exception from L0 to L4 using L9
L0:     aload_0
L1:     invokespecial Method QA else ()V
L4:     aload_0
L5:     goto L25
L8:     athrow
L9:     astore_1
L10:    aload_0
L11:    aload_1
L12:    dup
L13:    invokevirtual Method java/lang/Exception printStackTrace ()V
L16:    invokestatic Method QA break (Ljava/lang/Throwable;)Ljava/lang/String;
L19:    invokespecial Method QA break (Ljava/lang/String;)V
L22:    return
L23:    nop
L24:    athrow
L25:    new java/lang/StringBuffer
L28:    dup
L29:    ldc_w "Starting applet "
L32:    invokespecial Method java/lang/StringBuffer <init> (Ljava/lang/String;)V
L35:    aload_0
L36:    getfield Field QA byte Ljava/lang/String;
L39:    invokevirtual Method java/lang/StringBuffer append (Ljava/lang/String;)Ljava/lang/StringBuffer;
L42:    invokevirtual Method java/lang/StringBuffer toString ()Ljava/lang/String;
L45:    invokespecial Method QA const (Ljava/lang/String;)V
L48:    aload_0
L49:    iconst_0
L50:    iconst_1
L51:    dup
L52:    pop2
L53:    invokespecial Method QA break (I)V
L56:    new UA
L59:    dup
L60:    aload_0
L61:    invokespecial Method UA <init> (LQA;)V
L64:    invokestatic Method javax/swing/SwingUtilities invokeLater (Ljava/lang/Runnable;)V
L67:    return
L68:    
        .attribute StackMap b'\x00\x04\x00\x08\x00\x00\x00\x01\x07\x00\x73\x00\x09\x00\x01\x07\x00\x02\x00\x01\x07\x02\x9A\x00\x17\x00\x00\x00\x01\x07\x00\x73\x00\x19\x00\x01\x07\x00\x02\x00\x01\x07\x00\x02'
    .end code
.end method

.method private goto : ()V
    .code stack 3 locals 1
L0:     aload_0
L1:     ldc_w "noddraw.check"
L4:     invokespecial Method QA short (Ljava/lang/String;)Z
L7:     ifne L12
L10:    return
L11:    athrow
L12:    ldc_w "os.name"
L15:    invokestatic Method java/lang/System getProperty (Ljava/lang/String;)Ljava/lang/String;
L18:    invokevirtual Method java/lang/String toLowerCase ()Ljava/lang/String;
L21:    ldc_w "windows"
L24:    invokevirtual Method java/lang/String startsWith (Ljava/lang/String;)Z
L27:    ifeq L70
L30:    ldc_w "true"
L33:    ldc_w "sun.java2d.noddraw"
L36:    invokestatic Method java/lang/System getProperty (Ljava/lang/String;)Ljava/lang/String;
L39:    invokevirtual Method java/lang/String equalsIgnoreCase (Ljava/lang/String;)Z
L42:    ifne L70
L45:    invokestatic Method javax/swing/SwingUtilities isEventDispatchThread ()Z
L48:    ifne L66
        .catch java/lang/Exception from L51 to L62 using L64
L51:    new bA
L54:    dup
L55:    aload_0
L56:    invokespecial Method bA <init> (LQA;)V
L59:    invokestatic Method javax/swing/SwingUtilities invokeAndWait (Ljava/lang/Runnable;)V
L62:    return
L63:    athrow
L64:    pop
L65:    return
L66:    aload_0
L67:    invokespecial Method QA char ()V
L70:    return
L71:    
        .attribute StackMap b'\x00\x06\x00\x0B\x00\x00\x00\x01\x07\x00\x73\x00\x0C\x00\x01\x07\x00\x02\x00\x00\x00\x3F\x00\x00\x00\x01\x07\x00\x73\x00\x40\x00\x01\x07\x00\x02\x00\x01\x07\x02\x9A\x00\x42\x00\x01\x07\x00\x02\x00\x00\x00\x46\x00\x01\x07\x00\x02\x00\x00'
    .end code
.end method

.method private const : (Ljava/lang/String;)V
    .code stack 4 locals 2
L0:     aload_0
L1:     getfield Field QA goto Ljavax/swing/JProgressBar;
L4:     ifnull L19
L7:     new uA
L10:    dup
L11:    aload_0
L12:    aload_1
L13:    invokespecial Method uA <init> (LQA;Ljava/lang/String;)V
L16:    invokestatic Method javax/swing/SwingUtilities invokeLater (Ljava/lang/Runnable;)V
L19:    return
L20:    
        .attribute StackMap b'\x00\x01\x00\x13\x00\x02\x07\x00\x02\x07\x00\x89\x00\x00'
    .end code
.end method

.method public start : ()V
    .code stack 5 locals 2
L0:     getstatic Field QA "enum" Z
L3:     ifeq L15
L6:     getstatic Field java/lang/System err Ljava/io/PrintStream;
L9:     ldc_w "Applet.start"
L12:    invokevirtual Method java/io/PrintStream println (Ljava/lang/String;)V
L15:    aload_0
L16:    getfield Field QA char Z
L19:    ifeq L85
L22:    aload_0
L23:    getfield Field QA null Z
L26:    ifeq L67
L29:    aload_0
L30:    iconst_0
L31:    iconst_1
L32:    dup
L33:    pop2
L34:    putfield Field QA null Z
L37:    new SA
L40:    dup
L41:    aload_0
L42:    invokespecial Method SA <init> (LQA;)V
L45:    astore_1
L46:    iconst_4
L47:    aload_1
L48:    dup_x1
L49:    dup_x2
L50:    ldc_w "AppletLauncher-Startup"
L53:    invokevirtual Method java/lang/Thread setName (Ljava/lang/String;)V
L56:    iconst_1
L57:    dup
L58:    pop2
L59:    invokevirtual Method java/lang/Thread setPriority (I)V
L62:    invokevirtual Method java/lang/Thread start ()V
L65:    return
L66:    athrow
L67:    aload_0
L68:    getfield Field QA try Z
L71:    ifeq L85
L74:    aload_0
L75:    dup
L76:    invokespecial Method QA goto ()V
L79:    getfield Field QA for Ljava/applet/Applet;
L82:    invokevirtual Method java/applet/Applet start ()V
L85:    return
L86:    
        .attribute StackMap b'\x00\x04\x00\x0F\x00\x01\x07\x00\x02\x00\x00\x00\x42\x00\x00\x00\x01\x07\x00\x73\x00\x43\x00\x01\x07\x00\x02\x00\x00\x00\x55\x00\x01\x07\x00\x02\x00\x00'
    .end code
.end method

.method private else : (Ljava/io/File;)J
    .code stack 5 locals 5
L0:     new java/io/BufferedReader
L3:     dup
L4:     new java/io/FileReader
L7:     dup
L8:     aload_1
L9:     invokespecial Method java/io/FileReader <init> (Ljava/io/File;)V
L12:    invokespecial Method java/io/BufferedReader <init> (Ljava/io/Reader;)V
L15:    astore_1
        .catch [0] from L16 to L24 using L31
        .catch java/lang/Exception from L0 to L28 using L38
L16:    aload_1
L17:    invokevirtual Method java/io/BufferedReader readLine ()Ljava/lang/String;
L20:    invokestatic Method java/lang/Long parseLong (Ljava/lang/String;)J
L23:    lstore_3
L24:    aload_1
L25:    invokevirtual Method java/io/BufferedReader close ()V
L28:    lload_3
L29:    lreturn
L30:    athrow
        .catch java/lang/Exception from L31 to L38 using L38
L31:    astore_2
L32:    aload_2
L33:    aload_1
L34:    invokevirtual Method java/io/BufferedReader close ()V
L37:    athrow
L38:    pop
L39:    ldc2_w -1L
L42:    lreturn
L43:    
        .attribute StackMap b'\x00\x03\x00\x1E\x00\x00\x00\x01\x07\x00\x73\x00\x1F\x00\x02\x07\x00\x02\x07\x02\xDB\x00\x01\x07\x00\x73\x00\x26\x00\x02\x07\x00\x02\x07\x00\x7A\x00\x01\x07\x02\x9A'
    .end code
.end method

.method private break : (I)V
    .code stack 4 locals 2
L0:     aload_0
L1:     getfield Field QA goto Ljavax/swing/JProgressBar;
L4:     ifnull L19
L7:     new mA
L10:    dup
L11:    aload_0
L12:    iload_1
L13:    invokespecial Method mA <init> (LQA;I)V
L16:    invokestatic Method javax/swing/SwingUtilities invokeLater (Ljava/lang/Runnable;)V
L19:    return
L20:    
        .attribute StackMap b'\x00\x01\x00\x13\x00\x02\x07\x00\x02\x01\x00\x00'
    .end code
.end method

.method public static <clinit> : ()V
    .code stack 4 locals 2
L0:     ldc_w "deployment.javapi.jre."
L3:     putstatic Field QA continue Ljava/lang/String;
L6:     ldc_w "-Dsun.java2d.noddraw=true"
L9:     putstatic Field QA if Ljava/lang/String;
L12:    ldc_w ".dont_ask"
L15:    putstatic Field QA "super" Ljava/lang/String;
L18:    iconst_0
L19:    iconst_1
L20:    dup
L21:    pop2
L22:    putstatic Field QA short Z
L25:    iconst_0
L26:    iconst_1
L27:    dup
L28:    pop2
L29:    putstatic Field QA "enum" Z
L32:    iconst_1
L33:    dup
L34:    dup
L35:    pop2
L36:    putstatic Field QA long Z
L39:    aconst_null
L40:    putstatic Field QA case Ljava/util/List;
L43:    aconst_null
L44:    putstatic Field QA int Ljava/lang/String;
L47:    iconst_0
L48:    iconst_1
L49:    dup
L50:    pop2
L51:    putstatic Field QA false Z
L54:    getstatic Field java/lang/System err Ljava/io/PrintStream;
L57:    ldc_w "JNLPAppletLauncher: static initializer"
L60:    invokevirtual Method java/io/PrintStream println (Ljava/lang/String;)V
L63:    ldc_w "os.name"
L66:    invokestatic Method java/lang/System getProperty (Ljava/lang/String;)Ljava/lang/String;
L69:    invokevirtual Method java/lang/String toLowerCase ()Ljava/lang/String;
L72:    dup
L73:    astore_0
L74:    ldc_w "mac"
L77:    invokevirtual Method java/lang/String startsWith (Ljava/lang/String;)Z
L80:    ifeq L99
L83:    ldc_w "lib"
L86:    putstatic Field QA const Ljava/lang/String;
L89:    ldc_w ".jnilib"
L92:    putstatic Field QA this Ljava/lang/String;
L95:    goto L137
L98:    athrow
L99:    aload_0
L100:   ldc_w "windows"
L103:   invokevirtual Method java/lang/String startsWith (Ljava/lang/String;)Z
L106:   ifeq L125
L109:   ldc_w ""
L112:   putstatic Field QA const Ljava/lang/String;
L115:   ldc_w ".dll"
L118:   putstatic Field QA this Ljava/lang/String;
L121:   goto L137
L124:   athrow
L125:   ldc_w "lib"
L128:   putstatic Field QA const Ljava/lang/String;
L131:   ldc_w ".so"
L134:   putstatic Field QA this Ljava/lang/String;
L137:   getstatic Field QA "enum" Z
L140:   ifeq L203
L143:   getstatic Field java/lang/System err Ljava/io/PrintStream;
L146:   new java/lang/StringBuffer
L149:   dup
L150:   ldc_w "os.name = "
L153:   invokespecial Method java/lang/StringBuffer <init> (Ljava/lang/String;)V
L156:   aload_0
L157:   invokevirtual Method java/lang/StringBuffer append (Ljava/lang/String;)Ljava/lang/StringBuffer;
L160:   invokevirtual Method java/lang/StringBuffer toString ()Ljava/lang/String;
L163:   invokevirtual Method java/io/PrintStream println (Ljava/lang/String;)V
L166:   getstatic Field java/lang/System err Ljava/io/PrintStream;
L169:   new java/lang/StringBuffer
L172:   dup
L173:   ldc_w "nativePrefix = "
L176:   invokespecial Method java/lang/StringBuffer <init> (Ljava/lang/String;)V
L179:   getstatic Field QA const Ljava/lang/String;
L182:   invokevirtual Method java/lang/StringBuffer append (Ljava/lang/String;)Ljava/lang/StringBuffer;
L185:   ldc_w "  nativeSuffix = "
L188:   invokevirtual Method java/lang/StringBuffer append (Ljava/lang/String;)Ljava/lang/StringBuffer;
L191:   getstatic Field QA this Ljava/lang/String;
L194:   invokevirtual Method java/lang/StringBuffer append (Ljava/lang/String;)Ljava/lang/StringBuffer;
L197:   invokevirtual Method java/lang/StringBuffer toString ()Ljava/lang/String;
L200:   invokevirtual Method java/io/PrintStream println (Ljava/lang/String;)V
        .catch java/lang/Exception from L203 to L206 using L207
L203:   invokestatic Method QA for ()V
L206:   return
L207:   astore_1
L208:   iconst_1
L209:   aload_1
L210:   invokevirtual Method java/lang/Exception printStackTrace ()V
L213:   iconst_1
L214:   dup
L215:   pop2
L216:   putstatic Field QA false Z
L219:   return
L220:   
        .attribute StackMap b'\x00\x07\x00\x62\x00\x00\x00\x01\x07\x00\x73\x00\x63\x00\x01\x07\x00\x89\x00\x00\x00\x7C\x00\x00\x00\x01\x07\x00\x73\x00\x7D\x00\x01\x07\x00\x89\x00\x00\x00\x89\x00\x01\x07\x00\x89\x00\x00\x00\xCB\x00\x01\x07\x00\x89\x00\x00\x00\xCF\x00\x01\x07\x00\x89\x00\x01\x07\x02\x9A'
    .end code
.end method

.method private static do : ()V
    .code stack 2 locals 0
L0:     getstatic Field java/lang/System err Ljava/io/PrintStream;
L3:     ldc_w "  Resources:"
L6:     invokevirtual Method java/io/PrintStream println (Ljava/lang/String;)V
L9:     getstatic Field java/lang/System err Ljava/io/PrintStream;
L12:    ldc_w "    Class Jars:"
L15:    invokevirtual Method java/io/PrintStream println (Ljava/lang/String;)V
L18:    getstatic Field QA do Ljava/util/Set;
L21:    invokestatic Method QA break (Ljava/util/Collection;)V
L24:    getstatic Field java/lang/System err Ljava/io/PrintStream;
L27:    invokevirtual Method java/io/PrintStream println ()V
L30:    getstatic Field java/lang/System err Ljava/io/PrintStream;
L33:    ldc_w "    Native Jars:"
L36:    invokevirtual Method java/io/PrintStream println (Ljava/lang/String;)V
L39:    getstatic Field QA "static" Ljava/util/Set;
L42:    invokestatic Method QA break (Ljava/util/Collection;)V
L45:    return
L46:    
    .end code
.end method

.method public static break : (LQA;)Ljavax/swing/JProgressBar;
    .code stack 1 locals 1
L0:     aload_0
L1:     getfield Field QA goto Ljavax/swing/JProgressBar;
L4:     areturn
L5:     
    .end code
    .synthetic
.end method

.method private static for : ()V
    .code stack 7 locals 6
L0:     getstatic Field QA short Z
L3:     ifeq L15
L6:     getstatic Field java/lang/System err Ljava/io/PrintStream;
L9:     ldc_w "---------------------------------------------------"
L12:    invokevirtual Method java/io/PrintStream println (Ljava/lang/String;)V
L15:    getstatic Field java/lang/System out Ljava/io/PrintStream;
L18:    dup
L19:    astore_0
L20:    monitorenter
        .catch [0] from L21 to L480 using L639
L21:    new java/lang/StringBuffer
L24:    dup
L25:    ldc_w "java.io.tmpdir"
L28:    invokestatic Method java/lang/System getProperty (Ljava/lang/String;)Ljava/lang/String;
L31:    invokestatic Method java/lang/String valueOf (Ljava/lang/Object;)Ljava/lang/String;
L34:    invokespecial Method java/lang/StringBuffer <init> (Ljava/lang/String;)V
L37:    getstatic Field java/io/File separator Ljava/lang/String;
L40:    invokevirtual Method java/lang/StringBuffer append (Ljava/lang/String;)Ljava/lang/StringBuffer;
L43:    ldc_w "jnlp-applet"
L46:    invokevirtual Method java/lang/StringBuffer append (Ljava/lang/String;)Ljava/lang/StringBuffer;
L49:    invokevirtual Method java/lang/StringBuffer toString ()Ljava/lang/String;
L52:    astore_1
L53:    new java/io/File
L56:    dup
L57:    aload_1
L58:    invokespecial Method java/io/File <init> (Ljava/lang/String;)V
L61:    putstatic Field QA break Ljava/io/File;
L64:    ldc_w "jnlp.applet.launcher.tmproot"
L67:    invokestatic Method java/lang/System getProperty (Ljava/lang/String;)Ljava/lang/String;
L70:    putstatic Field QA new Ljava/lang/String;
L73:    getstatic Field QA new Ljava/lang/String;
L76:    ifnonnull L481
L79:    getstatic Field QA break Ljava/io/File;
L82:    invokevirtual Method java/io/File mkdir ()Z
L85:    pop
L86:    getstatic Field QA break Ljava/io/File;
L89:    invokevirtual Method java/io/File isDirectory ()Z
L92:    ifne L122
L95:    new java/io/IOException
L98:    dup
L99:    new java/lang/StringBuffer
L102:   dup
L103:   ldc_w "Cannot create directory "
L106:   invokespecial Method java/lang/StringBuffer <init> (Ljava/lang/String;)V
L109:   getstatic Field QA break Ljava/io/File;
L112:   invokevirtual Method java/lang/StringBuffer append (Ljava/lang/Object;)Ljava/lang/StringBuffer;
L115:   invokevirtual Method java/lang/StringBuffer toString ()Ljava/lang/String;
L118:   invokespecial Method java/io/IOException <init> (Ljava/lang/String;)V
L121:   athrow
L122:   ldc_w "jln"
L125:   ldc_w ".tmp"
L128:   getstatic Field QA break Ljava/io/File;
L131:   invokestatic Method java/io/File createTempFile (Ljava/lang/String;Ljava/lang/String;Ljava/io/File;)Ljava/io/File;
L134:   astore_1
L135:   getstatic Field QA short Z
L138:   ifeq L167
L141:   getstatic Field java/lang/System err Ljava/io/PrintStream;
L144:   new java/lang/StringBuffer
L147:   dup
L148:   ldc_w "tmpFile = "
L151:   invokespecial Method java/lang/StringBuffer <init> (Ljava/lang/String;)V
L154:   aload_1
L155:   invokevirtual Method java/io/File getAbsolutePath ()Ljava/lang/String;
L158:   invokevirtual Method java/lang/StringBuffer append (Ljava/lang/String;)Ljava/lang/StringBuffer;
L161:   invokevirtual Method java/lang/StringBuffer toString ()Ljava/lang/String;
L164:   invokevirtual Method java/io/PrintStream println (Ljava/lang/String;)V
L167:   new java/io/FileOutputStream
L170:   dup
L171:   aload_1
L172:   invokespecial Method java/io/FileOutputStream <init> (Ljava/io/File;)V
L175:   dup
L176:   astore_2
L177:   invokevirtual Method java/io/FileOutputStream getChannel ()Ljava/nio/channels/FileChannel;
L180:   invokevirtual Method java/nio/channels/FileChannel lock ()Ljava/nio/channels/FileLock;
L183:   astore_3
L184:   aload_1
L185:   invokevirtual Method java/io/File getAbsolutePath ()Ljava/lang/String;
L188:   astore_1
L189:   iconst_0
L190:   iconst_1
L191:   dup
L192:   pop2
L193:   aload_1
L194:   dup_x1
L195:   ldc_w ".tmp"
L198:   invokevirtual Method java/lang/String lastIndexOf (Ljava/lang/String;)I
L201:   invokevirtual Method java/lang/String substring (II)Ljava/lang/String;
L204:   astore_1
L205:   new java/lang/StringBuffer
L208:   dup
L209:   aload_1
L210:   invokestatic Method java/lang/String valueOf (Ljava/lang/Object;)Ljava/lang/String;
L213:   invokespecial Method java/lang/StringBuffer <init> (Ljava/lang/String;)V
L216:   ldc_w ".lck"
L219:   invokevirtual Method java/lang/StringBuffer append (Ljava/lang/String;)Ljava/lang/StringBuffer;
L222:   invokevirtual Method java/lang/StringBuffer toString ()Ljava/lang/String;
L225:   astore 4
L227:   new java/io/File
L230:   dup
L231:   aload 4
L233:   invokespecial Method java/io/File <init> (Ljava/lang/String;)V
L236:   astore 4
L238:   getstatic Field QA short Z
L241:   ifeq L271
L244:   getstatic Field java/lang/System err Ljava/io/PrintStream;
L247:   new java/lang/StringBuffer
L250:   dup
L251:   ldc_w "lckFile = "
L254:   invokespecial Method java/lang/StringBuffer <init> (Ljava/lang/String;)V
L257:   aload 4
L259:   invokevirtual Method java/io/File getAbsolutePath ()Ljava/lang/String;
L262:   invokevirtual Method java/lang/StringBuffer append (Ljava/lang/String;)Ljava/lang/StringBuffer;
L265:   invokevirtual Method java/lang/StringBuffer toString ()Ljava/lang/String;
L268:   invokevirtual Method java/io/PrintStream println (Ljava/lang/String;)V
L271:   aload 4
L273:   invokevirtual Method java/io/File createNewFile ()Z
L276:   new java/io/FileOutputStream
L279:   dup
L280:   aload 4
L282:   invokespecial Method java/io/FileOutputStream <init> (Ljava/io/File;)V
L285:   dup
L286:   astore 4
L288:   invokevirtual Method java/io/FileOutputStream getChannel ()Ljava/nio/channels/FileChannel;
L291:   invokevirtual Method java/nio/channels/FileChannel lock ()Ljava/nio/channels/FileLock;
L294:   astore 5
L296:   new java/io/File
L299:   dup
L300:   aload_1
L301:   invokespecial Method java/io/File <init> (Ljava/lang/String;)V
L304:   putstatic Field QA float Ljava/io/File;
L307:   pop
L308:   getstatic Field QA "enum" Z
L311:   ifeq L342
L314:   getstatic Field java/lang/System err Ljava/io/PrintStream;
L317:   new java/lang/StringBuffer
L320:   dup
L321:   ldc_w "tmpRootDir = "
L324:   invokespecial Method java/lang/StringBuffer <init> (Ljava/lang/String;)V
L327:   getstatic Field QA float Ljava/io/File;
L330:   invokevirtual Method java/io/File getAbsolutePath ()Ljava/lang/String;
L333:   invokevirtual Method java/lang/StringBuffer append (Ljava/lang/String;)Ljava/lang/StringBuffer;
L336:   invokevirtual Method java/lang/StringBuffer toString ()Ljava/lang/String;
L339:   invokevirtual Method java/io/PrintStream println (Ljava/lang/String;)V
L342:   getstatic Field QA float Ljava/io/File;
L345:   invokevirtual Method java/io/File mkdir ()Z
L348:   ifne L378
L351:   new java/io/IOException
L354:   dup
L355:   new java/lang/StringBuffer
L358:   dup
L359:   ldc_w "Cannot create "
L362:   invokespecial Method java/lang/StringBuffer <init> (Ljava/lang/String;)V
L365:   getstatic Field QA float Ljava/io/File;
L368:   invokevirtual Method java/lang/StringBuffer append (Ljava/lang/Object;)Ljava/lang/StringBuffer;
L371:   invokevirtual Method java/lang/StringBuffer toString ()Ljava/lang/String;
L374:   invokespecial Method java/io/IOException <init> (Ljava/lang/String;)V
L377:   athrow
L378:   invokestatic Method java/lang/Runtime getRuntime ()Ljava/lang/Runtime;
L381:   new ZA
L384:   dup
L385:   aload_2
L386:   aload_3
L387:   aload 4
L389:   aload 5
L391:   invokespecial Method ZA <init> (Ljava/io/FileOutputStream;Ljava/nio/channels/FileLock;Ljava/io/FileOutputStream;Ljava/nio/channels/FileLock;)V
L394:   invokevirtual Method java/lang/Runtime addShutdownHook (Ljava/lang/Thread;)V
L397:   ldc_w "jnlp.applet.launcher.tmproot"
L400:   aload_1
L401:   dup
L402:   getstatic Field java/io/File separator Ljava/lang/String;
L405:   invokevirtual Method java/lang/String lastIndexOf (Ljava/lang/String;)I
L408:   iconst_1
L409:   dup
L410:   dup
L411:   pop2
L412:   iadd
L413:   invokevirtual Method java/lang/String substring (I)Ljava/lang/String;
L416:   putstatic Field QA new Ljava/lang/String;
L419:   getstatic Field QA new Ljava/lang/String;
L422:   invokestatic Method java/lang/System setProperty (Ljava/lang/String;Ljava/lang/String;)Ljava/lang/String;
L425:   pop
L426:   getstatic Field QA short Z
L429:   ifeq L457
L432:   getstatic Field java/lang/System err Ljava/io/PrintStream;
L435:   new java/lang/StringBuffer
L438:   dup
L439:   ldc_w "Setting jnlp.applet.launcher.tmproot="
L442:   invokespecial Method java/lang/StringBuffer <init> (Ljava/lang/String;)V
L445:   getstatic Field QA new Ljava/lang/String;
L448:   invokevirtual Method java/lang/StringBuffer append (Ljava/lang/String;)Ljava/lang/StringBuffer;
L451:   invokevirtual Method java/lang/StringBuffer toString ()Ljava/lang/String;
L454:   invokevirtual Method java/io/PrintStream println (Ljava/lang/String;)V
L457:   new TA
L460:   dup
L461:   invokespecial Method TA <init> ()V
L464:   astore_1
L465:   aload_0
L466:   aload_1
L467:   dup
L468:   ldc_w "AppletLauncher-Reaper"
L471:   invokevirtual Method java/lang/Thread setName (Ljava/lang/String;)V
L474:   invokevirtual Method java/lang/Thread start ()V
L477:   goto L636
L480:   athrow
        .catch [0] from L481 to L637 using L639
L481:   getstatic Field QA new Ljava/lang/String;
L484:   bipush 47
L486:   iconst_1
L487:   dup
L488:   pop2
L489:   invokevirtual Method java/lang/String indexOf (I)I
L492:   ifge L507
L495:   getstatic Field QA new Ljava/lang/String;
L498:   getstatic Field java/io/File separatorChar C
L501:   invokevirtual Method java/lang/String indexOf (I)I
L504:   iflt L518
L507:   new java/io/IOException
L510:   dup
L511:   ldc_w "Illegal value of: jnlp.applet.launcher.tmproot"
L514:   invokespecial Method java/io/IOException <init> (Ljava/lang/String;)V
L517:   athrow
L518:   getstatic Field QA short Z
L521:   ifeq L549
L524:   getstatic Field java/lang/System err Ljava/io/PrintStream;
L527:   new java/lang/StringBuffer
L530:   dup
L531:   ldc_w "Using existing value of: jnlp.applet.launcher.tmproot="
L534:   invokespecial Method java/lang/StringBuffer <init> (Ljava/lang/String;)V
L537:   getstatic Field QA new Ljava/lang/String;
L540:   invokevirtual Method java/lang/StringBuffer append (Ljava/lang/String;)Ljava/lang/StringBuffer;
L543:   invokevirtual Method java/lang/StringBuffer toString ()Ljava/lang/String;
L546:   invokevirtual Method java/io/PrintStream println (Ljava/lang/String;)V
L549:   new java/io/File
L552:   dup
L553:   getstatic Field QA break Ljava/io/File;
L556:   getstatic Field QA new Ljava/lang/String;
L559:   invokespecial Method java/io/File <init> (Ljava/io/File;Ljava/lang/String;)V
L562:   putstatic Field QA float Ljava/io/File;
L565:   getstatic Field QA "enum" Z
L568:   ifeq L599
L571:   getstatic Field java/lang/System err Ljava/io/PrintStream;
L574:   new java/lang/StringBuffer
L577:   dup
L578:   ldc_w "tmpRootDir = "
L581:   invokespecial Method java/lang/StringBuffer <init> (Ljava/lang/String;)V
L584:   getstatic Field QA float Ljava/io/File;
L587:   invokevirtual Method java/io/File getAbsolutePath ()Ljava/lang/String;
L590:   invokevirtual Method java/lang/StringBuffer append (Ljava/lang/String;)Ljava/lang/StringBuffer;
L593:   invokevirtual Method java/lang/StringBuffer toString ()Ljava/lang/String;
L596:   invokevirtual Method java/io/PrintStream println (Ljava/lang/String;)V
L599:   getstatic Field QA float Ljava/io/File;
L602:   invokevirtual Method java/io/File isDirectory ()Z
L605:   ifne L635
L608:   new java/io/IOException
L611:   dup
L612:   new java/lang/StringBuffer
L615:   dup
L616:   ldc_w "Cannot access "
L619:   invokespecial Method java/lang/StringBuffer <init> (Ljava/lang/String;)V
L622:   getstatic Field QA float Ljava/io/File;
L625:   invokevirtual Method java/lang/StringBuffer append (Ljava/lang/Object;)Ljava/lang/StringBuffer;
L628:   invokevirtual Method java/lang/StringBuffer toString ()Ljava/lang/String;
L631:   invokespecial Method java/io/IOException <init> (Ljava/lang/String;)V
L634:   athrow
L635:   aload_0
L636:   monitorexit
L637:   return
L638:   athrow
        .catch [0] from L639 to L641 using L639
L639:   aload_0
L640:   monitorexit
L641:   athrow
L642:   athrow
L643:   
        .attribute StackMap b'\x00\x12\x00\x0F\x00\x00\x00\x00\x00\x7A\x00\x02\x07\x00\xCD\x07\x00\x89\x00\x00\x00\xA7\x00\x02\x07\x00\xCD\x07\x00\x99\x00\x00\x01\x0F\x00\x05\x07\x00\xCD\x07\x00\x89\x07\x00\x64\x07\x01\x76\x07\x00\x99\x00\x00\x01\x56\x00\x06\x07\x00\xCD\x07\x00\x89\x07\x00\x64\x07\x01\x76\x07\x00\x64\x07\x01\x76\x00\x00\x01\x7A\x00\x06\x07\x00\xCD\x07\x00\x89\x07\x00\x64\x07\x01\x76\x07\x00\x64\x07\x01\x76\x00\x00\x01\xC9\x00\x06\x07\x00\xCD\x07\x00\x89\x07\x00\x64\x07\x01\x76\x07\x00\x64\x07\x01\x76\x00\x00\x01\xE0\x00\x00\x00\x01\x07\x00\x73\x01\xE1\x00\x02\x07\x00\xCD\x07\x00\x89\x00\x00\x01\xFB\x00\x02\x07\x00\xCD\x07\x00\x89\x00\x00\x02\x06\x00\x02\x07\x00\xCD\x07\x00\x89\x00\x00\x02\x25\x00\x02\x07\x00\xCD\x07\x00\x89\x00\x00\x02\x57\x00\x02\x07\x00\xCD\x07\x00\x89\x00\x00\x02\x7B\x00\x02\x07\x00\xCD\x07\x00\x89\x00\x00\x02\x7C\x00\x02\x07\x00\xCD\x07\x00\x7A\x00\x01\x07\x00\xCD\x02\x7E\x00\x00\x00\x01\x07\x00\x73\x02\x7F\x00\x01\x07\x00\xCD\x00\x01\x07\x00\x73\x02\x82\x00\x00\x00\x01\x07\x00\x73'
    .end code
    .exceptions java/io/IOException
.end method

.method private break : (Ljava/io/InputStream;Ljava/io/OutputStream;I)I
    .code stack 5 locals 8
L0:     iconst_0
L1:     iconst_1
L2:     dup
L3:     pop2
L4:     istore 4
L6:     ldc_w 1e2f
L9:     iload_3
L10:    i2f
L11:    fdiv
L12:    fstore 5
L14:    sipush 1000
L17:    iconst_1
L18:    dup
L19:    pop2
L20:    newarray byte
L22:    iconst_1
L23:    dup
L24:    pop2
L25:    astore 6
L27:    aload_0
L28:    iconst_0
L29:    iconst_1
L30:    dup
L31:    pop2
L32:    invokespecial Method QA break (I)V
L35:    aload_1
L36:    aload 6
L38:    invokevirtual Method java/io/InputStream read ([B)I
L41:    dup
L42:    istore 7
L44:    iconst_m1
L45:    iconst_1
L46:    dup
L47:    pop2
L48:    if_icmpne L56
L51:    aload_0
L52:    goto L98
L55:    athrow
L56:    aload_2
L57:    aload 6
L59:    iconst_0
L60:    iconst_1
L61:    dup
L62:    pop2
L63:    iload 7
L65:    invokevirtual Method java/io/OutputStream write ([BII)V
L68:    iload 4
L70:    iload 7
L72:    iadd
L73:    istore 4
L75:    iload_3
L76:    ifle L35
L79:    aload_1
L80:    aload_0
L81:    iload 4
L83:    i2f
L84:    fload 5
L86:    fmul
L87:    invokestatic Method java/lang/Math round (F)I
L90:    invokespecial Method QA break (I)V
L93:    goto L36
L96:    nop
L97:    athrow
L98:    bipush 100
L100:   iconst_1
L101:   dup
L102:   pop2
L103:   invokespecial Method QA break (I)V
L106:   iload 4
L108:   ireturn
L109:   
        .attribute StackMap b'\x00\x06\x00\x23\x00\x07\x07\x00\x02\x07\x00\x7C\x07\x00\x75\x01\x01\x02\x07\x02\x7C\x00\x00\x00\x24\x00\x07\x07\x00\x02\x07\x00\x7C\x07\x00\x75\x01\x01\x02\x07\x02\x7C\x00\x01\x07\x00\x7C\x00\x37\x00\x00\x00\x01\x07\x00\x73\x00\x38\x00\x08\x07\x00\x02\x07\x00\x7C\x07\x00\x75\x01\x01\x02\x07\x02\x7C\x01\x00\x00\x00\x60\x00\x00\x00\x01\x07\x00\x73\x00\x62\x00\x08\x07\x00\x02\x07\x00\x7C\x07\x00\x75\x01\x01\x02\x07\x02\x7C\x01\x00\x01\x07\x00\x02'
    .end code
    .exceptions java/io/IOException
.end method

.method private break : (Ljava/util/jar/JarFile;)Ljava/util/Set;
    .code stack 4 locals 4
L0:     getstatic Field QA short Z
L3:     ifeq L15
L6:     getstatic Field java/lang/System err Ljava/io/PrintStream;
L9:     ldc_w "getNativeLibNames:"
L12:    invokevirtual Method java/io/PrintStream println (Ljava/lang/String;)V
L15:    new java/util/HashSet
L18:    dup
L19:    invokespecial Method java/util/HashSet <init> ()V
L22:    astore_2
L23:    aload_1
L24:    invokevirtual Method java/util/jar/JarFile entries ()Ljava/util/Enumeration;
L27:    dup
L28:    astore_1
L29:    goto L140
L32:    athrow
L33:    aload_1
L34:    invokeinterface InterfaceMethod java/util/Enumeration nextElement ()Ljava/lang/Object; 1
L39:    checkcast java/util/jar/JarEntry
L42:    invokevirtual Method java/util/jar/JarEntry getName ()Ljava/lang/String;
L45:    astore_3
L46:    getstatic Field QA short Z
L49:    ifeq L75
L52:    getstatic Field java/lang/System err Ljava/io/PrintStream;
L55:    new java/lang/StringBuffer
L58:    dup
L59:    ldc_w "JarEntry : "
L62:    invokespecial Method java/lang/StringBuffer <init> (Ljava/lang/String;)V
L65:    aload_3
L66:    invokevirtual Method java/lang/StringBuffer append (Ljava/lang/String;)Ljava/lang/StringBuffer;
L69:    invokevirtual Method java/lang/StringBuffer toString ()Ljava/lang/String;
L72:    invokevirtual Method java/io/PrintStream println (Ljava/lang/String;)V
L75:    aload_3
L76:    bipush 47
L78:    iconst_1
L79:    dup
L80:    pop2
L81:    invokevirtual Method java/lang/String indexOf (I)I
L84:    iconst_m1
L85:    iconst_1
L86:    dup
L87:    pop2
L88:    if_icmpne L139
L91:    aload_3
L92:    getstatic Field java/io/File separatorChar C
L95:    invokevirtual Method java/lang/String indexOf (I)I
L98:    iconst_m1
L99:    iconst_1
L100:   dup
L101:   pop2
L102:   if_icmpne L139
L105:   aload_3
L106:   invokevirtual Method java/lang/String toLowerCase ()Ljava/lang/String;
L109:   getstatic Field QA const Ljava/lang/String;
L112:   invokevirtual Method java/lang/String startsWith (Ljava/lang/String;)Z
L115:   ifeq L139
L118:   aload_3
L119:   invokevirtual Method java/lang/String toLowerCase ()Ljava/lang/String;
L122:   getstatic Field QA this Ljava/lang/String;
L125:   invokevirtual Method java/lang/String endsWith (Ljava/lang/String;)Z
L128:   ifeq L139
L131:   aload_2
L132:   aload_3
L133:   invokeinterface InterfaceMethod java/util/Set add (Ljava/lang/Object;)Z 2
L138:   pop
L139:   aload_1
L140:   invokeinterface InterfaceMethod java/util/Enumeration hasMoreElements ()Z 1
L145:   ifne L33
L148:   aload_2
L149:   areturn
L150:   
        .attribute StackMap b'\x00\x06\x00\x0F\x00\x02\x07\x00\x02\x07\x01\x13\x00\x00\x00\x20\x00\x00\x00\x01\x07\x00\x73\x00\x21\x00\x03\x07\x00\x02\x07\x01\x28\x07\x02\x33\x00\x00\x00\x4B\x00\x04\x07\x00\x02\x07\x01\x28\x07\x02\x33\x07\x00\x89\x00\x00\x00\x8B\x00\x04\x07\x00\x02\x07\x01\x28\x07\x02\x33\x07\x00\x89\x00\x00\x00\x8C\x00\x03\x07\x00\x02\x07\x01\x28\x07\x02\x33\x00\x01\x07\x01\x28'
    .end code
.end method

.method private static else : (Ljava/lang/String;)Ljava/lang/String;
    .code stack 4 locals 5
L0:     aconst_null
L1:     astore_1
        .catch java/security/NoSuchAlgorithmException from L2 to L9 using L14
L2:     ldc_w "SHA-1"
L5:     invokestatic Method java/security/MessageDigest getInstance (Ljava/lang/String;)Ljava/security/MessageDigest;
L8:     astore_1
L9:     aload_1
L10:    goto L25
L13:    athrow
L14:    astore_2
L15:    new java/lang/RuntimeException
L18:    dup
L19:    aload_2
L20:    invokespecial Method java/lang/RuntimeException <init> (Ljava/lang/Throwable;)V
L23:    athrow
L24:    athrow
L25:    aload_0
L26:    invokevirtual Method java/lang/String getBytes ()[B
L29:    invokevirtual Method java/security/MessageDigest digest ([B)[B
L32:    dup
L33:    astore_2
L34:    ifnull L42
L37:    aload_2
L38:    arraylength
L39:    ifne L53
L42:    new java/lang/RuntimeException
L45:    dup
L46:    ldc_w "Error reading message digest"
L49:    invokespecial Method java/lang/RuntimeException <init> (Ljava/lang/String;)V
L52:    athrow
L53:    new java/lang/StringBuffer
L56:    dup
L57:    invokespecial Method java/lang/StringBuffer <init> ()V
L60:    astore_1
L61:    iconst_0
L62:    iconst_1
L63:    dup
L64:    pop2
L65:    dup
L66:    istore_3
L67:    goto L114
L70:    athrow
L71:    aload_2
L72:    iload_3
L73:    baload
L74:    sipush 255
L77:    iconst_1
L78:    dup
L79:    pop2
L80:    iand
L81:    dup
L82:    istore 4
L84:    bipush 16
L86:    iconst_1
L87:    dup
L88:    pop2
L89:    if_icmpge L100
L92:    aload_1
L93:    ldc_w "0"
L96:    invokevirtual Method java/lang/StringBuffer append (Ljava/lang/String;)Ljava/lang/StringBuffer;
L99:    pop
L100:   aload_1
L101:   iinc 3 1
L104:   iload 4
L106:   invokestatic Method java/lang/Integer toHexString (I)Ljava/lang/String;
L109:   invokevirtual Method java/lang/StringBuffer append (Ljava/lang/String;)Ljava/lang/StringBuffer;
L112:   pop
L113:   iload_3
L114:   aload_2
L115:   arraylength
L116:   if_icmplt L71
L119:   aload_1
L120:   invokevirtual Method java/lang/StringBuffer toString ()Ljava/lang/String;
L123:   areturn
L124:   
        .attribute StackMap b'\x00\x0A\x00\x0D\x00\x00\x00\x01\x07\x00\x73\x00\x0E\x00\x02\x07\x00\x89\x07\x03\x6D\x00\x01\x07\x03\x69\x00\x18\x00\x00\x00\x01\x07\x00\x73\x00\x19\x00\x02\x07\x00\x89\x07\x03\x6D\x00\x01\x07\x03\x6D\x00\x2A\x00\x03\x07\x00\x89\x07\x03\x6D\x07\x02\x7C\x00\x00\x00\x35\x00\x03\x07\x00\x89\x07\x03\x6D\x07\x02\x7C\x00\x00\x00\x46\x00\x00\x00\x01\x07\x00\x73\x00\x47\x00\x04\x07\x00\x89\x07\x00\xA4\x07\x02\x7C\x01\x00\x00\x00\x64\x00\x05\x07\x00\x89\x07\x00\xA4\x07\x02\x7C\x01\x01\x00\x00\x00\x72\x00\x04\x07\x00\x89\x07\x00\xA4\x07\x02\x7C\x01\x00\x01\x01'
    .end code
.end method

.method private break : (Ljava/net/URL;)V
    .code stack 2 locals 2
L0:     getstatic Field QA "static" Ljava/util/Set;
L3:     aload_1
L4:     invokeinterface InterfaceMethod java/util/Set add (Ljava/lang/Object;)Z 2
L9:     pop
L10:    return
L11:    
    .end code
.end method

.method private break : (Ljava/lang/String;)V
    .code stack 4 locals 2
L0:     ldc_w "global"
L3:     invokestatic Method java/util/logging/Logger getLogger (Ljava/lang/String;)Ljava/util/logging/Logger;
L6:     aload_1
L7:     invokevirtual Method java/util/logging/Logger severe (Ljava/lang/String;)V
L10:    aload_0
L11:    getfield Field QA goto Ljavax/swing/JProgressBar;
L14:    ifnull L29
L17:    new EA
L20:    dup
L21:    aload_0
L22:    aload_1
L23:    invokespecial Method EA <init> (LQA;Ljava/lang/String;)V
L26:    invokestatic Method javax/swing/SwingUtilities invokeLater (Ljava/lang/Runnable;)V
L29:    return
L30:    
        .attribute StackMap b'\x00\x01\x00\x1D\x00\x02\x07\x00\x02\x07\x00\x89\x00\x00'
    .end code
.end method

.method private static catch : ()V
    .code stack 4 locals 11
L0:     getstatic Field QA short Z
L3:     ifeq L34
L6:     getstatic Field java/lang/System err Ljava/io/PrintStream;
L9:     new java/lang/StringBuffer
L12:    dup
L13:    ldc_w "*** Reaper: deleteOldTempDirs in "
L16:    invokespecial Method java/lang/StringBuffer <init> (Ljava/lang/String;)V
L19:    getstatic Field QA break Ljava/io/File;
L22:    invokevirtual Method java/io/File getAbsolutePath ()Ljava/lang/String;
L25:    invokevirtual Method java/lang/StringBuffer append (Ljava/lang/String;)Ljava/lang/StringBuffer;
L28:    invokevirtual Method java/lang/StringBuffer toString ()Ljava/lang/String;
L31:    invokevirtual Method java/io/PrintStream println (Ljava/lang/String;)V
L34:    new java/lang/StringBuffer
L37:    dup
L38:    getstatic Field QA new Ljava/lang/String;
L41:    invokestatic Method java/lang/String valueOf (Ljava/lang/Object;)Ljava/lang/String;
L44:    invokespecial Method java/lang/StringBuffer <init> (Ljava/lang/String;)V
L47:    ldc_w ".lck"
L50:    invokevirtual Method java/lang/StringBuffer append (Ljava/lang/String;)Ljava/lang/StringBuffer;
L53:    invokevirtual Method java/lang/StringBuffer toString ()Ljava/lang/String;
L56:    astore_0
L57:    new WA
L60:    dup
L61:    aload_0
L62:    invokespecial Method WA <init> (Ljava/lang/String;)V
L65:    astore_1
L66:    getstatic Field QA break Ljava/io/File;
L69:    aload_1
L70:    invokevirtual Method java/io/File list (Ljava/io/FilenameFilter;)[Ljava/lang/String;
L73:    dup
L74:    astore_1
L75:    ifnull L426
L78:    iconst_0
L79:    iconst_1
L80:    dup
L81:    pop2
L82:    dup
L83:    istore_2
L84:    goto L421
L87:    athrow
L88:    aload_1
L89:    iload_2
L90:    aaload
L91:    astore_3
L92:    iconst_0
L93:    iconst_1
L94:    dup
L95:    pop2
L96:    aload_3
L97:    dup_x1
L98:    ldc_w ".lck"
L101:   invokevirtual Method java/lang/String lastIndexOf (Ljava/lang/String;)I
L104:   invokevirtual Method java/lang/String substring (II)Ljava/lang/String;
L107:   astore 4
L109:   new java/lang/StringBuffer
L112:   dup
L113:   aload 4
L115:   invokestatic Method java/lang/String valueOf (Ljava/lang/Object;)Ljava/lang/String;
L118:   invokespecial Method java/lang/StringBuffer <init> (Ljava/lang/String;)V
L121:   ldc_w ".tmp"
L124:   invokevirtual Method java/lang/StringBuffer append (Ljava/lang/String;)Ljava/lang/StringBuffer;
L127:   invokevirtual Method java/lang/StringBuffer toString ()Ljava/lang/String;
L130:   astore 5
L132:   new java/io/File
L135:   dup
L136:   getstatic Field QA break Ljava/io/File;
L139:   aload_3
L140:   invokespecial Method java/io/File <init> (Ljava/io/File;Ljava/lang/String;)V
L143:   astore_3
L144:   new java/io/File
L147:   dup
L148:   getstatic Field QA break Ljava/io/File;
L151:   aload 5
L153:   invokespecial Method java/io/File <init> (Ljava/io/File;Ljava/lang/String;)V
L156:   astore 5
L158:   new java/io/File
L161:   dup
L162:   getstatic Field QA break Ljava/io/File;
L165:   aload 4
L167:   invokespecial Method java/io/File <init> (Ljava/io/File;Ljava/lang/String;)V
L170:   astore 4
L172:   aload_3
L173:   invokevirtual Method java/io/File exists ()Z
L176:   ifeq L384
L179:   aload 5
L181:   invokevirtual Method java/io/File exists ()Z
L184:   ifeq L384
L187:   aload 4
L189:   invokevirtual Method java/io/File isDirectory ()Z
L192:   ifeq L384
L195:   aconst_null
L196:   astore 6
L198:   aconst_null
L199:   astore 7
L201:   aconst_null
L202:   astore 8
        .catch java/lang/Exception from L204 to L227 using L233
L204:   new java/io/FileOutputStream
L207:   dup
L208:   aload 5
L210:   invokespecial Method java/io/FileOutputStream <init> (Ljava/io/File;)V
L213:   dup
L214:   astore 6
L216:   invokevirtual Method java/io/FileOutputStream getChannel ()Ljava/nio/channels/FileChannel;
L219:   dup
L220:   astore 7
L222:   invokevirtual Method java/nio/channels/FileChannel tryLock ()Ljava/nio/channels/FileLock;
L225:   astore 8
L227:   aload 8
L229:   goto L248
L232:   athrow
L233:   astore 7
L235:   getstatic Field QA "enum" Z
L238:   ifeq L246
L241:   aload 7
L243:   invokevirtual Method java/lang/Exception printStackTrace ()V
L246:   aload 8
L248:   ifnull L417
L251:   aconst_null
L252:   astore 7
L254:   aconst_null
L255:   astore 9
L257:   aconst_null
L258:   astore 10
        .catch java/lang/Exception from L260 to L282 using L287
L260:   new java/io/FileOutputStream
L263:   dup
L264:   aload_3
L265:   invokespecial Method java/io/FileOutputStream <init> (Ljava/io/File;)V
L268:   dup
L269:   astore 7
L271:   invokevirtual Method java/io/FileOutputStream getChannel ()Ljava/nio/channels/FileChannel;
L274:   dup
L275:   astore 9
L277:   invokevirtual Method java/nio/channels/FileChannel tryLock ()Ljava/nio/channels/FileLock;
L280:   astore 10
L282:   aload 10
L284:   goto L302
L287:   astore 9
L289:   getstatic Field QA "enum" Z
L292:   ifeq L300
L295:   aload 9
L297:   invokevirtual Method java/lang/Exception printStackTrace ()V
L300:   aload 10
L302:   ifnull L345
L305:   aload 4
L307:   invokestatic Method QA break (Ljava/io/File;)V
        .catch java/io/IOException from L310 to L315 using L319
L310:   aload 7
L312:   invokevirtual Method java/io/FileOutputStream close ()V
L315:   aload_3
L316:   goto L321
L319:   pop
L320:   aload_3
L321:   invokevirtual Method java/io/File delete ()Z
L324:   pop
        .catch java/io/IOException from L325 to L330 using L335
L325:   aload 6
L327:   invokevirtual Method java/io/FileOutputStream close ()V
L330:   aload 5
L332:   goto L338
L335:   pop
L336:   aload 5
L338:   invokevirtual Method java/io/File delete ()Z
L341:   pop
L342:   goto L417
        .catch java/io/IOException from L345 to L365 using L368
L345:   aload 7
L347:   ifnull L355
L350:   aload 7
L352:   invokevirtual Method java/io/FileOutputStream close ()V
L355:   aload 6
L357:   invokevirtual Method java/io/FileOutputStream close ()V
L360:   aload 8
L362:   invokevirtual Method java/nio/channels/FileLock release ()V
L365:   goto L417
L368:   astore 9
L370:   getstatic Field QA "enum" Z
L373:   ifeq L417
L376:   aload 9
L378:   invokevirtual Method java/io/IOException printStackTrace ()V
L381:   goto L417
L384:   getstatic Field QA short Z
L387:   ifeq L417
L390:   getstatic Field java/lang/System err Ljava/io/PrintStream;
L393:   new java/lang/StringBuffer
L396:   dup
L397:   ldc_w "    Skipping: "
L400:   invokespecial Method java/lang/StringBuffer <init> (Ljava/lang/String;)V
L403:   aload 4
L405:   invokevirtual Method java/io/File getAbsolutePath ()Ljava/lang/String;
L408:   invokevirtual Method java/lang/StringBuffer append (Ljava/lang/String;)Ljava/lang/StringBuffer;
L411:   invokevirtual Method java/lang/StringBuffer toString ()Ljava/lang/String;
L414:   invokevirtual Method java/io/PrintStream println (Ljava/lang/String;)V
L417:   iinc 2 1
L420:   iload_2
L421:   aload_1
L422:   arraylength
L423:   if_icmplt L88
L426:   return
L427:   
        .attribute StackMap b'\x00\x15\x00\x22\x00\x00\x00\x00\x00\x57\x00\x00\x00\x01\x07\x00\x73\x00\x58\x00\x03\x07\x00\x89\x07\x03\x9D\x01\x00\x00\x00\xE8\x00\x00\x00\x01\x07\x00\x73\x00\xE9\x00\x09\x07\x00\x89\x07\x03\x9D\x01\x07\x00\x99\x07\x00\x99\x07\x00\x99\x07\x00\x64\x07\x01\x66\x07\x01\x76\x00\x01\x07\x02\x9A\x00\xF6\x00\x09\x07\x00\x89\x07\x03\x9D\x01\x07\x00\x99\x07\x00\x99\x07\x00\x99\x07\x00\x64\x07\x02\x9A\x07\x01\x76\x00\x00\x00\xF8\x00\x09\x07\x00\x89\x07\x03\x9D\x01\x07\x00\x99\x07\x00\x99\x07\x00\x99\x07\x00\x64\x07\x00\x7A\x07\x01\x76\x00\x01\x07\x01\x76\x01\x1F\x00\x0B\x07\x00\x89\x07\x03\x9D\x01\x07\x00\x99\x07\x00\x99\x07\x00\x99\x07\x00\x64\x07\x00\x64\x07\x01\x76\x07\x01\x66\x07\x01\x76\x00\x01\x07\x02\x9A\x01\x2C\x00\x0B\x07\x00\x89\x07\x03\x9D\x01\x07\x00\x99\x07\x00\x99\x07\x00\x99\x07\x00\x64\x07\x00\x64\x07\x01\x76\x07\x02\x9A\x07\x01\x76\x00\x00\x01\x2E\x00\x0B\x07\x00\x89\x07\x03\x9D\x01\x07\x00\x99\x07\x00\x99\x07\x00\x99\x07\x00\x64\x07\x00\x64\x07\x01\x76\x07\x00\x7A\x07\x01\x76\x00\x01\x07\x01\x76\x01\x3F\x00\x0B\x07\x00\x89\x07\x03\x9D\x01\x07\x00\x99\x07\x00\x99\x07\x00\x99\x07\x00\x64\x07\x00\x64\x07\x01\x76\x07\x00\x7A\x07\x01\x76\x00\x01\x07\x00\x54\x01\x41\x00\x0B\x07\x00\x89\x07\x03\x9D\x01\x07\x00\x99\x07\x00\x99\x07\x00\x99\x07\x00\x64\x07\x00\x64\x07\x01\x76\x07\x00\x7A\x07\x01\x76\x00\x01\x07\x00\x99\x01\x4F\x00\x0B\x07\x00\x89\x07\x03\x9D\x01\x07\x00\x99\x07\x00\x99\x07\x00\x99\x07\x00\x64\x07\x00\x64\x07\x01\x76\x07\x00\x7A\x07\x01\x76\x00\x01\x07\x00\x54\x01\x52\x00\x0B\x07\x00\x89\x07\x03\x9D\x01\x07\x00\x99\x07\x00\x99\x07\x00\x99\x07\x00\x64\x07\x00\x64\x07\x01\x76\x07\x00\x7A\x07\x01\x76\x00\x01\x07\x00\x99\x01\x59\x00\x0B\x07\x00\x89\x07\x03\x9D\x01\x07\x00\x99\x07\x00\x99\x07\x00\x99\x07\x00\x64\x07\x00\x64\x07\x01\x76\x07\x00\x7A\x07\x01\x76\x00\x00\x01\x63\x00\x0B\x07\x00\x89\x07\x03\x9D\x01\x07\x00\x99\x07\x00\x99\x07\x00\x99\x07\x00\x64\x07\x00\x64\x07\x01\x76\x07\x00\x7A\x07\x01\x76\x00\x00\x01\x70\x00\x0B\x07\x00\x89\x07\x03\x9D\x01\x07\x00\x99\x07\x00\x99\x07\x00\x99\x07\x00\x64\x07\x00\x64\x07\x01\x76\x07\x00\x7A\x07\x01\x76\x00\x01\x07\x00\x54\x01\x80\x00\x06\x07\x00\x89\x07\x03\x9D\x01\x07\x00\x99\x07\x00\x99\x07\x00\x99\x00\x00\x01\xA1\x00\x06\x07\x00\x89\x07\x03\x9D\x01\x07\x00\x99\x07\x00\x99\x07\x00\x99\x00\x00\x01\xA5\x00\x03\x07\x00\x89\x07\x03\x9D\x01\x00\x01\x01\x01\xAA\x00\x02\x07\x00\x89\x07\x03\x9D\x00\x00'
    .end code
.end method

.method private static break : (Ljava/util/Collection;)V
    .code stack 4 locals 3
L0:     aload_0
L1:     invokeinterface InterfaceMethod java/util/Collection iterator ()Ljava/util/Iterator; 1
L6:     dup
L7:     astore_1
L8:     goto L49
L11:    athrow
L12:    aload_1
L13:    invokeinterface InterfaceMethod java/util/Iterator next ()Ljava/lang/Object; 1
L18:    checkcast java/net/URL
L21:    invokevirtual Method java/net/URL toExternalForm ()Ljava/lang/String;
L24:    astore_2
L25:    getstatic Field java/lang/System err Ljava/io/PrintStream;
L28:    new java/lang/StringBuffer
L31:    dup
L32:    ldc_w "      "
L35:    invokespecial Method java/lang/StringBuffer <init> (Ljava/lang/String;)V
L38:    aload_2
L39:    invokevirtual Method java/lang/StringBuffer append (Ljava/lang/String;)Ljava/lang/StringBuffer;
L42:    invokevirtual Method java/lang/StringBuffer toString ()Ljava/lang/String;
L45:    invokevirtual Method java/io/PrintStream println (Ljava/lang/String;)V
L48:    aload_1
L49:    invokeinterface InterfaceMethod java/util/Iterator hasNext ()Z 1
L54:    ifne L12
L57:    return
L58:    
        .attribute StackMap b'\x00\x03\x00\x0B\x00\x00\x00\x01\x07\x00\x73\x00\x0C\x00\x02\x07\x03\xA7\x07\x00\xF0\x00\x00\x00\x31\x00\x02\x07\x03\xA7\x07\x00\xF0\x00\x01\x07\x00\xF0'
    .end code
.end method

.method private float : ()Ljava/lang/String;
    .code stack 4 locals 3
L0:     ldc_w "os.name"
L3:     invokestatic Method java/lang/System getProperty (Ljava/lang/String;)Ljava/lang/String;
L6:     invokevirtual Method java/lang/String toLowerCase ()Ljava/lang/String;
L9:     astore_1
L10:    new java/lang/StringBuffer
L13:    dup
L14:    invokespecial Method java/lang/StringBuffer <init> ()V
L17:    astore_2
L18:    aload_1
L19:    ldc_w "windows"
L22:    aload_2
L23:    ldc_w "user.home"
L26:    invokestatic Method java/lang/System getProperty (Ljava/lang/String;)Ljava/lang/String;
L29:    invokevirtual Method java/lang/StringBuffer append (Ljava/lang/String;)Ljava/lang/StringBuffer;
L32:    pop
L33:    invokevirtual Method java/lang/String startsWith (Ljava/lang/String;)Z
L36:    ifeq L141
L39:    aload_1
L40:    ldc_w "vista"
L43:    invokevirtual Method java/lang/String indexOf (Ljava/lang/String;)I
L46:    iconst_m1
L47:    iconst_1
L48:    dup
L49:    pop2
L50:    if_icmpeq L84
L53:    aload_2
L54:    dup
L55:    getstatic Field java/io/File separator Ljava/lang/String;
L58:    invokevirtual Method java/lang/StringBuffer append (Ljava/lang/String;)Ljava/lang/StringBuffer;
L61:    ldc_w "AppData"
L64:    invokevirtual Method java/lang/StringBuffer append (Ljava/lang/String;)Ljava/lang/StringBuffer;
L67:    getstatic Field java/io/File separator Ljava/lang/String;
L70:    invokevirtual Method java/lang/StringBuffer append (Ljava/lang/String;)Ljava/lang/StringBuffer;
L73:    ldc_w "LocalLow"
L76:    invokevirtual Method java/lang/StringBuffer append (Ljava/lang/String;)Ljava/lang/StringBuffer;
L79:    pop
L80:    goto L99
L83:    athrow
L84:    aload_2
L85:    dup
L86:    getstatic Field java/io/File separator Ljava/lang/String;
L89:    invokevirtual Method java/lang/StringBuffer append (Ljava/lang/String;)Ljava/lang/StringBuffer;
L92:    ldc_w "Application Data"
L95:    invokevirtual Method java/lang/StringBuffer append (Ljava/lang/String;)Ljava/lang/StringBuffer;
L98:    pop
L99:    getstatic Field java/io/File separator Ljava/lang/String;
L102:   invokevirtual Method java/lang/StringBuffer append (Ljava/lang/String;)Ljava/lang/StringBuffer;
L105:   ldc_w "Sun"
L108:   invokevirtual Method java/lang/StringBuffer append (Ljava/lang/String;)Ljava/lang/StringBuffer;
L111:   getstatic Field java/io/File separator Ljava/lang/String;
L114:   invokevirtual Method java/lang/StringBuffer append (Ljava/lang/String;)Ljava/lang/StringBuffer;
L117:   ldc_w "Java"
L120:   invokevirtual Method java/lang/StringBuffer append (Ljava/lang/String;)Ljava/lang/StringBuffer;
L123:   getstatic Field java/io/File separator Ljava/lang/String;
L126:   invokevirtual Method java/lang/StringBuffer append (Ljava/lang/String;)Ljava/lang/StringBuffer;
L129:   ldc_w "Deployment"
L132:   invokevirtual Method java/lang/StringBuffer append (Ljava/lang/String;)Ljava/lang/StringBuffer;
L135:   pop
L136:   aload_2
L137:   goto L220
L140:   athrow
L141:   aload_1
L142:   ldc_w "mac"
L145:   invokevirtual Method java/lang/String startsWith (Ljava/lang/String;)Z
L148:   aload_2
L149:   swap
L150:   ifeq L194
L153:   getstatic Field java/io/File separator Ljava/lang/String;
L156:   invokevirtual Method java/lang/StringBuffer append (Ljava/lang/String;)Ljava/lang/StringBuffer;
L159:   ldc_w "Library"
L162:   invokevirtual Method java/lang/StringBuffer append (Ljava/lang/String;)Ljava/lang/StringBuffer;
L165:   getstatic Field java/io/File separator Ljava/lang/String;
L168:   invokevirtual Method java/lang/StringBuffer append (Ljava/lang/String;)Ljava/lang/StringBuffer;
L171:   ldc_w "Caches"
L174:   invokevirtual Method java/lang/StringBuffer append (Ljava/lang/String;)Ljava/lang/StringBuffer;
L177:   getstatic Field java/io/File separator Ljava/lang/String;
L180:   invokevirtual Method java/lang/StringBuffer append (Ljava/lang/String;)Ljava/lang/StringBuffer;
L183:   ldc_w "Java"
L186:   invokevirtual Method java/lang/StringBuffer append (Ljava/lang/String;)Ljava/lang/StringBuffer;
L189:   pop
L190:   aload_2
L191:   goto L220
L194:   getstatic Field java/io/File separator Ljava/lang/String;
L197:   invokevirtual Method java/lang/StringBuffer append (Ljava/lang/String;)Ljava/lang/StringBuffer;
L200:   ldc_w ".java"
L203:   invokevirtual Method java/lang/StringBuffer append (Ljava/lang/String;)Ljava/lang/StringBuffer;
L206:   getstatic Field java/io/File separator Ljava/lang/String;
L209:   invokevirtual Method java/lang/StringBuffer append (Ljava/lang/String;)Ljava/lang/StringBuffer;
L212:   ldc_w "deployment"
L215:   invokevirtual Method java/lang/StringBuffer append (Ljava/lang/String;)Ljava/lang/StringBuffer;
L218:   pop
L219:   aload_2
L220:   invokevirtual Method java/lang/StringBuffer toString ()Ljava/lang/String;
L223:   areturn
L224:   
        .attribute StackMap b'\x00\x07\x00\x53\x00\x00\x00\x01\x07\x00\x73\x00\x54\x00\x03\x07\x00\x02\x07\x00\x89\x07\x00\xA4\x00\x00\x00\x63\x00\x03\x07\x00\x02\x07\x00\x89\x07\x00\xA4\x00\x01\x07\x00\xA4\x00\x8C\x00\x00\x00\x01\x07\x00\x73\x00\x8D\x00\x03\x07\x00\x02\x07\x00\x89\x07\x00\xA4\x00\x00\x00\xC2\x00\x03\x07\x00\x02\x07\x00\x89\x07\x00\xA4\x00\x01\x07\x00\xA4\x00\xDC\x00\x03\x07\x00\x02\x07\x00\x89\x07\x00\xA4\x00\x01\x07\x00\xA4'
    .end code
.end method

.method public <init> : ()V
    .code stack 10 locals 1
L0:     aconst_null
L1:     aload_0
L2:     dup_x1
L3:     iconst_0
L4:     iconst_1
L5:     aload_0
L6:     dup_x1
L7:     iconst_0
L8:     aload_0
L9:     invokespecial Method java/applet/Applet <init> ()V
L12:    iconst_1
L13:    dup
L14:    pop2
L15:    putfield Field QA char Z
L18:    iconst_1
L19:    dup
L20:    pop2
L21:    putfield Field QA null Z
L24:    iconst_1
L25:    dup
L26:    pop2
L27:    putfield Field QA try Z
L30:    putfield Field QA goto Ljavax/swing/JProgressBar;
L33:    return
L34:    
    .end code
.end method

.method private short : ()V
    .code stack 5 locals 2
L0:     new java/lang/StringBuffer
L3:     dup
L4:     invokespecial Method java/lang/StringBuffer <init> ()V
L7:     dup
L8:     astore_1
L9:     ldc_w "user.home"
L12:    invokestatic Method java/lang/System getProperty (Ljava/lang/String;)Ljava/lang/String;
L15:    invokevirtual Method java/lang/StringBuffer append (Ljava/lang/String;)Ljava/lang/StringBuffer;
L18:    getstatic Field java/io/File separator Ljava/lang/String;
L21:    invokevirtual Method java/lang/StringBuffer append (Ljava/lang/String;)Ljava/lang/StringBuffer;
L24:    ldc_w ".jnlp-applet"
L27:    invokevirtual Method java/lang/StringBuffer append (Ljava/lang/String;)Ljava/lang/StringBuffer;
L30:    getstatic Field java/io/File separator Ljava/lang/String;
L33:    invokevirtual Method java/lang/StringBuffer append (Ljava/lang/String;)Ljava/lang/StringBuffer;
L36:    ldc_w "cache"
L39:    invokevirtual Method java/lang/StringBuffer append (Ljava/lang/String;)Ljava/lang/StringBuffer;
L42:    new java/io/File
L45:    dup
L46:    aload_1
L47:    invokevirtual Method java/lang/StringBuffer toString ()Ljava/lang/String;
L50:    invokespecial Method java/io/File <init> (Ljava/lang/String;)V
L53:    astore_1
L54:    pop
L55:    getstatic Field QA short Z
L58:    ifeq L87
L61:    getstatic Field java/lang/System err Ljava/io/PrintStream;
L64:    new java/lang/StringBuffer
L67:    dup
L68:    ldc_w "cacheBaseDir = "
L71:    invokespecial Method java/lang/StringBuffer <init> (Ljava/lang/String;)V
L74:    aload_1
L75:    invokevirtual Method java/io/File getAbsolutePath ()Ljava/lang/String;
L78:    invokevirtual Method java/lang/StringBuffer append (Ljava/lang/String;)Ljava/lang/StringBuffer;
L81:    invokevirtual Method java/lang/StringBuffer toString ()Ljava/lang/String;
L84:    invokevirtual Method java/io/PrintStream println (Ljava/lang/String;)V
L87:    new java/io/File
L90:    dup
L91:    aload_1
L92:    aload_0
L93:    invokespecial Method QA new ()Ljava/lang/String;
L96:    invokespecial Method java/io/File <init> (Ljava/io/File;Ljava/lang/String;)V
L99:    putstatic Field QA catch Ljava/io/File;
L102:   getstatic Field QA short Z
L105:   ifeq L136
L108:   getstatic Field java/lang/System err Ljava/io/PrintStream;
L111:   new java/lang/StringBuffer
L114:   dup
L115:   ldc_w "cacheDir = "
L118:   invokespecial Method java/lang/StringBuffer <init> (Ljava/lang/String;)V
L121:   getstatic Field QA catch Ljava/io/File;
L124:   invokevirtual Method java/io/File getAbsolutePath ()Ljava/lang/String;
L127:   invokevirtual Method java/lang/StringBuffer append (Ljava/lang/String;)Ljava/lang/StringBuffer;
L130:   invokevirtual Method java/lang/StringBuffer toString ()Ljava/lang/String;
L133:   invokevirtual Method java/io/PrintStream println (Ljava/lang/String;)V
L136:   getstatic Field QA catch Ljava/io/File;
L139:   invokevirtual Method java/io/File isDirectory ()Z
L142:   ifne L181
L145:   getstatic Field QA catch Ljava/io/File;
L148:   invokevirtual Method java/io/File mkdirs ()Z
L151:   ifne L181
L154:   new java/io/IOException
L157:   dup
L158:   new java/lang/StringBuffer
L161:   dup
L162:   ldc_w "Cannot create directory "
L165:   invokespecial Method java/lang/StringBuffer <init> (Ljava/lang/String;)V
L168:   getstatic Field QA catch Ljava/io/File;
L171:   invokevirtual Method java/lang/StringBuffer append (Ljava/lang/Object;)Ljava/lang/StringBuffer;
L174:   invokevirtual Method java/lang/StringBuffer toString ()Ljava/lang/String;
L177:   invokespecial Method java/io/IOException <init> (Ljava/lang/String;)V
L180:   athrow
L181:   return
L182:   
        .attribute StackMap b'\x00\x03\x00\x57\x00\x02\x07\x00\x02\x07\x00\x99\x00\x00\x00\x88\x00\x02\x07\x00\x02\x07\x00\x99\x00\x00\x00\xB5\x00\x02\x07\x00\x02\x07\x00\x99\x00\x00'
    .end code
    .exceptions java/io/IOException
.end method

.method private break : (Ljava/util/jar/JarFile;Ljava/util/jar/JarEntry;[B)Z
    .code stack 3 locals 6
L0:     aload_1
L1:     aload_2
L2:     invokevirtual Method java/util/jar/JarFile getInputStream (Ljava/util/zip/ZipEntry;)Ljava/io/InputStream;
L5:     astore_1
L6:     aload_2
L7:     invokevirtual Method java/util/jar/JarEntry getSize ()J
L10:    pop2
L11:    aload_1
L12:    aload_3
L13:    invokevirtual Method java/io/InputStream read ([B)I
L16:    ifgt L11
L19:    aload_1
L20:    invokevirtual Method java/io/InputStream close ()V
L23:    getstatic Field QA class Ljava/lang/Class;
L26:    dup
L27:    ifnonnull L57
L30:    pop
        .catch java/lang/ClassNotFoundException from L31 to L37 using L45
L31:    ldc_w "QA"
L34:    invokestatic Method java/lang/Class forName (Ljava/lang/String;)Ljava/lang/Class;
L37:    dup
L38:    putstatic Field QA class Ljava/lang/Class;
L41:    goto L57
L44:    athrow
L45:    new java/lang/NoClassDefFoundError
L48:    dup_x1
L49:    swap
L50:    invokevirtual Method java/lang/Throwable getMessage ()Ljava/lang/String;
L53:    invokespecial Method java/lang/NoClassDefFoundError <init> (Ljava/lang/String;)V
L56:    athrow
L57:    invokevirtual Method java/lang/Class getProtectionDomain ()Ljava/security/ProtectionDomain;
L60:    invokevirtual Method java/security/ProtectionDomain getCodeSource ()Ljava/security/CodeSource;
L63:    invokevirtual Method java/security/CodeSource getCertificates ()[Ljava/security/cert/Certificate;
L66:    dup
L67:    astore_1
L68:    ifnull L76
L71:    aload_1
L72:    arraylength
L73:    ifne L87
L76:    new java/io/IOException
L79:    dup
L80:    ldc_w "Cannot find certificates for JNLPAppletLauncher class"
L83:    invokespecial Method java/io/IOException <init> (Ljava/lang/String;)V
L86:    athrow
L87:    aload_2
L88:    invokevirtual Method java/util/jar/JarEntry getCertificates ()[Ljava/security/cert/Certificate;
L91:    dup
L92:    astore_2
L93:    ifnull L101
L96:    aload_2
L97:    arraylength
L98:    ifne L107
L101:   iconst_0
L102:   iconst_1
L103:   dup
L104:   pop2
L105:   ireturn
L106:   athrow
L107:   iconst_0
L108:   iconst_1
L109:   dup
L110:   pop2
L111:   istore_3
L112:   iconst_0
L113:   iconst_1
L114:   dup
L115:   pop2
L116:   dup
L117:   istore 4
L119:   goto L167
L122:   iconst_0
L123:   iconst_1
L124:   dup
L125:   pop2
L126:   dup
L127:   istore 5
L129:   goto L157
L132:   aload_2
L133:   iload 5
L135:   aaload
L136:   aload_1
L137:   iload 4
L139:   aaload
L140:   invokevirtual Method java/security/cert/Certificate equals (Ljava/lang/Object;)Z
L143:   ifeq L152
L146:   iinc 3 1
L149:   goto L162
L152:   iinc 5 1
L155:   iload 5
L157:   aload_2
L158:   arraylength
L159:   if_icmplt L132
L162:   iinc 4 1
L165:   iload 4
L167:   aload_1
L168:   arraylength
L169:   if_icmplt L122
L172:   iload_3
L173:   aload_1
L174:   arraylength
L175:   if_icmpne L183
L178:   iconst_1
L179:   dup
L180:   dup
L181:   pop2
L182:   ireturn
L183:   iconst_0
L184:   iconst_1
L185:   dup
L186:   pop2
L187:   ireturn
L188:   
        .attribute StackMap b'\x00\x10\x00\x0B\x00\x04\x07\x00\x02\x07\x00\x7C\x07\x01\x2D\x07\x02\x7C\x00\x00\x00\x2C\x00\x00\x00\x01\x07\x00\x73\x00\x2D\x00\x04\x07\x00\x02\x07\x00\x7C\x07\x01\x2D\x07\x02\x7C\x00\x01\x07\x03\xCE\x00\x39\x00\x04\x07\x00\x02\x07\x00\x7C\x07\x01\x2D\x07\x02\x7C\x00\x01\x07\x03\xD6\x00\x4C\x00\x04\x07\x00\x02\x07\x03\xF2\x07\x01\x2D\x07\x02\x7C\x00\x00\x00\x57\x00\x04\x07\x00\x02\x07\x03\xF2\x07\x01\x2D\x07\x02\x7C\x00\x00\x00\x65\x00\x04\x07\x00\x02\x07\x03\xF2\x07\x03\xF2\x07\x02\x7C\x00\x00\x00\x6A\x00\x00\x00\x01\x07\x00\x73\x00\x6B\x00\x04\x07\x00\x02\x07\x03\xF2\x07\x03\xF2\x07\x02\x7C\x00\x00\x00\x7A\x00\x05\x07\x00\x02\x07\x03\xF2\x07\x03\xF2\x01\x01\x00\x00\x00\x84\x00\x06\x07\x00\x02\x07\x03\xF2\x07\x03\xF2\x01\x01\x01\x00\x00\x00\x98\x00\x06\x07\x00\x02\x07\x03\xF2\x07\x03\xF2\x01\x01\x01\x00\x00\x00\x9D\x00\x06\x07\x00\x02\x07\x03\xF2\x07\x03\xF2\x01\x01\x01\x00\x01\x01\x00\xA2\x00\x06\x07\x00\x02\x07\x03\xF2\x07\x03\xF2\x01\x01\x01\x00\x00\x00\xA7\x00\x05\x07\x00\x02\x07\x03\xF2\x07\x03\xF2\x01\x01\x00\x01\x01\x00\xB7\x00\x05\x07\x00\x02\x07\x03\xF2\x07\x03\xF2\x01\x01\x00\x00'
    .end code
    .exceptions java/io/IOException
.end method

.method private const : ()V
    .code stack 8 locals 2
        .catch java/lang/ClassNotFoundException from L0 to L33 using L38
        .catch java/lang/Exception from L0 to L33 using L72
L0:     aload_0
L1:     dup
L2:     getfield Field QA extends Ljava/lang/String;
L5:     invokestatic Method java/lang/Class forName (Ljava/lang/String;)Ljava/lang/Class;
L8:     invokevirtual Method java/lang/Class newInstance ()Ljava/lang/Object;
L11:    checkcast java/applet/Applet
L14:    putfield Field QA for Ljava/applet/Applet;
L17:    aload_0
L18:    getfield Field QA for Ljava/applet/Applet;
L21:    new cA
L24:    dup
L25:    aload_0
L26:    aconst_null
L27:    invokespecial Method cA <init> (LQA;LcA;)V
L30:    invokevirtual Method java/applet/Applet setStub (Ljava/applet/AppletStub;)V
L33:    aload_0
L34:    goto L106
L37:    athrow
L38:    astore_1
L39:    aload_1
L40:    invokevirtual Method java/lang/ClassNotFoundException printStackTrace ()V
L43:    new java/lang/StringBuffer
L46:    aload_0
L47:    dup
L48:    pop2
L49:    dup
L50:    ldc_w "Class not found: "
L53:    invokespecial Method java/lang/StringBuffer <init> (Ljava/lang/String;)V
L56:    aload_0
L57:    dup_x1
L58:    getfield Field QA extends Ljava/lang/String;
L61:    invokevirtual Method java/lang/StringBuffer append (Ljava/lang/String;)Ljava/lang/StringBuffer;
L64:    invokevirtual Method java/lang/StringBuffer toString ()Ljava/lang/String;
L67:    invokespecial Method QA break (Ljava/lang/String;)V
L70:    return
L71:    athrow
L72:    astore_1
L73:    aload_1
L74:    invokevirtual Method java/lang/Exception printStackTrace ()V
L77:    new java/lang/StringBuffer
L80:    aload_0
L81:    dup
L82:    pop2
L83:    dup
L84:    ldc_w "Unable to start "
L87:    invokespecial Method java/lang/StringBuffer <init> (Ljava/lang/String;)V
L90:    aload_0
L91:    dup_x1
L92:    getfield Field QA byte Ljava/lang/String;
L95:    invokevirtual Method java/lang/StringBuffer append (Ljava/lang/String;)Ljava/lang/StringBuffer;
L98:    invokevirtual Method java/lang/StringBuffer toString ()Ljava/lang/String;
L101:   invokespecial Method QA break (Ljava/lang/String;)V
L104:   return
L105:   athrow
L106:   aload_0
L107:   getfield Field QA for Ljava/applet/Applet;
L110:   ldc_w "Center"
L113:   invokevirtual Method QA add (Ljava/awt/Component;Ljava/lang/Object;)V
        .catch java/lang/Exception from L116 to L152 using L153
L116:   aload_0
L117:   iconst_1
L118:   aload_0
L119:   dup
L120:   dup2
L121:   dup2
L122:   getfield Field QA for Ljava/applet/Applet;
L125:   invokevirtual Method java/applet/Applet init ()V
L128:   getfield Field QA true Ljavax/swing/JPanel;
L131:   invokevirtual Method QA remove (Ljava/awt/Component;)V
L134:   invokevirtual Method QA validate ()V
L137:   invokespecial Method QA goto ()V
L140:   getfield Field QA for Ljava/applet/Applet;
L143:   invokevirtual Method java/applet/Applet start ()V
L146:   iconst_1
L147:   dup
L148:   pop2
L149:   putfield Field QA try Z
L152:   return
L153:   astore_1
L154:   aload_1
L155:   invokevirtual Method java/lang/Exception printStackTrace ()V
L158:   return
L159:   
        .attribute StackMap b'\x00\x07\x00\x25\x00\x00\x00\x01\x07\x00\x73\x00\x26\x00\x01\x07\x00\x02\x00\x01\x07\x03\xCE\x00\x47\x00\x00\x00\x01\x07\x00\x73\x00\x48\x00\x01\x07\x00\x02\x00\x01\x07\x02\x9A\x00\x69\x00\x00\x00\x01\x07\x00\x73\x00\x6A\x00\x01\x07\x00\x02\x00\x01\x07\x00\x02\x00\x99\x00\x01\x07\x00\x02\x00\x01\x07\x02\x9A'
    .end code
.end method

.method private static break : (Ljava/io/File;)V
    .code stack 4 locals 3
L0:     getstatic Field QA short Z
L3:     ifeq L35
L6:     getstatic Field java/lang/System err Ljava/io/PrintStream;
L9:     new java/lang/StringBuffer
L12:    dup
L13:    ldc_w "removeAll("
L16:    invokespecial Method java/lang/StringBuffer <init> (Ljava/lang/String;)V
L19:    aload_0
L20:    invokevirtual Method java/lang/StringBuffer append (Ljava/lang/Object;)Ljava/lang/StringBuffer;
L23:    ldc_w ")"
L26:    invokevirtual Method java/lang/StringBuffer append (Ljava/lang/String;)Ljava/lang/StringBuffer;
L29:    invokevirtual Method java/lang/StringBuffer toString ()Ljava/lang/String;
L32:    invokevirtual Method java/io/PrintStream println (Ljava/lang/String;)V
L35:    aload_0
L36:    invokevirtual Method java/io/File isDirectory ()Z
L39:    ifeq L76
L42:    aload_0
L43:    invokevirtual Method java/io/File listFiles ()[Ljava/io/File;
L46:    dup
L47:    astore_1
L48:    ifnull L76
L51:    iconst_0
L52:    iconst_1
L53:    dup
L54:    pop2
L55:    dup
L56:    istore_2
L57:    goto L71
L60:    athrow
L61:    aload_1
L62:    iload_2
L63:    iinc 2 1
L66:    aaload
L67:    invokestatic Method QA break (Ljava/io/File;)V
L70:    iload_2
L71:    aload_1
L72:    arraylength
L73:    if_icmplt L61
L76:    aload_0
L77:    invokevirtual Method java/io/File delete ()Z
L80:    pop
L81:    return
L82:    
        .attribute StackMap b'\x00\x05\x00\x23\x00\x01\x07\x00\x99\x00\x00\x00\x3C\x00\x00\x00\x01\x07\x00\x73\x00\x3D\x00\x03\x07\x00\x99\x07\x04\x1A\x01\x00\x00\x00\x47\x00\x03\x07\x00\x99\x07\x04\x1A\x01\x00\x01\x01\x00\x4C\x00\x01\x07\x00\x99\x00\x00'
    .end code
.end method

.method private break : (Ljava/io/File;J)V
    .code stack 5 locals 4
L0:     new java/io/BufferedWriter
L3:     dup
L4:     new java/io/FileWriter
L7:     dup
L8:     aload_1
L9:     invokespecial Method java/io/FileWriter <init> (Ljava/io/File;)V
L12:    invokespecial Method java/io/BufferedWriter <init> (Ljava/io/Writer;)V
L15:    astore_1
        .catch [0] from L16 to L47 using L48
        .catch java/lang/Exception from L0 to L47 using L61
L16:    aload_1
L17:    dup
L18:    new java/lang/StringBuffer
L21:    dup
L22:    invokespecial Method java/lang/StringBuffer <init> ()V
L25:    lload_2
L26:    invokevirtual Method java/lang/StringBuffer append (J)Ljava/lang/StringBuffer;
L29:    ldc_w "\u000A"
L32:    invokevirtual Method java/lang/StringBuffer append (Ljava/lang/String;)Ljava/lang/StringBuffer;
L35:    invokevirtual Method java/lang/StringBuffer toString ()Ljava/lang/String;
L38:    invokevirtual Method java/io/BufferedWriter write (Ljava/lang/String;)V
L41:    invokevirtual Method java/io/BufferedWriter flush ()V
L44:    goto L55
L47:    athrow
        .catch java/lang/Exception from L48 to L59 using L61
L48:    astore_2
L49:    aload_2
L50:    aload_1
L51:    invokevirtual Method java/io/BufferedWriter close ()V
L54:    athrow
L55:    aload_1
L56:    invokevirtual Method java/io/BufferedWriter close ()V
L59:    return
L60:    athrow
L61:    pop
L62:    aload_0
L63:    ldc_w "Error writing time stamp for native libraries"
L66:    invokespecial Method QA break (Ljava/lang/String;)V
L69:    return
L70:    
        .attribute StackMap b'\x00\x05\x00\x2F\x00\x00\x00\x01\x07\x00\x73\x00\x30\x00\x03\x07\x00\x02\x07\x04\x1C\x04\x00\x01\x07\x00\x73\x00\x37\x00\x03\x07\x00\x02\x07\x04\x1C\x04\x00\x00\x00\x3C\x00\x00\x00\x01\x07\x00\x73\x00\x3D\x00\x02\x07\x00\x02\x07\x00\x7A\x00\x01\x07\x02\x9A'
    .end code
.end method

.method public static else : (LQA;Ljava/net/URL;)V
    .code stack 2 locals 2
L0:     aload_0
L1:     aload_1
L2:     invokespecial Method QA else (Ljava/net/URL;)V
L5:     return
L6:     
    .end code
    .synthetic
.end method

.method public static break : (LQA;Ljava/net/URL;)V
    .code stack 2 locals 2
L0:     aload_0
L1:     aload_1
L2:     invokespecial Method QA break (Ljava/net/URL;)V
L5:     return
L6:     
    .end code
    .synthetic
.end method

.method private else : ()V
    .code stack 5 locals 7
L0:     getstatic Field QA class Ljava/lang/Class;
L3:     dup
L4:     ifnonnull L34
L7:     pop
        .catch java/lang/ClassNotFoundException from L8 to L14 using L22
L8:     ldc_w "QA"
L11:    invokestatic Method java/lang/Class forName (Ljava/lang/String;)Ljava/lang/Class;
L14:    dup
L15:    putstatic Field QA class Ljava/lang/Class;
L18:    goto L34
L21:    athrow
L22:    new java/lang/NoClassDefFoundError
L25:    dup_x1
L26:    swap
L27:    invokevirtual Method java/lang/Throwable getMessage ()Ljava/lang/String;
L30:    invokespecial Method java/lang/NoClassDefFoundError <init> (Ljava/lang/String;)V
L33:    athrow
L34:    dup
L35:    astore_1
L36:    monitorenter
L37:    getstatic Field QA long Z
L40:    ifeq L116
L43:    ldc_w "archive"
L46:    aload_0
L47:    dup_x1
L48:    invokevirtual Method QA getCodeBase ()Ljava/net/URL;
L51:    putstatic Field QA void Ljava/net/URL;
L54:    invokevirtual Method QA getParameter (Ljava/lang/String;)Ljava/lang/String;
L57:    putstatic Field QA int Ljava/lang/String;
L60:    getstatic Field QA int Ljava/lang/String;
L63:    ifnull L75
L66:    getstatic Field QA int Ljava/lang/String;
L69:    invokevirtual Method java/lang/String length ()I
L72:    ifne L86
L75:    new java/lang/IllegalArgumentException
L78:    dup
L79:    ldc_w "Missing archive parameter"
L82:    invokespecial Method java/lang/IllegalArgumentException <init> (Ljava/lang/String;)V
L85:    athrow
L86:    new java/util/HashSet
L89:    dup
L90:    invokespecial Method java/util/HashSet <init> ()V
L93:    putstatic Field QA do Ljava/util/Set;
L96:    new java/util/HashSet
L99:    dup
L100:   invokespecial Method java/util/HashSet <init> ()V
L103:   putstatic Field QA "static" Ljava/util/Set;
L106:   new java/util/HashMap
L109:   dup
L110:   invokespecial Method java/util/HashMap <init> ()V
L113:   putstatic Field QA "final" Ljava/util/Map;
L116:   iconst_m1
L117:   iconst_1
L118:   dup
L119:   pop2
L120:   istore_2
L121:   aload_0
L122:   ldc_w "jnlpNumExtensions"
L125:   invokevirtual Method QA getParameter (Ljava/lang/String;)Ljava/lang/String;
L128:   dup
L129:   astore_3
L130:   ifnull L159
        .catch java/lang/NumberFormatException from L133 to L138 using L143
        .catch [0] from L37 to L142 using L424
L133:   aload_3
L134:   invokestatic Method java/lang/Integer parseInt (Ljava/lang/String;)I
L137:   istore_2
L138:   iload_2
L139:   goto L145
L142:   athrow
        .catch [0] from L143 to L423 using L424
L143:   pop
L144:   iload_2
L145:   ifgt L159
L148:   new java/lang/IllegalArgumentException
L151:   dup
L152:   ldc_w "Missing or invalid jnlpNumExtensions parameter"
L155:   invokespecial Method java/lang/IllegalArgumentException <init> (Ljava/lang/String;)V
L158:   athrow
L159:   new java/util/ArrayList
L162:   dup
L163:   invokespecial Method java/util/ArrayList <init> ()V
L166:   astore_3
L167:   iconst_1
L168:   dup
L169:   dup
L170:   pop2
L171:   dup
L172:   istore 4
L174:   goto L274
L177:   new java/lang/StringBuffer
L180:   dup
L181:   ldc_w "jnlpExtension"
L184:   invokespecial Method java/lang/StringBuffer <init> (Ljava/lang/String;)V
L187:   iload 4
L189:   invokevirtual Method java/lang/StringBuffer append (I)Ljava/lang/StringBuffer;
L192:   invokevirtual Method java/lang/StringBuffer toString ()Ljava/lang/String;
L195:   astore 5
L197:   aload_0
L198:   aload 5
L200:   invokevirtual Method QA getParameter (Ljava/lang/String;)Ljava/lang/String;
L203:   dup
L204:   astore 6
L206:   ifnull L217
L209:   aload 6
L211:   invokevirtual Method java/lang/String length ()I
L214:   ifne L249
L217:   new java/lang/IllegalArgumentException
L220:   dup
L221:   new java/lang/StringBuffer
L224:   dup
L225:   ldc_w "Missing "
L228:   invokespecial Method java/lang/StringBuffer <init> (Ljava/lang/String;)V
L231:   aload 5
L233:   invokevirtual Method java/lang/StringBuffer append (Ljava/lang/String;)Ljava/lang/StringBuffer;
L236:   ldc_w " parameter"
L239:   invokevirtual Method java/lang/StringBuffer append (Ljava/lang/String;)Ljava/lang/StringBuffer;
L242:   invokevirtual Method java/lang/StringBuffer toString ()Ljava/lang/String;
L245:   invokespecial Method java/lang/IllegalArgumentException <init> (Ljava/lang/String;)V
L248:   athrow
L249:   new java/net/URL
L252:   dup
L253:   aload 6
L255:   invokespecial Method java/net/URL <init> (Ljava/lang/String;)V
L258:   astore 6
L260:   iinc 4 1
L263:   aload_3
L264:   aload 6
L266:   invokeinterface InterfaceMethod java/util/List add (Ljava/lang/Object;)Z 2
L271:   pop
L272:   iload 4
L274:   iload_2
L275:   if_icmple L177
L278:   getstatic Field QA long Z
L281:   ifeq L391
L284:   aload_0
L285:   aload_3
L286:   dup
L287:   putstatic Field QA case Ljava/util/List;
L290:   invokespecial Method QA break (Ljava/util/List;)V
L293:   getstatic Field QA short Z
L296:   ifeq L317
L299:   getstatic Field java/lang/System err Ljava/io/PrintStream;
L302:   invokevirtual Method java/io/PrintStream println ()V
L305:   getstatic Field java/lang/System err Ljava/io/PrintStream;
L308:   ldc_w "All files successfully parsed"
L311:   invokevirtual Method java/io/PrintStream println (Ljava/lang/String;)V
L314:   invokestatic Method QA do ()V
L317:   getstatic Field QA "static" Ljava/util/Set;
L320:   invokeinterface InterfaceMethod java/util/Set size ()I 1
L325:   ifle L378
L328:   aload_0
L329:   dup
L330:   invokespecial Method QA short ()V
L333:   invokespecial Method QA try ()V
L336:   getstatic Field QA "static" Ljava/util/Set;
L339:   invokeinterface InterfaceMethod java/util/Set iterator ()Ljava/util/Iterator; 1
L344:   dup
L345:   astore 4
L347:   goto L370
L350:   aload 4
L352:   invokeinterface InterfaceMethod java/util/Iterator next ()Ljava/lang/Object; 1
L357:   checkcast java/net/URL
L360:   astore 5
L362:   aload 4
L364:   aload_0
L365:   aload 5
L367:   invokespecial Method QA const (Ljava/net/URL;)V
L370:   invokeinterface InterfaceMethod java/util/Iterator hasNext ()Z 1
L375:   ifne L350
L378:   ldc_w "sun.jnlp.applet.launcher"
L381:   ldc_w "true"
L384:   invokestatic Method java/lang/System setProperty (Ljava/lang/String;Ljava/lang/String;)Ljava/lang/String;
L387:   pop
L388:   goto L414
L391:   getstatic Field QA case Ljava/util/List;
L394:   aload_3
L395:   invokeinterface InterfaceMethod java/util/List equals (Ljava/lang/Object;)Z 2
L400:   ifne L414
L403:   new java/lang/IllegalArgumentException
L406:   dup
L407:   ldc_w "jnlpExtension parameters do not match previously loaded applet"
L410:   invokespecial Method java/lang/IllegalArgumentException <init> (Ljava/lang/String;)V
L413:   athrow
L414:   iconst_0
L415:   iconst_1
L416:   dup
L417:   pop2
L418:   putstatic Field QA long Z
L421:   aload_1
L422:   monitorexit
L423:   return
        .catch [0] from L424 to L426 using L424
L424:   aload_1
L425:   monitorexit
L426:   athrow
L427:   athrow
L428:   
        .attribute StackMap b'\x00\x16\x00\x15\x00\x00\x00\x01\x07\x00\x73\x00\x16\x00\x01\x07\x00\x02\x00\x01\x07\x03\xCE\x00\x22\x00\x01\x07\x00\x02\x00\x01\x07\x03\xD6\x00\x4B\x00\x02\x07\x00\x02\x07\x03\xD6\x00\x00\x00\x56\x00\x02\x07\x00\x02\x07\x03\xD6\x00\x00\x00\x74\x00\x02\x07\x00\x02\x07\x03\xD6\x00\x00\x00\x8E\x00\x00\x00\x01\x07\x00\x73\x00\x8F\x00\x04\x07\x00\x02\x07\x03\xD6\x01\x07\x00\x89\x00\x01\x07\x04\x34\x00\x91\x00\x04\x07\x00\x02\x07\x03\xD6\x01\x07\x00\x89\x00\x01\x01\x00\x9F\x00\x04\x07\x00\x02\x07\x03\xD6\x01\x07\x00\x89\x00\x00\x00\xB1\x00\x05\x07\x00\x02\x07\x03\xD6\x01\x07\x04\x47\x01\x00\x00\x00\xD9\x00\x07\x07\x00\x02\x07\x03\xD6\x01\x07\x04\x47\x01\x07\x00\x89\x07\x00\x89\x00\x00\x00\xF9\x00\x07\x07\x00\x02\x07\x03\xD6\x01\x07\x04\x47\x01\x07\x00\x89\x07\x00\x89\x00\x00\x01\x12\x00\x05\x07\x00\x02\x07\x03\xD6\x01\x07\x04\x47\x01\x00\x01\x01\x01\x3D\x00\x05\x07\x00\x02\x07\x03\xD6\x01\x07\x04\x47\x01\x00\x00\x01\x5E\x00\x05\x07\x00\x02\x07\x03\xD6\x01\x07\x04\x47\x07\x00\xF0\x00\x00\x01\x72\x00\x05\x07\x00\x02\x07\x03\xD6\x01\x07\x04\x47\x07\x00\xF0\x00\x01\x07\x00\xF0\x01\x7A\x00\x04\x07\x00\x02\x07\x03\xD6\x01\x07\x04\x47\x00\x00\x01\x87\x00\x05\x07\x00\x02\x07\x03\xD6\x01\x07\x04\x47\x01\x00\x00\x01\x9E\x00\x04\x07\x00\x02\x07\x03\xD6\x01\x07\x04\x47\x00\x00\x01\xA8\x00\x02\x07\x00\x02\x07\x03\xD6\x00\x01\x07\x00\x73\x01\xAB\x00\x00\x00\x01\x07\x00\x73'
    .end code
    .exceptions java/io/IOException
.end method

.method public static break : (Ljava/lang/String;Li;)V
    .code stack 4 locals 3
L0:     getstatic Field QA short Z
L3:     ifeq L18
L6:     getstatic Field java/lang/System err Ljava/io/PrintStream;
L9:     ldc_w "-----------"
L12:    invokevirtual Method java/io/PrintStream println (Ljava/lang/String;)V
L15:    invokestatic Method java/lang/Thread dumpStack ()V
L18:    getstatic Field QA "enum" Z
L21:    ifeq L53
L24:    getstatic Field java/lang/System err Ljava/io/PrintStream;
L27:    new java/lang/StringBuffer
L30:    dup
L31:    ldc_w "JNLPAppletLauncher.loadLibrary(\""
L34:    invokespecial Method java/lang/StringBuffer <init> (Ljava/lang/String;)V
L37:    aload_0
L38:    invokevirtual Method java/lang/StringBuffer append (Ljava/lang/String;)Ljava/lang/StringBuffer;
L41:    ldc_w "\")"
L44:    invokevirtual Method java/lang/StringBuffer append (Ljava/lang/String;)Ljava/lang/StringBuffer;
L47:    invokevirtual Method java/lang/StringBuffer toString ()Ljava/lang/String;
L50:    invokevirtual Method java/io/PrintStream println (Ljava/lang/String;)V
L53:    getstatic Field QA "final" Ljava/util/Map;
L56:    aload_0
L57:    invokeinterface InterfaceMethod java/util/Map get (Ljava/lang/Object;)Ljava/lang/Object; 2
L62:    checkcast java/lang/String
L65:    dup
L66:    astore_2
L67:    ifnonnull L79
L70:    new java/lang/UnsatisfiedLinkError
L73:    dup
L74:    aload_0
L75:    invokespecial Method java/lang/UnsatisfiedLinkError <init> (Ljava/lang/String;)V
L78:    athrow
L79:    getstatic Field QA "enum" Z
L82:    ifeq L108
L85:    getstatic Field java/lang/System err Ljava/io/PrintStream;
L88:    new java/lang/StringBuffer
L91:    dup
L92:    ldc_w "    loading: "
L95:    invokespecial Method java/lang/StringBuffer <init> (Ljava/lang/String;)V
L98:    aload_2
L99:    invokevirtual Method java/lang/StringBuffer append (Ljava/lang/String;)Ljava/lang/StringBuffer;
L102:   invokevirtual Method java/lang/StringBuffer toString ()Ljava/lang/String;
L105:   invokevirtual Method java/io/PrintStream println (Ljava/lang/String;)V
L108:   aload_1
L109:   ifnull L121
L112:   aload_1
L113:   aload_2
L114:   invokeinterface InterfaceMethod i break (Ljava/lang/String;)V 2
L119:   return
L120:   athrow
L121:   aload_2
L122:   invokestatic Method java/lang/System load (Ljava/lang/String;)V
L125:   return
L126:   
        .attribute StackMap b'\x00\x06\x00\x12\x00\x02\x07\x00\x89\x07\x00\x18\x00\x00\x00\x35\x00\x02\x07\x00\x89\x07\x00\x18\x00\x00\x00\x4F\x00\x03\x07\x00\x89\x07\x00\x18\x07\x00\x89\x00\x00\x00\x6C\x00\x03\x07\x00\x89\x07\x00\x18\x07\x00\x89\x00\x00\x00\x78\x00\x00\x00\x01\x07\x00\x73\x00\x79\x00\x03\x07\x00\x89\x07\x00\x18\x07\x00\x89\x00\x00'
    .end code
.end method

.method public static break : ()V
    .code stack 0 locals 0
L0:     invokestatic Method QA catch ()V
L3:     return
L4:     
    .end code
    .synthetic
.end method

.method public stop : ()V
    .code stack 1 locals 1
L0:     aload_0
L1:     getfield Field QA for Ljava/applet/Applet;
L4:     ifnull L14
L7:     aload_0
L8:     getfield Field QA for Ljava/applet/Applet;
L11:    invokevirtual Method java/applet/Applet stop ()V
L14:    return
L15:    
        .attribute StackMap b'\x00\x01\x00\x0E\x00\x01\x07\x00\x02\x00\x00'
    .end code
.end method
.innerclasses
    DA QA [0] private static
    EA [0] [0]
    SA [0] [0]
    TA [0] [0]
    UA [0] [0]
    WA [0] [0]
    ZA [0] [0]
    bA [0] [0]
    cA QA [0] private
    i QA [0] public static interface abstract
    java/util/Map$Entry java/util/Map Entry public static interface abstract
    mA [0] [0]
    uA [0] [0]
.end innerclasses
.const [_534] = String [_533]
.const [_533] = Utf8 "For best robustness of OpenGL applets on Windows,\u000Awe recommend disabling Java2D's use of DirectDraw.\u000AThis setting will affect all applets, but is unlikely\u000Ato slow other applets down significantly. May we update\u000Ayour deployment.properties to turn off DirectDraw for\u000Aapplets? You can change this back later if necessary\u000Ausing the Java Control Panel, Java tab, under Java\u000AApplet Runtime Settings."
.end class
