.version 49 0
.class public super abstract qd
.super java/lang/Object
.field public package I
.field public finally B
.field public static final "transient" I = 2147483647
.field public while D
.field public instanceof I
.field public "protected" Ljava/lang/String;
.field public static final import I = -1
.field public "native" Z
.field public throws Z
.field public "static" Ljava/util/LinkedHashMap;
.field public continue Ljava/util/Set;
.field public extends Z
.field private float LM;
.field public "final" Z
.field private catch Z
.field public false Ljava/util/Set;
.field public class Ljava/util/Set;
.field public if Ljava/lang/String;
.field public true Z
.field public for Ljava/util/Set;
.field private case F
.field public byte Z
.field public "super" I
.field public int J
.field public short Z
.field public goto Z
.field public static final break F = 1e-1f
.field public long Ljava/util/LinkedHashMap;
.field public void Leb;
.field private try F
.field public const D
.field public new Ljava/util/LinkedHashMap;
.field public null LQB;
.field public this Ljava/lang/String;
.field public char I
.field public else LNE;
.field public "enum" Ljava/util/Map;
.field public do Z

.method public break : (LG;)V
    .code stack 5 locals 6
L0:     invokestatic Method mc values ()[Lmc;
L3:     dup
L4:     astore_2
L5:     arraylength
L6:     istore_3
L7:     iconst_0
L8:     iconst_1
L9:     dup
L10:    pop2
L11:    dup
L12:    istore 4
L14:    iload_3
L15:    if_icmpge L57
L18:    aload_2
L19:    iload 4
L21:    aaload
L22:    astore 5
L24:    aload_0
L25:    getfield Field qd continue Ljava/util/Set;
L28:    new Dc
L31:    dup
L32:    aload_1
L33:    aload 5
L35:    invokespecial Method Dc <init> (Ljava/lang/Object;Ljava/lang/Object;)V
L38:    invokeinterface InterfaceMethod java/util/Set remove (Ljava/lang/Object;)Z 2
L43:    ifeq L48
L46:    return
L47:    athrow
L48:    iinc 4 1
L51:    iload 4
L53:    goto L14
L56:    athrow
L57:    return
L58:    
        .attribute StackMap b'\x00\x05\x00\x0E\x00\x05\x07\x00\x02\x07\x00\x4F\x07\x00\x51\x01\x01\x00\x01\x01\x00\x2F\x00\x00\x00\x01\x07\x00\x61\x00\x30\x00\x06\x07\x00\x02\x07\x00\x4F\x07\x00\x51\x01\x01\x07\x00\x49\x00\x00\x00\x38\x00\x00\x00\x01\x07\x00\x61\x00\x39\x00\x05\x07\x00\x02\x07\x00\x4F\x07\x00\x51\x01\x01\x00\x00'
    .end code
.end method

.method public "enum" : ()[B
    .code stack 7 locals 1
L0:     aload_0
L1:     getfield Field qd else LNE;
L4:     ifnonnull L66
L7:     new java/lang/RuntimeException
L10:    dup
L11:    new java/lang/StringBuilder
L14:    dup
L15:    invokespecial Method java/lang/StringBuilder <init> ()V
L18:    iconst_0
L19:    ldc "Wawiwo? "
L21:    invokevirtual Method java/lang/StringBuilder insert (ILjava/lang/String;)Ljava/lang/StringBuilder;
L24:    aload_0
L25:    getfield Field qd throws Z
L28:    invokevirtual Method java/lang/StringBuilder append (Z)Ljava/lang/StringBuilder;
L31:    ldc " "
L33:    invokevirtual Method java/lang/StringBuilder append (Ljava/lang/String;)Ljava/lang/StringBuilder;
L36:    aload_0
L37:    getfield Field qd null LQB;
L40:    invokevirtual Method java/lang/StringBuilder append (Ljava/lang/Object;)Ljava/lang/StringBuilder;
L43:    ldc " "
L45:    invokevirtual Method java/lang/StringBuilder append (Ljava/lang/String;)Ljava/lang/StringBuilder;
L48:    invokestatic Method OC else ()D
L51:    aload_0
L52:    getfield Field qd while D
L55:    dsub
L56:    invokevirtual Method java/lang/StringBuilder append (D)Ljava/lang/StringBuilder;
L59:    invokevirtual Method java/lang/StringBuilder toString ()Ljava/lang/String;
L62:    invokespecial Method java/lang/RuntimeException <init> (Ljava/lang/String;)V
L65:    athrow
L66:    aload_0
L67:    getfield Field qd else LNE;
L70:    invokevirtual Method NE else ()[B
L73:    areturn
L74:    
        .attribute StackMap b'\x00\x01\x00\x42\x00\x01\x07\x00\x02\x00\x00'
    .end code
.end method

.method public abstract long : ()D
.end method

.method public abstract else : (LD;)V
.end method

.method public class : ()V
    .code stack 7 locals 1
L0:     aload_0
L1:     dup
L2:     dup2
L3:     invokestatic Method OC else ()D
L6:     putfield Field qd while D
L9:     getstatic Field QB else LQB;
L12:    putfield Field qd null LQB;
L15:    invokevirtual Method qd char ()V
L18:    new xC
L21:    aload_0
L22:    dup
L23:    pop2
L24:    dup
L25:    aload_0
L26:    dup
L27:    getfield Field qd null LQB;
L30:    swap
L31:    getfield Field qd "enum" Ljava/util/Map;
L34:    aload_0
L35:    dup
L36:    getfield Field qd long Ljava/util/LinkedHashMap;
L39:    swap
L40:    getfield Field qd "static" Ljava/util/LinkedHashMap;
L43:    invokespecial Method xC <init> (LQB;Ljava/util/Map;Ljava/util/Map;Ljava/util/Map;)V
L46:    invokevirtual Method qd else (LD;)V
L49:    return
L50:    
    .end code
.end method

.method public if : ()V
    .code stack 2 locals 2
L0:     aload_0
L1:     dup
L2:     invokespecial Method qd this ()Ljava/util/EnumMap;
L5:     astore_1
L6:     getfield Field qd null LQB;
L9:     getstatic Field QB char LQB;
L12:    if_acmpeq L31
L15:    aload_0
L16:    getfield Field qd new Ljava/util/LinkedHashMap;
L19:    invokevirtual Method java/util/LinkedHashMap size ()I
L22:    ifne L31
L25:    aload_0
L26:    invokevirtual Method qd else ()V
L29:    return
L30:    athrow
L31:    getstatic Field HC do [I
L34:    aload_0
L35:    getfield Field qd null LQB;
L38:    invokevirtual Method QB ordinal ()I
L41:    iaload
L42:    tableswitch 1
            L72
            L83
            L89
            L98
            default : L103
L72:    aload_0
L73:    iconst_0
L74:    ifne L95
L77:    aload_1
L78:    invokespecial Method qd float (Ljava/util/Map;)V
L81:    return
L82:    athrow
L83:    aload_0
L84:    aload_1
L85:    invokespecial Method qd break (Ljava/util/Map;)V
L88:    return
L89:    aload_0
L90:    aload_1
L91:    invokespecial Method qd const (Ljava/util/Map;)V
L94:    return
L95:    goto L73
L98:    aload_0
L99:    aload_1
L100:   invokespecial Method qd else (Ljava/util/Map;)V
L103:   return
L104:   
        .attribute StackMap b'\x00\x0A\x00\x1E\x00\x00\x00\x01\x07\x00\x61\x00\x1F\x00\x02\x07\x00\x02\x07\x00\xB9\x00\x00\x00\x48\x00\x02\x07\x00\x02\x07\x00\xB9\x00\x00\x00\x49\x00\x02\x07\x00\x02\x07\x00\xB9\x00\x01\x07\x00\x02\x00\x52\x00\x00\x00\x01\x07\x00\x61\x00\x53\x00\x02\x07\x00\x02\x07\x00\xB9\x00\x00\x00\x59\x00\x02\x07\x00\x02\x07\x00\xB9\x00\x00\x00\x5F\x00\x02\x07\x00\x02\x07\x00\xB9\x00\x01\x07\x00\x02\x00\x62\x00\x02\x07\x00\x02\x07\x00\xB9\x00\x00\x00\x67\x00\x02\x07\x00\x02\x07\x00\xB9\x00\x00'
    .end code
.end method

.method public char : ()V
    .code stack 6 locals 5
L0:     aload_0
L1:     getfield Field qd void Leb;
L4:     aload_0
L5:     dup_x1
L6:     invokevirtual Method eb const (Lqd;)V
L9:     new java/util/HashSet
L12:    dup
L13:    invokespecial Method java/util/HashSet <init> ()V
L16:    astore_1
L17:    getfield Field qd "enum" Ljava/util/Map;
L20:    invokeinterface InterfaceMethod java/util/Map values ()Ljava/util/Collection; 1
L25:    invokeinterface InterfaceMethod java/util/Collection iterator ()Ljava/util/Iterator; 1
L30:    dup
L31:    astore_2
L32:    invokeinterface InterfaceMethod java/util/Iterator hasNext ()Z 1
L37:    ifeq L63
L40:    aload_2
L41:    invokeinterface InterfaceMethod java/util/Iterator next ()Ljava/lang/Object; 1
L46:    checkcast java/lang/Integer
L49:    astore_3
L50:    aload_2
L51:    aload_1
L52:    aload_3
L53:    invokeinterface InterfaceMethod java/util/Set add (Ljava/lang/Object;)Z 2
L58:    pop
L59:    goto L32
L62:    athrow
L63:    aload_1
L64:    invokeinterface InterfaceMethod java/util/Set size ()I 1
L69:    iconst_1
L70:    dup
L71:    dup
L72:    pop2
L73:    if_icmple L340
L76:    new java/util/HashSet
L79:    dup
L80:    invokespecial Method java/util/HashSet <init> ()V
L83:    astore_2
L84:    aload_0
L85:    getfield Field qd "enum" Ljava/util/Map;
L88:    invokeinterface InterfaceMethod java/util/Map entrySet ()Ljava/util/Set; 1
L93:    invokeinterface InterfaceMethod java/util/Set iterator ()Ljava/util/Iterator; 1
L98:    astore_3
L99:    aload_3
L100:   invokeinterface InterfaceMethod java/util/Iterator hasNext ()Z 1
L105:   ifeq L271
L108:   aload_3
L109:   invokeinterface InterfaceMethod java/util/Iterator next ()Ljava/lang/Object; 1
L114:   checkcast java/util/Map$Entry
L117:   astore_1
L118:   aload_0
L119:   getfield Field qd long Ljava/util/LinkedHashMap;
L122:   aload_1
L123:   invokeinterface InterfaceMethod java/util/Map$Entry getKey ()Ljava/lang/Object; 1
L128:   checkcast Rg
L131:   getfield Field Rg false Led;
L134:   invokevirtual Method java/util/LinkedHashMap get (Ljava/lang/Object;)Ljava/lang/Object;
L137:   checkcast java/lang/Integer
L140:   dup
L141:   astore 4
L143:   ifnonnull L155
L146:   iconst_0
L147:   iconst_1
L148:   dup
L149:   pop2
L150:   invokestatic Method java/lang/Integer valueOf (I)Ljava/lang/Integer;
L153:   astore 4
L155:   aload_0
L156:   getfield Field qd long Ljava/util/LinkedHashMap;
L159:   aload_1
L160:   invokeinterface InterfaceMethod java/util/Map$Entry getKey ()Ljava/lang/Object; 1
L165:   checkcast Rg
L168:   getfield Field Rg false Led;
L171:   aload 4
L173:   invokevirtual Method java/lang/Integer intValue ()I
L176:   aload_0
L177:   getfield Field qd "enum" Ljava/util/Map;
L180:   invokeinterface InterfaceMethod java/util/Map size ()I 1
L185:   iadd
L186:   aload_1
L187:   invokeinterface InterfaceMethod java/util/Map$Entry getValue ()Ljava/lang/Object; 1
L192:   checkcast java/lang/Integer
L195:   invokevirtual Method java/lang/Integer intValue ()I
L198:   isub
L199:   invokestatic Method java/lang/Integer valueOf (I)Ljava/lang/Integer;
L202:   invokevirtual Method java/util/LinkedHashMap put (Ljava/lang/Object;Ljava/lang/Object;)Ljava/lang/Object;
L205:   pop
L206:   aload_1
L207:   invokeinterface InterfaceMethod java/util/Map$Entry getValue ()Ljava/lang/Object; 1
L212:   checkcast java/lang/Integer
L215:   invokevirtual Method java/lang/Integer intValue ()I
L218:   iconst_1
L219:   dup
L220:   dup
L221:   pop2
L222:   if_icmpne L99
L225:   aload_0
L226:   getfield Field qd "native" Z
L229:   ifeq L99
L232:   aload_0
L233:   getfield Field qd class Ljava/util/Set;
L236:   invokeinterface InterfaceMethod java/util/Set size ()I 1
L241:   iconst_1
L242:   dup
L243:   dup
L244:   pop2
L245:   if_icmple L99
L248:   aload_2
L249:   aload_1
L250:   invokeinterface InterfaceMethod java/util/Map$Entry getKey ()Ljava/lang/Object; 1
L255:   checkcast Rg
L258:   getfield Field Rg short LsE;
L261:   invokeinterface InterfaceMethod java/util/Set add (Ljava/lang/Object;)Z 2
L266:   pop
L267:   goto L99
L270:   athrow
L271:   aload_0
L272:   getfield Field qd "native" Z
L275:   ifeq L340
L278:   aload_2
L279:   invokeinterface InterfaceMethod java/util/Set iterator ()Ljava/util/Iterator; 1
L284:   dup
L285:   astore_3
L286:   invokeinterface InterfaceMethod java/util/Iterator hasNext ()Z 1
L291:   ifeq L340
L294:   aload_3
L295:   invokeinterface InterfaceMethod java/util/Iterator next ()Ljava/lang/Object; 1
L300:   checkcast sE
L303:   astore_1
L304:   aload_0
L305:   dup
L306:   getfield Field qd "static" Ljava/util/LinkedHashMap;
L309:   swap
L310:   getfield Field qd "static" Ljava/util/LinkedHashMap;
L313:   aload_1
L314:   dup_x1
L315:   invokevirtual Method java/util/LinkedHashMap get (Ljava/lang/Object;)Ljava/lang/Object;
L318:   checkcast java/lang/Integer
L321:   invokevirtual Method java/lang/Integer intValue ()I
L324:   iconst_1
L325:   dup
L326:   dup
L327:   pop2
L328:   iadd
L329:   invokestatic Method java/lang/Integer valueOf (I)Ljava/lang/Integer;
L332:   invokevirtual Method java/util/LinkedHashMap put (Ljava/lang/Object;Ljava/lang/Object;)Ljava/lang/Object;
L335:   pop
L336:   aload_3
L337:   goto L286
L340:   aload_0
L341:   getfield Field qd "native" Z
L344:   ifeq L407
L347:   invokestatic Method sE values ()[LsE;
L350:   dup
L351:   astore_2
L352:   arraylength
L353:   istore_3
L354:   iconst_0
L355:   iconst_1
L356:   dup
L357:   pop2
L358:   dup
L359:   istore_1
L360:   iload_3
L361:   if_icmpge L407
L364:   aload_2
L365:   iload_1
L366:   aaload
L367:   astore 4
L369:   aload_0
L370:   getfield Field qd class Ljava/util/Set;
L373:   aload 4
L375:   invokeinterface InterfaceMethod java/util/Set contains (Ljava/lang/Object;)Z 2
L380:   ifne L400
L383:   aload_0
L384:   getfield Field qd "static" Ljava/util/LinkedHashMap;
L387:   aload 4
L389:   iconst_0
L390:   iconst_1
L391:   dup
L392:   pop2
L393:   invokestatic Method java/lang/Integer valueOf (I)Ljava/lang/Integer;
L396:   invokevirtual Method java/util/LinkedHashMap put (Ljava/lang/Object;Ljava/lang/Object;)Ljava/lang/Object;
L399:   pop
L400:   iinc 1 1
L403:   iload_1
L404:   goto L360
L407:   aload_0
L408:   invokevirtual Method qd try ()V
L411:   return
L412:   
        .attribute StackMap b'\x00\x0C\x00\x20\x00\x03\x07\x00\x02\x07\x00\xD1\x07\x00\xDD\x00\x01\x07\x00\xDD\x00\x3E\x00\x00\x00\x01\x07\x00\x61\x00\x3F\x00\x03\x07\x00\x02\x07\x00\xD1\x07\x00\xDD\x00\x00\x00\x63\x00\x04\x07\x00\x02\x07\x00\x04\x07\x00\xD1\x07\x00\xDD\x00\x00\x00\x9B\x00\x05\x07\x00\x02\x07\x00\x0C\x07\x00\xD1\x07\x00\xDD\x07\x00\xE7\x00\x00\x01\x0E\x00\x00\x00\x01\x07\x00\x61\x01\x0F\x00\x04\x07\x00\x02\x07\x00\x04\x07\x00\xD1\x07\x00\xDD\x00\x00\x01\x1E\x00\x04\x07\x00\x02\x07\x00\x04\x07\x00\xD1\x07\x00\xDD\x00\x01\x07\x00\xDD\x01\x54\x00\x03\x07\x00\x02\x07\x00\x04\x07\x00\x04\x00\x00\x01\x68\x00\x04\x07\x00\x02\x01\x07\x01\x19\x01\x00\x01\x01\x01\x90\x00\x05\x07\x00\x02\x01\x07\x01\x19\x01\x07\x01\x14\x00\x00\x01\x97\x00\x03\x07\x00\x02\x00\x07\x00\x04\x00\x00'
    .end code
.end method

.method public new : ()I
    .code stack 3 locals 4
L0:     iconst_0
L1:     iconst_1
L2:     dup
L3:     pop2
L4:     istore_1
L5:     aload_0
L6:     getfield Field qd new Ljava/util/LinkedHashMap;
L9:     invokevirtual Method java/util/LinkedHashMap values ()Ljava/util/Collection;
L12:    invokeinterface InterfaceMethod java/util/Collection iterator ()Ljava/util/Iterator; 1
L17:    astore_2
L18:    aload_2
L19:    invokeinterface InterfaceMethod java/util/Iterator hasNext ()Z 1
L24:    ifeq L115
L27:    aload_2
L28:    invokeinterface InterfaceMethod java/util/Iterator next ()Ljava/lang/Object; 1
L33:    checkcast Rg
L36:    dup
L37:    astore_3
L38:    instanceof oF
L41:    ifne L18
L44:    getstatic Field HC "enum" [I
L47:    aload_3
L48:    getfield Field Rg case LqE;
L51:    invokevirtual Method qE ordinal ()I
L54:    iaload
L55:    tableswitch 1
            L100
            L100
            L100
            L100
            L111
            L111
            L111
            L111
            default : L111
L100:   iinc 1 1
L103:   iconst_0
L104:   ifne L103
L107:   goto L18
L110:   athrow
L111:   goto L18
L114:   athrow
L115:   iload_1
L116:   ireturn
L117:   
        .attribute StackMap b'\x00\x07\x00\x12\x00\x03\x07\x00\x02\x01\x07\x00\xDD\x00\x00\x00\x64\x00\x04\x07\x00\x02\x01\x07\x00\xDD\x07\x00\xF5\x00\x00\x00\x67\x00\x04\x07\x00\x02\x01\x07\x00\xDD\x07\x00\xF5\x00\x00\x00\x6E\x00\x00\x00\x01\x07\x00\x61\x00\x6F\x00\x04\x07\x00\x02\x01\x07\x00\xDD\x07\x00\xF5\x00\x00\x00\x72\x00\x00\x00\x01\x07\x00\x61\x00\x73\x00\x03\x07\x00\x02\x01\x07\x00\xDD\x00\x00'
    .end code
.end method

.method public static synthetic break : (Lqd;)F
    .code stack 1 locals 1
L0:     aload_0
L1:     getfield Field qd case F
L4:     freturn
L5:     
    .end code
.end method

.method public <init> : (Leb;ZZZIIIZZZLjava/lang/String;Ljava/lang/String;I)V
    .code stack 45 locals 14
L0:     iload 5
L2:     iload 13
L4:     aload_0
L5:     dup_x1
L6:     aload 12
L8:     aload 11
L10:    aload_0
L11:    dup_x1
L12:    iload 10
L14:    iload 9
L16:    aload_0
L17:    dup_x1
L18:    iload 8
L20:    iload 7
L22:    aload_0
L23:    dup_x1
L24:    iload 4
L26:    iload_3
L27:    aload_0
L28:    dup
L29:    dup_x2
L30:    iload_2
L31:    aload_1
L32:    aload_0
L33:    dup
L34:    dup_x2
L35:    iconst_0
L36:    aload_0
L37:    dup_x1
L38:    iconst_1
L39:    dup
L40:    aload_0
L41:    dup_x1
L42:    iconst_m1
L43:    aload_0
L44:    dup
L45:    dup2
L46:    dup2
L47:    dup2
L48:    invokespecial Method java/lang/Object <init> ()V
L51:    new java/util/HashSet
L54:    aload_0
L55:    dup_x2
L56:    dup
L57:    pop2
L58:    dup
L59:    invokespecial Method java/util/HashSet <init> ()V
L62:    putfield Field qd class Ljava/util/Set;
L65:    new java/util/LinkedHashMap
L68:    aload_0
L69:    dup
L70:    pop2
L71:    dup
L72:    invokespecial Method java/util/LinkedHashMap <init> ()V
L75:    putfield Field qd "enum" Ljava/util/Map;
L78:    new java/util/LinkedHashMap
L81:    aload_0
L82:    dup
L83:    pop2
L84:    dup
L85:    invokespecial Method java/util/LinkedHashMap <init> ()V
L88:    putfield Field qd long Ljava/util/LinkedHashMap;
L91:    new java/util/LinkedHashMap
L94:    aload_0
L95:    dup
L96:    pop2
L97:    dup
L98:    invokespecial Method java/util/LinkedHashMap <init> ()V
L101:   putfield Field qd "static" Ljava/util/LinkedHashMap;
L104:   new java/util/HashSet
L107:   aload_0
L108:   dup
L109:   pop2
L110:   dup
L111:   invokespecial Method java/util/HashSet <init> ()V
L114:   putfield Field qd for Ljava/util/Set;
L117:   new java/util/HashSet
L120:   aload_0
L121:   dup
L122:   pop2
L123:   dup
L124:   invokespecial Method java/util/HashSet <init> ()V
L127:   putfield Field qd false Ljava/util/Set;
L130:   new java/util/concurrent/CopyOnWriteArraySet
L133:   aload_0
L134:   dup
L135:   pop2
L136:   dup
L137:   invokespecial Method java/util/concurrent/CopyOnWriteArraySet <init> ()V
L140:   putfield Field qd continue Ljava/util/Set;
L143:   new java/util/LinkedHashMap
L146:   aload_0
L147:   dup
L148:   pop2
L149:   dup
L150:   invokespecial Method java/util/LinkedHashMap <init> ()V
L153:   putfield Field qd new Ljava/util/LinkedHashMap;
L156:   iconst_1
L157:   dup
L158:   pop2
L159:   putfield Field qd "super" I
L162:   iconst_1
L163:   dup
L164:   pop2
L165:   putfield Field qd do Z
L168:   iconst_1
L169:   dup
L170:   pop2
L171:   putfield Field qd byte Z
L174:   iconst_1
L175:   dup
L176:   pop2
L177:   putfield Field qd extends Z
L180:   new iC
L183:   aload_0
L184:   dup
L185:   pop2
L186:   dup
L187:   aload_0
L188:   invokespecial Method iC <init> (Lqd;)V
L191:   putfield Field qd float LM;
L194:   getstatic Field QB char LQB;
L197:   putfield Field qd null LQB;
L200:   putfield Field qd void Leb;
L203:   putfield Field qd short Z
L206:   invokestatic Method OC else ()D
L209:   putfield Field qd while D
L212:   putfield Field qd "native" Z
L215:   putfield Field qd true Z
L218:   putfield Field qd "super" I
L221:   putfield Field qd catch Z
L224:   putfield Field qd "final" Z
L227:   putfield Field qd throws Z
L230:   putfield Field qd "protected" Ljava/lang/String;
L233:   putfield Field qd if Ljava/lang/String;
L236:   putfield Field qd package I
L239:   iconst_m1
L240:   iconst_1
L241:   dup
L242:   pop2
L243:   if_icmpne L257
L246:   aload_0
L247:   dup
L248:   ldc 2147483647
L250:   putfield Field qd instanceof I
L253:   goto L264
L256:   athrow
L257:   aload_0
L258:   dup
L259:   iload 5
L261:   putfield Field qd instanceof I
L264:   iload 6
L266:   putfield Field qd char I
L269:   invokestatic Method sE values ()[LsE;
L272:   dup
L273:   astore_1
L274:   arraylength
L275:   istore_2
L276:   iconst_0
L277:   iconst_1
L278:   dup
L279:   pop2
L280:   dup
L281:   istore_3
L282:   iload_2
L283:   if_icmpge L316
L286:   aload_1
L287:   iload_3
L288:   iinc 3 1
L291:   aaload
L292:   astore 4
L294:   aload_0
L295:   getfield Field qd "static" Ljava/util/LinkedHashMap;
L298:   aload 4
L300:   iconst_0
L301:   iconst_1
L302:   dup
L303:   pop2
L304:   invokestatic Method java/lang/Integer valueOf (I)Ljava/lang/Integer;
L307:   invokevirtual Method java/util/LinkedHashMap put (Ljava/lang/Object;Ljava/lang/Object;)Ljava/lang/Object;
L310:   pop
L311:   iload_3
L312:   goto L282
L315:   athrow
L316:   return
L317:   
        .attribute StackMap b'\x00\x06\x01\x00\x00\x00\x00\x01\x07\x00\x61\x01\x01\x00\x0E\x07\x00\x02\x07\x00\xCC\x01\x01\x01\x01\x01\x01\x01\x01\x01\x07\x01\x54\x07\x01\x54\x01\x00\x00\x01\x08\x00\x0E\x07\x00\x02\x07\x00\xCC\x01\x01\x01\x01\x01\x01\x01\x01\x01\x07\x01\x54\x07\x01\x54\x01\x00\x01\x07\x00\x02\x01\x1A\x00\x0E\x07\x00\x02\x07\x01\x19\x01\x01\x00\x01\x01\x01\x01\x01\x01\x07\x01\x54\x07\x01\x54\x01\x00\x01\x01\x01\x3B\x00\x00\x00\x01\x07\x00\x61\x01\x3C\x00\x0E\x07\x00\x02\x07\x01\x19\x01\x01\x00\x01\x01\x01\x01\x01\x01\x07\x01\x54\x07\x01\x54\x01\x00\x00'
    .end code
.end method

.method private float : (Ljava/util/Map;)V
    .code stack 6 locals 4
L0:     iconst_0
L1:     iconst_1
L2:     dup
L3:     pop2
L4:     istore_1
L5:     aload_0
L6:     getfield Field qd new Ljava/util/LinkedHashMap;
L9:     invokevirtual Method java/util/LinkedHashMap values ()Ljava/util/Collection;
L12:    invokeinterface InterfaceMethod java/util/Collection iterator ()Ljava/util/Iterator; 1
L17:    astore_2
L18:    aload_2
L19:    invokeinterface InterfaceMethod java/util/Iterator hasNext ()Z 1
L24:    ifeq L144
L27:    aload_2
L28:    invokeinterface InterfaceMethod java/util/Iterator next ()Ljava/lang/Object; 1
L33:    checkcast Rg
L36:    astore_3
L37:    getstatic Field HC "enum" [I
L40:    aload_3
L41:    getfield Field Rg case LqE;
L44:    invokevirtual Method qE ordinal ()I
L47:    iaload
L48:    tableswitch 1
            L96
            L96
            L96
            L96
            L109
            L141
            L141
            L141
            default : L141
L96:    iconst_1
L97:    iconst_0
L98:    ifne L97
L101:   dup
L102:   dup
L103:   pop2
L104:   istore_1
L105:   goto L18
L108:   athrow
L109:   aload_0
L110:   getfield Field qd do Z
L113:   ifne L132
L116:   aload_0
L117:   getfield Field qd false Ljava/util/Set;
L120:   aload_3
L121:   getfield Field Rg false Led;
L124:   invokeinterface InterfaceMethod java/util/Set contains (Ljava/lang/Object;)Z 2
L129:   ifeq L18
L132:   iconst_1
L133:   dup
L134:   dup
L135:   pop2
L136:   istore_1
L137:   goto L18
L140:   athrow
L141:   goto L18
L144:   aload_0
L145:   getfield Field qd byte Z
L148:   ifne L158
L151:   aload_0
L152:   getfield Field qd extends Z
L155:   ifeq L180
L158:   iload_1
L159:   ifeq L180
L162:   new java/util/Random
L165:   aload_0
L166:   dup_x1
L167:   dup
L168:   pop2
L169:   dup
L170:   invokespecial Method java/util/Random <init> ()V
L173:   invokevirtual Method java/util/Random nextLong ()J
L176:   invokevirtual Method qd break (J)V
L179:   return
L180:   aload_0
L181:   getfield Field qd new Ljava/util/LinkedHashMap;
L184:   invokevirtual Method java/util/LinkedHashMap isEmpty ()Z
L187:   ifne L198
L190:   aload_0
L191:   invokestatic Method OC else ()D
L194:   putfield Field qd while D
L197:   return
L198:   aload_0
L199:   getfield Field qd catch Z
L202:   ifeq L235
L205:   invokestatic Method OC else ()D
L208:   aload_0
L209:   getfield Field qd while D
L212:   ldc2_w 5e0
L215:   dadd
L216:   dcmpl
L217:   ifle L235
L220:   aload_0
L221:   getfield Field qd new Ljava/util/LinkedHashMap;
L224:   invokevirtual Method java/util/LinkedHashMap isEmpty ()Z
L227:   ifeq L235
L230:   aload_0
L231:   invokevirtual Method qd for ()V
L234:   return
L235:   return
L236:   
        .attribute StackMap b'\x00\x0D\x00\x12\x00\x03\x07\x00\x02\x01\x07\x00\xDD\x00\x00\x00\x60\x00\x04\x07\x00\x02\x01\x07\x00\xDD\x07\x00\xF5\x00\x00\x00\x61\x00\x04\x07\x00\x02\x01\x07\x00\xDD\x07\x00\xF5\x00\x01\x01\x00\x6C\x00\x00\x00\x01\x07\x00\x61\x00\x6D\x00\x04\x07\x00\x02\x01\x07\x00\xDD\x07\x00\xF5\x00\x00\x00\x84\x00\x04\x07\x00\x02\x01\x07\x00\xDD\x07\x00\xF5\x00\x00\x00\x8C\x00\x00\x00\x01\x07\x00\x61\x00\x8D\x00\x04\x07\x00\x02\x01\x07\x00\xDD\x07\x00\xF5\x00\x00\x00\x90\x00\x03\x07\x00\x02\x01\x07\x00\xDD\x00\x00\x00\x9E\x00\x03\x07\x00\x02\x01\x07\x00\xDD\x00\x00\x00\xB4\x00\x03\x07\x00\x02\x01\x07\x00\xDD\x00\x00\x00\xC6\x00\x03\x07\x00\x02\x01\x07\x00\xDD\x00\x00\x00\xEB\x00\x03\x07\x00\x02\x01\x07\x00\xDD\x00\x00'
    .end code
.end method

.method public try : ()V
    .code stack 5 locals 1
L0:     aload_0
L1:     dup
L2:     getfield Field qd long Ljava/util/LinkedHashMap;
L5:     iconst_0
L6:     iconst_1
L7:     dup
L8:     pop2
L9:     invokestatic Method OC break (Ljava/util/LinkedHashMap;Z)V
L12:    getfield Field qd "static" Ljava/util/LinkedHashMap;
L15:    iconst_0
L16:    iconst_1
L17:    dup
L18:    pop2
L19:    invokestatic Method OC break (Ljava/util/LinkedHashMap;Z)V
L22:    return
L23:    
    .end code
.end method

.method public static synthetic else : (Lqd;F)F
    .code stack 3 locals 2
L0:     aload_0
L1:     dup
L2:     getfield Field qd case F
L5:     fload_1
L6:     fsub
L7:     dup_x1
L8:     putfield Field qd case F
L11:    freturn
L12:    
    .end code
.end method

.method private this : ()Ljava/util/EnumMap;
    .code stack 5 locals 6
L0:     new java/util/EnumMap
L3:     dup
L4:     ldc_w Class qE
L7:     invokespecial Method java/util/EnumMap <init> (Ljava/lang/Class;)V
L10:    astore_1
L11:    invokestatic Method qE values ()[LqE;
L14:    dup
L15:    astore_2
L16:    arraylength
L17:    istore_3
L18:    iconst_0
L19:    iconst_1
L20:    dup
L21:    pop2
L22:    dup
L23:    istore 4
L25:    iload_3
L26:    if_icmpge L61
L29:    aload_2
L30:    iload 4
L32:    iinc 4 1
L35:    aaload
L36:    astore 5
L38:    aload_1
L39:    new java/util/LinkedList
L42:    aload 5
L44:    dup_x1
L45:    dup
L46:    pop2
L47:    dup
L48:    invokespecial Method java/util/LinkedList <init> ()V
L51:    invokevirtual Method java/util/EnumMap put (Ljava/lang/Enum;Ljava/lang/Object;)Ljava/lang/Object;
L54:    pop
L55:    iload 4
L57:    goto L25
L60:    athrow
L61:    aload_0
L62:    getfield Field qd new Ljava/util/LinkedHashMap;
L65:    invokevirtual Method java/util/LinkedHashMap values ()Ljava/util/Collection;
L68:    invokeinterface InterfaceMethod java/util/Collection iterator ()Ljava/util/Iterator; 1
L73:    dup
L74:    astore_2
L75:    invokeinterface InterfaceMethod java/util/Iterator hasNext ()Z 1
L80:    ifeq L116
L83:    aload_2
L84:    invokeinterface InterfaceMethod java/util/Iterator next ()Ljava/lang/Object; 1
L89:    checkcast Rg
L92:    astore_3
L93:    aload_1
L94:    aload_3
L95:    getfield Field Rg case LqE;
L98:    invokevirtual Method java/util/EnumMap get (Ljava/lang/Object;)Ljava/lang/Object;
L101:   checkcast java/util/List
L104:   aload_3
L105:   invokeinterface InterfaceMethod java/util/List add (Ljava/lang/Object;)Z 2
L110:   pop
L111:   aload_2
L112:   goto L75
L115:   athrow
L116:   aload_1
L117:   areturn
L118:   
        .attribute StackMap b'\x00\x06\x00\x19\x00\x05\x07\x00\x02\x07\x00\xB9\x07\x01\x73\x01\x01\x00\x01\x01\x00\x3C\x00\x00\x00\x01\x07\x00\x61\x00\x3D\x00\x05\x07\x00\x02\x07\x00\xB9\x07\x01\x73\x01\x01\x00\x00\x00\x4B\x00\x05\x07\x00\x02\x07\x00\xB9\x07\x00\xDD\x00\x01\x00\x01\x07\x00\xDD\x00\x73\x00\x00\x00\x01\x07\x00\x61\x00\x74\x00\x05\x07\x00\x02\x07\x00\xB9\x07\x00\xDD\x00\x01\x00\x00'
    .end code
.end method

.method public goto : ()V
    .code stack 1 locals 1
L0:     aload_0
L1:     getfield Field qd float LM;
L4:     invokestatic Method ib break (LM;)V
L7:     return
L8:     
    .end code
.end method

.method public do : ()I
    .code stack 3 locals 4
L0:     iconst_0
L1:     iconst_1
L2:     dup
L3:     pop2
L4:     istore_1
L5:     aload_0
L6:     getfield Field qd new Ljava/util/LinkedHashMap;
L9:     invokevirtual Method java/util/LinkedHashMap values ()Ljava/util/Collection;
L12:    invokeinterface InterfaceMethod java/util/Collection iterator ()Ljava/util/Iterator; 1
L17:    astore_2
L18:    aload_2
L19:    invokeinterface InterfaceMethod java/util/Iterator hasNext ()Z 1
L24:    ifeq L61
L27:    aload_2
L28:    invokeinterface InterfaceMethod java/util/Iterator next ()Ljava/lang/Object; 1
L33:    checkcast Rg
L36:    dup
L37:    astore_3
L38:    instanceof oF
L41:    ifne L18
L44:    aload_3
L45:    getfield Field Rg case LqE;
L48:    getstatic Field qE this LqE;
L51:    if_acmpne L18
L54:    iinc 1 1
L57:    goto L18
L60:    athrow
L61:    iload_1
L62:    ireturn
L63:    
        .attribute StackMap b'\x00\x03\x00\x12\x00\x03\x07\x00\x02\x01\x07\x00\xDD\x00\x00\x00\x3C\x00\x00\x00\x01\x07\x00\x61\x00\x3D\x00\x03\x07\x00\x02\x01\x07\x00\xDD\x00\x00'
    .end code
.end method

.method private short : (Ljava/util/Map;)V
    .code stack 6 locals 4
L0:     aload_1
L1:     getstatic Field qE this LqE;
L4:     invokeinterface InterfaceMethod java/util/Map get (Ljava/lang/Object;)Ljava/lang/Object; 2
L9:     checkcast java/util/List
L12:    invokeinterface InterfaceMethod java/util/List iterator ()Ljava/util/Iterator; 1
L17:    dup
L18:    astore_2
L19:    invokeinterface InterfaceMethod java/util/Iterator hasNext ()Z 1
L24:    ifeq L121
L27:    aload_2
L28:    invokeinterface InterfaceMethod java/util/Iterator next ()Ljava/lang/Object; 1
L33:    checkcast Rg
L36:    astore_3
L37:    aload_0
L38:    getfield Field qd "enum" Ljava/util/Map;
L41:    aload_3
L42:    invokeinterface InterfaceMethod java/util/Map containsKey (Ljava/lang/Object;)Z 2
L47:    ifne L102
L50:    aload_0
L51:    getfield Field qd "enum" Ljava/util/Map;
L54:    aload_3
L55:    iconst_0
L56:    iconst_1
L57:    dup
L58:    pop2
L59:    invokestatic Method java/lang/Integer valueOf (I)Ljava/lang/Integer;
L62:    invokeinterface InterfaceMethod java/util/Map put (Ljava/lang/Object;Ljava/lang/Object;)Ljava/lang/Object; 3
L67:    pop
L68:    new Ad
L71:    aload_0
L72:    dup_x1
L73:    dup
L74:    pop2
L75:    dup
L76:    aload_3
L77:    getfield Field Rg false Led;
L80:    aload_0
L81:    getfield Field qd "enum" Ljava/util/Map;
L84:    aload_3
L85:    invokeinterface InterfaceMethod java/util/Map get (Ljava/lang/Object;)Ljava/lang/Object; 2
L90:    checkcast java/lang/Integer
L93:    invokevirtual Method java/lang/Integer intValue ()I
L96:    invokespecial Method Ad <init> (Led;I)V
L99:    invokevirtual Method qd else (LD;)V
L102:   aload_0
L103:   getfield Field qd class Ljava/util/Set;
L106:   aload_3
L107:   getfield Field Rg short LsE;
L110:   invokeinterface InterfaceMethod java/util/Set add (Ljava/lang/Object;)Z 2
L115:   pop
L116:   aload_2
L117:   goto L19
L120:   athrow
L121:   aload_1
L122:   getstatic Field qE const LqE;
L125:   invokeinterface InterfaceMethod java/util/Map get (Ljava/lang/Object;)Ljava/lang/Object; 2
L130:   checkcast java/util/List
L133:   invokeinterface InterfaceMethod java/util/List iterator ()Ljava/util/Iterator; 1
L138:   dup
L139:   astore_2
L140:   invokeinterface InterfaceMethod java/util/Iterator hasNext ()Z 1
L145:   ifeq L242
L148:   aload_2
L149:   invokeinterface InterfaceMethod java/util/Iterator next ()Ljava/lang/Object; 1
L154:   checkcast Rg
L157:   astore_3
L158:   aload_0
L159:   getfield Field qd "enum" Ljava/util/Map;
L162:   aload_3
L163:   invokeinterface InterfaceMethod java/util/Map containsKey (Ljava/lang/Object;)Z 2
L168:   ifne L223
L171:   aload_0
L172:   getfield Field qd "enum" Ljava/util/Map;
L175:   aload_3
L176:   iconst_0
L177:   iconst_1
L178:   dup
L179:   pop2
L180:   invokestatic Method java/lang/Integer valueOf (I)Ljava/lang/Integer;
L183:   invokeinterface InterfaceMethod java/util/Map put (Ljava/lang/Object;Ljava/lang/Object;)Ljava/lang/Object; 3
L188:   pop
L189:   new Ad
L192:   aload_0
L193:   dup_x1
L194:   dup
L195:   pop2
L196:   dup
L197:   aload_3
L198:   getfield Field Rg false Led;
L201:   aload_0
L202:   getfield Field qd "enum" Ljava/util/Map;
L205:   aload_3
L206:   invokeinterface InterfaceMethod java/util/Map get (Ljava/lang/Object;)Ljava/lang/Object; 2
L211:   checkcast java/lang/Integer
L214:   invokevirtual Method java/lang/Integer intValue ()I
L217:   invokespecial Method Ad <init> (Led;I)V
L220:   invokevirtual Method qd else (LD;)V
L223:   aload_0
L224:   getfield Field qd class Ljava/util/Set;
L227:   aload_3
L228:   getfield Field Rg short LsE;
L231:   invokeinterface InterfaceMethod java/util/Set add (Ljava/lang/Object;)Z 2
L236:   pop
L237:   aload_2
L238:   goto L140
L241:   athrow
L242:   aload_0
L243:   getfield Field qd "enum" Ljava/util/Map;
L246:   invokeinterface InterfaceMethod java/util/Map keySet ()Ljava/util/Set; 1
L251:   invokeinterface InterfaceMethod java/util/Set iterator ()Ljava/util/Iterator; 1
L256:   astore_2
L257:   aload_2
L258:   invokeinterface InterfaceMethod java/util/Iterator hasNext ()Z 1
L263:   ifeq L365
L266:   aload_2
L267:   invokeinterface InterfaceMethod java/util/Iterator next ()Ljava/lang/Object; 1
L272:   checkcast Rg
L275:   astore_3
L276:   aload_0
L277:   getfield Field qd "enum" Ljava/util/Map;
L280:   aload_3
L281:   invokeinterface InterfaceMethod java/util/Map get (Ljava/lang/Object;)Ljava/lang/Object; 2
L286:   checkcast java/lang/Integer
L289:   invokevirtual Method java/lang/Integer intValue ()I
L292:   ifne L257
L295:   aload_0
L296:   getfield Field qd new Ljava/util/LinkedHashMap;
L299:   aload_3
L300:   getfield Field Rg false Led;
L303:   invokevirtual Method java/util/LinkedHashMap containsKey (Ljava/lang/Object;)Z
L306:   ifeq L319
L309:   aload_3
L310:   getfield Field Rg case LqE;
L313:   getstatic Field qE null LqE;
L316:   if_acmpne L257
L319:   aload_0
L320:   dup
L321:   getfield Field qd void Leb;
L324:   aload_0
L325:   aload_3
L326:   invokevirtual Method eb break (Lqd;LRg;)V
L329:   new Ad
L332:   aload_0
L333:   dup
L334:   pop2
L335:   dup
L336:   aload_3
L337:   getfield Field Rg false Led;
L340:   aload_0
L341:   getfield Field qd "enum" Ljava/util/Map;
L344:   aload_3
L345:   invokeinterface InterfaceMethod java/util/Map get (Ljava/lang/Object;)Ljava/lang/Object; 2
L350:   checkcast java/lang/Integer
L353:   invokevirtual Method java/lang/Integer intValue ()I
L356:   invokespecial Method Ad <init> (Led;I)V
L359:   invokevirtual Method qd else (LD;)V
L362:   goto L257
L365:   aload_1
L366:   getstatic Field qE new LqE;
L369:   invokeinterface InterfaceMethod java/util/Map get (Ljava/lang/Object;)Ljava/lang/Object; 2
L374:   checkcast java/util/List
L377:   invokeinterface InterfaceMethod java/util/List iterator ()Ljava/util/Iterator; 1
L382:   astore_2
L383:   aload_2
L384:   invokeinterface InterfaceMethod java/util/Iterator hasNext ()Z 1
L389:   ifeq L498
L392:   aload_2
L393:   invokeinterface InterfaceMethod java/util/Iterator next ()Ljava/lang/Object; 1
L398:   checkcast Rg
L401:   astore_3
L402:   aload_0
L403:   getfield Field qd "enum" Ljava/util/Map;
L406:   aload_3
L407:   invokeinterface InterfaceMethod java/util/Map containsKey (Ljava/lang/Object;)Z 2
L412:   ifne L433
L415:   aload_0
L416:   getfield Field qd "enum" Ljava/util/Map;
L419:   aload_3
L420:   iconst_0
L421:   iconst_1
L422:   dup
L423:   pop2
L424:   invokestatic Method java/lang/Integer valueOf (I)Ljava/lang/Integer;
L427:   invokeinterface InterfaceMethod java/util/Map put (Ljava/lang/Object;Ljava/lang/Object;)Ljava/lang/Object; 3
L432:   pop
L433:   aload_0
L434:   getfield Field qd "enum" Ljava/util/Map;
L437:   aload_3
L438:   invokeinterface InterfaceMethod java/util/Map get (Ljava/lang/Object;)Ljava/lang/Object; 2
L443:   checkcast java/lang/Integer
L446:   invokevirtual Method java/lang/Integer intValue ()I
L449:   ifne L383
L452:   aload_0
L453:   getfield Field qd void Leb;
L456:   aload_0
L457:   aload_3
L458:   invokevirtual Method eb break (Lqd;LRg;)V
L461:   new Ad
L464:   aload_0
L465:   dup_x1
L466:   dup
L467:   pop2
L468:   dup
L469:   aload_3
L470:   getfield Field Rg false Led;
L473:   aload_0
L474:   getfield Field qd "enum" Ljava/util/Map;
L477:   aload_3
L478:   invokeinterface InterfaceMethod java/util/Map get (Ljava/lang/Object;)Ljava/lang/Object; 2
L483:   checkcast java/lang/Integer
L486:   invokevirtual Method java/lang/Integer intValue ()I
L489:   invokespecial Method Ad <init> (Led;I)V
L492:   invokevirtual Method qd else (LD;)V
L495:   goto L383
L498:   return
L499:   
        .attribute StackMap b'\x00\x0E\x00\x13\x00\x03\x07\x00\x02\x07\x00\x0E\x07\x00\xDD\x00\x01\x07\x00\xDD\x00\x66\x00\x04\x07\x00\x02\x07\x00\x0E\x07\x00\xDD\x07\x00\xF5\x00\x00\x00\x78\x00\x00\x00\x01\x07\x00\x61\x00\x79\x00\x03\x07\x00\x02\x07\x00\x0E\x07\x00\xDD\x00\x00\x00\x8C\x00\x03\x07\x00\x02\x07\x00\x0E\x07\x00\xDD\x00\x01\x07\x00\xDD\x00\xDF\x00\x04\x07\x00\x02\x07\x00\x0E\x07\x00\xDD\x07\x00\xF5\x00\x00\x00\xF1\x00\x00\x00\x01\x07\x00\x61\x00\xF2\x00\x03\x07\x00\x02\x07\x00\x0E\x07\x00\xDD\x00\x00\x01\x01\x00\x03\x07\x00\x02\x07\x00\x0E\x07\x00\xDD\x00\x00\x01\x3F\x00\x04\x07\x00\x02\x07\x00\x0E\x07\x00\xDD\x07\x00\xF5\x00\x00\x01\x6D\x00\x03\x07\x00\x02\x07\x00\x0E\x07\x00\xDD\x00\x00\x01\x7F\x00\x03\x07\x00\x02\x07\x00\x0E\x07\x00\xDD\x00\x00\x01\xB1\x00\x04\x07\x00\x02\x07\x00\x0E\x07\x00\xDD\x07\x00\xF5\x00\x00\x01\xF2\x00\x03\x07\x00\x02\x07\x00\x0E\x07\x00\xDD\x00\x00'
    .end code
.end method

.method public for : ()V
    .code stack 1 locals 1
L0:     aload_0
L1:     getfield Field qd float LM;
L4:     invokestatic Method ib else (LM;)V
L7:     return
L8:     
    .end code
.end method

.method public break : (LG;Lmc;)V
    .code stack 5 locals 3
L0:     aload_0
L1:     getfield Field qd continue Ljava/util/Set;
L4:     new Dc
L7:     dup
L8:     aload_1
L9:     aload_2
L10:    invokespecial Method Dc <init> (Ljava/lang/Object;Ljava/lang/Object;)V
L13:    invokeinterface InterfaceMethod java/util/Set add (Ljava/lang/Object;)Z 2
L18:    ifne L32
L21:    new java/lang/RuntimeException
L24:    dup
L25:    ldc_w "duplicate"
L28:    invokespecial Method java/lang/RuntimeException <init> (Ljava/lang/String;)V
L31:    athrow
L32:    return
L33:    
        .attribute StackMap b'\x00\x01\x00\x20\x00\x03\x07\x00\x02\x07\x00\x4F\x07\x00\x49\x00\x00'
    .end code
.end method

.method private const : (Ljava/util/Map;)V
    .code stack 6 locals 6
L0:     aload_1
L1:     getstatic Field qE const LqE;
L4:     invokeinterface InterfaceMethod java/util/Map get (Ljava/lang/Object;)Ljava/lang/Object; 2
L9:     checkcast java/util/List
L12:    invokeinterface InterfaceMethod java/util/List isEmpty ()Z 1
L17:    ifeq L583
L20:    aload_1
L21:    aload_0
L22:    dup_x1
L23:    dup_x2
L24:    getfield Field qd void Leb;
L27:    aload_0
L28:    ldc 1e-1f
L30:    invokevirtual Method eb break (Lqd;F)V
L33:    invokespecial Method qd short (Ljava/util/Map;)V
L36:    getfield Field qd "native" Z
L39:    ifeq L297
L42:    new java/util/HashSet
L45:    dup
L46:    invokespecial Method java/util/HashSet <init> ()V
L49:    astore_2
L50:    aload_1
L51:    getstatic Field qE this LqE;
L54:    invokeinterface InterfaceMethod java/util/Map get (Ljava/lang/Object;)Ljava/lang/Object; 2
L59:    checkcast java/util/List
L62:    invokeinterface InterfaceMethod java/util/List iterator ()Ljava/util/Iterator; 1
L67:    dup
L68:    astore_3
L69:    invokeinterface InterfaceMethod java/util/Iterator hasNext ()Z 1
L74:    ifeq L105
L77:    aload_3
L78:    invokeinterface InterfaceMethod java/util/Iterator next ()Ljava/lang/Object; 1
L83:    checkcast Rg
L86:    astore 4
L88:    aload_3
L89:    aload_2
L90:    aload 4
L92:    getfield Field Rg short LsE;
L95:    invokeinterface InterfaceMethod java/util/Set add (Ljava/lang/Object;)Z 2
L100:   pop
L101:   goto L69
L104:   athrow
L105:   new java/util/HashSet
L108:   dup
L109:   invokespecial Method java/util/HashSet <init> ()V
L112:   astore_3
L113:   aload_1
L114:   getstatic Field qE char LqE;
L117:   invokeinterface InterfaceMethod java/util/Map get (Ljava/lang/Object;)Ljava/lang/Object; 2
L122:   checkcast java/util/List
L125:   invokeinterface InterfaceMethod java/util/List iterator ()Ljava/util/Iterator; 1
L130:   astore 4
L132:   aload 4
L134:   invokeinterface InterfaceMethod java/util/Iterator hasNext ()Z 1
L139:   ifeq L194
L142:   aload 4
L144:   invokeinterface InterfaceMethod java/util/Iterator next ()Ljava/lang/Object; 1
L149:   checkcast Rg
L152:   astore 5
L154:   aload_0
L155:   getfield Field qd do Z
L158:   ifne L178
L161:   aload_0
L162:   getfield Field qd false Ljava/util/Set;
L165:   aload 5
L167:   getfield Field Rg false Led;
L170:   invokeinterface InterfaceMethod java/util/Set contains (Ljava/lang/Object;)Z 2
L175:   ifeq L132
L178:   aload_3
L179:   aload 5
L181:   getfield Field Rg short LsE;
L184:   invokeinterface InterfaceMethod java/util/Set add (Ljava/lang/Object;)Z 2
L189:   pop
L190:   goto L132
L193:   athrow
L194:   aload_3
L195:   aload_2
L196:   invokeinterface InterfaceMethod java/util/Set removeAll (Ljava/util/Collection;)Z 2
L201:   pop
L202:   aload_2
L203:   invokeinterface InterfaceMethod java/util/Set size ()I 1
L208:   iconst_2
L209:   iconst_1
L210:   dup
L211:   pop2
L212:   if_icmpge L236
L215:   aload_0
L216:   getfield Field qd class Ljava/util/Set;
L219:   invokeinterface InterfaceMethod java/util/Set size ()I 1
L224:   iconst_1
L225:   dup
L226:   dup
L227:   pop2
L228:   if_icmple L236
L231:   aload_0
L232:   invokevirtual Method qd class ()V
L235:   return
L236:   aload_2
L237:   invokeinterface InterfaceMethod java/util/Set size ()I 1
L242:   iconst_1
L243:   dup
L244:   dup
L245:   pop2
L246:   if_icmpne L297
L249:   aload_0
L250:   getfield Field qd class Ljava/util/Set;
L253:   invokeinterface InterfaceMethod java/util/Set size ()I 1
L258:   iconst_1
L259:   dup
L260:   dup
L261:   pop2
L262:   if_icmpne L297
L265:   aload_3
L266:   invokeinterface InterfaceMethod java/util/Set size ()I 1
L271:   ifle L297
L274:   aload_0
L275:   getfield Field qd byte Z
L278:   ifeq L297
L281:   aload_0
L282:   invokevirtual Method qd catch ()I
L285:   aload_0
L286:   getfield Field qd instanceof I
L289:   if_icmpge L297
L292:   aload_0
L293:   invokevirtual Method qd class ()V
L296:   return
L297:   aload_1
L298:   getstatic Field qE this LqE;
L301:   invokeinterface InterfaceMethod java/util/Map get (Ljava/lang/Object;)Ljava/lang/Object; 2
L306:   checkcast java/util/List
L309:   dup
L310:   astore_2
L311:   invokeinterface InterfaceMethod java/util/List size ()I 1
L316:   iconst_2
L317:   iconst_1
L318:   dup
L319:   pop2
L320:   if_icmpge L344
L323:   aload_0
L324:   getfield Field qd "enum" Ljava/util/Map;
L327:   invokeinterface InterfaceMethod java/util/Map size ()I 1
L332:   iconst_1
L333:   dup
L334:   dup
L335:   pop2
L336:   if_icmple L344
L339:   aload_0
L340:   invokevirtual Method qd class ()V
L343:   return
L344:   aload_0
L345:   getfield Field qd "enum" Ljava/util/Map;
L348:   invokeinterface InterfaceMethod java/util/Map size ()I 1
L353:   iconst_1
L354:   dup
L355:   dup
L356:   pop2
L357:   if_icmpne L500
L360:   aload_2
L361:   invokeinterface InterfaceMethod java/util/List size ()I 1
L366:   iconst_1
L367:   dup
L368:   dup
L369:   pop2
L370:   if_icmpne L500
L373:   aload_1
L374:   getstatic Field qE char LqE;
L377:   invokeinterface InterfaceMethod java/util/Map get (Ljava/lang/Object;)Ljava/lang/Object; 2
L382:   checkcast java/util/List
L385:   invokeinterface InterfaceMethod java/util/List size ()I 1
L390:   ifle L500
L393:   aload_0
L394:   getfield Field qd "native" Z
L397:   ifne L500
L400:   aload_0
L401:   getfield Field qd byte Z
L404:   ifeq L500
L407:   aload_0
L408:   getfield Field qd do Z
L411:   dup
L412:   istore_3
L413:   ifne L491
L416:   aload_0
L417:   getfield Field qd new Ljava/util/LinkedHashMap;
L420:   invokevirtual Method java/util/LinkedHashMap values ()Ljava/util/Collection;
L423:   invokeinterface InterfaceMethod java/util/Collection iterator ()Ljava/util/Iterator; 1
L428:   astore 4
L430:   aload 4
L432:   invokeinterface InterfaceMethod java/util/Iterator hasNext ()Z 1
L437:   ifeq L491
L440:   aload 4
L442:   invokeinterface InterfaceMethod java/util/Iterator next ()Ljava/lang/Object; 1
L447:   checkcast Rg
L450:   dup
L451:   astore 5
L453:   getfield Field Rg case LqE;
L456:   getstatic Field qE char LqE;
L459:   if_acmpne L430
L462:   aload_0
L463:   getfield Field qd false Ljava/util/Set;
L466:   aload 5
L468:   getfield Field Rg false Led;
L471:   invokeinterface InterfaceMethod java/util/Set contains (Ljava/lang/Object;)Z 2
L476:   ifeq L430
L479:   iconst_1
L480:   dup
L481:   dup
L482:   pop2
L483:   dup
L484:   istore_3
L485:   goto L492
L488:   nop
L489:   nop
L490:   athrow
L491:   iload_3
L492:   ifeq L500
L495:   aload_0
L496:   invokevirtual Method qd class ()V
L499:   return
L500:   iconst_1
L501:   dup
L502:   dup
L503:   pop2
L504:   istore_3
L505:   aload_2
L506:   invokeinterface InterfaceMethod java/util/List iterator ()Ljava/util/Iterator; 1
L511:   astore 4
L513:   aload 4
L515:   invokeinterface InterfaceMethod java/util/Iterator hasNext ()Z 1
L520:   ifeq L554
L523:   aload 4
L525:   invokeinterface InterfaceMethod java/util/Iterator next ()Ljava/lang/Object; 1
L530:   checkcast Rg
L533:   dup
L534:   astore 5
L536:   instanceof ae
L539:   ifne L513
L542:   iconst_0
L543:   iconst_1
L544:   dup
L545:   pop2
L546:   dup
L547:   istore_3
L548:   goto L555
L551:   nop
L552:   nop
L553:   athrow
L554:   iload_3
L555:   ifeq L583
L558:   aload_0
L559:   dup
L560:   dup
L561:   getfield Field qd try F
L564:   ldc 1e-1f
L566:   fsub
L567:   putfield Field qd try F
L570:   getfield Field qd try F
L573:   fconst_0
L574:   fcmpg
L575:   ifge L583
L578:   aload_0
L579:   invokevirtual Method qd class ()V
L582:   return
L583:   return
L584:   
        .attribute StackMap b'\x00\x14\x00\x45\x00\x04\x07\x00\x02\x07\x00\x0E\x07\x00\xD1\x07\x00\xDD\x00\x01\x07\x00\xDD\x00\x68\x00\x00\x00\x01\x07\x00\x61\x00\x69\x00\x04\x07\x00\x02\x07\x00\x0E\x07\x00\xD1\x07\x00\xDD\x00\x00\x00\x84\x00\x05\x07\x00\x02\x07\x00\x0E\x07\x00\xD1\x07\x00\xD1\x07\x00\xDD\x00\x00\x00\xB2\x00\x06\x07\x00\x02\x07\x00\x0E\x07\x00\xD1\x07\x00\xD1\x07\x00\xDD\x07\x00\xF5\x00\x00\x00\xC1\x00\x00\x00\x01\x07\x00\x61\x00\xC2\x00\x05\x07\x00\x02\x07\x00\x0E\x07\x00\xD1\x07\x00\xD1\x07\x00\xDD\x00\x00\x00\xEC\x00\x05\x07\x00\x02\x07\x00\x0E\x07\x00\xD1\x07\x00\xD1\x07\x00\xDD\x00\x00\x01\x29\x00\x02\x07\x00\x02\x07\x00\x0E\x00\x00\x01\x58\x00\x03\x07\x00\x02\x07\x00\x0E\x07\x01\x7C\x00\x00\x01\xAE\x00\x05\x07\x00\x02\x07\x00\x0E\x07\x01\x7C\x01\x07\x00\xDD\x00\x00\x01\xE8\x00\x00\x00\x01\x07\x00\x61\x01\xEB\x00\x04\x07\x00\x02\x07\x00\x0E\x07\x01\x7C\x01\x00\x00\x01\xEC\x00\x04\x07\x00\x02\x07\x00\x0E\x07\x01\x7C\x01\x00\x01\x01\x01\xF4\x00\x03\x07\x00\x02\x07\x00\x0E\x07\x01\x7C\x00\x00\x02\x01\x00\x05\x07\x00\x02\x07\x00\x0E\x07\x01\x7C\x01\x07\x00\xDD\x00\x00\x02\x27\x00\x00\x00\x01\x07\x00\x61\x02\x2A\x00\x05\x07\x00\x02\x07\x00\x0E\x07\x01\x7C\x01\x07\x00\xDD\x00\x00\x02\x2B\x00\x05\x07\x00\x02\x07\x00\x0E\x07\x01\x7C\x01\x07\x00\xDD\x00\x01\x01\x02\x47\x00\x02\x07\x00\x02\x07\x00\x0E\x00\x00'
    .end code
.end method

.method public break : (J)V
    .code stack 13 locals 3
L0:     lload_1
L1:     aload_0
L2:     dup_x2
L3:     dup_x2
L4:     aload_0
L5:     dup
L6:     dup_x1
L7:     dup2
L8:     iconst_0
L9:     iconst_1
L10:    dup
L11:    pop2
L12:    putfield Field qd extends Z
L15:    getfield Field qd for Ljava/util/Set;
L18:    invokeinterface InterfaceMethod java/util/Set clear ()V 1
L23:    getfield Field qd "enum" Ljava/util/Map;
L26:    invokeinterface InterfaceMethod java/util/Map clear ()V 1
L31:    getfield Field qd class Ljava/util/Set;
L34:    invokeinterface InterfaceMethod java/util/Set clear ()V 1
L39:    invokestatic Method OC else ()D
L42:    putfield Field qd while D
L45:    getstatic Field QB "enum" LQB;
L48:    putfield Field qd null LQB;
L51:    putfield Field qd int J
L54:    invokevirtual Method qd const ()V
L57:    new xC
L60:    aload_0
L61:    dup
L62:    pop2
L63:    dup
L64:    aload_0
L65:    dup_x2
L66:    getfield Field qd null LQB;
L69:    aload_0
L70:    getfield Field qd int J
L73:    invokespecial Method xC <init> (LQB;J)V
L76:    invokevirtual Method qd else (LD;)V
L79:    return
L80:    
    .end code
.end method

.method public else : (Led;)V
    .code stack 3 locals 2
L0:     aload_0
L1:     aload_1
L2:     aconst_null
L3:     invokevirtual Method qd break (Led;LK;)V
L6:     return
L7:     
    .end code
.end method

.method private else : (Ljava/util/Map;)V
    .code stack 6 locals 5
L0:     invokestatic Method OC else ()D
L3:     aload_0
L4:     getfield Field qd while D
L7:     aload_0
L8:     invokevirtual Method qd long ()D
L11:    dadd
L12:    dcmpl
L13:    ifle L23
L16:    aload_0
L17:    getfield Field qd byte Z
L20:    ifne L30
L23:    aload_0
L24:    getfield Field qd extends Z
L27:    ifeq L242
L30:    aload_1
L31:    getstatic Field qE this LqE;
L34:    invokeinterface InterfaceMethod java/util/Map get (Ljava/lang/Object;)Ljava/lang/Object; 2
L39:    checkcast java/util/List
L42:    invokeinterface InterfaceMethod java/util/List isEmpty ()Z 1
L47:    ifeq L242
L50:    iconst_0
L51:    iconst_1
L52:    dup
L53:    pop2
L54:    istore_1
L55:    iconst_0
L56:    iconst_1
L57:    dup
L58:    pop2
L59:    istore_2
L60:    aload_0
L61:    getfield Field qd new Ljava/util/LinkedHashMap;
L64:    invokevirtual Method java/util/LinkedHashMap values ()Ljava/util/Collection;
L67:    invokeinterface InterfaceMethod java/util/Collection iterator ()Ljava/util/Iterator; 1
L72:    astore_3
L73:    aload_3
L74:    invokeinterface InterfaceMethod java/util/Iterator hasNext ()Z 1
L79:    ifeq L203
L82:    aload_3
L83:    invokeinterface InterfaceMethod java/util/Iterator next ()Ljava/lang/Object; 1
L88:    checkcast Rg
L91:    astore 4
L93:    getstatic Field HC "enum" [I
L96:    aload 4
L98:    getfield Field Rg case LqE;
L101:   invokevirtual Method qE ordinal ()I
L104:   iaload
L105:   tableswitch 1
            L152
            L161
            L161
            L161
            L170
            L199
            L199
            L199
            default : L199
L152:   iconst_1
L153:   iconst_0
L154:   ifne L153
L157:   dup
L158:   dup
L159:   pop2
L160:   istore_2
L161:   iconst_1
L162:   dup
L163:   dup
L164:   pop2
L165:   istore_1
L166:   goto L73
L169:   athrow
L170:   aload_0
L171:   getfield Field qd do Z
L174:   ifne L194
L177:   aload_0
L178:   getfield Field qd false Ljava/util/Set;
L181:   aload 4
L183:   getfield Field Rg false Led;
L186:   invokeinterface InterfaceMethod java/util/Set contains (Ljava/lang/Object;)Z 2
L191:   ifeq L73
L194:   iconst_1
L195:   dup
L196:   dup
L197:   pop2
L198:   istore_1
L199:   goto L73
L202:   athrow
L203:   iload_1
L204:   ifeq L229
L207:   iload_2
L208:   ifne L229
L211:   new java/util/Random
L214:   aload_0
L215:   dup_x1
L216:   dup
L217:   pop2
L218:   dup
L219:   invokespecial Method java/util/Random <init> ()V
L222:   invokevirtual Method java/util/Random nextLong ()J
L225:   invokevirtual Method qd break (J)V
L228:   return
L229:   iload_1
L230:   ifne L242
L233:   iload_2
L234:   ifne L242
L237:   aload_0
L238:   invokevirtual Method qd else ()V
L241:   return
L242:   return
L243:   
        .attribute StackMap b'\x00\x0E\x00\x17\x00\x02\x07\x00\x02\x07\x00\x0E\x00\x00\x00\x1E\x00\x02\x07\x00\x02\x07\x00\x0E\x00\x00\x00\x49\x00\x04\x07\x00\x02\x01\x01\x07\x00\xDD\x00\x00\x00\x98\x00\x05\x07\x00\x02\x01\x01\x07\x00\xDD\x07\x00\xF5\x00\x00\x00\x99\x00\x05\x07\x00\x02\x01\x01\x07\x00\xDD\x07\x00\xF5\x00\x01\x01\x00\xA1\x00\x05\x07\x00\x02\x01\x01\x07\x00\xDD\x07\x00\xF5\x00\x00\x00\xA9\x00\x00\x00\x01\x07\x00\x61\x00\xAA\x00\x05\x07\x00\x02\x01\x01\x07\x00\xDD\x07\x00\xF5\x00\x00\x00\xC2\x00\x05\x07\x00\x02\x01\x01\x07\x00\xDD\x07\x00\xF5\x00\x00\x00\xC7\x00\x05\x07\x00\x02\x01\x01\x07\x00\xDD\x07\x00\xF5\x00\x00\x00\xCA\x00\x00\x00\x01\x07\x00\x61\x00\xCB\x00\x04\x07\x00\x02\x01\x01\x07\x00\xDD\x00\x00\x00\xE5\x00\x04\x07\x00\x02\x01\x01\x07\x00\xDD\x00\x00\x00\xF2\x00\x01\x07\x00\x02\x00\x00'
    .end code
.end method

.method public break : (LD;)V
    .code stack 3 locals 8
L0:     invokestatic Method mc values ()[Lmc;
L3:     dup
L4:     astore_2
L5:     arraylength
L6:     istore_3
L7:     iconst_0
L8:     iconst_1
L9:     dup
L10:    pop2
L11:    dup
L12:    istore 4
L14:    iload_3
L15:    if_icmpge L93
L18:    aload_2
L19:    iload 4
L21:    aaload
L22:    astore 5
L24:    aload_0
L25:    getfield Field qd continue Ljava/util/Set;
L28:    invokeinterface InterfaceMethod java/util/Set iterator ()Ljava/util/Iterator; 1
L33:    astore 6
L35:    aload 6
L37:    invokeinterface InterfaceMethod java/util/Iterator hasNext ()Z 1
L42:    ifeq L84
L45:    aload 6
L47:    invokeinterface InterfaceMethod java/util/Iterator next ()Ljava/lang/Object; 1
L52:    checkcast Dc
L55:    dup
L56:    astore 7
L58:    getfield Field Dc do Ljava/lang/Object;
L61:    aload 5
L63:    if_acmpne L35
L66:    aload 7
L68:    getfield Field Dc "enum" Ljava/lang/Object;
L71:    checkcast G
L74:    aload_1
L75:    invokeinterface InterfaceMethod G break (LD;)V 2
L80:    goto L35
L83:    athrow
L84:    iinc 4 1
L87:    iload 4
L89:    goto L14
L92:    athrow
L93:    return
L94:    
        .attribute StackMap b'\x00\x06\x00\x0E\x00\x05\x07\x00\x02\x07\x01\xCA\x07\x00\x51\x01\x01\x00\x01\x01\x00\x23\x00\x07\x07\x00\x02\x07\x01\xCA\x07\x00\x51\x01\x01\x07\x00\x49\x07\x00\xDD\x00\x00\x00\x53\x00\x00\x00\x01\x07\x00\x61\x00\x54\x00\x07\x07\x00\x02\x07\x01\xCA\x07\x00\x51\x01\x01\x07\x00\x49\x07\x00\xDD\x00\x00\x00\x5C\x00\x00\x00\x01\x07\x00\x61\x00\x5D\x00\x05\x07\x00\x02\x07\x01\xCA\x07\x00\x51\x01\x01\x00\x00'
    .end code
.end method

.method public catch : ()I
    .code stack 3 locals 4
L0:     iconst_0
L1:     iconst_1
L2:     dup
L3:     pop2
L4:     istore_1
L5:     aload_0
L6:     getfield Field qd new Ljava/util/LinkedHashMap;
L9:     invokevirtual Method java/util/LinkedHashMap values ()Ljava/util/Collection;
L12:    invokeinterface InterfaceMethod java/util/Collection iterator ()Ljava/util/Iterator; 1
L17:    astore_2
L18:    aload_2
L19:    invokeinterface InterfaceMethod java/util/Iterator hasNext ()Z 1
L24:    ifeq L130
L27:    aload_2
L28:    invokeinterface InterfaceMethod java/util/Iterator next ()Ljava/lang/Object; 1
L33:    checkcast Rg
L36:    astore_3
L37:    getstatic Field HC "enum" [I
L40:    aload_3
L41:    getfield Field Rg case LqE;
L44:    invokevirtual Method qE ordinal ()I
L47:    iaload
L48:    tableswitch 1
            L96
            L96
            L96
            L96
            L107
            L127
            L127
            L127
            default : L127
L96:    iinc 1 1
L99:    iconst_0
L100:   ifne L99
L103:   goto L18
L106:   athrow
L107:   aload_0
L108:   getfield Field qd for Ljava/util/Set;
L111:   aload_3
L112:   invokeinterface InterfaceMethod java/util/Set contains (Ljava/lang/Object;)Z 2
L117:   ifeq L18
L120:   iinc 1 1
L123:   goto L18
L126:   athrow
L127:   goto L18
L130:   iload_1
L131:   ireturn
L132:   
        .attribute StackMap b'\x00\x08\x00\x12\x00\x03\x07\x00\x02\x01\x07\x00\xDD\x00\x00\x00\x60\x00\x04\x07\x00\x02\x01\x07\x00\xDD\x07\x00\xF5\x00\x00\x00\x63\x00\x04\x07\x00\x02\x01\x07\x00\xDD\x07\x00\xF5\x00\x00\x00\x6A\x00\x00\x00\x01\x07\x00\x61\x00\x6B\x00\x04\x07\x00\x02\x01\x07\x00\xDD\x07\x00\xF5\x00\x00\x00\x7E\x00\x00\x00\x01\x07\x00\x61\x00\x7F\x00\x04\x07\x00\x02\x01\x07\x00\xDD\x07\x00\xF5\x00\x00\x00\x82\x00\x03\x07\x00\x02\x01\x07\x00\xDD\x00\x00'
    .end code
.end method

.method public break : (LRg;)Z
    .code stack 2 locals 2
L0:     aload_0
L1:     getfield Field qd "enum" Ljava/util/Map;
L4:     aload_1
L5:     invokeinterface InterfaceMethod java/util/Map containsKey (Ljava/lang/Object;)Z 2
L10:    ireturn
L11:    
    .end code
.end method

.method public float : ()V
    .code stack 12 locals 2
L0:     aload_0
L1:     dup
L2:     dup_x1
L3:     dup2
L4:     fconst_1
L5:     aload_0
L6:     dup_x2
L7:     aload_0
L8:     dup
L9:     invokestatic Method OC else ()D
L12:    putfield Field qd while D
L15:    getstatic Field QB do LQB;
L18:    putfield Field qd null LQB;
L21:    invokestatic Method OC else ()D
L24:    putfield Field qd const D
L27:    putfield Field qd try F
L30:    getfield Field qd "enum" Ljava/util/Map;
L33:    invokeinterface InterfaceMethod java/util/Map clear ()V 1
L38:    invokespecial Method qd this ()Ljava/util/EnumMap;
L41:    invokespecial Method qd short (Ljava/util/Map;)V
L44:    invokevirtual Method qd const ()V
L47:    new xC
L50:    aload_0
L51:    dup
L52:    pop2
L53:    dup
L54:    aload_0
L55:    getfield Field qd null LQB;
L58:    invokespecial Method xC <init> (LQB;)V
L61:    invokevirtual Method qd else (LD;)V
        .catch java/lang/Exception from L64 to L86 using L88
L64:    aload_0
L65:    getfield Field qd throws Z
L68:    ifeq L98
L71:    new NE
L74:    aload_0
L75:    dup
L76:    pop2
L77:    dup
L78:    aload_0
L79:    dup_x2
L80:    invokespecial Method NE <init> (Lqd;)V
L83:    putfield Field qd else LNE;
L86:    return
L87:    athrow
L88:    astore_1
L89:    new java/lang/RuntimeException
L92:    dup
L93:    aload_1
L94:    invokespecial Method java/lang/RuntimeException <init> (Ljava/lang/Throwable;)V
L97:    athrow
L98:    return
L99:    
        .attribute StackMap b'\x00\x03\x00\x57\x00\x00\x00\x01\x07\x00\x61\x00\x58\x00\x01\x07\x00\x02\x00\x01\x07\x01\xD4\x00\x62\x00\x01\x07\x00\x02\x00\x00'
    .end code
.end method

.method private break : (Ljava/util/Map;)V
    .code stack 6 locals 4
L0:     aload_1
L1:     getstatic Field qE char LqE;
L4:     invokeinterface InterfaceMethod java/util/Map get (Ljava/lang/Object;)Ljava/lang/Object; 2
L9:     checkcast java/util/List
L12:    invokeinterface InterfaceMethod java/util/List iterator ()Ljava/util/Iterator; 1
L17:    astore_2
L18:    aload_2
L19:    invokeinterface InterfaceMethod java/util/Iterator hasNext ()Z 1
L24:    ifeq L114
L27:    aload_2
L28:    invokeinterface InterfaceMethod java/util/Iterator next ()Ljava/lang/Object; 1
L33:    checkcast Rg
L36:    astore_3
L37:    aload_0
L38:    invokevirtual Method qd catch ()I
L41:    aload_0
L42:    getfield Field qd instanceof I
L45:    if_icmpge L18
L48:    aload_0
L49:    getfield Field qd for Ljava/util/Set;
L52:    aload_3
L53:    invokeinterface InterfaceMethod java/util/Set contains (Ljava/lang/Object;)Z 2
L58:    ifne L18
L61:    aload_0
L62:    getfield Field qd do Z
L65:    ifne L84
L68:    aload_0
L69:    getfield Field qd false Ljava/util/Set;
L72:    aload_3
L73:    getfield Field Rg false Led;
L76:    invokeinterface InterfaceMethod java/util/Set contains (Ljava/lang/Object;)Z 2
L81:    ifeq L18
L84:    aload_0
L85:    dup
L86:    new qD
L89:    dup
L90:    aload_3
L91:    getfield Field Rg false Led;
L94:    invokespecial Method qD <init> (Led;)V
L97:    invokevirtual Method qd else (LD;)V
L100:   getfield Field qd for Ljava/util/Set;
L103:   aload_3
L104:   invokeinterface InterfaceMethod java/util/Set add (Ljava/lang/Object;)Z 2
L109:   pop
L110:   goto L18
L113:   athrow
L114:   invokestatic Method OC else ()D
L117:   aload_0
L118:   getfield Field qd while D
L121:   ldc2_w 2e0
L124:   dadd
L125:   dcmpg
L126:   ifgt L131
L129:   return
L130:   athrow
L131:   aload_1
L132:   getstatic Field qE const LqE;
L135:   invokeinterface InterfaceMethod java/util/Map get (Ljava/lang/Object;)Ljava/lang/Object; 2
L140:   checkcast java/util/List
L143:   invokeinterface InterfaceMethod java/util/List size ()I 1
L148:   ifne L251
L151:   aload_1
L152:   getstatic Field qE const LqE;
L155:   invokeinterface InterfaceMethod java/util/Map get (Ljava/lang/Object;)Ljava/lang/Object; 2
L160:   checkcast java/util/List
L163:   invokeinterface InterfaceMethod java/util/List size ()I 1
L168:   ifgt L231
L171:   aload_1
L172:   getstatic Field qE this LqE;
L175:   invokeinterface InterfaceMethod java/util/Map get (Ljava/lang/Object;)Ljava/lang/Object; 2
L180:   checkcast java/util/List
L183:   invokeinterface InterfaceMethod java/util/List size ()I 1
L188:   ifgt L231
L191:   aload_1
L192:   getstatic Field qE new LqE;
L195:   invokeinterface InterfaceMethod java/util/Map get (Ljava/lang/Object;)Ljava/lang/Object; 2
L200:   checkcast java/util/List
L203:   invokeinterface InterfaceMethod java/util/List size ()I 1
L208:   ifgt L231
L211:   aload_1
L212:   getstatic Field qE do LqE;
L215:   invokeinterface InterfaceMethod java/util/Map get (Ljava/lang/Object;)Ljava/lang/Object; 2
L220:   checkcast java/util/List
L223:   invokeinterface InterfaceMethod java/util/List size ()I 1
L228:   ifle L246
L231:   aload_0
L232:   new java/util/Random
L235:   dup
L236:   invokespecial Method java/util/Random <init> ()V
L239:   invokevirtual Method java/util/Random nextLong ()J
L242:   invokevirtual Method qd break (J)V
L245:   return
L246:   aload_0
L247:   invokevirtual Method qd else ()V
L250:   return
L251:   aload_0
L252:   invokevirtual Method qd float ()V
L255:   return
L256:   
        .attribute StackMap b'\x00\x09\x00\x12\x00\x03\x07\x00\x02\x07\x00\x0E\x07\x00\xDD\x00\x00\x00\x54\x00\x04\x07\x00\x02\x07\x00\x0E\x07\x00\xDD\x07\x00\xF5\x00\x00\x00\x71\x00\x00\x00\x01\x07\x00\x61\x00\x72\x00\x03\x07\x00\x02\x07\x00\x0E\x07\x00\xDD\x00\x00\x00\x82\x00\x00\x00\x01\x07\x00\x61\x00\x83\x00\x03\x07\x00\x02\x07\x00\x0E\x07\x00\xDD\x00\x00\x00\xE7\x00\x03\x07\x00\x02\x07\x00\x0E\x07\x00\xDD\x00\x00\x00\xF6\x00\x03\x07\x00\x02\x07\x00\x0E\x07\x00\xDD\x00\x00\x00\xFB\x00\x03\x07\x00\x02\x07\x00\x0E\x07\x00\xDD\x00\x00'
    .end code
.end method

.method public abstract break : (Led;LK;)V
.end method

.method public short : ()V
    .code stack 1 locals 1
L0:     aload_0
L1:     getfield Field qd float LM;
L4:     invokestatic Method ib break (LM;)V
L7:     return
L8:     
    .end code
.end method

.method public break : (Led;)V
    .code stack 5 locals 2
L0:     aload_0
L1:     aload_1
L2:     iconst_0
L3:     iconst_1
L4:     dup
L5:     pop2
L6:     aconst_null
L7:     dup
L8:     invokevirtual Method qd break (Led;ZLjava/lang/String;LK;)V
L11:    return
L12:    
    .end code
.end method

.method public const : ()V
    .code stack 3 locals 4
L0:     new java/util/ArrayList
L3:     dup
L4:     invokespecial Method java/util/ArrayList <init> ()V
L7:     astore_1
L8:     aload_0
L9:     getfield Field qd long Ljava/util/LinkedHashMap;
L12:    invokevirtual Method java/util/LinkedHashMap keySet ()Ljava/util/Set;
L15:    invokeinterface InterfaceMethod java/util/Set iterator ()Ljava/util/Iterator; 1
L20:    astore_2
L21:    aload_2
L22:    invokeinterface InterfaceMethod java/util/Iterator hasNext ()Z 1
L27:    ifeq L83
L30:    aload_2
L31:    invokeinterface InterfaceMethod java/util/Iterator next ()Ljava/lang/Object; 1
L36:    checkcast ed
L39:    astore_3
L40:    aload_0
L41:    getfield Field qd new Ljava/util/LinkedHashMap;
L44:    aload_3
L45:    invokevirtual Method java/util/LinkedHashMap containsKey (Ljava/lang/Object;)Z
L48:    ifeq L71
L51:    aload_0
L52:    getfield Field qd new Ljava/util/LinkedHashMap;
L55:    aload_3
L56:    invokevirtual Method java/util/LinkedHashMap get (Ljava/lang/Object;)Ljava/lang/Object;
L59:    checkcast Rg
L62:    getfield Field Rg case LqE;
L65:    getstatic Field qE try LqE;
L68:    if_acmpne L21
L71:    aload_1
L72:    aload_3
L73:    invokeinterface InterfaceMethod java/util/List add (Ljava/lang/Object;)Z 2
L78:    pop
L79:    goto L21
L82:    athrow
L83:    aload_1
L84:    invokeinterface InterfaceMethod java/util/List iterator ()Ljava/util/Iterator; 1
L89:    dup
L90:    astore_2
L91:    invokeinterface InterfaceMethod java/util/Iterator hasNext ()Z 1
L96:    ifeq L123
L99:    aload_2
L100:   invokeinterface InterfaceMethod java/util/Iterator next ()Ljava/lang/Object; 1
L105:   checkcast ed
L108:   astore_3
L109:   aload_2
L110:   aload_0
L111:   getfield Field qd long Ljava/util/LinkedHashMap;
L114:   aload_3
L115:   invokevirtual Method java/util/LinkedHashMap remove (Ljava/lang/Object;)Ljava/lang/Object;
L118:   pop
L119:   goto L91
L122:   athrow
L123:   return
L124:   
        .attribute StackMap b'\x00\x07\x00\x15\x00\x03\x07\x00\x02\x07\x01\xEE\x07\x00\xDD\x00\x00\x00\x47\x00\x04\x07\x00\x02\x07\x01\xEE\x07\x00\xDD\x07\x01\xF2\x00\x00\x00\x52\x00\x00\x00\x01\x07\x00\x61\x00\x53\x00\x03\x07\x00\x02\x07\x01\xEE\x07\x00\xDD\x00\x00\x00\x5B\x00\x03\x07\x00\x02\x07\x01\xEE\x07\x00\xDD\x00\x01\x07\x00\xDD\x00\x7A\x00\x00\x00\x01\x07\x00\x61\x00\x7B\x00\x03\x07\x00\x02\x07\x01\xEE\x07\x00\xDD\x00\x00'
    .end code
.end method

.method public static synthetic break : (Lqd;F)F
    .code stack 3 locals 2
L0:     aload_0
L1:     dup
L2:     getfield Field qd case F
L5:     fload_1
L6:     fadd
L7:     dup_x1
L8:     putfield Field qd case F
L11:    freturn
L12:    
    .end code
.end method

.method public else : ()V
    .code stack 7 locals 1
L0:     aload_0
L1:     dup
L2:     dup_x1
L3:     dup2
L4:     invokestatic Method OC else ()D
L7:     putfield Field qd while D
L10:    getstatic Field QB char LQB;
L13:    putfield Field qd null LQB;
L16:    getfield Field qd "enum" Ljava/util/Map;
L19:    invokeinterface InterfaceMethod java/util/Map clear ()V 1
L24:    getfield Field qd class Ljava/util/Set;
L27:    invokeinterface InterfaceMethod java/util/Set clear ()V 1
L32:    new xC
L35:    aload_0
L36:    dup
L37:    pop2
L38:    dup
L39:    aload_0
L40:    getfield Field qd null LQB;
L43:    invokespecial Method xC <init> (LQB;)V
L46:    invokevirtual Method qd else (LD;)V
L49:    return
L50:    
    .end code
.end method

.method public abstract break : (Led;ZLjava/lang/String;LK;)V
.end method
.innerclasses
    HC qd [0] static synthetic
    QB qd [0] public static final enum
    iC [0] [0]
    java/util/Map$Entry java/util/Map Entry public static interface abstract
.end innerclasses
.end class
