.version 49 0
.class public final super rB
.super java/lang/Object
.implements h
.field public final synthetic field1457 LGD;

.method public method728 : (LgB;)V
    .code stack 5 locals 2
L0:     aload_1
L1:     checkcast jC
L4:     invokevirtual Method jC method132 ()I
L7:     lookupswitch
            0 : L32
            1 : L111
            default : L149
L32:    invokestatic Method org/lwjgl/LWJGLUtil getPlatform ()I
L35:    iconst_0
L36:    ifne L35
L39:    iconst_2
L40:    iconst_1
L41:    dup
L42:    pop2
L43:    if_icmpne L68
L46:    aload_0
L47:    dup
L48:    getfield Field rB field1457 LGD;
L51:    invokestatic Method GD method553 (LGD;)LFE;
L54:    invokevirtual Method FE method56 ()V
L57:    invokestatic Method dc method1125 ()Ljava/lang/String;
L60:    invokestatic Method org/lwjgl/Sys method1892 (Ljava/lang/String;)Z
L63:    pop
L64:    goto L150
L67:    athrow
L68:    aload_0
L69:    dup
L70:    getfield Field rB field1457 LGD;
L73:    invokestatic Method GD method564 (LGD;)LFE;
L76:    aload_0
L77:    dup_x1
L78:    getfield Field rB field1457 LGD;
L81:    invokevirtual Method FE method203 (LbC;)V
L84:    getfield Field rB field1457 LGD;
L87:    invokestatic Method GD method571 (LGD;)LFE;
L90:    aload_0
L91:    getfield Field rB field1457 LGD;
L94:    invokestatic Method GD true (LGD;)LCC;
L97:    new kB
L100:   dup
L101:   invokespecial Method kB <init> ()V
L104:   invokevirtual Method FE method455 (LbC;LbC;)V
L107:   goto L150
L110:   athrow
L111:   aload_0
L112:   dup
L113:   getfield Field rB field1457 LGD;
L116:   invokestatic Method GD return (LGD;)LFE;
L119:   aload_0
L120:   getfield Field rB field1457 LGD;
L123:   invokevirtual Method FE method203 (LbC;)V
L126:   getfield Field rB field1457 LGD;
L129:   invokestatic Method GD method565 (LGD;)LFE;
L132:   aload_0
L133:   getfield Field rB field1457 LGD;
L136:   invokestatic Method GD true (LGD;)LCC;
L139:   new cb
L142:   dup
L143:   invokespecial Method cb <init> ()V
L146:   invokevirtual Method FE method455 (LbC;LbC;)V
L149:   aload_0
L150:   getfield Field rB field1457 LGD;
L153:   invokestatic Method GD method572 (LGD;)LFE;
L156:   aload_1
L157:   checkcast jC
L160:   invokevirtual Method FE method458 (LjC;)V
L163:   return
L164:   
        .attribute StackMap b'\x00\x08\x00\x20\x00\x02\x07\x00\x02\x07\x00\x17\x00\x00\x00\x23\x00\x02\x07\x00\x02\x07\x00\x17\x00\x01\x01\x00\x43\x00\x00\x00\x01\x07\x00\x35\x00\x44\x00\x02\x07\x00\x02\x07\x00\x17\x00\x00\x00\x6E\x00\x00\x00\x01\x07\x00\x35\x00\x6F\x00\x02\x07\x00\x02\x07\x00\x17\x00\x00\x00\x95\x00\x02\x07\x00\x02\x07\x00\x17\x00\x00\x00\x96\x00\x02\x07\x00\x02\x07\x00\x17\x00\x01\x07\x00\x02'
    .end code
.end method

.method public <init> : (LGD;)V
    .code stack 3 locals 2
L0:     aload_0
L1:     dup
L2:     aload_1
L3:     putfield Field rB field1457 LGD;
L6:     invokespecial Method java/lang/Object <init> ()V
L9:     return
L10:    
    .end code
.end method
.innerclasses
    rB [0] [0]
.end innerclasses
.enclosing method GD method74 ()V
.end class
