.version 49 0
.class public final super rb
.super java/lang/Object
.implements h
.field public final synthetic do LUb;

.method public break : (LgB;)V
    .code stack 11 locals 8
L0:     aload_0
L1:     getfield Field rb do LUb;
L4:     getfield Field Ub new Lnf;
L7:     invokevirtual Method nf const ()Ljava/lang/String;
L10:    dup
L11:    astore_2
L12:    ifnull L27
L15:    ldc ""
L17:    aload_2
L18:    invokevirtual Method java/lang/String trim ()Ljava/lang/String;
L21:    invokevirtual Method java/lang/String equals (Ljava/lang/Object;)Z
L24:    ifeq L29
L27:    return
L28:    athrow
L29:    ldc "/save"
L31:    aload_2
L32:    invokevirtual Method java/lang/String equals (Ljava/lang/Object;)Z
L35:    ifeq L437
L38:    aconst_null
L39:    astore_3
L40:    aconst_null
L41:    astore 4
        .catch java/lang/Exception from L43 to L236 using L390
L43:    new java/text/SimpleDateFormat
L46:    dup
L47:    ldc "yyyy-MM-dd HH.mm.ss"
L49:    invokespecial Method java/text/SimpleDateFormat <init> (Ljava/lang/String;)V
L52:    astore 5
L54:    new java/io/File
L57:    dup
L58:    ldc "user.home"
L60:    invokestatic Method java/lang/System getProperty (Ljava/lang/String;)Ljava/lang/String;
L63:    new java/lang/StringBuilder
L66:    dup
L67:    invokespecial Method java/lang/StringBuilder <init> ()V
L70:    iconst_0
L71:    ldc "Cultris II chat log "
L73:    invokevirtual Method java/lang/StringBuilder insert (ILjava/lang/String;)Ljava/lang/StringBuilder;
L76:    new java/util/Date
L79:    aload 5
L81:    dup_x1
L82:    dup
L83:    pop2
L84:    dup
L85:    invokespecial Method java/util/Date <init> ()V
L88:    invokevirtual Method java/text/SimpleDateFormat format (Ljava/util/Date;)Ljava/lang/String;
L91:    invokevirtual Method java/lang/StringBuilder append (Ljava/lang/String;)Ljava/lang/StringBuilder;
L94:    ldc ".txt"
L96:    invokevirtual Method java/lang/StringBuilder append (Ljava/lang/String;)Ljava/lang/StringBuilder;
L99:    invokevirtual Method java/lang/StringBuilder toString ()Ljava/lang/String;
L102:   invokespecial Method java/io/File <init> (Ljava/lang/String;Ljava/lang/String;)V
L105:   dup
L106:   astore 4
L108:   invokevirtual Method java/io/File createNewFile ()Z
L111:   ifne L135
L114:   ldc "Cultris II chat log "
L116:   ldc ".txt"
L118:   new java/io/File
L121:   dup
L122:   ldc "user.home"
L124:   invokestatic Method java/lang/System getProperty (Ljava/lang/String;)Ljava/lang/String;
L127:   invokespecial Method java/io/File <init> (Ljava/lang/String;)V
L130:   invokestatic Method java/io/File createTempFile (Ljava/lang/String;Ljava/lang/String;Ljava/io/File;)Ljava/io/File;
L133:   astore 4
L135:   new java/io/PrintWriter
L138:   dup
L139:   aload 4
L141:   invokespecial Method java/io/PrintWriter <init> (Ljava/io/File;)V
L144:   astore_3
L145:   aload_0
L146:   getfield Field rb do LUb;
L149:   invokevirtual Method Ub const ()Ljava/util/LinkedList;
L152:   invokevirtual Method java/util/LinkedList iterator ()Ljava/util/Iterator;
L155:   astore 6
L157:   aload 6
L159:   invokeinterface InterfaceMethod java/util/Iterator hasNext ()Z 1
L164:   ifeq L276
L167:   aload 6
L169:   invokeinterface InterfaceMethod java/util/Iterator next ()Ljava/lang/Object; 1
L174:   checkcast Dc
L177:   dup
L178:   astore 7
L180:   getfield Field Dc "enum" Ljava/lang/Object;
L183:   ifnull L237
L186:   new java/lang/StringBuilder
L189:   aload_3
L190:   dup_x1
L191:   dup
L192:   pop2
L193:   dup
L194:   invokespecial Method java/lang/StringBuilder <init> ()V
L197:   aload 7
L199:   getfield Field Dc "enum" Ljava/lang/Object;
L202:   checkcast ed
L205:   getfield Field ed "super" Ljava/lang/String;
L208:   invokevirtual Method java/lang/StringBuilder append (Ljava/lang/String;)Ljava/lang/StringBuilder;
L211:   ldc ": "
L213:   invokevirtual Method java/lang/StringBuilder append (Ljava/lang/String;)Ljava/lang/StringBuilder;
L216:   aload 7
L218:   getfield Field Dc do Ljava/lang/Object;
L221:   checkcast java/lang/String
L224:   invokevirtual Method java/lang/StringBuilder append (Ljava/lang/String;)Ljava/lang/StringBuilder;
L227:   invokevirtual Method java/lang/StringBuilder toString ()Ljava/lang/String;
L230:   invokevirtual Method java/io/PrintWriter println (Ljava/lang/String;)V
L233:   goto L157
L236:   athrow
        .catch java/lang/Exception from L237 to L387 using L390
L237:   aload_3
L238:   new java/lang/StringBuilder
L241:   dup
L242:   invokespecial Method java/lang/StringBuilder <init> ()V
L245:   iconst_0
L246:   ldc "- "
L248:   invokevirtual Method java/lang/StringBuilder insert (ILjava/lang/String;)Ljava/lang/StringBuilder;
L251:   aload 7
L253:   getfield Field Dc do Ljava/lang/Object;
L256:   checkcast java/lang/String
L259:   invokevirtual Method java/lang/StringBuilder append (Ljava/lang/String;)Ljava/lang/StringBuilder;
L262:   ldc " -"
L264:   invokevirtual Method java/lang/StringBuilder append (Ljava/lang/String;)Ljava/lang/StringBuilder;
L267:   invokevirtual Method java/lang/StringBuilder toString ()Ljava/lang/String;
L270:   invokevirtual Method java/io/PrintWriter println (Ljava/lang/String;)V
L273:   goto L157
L276:   aload_3
L277:   invokevirtual Method java/io/PrintWriter close ()V
L280:   new qc
L283:   dup
L284:   new fG
L287:   dup
L288:   getstatic Field LE else LLE;
L291:   fconst_0
L292:   invokespecial Method fG <init> (LLE;F)V
L295:   invokespecial Method qc <init> (Ld;)V
L298:   astore 6
L300:   new SB
L303:   aload 6
L305:   dup_x1
L306:   dup
L307:   pop2
L308:   dup
L309:   new DF
L312:   dup
L313:   ldc "Chat log saved to"
L315:   getstatic Field We float LWe;
L318:   invokespecial Method DF <init> (Ljava/lang/String;LWe;)V
L321:   fconst_0
L322:   ldc 1.45e-1f
L324:   invokespecial Method SB <init> (LgB;FF)V
L327:   invokevirtual Method qc float (LgB;)LgB;
L330:   aload 4
L332:   invokevirtual Method java/io/File getAbsolutePath ()Ljava/lang/String;
L335:   astore 7
L337:   new KF
L340:   aload 6
L342:   dup_x1
L343:   dup
L344:   pop2
L345:   dup
L346:   aload 7
L348:   getstatic Field We float LWe;
L351:   getfield Field We long F
L354:   iconst_1
L355:   dup
L356:   dup
L357:   pop2
L358:   new QC
L361:   dup
L362:   aload_0
L363:   aload 7
L365:   invokespecial Method QC <init> (Lrb;Ljava/lang/String;)V
L368:   invokespecial Method KF <init> (Ljava/lang/String;FZLh;)V
L371:   invokevirtual Method qc float (LgB;)LgB;
L374:   pop2
L375:   aload_0
L376:   getfield Field rb do LUb;
L379:   getfield Field Ub try LtD;
L382:   aload 6
L384:   invokevirtual Method tD const (Lqc;)V
L387:   goto L480
L390:   astore 5
L392:   aload_3
L393:   ifnull L407
        .catch java/lang/Exception from L396 to L400 using L405
L396:   aload_3
L397:   invokevirtual Method java/io/PrintWriter close ()V
L400:   aload 4
L402:   goto L409
L405:   astore 6
L407:   aload 4
L409:   ifnull L429
        .catch java/lang/Exception from L412 to L422 using L427
L412:   aload 4
L414:   dup
L415:   invokevirtual Method java/io/File deleteOnExit ()V
L418:   invokevirtual Method java/io/File delete ()Z
L421:   pop
L422:   aload 5
L424:   goto L431
L427:   astore 6
L429:   aload 5
L431:   invokevirtual Method java/lang/Exception printStackTrace ()V
L434:   goto L480
L437:   getstatic Field Kc else LKc;
L440:   getstatic Field Pc do LPc;
L443:   invokevirtual Method Kc else (LPc;)Led;
L446:   dup
L447:   astore_3
L448:   aload_0
L449:   swap
L450:   ifnonnull L472
L453:   getfield Field rb do LUb;
L456:   invokestatic Method Ub break (LUb;)LFE;
L459:   getstatic Field Ae else LAe;
L462:   ldc "You can only chat when connected to GEWALTIG.net."
L464:   invokevirtual Method FE break (LAe;Ljava/lang/String;)LjC;
L467:   pop
L468:   aload_0
L469:   goto L481
L472:   getfield Field rb do LUb;
L475:   aload_3
L476:   aload_2
L477:   invokevirtual Method Ub else (Led;Ljava/lang/String;)V
L480:   aload_0
L481:   getfield Field rb do LUb;
L484:   getfield Field Ub new Lnf;
L487:   ldc ""
L489:   invokevirtual Method nf break (Ljava/lang/String;)V
L492:   return
L493:   
        .attribute StackMap b'\x00\x13\x00\x1B\x00\x03\x07\x00\x02\x07\x00\x38\x07\x00\x2F\x00\x00\x00\x1C\x00\x00\x00\x01\x07\x00\x3A\x00\x1D\x00\x03\x07\x00\x02\x07\x00\x38\x07\x00\x2F\x00\x00\x00\x87\x00\x06\x07\x00\x02\x07\x00\x38\x07\x00\x2F\x05\x07\x00\x43\x07\x00\x3E\x00\x00\x00\x9D\x00\x07\x07\x00\x02\x07\x00\x38\x07\x00\x2F\x07\x00\x74\x07\x00\x43\x07\x00\x3E\x07\x00\x82\x00\x00\x00\xEC\x00\x00\x00\x01\x07\x00\x3A\x00\xED\x00\x08\x07\x00\x02\x07\x00\x38\x07\x00\x2F\x07\x00\x74\x07\x00\x43\x07\x00\x3E\x07\x00\x82\x07\x00\x8B\x00\x00\x01\x14\x00\x07\x07\x00\x02\x07\x00\x38\x07\x00\x2F\x07\x00\x74\x07\x00\x43\x07\x00\x3E\x07\x00\x82\x00\x00\x01\x86\x00\x05\x07\x00\x02\x07\x00\x38\x07\x00\x2F\x07\x00\x74\x07\x00\x43\x00\x01\x07\x00\x1F\x01\x95\x00\x06\x07\x00\x02\x07\x00\x38\x07\x00\x2F\x07\x00\x74\x07\x00\x43\x07\x00\x1F\x00\x01\x07\x00\x1F\x01\x97\x00\x06\x07\x00\x02\x07\x00\x38\x07\x00\x2F\x07\x00\x74\x07\x00\x43\x07\x00\x1F\x00\x00\x01\x99\x00\x06\x07\x00\x02\x07\x00\x38\x07\x00\x2F\x07\x00\x74\x07\x00\x43\x07\x00\x1F\x00\x01\x07\x00\x43\x01\xAB\x00\x06\x07\x00\x02\x07\x00\x38\x07\x00\x2F\x07\x00\x74\x07\x00\x43\x07\x00\x1F\x00\x01\x07\x00\x1F\x01\xAD\x00\x06\x07\x00\x02\x07\x00\x38\x07\x00\x2F\x07\x00\x74\x07\x00\x43\x07\x00\x1F\x00\x00\x01\xAF\x00\x06\x07\x00\x02\x07\x00\x38\x07\x00\x2F\x07\x00\x74\x07\x00\x43\x07\x00\x1F\x00\x01\x07\x00\x1F\x01\xB5\x00\x03\x07\x00\x02\x07\x00\x38\x07\x00\x2F\x00\x00\x01\xD8\x00\x04\x07\x00\x02\x07\x00\x38\x07\x00\x2F\x07\x00\x91\x00\x01\x07\x00\x02\x01\xE0\x00\x04\x07\x00\x02\x07\x00\x38\x07\x00\x2F\x07\x00\x04\x00\x00\x01\xE1\x00\x04\x07\x00\x02\x07\x00\x38\x07\x00\x2F\x07\x00\x04\x00\x01\x07\x00\x02'
    .end code
.end method

.method public <init> : (LUb;)V
    .code stack 3 locals 2
L0:     aload_0
L1:     dup
L2:     aload_1
L3:     putfield Field rb do LUb;
L6:     invokespecial Method java/lang/Object <init> ()V
L9:     return
L10:    
    .end code
.end method
.innerclasses
    Ae ig [0] public static final enum
    LE fG [0] public static final enum
    Pc JB [0] public static final enum
    QC [0] [0]
    rb [0] [0]
.end innerclasses
.enclosing method Ub <init> (Ljava/lang/String;)V
.end class
