.version 49 0
.class public final super rd
.super java/lang/Object
.implements D
.field public this LKD;
.field private char LRC;
.field public else I
.field public "enum" Led;
.field private do Z

.method public <init> : (LMd;)V
    .code stack 5 locals 2
L0:     aload_1
L1:     aload_0
L2:     invokespecial Method java/lang/Object <init> ()V
L5:     invokevirtual Method Md for ()Z
L8:     ifeq L42
L11:    aload_0
L12:    getstatic Field Kc else LKc;
L15:    invokevirtual Method Kc const ()Ljava/util/LinkedHashMap;
L18:    aload_1
L19:    invokevirtual Method Md long ()I
L22:    invokestatic Method java/lang/Integer valueOf (I)Ljava/lang/Integer;
L25:    invokevirtual Method java/util/LinkedHashMap get (Ljava/lang/Object;)Ljava/lang/Object;
L28:    checkcast RC
L31:    putfield Field rd char LRC;
L34:    aload_0
L35:    getfield Field rd char LRC;
L38:    aload_1
L39:    invokevirtual Method RC break (LMd;)V
L42:    aload_0
L43:    dup
L44:    dup_x1
L45:    getstatic Field Kc else LKc;
L48:    aload_1
L49:    invokevirtual Method Md long ()I
L52:    invokevirtual Method Kc break (I)Led;
L55:    putfield Field rd "enum" Led;
L58:    invokestatic Method KD values ()[LKD;
L61:    aload_1
L62:    dup_x2
L63:    invokevirtual Method Md long ()I
L66:    aaload
L67:    putfield Field rd this LKD;
L70:    invokevirtual Method Md long ()I
L73:    putfield Field rd else I
L76:    return
L77:    
        .attribute StackMap b'\x00\x01\x00\x2A\x00\x02\x07\x00\x02\x07\x00\x1D\x00\x00'
    .end code
    .exceptions java/io/IOException
.end method

.method public <init> : (ZLRC;Led;LKD;I)V
    .code stack 11 locals 6
L0:     iload_1
L1:     aload_0
L2:     dup_x1
L3:     iload 5
L5:     aload 4
L7:     aload_0
L8:     dup_x1
L9:     aload_3
L10:    aload_2
L11:    aload_0
L12:    dup_x1
L13:    invokespecial Method java/lang/Object <init> ()V
L16:    putfield Field rd char LRC;
L19:    putfield Field rd "enum" Led;
L22:    putfield Field rd this LKD;
L25:    putfield Field rd else I
L28:    putfield Field rd do Z
L31:    return
L32:    
    .end code
.end method

.method public break : (LAC;)V
    .code stack 6 locals 2
L0:     aload_1
L1:     aload_0
L2:     dup_x1
L3:     getfield Field rd do Z
L6:     invokevirtual Method AC break (Z)V
L9:     getfield Field rd do Z
L12:    ifeq L34
L15:    aload_1
L16:    aload_0
L17:    dup_x1
L18:    getfield Field rd char LRC;
L21:    getfield Field RC "enum" I
L24:    invokevirtual Method AC break (I)V
L27:    getfield Field rd char LRC;
L30:    aload_1
L31:    invokevirtual Method RC else (LAC;)V
L34:    aload_1
L35:    dup
L36:    aload_0
L37:    dup_x1
L38:    aload_1
L39:    aload_0
L40:    getfield Field rd "enum" Led;
L43:    getfield Field ed try I
L46:    invokevirtual Method AC break (I)V
L49:    getfield Field rd this LKD;
L52:    invokevirtual Method KD ordinal ()I
L55:    invokevirtual Method AC break (I)V
L58:    getfield Field rd else I
L61:    invokevirtual Method AC break (I)V
L64:    return
L65:    
        .attribute StackMap b'\x00\x01\x00\x22\x00\x02\x07\x00\x02\x07\x00\x54\x00\x00'
    .end code
    .exceptions java/io/IOException
.end method
.innerclasses
    KD K [0] public static final enum
.end innerclasses
.end class
