.version 49 0
.class public super abstract Rg
.super java/lang/Object
.implements G
.implements M
.implements java/lang/Comparable
.field public package J
.field private field211 Ljava/util/List;
.field public field212 F
.field public while Ljava/util/Map;
.field public field213 I
.field public field214 [D
.field public field215 F
.field public field216 Ljava/util/Random;
.field public field217 LbD;
.field public field218 I
.field public field219 F
.field public field220 Ljava/util/List;
.field public field221 Lff;
.field public field222 I
.field public field223 I
.field public false Led;
.field private field224 F
.field public field225 I
.field public true I
.field public field226 F
.field public field227 LqE;
.field public field228 I
.field public field229 Z
.field public field230 I
.field public field231 LsE;
.field public field232 I
.field private static final field233 I = 10
.field private field234 Ljava/util/LinkedList;
.field public field235 Ljava/util/LinkedList;
.field public try I
.field public field236 I
.field public new Ljava/util/Random;
.field private static final field237 F = 1e-1f
.field public this [[I
.field public field238 Lff;
.field public field239 Lqd;
.field public field240 D
.field public field241 F

.method public method226 : (LqE;)V
    .code stack 23 locals 4
L0:     aload_0
L1:     getfield Field Rg field227 LqE;
L4:     aload_1
L5:     if_acmpne L10
L8:     return
L9:     athrow
L10:    aload_0
L11:    aload_1
L12:    putfield Field Rg field227 LqE;
L15:    getstatic Field XE field2166 [I
L18:    aload_1
L19:    invokevirtual Method qE ordinal ()I
L22:    iaload
L23:    tableswitch 1
            L68
            L251
            L251
            L199
            L285
            L300
            L263
            L300
            default : L300
L68:    aload_0
L69:    iconst_0
L70:    ifne L297
L73:    dup
L74:    iconst_0
L75:    aload_0
L76:    dup_x2
L77:    dconst_0
L78:    iconst_0
L79:    aload_0
L80:    dup_x1
L81:    dup_x2
L82:    iconst_1
L83:    aload_0
L84:    dup_x1
L85:    iconst_0
L86:    aload_0
L87:    dup
L88:    dup_x1
L89:    dup2
L90:    iconst_1
L91:    dup
L92:    dup
L93:    pop2
L94:    invokevirtual Method Rg method95 (Z)V
L97:    getfield Field Rg field235 Ljava/util/LinkedList;
L100:   invokevirtual Method java/util/LinkedList clear ()V
L103:   getfield Field Rg field239 Lqd;
L106:   getfield Field qd field761 Leb;
L109:   aload_0
L110:   invokevirtual Method eb method754 (LRg;)V
L113:   getfield Field Rg field239 Lqd;
L116:   getfield Field qd field756 J
L119:   invokevirtual Method Rg method234 (J)V
L122:   iconst_1
L123:   dup
L124:   pop2
L125:   putfield Field Rg try I
L128:   iconst_1
L129:   dup
L130:   pop2
L131:   invokevirtual Method Rg method228 (Z)Lff;
L134:   putfield Field Rg field221 Lff;
L137:   iconst_1
L138:   dup
L139:   pop2
L140:   invokevirtual Method Rg method228 (Z)Lff;
L143:   putfield Field Rg field238 Lff;
L146:   putfield Field Rg field240 D
L149:   iconst_1
L150:   dup
L151:   pop2
L152:   invokevirtual Method Rg method95 (Z)V
L155:   invokespecial Method Rg method61 ()V
L158:   getfield Field Rg field211 Ljava/util/List;
L161:   invokeinterface InterfaceMethod java/util/List iterator ()Ljava/util/Iterator; 1
L166:   dup
L167:   astore_1
L168:   invokeinterface InterfaceMethod java/util/Iterator hasNext ()Z 1
L173:   ifeq L300
L176:   aload_1
L177:   invokeinterface InterfaceMethod java/util/Iterator next ()Ljava/lang/Object; 1
L182:   checkcast Uf
L185:   astore_2
L186:   aload_1
L187:   aload_2
L188:   aload_0
L189:   invokevirtual Method Uf method703 (LRg;)V
L192:   goto L168
L195:   nop
L196:   nop
L197:   nop
L198:   athrow
L199:   aload_0
L200:   dup
L201:   dup_x1
L202:   getfield Field Rg field235 Ljava/util/LinkedList;
L205:   invokevirtual Method java/util/LinkedList clear ()V
L208:   invokespecial Method Rg method61 ()V
L211:   getfield Field Rg field211 Ljava/util/List;
L214:   invokeinterface InterfaceMethod java/util/List iterator ()Ljava/util/Iterator; 1
L219:   dup
L220:   astore_1
L221:   invokeinterface InterfaceMethod java/util/Iterator hasNext ()Z 1
L226:   ifeq L300
L229:   aload_1
L230:   invokeinterface InterfaceMethod java/util/Iterator next ()Ljava/lang/Object; 1
L235:   checkcast Uf
L238:   astore_2
L239:   aload_1
L240:   aload_2
L241:   aload_0
L242:   invokevirtual Method Uf method703 (LRg;)V
L245:   goto L221
L248:   nop
L249:   nop
L250:   athrow
L251:   aload_0
L252:   dup
L253:   iconst_1
L254:   dup
L255:   dup
L256:   pop2
L257:   invokespecial Method Rg method238 (Z)V
L260:   goto L301
L263:   aload_0
L264:   bipush 10
L266:   iconst_1
L267:   dup
L268:   pop2
L269:   bipush 28
L271:   iconst_1
L272:   dup
L273:   pop2
L274:   multianewarray [[I 2
L278:   putfield Field Rg this [[I
L281:   aload_0
L282:   goto L301
L285:   aload_0
L286:   dup
L287:   iconst_0
L288:   iconst_1
L289:   dup
L290:   pop2
L291:   invokespecial Method Rg method238 (Z)V
L294:   goto L301
L297:   goto L69
L300:   aload_0
L301:   getfield Field Rg field220 Ljava/util/List;
L304:   invokeinterface InterfaceMethod java/util/List iterator ()Ljava/util/Iterator; 1
L309:   dup
L310:   astore_1
L311:   invokeinterface InterfaceMethod java/util/Iterator hasNext ()Z 1
L316:   ifeq L339
L319:   aload_1
L320:   invokeinterface InterfaceMethod java/util/Iterator next ()Ljava/lang/Object; 1
L325:   checkcast F
L328:   astore_2
L329:   aload_1
L330:   aload_2
L331:   invokeinterface InterfaceMethod F method65 ()V 1
L336:   goto L311
L339:   aload_0
L340:   invokespecial Method Rg method240 ()Ljava/util/List;
L343:   invokeinterface InterfaceMethod java/util/List iterator ()Ljava/util/Iterator; 1
L348:   astore_1
L349:   aload_1
L350:   invokeinterface InterfaceMethod java/util/Iterator hasNext ()Z 1
L355:   ifeq L409
L358:   aload_1
L359:   invokeinterface InterfaceMethod java/util/Iterator next ()Ljava/lang/Object; 1
L364:   checkcast Uf
L367:   astore_2
L368:   aload_0
L369:   getfield Field Rg field220 Ljava/util/List;
L372:   invokeinterface InterfaceMethod java/util/List iterator ()Ljava/util/Iterator; 1
L377:   dup
L378:   astore_3
L379:   invokeinterface InterfaceMethod java/util/Iterator hasNext ()Z 1
L384:   ifeq L349
L387:   aload_3
L388:   invokeinterface InterfaceMethod java/util/Iterator next ()Ljava/lang/Object; 1
L393:   checkcast F
L396:   aload_2
L397:   invokeinterface InterfaceMethod F method60 (LUf;)V 2
L402:   aload_3
L403:   goto L379
L406:   nop
L407:   nop
L408:   athrow
L409:   return
L410:   
        .attribute StackMap b'\x00\x15\x00\x09\x00\x00\x00\x01\x07\x00\x5B\x00\x0A\x00\x02\x07\x00\x02\x07\x00\x5D\x00\x00\x00\x44\x00\x02\x07\x00\x02\x07\x00\x5D\x00\x00\x00\x45\x00\x02\x07\x00\x02\x07\x00\x5D\x00\x01\x07\x00\x02\x00\xA8\x00\x02\x07\x00\x02\x07\x00\x9D\x00\x01\x07\x00\x9D\x00\xC3\x00\x00\x00\x01\x07\x00\x5B\x00\xC7\x00\x02\x07\x00\x02\x07\x00\x5D\x00\x00\x00\xDD\x00\x02\x07\x00\x02\x07\x00\x9D\x00\x01\x07\x00\x9D\x00\xF8\x00\x00\x00\x01\x07\x00\x5B\x00\xFB\x00\x02\x07\x00\x02\x07\x00\x5D\x00\x00\x01\x07\x00\x02\x07\x00\x02\x07\x00\x5D\x00\x00\x01\x1D\x00\x02\x07\x00\x02\x07\x00\x5D\x00\x00\x01\x29\x00\x02\x07\x00\x02\x07\x00\x5D\x00\x01\x07\x00\x02\x01\x2C\x00\x02\x07\x00\x02\x07\x00\x04\x00\x00\x01\x2D\x00\x02\x07\x00\x02\x07\x00\x04\x00\x01\x07\x00\x02\x01\x37\x00\x02\x07\x00\x02\x07\x00\x9D\x00\x01\x07\x00\x9D\x01\x53\x00\x02\x07\x00\x02\x07\x00\x9D\x00\x00\x01\x5D\x00\x02\x07\x00\x02\x07\x00\x9D\x00\x00\x01\x7B\x00\x04\x07\x00\x02\x07\x00\x9D\x07\x00\xA7\x07\x00\x9D\x00\x01\x07\x00\x9D\x01\x96\x00\x00\x00\x01\x07\x00\x5B\x01\x99\x00\x02\x07\x00\x02\x07\x00\x9D\x00\x00'
    .end code
.end method

.method public method227 : ()Z
    .code stack 6 locals 2
L0:     aload_0
L1:     getfield Field Rg field227 LqE;
L4:     getstatic Field qE this LqE;
L7:     if_acmpeq L16
L10:    iconst_0
L11:    iconst_1
L12:    dup
L13:    pop2
L14:    ireturn
L15:    athrow
L16:    aload_0
L17:    dup
L18:    dup_x1
L19:    iconst_1
L20:    dup
L21:    dup
L22:    pop2
L23:    invokevirtual Method Rg method95 (Z)V
L26:    invokespecial Method Rg method84 ()V
L29:    getfield Field Rg field225 I
L32:    ifle L94
L35:    aload_0
L36:    getfield Field Rg field240 D
L39:    aload_0
L40:    getfield Field Rg field241 F
L43:    f2d
L44:    dcmpg
L45:    ifge L94
L48:    aload_0
L49:    dup
L50:    iconst_0
L51:    iconst_1
L52:    dup
L53:    pop2
L54:    putfield Field Rg field225 I
L57:    getfield Field Rg field220 Ljava/util/List;
L60:    invokeinterface InterfaceMethod java/util/List iterator ()Ljava/util/Iterator; 1
L65:    dup
L66:    astore_1
L67:    invokeinterface InterfaceMethod java/util/Iterator hasNext ()Z 1
L72:    ifeq L94
L75:    aload_1
L76:    invokeinterface InterfaceMethod java/util/Iterator next ()Ljava/lang/Object; 1
L81:    checkcast F
L84:    invokeinterface InterfaceMethod F method52 ()V 1
L89:    aload_1
L90:    goto L67
L93:    athrow
L94:    aload_0
L95:    iconst_0
L96:    aload_0
L97:    dup
L98:    getfield Field Rg field241 F
L101:   getstatic Field ib field2312 F
L104:   fadd
L105:   putfield Field Rg field241 F
L108:   iconst_1
L109:   dup
L110:   pop2
L111:   invokevirtual Method Rg method95 (Z)V
L114:   iconst_0
L115:   iconst_1
L116:   dup
L117:   pop2
L118:   ireturn
L119:   
        .attribute StackMap b'\x00\x05\x00\x0F\x00\x00\x00\x01\x07\x00\x5B\x00\x10\x00\x01\x07\x00\x02\x00\x00\x00\x43\x00\x02\x07\x00\x02\x07\x00\x9D\x00\x01\x07\x00\x9D\x00\x5D\x00\x00\x00\x01\x07\x00\x5B\x00\x5E\x00\x01\x07\x00\x02\x00\x00'
    .end code
    .exceptions java/lang/Exception
.end method

.method public method228 : (Z)Lff;
    .code stack 5 locals 4
L0:     aload_0
L1:     getfield Field Rg field239 Lqd;
L4:     getfield Field qd field761 Leb;
L7:     iload_1
L8:     aload_0
L9:     invokevirtual Method eb method753 (ZLRg;)Lff;
L12:    astore_1
L13:    iconst_0
L14:    aload_1
L15:    dup_x1
L16:    aload_0
L17:    getfield Field Rg field217 LbD;
L20:    aload_1
L21:    invokevirtual Method bD method390 (Lff;)I
L24:    invokevirtual Method ff method14 (I)V
L27:    iconst_1
L28:    dup
L29:    pop2
L30:    istore_2
L31:    instanceof tF
L34:    ifeq L70
L37:    new java/lang/StringBuilder
L40:    dup
L41:    invokespecial Method java/lang/StringBuilder <init> ()V
L44:    iconst_0
L45:    aload_0
L46:    getfield Field Rg false Led;
L49:    getfield Field ed field711 LPc;
L52:    getfield Field Pc field370 Ljava/lang/String;
L55:    invokevirtual Method java/lang/StringBuilder insert (ILjava/lang/String;)Ljava/lang/StringBuilder;
L58:    ldc "si"
L60:    invokevirtual Method java/lang/StringBuilder append (Ljava/lang/String;)Ljava/lang/StringBuilder;
L63:    invokevirtual Method java/lang/StringBuilder toString ()Ljava/lang/String;
L66:    invokestatic Method JB method831 (Ljava/lang/String;)I
L69:    istore_2
L70:    aload_1
L71:    instanceof AF
L74:    ifeq L111
L77:    new java/lang/StringBuilder
L80:    dup
L81:    invokespecial Method java/lang/StringBuilder <init> ()V
L84:    iconst_0
L85:    aload_0
L86:    getfield Field Rg false Led;
L89:    getfield Field ed field711 LPc;
L92:    getfield Field Pc field370 Ljava/lang/String;
L95:    invokevirtual Method java/lang/StringBuilder insert (ILjava/lang/String;)Ljava/lang/StringBuilder;
L98:    ldc_w "sj"
L101:   invokevirtual Method java/lang/StringBuilder append (Ljava/lang/String;)Ljava/lang/StringBuilder;
L104:   invokevirtual Method java/lang/StringBuilder toString ()Ljava/lang/String;
L107:   invokestatic Method JB method831 (Ljava/lang/String;)I
L110:   istore_2
L111:   aload_1
L112:   instanceof VF
L115:   ifeq L152
L118:   new java/lang/StringBuilder
L121:   dup
L122:   invokespecial Method java/lang/StringBuilder <init> ()V
L125:   iconst_0
L126:   aload_0
L127:   getfield Field Rg false Led;
L130:   getfield Field ed field711 LPc;
L133:   getfield Field Pc field370 Ljava/lang/String;
L136:   invokevirtual Method java/lang/StringBuilder insert (ILjava/lang/String;)Ljava/lang/StringBuilder;
L139:   ldc_w "sl"
L142:   invokevirtual Method java/lang/StringBuilder append (Ljava/lang/String;)Ljava/lang/StringBuilder;
L145:   invokevirtual Method java/lang/StringBuilder toString ()Ljava/lang/String;
L148:   invokestatic Method JB method831 (Ljava/lang/String;)I
L151:   istore_2
L152:   aload_1
L153:   instanceof Df
L156:   ifeq L164
L159:   iconst_0
L160:   iconst_1
L161:   dup
L162:   pop2
L163:   istore_2
L164:   aload_1
L165:   instanceof mE
L168:   ifeq L205
L171:   new java/lang/StringBuilder
L174:   dup
L175:   invokespecial Method java/lang/StringBuilder <init> ()V
L178:   iconst_0
L179:   aload_0
L180:   getfield Field Rg false Led;
L183:   getfield Field ed field711 LPc;
L186:   getfield Field Pc field370 Ljava/lang/String;
L189:   invokevirtual Method java/lang/StringBuilder insert (ILjava/lang/String;)Ljava/lang/StringBuilder;
L192:   ldc_w "ss"
L195:   invokevirtual Method java/lang/StringBuilder append (Ljava/lang/String;)Ljava/lang/StringBuilder;
L198:   invokevirtual Method java/lang/StringBuilder toString ()Ljava/lang/String;
L201:   invokestatic Method JB method831 (Ljava/lang/String;)I
L204:   istore_2
L205:   aload_1
L206:   instanceof TE
L209:   ifeq L246
L212:   new java/lang/StringBuilder
L215:   dup
L216:   invokespecial Method java/lang/StringBuilder <init> ()V
L219:   iconst_0
L220:   aload_0
L221:   getfield Field Rg false Led;
L224:   getfield Field ed field711 LPc;
L227:   getfield Field Pc field370 Ljava/lang/String;
L230:   invokevirtual Method java/lang/StringBuilder insert (ILjava/lang/String;)Ljava/lang/StringBuilder;
L233:   ldc_w "st"
L236:   invokevirtual Method java/lang/StringBuilder append (Ljava/lang/String;)Ljava/lang/StringBuilder;
L239:   invokevirtual Method java/lang/StringBuilder toString ()Ljava/lang/String;
L242:   invokestatic Method JB method831 (Ljava/lang/String;)I
L245:   istore_2
L246:   aload_1
L247:   instanceof Af
L250:   ifeq L287
L253:   new java/lang/StringBuilder
L256:   dup
L257:   invokespecial Method java/lang/StringBuilder <init> ()V
L260:   iconst_0
L261:   aload_0
L262:   getfield Field Rg false Led;
L265:   getfield Field ed field711 LPc;
L268:   getfield Field Pc field370 Ljava/lang/String;
L271:   invokevirtual Method java/lang/StringBuilder insert (ILjava/lang/String;)Ljava/lang/StringBuilder;
L274:   ldc_w "sz"
L277:   invokevirtual Method java/lang/StringBuilder append (Ljava/lang/String;)Ljava/lang/StringBuilder;
L280:   invokevirtual Method java/lang/StringBuilder toString ()Ljava/lang/String;
L283:   invokestatic Method JB method831 (Ljava/lang/String;)I
L286:   istore_2
L287:   iconst_0
L288:   iconst_1
L289:   dup
L290:   pop2
L291:   dup
L292:   istore_3
L293:   iload_2
L294:   if_icmpge L309
L297:   iinc 3 1
L300:   aload_1
L301:   invokevirtual Method ff method74 ()V
L304:   iload_3
L305:   goto L293
L308:   athrow
L309:   aload_1
L310:   areturn
L311:   
        .attribute StackMap b'\x00\x0A\x00\x46\x00\x03\x07\x00\x02\x07\x00\xE0\x01\x00\x00\x00\x6F\x00\x03\x07\x00\x02\x07\x00\xE0\x01\x00\x00\x00\x98\x00\x03\x07\x00\x02\x07\x00\xE0\x01\x00\x00\x00\xA4\x00\x03\x07\x00\x02\x07\x00\xE0\x01\x00\x00\x00\xCD\x00\x03\x07\x00\x02\x07\x00\xE0\x01\x00\x00\x00\xF6\x00\x03\x07\x00\x02\x07\x00\xE0\x01\x00\x00\x01\x1F\x00\x03\x07\x00\x02\x07\x00\xE0\x01\x00\x00\x01\x25\x00\x04\x07\x00\x02\x07\x00\xE0\x01\x01\x00\x01\x01\x01\x34\x00\x00\x00\x01\x07\x00\x5B\x01\x35\x00\x04\x07\x00\x02\x07\x00\xE0\x01\x01\x00\x00'
    .end code
.end method

.method public method229 : (LRg;)I
    .code stack 3 locals 2
L0:     aload_0
L1:     invokevirtual Method Rg method94 ()Z
L4:     ifeq L20
L7:     aload_1
L8:     invokevirtual Method Rg method94 ()Z
L11:    ifne L20
L14:    iconst_m1
L15:    iconst_1
L16:    dup
L17:    pop2
L18:    ireturn
L19:    athrow
L20:    aload_0
L21:    invokevirtual Method Rg method94 ()Z
L24:    ifne L40
L27:    aload_1
L28:    invokevirtual Method Rg method94 ()Z
L31:    ifeq L40
L34:    iconst_1
L35:    dup
L36:    dup
L37:    pop2
L38:    ireturn
L39:    athrow
L40:    aload_0
L41:    invokevirtual Method Rg method132 ()I
L44:    aload_1
L45:    invokevirtual Method Rg method132 ()I
L48:    if_icmple L56
L51:    iconst_m1
L52:    iconst_1
L53:    dup
L54:    pop2
L55:    ireturn
L56:    aload_1
L57:    invokevirtual Method Rg method132 ()I
L60:    aload_0
L61:    invokevirtual Method Rg method132 ()I
L64:    if_icmple L72
L67:    iconst_1
L68:    dup
L69:    dup
L70:    pop2
L71:    ireturn
L72:    aload_0
L73:    getfield Field Rg false Led;
L76:    getfield Field ed field701 Ljava/lang/String;
L79:    aload_1
L80:    getfield Field Rg false Led;
L83:    getfield Field ed field701 Ljava/lang/String;
L86:    invokevirtual Method java/lang/String compareTo (Ljava/lang/String;)I
L89:    ireturn
L90:    
        .attribute StackMap b'\x00\x06\x00\x13\x00\x00\x00\x01\x07\x00\x5B\x00\x14\x00\x02\x07\x00\x02\x07\x00\x02\x00\x00\x00\x27\x00\x00\x00\x01\x07\x00\x5B\x00\x28\x00\x02\x07\x00\x02\x07\x00\x02\x00\x00\x00\x38\x00\x02\x07\x00\x02\x07\x00\x02\x00\x00\x00\x48\x00\x02\x07\x00\x02\x07\x00\x02\x00\x00'
    .end code
.end method

.method public method230 : ()J
    .code stack 6 locals 1
L0:     aload_0
L1:     getfield Field Rg field225 I
L4:     i2l
L5:     ldc2_w 8L
L8:     lmul
L9:     aload_0
L10:    getfield Field Rg field240 D
L13:    invokestatic Method java/lang/Double doubleToLongBits (D)J
L16:    lxor
L17:    aload_0
L18:    getfield Field Rg field222 I
L21:    i2l
L22:    ldc2_w 7L
L25:    lmul
L26:    lxor
L27:    aload_0
L28:    getfield Field Rg field232 I
L31:    i2l
L32:    ldc2_w 15L
L35:    lmul
L36:    lxor
L37:    aload_0
L38:    getfield Field Rg field213 I
L41:    i2l
L42:    ldc2_w 21L
L45:    lmul
L46:    lxor
L47:    aload_0
L48:    getfield Field Rg field241 F
L51:    invokestatic Method java/lang/Float floatToIntBits (F)I
L54:    i2l
L55:    ldc2_w 57L
L58:    lmul
L59:    lxor
L60:    aload_0
L61:    getfield Field Rg field230 I
L64:    i2l
L65:    ldc2_w 27L
L68:    lmul
L69:    lxor
L70:    aload_0
L71:    getfield Field Rg field218 I
L74:    i2l
L75:    ldc2_w 29L
L78:    lmul
L79:    lxor
L80:    aload_0
L81:    getfield Field Rg true I
L84:    i2l
L85:    ldc2_w 31L
L88:    lmul
L89:    lxor
L90:    aload_0
L91:    getfield Field Rg field236 I
L94:    i2l
L95:    ldc2_w 35L
L98:    lmul
L99:    lxor
L100:   aload_0
L101:   getfield Field Rg field215 F
L104:   invokestatic Method java/lang/Float floatToIntBits (F)I
L107:   i2l
L108:   ldc2_w 53L
L111:   lmul
L112:   lxor
L113:   aload_0
L114:   getfield Field Rg field228 I
L117:   i2l
L118:   ldc2_w 41L
L121:   lmul
L122:   lxor
L123:   aload_0
L124:   getfield Field Rg field219 F
L127:   invokestatic Method java/lang/Float floatToIntBits (F)I
L130:   i2l
L131:   ldc2_w 47L
L134:   lmul
L135:   lxor
L136:   aload_0
L137:   getfield Field Rg field226 F
L140:   invokestatic Method java/lang/Float floatToIntBits (F)I
L143:   i2l
L144:   ldc2_w 51L
L147:   lmul
L148:   lxor
L149:   lreturn
L150:   
    .end code
.end method

.method private method84 : ()V
    .code stack 4 locals 2
L0:     aload_0
L1:     dup
L2:     fconst_0
L3:     putfield Field Rg field212 F
L6:     getfield Field Rg field234 Ljava/util/LinkedList;
L9:     invokevirtual Method java/util/LinkedList size ()I
L12:    iconst_1
L13:    dup
L14:    dup
L15:    pop2
L16:    if_icmple L76
L19:    aload_0
L20:    dup
L21:    getfield Field Rg field241 F
L24:    swap
L25:    getfield Field Rg field234 Ljava/util/LinkedList;
L28:    invokevirtual Method java/util/LinkedList getFirst ()Ljava/lang/Object;
L31:    checkcast java/lang/Float
L34:    invokevirtual Method java/lang/Float floatValue ()F
L37:    fsub
L38:    aload_0
L39:    getfield Field Rg field234 Ljava/util/LinkedList;
L42:    invokevirtual Method java/util/LinkedList size ()I
L45:    i2f
L46:    fdiv
L47:    dup
L48:    fstore_1
L49:    fconst_0
L50:    fcmpl
L51:    ifle L76
L54:    ldc_w 6e1f
L57:    fload_1
L58:    fdiv
L59:    aload_0
L60:    dup_x1
L61:    getfield Field Rg field234 Ljava/util/LinkedList;
L64:    invokevirtual Method java/util/LinkedList size ()I
L67:    i2f
L68:    ldc_w 1e1f
L71:    fdiv
L72:    fmul
L73:    putfield Field Rg field212 F
L76:    aload_0
L77:    dup
L78:    getfield Field Rg field212 F
L81:    swap
L82:    getfield Field Rg field219 F
L85:    fcmpl
L86:    ifle L97
L89:    aload_0
L90:    dup
L91:    getfield Field Rg field212 F
L94:    putfield Field Rg field219 F
L97:    return
L98:    
        .attribute StackMap b'\x00\x02\x00\x4C\x00\x01\x07\x00\x02\x00\x00\x00\x61\x00\x01\x07\x00\x02\x00\x00'
    .end code
.end method

.method public method231 : (LF;)V
    .code stack 2 locals 2
L0:     aload_0
L1:     getfield Field Rg field220 Ljava/util/List;
L4:     aload_1
L5:     invokeinterface InterfaceMethod java/util/List remove (Ljava/lang/Object;)Z 2
L10:    pop
L11:    return
L12:    
    .end code
.end method

.method public method232 : (LsE;)V
    .code stack 3 locals 2
L0:     aload_0
L1:     dup
L2:     aload_1
L3:     putfield Field Rg field231 LsE;
L6:     getfield Field Rg field220 Ljava/util/List;
L9:     invokeinterface InterfaceMethod java/util/List iterator ()Ljava/util/Iterator; 1
L14:    dup
L15:    astore_1
L16:    invokeinterface InterfaceMethod java/util/Iterator hasNext ()Z 1
L21:    ifeq L43
L24:    aload_1
L25:    invokeinterface InterfaceMethod java/util/Iterator next ()Ljava/lang/Object; 1
L30:    checkcast F
L33:    invokeinterface InterfaceMethod F method76 ()V 1
L38:    aload_1
L39:    goto L16
L42:    athrow
L43:    return
L44:    
        .attribute StackMap b'\x00\x03\x00\x10\x00\x02\x07\x00\x02\x07\x00\x9D\x00\x01\x07\x00\x9D\x00\x2A\x00\x00\x00\x01\x07\x00\x5B\x00\x2B\x00\x02\x07\x00\x02\x07\x00\x9D\x00\x00'
    .end code
.end method

.method public <init> : (Led;Lqd;Ljava/util/List;)V
    .code stack 21 locals 4
L0:     aload_0
L1:     dup
L2:     aconst_null
L3:     aload_0
L4:     dup
L5:     dup_x2
L6:     aload_3
L7:     iconst_0
L8:     aload_0
L9:     dup_x1
L10:    dup
L11:    dup_x2
L12:    aload_1
L13:    aload_0
L14:    dup_x1
L15:    dup_x2
L16:    aload_2
L17:    aload_0
L18:    dup
L19:    dup2
L20:    invokespecial Method java/lang/Object <init> ()V
L23:    invokevirtual Method Rg method230 ()J
L26:    putfield Field Rg package J
L29:    new java/util/concurrent/CopyOnWriteArrayList
L32:    aload_0
L33:    dup
L34:    pop2
L35:    dup
L36:    invokespecial Method java/util/concurrent/CopyOnWriteArrayList <init> ()V
L39:    putfield Field Rg field220 Ljava/util/List;
L42:    putfield Field Rg field239 Lqd;
L45:    putfield Field Rg false Led;
L48:    new java/util/LinkedList
L51:    aload_0
L52:    dup
L53:    pop2
L54:    dup
L55:    invokespecial Method java/util/LinkedList <init> ()V
L58:    putfield Field Rg field235 Ljava/util/LinkedList;
L61:    invokestatic Method bD method392 ()LbD;
L64:    putfield Field Rg field217 LbD;
L67:    new java/util/HashMap
L70:    aload_0
L71:    dup
L72:    pop2
L73:    dup
L74:    invokespecial Method java/util/HashMap <init> ()V
L77:    putfield Field Rg while Ljava/util/Map;
L80:    iconst_1
L81:    dup
L82:    pop2
L83:    invokespecial Method Rg method238 (Z)V
L86:    new java/util/LinkedList
L89:    aload_0
L90:    dup_x2
L91:    dup
L92:    pop2
L93:    dup
L94:    invokespecial Method java/util/LinkedList <init> ()V
L97:    putfield Field Rg field234 Ljava/util/LinkedList;
L100:   getfield Field Rg field239 Lqd;
L103:   getfield Field qd field761 Leb;
L106:   aload_0
L107:   invokevirtual Method eb method754 (LRg;)V
L110:   putfield Field Rg field211 Ljava/util/List;
L113:   getfield Field Rg field239 Lqd;
L116:   aload_0
L117:   getstatic Field mc field386 Lmc;
L120:   invokevirtual Method qd method408 (LG;Lmc;)V
L123:   putfield Field Rg field231 LsE;
L126:   new java/util/Random
L129:   aload_0
L130:   dup_x2
L131:   dup
L132:   pop2
L133:   dup
L134:   invokespecial Method java/util/Random <init> ()V
L137:   invokevirtual Method java/util/Random nextLong ()J
L140:   invokevirtual Method Rg method234 (J)V
L143:   invokestatic Method ib method1156 (LM;)V
L146:   getstatic Field qE try LqE;
L149:   invokevirtual Method Rg method226 (LqE;)V
L152:   return
L153:   
    .end code
.end method

.method private method233 : ([[ILff;[I)Ljava/util/List;
    .code stack 5 locals 7
L0:     new java/util/LinkedList
L3:     dup
L4:     invokespecial Method java/util/LinkedList <init> ()V
L7:     astore 4
L9:     aload_0
L10:    getfield Field Rg field211 Ljava/util/List;
L13:    invokeinterface InterfaceMethod java/util/List iterator ()Ljava/util/Iterator; 1
L18:    astore 5
L20:    aload 5
L22:    invokeinterface InterfaceMethod java/util/Iterator hasNext ()Z 1
L27:    ifeq L67
L30:    aload 5
L32:    invokeinterface InterfaceMethod java/util/Iterator next ()Ljava/lang/Object; 1
L37:    checkcast Uf
L40:    dup
L41:    astore 6
L43:    aload_0
L44:    aload_1
L45:    aload_2
L46:    aload_3
L47:    invokevirtual Method Uf method699 (LRg;[[ILff;[I)Z
L50:    ifeq L20
L53:    aload 4
L55:    aload 6
L57:    invokeinterface InterfaceMethod java/util/List add (Ljava/lang/Object;)Z 2
L62:    pop
L63:    goto L20
L66:    athrow
L67:    aload_0
L68:    getfield Field Rg field211 Ljava/util/List;
L71:    aload 4
L73:    invokeinterface InterfaceMethod java/util/List removeAll (Ljava/util/Collection;)Z 2
L78:    pop
L79:    aload 4
L81:    areturn
L82:    
        .attribute StackMap b'\x00\x03\x00\x14\x00\x06\x07\x00\x02\x07\x00\xAE\x07\x00\xE0\x07\x01\xBB\x07\x00\x6D\x07\x00\x9D\x00\x00\x00\x42\x00\x00\x00\x01\x07\x00\x5B\x00\x43\x00\x06\x07\x00\x02\x07\x00\xAE\x07\x00\xE0\x07\x01\xBB\x07\x00\x6D\x07\x00\x9D\x00\x00'
    .end code
.end method

.method public method95 : (Z)V
    .code stack 0 locals 2
L0:     return
L1:     
    .end code
.end method

.method public new : ()I
    .code stack 3 locals 1
L0:     aload_0
L1:     getfield Field Rg field239 Lqd;
L4:     getfield Field qd field766 Ljava/util/Map;
L7:     aload_0
L8:     invokeinterface InterfaceMethod java/util/Map containsKey (Ljava/lang/Object;)Z 2
L13:    ifne L22
L16:    iconst_0
L17:    iconst_1
L18:    dup
L19:    pop2
L20:    ireturn
L21:    athrow
L22:    aload_0
L23:    getfield Field Rg field239 Lqd;
L26:    getfield Field qd field766 Ljava/util/Map;
L29:    aload_0
L30:    invokeinterface InterfaceMethod java/util/Map get (Ljava/lang/Object;)Ljava/lang/Object; 2
L35:    checkcast java/lang/Integer
L38:    invokevirtual Method java/lang/Integer intValue ()I
L41:    ireturn
L42:    
        .attribute StackMap b'\x00\x02\x00\x15\x00\x00\x00\x01\x07\x00\x5B\x00\x16\x00\x01\x07\x00\x02\x00\x00'
    .end code
.end method

.method public method8 : (LD;)V
    .code stack 4 locals 3
L0:     aload_1
L1:     instanceof gC
L4:     ifeq L29
L7:     aload_1
L8:     checkcast gC
L11:    dup
L12:    astore_2
L13:    getfield Field gC field872 Led;
L16:    aload_0
L17:    getfield Field Rg false Led;
L20:    if_acmpne L388
L23:    aload_0
L24:    invokevirtual Method Rg method52 ()V
L27:    return
L28:    athrow
L29:    aload_1
L30:    instanceof fc
L33:    ifeq L203
L36:    aload_1
L37:    checkcast fc
L40:    astore_2
L41:    getstatic Field XE field2163 [I
L44:    aload_2
L45:    getfield Field fc field876 Loc;
L48:    invokevirtual Method oc ordinal ()I
L51:    iaload
L52:    tableswitch 1
            L108
            L134
            L153
            L202
            L202
            L202
            L202
            L202
            L202
            L202
            default : L202
L108:   aload_0
L109:   iconst_0
L110:   ifne L199
L113:   getfield Field Rg while Ljava/util/Map;
L116:   getstatic Field wD try LwD;
L119:   getstatic Field wD try LwD;
L122:   aload_0
L123:   invokevirtual Method wD method306 (LRg;)Ljava/lang/Object;
L126:   invokeinterface InterfaceMethod java/util/Map put (Ljava/lang/Object;Ljava/lang/Object;)Ljava/lang/Object; 3
L131:   pop
L132:   return
L133:   athrow
L134:   aload_2
L135:   getfield Field fc field875 Led;
L138:   aload_0
L139:   getfield Field Rg false Led;
L142:   if_acmpne L388
L145:   aload_0
L146:   getstatic Field qE field628 LqE;
L149:   invokevirtual Method Rg method226 (LqE;)V
L152:   return
L153:   aload_2
L154:   getfield Field fc field875 Led;
L157:   aload_0
L158:   getfield Field Rg false Led;
L161:   if_acmpne L388
L164:   aload_0
L165:   getfield Field Rg field239 Lqd;
L168:   getfield Field qd field763 LQB;
L171:   getstatic Field QB field367 LQB;
L174:   if_acmpeq L190
L177:   aload_0
L178:   getfield Field Rg field239 Lqd;
L181:   getfield Field qd field763 LQB;
L184:   getstatic Field QB field366 LQB;
L187:   if_acmpne L388
L190:   aload_0
L191:   aload_2
L192:   getfield Field fc field873 LsE;
L195:   invokevirtual Method Rg method232 (LsE;)V
L198:   return
L199:   goto L109
L202:   return
L203:   aload_1
L204:   instanceof Td
L207:   ifeq L215
L210:   aload_0
L211:   invokevirtual Method Rg method52 ()V
L214:   return
L215:   aload_1
L216:   instanceof qD
L219:   ifeq L276
L222:   aload_0
L223:   instanceof Mg
L226:   ifne L388
L229:   aload_1
L230:   checkcast qD
L233:   dup
L234:   astore_2
L235:   getfield Field qD field945 Led;
L238:   aload_0
L239:   getfield Field Rg false Led;
L242:   if_acmpne L388
L245:   aload_0
L246:   getfield Field Rg field227 LqE;
L249:   getstatic Field qE field628 LqE;
L252:   if_acmpne L388
L255:   aload_0
L256:   getfield Field Rg field239 Lqd;
L259:   getfield Field qd field763 LQB;
L262:   getstatic Field QB field368 LQB;
L265:   if_acmpne L388
L268:   aload_0
L269:   getstatic Field qE field626 LqE;
L272:   invokevirtual Method Rg method226 (LqE;)V
L275:   return
L276:   aload_1
L277:   instanceof uE
L280:   ifeq L318
L283:   aload_1
L284:   checkcast uE
L287:   dup
L288:   astore_2
L289:   getfield Field uE field941 Led;
L292:   aload_0
L293:   getfield Field Rg false Led;
L296:   if_acmpne L388
L299:   aload_0
L300:   getfield Field Rg field227 LqE;
L303:   getstatic Field qE this LqE;
L306:   if_acmpne L388
L309:   aload_0
L310:   aload_2
L311:   getfield Field uE field942 I
L314:   invokespecial Method Rg method14 (I)V
L317:   return
L318:   aload_1
L319:   instanceof xC
L322:   ifeq L388
L325:   aload_1
L326:   checkcast xC
L329:   astore_2
L330:   getstatic Field XE field2165 [I
L333:   aload_2
L334:   getfield Field xC field888 LQB;
L337:   invokevirtual Method QB ordinal ()I
L340:   iaload
L341:   tableswitch 1
            L372
            L388
            L388
            L388
            default : L388
L372:   aload_0
L373:   iconst_0
L374:   ifne L385
L377:   iconst_1
L378:   dup
L379:   dup
L380:   pop2
L381:   invokespecial Method Rg method238 (Z)V
L384:   return
L385:   goto L373
L388:   return
L389:   
        .attribute StackMap b'\x00\x12\x00\x1C\x00\x00\x00\x01\x07\x00\x5B\x00\x1D\x00\x02\x07\x00\x02\x07\x01\xE0\x00\x00\x00\x6C\x00\x03\x07\x00\x02\x07\x01\xE0\x07\x00\x1C\x00\x00\x00\x6D\x00\x03\x07\x00\x02\x07\x01\xE0\x07\x00\x1C\x00\x01\x07\x00\x02\x00\x85\x00\x00\x00\x01\x07\x00\x5B\x00\x86\x00\x03\x07\x00\x02\x07\x01\xE0\x07\x00\x1C\x00\x00\x00\x99\x00\x03\x07\x00\x02\x07\x01\xE0\x07\x00\x1C\x00\x00\x00\xBE\x00\x03\x07\x00\x02\x07\x01\xE0\x07\x00\x1C\x00\x00\x00\xC7\x00\x03\x07\x00\x02\x07\x01\xE0\x07\x00\x1C\x00\x01\x07\x00\x02\x00\xCA\x00\x03\x07\x00\x02\x07\x01\xE0\x07\x00\x1C\x00\x00\x00\xCB\x00\x02\x07\x00\x02\x07\x01\xE0\x00\x00\x00\xD7\x00\x02\x07\x00\x02\x07\x01\xE0\x00\x00\x01\x14\x00\x02\x07\x00\x02\x07\x01\xE0\x00\x00\x01\x3E\x00\x02\x07\x00\x02\x07\x01\xE0\x00\x00\x01\x74\x00\x03\x07\x00\x02\x07\x01\xE0\x07\x02\x24\x00\x00\x01\x75\x00\x03\x07\x00\x02\x07\x01\xE0\x07\x02\x24\x00\x01\x07\x00\x02\x01\x81\x00\x03\x07\x00\x02\x07\x01\xE0\x07\x02\x24\x00\x01\x07\x00\x02\x01\x84\x00\x02\x07\x00\x02\x07\x01\xE0\x00\x00'
    .end code
.end method

.method public method87 : (Led;I[I)V
    .code stack 4 locals 5
L0:     aload_0
L1:     getfield Field Rg field220 Ljava/util/List;
L4:     invokeinterface InterfaceMethod java/util/List iterator ()Ljava/util/Iterator; 1
L9:     dup
L10:    astore 4
L12:    invokeinterface InterfaceMethod java/util/Iterator hasNext ()Z 1
L17:    ifeq L44
L20:    aload 4
L22:    invokeinterface InterfaceMethod java/util/Iterator next ()Ljava/lang/Object; 1
L27:    checkcast F
L30:    aload_1
L31:    iload_2
L32:    aload_3
L33:    invokeinterface InterfaceMethod F method87 (Led;I[I)V 4
L38:    aload 4
L40:    goto L12
L43:    athrow
L44:    return
L45:    
        .attribute StackMap b'\x00\x03\x00\x0C\x00\x05\x07\x00\x02\x07\x00\xEF\x01\x07\x01\xBB\x07\x00\x9D\x00\x01\x07\x00\x9D\x00\x2B\x00\x00\x00\x01\x07\x00\x5B\x00\x2C\x00\x05\x07\x00\x02\x07\x00\xEF\x01\x07\x01\xBB\x07\x00\x9D\x00\x00'
    .end code
.end method

.method private method14 : (I)V
    .code stack 9 locals 5
L0:     iload_1
L1:     ifne L6
L4:     return
L5:     athrow
L6:     aload_0
L7:     dup
L8:     iconst_0
L9:     aload_0
L10:    dup
L11:    dup_x2
L12:    iconst_1
L13:    dup
L14:    dup
L15:    pop2
L16:    invokevirtual Method Rg method95 (Z)V
L19:    dup
L20:    getfield Field Rg field213 I
L23:    iload_1
L24:    iadd
L25:    putfield Field Rg field213 I
L28:    iconst_1
L29:    dup
L30:    pop2
L31:    invokevirtual Method Rg method95 (Z)V
L34:    getfield Field Rg field239 Lqd;
L37:    getfield Field qd field761 Leb;
L40:    aload_0
L41:    dup_x1
L42:    getfield Field Rg field239 Lqd;
L45:    invokevirtual Method eb method758 (Lqd;)F
L48:    fstore_2
L49:    getfield Field Rg field241 F
L52:    aload_0
L53:    getfield Field Rg field239 Lqd;
L56:    getfield Field qd field761 Leb;
L59:    aload_0
L60:    getfield Field Rg field239 Lqd;
L63:    invokevirtual Method eb method764 (Lqd;)F
L66:    fadd
L67:    fstore_3
L68:    getfield Field Rg field235 Ljava/util/LinkedList;
L71:    invokevirtual Method java/util/LinkedList isEmpty ()Z
L74:    ifne L97
L77:    fload_3
L78:    aload_0
L79:    getfield Field Rg field235 Ljava/util/LinkedList;
L82:    invokevirtual Method java/util/LinkedList getLast ()Ljava/lang/Object;
L85:    checkcast java/lang/Float
L88:    invokevirtual Method java/lang/Float floatValue ()F
L91:    fload_2
L92:    fadd
L93:    invokestatic Method java/lang/Math max (FF)F
L96:    fstore_3
L97:    iconst_0
L98:    iconst_1
L99:    dup
L100:   pop2
L101:   dup
L102:   istore 4
L104:   iload_1
L105:   if_icmpge L135
L108:   aload_0
L109:   getfield Field Rg field235 Ljava/util/LinkedList;
L112:   fload_3
L113:   iload 4
L115:   i2f
L116:   fload_2
L117:   fmul
L118:   iinc 4 1
L121:   fadd
L122:   invokestatic Method java/lang/Float valueOf (F)Ljava/lang/Float;
L125:   invokevirtual Method java/util/LinkedList add (Ljava/lang/Object;)Z
L128:   pop
L129:   iload 4
L131:   goto L104
L134:   athrow
L135:   aload_0
L136:   getfield Field Rg field220 Ljava/util/List;
L139:   invokeinterface InterfaceMethod java/util/List iterator ()Ljava/util/Iterator; 1
L144:   dup
L145:   astore 4
L147:   invokeinterface InterfaceMethod java/util/Iterator hasNext ()Z 1
L152:   ifeq L175
L155:   aload 4
L157:   invokeinterface InterfaceMethod java/util/Iterator next ()Ljava/lang/Object; 1
L162:   checkcast F
L165:   invokeinterface InterfaceMethod F method74 ()V 1
L170:   aload 4
L172:   goto L147
L175:   return
L176:   
        .attribute StackMap b'\x00\x08\x00\x05\x00\x00\x00\x01\x07\x00\x5B\x00\x06\x00\x02\x07\x00\x02\x01\x00\x00\x00\x61\x00\x04\x07\x00\x02\x01\x02\x02\x00\x00\x00\x68\x00\x05\x07\x00\x02\x01\x02\x02\x01\x00\x01\x01\x00\x86\x00\x00\x00\x01\x07\x00\x5B\x00\x87\x00\x05\x07\x00\x02\x01\x02\x02\x01\x00\x00\x00\x93\x00\x05\x07\x00\x02\x01\x02\x02\x07\x00\x9D\x00\x01\x07\x00\x9D\x00\xAF\x00\x05\x07\x00\x02\x01\x02\x02\x07\x00\x9D\x00\x00'
    .end code
.end method

.method public try : ()V
    .code stack 8 locals 1
L0:     aload_0
L1:     dup
L2:     iconst_1
L3:     dup
L4:     dup
L5:     pop2
L6:     invokevirtual Method Rg method95 (Z)V
L9:     getfield Field Rg field235 Ljava/util/LinkedList;
L12:    invokevirtual Method java/util/LinkedList isEmpty ()Z
L15:    ifne L76
L18:    aload_0
L19:    getfield Field Rg field235 Ljava/util/LinkedList;
L22:    invokevirtual Method java/util/LinkedList getFirst ()Ljava/lang/Object;
L25:    checkcast java/lang/Float
L28:    invokevirtual Method java/lang/Float floatValue ()F
L31:    aload_0
L32:    getfield Field Rg field241 F
L35:    fcmpg
L36:    ifgt L76
L39:    aload_0
L40:    getfield Field Rg field235 Ljava/util/LinkedList;
L43:    invokevirtual Method java/util/LinkedList removeFirst ()Ljava/lang/Object;
L46:    aload_0
L47:    dup
L48:    dup_x2
L49:    dup
L50:    getfield Field Rg field218 I
L53:    iconst_1
L54:    dup
L55:    dup
L56:    pop2
L57:    iadd
L58:    putfield Field Rg field218 I
L61:    getfield Field Rg field239 Lqd;
L64:    getfield Field qd field761 Leb;
L67:    aload_0
L68:    invokevirtual Method eb method762 (LRg;)V
L71:    pop
L72:    goto L9
L75:    athrow
L76:    aload_0
L77:    iconst_0
L78:    iconst_1
L79:    dup
L80:    pop2
L81:    invokevirtual Method Rg method95 (Z)V
L84:    return
L85:    
        .attribute StackMap b'\x00\x03\x00\x09\x00\x01\x07\x00\x02\x00\x01\x07\x00\x02\x00\x4B\x00\x00\x00\x01\x07\x00\x5B\x00\x4C\x00\x01\x07\x00\x02\x00\x00'
    .end code
.end method

.method public this : ()V
    .code stack 4 locals 1
L0:     new ng
L3:     aload_0
L4:     dup
L5:     pop2
L6:     dup
L7:     aload_0
L8:     dup_x2
L9:     invokespecial Method ng <init> (LRg;)V
L12:    invokevirtual Method Rg method235 (LF;)V
L15:    return
L16:    
    .end code
.end method

.method public method234 : (J)V
    .code stack 8 locals 3
L0:     bipush 7
L2:     aload_0
L3:     dup_x1
L4:     dup_x2
L5:     new java/util/Random
L8:     aload_0
L9:     dup
L10:    pop2
L11:    dup
L12:    lload_1
L13:    invokespecial Method java/util/Random <init> (J)V
L16:    putfield Field Rg field216 Ljava/util/Random;
L19:    iconst_1
L20:    dup
L21:    pop2
L22:    newarray double
L24:    iconst_1
L25:    dup
L26:    pop2
L27:    putfield Field Rg field214 [D
L30:    new java/util/Random
L33:    aload_0
L34:    dup
L35:    pop2
L36:    dup
L37:    lload_1
L38:    invokespecial Method java/util/Random <init> (J)V
L41:    putfield Field Rg new Ljava/util/Random;
L44:    return
L45:    
    .end code
.end method

.method public method235 : (LF;)V
    .code stack 2 locals 2
L0:     aload_0
L1:     getfield Field Rg field220 Ljava/util/List;
L4:     aload_1
L5:     invokeinterface InterfaceMethod java/util/List add (Ljava/lang/Object;)Z 2
L10:    pop
L11:    return
L12:    
    .end code
.end method

.method public method236 : (II)V
    .code stack 7 locals 5
L0:     iconst_0
L1:     iconst_1
L2:     dup
L3:     pop2
L4:     dup
L5:     istore_3
L6:     bipush 27
L8:     iconst_1
L9:     dup
L10:    pop2
L11:    if_icmpge L69
L14:    iconst_0
L15:    iconst_1
L16:    dup
L17:    pop2
L18:    dup
L19:    istore 4
L21:    bipush 10
L23:    iconst_1
L24:    dup
L25:    pop2
L26:    if_icmpge L61
L29:    aload_0
L30:    getfield Field Rg this [[I
L33:    iload 4
L35:    aaload
L36:    aload_0
L37:    getfield Field Rg this [[I
L40:    iload 4
L42:    aaload
L43:    iload_3
L44:    dup_x1
L45:    iconst_1
L46:    dup
L47:    dup
L48:    pop2
L49:    iadd
L50:    iaload
L51:    iinc 4 1
L54:    iastore
L55:    iload 4
L57:    goto L21
L60:    athrow
L61:    iinc 3 1
L64:    iload_3
L65:    goto L6
L68:    athrow
L69:    iconst_0
L70:    iconst_1
L71:    dup
L72:    pop2
L73:    dup
L74:    istore_3
L75:    bipush 10
L77:    iconst_1
L78:    dup
L79:    pop2
L80:    if_icmpge L115
L83:    aload_0
L84:    getfield Field Rg this [[I
L87:    iload_3
L88:    aaload
L89:    bipush 27
L91:    iconst_1
L92:    dup
L93:    pop2
L94:    iload_3
L95:    iload_1
L96:    if_icmpne L106
L99:    iconst_0
L100:   iconst_1
L101:   dup
L102:   pop2
L103:   goto L107
L106:   iload_2
L107:   iastore
L108:   iinc 3 1
L111:   iload_3
L112:   goto L75
L115:   aload_0
L116:   dup
L117:   getfield Field Rg field221 Lff;
L120:   dup
L121:   getfield Field ff field881 I
L124:   iconst_1
L125:   dup
L126:   dup
L127:   pop2
L128:   isub
L129:   putfield Field ff field881 I
L132:   getfield Field Rg field221 Lff;
L135:   getfield Field ff field881 I
L138:   ifge L152
L141:   aload_0
L142:   getfield Field Rg field221 Lff;
L145:   iconst_0
L146:   iconst_1
L147:   dup
L148:   pop2
L149:   putfield Field ff field881 I
L152:   aload_0
L153:   dup
L154:   getfield Field Rg this [[I
L157:   invokestatic Method hE method1143 ([[I)V
L160:   getfield Field Rg field220 Ljava/util/List;
L163:   invokeinterface InterfaceMethod java/util/List iterator ()Ljava/util/Iterator; 1
L168:   dup
L169:   astore_3
L170:   invokeinterface InterfaceMethod java/util/Iterator hasNext ()Z 1
L175:   ifeq L216
L178:   aload_3
L179:   invokeinterface InterfaceMethod java/util/Iterator next ()Ljava/lang/Object; 1
L184:   checkcast F
L187:   astore 4
L189:   aload_3
L190:   aload 4
L192:   iload_1
L193:   iload_2
L194:   aload_0
L195:   getfield Field Rg field239 Lqd;
L198:   getfield Field qd field761 Leb;
L201:   aload_0
L202:   getfield Field Rg field239 Lqd;
L205:   invokevirtual Method eb method758 (Lqd;)F
L208:   invokeinterface InterfaceMethod F method73 (IIF)V 4
L213:   goto L170
L216:   return
L217:   
        .attribute StackMap b'\x00\x0D\x00\x06\x00\x04\x07\x00\x02\x01\x01\x01\x00\x01\x01\x00\x15\x00\x05\x07\x00\x02\x01\x01\x01\x01\x00\x01\x01\x00\x3C\x00\x00\x00\x01\x07\x00\x5B\x00\x3D\x00\x05\x07\x00\x02\x01\x01\x01\x01\x00\x00\x00\x44\x00\x00\x00\x01\x07\x00\x5B\x00\x45\x00\x04\x07\x00\x02\x01\x01\x01\x00\x00\x00\x4B\x00\x04\x07\x00\x02\x01\x01\x01\x00\x01\x01\x00\x6A\x00\x04\x07\x00\x02\x01\x01\x01\x00\x02\x07\x01\xBB\x01\x00\x6B\x00\x04\x07\x00\x02\x01\x01\x01\x00\x03\x07\x01\xBB\x01\x01\x00\x73\x00\x04\x07\x00\x02\x01\x01\x01\x00\x00\x00\x98\x00\x04\x07\x00\x02\x01\x01\x01\x00\x00\x00\xAA\x00\x04\x07\x00\x02\x01\x01\x07\x00\x9D\x00\x01\x07\x00\x9D\x00\xD8\x00\x04\x07\x00\x02\x01\x01\x07\x00\x9D\x00\x00'
    .end code
.end method

.method public method237 : ()I
    .code stack 4 locals 5
L0:     iconst_0
L1:     iconst_1
L2:     dup
L3:     pop2
L4:     istore_1
L5:     iconst_0
L6:     iconst_1
L7:     dup
L8:     pop2
L9:     dup
L10:    istore_2
L11:    bipush 28
L13:    iconst_1
L14:    dup
L15:    pop2
L16:    if_icmpge L95
L19:    iconst_0
L20:    iconst_1
L21:    dup
L22:    pop2
L23:    istore_3
L24:    iconst_0
L25:    iconst_1
L26:    dup
L27:    pop2
L28:    dup
L29:    istore 4
L31:    bipush 10
L33:    iconst_1
L34:    dup
L35:    pop2
L36:    if_icmpge L81
L39:    aload_0
L40:    getfield Field Rg this [[I
L43:    iload 4
L45:    aaload
L46:    iload_2
L47:    iaload
L48:    bipush 31
L50:    iconst_1
L51:    dup
L52:    pop2
L53:    iand
L54:    bipush 13
L56:    iconst_1
L57:    dup
L58:    pop2
L59:    if_icmpne L72
L62:    iconst_1
L63:    dup
L64:    dup
L65:    pop2
L66:    dup
L67:    istore_3
L68:    goto L82
L71:    athrow
L72:    iinc 4 1
L75:    iload 4
L77:    goto L31
L80:    athrow
L81:    iload_3
L82:    ifeq L88
L85:    iinc 1 1
L88:    iinc 2 1
L91:    iload_2
L92:    goto L11
L95:    iload_1
L96:    ireturn
L97:    
        .attribute StackMap b'\x00\x09\x00\x0B\x00\x03\x07\x00\x02\x01\x01\x00\x01\x01\x00\x1F\x00\x05\x07\x00\x02\x01\x01\x01\x01\x00\x01\x01\x00\x47\x00\x00\x00\x01\x07\x00\x5B\x00\x48\x00\x05\x07\x00\x02\x01\x01\x01\x01\x00\x00\x00\x50\x00\x00\x00\x01\x07\x00\x5B\x00\x51\x00\x05\x07\x00\x02\x01\x01\x01\x01\x00\x00\x00\x52\x00\x05\x07\x00\x02\x01\x01\x01\x01\x00\x01\x01\x00\x58\x00\x05\x07\x00\x02\x01\x01\x01\x01\x00\x00\x00\x5F\x00\x03\x07\x00\x02\x01\x01\x00\x00'
    .end code
.end method

.method private method238 : (Z)V
    .code stack 4 locals 6
L0:     aload_0
L1:     getfield Field Rg while Ljava/util/Map;
L4:     invokeinterface InterfaceMethod java/util/Map clear ()V 1
L9:     invokestatic Method wD values ()[LwD;
L12:    dup
L13:    astore_2
L14:    arraylength
L15:    istore_3
L16:    iconst_0
L17:    iconst_1
L18:    dup
L19:    pop2
L20:    dup
L21:    istore 4
L23:    iload_3
L24:    if_icmpge L81
L27:    aload_2
L28:    iload 4
L30:    aaload
L31:    dup
L32:    astore 5
L34:    getfield Field wD field447 Z
L37:    ifne L55
L40:    iload_1
L41:    ifeq L72
L44:    aload_0
L45:    getfield Field Rg field239 Lqd;
L48:    aload_0
L49:    invokevirtual Method qd method412 (LRg;)Z
L52:    ifeq L72
L55:    aload_0
L56:    getfield Field Rg while Ljava/util/Map;
L59:    aload 5
L61:    dup
L62:    aload_0
L63:    invokevirtual Method wD method306 (LRg;)Ljava/lang/Object;
L66:    invokeinterface InterfaceMethod java/util/Map put (Ljava/lang/Object;Ljava/lang/Object;)Ljava/lang/Object; 3
L71:    pop
L72:    iinc 4 1
L75:    iload 4
L77:    goto L23
L80:    athrow
L81:    return
L82:    
        .attribute StackMap b'\x00\x05\x00\x17\x00\x05\x07\x00\x02\x01\x07\x02\x72\x01\x01\x00\x01\x01\x00\x37\x00\x06\x07\x00\x02\x01\x07\x02\x72\x01\x01\x07\x01\xEA\x00\x00\x00\x48\x00\x06\x07\x00\x02\x01\x07\x02\x72\x01\x01\x07\x01\xEA\x00\x00\x00\x50\x00\x00\x00\x01\x07\x00\x5B\x00\x51\x00\x05\x07\x00\x02\x01\x07\x02\x72\x01\x01\x00\x00'
    .end code
.end method

.method public method239 : (LFe;)V
    .code stack 5 locals 5
L0:     getstatic Field XE field2164 [I
L3:     aload_1
L4:     invokevirtual Method Fe ordinal ()I
L7:     iaload
L8:     tableswitch 1
            L52
            L120
            L182
            L249
            L257
            L257
            L257
            default : L708
L52:    aload_0
L53:    iconst_0
L54:    ifne L254
L57:    getfield Field Rg field221 Lff;
L60:    iconst_m1
L61:    iconst_1
L62:    dup
L63:    pop2
L64:    iconst_0
L65:    iconst_1
L66:    dup
L67:    pop2
L68:    aload_0
L69:    getfield Field Rg this [[I
L72:    invokevirtual Method ff method474 (II[[I)Z
L75:    ifeq L708
L78:    aload_0
L79:    getfield Field Rg field220 Ljava/util/List;
L82:    invokeinterface InterfaceMethod java/util/List iterator ()Ljava/util/Iterator; 1
L87:    dup
L88:    astore_2
L89:    invokeinterface InterfaceMethod java/util/Iterator hasNext ()Z 1
L94:    ifeq L708
L97:    aload_2
L98:    invokeinterface InterfaceMethod java/util/Iterator next ()Ljava/lang/Object; 1
L103:   checkcast F
L106:   astore_3
L107:   aload_2
L108:   aload_3
L109:   invokeinterface InterfaceMethod F method67 ()V 1
L114:   goto L89
L117:   nop
L118:   nop
L119:   athrow
L120:   aload_0
L121:   getfield Field Rg field221 Lff;
L124:   iconst_1
L125:   dup
L126:   pop2
L127:   iconst_0
L128:   iconst_1
L129:   dup_x1
L130:   dup
L131:   pop2
L132:   aload_0
L133:   getfield Field Rg this [[I
L136:   invokevirtual Method ff method474 (II[[I)Z
L139:   ifeq L708
L142:   aload_0
L143:   getfield Field Rg field220 Ljava/util/List;
L146:   invokeinterface InterfaceMethod java/util/List iterator ()Ljava/util/Iterator; 1
L151:   dup
L152:   astore_2
L153:   invokeinterface InterfaceMethod java/util/Iterator hasNext ()Z 1
L158:   ifeq L708
L161:   aload_2
L162:   invokeinterface InterfaceMethod java/util/Iterator next ()Ljava/lang/Object; 1
L167:   checkcast F
L170:   astore_3
L171:   aload_2
L172:   aload_3
L173:   invokeinterface InterfaceMethod F method67 ()V 1
L178:   goto L153
L181:   athrow
L182:   aload_0
L183:   getfield Field Rg field221 Lff;
L186:   iconst_0
L187:   iconst_1
L188:   dup
L189:   pop2
L190:   iconst_1
L191:   dup
L192:   dup
L193:   pop2
L194:   aload_0
L195:   getfield Field Rg this [[I
L198:   invokevirtual Method ff method474 (II[[I)Z
L201:   ifeq L244
L204:   aload_0
L205:   getfield Field Rg field220 Ljava/util/List;
L208:   invokeinterface InterfaceMethod java/util/List iterator ()Ljava/util/Iterator; 1
L213:   dup
L214:   astore_2
L215:   invokeinterface InterfaceMethod java/util/Iterator hasNext ()Z 1
L220:   ifeq L708
L223:   aload_2
L224:   invokeinterface InterfaceMethod java/util/Iterator next ()Ljava/lang/Object; 1
L229:   checkcast F
L232:   astore_3
L233:   aload_2
L234:   aload_3
L235:   invokeinterface InterfaceMethod F method67 ()V 1
L240:   goto L215
L243:   athrow
L244:   aload_0
L245:   invokevirtual Method Rg method69 ()V
L248:   return
L249:   aload_0
L250:   invokevirtual Method Rg method69 ()V
L253:   return
L254:   goto L53
L257:   iconst_1
L258:   dup
L259:   dup
L260:   pop2
L261:   istore_2
L262:   aload_1
L263:   getstatic Field Fe field427 LFe;
L266:   if_acmpne L280
L269:   aload_0
L270:   dup
L271:   getfield Field Rg field221 Lff;
L274:   invokevirtual Method ff method52 ()V
L277:   goto L306
L280:   aload_1
L281:   getstatic Field Fe field423 LFe;
L284:   if_acmpne L298
L287:   aload_0
L288:   dup
L289:   getfield Field Rg field221 Lff;
L292:   invokevirtual Method ff method74 ()V
L295:   goto L306
L298:   aload_0
L299:   dup
L300:   getfield Field Rg field221 Lff;
L303:   invokevirtual Method ff method69 ()V
L306:   getfield Field Rg field221 Lff;
L309:   aload_0
L310:   getfield Field Rg this [[I
L313:   invokevirtual Method ff method472 ([[I)Z
L316:   ifeq L565
L319:   aload_0
L320:   getfield Field Rg field221 Lff;
L323:   iconst_m1
L324:   iconst_1
L325:   dup
L326:   pop2
L327:   iconst_0
L328:   iconst_1
L329:   dup
L330:   pop2
L331:   aload_0
L332:   getfield Field Rg this [[I
L335:   invokevirtual Method ff method474 (II[[I)Z
L338:   ifne L520
L341:   aload_0
L342:   getfield Field Rg field221 Lff;
L345:   iconst_1
L346:   dup
L347:   pop2
L348:   iconst_0
L349:   iconst_1
L350:   dup_x1
L351:   dup
L352:   pop2
L353:   aload_0
L354:   getfield Field Rg this [[I
L357:   invokevirtual Method ff method474 (II[[I)Z
L360:   ifne L520
L363:   aload_0
L364:   getfield Field Rg field221 Lff;
L367:   iconst_0
L368:   iconst_1
L369:   dup
L370:   pop2
L371:   iconst_1
L372:   dup
L373:   dup
L374:   pop2
L375:   aload_0
L376:   getfield Field Rg this [[I
L379:   invokevirtual Method ff method474 (II[[I)Z
L382:   ifne L520
L385:   aload_0
L386:   getfield Field Rg field221 Lff;
L389:   iconst_m1
L390:   iconst_1
L391:   dup
L392:   pop2
L393:   iconst_1
L394:   dup
L395:   dup
L396:   pop2
L397:   aload_0
L398:   getfield Field Rg this [[I
L401:   invokevirtual Method ff method474 (II[[I)Z
L404:   ifne L520
L407:   aload_0
L408:   getfield Field Rg field221 Lff;
L411:   iconst_1
L412:   dup
L413:   pop2
L414:   iconst_1
L415:   dup
L416:   dup_x1
L417:   dup
L418:   pop2
L419:   aload_0
L420:   getfield Field Rg this [[I
L423:   invokevirtual Method ff method474 (II[[I)Z
L426:   ifne L520
L429:   aload_0
L430:   getfield Field Rg field221 Lff;
L433:   bipush -2
L435:   iconst_1
L436:   dup
L437:   pop2
L438:   iconst_0
L439:   iconst_1
L440:   dup
L441:   pop2
L442:   aload_0
L443:   getfield Field Rg this [[I
L446:   invokevirtual Method ff method474 (II[[I)Z
L449:   ifne L520
L452:   aload_0
L453:   getfield Field Rg field221 Lff;
L456:   iconst_2
L457:   iconst_1
L458:   dup
L459:   pop2
L460:   iconst_0
L461:   iconst_1
L462:   dup
L463:   pop2
L464:   aload_0
L465:   getfield Field Rg this [[I
L468:   invokevirtual Method ff method474 (II[[I)Z
L471:   ifne L520
L474:   aload_1
L475:   getstatic Field Fe field427 LFe;
L478:   if_acmpne L491
L481:   aload_0
L482:   getfield Field Rg field221 Lff;
L485:   invokevirtual Method ff method74 ()V
L488:   goto L515
L491:   aload_1
L492:   getstatic Field Fe field423 LFe;
L495:   if_acmpne L508
L498:   aload_0
L499:   getfield Field Rg field221 Lff;
L502:   invokevirtual Method ff method52 ()V
L505:   goto L515
L508:   aload_0
L509:   getfield Field Rg field221 Lff;
L512:   invokevirtual Method ff method69 ()V
L515:   iconst_0
L516:   iconst_1
L517:   dup
L518:   pop2
L519:   istore_2
L520:   iload_2
L521:   ifeq L565
L524:   aload_0
L525:   getfield Field Rg field220 Ljava/util/List;
L528:   invokeinterface InterfaceMethod java/util/List iterator ()Ljava/util/Iterator; 1
L533:   dup
L534:   astore_3
L535:   invokeinterface InterfaceMethod java/util/Iterator hasNext ()Z 1
L540:   ifeq L565
L543:   aload_3
L544:   invokeinterface InterfaceMethod java/util/Iterator next ()Ljava/lang/Object; 1
L549:   checkcast F
L552:   astore 4
L554:   aload_3
L555:   aload 4
L557:   invokeinterface InterfaceMethod F method67 ()V 1
L562:   goto L535
L565:   iload_2
L566:   ifeq L708
L569:   aload_1
L570:   getstatic Field Fe field427 LFe;
L573:   if_acmpne L618
L576:   aload_0
L577:   getfield Field Rg field220 Ljava/util/List;
L580:   invokeinterface InterfaceMethod java/util/List iterator ()Ljava/util/Iterator; 1
L585:   dup
L586:   astore_3
L587:   invokeinterface InterfaceMethod java/util/Iterator hasNext ()Z 1
L592:   ifeq L708
L595:   aload_3
L596:   invokeinterface InterfaceMethod java/util/Iterator next ()Ljava/lang/Object; 1
L601:   checkcast F
L604:   astore 4
L606:   aload_3
L607:   aload 4
L609:   invokeinterface InterfaceMethod F method68 ()V 1
L614:   goto L587
L617:   athrow
L618:   aload_1
L619:   getstatic Field Fe field423 LFe;
L622:   if_acmpne L667
L625:   aload_0
L626:   getfield Field Rg field220 Ljava/util/List;
L629:   invokeinterface InterfaceMethod java/util/List iterator ()Ljava/util/Iterator; 1
L634:   dup
L635:   astore_3
L636:   invokeinterface InterfaceMethod java/util/Iterator hasNext ()Z 1
L641:   ifeq L708
L644:   aload_3
L645:   invokeinterface InterfaceMethod java/util/Iterator next ()Ljava/lang/Object; 1
L650:   checkcast F
L653:   astore 4
L655:   aload_3
L656:   aload 4
L658:   invokeinterface InterfaceMethod F method69 ()V 1
L663:   goto L636
L666:   athrow
L667:   aload_0
L668:   getfield Field Rg field220 Ljava/util/List;
L671:   invokeinterface InterfaceMethod java/util/List iterator ()Ljava/util/Iterator; 1
L676:   dup
L677:   astore_3
L678:   invokeinterface InterfaceMethod java/util/Iterator hasNext ()Z 1
L683:   ifeq L708
L686:   aload_3
L687:   invokeinterface InterfaceMethod java/util/Iterator next ()Ljava/lang/Object; 1
L692:   checkcast F
L695:   astore 4
L697:   aload_3
L698:   aload 4
L700:   invokeinterface InterfaceMethod F this ()V 1
L705:   goto L678
L708:   return
L709:   
        .attribute StackMap b'\x00\x1F\x00\x34\x00\x02\x07\x00\x02\x07\x00\x0C\x00\x00\x00\x35\x00\x02\x07\x00\x02\x07\x00\x0C\x00\x01\x07\x00\x02\x00\x59\x00\x03\x07\x00\x02\x07\x00\x0C\x07\x00\x9D\x00\x01\x07\x00\x9D\x00\x75\x00\x00\x00\x01\x07\x00\x5B\x00\x78\x00\x02\x07\x00\x02\x07\x00\x0C\x00\x00\x00\x99\x00\x03\x07\x00\x02\x07\x00\x0C\x07\x00\x9D\x00\x01\x07\x00\x9D\x00\xB5\x00\x00\x00\x01\x07\x00\x5B\x00\xB6\x00\x02\x07\x00\x02\x07\x00\x0C\x00\x00\x00\xD7\x00\x03\x07\x00\x02\x07\x00\x0C\x07\x00\x9D\x00\x01\x07\x00\x9D\x00\xF3\x00\x00\x00\x01\x07\x00\x5B\x00\xF4\x00\x02\x07\x00\x02\x07\x00\x0C\x00\x00\x00\xF9\x00\x02\x07\x00\x02\x07\x00\x0C\x00\x00\x00\xFE\x00\x02\x07\x00\x02\x07\x00\x0C\x00\x01\x07\x00\x02\x01\x01\x00\x02\x07\x00\x02\x07\x00\x0C\x00\x00\x01\x18\x00\x03\x07\x00\x02\x07\x00\x0C\x01\x00\x00\x01\x2A\x00\x03\x07\x00\x02\x07\x00\x0C\x01\x00\x00\x01\x32\x00\x03\x07\x00\x02\x07\x00\x0C\x01\x00\x01\x07\x00\x02\x01\xEB\x00\x03\x07\x00\x02\x07\x00\x0C\x01\x00\x00\x01\xFC\x00\x03\x07\x00\x02\x07\x00\x0C\x01\x00\x00\x02\x03\x00\x03\x07\x00\x02\x07\x00\x0C\x01\x00\x00\x02\x08\x00\x03\x07\x00\x02\x07\x00\x0C\x01\x00\x00\x02\x17\x00\x04\x07\x00\x02\x07\x00\x0C\x01\x07\x00\x9D\x00\x01\x07\x00\x9D\x02\x35\x00\x03\x07\x00\x02\x07\x00\x0C\x01\x00\x00\x02\x4B\x00\x04\x07\x00\x02\x07\x00\x0C\x01\x07\x00\x9D\x00\x01\x07\x00\x9D\x02\x69\x00\x00\x00\x01\x07\x00\x5B\x02\x6A\x00\x03\x07\x00\x02\x07\x00\x0C\x01\x00\x00\x02\x7C\x00\x04\x07\x00\x02\x07\x00\x0C\x01\x07\x00\x9D\x00\x01\x07\x00\x9D\x02\x9A\x00\x00\x00\x01\x07\x00\x5B\x02\x9B\x00\x03\x07\x00\x02\x07\x00\x0C\x01\x00\x00\x02\xA6\x00\x04\x07\x00\x02\x07\x00\x0C\x01\x07\x00\x9D\x00\x01\x07\x00\x9D\x02\xC4\x00\x02\x07\x00\x02\x07\x00\x0C\x00\x00'
    .end code
.end method

.method public method89 : ()V
    .code stack 4 locals 1
L0:     aload_0
L1:     dup
L2:     dup
L3:     getfield Field Rg field224 F
L6:     getstatic Field ib field2312 F
L9:     fadd
L10:    putfield Field Rg field224 F
L13:    getfield Field Rg field224 F
L16:    ldc 1e-1f
L18:    fcmpg
L19:    ifge L24
L22:    return
L23:    athrow
L24:    aload_0
L25:    dup
L26:    getfield Field Rg field224 F
L29:    ldc 1e-1f
L31:    fsub
L32:    putfield Field Rg field224 F
L35:    getstatic Field XE field2166 [I
L38:    aload_0
L39:    getfield Field Rg field227 LqE;
L42:    invokevirtual Method qE ordinal ()I
L45:    iaload
L46:    tableswitch 1
            L150
            L92
            L129
            L196
            L217
            L217
            L217
            L221
            default : L253
L92:    aload_0
L93:    invokevirtual Method Rg new ()I
L96:    ifeq L108
L99:    aload_0
L100:   getstatic Field qE field631 LqE;
L103:   invokevirtual Method Rg method226 (LqE;)V
L106:   return
L107:   athrow
L108:   aload_0
L109:   getfield Field Rg field239 Lqd;
L112:   getfield Field qd field763 LQB;
L115:   getstatic Field QB field368 LQB;
L118:   if_acmpne L253
L121:   aload_0
L122:   getstatic Field qE field631 LqE;
L125:   invokevirtual Method Rg method226 (LqE;)V
L128:   return
L129:   aload_0
L130:   getfield Field Rg field239 Lqd;
L133:   getfield Field qd field763 LQB;
L136:   getstatic Field QB field368 LQB;
L139:   if_acmpne L253
L142:   aload_0
L143:   getstatic Field qE field626 LqE;
L146:   invokevirtual Method Rg method226 (LqE;)V
L149:   return
L150:   aload_0
L151:   iconst_0
L152:   ifne L218
L155:   getfield Field Rg field239 Lqd;
L158:   getfield Field qd field763 LQB;
L161:   getstatic Field QB field369 LQB;
L164:   if_acmpne L175
L167:   aload_0
L168:   getstatic Field qE this LqE;
L171:   invokevirtual Method Rg method226 (LqE;)V
L174:   return
L175:   aload_0
L176:   getfield Field Rg field239 Lqd;
L179:   getfield Field qd field763 LQB;
L182:   getstatic Field QB field367 LQB;
L185:   if_acmpne L253
L188:   aload_0
L189:   getstatic Field qE new LqE;
L192:   invokevirtual Method Rg method226 (LqE;)V
L195:   return
L196:   aload_0
L197:   getfield Field Rg field239 Lqd;
L200:   getfield Field qd field763 LQB;
L203:   getstatic Field QB field367 LQB;
L206:   if_acmpne L253
L209:   aload_0
L210:   getstatic Field qE new LqE;
L213:   invokevirtual Method Rg method226 (LqE;)V
L216:   return
L217:   return
L218:   goto L151
L221:   aload_0
L222:   getfield Field Rg field239 Lqd;
L225:   getfield Field qd field742 Z
L228:   aload_0
L229:   swap
L230:   ifne L240
L233:   getstatic Field qE field628 LqE;
L236:   invokevirtual Method Rg method226 (LqE;)V
L239:   return
L240:   getfield Field Rg field231 LsE;
L243:   ifnull L253
L246:   aload_0
L247:   getstatic Field qE field628 LqE;
L250:   invokevirtual Method Rg method226 (LqE;)V
L253:   return
L254:   
        .attribute StackMap b'\x00\x0F\x00\x17\x00\x00\x00\x01\x07\x00\x5B\x00\x18\x00\x01\x07\x00\x02\x00\x00\x00\x5C\x00\x01\x07\x00\x02\x00\x00\x00\x6B\x00\x00\x00\x01\x07\x00\x5B\x00\x6C\x00\x01\x07\x00\x02\x00\x00\x00\x81\x00\x01\x07\x00\x02\x00\x00\x00\x96\x00\x01\x07\x00\x02\x00\x00\x00\x97\x00\x01\x07\x00\x02\x00\x01\x07\x00\x02\x00\xAF\x00\x01\x07\x00\x02\x00\x00\x00\xC4\x00\x01\x07\x00\x02\x00\x00\x00\xD9\x00\x01\x07\x00\x02\x00\x00\x00\xDA\x00\x01\x07\x00\x02\x00\x01\x07\x00\x02\x00\xDD\x00\x01\x07\x00\x02\x00\x00\x00\xF0\x00\x01\x07\x00\x02\x00\x01\x07\x00\x02\x00\xFD\x00\x01\x07\x00\x02\x00\x00'
    .end code
.end method

.method public method27 : (Ljava/util/List;)V
    .code stack 2 locals 2
L0:     aload_0
L1:     aload_1
L2:     putfield Field Rg field211 Ljava/util/List;
L5:     return
L6:     
    .end code
.end method

.method private method61 : ()V
    .code stack 26 locals 2
L0:     dconst_0
L1:     aload_0
L2:     dup_x2
L3:     dup_x2
L4:     iconst_0
L5:     dup
L6:     aload_0
L7:     dup_x1
L8:     iconst_0
L9:     aload_0
L10:    dup
L11:    iconst_1
L12:    dup
L13:    dup
L14:    pop2
L15:    invokevirtual Method Rg method95 (Z)V
L18:    getfield Field Rg field234 Ljava/util/LinkedList;
L21:    invokevirtual Method java/util/LinkedList clear ()V
L24:    iconst_1
L25:    dup
L26:    pop2
L27:    putfield Field Rg field223 I
L30:    iconst_1
L31:    dup
L32:    pop2
L33:    putfield Field Rg field225 I
L36:    iconst_1
L37:    dup
L38:    pop2
L39:    putfield Field Rg field222 I
L42:    putfield Field Rg field240 D
L45:    getfield Field Rg field220 Ljava/util/List;
L48:    invokeinterface InterfaceMethod java/util/List iterator ()Ljava/util/Iterator; 1
L53:    dup
L54:    astore_1
L55:    invokeinterface InterfaceMethod java/util/Iterator hasNext ()Z 1
L60:    ifeq L82
L63:    aload_1
L64:    invokeinterface InterfaceMethod java/util/Iterator next ()Ljava/lang/Object; 1
L69:    checkcast F
L72:    invokeinterface InterfaceMethod F method52 ()V 1
L77:    aload_1
L78:    goto L55
L81:    athrow
L82:    aload_0
L83:    iconst_0
L84:    dup
L85:    aload_0
L86:    dup_x1
L87:    fconst_0
L88:    iconst_0
L89:    aload_0
L90:    dup_x1
L91:    iconst_0
L92:    dup
L93:    aload_0
L94:    dup_x1
L95:    iconst_0
L96:    dup
L97:    aload_0
L98:    dup_x1
L99:    iconst_0
L100:   fconst_0
L101:   aload_0
L102:   dup_x1
L103:   fconst_0
L104:   dup
L105:   aload_0
L106:   dup_x1
L107:   fconst_0
L108:   putfield Field Rg field212 F
L111:   putfield Field Rg field219 F
L114:   putfield Field Rg field241 F
L117:   putfield Field Rg field226 F
L120:   iconst_1
L121:   dup
L122:   pop2
L123:   putfield Field Rg field232 I
L126:   iconst_1
L127:   dup
L128:   pop2
L129:   putfield Field Rg field213 I
L132:   iconst_1
L133:   dup
L134:   pop2
L135:   putfield Field Rg field230 I
L138:   iconst_1
L139:   dup
L140:   pop2
L141:   putfield Field Rg field218 I
L144:   iconst_1
L145:   dup
L146:   pop2
L147:   putfield Field Rg true I
L150:   iconst_1
L151:   dup
L152:   pop2
L153:   putfield Field Rg field236 I
L156:   putfield Field Rg field215 F
L159:   iconst_1
L160:   dup
L161:   pop2
L162:   putfield Field Rg field228 I
L165:   iconst_1
L166:   dup
L167:   pop2
L168:   invokevirtual Method Rg method95 (Z)V
L171:   return
L172:   
        .attribute StackMap b'\x00\x03\x00\x37\x00\x02\x07\x00\x02\x07\x00\x9D\x00\x01\x07\x00\x9D\x00\x51\x00\x00\x00\x01\x07\x00\x5B\x00\x52\x00\x02\x07\x00\x02\x07\x00\x9D\x00\x00'
    .end code
.end method

.method private method240 : ()Ljava/util/List;
    .code stack 2 locals 4
L0:     new java/util/LinkedList
L3:     dup
L4:     invokespecial Method java/util/LinkedList <init> ()V
L7:     astore_1
L8:     aload_0
L9:     getfield Field Rg field211 Ljava/util/List;
L12:    invokeinterface InterfaceMethod java/util/List iterator ()Ljava/util/Iterator; 1
L17:    astore_2
L18:    aload_2
L19:    invokeinterface InterfaceMethod java/util/Iterator hasNext ()Z 1
L24:    ifeq L57
L27:    aload_2
L28:    invokeinterface InterfaceMethod java/util/Iterator next ()Ljava/lang/Object; 1
L33:    checkcast Uf
L36:    dup
L37:    astore_3
L38:    aload_0
L39:    invokevirtual Method Uf method704 (LRg;)Z
L42:    ifeq L18
L45:    aload_1
L46:    aload_3
L47:    invokeinterface InterfaceMethod java/util/List add (Ljava/lang/Object;)Z 2
L52:    pop
L53:    goto L18
L56:    athrow
L57:    aload_0
L58:    getfield Field Rg field211 Ljava/util/List;
L61:    aload_1
L62:    invokeinterface InterfaceMethod java/util/List removeAll (Ljava/util/Collection;)Z 2
L67:    pop
L68:    aload_1
L69:    areturn
L70:    
        .attribute StackMap b'\x00\x03\x00\x12\x00\x03\x07\x00\x02\x07\x00\x6D\x07\x00\x9D\x00\x00\x00\x38\x00\x00\x00\x01\x07\x00\x5B\x00\x39\x00\x03\x07\x00\x02\x07\x00\x6D\x07\x00\x9D\x00\x00'
    .end code
.end method

.method public method69 : ()V
    .code stack 15 locals 6
L0:     aload_0
L1:     dup
L2:     iconst_1
L3:     dup
L4:     dup
L5:     pop2
L6:     invokevirtual Method Rg method95 (Z)V
L9:     getfield Field Rg field221 Lff;
L12:    aload_0
L13:    getfield Field Rg this [[I
L16:    invokevirtual Method ff method470 ([[I)Z
L19:    ifeq L62
L22:    aload_0
L23:    getfield Field Rg field220 Ljava/util/List;
L26:    invokeinterface InterfaceMethod java/util/List iterator ()Ljava/util/Iterator; 1
L31:    dup
L32:    astore_1
L33:    invokeinterface InterfaceMethod java/util/Iterator hasNext ()Z 1
L38:    ifeq L62
L41:    aload_1
L42:    invokeinterface InterfaceMethod java/util/Iterator next ()Ljava/lang/Object; 1
L47:    checkcast F
L50:    astore_2
L51:    aload_1
L52:    aload_2
L53:    invokeinterface InterfaceMethod F method84 ()V 1
L58:    goto L33
L61:    athrow
L62:    aload_0
L63:    dup
L64:    dup_x1
L65:    getfield Field Rg field234 Ljava/util/LinkedList;
L68:    swap
L69:    getfield Field Rg field241 F
L72:    invokestatic Method java/lang/Float valueOf (F)Ljava/lang/Float;
L75:    invokevirtual Method java/util/LinkedList addLast (Ljava/lang/Object;)V
L78:    getfield Field Rg field234 Ljava/util/LinkedList;
L81:    invokevirtual Method java/util/LinkedList size ()I
L84:    bipush 10
L86:    iconst_1
L87:    dup
L88:    pop2
L89:    if_icmple L105
L92:    aload_0
L93:    dup
L94:    getfield Field Rg field234 Ljava/util/LinkedList;
L97:    invokevirtual Method java/util/LinkedList removeFirst ()Ljava/lang/Object;
L100:   pop
L101:   goto L78
L104:   athrow
L105:   aload_0
L106:   dup
L107:   dup_x1
L108:   dup2
L109:   dup
L110:   getfield Field Rg field228 I
L113:   iconst_1
L114:   dup
L115:   dup
L116:   pop2
L117:   iadd
L118:   putfield Field Rg field228 I
L121:   getfield Field Rg this [[I
L124:   invokestatic Method OC method1012 ([[I)[[I
L127:   astore_1
L128:   getfield Field Rg field221 Lff;
L131:   aload_0
L132:   getfield Field Rg this [[I
L135:   invokevirtual Method ff method471 ([[I)V
L138:   getfield Field Rg this [[I
L141:   invokestatic Method hE method1142 ([[I)[I
L144:   astore_2
L145:   dup
L146:   getfield Field Rg true I
L149:   aload_2
L150:   arraylength
L151:   iadd
L152:   putfield Field Rg true I
L155:   aload_0
L156:   aload_2
L157:   arraylength
L158:   putfield Field Rg field236 I
L161:   aload_2
L162:   arraylength
L163:   iconst_4
L164:   iconst_1
L165:   dup
L166:   pop2
L167:   if_icmplt L180
L170:   aload_0
L171:   dup
L172:   getfield Field Rg field215 F
L175:   fconst_1
L176:   fadd
L177:   putfield Field Rg field215 F
L180:   aload_0
L181:   dup
L182:   dup2
L183:   dup2
L184:   dup2
L185:   aload_2
L186:   iconst_1
L187:   aload_0
L188:   dup_x2
L189:   iconst_0
L190:   iconst_1
L191:   dup
L192:   pop2
L193:   invokevirtual Method Rg method95 (Z)V
L196:   iconst_1
L197:   dup
L198:   pop2
L199:   invokevirtual Method Rg method241 ([IZ)V
L202:   getfield Field Rg field221 Lff;
L205:   astore_3
L206:   getfield Field Rg field238 Lff;
L209:   putfield Field Rg field221 Lff;
L212:   iconst_0
L213:   iconst_1
L214:   dup
L215:   pop2
L216:   invokevirtual Method Rg method228 (Z)Lff;
L219:   putfield Field Rg field238 Lff;
L222:   getfield Field Rg field238 Lff;
L225:   dup
L226:   getfield Field ff field881 I
L229:   aload_0
L230:   getfield Field Rg try I
L233:   iadd
L234:   putfield Field ff field881 I
L237:   fconst_0
L238:   putfield Field Rg field226 F
L241:   aload_1
L242:   aload_3
L243:   aload_2
L244:   invokespecial Method Rg method233 ([[ILff;[I)Ljava/util/List;
L247:   invokeinterface InterfaceMethod java/util/List iterator ()Ljava/util/Iterator; 1
L252:   astore_1
L253:   aload_1
L254:   invokeinterface InterfaceMethod java/util/Iterator hasNext ()Z 1
L259:   ifeq L318
L262:   aload_1
L263:   invokeinterface InterfaceMethod java/util/Iterator next ()Ljava/lang/Object; 1
L268:   checkcast Uf
L271:   astore 4
L273:   aload_0
L274:   getfield Field Rg field220 Ljava/util/List;
L277:   invokeinterface InterfaceMethod java/util/List iterator ()Ljava/util/Iterator; 1
L282:   dup
L283:   astore 5
L285:   invokeinterface InterfaceMethod java/util/Iterator hasNext ()Z 1
L290:   ifeq L253
L293:   aload 5
L295:   invokeinterface InterfaceMethod java/util/Iterator next ()Ljava/lang/Object; 1
L300:   checkcast F
L303:   aload 4
L305:   invokeinterface InterfaceMethod F method60 (LUf;)V 2
L310:   aload 5
L312:   goto L285
L315:   nop
L316:   nop
L317:   athrow
L318:   aload_0
L319:   getfield Field Rg field220 Ljava/util/List;
L322:   invokeinterface InterfaceMethod java/util/List iterator ()Ljava/util/Iterator; 1
L327:   dup
L328:   astore_1
L329:   invokeinterface InterfaceMethod java/util/Iterator hasNext ()Z 1
L334:   ifeq L360
L337:   aload_1
L338:   invokeinterface InterfaceMethod java/util/Iterator next ()Ljava/lang/Object; 1
L343:   checkcast F
L346:   astore 4
L348:   aload_1
L349:   aload 4
L351:   aload_3
L352:   invokeinterface InterfaceMethod F method91 (Lff;)V 2
L357:   goto L329
L360:   aload_0
L361:   getfield Field Rg field239 Lqd;
L364:   getfield Field qd field761 Leb;
L367:   aload_0
L368:   aload_2
L369:   arraylength
L370:   invokevirtual Method eb method760 (LRg;I)V
L373:   aload_0
L374:   getfield Field Rg field240 D
L377:   aload_0
L378:   getfield Field Rg field241 F
L381:   f2d
L382:   dcmpg
L383:   ifge L435
L386:   aload_0
L387:   dup
L388:   iconst_0
L389:   iconst_1
L390:   dup
L391:   pop2
L392:   putfield Field Rg field225 I
L395:   getfield Field Rg field220 Ljava/util/List;
L398:   invokeinterface InterfaceMethod java/util/List iterator ()Ljava/util/Iterator; 1
L403:   dup
L404:   astore_1
L405:   invokeinterface InterfaceMethod java/util/Iterator hasNext ()Z 1
L410:   ifeq L435
L413:   aload_1
L414:   invokeinterface InterfaceMethod java/util/Iterator next ()Ljava/lang/Object; 1
L419:   checkcast F
L422:   astore 4
L424:   aload_1
L425:   aload 4
L427:   invokeinterface InterfaceMethod F method52 ()V 1
L432:   goto L405
L435:   aload_0
L436:   iconst_0
L437:   iconst_1
L438:   dup
L439:   pop2
L440:   invokevirtual Method Rg method95 (Z)V
L443:   return
L444:   
        .attribute StackMap b'\x00\x0F\x00\x21\x00\x02\x07\x00\x02\x07\x00\x9D\x00\x01\x07\x00\x9D\x00\x3D\x00\x00\x00\x01\x07\x00\x5B\x00\x3E\x00\x01\x07\x00\x02\x00\x00\x00\x4E\x00\x01\x07\x00\x02\x00\x01\x07\x00\x02\x00\x68\x00\x00\x00\x01\x07\x00\x5B\x00\x69\x00\x01\x07\x00\x02\x00\x00\x00\xB4\x00\x03\x07\x00\x02\x07\x00\xAE\x07\x01\xBB\x00\x00\x00\xFD\x00\x04\x07\x00\x02\x07\x00\x9D\x07\x01\xBB\x07\x00\xE0\x00\x00\x01\x1D\x00\x06\x07\x00\x02\x07\x00\x9D\x07\x01\xBB\x07\x00\xE0\x07\x00\xA7\x07\x00\x9D\x00\x01\x07\x00\x9D\x01\x3B\x00\x00\x00\x01\x07\x00\x5B\x01\x3E\x00\x04\x07\x00\x02\x07\x00\x9D\x07\x01\xBB\x07\x00\xE0\x00\x00\x01\x49\x00\x04\x07\x00\x02\x07\x00\x9D\x07\x01\xBB\x07\x00\xE0\x00\x01\x07\x00\x9D\x01\x68\x00\x04\x07\x00\x02\x07\x00\x9D\x07\x01\xBB\x07\x00\xE0\x00\x00\x01\x95\x00\x04\x07\x00\x02\x07\x00\x9D\x07\x01\xBB\x07\x00\xE0\x00\x01\x07\x00\x9D\x01\xB3\x00\x04\x07\x00\x02\x07\x00\x9D\x07\x01\xBB\x07\x00\xE0\x00\x00'
    .end code
.end method

.method public method132 : ()I
    .code stack 3 locals 1
L0:     aload_0
L1:     getfield Field Rg field239 Lqd;
L4:     getfield Field qd field760 Ljava/util/LinkedHashMap;
L7:     aload_0
L8:     getfield Field Rg false Led;
L11:    invokevirtual Method java/util/LinkedHashMap containsKey (Ljava/lang/Object;)Z
L14:    ifne L23
L17:    iconst_0
L18:    iconst_1
L19:    dup
L20:    pop2
L21:    ireturn
L22:    athrow
L23:    aload_0
L24:    getfield Field Rg field239 Lqd;
L27:    getfield Field qd field760 Ljava/util/LinkedHashMap;
L30:    aload_0
L31:    getfield Field Rg false Led;
L34:    invokevirtual Method java/util/LinkedHashMap get (Ljava/lang/Object;)Ljava/lang/Object;
L37:    checkcast java/lang/Integer
L40:    invokevirtual Method java/lang/Integer intValue ()I
L43:    ireturn
L44:    
        .attribute StackMap b'\x00\x02\x00\x16\x00\x00\x00\x01\x07\x00\x5B\x00\x17\x00\x01\x07\x00\x02\x00\x00'
    .end code
.end method

.method public method52 : ()V
    .code stack 3 locals 2
L0:     aload_0
L1:     dup
L2:     invokestatic Method ib method1153 (LM;)V
L5:     getfield Field Rg field239 Lqd;
L8:     aload_0
L9:     dup_x1
L10:    invokevirtual Method qd method401 (LG;)V
L13:    getfield Field Rg field220 Ljava/util/List;
L16:    invokeinterface InterfaceMethod java/util/List iterator ()Ljava/util/Iterator; 1
L21:    dup
L22:    astore_1
L23:    invokeinterface InterfaceMethod java/util/Iterator hasNext ()Z 1
L28:    ifeq L50
L31:    aload_1
L32:    invokeinterface InterfaceMethod java/util/Iterator next ()Ljava/lang/Object; 1
L37:    checkcast F
L40:    invokeinterface InterfaceMethod F method61 ()V 1
L45:    aload_1
L46:    goto L23
L49:    athrow
L50:    return
L51:    
        .attribute StackMap b'\x00\x03\x00\x17\x00\x02\x07\x00\x02\x07\x00\x9D\x00\x01\x07\x00\x9D\x00\x31\x00\x00\x00\x01\x07\x00\x5B\x00\x32\x00\x02\x07\x00\x02\x07\x00\x9D\x00\x00'
    .end code
.end method

.method public fpsfoundhere : (F)Z
    .code stack 3 locals 2
L0:     iconst_0
L1:     iconst_1
L2:     dup
L3:     pop2
L4:     ireturn
L5:     
    .end code
    .exceptions java/lang/Exception
.end method

.method public method241 : ([IZ)V
    .code stack 7 locals 8
L0:     aload_1
L1:     dup
L2:     astore_3
L3:     arraylength
L4:     istore 4
L6:     iconst_0
L7:     iconst_1
L8:     dup
L9:     pop2
L10:    dup
L11:    istore 5
L13:    iload 4
L15:    if_icmpge L132
L18:    aload_3
L19:    iload 5
L21:    iaload
L22:    dup
L23:    istore 6
L25:    ifle L85
L28:    iconst_0
L29:    iconst_1
L30:    dup
L31:    pop2
L32:    dup
L33:    istore 7
L35:    aload_0
L36:    getfield Field Rg this [[I
L39:    arraylength
L40:    if_icmpge L76
L43:    aload_0
L44:    getfield Field Rg this [[I
L47:    iload 7
L49:    aaload
L50:    aload_0
L51:    getfield Field Rg this [[I
L54:    iload 7
L56:    aaload
L57:    iload 6
L59:    dup_x1
L60:    iconst_1
L61:    dup
L62:    dup
L63:    pop2
L64:    isub
L65:    iaload
L66:    iinc 7 1
L69:    iastore
L70:    iload 7
L72:    goto L35
L75:    athrow
L76:    iinc 6 -1
L79:    iload 6
L81:    goto L25
L84:    athrow
L85:    iconst_0
L86:    iconst_1
L87:    dup
L88:    pop2
L89:    dup
L90:    istore 6
L92:    aload_0
L93:    getfield Field Rg this [[I
L96:    arraylength
L97:    if_icmpge L124
L100:   aload_0
L101:   getfield Field Rg this [[I
L104:   iload 6
L106:   aaload
L107:   iconst_0
L108:   iconst_1
L109:   dup
L110:   pop2
L111:   iconst_0
L112:   iconst_1
L113:   dup
L114:   pop2
L115:   iinc 6 1
L118:   iastore
L119:   iload 6
L121:   goto L92
L124:   iinc 5 1
L127:   iload 5
L129:   goto L13
L132:   iload_2
L133:   ifeq L148
L136:   aload_0
L137:   getfield Field Rg field239 Lqd;
L140:   getfield Field qd field761 Leb;
L143:   aload_0
L144:   aload_1
L145:   invokevirtual Method eb method765 (LRg;[I)V
L148:   aload_1
L149:   arraylength
L150:   ifle L202
L153:   aload_0
L154:   dup
L155:   getfield Field Rg this [[I
L158:   invokestatic Method hE method1143 ([[I)V
L161:   getfield Field Rg field220 Ljava/util/List;
L164:   invokeinterface InterfaceMethod java/util/List iterator ()Ljava/util/Iterator; 1
L169:   dup
L170:   astore_3
L171:   invokeinterface InterfaceMethod java/util/Iterator hasNext ()Z 1
L176:   ifeq L202
L179:   aload_3
L180:   invokeinterface InterfaceMethod java/util/Iterator next ()Ljava/lang/Object; 1
L185:   checkcast F
L188:   astore 4
L190:   aload_3
L191:   aload 4
L193:   aload_1
L194:   invokeinterface InterfaceMethod F method82 ([I)V 2
L199:   goto L171
L202:   return
L203:   
        .attribute StackMap b'\x00\x0D\x00\x0D\x00\x06\x07\x00\x02\x07\x01\xBB\x01\x07\x01\xBB\x01\x01\x00\x01\x01\x00\x19\x00\x07\x07\x00\x02\x07\x01\xBB\x01\x07\x01\xBB\x01\x01\x01\x00\x01\x01\x00\x23\x00\x08\x07\x00\x02\x07\x01\xBB\x01\x07\x01\xBB\x01\x01\x01\x01\x00\x01\x01\x00\x4B\x00\x00\x00\x01\x07\x00\x5B\x00\x4C\x00\x08\x07\x00\x02\x07\x01\xBB\x01\x07\x01\xBB\x01\x01\x01\x01\x00\x00\x00\x54\x00\x00\x00\x01\x07\x00\x5B\x00\x55\x00\x07\x07\x00\x02\x07\x01\xBB\x01\x07\x01\xBB\x01\x01\x01\x00\x00\x00\x5C\x00\x07\x07\x00\x02\x07\x01\xBB\x01\x07\x01\xBB\x01\x01\x01\x00\x01\x01\x00\x7C\x00\x07\x07\x00\x02\x07\x01\xBB\x01\x07\x01\xBB\x01\x01\x01\x00\x00\x00\x84\x00\x06\x07\x00\x02\x07\x01\xBB\x01\x07\x01\xBB\x01\x01\x00\x00\x00\x94\x00\x06\x07\x00\x02\x07\x01\xBB\x01\x07\x01\xBB\x01\x01\x00\x00\x00\xAB\x00\x06\x07\x00\x02\x07\x01\xBB\x01\x07\x00\x9D\x00\x01\x00\x01\x07\x00\x9D\x00\xCA\x00\x06\x07\x00\x02\x07\x01\xBB\x01\x07\x00\x04\x00\x01\x00\x00'
    .end code
.end method

.method public bridge synthetic compareTo : (Ljava/lang/Object;)I
    .code stack 2 locals 2
L0:     aload_0
L1:     aload_1
L2:     checkcast Rg
L5:     invokevirtual Method Rg method229 (LRg;)I
L8:     ireturn
L9:     
    .end code
.end method

.method public method104 : (F)V
    .code stack 7 locals 3
L0:     aload_0
L1:     dup
L2:     iconst_1
L3:     dup
L4:     dup
L5:     pop2
L6:     invokevirtual Method Rg method95 (Z)V
L9:     getfield Field Rg field239 Lqd;
L12:    getfield Field qd field761 Leb;
L15:    aload_0
L16:    dup_x1
L17:    invokevirtual Method eb method750 (LRg;)F
L20:    fstore_2
L21:    getfield Field Rg field221 Lff;
L24:    iconst_0
L25:    iconst_1
L26:    dup
L27:    pop2
L28:    iconst_1
L29:    dup
L30:    dup
L31:    pop2
L32:    aload_0
L33:    getfield Field Rg this [[I
L36:    invokevirtual Method ff method474 (II[[I)Z
L39:    ifeq L73
L42:    aload_0
L43:    dup
L44:    dup_x1
L45:    getfield Field Rg field221 Lff;
L48:    dup
L49:    getfield Field ff field881 I
L52:    iconst_1
L53:    dup
L54:    dup
L55:    pop2
L56:    isub
L57:    putfield Field ff field881 I
L60:    dup
L61:    getfield Field Rg field226 F
L64:    fload_1
L65:    fadd
L66:    putfield Field Rg field226 F
L69:    goto L90
L72:    athrow
L73:    aload_0
L74:    dup
L75:    dup
L76:    getfield Field Rg field226 F
L79:    fload_1
L80:    fload_2
L81:    fmul
L82:    ldc_w 2.5e0f
L85:    fmul
L86:    fadd
L87:    putfield Field Rg field226 F
L90:    iconst_0
L91:    iconst_1
L92:    dup
L93:    pop2
L94:    invokevirtual Method Rg method95 (Z)V
L97:    aload_0
L98:    getfield Field Rg field226 F
L101:   fload_2
L102:   fcmpl
L103:   ifle L136
L106:   iconst_0
L107:   aload_0
L108:   dup_x1
L109:   dup_x2
L110:   aload_0
L111:   getstatic Field Fe field424 LFe;
L114:   invokevirtual Method Rg method239 (LFe;)V
L117:   dup
L118:   getfield Field Rg field226 F
L121:   fload_2
L122:   fsub
L123:   putfield Field Rg field226 F
L126:   iconst_1
L127:   dup
L128:   pop2
L129:   invokevirtual Method Rg method95 (Z)V
L132:   goto L98
L135:   athrow
L136:   return
L137:   
        .attribute StackMap b'\x00\x06\x00\x48\x00\x00\x00\x01\x07\x00\x5B\x00\x49\x00\x03\x07\x00\x02\x02\x02\x00\x00\x00\x5A\x00\x03\x07\x00\x02\x02\x02\x00\x01\x07\x00\x02\x00\x62\x00\x03\x07\x00\x02\x02\x02\x00\x01\x07\x00\x02\x00\x87\x00\x00\x00\x01\x07\x00\x5B\x00\x88\x00\x03\x07\x00\x02\x02\x02\x00\x00'
    .end code
.end method

.method public method94 : ()Z
    .code stack 3 locals 1
L0:     getstatic Field XE field2166 [I
L3:     aload_0
L4:     getfield Field Rg field227 LqE;
L7:     invokevirtual Method qE ordinal ()I
L10:    iaload
L11:    tableswitch 1
            L40
            L40
            L40
            L40
            default : L50
L40:    iconst_1
L41:    iconst_0
L42:    ifne L41
L45:    dup
L46:    dup
L47:    pop2
L48:    ireturn
L49:    athrow
L50:    iconst_0
L51:    iconst_1
L52:    dup
L53:    pop2
L54:    ireturn
L55:    
        .attribute StackMap b'\x00\x04\x00\x28\x00\x01\x07\x00\x02\x00\x00\x00\x29\x00\x01\x07\x00\x02\x00\x01\x01\x00\x31\x00\x00\x00\x01\x07\x00\x5B\x00\x32\x00\x01\x07\x00\x02\x00\x00'
    .end code
.end method
.innerclasses
    Fe Rg [0] static final enum
    Pc JB [0] public static final enum
    QB qd [0] public static final enum
    XE Rg [0] static synthetic
    ng [0] [0]
    oc fc [0] public static final enum
.end innerclasses
.end class
