.version 49 0
.class public final super Sb
.super qB
.field public field1440 F
.field public try F
.field public field1441 F
.field public new F
.field public field1442 F
.field public this F
.field public field1443 F
.field public field1444 I
.field public field1445 LDF;
.field public field1446 F

.method public method721 : ()V
    .code stack 6 locals 2
L0:     aload_0
L1:     dup
L2:     getfield Field Sb field1444 I
L5:     swap
L6:     getfield Field Sb field1430 LLD;
L9:     getfield Field LD field137 LRg;
L12:    getfield Field Rg field235 Ljava/util/LinkedList;
L15:    invokevirtual Method java/util/LinkedList size ()I
L18:    if_icmpne L23
L21:    return
L22:    athrow
L23:    aload_0
L24:    dup
L25:    dup_x1
L26:    dup2
L27:    getfield Field Sb field1444 I
L30:    istore_1
L31:    getfield Field Sb field1430 LLD;
L34:    getfield Field LD field137 LRg;
L37:    getfield Field Rg field235 Ljava/util/LinkedList;
L40:    invokevirtual Method java/util/LinkedList size ()I
L43:    putfield Field Sb field1444 I
L46:    getfield Field Sb field1445 LDF;
L49:    new java/lang/StringBuilder
L52:    dup
L53:    invokespecial Method java/lang/StringBuilder <init> ()V
L56:    aload_0
L57:    getfield Field Sb field1444 I
L60:    invokevirtual Method java/lang/StringBuilder append (I)Ljava/lang/StringBuilder;
L63:    ldc ""
L65:    invokevirtual Method java/lang/StringBuilder append (Ljava/lang/String;)Ljava/lang/StringBuilder;
L68:    invokevirtual Method java/lang/StringBuilder toString ()Ljava/lang/String;
L71:    invokevirtual Method DF method12 (Ljava/lang/String;)V
L74:    getfield Field Sb field1444 I
L77:    iload_1
L78:    if_icmple L123
L81:    aload_0
L82:    dup
L83:    dup2
L84:    getfield Field Sb field1444 I
L87:    i2f
L88:    ldc 4e-1f
L90:    fmul
L91:    fconst_0
L92:    fconst_1
L93:    invokestatic Method OC method1001 (FFF)F
L96:    putfield Field Sb field1441 F
L99:    dup
L100:   getfield Field Sb field1443 F
L103:   fconst_1
L104:   fadd
L105:   putfield Field Sb field1443 F
L108:   getfield Field Sb field1443 F
L111:   ldc 1.5e0f
L113:   fcmpl
L114:   ifle L123
L117:   aload_0
L118:   ldc 1.5e0f
L120:   putfield Field Sb field1443 F
L123:   iload_1
L124:   aload_0
L125:   getfield Field Sb field1444 I
L128:   if_icmple L148
L131:   aload_0
L132:   dup
L133:   getfield Field Sb field1444 I
L136:   i2f
L137:   ldc 2.5e-1f
L139:   fmul
L140:   fconst_0
L141:   fconst_1
L142:   invokestatic Method OC method1001 (FFF)F
L145:   putfield Field Sb field1441 F
L148:   aload_0
L149:   dup
L150:   dup_x1
L151:   getfield Field Sb field1445 LDF;
L154:   swap
L155:   getfield Field Sb field1440 F
L158:   ldc 1.4e0f
L160:   dup
L161:   aload_0
L162:   getfield Field Sb field1441 F
L165:   fmul
L166:   fadd
L167:   fmul
L168:   invokevirtual Method DF method104 (F)V
L171:   getfield Field Sb field1445 LDF;
L174:   aload_0
L175:   dup
L176:   getfield Field Sb field1441 F
L179:   swap
L180:   getfield Field Sb field1446 F
L183:   fconst_1
L184:   invokestatic Method OC method1011 (FFF)F
L187:   aload_0
L188:   dup
L189:   getfield Field Sb field1441 F
L192:   swap
L193:   getfield Field Sb new F
L196:   fconst_0
L197:   invokestatic Method OC method1011 (FFF)F
L200:   aload_0
L201:   dup
L202:   getfield Field Sb field1441 F
L205:   swap
L206:   getfield Field Sb field1442 F
L209:   fconst_0
L210:   invokestatic Method OC method1011 (FFF)F
L213:   invokevirtual Method DF method606 (FFF)V
L216:   return
L217:   
        .attribute StackMap b'\x00\x04\x00\x16\x00\x00\x00\x01\x07\x00\x31\x00\x17\x00\x01\x07\x00\x02\x00\x00\x00\x7B\x00\x02\x07\x00\x02\x01\x00\x00\x00\x94\x00\x02\x07\x00\x02\x01\x00\x00'
    .end code
.end method

.method public method718 : (FFFLsE;)V
    .code stack 12 locals 5
L0:     fload_3
L1:     aload_0
L2:     dup_x1
L3:     fload_2
L4:     fload_1
L5:     aload_0
L6:     dup
L7:     dup_x2
L8:     fload_1
L9:     fload_2
L10:    fload_3
L11:    aload 4
L13:    invokespecial Method qB method718 (FFFLsE;)V
L16:    getfield Field Sb field1445 LDF;
L19:    fload_1
L20:    fload_2
L21:    fload_3
L22:    invokevirtual Method DF method606 (FFF)V
L25:    putfield Field Sb field1446 F
L28:    putfield Field Sb new F
L31:    putfield Field Sb field1442 F
L34:    return
L35:    
    .end code
.end method

.method public <init> : (LLD;)V
    .code stack 7 locals 2
L0:     aload_0
L1:     dup
L2:     dup_x1
L3:     aload_1
L4:     ldc "Pending lines"
L6:     invokespecial Method qB <init> (LLD;Ljava/lang/String;)V
L9:     new DF
L12:    aload_0
L13:    dup_x2
L14:    dup
L15:    pop2
L16:    dup
L17:    ldc "0"
L19:    getstatic Field We field469 LWe;
L22:    invokespecial Method DF <init> (Ljava/lang/String;LWe;)V
L25:    putfield Field Sb field1445 LDF;
L28:    getfield Field Sb field1445 LDF;
L31:    getstatic Field vD field358 LvD;
L34:    invokevirtual Method DF method610 (LvD;)V
L37:    getfield Field Sb field1430 LLD;
L40:    aload_0
L41:    getfield Field Sb field1445 LDF;
L44:    invokevirtual Method LD method36 (LgB;)LgB;
L47:    pop
L48:    return
L49:    
    .end code
.end method

.method public method715 : (FF)V
    .code stack 4 locals 3
L0:     aload_0
L1:     dup
L2:     fload_1
L3:     fload_2
L4:     invokespecial Method qB method715 (FF)V
L7:     getfield Field Sb field1445 LDF;
L10:    fload_2
L11:    invokevirtual Method DF method102 (F)V
L14:    return
L15:    
    .end code
.end method

.method public method714 : ()V
    .code stack 6 locals 1
L0:     aload_0
L1:     dup
L2:     dup_x1
L3:     invokespecial Method qB method714 ()V
L6:     dup
L7:     getfield Field Sb field1443 F
L10:    getstatic Field ib field2312 F
L13:    fconst_2
L14:    fmul
L15:    fsub
L16:    putfield Field Sb field1443 F
L19:    getfield Field Sb field1443 F
L22:    fconst_0
L23:    fcmpg
L24:    ifge L80
L27:    aload_0
L28:    getfield Field Sb field1443 F
L31:    getstatic Field ib field2312 F
L34:    fneg
L35:    fconst_2
L36:    fmul
L37:    fcmpl
L38:    ifle L73
L41:    aload_0
L42:    dup
L43:    getfield Field Sb field1445 LDF;
L46:    swap
L47:    getfield Field Sb field1430 LLD;
L50:    getfield Field LD field1134 F
L53:    aload_0
L54:    getfield Field Sb this F
L57:    fadd
L58:    aload_0
L59:    getfield Field Sb field1430 LLD;
L62:    getfield Field LD field1126 F
L65:    aload_0
L66:    getfield Field Sb try F
L69:    fadd
L70:    invokevirtual Method DF method37 (FF)V
L73:    aload_0
L74:    fconst_0
L75:    putfield Field Sb field1443 F
L78:    return
L79:    athrow
L80:    aload_0
L81:    dup
L82:    getfield Field Sb field1445 LDF;
L85:    swap
L86:    getfield Field Sb field1430 LLD;
L89:    getfield Field LD field1134 F
L92:    aload_0
L93:    getfield Field Sb this F
L96:    fadd
L97:    aload_0
L98:    getfield Field Sb field1440 F
L101:   invokestatic Method java/lang/Math random ()D
L104:   d2f
L105:   ldc 5e-1f
L107:   fsub
L108:   fmul
L109:   aload_0
L110:   getfield Field Sb field1443 F
L113:   fmul
L114:   fadd
L115:   aload_0
L116:   getfield Field Sb field1430 LLD;
L119:   getfield Field LD field1126 F
L122:   aload_0
L123:   getfield Field Sb try F
L126:   fadd
L127:   aload_0
L128:   getfield Field Sb field1440 F
L131:   invokestatic Method java/lang/Math random ()D
L134:   d2f
L135:   ldc 5e-1f
L137:   fsub
L138:   fmul
L139:   aload_0
L140:   getfield Field Sb field1443 F
L143:   fmul
L144:   fadd
L145:   invokevirtual Method DF method37 (FF)V
L148:   return
L149:   
        .attribute StackMap b'\x00\x03\x00\x49\x00\x01\x07\x00\x02\x00\x00\x00\x4F\x00\x00\x00\x01\x07\x00\x31\x00\x50\x00\x01\x07\x00\x02\x00\x00'
    .end code
.end method

.method public method719 : ()V
    .code stack 2 locals 1
L0:     aload_0
L1:     getstatic Field ib field2312 F
L4:     putfield Field Sb field1443 F
L7:     return
L8:     
    .end code
.end method

.method public method717 : (FFF)V
    .code stack 12 locals 4
L0:     aload_0
L1:     dup
L2:     dup_x1
L3:     fload_3
L4:     aload_0
L5:     dup_x2
L6:     fload_2
L7:     aload_0
L8:     fload_1
L9:     dup_x1
L10:    fload_2
L11:    fload_3
L12:    invokespecial Method qB method717 (FFF)V
L15:    aload_0
L16:    dup_x1
L17:    getfield Field Sb field1430 LLD;
L20:    getfield Field LD field1134 F
L23:    fsub
L24:    putfield Field Sb this F
L27:    fload_3
L28:    fadd
L29:    aload_0
L30:    getfield Field Sb field1430 LLD;
L33:    getfield Field LD field1126 F
L36:    fsub
L37:    putfield Field Sb try F
L40:    putfield Field Sb field1440 F
L43:    getfield Field Sb field1445 LDF;
L46:    fload_1
L47:    fload_2
L48:    fload_3
L49:    fadd
L50:    invokevirtual Method DF method37 (FF)V
L53:    getfield Field Sb field1445 LDF;
L56:    fload_3
L57:    ldc 4e0f
L59:    fmul
L60:    fload_3
L61:    ldc 2.8e0f
L63:    fmul
L64:    invokevirtual Method DF method32 (FF)V
L67:    getfield Field Sb field1445 LDF;
L70:    fload_3
L71:    ldc 1.4e0f
L73:    dup
L74:    aload_0
L75:    getfield Field Sb field1441 F
L78:    fmul
L79:    fadd
L80:    fmul
L81:    invokevirtual Method DF method104 (F)V
L84:    return
L85:    
    .end code
.end method

.method public method726 : ()D
    .code stack 2 locals 1
L0:     ldc2_w 3e0
L3:     dreturn
L4:     
    .end code
.end method
.innerclasses
    vD DF [0] public static final enum
.end innerclasses
.end class
