.version 49 0
.class public final super sb
.super qc
.implements G
.implements d
.field private field159 LlF;
.field private field160 LUb;
.field private field161 Ljava/util/ArrayList;
.field public field162 Lqd;
.field private field163 F
.field private field164 Lbb;
.field private field165 LgB;
.field private try F
.field private field166 Z
.field private new LUb;
.field private field167 Ljava/util/LinkedHashMap;
.field private this I
.field private field168 Lod;
.field private field169 LgB;
.field private field170 LlF;
.field private field171 LId;

.method public method8 : (LD;)V
    .code stack 7 locals 6
L0:     aload_1
L1:     instanceof Re
L4:     ifeq L139
L7:     aload_0
L8:     getfield Field sb field162 Lqd;
L11:    getfield Field qd field761 Leb;
L14:    instanceof sg
L17:    ifeq L752
L20:    aload_1
L21:    checkcast Re
L24:    astore_2
L25:    aload_0
L26:    getfield Field sb field162 Lqd;
L29:    getfield Field qd new Ljava/util/LinkedHashMap;
L32:    aload_2
L33:    getfield Field Re field902 Led;
L36:    invokevirtual Method java/util/LinkedHashMap get (Ljava/lang/Object;)Ljava/lang/Object;
L39:    checkcast Rg
L42:    dup
L43:    astore_3
L44:    ifnull L752
L47:    aload_3
L48:    invokevirtual Method Rg method237 ()I
L51:    dup
L52:    istore 4
L54:    aload_0
L55:    getfield Field sb this I
L58:    if_icmpge L752
L61:    aload_0
L62:    dup
L63:    iload 4
L65:    putfield Field sb this I
L68:    getfield Field sb field162 Lqd;
L71:    getfield Field qd new Ljava/util/LinkedHashMap;
L74:    invokevirtual Method java/util/LinkedHashMap values ()Ljava/util/Collection;
L77:    invokeinterface InterfaceMethod java/util/Collection iterator ()Ljava/util/Iterator; 1
L82:    astore 4
L84:    aload 4
L86:    invokeinterface InterfaceMethod java/util/Iterator hasNext ()Z 1
L91:    ifeq L752
L94:    aload 4
L96:    invokeinterface InterfaceMethod java/util/Iterator next ()Ljava/lang/Object; 1
L101:   checkcast Rg
L104:   astore 5
L106:   aload_0
L107:   aload 5
L109:   invokevirtual Method sb method139 (LRg;)LLD;
L112:   dup
L113:   astore 5
L115:   ifnull L84
L118:   aload 5
L120:   bipush 28
L122:   iconst_1
L123:   dup
L124:   pop2
L125:   aload_0
L126:   getfield Field sb this I
L129:   isub
L130:   invokevirtual Method LD method115 (I)V
L133:   goto L84
L136:   nop
L137:   nop
L138:   athrow
L139:   aload_1
L140:   instanceof LF
L143:   ifeq L222
L146:   aload_1
L147:   checkcast LF
L150:   astore_2
L151:   aload_0
L152:   getfield Field sb field162 Lqd;
L155:   getfield Field qd new Ljava/util/LinkedHashMap;
L158:   aload_2
L159:   getfield Field LF field953 Led;
L162:   invokevirtual Method java/util/LinkedHashMap get (Ljava/lang/Object;)Ljava/lang/Object;
L165:   checkcast Rg
L168:   getfield Field Rg field227 LqE;
L171:   dup
L172:   astore_3
L173:   getstatic Field qE field627 LqE;
L176:   if_acmpeq L752
L179:   aload_3
L180:   getstatic Field qE try LqE;
L183:   if_acmpeq L752
L186:   aload_3
L187:   getstatic Field qE field630 LqE;
L190:   if_acmpeq L752
L193:   aload_3
L194:   getstatic Field qE field628 LqE;
L197:   if_acmpeq L752
L200:   aload_0
L201:   dup
L202:   getfield Field sb field162 Lqd;
L205:   getfield Field qd new Ljava/util/LinkedHashMap;
L208:   aload_2
L209:   getfield Field LF field953 Led;
L212:   invokevirtual Method java/util/LinkedHashMap get (Ljava/lang/Object;)Ljava/lang/Object;
L215:   checkcast Rg
L218:   invokespecial Method sb method140 (LRg;)V
L221:   return
L222:   aload_1
L223:   instanceof xC
L226:   ifeq L518
L229:   aload_1
L230:   checkcast xC
L233:   astore_2
L234:   getstatic Field OD field2040 [I
L237:   aload_2
L238:   getfield Field xC field888 LQB;
L241:   invokevirtual Method QB ordinal ()I
L244:   iaload
L245:   tableswitch 1
            L276
            L281
            L506
            L517
            default : L517
L276:   return
L277:   nop
L278:   nop
L279:   nop
L280:   athrow
L281:   aload_0
L282:   getfield Field sb field159 LlF;
L285:   invokevirtual Method lF method134 ()I
L288:   ifeq L491
L291:   aload_0
L292:   getfield Field sb field161 Ljava/util/ArrayList;
L295:   invokevirtual Method java/util/ArrayList size ()I
L298:   ifle L491
L301:   aload_0
L302:   getfield Field sb field161 Ljava/util/ArrayList;
L305:   iconst_0
L306:   iconst_1
L307:   dup
L308:   pop2
L309:   invokevirtual Method java/util/ArrayList get (I)Ljava/lang/Object;
L312:   checkcast LD
L315:   getfield Field LD field137 LRg;
L318:   getfield Field Rg field227 LqE;
L321:   getstatic Field qE field627 LqE;
L324:   if_acmpeq L491
L327:   aload_0
L328:   getfield Field sb field161 Ljava/util/ArrayList;
L331:   iconst_0
L332:   iconst_1
L333:   dup
L334:   pop2
L335:   invokevirtual Method java/util/ArrayList get (I)Ljava/lang/Object;
L338:   checkcast LD
L341:   getfield Field LD field137 LRg;
L344:   getfield Field Rg field227 LqE;
L347:   getstatic Field qE field628 LqE;
L350:   if_acmpeq L491
L353:   aload_0
L354:   getfield Field sb field159 LlF;
L357:   invokevirtual Method lF method498 ()LgB;
L360:   aload_0
L361:   getfield Field sb field169 LgB;
L364:   if_acmpne L411
L367:   ldc ""
L369:   aload_0
L370:   getfield Field sb new LUb;
L373:   getfield Field Ub new Lnf;
L376:   invokevirtual Method nf method426 ()Ljava/lang/String;
L379:   invokevirtual Method java/lang/String equals (Ljava/lang/Object;)Z
L382:   ifeq L491
L385:   aload_0
L386:   dup
L387:   dup_x1
L388:   getfield Field sb field159 LlF;
L391:   iconst_0
L392:   iconst_1
L393:   dup
L394:   pop2
L395:   invokevirtual Method lF method14 (I)V
L398:   getfield Field sb field170 LlF;
L401:   iconst_0
L402:   iconst_1
L403:   dup
L404:   pop2
L405:   invokevirtual Method lF method14 (I)V
L408:   goto L492
L411:   aload_0
L412:   getfield Field sb field159 LlF;
L415:   invokevirtual Method lF method498 ()LgB;
L418:   aload_0
L419:   getfield Field sb field165 LgB;
L422:   if_acmpne L469
L425:   ldc ""
L427:   aload_0
L428:   getfield Field sb field160 LUb;
L431:   getfield Field Ub new Lnf;
L434:   invokevirtual Method nf method426 ()Ljava/lang/String;
L437:   invokevirtual Method java/lang/String equals (Ljava/lang/Object;)Z
L440:   ifeq L491
L443:   aload_0
L444:   dup
L445:   dup_x1
L446:   getfield Field sb field159 LlF;
L449:   iconst_0
L450:   iconst_1
L451:   dup
L452:   pop2
L453:   invokevirtual Method lF method14 (I)V
L456:   getfield Field sb field170 LlF;
L459:   iconst_0
L460:   iconst_1
L461:   dup
L462:   pop2
L463:   invokevirtual Method lF method14 (I)V
L466:   goto L492
L469:   aload_0
L470:   dup
L471:   getfield Field sb field159 LlF;
L474:   iconst_0
L475:   iconst_1
L476:   dup
L477:   pop2
L478:   invokevirtual Method lF method14 (I)V
L481:   getfield Field sb field170 LlF;
L484:   iconst_0
L485:   iconst_1
L486:   dup
L487:   pop2
L488:   invokevirtual Method lF method14 (I)V
L491:   aload_0
L492:   fconst_2
L493:   putfield Field sb try F
L496:   aload_0
L497:   bipush 28
L499:   iconst_1
L500:   dup
L501:   pop2
L502:   putfield Field sb this I
L505:   return
L506:   aload_0
L507:   getfield Field sb field167 Ljava/util/LinkedHashMap;
L510:   invokevirtual Method java/util/LinkedHashMap clear ()V
L513:   return
L514:   nop
L515:   nop
L516:   athrow
L517:   return
L518:   aload_1
L519:   instanceof pc
L522:   ifeq L582
L525:   aload_1
L526:   checkcast pc
L529:   astore_2
L530:   aload_0
L531:   getfield Field sb field162 Lqd;
L534:   getfield Field qd new Ljava/util/LinkedHashMap;
L537:   aload_2
L538:   getfield Field pc field943 Led;
L541:   invokevirtual Method java/util/LinkedHashMap get (Ljava/lang/Object;)Ljava/lang/Object;
L544:   instanceof oF
L547:   ifeq L752
L550:   aload_0
L551:   getfield Field sb field171 LId;
L554:   getstatic Field Id field638 LId;
L557:   if_acmpeq L752
L560:   aload_0
L561:   dup
L562:   getfield Field sb field162 Lqd;
L565:   getfield Field qd new Ljava/util/LinkedHashMap;
L568:   aload_2
L569:   getfield Field pc field943 Led;
L572:   invokevirtual Method java/util/LinkedHashMap get (Ljava/lang/Object;)Ljava/lang/Object;
L575:   checkcast Rg
L578:   invokespecial Method sb method140 (LRg;)V
L581:   return
L582:   aload_1
L583:   instanceof uE
L586:   ifeq L752
L589:   aload_1
L590:   checkcast uE
L593:   dup
L594:   astore_2
L595:   dup
L596:   getfield Field uE field939 Led;
L599:   swap
L600:   getfield Field uE field941 Led;
L603:   if_acmpne L648
L606:   aload_0
L607:   getfield Field sb field162 Lqd;
L610:   getfield Field qd field761 Leb;
L613:   invokevirtual Method eb method768 ()Z
L616:   ifeq L752
L619:   aload_0
L620:   getfield Field sb field166 Z
L623:   ifne L752
L626:   getstatic Field zg this Lzg;
L629:   aload_0
L630:   aload_2
L631:   getfield Field uE field941 Led;
L634:   invokevirtual Method sb method138 (Led;)LLD;
L637:   getfield Field LD field92 F
L640:   ldc_w 5e-1f
L643:   fmul
L644:   invokestatic Method UE method422 (Lzg;F)V
L647:   return
L648:   aload_0
L649:   getfield Field sb field167 Ljava/util/LinkedHashMap;
L652:   aload_2
L653:   getfield Field uE field939 Led;
L656:   invokevirtual Method java/util/LinkedHashMap containsKey (Ljava/lang/Object;)Z
L659:   ifne L692
L662:   aload_0
L663:   getfield Field sb field167 Ljava/util/LinkedHashMap;
L666:   aload_2
L667:   getfield Field uE field939 Led;
L670:   new Dc
L673:   dup
L674:   fconst_0
L675:   invokestatic Method java/lang/Float valueOf (F)Ljava/lang/Float;
L678:   new java/util/LinkedList
L681:   dup
L682:   invokespecial Method java/util/LinkedList <init> ()V
L685:   invokespecial Method Dc <init> (Ljava/lang/Object;Ljava/lang/Object;)V
L688:   invokevirtual Method java/util/LinkedHashMap put (Ljava/lang/Object;Ljava/lang/Object;)Ljava/lang/Object;
L691:   pop
L692:   iconst_0
L693:   iconst_1
L694:   dup
L695:   pop2
L696:   dup
L697:   istore_3
L698:   aload_2
L699:   getfield Field uE field942 I
L702:   if_icmpge L752
L705:   aload_0
L706:   getfield Field sb field167 Ljava/util/LinkedHashMap;
L709:   aload_2
L710:   getfield Field uE field939 Led;
L713:   invokevirtual Method java/util/LinkedHashMap get (Ljava/lang/Object;)Ljava/lang/Object;
L716:   checkcast Dc
L719:   getfield Field Dc field1794 Ljava/lang/Object;
L722:   checkcast java/util/LinkedList
L725:   new Dc
L728:   dup
L729:   aload_2
L730:   dup
L731:   getfield Field uE field941 Led;
L734:   swap
L735:   iinc 3 1
L738:   getfield Field uE field940 [I
L741:   invokespecial Method Dc <init> (Ljava/lang/Object;Ljava/lang/Object;)V
L744:   invokevirtual Method java/util/LinkedList add (Ljava/lang/Object;)Z
L747:   pop
L748:   iload_3
L749:   goto L698
L752:   return
L753:   
        .attribute StackMap b'\x00\x14\x00\x54\x00\x05\x07\x00\x02\x07\x00\x69\x07\x00\x41\x07\x00\x57\x07\x00\x6B\x00\x00\x00\x88\x00\x00\x00\x01\x07\x00\x7F\x00\x8B\x00\x02\x07\x00\x02\x07\x00\x69\x00\x00\x00\xDE\x00\x02\x07\x00\x02\x07\x00\x69\x00\x00\x01\x14\x00\x03\x07\x00\x02\x07\x00\x69\x07\x00\x9B\x00\x00\x01\x15\x00\x00\x00\x01\x07\x00\x7F\x01\x19\x00\x03\x07\x00\x02\x07\x00\x69\x07\x00\x9B\x00\x00\x01\x9B\x00\x03\x07\x00\x02\x07\x00\x69\x07\x00\x9B\x00\x00\x01\xD5\x00\x03\x07\x00\x02\x07\x00\x69\x07\x00\x9B\x00\x00\x01\xEB\x00\x03\x07\x00\x02\x07\x00\x69\x07\x00\x9B\x00\x00\x01\xEC\x00\x03\x07\x00\x02\x07\x00\x69\x07\x00\x9B\x00\x01\x07\x00\x02\x01\xFA\x00\x03\x07\x00\x02\x07\x00\x69\x07\x00\x9B\x00\x00\x02\x02\x00\x00\x00\x01\x07\x00\x7F\x02\x05\x00\x03\x07\x00\x02\x07\x00\x69\x07\x00\x9B\x00\x00\x02\x06\x00\x02\x07\x00\x02\x07\x00\x69\x00\x00\x02\x46\x00\x02\x07\x00\x02\x07\x00\x69\x00\x00\x02\x88\x00\x03\x07\x00\x02\x07\x00\x69\x07\x00\xF5\x00\x00\x02\xB4\x00\x03\x07\x00\x02\x07\x00\x69\x07\x00\xF5\x00\x00\x02\xBA\x00\x04\x07\x00\x02\x07\x00\x69\x07\x00\xF5\x01\x00\x01\x01\x02\xF0\x00\x02\x07\x00\x02\x07\x00\x69\x00\x00'
    .end code
.end method

.method public method2 : ()V
    .code stack 2 locals 1
L0:     aload_0
L1:     dup
L2:     invokespecial Method qc method2 ()V
L5:     getfield Field sb field162 Lqd;
L8:     ifnull L19
L11:    aload_0
L12:    getfield Field sb field162 Lqd;
L15:    aload_0
L16:    invokevirtual Method qd method401 (LG;)V
L19:    return
L20:    
        .attribute StackMap b'\x00\x01\x00\x13\x00\x01\x07\x00\x02\x00\x00'
    .end code
.end method

.method public method95 : (Z)V
    .code stack 3 locals 3
L0:     aload_0
L1:     dup
L2:     iload_1
L3:     putfield Field sb field166 Z
L6:     getfield Field sb field166 Z
L9:     ifeq L88
L12:    aload_0
L13:    getfield Field sb field161 Ljava/util/ArrayList;
L16:    invokevirtual Method java/util/ArrayList iterator ()Ljava/util/Iterator;
L19:    dup
L20:    astore_1
L21:    invokeinterface InterfaceMethod java/util/Iterator hasNext ()Z 1
L26:    ifeq L48
L29:    aload_1
L30:    invokeinterface InterfaceMethod java/util/Iterator next ()Ljava/lang/Object; 1
L35:    checkcast LD
L38:    astore_2
L39:    aload_1
L40:    aload_2
L41:    invokevirtual Method LD try ()V
L44:    goto L21
L47:    athrow
L48:    aload_0
L49:    getfield Field sb field168 Lod;
L52:    getfield Field od field978 Ljava/util/LinkedList;
L55:    invokevirtual Method java/util/LinkedList iterator ()Ljava/util/Iterator;
L58:    dup
L59:    astore_1
L60:    invokeinterface InterfaceMethod java/util/Iterator hasNext ()Z 1
L65:    ifeq L161
L68:    aload_1
L69:    invokeinterface InterfaceMethod java/util/Iterator next ()Ljava/lang/Object; 1
L74:    checkcast LD
L77:    astore_2
L78:    aload_1
L79:    aload_2
L80:    invokevirtual Method LD try ()V
L83:    goto L60
L86:    nop
L87:    athrow
L88:    aload_0
L89:    getfield Field sb field161 Ljava/util/ArrayList;
L92:    invokevirtual Method java/util/ArrayList iterator ()Ljava/util/Iterator;
L95:    dup
L96:    astore_1
L97:    invokeinterface InterfaceMethod java/util/Iterator hasNext ()Z 1
L102:   ifeq L123
L105:   aload_1
L106:   invokeinterface InterfaceMethod java/util/Iterator next ()Ljava/lang/Object; 1
L111:   checkcast LD
L114:   astore_2
L115:   aload_1
L116:   aload_2
L117:   invokevirtual Method LD method120 ()V
L120:   goto L97
L123:   aload_0
L124:   getfield Field sb field168 Lod;
L127:   getfield Field od field978 Ljava/util/LinkedList;
L130:   invokevirtual Method java/util/LinkedList iterator ()Ljava/util/Iterator;
L133:   dup
L134:   astore_1
L135:   invokeinterface InterfaceMethod java/util/Iterator hasNext ()Z 1
L140:   ifeq L161
L143:   aload_1
L144:   invokeinterface InterfaceMethod java/util/Iterator next ()Ljava/lang/Object; 1
L149:   checkcast LD
L152:   astore_2
L153:   aload_1
L154:   aload_2
L155:   invokevirtual Method LD method120 ()V
L158:   goto L135
L161:   return
L162:   
        .attribute StackMap b'\x00\x0A\x00\x15\x00\x02\x07\x00\x02\x07\x00\x6B\x00\x01\x07\x00\x6B\x00\x2F\x00\x00\x00\x01\x07\x00\x7F\x00\x30\x00\x02\x07\x00\x02\x07\x00\x6B\x00\x00\x00\x3C\x00\x02\x07\x00\x02\x07\x00\x6B\x00\x01\x07\x00\x6B\x00\x56\x00\x00\x00\x01\x07\x00\x7F\x00\x58\x00\x02\x07\x00\x02\x01\x00\x00\x00\x61\x00\x02\x07\x00\x02\x07\x00\x6B\x00\x01\x07\x00\x6B\x00\x7B\x00\x02\x07\x00\x02\x07\x00\x6B\x00\x00\x00\x87\x00\x02\x07\x00\x02\x07\x00\x6B\x00\x01\x07\x00\x6B\x00\xA1\x00\x02\x07\x00\x02\x07\x00\x6B\x00\x00'
    .end code
.end method

.method public method48 : (LgB;IC)Z
    .code stack 3 locals 5
L0:     iload_2
L1:     ldc_w "j"
L4:     invokestatic Method JB method831 (Ljava/lang/String;)I
L7:     if_icmpne L16
L10:    iconst_1
L11:    dup
L12:    dup
L13:    pop2
L14:    ireturn
L15:    athrow
L16:    aload_0
L17:    getfield Field sb field159 LlF;
L20:    invokevirtual Method lF method498 ()LgB;
L23:    aload_0
L24:    getfield Field sb field169 LgB;
L27:    if_acmpeq L44
L30:    aload_0
L31:    getfield Field sb field170 LlF;
L34:    invokevirtual Method lF method498 ()LgB;
L37:    aload_0
L38:    getfield Field sb field169 LgB;
L41:    if_acmpne L57
L44:    aload_0
L45:    getfield Field sb new LUb;
L48:    invokevirtual Method Ub method10 ()V
L51:    iconst_0
L52:    iconst_1
L53:    dup
L54:    pop2
L55:    ireturn
L56:    athrow
L57:    aload_0
L58:    getfield Field sb field159 LlF;
L61:    invokevirtual Method lF method498 ()LgB;
L64:    aload_0
L65:    getfield Field sb field165 LgB;
L68:    if_acmpeq L85
L71:    aload_0
L72:    getfield Field sb field170 LlF;
L75:    invokevirtual Method lF method498 ()LgB;
L78:    aload_0
L79:    getfield Field sb field165 LgB;
L82:    if_acmpne L97
L85:    aload_0
L86:    getfield Field sb field160 LUb;
L89:    invokevirtual Method Ub method10 ()V
L92:    iconst_0
L93:    iconst_1
L94:    dup
L95:    pop2
L96:    ireturn
L97:    iconst_0
L98:    iconst_1
L99:    dup
L100:   pop2
L101:   istore_1
L102:   aload_0
L103:   getfield Field sb field161 Ljava/util/ArrayList;
L106:   invokevirtual Method java/util/ArrayList iterator ()Ljava/util/Iterator;
L109:   astore_3
L110:   aload_3
L111:   invokeinterface InterfaceMethod java/util/Iterator hasNext ()Z 1
L116:   ifeq L161
L119:   aload_3
L120:   invokeinterface InterfaceMethod java/util/Iterator next ()Ljava/lang/Object; 1
L125:   checkcast LD
L128:   dup
L129:   astore 4
L131:   getfield Field LD field137 LRg;
L134:   getfield Field Rg field227 LqE;
L137:   getstatic Field qE field630 LqE;
L140:   if_acmpeq L110
L143:   iload_1
L144:   aload 4
L146:   getfield Field LD field137 LRg;
L149:   checkcast oF
L152:   iload_2
L153:   invokevirtual Method oF method382 (I)Z
L156:   ior
L157:   istore_1
L158:   goto L110
L161:   iload_1
L162:   ireturn
L163:   
        .attribute StackMap b'\x00\x09\x00\x0F\x00\x00\x00\x01\x07\x00\x7F\x00\x10\x00\x04\x07\x00\x02\x07\x01\x57\x01\x01\x00\x00\x00\x2C\x00\x04\x07\x00\x02\x07\x01\x57\x01\x01\x00\x00\x00\x38\x00\x00\x00\x01\x07\x00\x7F\x00\x39\x00\x04\x07\x00\x02\x07\x01\x57\x01\x01\x00\x00\x00\x55\x00\x04\x07\x00\x02\x07\x01\x57\x01\x01\x00\x00\x00\x61\x00\x04\x07\x00\x02\x07\x01\x57\x01\x01\x00\x00\x00\x6E\x00\x04\x07\x00\x02\x01\x01\x07\x00\x6B\x00\x00\x00\xA1\x00\x04\x07\x00\x02\x01\x01\x07\x00\x6B\x00\x00'
    .end code
.end method

.method public <init> : (LId;Lqd;)V
    .code stack 12 locals 3
L0:     aload_0
L1:     dup
L2:     aload_1
L3:     aload_0
L4:     dup
L5:     dup_x2
L6:     aload_2
L7:     new sF
L10:    aload_0
L11:    dup_x1
L12:    dup_x1
L13:    dup
L14:    pop2
L15:    dup
L16:    invokespecial Method sF <init> ()V
L19:    invokespecial Method qc <init> (Ld;)V
L22:    new java/util/LinkedHashMap
L25:    aload_0
L26:    dup_x2
L27:    dup
L28:    pop2
L29:    dup
L30:    invokespecial Method java/util/LinkedHashMap <init> ()V
L33:    putfield Field sb field167 Ljava/util/LinkedHashMap;
L36:    new java/util/ArrayList
L39:    aload_0
L40:    dup
L41:    pop2
L42:    dup
L43:    invokespecial Method java/util/ArrayList <init> ()V
L46:    putfield Field sb field161 Ljava/util/ArrayList;
L49:    putfield Field sb field162 Lqd;
L52:    getfield Field sb field162 Lqd;
L55:    aload_0
L56:    getstatic Field mc field387 Lmc;
L59:    invokevirtual Method qd method408 (LG;Lmc;)V
L62:    putfield Field sb field171 LId;
L65:    new bb
L68:    aload_0
L69:    dup_x2
L70:    dup
L71:    pop2
L72:    dup
L73:    invokespecial Method bb <init> ()V
L76:    putfield Field sb field164 Lbb;
L79:    getfield Field sb field164 Lbb;
L82:    invokevirtual Method sb method36 (LgB;)LgB;
L85:    iconst_0
L86:    aload_0
L87:    dup_x1
L88:    dup
L89:    dup_x2
L90:    aload_0
L91:    fconst_0
L92:    putfield Field sb try F
L95:    new lF
L98:    aload_0
L99:    dup
L100:   pop2
L101:   dup
L102:   invokespecial Method lF <init> ()V
L105:   putfield Field sb field159 LlF;
L108:   new lF
L111:   aload_0
L112:   dup
L113:   pop2
L114:   dup
L115:   invokespecial Method lF <init> ()V
L118:   putfield Field sb field170 LlF;
L121:   iconst_1
L122:   dup
L123:   pop2
L124:   putfield Field sb field166 Z
L127:   new od
L130:   aload_0
L131:   dup_x2
L132:   dup
L133:   pop2
L134:   dup
L135:   aload_2
L136:   aload_1
L137:   invokespecial Method od <init> (Lqd;LId;)V
L140:   putfield Field sb field168 Lod;
L143:   invokespecial Method sb method74 ()V
L146:   pop
L147:   getstatic Field OD field2041 [I
L150:   aload_0
L151:   getfield Field sb field171 LId;
L154:   invokevirtual Method Id ordinal ()I
L157:   iaload
L158:   tableswitch 1
            L208
            L226
            L257
            L276
            L280
            L289
            L308
            L359
            L507
            default : L521
L208:   aload_0
L209:   iconst_0
L210:   ifne L504
L213:   getfield Field sb field170 LlF;
L216:   ldc_w "Opponents"
L219:   aload_0
L220:   getfield Field sb field168 Lod;
L223:   invokevirtual Method lF method182 (Ljava/lang/String;LgB;)V
L226:   aload_0
L227:   fconst_1
L228:   aload_0
L229:   dup_x1
L230:   getfield Field sb field170 LlF;
L233:   ldc_w "Stats"
L236:   new RD
L239:   dup
L240:   aload_0
L241:   getfield Field sb field162 Lqd;
L244:   invokespecial Method RD <init> (Lqd;)V
L247:   invokevirtual Method lF method182 (Ljava/lang/String;LgB;)V
L250:   putfield Field sb field163 F
L253:   goto L522
L256:   athrow
L257:   aload_0
L258:   fconst_1
L259:   aload_0
L260:   getfield Field sb field170 LlF;
L263:   ldc_w "Opponents"
L266:   aload_0
L267:   getfield Field sb field168 Lod;
L270:   invokevirtual Method lF method182 (Ljava/lang/String;LgB;)V
L273:   putfield Field sb field163 F
L276:   goto L521
L279:   athrow
L280:   aload_0
L281:   dup
L282:   fconst_1
L283:   putfield Field sb field163 F
L286:   goto L522
L289:   aload_0
L290:   fconst_1
L291:   aload_0
L292:   getfield Field sb field170 LlF;
L295:   ldc_w "Opponents"
L298:   aload_0
L299:   getfield Field sb field168 Lod;
L302:   invokevirtual Method lF method182 (Ljava/lang/String;LgB;)V
L305:   putfield Field sb field163 F
L308:   aload_0
L309:   dup
L310:   new CD
L313:   dup
L314:   invokespecial Method CD <init> ()V
L317:   putfield Field sb new LUb;
L320:   getfield Field sb field159 LlF;
L323:   aload_0
L324:   getfield Field sb new LUb;
L327:   invokevirtual Method Ub method13 ()Ljava/lang/String;
L330:   new SB
L333:   aload_0
L334:   dup
L335:   pop2
L336:   dup
L337:   aload_0
L338:   dup_x2
L339:   getfield Field sb new LUb;
L342:   ldc_w 2e-1f
L345:   invokespecial Method SB <init> (LgB;F)V
L348:   dup_x1
L349:   putfield Field sb field169 LgB;
L352:   invokevirtual Method lF method182 (Ljava/lang/String;LgB;)V
L355:   aload_0
L356:   goto L522
L359:   aload_0
L360:   new AB
L363:   dup
L364:   aload_0
L365:   dup_x2
L366:   getfield Field sb field162 Lqd;
L369:   invokespecial Method AB <init> (Lqd;)V
L372:   putfield Field sb field160 LUb;
L375:   getfield Field sb field159 LlF;
L378:   aload_0
L379:   getfield Field sb field160 LUb;
L382:   invokevirtual Method Ub method13 ()Ljava/lang/String;
L385:   new SB
L388:   aload_0
L389:   dup
L390:   pop2
L391:   dup
L392:   aload_0
L393:   dup_x2
L394:   getfield Field sb field160 LUb;
L397:   ldc_w 2e-1f
L400:   invokespecial Method SB <init> (LgB;F)V
L403:   dup_x1
L404:   putfield Field sb field165 LgB;
L407:   invokevirtual Method lF method182 (Ljava/lang/String;LgB;)V
L410:   new CD
L413:   aload_0
L414:   dup_x1
L415:   dup_x2
L416:   dup
L417:   pop2
L418:   dup
L419:   invokespecial Method CD <init> ()V
L422:   putfield Field sb new LUb;
L425:   getfield Field sb field159 LlF;
L428:   aload_0
L429:   getfield Field sb new LUb;
L432:   invokevirtual Method Ub method13 ()Ljava/lang/String;
L435:   new SB
L438:   aload_0
L439:   dup
L440:   pop2
L441:   dup
L442:   aload_0
L443:   dup_x2
L444:   getfield Field sb new LUb;
L447:   ldc_w 2e-1f
L450:   invokespecial Method SB <init> (LgB;F)V
L453:   dup_x1
L454:   putfield Field sb field169 LgB;
L457:   invokevirtual Method lF method182 (Ljava/lang/String;LgB;)V
L460:   fconst_1
L461:   aload_0
L462:   dup_x1
L463:   dup_x2
L464:   aload_0
L465:   getfield Field sb field170 LlF;
L468:   ldc_w "Opponents"
L471:   aload_0
L472:   getfield Field sb field168 Lod;
L475:   invokevirtual Method lF method182 (Ljava/lang/String;LgB;)V
L478:   getfield Field sb field170 LlF;
L481:   ldc_w "Stats"
L484:   new RD
L487:   dup
L488:   aload_0
L489:   getfield Field sb field162 Lqd;
L492:   invokespecial Method RD <init> (Lqd;)V
L495:   invokevirtual Method lF method182 (Ljava/lang/String;LgB;)V
L498:   putfield Field sb field163 F
L501:   goto L522
L504:   goto L209
L507:   aload_0
L508:   dup
L509:   getfield Field sb field168 Lod;
L512:   invokevirtual Method sb method36 (LgB;)LgB;
L515:   aload_0
L516:   fconst_0
L517:   putfield Field sb field163 F
L520:   pop
L521:   aload_0
L522:   aload_0
L523:   getfield Field sb field159 LlF;
L526:   invokevirtual Method sb method36 (LgB;)LgB;
L529:   aload_0
L530:   dup
L531:   getfield Field sb field170 LlF;
L534:   invokevirtual Method sb method36 (LgB;)LgB;
L537:   aload_0
L538:   dup
L539:   invokevirtual Method sb method34 (Ld;)V
L542:   pop2
L543:   return
L544:   
        .attribute StackMap b'\x00\x0F\x00\xD0\x00\x03\x07\x00\x02\x07\x00\x0A\x07\x00\x14\x00\x00\x00\xD1\x00\x03\x07\x00\x02\x07\x00\x0A\x07\x00\x14\x00\x01\x07\x00\x02\x00\xE2\x00\x03\x07\x00\x02\x07\x00\x0A\x07\x00\x14\x00\x00\x01\x00\x00\x00\x00\x01\x07\x00\x7F\x01\x01\x00\x03\x07\x00\x02\x07\x00\x0A\x07\x00\x14\x00\x00\x01\x14\x00\x03\x07\x00\x02\x07\x00\x0A\x07\x00\x14\x00\x00\x01\x17\x00\x00\x00\x01\x07\x00\x7F\x01\x18\x00\x03\x07\x00\x02\x07\x00\x0A\x07\x00\x14\x00\x00\x01\x21\x00\x03\x07\x00\x02\x07\x00\x0A\x07\x00\x14\x00\x00\x01\x34\x00\x03\x07\x00\x02\x07\x00\x0A\x07\x00\x14\x00\x00\x01\x67\x00\x03\x07\x00\x02\x07\x00\x0A\x07\x00\x14\x00\x00\x01\xF8\x00\x03\x07\x00\x02\x07\x00\x0A\x07\x00\x14\x00\x01\x07\x00\x02\x01\xFB\x00\x03\x07\x00\x02\x07\x00\x0A\x07\x00\x14\x00\x00\x02\x09\x00\x03\x07\x00\x02\x07\x00\x0A\x07\x00\x14\x00\x00\x02\x0A\x00\x03\x07\x00\x02\x07\x00\x0A\x07\x00\x14\x00\x01\x07\x00\x02'
    .end code
.end method

.method public method40 : (LgB;I)V
    .code stack 2 locals 3
L0:     aload_0
L1:     getfield Field sb field171 LId;
L4:     getstatic Field Id field638 LId;
L7:     if_acmpne L12
L10:    return
L11:    athrow
L12:    aload_0
L13:    getfield Field sb field161 Ljava/util/ArrayList;
L16:    invokevirtual Method java/util/ArrayList iterator ()Ljava/util/Iterator;
L19:    dup
L20:    astore_1
L21:    invokeinterface InterfaceMethod java/util/Iterator hasNext ()Z 1
L26:    ifeq L53
L29:    aload_1
L30:    invokeinterface InterfaceMethod java/util/Iterator next ()Ljava/lang/Object; 1
L35:    checkcast LD
L38:    getfield Field LD field137 LRg;
L41:    checkcast oF
L44:    iload_2
L45:    invokevirtual Method oF method125 (I)V
L48:    aload_1
L49:    goto L21
L52:    athrow
L53:    return
L54:    
        .attribute StackMap b'\x00\x05\x00\x0B\x00\x00\x00\x01\x07\x00\x7F\x00\x0C\x00\x03\x07\x00\x02\x07\x01\x57\x01\x00\x00\x00\x15\x00\x03\x07\x00\x02\x07\x00\x6B\x01\x00\x01\x07\x00\x6B\x00\x34\x00\x00\x00\x01\x07\x00\x7F\x00\x35\x00\x03\x07\x00\x02\x07\x00\x6B\x01\x00\x00'
    .end code
.end method

.method public background : (ZF)V
    .code stack 5 locals 3
L0:     invokestatic Method FE method10 ()V
L3:     aload_0
L4:     getfield Field sb field171 LId;
L7:     getstatic Field Id field638 LId;
L10:    if_acmpeq L121
L13:    fconst_0
L14:    dup
L15:    dup_x1
L16:    fload_2
L17:    ldc_w 6e-1f
L20:    fmul
L21:    invokestatic Method org/lwjgl/opengl/GL11 method3888 (FFFF)V
L24:    bipush 7
L26:    iconst_1
L27:    dup
L28:    pop2
L29:    invokestatic Method org/lwjgl/opengl/GL11 method3664 (I)V
L32:    aload_0
L33:    dup
L34:    dup_x1
L35:    getfield Field sb field159 LlF;
L38:    getfield Field lF field1134 F
L41:    aload_0
L42:    dup_x2
L43:    getfield Field sb field1134 F
L46:    fsub
L47:    fconst_0
L48:    invokestatic Method org/lwjgl/opengl/GL11 method3848 (FF)V
L51:    getfield Field sb field159 LlF;
L54:    getfield Field lF field1134 F
L57:    aload_0
L58:    getfield Field sb field1134 F
L61:    fsub
L62:    aload_0
L63:    getfield Field sb field1132 F
L66:    invokestatic Method org/lwjgl/opengl/GL11 method3848 (FF)V
L69:    getfield Field sb field159 LlF;
L72:    getfield Field lF field1134 F
L75:    aload_0
L76:    getfield Field sb field159 LlF;
L79:    getfield Field lF field1124 F
L82:    fadd
L83:    aload_0
L84:    getfield Field sb field1134 F
L87:    fsub
L88:    aload_0
L89:    getfield Field sb field1132 F
L92:    invokestatic Method org/lwjgl/opengl/GL11 method3848 (FF)V
L95:    getfield Field sb field159 LlF;
L98:    getfield Field lF field1134 F
L101:   aload_0
L102:   getfield Field sb field159 LlF;
L105:   getfield Field lF field1124 F
L108:   fadd
L109:   aload_0
L110:   getfield Field sb field1134 F
L113:   fsub
L114:   fconst_0
L115:   invokestatic Method org/lwjgl/opengl/GL11 method3848 (FF)V
L118:   invokestatic Method org/lwjgl/opengl/GL11 method3788 ()V
L121:   aload_0
L122:   getfield Field sb field163 F
L125:   fconst_0
L126:   fcmpl
L127:   ifle L243
L130:   fconst_0
L131:   dup
L132:   dup_x1
L133:   aload_0
L134:   getfield Field sb field163 F
L137:   fload_2
L138:   fmul
L139:   ldc_w 6e-1f
L142:   fmul
L143:   invokestatic Method org/lwjgl/opengl/GL11 method3888 (FFFF)V
L146:   bipush 7
L148:   iconst_1
L149:   dup
L150:   pop2
L151:   invokestatic Method org/lwjgl/opengl/GL11 method3664 (I)V
L154:   aload_0
L155:   dup
L156:   dup_x1
L157:   getfield Field sb field170 LlF;
L160:   getfield Field lF field1134 F
L163:   aload_0
L164:   dup_x2
L165:   getfield Field sb field1134 F
L168:   fsub
L169:   fconst_0
L170:   invokestatic Method org/lwjgl/opengl/GL11 method3848 (FF)V
L173:   getfield Field sb field170 LlF;
L176:   getfield Field lF field1134 F
L179:   aload_0
L180:   getfield Field sb field1134 F
L183:   fsub
L184:   aload_0
L185:   getfield Field sb field1132 F
L188:   invokestatic Method org/lwjgl/opengl/GL11 method3848 (FF)V
L191:   getfield Field sb field170 LlF;
L194:   getfield Field lF field1134 F
L197:   aload_0
L198:   getfield Field sb field170 LlF;
L201:   getfield Field lF field1124 F
L204:   fadd
L205:   aload_0
L206:   getfield Field sb field1134 F
L209:   fsub
L210:   aload_0
L211:   getfield Field sb field1132 F
L214:   invokestatic Method org/lwjgl/opengl/GL11 method3848 (FF)V
L217:   getfield Field sb field170 LlF;
L220:   getfield Field lF field1134 F
L223:   aload_0
L224:   getfield Field sb field170 LlF;
L227:   getfield Field lF field1124 F
L230:   fadd
L231:   aload_0
L232:   getfield Field sb field1134 F
L235:   fsub
L236:   fconst_0
L237:   invokestatic Method org/lwjgl/opengl/GL11 method3848 (FF)V
L240:   invokestatic Method org/lwjgl/opengl/GL11 method3788 ()V
L243:   aload_0
L244:   iload_1
L245:   fload_2
L246:   invokespecial Method qc background (ZF)V
L249:   return
L250:   
        .attribute StackMap b'\x00\x02\x00\x79\x00\x03\x07\x00\x02\x01\x02\x00\x00\x00\xF3\x00\x03\x07\x00\x02\x01\x02\x00\x00'
    .end code
.end method

.method public method138 : (Led;)LLD;
    .code stack 2 locals 4
L0:     aload_0
L1:     getfield Field sb field161 Ljava/util/ArrayList;
L4:     invokevirtual Method java/util/ArrayList iterator ()Ljava/util/Iterator;
L7:     astore_2
L8:     aload_2
L9:     invokeinterface InterfaceMethod java/util/Iterator hasNext ()Z 1
L14:    ifeq L45
L17:    aload_2
L18:    invokeinterface InterfaceMethod java/util/Iterator next ()Ljava/lang/Object; 1
L23:    checkcast LD
L26:    dup
L27:    astore_3
L28:    getfield Field LD field137 LRg;
L31:    getfield Field Rg false Led;
L34:    aload_1
L35:    if_acmpne L8
L38:    aload_3
L39:    areturn
L40:    nop
L41:    nop
L42:    nop
L43:    nop
L44:    athrow
L45:    aload_0
L46:    getfield Field sb field168 Lod;
L49:    aload_1
L50:    invokevirtual Method od method138 (Led;)LLD;
L53:    areturn
L54:    
        .attribute StackMap b'\x00\x03\x00\x08\x00\x03\x07\x00\x02\x07\x01\xCF\x07\x00\x6B\x00\x00\x00\x28\x00\x00\x00\x01\x07\x00\x7F\x00\x2D\x00\x03\x07\x00\x02\x07\x01\xCF\x07\x00\x6B\x00\x00'
    .end code
.end method

.method public method26 : ()V
    .code stack 5 locals 4
L0:     aload_0
L1:     dup
L2:     invokespecial Method qc method26 ()V
L5:     getfield Field sb try F
L8:     fconst_0
L9:     fcmpl
L10:    ifle L78
L13:    aload_0
L14:    dup
L15:    dup2
L16:    getfield Field sb try F
L19:    f2i
L20:    istore_1
L21:    dup
L22:    getfield Field sb try F
L25:    getstatic Field ib field2312 F
L28:    fsub
L29:    putfield Field sb try F
L32:    getfield Field sb try F
L35:    f2i
L36:    istore_2
L37:    getfield Field sb try F
L40:    fconst_0
L41:    fcmpg
L42:    ifgt L59
L45:    aload_0
L46:    getfield Field sb field166 Z
L49:    ifne L59
L52:    getstatic Field zg field461 Lzg;
L55:    fconst_1
L56:    invokestatic Method UE method422 (Lzg;F)V
L59:    iload_2
L60:    iload_1
L61:    if_icmpeq L78
L64:    aload_0
L65:    getfield Field sb field166 Z
L68:    ifne L78
L71:    getstatic Field zg field463 Lzg;
L74:    fconst_1
L75:    invokestatic Method UE method422 (Lzg;F)V
L78:    aload_0
L79:    getfield Field sb field167 Ljava/util/LinkedHashMap;
L82:    invokevirtual Method java/util/LinkedHashMap entrySet ()Ljava/util/Set;
L85:    invokeinterface InterfaceMethod java/util/Set iterator ()Ljava/util/Iterator; 1
L90:    astore_1
L91:    aload_1
L92:    invokeinterface InterfaceMethod java/util/Iterator hasNext ()Z 1
L97:    ifeq L317
L100:   aload_1
L101:   invokeinterface InterfaceMethod java/util/Iterator next ()Ljava/lang/Object; 1
L106:   checkcast java/util/Map$Entry
L109:   dup
L110:   astore_2
L111:   invokeinterface InterfaceMethod java/util/Map$Entry getValue ()Ljava/lang/Object; 1
L116:   checkcast Dc
L119:   getfield Field Dc field1794 Ljava/lang/Object;
L122:   checkcast java/util/LinkedList
L125:   invokevirtual Method java/util/LinkedList isEmpty ()Z
L128:   ifeq L141
L131:   aload_1
L132:   invokeinterface InterfaceMethod java/util/Iterator remove ()V 1
L137:   goto L91
L140:   athrow
L141:   aload_2
L142:   invokeinterface InterfaceMethod java/util/Map$Entry getValue ()Ljava/lang/Object; 1
L147:   checkcast Dc
L150:   dup
L151:   astore_3
L152:   dup
L153:   getfield Field Dc field1793 Ljava/lang/Object;
L156:   checkcast java/lang/Float
L159:   invokevirtual Method java/lang/Float floatValue ()F
L162:   getstatic Field ib field2312 F
L165:   fsub
L166:   invokestatic Method java/lang/Float valueOf (F)Ljava/lang/Float;
L169:   dup_x1
L170:   putfield Field Dc field1793 Ljava/lang/Object;
L173:   pop
L174:   aload_2
L175:   invokeinterface InterfaceMethod java/util/Map$Entry getValue ()Ljava/lang/Object; 1
L180:   checkcast Dc
L183:   getfield Field Dc field1793 Ljava/lang/Object;
L186:   checkcast java/lang/Float
L189:   invokevirtual Method java/lang/Float floatValue ()F
L192:   fconst_0
L193:   fcmpg
L194:   ifge L91
L197:   aload_2
L198:   invokeinterface InterfaceMethod java/util/Map$Entry getValue ()Ljava/lang/Object; 1
L203:   checkcast Dc
L206:   getfield Field Dc field1794 Ljava/lang/Object;
L209:   checkcast java/util/LinkedList
L212:   invokevirtual Method java/util/LinkedList isEmpty ()Z
L215:   ifne L91
L218:   aload_2
L219:   invokeinterface InterfaceMethod java/util/Map$Entry getValue ()Ljava/lang/Object; 1
L224:   checkcast Dc
L227:   dup
L228:   astore_3
L229:   dup
L230:   getfield Field Dc field1793 Ljava/lang/Object;
L233:   checkcast java/lang/Float
L236:   invokevirtual Method java/lang/Float floatValue ()F
L239:   ldc_w 2e-2f
L242:   invokestatic Method java/lang/Math random ()D
L245:   d2f
L246:   ldc_w 9e-2f
L249:   fmul
L250:   fadd
L251:   fadd
L252:   invokestatic Method java/lang/Float valueOf (F)Ljava/lang/Float;
L255:   dup_x1
L256:   putfield Field Dc field1793 Ljava/lang/Object;
L259:   pop
L260:   aload_2
L261:   invokeinterface InterfaceMethod java/util/Map$Entry getValue ()Ljava/lang/Object; 1
L266:   checkcast Dc
L269:   getfield Field Dc field1794 Ljava/lang/Object;
L272:   checkcast java/util/LinkedList
L275:   invokevirtual Method java/util/LinkedList removeFirst ()Ljava/lang/Object;
L278:   checkcast Dc
L281:   astore_3
L282:   aload_0
L283:   aload_2
L284:   invokeinterface InterfaceMethod java/util/Map$Entry getKey ()Ljava/lang/Object; 1
L289:   checkcast ed
L292:   aload_3
L293:   getfield Field Dc field1793 Ljava/lang/Object;
L296:   checkcast ed
L299:   aload_3
L300:   getfield Field Dc field1794 Ljava/lang/Object;
L303:   checkcast [I
L306:   invokespecial Method sb method141 (Led;Led;[I)V
L309:   aload_2
L310:   goto L175
L313:   nop
L314:   nop
L315:   nop
L316:   athrow
L317:   return
L318:   
        .attribute StackMap b'\x00\x08\x00\x3B\x00\x03\x07\x00\x02\x01\x01\x00\x00\x00\x4E\x00\x01\x07\x00\x02\x00\x00\x00\x5B\x00\x02\x07\x00\x02\x07\x00\x6B\x00\x00\x00\x8C\x00\x00\x00\x01\x07\x00\x7F\x00\x8D\x00\x03\x07\x00\x02\x07\x00\x6B\x07\x00\x16\x00\x00\x00\xAF\x00\x04\x07\x00\x02\x07\x00\x6B\x07\x00\x16\x07\x01\x16\x00\x01\x07\x00\x16\x01\x39\x00\x00\x00\x01\x07\x00\x7F\x01\x3D\x00\x02\x07\x00\x02\x07\x00\x6B\x00\x00'
    .end code
.end method

.method public method75 : (Lqc;)V
    .code stack 3 locals 2
L0:     aload_0
L1:     dup
L2:     ldc_w 1.6e1f
L5:     putfield Field sb field1128 F
L8:     getstatic Field FE field822 F
L11:    putfield Field sb field1137 F
L14:    return
L15:    
    .end code
.end method

.method public method62 : (Lqc;)V
    .code stack 8 locals 3
L0:     aload_0
L1:     aload_1
L2:     getfield Field qc field1132 F
L5:     invokestatic Method QD method385 ()F
L8:     ldc_w 4e-1f
L11:    fmul
L12:    ldc_w 8e-1f
L15:    fmul
L16:    fsub
L17:    invokestatic Method LD method124 ()F
L20:    fmul
L21:    fstore_2
L22:    getfield Field sb field161 Ljava/util/ArrayList;
L25:    invokevirtual Method java/util/ArrayList size ()I
L28:    tableswitch 0
            L56
            L105
            L189
            default : L301
L56:    aload_0
L57:    iconst_0
L58:    ifne L57
L61:    dup
L62:    dup2
L63:    getfield Field sb field159 LlF;
L66:    fconst_0
L67:    dup
L68:    invokevirtual Method lF method32 (FF)V
L71:    getfield Field sb field170 LlF;
L74:    aload_1
L75:    dup
L76:    getfield Field qc field1134 F
L79:    swap
L80:    getfield Field qc field1126 F
L83:    invokevirtual Method lF method37 (FF)V
L86:    getfield Field sb field170 LlF;
L89:    aload_1
L90:    dup
L91:    getfield Field qc field1124 F
L94:    swap
L95:    getfield Field qc field1132 F
L98:    invokevirtual Method lF method32 (FF)V
L101:   goto L313
L104:   athrow
L105:   aload_0
L106:   dup
L107:   dup_x1
L108:   dup2
L109:   getfield Field sb field159 LlF;
L112:   aload_1
L113:   dup
L114:   getfield Field qc field1134 F
L117:   swap
L118:   getfield Field qc field1126 F
L121:   invokevirtual Method lF method37 (FF)V
L124:   getfield Field sb field159 LlF;
L127:   fload_2
L128:   aload_1
L129:   getfield Field qc field1132 F
L132:   invokevirtual Method lF method32 (FF)V
L135:   getfield Field sb field170 LlF;
L138:   aload_1
L139:   getfield Field qc field1134 F
L142:   fload_2
L143:   fadd
L144:   ldc_w 2e-2f
L147:   aload_0
L148:   getfield Field sb field1124 F
L151:   fmul
L152:   fadd
L153:   aload_1
L154:   getfield Field qc field1126 F
L157:   invokevirtual Method lF method37 (FF)V
L160:   getfield Field sb field170 LlF;
L163:   aload_1
L164:   getfield Field qc field1124 F
L167:   fload_2
L168:   fsub
L169:   ldc_w 2e-2f
L172:   aload_0
L173:   getfield Field sb field1124 F
L176:   fmul
L177:   fsub
L178:   aload_1
L179:   getfield Field qc field1132 F
L182:   invokevirtual Method lF method32 (FF)V
L185:   goto L313
L188:   athrow
L189:   aload_0
L190:   dup
L191:   dup_x1
L192:   dup2
L193:   getfield Field sb field159 LlF;
L196:   aload_1
L197:   dup
L198:   getfield Field qc field1134 F
L201:   swap
L202:   getfield Field qc field1124 F
L205:   fconst_2
L206:   fdiv
L207:   fload_2
L208:   fsub
L209:   fconst_2
L210:   fdiv
L211:   fadd
L212:   aload_1
L213:   getfield Field qc field1126 F
L216:   invokevirtual Method lF method37 (FF)V
L219:   getfield Field sb field159 LlF;
L222:   fload_2
L223:   aload_1
L224:   getfield Field qc field1132 F
L227:   invokevirtual Method lF method32 (FF)V
L230:   getfield Field sb field170 LlF;
L233:   aload_1
L234:   dup
L235:   getfield Field qc field1134 F
L238:   swap
L239:   getfield Field qc field1124 F
L242:   fconst_2
L243:   fdiv
L244:   fload_2
L245:   fsub
L246:   fconst_2
L247:   fdiv
L248:   fsub
L249:   aload_1
L250:   getfield Field qc field1124 F
L253:   fadd
L254:   fload_2
L255:   fsub
L256:   aload_1
L257:   getfield Field qc field1126 F
L260:   invokevirtual Method lF method37 (FF)V
L263:   getfield Field sb field170 LlF;
L266:   fload_2
L267:   aload_1
L268:   getfield Field qc field1132 F
L271:   invokevirtual Method lF method32 (FF)V
L274:   getfield Field sb field162 Lqd;
L277:   getfield Field qd new Ljava/util/LinkedHashMap;
L280:   invokevirtual Method java/util/LinkedHashMap size ()I
L283:   iconst_2
L284:   iconst_1
L285:   dup
L286:   pop2
L287:   if_icmpeq L312
L290:   new java/lang/RuntimeException
L293:   dup
L294:   ldc_w "unsupported layout #1"
L297:   invokespecial Method java/lang/RuntimeException <init> (Ljava/lang/String;)V
L300:   athrow
L301:   new java/lang/RuntimeException
L304:   dup
L305:   ldc_w "unsupported layout #3"
L308:   invokespecial Method java/lang/RuntimeException <init> (Ljava/lang/String;)V
L311:   athrow
L312:   aload_0
L313:   getfield Field sb field171 LId;
L316:   getstatic Field Id field638 LId;
L319:   if_acmpne L354
L322:   aload_0
L323:   dup
L324:   getfield Field sb field168 Lod;
L327:   aload_1
L328:   dup
L329:   getfield Field qc field1134 F
L332:   swap
L333:   getfield Field qc field1126 F
L336:   invokevirtual Method od method37 (FF)V
L339:   getfield Field sb field168 Lod;
L342:   aload_1
L343:   dup
L344:   getfield Field qc field1124 F
L347:   swap
L348:   getfield Field qc field1132 F
L351:   invokevirtual Method od method32 (FF)V
L354:   aload_0
L355:   dup
L356:   dup_x1
L357:   getfield Field sb field164 Lbb;
L360:   aload_1
L361:   dup
L362:   getfield Field qc field1134 F
L365:   swap
L366:   getfield Field qc field1126 F
L369:   invokevirtual Method bb method37 (FF)V
L372:   getfield Field sb field164 Lbb;
L375:   aload_1
L376:   dup
L377:   getfield Field qc field1124 F
L380:   swap
L381:   getfield Field qc field1132 F
L384:   invokevirtual Method bb method32 (FF)V
L387:   getfield Field sb field168 Lod;
L390:   invokevirtual Method od method263 ()Z
L393:   aload_0
L394:   swap
L395:   ifeq L406
L398:   aload_0
L399:   getfield Field sb field170 LlF;
L402:   invokevirtual Method sb method25 (LgB;)V
L405:   return
L406:   aload_0
L407:   getfield Field sb field164 Lbb;
L410:   invokevirtual Method sb method25 (LgB;)V
L413:   return
L414:   
        .attribute StackMap b'\x00\x0B\x00\x38\x00\x03\x07\x00\x02\x07\x00\x04\x02\x00\x00\x00\x39\x00\x03\x07\x00\x02\x07\x00\x04\x02\x00\x01\x07\x00\x02\x00\x68\x00\x00\x00\x01\x07\x00\x7F\x00\x69\x00\x03\x07\x00\x02\x07\x00\x04\x02\x00\x00\x00\xBC\x00\x00\x00\x01\x07\x00\x7F\x00\xBD\x00\x03\x07\x00\x02\x07\x00\x04\x02\x00\x00\x01\x2D\x00\x03\x07\x00\x02\x07\x00\x04\x02\x00\x00\x01\x38\x00\x03\x07\x00\x02\x07\x00\x04\x02\x00\x00\x01\x39\x00\x03\x07\x00\x02\x07\x00\x04\x02\x00\x01\x07\x00\x02\x01\x62\x00\x03\x07\x00\x02\x07\x00\x04\x02\x00\x00\x01\x96\x00\x03\x07\x00\x02\x07\x00\x04\x02\x00\x01\x07\x00\x02'
    .end code
.end method

.method public method139 : (LRg;)LLD;
    .code stack 2 locals 4
L0:     aload_0
L1:     getfield Field sb field161 Ljava/util/ArrayList;
L4:     invokevirtual Method java/util/ArrayList iterator ()Ljava/util/Iterator;
L7:     astore_2
L8:     aload_2
L9:     invokeinterface InterfaceMethod java/util/Iterator hasNext ()Z 1
L14:    ifeq L42
L17:    aload_2
L18:    invokeinterface InterfaceMethod java/util/Iterator next ()Ljava/lang/Object; 1
L23:    checkcast LD
L26:    dup
L27:    astore_3
L28:    getfield Field LD field137 LRg;
L31:    aload_1
L32:    if_acmpne L8
L35:    aload_3
L36:    areturn
L37:    nop
L38:    nop
L39:    nop
L40:    nop
L41:    athrow
L42:    aload_0
L43:    getfield Field sb field168 Lod;
L46:    aload_1
L47:    invokevirtual Method od method479 (LRg;)LLD;
L50:    areturn
L51:    
        .attribute StackMap b'\x00\x03\x00\x08\x00\x03\x07\x00\x02\x07\x00\x57\x07\x00\x6B\x00\x00\x00\x25\x00\x00\x00\x01\x07\x00\x7F\x00\x2A\x00\x03\x07\x00\x02\x07\x00\x57\x07\x00\x6B\x00\x00'
    .end code
.end method

.method public method47 : (LgB;I)Z
    .code stack 6 locals 5
L0:     aload_0
L1:     getfield Field sb field171 LId;
L4:     getstatic Field Id field638 LId;
L7:     if_acmpne L16
L10:    iconst_0
L11:    iconst_1
L12:    dup
L13:    pop2
L14:    ireturn
L15:    athrow
L16:    iload_2
L17:    iconst_1
L18:    dup
L19:    dup
L20:    pop2
L21:    if_icmpne L30
L24:    iconst_0
L25:    iconst_1
L26:    dup
L27:    pop2
L28:    ireturn
L29:    athrow
L30:    iload_2
L31:    bipush 60
L33:    iconst_1
L34:    dup
L35:    pop2
L36:    if_icmpne L83
L39:    getstatic Field Kc field1931 LKc;
L42:    getstatic Field Pc field373 LPc;
L45:    invokevirtual Method Kc method853 (LPc;)Led;
L48:    dup
L49:    astore_1
L50:    aload_0
L51:    getfield Field sb field162 Lqd;
L54:    invokestatic Method Ob method1020 (Led;Lqd;)Z
L57:    ifeq L83
L60:    iconst_1
L61:    aload_0
L62:    getfield Field sb field162 Lqd;
L65:    new fc
L68:    dup
L69:    aload_1
L70:    getstatic Field oc field376 Loc;
L73:    invokespecial Method fc <init> (Led;Loc;)V
L76:    invokevirtual Method qd method394 (LD;)V
L79:    iconst_1
L80:    dup
L81:    pop2
L82:    ireturn
L83:    iload_2
L84:    ldc_w "j"
L87:    invokestatic Method JB method831 (Ljava/lang/String;)I
L90:    if_icmpne L221
L93:    aload_0
L94:    getfield Field sb field159 LlF;
L97:    invokevirtual Method lF method331 ()I
L100:   iconst_1
L101:   dup
L102:   dup
L103:   pop2
L104:   if_icmpgt L121
L107:   aload_0
L108:   getfield Field sb field170 LlF;
L111:   invokevirtual Method lF method331 ()I
L114:   iconst_1
L115:   dup
L116:   dup
L117:   pop2
L118:   if_icmple L216
L121:   aload_0
L122:   getfield Field sb field159 LlF;
L125:   invokevirtual Method lF method134 ()I
L128:   ifne L141
L131:   aload_0
L132:   getfield Field sb field170 LlF;
L135:   invokevirtual Method lF method134 ()I
L138:   ifeq L166
L141:   aload_0
L142:   dup
L143:   getfield Field sb field159 LlF;
L146:   iconst_0
L147:   iconst_1
L148:   dup
L149:   pop2
L150:   invokevirtual Method lF method14 (I)V
L153:   getfield Field sb field170 LlF;
L156:   iconst_0
L157:   iconst_1
L158:   dup
L159:   pop2
L160:   invokevirtual Method lF method14 (I)V
L163:   goto L216
L166:   aload_0
L167:   getfield Field sb field159 LlF;
L170:   invokevirtual Method lF method331 ()I
L173:   iconst_1
L174:   dup
L175:   dup
L176:   pop2
L177:   if_icmple L191
L180:   aload_0
L181:   getfield Field sb field159 LlF;
L184:   iconst_1
L185:   dup
L186:   dup
L187:   pop2
L188:   invokevirtual Method lF method14 (I)V
L191:   aload_0
L192:   getfield Field sb field170 LlF;
L195:   invokevirtual Method lF method331 ()I
L198:   iconst_1
L199:   dup
L200:   dup
L201:   pop2
L202:   if_icmple L216
L205:   aload_0
L206:   getfield Field sb field170 LlF;
L209:   iconst_1
L210:   dup
L211:   dup
L212:   pop2
L213:   invokevirtual Method lF method14 (I)V
L216:   iconst_1
L217:   dup
L218:   dup
L219:   pop2
L220:   ireturn
L221:   aload_0
L222:   getfield Field sb field159 LlF;
L225:   invokevirtual Method lF method498 ()LgB;
L228:   aload_0
L229:   getfield Field sb field169 LgB;
L232:   if_acmpeq L249
L235:   aload_0
L236:   getfield Field sb field170 LlF;
L239:   invokevirtual Method lF method498 ()LgB;
L242:   aload_0
L243:   getfield Field sb field169 LgB;
L246:   if_acmpne L268
L249:   aload_0
L250:   dup
L251:   getfield Field sb new LUb;
L254:   swap
L255:   getfield Field sb new LUb;
L258:   iload_2
L259:   invokevirtual Method Ub method53 (LgB;I)Z
L262:   pop
L263:   iconst_0
L264:   iconst_1
L265:   dup
L266:   pop2
L267:   ireturn
L268:   aload_0
L269:   getfield Field sb field159 LlF;
L272:   invokevirtual Method lF method498 ()LgB;
L275:   aload_0
L276:   getfield Field sb field165 LgB;
L279:   if_acmpeq L296
L282:   aload_0
L283:   getfield Field sb field170 LlF;
L286:   invokevirtual Method lF method498 ()LgB;
L289:   aload_0
L290:   getfield Field sb field165 LgB;
L293:   if_acmpne L315
L296:   aload_0
L297:   dup
L298:   getfield Field sb field160 LUb;
L301:   swap
L302:   getfield Field sb field160 LUb;
L305:   iload_2
L306:   invokevirtual Method Ub method53 (LgB;I)Z
L309:   pop
L310:   iconst_0
L311:   iconst_1
L312:   dup
L313:   pop2
L314:   ireturn
L315:   iconst_0
L316:   iconst_1
L317:   dup
L318:   pop2
L319:   istore_1
L320:   aload_0
L321:   getfield Field sb field161 Ljava/util/ArrayList;
L324:   invokevirtual Method java/util/ArrayList iterator ()Ljava/util/Iterator;
L327:   astore_3
L328:   aload_3
L329:   invokeinterface InterfaceMethod java/util/Iterator hasNext ()Z 1
L334:   ifeq L379
L337:   aload_3
L338:   invokeinterface InterfaceMethod java/util/Iterator next ()Ljava/lang/Object; 1
L343:   checkcast LD
L346:   dup
L347:   astore 4
L349:   getfield Field LD field137 LRg;
L352:   getfield Field Rg field227 LqE;
L355:   getstatic Field qE field630 LqE;
L358:   if_acmpeq L328
L361:   iload_1
L362:   aload 4
L364:   getfield Field LD field137 LRg;
L367:   checkcast oF
L370:   iload_2
L371:   invokevirtual Method oF method383 (I)Z
L374:   ior
L375:   istore_1
L376:   goto L328
L379:   iload_1
L380:   ireturn
L381:   
        .attribute StackMap b'\x00\x11\x00\x0F\x00\x00\x00\x01\x07\x00\x7F\x00\x10\x00\x03\x07\x00\x02\x07\x01\x57\x01\x00\x00\x00\x1D\x00\x00\x00\x01\x07\x00\x7F\x00\x1E\x00\x03\x07\x00\x02\x07\x01\x57\x01\x00\x00\x00\x53\x00\x03\x07\x00\x02\x07\x02\x69\x01\x00\x00\x00\x79\x00\x03\x07\x00\x02\x07\x02\x69\x01\x00\x00\x00\x8D\x00\x03\x07\x00\x02\x07\x02\x69\x01\x00\x00\x00\xA6\x00\x03\x07\x00\x02\x07\x02\x69\x01\x00\x00\x00\xBF\x00\x03\x07\x00\x02\x07\x02\x69\x01\x00\x00\x00\xD8\x00\x03\x07\x00\x02\x07\x02\x69\x01\x00\x00\x00\xDD\x00\x03\x07\x00\x02\x07\x02\x69\x01\x00\x00\x00\xF9\x00\x03\x07\x00\x02\x07\x02\x69\x01\x00\x00\x01\x0C\x00\x03\x07\x00\x02\x07\x02\x69\x01\x00\x00\x01\x28\x00\x03\x07\x00\x02\x07\x02\x69\x01\x00\x00\x01\x3B\x00\x03\x07\x00\x02\x07\x02\x69\x01\x00\x00\x01\x48\x00\x04\x07\x00\x02\x01\x01\x07\x00\x6B\x00\x00\x01\x7B\x00\x04\x07\x00\x02\x01\x01\x07\x00\x6B\x00\x00'
    .end code
.end method

.method public false : ()Z
    .code stack 3 locals 1
L0:     iconst_1
L1:     dup
L2:     dup
L3:     pop2
L4:     ireturn
L5:     
    .end code
.end method

.method private method140 : (LRg;)V
    .code stack 7 locals 2
L0:     aload_1
L1:     ifnonnull L6
L4:     return
L5:     athrow
L6:     aload_1
L7:     instanceof oF
L10:    ifne L15
L13:    return
L14:    athrow
L15:    aload_0
L16:    aload_1
L17:    invokevirtual Method sb method139 (LRg;)LLD;
L20:    ifnull L24
L23:    return
L24:    new LD
L27:    dup
L28:    aload_1
L29:    dup
L30:    instanceof oF
L33:    ifeq L40
L36:    fconst_1
L37:    goto L43
L40:    ldc_w 1e-1f
L43:    invokespecial Method LD <init> (LRg;F)V
L46:    astore_1
L47:    aload_0
L48:    dup
L49:    getfield Field sb field161 Ljava/util/ArrayList;
L52:    aload_1
L53:    invokevirtual Method java/util/ArrayList add (Ljava/lang/Object;)Z
L56:    pop
L57:    getfield Field sb field161 Ljava/util/ArrayList;
L60:    invokevirtual Method java/util/ArrayList size ()I
L63:    iconst_1
L64:    dup
L65:    dup
L66:    pop2
L67:    if_icmpne L89
L70:    aload_0
L71:    dup
L72:    getfield Field sb field159 LlF;
L75:    ldc_w "Play"
L78:    aload_1
L79:    iconst_0
L80:    iconst_1
L81:    dup
L82:    pop2
L83:    invokevirtual Method lF method496 (Ljava/lang/String;LgB;I)V
L86:    goto L105
L89:    aload_0
L90:    dup
L91:    getfield Field sb field170 LlF;
L94:    ldc_w "Play"
L97:    aload_1
L98:    iconst_0
L99:    iconst_1
L100:   dup
L101:   pop2
L102:   invokevirtual Method lF method496 (Ljava/lang/String;LgB;I)V
L105:   invokevirtual Method sb method21 ()V
L108:   return
L109:   
        .attribute StackMap b'\x00\x09\x00\x05\x00\x00\x00\x01\x07\x00\x7F\x00\x06\x00\x02\x07\x00\x02\x07\x00\x57\x00\x00\x00\x0E\x00\x00\x00\x01\x07\x00\x7F\x00\x0F\x00\x02\x07\x00\x02\x07\x00\x57\x00\x00\x00\x18\x00\x02\x07\x00\x02\x07\x00\x57\x00\x00\x00\x28\x00\x02\x07\x00\x02\x07\x00\x57\x00\x03\x08\x00\x18\x08\x00\x18\x07\x00\x57\x00\x2B\x00\x02\x07\x00\x02\x07\x00\x57\x00\x04\x08\x00\x18\x08\x00\x18\x07\x00\x57\x02\x00\x59\x00\x02\x07\x00\x02\x07\x00\x79\x00\x00\x00\x69\x00\x02\x07\x00\x02\x07\x00\x79\x00\x01\x07\x00\x02'
    .end code
.end method

.method public method10 : ()V
    .code stack 4 locals 1
L0:     aload_0
L1:     getfield Field sb field161 Ljava/util/ArrayList;
L4:     invokevirtual Method java/util/ArrayList isEmpty ()Z
L7:     ifne L27
L10:    aload_0
L11:    getfield Field sb field161 Ljava/util/ArrayList;
L14:    iconst_0
L15:    iconst_1
L16:    dup
L17:    pop2
L18:    invokevirtual Method java/util/ArrayList get (I)Ljava/lang/Object;
L21:    checkcast LD
L24:    invokevirtual Method LD method10 ()V
L27:    return
L28:    
        .attribute StackMap b'\x00\x01\x00\x1B\x00\x01\x07\x00\x02\x00\x00'
    .end code
.end method

.method private method74 : ()V
    .code stack 2 locals 3
L0:     aload_0
L1:     getfield Field sb field162 Lqd;
L4:     getfield Field qd new Ljava/util/LinkedHashMap;
L7:     invokevirtual Method java/util/LinkedHashMap values ()Ljava/util/Collection;
L10:    invokeinterface InterfaceMethod java/util/Collection iterator ()Ljava/util/Iterator; 1
L15:    astore_1
L16:    aload_1
L17:    invokeinterface InterfaceMethod java/util/Iterator hasNext ()Z 1
L22:    ifeq L51
L25:    aload_1
L26:    invokeinterface InterfaceMethod java/util/Iterator next ()Ljava/lang/Object; 1
L31:    checkcast Rg
L34:    dup
L35:    astore_2
L36:    instanceof oF
L39:    ifeq L16
L42:    aload_0
L43:    aload_2
L44:    invokespecial Method sb method140 (LRg;)V
L47:    goto L16
L50:    athrow
L51:    return
L52:    
        .attribute StackMap b'\x00\x03\x00\x10\x00\x02\x07\x00\x02\x07\x00\x6B\x00\x00\x00\x32\x00\x00\x00\x01\x07\x00\x7F\x00\x33\x00\x02\x07\x00\x02\x07\x00\x6B\x00\x00'
    .end code
.end method

.method private method141 : (Led;Led;[I)V
    .code stack 7 locals 6
L0:     aload_3
L1:     arraylength
L2:     newarray int
L4:     iconst_1
L5:     dup
L6:     pop2
L7:     astore 4
L9:     iconst_0
L10:    iconst_1
L11:    dup
L12:    pop2
L13:    dup
L14:    istore 5
L16:    aload_3
L17:    arraylength
L18:    if_icmpge L44
L21:    aload 4
L23:    aload_3
L24:    iload 5
L26:    dup_x1
L27:    iaload
L28:    bipush 10
L30:    iconst_1
L31:    dup
L32:    pop2
L33:    isub
L34:    iinc 5 1
L37:    iastore
L38:    iload 5
L40:    goto L16
L43:    athrow
L44:    aload_0
L45:    dup
L46:    aload_1
L47:    invokevirtual Method sb method138 (Led;)LLD;
L50:    astore 5
L52:    aload_2
L53:    invokevirtual Method sb method138 (Led;)LLD;
L56:    astore_3
L57:    aload 5
L59:    ifnull L66
L62:    aload_3
L63:    ifnonnull L68
L66:    return
L67:    athrow
L68:    aload_0
L69:    getfield Field sb field162 Lqd;
L72:    getfield Field qd field761 Leb;
L75:    invokevirtual Method eb method768 ()Z
L78:    ifeq L133
L81:    aload 5
L83:    getfield Field LD field92 F
L86:    aload_3
L87:    getfield Field LD field92 F
L90:    fcmpl
L91:    ifle L116
L94:    aload_0
L95:    getfield Field sb field166 Z
L98:    ifne L116
L101:   getstatic Field zg field465 Lzg;
L104:   aload 5
L106:   getfield Field LD field92 F
L109:   invokestatic Method UE method422 (Lzg;F)V
L112:   aload_0
L113:   goto L134
L116:   aload_0
L117:   getfield Field sb field166 Z
L120:   ifne L133
L123:   getstatic Field zg this Lzg;
L126:   aload_3
L127:   getfield Field LD field92 F
L130:   invokestatic Method UE method422 (Lzg;F)V
L133:   aload_0
L134:   getfield Field sb field159 LlF;
L137:   invokevirtual Method lF method497 ()F
L140:   ldc_w 1e-1f
L143:   fcmpl
L144:   ifle L182
L147:   aload_0
L148:   getfield Field sb field162 Lqd;
L151:   getfield Field qd new Ljava/util/LinkedHashMap;
L154:   aload_1
L155:   invokevirtual Method java/util/LinkedHashMap get (Ljava/lang/Object;)Ljava/lang/Object;
L158:   instanceof oF
L161:   ifne L181
L164:   aload_0
L165:   getfield Field sb field162 Lqd;
L168:   getfield Field qd new Ljava/util/LinkedHashMap;
L171:   aload_2
L172:   invokevirtual Method java/util/LinkedHashMap get (Ljava/lang/Object;)Ljava/lang/Object;
L175:   instanceof oF
L178:   ifeq L182
L181:   return
L182:   aload_0
L183:   getfield Field sb field170 LlF;
L186:   invokevirtual Method lF method498 ()LgB;
L189:   aload_0
L190:   getfield Field sb field168 Lod;
L193:   if_acmpeq L245
L196:   aload_0
L197:   getfield Field sb field170 LlF;
L200:   invokevirtual Method lF method497 ()F
L203:   ldc_w 1e-1f
L206:   fcmpl
L207:   ifle L245
L210:   aload_0
L211:   getfield Field sb field162 Lqd;
L214:   getfield Field qd new Ljava/util/LinkedHashMap;
L217:   aload_1
L218:   invokevirtual Method java/util/LinkedHashMap get (Ljava/lang/Object;)Ljava/lang/Object;
L221:   instanceof oF
L224:   ifeq L244
L227:   aload_0
L228:   getfield Field sb field162 Lqd;
L231:   getfield Field qd new Ljava/util/LinkedHashMap;
L234:   aload_2
L235:   invokevirtual Method java/util/LinkedHashMap get (Ljava/lang/Object;)Ljava/lang/Object;
L238:   instanceof oF
L241:   ifne L245
L244:   return
L245:   aload 5
L247:   aload_3
L248:   aload 5
L250:   invokevirtual Method LD method121 ()F
L253:   aload_0
L254:   getfield Field sb field1134 F
L257:   fsub
L258:   fstore_1
L259:   aload_3
L260:   invokevirtual Method LD method116 ()F
L263:   aload_0
L264:   getfield Field sb field1134 F
L267:   fsub
L268:   fstore_2
L269:   invokevirtual Method LD switch ()F
L272:   aload_0
L273:   getfield Field sb field1126 F
L276:   fsub
L277:   fstore_3
L278:   getfield Field LD field137 LRg;
L281:   instanceof oF
L284:   ifeq L298
L287:   aload 5
L289:   invokevirtual Method LD method123 ()F
L292:   aload_0
L293:   getfield Field sb field1134 F
L296:   fsub
L297:   fstore_1
L298:   ldc_w "det_sw"
L301:   invokestatic Method JB method831 (Ljava/lang/String;)I
L304:   ifeq L348
L307:   aload 4
L309:   arraylength
L310:   ifle L348
L313:   aload_0
L314:   getfield Field sb field164 Lbb;
L317:   fload_1
L318:   aload 5
L320:   aload 4
L322:   iconst_0
L323:   iconst_1
L324:   dup
L325:   pop2
L326:   iaload
L327:   invokevirtual Method LD method119 (I)F
L330:   aload_0
L331:   getfield Field sb field1126 F
L334:   fsub
L335:   fload_2
L336:   fload_3
L337:   aload 5
L339:   getfield Field LD field137 LRg;
L342:   getfield Field Rg field231 LsE;
L345:   invokevirtual Method bb method600 (FFFFLsE;)V
L348:   return
L349:   
        .attribute StackMap b'\x00\x0F\x00\x10\x00\x06\x07\x00\x02\x07\x01\xCF\x07\x01\xCF\x07\x02\x07\x07\x02\x07\x01\x00\x01\x01\x00\x2B\x00\x00\x00\x01\x07\x00\x7F\x00\x2C\x00\x06\x07\x00\x02\x07\x01\xCF\x07\x01\xCF\x07\x02\x07\x07\x02\x07\x01\x00\x00\x00\x42\x00\x06\x07\x00\x02\x07\x01\xCF\x07\x01\xCF\x07\x00\x79\x07\x02\x07\x07\x00\x79\x00\x00\x00\x43\x00\x00\x00\x01\x07\x00\x7F\x00\x44\x00\x06\x07\x00\x02\x07\x01\xCF\x07\x01\xCF\x07\x00\x79\x07\x02\x07\x07\x00\x79\x00\x00\x00\x74\x00\x06\x07\x00\x02\x07\x01\xCF\x07\x01\xCF\x07\x00\x79\x07\x02\x07\x07\x00\x79\x00\x00\x00\x85\x00\x06\x07\x00\x02\x07\x01\xCF\x07\x01\xCF\x07\x00\x79\x07\x02\x07\x07\x00\x79\x00\x00\x00\x86\x00\x06\x07\x00\x02\x07\x01\xCF\x07\x01\xCF\x07\x00\x79\x07\x02\x07\x07\x00\x79\x00\x01\x07\x00\x02\x00\xB5\x00\x06\x07\x00\x02\x07\x01\xCF\x07\x01\xCF\x07\x00\x79\x07\x02\x07\x07\x00\x79\x00\x00\x00\xB6\x00\x06\x07\x00\x02\x07\x01\xCF\x07\x01\xCF\x07\x00\x79\x07\x02\x07\x07\x00\x79\x00\x00\x00\xF4\x00\x06\x07\x00\x02\x07\x01\xCF\x07\x01\xCF\x07\x00\x79\x07\x02\x07\x07\x00\x79\x00\x00\x00\xF5\x00\x06\x07\x00\x02\x07\x01\xCF\x07\x01\xCF\x07\x00\x79\x07\x02\x07\x07\x00\x79\x00\x00\x01\x2A\x00\x06\x07\x00\x02\x02\x02\x02\x07\x02\x07\x07\x00\x79\x00\x00\x01\x5C\x00\x06\x07\x00\x02\x02\x02\x02\x07\x02\x07\x07\x00\x79\x00\x00'
    .end code
.end method

.method public method142 : (Lqd;)V
    .code stack 8 locals 2
L0:     aload_1
L1:     aload_0
L2:     dup_x1
L3:     dup_x2
L4:     aload_0
L5:     dup
L6:     getfield Field sb field162 Lqd;
L9:     aload_0
L10:    dup_x2
L11:    invokevirtual Method qd method401 (LG;)V
L14:    getfield Field sb field168 Lod;
L17:    aload_1
L18:    invokevirtual Method od method142 (Lqd;)V
L21:    getfield Field sb field161 Ljava/util/ArrayList;
L24:    invokevirtual Method java/util/ArrayList clear ()V
L27:    getfield Field sb field167 Ljava/util/LinkedHashMap;
L30:    invokevirtual Method java/util/LinkedHashMap clear ()V
L33:    putfield Field sb field162 Lqd;
L36:    getfield Field sb field162 Lqd;
L39:    aload_0
L40:    getstatic Field mc field387 Lmc;
L43:    invokevirtual Method qd method408 (LG;Lmc;)V
L46:    return
L47:    
    .end code
.end method
.innerclasses
    Id sb [0] public static final enum
    OD sb [0] static synthetic
    Pc JB [0] public static final enum
    QB qd [0] public static final enum
    java/util/Map$Entry java/util/Map Entry public static interface abstract
    oc fc [0] public static final enum
    zg UE [0] public static final enum
.end innerclasses
.end class
