.version 49 0
.class public final super sc
.super java/lang/Object
.implements D
.field public field893 Ljava/lang/String;
.field public field894 Ljava/lang/String;
.field public field895 Ljava/lang/String;
.field public try Z
.field public field896 Z
.field public new I
.field public field897 Z
.field public this I
.field public field898 I
.field public field899 Leb;
.field public field900 Ljava/lang/String;
.field public field901 I

.method public <init> : (LMd;)V
    .code stack 25 locals 2
L0:     aload_1
L1:     aload_0
L2:     dup_x1
L3:     aload_0
L4:     aload_1
L5:     dup_x1
L6:     aload_1
L7:     aload_0
L8:     dup_x1
L9:     aload_0
L10:    aload_1
L11:    dup_x1
L12:    aload_1
L13:    aload_0
L14:    dup_x1
L15:    aload_0
L16:    aload_1
L17:    dup_x1
L18:    aload_1
L19:    aload_0
L20:    dup_x1
L21:    aload_0
L22:    aload_1
L23:    dup_x1
L24:    aload_0
L25:    invokespecial Method java/lang/Object <init> ()V
L28:    invokevirtual Method Md new ()Ljava/lang/String;
L31:    putfield Field sc field900 Ljava/lang/String;
L34:    invokevirtual Method Md method892 ()Z
L37:    putfield Field sc field896 Z
L40:    invokevirtual Method Md method892 ()Z
L43:    putfield Field sc field897 Z
L46:    invokevirtual Method Md try ()Ljava/lang/String;
L49:    putfield Field sc field893 Ljava/lang/String;
L52:    invokevirtual Method Md method886 ()I
L55:    invokestatic Method GF method793 (I)Leb;
L58:    putfield Field sc field899 Leb;
L61:    invokevirtual Method Md method886 ()I
L64:    putfield Field sc this I
L67:    invokevirtual Method Md method886 ()I
L70:    putfield Field sc field901 I
L73:    invokevirtual Method Md method886 ()I
L76:    putfield Field sc new I
L79:    invokevirtual Method Md method892 ()Z
L82:    putfield Field sc try Z
L85:    invokevirtual Method Md method889 ()I
L88:    putfield Field sc field898 I
L91:    invokevirtual Method Md try ()Ljava/lang/String;
L94:    putfield Field sc field894 Ljava/lang/String;
L97:    invokevirtual Method Md try ()Ljava/lang/String;
L100:   putfield Field sc field895 Ljava/lang/String;
L103:   return
L104:   
    .end code
    .exceptions java/io/IOException
.end method

.method public method384 : (LAC;)V
    .code stack 16 locals 2
L0:     aload_1
L1:     aload_0
L2:     dup_x1
L3:     aload_0
L4:     aload_1
L5:     dup_x1
L6:     aload_1
L7:     aload_0
L8:     dup_x1
L9:     getfield Field sc field900 Ljava/lang/String;
L12:    invokevirtual Method AC method683 (Ljava/lang/String;)V
L15:    getfield Field sc field896 Z
L18:    invokevirtual Method AC method684 (Z)V
L21:    getfield Field sc field897 Z
L24:    invokevirtual Method AC method684 (Z)V
L27:    invokevirtual Method sc method227 ()Z
L30:    invokevirtual Method AC method684 (Z)V
L33:    invokevirtual Method sc method227 ()Z
L36:    ifeq L47
L39:    aload_1
L40:    aload_0
L41:    getfield Field sc field893 Ljava/lang/String;
L44:    invokevirtual Method AC method683 (Ljava/lang/String;)V
L47:    aload_1
L48:    dup
L49:    aload_0
L50:    dup_x1
L51:    aload_0
L52:    aload_1
L53:    dup_x1
L54:    aload_1
L55:    aload_0
L56:    dup_x1
L57:    aload_0
L58:    aload_1
L59:    dup_x1
L60:    aload_1
L61:    aload_0
L62:    dup_x1
L63:    getfield Field sc field899 Leb;
L66:    invokestatic Method GF method790 (Leb;)I
L69:    invokevirtual Method AC method691 (I)V
L72:    getfield Field sc this I
L75:    invokevirtual Method AC method691 (I)V
L78:    getfield Field sc field901 I
L81:    invokevirtual Method AC method691 (I)V
L84:    getfield Field sc new I
L87:    invokevirtual Method AC method691 (I)V
L90:    getfield Field sc try Z
L93:    invokevirtual Method AC method684 (Z)V
L96:    getfield Field sc field898 I
L99:    invokevirtual Method AC method674 (I)V
L102:   getfield Field sc field894 Ljava/lang/String;
L105:   invokevirtual Method AC method678 (Ljava/lang/String;)V
L108:   getfield Field sc field895 Ljava/lang/String;
L111:   invokevirtual Method AC method678 (Ljava/lang/String;)V
L114:   return
L115:   
        .attribute StackMap b'\x00\x01\x00\x2F\x00\x02\x07\x00\x02\x07\x00\x51\x00\x00'
    .end code
    .exceptions java/io/IOException
.end method

.method public <init> : (Ljava/lang/String;Ljava/lang/String;Leb;ZZIIILed;)V
    .code stack 14 locals 10
L0:     aload_2
L1:     aload_0
L2:     dup_x1
L3:     dup_x2
L4:     iload 5
L6:     iload 4
L8:     aload_0
L9:     dup_x1
L10:    aload_1
L11:    aload_0
L12:    invokespecial Method java/lang/Object <init> ()V
L15:    putfield Field sc field900 Ljava/lang/String;
L18:    putfield Field sc field896 Z
L21:    putfield Field sc field897 Z
L24:    putfield Field sc field893 Ljava/lang/String;
L27:    getfield Field sc field893 Ljava/lang/String;
L30:    ifnull L53
L33:    aload_0
L34:    getfield Field sc field893 Ljava/lang/String;
L37:    invokevirtual Method java/lang/String trim ()Ljava/lang/String;
L40:    ldc ""
L42:    invokevirtual Method java/lang/String equals (Ljava/lang/Object;)Z
L45:    ifeq L53
L48:    aload_0
L49:    aconst_null
L50:    putfield Field sc field893 Ljava/lang/String;
L53:    aload_0
L54:    dup
L55:    aload 9
L57:    dup_x1
L58:    aload 9
L60:    aload_0
L61:    dup_x1
L62:    iload 8
L64:    iload 7
L66:    aload_0
L67:    dup_x1
L68:    iload 6
L70:    aload_0
L71:    aload_3
L72:    putfield Field sc field899 Leb;
L75:    putfield Field sc this I
L78:    putfield Field sc field901 I
L81:    putfield Field sc new I
L84:    getfield Field ed field712 I
L87:    putfield Field sc field898 I
L90:    getfield Field ed field701 Ljava/lang/String;
L93:    putfield Field sc field894 Ljava/lang/String;
L96:    getfield Field ed new Ljava/lang/String;
L99:    putfield Field sc field895 Ljava/lang/String;
L102:   return
L103:   
        .attribute StackMap b'\x00\x01\x00\x35\x00\x0A\x07\x00\x02\x07\x00\x6D\x07\x00\x6D\x07\x00\x78\x01\x01\x01\x01\x01\x07\x00\x7A\x00\x00'
    .end code
.end method

.method public method227 : ()Z
    .code stack 3 locals 1
L0:     aload_0
L1:     getfield Field sc field893 Ljava/lang/String;
L4:     ifnull L13
L7:     iconst_1
L8:     dup
L9:     dup
L10:    pop2
L11:    ireturn
L12:    athrow
L13:    iconst_0
L14:    iconst_1
L15:    dup
L16:    pop2
L17:    ireturn
L18:    
        .attribute StackMap b'\x00\x02\x00\x0C\x00\x00\x00\x01\x07\x00\x84\x00\x0D\x00\x01\x07\x00\x02\x00\x00'
    .end code
.end method
.end class
