.version 49 0
.class public final super sD
.super java/awt/Frame
.field private static final field543 J = 1L

.method public method333 : (LFE;Ljava/lang/Throwable;Ljava/lang/String;Ljava/lang/String;)V
    .code stack 11 locals 7
        .catch java/lang/Throwable from L0 to L130 using L139
L0:     new java/net/URL
L3:     dup
L4:     ldc "http://gewaltig.net/crashreport.aspx?v=c2"
L6:     invokespecial Method java/net/URL <init> (Ljava/lang/String;)V
L9:     invokevirtual Method java/net/URL openConnection ()Ljava/net/URLConnection;
L12:    astore 5
L14:    ldc "Content-Type"
L16:    aload 5
L18:    dup_x1
L19:    dup_x2
L20:    iconst_0
L21:    iconst_1
L22:    aload 5
L24:    dup_x1
L25:    iconst_1
L26:    dup
L27:    dup
L28:    pop2
L29:    invokevirtual Method java/net/URLConnection setDoInput (Z)V
L32:    iconst_1
L33:    dup
L34:    pop2
L35:    invokevirtual Method java/net/URLConnection setDoOutput (Z)V
L38:    iconst_1
L39:    dup
L40:    pop2
L41:    invokevirtual Method java/net/URLConnection setUseCaches (Z)V
L44:    ldc "application/x-www-form-urlencoded"
L46:    invokevirtual Method java/net/URLConnection setRequestProperty (Ljava/lang/String;Ljava/lang/String;)V
L49:    new java/io/OutputStreamWriter
L52:    dup
L53:    aload 5
L55:    invokevirtual Method java/net/URLConnection getOutputStream ()Ljava/io/OutputStream;
L58:    invokespecial Method java/io/OutputStreamWriter <init> (Ljava/io/OutputStream;)V
L61:    dup
L62:    astore 6
L64:    dup
L65:    new java/lang/StringBuilder
L68:    aload 6
L70:    dup_x2
L71:    dup
L72:    pop2
L73:    dup
L74:    invokespecial Method java/lang/StringBuilder <init> ()V
L77:    ldc "report="
L79:    invokevirtual Method java/lang/StringBuilder append (Ljava/lang/String;)Ljava/lang/StringBuilder;
L82:    aload_0
L83:    aload_1
L84:    aload_2
L85:    aload_3
L86:    aload 4
L88:    invokespecial Method sD method334 (LFE;Ljava/lang/Throwable;Ljava/lang/String;Ljava/lang/String;)Ljava/lang/String;
L91:    ldc "UTF-8"
L93:    invokestatic Method java/net/URLEncoder encode (Ljava/lang/String;Ljava/lang/String;)Ljava/lang/String;
L96:    invokevirtual Method java/lang/StringBuilder append (Ljava/lang/String;)Ljava/lang/StringBuilder;
L99:    invokevirtual Method java/lang/StringBuilder toString ()Ljava/lang/String;
L102:   invokevirtual Method java/io/OutputStreamWriter write (Ljava/lang/String;)V
L105:   invokevirtual Method java/io/OutputStreamWriter flush ()V
L108:   invokevirtual Method java/io/OutputStreamWriter close ()V
L111:   invokevirtual Method java/net/URLConnection getInputStream ()Ljava/io/InputStream;
L114:   dup
L115:   astore_3
L116:   invokevirtual Method java/io/InputStream read ()I
L119:   iconst_m1
L120:   iconst_1
L121:   dup
L122:   pop2
L123:   if_icmpeq L131
L126:   aload_3
L127:   goto L116
L130:   athrow
        .catch java/lang/Throwable from L131 to L135 using L139
L131:   aload_3
L132:   invokevirtual Method java/io/InputStream close ()V
L135:   goto L151
L138:   athrow
L139:   astore 5
L141:   aload_1
L142:   aload_2
L143:   aload 5
L145:   invokevirtual Method java/lang/Throwable printStackTrace ()V
L148:   invokestatic Method sD method335 (LFE;Ljava/lang/Throwable;)V
L151:   iconst_0
L152:   iconst_1
L153:   dup
L154:   pop2
L155:   invokestatic Method java/lang/System exit (I)V
L158:   return
L159:   
        .attribute StackMap b'\x00\x06\x00\x74\x00\x07\x07\x00\x02\x07\x00\x67\x07\x00\x14\x07\x00\x69\x07\x00\x6B\x07\x00\x24\x07\x00\x36\x00\x01\x07\x00\x69\x00\x82\x00\x00\x00\x01\x07\x00\x14\x00\x83\x00\x07\x07\x00\x02\x07\x00\x67\x07\x00\x14\x07\x00\x69\x07\x00\x6B\x07\x00\x24\x07\x00\x36\x00\x00\x00\x8A\x00\x00\x00\x01\x07\x00\x14\x00\x8B\x00\x05\x07\x00\x02\x07\x00\x67\x07\x00\x14\x07\x00\x72\x07\x00\x6B\x00\x01\x07\x00\x14\x00\x97\x00\x06\x07\x00\x02\x07\x00\x67\x07\x00\x14\x07\x00\x72\x07\x00\x6B\x07\x00\x72\x00\x00'
    .end code
.end method

.method private method334 : (LFE;Ljava/lang/Throwable;Ljava/lang/String;Ljava/lang/String;)Ljava/lang/String;
    .code stack 8 locals 7
L0:     new java/io/ByteArrayOutputStream
L3:     dup
L4:     sipush 8192
L7:     iconst_1
L8:     dup
L9:     pop2
L10:    invokespecial Method java/io/ByteArrayOutputStream <init> (I)V
L13:    astore 5
L15:    new java/io/PrintWriter
L18:    dup
L19:    aload 5
L21:    invokespecial Method java/io/PrintWriter <init> (Ljava/io/OutputStream;)V
L24:    dup
L25:    astore 6
L27:    ldc "%1$tY-%1$tm-%1$td %1$tH:%1$tM:%1$tS"
L29:    iconst_1
L30:    dup
L31:    dup
L32:    pop2
L33:    anewarray java/lang/Object
L36:    iconst_1
L37:    dup
L38:    pop2
L39:    dup
L40:    iconst_0
L41:    iconst_1
L42:    dup
L43:    pop2
L44:    invokestatic Method java/util/Calendar getInstance ()Ljava/util/Calendar;
L47:    aastore
L48:    invokestatic Method java/lang/String format (Ljava/lang/String;[Ljava/lang/Object;)Ljava/lang/String;
L51:    invokevirtual Method java/io/PrintWriter println (Ljava/lang/String;)V
L54:    aload 6
L56:    dup
L57:    ldc "1.4c 29"
L59:    invokevirtual Method java/io/PrintWriter println (Ljava/lang/String;)V
L62:    new java/lang/StringBuilder
L65:    aload 6
L67:    dup_x2
L68:    dup
L69:    pop2
L70:    dup
L71:    invokespecial Method java/lang/StringBuilder <init> ()V
L74:    ldc "From: "
L76:    invokevirtual Method java/lang/StringBuilder append (Ljava/lang/String;)Ljava/lang/StringBuilder;
L79:    aload 4
L81:    invokevirtual Method java/lang/StringBuilder append (Ljava/lang/String;)Ljava/lang/StringBuilder;
L84:    ldc " ("
L86:    invokevirtual Method java/lang/StringBuilder append (Ljava/lang/String;)Ljava/lang/StringBuilder;
L89:    new java/lang/StringBuilder
L92:    dup
L93:    invokespecial Method java/lang/StringBuilder <init> ()V
L96:    iconst_0
L97:    getstatic Field Pc field373 LPc;
L100:   getfield Field Pc field370 Ljava/lang/String;
L103:   invokevirtual Method java/lang/StringBuilder insert (ILjava/lang/String;)Ljava/lang/StringBuilder;
L106:   ldc "li"
L108:   invokevirtual Method java/lang/StringBuilder append (Ljava/lang/String;)Ljava/lang/StringBuilder;
L111:   invokevirtual Method java/lang/StringBuilder toString ()Ljava/lang/String;
L114:   invokestatic Method JB method822 (Ljava/lang/String;)Ljava/lang/String;
L117:   invokevirtual Method java/lang/StringBuilder append (Ljava/lang/String;)Ljava/lang/StringBuilder;
L120:   ldc "/"
L122:   invokevirtual Method java/lang/StringBuilder append (Ljava/lang/String;)Ljava/lang/StringBuilder;
L125:   new java/lang/StringBuilder
L128:   dup
L129:   invokespecial Method java/lang/StringBuilder <init> ()V
L132:   iconst_0
L133:   getstatic Field Pc field373 LPc;
L136:   getfield Field Pc field370 Ljava/lang/String;
L139:   invokevirtual Method java/lang/StringBuilder insert (ILjava/lang/String;)Ljava/lang/StringBuilder;
L142:   ldc "a"
L144:   invokevirtual Method java/lang/StringBuilder append (Ljava/lang/String;)Ljava/lang/StringBuilder;
L147:   invokevirtual Method java/lang/StringBuilder toString ()Ljava/lang/String;
L150:   invokestatic Method JB method822 (Ljava/lang/String;)Ljava/lang/String;
L153:   invokevirtual Method java/lang/StringBuilder append (Ljava/lang/String;)Ljava/lang/StringBuilder;
L156:   ldc ")"
L158:   invokevirtual Method java/lang/StringBuilder append (Ljava/lang/String;)Ljava/lang/StringBuilder;
L161:   invokevirtual Method java/lang/StringBuilder toString ()Ljava/lang/String;
L164:   invokevirtual Method java/io/PrintWriter println (Ljava/lang/String;)V
L167:   new java/lang/StringBuilder
L170:   aload 6
L172:   dup
L173:   pop2
L174:   dup
L175:   invokespecial Method java/lang/StringBuilder <init> ()V
L178:   ldc "Cores: "
L180:   invokevirtual Method java/lang/StringBuilder append (Ljava/lang/String;)Ljava/lang/StringBuilder;
L183:   invokestatic Method java/lang/Runtime getRuntime ()Ljava/lang/Runtime;
L186:   invokevirtual Method java/lang/Runtime availableProcessors ()I
L189:   invokevirtual Method java/lang/StringBuilder append (I)Ljava/lang/StringBuilder;
L192:   ldc ""
L194:   invokevirtual Method java/lang/StringBuilder append (Ljava/lang/String;)Ljava/lang/StringBuilder;
L197:   invokevirtual Method java/lang/StringBuilder toString ()Ljava/lang/String;
L200:   invokevirtual Method java/io/PrintWriter println (Ljava/lang/String;)V
        .catch java/lang/Exception from L203 to L230 using L236
L203:   aload 6
L205:   new java/lang/StringBuilder
L208:   dup
L209:   invokespecial Method java/lang/StringBuilder <init> ()V
L212:   iconst_0
L213:   ldc "Adapter: "
L215:   invokevirtual Method java/lang/StringBuilder insert (ILjava/lang/String;)Ljava/lang/StringBuilder;
L218:   invokestatic Method org/lwjgl/opengl/Display method3025 ()Ljava/lang/String;
L221:   invokevirtual Method java/lang/StringBuilder append (Ljava/lang/String;)Ljava/lang/StringBuilder;
L224:   invokevirtual Method java/lang/StringBuilder toString ()Ljava/lang/String;
L227:   invokevirtual Method java/io/PrintWriter println (Ljava/lang/String;)V
L230:   aload 6
L232:   goto L240
L235:   athrow
L236:   astore 4
        .catch java/lang/Exception from L238 to L265 using L271
L238:   aload 6
L240:   new java/lang/StringBuilder
L243:   dup
L244:   invokespecial Method java/lang/StringBuilder <init> ()V
L247:   iconst_0
L248:   ldc "Sound: "
L250:   invokevirtual Method java/lang/StringBuilder insert (ILjava/lang/String;)Ljava/lang/StringBuilder;
L253:   invokestatic Method UE method420 ()Ljava/lang/String;
L256:   invokevirtual Method java/lang/StringBuilder append (Ljava/lang/String;)Ljava/lang/StringBuilder;
L259:   invokevirtual Method java/lang/StringBuilder toString ()Ljava/lang/String;
L262:   invokevirtual Method java/io/PrintWriter println (Ljava/lang/String;)V
L265:   aload 6
L267:   goto L275
L270:   athrow
L271:   astore 4
L273:   aload 6
L275:   new java/lang/StringBuilder
L278:   dup
L279:   invokespecial Method java/lang/StringBuilder <init> ()V
L282:   iconst_0
L283:   ldc "OS: "
L285:   invokevirtual Method java/lang/StringBuilder insert (ILjava/lang/String;)Ljava/lang/StringBuilder;
L288:   ldc "os.name"
L290:   invokestatic Method java/lang/System getProperty (Ljava/lang/String;)Ljava/lang/String;
L293:   invokevirtual Method java/lang/StringBuilder append (Ljava/lang/String;)Ljava/lang/StringBuilder;
L296:   ldc " "
L298:   invokevirtual Method java/lang/StringBuilder append (Ljava/lang/String;)Ljava/lang/StringBuilder;
L301:   ldc "os.arch"
L303:   invokestatic Method java/lang/System getProperty (Ljava/lang/String;)Ljava/lang/String;
L306:   invokevirtual Method java/lang/StringBuilder append (Ljava/lang/String;)Ljava/lang/StringBuilder;
L309:   ldc " "
L311:   invokevirtual Method java/lang/StringBuilder append (Ljava/lang/String;)Ljava/lang/StringBuilder;
L314:   ldc "os.version"
L316:   invokestatic Method java/lang/System getProperty (Ljava/lang/String;)Ljava/lang/String;
L319:   invokevirtual Method java/lang/StringBuilder append (Ljava/lang/String;)Ljava/lang/StringBuilder;
L322:   invokevirtual Method java/lang/StringBuilder toString ()Ljava/lang/String;
L325:   invokevirtual Method java/io/PrintWriter println (Ljava/lang/String;)V
L328:   aload 6
L330:   dup
L331:   new java/lang/StringBuilder
L334:   aload 6
L336:   dup_x1
L337:   dup
L338:   pop2
L339:   dup
L340:   invokespecial Method java/lang/StringBuilder <init> ()V
L343:   ldc "Mem: "
L345:   invokevirtual Method java/lang/StringBuilder append (Ljava/lang/String;)Ljava/lang/StringBuilder;
L348:   invokestatic Method java/lang/Runtime getRuntime ()Ljava/lang/Runtime;
L351:   invokevirtual Method java/lang/Runtime freeMemory ()J
L354:   ldc2_w 1024L
L357:   ldiv
L358:   invokevirtual Method java/lang/StringBuilder append (J)Ljava/lang/StringBuilder;
L361:   ldc "kb free of "
L363:   invokevirtual Method java/lang/StringBuilder append (Ljava/lang/String;)Ljava/lang/StringBuilder;
L366:   invokestatic Method java/lang/Runtime getRuntime ()Ljava/lang/Runtime;
L369:   invokevirtual Method java/lang/Runtime totalMemory ()J
L372:   ldc2_w 1024L
L375:   ldiv
L376:   invokevirtual Method java/lang/StringBuilder append (J)Ljava/lang/StringBuilder;
L379:   ldc "kb"
L381:   invokevirtual Method java/lang/StringBuilder append (Ljava/lang/String;)Ljava/lang/StringBuilder;
L384:   invokevirtual Method java/lang/StringBuilder toString ()Ljava/lang/String;
L387:   invokevirtual Method java/io/PrintWriter println (Ljava/lang/String;)V
L390:   new java/lang/StringBuilder
L393:   aload 6
L395:   dup_x2
L396:   dup
L397:   pop2
L398:   dup
L399:   invokespecial Method java/lang/StringBuilder <init> ()V
L402:   ldc "Machine: "
L404:   invokevirtual Method java/lang/StringBuilder append (Ljava/lang/String;)Ljava/lang/StringBuilder;
L407:   ldc "uuid"
L409:   invokestatic Method JB method822 (Ljava/lang/String;)Ljava/lang/String;
L412:   invokevirtual Method java/lang/StringBuilder append (Ljava/lang/String;)Ljava/lang/StringBuilder;
L415:   invokevirtual Method java/lang/StringBuilder toString ()Ljava/lang/String;
L418:   invokevirtual Method java/io/PrintWriter println (Ljava/lang/String;)V
L421:   new java/lang/StringBuilder
L424:   aload 6
L426:   dup
L427:   pop2
L428:   dup
L429:   invokespecial Method java/lang/StringBuilder <init> ()V
L432:   ldc "JVM: "
L434:   invokevirtual Method java/lang/StringBuilder append (Ljava/lang/String;)Ljava/lang/StringBuilder;
L437:   ldc "java.vm.name"
L439:   invokestatic Method java/lang/System getProperty (Ljava/lang/String;)Ljava/lang/String;
L442:   invokevirtual Method java/lang/StringBuilder append (Ljava/lang/String;)Ljava/lang/StringBuilder;
L445:   ldc " "
L447:   invokevirtual Method java/lang/StringBuilder append (Ljava/lang/String;)Ljava/lang/StringBuilder;
L450:   ldc "java.vm.version"
L452:   invokestatic Method java/lang/System getProperty (Ljava/lang/String;)Ljava/lang/String;
L455:   invokevirtual Method java/lang/StringBuilder append (Ljava/lang/String;)Ljava/lang/StringBuilder;
L458:   invokevirtual Method java/lang/StringBuilder toString ()Ljava/lang/String;
L461:   invokevirtual Method java/io/PrintWriter println (Ljava/lang/String;)V
L464:   new java/lang/StringBuilder
L467:   aload 6
L469:   dup
L470:   pop2
L471:   dup
L472:   invokespecial Method java/lang/StringBuilder <init> ()V
L475:   ldc "Time: "
L477:   invokevirtual Method java/lang/StringBuilder append (Ljava/lang/String;)Ljava/lang/StringBuilder;
L480:   ldc_w "%.1f"
L483:   iconst_1
L484:   dup
L485:   dup
L486:   pop2
L487:   anewarray java/lang/Object
L490:   iconst_1
L491:   dup
L492:   pop2
L493:   dup
L494:   iconst_0
L495:   iconst_1
L496:   dup
L497:   pop2
L498:   invokestatic Method OC method1015 ()D
L501:   invokestatic Method java/lang/Double valueOf (D)Ljava/lang/Double;
L504:   aastore
L505:   invokestatic Method java/lang/String format (Ljava/lang/String;[Ljava/lang/Object;)Ljava/lang/String;
L508:   invokevirtual Method java/lang/StringBuilder append (Ljava/lang/String;)Ljava/lang/StringBuilder;
L511:   invokevirtual Method java/lang/StringBuilder toString ()Ljava/lang/String;
L514:   invokevirtual Method java/io/PrintWriter println (Ljava/lang/String;)V
L517:   aload_1
L518:   aload 6
L520:   ldc_w "-------------------------------------------"
L523:   invokevirtual Method java/io/PrintWriter println (Ljava/lang/String;)V
L526:   ifnull L535
L529:   aload_1
L530:   aload 6
L532:   invokevirtual Method FE method461 (Ljava/io/PrintWriter;)V
L535:   aload 6
L537:   ldc_w "-------------------------------------------"
L540:   invokevirtual Method java/io/PrintWriter println (Ljava/lang/String;)V
L543:   aload_2
L544:   dup
L545:   aload 6
L547:   invokevirtual Method java/lang/Throwable printStackTrace (Ljava/io/PrintWriter;)V
L550:   invokevirtual Method java/lang/Throwable getCause ()Ljava/lang/Throwable;
L553:   ifnull L579
L556:   aload_2
L557:   invokevirtual Method java/lang/Throwable getCause ()Ljava/lang/Throwable;
L560:   dup
L561:   astore_2
L562:   dup
L563:   aload 6
L565:   ldc_w "Caused by "
L568:   invokevirtual Method java/io/PrintWriter print (Ljava/lang/String;)V
L571:   aload 6
L573:   invokevirtual Method java/lang/Throwable printStackTrace (Ljava/io/PrintWriter;)V
L576:   goto L550
L579:   aload 6
L581:   aload_3
L582:   aload 6
L584:   dup_x1
L585:   ldc_w "-------------------------------------------"
L588:   invokevirtual Method java/io/PrintWriter println (Ljava/lang/String;)V
L591:   invokevirtual Method java/io/PrintWriter println (Ljava/lang/String;)V
L594:   invokevirtual Method java/io/PrintWriter close ()V
L597:   aload 5
L599:   invokevirtual Method java/io/ByteArrayOutputStream toString ()Ljava/lang/String;
L602:   areturn
L603:   
        .attribute StackMap b'\x00\x09\x00\xEB\x00\x00\x00\x01\x07\x00\x14\x00\xEC\x00\x07\x07\x00\x02\x07\x00\x67\x07\x00\x14\x07\x00\x6B\x07\x00\x6B\x07\x00\x83\x07\x00\x87\x00\x01\x07\x00\x81\x00\xF0\x00\x07\x07\x00\x02\x07\x00\x67\x07\x00\x14\x07\x00\x6B\x07\x00\x72\x07\x00\x83\x07\x00\x87\x00\x01\x07\x00\x87\x01\x0E\x00\x00\x00\x01\x07\x00\x14\x01\x0F\x00\x07\x07\x00\x02\x07\x00\x67\x07\x00\x14\x07\x00\x6B\x07\x00\x72\x07\x00\x83\x07\x00\x87\x00\x01\x07\x00\x81\x01\x13\x00\x07\x07\x00\x02\x07\x00\x67\x07\x00\x14\x07\x00\x6B\x07\x00\x72\x07\x00\x83\x07\x00\x87\x00\x01\x07\x00\x87\x02\x17\x00\x07\x07\x00\x02\x07\x00\x67\x07\x00\x14\x07\x00\x6B\x07\x00\x72\x07\x00\x83\x07\x00\x87\x00\x00\x02\x26\x00\x07\x07\x00\x02\x07\x00\x67\x07\x00\x14\x07\x00\x6B\x07\x00\x72\x07\x00\x83\x07\x00\x87\x00\x01\x07\x00\x14\x02\x43\x00\x07\x07\x00\x02\x07\x00\x67\x07\x00\x14\x07\x00\x6B\x07\x00\x72\x07\x00\x83\x07\x00\x87\x00\x00'
    .end code
.end method

.method public getInsets : ()Ljava/awt/Insets;
    .code stack 9 locals 1
L0:     aload_0
L1:     invokespecial Method java/awt/Frame getInsets ()Ljava/awt/Insets;
L4:     dup
L5:     dup_x1
L6:     dup2
L7:     dup
L8:     getfield Field java/awt/Insets bottom I
L11:    bipush 16
L13:    iconst_1
L14:    dup
L15:    pop2
L16:    iadd
L17:    putfield Field java/awt/Insets bottom I
L20:    dup
L21:    getfield Field java/awt/Insets top I
L24:    bipush 16
L26:    iconst_1
L27:    dup
L28:    pop2
L29:    iadd
L30:    putfield Field java/awt/Insets top I
L33:    dup
L34:    getfield Field java/awt/Insets left I
L37:    bipush 16
L39:    iconst_1
L40:    dup
L41:    pop2
L42:    iadd
L43:    putfield Field java/awt/Insets left I
L46:    dup
L47:    getfield Field java/awt/Insets right I
L50:    bipush 16
L52:    iconst_1
L53:    dup
L54:    pop2
L55:    iadd
L56:    putfield Field java/awt/Insets right I
L59:    areturn
L60:    
    .end code
.end method

.method public <init> : (LFE;Ljava/lang/Throwable;)V
    .code stack 22 locals 7
L0:     aload_0
L1:     dup
L2:     dup_x1
L3:     dup2
L4:     dup2
L5:     dup2
L6:     dup2
L7:     iconst_0
L8:     aload_0
L9:     dup
L10:    dup_x2
L11:    ldc_w "Cultris II"
L14:    invokespecial Method java/awt/Frame <init> (Ljava/lang/String;)V
L17:    invokestatic Method mD method1708 ()Ljava/awt/Image;
L20:    invokevirtual Method sD setIconImage (Ljava/awt/Image;)V
L23:    iconst_1
L24:    dup
L25:    pop2
L26:    invokevirtual Method sD setResizable (Z)V
L29:    new java/awt/GridBagLayout
L32:    aload_0
L33:    dup_x2
L34:    dup
L35:    pop2
L36:    dup
L37:    invokespecial Method java/awt/GridBagLayout <init> ()V
L40:    invokevirtual Method sD setLayout (Ljava/awt/LayoutManager;)V
L43:    new java/awt/GridBagConstraints
L46:    dup
L47:    invokespecial Method java/awt/GridBagConstraints <init> ()V
L50:    astore_3
L51:    new java/awt/Label
L54:    dup
L55:    ldc_w "Oh oh, it looks like Cultris II just crashed. Sorry about that!"
L58:    invokespecial Method java/awt/Label <init> (Ljava/lang/String;)V
L61:    astore 4
L63:    aload_3
L64:    dup
L65:    aload 4
L67:    dup_x2
L68:    new java/awt/Font
L71:    aload 4
L73:    dup
L74:    pop2
L75:    dup
L76:    ldc_w "SansSerif"
L79:    iconst_1
L80:    dup
L81:    pop2
L82:    bipush 15
L84:    iconst_1
L85:    dup_x1
L86:    dup
L87:    pop2
L88:    invokespecial Method java/awt/Font <init> (Ljava/lang/String;II)V
L91:    invokevirtual Method java/awt/Label setFont (Ljava/awt/Font;)V
L94:    iconst_2
L95:    iconst_0
L96:    aload_3
L97:    dup_x1
L98:    bipush 17
L100:   iconst_1
L101:   dup
L102:   pop2
L103:   putfield Field java/awt/GridBagConstraints anchor I
L106:   iconst_1
L107:   dup
L108:   pop2
L109:   putfield Field java/awt/GridBagConstraints gridwidth I
L112:   iconst_1
L113:   dup
L114:   pop2
L115:   putfield Field java/awt/GridBagConstraints fill I
L118:   invokevirtual Method sD add (Ljava/awt/Component;Ljava/lang/Object;)V
L121:   iconst_2
L122:   aload_3
L123:   dup_x1
L124:   iconst_0
L125:   aload_3
L126:   bipush 17
L128:   iconst_1
L129:   dup
L130:   pop2
L131:   putfield Field java/awt/GridBagConstraints anchor I
L134:   iconst_1
L135:   dup
L136:   pop2
L137:   putfield Field java/awt/GridBagConstraints gridwidth I
L140:   iconst_1
L141:   dup
L142:   pop2
L143:   putfield Field java/awt/GridBagConstraints fill I
L146:   new java/awt/Label
L149:   aload_0
L150:   dup
L151:   pop2
L152:   dup
L153:   ldc_w "Please help us fix this problem! What did you do before it crashed?"
L156:   invokespecial Method java/awt/Label <init> (Ljava/lang/String;)V
L159:   aload_3
L160:   invokevirtual Method sD add (Ljava/awt/Component;Ljava/lang/Object;)V
L163:   new java/awt/TextArea
L166:   dup
L167:   aconst_null
L168:   bipush 6
L170:   iconst_1
L171:   dup
L172:   pop2
L173:   iconst_0
L174:   iconst_1
L175:   dup
L176:   pop2
L177:   iconst_1
L178:   dup
L179:   dup
L180:   pop2
L181:   invokespecial Method java/awt/TextArea <init> (Ljava/lang/String;III)V
L184:   dup
L185:   astore 4
L187:   iconst_2
L188:   aload_3
L189:   dup_x1
L190:   dup_x2
L191:   iconst_0
L192:   aload_3
L193:   bipush 17
L195:   iconst_1
L196:   dup
L197:   pop2
L198:   putfield Field java/awt/GridBagConstraints anchor I
L201:   iconst_1
L202:   dup
L203:   pop2
L204:   putfield Field java/awt/GridBagConstraints gridwidth I
L207:   iconst_1
L208:   dup
L209:   pop2
L210:   putfield Field java/awt/GridBagConstraints fill I
L213:   invokevirtual Method sD add (Ljava/awt/Component;Ljava/lang/Object;)V
L216:   iconst_2
L217:   aload_3
L218:   dup_x1
L219:   dup_x2
L220:   iconst_0
L221:   aload_3
L222:   bipush 17
L224:   iconst_1
L225:   dup
L226:   pop2
L227:   putfield Field java/awt/GridBagConstraints anchor I
L230:   iconst_1
L231:   dup
L232:   pop2
L233:   putfield Field java/awt/GridBagConstraints gridwidth I
L236:   iconst_1
L237:   dup
L238:   pop2
L239:   putfield Field java/awt/GridBagConstraints fill I
L242:   getfield Field java/awt/GridBagConstraints insets Ljava/awt/Insets;
L245:   bipush 16
L247:   iconst_1
L248:   dup
L249:   pop2
L250:   putfield Field java/awt/Insets top I
L253:   new java/awt/Label
L256:   aload_0
L257:   dup
L258:   pop2
L259:   dup
L260:   ldc_w "It might happen that we'd like to ask you some additional questions in order to"
L263:   invokespecial Method java/awt/Label <init> (Ljava/lang/String;)V
L266:   aload_3
L267:   invokevirtual Method sD add (Ljava/awt/Component;Ljava/lang/Object;)V
L270:   aload_3
L271:   getfield Field java/awt/GridBagConstraints insets Ljava/awt/Insets;
L274:   bipush -5
L276:   iconst_1
L277:   dup
L278:   pop2
L279:   putfield Field java/awt/Insets top I
L282:   new java/awt/Label
L285:   aload_0
L286:   dup
L287:   pop2
L288:   dup
L289:   ldc_w "fix the bug. Please leave your email address if you're ok with that."
L292:   invokespecial Method java/awt/Label <init> (Ljava/lang/String;)V
L295:   aload_3
L296:   invokevirtual Method sD add (Ljava/awt/Component;Ljava/lang/Object;)V
L299:   new java/awt/TextField
L302:   dup
L303:   invokespecial Method java/awt/TextField <init> ()V
L306:   dup
L307:   astore 5
L309:   aload_3
L310:   dup
L311:   iconst_0
L312:   aload_3
L313:   dup_x2
L314:   iconst_2
L315:   aload_3
L316:   bipush 17
L318:   iconst_1
L319:   dup
L320:   pop2
L321:   putfield Field java/awt/GridBagConstraints anchor I
L324:   iconst_1
L325:   dup
L326:   pop2
L327:   putfield Field java/awt/GridBagConstraints fill I
L330:   iconst_1
L331:   dup
L332:   pop2
L333:   putfield Field java/awt/GridBagConstraints gridwidth I
L336:   getfield Field java/awt/GridBagConstraints insets Ljava/awt/Insets;
L339:   iconst_0
L340:   iconst_1
L341:   dup
L342:   pop2
L343:   putfield Field java/awt/Insets top I
L346:   invokevirtual Method sD add (Ljava/awt/Component;Ljava/lang/Object;)V
L349:   new java/awt/Button
L352:   dup
L353:   ldc_w "Send report"
L356:   invokespecial Method java/awt/Button <init> (Ljava/lang/String;)V
L359:   dup
L360:   astore 6
L362:   aload_3
L363:   dup
L364:   iconst_0
L365:   aload_3
L366:   dup_x2
L367:   bipush 13
L369:   aload_3
L370:   iconst_0
L371:   iconst_1
L372:   dup
L373:   pop2
L374:   putfield Field java/awt/GridBagConstraints gridwidth I
L377:   iconst_1
L378:   dup
L379:   pop2
L380:   putfield Field java/awt/GridBagConstraints anchor I
L383:   iconst_1
L384:   dup
L385:   pop2
L386:   putfield Field java/awt/GridBagConstraints fill I
L389:   getfield Field java/awt/GridBagConstraints insets Ljava/awt/Insets;
L392:   bipush 8
L394:   iconst_1
L395:   dup
L396:   pop2
L397:   putfield Field java/awt/Insets top I
L400:   invokevirtual Method sD add (Ljava/awt/Component;Ljava/lang/Object;)V
L403:   new sd
L406:   aload 6
L408:   dup_x1
L409:   dup
L410:   pop2
L411:   dup
L412:   aload_0
L413:   invokespecial Method sd <init> (LsD;)V
L416:   invokevirtual Method java/awt/Button addActionListener (Ljava/awt/event/ActionListener;)V
L419:   new Wc
L422:   aload_0
L423:   dup
L424:   pop2
L425:   dup
L426:   aload_0
L427:   aload_1
L428:   aload_2
L429:   aload 4
L431:   aload 5
L433:   invokespecial Method Wc <init> (LsD;LFE;Ljava/lang/Throwable;Ljava/awt/TextArea;Ljava/awt/TextField;)V
L436:   invokevirtual Method sD addWindowListener (Ljava/awt/event/WindowListener;)V
L439:   invokevirtual Method sD pack ()V
L442:   aconst_null
L443:   invokevirtual Method sD setLocationRelativeTo (Ljava/awt/Component;)V
L446:   iconst_1
L447:   dup
L448:   dup
L449:   pop2
L450:   invokevirtual Method sD setVisible (Z)V
L453:   return
L454:   
    .end code
    .exceptions java/lang/Exception
.end method

.method public static method335 : (LFE;Ljava/lang/Throwable;)V
    .code stack 7 locals 3
        .catch java/lang/Throwable from L0 to L70 using L74
L0:     new java/io/PrintWriter
L3:     dup
L4:     ldc_w "errlog.txt"
L7:     invokespecial Method java/io/PrintWriter <init> (Ljava/lang/String;)V
L10:    astore_2
L11:    ldc "%1$tY-%1$tm-%1$td %1$tH:%1$tM:%1$tS"
L13:    aload_2
L14:    dup_x1
L15:    ldc_w "---------------------------------------"
L18:    invokevirtual Method java/io/PrintWriter println (Ljava/lang/String;)V
L21:    iconst_1
L22:    dup
L23:    dup
L24:    pop2
L25:    anewarray java/lang/Object
L28:    iconst_1
L29:    dup
L30:    pop2
L31:    dup
L32:    iconst_0
L33:    iconst_1
L34:    dup
L35:    pop2
L36:    invokestatic Method java/util/Calendar getInstance ()Ljava/util/Calendar;
L39:    aastore
L40:    invokestatic Method java/lang/String format (Ljava/lang/String;[Ljava/lang/Object;)Ljava/lang/String;
L43:    invokevirtual Method java/io/PrintWriter println (Ljava/lang/String;)V
L46:    aload_0
L47:    aload_2
L48:    ldc "1.4c 29"
L50:    invokevirtual Method java/io/PrintWriter println (Ljava/lang/String;)V
L53:    ifnull L61
L56:    aload_0
L57:    aload_2
L58:    invokevirtual Method FE method461 (Ljava/io/PrintWriter;)V
L61:    aload_1
L62:    aload_2
L63:    invokevirtual Method java/lang/Throwable printStackTrace (Ljava/io/PrintWriter;)V
L66:    aload_2
L67:    invokevirtual Method java/io/PrintWriter close ()V
L70:    goto L75
L73:    athrow
L74:    astore_2
L75:    ldc_w "Cultris II"
L78:    ldc_w "Cultris II crashed and we couldn't send a report automatically.\u000APlease post in our forum on http://gewaltig.net/ and attach the\u000Afile errlog.txt from the application directory.\u000A\u000AThank you very much!"
L81:    invokestatic Method org/lwjgl/Sys method1890 (Ljava/lang/String;Ljava/lang/String;)V
L84:    return
L85:    
        .attribute StackMap b'\x00\x04\x00\x3D\x00\x03\x07\x00\x67\x07\x00\x14\x07\x00\x87\x00\x00\x00\x49\x00\x00\x00\x01\x07\x00\x14\x00\x4A\x00\x02\x07\x00\x67\x07\x00\x14\x00\x01\x07\x00\x14\x00\x4B\x00\x03\x07\x00\x67\x07\x00\x14\x07\x00\x72\x00\x00'
    .end code
.end method
.innerclasses
    Pc JB [0] public static final enum
    Wc [0] [0]
    sd [0] [0]
.end innerclasses
.end class
