.version 49 0
.class public final super Sd
.super java/lang/Object
.implements java/lang/Runnable
.field public final synthetic field1698 Lwb;

.method public run : ()V
    .code stack 5 locals 7
L0:     aconst_null
L1:     astore_1
        .catch java/lang/NullPointerException from L2 to L49 using L191
L2:     new java/io/BufferedOutputStream
L5:     dup
L6:     aload_0
L7:     getfield Field Sd field1698 Lwb;
L10:    getfield Field wb new Ljava/net/Socket;
L13:    invokevirtual Method java/net/Socket getOutputStream ()Ljava/io/OutputStream;
L16:    invokespecial Method java/io/BufferedOutputStream <init> (Ljava/io/OutputStream;)V
L19:    astore_1
L20:    new java/util/Random
L23:    dup
L24:    invokespecial Method java/util/Random <init> ()V
L27:    dup
L28:    astore_2
L29:    invokevirtual Method java/util/Random nextInt ()I
L32:    sipush 255
L35:    iconst_1
L36:    dup
L37:    pop2
L38:    iand
L39:    i2b
L40:    dup
L41:    istore_3
L42:    ifne L50
L45:    aload_2
L46:    goto L29
L49:    athrow
        .catch java/lang/NullPointerException from L50 to L172 using L191
L50:    aload_1
L51:    dup
L52:    iload_3
L53:    invokevirtual Method java/io/BufferedOutputStream write (I)V
L56:    invokevirtual Method java/io/BufferedOutputStream flush ()V
L59:    new java/util/ArrayList
L62:    dup
L63:    iconst_5
L64:    iconst_1
L65:    dup
L66:    pop2
L67:    invokespecial Method java/util/ArrayList <init> (I)V
L70:    dup
L71:    astore 4
L73:    aload_0
L74:    getfield Field Sd field1698 Lwb;
L77:    getfield Field wb field5830 Ljava/util/concurrent/LinkedBlockingQueue;
L80:    invokevirtual Method java/util/concurrent/LinkedBlockingQueue take ()Ljava/lang/Object;
L83:    invokevirtual Method java/util/ArrayList add (Ljava/lang/Object;)Z
L86:    ldc2_w 60L
L89:    invokestatic Method java/lang/Thread sleep (J)V
L92:    aload_0
L93:    getfield Field Sd field1698 Lwb;
L96:    getfield Field wb field5830 Ljava/util/concurrent/LinkedBlockingQueue;
L99:    aload 4
L101:   invokevirtual Method java/util/concurrent/LinkedBlockingQueue drainTo (Ljava/util/Collection;)I
L104:   aload 4
L106:   dup
L107:   invokestatic Method Wb method1079 (Ljava/util/List;)V
L110:   invokevirtual Method java/util/ArrayList iterator ()Ljava/util/Iterator;
L113:   astore 4
L115:   pop2
L116:   aload 4
L118:   invokeinterface InterfaceMethod java/util/Iterator hasNext ()Z 1
L123:   ifeq L184
L126:   aload 4
L128:   invokeinterface InterfaceMethod java/util/Iterator next ()Ljava/lang/Object; 1
L133:   checkcast fD
L136:   invokevirtual Method fD method1138 ()[B
L139:   astore 5
L141:   iconst_0
L142:   iconst_1
L143:   dup
L144:   pop2
L145:   dup
L146:   istore 6
L148:   aload 5
L150:   arraylength
L151:   if_icmpge L173
L154:   aload 5
L156:   iload 6
L158:   dup2
L159:   baload
L160:   iload_3
L161:   ixor
L162:   i2b
L163:   iinc 6 1
L166:   bastore
L167:   iload 6
L169:   goto L148
L172:   athrow
        .catch java/lang/NullPointerException from L173 to L191 using L191
        .catch java/io/IOException from L2 to L49 using L196
        .catch java/io/IOException from L50 to L172 using L196
        .catch java/io/IOException from L173 to L191 using L196
        .catch java/lang/InterruptedException from L2 to L49 using L201
        .catch java/lang/InterruptedException from L50 to L172 using L201
        .catch java/lang/InterruptedException from L173 to L191 using L201
L173:   aload_1
L174:   aload 5
L176:   invokevirtual Method java/io/BufferedOutputStream write ([B)V
L179:   aload 4
L181:   goto L118
L184:   aload_1
L185:   invokevirtual Method java/io/BufferedOutputStream flush ()V
L188:   goto L59
L191:   astore_2
L192:   aload_1
L193:   goto L203
L196:   astore_2
L197:   aload_1
L198:   goto L203
L201:   astore_2
L202:   aload_1
L203:   ifnull L219
        .catch java/io/IOException from L206 to L210 using L214
L206:   aload_1
L207:   invokevirtual Method java/io/BufferedOutputStream close ()V
L210:   aload_0
L211:   goto L220
L214:   astore_2
L215:   aload_2
L216:   invokevirtual Method java/io/IOException printStackTrace ()V
L219:   aload_0
L220:   getfield Field Sd field1698 Lwb;
L223:   invokevirtual Method wb method5822 ()V
L226:   return
L227:   
        .attribute StackMap b'\x00\x10\x00\x1D\x00\x03\x07\x00\x02\x07\x00\x14\x07\x00\x26\x00\x01\x07\x00\x26\x00\x31\x00\x00\x00\x01\x07\x00\x2E\x00\x32\x00\x04\x07\x00\x02\x07\x00\x14\x07\x00\x26\x01\x00\x00\x00\x3B\x00\x04\x07\x00\x02\x07\x00\x14\x07\x00\x26\x01\x00\x00\x00\x76\x00\x05\x07\x00\x02\x07\x00\x14\x07\x00\x26\x01\x07\x00\x5F\x00\x01\x07\x00\x5F\x00\x94\x00\x07\x07\x00\x02\x07\x00\x14\x07\x00\x26\x01\x07\x00\x5F\x07\x00\x6E\x01\x00\x01\x01\x00\xAC\x00\x00\x00\x01\x07\x00\x2E\x00\xAD\x00\x07\x07\x00\x02\x07\x00\x14\x07\x00\x26\x01\x07\x00\x5F\x07\x00\x6E\x01\x00\x00\x00\xB8\x00\x05\x07\x00\x02\x07\x00\x14\x07\x00\x26\x01\x07\x00\x5F\x00\x00\x00\xBF\x00\x02\x07\x00\x02\x07\x00\x14\x00\x01\x07\x00\x0E\x00\xC4\x00\x02\x07\x00\x02\x07\x00\x14\x00\x01\x07\x00\x10\x00\xC9\x00\x02\x07\x00\x02\x07\x00\x14\x00\x01\x07\x00\x12\x00\xCB\x00\x03\x07\x00\x02\x07\x00\x14\x07\x00\x73\x00\x01\x07\x00\x14\x00\xD6\x00\x03\x07\x00\x02\x07\x00\x14\x07\x00\x73\x00\x01\x07\x00\x10\x00\xDB\x00\x03\x07\x00\x02\x07\x00\x14\x07\x00\x73\x00\x00\x00\xDC\x00\x03\x07\x00\x02\x07\x00\x14\x07\x00\x73\x00\x01\x07\x00\x02'
    .end code
.end method

.method public <init> : (Lwb;)V
    .code stack 3 locals 2
L0:     aload_0
L1:     dup
L2:     aload_1
L3:     putfield Field Sd field1698 Lwb;
L6:     invokespecial Method java/lang/Object <init> ()V
L9:     return
L10:    
    .end code
.end method
.innerclasses
    Sd [0] [0]
.end innerclasses
.enclosing method wb [0]
.end class
