.version 49 0
.class public final super SE
.super java/lang/Object
.field public static final else Ljava/util/Map;
.field public static final "enum" LTe;
.field public static final do Ljava/util/Map;

.method private static varargs kajitani : ([LTe;)LTe;
    .code stack 22 locals 1
L0:     new Te
L3:     dup
L4:     ldc "Kajitani"
L6:     ldc "You're safe as long as you play faster than your opponents."
L8:     ldc "kajitani"
L10:    new XF
L13:    dup
L14:    invokespecial Method XF <init> ()V
L17:    iconst_2
L18:    iconst_1
L19:    dup
L20:    pop2
L21:    ldc 3e-1f
L23:    ldc 2147483647
L25:    iconst_1
L26:    dup
L27:    dup
L28:    pop2
L29:    anewarray Uf
L32:    iconst_1
L33:    dup
L34:    pop2
L35:    dup
L36:    iconst_0
L37:    iconst_1
L38:    dup
L39:    pop2
L40:    new uD
L43:    dup
L44:    aconst_null
L45:    dup
L46:    dup_x1
L47:    iconst_1
L48:    dup
L49:    pop2
L50:    iconst_0
L51:    iconst_1
L52:    dup
L53:    pop2
L54:    iconst_0
L55:    dup_x1
L56:    iconst_1
L57:    dup
L58:    pop2
L59:    invokespecial Method uD <init> (Ljava/lang/String;Ljava/lang/String;Ljava/lang/String;IIZ)V
L62:    aastore
L63:    iconst_0
L64:    iconst_1
L65:    dup
L66:    pop2
L67:    anewarray Uf
L70:    iconst_1
L71:    dup
L72:    pop2
L73:    invokespecial Method Te <init> (Ljava/lang/String;Ljava/lang/String;Ljava/lang/String;Leb;IFI[LUf;[LUf;)V
L76:    dup
L77:    getfield Field Te char Ljava/util/LinkedList;
L80:    aload_0
L81:    invokestatic Method java/util/Arrays asList ([Ljava/lang/Object;)Ljava/util/List;
L84:    invokevirtual Method java/util/LinkedList addAll (Ljava/util/Collection;)Z
L87:    pop
L88:    areturn
L89:    
    .end code
.end method

.method private static varargs booring : ([LTe;)LTe;
    .code stack 22 locals 1
L0:     new Te
L3:     dup
L4:     ldc "April 11th, 1954"
L6:     ldc "Win against two opponents while staying below 60 BPM."
L8:     ldc "booring"
L10:    new Qb
L13:    dup
L14:    invokespecial Method Qb <init> ()V
L17:    iconst_2
L18:    iconst_1
L19:    dup
L20:    pop2
L21:    ldc 2.5e-1f
L23:    bipush 60
L25:    iconst_1
L26:    dup
L27:    pop2
L28:    iconst_1
L29:    dup
L30:    dup
L31:    pop2
L32:    anewarray Uf
L35:    iconst_1
L36:    dup
L37:    pop2
L38:    dup
L39:    iconst_0
L40:    iconst_1
L41:    dup
L42:    pop2
L43:    new uD
L46:    dup
L47:    aconst_null
L48:    dup
L49:    dup_x1
L50:    iconst_1
L51:    dup
L52:    pop2
L53:    iconst_0
L54:    iconst_1
L55:    dup
L56:    pop2
L57:    iconst_0
L58:    dup_x1
L59:    iconst_1
L60:    dup
L61:    pop2
L62:    invokespecial Method uD <init> (Ljava/lang/String;Ljava/lang/String;Ljava/lang/String;IIZ)V
L65:    aastore
L66:    iconst_0
L67:    iconst_1
L68:    dup
L69:    pop2
L70:    anewarray Uf
L73:    iconst_1
L74:    dup
L75:    pop2
L76:    invokespecial Method Te <init> (Ljava/lang/String;Ljava/lang/String;Ljava/lang/String;Leb;IFI[LUf;[LUf;)V
L79:    dup
L80:    getfield Field Te char Ljava/util/LinkedList;
L83:    aload_0
L84:    invokestatic Method java/util/Arrays asList ([Ljava/lang/Object;)Ljava/util/List;
L87:    invokevirtual Method java/util/LinkedList addAll (Ljava/util/Collection;)Z
L90:    pop
L91:    areturn
L92:    
    .end code
.end method

.method private static varargs brrr : ([LTe;)LTe;
    .code stack 24 locals 1
L0:     new Te
L3:     dup
L4:     ldc "Battle Royale"
L6:     ldc "Just keep playing for 90 seconds."
L8:     ldc "brrr"
L10:    new Qb
L13:    dup
L14:    invokespecial Method Qb <init> ()V
L17:    iconst_0
L18:    iconst_1
L19:    dup
L20:    pop2
L21:    fconst_1
L22:    ldc 2147483647
L24:    iconst_1
L25:    dup
L26:    dup
L27:    pop2
L28:    anewarray Uf
L31:    iconst_1
L32:    dup
L33:    pop2
L34:    dup
L35:    iconst_0
L36:    iconst_1
L37:    dup
L38:    pop2
L39:    new mg
L42:    dup
L43:    aconst_null
L44:    dup
L45:    dup_x1
L46:    ldc 9e1f
L48:    iconst_1
L49:    dup
L50:    pop2
L51:    iconst_0
L52:    iconst_1
L53:    dup
L54:    pop2
L55:    iconst_0
L56:    iconst_1
L57:    dup_x2
L58:    dup
L59:    pop2
L60:    iconst_0
L61:    iconst_1
L62:    dup
L63:    pop2
L64:    invokespecial Method mg <init> (Ljava/lang/String;Ljava/lang/String;Ljava/lang/String;FZZIZ)V
L67:    aastore
L68:    iconst_1
L69:    dup
L70:    dup
L71:    pop2
L72:    anewarray Uf
L75:    iconst_1
L76:    dup
L77:    pop2
L78:    dup
L79:    iconst_0
L80:    iconst_1
L81:    dup
L82:    pop2
L83:    new ve
L86:    dup
L87:    iconst_1
L88:    dup
L89:    dup
L90:    pop2
L91:    ldc 6e0f
L93:    invokespecial Method ve <init> (IF)V
L96:    aastore
L97:    invokespecial Method Te <init> (Ljava/lang/String;Ljava/lang/String;Ljava/lang/String;Leb;IFI[LUf;[LUf;)V
L100:   dup
L101:   getfield Field Te char Ljava/util/LinkedList;
L104:   aload_0
L105:   invokestatic Method java/util/Arrays asList ([Ljava/lang/Object;)Ljava/util/List;
L108:   invokevirtual Method java/util/LinkedList addAll (Ljava/util/Collection;)Z
L111:   pop
L112:   areturn
L113:   
    .end code
.end method

.method private static varargs tgm : ([LTe;)LTe;
    .code stack 22 locals 1
L0:     new Te
L3:     dup
L4:     ldc "Shi Tai Ye"
L6:     ldc "Who wants to be \u00ABThe Great Grand Master\u00BB?"
L8:     ldc "tgm"
L10:    new Qe
L13:    dup
L14:    invokespecial Method Qe <init> ()V
L17:    iconst_0
L18:    iconst_1
L19:    dup
L20:    pop2
L21:    fconst_1
L22:    ldc 2147483647
L24:    iconst_1
L25:    dup
L26:    dup
L27:    pop2
L28:    anewarray Uf
L31:    iconst_1
L32:    dup
L33:    pop2
L34:    dup
L35:    iconst_0
L36:    iconst_1
L37:    dup
L38:    pop2
L39:    new YE
L42:    dup
L43:    aconst_null
L44:    dup
L45:    dup_x1
L46:    bipush 10
L48:    iconst_1
L49:    dup
L50:    pop2
L51:    iconst_0
L52:    iconst_1
L53:    dup
L54:    pop2
L55:    iconst_0
L56:    iconst_1
L57:    dup
L58:    pop2
L59:    invokespecial Method YE <init> (Ljava/lang/String;Ljava/lang/String;Ljava/lang/String;IIZ)V
L62:    aastore
L63:    iconst_1
L64:    dup
L65:    dup
L66:    pop2
L67:    anewarray Uf
L70:    iconst_1
L71:    dup
L72:    pop2
L73:    dup
L74:    iconst_0
L75:    iconst_1
L76:    dup
L77:    pop2
L78:    new Le
L81:    dup
L82:    invokespecial Method Le <init> ()V
L85:    aastore
L86:    invokespecial Method Te <init> (Ljava/lang/String;Ljava/lang/String;Ljava/lang/String;Leb;IFI[LUf;[LUf;)V
L89:    dup
L90:    getfield Field Te char Ljava/util/LinkedList;
L93:    aload_0
L94:    invokestatic Method java/util/Arrays asList ([Ljava/lang/Object;)Ljava/util/List;
L97:    invokevirtual Method java/util/LinkedList addAll (Ljava/util/Collection;)Z
L100:   pop
L101:   areturn
L102:   
    .end code
.end method

.method private static varargs shep : ([LTe;)LTe;
    .code stack 24 locals 1
L0:     new Te
L3:     dup
L4:     ldc "Shepherd"
L6:     ldc "Take good care of your opponent for three minutes."
L8:     ldc "shep"
L10:    new yF
L13:    dup
L14:    invokespecial Method yF <init> ()V
L17:    iconst_1
L18:    dup
L19:    pop2
L20:    fconst_1
L21:    ldc 2147483647
L23:    iconst_1
L24:    dup_x2
L25:    iconst_1
L26:    dup
L27:    pop2
L28:    anewarray Uf
L31:    iconst_1
L32:    dup
L33:    pop2
L34:    dup
L35:    iconst_0
L36:    iconst_1
L37:    dup
L38:    pop2
L39:    new mg
L42:    dup
L43:    aconst_null
L44:    dup
L45:    dup_x1
L46:    ldc 1.8e2f
L48:    iconst_1
L49:    dup
L50:    pop2
L51:    iconst_0
L52:    iconst_1
L53:    dup
L54:    pop2
L55:    iconst_0
L56:    iconst_1
L57:    dup_x2
L58:    dup
L59:    pop2
L60:    iconst_0
L61:    iconst_1
L62:    dup
L63:    pop2
L64:    invokespecial Method mg <init> (Ljava/lang/String;Ljava/lang/String;Ljava/lang/String;FZZIZ)V
L67:    aastore
L68:    iconst_1
L69:    dup
L70:    dup
L71:    pop2
L72:    anewarray Uf
L75:    iconst_1
L76:    dup
L77:    pop2
L78:    dup
L79:    iconst_0
L80:    iconst_1
L81:    dup
L82:    pop2
L83:    new uD
L86:    dup
L87:    aconst_null
L88:    dup
L89:    dup_x1
L90:    iconst_1
L91:    dup
L92:    pop2
L93:    iconst_0
L94:    iconst_1
L95:    dup
L96:    pop2
L97:    iconst_0
L98:    dup_x1
L99:    iconst_1
L100:   dup
L101:   pop2
L102:   invokespecial Method uD <init> (Ljava/lang/String;Ljava/lang/String;Ljava/lang/String;IIZ)V
L105:   aastore
L106:   invokespecial Method Te <init> (Ljava/lang/String;Ljava/lang/String;Ljava/lang/String;Leb;IFI[LUf;[LUf;)V
L109:   dup
L110:   getfield Field Te char Ljava/util/LinkedList;
L113:   aload_0
L114:   invokestatic Method java/util/Arrays asList ([Ljava/lang/Object;)Ljava/util/List;
L117:   invokevirtual Method java/util/LinkedList addAll (Ljava/util/Collection;)Z
L120:   pop
L121:   areturn
L122:   
    .end code
.end method

.method private static varargs portalftw : ([LTe;)LTe;
    .code stack 24 locals 1
L0:     new Te
L3:     dup
L4:     ldc "Lying"
L6:     ldc "At the end of the challenge there will be a green piece. Dear [subject name here] try to play for two minutes."
L8:     ldc "portalftw"
L10:    new gf
L13:    dup
L14:    invokespecial Method gf <init> ()V
L17:    iconst_0
L18:    iconst_1
L19:    dup
L20:    pop2
L21:    fconst_0
L22:    ldc 2147483647
L24:    iconst_1
L25:    dup
L26:    dup
L27:    pop2
L28:    anewarray Uf
L31:    iconst_1
L32:    dup
L33:    pop2
L34:    dup
L35:    iconst_0
L36:    iconst_1
L37:    dup
L38:    pop2
L39:    new mg
L42:    dup
L43:    aconst_null
L44:    dup
L45:    dup_x1
L46:    ldc 1.2e2f
L48:    iconst_1
L49:    dup
L50:    pop2
L51:    iconst_0
L52:    iconst_1
L53:    dup
L54:    pop2
L55:    iconst_0
L56:    iconst_1
L57:    dup_x2
L58:    dup
L59:    pop2
L60:    iconst_0
L61:    iconst_1
L62:    dup
L63:    pop2
L64:    invokespecial Method mg <init> (Ljava/lang/String;Ljava/lang/String;Ljava/lang/String;FZZIZ)V
L67:    aastore
L68:    iconst_0
L69:    iconst_1
L70:    dup
L71:    pop2
L72:    anewarray Uf
L75:    iconst_1
L76:    dup
L77:    pop2
L78:    invokespecial Method Te <init> (Ljava/lang/String;Ljava/lang/String;Ljava/lang/String;Leb;IFI[LUf;[LUf;)V
L81:    dup
L82:    getfield Field Te char Ljava/util/LinkedList;
L85:    aload_0
L86:    invokestatic Method java/util/Arrays asList ([Ljava/lang/Object;)Ljava/util/List;
L89:    invokevirtual Method java/util/LinkedList addAll (Ljava/util/Collection;)Z
L92:    pop
L93:    areturn
L94:    
    .end code
.end method

.method private static varargs maserati : ([LTe;)LTe;
    .code stack 25 locals 1
L0:     new Te
L3:     dup
L4:     ldc "Maserati"
L6:     ldc "Clear 40 lines."
L8:     ldc "maserati"
L10:    new bG
L13:    dup
L14:    invokespecial Method bG <init> ()V
L17:    iconst_0
L18:    iconst_1
L19:    dup
L20:    pop2
L21:    fconst_1
L22:    ldc 2147483647
L24:    iconst_1
L25:    dup
L26:    dup
L27:    pop2
L28:    anewarray Uf
L31:    iconst_1
L32:    dup
L33:    pop2
L34:    dup
L35:    iconst_0
L36:    iconst_1
L37:    dup
L38:    pop2
L39:    new YE
L42:    dup
L43:    aconst_null
L44:    dup
L45:    dup_x1
L46:    bipush 40
L48:    iconst_1
L49:    dup
L50:    pop2
L51:    iconst_0
L52:    iconst_1
L53:    dup
L54:    pop2
L55:    iconst_0
L56:    iconst_1
L57:    dup
L58:    pop2
L59:    invokespecial Method YE <init> (Ljava/lang/String;Ljava/lang/String;Ljava/lang/String;IIZ)V
L62:    aastore
L63:    iconst_1
L64:    dup
L65:    dup
L66:    pop2
L67:    anewarray Uf
L70:    iconst_1
L71:    dup
L72:    pop2
L73:    dup
L74:    iconst_0
L75:    iconst_1
L76:    dup
L77:    pop2
L78:    new mg
L81:    dup
L82:    aconst_null
L83:    dup
L84:    dup_x1
L85:    ldc 6e1f
L87:    iconst_1
L88:    dup
L89:    pop2
L90:    iconst_1
L91:    dup
L92:    pop2
L93:    iconst_0
L94:    iconst_1
L95:    dup
L96:    pop2
L97:    iconst_0
L98:    dup_x1
L99:    dup_x2
L100:   iconst_1
L101:   dup
L102:   pop2
L103:   invokespecial Method mg <init> (Ljava/lang/String;Ljava/lang/String;Ljava/lang/String;FZZIZ)V
L106:   aastore
L107:   invokespecial Method Te <init> (Ljava/lang/String;Ljava/lang/String;Ljava/lang/String;Leb;IFI[LUf;[LUf;)V
L110:   dup
L111:   getfield Field Te char Ljava/util/LinkedList;
L114:   aload_0
L115:   invokestatic Method java/util/Arrays asList ([Ljava/lang/Object;)Ljava/util/List;
L118:   invokevirtual Method java/util/LinkedList addAll (Ljava/util/Collection;)Z
L121:   pop
L122:   areturn
L123:   
    .end code
.end method

.method public static <clinit> : ()V
    .code stack 25 locals 0
L0:     new java/util/LinkedHashMap
L3:     dup
L4:     invokespecial Method java/util/LinkedHashMap <init> ()V
L7:     putstatic Field SE do Ljava/util/Map;
L10:    new java/util/LinkedHashMap
L13:    dup
L14:    invokespecial Method java/util/LinkedHashMap <init> ()V
L17:    putstatic Field SE else Ljava/util/Map;
L20:    iconst_1
L21:    dup
L22:    dup
L23:    pop2
L24:    anewarray Te
L27:    iconst_1
L28:    dup
L29:    pop2
L30:    dup
L31:    iconst_0
L32:    iconst_1
L33:    dup
L34:    pop2
L35:    iconst_2
L36:    iconst_1
L37:    dup
L38:    pop2
L39:    anewarray Te
L42:    iconst_1
L43:    dup
L44:    pop2
L45:    dup
L46:    iconst_0
L47:    iconst_1
L48:    dup
L49:    pop2
L50:    iconst_2
L51:    iconst_1
L52:    dup
L53:    pop2
L54:    anewarray Te
L57:    iconst_1
L58:    dup
L59:    pop2
L60:    dup
L61:    iconst_0
L62:    iconst_1
L63:    dup
L64:    pop2
L65:    iconst_2
L66:    iconst_1
L67:    dup
L68:    pop2
L69:    anewarray Te
L72:    iconst_1
L73:    dup
L74:    pop2
L75:    dup
L76:    iconst_0
L77:    iconst_1
L78:    dup
L79:    pop2
L80:    iconst_2
L81:    iconst_1
L82:    dup
L83:    pop2
L84:    anewarray Te
L87:    iconst_1
L88:    dup
L89:    pop2
L90:    dup
L91:    iconst_0
L92:    iconst_1
L93:    dup
L94:    pop2
L95:    iconst_0
L96:    iconst_1
L97:    dup
L98:    pop2
L99:    anewarray Te
L102:   iconst_1
L103:   dup
L104:   pop2
L105:   invokestatic Method SE pocall2 ([LTe;)LTe;
L108:   aastore
L109:   dup
L110:   iconst_1
L111:   dup
L112:   pop2
L113:   iconst_0
L114:   iconst_1
L115:   dup_x1
L116:   dup
L117:   pop2
L118:   anewarray Te
L121:   iconst_1
L122:   dup
L123:   pop2
L124:   invokestatic Method SE winterbottom ([LTe;)LTe;
L127:   aastore
L128:   invokestatic Method SE booring ([LTe;)LTe;
L131:   aastore
L132:   dup
L133:   iconst_1
L134:   dup
L135:   pop2
L136:   iconst_2
L137:   iconst_1
L138:   dup_x1
L139:   dup
L140:   pop2
L141:   anewarray Te
L144:   iconst_1
L145:   dup
L146:   pop2
L147:   dup
L148:   iconst_0
L149:   iconst_1
L150:   dup
L151:   pop2
L152:   iconst_0
L153:   iconst_1
L154:   dup
L155:   pop2
L156:   anewarray Te
L159:   iconst_1
L160:   dup
L161:   pop2
L162:   invokestatic Method SE abc ([LTe;)LTe;
L165:   aastore
L166:   dup
L167:   iconst_1
L168:   dup
L169:   pop2
L170:   iconst_0
L171:   iconst_1
L172:   dup_x1
L173:   dup
L174:   pop2
L175:   anewarray Te
L178:   iconst_1
L179:   dup
L180:   pop2
L181:   invokestatic Method SE e123 ([LTe;)LTe;
L184:   aastore
L185:   invokestatic Method SE easyaspie ([LTe;)LTe;
L188:   aastore
L189:   invokestatic Method SE quickstart ([LTe;)LTe;
L192:   aastore
L193:   dup
L194:   iconst_1
L195:   dup
L196:   pop2
L197:   iconst_2
L198:   iconst_1
L199:   dup_x1
L200:   dup
L201:   pop2
L202:   anewarray Te
L205:   iconst_1
L206:   dup
L207:   pop2
L208:   dup
L209:   iconst_0
L210:   iconst_1
L211:   dup
L212:   pop2
L213:   iconst_2
L214:   iconst_1
L215:   dup
L216:   pop2
L217:   anewarray Te
L220:   iconst_1
L221:   dup
L222:   pop2
L223:   dup
L224:   iconst_0
L225:   iconst_1
L226:   dup
L227:   pop2
L228:   iconst_0
L229:   iconst_1
L230:   dup
L231:   pop2
L232:   anewarray Te
L235:   iconst_1
L236:   dup
L237:   pop2
L238:   invokestatic Method SE garbageman ([LTe;)LTe;
L241:   aastore
L242:   dup
L243:   iconst_1
L244:   dup
L245:   pop2
L246:   iconst_0
L247:   iconst_1
L248:   dup_x1
L249:   dup
L250:   pop2
L251:   anewarray Te
L254:   iconst_1
L255:   dup
L256:   pop2
L257:   invokestatic Method SE veyron ([LTe;)LTe;
L260:   aastore
L261:   invokestatic Method SE speed ([LTe;)LTe;
L264:   aastore
L265:   dup
L266:   iconst_1
L267:   dup
L268:   pop2
L269:   iconst_2
L270:   iconst_1
L271:   dup_x1
L272:   dup
L273:   pop2
L274:   anewarray Te
L277:   iconst_1
L278:   dup
L279:   pop2
L280:   dup
L281:   iconst_0
L282:   iconst_1
L283:   dup
L284:   pop2
L285:   iconst_0
L286:   iconst_1
L287:   dup
L288:   pop2
L289:   anewarray Te
L292:   iconst_1
L293:   dup
L294:   pop2
L295:   invokestatic Method SE shep ([LTe;)LTe;
L298:   aastore
L299:   dup
L300:   iconst_1
L301:   dup
L302:   pop2
L303:   iconst_0
L304:   iconst_1
L305:   dup_x1
L306:   dup
L307:   pop2
L308:   anewarray Te
L311:   iconst_1
L312:   dup
L313:   pop2
L314:   invokestatic Method SE brrr ([LTe;)LTe;
L317:   aastore
L318:   invokestatic Method SE cleveland ([LTe;)LTe;
L321:   aastore
L322:   invokestatic Method SE mampf ([LTe;)LTe;
L325:   aastore
L326:   invokestatic Method SE tgm ([LTe;)LTe;
L329:   aastore
L330:   dup
L331:   iconst_1
L332:   dup
L333:   pop2
L334:   iconst_2
L335:   iconst_1
L336:   dup_x1
L337:   dup
L338:   pop2
L339:   anewarray Te
L342:   iconst_1
L343:   dup
L344:   pop2
L345:   dup
L346:   iconst_0
L347:   iconst_1
L348:   dup
L349:   pop2
L350:   iconst_2
L351:   iconst_1
L352:   dup
L353:   pop2
L354:   anewarray Te
L357:   iconst_1
L358:   dup
L359:   pop2
L360:   dup
L361:   iconst_0
L362:   iconst_1
L363:   dup
L364:   pop2
L365:   iconst_2
L366:   iconst_1
L367:   dup
L368:   pop2
L369:   anewarray Te
L372:   iconst_1
L373:   dup
L374:   pop2
L375:   dup
L376:   iconst_0
L377:   iconst_1
L378:   dup
L379:   pop2
L380:   iconst_0
L381:   iconst_1
L382:   dup
L383:   pop2
L384:   anewarray Te
L387:   iconst_1
L388:   dup
L389:   pop2
L390:   invokestatic Method SE fast ([LTe;)LTe;
L393:   aastore
L394:   dup
L395:   iconst_1
L396:   dup
L397:   pop2
L398:   iconst_0
L399:   iconst_1
L400:   dup_x1
L401:   dup
L402:   pop2
L403:   anewarray Te
L406:   iconst_1
L407:   dup
L408:   pop2
L409:   invokestatic Method SE unbreakable ([LTe;)LTe;
L412:   aastore
L413:   invokestatic Method SE omnomnom ([LTe;)LTe;
L416:   aastore
L417:   dup
L418:   iconst_1
L419:   dup
L420:   pop2
L421:   iconst_2
L422:   iconst_1
L423:   dup_x1
L424:   dup
L425:   pop2
L426:   anewarray Te
L429:   iconst_1
L430:   dup
L431:   pop2
L432:   dup
L433:   iconst_0
L434:   iconst_1
L435:   dup
L436:   pop2
L437:   iconst_0
L438:   iconst_1
L439:   dup
L440:   pop2
L441:   anewarray Te
L444:   iconst_1
L445:   dup
L446:   pop2
L447:   invokestatic Method SE wtf ([LTe;)LTe;
L450:   aastore
L451:   dup
L452:   iconst_1
L453:   dup
L454:   pop2
L455:   iconst_0
L456:   iconst_1
L457:   dup_x1
L458:   dup
L459:   pop2
L460:   anewarray Te
L463:   iconst_1
L464:   dup
L465:   pop2
L466:   invokestatic Method SE ruggu ([LTe;)LTe;
L469:   aastore
L470:   invokestatic Method SE angularmomentum ([LTe;)LTe;
L473:   aastore
L474:   invokestatic Method SE melee ([LTe;)LTe;
L477:   aastore
L478:   dup
L479:   iconst_1
L480:   dup
L481:   pop2
L482:   iconst_2
L483:   iconst_1
L484:   dup_x1
L485:   dup
L486:   pop2
L487:   anewarray Te
L490:   iconst_1
L491:   dup
L492:   pop2
L493:   dup
L494:   iconst_0
L495:   iconst_1
L496:   dup
L497:   pop2
L498:   iconst_2
L499:   iconst_1
L500:   dup
L501:   pop2
L502:   anewarray Te
L505:   iconst_1
L506:   dup
L507:   pop2
L508:   dup
L509:   iconst_0
L510:   iconst_1
L511:   dup
L512:   pop2
L513:   iconst_0
L514:   iconst_1
L515:   dup
L516:   pop2
L517:   anewarray Te
L520:   iconst_1
L521:   dup
L522:   pop2
L523:   invokestatic Method SE appezoell1 ([LTe;)LTe;
L526:   aastore
L527:   dup
L528:   iconst_1
L529:   dup
L530:   pop2
L531:   iconst_0
L532:   iconst_1
L533:   dup_x1
L534:   dup
L535:   pop2
L536:   anewarray Te
L539:   iconst_1
L540:   dup
L541:   pop2
L542:   invokestatic Method SE kajitani ([LTe;)LTe;
L545:   aastore
L546:   invokestatic Method SE portalftw ([LTe;)LTe;
L549:   aastore
L550:   dup
L551:   iconst_1
L552:   dup
L553:   pop2
L554:   iconst_2
L555:   iconst_1
L556:   dup_x1
L557:   dup
L558:   pop2
L559:   anewarray Te
L562:   iconst_1
L563:   dup
L564:   pop2
L565:   dup
L566:   iconst_0
L567:   iconst_1
L568:   dup
L569:   pop2
L570:   iconst_0
L571:   iconst_1
L572:   dup
L573:   pop2
L574:   anewarray Te
L577:   iconst_1
L578:   dup
L579:   pop2
L580:   invokestatic Method SE twscombos ([LTe;)LTe;
L583:   aastore
L584:   dup
L585:   iconst_1
L586:   dup
L587:   pop2
L588:   iconst_0
L589:   iconst_1
L590:   dup_x1
L591:   dup
L592:   pop2
L593:   anewarray Te
L596:   iconst_1
L597:   dup
L598:   pop2
L599:   invokestatic Method SE elvis ([LTe;)LTe;
L602:   aastore
L603:   invokestatic Method SE travoltafever ([LTe;)LTe;
L606:   aastore
L607:   invokestatic Method SE emptyhouse ([LTe;)LTe;
L610:   aastore
L611:   invokestatic Method SE maserati ([LTe;)LTe;
L614:   aastore
L615:   invokestatic Method SE grandefinale ([LTe;)LTe;
L618:   aastore
L619:   invokestatic Method SE uberleet ([LTe;)LTe;
L622:   putstatic Field SE "enum" LTe;
L625:   getstatic Field SE "enum" LTe;
L628:   invokestatic Method SE else (LTe;)V
L631:   new Te
L634:   dup
L635:   ldc "Maserati"
L637:   ldc "Clear 40 lines."
L639:   ldc_w "ol-maserati"
L642:   new lf
L645:   dup
L646:   invokespecial Method lf <init> ()V
L649:   iconst_0
L650:   iconst_1
L651:   dup
L652:   pop2
L653:   fconst_1
L654:   ldc 2147483647
L656:   iconst_1
L657:   dup
L658:   dup
L659:   pop2
L660:   anewarray Uf
L663:   iconst_1
L664:   dup
L665:   pop2
L666:   dup
L667:   iconst_0
L668:   iconst_1
L669:   dup
L670:   pop2
L671:   new YE
L674:   dup
L675:   aconst_null
L676:   dup
L677:   dup_x1
L678:   bipush 40
L680:   iconst_1
L681:   dup
L682:   pop2
L683:   iconst_0
L684:   iconst_1
L685:   dup
L686:   pop2
L687:   iconst_0
L688:   iconst_1
L689:   dup
L690:   pop2
L691:   invokespecial Method YE <init> (Ljava/lang/String;Ljava/lang/String;Ljava/lang/String;IIZ)V
L694:   aastore
L695:   iconst_1
L696:   dup
L697:   dup
L698:   pop2
L699:   anewarray Uf
L702:   iconst_1
L703:   dup
L704:   pop2
L705:   dup
L706:   iconst_0
L707:   iconst_1
L708:   dup
L709:   pop2
L710:   new df
L713:   dup
L714:   invokespecial Method df <init> ()V
L717:   aastore
L718:   getstatic Field fE new LfE;
L721:   getstatic Field fE char LfE;
L724:   iconst_1
L725:   dup
L726:   dup
L727:   pop2
L728:   invokespecial Method Te <init> (Ljava/lang/String;Ljava/lang/String;Ljava/lang/String;Leb;IFI[LUf;[LUf;LfE;LfE;Z)V
L731:   invokestatic Method SE break (LTe;)V
L734:   new Te
L737:   dup
L738:   ldc_w "Survivor"
L741:   ldc_w "Play as long as you can."
L744:   ldc_w "ol-survivor"
L747:   new Yf
L750:   dup
L751:   invokespecial Method Yf <init> ()V
L754:   iconst_0
L755:   iconst_1
L756:   dup
L757:   pop2
L758:   fconst_1
L759:   ldc 2147483647
L761:   iconst_1
L762:   dup
L763:   dup
L764:   pop2
L765:   anewarray Uf
L768:   iconst_1
L769:   dup
L770:   pop2
L771:   dup
L772:   iconst_0
L773:   iconst_1
L774:   dup
L775:   pop2
L776:   new uD
L779:   dup
L780:   aconst_null
L781:   dup
L782:   dup_x1
L783:   iconst_1
L784:   dup
L785:   pop2
L786:   iconst_0
L787:   iconst_1
L788:   dup
L789:   pop2
L790:   iconst_0
L791:   dup_x1
L792:   iconst_1
L793:   dup
L794:   pop2
L795:   invokespecial Method uD <init> (Ljava/lang/String;Ljava/lang/String;Ljava/lang/String;IIZ)V
L798:   aastore
L799:   iconst_1
L800:   dup
L801:   dup
L802:   pop2
L803:   anewarray Uf
L806:   iconst_1
L807:   dup
L808:   pop2
L809:   dup
L810:   iconst_0
L811:   iconst_1
L812:   dup
L813:   pop2
L814:   new df
L817:   dup
L818:   invokespecial Method df <init> ()V
L821:   aastore
L822:   getstatic Field fE "enum" LfE;
L825:   getstatic Field fE void LfE;
L828:   iconst_1
L829:   dup
L830:   dup
L831:   pop2
L832:   invokespecial Method Te <init> (Ljava/lang/String;Ljava/lang/String;Ljava/lang/String;Leb;IFI[LUf;[LUf;LfE;LfE;Z)V
L835:   invokestatic Method SE break (LTe;)V
L838:   new Te
L841:   dup
L842:   ldc_w "Swiss cheese"
L845:   ldc_w "Complete a swiss cheese challenge."
L848:   ldc_w "ol-cheese"
L851:   new sg
L854:   dup
L855:   invokespecial Method sg <init> ()V
L858:   iconst_0
L859:   iconst_1
L860:   dup
L861:   pop2
L862:   fconst_1
L863:   ldc 2147483647
L865:   iconst_1
L866:   dup
L867:   dup
L868:   pop2
L869:   anewarray Uf
L872:   iconst_1
L873:   dup
L874:   pop2
L875:   dup
L876:   iconst_0
L877:   iconst_1
L878:   dup
L879:   pop2
L880:   new uD
L883:   dup
L884:   aconst_null
L885:   dup
L886:   dup_x1
L887:   iconst_1
L888:   dup
L889:   pop2
L890:   iconst_0
L891:   iconst_1
L892:   dup
L893:   pop2
L894:   iconst_0
L895:   dup_x1
L896:   iconst_1
L897:   dup
L898:   pop2
L899:   invokespecial Method uD <init> (Ljava/lang/String;Ljava/lang/String;Ljava/lang/String;IIZ)V
L902:   aastore
L903:   iconst_1
L904:   dup
L905:   dup
L906:   pop2
L907:   anewarray Uf
L910:   iconst_1
L911:   dup
L912:   pop2
L913:   dup
L914:   iconst_0
L915:   iconst_1
L916:   dup
L917:   pop2
L918:   new df
L921:   dup
L922:   invokespecial Method df <init> ()V
L925:   aastore
L926:   getstatic Field fE new LfE;
L929:   getstatic Field fE char LfE;
L932:   iconst_1
L933:   dup
L934:   dup
L935:   pop2
L936:   invokespecial Method Te <init> (Ljava/lang/String;Ljava/lang/String;Ljava/lang/String;Leb;IFI[LUf;[LUf;LfE;LfE;Z)V
L939:   invokestatic Method SE break (LTe;)V
L942:   new Te
L945:   dup
L946:   ldc_w "49.6 \u03BCFortnight"
L949:   ldc_w "Send as many lines as you can in a minute."
L952:   ldc_w "ol-send"
L955:   new Sg
L958:   dup
L959:   invokespecial Method Sg <init> ()V
L962:   iconst_0
L963:   iconst_1
L964:   dup
L965:   pop2
L966:   fconst_1
L967:   ldc 2147483647
L969:   iconst_1
L970:   dup
L971:   dup
L972:   pop2
L973:   anewarray Uf
L976:   iconst_1
L977:   dup
L978:   pop2
L979:   dup
L980:   iconst_0
L981:   iconst_1
L982:   dup
L983:   pop2
L984:   new mg
L987:   dup
L988:   aconst_null
L989:   dup
L990:   dup_x1
L991:   ldc 6e1f
L993:   iconst_1
L994:   dup
L995:   pop2
L996:   iconst_1
L997:   dup
L998:   pop2
L999:   iconst_0
L1000:  iconst_1
L1001:  dup
L1002:  pop2
L1003:  iconst_0
L1004:  dup_x1
L1005:  dup_x2
L1006:  iconst_1
L1007:  dup
L1008:  pop2
L1009:  invokespecial Method mg <init> (Ljava/lang/String;Ljava/lang/String;Ljava/lang/String;FZZIZ)V
L1012:  aastore
L1013:  iconst_1
L1014:  dup
L1015:  dup
L1016:  pop2
L1017:  anewarray Uf
L1020:  iconst_1
L1021:  dup
L1022:  pop2
L1023:  dup
L1024:  iconst_0
L1025:  iconst_1
L1026:  dup
L1027:  pop2
L1028:  new YD
L1031:  dup
L1032:  invokespecial Method YD <init> ()V
L1035:  aastore
L1036:  getstatic Field fE do LfE;
L1039:  getstatic Field fE void LfE;
L1042:  iconst_1
L1043:  dup
L1044:  dup
L1045:  pop2
L1046:  invokespecial Method Te <init> (Ljava/lang/String;Ljava/lang/String;Ljava/lang/String;Leb;IFI[LUf;[LUf;LfE;LfE;Z)V
L1049:  invokestatic Method SE break (LTe;)V
L1052:  new Te
L1055:  dup
L1056:  ldc_w "Ten"
L1059:  ldc_w "Do a level 10 combo."
L1062:  ldc_w "ol-ten"
L1065:  new KG
L1068:  dup
L1069:  invokespecial Method KG <init> ()V
L1072:  iconst_0
L1073:  iconst_1
L1074:  dup
L1075:  pop2
L1076:  fconst_1
L1077:  ldc 2147483647
L1079:  iconst_1
L1080:  dup
L1081:  dup
L1082:  pop2
L1083:  anewarray Uf
L1086:  iconst_1
L1087:  dup
L1088:  pop2
L1089:  dup
L1090:  iconst_0
L1091:  iconst_1
L1092:  dup
L1093:  pop2
L1094:  new jF
L1097:  dup
L1098:  aconst_null
L1099:  dup
L1100:  dup_x1
L1101:  bipush 10
L1103:  iconst_1
L1104:  dup
L1105:  pop2
L1106:  iconst_1
L1107:  dup
L1108:  pop2
L1109:  iconst_0
L1110:  iconst_1
L1111:  dup
L1112:  pop2
L1113:  iconst_0
L1114:  iconst_1
L1115:  dup_x2
L1116:  dup
L1117:  pop2
L1118:  invokespecial Method jF <init> (Ljava/lang/String;Ljava/lang/String;Ljava/lang/String;IIIZ)V
L1121:  aastore
L1122:  iconst_1
L1123:  dup
L1124:  dup
L1125:  pop2
L1126:  anewarray Uf
L1129:  iconst_1
L1130:  dup
L1131:  pop2
L1132:  dup
L1133:  iconst_0
L1134:  iconst_1
L1135:  dup
L1136:  pop2
L1137:  new df
L1140:  dup
L1141:  invokespecial Method df <init> ()V
L1144:  aastore
L1145:  getstatic Field fE new LfE;
L1148:  getstatic Field fE this LfE;
L1151:  iconst_1
L1152:  dup
L1153:  dup
L1154:  pop2
L1155:  invokespecial Method Te <init> (Ljava/lang/String;Ljava/lang/String;Ljava/lang/String;Leb;IFI[LUf;[LUf;LfE;LfE;Z)V
L1158:  invokestatic Method SE break (LTe;)V
L1161:  new ef
L1164:  dup
L1165:  ldc_w "James Clewett's"
L1168:  ldc_w "Clear as many Tetrises as possible."
L1171:  ldc_w "ol-clewett"
L1174:  new tE
L1177:  dup
L1178:  invokespecial Method tE <init> ()V
L1181:  iconst_0
L1182:  iconst_1
L1183:  dup
L1184:  pop2
L1185:  fconst_1
L1186:  ldc 2147483647
L1188:  iconst_4
L1189:  iconst_1
L1190:  dup
L1191:  pop2
L1192:  anewarray Uf
L1195:  iconst_1
L1196:  dup
L1197:  pop2
L1198:  dup
L1199:  iconst_0
L1200:  iconst_1
L1201:  dup
L1202:  pop2
L1203:  new uD
L1206:  dup
L1207:  aconst_null
L1208:  dup
L1209:  dup_x1
L1210:  iconst_1
L1211:  dup
L1212:  pop2
L1213:  iconst_0
L1214:  iconst_1
L1215:  dup
L1216:  pop2
L1217:  iconst_0
L1218:  dup_x1
L1219:  iconst_1
L1220:  dup
L1221:  pop2
L1222:  invokespecial Method uD <init> (Ljava/lang/String;Ljava/lang/String;Ljava/lang/String;IIZ)V
L1225:  aastore
L1226:  dup
L1227:  iconst_1
L1228:  dup
L1229:  dup
L1230:  pop2
L1231:  new YF
L1234:  dup
L1235:  aconst_null
L1236:  dup
L1237:  dup_x1
L1238:  iconst_1
L1239:  dup
L1240:  pop2
L1241:  iconst_1
L1242:  dup
L1243:  pop2
L1244:  iconst_0
L1245:  iconst_1
L1246:  dup_x1
L1247:  dup_x2
L1248:  dup
L1249:  pop2
L1250:  iconst_0
L1251:  iconst_1
L1252:  dup
L1253:  pop2
L1254:  iconst_0
L1255:  iconst_1
L1256:  dup
L1257:  pop2
L1258:  invokespecial Method YF <init> (Ljava/lang/String;Ljava/lang/String;Ljava/lang/String;IIIZZ)V
L1261:  aastore
L1262:  dup
L1263:  iconst_2
L1264:  iconst_1
L1265:  dup
L1266:  pop2
L1267:  new YF
L1270:  dup
L1271:  aconst_null
L1272:  dup
L1273:  dup_x1
L1274:  iconst_2
L1275:  iconst_1
L1276:  dup
L1277:  pop2
L1278:  iconst_1
L1279:  dup
L1280:  pop2
L1281:  iconst_0
L1282:  iconst_1
L1283:  dup
L1284:  pop2
L1285:  iconst_0
L1286:  iconst_1
L1287:  dup_x2
L1288:  dup
L1289:  pop2
L1290:  iconst_0
L1291:  iconst_1
L1292:  dup
L1293:  pop2
L1294:  invokespecial Method YF <init> (Ljava/lang/String;Ljava/lang/String;Ljava/lang/String;IIIZZ)V
L1297:  aastore
L1298:  dup
L1299:  iconst_3
L1300:  iconst_1
L1301:  dup
L1302:  pop2
L1303:  new YF
L1306:  dup
L1307:  aconst_null
L1308:  dup
L1309:  dup_x1
L1310:  iconst_3
L1311:  iconst_1
L1312:  dup
L1313:  pop2
L1314:  iconst_1
L1315:  dup
L1316:  pop2
L1317:  iconst_0
L1318:  iconst_1
L1319:  dup
L1320:  pop2
L1321:  iconst_0
L1322:  iconst_1
L1323:  dup_x2
L1324:  dup
L1325:  pop2
L1326:  iconst_0
L1327:  iconst_1
L1328:  dup
L1329:  pop2
L1330:  invokespecial Method YF <init> (Ljava/lang/String;Ljava/lang/String;Ljava/lang/String;IIIZZ)V
L1333:  aastore
L1334:  iconst_1
L1335:  dup
L1336:  dup
L1337:  pop2
L1338:  anewarray Uf
L1341:  iconst_1
L1342:  dup
L1343:  pop2
L1344:  dup
L1345:  iconst_0
L1346:  iconst_1
L1347:  dup
L1348:  pop2
L1349:  new YF
L1352:  dup
L1353:  aconst_null
L1354:  dup
L1355:  dup_x1
L1356:  iconst_4
L1357:  iconst_1
L1358:  dup
L1359:  pop2
L1360:  iconst_1
L1361:  dup
L1362:  pop2
L1363:  iconst_0
L1364:  iconst_1
L1365:  dup
L1366:  pop2
L1367:  iconst_0
L1368:  dup_x1
L1369:  iconst_1
L1370:  dup
L1371:  pop2
L1372:  iconst_1
L1373:  dup
L1374:  dup
L1375:  pop2
L1376:  invokespecial Method YF <init> (Ljava/lang/String;Ljava/lang/String;Ljava/lang/String;IIIZZ)V
L1379:  aastore
L1380:  getstatic Field fE try LfE;
L1383:  getstatic Field fE new LfE;
L1386:  iconst_0
L1387:  iconst_1
L1388:  dup
L1389:  pop2
L1390:  invokespecial Method ef <init> (Ljava/lang/String;Ljava/lang/String;Ljava/lang/String;Leb;IFI[LUf;[LUf;LfE;LfE;Z)V
L1393:  invokestatic Method SE break (LTe;)V
L1396:  new Te
L1399:  dup
L1400:  ldc_w "Quickstart"
L1403:  ldc_w "Beat your opponent as fast as you can."
L1406:  ldc_w "ol-qs"
L1409:  new jg
L1412:  dup
L1413:  invokespecial Method jg <init> ()V
L1416:  iconst_1
L1417:  dup
L1418:  pop2
L1419:  ldc_w 8e-1f
L1422:  ldc 2147483647
L1424:  iconst_1
L1425:  dup_x2
L1426:  iconst_1
L1427:  dup
L1428:  pop2
L1429:  anewarray Uf
L1432:  iconst_1
L1433:  dup
L1434:  pop2
L1435:  dup
L1436:  iconst_0
L1437:  iconst_1
L1438:  dup
L1439:  pop2
L1440:  new uD
L1443:  dup
L1444:  aconst_null
L1445:  dup
L1446:  dup_x1
L1447:  iconst_1
L1448:  dup
L1449:  pop2
L1450:  iconst_0
L1451:  iconst_1
L1452:  dup
L1453:  pop2
L1454:  iconst_0
L1455:  dup_x1
L1456:  iconst_1
L1457:  dup
L1458:  pop2
L1459:  invokespecial Method uD <init> (Ljava/lang/String;Ljava/lang/String;Ljava/lang/String;IIZ)V
L1462:  aastore
L1463:  iconst_1
L1464:  dup
L1465:  dup
L1466:  pop2
L1467:  anewarray Uf
L1470:  iconst_1
L1471:  dup
L1472:  pop2
L1473:  dup
L1474:  iconst_0
L1475:  iconst_1
L1476:  dup
L1477:  pop2
L1478:  new df
L1481:  dup
L1482:  invokespecial Method df <init> ()V
L1485:  aastore
L1486:  getstatic Field fE new LfE;
L1489:  getstatic Field fE void LfE;
L1492:  iconst_1
L1493:  dup
L1494:  dup
L1495:  pop2
L1496:  invokespecial Method Te <init> (Ljava/lang/String;Ljava/lang/String;Ljava/lang/String;Leb;IFI[LUf;[LUf;LfE;LfE;Z)V
L1499:  invokestatic Method SE break (LTe;)V
L1502:  new Te
L1505:  dup
L1506:  ldc "Shi Tai Ye"
L1508:  ldc_w "Clear as many lines as you can."
L1511:  ldc_w "ol-tgm"
L1514:  new qg
L1517:  dup
L1518:  invokespecial Method qg <init> ()V
L1521:  iconst_0
L1522:  iconst_1
L1523:  dup
L1524:  pop2
L1525:  fconst_1
L1526:  ldc 2147483647
L1528:  iconst_1
L1529:  dup
L1530:  dup
L1531:  pop2
L1532:  anewarray Uf
L1535:  iconst_1
L1536:  dup
L1537:  pop2
L1538:  dup
L1539:  iconst_0
L1540:  iconst_1
L1541:  dup
L1542:  pop2
L1543:  new uD
L1546:  dup
L1547:  aconst_null
L1548:  dup
L1549:  dup_x1
L1550:  iconst_1
L1551:  dup
L1552:  pop2
L1553:  iconst_0
L1554:  iconst_1
L1555:  dup
L1556:  pop2
L1557:  iconst_0
L1558:  dup_x1
L1559:  iconst_1
L1560:  dup
L1561:  pop2
L1562:  invokespecial Method uD <init> [_85]
L1565:  aastore
L1566:  iconst_2
L1567:  iconst_1
L1568:  dup
L1569:  pop2
L1570:  anewarray Uf
L1573:  iconst_1
L1574:  dup
L1575:  pop2
L1576:  dup
L1577:  iconst_0
L1578:  iconst_1
L1579:  dup
L1580:  pop2
L1581:  new YE
L1584:  dup
L1585:  aconst_null
L1586:  dup
L1587:  dup_x1
L1588:  iconst_1
L1589:  dup
L1590:  pop2
L1591:  iconst_0
L1592:  iconst_1
L1593:  dup
L1594:  pop2
L1595:  iconst_0
L1596:  dup_x1
L1597:  iconst_1
L1598:  dup
L1599:  pop2
L1600:  invokespecial Method YE <init> [_85]
L1603:  aastore
L1604:  dup
L1605:  iconst_1
L1606:  dup
L1607:  dup
L1608:  pop2
L1609:  new Le
L1612:  dup
L1613:  invokespecial Method Le <init> ()V
L1616:  aastore
L1617:  getstatic Field fE else LfE;
L1620:  getstatic Field fE new LfE;
L1623:  iconst_1
L1624:  dup
L1625:  dup
L1626:  pop2
L1627:  invokespecial Method Te <init> (Ljava/lang/String;Ljava/lang/String;Ljava/lang/String;Leb;IFI[LUf;[LUf;LfE;LfE;Z)V
L1630:  invokestatic Method SE break (LTe;)V
L1633:  return
L1634:  
    .end code
.end method

.method private static varargs elvis : ([LTe;)LTe;
    .code stack 23 locals 1
L0:     new Te
L3:     dup
L4:     ldc_w "Return to sender"
L7:     ldc_w "Send 30 lines to your opponents."
L10:    ldc_w "elvis"
L13:    new jf
L16:    dup
L17:    invokespecial Method jf <init> ()V
L20:    iconst_2
L21:    iconst_1
L22:    dup
L23:    pop2
L24:    fconst_1
L25:    ldc 2147483647
L27:    iconst_1
L28:    dup
L29:    dup
L30:    pop2
L31:    anewarray Uf
L34:    iconst_1
L35:    dup
L36:    pop2
L37:    dup
L38:    iconst_0
L39:    iconst_1
L40:    dup
L41:    pop2
L42:    new yD
L45:    dup
L46:    aconst_null
L47:    dup
L48:    dup_x1
L49:    bipush 30
L51:    iconst_1
L52:    dup
L53:    pop2
L54:    iconst_1
L55:    dup
L56:    pop2
L57:    iconst_0
L58:    iconst_1
L59:    dup
L60:    pop2
L61:    iconst_0
L62:    dup_x1
L63:    iconst_1
L64:    dup
L65:    pop2
L66:    invokespecial Method yD <init> (Ljava/lang/String;Ljava/lang/String;Ljava/lang/String;IZIZ)V
L69:    aastore
L70:    iconst_0
L71:    iconst_1
L72:    dup
L73:    pop2
L74:    anewarray Uf
L77:    iconst_1
L78:    dup
L79:    pop2
L80:    invokespecial Method Te <init> (Ljava/lang/String;Ljava/lang/String;Ljava/lang/String;Leb;IFI[LUf;[LUf;)V
L83:    dup
L84:    getfield Field Te char Ljava/util/LinkedList;
L87:    aload_0
L88:    invokestatic Method java/util/Arrays asList ([Ljava/lang/Object;)Ljava/util/List;
L91:    invokevirtual Method java/util/LinkedList addAll (Ljava/util/Collection;)Z
L94:    pop
L95:    areturn
L96:    
    .end code
.end method

.method private static varargs uberleet : ([LTe;)LTe;
    .code stack 23 locals 2
L0:     new Te
L3:     dup
L4:     ldc_w "Uber l33t"
L7:     ldc_w "Send 250 lines."
L10:    ldc_w "ul"
L13:    new Qb
L16:    dup
L17:    invokespecial Method Qb <init> ()V
L20:    iconst_0
L21:    iconst_1
L22:    dup
L23:    pop2
L24:    fconst_1
L25:    ldc 2147483647
L27:    iconst_1
L28:    dup
L29:    dup
L30:    pop2
L31:    anewarray Uf
L34:    iconst_1
L35:    dup
L36:    pop2
L37:    dup
L38:    iconst_0
L39:    iconst_1
L40:    dup
L41:    pop2
L42:    new yD
L45:    dup
L46:    aconst_null
L47:    dup
L48:    dup_x1
L49:    sipush 250
L52:    iconst_1
L53:    dup
L54:    pop2
L55:    iconst_1
L56:    dup
L57:    pop2
L58:    iconst_0
L59:    iconst_1
L60:    dup
L61:    pop2
L62:    iconst_0
L63:    dup_x1
L64:    iconst_1
L65:    dup
L66:    pop2
L67:    invokespecial Method yD <init> (Ljava/lang/String;Ljava/lang/String;Ljava/lang/String;IZIZ)V
L70:    aastore
L71:    iconst_1
L72:    dup
L73:    dup
L74:    pop2
L75:    anewarray Uf
L78:    iconst_1
L79:    dup
L80:    pop2
L81:    dup
L82:    iconst_0
L83:    iconst_1
L84:    dup
L85:    pop2
L86:    new ve
L89:    dup
L90:    iconst_4
L91:    iconst_1
L92:    dup
L93:    pop2
L94:    ldc_w 6.5e0f
L97:    invokespecial Method ve <init> (IF)V
L100:   aastore
L101:   invokespecial Method Te <init> (Ljava/lang/String;Ljava/lang/String;Ljava/lang/String;Leb;IFI[LUf;[LUf;)V
L104:   dup
L105:   astore_1
L106:   dup
L107:   iconst_0
L108:   aload_1
L109:   dup_x2
L110:   iconst_1
L111:   dup
L112:   dup
L113:   pop2
L114:   putfield Field Te else Z
L117:   iconst_1
L118:   dup
L119:   pop2
L120:   putfield Field Te byte Z
L123:   getfield Field Te char Ljava/util/LinkedList;
L126:   aload_0
L127:   invokestatic Method java/util/Arrays asList ([Ljava/lang/Object;)Ljava/util/List;
L130:   invokevirtual Method java/util/LinkedList addAll (Ljava/util/Collection;)Z
L133:   pop
L134:   areturn
L135:   
    .end code
.end method

.method private static else : (LTe;)V
    .code stack 5 locals 2
L0:     getstatic Field SE else Ljava/util/Map;
L3:     aload_0
L4:     getfield Field Te const Ljava/lang/String;
L7:     invokeinterface InterfaceMethod java/util/Map containsKey (Ljava/lang/Object;)Z 2
L12:    ifeq L47
L15:    new java/lang/RuntimeException
L18:    dup
L19:    new java/lang/StringBuilder
L22:    dup
L23:    invokespecial Method java/lang/StringBuilder <init> ()V
L26:    iconst_0
L27:    ldc_w "Duplicate key "
L30:    invokevirtual Method java/lang/StringBuilder insert (ILjava/lang/String;)Ljava/lang/StringBuilder;
L33:    aload_0
L34:    getfield Field Te const Ljava/lang/String;
L37:    invokevirtual Method java/lang/StringBuilder append (Ljava/lang/String;)Ljava/lang/StringBuilder;
L40:    invokevirtual Method java/lang/StringBuilder toString ()Ljava/lang/String;
L43:    invokespecial Method java/lang/RuntimeException <init> (Ljava/lang/String;)V
L46:    athrow
L47:    getstatic Field SE do Ljava/util/Map;
L50:    aload_0
L51:    getfield Field Te const Ljava/lang/String;
L54:    aload_0
L55:    invokeinterface InterfaceMethod java/util/Map put (Ljava/lang/Object;Ljava/lang/Object;)Ljava/lang/Object; 3
L60:    ifnull L95
L63:    new java/lang/RuntimeException
L66:    dup
L67:    new java/lang/StringBuilder
L70:    dup
L71:    invokespecial Method java/lang/StringBuilder <init> ()V
L74:    iconst_0
L75:    ldc_w "Duplicate key "
L78:    invokevirtual Method java/lang/StringBuilder insert (ILjava/lang/String;)Ljava/lang/StringBuilder;
L81:    aload_0
L82:    getfield Field Te const Ljava/lang/String;
L85:    invokevirtual Method java/lang/StringBuilder append (Ljava/lang/String;)Ljava/lang/StringBuilder;
L88:    invokevirtual Method java/lang/StringBuilder toString ()Ljava/lang/String;
L91:    invokespecial Method java/lang/RuntimeException <init> (Ljava/lang/String;)V
L94:    athrow
L95:    aload_0
L96:    getfield Field Te char Ljava/util/LinkedList;
L99:    invokevirtual Method java/util/LinkedList iterator ()Ljava/util/Iterator;
L102:   dup
L103:   astore_1
L104:   invokeinterface InterfaceMethod java/util/Iterator hasNext ()Z 1
L109:   ifeq L129
L112:   aload_1
L113:   invokeinterface InterfaceMethod java/util/Iterator next ()Ljava/lang/Object; 1
L118:   checkcast Te
L121:   invokestatic Method SE else (LTe;)V
L124:   aload_1
L125:   goto L104
L128:   athrow
L129:   return
L130:   
        .attribute StackMap b'\x00\x05\x00\x2F\x00\x01\x07\x00\x43\x00\x00\x00\x5F\x00\x01\x07\x00\x43\x00\x00\x00\x68\x00\x02\x07\x00\x43\x07\x01\xB6\x00\x01\x07\x01\xB6\x00\x80\x00\x00\x00\x01\x07\x01\xC0\x00\x81\x00\x02\x07\x00\x43\x07\x01\xB6\x00\x00'
    .end code
.end method

.method private static varargs appezoell1 : ([LTe;)LTe;
    .code stack 22 locals 1
L0:     new Te
L3:     dup
L4:     ldc_w "Guots us Appez\u00F6ll"
L7:     ldc_w "Have some cheese, will ya?"
L10:    ldc_w "appezoell"
L13:    new sg
L16:    dup
L17:    invokespecial Method sg <init> ()V
L20:    iconst_3
L21:    iconst_1
L22:    dup
L23:    pop2
L24:    ldc 3e-1f
L26:    ldc 2147483647
L28:    iconst_1
L29:    dup
L30:    dup
L31:    pop2
L32:    anewarray Uf
L35:    iconst_1
L36:    dup
L37:    pop2
L38:    dup
L39:    iconst_0
L40:    iconst_1
L41:    dup
L42:    pop2
L43:    new uD
L46:    dup
L47:    aconst_null
L48:    dup
L49:    dup_x1
L50:    iconst_1
L51:    dup
L52:    pop2
L53:    iconst_0
L54:    iconst_1
L55:    dup
L56:    pop2
L57:    iconst_0
L58:    dup_x1
L59:    iconst_1
L60:    dup
L61:    pop2
L62:    invokespecial Method uD <init> [_85]
L65:    aastore
L66:    iconst_0
L67:    iconst_1
L68:    dup
L69:    pop2
L70:    anewarray Uf
L73:    iconst_1
L74:    dup
L75:    pop2
L76:    invokespecial Method Te <init> (Ljava/lang/String;Ljava/lang/String;Ljava/lang/String;Leb;IFI[LUf;[LUf;)V
L79:    dup
L80:    getfield Field Te char Ljava/util/LinkedList;
L83:    aload_0
L84:    invokestatic Method java/util/Arrays asList ([Ljava/lang/Object;)Ljava/util/List;
L87:    invokevirtual Method java/util/LinkedList addAll (Ljava/util/Collection;)Z
L90:    pop
L91:    areturn
L92:    
    .end code
.end method

.method private static varargs fast : ([LTe;)LTe;
    .code stack 24 locals 1
L0:     new Te
L3:     dup
L4:     ldc_w "Fast"
L7:     ldc_w "Stay alive for two minutes."
L10:    ldc_w "efast"
L13:    new HE
L16:    dup
L17:    invokespecial Method HE <init> ()V
L20:    iconst_0
L21:    iconst_1
L22:    dup
L23:    pop2
L24:    fconst_1
L25:    ldc 2147483647
L27:    iconst_1
L28:    dup
L29:    dup
L30:    pop2
L31:    anewarray Uf
L34:    iconst_1
L35:    dup
L36:    pop2
L37:    dup
L38:    iconst_0
L39:    iconst_1
L40:    dup
L41:    pop2
L42:    new mg
L45:    dup
L46:    aconst_null
L47:    dup
L48:    dup_x1
L49:    ldc 1.2e2f
L51:    iconst_1
L52:    dup
L53:    pop2
L54:    iconst_0
L55:    iconst_1
L56:    dup
L57:    pop2
L58:    iconst_0
L59:    iconst_1
L60:    dup_x2
L61:    dup
L62:    pop2
L63:    iconst_0
L64:    iconst_1
L65:    dup
L66:    pop2
L67:    invokespecial Method mg <init> (Ljava/lang/String;Ljava/lang/String;Ljava/lang/String;FZZIZ)V
L70:    aastore
L71:    iconst_0
L72:    iconst_1
L73:    dup
L74:    pop2
L75:    anewarray Uf
L78:    iconst_1
L79:    dup
L80:    pop2
L81:    invokespecial Method Te <init> [_88]
L84:    dup
L85:    getfield Field Te char Ljava/util/LinkedList;
L88:    aload_0
L89:    invokestatic Method java/util/Arrays asList ([Ljava/lang/Object;)Ljava/util/List;
L92:    invokevirtual Method java/util/LinkedList addAll (Ljava/util/Collection;)Z
L95:    pop
L96:    areturn
L97:    
    .end code
.end method

.method private static varargs e123 : ([LTe;)LTe;
    .code stack 25 locals 1
L0:     new Te
L3:     dup
L4:     ldc_w "Easy as 1-2-3"
L7:     ldc_w "You have one minute to do two level 3 combos."
L10:    ldc_w "e123"
L13:    new Bg
L16:    dup
L17:    invokespecial Method Bg <init> ()V
L20:    iconst_0
L21:    iconst_1
L22:    dup
L23:    pop2
L24:    fconst_0
L25:    ldc 2147483647
L27:    iconst_1
L28:    dup
L29:    dup
L30:    pop2
L31:    anewarray Uf
L34:    iconst_1
L35:    dup
L36:    pop2
L37:    dup
L38:    iconst_0
L39:    iconst_1
L40:    dup
L41:    pop2
L42:    new jF
L45:    dup
L46:    aconst_null
L47:    dup
L48:    dup_x1
L49:    iconst_3
L50:    iconst_1
L51:    dup
L52:    pop2
L53:    iconst_2
L54:    iconst_1
L55:    dup
L56:    pop2
L57:    iconst_0
L58:    iconst_1
L59:    dup
L60:    pop2
L61:    iconst_0
L62:    iconst_1
L63:    dup
L64:    pop2
L65:    invokespecial Method jF <init> (Ljava/lang/String;Ljava/lang/String;Ljava/lang/String;IIIZ)V
L68:    aastore
L69:    iconst_1
L70:    dup
L71:    dup
L72:    pop2
L73:    anewarray Uf
L76:    iconst_1
L77:    dup
L78:    pop2
L79:    dup
L80:    iconst_0
L81:    iconst_1
L82:    dup
L83:    pop2
L84:    new mg
L87:    dup
L88:    aconst_null
L89:    dup
L90:    dup_x1
L91:    ldc 6e1f
L93:    iconst_1
L94:    dup
L95:    pop2
L96:    iconst_0
L97:    iconst_1
L98:    dup
L99:    pop2
L100:   iconst_0
L101:   iconst_1
L102:   dup_x2
L103:   dup
L104:   pop2
L105:   iconst_0
L106:   iconst_1
L107:   dup
L108:   pop2
L109:   invokespecial Method mg <init> (Ljava/lang/String;Ljava/lang/String;Ljava/lang/String;FZZIZ)V
L112:   aastore
L113:   invokespecial Method Te <init> [_88]
L116:   dup
L117:   getfield Field Te char Ljava/util/LinkedList;
L120:   aload_0
L121:   invokestatic Method java/util/Arrays asList ([Ljava/lang/Object;)Ljava/util/List;
L124:   invokevirtual Method java/util/LinkedList addAll (Ljava/util/Collection;)Z
L127:   pop
L128:   areturn
L129:   
    .end code
.end method

.method private static varargs pocall2 : ([LTe;)LTe;
    .code stack 22 locals 1
L0:     new Te
L3:     dup
L4:     ldc_w "Piece of cake"
L7:     ldc_w "Clear 25 lines."
L10:    ldc_w "pocall2"
L13:    new Qb
L16:    dup
L17:    invokespecial Method Qb <init> ()V
L20:    iconst_0
L21:    iconst_1
L22:    dup
L23:    pop2
L24:    fconst_0
L25:    ldc 2147483647
L27:    iconst_1
L28:    dup
L29:    dup
L30:    pop2
L31:    anewarray Uf
L34:    iconst_1
L35:    dup
L36:    pop2
L37:    dup
L38:    iconst_0
L39:    iconst_1
L40:    dup
L41:    pop2
L42:    new YE
L45:    dup
L46:    aconst_null
L47:    dup
L48:    dup_x1
L49:    bipush 25
L51:    iconst_1
L52:    dup
L53:    pop2
L54:    iconst_0
L55:    iconst_1
L56:    dup
L57:    pop2
L58:    iconst_0
L59:    iconst_1
L60:    dup
L61:    pop2
L62:    invokespecial Method YE <init> [_85]
L65:    aastore
L66:    iconst_0
L67:    iconst_1
L68:    dup
L69:    pop2
L70:    anewarray Uf
L73:    iconst_1
L74:    dup
L75:    pop2
L76:    invokespecial Method Te <init> [_88]
L79:    dup
L80:    getfield Field Te char Ljava/util/LinkedList;
L83:    aload_0
L84:    invokestatic Method java/util/Arrays asList ([Ljava/lang/Object;)Ljava/util/List;
L87:    invokevirtual Method java/util/LinkedList addAll (Ljava/util/Collection;)Z
L90:    pop
L91:    areturn
L92:    
    .end code
.end method

.method private static break : (LTe;)V
    .code stack 5 locals 1
L0:     getstatic Field SE do Ljava/util/Map;
L3:     aload_0
L4:     getfield Field Te const Ljava/lang/String;
L7:     invokeinterface InterfaceMethod java/util/Map containsKey (Ljava/lang/Object;)Z 2
L12:    ifeq L47
L15:    new java/lang/RuntimeException
L18:    dup
L19:    new java/lang/StringBuilder
L22:    dup
L23:    invokespecial Method java/lang/StringBuilder <init> ()V
L26:    iconst_0
L27:    ldc_w "Duplicate key "
L30:    invokevirtual Method java/lang/StringBuilder insert (ILjava/lang/String;)Ljava/lang/StringBuilder;
L33:    aload_0
L34:    getfield Field Te const Ljava/lang/String;
L37:    invokevirtual Method java/lang/StringBuilder append (Ljava/lang/String;)Ljava/lang/StringBuilder;
L40:    invokevirtual Method java/lang/StringBuilder toString ()Ljava/lang/String;
L43:    invokespecial Method java/lang/RuntimeException <init> (Ljava/lang/String;)V
L46:    athrow
L47:    getstatic Field SE else Ljava/util/Map;
L50:    aload_0
L51:    getfield Field Te const Ljava/lang/String;
L54:    aload_0
L55:    invokeinterface InterfaceMethod java/util/Map put (Ljava/lang/Object;Ljava/lang/Object;)Ljava/lang/Object; 3
L60:    ifnull L95
L63:    new java/lang/RuntimeException
L66:    dup
L67:    new java/lang/StringBuilder
L70:    dup
L71:    invokespecial Method java/lang/StringBuilder <init> ()V
L74:    iconst_0
L75:    ldc_w "Duplicate key "
L78:    invokevirtual Method java/lang/StringBuilder insert (ILjava/lang/String;)Ljava/lang/StringBuilder;
L81:    aload_0
L82:    getfield Field Te const Ljava/lang/String;
L85:    invokevirtual Method java/lang/StringBuilder append (Ljava/lang/String;)Ljava/lang/StringBuilder;
L88:    invokevirtual Method java/lang/StringBuilder toString ()Ljava/lang/String;
L91:    invokespecial Method java/lang/RuntimeException <init> (Ljava/lang/String;)V
L94:    athrow
L95:    return
L96:    
        .attribute StackMap b'\x00\x02\x00\x2F\x00\x01\x07\x00\x43\x00\x00\x00\x5F\x00\x01\x07\x00\x43\x00\x00'
    .end code
.end method

.method private static varargs abc : ([LTe;)LTe;
    .code stack 22 locals 1
L0:     new Te
L3:     dup
L4:     ldc_w "Easy as ABC"
L7:     ldc_w "Win against two opponents."
L10:    ldc_w "abc"
L13:    new Pe
L16:    dup
L17:    invokespecial Method Pe <init> ()V
L20:    iconst_2
L21:    iconst_1
L22:    dup
L23:    pop2
L24:    ldc_w 1e-1f
L27:    ldc 2147483647
L29:    iconst_1
L30:    dup
L31:    dup
L32:    pop2
L33:    anewarray Uf
L36:    iconst_1
L37:    dup
L38:    pop2
L39:    dup
L40:    iconst_0
L41:    iconst_1
L42:    dup
L43:    pop2
L44:    new uD
L47:    dup
L48:    aconst_null
L49:    dup
L50:    dup_x1
L51:    iconst_1
L52:    dup
L53:    pop2
L54:    iconst_0
L55:    iconst_1
L56:    dup
L57:    pop2
L58:    iconst_0
L59:    dup_x1
L60:    iconst_1
L61:    dup
L62:    pop2
L63:    invokespecial Method uD <init> [_85]
L66:    aastore
L67:    iconst_0
L68:    iconst_1
L69:    dup
L70:    pop2
L71:    anewarray Uf
L74:    iconst_1
L75:    dup
L76:    pop2
L77:    invokespecial Method Te <init> [_88]
L80:    dup
L81:    getfield Field Te char Ljava/util/LinkedList;
L84:    aload_0
L85:    invokestatic Method java/util/Arrays asList ([Ljava/lang/Object;)Ljava/util/List;
L88:    invokevirtual Method java/util/LinkedList addAll (Ljava/util/Collection;)Z
L91:    pop
L92:    areturn
L93:    
    .end code
.end method

.method private static varargs emptyhouse : ([LTe;)LTe;
    .code stack 22 locals 1
L0:     new Te
L3:     dup
L4:     ldc_w "Empty House"
L7:     ldc_w "Clear the playfield completely."
L10:    ldc_w "empty"
L13:    new RE
L16:    dup
L17:    invokespecial Method RE <init> ()V
L20:    iconst_0
L21:    iconst_1
L22:    dup
L23:    pop2
L24:    fconst_1
L25:    ldc 2147483647
L27:    iconst_1
L28:    dup
L29:    dup
L30:    pop2
L31:    anewarray Uf
L34:    iconst_1
L35:    dup
L36:    pop2
L37:    dup
L38:    iconst_0
L39:    iconst_1
L40:    dup
L41:    pop2
L42:    new bE
L45:    dup
L46:    aconst_null
L47:    dup
L48:    dup_x1
L49:    iconst_1
L50:    dup
L51:    pop2
L52:    iconst_0
L53:    iconst_1
L54:    dup
L55:    pop2
L56:    iconst_0
L57:    iconst_1
L58:    dup_x2
L59:    dup
L60:    pop2
L61:    invokespecial Method bE <init> [_85]
L64:    aastore
L65:    iconst_0
L66:    iconst_1
L67:    dup
L68:    pop2
L69:    anewarray Uf
L72:    iconst_1
L73:    dup
L74:    pop2
L75:    invokespecial Method Te <init> [_88]
L78:    dup
L79:    getfield Field Te char Ljava/util/LinkedList;
L82:    aload_0
L83:    invokestatic Method java/util/Arrays asList ([Ljava/lang/Object;)Ljava/util/List;
L86:    invokevirtual Method java/util/LinkedList addAll (Ljava/util/Collection;)Z
L89:    pop
L90:    areturn
L91:    
    .end code
.end method

.method private static varargs grandefinale : ([LTe;)LTe;
    .code stack 22 locals 1
L0:     new Te
L3:     dup
L4:     ldc_w "Grande Finale"
L7:     ldc_w "Clear 100 lines."
L10:    ldc_w "tf"
L13:    new Qb
L16:    dup
L17:    invokespecial Method Qb <init> ()V
L20:    iconst_0
L21:    iconst_1
L22:    dup
L23:    pop2
L24:    fconst_1
L25:    ldc 2147483647
L27:    iconst_1
L28:    dup
L29:    dup
L30:    pop2
L31:    anewarray Uf
L34:    iconst_1
L35:    dup
L36:    pop2
L37:    dup
L38:    iconst_0
L39:    iconst_1
L40:    dup
L41:    pop2
L42:    new YE
L45:    dup
L46:    aconst_null
L47:    dup
L48:    dup_x1
L49:    bipush 100
L51:    iconst_1
L52:    dup
L53:    pop2
L54:    iconst_0
L55:    iconst_1
L56:    dup
L57:    pop2
L58:    iconst_0
L59:    iconst_1
L60:    dup
L61:    pop2
L62:    invokespecial Method YE <init> [_85]
L65:    aastore
L66:    iconst_1
L67:    dup
L68:    dup
L69:    pop2
L70:    anewarray Uf
L73:    iconst_1
L74:    dup
L75:    pop2
L76:    dup
L77:    iconst_0
L78:    iconst_1
L79:    dup
L80:    pop2
L81:    new ve
L84:    dup
L85:    iconst_4
L86:    iconst_1
L87:    dup
L88:    pop2
L89:    ldc_w 1e1f
L92:    invokespecial Method ve <init> (IF)V
L95:    aastore
L96:    invokespecial Method Te <init> [_88]
L99:    dup
L100:   dup_x1
L101:   iconst_1
L102:   dup
L103:   dup
L104:   pop2
L105:   putfield Field Te else Z
L108:   getfield Field Te char Ljava/util/LinkedList;
L111:   aload_0
L112:   invokestatic Method java/util/Arrays asList ([Ljava/lang/Object;)Ljava/util/List;
L115:   invokevirtual Method java/util/LinkedList addAll (Ljava/util/Collection;)Z
L118:   pop
L119:   areturn
L120:   
    .end code
.end method

.method private static varargs melee : ([LTe;)LTe;
    .code stack 22 locals 1
L0:     new Te
L3:     dup
L4:     ldc_w "Melee"
L7:     ldc_w "Too many cooks spoil the broth. Can you take on all those cooks?"
L10:    ldc_w "tmp"
L13:    new Qb
L16:    dup
L17:    invokespecial Method Qb <init> ()V
L20:    bipush 65
L22:    iconst_1
L23:    dup
L24:    pop2
L25:    ldc_w 3.5e-1f
L28:    ldc 2147483647
L30:    iconst_1
L31:    dup
L32:    dup
L33:    pop2
L34:    anewarray Uf
L37:    iconst_1
L38:    dup
L39:    pop2
L40:    dup
L41:    iconst_0
L42:    iconst_1
L43:    dup
L44:    pop2
L45:    new uD
L48:    dup
L49:    aconst_null
L50:    dup
L51:    dup_x1
L52:    iconst_1
L53:    dup
L54:    pop2
L55:    iconst_0
L56:    iconst_1
L57:    dup
L58:    pop2
L59:    iconst_0
L60:    dup_x1
L61:    iconst_1
L62:    dup
L63:    pop2
L64:    invokespecial Method uD <init> [_85]
L67:    aastore
L68:    iconst_1
L69:    dup
L70:    dup
L71:    pop2
L72:    anewarray Uf
L75:    iconst_1
L76:    dup
L77:    pop2
L78:    dup
L79:    iconst_0
L80:    iconst_1
L81:    dup
L82:    pop2
L83:    new TF
L86:    dup
L87:    invokespecial Method TF <init> ()V
L90:    aastore
L91:    invokespecial Method Te <init> [_88]
L94:    dup
L95:    getfield Field Te char Ljava/util/LinkedList;
L98:    aload_0
L99:    invokestatic Method java/util/Arrays asList ([Ljava/lang/Object;)Ljava/util/List;
L102:   invokevirtual Method java/util/LinkedList addAll (Ljava/util/Collection;)Z
L105:   pop
L106:   areturn
L107:   
    .end code
.end method

.method private static varargs omnomnom : ([LTe;)LTe;
    .code stack 22 locals 1
L0:     new Te
L3:     dup
L4:     ldc_w "Om Nom Nom Nom"
L7:     ldc_w "Clear 20 lines."
L10:    ldc_w "omnomnom"
L13:    new Qb
L16:    dup
L17:    invokespecial Method Qb <init> ()V
L20:    iconst_0
L21:    iconst_1
L22:    dup
L23:    pop2
L24:    fconst_1
L25:    ldc 2147483647
L27:    iconst_1
L28:    dup
L29:    dup
L30:    pop2
L31:    anewarray Uf
L34:    iconst_1
L35:    dup
L36:    pop2
L37:    dup
L38:    iconst_0
L39:    iconst_1
L40:    dup
L41:    pop2
L42:    new YE
L45:    dup
L46:    aconst_null
L47:    dup
L48:    dup_x1
L49:    bipush 20
L51:    iconst_1
L52:    dup
L53:    pop2
L54:    iconst_0
L55:    iconst_1
L56:    dup
L57:    pop2
L58:    iconst_0
L59:    iconst_1
L60:    dup
L61:    pop2
L62:    invokespecial Method YE <init> [_85]
L65:    aastore
L66:    iconst_1
L67:    dup
L68:    dup
L69:    pop2
L70:    anewarray Uf
L73:    iconst_1
L74:    dup
L75:    pop2
L76:    dup
L77:    iconst_0
L78:    iconst_1
L79:    dup
L80:    pop2
L81:    new AG
L84:    dup
L85:    invokespecial Method AG <init> ()V
L88:    aastore
L89:    invokespecial Method Te <init> [_88]
L92:    dup
L93:    getfield Field Te char Ljava/util/LinkedList;
L96:    aload_0
L97:    invokestatic Method java/util/Arrays asList ([Ljava/lang/Object;)Ljava/util/List;
L100:   invokevirtual Method java/util/LinkedList addAll (Ljava/util/Collection;)Z
L103:   pop
L104:   areturn
L105:   
    .end code
.end method

.method private static varargs winterbottom : ([LTe;)LTe;
    .code stack 22 locals 1
L0:     new Te
L3:     dup
L4:     ldc_w "Winterbottom"
L7:     ldc_w "Gobble all flying cheese."
L10:    ldc_w "oddpb"
L13:    new Me
L16:    dup
L17:    invokespecial Method Me <init> ()V
L20:    iconst_0
L21:    iconst_1
L22:    dup
L23:    pop2
L24:    fconst_0
L25:    ldc 2147483647
L27:    iconst_1
L28:    dup
L29:    dup
L30:    pop2
L31:    anewarray Uf
L34:    iconst_1
L35:    dup
L36:    pop2
L37:    dup
L38:    iconst_0
L39:    iconst_1
L40:    dup
L41:    pop2
L42:    new uD
L45:    dup
L46:    aconst_null
L47:    dup
L48:    dup_x1
L49:    iconst_1
L50:    dup
L51:    pop2
L52:    iconst_0
L53:    iconst_1
L54:    dup
L55:    pop2
L56:    iconst_0
L57:    dup_x1
L58:    iconst_1
L59:    dup
L60:    pop2
L61:    invokespecial Method uD <init> [_85]
L64:    aastore
L65:    iconst_0
L66:    iconst_1
L67:    dup
L68:    pop2
L69:    anewarray Uf
L72:    iconst_1
L73:    dup
L74:    pop2
L75:    invokespecial Method Te <init> [_88]
L78:    dup
L79:    getfield Field Te char Ljava/util/LinkedList;
L82:    aload_0
L83:    invokestatic Method java/util/Arrays asList ([Ljava/lang/Object;)Ljava/util/List;
L86:    invokevirtual Method java/util/LinkedList addAll (Ljava/util/Collection;)Z
L89:    pop
L90:    areturn
L91:    
    .end code
.end method

.method private static varargs wtf : ([LTe;)LTe;
    .code stack 22 locals 1
L0:     new Te
L3:     dup
L4:     ldc_w "WTF"
L7:     ldc_w "Place 60 pieces. No need to hurry."
L10:    ldc_w "wtf"
L13:    new WE
L16:    dup
L17:    invokespecial Method WE <init> ()V
L20:    iconst_0
L21:    iconst_1
L22:    dup
L23:    pop2
L24:    fconst_1
L25:    ldc 2147483647
L27:    iconst_1
L28:    dup
L29:    dup
L30:    pop2
L31:    anewarray Uf
L34:    iconst_1
L35:    dup
L36:    pop2
L37:    dup
L38:    iconst_0
L39:    iconst_1
L40:    dup
L41:    pop2
L42:    new ee
L45:    dup
L46:    aconst_null
L47:    dup
L48:    dup_x1
L49:    bipush 60
L51:    iconst_1
L52:    dup
L53:    pop2
L54:    iconst_0
L55:    iconst_1
L56:    dup
L57:    pop2
L58:    iconst_0
L59:    iconst_1
L60:    dup
L61:    pop2
L62:    invokespecial Method ee <init> [_85]
L65:    aastore
L66:    iconst_0
L67:    iconst_1
L68:    dup
L69:    pop2
L70:    anewarray Uf
L73:    iconst_1
L74:    dup
L75:    pop2
L76:    invokespecial Method Te <init> [_88]
L79:    dup
L80:    getfield Field Te char Ljava/util/LinkedList;
L83:    aload_0
L84:    invokestatic Method java/util/Arrays asList ([Ljava/lang/Object;)Ljava/util/List;
L87:    invokevirtual Method java/util/LinkedList addAll (Ljava/util/Collection;)Z
L90:    pop
L91:    areturn
L92:    
    .end code
.end method

.method private static varargs angularmomentum : ([LTe;)LTe;
    .code stack 22 locals 1
L0:     new Te
L3:     dup
L4:     ldc_w "Angular momentum"
L7:     ldc_w "You spin me right round, baby right round like a record, baby right round round round."
L10:    ldc_w "amm"
L13:    new Qb
L16:    dup
L17:    invokespecial Method Qb <init> ()V
L20:    iconst_2
L21:    iconst_1
L22:    dup
L23:    pop2
L24:    ldc_w 2.3e-1f
L27:    ldc 2147483647
L29:    iconst_1
L30:    dup
L31:    dup
L32:    pop2
L33:    anewarray Uf
L36:    iconst_1
L37:    dup
L38:    pop2
L39:    dup
L40:    iconst_0
L41:    iconst_1
L42:    dup
L43:    pop2
L44:    new uD
L47:    dup
L48:    aconst_null
L49:    dup
L50:    dup_x1
L51:    iconst_1
L52:    dup
L53:    pop2
L54:    iconst_0
L55:    iconst_1
L56:    dup
L57:    pop2
L58:    iconst_0
L59:    dup_x1
L60:    iconst_1
L61:    dup
L62:    pop2
L63:    invokespecial Method uD <init> [_85]
L66:    aastore
L67:    iconst_1
L68:    dup
L69:    dup
L70:    pop2
L71:    anewarray Uf
L74:    iconst_1
L75:    dup
L76:    pop2
L77:    dup
L78:    iconst_0
L79:    iconst_1
L80:    dup
L81:    pop2
L82:    new Xf
L85:    dup
L86:    invokespecial Method Xf <init> ()V
L89:    aastore
L90:    invokespecial Method Te <init> [_88]
L93:    dup
L94:    getfield Field Te char Ljava/util/LinkedList;
L97:    aload_0
L98:    invokestatic Method java/util/Arrays asList ([Ljava/lang/Object;)Ljava/util/List;
L101:   invokevirtual Method java/util/LinkedList addAll (Ljava/util/Collection;)Z
L104:   pop
L105:   areturn
L106:   
    .end code
.end method

.method private static varargs mampf : ([LTe;)LTe;
    .code stack 25 locals 1
L0:     new Te
L3:     dup
L4:     ldc_w "Hungry"
L7:     ldc_w "You have only 25 seconds to eat all the cheese."
L10:    ldc_w "mampf"
L13:    new sg
L16:    dup
L17:    invokespecial Method sg <init> ()V
L20:    iconst_0
L21:    iconst_1
L22:    dup
L23:    pop2
L24:    fconst_0
L25:    ldc 2147483647
L27:    iconst_1
L28:    dup
L29:    dup
L30:    pop2
L31:    anewarray Uf
L34:    iconst_1
L35:    dup
L36:    pop2
L37:    dup
L38:    iconst_0
L39:    iconst_1
L40:    dup
L41:    pop2
L42:    new uD
L45:    dup
L46:    aconst_null
L47:    dup
L48:    dup_x1
L49:    iconst_1
L50:    dup
L51:    pop2
L52:    iconst_0
L53:    iconst_1
L54:    dup
L55:    pop2
L56:    iconst_0
L57:    dup_x1
L58:    iconst_1
L59:    dup
L60:    pop2
L61:    invokespecial Method uD <init> [_85]
L64:    aastore
L65:    iconst_1
L66:    dup
L67:    dup
L68:    pop2
L69:    anewarray Uf
L72:    iconst_1
L73:    dup
L74:    pop2
L75:    dup
L76:    iconst_0
L77:    iconst_1
L78:    dup
L79:    pop2
L80:    new mg
L83:    dup
L84:    aconst_null
L85:    dup
L86:    dup_x1
L87:    ldc_w 2.5e1f
L90:    iconst_1
L91:    dup
L92:    pop2
L93:    iconst_1
L94:    dup
L95:    pop2
L96:    iconst_0
L97:    iconst_1
L98:    dup
L99:    pop2
L100:   iconst_0
L101:   dup_x1
L102:   dup_x2
L103:   iconst_1
L104:   dup
L105:   pop2
L106:   invokespecial Method mg <init> (Ljava/lang/String;Ljava/lang/String;Ljava/lang/String;FZZIZ)V
L109:   aastore
L110:   invokespecial Method Te <init> [_88]
L113:   dup
L114:   getfield Field Te char Ljava/util/LinkedList;
L117:   aload_0
L118:   invokestatic Method java/util/Arrays asList ([Ljava/lang/Object;)Ljava/util/List;
L121:   invokevirtual Method java/util/LinkedList addAll (Ljava/util/Collection;)Z
L124:   pop
L125:   areturn
L126:   
    .end code
.end method

.method private static varargs twscombos : ([LTe;)LTe;
    .code stack 26 locals 1
L0:     new Te
L3:     dup
L4:     ldc_w "The whole six combos"
L7:     ldc_w "Make a combo of every single level, from one to six."
L10:    ldc_w "twscombos"
L13:    new Qb
L16:    dup
L17:    invokespecial Method Qb <init> ()V
L20:    iconst_0
L21:    iconst_1
L22:    dup
L23:    pop2
L24:    fconst_1
L25:    ldc 2147483647
L27:    iconst_1
L28:    dup
L29:    dup
L30:    pop2
L31:    anewarray Uf
L34:    iconst_1
L35:    dup
L36:    pop2
L37:    dup
L38:    iconst_0
L39:    iconst_1
L40:    dup
L41:    pop2
L42:    new Lg
L45:    dup
L46:    aconst_null
L47:    dup
L48:    dup_x1
L49:    iconst_1
L50:    dup
L51:    pop2
L52:    iconst_1
L53:    dup
L54:    dup
L55:    pop2
L56:    iconst_0
L57:    dup_x1
L58:    iconst_1
L59:    dup
L60:    pop2
L61:    bipush 6
L63:    iconst_1
L64:    dup
L65:    pop2
L66:    newarray int
L68:    iconst_1
L69:    dup
L70:    pop2
L71:    dup
L72:    iconst_0
L73:    iconst_1
L74:    dup
L75:    pop2
L76:    iconst_1
L77:    dup
L78:    dup
L79:    pop2
L80:    iastore
L81:    dup
L82:    iconst_1
L83:    dup
L84:    pop2
L85:    iconst_2
L86:    iconst_1
L87:    dup_x1
L88:    dup
L89:    pop2
L90:    iastore
L91:    dup
L92:    iconst_2
L93:    iconst_1
L94:    dup
L95:    pop2
L96:    iconst_3
L97:    iconst_1
L98:    dup
L99:    pop2
L100:   iastore
L101:   dup
L102:   iconst_3
L103:   iconst_1
L104:   dup
L105:   pop2
L106:   iconst_4
L107:   iconst_1
L108:   dup
L109:   pop2
L110:   iastore
L111:   dup
L112:   iconst_4
L113:   iconst_1
L114:   dup
L115:   pop2
L116:   iconst_5
L117:   iconst_1
L118:   dup
L119:   pop2
L120:   iastore
L121:   dup
L122:   iconst_5
L123:   iconst_1
L124:   dup
L125:   pop2
L126:   bipush 6
L128:   iconst_1
L129:   dup
L130:   pop2
L131:   iastore
L132:   invokespecial Method Lg <init> (Ljava/lang/String;Ljava/lang/String;Ljava/lang/String;IIZ[I)V
L135:   aastore
L136:   iconst_0
L137:   iconst_1
L138:   dup
L139:   pop2
L140:   anewarray Uf
L143:   iconst_1
L144:   dup
L145:   pop2
L146:   invokespecial Method Te <init> [_88]
L149:   dup
L150:   getfield Field Te char Ljava/util/LinkedList;
L153:   aload_0
L154:   invokestatic Method java/util/Arrays asList ([Ljava/lang/Object;)Ljava/util/List;
L157:   invokevirtual Method java/util/LinkedList addAll (Ljava/util/Collection;)Z
L160:   pop
L161:   areturn
L162:   
    .end code
.end method

.method private static varargs unbreakable : ([LTe;)LTe;
    .code stack 22 locals 1
L0:     new Te
L3:     dup
L4:     ldc_w "Unbreakable"
L7:     ldc_w "Stop your opponent. Be aware that these garbage lines are here to stay."
L10:    ldc_w "ahgurkgurk"
L13:    new Ce
L16:    dup
L17:    invokespecial Method Ce <init> ()V
L20:    iconst_1
L21:    dup
L22:    pop2
L23:    ldc 3e-1f
L25:    ldc 2147483647
L27:    iconst_1
L28:    dup_x2
L29:    iconst_1
L30:    dup
L31:    pop2
L32:    anewarray Uf
L35:    iconst_1
L36:    dup
L37:    pop2
L38:    dup
L39:    iconst_0
L40:    iconst_1
L41:    dup
L42:    pop2
L43:    new uD
L46:    dup
L47:    aconst_null
L48:    dup
L49:    dup_x1
L50:    iconst_1
L51:    dup
L52:    pop2
L53:    iconst_0
L54:    iconst_1
L55:    dup
L56:    pop2
L57:    iconst_0
L58:    dup_x1
L59:    iconst_1
L60:    dup
L61:    pop2
L62:    invokespecial Method uD <init> [_85]
L65:    aastore
L66:    iconst_0
L67:    iconst_1
L68:    dup
L69:    pop2
L70:    anewarray Uf
L73:    iconst_1
L74:    dup
L75:    pop2
L76:    invokespecial Method Te <init> [_88]
L79:    dup
L80:    getfield Field Te char Ljava/util/LinkedList;
L83:    aload_0
L84:    invokestatic Method java/util/Arrays asList ([Ljava/lang/Object;)Ljava/util/List;
L87:    invokevirtual Method java/util/LinkedList addAll (Ljava/util/Collection;)Z
L90:    pop
L91:    areturn
L92:    
    .end code
.end method

.method private static varargs quickstart : ([LTe;)LTe;
    .code stack 25 locals 1
L0:     new Te
L3:     dup
L4:     ldc_w "Quickstart"
L7:     ldc_w "Beat your opponent in less than 30 seconds."
L10:    ldc_w "qs"
L13:    new rF
L16:    dup
L17:    invokespecial Method rF <init> ()V
L20:    iconst_1
L21:    dup
L22:    pop2
L23:    ldc_w 5.8e-1f
L26:    ldc 2147483647
L28:    iconst_1
L29:    dup_x2
L30:    iconst_1
L31:    dup
L32:    pop2
L33:    anewarray Uf
L36:    iconst_1
L37:    dup
L38:    pop2
L39:    dup
L40:    iconst_0
L41:    iconst_1
L42:    dup
L43:    pop2
L44:    new uD
L47:    dup
L48:    aconst_null
L49:    dup
L50:    dup_x1
L51:    iconst_1
L52:    dup
L53:    pop2
L54:    iconst_0
L55:    iconst_1
L56:    dup
L57:    pop2
L58:    iconst_0
L59:    dup_x1
L60:    iconst_1
L61:    dup
L62:    pop2
L63:    invokespecial Method uD <init> [_85]
L66:    aastore
L67:    iconst_1
L68:    dup
L69:    dup
L70:    pop2
L71:    anewarray Uf
L74:    iconst_1
L75:    dup
L76:    pop2
L77:    dup
L78:    iconst_0
L79:    iconst_1
L80:    dup
L81:    pop2
L82:    new mg
L85:    dup
L86:    aconst_null
L87:    dup
L88:    dup_x1
L89:    ldc_w 3e1f
L92:    iconst_1
L93:    dup
L94:    pop2
L95:    iconst_1
L96:    dup
L97:    pop2
L98:    iconst_0
L99:    iconst_1
L100:   dup
L101:   pop2
L102:   iconst_0
L103:   dup_x1
L104:   dup_x2
L105:   iconst_1
L106:   dup
L107:   pop2
L108:   invokespecial Method mg <init> (Ljava/lang/String;Ljava/lang/String;Ljava/lang/String;FZZIZ)V
L111:   aastore
L112:   invokespecial Method Te <init> [_88]
L115:   dup
L116:   getfield Field Te char Ljava/util/LinkedList;
L119:   aload_0
L120:   invokestatic Method java/util/Arrays asList ([Ljava/lang/Object;)Ljava/util/List;
L123:   invokevirtual Method java/util/LinkedList addAll (Ljava/util/Collection;)Z
L126:   pop
L127:   areturn
L128:   
    .end code
.end method

.method private static varargs cleveland : ([LTe;)LTe;
    .code stack 22 locals 1
L0:     new Te
L3:     dup
L4:     ldc_w "Hello Cleveland"
L7:     ldc_w "Something's fishy with the directions here."
L10:    ldc_w "cleveland"
L13:    new Qb
L16:    dup
L17:    invokespecial Method Qb <init> ()V
L20:    iconst_1
L21:    dup
L22:    pop2
L23:    ldc 2.5e-1f
L25:    ldc 2147483647
L27:    iconst_1
L28:    dup_x2
L29:    iconst_1
L30:    dup
L31:    pop2
L32:    anewarray Uf
L35:    iconst_1
L36:    dup
L37:    pop2
L38:    dup
L39:    iconst_0
L40:    iconst_1
L41:    dup
L42:    pop2
L43:    new uD
L46:    dup
L47:    aconst_null
L48:    dup
L49:    dup_x1
L50:    iconst_1
L51:    dup
L52:    pop2
L53:    iconst_0
L54:    iconst_1
L55:    dup
L56:    pop2
L57:    iconst_0
L58:    dup_x1
L59:    iconst_1
L60:    dup
L61:    pop2
L62:    invokespecial Method uD <init> [_85]
L65:    aastore
L66:    iconst_1
L67:    dup
L68:    dup
L69:    pop2
L70:    anewarray Uf
L73:    iconst_1
L74:    dup
L75:    pop2
L76:    dup
L77:    iconst_0
L78:    iconst_1
L79:    dup
L80:    pop2
L81:    new je
L84:    dup
L85:    invokespecial Method je <init> ()V
L88:    aastore
L89:    invokespecial Method Te <init> [_88]
L92:    dup
L93:    getfield Field Te char Ljava/util/LinkedList;
L96:    aload_0
L97:    invokestatic Method java/util/Arrays asList ([Ljava/lang/Object;)Ljava/util/List;
L100:   invokevirtual Method java/util/LinkedList addAll (Ljava/util/Collection;)Z
L103:   pop
L104:   areturn
L105:   
    .end code
.end method

.method private static varargs easyaspie : ([LTe;)LTe;
    .code stack 25 locals 1
L0:     new Te
L3:     dup
L4:     ldc_w "Easy as pie"
L7:     ldc_w "Make two level 5 combos in a minute."
L10:    ldc_w "pb2"
L13:    new Qb
L16:    dup
L17:    invokespecial Method Qb <init> ()V
L20:    iconst_0
L21:    iconst_1
L22:    dup
L23:    pop2
L24:    fconst_0
L25:    ldc 2147483647
L27:    iconst_1
L28:    dup
L29:    dup
L30:    pop2
L31:    anewarray Uf
L34:    iconst_1
L35:    dup
L36:    pop2
L37:    dup
L38:    iconst_0
L39:    iconst_1
L40:    dup
L41:    pop2
L42:    new jF
L45:    dup
L46:    aconst_null
L47:    dup
L48:    dup_x1
L49:    iconst_5
L50:    iconst_1
L51:    dup
L52:    pop2
L53:    iconst_2
L54:    iconst_1
L55:    dup
L56:    pop2
L57:    iconst_0
L58:    iconst_1
L59:    dup
L60:    pop2
L61:    iconst_0
L62:    iconst_1
L63:    dup
L64:    pop2
L65:    invokespecial Method jF <init> (Ljava/lang/String;Ljava/lang/String;Ljava/lang/String;IIIZ)V
L68:    aastore
L69:    iconst_1
L70:    dup
L71:    dup
L72:    pop2
L73:    anewarray Uf
L76:    iconst_1
L77:    dup
L78:    pop2
L79:    dup
L80:    iconst_0
L81:    iconst_1
L82:    dup
L83:    pop2
L84:    new mg
L87:    dup
L88:    aconst_null
L89:    dup
L90:    dup_x1
L91:    ldc 6e1f
L93:    iconst_1
L94:    dup
L95:    pop2
L96:    iconst_0
L97:    iconst_1
L98:    dup
L99:    pop2
L100:   iconst_0
L101:   iconst_1
L102:   dup_x2
L103:   dup
L104:   pop2
L105:   iconst_0
L106:   iconst_1
L107:   dup
L108:   pop2
L109:   invokespecial Method mg <init> (Ljava/lang/String;Ljava/lang/String;Ljava/lang/String;FZZIZ)V
L112:   aastore
L113:   invokespecial Method Te <init> [_88]
L116:   dup
L117:   getfield Field Te char Ljava/util/LinkedList;
L120:   aload_0
L121:   invokestatic Method java/util/Arrays asList ([Ljava/lang/Object;)Ljava/util/List;
L124:   invokevirtual Method java/util/LinkedList addAll (Ljava/util/Collection;)Z
L127:   pop
L128:   areturn
L129:   
    .end code
.end method

.method private static varargs garbageman : ([LTe;)LTe;
    .code stack 24 locals 1
L0:     new Te
L3:     dup
L4:     ldc_w "Who can?"
L7:     ldc_w "The garbageman can!"
L10:    ldc_w "gmc"
L13:    new GE
L16:    dup
L17:    invokespecial Method GE <init> ()V
L20:    iconst_0
L21:    iconst_1
L22:    dup
L23:    pop2
L24:    fconst_1
L25:    ldc 2147483647
L27:    iconst_1
L28:    dup
L29:    dup
L30:    pop2
L31:    anewarray Uf
L34:    iconst_1
L35:    dup
L36:    pop2
L37:    dup
L38:    iconst_0
L39:    iconst_1
L40:    dup
L41:    pop2
L42:    new mg
L45:    dup
L46:    aconst_null
L47:    dup
L48:    dup_x1
L49:    ldc 9e1f
L51:    iconst_1
L52:    dup
L53:    pop2
L54:    iconst_0
L55:    iconst_1
L56:    dup
L57:    pop2
L58:    iconst_0
L59:    iconst_1
L60:    dup_x2
L61:    dup
L62:    pop2
L63:    iconst_0
L64:    iconst_1
L65:    dup
L66:    pop2
L67:    invokespecial Method mg <init> [_126]
L70:    aastore
L71:    iconst_0
L72:    iconst_1
L73:    dup
L74:    pop2
L75:    anewarray Uf
L78:    iconst_1
L79:    dup
L80:    pop2
L81:    invokespecial Method Te <init> [_88]
L84:    dup
L85:    getfield Field Te char Ljava/util/LinkedList;
L88:    aload_0
L89:    invokestatic Method java/util/Arrays asList ([Ljava/lang/Object;)Ljava/util/List;
L92:    invokevirtual Method java/util/LinkedList addAll (Ljava/util/Collection;)Z
L95:    pop
L96:    areturn
L97:    
    .end code
.end method

.method private static varargs ruggu : ([LTe;)LTe;
    .code stack 23 locals 2
L0:     new Cg
L3:     dup
L4:     invokespecial Method Cg <init> ()V
L7:     astore_1
L8:     new Te
L11:    dup
L12:    iconst_1
L13:    ldc_w "settings/ruggu/Cg-current_ruggu.txt"
L16:    invokestatic Method rugguUtils getNthLn (ILjava/lang/String;)Ljava/lang/String;
L19:    iconst_2
L20:    ldc_w "settings/ruggu/Cg-current_ruggu.txt"
L23:    invokestatic Method rugguUtils getNthLn (ILjava/lang/String;)Ljava/lang/String;
L26:    ldc_w "stages"
L29:    new gF
L32:    dup
L33:    aload_1
L34:    invokespecial Method gF <init> (LCg;)V
L37:    iconst_0
L38:    iconst_1
L39:    dup
L40:    pop2
L41:    fconst_1
L42:    ldc 2147483647
L44:    iconst_1
L45:    dup
L46:    dup
L47:    pop2
L48:    anewarray Uf
L51:    iconst_1
L52:    dup
L53:    pop2
L54:    dup
L55:    iconst_0
L56:    iconst_1
L57:    dup
L58:    pop2
L59:    aload_1
L60:    aastore
L61:    iconst_2
L62:    iconst_1
L63:    dup
L64:    pop2
L65:    anewarray Uf
L68:    iconst_1
L69:    dup
L70:    pop2
L71:    dup
L72:    iconst_0
L73:    iconst_1
L74:    dup
L75:    pop2
L76:    new ee
L79:    dup
L80:    aconst_null
L81:    dup
L82:    dup_x1
L83:    aload_1
L84:    getfield Field Cg pieces Ljava/util/ArrayList;
L87:    invokevirtual Method java/util/ArrayList size ()I
L90:    iconst_1
L91:    dup
L92:    dup
L93:    pop2
L94:    iadd
L95:    iconst_0
L96:    iconst_1
L97:    dup
L98:    pop2
L99:    iconst_0
L100:   iconst_1
L101:   dup
L102:   pop2
L103:   invokespecial Method ee <init> [_85]
L106:   aastore
L107:   dup
L108:   iconst_1
L109:   dup
L110:   dup
L111:   pop2
L112:   new yg
L115:   dup
L116:   aconst_null
L117:   dup
L118:   dup_x1
L119:   iconst_0
L120:   iconst_1
L121:   dup
L122:   pop2
L123:   iconst_0
L124:   iconst_1
L125:   dup
L126:   pop2
L127:   invokespecial Method yg <init> (Ljava/lang/String;Ljava/lang/String;Ljava/lang/String;IZ)V
L130:   aastore
L131:   invokespecial Method Te <init> [_88]
L134:   dup
L135:   getfield Field Te char Ljava/util/LinkedList;
L138:   aload_0
L139:   invokestatic Method java/util/Arrays asList ([Ljava/lang/Object;)Ljava/util/List;
L142:   invokevirtual Method java/util/LinkedList addAll (Ljava/util/Collection;)Z
L145:   pop
L146:   areturn
L147:   
    .end code
.end method

.method public <init> : ()V
    .code stack 1 locals 1
L0:     aload_0
L1:     invokespecial Method java/lang/Object <init> ()V
L4:     return
L5:     
    .end code
.end method

.method private static varargs travoltafever : ([LTe;)LTe;
    .code stack 24 locals 1
L0:     new Te
L3:     dup
L4:     ldc_w "Travolta Fever"
L7:     ldc_w "Stay alive for 90 seconds."
L10:    ldc_w "tfev"
L13:    new Jg
L16:    dup
L17:    invokespecial Method Jg <init> ()V
L20:    iconst_0
L21:    iconst_1
L22:    dup
L23:    pop2
L24:    fconst_1
L25:    ldc 2147483647
L27:    iconst_1
L28:    dup
L29:    dup
L30:    pop2
L31:    anewarray Uf
L34:    iconst_1
L35:    dup
L36:    pop2
L37:    dup
L38:    iconst_0
L39:    iconst_1
L40:    dup
L41:    pop2
L42:    new mg
L45:    dup
L46:    aconst_null
L47:    dup
L48:    dup_x1
L49:    ldc 9e1f
L51:    iconst_1
L52:    dup
L53:    pop2
L54:    iconst_0
L55:    iconst_1
L56:    dup
L57:    pop2
L58:    iconst_0
L59:    iconst_1
L60:    dup_x2
L61:    dup
L62:    pop2
L63:    iconst_0
L64:    iconst_1
L65:    dup
L66:    pop2
L67:    invokespecial Method mg <init> [_126]
L70:    aastore
L71:    iconst_0
L72:    iconst_1
L73:    dup
L74:    pop2
L75:    anewarray Uf
L78:    iconst_1
L79:    dup
L80:    pop2
L81:    invokespecial Method Te <init> [_88]
L84:    dup
L85:    getfield Field Te char Ljava/util/LinkedList;
L88:    aload_0
L89:    invokestatic Method java/util/Arrays asList ([Ljava/lang/Object;)Ljava/util/List;
L92:    invokevirtual Method java/util/LinkedList addAll (Ljava/util/Collection;)Z
L95:    pop
L96:    areturn
L97:    
    .end code
.end method

.method private static varargs speed : ([LTe;)LTe;
    .code stack 24 locals 1
L0:     new Te
L3:     dup
L4:     ldc_w "Speed"
L7:     ldc_w "Don't make Keanu sad. Always stay above 80 BPM."
L10:    ldc_w "bullock"
L13:    new Qb
L16:    dup
L17:    invokespecial Method Qb <init> ()V
L20:    iconst_0
L21:    iconst_1
L22:    dup
L23:    pop2
L24:    ldc_w 5e-1f
L27:    ldc 2147483647
L29:    iconst_1
L30:    dup
L31:    dup
L32:    pop2
L33:    anewarray Uf
L36:    iconst_1
L37:    dup
L38:    pop2
L39:    dup
L40:    iconst_0
L41:    iconst_1
L42:    dup
L43:    pop2
L44:    new mg
L47:    dup
L48:    aconst_null
L49:    dup
L50:    dup_x1
L51:    ldc 1.8e2f
L53:    iconst_1
L54:    dup
L55:    pop2
L56:    iconst_0
L57:    iconst_1
L58:    dup
L59:    pop2
L60:    iconst_0
L61:    iconst_1
L62:    dup_x2
L63:    dup
L64:    pop2
L65:    iconst_0
L66:    iconst_1
L67:    dup
L68:    pop2
L69:    invokespecial Method mg <init> [_126]
L72:    aastore
L73:    iconst_1
L74:    dup
L75:    dup
L76:    pop2
L77:    anewarray Uf
L80:    iconst_1
L81:    dup
L82:    pop2
L83:    dup
L84:    iconst_0
L85:    iconst_1
L86:    dup
L87:    pop2
L88:    new wf
L91:    dup
L92:    aconst_null
L93:    dup
L94:    dup_x1
L95:    bipush 80
L97:    iconst_1
L98:    dup
L99:    pop2
L100:   ldc_w 5e0f
L103:   iconst_0
L104:   iconst_1
L105:   dup
L106:   pop2
L107:   iconst_0
L108:   iconst_1
L109:   dup
L110:   pop2
L111:   invokespecial Method wf <init> (Ljava/lang/String;Ljava/lang/String;Ljava/lang/String;IFIZ)V
L114:   aastore
L115:   invokespecial Method Te <init> [_88]
L118:   dup
L119:   getfield Field Te char Ljava/util/LinkedList;
L122:   aload_0
L123:   invokestatic Method java/util/Arrays asList ([Ljava/lang/Object;)Ljava/util/List;
L126:   invokevirtual Method java/util/LinkedList addAll (Ljava/util/Collection;)Z
L129:   pop
L130:   areturn
L131:   
    .end code
.end method

.method private static varargs veyron : ([LTe;)LTe;
    .code stack 23 locals 1
L0:     new Te
L3:     dup
L4:     ldc_w "Veyron"
L7:     ldc_w "Win a 100 piece drag race."
L10:    ldc_w "bveyron"
L13:    new oe
L16:    dup
L17:    invokespecial Method oe <init> ()V
L20:    iconst_1
L21:    dup
L22:    pop2
L23:    ldc 3e-1f
L25:    ldc 2147483647
L27:    iconst_1
L28:    dup_x2
L29:    iconst_1
L30:    dup
L31:    pop2
L32:    anewarray Uf
L35:    iconst_1
L36:    dup
L37:    pop2
L38:    dup
L39:    iconst_0
L40:    iconst_1
L41:    dup
L42:    pop2
L43:    new ee
L46:    dup
L47:    aconst_null
L48:    dup
L49:    dup_x1
L50:    bipush 100
L52:    iconst_1
L53:    dup
L54:    pop2
L55:    iconst_0
L56:    iconst_1
L57:    dup
L58:    pop2
L59:    iconst_0
L60:    iconst_1
L61:    dup
L62:    pop2
L63:    invokespecial Method ee <init> [_85]
L66:    aastore
L67:    iconst_1
L68:    dup
L69:    dup
L70:    pop2
L71:    anewarray Uf
L74:    iconst_1
L75:    dup
L76:    pop2
L77:    dup
L78:    iconst_0
L79:    iconst_1
L80:    dup
L81:    pop2
L82:    new Ee
L85:    dup
L86:    aconst_null
L87:    dup
L88:    dup_x1
L89:    bipush 100
L91:    iconst_1
L92:    dup
L93:    pop2
L94:    iconst_0
L95:    iconst_1
L96:    dup
L97:    pop2
L98:    iconst_0
L99:    iconst_1
L100:   dup
L101:   pop2
L102:   invokespecial Method Ee <init> [_85]
L105:   aastore
L106:   invokespecial Method Te <init> [_88]
L109:   dup
L110:   getfield Field Te char Ljava/util/LinkedList;
L113:   aload_0
L114:   invokestatic Method java/util/Arrays asList ([Ljava/lang/Object;)Ljava/util/List;
L117:   invokevirtual Method java/util/LinkedList addAll (Ljava/util/Collection;)Z
L120:   pop
L121:   areturn
L122:   
    .end code
.end method
.innerclasses
    Bg [0] [0] static
    Ce [0] [0] static
    GE [0] [0] static
    HE [0] [0] static
    Jg [0] [0] static
    KG [0] [0] static
    Me [0] [0] static
    Pe [0] [0] static
    Qe [0] [0] static
    RE [0] [0] static
    Sg [0] [0] static
    WE [0] [0] static
    Xf [0] [0] static
    Yf [0] [0] static
    bG [0] [0] static
    ef [0] [0] static
    gF [0] [0] static
    gf [0] [0] static
    je [0] [0] static
    jf [0] [0] static
    jg [0] [0] static
    lf [0] [0] static
    oe [0] [0] static
    qg [0] [0] static
    rF [0] [0] static
    tE [0] [0] static
    yF [0] [0] static
.end innerclasses
.const [_85] = Utf8 (Ljava/lang/String;Ljava/lang/String;Ljava/lang/String;IIZ)V
.const [_88] = Utf8 (Ljava/lang/String;Ljava/lang/String;Ljava/lang/String;Leb;IFI[LUf;[LUf;)V
.const [_126] = Utf8 (Ljava/lang/String;Ljava/lang/String;Ljava/lang/String;FZZIZ)V
.end class
