.version 49 0
.class public final super tb
.super java/lang/Object
.implements java/lang/Runnable
.field public final synthetic field1693 Led;
.field public final synthetic field1694 LK;
.field public final synthetic field1695 Lab;

.method public run : ()V
    .code stack 3 locals 9
L0:     aload_0
L1:     getfield Field tb field1695 Lab;
L4:     getfield Field ab new Ljava/util/LinkedHashMap;
L7:     aload_0
L8:     getfield Field tb field1693 Led;
L11:    invokevirtual Method java/util/LinkedHashMap remove (Ljava/lang/Object;)Ljava/lang/Object;
L14:    checkcast Rg
L17:    astore_1
L18:    aload_0
L19:    getfield Field tb field1694 LK;
L22:    ifnull L35
L25:    aload_0
L26:    getfield Field tb field1694 LK;
L29:    aload_1
L30:    invokeinterface InterfaceMethod K method734 (Ljava/lang/Object;)V 2
L35:    new gC
L38:    dup
L39:    aload_0
L40:    getfield Field tb field1693 Led;
L43:    invokespecial Method gC <init> (Led;)V
L46:    astore_2
L47:    invokestatic Method mc values ()[Lmc;
L50:    dup
L51:    astore_3
L52:    arraylength
L53:    istore 4
L55:    iconst_0
L56:    iconst_1
L57:    dup
L58:    pop2
L59:    dup
L60:    istore 5
L62:    iload 4
L64:    if_icmpge L145
L67:    aload_3
L68:    iload 5
L70:    aaload
L71:    astore 6
L73:    aload_0
L74:    getfield Field tb field1695 Lab;
L77:    getfield Field ab field745 Ljava/util/Set;
L80:    invokeinterface InterfaceMethod java/util/Set iterator ()Ljava/util/Iterator; 1
L85:    astore 7
L87:    aload 7
L89:    invokeinterface InterfaceMethod java/util/Iterator hasNext ()Z 1
L94:    ifeq L136
L97:    aload 7
L99:    invokeinterface InterfaceMethod java/util/Iterator next ()Ljava/lang/Object; 1
L104:   checkcast Dc
L107:   dup
L108:   astore 8
L110:   getfield Field Dc field1794 Ljava/lang/Object;
L113:   aload 6
L115:   if_acmpne L87
L118:   aload 8
L120:   getfield Field Dc field1793 Ljava/lang/Object;
L123:   checkcast G
L126:   aload_2
L127:   invokeinterface InterfaceMethod G method8 (LD;)V 2
L132:   goto L87
L135:   athrow
L136:   iinc 5 1
L139:   iload 5
L141:   goto L62
L144:   athrow
L145:   return
L146:   
        .attribute StackMap b'\x00\x07\x00\x23\x00\x02\x07\x00\x02\x07\x00\x23\x00\x00\x00\x3E\x00\x06\x07\x00\x02\x07\x00\x23\x07\x00\x2D\x07\x00\x39\x01\x01\x00\x01\x01\x00\x57\x00\x08\x07\x00\x02\x07\x00\x23\x07\x00\x2D\x07\x00\x39\x01\x01\x07\x00\x33\x07\x00\x45\x00\x00\x00\x87\x00\x00\x00\x01\x07\x00\x5E\x00\x88\x00\x08\x07\x00\x02\x07\x00\x23\x07\x00\x2D\x07\x00\x39\x01\x01\x07\x00\x33\x07\x00\x45\x00\x00\x00\x90\x00\x00\x00\x01\x07\x00\x5E\x00\x91\x00\x06\x07\x00\x02\x07\x00\x23\x07\x00\x2D\x07\x00\x39\x01\x01\x00\x00'
    .end code
.end method

.method public <init> : (Lab;Led;LK;)V
    .code stack 7 locals 4
L0:     aload_3
L1:     aload_0
L2:     dup_x1
L3:     dup_x2
L4:     aload_2
L5:     aload_0
L6:     aload_1
L7:     putfield Field tb field1695 Lab;
L10:    putfield Field tb field1693 Led;
L13:    putfield Field tb field1694 LK;
L16:    invokespecial Method java/lang/Object <init> ()V
L19:    return
L20:    
    .end code
.end method
.innerclasses
    tb [0] [0]
.end innerclasses
.enclosing method ab method393 (Led;LK;)V
.end class
