.version 49 0
.class public final super tC
.super java/lang/Object
.implements java/lang/Runnable
.field public final synthetic field1650 Lob;
.field public final synthetic field1651 Ljava/net/Socket;

.method public <init> : (Lob;Ljava/net/Socket;)V
    .code stack 5 locals 3
L0:     aload_2
L1:     aload_0
L2:     dup_x1
L3:     dup_x2
L4:     aload_1
L5:     putfield Field tC field1650 Lob;
L8:     putfield Field tC field1651 Ljava/net/Socket;
L11:    invokespecial Method java/lang/Object <init> ()V
L14:    return
L15:    
    .end code
.end method

.method public run : ()V
    .code stack 11 locals 2
        .catch java/net/SocketException from L0 to L117 using L119
L0:     new wb
L3:     dup
L4:     aload_0
L5:     getfield Field tC field1650 Lob;
L8:     getfield Field ob field1673 LqC;
L11:    aload_0
L12:    getfield Field tC field1651 Ljava/net/Socket;
L15:    invokespecial Method wb <init> (Lbc;Ljava/net/Socket;)V
L18:    astore_1
L19:    aload_0
L20:    getfield Field tC field1650 Lob;
L23:    getfield Field ob field1673 LqC;
L26:    aload_1
L27:    getfield Field wb field5832 I
L30:    invokestatic Method qC method432 (LqC;I)I
L33:    aload_0
L34:    getfield Field tC field1650 Lob;
L37:    getfield Field ob field1673 LqC;
L40:    iconst_0
L41:    iconst_1
L42:    dup
L43:    pop2
L44:    invokestatic Method qC method437 (LqC;Z)Z
L47:    aload_0
L48:    dup_x2
L49:    getfield Field tC field1650 Lob;
L52:    getfield Field ob field1673 LqC;
L55:    aload_0
L56:    getfield Field tC field1650 Lob;
L59:    getfield Field ob field1673 LqC;
L62:    invokestatic Method qC method433 (LqC;)I
L65:    new aC
L68:    dup
L69:    ldc "cultrisIIrulez"
L71:    bipush 29
L73:    iconst_1
L74:    dup
L75:    pop2
L76:    invokespecial Method aC <init> (Ljava/lang/String;I)V
L79:    invokevirtual Method qC method431 (ILD;)V
L82:    pop2
L83:    getfield Field tC field1650 Lob;
L86:    getfield Field ob field1673 LqC;
L89:    new vC
L92:    dup
L93:    aload_0
L94:    getfield Field tC field1650 Lob;
L97:    getfield Field ob field1673 LqC;
L100:   aload_0
L101:   getfield Field tC field1650 Lob;
L104:   getfield Field ob field1673 LqC;
L107:   invokestatic Method qC method433 (LqC;)I
L110:   invokespecial Method vC <init> (Lbc;I)V
L113:   invokestatic Method qC method434 (LqC;LvC;)LvC;
L116:   pop
L117:   return
L118:   athrow
L119:   astore_1
L120:   aload_1
L121:   invokevirtual Method java/net/SocketException printStackTrace ()V
L124:   return
L125:   
        .attribute StackMap b'\x00\x02\x00\x76\x00\x00\x00\x01\x07\x00\x4A\x00\x77\x00\x01\x07\x00\x02\x00\x01\x07\x00\x19'
    .end code
.end method
.innerclasses
    ob [0] [0]
    tC [0] [0]
.end innerclasses
.enclosing method ob run ()V
.end class
