.version 49 0
.class public final super tD
.super Cd
.field public field86 Lqc;

.method public <init> : ()V
    .code stack 9 locals 1
L0:     aload_0
L1:     dup
L2:     new qc
L5:     aload_0
L6:     dup_x2
L7:     dup
L8:     pop2
L9:     dup
L10:    new fG
L13:    dup
L14:    getstatic Field LE field634 LLE;
L17:    ldc 1.5e-1f
L19:    invokespecial Method fG <init> (LLE;F)V
L22:    invokespecial Method qc <init> (Ld;)V
L25:    invokespecial Method Cd <init> (LgB;)V
L28:    getfield Field tD field85 LgB;
L31:    checkcast qc
L34:    putfield Field tD field86 Lqc;
L37:    return
L38:    
    .end code
.end method

.method public method96 : (Led;Lqd;LsE;Ljava/lang/String;)V
    .code stack 6 locals 5
L0:     aload_0
L1:     dup
L2:     aload_1
L3:     aload_2
L4:     aload_3
L5:     aload 4
L7:     invokevirtual Method tD method97 (Led;Lqd;LsE;Ljava/lang/String;)Lqc;
L10:    invokevirtual Method tD method100 (Lqc;)V
L13:    return
L14:    
    .end code
.end method

.method public method97 : (Led;Lqd;LsE;Ljava/lang/String;)Lqc;
    .code stack 9 locals 10
L0:     new qc
L3:     dup
L4:     new VD
L7:     dup
L8:     invokespecial Method VD <init> ()V
L11:    invokespecial Method qc <init> (Ld;)V
L14:    astore 5
L16:    aconst_null
L17:    astore 6
L19:    iconst_0
L20:    iconst_1
L21:    dup
L22:    pop2
L23:    istore 7
L25:    aload_1
L26:    ifnull L253
L29:    aload 4
L31:    invokevirtual Method java/lang/String toLowerCase ()Ljava/lang/String;
L34:    ldc "/me"
L36:    invokevirtual Method java/lang/String startsWith (Ljava/lang/String;)Z
L39:    istore 7
L41:    new DF
L44:    dup
L45:    new java/lang/StringBuilder
L48:    dup
L49:    invokespecial Method java/lang/StringBuilder <init> ()V
L52:    iconst_0
L53:    ldc " "
L55:    invokevirtual Method java/lang/StringBuilder insert (ILjava/lang/String;)Ljava/lang/StringBuilder;
L58:    aload_1
L59:    getfield Field ed field701 Ljava/lang/String;
L62:    invokevirtual Method java/lang/StringBuilder append (Ljava/lang/String;)Ljava/lang/StringBuilder;
L65:    iload 7
L67:    ifeq L76
L70:    ldc ""
L72:    goto L78
L75:    athrow
L76:    ldc ": "
L78:    invokevirtual Method java/lang/StringBuilder append (Ljava/lang/String;)Ljava/lang/StringBuilder;
L81:    invokevirtual Method java/lang/StringBuilder toString ()Ljava/lang/String;
L84:    iload 7
L86:    ifeq L96
L89:    getstatic Field We field476 LWe;
L92:    goto L99
L95:    athrow
L96:    getstatic Field We field491 LWe;
L99:    invokespecial Method DF <init> (Ljava/lang/String;LWe;)V
L102:   astore 6
L104:   new Rb
L107:   aload 6
L109:   dup_x1
L110:   dup
L111:   pop2
L112:   dup
L113:   aload_0
L114:   aload_1
L115:   aload_2
L116:   invokespecial Method Rb <init> (LtD;Led;Lqd;)V
L119:   invokevirtual Method DF method587 (Lh;)V
L122:   new qc
L125:   dup
L126:   new VD
L129:   dup
L130:   invokespecial Method VD <init> ()V
L133:   invokespecial Method qc <init> (Ld;)V
L136:   astore 8
L138:   iload 7
L140:   ifeq L148
L143:   ldc 2.3e-1f
L145:   goto L150
L148:   ldc 2.8e-1f
L150:   fstore 9
L152:   iload 7
L154:   aload 6
L156:   aload 8
L158:   dup_x1
L159:   new EG
L162:   aload 8
L164:   dup
L165:   pop2
L166:   dup
L167:   aload_1
L168:   getfield Field ed new Ljava/lang/String;
L171:   fload 9
L173:   dup
L174:   invokespecial Method EG <init> (Ljava/lang/String;FF)V
L177:   getstatic Field VD field149 Ljava/lang/Object;
L180:   invokevirtual Method qc method31 (LgB;Ljava/lang/Object;)V
L183:   getstatic Field VD field147 Ljava/lang/Object;
L186:   invokevirtual Method qc method31 (LgB;Ljava/lang/Object;)V
L189:   ifne L212
L192:   new Vg
L195:   aload 8
L197:   dup_x1
L198:   dup
L199:   pop2
L200:   dup
L201:   fconst_2
L202:   fconst_0
L203:   invokespecial Method Vg <init> (FF)V
L206:   getstatic Field VD field148 Ljava/lang/Object;
L209:   invokevirtual Method qc method31 (LgB;Ljava/lang/Object;)V
L212:   aload 8
L214:   new ac
L217:   dup
L218:   aload_0
L219:   aload_1
L220:   aload_2
L221:   invokespecial Method ac <init> (LtD;Led;Lqd;)V
L224:   invokevirtual Method qc method587 (Lh;)V
L227:   new SB
L230:   aload 5
L232:   dup_x1
L233:   dup
L234:   pop2
L235:   dup
L236:   aload 8
L238:   fconst_0
L239:   dup
L240:   dup_x1
L241:   getstatic Field FE field822 F
L244:   invokespecial Method SB <init> (LgB;FFFF)V
L247:   getstatic Field VD field149 Ljava/lang/Object;
L250:   invokevirtual Method qc method31 (LgB;Ljava/lang/Object;)V
L253:   new DF
L256:   dup
L257:   iload 7
L259:   aload 4
L261:   swap
L262:   ifeq L276
L265:   iconst_3
L266:   iconst_1
L267:   dup
L268:   pop2
L269:   invokevirtual Method java/lang/String substring (I)Ljava/lang/String;
L272:   aload_1
L273:   goto L277
L276:   aload_1
L277:   ifnull L285
L280:   iload 7
L282:   ifeq L291
L285:   getstatic Field We field476 LWe;
L288:   goto L294
L291:   getstatic Field We field472 LWe;
L294:   iconst_1
L295:   dup
L296:   dup
L297:   pop2
L298:   invokespecial Method DF <init> (Ljava/lang/String;LWe;Z)V
L301:   astore 8
L303:   aload_3
L304:   aload 5
L306:   aload 8
L308:   getstatic Field VD field147 Ljava/lang/Object;
L311:   invokevirtual Method qc method31 (LgB;Ljava/lang/Object;)V
L314:   ifnull L358
L317:   aload 6
L319:   ifnull L340
L322:   aload 6
L324:   aload_3
L325:   dup
L326:   getfield Field sE try F
L329:   swap
L330:   getfield Field sE field620 F
L333:   aload_3
L334:   getfield Field sE new F
L337:   invokevirtual Method DF method606 (FFF)V
L340:   aload 8
L342:   aload_3
L343:   dup
L344:   getfield Field sE try F
L347:   swap
L348:   getfield Field sE field620 F
L351:   aload_3
L352:   getfield Field sE new F
L355:   invokevirtual Method DF method606 (FFF)V
L358:   aload 5
L360:   areturn
L361:   
        .attribute StackMap b'\x00\x11\x00\x4B\x00\x00\x00\x01\x07\x00\x5B\x00\x4C\x00\x08\x07\x00\x02\x07\x00\x4F\x07\x00\x5D\x07\x00\x5F\x07\x00\x38\x07\x00\x14\x05\x01\x00\x03\x08\x00\x29\x08\x00\x29\x07\x00\x46\x00\x4E\x00\x08\x07\x00\x02\x07\x00\x4F\x07\x00\x5D\x07\x00\x5F\x07\x00\x38\x07\x00\x14\x05\x01\x00\x04\x08\x00\x29\x08\x00\x29\x07\x00\x46\x07\x00\x38\x00\x5F\x00\x00\x00\x01\x07\x00\x5B\x00\x60\x00\x08\x07\x00\x02\x07\x00\x4F\x07\x00\x5D\x07\x00\x5F\x07\x00\x38\x07\x00\x14\x05\x01\x00\x03\x08\x00\x29\x08\x00\x29\x07\x00\x38\x00\x63\x00\x08\x07\x00\x02\x07\x00\x4F\x07\x00\x5D\x07\x00\x5F\x07\x00\x38\x07\x00\x14\x05\x01\x00\x04\x08\x00\x29\x08\x00\x29\x07\x00\x38\x07\x00\x66\x00\x94\x00\x09\x07\x00\x02\x07\x00\x4F\x07\x00\x5D\x07\x00\x5F\x07\x00\x38\x07\x00\x14\x07\x00\x44\x01\x07\x00\x14\x00\x00\x00\x96\x00\x09\x07\x00\x02\x07\x00\x4F\x07\x00\x5D\x07\x00\x5F\x07\x00\x38\x07\x00\x14\x07\x00\x44\x01\x07\x00\x14\x00\x01\x02\x00\xD4\x00\x0A\x07\x00\x02\x07\x00\x4F\x07\x00\x5D\x07\x00\x5F\x07\x00\x38\x07\x00\x14\x07\x00\x44\x01\x07\x00\x14\x02\x00\x00\x00\xFD\x00\x08\x07\x00\x02\x07\x00\x4F\x07\x00\x5D\x07\x00\x5F\x07\x00\x38\x07\x00\x14\x07\x00\x44\x01\x00\x00\x01\x14\x00\x08\x07\x00\x02\x07\x00\x4F\x07\x00\x5D\x07\x00\x5F\x07\x00\x38\x07\x00\x14\x07\x00\x44\x01\x00\x03\x08\x00\xFD\x08\x00\xFD\x07\x00\x38\x01\x15\x00\x08\x07\x00\x02\x07\x00\x4F\x07\x00\x5D\x07\x00\x5F\x07\x00\x38\x07\x00\x14\x07\x00\x44\x01\x00\x04\x08\x00\xFD\x08\x00\xFD\x07\x00\x38\x07\x00\x4F\x01\x1D\x00\x08\x07\x00\x02\x07\x00\x4F\x07\x00\x5D\x07\x00\x5F\x07\x00\x38\x07\x00\x14\x07\x00\x44\x01\x00\x03\x08\x00\xFD\x08\x00\xFD\x07\x00\x38\x01\x23\x00\x08\x07\x00\x02\x07\x00\x4F\x07\x00\x5D\x07\x00\x5F\x07\x00\x38\x07\x00\x14\x07\x00\x44\x01\x00\x03\x08\x00\xFD\x08\x00\xFD\x07\x00\x38\x01\x26\x00\x08\x07\x00\x02\x07\x00\x4F\x07\x00\x5D\x07\x00\x5F\x07\x00\x38\x07\x00\x14\x07\x00\x44\x01\x00\x04\x08\x00\xFD\x08\x00\xFD\x07\x00\x38\x07\x00\x66\x01\x54\x00\x09\x07\x00\x02\x07\x00\x4F\x07\x00\x5D\x07\x00\x5F\x07\x00\x38\x07\x00\x14\x07\x00\x44\x01\x07\x00\x44\x00\x00\x01\x66\x00\x09\x07\x00\x02\x07\x00\x4F\x07\x00\x5D\x07\x00\x5F\x07\x00\x38\x07\x00\x14\x07\x00\x44\x01\x07\x00\x44\x00\x00'
    .end code
.end method

.method public static synthetic method98 : (LtD;)LFE;
    .code stack 1 locals 1
L0:     aload_0
L1:     getfield Field tD field1136 LFE;
L4:     areturn
L5:     
    .end code
.end method

.method public static synthetic method99 : (LtD;)LFE;
    .code stack 1 locals 1
L0:     aload_0
L1:     getfield Field tD field1136 LFE;
L4:     areturn
L5:     
    .end code
.end method

.method public method24 : (LgB;)V
    .code stack 0 locals 2
L0:     return
L1:     
    .end code
.end method

.method public method29 : ()V
    .code stack 2 locals 1
L0:     aload_0
L1:     dup
L2:     invokespecial Method Cd method29 ()V
L5:     invokevirtual Method tD method74 ()V
L8:     return
L9:     
    .end code
.end method

.method public method100 : (Lqc;)V
    .code stack 5 locals 3
L0:     aload_0
L1:     invokevirtual Method tD method92 ()Z
L4:     ifne L14
L7:     aload_0
L8:     invokevirtual Method tD method94 ()Z
L11:    ifne L22
L14:    iconst_1
L15:    dup
L16:    dup
L17:    pop2
L18:    goto L26
L21:    athrow
L22:    iconst_0
L23:    iconst_1
L24:    dup
L25:    pop2
L26:    istore_2
L27:    aload_0
L28:    getfield Field tD field86 Lqc;
L31:    getfield Field qc field65 Ljava/util/ArrayList;
L34:    invokevirtual Method java/util/ArrayList size ()I
L37:    bipush 80
L39:    iconst_1
L40:    dup
L41:    pop2
L42:    if_icmple L75
L45:    aload_0
L46:    dup
L47:    getfield Field tD field86 Lqc;
L50:    swap
L51:    getfield Field tD field86 Lqc;
L54:    getfield Field qc field65 Ljava/util/ArrayList;
L57:    iconst_0
L58:    iconst_1
L59:    dup
L60:    pop2
L61:    invokevirtual Method java/util/ArrayList get (I)Ljava/lang/Object;
L64:    checkcast gB
L67:    invokevirtual Method qc method23 (LgB;)V
L70:    aload_0
L71:    goto L28
L74:    athrow
L75:    aload_0
L76:    getfield Field tD field86 Lqc;
L79:    aload_1
L80:    getstatic Field dg field337 Ldg;
L83:    invokevirtual Method qc method31 (LgB;Ljava/lang/Object;)V
L86:    iload_2
L87:    ifeq L98
L90:    aload_0
L91:    iconst_1
L92:    dup
L93:    dup
L94:    pop2
L95:    invokevirtual Method tD method95 (Z)V
L98:    return
L99:    
        .attribute StackMap b'\x00\x08\x00\x0E\x00\x02\x07\x00\x02\x07\x00\x14\x00\x00\x00\x15\x00\x00\x00\x01\x07\x00\x5B\x00\x16\x00\x02\x07\x00\x02\x07\x00\x14\x00\x00\x00\x1A\x00\x02\x07\x00\x02\x07\x00\x14\x00\x01\x01\x00\x1C\x00\x03\x07\x00\x02\x07\x00\x14\x01\x00\x01\x07\x00\x02\x00\x4A\x00\x00\x00\x01\x07\x00\x5B\x00\x4B\x00\x03\x07\x00\x02\x07\x00\x14\x01\x00\x00\x00\x62\x00\x03\x07\x00\x02\x07\x00\x14\x01\x00\x00'
    .end code
.end method
.innerclasses
    LE fG [0] public static final enum
    Rb [0] [0]
    ac [0] [0]
    dg fG [0] public static final enum
.end innerclasses
.end class
