.version 49 0
.class public super Te
.super java/lang/Object
.field public field2105 I
.field private field2106 D
.field public true Ljava/lang/String;
.field public field2107 Z
.field public field2108 Leb;
.field public field2109 Z
.field public field2110 I
.field public field2111 LfE;
.field public field2112 Ljava/lang/String;
.field public field2113 Z
.field public field2114 [LUf;
.field public field2115 Ljava/util/List;
.field public static field2116 Ljava/util/Map;
.field public try Ljava/util/List;
.field public field2117 Ljava/lang/String;
.field public new F
.field public field2118 LfE;
.field public static this Ljava/util/Map;
.field public field2119 Ljava/util/LinkedList;
.field public field2120 Z
.field private field2121 Ljava/util/Map;
.field public field2122 Z

.method public method1049 : (Ljava/lang/Class;)Z
    .code stack 2 locals 2
L0:     aload_0
L1:     getfield Field Te field2121 Ljava/util/Map;
L4:     aload_1
L5:     invokeinterface InterfaceMethod java/util/Map containsKey (Ljava/lang/Object;)Z 2
L10:    ireturn
L11:    
    .end code
.end method

.method public method1050 : (LPc;)V
    .code stack 4 locals 2
L0:     aload_0
L1:     aload_1
L2:     invokevirtual Method Te method1057 (LPc;)Z
L5:     ifeq L10
L8:     return
L9:     athrow
L10:    getstatic Field Te field2116 Ljava/util/Map;
L13:    aload_1
L14:    aload_0
L15:    invokeinterface InterfaceMethod java/util/Map put (Ljava/lang/Object;Ljava/lang/Object;)Ljava/lang/Object; 3
L20:    new java/lang/StringBuilder
L23:    dup
L24:    invokespecial Method java/lang/StringBuilder <init> ()V
L27:    iconst_0
L28:    aload_1
L29:    getfield Field Pc field370 Ljava/lang/String;
L32:    invokevirtual Method java/lang/StringBuilder insert (ILjava/lang/String;)Ljava/lang/StringBuilder;
L35:    ldc "mc"
L37:    invokevirtual Method java/lang/StringBuilder append (Ljava/lang/String;)Ljava/lang/StringBuilder;
L40:    invokevirtual Method java/lang/StringBuilder toString ()Ljava/lang/String;
L43:    aload_0
L44:    getfield Field Te field2117 Ljava/lang/String;
L47:    invokestatic Method JB method835 (Ljava/lang/String;Ljava/lang/String;)V
L50:    pop
L51:    return
L52:    
        .attribute StackMap b'\x00\x02\x00\x09\x00\x00\x00\x01\x07\x00\x3B\x00\x0A\x00\x02\x07\x00\x02\x07\x00\x06\x00\x00'
    .end code
.end method

.method public method1051 : (Ljava/lang/Class;)Ljava/util/List;
    .code stack 2 locals 2
L0:     aload_0
L1:     getfield Field Te field2121 Ljava/util/Map;
L4:     aload_1
L5:     invokeinterface InterfaceMethod java/util/Map get (Ljava/lang/Object;)Ljava/lang/Object; 2
L10:    checkcast java/util/List
L13:    dup
L14:    astore_1
L15:    ifnull L21
L18:    aload_1
L19:    areturn
L20:    athrow
L21:    new java/util/LinkedList
L24:    dup
L25:    invokespecial Method java/util/LinkedList <init> ()V
L28:    areturn
L29:    
        .attribute StackMap b'\x00\x02\x00\x14\x00\x00\x00\x01\x07\x00\x3B\x00\x15\x00\x02\x07\x00\x02\x07\x00\x66\x00\x00'
    .end code
.end method

.method public final method1052 : ()V
    .code stack 4 locals 1
L0:     new java/lang/StringBuilder
L3:     dup
L4:     invokespecial Method java/lang/StringBuilder <init> ()V
L7:     iconst_0
L8:     ldc "chg|w|"
L10:    invokevirtual Method java/lang/StringBuilder insert (ILjava/lang/String;)Ljava/lang/StringBuilder;
L13:    aload_0
L14:    getfield Field Te field2117 Ljava/lang/String;
L17:    invokevirtual Method java/lang/StringBuilder append (Ljava/lang/String;)Ljava/lang/StringBuilder;
L20:    invokevirtual Method java/lang/StringBuilder toString ()Ljava/lang/String;
L23:    iconst_1
L24:    dup
L25:    dup
L26:    pop2
L27:    invokestatic Method JB method824 (Ljava/lang/String;I)V
L30:    return
L31:    
    .end code
.end method

.method public method1053 : (LPc;)Z
    .code stack 3 locals 2
L0:     aload_0
L1:     getfield Field Te field2109 Z
L4:     ifne L15
L7:     aload_0
L8:     aload_1
L9:     invokevirtual Method Te method1059 (LPc;)Z
L12:    ifeq L21
L15:    iconst_1
L16:    dup
L17:    dup
L18:    pop2
L19:    ireturn
L20:    athrow
L21:    iconst_0
L22:    iconst_1
L23:    dup
L24:    pop2
L25:    ireturn
L26:    
        .attribute StackMap b'\x00\x03\x00\x0F\x00\x02\x07\x00\x02\x07\x00\x06\x00\x00\x00\x14\x00\x00\x00\x01\x07\x00\x3B\x00\x15\x00\x02\x07\x00\x02\x07\x00\x06\x00\x00'
    .end code
.end method

.method public method1054 : (LRg;)V
    .code stack 8 locals 4
L0:     aload_0
L1:     dup
L2:     iconst_0
L3:     aload_0
L4:     dup_x2
L5:     iconst_0
L6:     iconst_1
L7:     dup
L8:     pop2
L9:     putfield Field Te field2122 Z
L12:    iconst_1
L13:    dup
L14:    pop2
L15:    putfield Field Te field2113 Z
L18:    getfield Field Te field2115 Ljava/util/List;
L21:    invokeinterface InterfaceMethod java/util/List clear ()V 1
L26:    getfield Field Te try Ljava/util/List;
L29:    invokeinterface InterfaceMethod java/util/List iterator ()Ljava/util/Iterator; 1
L34:    astore_2
L35:    aload_2
L36:    invokeinterface InterfaceMethod java/util/Iterator hasNext ()Z 1
L41:    ifeq L90
L44:    aload_2
L45:    invokeinterface InterfaceMethod java/util/Iterator next ()Ljava/lang/Object; 1
L50:    checkcast Uf
L53:    astore_3
L54:    aload_0
L55:    aload_3
L56:    aload_1
L57:    invokevirtual Method Uf method703 (LRg;)V
L60:    getfield Field Te field2114 [LUf;
L63:    invokestatic Method java/util/Arrays asList ([Ljava/lang/Object;)Ljava/util/List;
L66:    aload_3
L67:    invokeinterface InterfaceMethod java/util/List contains (Ljava/lang/Object;)Z 2
L72:    ifne L35
L75:    aload_0
L76:    getfield Field Te field2115 Ljava/util/List;
L79:    aload_3
L80:    invokeinterface InterfaceMethod java/util/List add (Ljava/lang/Object;)Z 2
L85:    pop
L86:    goto L35
L89:    athrow
L90:    aload_1
L91:    new java/util/LinkedList
L94:    dup
L95:    aload_0
L96:    getfield Field Te try Ljava/util/List;
L99:    invokespecial Method java/util/LinkedList <init> (Ljava/util/Collection;)V
L102:   invokevirtual Method Rg method27 (Ljava/util/List;)V
L105:   return
L106:   
        .attribute StackMap b'\x00\x03\x00\x23\x00\x03\x07\x00\x02\x07\x00\x89\x07\x00\x8B\x00\x00\x00\x59\x00\x00\x00\x01\x07\x00\x3B\x00\x5A\x00\x03\x07\x00\x02\x07\x00\x89\x07\x00\x8B\x00\x00'
    .end code
.end method

.method public final method1055 : ()V
    .code stack 9 locals 1
L0:     aload_0
L1:     getfield Field Te field2106 D
L4:     dconst_0
L5:     dcmpl
L6:     ifne L11
L9:     return
L10:    athrow
L11:    aload_0
L12:    dconst_0
L13:    iconst_0
L14:    aload_0
L15:    dup_x1
L16:    iconst_0
L17:    iconst_1
L18:    dup
L19:    pop2
L20:    putfield Field Te field2122 Z
L23:    iconst_1
L24:    dup
L25:    pop2
L26:    putfield Field Te field2113 Z
L29:    new java/lang/StringBuilder
L32:    dup
L33:    invokespecial Method java/lang/StringBuilder <init> ()V
L36:    iconst_0
L37:    ldc "chg|s|"
L39:    invokevirtual Method java/lang/StringBuilder insert (ILjava/lang/String;)Ljava/lang/StringBuilder;
L42:    aload_0
L43:    getfield Field Te field2117 Ljava/lang/String;
L46:    invokevirtual Method java/lang/StringBuilder append (Ljava/lang/String;)Ljava/lang/StringBuilder;
L49:    invokevirtual Method java/lang/StringBuilder toString ()Ljava/lang/String;
L52:    ldc2_w 5e-1
L55:    invokestatic Method OC method1015 ()D
L58:    dadd
L59:    aload_0
L60:    getfield Field Te field2106 D
L63:    dsub
L64:    d2i
L65:    invokestatic Method JB method824 (Ljava/lang/String;I)V
L68:    putfield Field Te field2106 D
L71:    return
L72:    
        .attribute StackMap b'\x00\x02\x00\x0A\x00\x00\x00\x01\x07\x00\x3B\x00\x0B\x00\x01\x07\x00\x02\x00\x00'
    .end code
.end method

.method public <init> : (Ljava/lang/String;Ljava/lang/String;Ljava/lang/String;Leb;IFI[LUf;[LUf;)V
    .code stack 26 locals 10
L0:     aload 8
L2:     aload_0
L3:     dup
L4:     iconst_1
L5:     aload_0
L6:     dup_x2
L7:     aload 9
L9:     fload 6
L11:    aload_0
L12:    dup_x1
L13:    dup_x2
L14:    iload 5
L16:    iload 7
L18:    aload_0
L19:    dup_x1
L20:    aload 4
L22:    aload_3
L23:    aload_0
L24:    dup_x1
L25:    dup_x2
L26:    aload_2
L27:    aload_1
L28:    aload_0
L29:    dup
L30:    dup_x2
L31:    aload_0
L32:    invokespecial Method java/lang/Object <init> ()V
L35:    getstatic Field fE new LfE;
L38:    putfield Field Te field2111 LfE;
L41:    getstatic Field fE field415 LfE;
L44:    putfield Field Te field2118 LfE;
L47:    putfield Field Te true Ljava/lang/String;
L50:    putfield Field Te field2112 Ljava/lang/String;
L53:    putfield Field Te field2117 Ljava/lang/String;
L56:    new java/util/LinkedList
L59:    aload_0
L60:    dup
L61:    pop2
L62:    dup
L63:    invokespecial Method java/util/LinkedList <init> ()V
L66:    putfield Field Te field2119 Ljava/util/LinkedList;
L69:    putfield Field Te field2108 Leb;
L72:    putfield Field Te field2110 I
L75:    putfield Field Te field2105 I
L78:    putfield Field Te new F
L81:    new java/util/concurrent/CopyOnWriteArrayList
L84:    aload_0
L85:    dup
L86:    pop2
L87:    dup
L88:    invokespecial Method java/util/concurrent/CopyOnWriteArrayList <init> ()V
L91:    putfield Field Te field2115 Ljava/util/List;
L94:    putfield Field Te field2114 [LUf;
L97:    iconst_1
L98:    dup
L99:    pop2
L100:   putfield Field Te field2109 Z
L103:   getstatic Field fE new LfE;
L106:   putfield Field Te field2111 LfE;
L109:   getstatic Field fE field415 LfE;
L112:   putfield Field Te field2118 LfE;
L115:   dup
L116:   astore_1
L117:   arraylength
L118:   istore_2
L119:   iconst_0
L120:   iconst_1
L121:   dup
L122:   pop2
L123:   dup
L124:   istore_3
L125:   iload_2
L126:   if_icmpge L154
L129:   aload_1
L130:   iload_3
L131:   iinc 3 1
L134:   aaload
L135:   astore 4
L137:   aload_0
L138:   getfield Field Te field2115 Ljava/util/List;
L141:   aload 4
L143:   invokeinterface InterfaceMethod java/util/List add (Ljava/lang/Object;)Z 2
L148:   pop
L149:   iload_3
L150:   goto L125
L153:   athrow
L154:   aload_0
L155:   dup
L156:   new java/util/LinkedList
L159:   dup
L160:   invokespecial Method java/util/LinkedList <init> ()V
L163:   putfield Field Te try Ljava/util/List;
L166:   new java/util/HashMap
L169:   aload_0
L170:   dup
L171:   pop2
L172:   dup
L173:   invokespecial Method java/util/HashMap <init> ()V
L176:   putfield Field Te field2121 Ljava/util/Map;
L179:   iconst_2
L180:   iconst_1
L181:   dup
L182:   pop2
L183:   anewarray [LUf;
L186:   iconst_1
L187:   dup
L188:   pop2
L189:   dup
L190:   iconst_0
L191:   iconst_1
L192:   dup
L193:   pop2
L194:   aload 8
L196:   aastore
L197:   dup
L198:   iconst_1
L199:   dup
L200:   dup
L201:   pop2
L202:   aload 9
L204:   aastore
L205:   dup
L206:   astore_1
L207:   arraylength
L208:   istore_2
L209:   iconst_0
L210:   iconst_1
L211:   dup
L212:   pop2
L213:   dup
L214:   istore_3
L215:   iload_2
L216:   if_icmpge L343
L219:   aload_1
L220:   iload_3
L221:   aaload
L222:   dup
L223:   astore 4
L225:   astore 5
L227:   aload 5
L229:   arraylength
L230:   istore 6
L232:   iconst_0
L233:   iconst_1
L234:   dup
L235:   pop2
L236:   dup
L237:   istore 7
L239:   iload 6
L241:   if_icmpge L336
L244:   aload 5
L246:   iload 7
L248:   aaload
L249:   astore 8
L251:   aload_0
L252:   dup
L253:   getfield Field Te try Ljava/util/List;
L256:   aload 8
L258:   invokeinterface InterfaceMethod java/util/List add (Ljava/lang/Object;)Z 2
L263:   pop
L264:   getfield Field Te field2121 Ljava/util/Map;
L267:   aload 8
L269:   invokevirtual Method java/lang/Object getClass ()Ljava/lang/Class;
L272:   invokeinterface InterfaceMethod java/util/Map get (Ljava/lang/Object;)Ljava/lang/Object; 2
L277:   ifnonnull L302
L280:   aload_0
L281:   getfield Field Te field2121 Ljava/util/Map;
L284:   aload 8
L286:   invokevirtual Method java/lang/Object getClass ()Ljava/lang/Class;
L289:   new java/util/LinkedList
L292:   dup
L293:   invokespecial Method java/util/LinkedList <init> ()V
L296:   invokeinterface InterfaceMethod java/util/Map put (Ljava/lang/Object;Ljava/lang/Object;)Ljava/lang/Object; 3
L301:   pop
L302:   aload_0
L303:   getfield Field Te field2121 Ljava/util/Map;
L306:   aload 8
L308:   invokevirtual Method java/lang/Object getClass ()Ljava/lang/Class;
L311:   invokeinterface InterfaceMethod java/util/Map get (Ljava/lang/Object;)Ljava/lang/Object; 2
L316:   iinc 7 1
L319:   checkcast java/util/List
L322:   aload 8
L324:   invokeinterface InterfaceMethod java/util/List add (Ljava/lang/Object;)Z 2
L329:   pop
L330:   iload 7
L332:   goto L239
L335:   athrow
L336:   iinc 3 1
L339:   iload_3
L340:   goto L215
L343:   aload_0
L344:   iconst_1
L345:   iconst_0
L346:   aload_0
L347:   dup_x1
L348:   iconst_0
L349:   iconst_1
L350:   dup
L351:   pop2
L352:   putfield Field Te field2122 Z
L355:   iconst_1
L356:   dup
L357:   pop2
L358:   putfield Field Te field2113 Z
L361:   iconst_1
L362:   dup
L363:   pop2
L364:   putfield Field Te field2107 Z
L367:   return
L368:   
        .attribute StackMap b'\x00\x09\x00\x7D\x00\x0A\x07\x00\x02\x07\x00\xD9\x01\x01\x07\x00\x04\x01\x02\x01\x07\x00\xD9\x07\x00\xD9\x00\x01\x01\x00\x99\x00\x00\x00\x01\x07\x00\x3B\x00\x9A\x00\x0A\x07\x00\x02\x07\x00\xD9\x01\x01\x07\x00\x04\x01\x02\x01\x07\x00\xD9\x07\x00\xD9\x00\x00\x00\xD7\x00\x0A\x07\x00\x02\x07\x00\xDE\x01\x01\x07\x00\x04\x00\x00\x01\x07\x00\x04\x07\x00\xD9\x00\x01\x01\x00\xEF\x00\x0A\x07\x00\x02\x07\x00\xDE\x01\x01\x07\x00\xD9\x07\x00\xD9\x01\x01\x07\x00\x04\x07\x00\xD9\x00\x01\x01\x01\x2E\x00\x0A\x07\x00\x02\x07\x00\xDE\x01\x01\x07\x00\xD9\x07\x00\xD9\x01\x01\x07\x00\x95\x07\x00\xD9\x00\x00\x01\x4F\x00\x00\x00\x01\x07\x00\x3B\x01\x50\x00\x0A\x07\x00\x02\x07\x00\xDE\x01\x01\x07\x00\xD9\x07\x00\xD9\x01\x01\x07\x00\x04\x07\x00\xD9\x00\x00\x01\x57\x00\x0A\x07\x00\x02\x07\x00\xDE\x01\x01\x07\x00\x04\x00\x00\x01\x07\x00\x04\x07\x00\xD9\x00\x00'
    .end code
.end method

.method public final method1056 : ()V
    .code stack 4 locals 1
L0:     new java/lang/StringBuilder
L3:     dup
L4:     invokespecial Method java/lang/StringBuilder <init> ()V
L7:     iconst_0
L8:     ldc "chg|t|"
L10:    invokevirtual Method java/lang/StringBuilder insert (ILjava/lang/String;)Ljava/lang/StringBuilder;
L13:    aload_0
L14:    getfield Field Te field2117 Ljava/lang/String;
L17:    invokevirtual Method java/lang/StringBuilder append (Ljava/lang/String;)Ljava/lang/StringBuilder;
L20:    invokevirtual Method java/lang/StringBuilder toString ()Ljava/lang/String;
L23:    iconst_1
L24:    dup
L25:    dup
L26:    pop2
L27:    invokestatic Method JB method824 (Ljava/lang/String;I)V
L30:    return
L31:    
    .end code
.end method

.method public static <clinit> : ()V
    .code stack 2 locals 0
L0:     new java/util/HashMap
L3:     dup
L4:     invokespecial Method java/util/HashMap <init> ()V
L7:     putstatic Field Te field2116 Ljava/util/Map;
L10:    new java/util/HashMap
L13:    dup
L14:    invokespecial Method java/util/HashMap <init> ()V
L17:    putstatic Field Te this Ljava/util/Map;
L20:    return
L21:    
    .end code
.end method

.method public <init> : (Ljava/lang/String;Ljava/lang/String;Ljava/lang/String;Leb;IFI[LUf;[LUf;LfE;LfE;Z)V
    .code stack 16 locals 13
L0:     iload 12
L2:     aload_0
L3:     dup_x1
L4:     aload 11
L6:     aload 10
L8:     aload_0
L9:     dup_x1
L10:    aload_1
L11:    aload_2
L12:    aload_3
L13:    aload 4
L15:    iload 5
L17:    fload 6
L19:    iload 7
L21:    aload 8
L23:    aload 9
L25:    invokespecial Method Te <init> (Ljava/lang/String;Ljava/lang/String;Ljava/lang/String;Leb;IFI[LUf;[LUf;)V
L28:    putfield Field Te field2111 LfE;
L31:    putfield Field Te field2118 LfE;
L34:    putfield Field Te field2107 Z
L37:    return
L38:    
    .end code
.end method

.method public method1057 : (LPc;)Z
    .code stack 3 locals 2
L0:     new java/lang/StringBuilder
L3:     dup
L4:     invokespecial Method java/lang/StringBuilder <init> ()V
L7:     iconst_0
L8:     aload_1
L9:     getfield Field Pc field370 Ljava/lang/String;
L12:    invokevirtual Method java/lang/StringBuilder insert (ILjava/lang/String;)Ljava/lang/StringBuilder;
L15:    ldc "mc"
L17:    invokevirtual Method java/lang/StringBuilder append (Ljava/lang/String;)Ljava/lang/StringBuilder;
L20:    invokevirtual Method java/lang/StringBuilder toString ()Ljava/lang/String;
L23:    aload_0
L24:    getfield Field Te field2117 Ljava/lang/String;
L27:    invokestatic Method JB method832 (Ljava/lang/String;Ljava/lang/String;)Z
L30:    ireturn
L31:    
    .end code
.end method

.method public final method1058 : ()V
    .code stack 3 locals 1
L0:     aload_0
L1:     invokestatic Method OC method1015 ()D
L4:     putfield Field Te field2106 D
L7:     return
L8:     
    .end code
.end method

.method public method1059 : (LPc;)Z
    .code stack 3 locals 4
L0:     aload_0
L1:     getfield Field Te field2119 Ljava/util/LinkedList;
L4:     invokevirtual Method java/util/LinkedList isEmpty ()Z
L7:     ifeq L16
L10:    iconst_1
L11:    dup
L12:    dup
L13:    pop2
L14:    ireturn
L15:    athrow
L16:    aload_0
L17:    getfield Field Te field2119 Ljava/util/LinkedList;
L20:    invokevirtual Method java/util/LinkedList iterator ()Ljava/util/Iterator;
L23:    astore_2
L24:    aload_2
L25:    invokeinterface InterfaceMethod java/util/Iterator hasNext ()Z 1
L30:    ifeq L68
L33:    aload_2
L34:    invokeinterface InterfaceMethod java/util/Iterator next ()Ljava/lang/Object; 1
L39:    checkcast Te
L42:    dup
L43:    astore_3
L44:    aload_1
L45:    invokevirtual Method Te method1057 (LPc;)Z
L48:    ifeq L59
L51:    aload_3
L52:    aload_1
L53:    invokevirtual Method Te method1059 (LPc;)Z
L56:    ifne L24
L59:    iconst_0
L60:    iconst_1
L61:    dup
L62:    pop2
L63:    ireturn
L64:    nop
L65:    nop
L66:    nop
L67:    athrow
L68:    iconst_1
L69:    dup
L70:    dup
L71:    pop2
L72:    ireturn
L73:    
        .attribute StackMap b'\x00\x06\x00\x0F\x00\x00\x00\x01\x07\x00\x3B\x00\x10\x00\x02\x07\x00\x02\x07\x00\x06\x00\x00\x00\x18\x00\x03\x07\x00\x02\x07\x00\x06\x07\x00\x8B\x00\x00\x00\x3B\x00\x04\x07\x00\x02\x07\x00\x06\x07\x00\x8B\x07\x00\x02\x00\x00\x00\x40\x00\x00\x00\x01\x07\x00\x3B\x00\x44\x00\x03\x07\x00\x02\x07\x00\x06\x07\x00\x8B\x00\x00'
    .end code
.end method

.method public method1060 : (LRg;)V
    .code stack 0 locals 2
L0:     return
L1:     
    .end code
.end method

.method public method1061 : (LRg;)V
    .code stack 4 locals 5
L0:     aload_0
L1:     getfield Field Te field2122 Z
L4:     ifne L14
L7:     aload_0
L8:     getfield Field Te field2113 Z
L11:    ifeq L16
L14:    return
L15:    athrow
L16:    aload_0
L17:    getfield Field Te field2114 [LUf;
L20:    dup
L21:    astore_2
L22:    arraylength
L23:    istore_3
L24:    iconst_0
L25:    iconst_1
L26:    dup
L27:    pop2
L28:    dup
L29:    istore 4
L31:    iload_3
L32:    if_icmpge L64
L35:    aload_2
L36:    iload 4
L38:    aaload
L39:    aload_1
L40:    invokevirtual Method Uf method704 (LRg;)Z
L43:    ifeq L56
L46:    aload_0
L47:    iconst_1
L48:    dup
L49:    dup
L50:    pop2
L51:    putfield Field Te field2113 Z
L54:    return
L55:    athrow
L56:    iinc 4 1
L59:    iload 4
L61:    goto L31
L64:    aload_0
L65:    getfield Field Te field2115 Ljava/util/List;
L68:    invokeinterface InterfaceMethod java/util/List iterator ()Ljava/util/Iterator; 1
L73:    astore_2
L74:    aload_2
L75:    invokeinterface InterfaceMethod java/util/Iterator hasNext ()Z 1
L80:    ifeq L130
L83:    aload_2
L84:    invokeinterface InterfaceMethod java/util/Iterator next ()Ljava/lang/Object; 1
L89:    checkcast Uf
L92:    dup
L93:    astore_3
L94:    aload_1
L95:    invokevirtual Method Uf method704 (LRg;)Z
L98:    ifeq L74
L101:   aload_0
L102:   dup
L103:   getfield Field Te field2115 Ljava/util/List;
L106:   aload_3
L107:   invokeinterface InterfaceMethod java/util/List remove (Ljava/lang/Object;)Z 2
L112:   pop
L113:   getfield Field Te field2107 Z
L116:   ifne L74
L119:   aload_0
L120:   iconst_1
L121:   dup
L122:   dup
L123:   pop2
L124:   putfield Field Te field2122 Z
L127:   goto L74
L130:   aload_0
L131:   dup
L132:   dup
L133:   getfield Field Te field2122 Z
L136:   aload_0
L137:   getfield Field Te field2115 Ljava/util/List;
L140:   invokeinterface InterfaceMethod java/util/List isEmpty ()Z 1
L145:   ior
L146:   putfield Field Te field2122 Z
L149:   getfield Field Te field2122 Z
L152:   ifeq L160
L155:   aload_0
L156:   aload_1
L157:   invokevirtual Method Te method1060 (LRg;)V
L160:   return
L161:   
        .attribute StackMap b'\x00\x0A\x00\x0E\x00\x02\x07\x00\x02\x07\x00\x89\x00\x00\x00\x0F\x00\x00\x00\x01\x07\x00\x3B\x00\x10\x00\x02\x07\x00\x02\x07\x00\x89\x00\x00\x00\x1F\x00\x05\x07\x00\x02\x07\x00\x89\x07\x00\xD9\x01\x01\x00\x01\x01\x00\x37\x00\x00\x00\x01\x07\x00\x3B\x00\x38\x00\x05\x07\x00\x02\x07\x00\x89\x07\x00\xD9\x01\x01\x00\x00\x00\x40\x00\x05\x07\x00\x02\x07\x00\x89\x07\x00\xD9\x01\x01\x00\x00\x00\x4A\x00\x05\x07\x00\x02\x07\x00\x89\x07\x00\x8B\x00\x01\x00\x00\x00\x82\x00\x05\x07\x00\x02\x07\x00\x89\x07\x00\x8B\x00\x01\x00\x00\x00\xA0\x00\x05\x07\x00\x02\x07\x00\x89\x07\x00\x8B\x00\x01\x00\x00'
    .end code
.end method

.method public method1062 : (LRg;LUf;)V
    .code stack 4 locals 7
L0:     aload_0
L1:     getfield Field Te field2122 Z
L4:     ifne L14
L7:     aload_0
L8:     getfield Field Te field2113 Z
L11:    ifeq L16
L14:    return
L15:    athrow
L16:    aload_0
L17:    getfield Field Te field2114 [LUf;
L20:    dup
L21:    astore_3
L22:    arraylength
L23:    istore 4
L25:    iconst_0
L26:    iconst_1
L27:    dup
L28:    pop2
L29:    dup
L30:    istore 5
L32:    iload 4
L34:    if_icmpge L67
L37:    aload_3
L38:    iload 5
L40:    aaload
L41:    astore 6
L43:    aload_2
L44:    aload 6
L46:    if_acmpne L59
L49:    aload_0
L50:    iconst_1
L51:    dup
L52:    dup
L53:    pop2
L54:    putfield Field Te field2113 Z
L57:    return
L58:    athrow
L59:    iinc 5 1
L62:    iload 5
L64:    goto L32
L67:    aload_0
L68:    dup
L69:    getfield Field Te field2115 Ljava/util/List;
L72:    aload_2
L73:    invokeinterface InterfaceMethod java/util/List remove (Ljava/lang/Object;)Z 2
L78:    istore_3
L79:    getfield Field Te field2107 Z
L82:    ifeq L105
L85:    aload_0
L86:    getfield Field Te field2115 Ljava/util/List;
L89:    invokeinterface InterfaceMethod java/util/List isEmpty ()Z 1
L94:    ifeq L105
L97:    aload_0
L98:    iconst_1
L99:    dup
L100:   dup
L101:   pop2
L102:   putfield Field Te field2122 Z
L105:   aload_0
L106:   getfield Field Te field2107 Z
L109:   ifne L124
L112:   iload_3
L113:   ifeq L124
L116:   aload_0
L117:   iconst_1
L118:   dup
L119:   dup
L120:   pop2
L121:   putfield Field Te field2122 Z
L124:   aload_0
L125:   getfield Field Te field2122 Z
L128:   ifeq L136
L131:   aload_0
L132:   aload_1
L133:   invokevirtual Method Te method1060 (LRg;)V
L136:   return
L137:   
        .attribute StackMap b'\x00\x0A\x00\x0E\x00\x03\x07\x00\x02\x07\x00\x89\x07\x00\x95\x00\x00\x00\x0F\x00\x00\x00\x01\x07\x00\x3B\x00\x10\x00\x03\x07\x00\x02\x07\x00\x89\x07\x00\x95\x00\x00\x00\x20\x00\x06\x07\x00\x02\x07\x00\x89\x07\x00\x95\x07\x00\xD9\x01\x01\x00\x01\x01\x00\x3A\x00\x00\x00\x01\x07\x00\x3B\x00\x3B\x00\x07\x07\x00\x02\x07\x00\x89\x07\x00\x95\x07\x00\xD9\x01\x01\x07\x00\x95\x00\x00\x00\x43\x00\x06\x07\x00\x02\x07\x00\x89\x07\x00\x95\x07\x00\xD9\x01\x01\x00\x00\x00\x69\x00\x06\x07\x00\x02\x07\x00\x89\x07\x00\x95\x01\x01\x01\x00\x00\x00\x7C\x00\x06\x07\x00\x02\x07\x00\x89\x07\x00\x95\x01\x01\x01\x00\x00\x00\x88\x00\x06\x07\x00\x02\x07\x00\x89\x07\x00\x95\x01\x01\x01\x00\x00'
    .end code
.end method
.innerclasses
    Pc JB [0] public static final enum
.end innerclasses
.end class
