.version 49 0
.class public final super Uc
.super java/lang/Object
.implements K
.field public final synthetic field1740 LZb;

.method public method736 : (LRg;LKD;)V
    .code stack 0 locals 3
L0:     return
L1:     
    .end code
.end method

.method public bridge synthetic method734 : (Ljava/lang/Object;)V
    .code stack 2 locals 2
L0:     aload_0
L1:     aload_1
L2:     checkcast Rg
L5:     invokevirtual Method Uc method737 (LRg;)V
L8:     return
L9:     
    .end code
.end method

.method public method737 : (LRg;)V
    .code stack 11 locals 5
L0:     new LD
L3:     dup
L4:     aload_1
L5:     fconst_1
L6:     invokespecial Method LD <init> (LRg;F)V
L9:     astore_2
L10:    aload_1
L11:    dup
L12:    getstatic Field qE field626 LqE;
L15:    invokevirtual Method Rg method226 (LqE;)V
L18:    getstatic Field qE this LqE;
L21:    invokevirtual Method Rg method226 (LqE;)V
L24:    new EC
L27:    aload_1
L28:    dup_x1
L29:    dup
L30:    pop2
L31:    dup
L32:    aload_0
L33:    aload_1
L34:    invokespecial Method EC <init> (LUc;LRg;)V
L37:    invokevirtual Method Rg method235 (LF;)V
L40:    new qc
L43:    dup
L44:    new fG
L47:    dup
L48:    getstatic Field LE field634 LLE;
L51:    ldc 1e-1f
L53:    invokespecial Method fG <init> (LLE;F)V
L56:    invokespecial Method qc <init> (Ld;)V
L59:    dup
L60:    astore_3
L61:    aload_0
L62:    getfield Field Uc field1740 LZb;
L65:    new Yg
L68:    dup
L69:    ldc "Close"
L71:    new nd
L74:    dup
L75:    aload_0
L76:    invokespecial Method nd <init> (LUc;)V
L79:    invokespecial Method Yg <init> (Ljava/lang/String;Lh;)V
L82:    invokestatic Method Zb method514 (LZb;LYg;)LYg;
L85:    getstatic Field dg field335 Ldg;
L88:    invokevirtual Method qc method31 (LgB;Ljava/lang/Object;)V
L91:    new qc
L94:    dup
L95:    new VD
L98:    dup
L99:    invokespecial Method VD <init> ()V
L102:   invokespecial Method qc <init> (Ld;)V
L105:   astore 4
L107:   aload_0
L108:   dup
L109:   aload_2
L110:   aload 4
L112:   dup_x1
L113:   dup_x2
L114:   new Vg
L117:   aload 4
L119:   dup_x1
L120:   dup
L121:   pop2
L122:   dup
L123:   ldc 7e0f
L125:   invokestatic Method LD method124 ()F
L128:   fmul
L129:   fconst_0
L130:   invokespecial Method Vg <init> (FF)V
L133:   getstatic Field VD field150 Ljava/lang/Object;
L136:   invokevirtual Method qc method31 (LgB;Ljava/lang/Object;)V
L139:   new Vg
L142:   aload 4
L144:   dup
L145:   pop2
L146:   dup
L147:   fconst_0
L148:   ldc 8e0f
L150:   invokespecial Method Vg <init> (FF)V
L153:   getstatic Field VD field149 Ljava/lang/Object;
L156:   invokevirtual Method qc method31 (LgB;Ljava/lang/Object;)V
L159:   getstatic Field VD field147 Ljava/lang/Object;
L162:   invokevirtual Method qc method31 (LgB;Ljava/lang/Object;)V
L165:   new SB
L168:   aload 4
L170:   dup
L171:   pop2
L172:   dup
L173:   aload_3
L174:   ldc 3e-1f
L176:   fconst_0
L177:   dup
L178:   dup_x2
L179:   invokespecial Method SB <init> (LgB;FFFF)V
L182:   getstatic Field VD field148 Ljava/lang/Object;
L185:   invokevirtual Method qc method31 (LgB;Ljava/lang/Object;)V
L188:   getfield Field Uc field1740 LZb;
L191:   new If
L194:   dup
L195:   invokespecial Method If <init> ()V
L198:   invokevirtual Method Zb method34 (Ld;)V
L201:   getfield Field Uc field1740 LZb;
L204:   aload 4
L206:   invokestatic Method Wd method1093 (LgB;)Lqc;
L209:   invokevirtual Method Zb method36 (LgB;)LgB;
L212:   pop
L213:   return
L214:   
    .end code
.end method

.method public <init> : (LZb;)V
    .code stack 3 locals 2
L0:     aload_0
L1:     dup
L2:     aload_1
L3:     putfield Field Uc field1740 LZb;
L6:     invokespecial Method java/lang/Object <init> ()V
L9:     return
L10:    
    .end code
.end method

.method public bridge synthetic method735 : (Ljava/lang/Object;LKD;)V
    .code stack 3 locals 3
L0:     aload_0
L1:     aload_1
L2:     checkcast Rg
L5:     aload_2
L6:     invokevirtual Method Uc method736 (LRg;LKD;)V
L9:     return
L10:    
    .end code
.end method
.innerclasses
    EC [0] [0]
    LE fG [0] public static final enum
    Uc [0] [0]
    dg fG [0] public static final enum
    nd [0] [0]
    KD K [0] public static final enum
.end innerclasses
.enclosing method Zb method49 ()V
.end class
