.version 49 0
.class public final super UD
.super java/lang/Object
.implements D
.field private true F
.field private field667 F
.field private field668 F
.field private field669 F
.field private field670 F
.field private field671 F
.field private field672 F
.field private field673 F
.field private field674 F
.field private field675 F
.field private field676 F
.field private try F
.field private field677 F
.field private new [I
.field private field678 F
.field private this F
.field private field679 F
.field private field680 F
.field private field681 F
.field private field682 F

.method public method384 : (LAC;)V
    .code stack 40 locals 2
L0:     aload_0
L1:     aload_1
L2:     dup_x1
L3:     aload_1
L4:     aload_0
L5:     dup_x1
L6:     aload_0
L7:     aload_1
L8:     dup_x1
L9:     aload_1
L10:    aload_0
L11:    dup_x1
L12:    aload_0
L13:    aload_1
L14:    dup_x1
L15:    aload_1
L16:    aload_0
L17:    dup_x1
L18:    aload_0
L19:    aload_1
L20:    dup_x1
L21:    aload_1
L22:    aload_0
L23:    dup_x1
L24:    aload_0
L25:    aload_1
L26:    dup_x1
L27:    aload_1
L28:    aload_0
L29:    dup_x1
L30:    aload_0
L31:    aload_1
L32:    dup_x1
L33:    aload_1
L34:    aload_0
L35:    dup_x1
L36:    aload_0
L37:    aload_1
L38:    dup_x1
L39:    aload_0
L40:    getfield Field UD field679 F
L43:    invokevirtual Method AC method685 (F)V
L46:    getfield Field UD true F
L49:    invokevirtual Method AC method685 (F)V
L52:    getfield Field UD field671 F
L55:    invokevirtual Method AC method685 (F)V
L58:    getfield Field UD field678 F
L61:    invokevirtual Method AC method685 (F)V
L64:    getfield Field UD this F
L67:    invokevirtual Method AC method685 (F)V
L70:    getfield Field UD field667 F
L73:    invokevirtual Method AC method685 (F)V
L76:    getfield Field UD field680 F
L79:    invokevirtual Method AC method685 (F)V
L82:    getfield Field UD field670 F
L85:    invokevirtual Method AC method685 (F)V
L88:    getfield Field UD field673 F
L91:    invokevirtual Method AC method685 (F)V
L94:    getfield Field UD field668 F
L97:    invokevirtual Method AC method685 (F)V
L100:   getfield Field UD field682 F
L103:   invokevirtual Method AC method685 (F)V
L106:   getfield Field UD field681 F
L109:   invokevirtual Method AC method685 (F)V
L112:   getfield Field UD try F
L115:   invokevirtual Method AC method685 (F)V
L118:   getfield Field UD field676 F
L121:   invokevirtual Method AC method685 (F)V
L124:   getfield Field UD new [I
L127:   invokevirtual Method AC method673 ([I)V
L130:   getfield Field UD field675 F
L133:   invokevirtual Method AC method685 (F)V
L136:   getfield Field UD field674 F
L139:   invokevirtual Method AC method685 (F)V
L142:   getfield Field UD field672 F
L145:   invokevirtual Method AC method685 (F)V
L148:   getfield Field UD field677 F
L151:   invokevirtual Method AC method685 (F)V
L154:   getfield Field UD field669 F
L157:   invokevirtual Method AC method685 (F)V
L160:   return
L161:   
    .end code
    .exceptions java/io/IOException
.end method

.method public method136 : ()F
    .code stack 1 locals 1
L0:     aload_0
L1:     getfield Field UD field677 F
L4:     freturn
L5:     
    .end code
.end method

.method public method385 : ()F
    .code stack 1 locals 1
L0:     aload_0
L1:     getfield Field UD field669 F
L4:     freturn
L5:     
    .end code
.end method

.method public <init> : ()V
    .code stack 41 locals 1
L0:     ldc 5.5e-1f
L2:     aload_0
L3:     dup_x1
L4:     ldc 1.6e0f
L6:     fconst_1
L7:     aload_0
L8:     dup_x1
L9:     fconst_0
L10:    ldc 1.2e0f
L12:    aload_0
L13:    dup_x1
L14:    bipush 12
L16:    fconst_1
L17:    aload_0
L18:    dup_x1
L19:    fconst_1
L20:    ldc -3.9e-1f
L22:    aload_0
L23:    dup_x1
L24:    ldc 1e-1f
L26:    fconst_1
L27:    aload_0
L28:    dup_x1
L29:    ldc 1.6e0f
L31:    dup
L32:    aload_0
L33:    dup_x1
L34:    fconst_2
L35:    ldc 1.95e0f
L37:    aload_0
L38:    dup_x1
L39:    ldc 8e-2f
L41:    ldc 5e2f
L43:    aload_0
L44:    dup_x1
L45:    ldc 5e1f
L47:    ldc 3e2f
L49:    aload_0
L50:    dup_x1
L51:    ldc 6e1f
L53:    aload_0
L54:    invokespecial Method java/lang/Object <init> ()V
L57:    putfield Field UD field679 F
L60:    putfield Field UD true F
L63:    putfield Field UD field671 F
L66:    putfield Field UD field678 F
L69:    putfield Field UD this F
L72:    putfield Field UD field667 F
L75:    putfield Field UD field680 F
L78:    putfield Field UD field670 F
L81:    putfield Field UD field673 F
L84:    putfield Field UD field668 F
L87:    putfield Field UD field682 F
L90:    putfield Field UD field681 F
L93:    putfield Field UD try F
L96:    putfield Field UD field676 F
L99:    iconst_1
L100:   dup
L101:   pop2
L102:   newarray int
L104:   iconst_1
L105:   dup
L106:   pop2
L107:   dup
L108:   iconst_0
L109:   iconst_1
L110:   dup
L111:   pop2
L112:   iconst_0
L113:   iconst_1
L114:   dup
L115:   pop2
L116:   iastore
L117:   dup
L118:   iconst_1
L119:   dup
L120:   pop2
L121:   iconst_0
L122:   iconst_1
L123:   dup_x1
L124:   dup
L125:   pop2
L126:   iastore
L127:   dup
L128:   iconst_2
L129:   iconst_1
L130:   dup
L131:   pop2
L132:   iconst_1
L133:   dup
L134:   dup
L135:   pop2
L136:   iastore
L137:   dup
L138:   iconst_3
L139:   iconst_1
L140:   dup
L141:   pop2
L142:   iconst_1
L143:   dup
L144:   dup
L145:   pop2
L146:   iastore
L147:   dup
L148:   iconst_4
L149:   iconst_1
L150:   dup
L151:   pop2
L152:   iconst_1
L153:   dup
L154:   dup
L155:   pop2
L156:   iastore
L157:   dup
L158:   iconst_5
L159:   iconst_1
L160:   dup
L161:   pop2
L162:   iconst_2
L163:   iconst_1
L164:   dup
L165:   pop2
L166:   iastore
L167:   dup
L168:   bipush 6
L170:   iconst_1
L171:   dup
L172:   pop2
L173:   iconst_2
L174:   iconst_1
L175:   dup
L176:   pop2
L177:   iastore
L178:   dup
L179:   bipush 7
L181:   iconst_1
L182:   dup
L183:   pop2
L184:   iconst_3
L185:   iconst_1
L186:   dup
L187:   pop2
L188:   iastore
L189:   dup
L190:   bipush 8
L192:   iconst_1
L193:   dup
L194:   pop2
L195:   iconst_5
L196:   iconst_1
L197:   dup
L198:   pop2
L199:   iastore
L200:   dup
L201:   bipush 9
L203:   iconst_1
L204:   dup
L205:   pop2
L206:   bipush 7
L208:   iconst_1
L209:   dup
L210:   pop2
L211:   iastore
L212:   dup
L213:   bipush 10
L215:   iconst_1
L216:   dup
L217:   pop2
L218:   bipush 9
L220:   iconst_1
L221:   dup
L222:   pop2
L223:   iastore
L224:   dup
L225:   bipush 11
L227:   iconst_1
L228:   dup
L229:   pop2
L230:   bipush 11
L232:   iconst_1
L233:   dup
L234:   pop2
L235:   iastore
L236:   putfield Field UD new [I
L239:   putfield Field UD field675 F
L242:   putfield Field UD field674 F
L245:   putfield Field UD field672 F
L248:   putfield Field UD field677 F
L251:   putfield Field UD field669 F
L254:   return
L255:   
    .end code
.end method

.method public method386 : (IIDII)I
    .code stack 4 locals 7
L0:     iload_1
L1:     ifne L10
L4:     iconst_0
L5:     iconst_1
L6:     dup
L7:     pop2
L8:     ireturn
L9:     athrow
L10:    dload_3
L11:    d2f
L12:    aload_0
L13:    getfield Field UD field679 F
L16:    fsub
L17:    aload_0
L18:    dup
L19:    getfield Field UD true F
L22:    swap
L23:    getfield Field UD field679 F
L26:    fsub
L27:    fdiv
L28:    fconst_0
L29:    fconst_1
L30:    invokestatic Method OC method1001 (FFF)F
L33:    iload 5
L35:    i2f
L36:    aload_0
L37:    getfield Field UD field671 F
L40:    fsub
L41:    aload_0
L42:    dup
L43:    getfield Field UD field678 F
L46:    swap
L47:    getfield Field UD field671 F
L50:    fsub
L51:    fdiv
L52:    fconst_0
L53:    fconst_1
L54:    invokestatic Method OC method1001 (FFF)F
L57:    fadd
L58:    fconst_0
L59:    fconst_1
L60:    invokestatic Method OC method1001 (FFF)F
L63:    fstore 5
L65:    aload_0
L66:    iload_1
L67:    iload_2
L68:    invokespecial Method UD method389 (II)F
L71:    fconst_1
L72:    fload 5
L74:    fsub
L75:    fmul
L76:    aload_0
L77:    iload_1
L78:    iload_2
L79:    invokespecial Method UD method387 (II)F
L82:    fload 5
L84:    fmul
L85:    fadd
L86:    fstore_1
L87:    iload 6
L89:    ifle L114
L92:    fload_1
L93:    iload 6
L95:    i2f
L96:    aload_0
L97:    getfield Field UD this F
L100:   fmul
L101:   fconst_1
L102:   aload_0
L103:   getfield Field UD this F
L106:   fsub
L107:   fadd
L108:   fconst_2
L109:   invokestatic Method java/lang/Math min (FF)F
L112:   fmul
L113:   fstore_1
L114:   fload_1
L115:   invokestatic Method java/lang/Math round (F)I
L118:   ireturn
L119:   
        .attribute StackMap b'\x00\x03\x00\x09\x00\x00\x00\x01\x07\x00\x68\x00\x0A\x00\x06\x07\x00\x02\x01\x01\x03\x01\x01\x00\x00\x00\x72\x00\x06\x07\x00\x02\x02\x01\x03\x02\x01\x00\x00'
    .end code
.end method

.method private method387 : (II)F
    .code stack 3 locals 3
L0:     iload_1
L1:     ifne L7
L4:     fconst_0
L5:     freturn
L6:     athrow
L7:     iload_1
L8:     i2f
L9:     aload_0
L10:    getfield Field UD field675 F
L13:    fmul
L14:    iload_2
L15:    i2f
L16:    aload_0
L17:    getfield Field UD field674 F
L20:    fsub
L21:    aload_0
L22:    getfield Field UD field672 F
L25:    fmul
L26:    fadd
L27:    freturn
L28:    
        .attribute StackMap b'\x00\x02\x00\x06\x00\x00\x00\x01\x07\x00\x68\x00\x07\x00\x03\x07\x00\x02\x01\x01\x00\x00'
    .end code
.end method

.method public method388 : (IID)F
    .code stack 6 locals 5
L0:     iload_2
L1:     ifne L10
L4:     aload_0
L5:     getfield Field UD field681 F
L8:     freturn
L9:     athrow
L10:    aload_0
L11:    getfield Field UD field667 F
L14:    iload_2
L15:    i2f
L16:    aload_0
L17:    getfield Field UD field680 F
L20:    fadd
L21:    aload_0
L22:    getfield Field UD field670 F
L25:    fdiv
L26:    iload_1
L27:    i2d
L28:    aload_0
L29:    getfield Field UD field673 F
L32:    f2d
L33:    invokestatic Method java/lang/Math pow (DD)D
L36:    d2f
L37:    aload_0
L38:    getfield Field UD field668 F
L41:    fadd
L42:    fdiv
L43:    fmul
L44:    iload_1
L45:    i2f
L46:    aload_0
L47:    getfield Field UD field682 F
L50:    fmul
L51:    fsub
L52:    freturn
L53:    
        .attribute StackMap b'\x00\x02\x00\x09\x00\x00\x00\x01\x07\x00\x68\x00\x0A\x00\x04\x07\x00\x02\x01\x01\x03\x00\x00'
    .end code
.end method

.method private method389 : (II)F
    .code stack 7 locals 3
L0:     iload_1
L1:     ifne L7
L4:     fconst_0
L5:     freturn
L6:     athrow
L7:     iload_1
L8:     i2f
L9:     aload_0
L10:    getfield Field UD try F
L13:    fsub
L14:    aload_0
L15:    getfield Field UD field676 F
L18:    fmul
L19:    aload_0
L20:    getfield Field UD new [I
L23:    iload_2
L24:    aload_0
L25:    getfield Field UD new [I
L28:    arraylength
L29:    iconst_1
L30:    dup
L31:    dup
L32:    pop2
L33:    isub
L34:    invokestatic Method java/lang/Math min (II)I
L37:    iaload
L38:    i2f
L39:    fadd
L40:    freturn
L41:    
        .attribute StackMap b'\x00\x02\x00\x06\x00\x00\x00\x01\x07\x00\x68\x00\x07\x00\x03\x07\x00\x02\x01\x01\x00\x00'
    .end code
.end method

.method public <init> : (LMd;)V
    .code stack 81 locals 2
L0:     aload_1
L1:     aload_0
L2:     dup_x1
L3:     aload_0
L4:     aload_1
L5:     dup_x1
L6:     aload_1
L7:     aload_0
L8:     dup_x1
L9:     aload_0
L10:    aload_1
L11:    dup_x1
L12:    aload_1
L13:    aload_0
L14:    dup_x1
L15:    aload_0
L16:    aload_1
L17:    dup_x1
L18:    aload_1
L19:    aload_0
L20:    dup_x1
L21:    aload_0
L22:    aload_1
L23:    dup_x1
L24:    aload_1
L25:    aload_0
L26:    dup_x1
L27:    aload_0
L28:    aload_1
L29:    dup_x1
L30:    aload_1
L31:    aload_0
L32:    dup_x1
L33:    aload_0
L34:    aload_1
L35:    dup_x1
L36:    aload_1
L37:    aload_0
L38:    dup_x1
L39:    aload_1
L40:    ldc 5.5e-1f
L42:    aload_0
L43:    dup_x1
L44:    ldc 1.6e0f
L46:    fconst_1
L47:    aload_0
L48:    dup_x1
L49:    fconst_0
L50:    ldc 1.2e0f
L52:    aload_0
L53:    dup_x1
L54:    bipush 12
L56:    fconst_1
L57:    aload_0
L58:    dup_x1
L59:    fconst_1
L60:    ldc -3.9e-1f
L62:    aload_0
L63:    dup_x1
L64:    ldc 1e-1f
L66:    fconst_1
L67:    aload_0
L68:    dup_x1
L69:    ldc 1.6e0f
L71:    dup
L72:    aload_0
L73:    dup_x1
L74:    fconst_2
L75:    ldc 1.95e0f
L77:    aload_0
L78:    dup_x1
L79:    ldc 8e-2f
L81:    ldc 5e2f
L83:    aload_0
L84:    dup_x1
L85:    ldc 5e1f
L87:    ldc 3e2f
L89:    aload_0
L90:    dup_x1
L91:    ldc 6e1f
L93:    aload_0
L94:    invokespecial Method java/lang/Object <init> ()V
L97:    putfield Field UD field679 F
L100:   putfield Field UD true F
L103:   putfield Field UD field671 F
L106:   putfield Field UD field678 F
L109:   putfield Field UD this F
L112:   putfield Field UD field667 F
L115:   putfield Field UD field680 F
L118:   putfield Field UD field670 F
L121:   putfield Field UD field673 F
L124:   putfield Field UD field668 F
L127:   putfield Field UD field682 F
L130:   putfield Field UD field681 F
L133:   putfield Field UD try F
L136:   putfield Field UD field676 F
L139:   iconst_1
L140:   dup
L141:   pop2
L142:   newarray int
L144:   iconst_1
L145:   dup
L146:   pop2
L147:   dup
L148:   iconst_0
L149:   iconst_1
L150:   dup
L151:   pop2
L152:   iconst_0
L153:   iconst_1
L154:   dup
L155:   pop2
L156:   iastore
L157:   dup
L158:   iconst_1
L159:   dup
L160:   pop2
L161:   iconst_0
L162:   iconst_1
L163:   dup_x1
L164:   dup
L165:   pop2
L166:   iastore
L167:   dup
L168:   iconst_2
L169:   iconst_1
L170:   dup
L171:   pop2
L172:   iconst_1
L173:   dup
L174:   dup
L175:   pop2
L176:   iastore
L177:   dup
L178:   iconst_3
L179:   iconst_1
L180:   dup
L181:   pop2
L182:   iconst_1
L183:   dup
L184:   dup
L185:   pop2
L186:   iastore
L187:   dup
L188:   iconst_4
L189:   iconst_1
L190:   dup
L191:   pop2
L192:   iconst_1
L193:   dup
L194:   dup
L195:   pop2
L196:   iastore
L197:   dup
L198:   iconst_5
L199:   iconst_1
L200:   dup
L201:   pop2
L202:   iconst_2
L203:   iconst_1
L204:   dup
L205:   pop2
L206:   iastore
L207:   dup
L208:   bipush 6
L210:   iconst_1
L211:   dup
L212:   pop2
L213:   iconst_2
L214:   iconst_1
L215:   dup
L216:   pop2
L217:   iastore
L218:   dup
L219:   bipush 7
L221:   iconst_1
L222:   dup
L223:   pop2
L224:   iconst_3
L225:   iconst_1
L226:   dup
L227:   pop2
L228:   iastore
L229:   dup
L230:   bipush 8
L232:   iconst_1
L233:   dup
L234:   pop2
L235:   iconst_5
L236:   iconst_1
L237:   dup
L238:   pop2
L239:   iastore
L240:   dup
L241:   bipush 9
L243:   iconst_1
L244:   dup
L245:   pop2
L246:   bipush 7
L248:   iconst_1
L249:   dup
L250:   pop2
L251:   iastore
L252:   dup
L253:   bipush 10
L255:   iconst_1
L256:   dup
L257:   pop2
L258:   bipush 9
L260:   iconst_1
L261:   dup
L262:   pop2
L263:   iastore
L264:   dup
L265:   bipush 11
L267:   iconst_1
L268:   dup
L269:   pop2
L270:   bipush 11
L272:   iconst_1
L273:   dup
L274:   pop2
L275:   iastore
L276:   putfield Field UD new [I
L279:   putfield Field UD field675 F
L282:   putfield Field UD field674 F
L285:   putfield Field UD field672 F
L288:   putfield Field UD field677 F
L291:   putfield Field UD field669 F
L294:   invokevirtual Method Md method885 ()F
L297:   putfield Field UD field679 F
L300:   invokevirtual Method Md method885 ()F
L303:   putfield Field UD true F
L306:   invokevirtual Method Md method885 ()F
L309:   putfield Field UD field671 F
L312:   invokevirtual Method Md method885 ()F
L315:   putfield Field UD field678 F
L318:   invokevirtual Method Md method885 ()F
L321:   putfield Field UD this F
L324:   invokevirtual Method Md method885 ()F
L327:   putfield Field UD field667 F
L330:   invokevirtual Method Md method885 ()F
L333:   putfield Field UD field680 F
L336:   invokevirtual Method Md method885 ()F
L339:   putfield Field UD field670 F
L342:   invokevirtual Method Md method885 ()F
L345:   putfield Field UD field673 F
L348:   invokevirtual Method Md method885 ()F
L351:   putfield Field UD field668 F
L354:   invokevirtual Method Md method885 ()F
L357:   putfield Field UD field682 F
L360:   invokevirtual Method Md method885 ()F
L363:   putfield Field UD field681 F
L366:   invokevirtual Method Md method885 ()F
L369:   putfield Field UD try F
L372:   invokevirtual Method Md method885 ()F
L375:   putfield Field UD field676 F
L378:   invokevirtual Method Md method887 ()[I
L381:   putfield Field UD new [I
L384:   invokevirtual Method Md method885 ()F
L387:   putfield Field UD field675 F
L390:   invokevirtual Method Md method885 ()F
L393:   putfield Field UD field674 F
L396:   invokevirtual Method Md method885 ()F
L399:   putfield Field UD field672 F
L402:   invokevirtual Method Md method885 ()F
L405:   putfield Field UD field677 F
L408:   invokevirtual Method Md method885 ()F
L411:   putfield Field UD field669 F
L414:   return
L415:   
    .end code
    .exceptions java/io/IOException
.end method
.end class
