.version 49 0
.class public final super Ue
.super java/lang/Object
.field public field2134 [LHG;
.field public this LHG;
.field public field2135 I
.field public field2136 LHG;
.field public field2137 Z
.field public field2138 [LHG;

.method public method1063 : ()V
    .code stack 7 locals 2
L0:     aload_0
L1:     getfield Field Ue field2137 Z
L4:     ifeq L76
L7:     fconst_1
L8:     dup
L9:     dup_x1
L10:    ldc 2e-1f
L12:    invokestatic Method org/lwjgl/opengl/GL11 method3888 (FFFF)V
L15:    aload_0
L16:    getfield Field Ue field2136 LHG;
L19:    getfield Field HG field1841 F
L22:    aload_0
L23:    getfield Field Ue field2136 LHG;
L26:    getfield Field HG field1843 F
L29:    aload_0
L30:    dup_x2
L31:    getfield Field Ue field2136 LHG;
L34:    getfield Field HG field1844 F
L37:    invokestatic Method org/lwjgl/opengl/GL11 method3740 (FFF)V
L40:    getfield Field Ue field2136 LHG;
L43:    getfield Field HG field1841 F
L46:    aload_0
L47:    getfield Field Ue field2136 LHG;
L50:    getfield Field HG field1843 F
L53:    aload_0
L54:    getfield Field Ue this LHG;
L57:    getfield Field HG field1843 F
L60:    ldc 5e-2f
L62:    fmul
L63:    fadd
L64:    aload_0
L65:    getfield Field Ue field2136 LHG;
L68:    getfield Field HG field1844 F
L71:    invokestatic Method org/lwjgl/opengl/GL11 method3740 (FFF)V
L74:    return
L75:    athrow
L76:    iconst_0
L77:    iconst_1
L78:    dup
L79:    pop2
L80:    dup
L81:    istore_1
L82:    sipush 128
L85:    iconst_1
L86:    dup
L87:    pop2
L88:    if_icmpge L220
L91:    fconst_1
L92:    dup
L93:    dup_x1
L94:    ldc 3e-1f
L96:    fconst_1
L97:    aload_0
L98:    getfield Field Ue field2134 [LHG;
L101:   iload_1
L102:   aaload
L103:   getfield Field HG field1842 F
L106:   invokestatic Method java/lang/Math min (FF)F
L109:   fmul
L110:   invokestatic Method org/lwjgl/opengl/GL11 method3888 (FFFF)V
L113:   aload_0
L114:   getfield Field Ue field2134 [LHG;
L117:   iload_1
L118:   aaload
L119:   getfield Field HG field1841 F
L122:   aload_0
L123:   getfield Field Ue field2134 [LHG;
L126:   iload_1
L127:   aaload
L128:   getfield Field HG field1843 F
L131:   aload_0
L132:   dup_x2
L133:   getfield Field Ue field2134 [LHG;
L136:   iload_1
L137:   aaload
L138:   getfield Field HG field1844 F
L141:   invokestatic Method org/lwjgl/opengl/GL11 method3740 (FFF)V
L144:   getfield Field Ue field2134 [LHG;
L147:   iload_1
L148:   aaload
L149:   getfield Field HG field1841 F
L152:   aload_0
L153:   getfield Field Ue field2138 [LHG;
L156:   iload_1
L157:   aaload
L158:   getfield Field HG field1841 F
L161:   ldc 5e-2f
L163:   fmul
L164:   fadd
L165:   aload_0
L166:   getfield Field Ue field2134 [LHG;
L169:   iload_1
L170:   aaload
L171:   getfield Field HG field1843 F
L174:   aload_0
L175:   getfield Field Ue field2138 [LHG;
L178:   iload_1
L179:   aaload
L180:   getfield Field HG field1843 F
L183:   ldc 5e-2f
L185:   fmul
L186:   fadd
L187:   aload_0
L188:   getfield Field Ue field2134 [LHG;
L191:   iload_1
L192:   aaload
L193:   getfield Field HG field1844 F
L196:   aload_0
L197:   getfield Field Ue field2138 [LHG;
L200:   iload_1
L201:   iinc 1 1
L204:   aaload
L205:   getfield Field HG field1844 F
L208:   ldc 5e-2f
L210:   fmul
L211:   fadd
L212:   invokestatic Method org/lwjgl/opengl/GL11 method3740 (FFF)V
L215:   iload_1
L216:   goto L82
L219:   athrow
L220:   return
L221:   
        .attribute StackMap b'\x00\x05\x00\x4B\x00\x00\x00\x01\x07\x00\x32\x00\x4C\x00\x01\x07\x00\x02\x00\x00\x00\x52\x00\x02\x07\x00\x02\x01\x00\x01\x01\x00\xDB\x00\x00\x00\x01\x07\x00\x32\x00\xDC\x00\x02\x07\x00\x02\x01\x00\x00'
    .end code
.end method

.method public method1064 : (F)V
    .code stack 7 locals 4
L0:     aload_0
L1:     getfield Field Ue field2137 Z
L4:     ifeq L116
L7:     aload_0
L8:     dup
L9:     dup2
L10:    getfield Field Ue field2136 LHG;
L13:    dup
L14:    getfield Field HG field1841 F
L17:    aload_0
L18:    getfield Field Ue this LHG;
L21:    getfield Field HG field1841 F
L24:    fload_1
L25:    fmul
L26:    fadd
L27:    putfield Field HG field1841 F
L30:    getfield Field Ue field2136 LHG;
L33:    dup
L34:    getfield Field HG field1843 F
L37:    aload_0
L38:    dup_x2
L39:    getfield Field Ue this LHG;
L42:    getfield Field HG field1843 F
L45:    fload_1
L46:    fmul
L47:    fadd
L48:    putfield Field HG field1843 F
L51:    getfield Field Ue field2136 LHG;
L54:    dup
L55:    getfield Field HG field1844 F
L58:    aload_0
L59:    getfield Field Ue this LHG;
L62:    getfield Field HG field1844 F
L65:    fload_1
L66:    fmul
L67:    fadd
L68:    putfield Field HG field1844 F
L71:    getfield Field Ue this LHG;
L74:    dup
L75:    getfield Field HG field1843 F
L78:    ldc 3e-1f
L80:    fload_1
L81:    fmul
L82:    fadd
L83:    putfield Field HG field1843 F
L86:    getfield Field Ue this LHG;
L89:    getfield Field HG field1843 F
L92:    ldc 6e-1f
L94:    aload_0
L95:    getfield Field Ue field2135 I
L98:    i2f
L99:    fmul
L100:   ldc 2.4e1f
L102:   fdiv
L103:   ldc 4e-1f
L105:   fsub
L106:   fcmpl
L107:   ifle L351
L110:   aload_0
L111:   invokevirtual Method Ue method1065 ()V
L114:   return
L115:   athrow
L116:   iconst_0
L117:   iconst_1
L118:   dup
L119:   pop2
L120:   istore_2
L121:   iconst_0
L122:   iconst_1
L123:   dup
L124:   pop2
L125:   dup
L126:   istore_3
L127:   sipush 128
L130:   iconst_1
L131:   dup
L132:   pop2
L133:   if_icmpge L343
L136:   aload_0
L137:   dup
L138:   dup2
L139:   getfield Field Ue field2134 [LHG;
L142:   iload_3
L143:   aaload
L144:   dup
L145:   getfield Field HG field1841 F
L148:   aload_0
L149:   getfield Field Ue field2138 [LHG;
L152:   iload_3
L153:   aaload
L154:   getfield Field HG field1841 F
L157:   fload_1
L158:   fmul
L159:   fadd
L160:   putfield Field HG field1841 F
L163:   getfield Field Ue field2134 [LHG;
L166:   iload_3
L167:   aaload
L168:   dup
L169:   getfield Field HG field1843 F
L172:   aload_0
L173:   dup_x2
L174:   getfield Field Ue field2138 [LHG;
L177:   iload_3
L178:   aaload
L179:   getfield Field HG field1843 F
L182:   fload_1
L183:   fmul
L184:   fadd
L185:   putfield Field HG field1843 F
L188:   getfield Field Ue field2134 [LHG;
L191:   iload_3
L192:   aaload
L193:   dup
L194:   getfield Field HG field1844 F
L197:   aload_0
L198:   getfield Field Ue field2138 [LHG;
L201:   iload_3
L202:   aaload
L203:   getfield Field HG field1844 F
L206:   fload_1
L207:   fmul
L208:   fadd
L209:   putfield Field HG field1844 F
L212:   getfield Field Ue field2134 [LHG;
L215:   iload_3
L216:   aaload
L217:   dup
L218:   getfield Field HG field1842 F
L221:   aload_0
L222:   getfield Field Ue field2138 [LHG;
L225:   iload_3
L226:   aaload
L227:   getfield Field HG field1842 F
L230:   fload_1
L231:   fmul
L232:   fadd
L233:   putfield Field HG field1842 F
L236:   getfield Field Ue field2134 [LHG;
L239:   iload_3
L240:   aaload
L241:   getfield Field HG field1842 F
L244:   fconst_0
L245:   fcmpl
L246:   iflt L259
L249:   iconst_1
L250:   dup
L251:   dup
L252:   pop2
L253:   istore_2
L254:   aload_0
L255:   goto L270
L258:   athrow
L259:   aload_0
L260:   dup
L261:   getfield Field Ue field2134 [LHG;
L264:   iload_3
L265:   aaload
L266:   fconst_0
L267:   putfield Field HG field1842 F
L270:   getfield Field Ue field2138 [LHG;
L273:   iload_3
L274:   aaload
L275:   dup
L276:   getfield Field HG field1841 F
L279:   fconst_1
L280:   dup
L281:   fload_1
L282:   fmul
L283:   fsub
L284:   fmul
L285:   putfield Field HG field1841 F
L288:   aload_0
L289:   getfield Field Ue field2138 [LHG;
L292:   iload_3
L293:   aaload
L294:   aload_0
L295:   dup_x1
L296:   getfield Field Ue field2138 [LHG;
L299:   iload_3
L300:   aaload
L301:   getfield Field HG field1843 F
L304:   ldc 3e-1f
L306:   fload_1
L307:   fmul
L308:   fadd
L309:   fconst_1
L310:   dup
L311:   fload_1
L312:   fmul
L313:   fsub
L314:   fmul
L315:   putfield Field HG field1843 F
L318:   getfield Field Ue field2138 [LHG;
L321:   iload_3
L322:   iinc 3 1
L325:   aaload
L326:   dup
L327:   getfield Field HG field1844 F
L330:   fconst_1
L331:   dup
L332:   fload_1
L333:   fmul
L334:   fsub
L335:   fmul
L336:   putfield Field HG field1844 F
L339:   iload_3
L340:   goto L127
L343:   iload_2
L344:   ifne L351
L347:   aload_0
L348:   invokevirtual Method Ue method1066 ()V
L351:   return
L352:   
        .attribute StackMap b'\x00\x08\x00\x73\x00\x00\x00\x01\x07\x00\x32\x00\x74\x00\x02\x07\x00\x02\x02\x00\x00\x00\x7F\x00\x04\x07\x00\x02\x02\x01\x01\x00\x01\x01\x01\x02\x00\x00\x00\x01\x07\x00\x32\x01\x03\x00\x04\x07\x00\x02\x02\x01\x01\x00\x00\x01\x0E\x00\x04\x07\x00\x02\x02\x01\x01\x00\x01\x07\x00\x02\x01\x57\x00\x04\x07\x00\x02\x02\x01\x01\x00\x00\x01\x5F\x00\x02\x07\x00\x02\x02\x00\x00'
    .end code
.end method

.method public <init> : (I)V
    .code stack 6 locals 3
L0:     sipush 128
L3:     aload_0
L4:     dup_x1
L5:     invokespecial Method java/lang/Object <init> ()V
L8:     iconst_1
L9:     dup
L10:    pop2
L11:    anewarray HG
L14:    iconst_1
L15:    dup
L16:    pop2
L17:    putfield Field Ue field2134 [LHG;
L20:    aload_0
L21:    sipush 128
L24:    iconst_1
L25:    dup
L26:    pop2
L27:    anewarray HG
L30:    iconst_1
L31:    dup
L32:    pop2
L33:    putfield Field Ue field2138 [LHG;
L36:    iconst_0
L37:    aload_0
L38:    dup
L39:    iload_1
L40:    putfield Field Ue field2135 I
L43:    new HG
L46:    aload_0
L47:    dup_x2
L48:    dup
L49:    pop2
L50:    dup
L51:    invokespecial Method HG <init> ()V
L54:    putfield Field Ue field2136 LHG;
L57:    new HG
L60:    aload_0
L61:    dup
L62:    pop2
L63:    dup
L64:    invokespecial Method HG <init> ()V
L67:    putfield Field Ue this LHG;
L70:    iconst_1
L71:    dup
L72:    pop2
L73:    dup
L74:    istore_2
L75:    sipush 128
L78:    iconst_1
L79:    dup
L80:    pop2
L81:    if_icmpge L124
L84:    aload_0
L85:    dup
L86:    getfield Field Ue field2134 [LHG;
L89:    new HG
L92:    iload_2
L93:    dup_x1
L94:    dup
L95:    pop2
L96:    dup
L97:    invokespecial Method HG <init> ()V
L100:   aastore
L101:   getfield Field Ue field2138 [LHG;
L104:   new HG
L107:   iload_2
L108:   dup_x1
L109:   dup
L110:   pop2
L111:   dup
L112:   invokespecial Method HG <init> ()V
L115:   iinc 2 1
L118:   aastore
L119:   iload_2
L120:   goto L75
L123:   athrow
L124:   aload_0
L125:   invokevirtual Method Ue method1066 ()V
L128:   return
L129:   
        .attribute StackMap b'\x00\x03\x00\x4B\x00\x03\x07\x00\x02\x01\x01\x00\x01\x01\x00\x7B\x00\x00\x00\x01\x07\x00\x32\x00\x7C\x00\x03\x07\x00\x02\x01\x01\x00\x00'
    .end code
.end method

.method public method1065 : ()V
    .code stack 16 locals 3
L0:     aload_0
L1:     iconst_0
L2:     dup_x1
L3:     iconst_1
L4:     dup
L5:     pop2
L6:     putfield Field Ue field2137 Z
L9:     iconst_1
L10:    dup
L11:    pop2
L12:    dup
L13:    istore_1
L14:    sipush 128
L17:    iconst_1
L18:    dup
L19:    pop2
L20:    if_icmpge L339
L23:    aload_0
L24:    dup
L25:    dup2
L26:    dup2
L27:    ldc 1.25e0f
L29:    aload_0
L30:    dup_x2
L31:    aload_0
L32:    dup
L33:    dup_x1
L34:    dup2
L35:    getfield Field Ue field2134 [LHG;
L38:    iload_1
L39:    aaload
L40:    aload_0
L41:    dup_x2
L42:    getfield Field Ue field2136 LHG;
L45:    getfield Field HG field1841 F
L48:    putfield Field HG field1841 F
L51:    getfield Field Ue field2134 [LHG;
L54:    iload_1
L55:    aaload
L56:    aload_0
L57:    getfield Field Ue field2136 LHG;
L60:    getfield Field HG field1843 F
L63:    putfield Field HG field1843 F
L66:    getfield Field Ue field2134 [LHG;
L69:    iload_1
L70:    aaload
L71:    aload_0
L72:    getfield Field Ue field2136 LHG;
L75:    getfield Field HG field1844 F
L78:    putfield Field HG field1844 F
L81:    getfield Field Ue field2134 [LHG;
L84:    iload_1
L85:    aaload
L86:    fconst_2
L87:    putfield Field HG field1842 F
L90:    getfield Field Ue field2138 [LHG;
L93:    iload_1
L94:    aaload
L95:    invokestatic Method java/lang/Math random ()D
L98:    d2f
L99:    ldc 5e-1f
L101:   fsub
L102:   putfield Field HG field1841 F
L105:   getfield Field Ue field2138 [LHG;
L108:   iload_1
L109:   aaload
L110:   invokestatic Method java/lang/Math random ()D
L113:   d2f
L114:   ldc 5e-1f
L116:   fsub
L117:   putfield Field HG field1843 F
L120:   getfield Field Ue field2138 [LHG;
L123:   iload_1
L124:   aaload
L125:   invokestatic Method java/lang/Math random ()D
L128:   d2f
L129:   ldc 5e-1f
L131:   fsub
L132:   putfield Field HG field1844 F
L135:   aload_0
L136:   getfield Field Ue field2138 [LHG;
L139:   iload_1
L140:   aaload
L141:   getfield Field HG field1841 F
L144:   aload_0
L145:   getfield Field Ue field2138 [LHG;
L148:   iload_1
L149:   aaload
L150:   getfield Field HG field1841 F
L153:   fmul
L154:   aload_0
L155:   getfield Field Ue field2138 [LHG;
L158:   iload_1
L159:   aaload
L160:   getfield Field HG field1843 F
L163:   aload_0
L164:   getfield Field Ue field2138 [LHG;
L167:   iload_1
L168:   aaload
L169:   getfield Field HG field1843 F
L172:   fmul
L173:   fadd
L174:   aload_0
L175:   getfield Field Ue field2138 [LHG;
L178:   iload_1
L179:   aaload
L180:   getfield Field HG field1844 F
L183:   aload_0
L184:   getfield Field Ue field2138 [LHG;
L187:   iload_1
L188:   aaload
L189:   getfield Field HG field1844 F
L192:   fmul
L193:   fadd
L194:   f2d
L195:   invokestatic Method java/lang/Math sqrt (D)D
L198:   d2f
L199:   fmul
L200:   fconst_1
L201:   invokestatic Method java/lang/Math random ()D
L204:   d2f
L205:   ldc 2e-1f
L207:   fmul
L208:   fadd
L209:   fmul
L210:   fstore_2
L211:   getfield Field Ue field2138 [LHG;
L214:   iload_1
L215:   aaload
L216:   dup
L217:   getfield Field HG field1841 F
L220:   fload_2
L221:   fdiv
L222:   putfield Field HG field1841 F
L225:   getfield Field Ue field2138 [LHG;
L228:   iload_1
L229:   aaload
L230:   dup
L231:   getfield Field HG field1843 F
L234:   fload_2
L235:   fdiv
L236:   putfield Field HG field1843 F
L239:   getfield Field Ue field2138 [LHG;
L242:   iload_1
L243:   aaload
L244:   dup
L245:   getfield Field HG field1844 F
L248:   fload_2
L249:   fdiv
L250:   putfield Field HG field1844 F
L253:   getfield Field Ue field2138 [LHG;
L256:   iload_1
L257:   aaload
L258:   dup
L259:   getfield Field HG field1841 F
L262:   aload_0
L263:   getfield Field Ue this LHG;
L266:   getfield Field HG field1841 F
L269:   fadd
L270:   putfield Field HG field1841 F
L273:   getfield Field Ue field2138 [LHG;
L276:   iload_1
L277:   aaload
L278:   dup
L279:   getfield Field HG field1843 F
L282:   aload_0
L283:   getfield Field Ue this LHG;
L286:   getfield Field HG field1843 F
L289:   fadd
L290:   putfield Field HG field1843 F
L293:   getfield Field Ue field2138 [LHG;
L296:   iload_1
L297:   aaload
L298:   dup
L299:   getfield Field HG field1844 F
L302:   aload_0
L303:   getfield Field Ue this LHG;
L306:   getfield Field HG field1844 F
L309:   fadd
L310:   putfield Field HG field1844 F
L313:   getfield Field Ue field2138 [LHG;
L316:   iload_1
L317:   iinc 1 1
L320:   aaload
L321:   ldc -6e-1f
L323:   invokestatic Method java/lang/Math random ()D
L326:   d2f
L327:   ldc 8e-1f
L329:   fmul
L330:   fsub
L331:   putfield Field HG field1842 F
L334:   iload_1
L335:   goto L14
L338:   athrow
L339:   return
L340:   
        .attribute StackMap b'\x00\x03\x00\x0E\x00\x02\x07\x00\x02\x01\x00\x01\x01\x01\x52\x00\x00\x00\x01\x07\x00\x32\x01\x53\x00\x02\x07\x00\x02\x01\x00\x00'
    .end code
.end method

.method public method1066 : ()V
    .code stack 10 locals 1
L0:     aload_0
L1:     dup
L2:     dup_x1
L3:     dup2
L4:     dup2
L5:     iconst_1
L6:     dup
L7:     dup
L8:     pop2
L9:     putfield Field Ue field2137 Z
L12:    getfield Field Ue field2136 LHG;
L15:    invokestatic Method java/lang/Math random ()D
L18:    d2f
L19:    ldc 8e0f
L21:    fmul
L22:    ldc 4e0f
L24:    fsub
L25:    putfield Field HG field1841 F
L28:    getfield Field Ue field2136 LHG;
L31:    ldc 3e0f
L33:    putfield Field HG field1843 F
L36:    getfield Field Ue field2136 LHG;
L39:    invokestatic Method java/lang/Math random ()D
L42:    d2f
L43:    ldc 8e0f
L45:    fmul
L46:    ldc 4e0f
L48:    fsub
L49:    putfield Field HG field1844 F
L52:    getfield Field Ue this LHG;
L55:    invokestatic Method java/lang/Math random ()D
L58:    d2f
L59:    ldc 3e-1f
L61:    fmul
L62:    ldc 1.5e-1f
L64:    fsub
L65:    putfield Field HG field1841 F
L68:    getfield Field Ue this LHG;
L71:    ldc -1.1e0f
L73:    ldc 5e-1f
L75:    invokestatic Method java/lang/Math random ()D
L78:    d2f
L79:    fmul
L80:    fsub
L81:    putfield Field HG field1843 F
L84:    getfield Field Ue this LHG;
L87:    invokestatic Method java/lang/Math random ()D
L90:    d2f
L91:    ldc 3e-1f
L93:    fmul
L94:    ldc 1.5e-1f
L96:    fsub
L97:    putfield Field HG field1844 F
L100:   return
L101:   
    .end code
.end method
.innerclasses
    HG QE [0] static
    Ue QE [0] static
.end innerclasses
.end class
