.version 49 0
.class public final super ue
.super java/lang/Object
.implements D
.field public char I
.field public else I
.field public "enum" F
.field public do I

.method public break : (LAC;)V
    .code stack 8 locals 2
L0:     aload_0
L1:     aload_1
L2:     dup_x1
L3:     aload_1
L4:     aload_0
L5:     dup_x1
L6:     aload_1
L7:     aload_0
L8:     getfield Field ue else I
L11:    invokevirtual Method AC break (I)V
L14:    getfield Field ue char I
L17:    invokevirtual Method AC short (I)V
L20:    getfield Field ue do I
L23:    invokevirtual Method AC short (I)V
L26:    getfield Field ue "enum" F
L29:    invokevirtual Method AC break (F)V
L32:    return
L33:    
    .end code
    .exceptions java/io/IOException
.end method

.method public <init> : (IIIF)V
    .code stack 9 locals 5
L0:     fload 4
L2:     aload_0
L3:     dup_x1
L4:     iload_3
L5:     iload_2
L6:     aload_0
L7:     dup_x1
L8:     iload_1
L9:     aload_0
L10:    invokespecial Method java/lang/Object <init> ()V
L13:    putfield Field ue else I
L16:    putfield Field ue char I
L19:    putfield Field ue do I
L22:    putfield Field ue "enum" F
L25:    return
L26:    
    .end code
.end method

.method public <init> : (LMd;)V
    .code stack 9 locals 2
L0:     aload_1
L1:     aload_0
L2:     dup_x1
L3:     aload_0
L4:     aload_1
L5:     dup_x1
L6:     aload_1
L7:     aload_0
L8:     dup_x1
L9:     invokespecial Method java/lang/Object <init> ()V
L12:    invokevirtual Method Md long ()I
L15:    putfield Field ue else I
L18:    invokevirtual Method Md char ()I
L21:    putfield Field ue char I
L24:    invokevirtual Method Md char ()I
L27:    putfield Field ue do I
L30:    invokevirtual Method Md "enum" ()F
L33:    putfield Field ue "enum" F
L36:    return
L37:    
    .end code
    .exceptions java/io/IOException
.end method
.end class
