.version 49 0
.class public final super uE
.super java/lang/Object
.implements D
.field public field939 Led;
.field public field940 [I
.field public field941 Led;
.field public field942 I

.method public <init> : (Led;Led;I[I)V
    .code stack 9 locals 5
L0:     aload 4
L2:     aload_0
L3:     dup_x1
L4:     iload_3
L5:     aload_2
L6:     aload_0
L7:     dup_x1
L8:     aload_1
L9:     aload_0
L10:    invokespecial Method java/lang/Object <init> ()V
L13:    putfield Field uE field939 Led;
L16:    putfield Field uE field941 Led;
L19:    putfield Field uE field942 I
L22:    invokestatic Method OC method1013 ([I)[I
L25:    putfield Field uE field940 [I
L28:    return
L29:    
    .end code
.end method

.method public <init> : (LMd;)V
    .code stack 8 locals 3
L0:     aload_0
L1:     dup
L2:     aload_1
L3:     aload_0
L4:     dup_x2
L5:     aload_1
L6:     aload_0
L7:     invokespecial Method java/lang/Object <init> ()V
L10:    aload_1
L11:    dup_x1
L12:    invokevirtual Method Md method886 ()I
L15:    istore_1
L16:    invokevirtual Method Md method886 ()I
L19:    istore_2
L20:    invokevirtual Method Md method886 ()I
L23:    putfield Field uE field942 I
L26:    invokevirtual Method Md method887 ()[I
L29:    putfield Field uE field940 [I
L32:    getstatic Field Kc field1931 LKc;
L35:    iload_1
L36:    invokevirtual Method Kc method856 (I)Led;
L39:    putfield Field uE field939 Led;
L42:    getstatic Field Kc field1931 LKc;
L45:    iload_2
L46:    invokevirtual Method Kc method856 (I)Led;
L49:    putfield Field uE field941 Led;
L52:    return
L53:    
    .end code
    .exceptions java/io/IOException
.end method

.method public method384 : (LAC;)V
    .code stack 8 locals 2
L0:     aload_0
L1:     aload_1
L2:     dup_x1
L3:     aload_1
L4:     aload_0
L5:     dup_x1
L6:     aload_1
L7:     aload_0
L8:     getfield Field uE field939 Led;
L11:    getfield Field ed try I
L14:    invokevirtual Method AC method691 (I)V
L17:    getfield Field uE field941 Led;
L20:    getfield Field ed try I
L23:    invokevirtual Method AC method691 (I)V
L26:    getfield Field uE field942 I
L29:    invokevirtual Method AC method691 (I)V
L32:    getfield Field uE field940 [I
L35:    invokevirtual Method AC method673 ([I)V
L38:    return
L39:    
    .end code
    .exceptions java/io/IOException
.end method
.end class
