.version 49 0
.class public final super synthetic VC
.super java/lang/Object
.field public static final synthetic "enum" [I
.field public static final synthetic do [I

.method public static <clinit> : ()V
    .code stack 5 locals 1
L0:     invokestatic Method Hc values ()[LHc;
L3:     arraylength
L4:     newarray int
L6:     iconst_1
L7:     dup
L8:     pop2
L9:     putstatic Field VC "enum" [I
        .catch java/lang/NoSuchFieldError from L12 to L26 using L30
L12:    getstatic Field VC "enum" [I
L15:    getstatic Field Hc this LHc;
L18:    invokevirtual Method Hc ordinal ()I
L21:    iconst_1
L22:    dup
L23:    dup
L24:    pop2
L25:    iastore
L26:    goto L31
L29:    athrow
L30:    astore_0
        .catch java/lang/NoSuchFieldError from L31 to L45 using L49
L31:    getstatic Field VC "enum" [I
L34:    getstatic Field Hc "enum" LHc;
L37:    invokevirtual Method Hc ordinal ()I
L40:    iconst_2
L41:    iconst_1
L42:    dup
L43:    pop2
L44:    iastore
L45:    goto L50
L48:    athrow
L49:    astore_0
        .catch java/lang/NoSuchFieldError from L50 to L64 using L67
L50:    getstatic Field VC "enum" [I
L53:    getstatic Field Hc null LHc;
L56:    invokevirtual Method Hc ordinal ()I
L59:    iconst_3
L60:    iconst_1
L61:    dup
L62:    pop2
L63:    iastore
L64:    goto L68
L67:    astore_0
        .catch java/lang/NoSuchFieldError from L68 to L82 using L85
L68:    getstatic Field VC "enum" [I
L71:    getstatic Field Hc void LHc;
L74:    invokevirtual Method Hc ordinal ()I
L77:    iconst_4
L78:    iconst_1
L79:    dup
L80:    pop2
L81:    iastore
L82:    goto L86
L85:    astore_0
        .catch java/lang/NoSuchFieldError from L86 to L100 using L103
L86:    getstatic Field VC "enum" [I
L89:    getstatic Field Hc break LHc;
L92:    invokevirtual Method Hc ordinal ()I
L95:    iconst_5
L96:    iconst_1
L97:    dup
L98:    pop2
L99:    iastore
L100:   goto L104
L103:   astore_0
        .catch java/lang/NoSuchFieldError from L104 to L119 using L122
L104:   getstatic Field VC "enum" [I
L107:   getstatic Field Hc const LHc;
L110:   invokevirtual Method Hc ordinal ()I
L113:   bipush 6
L115:   iconst_1
L116:   dup
L117:   pop2
L118:   iastore
L119:   goto L123
L122:   astore_0
        .catch java/lang/NoSuchFieldError from L123 to L138 using L141
L123:   getstatic Field VC "enum" [I
L126:   getstatic Field Hc try LHc;
L129:   invokevirtual Method Hc ordinal ()I
L132:   bipush 7
L134:   iconst_1
L135:   dup
L136:   pop2
L137:   iastore
L138:   goto L142
L141:   astore_0
        .catch java/lang/NoSuchFieldError from L142 to L157 using L160
L142:   getstatic Field VC "enum" [I
L145:   getstatic Field Hc char LHc;
L148:   invokevirtual Method Hc ordinal ()I
L151:   bipush 8
L153:   iconst_1
L154:   dup
L155:   pop2
L156:   iastore
L157:   goto L161
L160:   astore_0
        .catch java/lang/NoSuchFieldError from L161 to L176 using L179
L161:   getstatic Field VC "enum" [I
L164:   getstatic Field Hc else LHc;
L167:   invokevirtual Method Hc ordinal ()I
L170:   bipush 9
L172:   iconst_1
L173:   dup
L174:   pop2
L175:   iastore
L176:   goto L180
L179:   astore_0
        .catch java/lang/NoSuchFieldError from L180 to L195 using L198
L180:   getstatic Field VC "enum" [I
L183:   getstatic Field Hc long LHc;
L186:   invokevirtual Method Hc ordinal ()I
L189:   bipush 10
L191:   iconst_1
L192:   dup
L193:   pop2
L194:   iastore
L195:   goto L199
L198:   astore_0
        .catch java/lang/NoSuchFieldError from L199 to L214 using L217
L199:   getstatic Field VC "enum" [I
L202:   getstatic Field Hc do LHc;
L205:   invokevirtual Method Hc ordinal ()I
L208:   bipush 11
L210:   iconst_1
L211:   dup
L212:   pop2
L213:   iastore
L214:   goto L218
L217:   astore_0
        .catch java/lang/NoSuchFieldError from L218 to L233 using L236
L218:   getstatic Field VC "enum" [I
L221:   getstatic Field Hc new LHc;
L224:   invokevirtual Method Hc ordinal ()I
L227:   bipush 12
L229:   iconst_1
L230:   dup
L231:   pop2
L232:   iastore
L233:   goto L237
L236:   astore_0
L237:   invokestatic Method QB values ()[LQB;
L240:   arraylength
L241:   newarray int
L243:   iconst_1
L244:   dup
L245:   pop2
L246:   putstatic Field VC do [I
        .catch java/lang/NoSuchFieldError from L249 to L263 using L266
L249:   getstatic Field VC do [I
L252:   getstatic Field QB else LQB;
L255:   invokevirtual Method QB ordinal ()I
L258:   iconst_1
L259:   dup
L260:   dup
L261:   pop2
L262:   iastore
L263:   goto L267
L266:   astore_0
        .catch java/lang/NoSuchFieldError from L267 to L281 using L282
L267:   getstatic Field VC do [I
L270:   getstatic Field QB "enum" LQB;
L273:   invokevirtual Method QB ordinal ()I
L276:   iconst_2
L277:   iconst_1
L278:   dup
L279:   pop2
L280:   iastore
L281:   return
L282:   astore_0
L283:   return
L284:   
        .attribute StackMap b'\x00\x1D\x00\x1D\x00\x00\x00\x01\x07\x00\x25\x00\x1E\x00\x00\x00\x01\x07\x00\x15\x00\x1F\x00\x00\x00\x00\x00\x30\x00\x00\x00\x01\x07\x00\x25\x00\x31\x00\x00\x00\x01\x07\x00\x15\x00\x32\x00\x00\x00\x00\x00\x43\x00\x00\x00\x01\x07\x00\x15\x00\x44\x00\x00\x00\x00\x00\x55\x00\x00\x00\x01\x07\x00\x15\x00\x56\x00\x00\x00\x00\x00\x67\x00\x00\x00\x01\x07\x00\x15\x00\x68\x00\x00\x00\x00\x00\x7A\x00\x00\x00\x01\x07\x00\x15\x00\x7B\x00\x00\x00\x00\x00\x8D\x00\x00\x00\x01\x07\x00\x15\x00\x8E\x00\x00\x00\x00\x00\xA0\x00\x00\x00\x01\x07\x00\x15\x00\xA1\x00\x00\x00\x00\x00\xB3\x00\x00\x00\x01\x07\x00\x15\x00\xB4\x00\x00\x00\x00\x00\xC6\x00\x00\x00\x01\x07\x00\x15\x00\xC7\x00\x00\x00\x00\x00\xD9\x00\x00\x00\x01\x07\x00\x15\x00\xDA\x00\x00\x00\x00\x00\xEC\x00\x00\x00\x01\x07\x00\x15\x00\xED\x00\x00\x00\x00\x01\x0A\x00\x00\x00\x01\x07\x00\x15\x01\x0B\x00\x00\x00\x00\x01\x1A\x00\x00\x00\x01\x07\x00\x15'
    .end code
.end method
.innerclasses
    Hc Xd [0] public static final enum
    QB qd [0] public static final enum
    VC Ub [0] static synthetic
.end innerclasses
.enclosing method Ub [0]
.end class
