.version 49 0
.class public final super VD
.super java/lang/Object
.implements d
.field public static final this Ljava/lang/Object;
.field public static final char Ljava/lang/Object;
.field public static final else Ljava/lang/Object;
.field public static final "enum" Ljava/lang/Object;
.field public static final do Ljava/lang/Object;

.method private short : (Lqc;)F
    .code stack 2 locals 9
L0:     aconst_null
L1:     astore_2
L2:     aconst_null
L3:     astore_3
L4:     aconst_null
L5:     astore 4
L7:     aconst_null
L8:     astore 5
L10:    aconst_null
L11:    astore 6
L13:    aload_1
L14:    getfield Field qc do Ljava/util/ArrayList;
L17:    invokevirtual Method java/util/ArrayList iterator ()Ljava/util/Iterator;
L20:    astore_1
L21:    aload_1
L22:    invokeinterface InterfaceMethod java/util/Iterator hasNext ()Z 1
L27:    ifeq L113
L30:    aload_1
L31:    invokeinterface InterfaceMethod java/util/Iterator next ()Ljava/lang/Object; 1
L36:    checkcast gB
L39:    dup
L40:    astore 7
L42:    getfield Field gB const Ljava/lang/Object;
L45:    dup
L46:    astore 8
L48:    getstatic Field VD do Ljava/lang/Object;
L51:    if_acmpne L62
L54:    aload 7
L56:    astore 4
L58:    goto L21
L61:    athrow
L62:    aload 8
L64:    getstatic Field VD else Ljava/lang/Object;
L67:    if_acmpne L78
L70:    aload 7
L72:    astore 5
L74:    goto L21
L77:    athrow
L78:    aload 8
L80:    getstatic Field VD "enum" Ljava/lang/Object;
L83:    if_acmpne L92
L86:    aload 7
L88:    astore_2
L89:    goto L21
L92:    aload 8
L94:    getstatic Field VD this Ljava/lang/Object;
L97:    if_acmpne L106
L100:   aload 7
L102:   astore_3
L103:   goto L21
L106:   aload 7
L108:   astore 6
L110:   goto L21
L113:   aload 4
L115:   ifnull L126
L118:   aload 4
L120:   getfield Field gB char F
L123:   goto L127
L126:   fconst_0
L127:   fstore_1
L128:   aload 5
L130:   ifnull L141
L133:   aload 5
L135:   getfield Field gB char F
L138:   goto L142
L141:   fconst_0
L142:   fstore 7
L144:   aload_2
L145:   ifnull L155
L148:   aload_2
L149:   getfield Field gB char F
L152:   goto L156
L155:   fconst_0
L156:   fstore 8
L158:   aload_3
L159:   ifnull L169
L162:   aload_3
L163:   getfield Field gB char F
L166:   goto L170
L169:   fconst_0
L170:   fstore_2
L171:   aload 6
L173:   ifnull L184
L176:   aload 6
L178:   getfield Field gB char F
L181:   goto L185
L184:   fconst_0
L185:   fstore_3
L186:   fconst_0
L187:   fstore 4
L189:   fload_2
L190:   getstatic Field FE "volatile" F
L193:   fcmpl
L194:   ifeq L205
L197:   fload 4
L199:   fload_2
L200:   invokestatic Method java/lang/Math max (FF)F
L203:   fstore 4
L205:   fload 8
L207:   getstatic Field FE "volatile" F
L210:   fcmpl
L211:   ifeq L223
L214:   fload 4
L216:   fload 8
L218:   invokestatic Method java/lang/Math max (FF)F
L221:   fstore 4
L223:   fconst_0
L224:   fstore_2
L225:   fload_1
L226:   getstatic Field FE "volatile" F
L229:   fcmpl
L230:   ifeq L237
L233:   fload_2
L234:   fload_1
L235:   fadd
L236:   fstore_2
L237:   fload_2
L238:   fload_3
L239:   fadd
L240:   fstore_2
L241:   fload 7
L243:   getstatic Field FE "volatile" F
L246:   fcmpl
L247:   ifeq L255
L250:   fload_2
L251:   fload 7
L253:   fadd
L254:   fstore_2
L255:   fload 4
L257:   fload_2
L258:   invokestatic Method java/lang/Math max (FF)F
L261:   dup
L262:   fstore 4
L264:   freturn
L265:   
        .attribute StackMap b'\x00\x16\x00\x15\x00\x07\x07\x00\x02\x07\x00\x1D\x07\x00\x1F\x07\x00\x1F\x07\x00\x1F\x07\x00\x1F\x07\x00\x1F\x00\x00\x00\x3D\x00\x00\x00\x01\x07\x00\x2E\x00\x3E\x00\x09\x07\x00\x02\x07\x00\x1D\x07\x00\x1F\x07\x00\x1F\x07\x00\x1F\x07\x00\x1F\x07\x00\x1F\x07\x00\x1F\x07\x00\x04\x00\x00\x00\x4D\x00\x00\x00\x01\x07\x00\x2E\x00\x4E\x00\x09\x07\x00\x02\x07\x00\x1D\x07\x00\x1F\x07\x00\x1F\x07\x00\x1F\x07\x00\x1F\x07\x00\x1F\x07\x00\x1F\x07\x00\x04\x00\x00\x00\x5C\x00\x09\x07\x00\x02\x07\x00\x1D\x07\x00\x1F\x07\x00\x1F\x07\x00\x1F\x07\x00\x1F\x07\x00\x1F\x07\x00\x1F\x07\x00\x04\x00\x00\x00\x6A\x00\x09\x07\x00\x02\x07\x00\x1D\x07\x00\x1F\x07\x00\x1F\x07\x00\x1F\x07\x00\x1F\x07\x00\x1F\x07\x00\x1F\x07\x00\x04\x00\x00\x00\x71\x00\x07\x07\x00\x02\x07\x00\x1D\x07\x00\x1F\x07\x00\x1F\x07\x00\x1F\x07\x00\x1F\x07\x00\x1F\x00\x00\x00\x7E\x00\x07\x07\x00\x02\x07\x00\x1D\x07\x00\x1F\x07\x00\x1F\x07\x00\x1F\x07\x00\x1F\x07\x00\x1F\x00\x00\x00\x7F\x00\x07\x07\x00\x02\x07\x00\x1D\x07\x00\x1F\x07\x00\x1F\x07\x00\x1F\x07\x00\x1F\x07\x00\x1F\x00\x01\x02\x00\x8D\x00\x07\x07\x00\x02\x02\x07\x00\x1F\x07\x00\x1F\x07\x00\x1F\x07\x00\x1F\x07\x00\x1F\x00\x00\x00\x8E\x00\x07\x07\x00\x02\x02\x07\x00\x1F\x07\x00\x1F\x07\x00\x1F\x07\x00\x1F\x07\x00\x1F\x00\x01\x02\x00\x9B\x00\x08\x07\x00\x02\x02\x07\x00\x1F\x07\x00\x1F\x07\x00\x1F\x07\x00\x1F\x07\x00\x1F\x02\x00\x00\x00\x9C\x00\x08\x07\x00\x02\x02\x07\x00\x1F\x07\x00\x1F\x07\x00\x1F\x07\x00\x1F\x07\x00\x1F\x02\x00\x01\x02\x00\xA9\x00\x09\x07\x00\x02\x02\x07\x00\x1F\x07\x00\x1F\x07\x00\x1F\x07\x00\x1F\x07\x00\x1F\x02\x02\x00\x00\x00\xAA\x00\x09\x07\x00\x02\x02\x07\x00\x1F\x07\x00\x1F\x07\x00\x1F\x07\x00\x1F\x07\x00\x1F\x02\x02\x00\x01\x02\x00\xB8\x00\x09\x07\x00\x02\x02\x02\x07\x00\x1F\x07\x00\x1F\x07\x00\x1F\x07\x00\x1F\x02\x02\x00\x00\x00\xB9\x00\x09\x07\x00\x02\x02\x02\x07\x00\x1F\x07\x00\x1F\x07\x00\x1F\x07\x00\x1F\x02\x02\x00\x01\x02\x00\xCD\x00\x09\x07\x00\x02\x02\x02\x02\x02\x07\x00\x1F\x07\x00\x1F\x02\x02\x00\x00\x00\xDF\x00\x09\x07\x00\x02\x02\x02\x02\x02\x07\x00\x1F\x07\x00\x1F\x02\x02\x00\x00\x00\xED\x00\x09\x07\x00\x02\x02\x02\x02\x02\x07\x00\x1F\x07\x00\x1F\x02\x02\x00\x00\x00\xFF\x00\x09\x07\x00\x02\x02\x02\x02\x02\x07\x00\x1F\x07\x00\x1F\x02\x02\x00\x00'
    .end code
.end method

.method private const : (Lqc;)F
    .code stack 2 locals 9
L0:     aconst_null
L1:     astore_2
L2:     aconst_null
L3:     astore_3
L4:     aconst_null
L5:     astore 4
L7:     aconst_null
L8:     astore 5
L10:    aconst_null
L11:    astore 6
L13:    aload_1
L14:    getfield Field qc do Ljava/util/ArrayList;
L17:    invokevirtual Method java/util/ArrayList iterator ()Ljava/util/Iterator;
L20:    astore_1
L21:    aload_1
L22:    invokeinterface InterfaceMethod java/util/Iterator hasNext ()Z 1
L27:    ifeq L113
L30:    aload_1
L31:    invokeinterface InterfaceMethod java/util/Iterator next ()Ljava/lang/Object; 1
L36:    checkcast gB
L39:    dup
L40:    astore 7
L42:    getfield Field gB const Ljava/lang/Object;
L45:    dup
L46:    astore 8
L48:    getstatic Field VD do Ljava/lang/Object;
L51:    if_acmpne L62
L54:    aload 7
L56:    astore 4
L58:    goto L21
L61:    athrow
L62:    aload 8
L64:    getstatic Field VD else Ljava/lang/Object;
L67:    if_acmpne L78
L70:    aload 7
L72:    astore 5
L74:    goto L21
L77:    athrow
L78:    aload 8
L80:    getstatic Field VD "enum" Ljava/lang/Object;
L83:    if_acmpne L92
L86:    aload 7
L88:    astore_2
L89:    goto L21
L92:    aload 8
L94:    getstatic Field VD this Ljava/lang/Object;
L97:    if_acmpne L106
L100:   aload 7
L102:   astore_3
L103:   goto L21
L106:   aload 7
L108:   astore 6
L110:   goto L21
L113:   aload 4
L115:   ifnull L126
L118:   aload 4
L120:   getfield Field gB case F
L123:   goto L127
L126:   fconst_0
L127:   fstore_1
L128:   aload 5
L130:   ifnull L141
L133:   aload 5
L135:   getfield Field gB case F
L138:   goto L142
L141:   fconst_0
L142:   fstore 7
L144:   aload_2
L145:   ifnull L155
L148:   aload_2
L149:   getfield Field gB case F
L152:   goto L156
L155:   fconst_0
L156:   fstore 8
L158:   aload_3
L159:   ifnull L169
L162:   aload_3
L163:   getfield Field gB case F
L166:   goto L170
L169:   fconst_0
L170:   fstore_2
L171:   aload 6
L173:   ifnull L184
L176:   aload 6
L178:   getfield Field gB case F
L181:   goto L185
L184:   fconst_0
L185:   fstore_3
L186:   fconst_0
L187:   fstore 4
L189:   fload_1
L190:   ldc 1.6e1f
L192:   fcmpl
L193:   ifeq L204
L196:   fload 4
L198:   fload_1
L199:   invokestatic Method java/lang/Math max (FF)F
L202:   fstore 4
L204:   fload 7
L206:   ldc 1.6e1f
L208:   fcmpl
L209:   ifeq L221
L212:   fload 4
L214:   fload 7
L216:   invokestatic Method java/lang/Math max (FF)F
L219:   fstore 4
L221:   fconst_0
L222:   fstore_1
L223:   fload_2
L224:   ldc 1.6e1f
L226:   fcmpl
L227:   ifeq L234
L230:   fload_1
L231:   fload_2
L232:   fadd
L233:   fstore_1
L234:   fload_1
L235:   fload_3
L236:   fadd
L237:   fstore_1
L238:   fload 8
L240:   ldc 1.6e1f
L242:   fcmpl
L243:   ifeq L251
L246:   fload_1
L247:   fload 8
L249:   fadd
L250:   fstore_1
L251:   fload 4
L253:   fload_1
L254:   invokestatic Method java/lang/Math max (FF)F
L257:   dup
L258:   fstore 4
L260:   freturn
L261:   
        .attribute StackMap b'\x00\x16\x00\x15\x00\x07\x07\x00\x02\x07\x00\x1D\x07\x00\x1F\x07\x00\x1F\x07\x00\x1F\x07\x00\x1F\x07\x00\x1F\x00\x00\x00\x3D\x00\x00\x00\x01\x07\x00\x2E\x00\x3E\x00\x09\x07\x00\x02\x07\x00\x1D\x07\x00\x1F\x07\x00\x1F\x07\x00\x1F\x07\x00\x1F\x07\x00\x1F\x07\x00\x1F\x07\x00\x04\x00\x00\x00\x4D\x00\x00\x00\x01\x07\x00\x2E\x00\x4E\x00\x09\x07\x00\x02\x07\x00\x1D\x07\x00\x1F\x07\x00\x1F\x07\x00\x1F\x07\x00\x1F\x07\x00\x1F\x07\x00\x1F\x07\x00\x04\x00\x00\x00\x5C\x00\x09\x07\x00\x02\x07\x00\x1D\x07\x00\x1F\x07\x00\x1F\x07\x00\x1F\x07\x00\x1F\x07\x00\x1F\x07\x00\x1F\x07\x00\x04\x00\x00\x00\x6A\x00\x09\x07\x00\x02\x07\x00\x1D\x07\x00\x1F\x07\x00\x1F\x07\x00\x1F\x07\x00\x1F\x07\x00\x1F\x07\x00\x1F\x07\x00\x04\x00\x00\x00\x71\x00\x07\x07\x00\x02\x07\x00\x1D\x07\x00\x1F\x07\x00\x1F\x07\x00\x1F\x07\x00\x1F\x07\x00\x1F\x00\x00\x00\x7E\x00\x07\x07\x00\x02\x07\x00\x1D\x07\x00\x1F\x07\x00\x1F\x07\x00\x1F\x07\x00\x1F\x07\x00\x1F\x00\x00\x00\x7F\x00\x07\x07\x00\x02\x07\x00\x1D\x07\x00\x1F\x07\x00\x1F\x07\x00\x1F\x07\x00\x1F\x07\x00\x1F\x00\x01\x02\x00\x8D\x00\x07\x07\x00\x02\x02\x07\x00\x1F\x07\x00\x1F\x07\x00\x1F\x07\x00\x1F\x07\x00\x1F\x00\x00\x00\x8E\x00\x07\x07\x00\x02\x02\x07\x00\x1F\x07\x00\x1F\x07\x00\x1F\x07\x00\x1F\x07\x00\x1F\x00\x01\x02\x00\x9B\x00\x08\x07\x00\x02\x02\x07\x00\x1F\x07\x00\x1F\x07\x00\x1F\x07\x00\x1F\x07\x00\x1F\x02\x00\x00\x00\x9C\x00\x08\x07\x00\x02\x02\x07\x00\x1F\x07\x00\x1F\x07\x00\x1F\x07\x00\x1F\x07\x00\x1F\x02\x00\x01\x02\x00\xA9\x00\x09\x07\x00\x02\x02\x07\x00\x1F\x07\x00\x1F\x07\x00\x1F\x07\x00\x1F\x07\x00\x1F\x02\x02\x00\x00\x00\xAA\x00\x09\x07\x00\x02\x02\x07\x00\x1F\x07\x00\x1F\x07\x00\x1F\x07\x00\x1F\x07\x00\x1F\x02\x02\x00\x01\x02\x00\xB8\x00\x09\x07\x00\x02\x02\x02\x07\x00\x1F\x07\x00\x1F\x07\x00\x1F\x07\x00\x1F\x02\x02\x00\x00\x00\xB9\x00\x09\x07\x00\x02\x02\x02\x07\x00\x1F\x07\x00\x1F\x07\x00\x1F\x07\x00\x1F\x02\x02\x00\x01\x02\x00\xCC\x00\x09\x07\x00\x02\x02\x02\x02\x02\x07\x00\x1F\x07\x00\x1F\x02\x02\x00\x00\x00\xDD\x00\x09\x07\x00\x02\x02\x02\x02\x02\x07\x00\x1F\x07\x00\x1F\x02\x02\x00\x00\x00\xEA\x00\x09\x07\x00\x02\x02\x02\x02\x02\x07\x00\x1F\x07\x00\x1F\x02\x02\x00\x00\x00\xFB\x00\x09\x07\x00\x02\x02\x02\x02\x02\x07\x00\x1F\x07\x00\x1F\x02\x02\x00\x00'
    .end code
.end method

.method public <init> : ()V
    .code stack 1 locals 1
L0:     aload_0
L1:     invokespecial Method java/lang/Object <init> ()V
L4:     return
L5:     
    .end code
.end method

.method public else : (Lqc;)V
    .code stack 7 locals 17
L0:     iconst_0
L1:     iconst_1
L2:     dup
L3:     pop2
L4:     istore_2
L5:     aconst_null
L6:     astore_3
L7:     aconst_null
L8:     astore 4
L10:    aconst_null
L11:    astore 5
L13:    aconst_null
L14:    astore 6
L16:    new java/util/ArrayList
L19:    dup
L20:    iconst_1
L21:    dup
L22:    dup
L23:    pop2
L24:    invokespecial Method java/util/ArrayList <init> (I)V
L27:    astore 7
L29:    new Tf
L32:    dup
L33:    ldc 5e-1f
L35:    dup
L36:    invokespecial Method Tf <init> (FF)V
L39:    astore 8
L41:    aload_1
L42:    getfield Field qc do Ljava/util/ArrayList;
L45:    invokevirtual Method java/util/ArrayList iterator ()Ljava/util/Iterator;
L48:    astore 9
L50:    aload 9
L52:    invokeinterface InterfaceMethod java/util/Iterator hasNext ()Z 1
L57:    ifeq L151
L60:    aload 9
L62:    invokeinterface InterfaceMethod java/util/Iterator next ()Ljava/lang/Object; 1
L67:    checkcast gB
L70:    dup
L71:    astore 10
L73:    getfield Field gB const Ljava/lang/Object;
L76:    dup
L77:    astore 11
L79:    getstatic Field VD do Ljava/lang/Object;
L82:    if_acmpne L93
L85:    aload 10
L87:    astore 5
L89:    goto L50
L92:    athrow
L93:    aload 11
L95:    getstatic Field VD else Ljava/lang/Object;
L98:    if_acmpne L109
L101:   aload 10
L103:   astore 6
L105:   goto L50
L108:   athrow
L109:   aload 11
L111:   getstatic Field VD "enum" Ljava/lang/Object;
L114:   if_acmpne L123
L117:   aload 10
L119:   astore_3
L120:   goto L50
L123:   aload 11
L125:   getstatic Field VD this Ljava/lang/Object;
L128:   if_acmpne L138
L131:   aload 10
L133:   astore 4
L135:   goto L50
L138:   aload 7
L140:   aload 10
L142:   invokeinterface InterfaceMethod java/util/List add (Ljava/lang/Object;)Z 2
L147:   pop
L148:   goto L50
L151:   aload 5
L153:   ifnull L164
L156:   aload 5
L158:   getfield Field gB char F
L161:   goto L165
L164:   fconst_0
L165:   fstore 9
L167:   aload 6
L169:   ifnull L180
L172:   aload 6
L174:   getfield Field gB char F
L177:   goto L181
L180:   fconst_0
L181:   fstore 10
L183:   aload_3
L184:   ifnull L194
L187:   aload_3
L188:   getfield Field gB case F
L191:   goto L195
L194:   fconst_0
L195:   fstore 11
L197:   aload 4
L199:   ifnull L210
L202:   aload 4
L204:   getfield Field gB case F
L207:   goto L211
L210:   fconst_0
L211:   fstore 12
L213:   fconst_0
L214:   fstore 13
L216:   fconst_0
L217:   fstore 14
L219:   aload 7
L221:   invokeinterface InterfaceMethod java/util/List iterator ()Ljava/util/Iterator; 1
L226:   dup
L227:   astore 15
L229:   invokeinterface InterfaceMethod java/util/Iterator hasNext ()Z 1
L234:   ifeq L278
L237:   aload 15
L239:   invokeinterface InterfaceMethod java/util/Iterator next ()Ljava/lang/Object; 1
L244:   checkcast gB
L247:   astore 16
L249:   fload 13
L251:   aload 16
L253:   getfield Field gB case F
L256:   invokestatic Method java/lang/Math max (FF)F
L259:   fstore 13
L261:   fload 14
L263:   aload 16
L265:   getfield Field gB char F
L268:   invokestatic Method java/lang/Math max (FF)F
L271:   fstore 14
L273:   aload 15
L275:   goto L229
L278:   fload 11
L280:   fload 12
L282:   fadd
L283:   fload 13
L285:   fadd
L286:   fstore 15
L288:   fload 9
L290:   fload 10
L292:   fadd
L293:   fload 14
L295:   fadd
L296:   fstore 16
L298:   fload 15
L300:   aload_1
L301:   getfield Field qc catch F
L304:   fcmpl
L305:   ifle L404
L308:   fload 11
L310:   ldc 1.6e1f
L312:   fcmpl
L313:   ifne L341
L316:   fload 12
L318:   ldc 1.6e1f
L320:   fcmpl
L321:   ifeq L341
L324:   aload_1
L325:   getfield Field qc catch F
L328:   fload 13
L330:   fsub
L331:   fload 12
L333:   fsub
L334:   fstore 11
L336:   fload 16
L338:   goto L406
L341:   fload 11
L343:   ldc 1.6e1f
L345:   fcmpl
L346:   ifeq L374
L349:   fload 12
L351:   ldc 1.6e1f
L353:   fcmpl
L354:   ifne L374
L357:   aload_1
L358:   getfield Field qc catch F
L361:   fload 13
L363:   fsub
L364:   fload 11
L366:   fsub
L367:   fstore 12
L369:   fload 16
L371:   goto L406
L374:   fload 11
L376:   ldc 1.6e1f
L378:   fcmpl
L379:   ifne L404
L382:   fload 12
L384:   ldc 1.6e1f
L386:   fcmpl
L387:   ifne L404
L390:   aload_1
L391:   getfield Field qc catch F
L394:   fload 13
L396:   fsub
L397:   fconst_2
L398:   fdiv
L399:   dup
L400:   fstore 12
L402:   fstore 11
L404:   fload 16
L406:   aload_1
L407:   getfield Field qc break F
L410:   fcmpl
L411:   ifle L516
L414:   fload 9
L416:   getstatic Field FE "volatile" F
L419:   fcmpl
L420:   ifne L449
L423:   fload 10
L425:   getstatic Field FE "volatile" F
L428:   fcmpl
L429:   ifeq L449
L432:   aload 5
L434:   aload_1
L435:   getfield Field qc break F
L438:   fload 14
L440:   fsub
L441:   fload 10
L443:   fsub
L444:   fstore 9
L446:   goto L518
L449:   fload 9
L451:   getstatic Field FE "volatile" F
L454:   fcmpl
L455:   ifeq L484
L458:   fload 10
L460:   getstatic Field FE "volatile" F
L463:   fcmpl
L464:   ifne L484
L467:   aload 5
L469:   aload_1
L470:   getfield Field qc break F
L473:   fload 14
L475:   fsub
L476:   fload 9
L478:   fsub
L479:   fstore 10
L481:   goto L518
L484:   fload 9
L486:   getstatic Field FE "volatile" F
L489:   fcmpl
L490:   ifne L516
L493:   fload 10
L495:   getstatic Field FE "volatile" F
L498:   fcmpl
L499:   ifne L516
L502:   aload_1
L503:   getfield Field qc break F
L506:   fload 14
L508:   fsub
L509:   fconst_2
L510:   fdiv
L511:   dup
L512:   fstore 9
L514:   fstore 10
L516:   aload 5
L518:   ifnull L590
L521:   aload_1
L522:   aload 5
L524:   dup_x1
L525:   dup_x2
L526:   aload_1
L527:   aload 5
L529:   dup
L530:   getfield Field gB case F
L533:   fstore 13
L535:   getfield Field gB char F
L538:   fstore 15
L540:   getfield Field qc catch F
L543:   fload 9
L545:   invokevirtual Method gB const (FF)V
L548:   getfield Field qc void F
L551:   aload_1
L552:   getfield Field qc if F
L555:   invokevirtual Method gB catch (FF)V
L558:   getfield Field gB case F
L561:   fload 13
L563:   fsub
L564:   invokestatic Method java/lang/Math abs (F)F
L567:   aload 5
L569:   getfield Field gB char F
L572:   fload 15
L574:   fsub
L575:   invokestatic Method java/lang/Math abs (F)F
L578:   fadd
L579:   ldc 1e-4f
L581:   fcmpl
L582:   ifle L590
L585:   iconst_1
L586:   dup
L587:   dup
L588:   pop2
L589:   istore_2
L590:   aload 6
L592:   ifnull L673
L595:   aload_1
L596:   aload 6
L598:   dup_x1
L599:   dup_x2
L600:   aload_1
L601:   aload 6
L603:   dup
L604:   getfield Field gB case F
L607:   fstore 13
L609:   getfield Field gB char F
L612:   fstore 15
L614:   getfield Field qc catch F
L617:   fload 10
L619:   invokevirtual Method gB const (FF)V
L622:   getfield Field qc void F
L625:   aload_1
L626:   dup
L627:   getfield Field qc if F
L630:   swap
L631:   getfield Field qc break F
L634:   fadd
L635:   fload 10
L637:   fsub
L638:   invokevirtual Method gB catch (FF)V
L641:   getfield Field gB case F
L644:   fload 13
L646:   fsub
L647:   invokestatic Method java/lang/Math abs (F)F
L650:   aload 6
L652:   getfield Field gB char F
L655:   fload 15
L657:   fsub
L658:   invokestatic Method java/lang/Math abs (F)F
L661:   fadd
L662:   ldc 1e-4f
L664:   fcmpl
L665:   ifle L673
L668:   iconst_1
L669:   dup
L670:   dup
L671:   pop2
L672:   istore_2
L673:   aload_3
L674:   ifnull L752
L677:   aload_1
L678:   aload_3
L679:   dup_x1
L680:   dup_x2
L681:   aload_3
L682:   dup
L683:   getfield Field gB case F
L686:   fstore 13
L688:   getfield Field gB char F
L691:   fstore 15
L693:   fload 11
L695:   aload_1
L696:   getfield Field qc break F
L699:   fload 9
L701:   fsub
L702:   fload 10
L704:   fsub
L705:   invokevirtual Method gB const (FF)V
L708:   getfield Field qc void F
L711:   aload_1
L712:   getfield Field qc if F
L715:   fload 9
L717:   fadd
L718:   invokevirtual Method gB catch (FF)V
L721:   getfield Field gB case F
L724:   fload 13
L726:   fsub
L727:   invokestatic Method java/lang/Math abs (F)F
L730:   aload_3
L731:   getfield Field gB char F
L734:   fload 15
L736:   fsub
L737:   invokestatic Method java/lang/Math abs (F)F
L740:   fadd
L741:   ldc 1e-4f
L743:   fcmpl
L744:   ifle L752
L747:   iconst_1
L748:   dup
L749:   dup
L750:   pop2
L751:   istore_2
L752:   aload 4
L754:   ifnull L843
L757:   aload_1
L758:   aload 4
L760:   dup_x1
L761:   dup_x2
L762:   aload 4
L764:   dup
L765:   getfield Field gB case F
L768:   fstore 13
L770:   getfield Field gB char F
L773:   fstore 15
L775:   fload 12
L777:   aload_1
L778:   getfield Field qc break F
L781:   fload 9
L783:   fsub
L784:   fload 10
L786:   fsub
L787:   invokevirtual Method gB const (FF)V
L790:   getfield Field qc void F
L793:   aload_1
L794:   getfield Field qc catch F
L797:   fadd
L798:   fload 12
L800:   fsub
L801:   aload_1
L802:   getfield Field qc if F
L805:   fload 9
L807:   fadd
L808:   invokevirtual Method gB catch (FF)V
L811:   getfield Field gB case F
L814:   fload 13
L816:   fsub
L817:   invokestatic Method java/lang/Math abs (F)F
L820:   aload 4
L822:   getfield Field gB char F
L825:   fload 15
L827:   fsub
L828:   invokestatic Method java/lang/Math abs (F)F
L831:   fadd
L832:   ldc 1e-4f
L834:   fcmpl
L835:   ifle L843
L838:   iconst_1
L839:   dup
L840:   dup
L841:   pop2
L842:   istore_2
L843:   aload 7
L845:   invokeinterface InterfaceMethod java/util/List iterator ()Ljava/util/Iterator; 1
L850:   astore 13
L852:   aload 13
L854:   invokeinterface InterfaceMethod java/util/Iterator hasNext ()Z 1
L859:   ifeq L1012
L862:   aload 13
L864:   invokeinterface InterfaceMethod java/util/Iterator next ()Ljava/lang/Object; 1
L869:   checkcast gB
L872:   dup
L873:   astore 15
L875:   dup
L876:   aload_1
L877:   aload 15
L879:   dup_x2
L880:   aload 15
L882:   getfield Field gB case F
L885:   fstore_3
L886:   getfield Field gB char F
L889:   fstore 4
L891:   aload_1
L892:   dup
L893:   getfield Field qc catch F
L896:   fload 12
L898:   fsub
L899:   fload 11
L901:   fsub
L902:   fstore 5
L904:   getfield Field qc break F
L907:   fload 9
L909:   fsub
L910:   fload 10
L912:   fsub
L913:   fstore 6
L915:   getfield Field qc void F
L918:   fload 11
L920:   fadd
L921:   aload_1
L922:   getfield Field qc catch F
L925:   fload 11
L927:   fsub
L928:   fload 12
L930:   fsub
L931:   fload 5
L933:   fsub
L934:   aload 8
L936:   getfield Field Tf "enum" F
L939:   fmul
L940:   fadd
L941:   aload_1
L942:   getfield Field qc if F
L945:   fload 9
L947:   fadd
L948:   aload_1
L949:   getfield Field qc break F
L952:   fload 9
L954:   fsub
L955:   fload 10
L957:   fsub
L958:   fload 6
L960:   fsub
L961:   aload 8
L963:   getfield Field Tf do F
L966:   fmul
L967:   fadd
L968:   invokevirtual Method gB catch (FF)V
L971:   fload 5
L973:   fload 6
L975:   invokevirtual Method gB const (FF)V
L978:   getfield Field gB case F
L981:   fload_3
L982:   fsub
L983:   invokestatic Method java/lang/Math abs (F)F
L986:   aload 15
L988:   getfield Field gB char F
L991:   fload 4
L993:   fsub
L994:   invokestatic Method java/lang/Math abs (F)F
L997:   fadd
L998:   ldc 1e-4f
L1000:  fcmpl
L1001:  ifle L852
L1004:  iconst_1
L1005:  dup
L1006:  dup
L1007:  pop2
L1008:  istore_2
L1009:  goto L852
L1012:  iload_2
L1013:  ifeq L1021
L1016:  aload_0
L1017:  aload_1
L1018:  invokevirtual Method VD else (Lqc;)V
L1021:  return
L1022:  
        .attribute StackMap b'\x00\x21\x00\x32\x00\x0A\x07\x00\x02\x07\x00\x12\x01\x07\x00\x1F\x07\x00\x1F\x07\x00\x1F\x07\x00\x1F\x07\x00\x17\x07\x00\x08\x07\x00\x1D\x00\x00\x00\x5C\x00\x00\x00\x01\x07\x00\x2E\x00\x5D\x00\x0C\x07\x00\x02\x07\x00\x12\x01\x07\x00\x1F\x07\x00\x1F\x07\x00\x1F\x07\x00\x1F\x07\x00\x17\x07\x00\x08\x07\x00\x1D\x07\x00\x1F\x07\x00\x04\x00\x00\x00\x6C\x00\x00\x00\x01\x07\x00\x2E\x00\x6D\x00\x0C\x07\x00\x02\x07\x00\x12\x01\x07\x00\x1F\x07\x00\x1F\x07\x00\x1F\x07\x00\x1F\x07\x00\x17\x07\x00\x08\x07\x00\x1D\x07\x00\x1F\x07\x00\x04\x00\x00\x00\x7B\x00\x0C\x07\x00\x02\x07\x00\x12\x01\x07\x00\x1F\x07\x00\x1F\x07\x00\x1F\x07\x00\x1F\x07\x00\x17\x07\x00\x08\x07\x00\x1D\x07\x00\x1F\x07\x00\x04\x00\x00\x00\x8A\x00\x0C\x07\x00\x02\x07\x00\x12\x01\x07\x00\x1F\x07\x00\x1F\x07\x00\x1F\x07\x00\x1F\x07\x00\x17\x07\x00\x08\x07\x00\x1D\x07\x00\x1F\x07\x00\x04\x00\x00\x00\x97\x00\x0A\x07\x00\x02\x07\x00\x12\x01\x07\x00\x1F\x07\x00\x1F\x07\x00\x1F\x07\x00\x1F\x07\x00\x17\x07\x00\x08\x07\x00\x1D\x00\x00\x00\xA4\x00\x0A\x07\x00\x02\x07\x00\x12\x01\x07\x00\x1F\x07\x00\x1F\x07\x00\x1F\x07\x00\x1F\x07\x00\x17\x07\x00\x08\x07\x00\x1D\x00\x00\x00\xA5\x00\x0A\x07\x00\x02\x07\x00\x12\x01\x07\x00\x1F\x07\x00\x1F\x07\x00\x1F\x07\x00\x1F\x07\x00\x17\x07\x00\x08\x07\x00\x1D\x00\x01\x02\x00\xB4\x00\x0A\x07\x00\x02\x07\x00\x12\x01\x07\x00\x1F\x07\x00\x1F\x07\x00\x1F\x07\x00\x1F\x07\x00\x17\x07\x00\x08\x02\x00\x00\x00\xB5\x00\x0A\x07\x00\x02\x07\x00\x12\x01\x07\x00\x1F\x07\x00\x1F\x07\x00\x1F\x07\x00\x1F\x07\x00\x17\x07\x00\x08\x02\x00\x01\x02\x00\xC2\x00\x0B\x07\x00\x02\x07\x00\x12\x01\x07\x00\x1F\x07\x00\x1F\x07\x00\x1F\x07\x00\x1F\x07\x00\x17\x07\x00\x08\x02\x02\x00\x00\x00\xC3\x00\x0B\x07\x00\x02\x07\x00\x12\x01\x07\x00\x1F\x07\x00\x1F\x07\x00\x1F\x07\x00\x1F\x07\x00\x17\x07\x00\x08\x02\x02\x00\x01\x02\x00\xD2\x00\x0C\x07\x00\x02\x07\x00\x12\x01\x07\x00\x1F\x07\x00\x1F\x07\x00\x1F\x07\x00\x1F\x07\x00\x17\x07\x00\x08\x02\x02\x02\x00\x00\x00\xD3\x00\x0C\x07\x00\x02\x07\x00\x12\x01\x07\x00\x1F\x07\x00\x1F\x07\x00\x1F\x07\x00\x1F\x07\x00\x17\x07\x00\x08\x02\x02\x02\x00\x01\x02\x00\xE5\x00\x10\x07\x00\x02\x07\x00\x12\x01\x07\x00\x1F\x07\x00\x1F\x07\x00\x1F\x07\x00\x1F\x07\x00\x17\x07\x00\x08\x02\x02\x02\x02\x02\x02\x07\x00\x1D\x00\x01\x07\x00\x1D\x01\x16\x00\x10\x07\x00\x02\x07\x00\x12\x01\x07\x00\x1F\x07\x00\x1F\x07\x00\x1F\x07\x00\x1F\x07\x00\x17\x07\x00\x08\x02\x02\x02\x02\x02\x02\x07\x00\x1D\x00\x00\x01\x55\x00\x11\x07\x00\x02\x07\x00\x12\x01\x07\x00\x1F\x07\x00\x1F\x07\x00\x1F\x07\x00\x1F\x07\x00\x17\x07\x00\x08\x02\x02\x02\x02\x02\x02\x02\x02\x00\x00\x01\x76\x00\x11\x07\x00\x02\x07\x00\x12\x01\x07\x00\x1F\x07\x00\x1F\x07\x00\x1F\x07\x00\x1F\x07\x00\x17\x07\x00\x08\x02\x02\x02\x02\x02\x02\x02\x02\x00\x00\x01\x94\x00\x11\x07\x00\x02\x07\x00\x12\x01\x07\x00\x1F\x07\x00\x1F\x07\x00\x1F\x07\x00\x1F\x07\x00\x17\x07\x00\x08\x02\x02\x02\x02\x02\x02\x02\x02\x00\x00\x01\x96\x00\x11\x07\x00\x02\x07\x00\x12\x01\x07\x00\x1F\x07\x00\x1F\x07\x00\x1F\x07\x00\x1F\x07\x00\x17\x07\x00\x08\x02\x02\x02\x02\x02\x02\x02\x02\x00\x01\x02\x01\xC1\x00\x11\x07\x00\x02\x07\x00\x12\x01\x07\x00\x1F\x07\x00\x1F\x07\x00\x1F\x07\x00\x1F\x07\x00\x17\x07\x00\x08\x02\x02\x02\x02\x02\x02\x02\x02\x00\x00\x01\xE4\x00\x11\x07\x00\x02\x07\x00\x12\x01\x07\x00\x1F\x07\x00\x1F\x07\x00\x1F\x07\x00\x1F\x07\x00\x17\x07\x00\x08\x02\x02\x02\x02\x02\x02\x02\x02\x00\x00\x02\x04\x00\x11\x07\x00\x02\x07\x00\x12\x01\x07\x00\x1F\x07\x00\x1F\x07\x00\x1F\x07\x00\x1F\x07\x00\x17\x07\x00\x08\x02\x02\x02\x02\x02\x02\x02\x02\x00\x00\x02\x06\x00\x11\x07\x00\x02\x07\x00\x12\x01\x07\x00\x1F\x07\x00\x1F\x07\x00\x1F\x07\x00\x1F\x07\x00\x17\x07\x00\x08\x02\x02\x02\x02\x02\x02\x02\x02\x00\x01\x07\x00\x1F\x02\x4E\x00\x11\x07\x00\x02\x07\x00\x12\x01\x07\x00\x1F\x07\x00\x1F\x07\x00\x1F\x07\x00\x1F\x07\x00\x17\x07\x00\x08\x02\x02\x02\x02\x02\x02\x02\x02\x00\x00\x02\xA1\x00\x11\x07\x00\x02\x07\x00\x12\x01\x07\x00\x1F\x07\x00\x1F\x07\x00\x1F\x07\x00\x1F\x07\x00\x17\x07\x00\x08\x02\x02\x02\x02\x02\x02\x02\x02\x00\x00\x02\xF0\x00\x11\x07\x00\x02\x07\x00\x12\x01\x07\x00\x1F\x07\x00\x1F\x07\x00\x1F\x07\x00\x1F\x07\x00\x17\x07\x00\x08\x02\x02\x02\x02\x02\x02\x02\x02\x00\x00\x03\x4B\x00\x11\x07\x00\x02\x07\x00\x12\x01\x07\x00\x1F\x07\x00\x1F\x07\x00\x1F\x07\x00\x1F\x07\x00\x17\x07\x00\x08\x02\x02\x02\x02\x02\x02\x02\x02\x00\x00\x03\x54\x00\x11\x07\x00\x02\x07\x00\x12\x01\x00\x00\x00\x00\x07\x00\x17\x07\x00\x08\x02\x02\x02\x02\x07\x00\x1D\x02\x00\x02\x00\x00\x03\xF4\x00\x11\x07\x00\x02\x07\x00\x12\x01\x00\x00\x00\x00\x07\x00\x17\x07\x00\x08\x02\x02\x02\x02\x07\x00\x1D\x02\x00\x02\x00\x00\x03\xFD\x00\x11\x07\x00\x02\x07\x00\x12\x01\x00\x00\x00\x00\x07\x00\x17\x07\x00\x08\x02\x02\x02\x02\x07\x00\x1D\x02\x00\x02\x00\x00'
    .end code
.end method

.method public break : (Lqc;)V
    .code stack 6 locals 2
L0:     aload_0
L1:     aload_1
L2:     dup
L3:     dup_x2
L4:     aload_0
L5:     aload_1
L6:     invokespecial Method VD const (Lqc;)F
L9:     putfield Field qc case F
L12:    invokespecial Method VD short (Lqc;)F
L15:    putfield Field qc char F
L18:    return
L19:    
    .end code
.end method

.method public static <clinit> : ()V
    .code stack 4 locals 0
L0:     new java/lang/Object
L3:     dup
L4:     invokespecial Method java/lang/Object <init> ()V
L7:     putstatic Field VD do Ljava/lang/Object;
L10:    new java/lang/Object
L13:    dup
L14:    invokespecial Method java/lang/Object <init> ()V
L17:    putstatic Field VD else Ljava/lang/Object;
L20:    new java/lang/Object
L23:    dup
L24:    invokespecial Method java/lang/Object <init> ()V
L27:    putstatic Field VD "enum" Ljava/lang/Object;
L30:    new java/lang/Object
L33:    dup
L34:    invokespecial Method java/lang/Object <init> ()V
L37:    putstatic Field VD this Ljava/lang/Object;
L40:    new Tf
L43:    dup
L44:    ldc 5e-1f
L46:    dup
L47:    invokespecial Method Tf <init> (FF)V
L50:    putstatic Field VD char Ljava/lang/Object;
L53:    return
L54:    
    .end code
.end method
.innerclasses
    Tf VD [0] public static
.end innerclasses
.end class
