.version 49 0
.class public final super vd
.super java/lang/Object
.implements D
.field public field730 Ljava/lang/String;
.field public this Ljava/lang/String;
.field public field731 Ljava/lang/String;
.field public field732 Ljava/util/Map;
.field public field733 LPc;
.field public field734 Ljava/lang/String;

.method public <init> : (LMd;)V
    .code stack 8 locals 2
L0:     aload_0
L1:     aload_1
L2:     dup_x1
L3:     aload_1
L4:     aload_0
L5:     dup
L6:     dup_x2
L7:     invokespecial Method java/lang/Object <init> ()V
L10:    invokestatic Method Pc values ()[LPc;
L13:    aload_1
L14:    invokevirtual Method Md method886 ()I
L17:    aaload
L18:    putfield Field vd field733 LPc;
L21:    invokevirtual Method Md new ()Ljava/lang/String;
L24:    putfield Field vd field731 Ljava/lang/String;
L27:    invokevirtual Method Md try ()Ljava/lang/String;
L30:    putfield Field vd this Ljava/lang/String;
L33:    invokevirtual Method Md method892 ()Z
L36:    ifeq L47
L39:    aload_0
L40:    aload_1
L41:    invokevirtual Method Md method888 ()Ljava/util/Map;
L44:    putfield Field vd field732 Ljava/util/Map;
L47:    aload_0
L48:    dup
L49:    aload_1
L50:    dup_x1
L51:    invokevirtual Method Md try ()Ljava/lang/String;
L54:    putfield Field vd field730 Ljava/lang/String;
L57:    invokevirtual Method Md try ()Ljava/lang/String;
L60:    putfield Field vd field734 Ljava/lang/String;
L63:    return
L64:    
        .attribute StackMap b'\x00\x01\x00\x2F\x00\x02\x07\x00\x02\x07\x00\x20\x00\x00'
    .end code
    .exceptions java/io/IOException
.end method

.method public method94 : ()Z
    .code stack 3 locals 1
L0:     aload_0
L1:     getfield Field vd this Ljava/lang/String;
L4:     ifnonnull L13
L7:     iconst_1
L8:     dup
L9:     dup
L10:    pop2
L11:    ireturn
L12:    athrow
L13:    iconst_0
L14:    iconst_1
L15:    dup
L16:    pop2
L17:    ireturn
L18:    
        .attribute StackMap b'\x00\x02\x00\x0C\x00\x00\x00\x01\x07\x00\x42\x00\x0D\x00\x01\x07\x00\x02\x00\x00'
    .end code
.end method

.method public <init> : (LPc;Ljava/lang/String;Ljava/lang/String;Ljava/lang/String;)V
    .code stack 9 locals 5
L0:     aload 4
L2:     aload_0
L3:     dup_x1
L4:     aload_3
L5:     aload_2
L6:     aload_0
L7:     dup_x1
L8:     aload_1
L9:     aload_0
L10:    invokespecial Method java/lang/Object <init> ()V
L13:    putfield Field vd field733 LPc;
L16:    putfield Field vd field731 Ljava/lang/String;
L19:    putfield Field vd field730 Ljava/lang/String;
L22:    putfield Field vd field734 Ljava/lang/String;
L25:    return
L26:    
    .end code
.end method

.method public method227 : ()Z
    .code stack 3 locals 1
L0:     aload_0
L1:     getfield Field vd field732 Ljava/util/Map;
L4:     ifnull L13
L7:     iconst_1
L8:     dup
L9:     dup
L10:    pop2
L11:    ireturn
L12:    athrow
L13:    iconst_0
L14:    iconst_1
L15:    dup
L16:    pop2
L17:    ireturn
L18:    
        .attribute StackMap b'\x00\x02\x00\x0C\x00\x00\x00\x01\x07\x00\x42\x00\x0D\x00\x01\x07\x00\x02\x00\x00'
    .end code
.end method

.method public <init> : (LPc;Ljava/util/Map;Ljava/lang/String;Ljava/lang/String;Ljava/lang/String;Ljava/lang/String;)V
    .code stack 13 locals 7
L0:     aload 6
L2:     aload_0
L3:     dup_x1
L4:     aload 5
L6:     aload_2
L7:     aload_0
L8:     dup_x1
L9:     aload 4
L11:    aload_3
L12:    aload_0
L13:    dup_x1
L14:    aload_1
L15:    aload_0
L16:    invokespecial Method java/lang/Object <init> ()V
L19:    putfield Field vd field733 LPc;
L22:    putfield Field vd field731 Ljava/lang/String;
L25:    putfield Field vd this Ljava/lang/String;
L28:    putfield Field vd field732 Ljava/util/Map;
L31:    putfield Field vd field730 Ljava/lang/String;
L34:    putfield Field vd field734 Ljava/lang/String;
L37:    return
L38:    
    .end code
.end method

.method public method384 : (LAC;)V
    .code stack 9 locals 2
L0:     aload_1
L1:     aload_0
L2:     dup_x1
L3:     aload_0
L4:     aload_1
L5:     dup_x1
L6:     aload_1
L7:     aload_0
L8:     dup_x1
L9:     getfield Field vd field733 LPc;
L12:    invokevirtual Method Pc ordinal ()I
L15:    invokevirtual Method AC method691 (I)V
L18:    getfield Field vd field731 Ljava/lang/String;
L21:    invokevirtual Method AC method683 (Ljava/lang/String;)V
L24:    getfield Field vd this Ljava/lang/String;
L27:    invokevirtual Method AC method678 (Ljava/lang/String;)V
L30:    invokevirtual Method vd method227 ()Z
L33:    invokevirtual Method AC method684 (Z)V
L36:    invokevirtual Method vd method227 ()Z
L39:    ifeq L50
L42:    aload_1
L43:    aload_0
L44:    getfield Field vd field732 Ljava/util/Map;
L47:    invokevirtual Method AC method687 (Ljava/util/Map;)V
L50:    aload_1
L51:    dup
L52:    aload_0
L53:    dup_x1
L54:    getfield Field vd field730 Ljava/lang/String;
L57:    invokevirtual Method AC method678 (Ljava/lang/String;)V
L60:    getfield Field vd field734 Ljava/lang/String;
L63:    invokevirtual Method AC method678 (Ljava/lang/String;)V
L66:    return
L67:    
        .attribute StackMap b'\x00\x01\x00\x32\x00\x02\x07\x00\x02\x07\x00\x4C\x00\x00'
    .end code
    .exceptions java/io/IOException
.end method
.innerclasses
    Pc JB [0] public static final enum
.end innerclasses
.end class
