.version 49 0
.class public final super vf
.super Rg
.field public new F
.field public field237 F
.field public this F
.field public field242 I
.field public field243 Lff;
.field public field244 Z
.field public field245 LMd;

.method public <init> : (LMd;Led;LgE;)V
    .code stack 8 locals 4
L0:     aload_1
L1:     aload_0
L2:     dup_x1
L3:     aload_2
L4:     new java/util/LinkedList
L7:     aload_3
L8:     dup_x1
L9:     dup
L10:    pop2
L11:    dup
L12:    invokespecial Method java/util/LinkedList <init> ()V
L15:    invokespecial Method Rg <init> (Led;Lqd;Ljava/util/List;)V
L18:    invokevirtual Method vf method242 (LMd;)V
L21:    return
L22:    
    .end code
    .exceptions java/io/IOException
.end method

.method public method61 : ()V
    .code stack 2 locals 2
L0:     aload_0
L1:     getfield Field vf field220 Ljava/util/List;
L4:     invokeinterface InterfaceMethod java/util/List iterator ()Ljava/util/Iterator; 1
L9:     dup
L10:    astore_1
L11:    invokeinterface InterfaceMethod java/util/Iterator hasNext ()Z 1
L16:    ifeq L38
L19:    aload_1
L20:    invokeinterface InterfaceMethod java/util/Iterator next ()Ljava/lang/Object; 1
L25:    checkcast F
L28:    invokeinterface InterfaceMethod F try ()V 1
L33:    aload_1
L34:    goto L11
L37:    athrow
L38:    return
L39:    
        .attribute StackMap b'\x00\x03\x00\x0B\x00\x02\x07\x00\x02\x07\x00\x2D\x00\x01\x07\x00\x2D\x00\x25\x00\x00\x00\x01\x07\x00\x3B\x00\x26\x00\x02\x07\x00\x02\x07\x00\x2D\x00\x00'
    .end code
.end method

.method public method227 : ()Z
    .code stack 5 locals 1
L0:     aload_0
L1:     getfield Field vf field227 LqE;
L4:     getstatic Field qE this LqE;
L7:     if_acmpne L43
L10:    ldc 6e2f
L12:    aload_0
L13:    getfield Field vf new F
L16:    fmul
L17:    ldc 6e2f
L19:    aload_0
L20:    dup_x2
L21:    getfield Field vf field241 F
L24:    aload_0
L25:    getfield Field vf this F
L28:    fsub
L29:    aload_0
L30:    getfield Field vf new F
L33:    fmul
L34:    fadd
L35:    fdiv
L36:    putfield Field vf field212 F
L39:    goto L48
L42:    athrow
L43:    aload_0
L44:    fconst_0
L45:    putfield Field vf field212 F
L48:    iconst_0
L49:    iconst_1
L50:    dup
L51:    pop2
L52:    ireturn
L53:    
        .attribute StackMap b'\x00\x03\x00\x2A\x00\x00\x00\x01\x07\x00\x3B\x00\x2B\x00\x01\x07\x00\x02\x00\x00\x00\x30\x00\x01\x07\x00\x02\x00\x00'
    .end code
    .exceptions java/lang/Exception
.end method

.method public method8 : (LD;)V
    .code stack 0 locals 2
L0:     return
L1:     
    .end code
.end method

.method public method76 : ()V
    .code stack 4 locals 3
L0:     aload_0
L1:     getfield Field vf field243 Lff;
L4:     ifnull L51
L7:     aload_0
L8:     getfield Field vf field220 Ljava/util/List;
L11:    invokeinterface InterfaceMethod java/util/List iterator ()Ljava/util/Iterator; 1
L16:    dup
L17:    astore_1
L18:    invokeinterface InterfaceMethod java/util/Iterator hasNext ()Z 1
L23:    ifeq L51
L26:    aload_1
L27:    invokeinterface InterfaceMethod java/util/Iterator next ()Ljava/lang/Object; 1
L32:    checkcast F
L35:    astore_2
L36:    aload_1
L37:    aload_2
L38:    aload_0
L39:    getfield Field vf field243 Lff;
L42:    invokeinterface InterfaceMethod F method91 (Lff;)V 2
L47:    goto L18
L50:    athrow
L51:    aload_0
L52:    getfield Field vf field220 Ljava/util/List;
L55:    invokeinterface InterfaceMethod java/util/List iterator ()Ljava/util/Iterator; 1
L60:    dup
L61:    astore_1
L62:    invokeinterface InterfaceMethod java/util/Iterator hasNext ()Z 1
L67:    ifeq L91
L70:    aload_1
L71:    invokeinterface InterfaceMethod java/util/Iterator next ()Ljava/lang/Object; 1
L76:    checkcast F
L79:    astore_2
L80:    aload_1
L81:    aload_2
L82:    invokeinterface InterfaceMethod F method74 ()V 1
L87:    goto L62
L90:    athrow
L91:    aload_0
L92:    getfield Field vf field220 Ljava/util/List;
L95:    invokeinterface InterfaceMethod java/util/List iterator ()Ljava/util/Iterator; 1
L100:   dup
L101:   astore_1
L102:   invokeinterface InterfaceMethod java/util/Iterator hasNext ()Z 1
L107:   ifeq L130
L110:   aload_1
L111:   invokeinterface InterfaceMethod java/util/Iterator next ()Ljava/lang/Object; 1
L116:   checkcast F
L119:   astore_2
L120:   aload_1
L121:   aload_2
L122:   invokeinterface InterfaceMethod F method52 ()V 1
L127:   goto L102
L130:   aload_0
L131:   getfield Field vf field220 Ljava/util/List;
L134:   invokeinterface InterfaceMethod java/util/List iterator ()Ljava/util/Iterator; 1
L139:   dup
L140:   astore_1
L141:   invokeinterface InterfaceMethod java/util/Iterator hasNext ()Z 1
L146:   ifeq L169
L149:   aload_1
L150:   invokeinterface InterfaceMethod java/util/Iterator next ()Ljava/lang/Object; 1
L155:   checkcast F
L158:   astore_2
L159:   aload_1
L160:   aload_2
L161:   invokeinterface InterfaceMethod F method67 ()V 1
L166:   goto L141
L169:   aload_0
L170:   getfield Field vf field244 Z
L173:   ifeq L223
L176:   aload_0
L177:   getfield Field vf field220 Ljava/util/List;
L180:   invokeinterface InterfaceMethod java/util/List iterator ()Ljava/util/Iterator; 1
L185:   dup
L186:   astore_1
L187:   invokeinterface InterfaceMethod java/util/Iterator hasNext ()Z 1
L192:   ifeq L215
L195:   aload_1
L196:   invokeinterface InterfaceMethod java/util/Iterator next ()Ljava/lang/Object; 1
L201:   checkcast F
L204:   astore_2
L205:   aload_1
L206:   aload_2
L207:   invokeinterface InterfaceMethod F method56 ()V 1
L212:   goto L187
L215:   aload_0
L216:   iconst_0
L217:   iconst_1
L218:   dup
L219:   pop2
L220:   putfield Field vf field244 Z
L223:   aload_0
L224:   getfield Field vf field220 Ljava/util/List;
L227:   invokeinterface InterfaceMethod java/util/List iterator ()Ljava/util/Iterator; 1
L232:   dup
L233:   astore_1
L234:   invokeinterface InterfaceMethod java/util/Iterator hasNext ()Z 1
L239:   ifeq L262
L242:   aload_1
L243:   invokeinterface InterfaceMethod java/util/Iterator next ()Ljava/lang/Object; 1
L248:   checkcast F
L251:   astore_2
L252:   aload_1
L253:   aload_2
L254:   invokeinterface InterfaceMethod F new ()V 1
L259:   goto L234
L262:   return
L263:   
        .attribute StackMap b'\x00\x0F\x00\x12\x00\x02\x07\x00\x02\x07\x00\x2D\x00\x01\x07\x00\x2D\x00\x32\x00\x00\x00\x01\x07\x00\x3B\x00\x33\x00\x01\x07\x00\x02\x00\x00\x00\x3E\x00\x02\x07\x00\x02\x07\x00\x2D\x00\x01\x07\x00\x2D\x00\x5A\x00\x00\x00\x01\x07\x00\x3B\x00\x5B\x00\x02\x07\x00\x02\x07\x00\x2D\x00\x00\x00\x66\x00\x02\x07\x00\x02\x07\x00\x2D\x00\x01\x07\x00\x2D\x00\x82\x00\x02\x07\x00\x02\x07\x00\x2D\x00\x00\x00\x8D\x00\x02\x07\x00\x02\x07\x00\x2D\x00\x01\x07\x00\x2D\x00\xA9\x00\x02\x07\x00\x02\x07\x00\x2D\x00\x00\x00\xBB\x00\x02\x07\x00\x02\x07\x00\x2D\x00\x01\x07\x00\x2D\x00\xD7\x00\x02\x07\x00\x02\x07\x00\x2D\x00\x00\x00\xDF\x00\x02\x07\x00\x02\x07\x00\x2D\x00\x00\x00\xEA\x00\x02\x07\x00\x02\x07\x00\x2D\x00\x01\x07\x00\x2D\x01\x06\x00\x02\x07\x00\x02\x07\x00\x2D\x00\x00'
    .end code
.end method

.method public method238 : (Z)V
    .code stack 22 locals 11
L0:     aload_0
L1:     dup
L2:     getfield Field vf field241 F
L5:     aload_0
L6:     getfield Field vf field239 Lqd;
L9:     checkcast gE
L12:    getfield Field gE field771 F
L15:    fadd
L16:    putfield Field vf field241 F
L19:    aload_0
L20:    getfield Field vf field245 LMd;
L23:    invokevirtual Method Md method886 ()I
L26:    dup
L27:    istore_2
L28:    sipush 1024
L31:    iconst_1
L32:    dup
L33:    pop2
L34:    iand
L35:    ifeq L177
L38:    aload_0
L39:    dup
L40:    getstatic Field qE new LqE;
L43:    invokevirtual Method vf method226 (LqE;)V
L46:    getfield Field vf field239 Lqd;
L49:    getfield Field qd field766 Ljava/util/Map;
L52:    aload_0
L53:    dup
L54:    getfield Field vf field245 LMd;
L57:    invokevirtual Method Md method886 ()I
L60:    invokestatic Method java/lang/Integer valueOf (I)Ljava/lang/Integer;
L63:    invokeinterface InterfaceMethod java/util/Map put (Ljava/lang/Object;Ljava/lang/Object;)Ljava/lang/Object; 3
L68:    aload_0
L69:    dup
L70:    dup_x1
L71:    dup2
L72:    dup2
L73:    dup2
L74:    dup2
L75:    dup2
L76:    dup2
L77:    dup2
L78:    dup2
L79:    dup2
L80:    getfield Field vf field245 LMd;
L83:    invokevirtual Method Md method885 ()F
L86:    putfield Field vf field219 F
L89:    getfield Field vf field245 LMd;
L92:    invokevirtual Method Md method886 ()I
L95:    putfield Field vf field222 I
L98:    getfield Field vf field245 LMd;
L101:   invokevirtual Method Md method886 ()I
L104:   putfield Field vf field232 I
L107:   getfield Field vf field245 LMd;
L110:   invokevirtual Method Md method886 ()I
L113:   putfield Field vf field213 I
L116:   getfield Field vf field245 LMd;
L119:   invokevirtual Method Md method886 ()I
L122:   putfield Field vf field230 I
L125:   getfield Field vf field245 LMd;
L128:   invokevirtual Method Md method886 ()I
L131:   putfield Field vf field218 I
L134:   getfield Field vf field245 LMd;
L137:   invokevirtual Method Md method886 ()I
L140:   putfield Field vf true I
L143:   getfield Field vf field245 LMd;
L146:   invokevirtual Method Md method886 ()I
L149:   putfield Field vf field236 I
L152:   getfield Field vf field245 LMd;
L155:   invokevirtual Method Md method885 ()F
L158:   putfield Field vf field215 F
L161:   getfield Field vf field245 LMd;
L164:   invokevirtual Method Md method886 ()I
L167:   putfield Field vf field228 I
L170:   getstatic Field qE field631 LqE;
L173:   invokevirtual Method vf method226 (LqE;)V
L176:   pop
L177:   iload_2
L178:   bipush 32
L180:   iconst_1
L181:   dup
L182:   pop2
L183:   iand
L184:   ifeq L277
L187:   aload_0
L188:   dup
L189:   dup2
L190:   getfield Field vf field223 I
L193:   istore_3
L194:   getfield Field vf field245 LMd;
L197:   invokevirtual Method Md method886 ()I
L200:   dup_x1
L201:   putfield Field vf field225 I
L204:   putfield Field vf field223 I
L207:   iload_3
L208:   aload_0
L209:   getfield Field vf field241 F
L212:   aload_0
L213:   dup_x1
L214:   getfield Field vf field245 LMd;
L217:   invokevirtual Method Md method885 ()F
L220:   fadd
L221:   f2d
L222:   putfield Field vf field240 D
L225:   aload_0
L226:   getfield Field vf field223 I
L229:   if_icmpeq L277
L232:   aload_0
L233:   getfield Field vf field220 Ljava/util/List;
L236:   invokeinterface InterfaceMethod java/util/List iterator ()Ljava/util/Iterator; 1
L241:   dup
L242:   astore 4
L244:   invokeinterface InterfaceMethod java/util/Iterator hasNext ()Z 1
L249:   ifeq L277
L252:   aload 4
L254:   invokeinterface InterfaceMethod java/util/Iterator next ()Ljava/lang/Object; 1
L259:   checkcast F
L262:   astore 5
L264:   aload 4
L266:   aload 5
L268:   invokeinterface InterfaceMethod F method52 ()V 1
L273:   goto L244
L276:   athrow
L277:   iload_2
L278:   sipush 128
L281:   iconst_1
L282:   dup
L283:   pop2
L284:   iand
L285:   ifeq L371
L288:   aload_0
L289:   dup
L290:   dup_x1
L291:   dup2
L292:   dup2
L293:   dup2
L294:   getfield Field vf field245 LMd;
L297:   invokevirtual Method Md method886 ()I
L300:   putfield Field vf field242 I
L303:   getfield Field vf field245 LMd;
L306:   invokevirtual Method Md method886 ()I
L309:   putfield Field vf true I
L312:   getfield Field vf field245 LMd;
L315:   invokevirtual Method Md method886 ()I
L318:   putfield Field vf field232 I
L321:   getfield Field vf field245 LMd;
L324:   invokevirtual Method Md method885 ()F
L327:   putfield Field vf field215 F
L330:   getfield Field vf field220 Ljava/util/List;
L333:   invokeinterface InterfaceMethod java/util/List iterator ()Ljava/util/Iterator; 1
L338:   dup
L339:   astore_3
L340:   invokeinterface InterfaceMethod java/util/Iterator hasNext ()Z 1
L345:   ifeq L371
L348:   aload_3
L349:   invokeinterface InterfaceMethod java/util/Iterator next ()Ljava/lang/Object; 1
L354:   checkcast F
L357:   astore 4
L359:   aload_3
L360:   aload 4
L362:   invokeinterface InterfaceMethod F method89 ()V 1
L367:   goto L340
L370:   athrow
L371:   iload_2
L372:   sipush 2048
L375:   iconst_1
L376:   dup
L377:   pop2
L378:   iand
L379:   ifeq L719
L382:   aload_0
L383:   dup
L384:   dup_x1
L385:   dup2
L386:   getfield Field vf field245 LMd;
L389:   invokevirtual Method Md method891 ()[[I
L392:   astore_3
L393:   getfield Field vf field245 LMd;
L396:   invokestatic Method ff method468 (LMd;)Lff;
L399:   astore 4
L401:   getfield Field vf field245 LMd;
L404:   invokestatic Method ff method468 (LMd;)Lff;
L407:   astore 5
L409:   getfield Field vf field245 LMd;
L412:   invokevirtual Method Md method886 ()I
L415:   istore 6
L417:   getfield Field vf field245 LMd;
L420:   invokevirtual Method Md method886 ()I
L423:   istore 7
L425:   iload_2
L426:   bipush 8
L428:   iconst_1
L429:   dup
L430:   pop2
L431:   iand
L432:   ifeq L498
L435:   iload_1
L436:   ifeq L498
L439:   aload_0
L440:   dup
L441:   getfield Field vf field221 Lff;
L444:   swap
L445:   getfield Field vf this [[I
L448:   invokevirtual Method ff method470 ([[I)Z
L451:   ifeq L498
L454:   aload_0
L455:   getfield Field vf field220 Ljava/util/List;
L458:   invokeinterface InterfaceMethod java/util/List iterator ()Ljava/util/Iterator; 1
L463:   dup
L464:   astore 8
L466:   invokeinterface InterfaceMethod java/util/Iterator hasNext ()Z 1
L471:   ifeq L498
L474:   aload 8
L476:   invokeinterface InterfaceMethod java/util/Iterator next ()Ljava/lang/Object; 1
L481:   checkcast F
L484:   astore 9
L486:   aload 8
L488:   aload 9
L490:   invokeinterface InterfaceMethod F method84 ()V 1
L495:   goto L466
L498:   aload_0
L499:   dup
L500:   dup_x1
L501:   dup2
L502:   dup2
L503:   aload 5
L505:   aload_0
L506:   dup_x2
L507:   aload 4
L509:   aload_0
L510:   dup
L511:   dup_x1
L512:   aload_3
L513:   putfield Field vf this [[I
L516:   getfield Field vf field221 Lff;
L519:   putfield Field vf field243 Lff;
L522:   putfield Field vf field238 Lff;
L525:   putfield Field vf field221 Lff;
L528:   getfield Field vf field221 Lff;
L531:   iload 6
L533:   putfield Field ff field879 I
L536:   getfield Field vf field221 Lff;
L539:   iload 7
L541:   putfield Field ff field881 I
L544:   getfield Field vf field245 LMd;
L547:   invokevirtual Method Md method885 ()F
L550:   putfield Field vf new F
L553:   getfield Field vf field241 F
L556:   putfield Field vf this F
L559:   getfield Field vf field245 LMd;
L562:   invokevirtual Method Md method886 ()I
L565:   newarray int
L567:   iconst_1
L568:   dup
L569:   pop2
L570:   astore 8
L572:   iconst_0
L573:   iconst_1
L574:   dup
L575:   pop2
L576:   dup
L577:   istore 9
L579:   aload 8
L581:   arraylength
L582:   if_icmpge L605
L585:   aload 8
L587:   iload 9
L589:   aload_0
L590:   getfield Field vf field245 LMd;
L593:   invokevirtual Method Md method886 ()I
L596:   iinc 9 1
L599:   iastore
L600:   iload 9
L602:   goto L579
L605:   iload_1
L606:   ifeq L719
L609:   iload_2
L610:   bipush 8
L612:   iconst_1
L613:   dup
L614:   pop2
L615:   iand
L616:   ifeq L667
L619:   aload_0
L620:   getfield Field vf field220 Ljava/util/List;
L623:   invokeinterface InterfaceMethod java/util/List iterator ()Ljava/util/Iterator; 1
L628:   dup
L629:   astore 9
L631:   invokeinterface InterfaceMethod java/util/Iterator hasNext ()Z 1
L636:   ifeq L667
L639:   aload 9
L641:   invokeinterface InterfaceMethod java/util/Iterator next ()Ljava/lang/Object; 1
L646:   checkcast F
L649:   astore 10
L651:   aload 9
L653:   aload 10
L655:   aload_0
L656:   getfield Field vf field243 Lff;
L659:   invokeinterface InterfaceMethod F method91 (Lff;)V 2
L664:   goto L631
L667:   aload 8
L669:   arraylength
L670:   ifle L719
L673:   aload_0
L674:   getfield Field vf field220 Ljava/util/List;
L677:   invokeinterface InterfaceMethod java/util/List iterator ()Ljava/util/Iterator; 1
L682:   dup
L683:   astore 9
L685:   invokeinterface InterfaceMethod java/util/Iterator hasNext ()Z 1
L690:   ifeq L719
L693:   aload 9
L695:   invokeinterface InterfaceMethod java/util/Iterator next ()Ljava/lang/Object; 1
L700:   checkcast F
L703:   astore 10
L705:   aload 9
L707:   aload 10
L709:   aload 8
L711:   invokeinterface InterfaceMethod F method82 ([I)V 2
L716:   goto L685
L719:   iload_2
L720:   iconst_1
L721:   dup
L722:   dup
L723:   pop2
L724:   iand
L725:   ifeq L788
L728:   iload_1
L729:   aload_0
L730:   dup
L731:   getfield Field vf field221 Lff;
L734:   swap
L735:   getfield Field vf field245 LMd;
L738:   invokevirtual Method Md method886 ()I
L741:   putfield Field ff field879 I
L744:   ifeq L788
L747:   aload_0
L748:   getfield Field vf field220 Ljava/util/List;
L751:   invokeinterface InterfaceMethod java/util/List iterator ()Ljava/util/Iterator; 1
L756:   dup
L757:   astore_3
L758:   invokeinterface InterfaceMethod java/util/Iterator hasNext ()Z 1
L763:   ifeq L788
L766:   aload_3
L767:   invokeinterface InterfaceMethod java/util/Iterator next ()Ljava/lang/Object; 1
L772:   checkcast F
L775:   astore 4
L777:   aload_3
L778:   aload 4
L780:   invokeinterface InterfaceMethod F method67 ()V 1
L785:   goto L758
L788:   iload_2
L789:   iconst_2
L790:   iconst_1
L791:   dup
L792:   pop2
L793:   iand
L794:   ifeq L857
L797:   iload_1
L798:   aload_0
L799:   dup
L800:   getfield Field vf field221 Lff;
L803:   swap
L804:   getfield Field vf field245 LMd;
L807:   invokevirtual Method Md method886 ()I
L810:   putfield Field ff field881 I
L813:   ifeq L857
L816:   aload_0
L817:   getfield Field vf field220 Ljava/util/List;
L820:   invokeinterface InterfaceMethod java/util/List iterator ()Ljava/util/Iterator; 1
L825:   dup
L826:   astore_3
L827:   invokeinterface InterfaceMethod java/util/Iterator hasNext ()Z 1
L832:   ifeq L857
L835:   aload_3
L836:   invokeinterface InterfaceMethod java/util/Iterator next ()Ljava/lang/Object; 1
L841:   checkcast F
L844:   astore 4
L846:   aload_3
L847:   aload 4
L849:   invokeinterface InterfaceMethod F method67 ()V 1
L854:   goto L827
L857:   iload_2
L858:   iconst_4
L859:   iconst_1
L860:   dup
L861:   pop2
L862:   iand
L863:   ifeq L1081
L866:   aload_0
L867:   dup
L868:   getfield Field vf field245 LMd;
L871:   invokevirtual Method Md method886 ()I
L874:   istore_3
L875:   iconst_0
L876:   iconst_1
L877:   dup
L878:   pop2
L879:   istore 4
L881:   getfield Field vf field221 Lff;
L884:   getfield Field ff field877 I
L887:   iload_3
L888:   if_icmpeq L905
L891:   aload_0
L892:   iinc 4 1
L895:   dup
L896:   getfield Field vf field221 Lff;
L899:   invokevirtual Method ff method74 ()V
L902:   goto L881
L905:   iload_1
L906:   ifeq L1081
L909:   iload 4
L911:   tableswitch 1
            L936
            L987
            L1037
            default : L1081
L936:   aload_0
L937:   iconst_0
L938:   ifne L1034
L941:   getfield Field vf field220 Ljava/util/List;
L944:   invokeinterface InterfaceMethod java/util/List iterator ()Ljava/util/Iterator; 1
L949:   dup
L950:   astore 5
L952:   invokeinterface InterfaceMethod java/util/Iterator hasNext ()Z 1
L957:   ifeq L1081
L960:   aload 5
L962:   invokeinterface InterfaceMethod java/util/Iterator next ()Ljava/lang/Object; 1
L967:   checkcast F
L970:   astore 6
L972:   aload 5
L974:   aload 6
L976:   invokeinterface InterfaceMethod F method68 ()V 1
L981:   goto L952
L984:   nop
L985:   nop
L986:   athrow
L987:   aload_0
L988:   getfield Field vf field220 Ljava/util/List;
L991:   invokeinterface InterfaceMethod java/util/List iterator ()Ljava/util/Iterator; 1
L996:   dup
L997:   astore 5
L999:   invokeinterface InterfaceMethod java/util/Iterator hasNext ()Z 1
L1004:  ifeq L1081
L1007:  aload 5
L1009:  invokeinterface InterfaceMethod java/util/Iterator next ()Ljava/lang/Object; 1
L1014:  checkcast F
L1017:  astore 6
L1019:  aload 5
L1021:  aload 6
L1023:  invokeinterface InterfaceMethod F this ()V 1
L1028:  goto L999
L1031:  nop
L1032:  nop
L1033:  athrow
L1034:  goto L937
L1037:  aload_0
L1038:  getfield Field vf field220 Ljava/util/List;
L1041:  invokeinterface InterfaceMethod java/util/List iterator ()Ljava/util/Iterator; 1
L1046:  dup
L1047:  astore 5
L1049:  invokeinterface InterfaceMethod java/util/Iterator hasNext ()Z 1
L1054:  ifeq L1081
L1057:  aload 5
L1059:  invokeinterface InterfaceMethod java/util/Iterator next ()Ljava/lang/Object; 1
L1064:  checkcast F
L1067:  astore 6
L1069:  aload 5
L1071:  aload 6
L1073:  invokeinterface InterfaceMethod F method69 ()V 1
L1078:  goto L1049
L1081:  iload_2
L1082:  bipush 64
L1084:  iconst_1
L1085:  dup
L1086:  pop2
L1087:  iand
L1088:  ifeq L1231
L1091:  aload_0
L1092:  dup
L1093:  getfield Field vf field235 Ljava/util/LinkedList;
L1096:  invokevirtual Method java/util/LinkedList size ()I
L1099:  istore_3
L1100:  getfield Field vf field245 LMd;
L1103:  invokevirtual Method Md method886 ()I
L1106:  istore 4
L1108:  iload_3
L1109:  iload 4
L1111:  if_icmple L1147
L1114:  iconst_0
L1115:  iconst_1
L1116:  dup
L1117:  pop2
L1118:  dup
L1119:  istore 5
L1121:  iload_3
L1122:  iload 4
L1124:  isub
L1125:  if_icmpge L1231
L1128:  iinc 5 1
L1131:  aload_0
L1132:  getfield Field vf field235 Ljava/util/LinkedList;
L1135:  invokevirtual Method java/util/LinkedList removeLast ()Ljava/lang/Object;
L1138:  pop
L1139:  iload 5
L1141:  goto L1121
L1144:  nop
L1145:  nop
L1146:  athrow
L1147:  iload 4
L1149:  iload_3
L1150:  if_icmple L1231
L1153:  iconst_0
L1154:  iconst_1
L1155:  dup
L1156:  pop2
L1157:  dup
L1158:  istore 5
L1160:  iload 4
L1162:  iload_3
L1163:  isub
L1164:  if_icmpge L1187
L1167:  aload_0
L1168:  getfield Field vf field235 Ljava/util/LinkedList;
L1171:  iinc 5 1
L1174:  fconst_0
L1175:  invokestatic Method java/lang/Float valueOf (F)Ljava/lang/Float;
L1178:  invokevirtual Method java/util/LinkedList add (Ljava/lang/Object;)Z
L1181:  pop
L1182:  iload 5
L1184:  goto L1160
L1187:  aload_0
L1188:  getfield Field vf field220 Ljava/util/List;
L1191:  invokeinterface InterfaceMethod java/util/List iterator ()Ljava/util/Iterator; 1
L1196:  dup
L1197:  astore 5
L1199:  invokeinterface InterfaceMethod java/util/Iterator hasNext ()Z 1
L1204:  ifeq L1231
L1207:  aload 5
L1209:  invokeinterface InterfaceMethod java/util/Iterator next ()Ljava/lang/Object; 1
L1214:  checkcast F
L1217:  astore 6
L1219:  aload 5
L1221:  aload 6
L1223:  invokeinterface InterfaceMethod F method74 ()V 1
L1228:  goto L1199
L1231:  iload_2
L1232:  bipush 16
L1234:  iconst_1
L1235:  dup
L1236:  pop2
L1237:  iand
L1238:  ifeq L1341
L1241:  aload_0
L1242:  dup
L1243:  dup2
L1244:  getfield Field vf field245 LMd;
L1247:  invokevirtual Method Md method886 ()I
L1250:  istore_3
L1251:  getfield Field vf field245 LMd;
L1254:  invokevirtual Method Md method885 ()F
L1257:  putfield Field vf field237 F
L1260:  dup
L1261:  getfield Field vf field218 I
L1264:  iload_3
L1265:  iadd
L1266:  putfield Field vf field218 I
L1269:  iload_1
L1270:  ifeq L1341
L1273:  aload_0
L1274:  getfield Field vf field220 Ljava/util/List;
L1277:  invokeinterface InterfaceMethod java/util/List iterator ()Ljava/util/Iterator; 1
L1282:  dup
L1283:  astore 4
L1285:  invokeinterface InterfaceMethod java/util/Iterator hasNext ()Z 1
L1290:  ifeq L1341
L1293:  aload 4
L1295:  invokeinterface InterfaceMethod java/util/Iterator next ()Ljava/lang/Object; 1
L1300:  checkcast F
L1303:  dup
L1304:  astore 5
L1306:  iconst_m1
L1307:  iconst_1
L1308:  dup
L1309:  pop2
L1310:  bipush 7
L1312:  iconst_1
L1313:  dup
L1314:  pop2
L1315:  aload_0
L1316:  dup
L1317:  getfield Field vf field237 F
L1320:  swap
L1321:  getfield Field vf field239 Lqd;
L1324:  checkcast gE
L1327:  getfield Field gE field776 F
L1330:  fdiv
L1331:  invokeinterface InterfaceMethod F method73 (IIF)V 4
L1336:  aload 4
L1338:  goto L1285
L1341:  iload_2
L1342:  sipush 512
L1345:  iconst_1
L1346:  dup
L1347:  pop2
L1348:  iand
L1349:  ifeq L1419
L1352:  iload_1
L1353:  aload_0
L1354:  dup
L1355:  getfield Field vf field245 LMd;
L1358:  invokevirtual Method Md method886 ()I
L1361:  putfield Field vf try I
L1364:  ifeq L1411
L1367:  aload_0
L1368:  getfield Field vf field220 Ljava/util/List;
L1371:  invokeinterface InterfaceMethod java/util/List iterator ()Ljava/util/Iterator; 1
L1376:  dup
L1377:  astore_3
L1378:  invokeinterface InterfaceMethod java/util/Iterator hasNext ()Z 1
L1383:  ifeq L1419
L1386:  aload_3
L1387:  invokeinterface InterfaceMethod java/util/Iterator next ()Ljava/lang/Object; 1
L1392:  checkcast F
L1395:  astore 4
L1397:  aload_3
L1398:  aload 4
L1400:  invokeinterface InterfaceMethod F method56 ()V 1
L1405:  goto L1378
L1408:  nop
L1409:  nop
L1410:  athrow
L1411:  aload_0
L1412:  iconst_1
L1413:  dup
L1414:  dup
L1415:  pop2
L1416:  putfield Field vf field244 Z
L1419:  iload_2
L1420:  sipush 256
L1423:  iconst_1
L1424:  dup
L1425:  pop2
L1426:  iand
L1427:  ifeq L1636
L1430:  aload_0
L1431:  getfield Field vf field245 LMd;
L1434:  invokevirtual Method Md method886 ()I
L1437:  istore_3
L1438:  iconst_0
L1439:  iconst_1
L1440:  dup
L1441:  pop2
L1442:  istore 4
L1444:  iconst_0
L1445:  iconst_1
L1446:  dup
L1447:  pop2
L1448:  dup
L1449:  istore 5
L1451:  iload_3
L1452:  if_icmpge L1586
L1455:  aload_0
L1456:  getfield Field vf field239 Lqd;
L1459:  checkcast gE
L1462:  getfield Field gE try [Led;
L1465:  aload_0
L1466:  getfield Field vf field245 LMd;
L1469:  invokevirtual Method Md method886 ()I
L1472:  aaload
L1473:  astore 6
L1475:  aload_0
L1476:  dup
L1477:  getfield Field vf field245 LMd;
L1480:  invokevirtual Method Md method886 ()I
L1483:  istore 7
L1485:  getfield Field vf field245 LMd;
L1488:  invokevirtual Method Md method887 ()[I
L1491:  astore 8
L1493:  iload_1
L1494:  ifeq L1571
L1497:  aload_0
L1498:  dup
L1499:  getfield Field vf field239 Lqd;
L1502:  new uE
L1505:  dup
L1506:  aload_0
L1507:  getfield Field vf false Led;
L1510:  aload 6
L1512:  iload 7
L1514:  aload 8
L1516:  invokespecial Method uE <init> (Led;Led;I[I)V
L1519:  invokevirtual Method qd method8 (LD;)V
L1522:  getfield Field vf field220 Ljava/util/List;
L1525:  invokeinterface InterfaceMethod java/util/List iterator ()Ljava/util/Iterator; 1
L1530:  dup
L1531:  astore 9
L1533:  invokeinterface InterfaceMethod java/util/Iterator hasNext ()Z 1
L1538:  ifeq L1571
L1541:  aload 9
L1543:  invokeinterface InterfaceMethod java/util/Iterator next ()Ljava/lang/Object; 1
L1548:  checkcast F
L1551:  astore 10
L1553:  aload 9
L1555:  aload 10
L1557:  aload 6
L1559:  iload 7
L1561:  aload 8
L1563:  invokeinterface InterfaceMethod F method87 (Led;I[I)V 4
L1568:  goto L1533
L1571:  iload 4
L1573:  iinc 5 1
L1576:  iload 7
L1578:  iadd
L1579:  istore 4
L1581:  iload 5
L1583:  goto L1451
L1586:  iload_1
L1587:  ifeq L1636
L1590:  aload_0
L1591:  getfield Field vf field220 Ljava/util/List;
L1594:  invokeinterface InterfaceMethod java/util/List iterator ()Ljava/util/Iterator; 1
L1599:  dup
L1600:  astore 5
L1602:  invokeinterface InterfaceMethod java/util/Iterator hasNext ()Z 1
L1607:  ifeq L1636
L1610:  aload 5
L1612:  invokeinterface InterfaceMethod java/util/Iterator next ()Ljava/lang/Object; 1
L1617:  checkcast F
L1620:  astore 6
L1622:  aload 5
L1624:  aload 6
L1626:  iload 4
L1628:  invokeinterface InterfaceMethod F method64 (I)V 2
L1633:  goto L1602
L1636:  return
L1637:  
        .attribute StackMap b'\x00\x33\x00\xB1\x00\x03\x07\x00\x02\x01\x01\x00\x00\x00\xF4\x00\x05\x07\x00\x02\x01\x01\x01\x07\x00\x2D\x00\x01\x07\x00\x2D\x01\x14\x00\x00\x00\x01\x07\x00\x3B\x01\x15\x00\x03\x07\x00\x02\x01\x01\x00\x00\x01\x54\x00\x04\x07\x00\x02\x01\x01\x07\x00\x2D\x00\x01\x07\x00\x2D\x01\x72\x00\x00\x00\x01\x07\x00\x3B\x01\x73\x00\x03\x07\x00\x02\x01\x01\x00\x00\x01\xD2\x00\x09\x07\x00\x02\x01\x01\x07\x00\xDE\x07\x00\xCF\x07\x00\xCF\x01\x01\x07\x00\x2D\x00\x01\x07\x00\x2D\x01\xF2\x00\x08\x07\x00\x02\x01\x01\x07\x00\xDE\x07\x00\xCF\x07\x00\xCF\x01\x01\x00\x00\x02\x43\x00\x0A\x07\x00\x02\x01\x01\x07\x00\xDE\x07\x00\xCF\x07\x00\xCF\x01\x01\x07\x00\xEC\x01\x00\x01\x01\x02\x5D\x00\x0A\x07\x00\x02\x01\x01\x07\x00\xDE\x07\x00\xCF\x07\x00\xCF\x01\x01\x07\x00\xEC\x01\x00\x00\x02\x77\x00\x0A\x07\x00\x02\x01\x01\x07\x00\xDE\x07\x00\xCF\x07\x00\xCF\x01\x01\x07\x00\xEC\x07\x00\x2D\x00\x01\x07\x00\x2D\x02\x9B\x00\x09\x07\x00\x02\x01\x01\x07\x00\xDE\x07\x00\xCF\x07\x00\xCF\x01\x01\x07\x00\xEC\x00\x00\x02\xAD\x00\x0A\x07\x00\x02\x01\x01\x07\x00\xDE\x07\x00\xCF\x07\x00\xCF\x01\x01\x07\x00\xEC\x07\x00\x2D\x00\x01\x07\x00\x2D\x02\xCF\x00\x03\x07\x00\x02\x01\x01\x00\x00\x02\xF6\x00\x04\x07\x00\x02\x01\x01\x07\x00\x2D\x00\x01\x07\x00\x2D\x03\x14\x00\x03\x07\x00\x02\x01\x01\x00\x00\x03\x3B\x00\x04\x07\x00\x02\x01\x01\x07\x00\x2D\x00\x01\x07\x00\x2D\x03\x59\x00\x03\x07\x00\x02\x01\x01\x00\x00\x03\x71\x00\x05\x07\x00\x02\x01\x01\x01\x01\x00\x01\x07\x00\x02\x03\x89\x00\x05\x07\x00\x02\x01\x01\x01\x01\x00\x00\x03\xA8\x00\x05\x07\x00\x02\x01\x01\x01\x01\x00\x00\x03\xA9\x00\x05\x07\x00\x02\x01\x01\x01\x01\x00\x01\x07\x00\x02\x03\xB8\x00\x06\x07\x00\x02\x01\x01\x01\x01\x07\x00\x2D\x00\x01\x07\x00\x2D\x03\xD8\x00\x00\x00\x01\x07\x00\x3B\x03\xDB\x00\x05\x07\x00\x02\x01\x01\x01\x01\x00\x00\x03\xE7\x00\x06\x07\x00\x02\x01\x01\x01\x01\x07\x00\x2D\x00\x01\x07\x00\x2D\x04\x07\x00\x00\x00\x01\x07\x00\x3B\x04\x0A\x00\x05\x07\x00\x02\x01\x01\x01\x01\x00\x01\x07\x00\x02\x04\x0D\x00\x05\x07\x00\x02\x01\x01\x01\x01\x00\x00\x04\x19\x00\x06\x07\x00\x02\x01\x01\x01\x01\x07\x00\x2D\x00\x01\x07\x00\x2D\x04\x39\x00\x03\x07\x00\x02\x01\x01\x00\x00\x04\x61\x00\x06\x07\x00\x02\x01\x01\x01\x01\x01\x00\x01\x01\x04\x78\x00\x00\x00\x01\x07\x00\x3B\x04\x7B\x00\x05\x07\x00\x02\x01\x01\x01\x01\x00\x00\x04\x88\x00\x06\x07\x00\x02\x01\x01\x01\x01\x01\x00\x01\x01\x04\xA3\x00\x06\x07\x00\x02\x01\x01\x01\x01\x01\x00\x00\x04\xAF\x00\x06\x07\x00\x02\x01\x01\x01\x01\x07\x00\x2D\x00\x01\x07\x00\x2D\x04\xCF\x00\x03\x07\x00\x02\x01\x01\x00\x00\x05\x05\x00\x05\x07\x00\x02\x01\x01\x01\x07\x00\x2D\x00\x01\x07\x00\x2D\x05\x3D\x00\x03\x07\x00\x02\x01\x01\x00\x00\x05\x62\x00\x04\x07\x00\x02\x01\x01\x07\x00\x2D\x00\x01\x07\x00\x2D\x05\x80\x00\x00\x00\x01\x07\x00\x3B\x05\x83\x00\x03\x07\x00\x02\x01\x01\x00\x00\x05\x8B\x00\x03\x07\x00\x02\x01\x01\x00\x00\x05\xAB\x00\x06\x07\x00\x02\x01\x01\x01\x01\x01\x00\x01\x01\x05\xFD\x00\x0A\x07\x00\x02\x01\x01\x01\x01\x01\x07\x01\x2E\x01\x07\x00\xEC\x07\x00\x2D\x00\x01\x07\x00\x2D\x06\x23\x00\x09\x07\x00\x02\x01\x01\x01\x01\x01\x07\x01\x2E\x01\x07\x00\xEC\x00\x00\x06\x32\x00\x06\x07\x00\x02\x01\x01\x01\x01\x01\x00\x00\x06\x42\x00\x06\x07\x00\x02\x01\x01\x01\x01\x07\x00\x2D\x00\x01\x07\x00\x2D\x06\x64\x00\x03\x07\x00\x02\x01\x01\x00\x00'
    .end code
    .exceptions java/io/IOException
.end method

.method public method242 : (LMd;)V
    .code stack 16 locals 3
L0:     aload_0
L1:     dup
L2:     aload_1
L3:     putfield Field vf field245 LMd;
L6:     getfield Field vf field245 LMd;
L9:     invokevirtual Method Md method892 ()Z
L12:    ifeq L30
L15:    invokestatic Method sE values ()[LsE;
L18:    aload_0
L19:    dup_x1
L20:    getfield Field vf field245 LMd;
L23:    invokevirtual Method Md method886 ()I
L26:    aaload
L27:    invokevirtual Method vf method232 (LsE;)V
L30:    aload_0
L31:    dup
L32:    fconst_0
L33:    aload_0
L34:    dup_x2
L35:    aload_0
L36:    dup
L37:    dup2
L38:    dup2
L39:    dup2
L40:    dup2
L41:    getstatic Field qE field626 LqE;
L44:    invokevirtual Method vf method226 (LqE;)V
L47:    getfield Field vf field245 LMd;
L50:    invokevirtual Method Md method891 ()[[I
L53:    putfield Field vf this [[I
L56:    getfield Field vf field245 LMd;
L59:    invokestatic Method ff method468 (LMd;)Lff;
L62:    putfield Field vf field221 Lff;
L65:    getfield Field vf field221 Lff;
L68:    aload_0
L69:    getfield Field vf field245 LMd;
L72:    invokevirtual Method Md method886 ()I
L75:    putfield Field ff field879 I
L78:    getfield Field vf field221 Lff;
L81:    aload_0
L82:    getfield Field vf field245 LMd;
L85:    invokevirtual Method Md method886 ()I
L88:    putfield Field ff field881 I
L91:    getfield Field vf field245 LMd;
L94:    invokestatic Method ff method468 (LMd;)Lff;
L97:    putfield Field vf field238 Lff;
L100:   getfield Field vf field245 LMd;
L103:   invokevirtual Method Md method886 ()I
L106:   putfield Field vf try I
L109:   dup_x1
L110:   putfield Field vf this F
L113:   dup_x1
L114:   putfield Field vf new F
L117:   putfield Field vf field212 F
L120:   aload_0
L121:   getfield Field vf field245 LMd;
L124:   invokevirtual Method Md method886 ()I
L127:   istore_1
L128:   iconst_0
L129:   iconst_1
L130:   dup
L131:   pop2
L132:   dup
L133:   istore_2
L134:   iload_1
L135:   if_icmpge L158
L138:   aload_0
L139:   getfield Field vf field235 Ljava/util/LinkedList;
L142:   iinc 2 1
L145:   fconst_0
L146:   invokestatic Method java/lang/Float valueOf (F)Ljava/lang/Float;
L149:   invokevirtual Method java/util/LinkedList add (Ljava/lang/Object;)Z
L152:   pop
L153:   iload_2
L154:   goto L134
L157:   athrow
L158:   aload_0
L159:   dup
L160:   dup_x1
L161:   getfield Field vf field245 LMd;
L164:   invokevirtual Method Md method886 ()I
L167:   putfield Field vf field242 I
L170:   getfield Field vf field220 Ljava/util/List;
L173:   invokeinterface InterfaceMethod java/util/List iterator ()Ljava/util/Iterator; 1
L178:   dup
L179:   astore_2
L180:   invokeinterface InterfaceMethod java/util/Iterator hasNext ()Z 1
L185:   ifeq L209
L188:   aload_2
L189:   invokeinterface InterfaceMethod java/util/Iterator next ()Ljava/lang/Object; 1
L194:   checkcast F
L197:   astore_1
L198:   aload_2
L199:   aload_1
L200:   invokeinterface InterfaceMethod F try ()V 1
L205:   goto L180
L208:   athrow
L209:   aload_0
L210:   getfield Field vf field220 Ljava/util/List;
L213:   invokeinterface InterfaceMethod java/util/List iterator ()Ljava/util/Iterator; 1
L218:   dup
L219:   astore_2
L220:   invokeinterface InterfaceMethod java/util/Iterator hasNext ()Z 1
L225:   ifeq L252
L228:   aload_2
L229:   invokeinterface InterfaceMethod java/util/Iterator next ()Ljava/lang/Object; 1
L234:   checkcast F
L237:   astore_1
L238:   aload_2
L239:   aload_1
L240:   aload_0
L241:   getfield Field vf field243 Lff;
L244:   invokeinterface InterfaceMethod F method91 (Lff;)V 2
L249:   goto L220
L252:   aload_0
L253:   getfield Field vf field220 Ljava/util/List;
L256:   invokeinterface InterfaceMethod java/util/List iterator ()Ljava/util/Iterator; 1
L261:   dup
L262:   astore_2
L263:   invokeinterface InterfaceMethod java/util/Iterator hasNext ()Z 1
L268:   ifeq L291
L271:   aload_2
L272:   invokeinterface InterfaceMethod java/util/Iterator next ()Ljava/lang/Object; 1
L277:   checkcast F
L280:   astore_1
L281:   aload_2
L282:   aload_1
L283:   invokeinterface InterfaceMethod F method74 ()V 1
L288:   goto L263
L291:   aload_0
L292:   getfield Field vf field220 Ljava/util/List;
L295:   invokeinterface InterfaceMethod java/util/List iterator ()Ljava/util/Iterator; 1
L300:   dup
L301:   astore_2
L302:   invokeinterface InterfaceMethod java/util/Iterator hasNext ()Z 1
L307:   ifeq L330
L310:   aload_2
L311:   invokeinterface InterfaceMethod java/util/Iterator next ()Ljava/lang/Object; 1
L316:   checkcast F
L319:   astore_1
L320:   aload_2
L321:   aload_1
L322:   invokeinterface InterfaceMethod F method52 ()V 1
L327:   goto L302
L330:   aload_0
L331:   getfield Field vf field220 Ljava/util/List;
L334:   invokeinterface InterfaceMethod java/util/List iterator ()Ljava/util/Iterator; 1
L339:   dup
L340:   astore_2
L341:   invokeinterface InterfaceMethod java/util/Iterator hasNext ()Z 1
L346:   ifeq L369
L349:   aload_2
L350:   invokeinterface InterfaceMethod java/util/Iterator next ()Ljava/lang/Object; 1
L355:   checkcast F
L358:   astore_1
L359:   aload_2
L360:   aload_1
L361:   invokeinterface InterfaceMethod F method89 ()V 1
L366:   goto L341
L369:   aload_0
L370:   getfield Field vf field220 Ljava/util/List;
L373:   invokeinterface InterfaceMethod java/util/List iterator ()Ljava/util/Iterator; 1
L378:   dup
L379:   astore_2
L380:   invokeinterface InterfaceMethod java/util/Iterator hasNext ()Z 1
L385:   ifeq L408
L388:   aload_2
L389:   invokeinterface InterfaceMethod java/util/Iterator next ()Ljava/lang/Object; 1
L394:   checkcast F
L397:   astore_1
L398:   aload_2
L399:   aload_1
L400:   invokeinterface InterfaceMethod F method67 ()V 1
L405:   goto L380
L408:   aload_0
L409:   getfield Field vf field220 Ljava/util/List;
L412:   invokeinterface InterfaceMethod java/util/List iterator ()Ljava/util/Iterator; 1
L417:   dup
L418:   astore_2
L419:   invokeinterface InterfaceMethod java/util/Iterator hasNext ()Z 1
L424:   ifeq L447
L427:   aload_2
L428:   invokeinterface InterfaceMethod java/util/Iterator next ()Ljava/lang/Object; 1
L433:   checkcast F
L436:   astore_1
L437:   aload_2
L438:   aload_1
L439:   invokeinterface InterfaceMethod F method56 ()V 1
L444:   goto L419
L447:   aload_0
L448:   getfield Field vf field220 Ljava/util/List;
L451:   invokeinterface InterfaceMethod java/util/List iterator ()Ljava/util/Iterator; 1
L456:   dup
L457:   astore_2
L458:   invokeinterface InterfaceMethod java/util/Iterator hasNext ()Z 1
L463:   ifeq L486
L466:   aload_2
L467:   invokeinterface InterfaceMethod java/util/Iterator next ()Ljava/lang/Object; 1
L472:   checkcast F
L475:   astore_1
L476:   aload_2
L477:   aload_1
L478:   invokeinterface InterfaceMethod F new ()V 1
L483:   goto L458
L486:   return
L487:   
        .attribute StackMap b'\x00\x15\x00\x1E\x00\x02\x07\x00\x02\x07\x00\x79\x00\x00\x00\x86\x00\x03\x07\x00\x02\x01\x01\x00\x01\x01\x00\x9D\x00\x00\x00\x01\x07\x00\x3B\x00\x9E\x00\x03\x07\x00\x02\x01\x01\x00\x00\x00\xB4\x00\x03\x07\x00\x02\x00\x07\x00\x2D\x00\x01\x07\x00\x2D\x00\xD0\x00\x00\x00\x01\x07\x00\x3B\x00\xD1\x00\x03\x07\x00\x02\x00\x07\x00\x2D\x00\x00\x00\xDC\x00\x03\x07\x00\x02\x00\x07\x00\x2D\x00\x01\x07\x00\x2D\x00\xFC\x00\x03\x07\x00\x02\x00\x07\x00\x2D\x00\x00\x01\x07\x00\x03\x07\x00\x02\x00\x07\x00\x2D\x00\x01\x07\x00\x2D\x01\x23\x00\x03\x07\x00\x02\x00\x07\x00\x2D\x00\x00\x01\x2E\x00\x03\x07\x00\x02\x00\x07\x00\x2D\x00\x01\x07\x00\x2D\x01\x4A\x00\x03\x07\x00\x02\x00\x07\x00\x2D\x00\x00\x01\x55\x00\x03\x07\x00\x02\x00\x07\x00\x2D\x00\x01\x07\x00\x2D\x01\x71\x00\x03\x07\x00\x02\x00\x07\x00\x2D\x00\x00\x01\x7C\x00\x03\x07\x00\x02\x00\x07\x00\x2D\x00\x01\x07\x00\x2D\x01\x98\x00\x03\x07\x00\x02\x00\x07\x00\x2D\x00\x00\x01\xA3\x00\x03\x07\x00\x02\x00\x07\x00\x2D\x00\x01\x07\x00\x2D\x01\xBF\x00\x03\x07\x00\x02\x00\x07\x00\x2D\x00\x00\x01\xCA\x00\x03\x07\x00\x02\x00\x07\x00\x2D\x00\x01\x07\x00\x2D\x01\xE6\x00\x03\x07\x00\x02\x00\x07\x00\x2D\x00\x00'
    .end code
    .exceptions java/io/IOException
.end method
.end class
