.version 49 0
.class public final super wd
.super java/lang/Object
.implements java/lang/Runnable

.method public run : ()V
    .code stack 7 locals 3
L0:     getstatic Field Fg const Ljava/util/concurrent/LinkedBlockingDeque;
L3:     invokevirtual Method java/util/concurrent/LinkedBlockingDeque take ()Ljava/lang/Object;
L6:     checkcast Dc
L9:     astore_1
        .catch java/lang/reflect/InvocationTargetException from L10 to L99 using L114
L10:    aload_1
L11:    getfield Field Dc "enum" Ljava/lang/Object;
L14:    checkcast java/lang/Class
L17:    ldc "fetchIcon"
L19:    iconst_1
L20:    dup
L21:    dup
L22:    pop2
L23:    anewarray java/lang/Class
L26:    iconst_1
L27:    dup
L28:    pop2
L29:    dup
L30:    iconst_0
L31:    iconst_1
L32:    dup
L33:    pop2
L34:    ldc Class java/lang/String
L36:    aastore
L37:    invokevirtual Method java/lang/Class getDeclaredMethod (Ljava/lang/String;[Ljava/lang/Class;)Ljava/lang/reflect/Method;
L40:    aconst_null
L41:    iconst_1
L42:    dup
L43:    dup
L44:    pop2
L45:    anewarray java/lang/Object
L48:    iconst_1
L49:    dup
L50:    pop2
L51:    dup
L52:    iconst_0
L53:    iconst_1
L54:    dup
L55:    pop2
L56:    aload_1
L57:    getfield Field Dc do Ljava/lang/Object;
L60:    aastore
L61:    invokevirtual Method java/lang/reflect/Method invoke (Ljava/lang/Object;[Ljava/lang/Object;)Ljava/lang/Object;
L64:    checkcast java/nio/ByteBuffer
L67:    dup
L68:    astore_2
L69:    ifnull L100
L72:    getstatic Field Fg "enum" Ljava/util/concurrent/LinkedBlockingQueue;
L75:    new Zd
L78:    dup
L79:    aload_1
L80:    dup
L81:    getfield Field Dc "enum" Ljava/lang/Object;
L84:    swap
L85:    getfield Field Dc do Ljava/lang/Object;
L88:    aload_2
L89:    invokespecial Method Zd <init> (Ljava/lang/Object;Ljava/lang/Object;Ljava/lang/Object;)V
L92:    invokevirtual Method java/util/concurrent/LinkedBlockingQueue add (Ljava/lang/Object;)Z
L95:    pop
L96:    goto L0
L99:    athrow
        .catch java/lang/reflect/InvocationTargetException from L100 to L110 using L114
        .catch java/lang/InterruptedException from L0 to L99 using L136
        .catch java/lang/InterruptedException from L100 to L113 using L136
L100:   getstatic Field Fg this Ljava/util/Set;
L103:   aload_1
L104:   invokeinterface InterfaceMethod java/util/Set add (Ljava/lang/Object;)Z 2
L109:   pop
L110:   goto L0
L113:   athrow
        .catch java/lang/InterruptedException from L114 to L136 using L136
        .catch java/lang/NoSuchMethodException from L0 to L99 using L138
        .catch java/lang/NoSuchMethodException from L100 to L113 using L138
        .catch java/lang/NoSuchMethodException from L114 to L136 using L138
        .catch java/lang/IllegalAccessException from L0 to L99 using L144
        .catch java/lang/IllegalAccessException from L100 to L113 using L144
        .catch java/lang/IllegalAccessException from L114 to L136 using L144
L114:   astore_2
L115:   ldc2_w 4000L
L118:   aload_2
L119:   invokevirtual Method java/lang/reflect/InvocationTargetException printStackTrace ()V
L122:   invokestatic Method java/lang/Thread sleep (J)V
L125:   getstatic Field Fg const Ljava/util/concurrent/LinkedBlockingDeque;
L128:   aload_1
L129:   invokevirtual Method java/util/concurrent/LinkedBlockingDeque add (Ljava/lang/Object;)Z
L132:   pop
L133:   goto L0
L136:   astore_1
L137:   return
L138:   astore_1
L139:   aload_1
L140:   invokevirtual Method java/lang/NoSuchMethodException printStackTrace ()V
L143:   return
L144:   astore_1
L145:   aload_1
L146:   invokevirtual Method java/lang/IllegalAccessException printStackTrace ()V
L149:   return
L150:   
        .attribute StackMap b'\x00\x08\x00\x00\x00\x01\x07\x00\x02\x00\x00\x00\x63\x00\x00\x00\x01\x07\x00\x48\x00\x64\x00\x03\x07\x00\x02\x07\x00\x1E\x07\x00\x37\x00\x00\x00\x71\x00\x00\x00\x01\x07\x00\x48\x00\x72\x00\x02\x07\x00\x02\x07\x00\x1E\x00\x01\x07\x00\x0C\x00\x88\x00\x01\x07\x00\x02\x00\x01\x07\x00\x0E\x00\x8A\x00\x01\x07\x00\x02\x00\x01\x07\x00\x10\x00\x90\x00\x01\x07\x00\x02\x00\x01\x07\x00\x12'
    .end code
.end method

.method public <init> : ()V
    .code stack 1 locals 1
L0:     aload_0
L1:     invokespecial Method java/lang/Object <init> ()V
L4:     return
L5:     
    .end code
.end method
.innerclasses
    wd [0] [0] static
.end innerclasses
.enclosing method Fg [0]
.end class
