.version 49 0
.class public final super enum We
.super java/lang/Enum
.field public static final enum field467 LWe;
.field public while F
.field public field468 Z
.field public static final enum field469 LWe;
.field public static final enum field470 LWe;
.field public static final enum field471 LWe;
.field public static final enum field472 LWe;
.field public field473 F
.field public static final enum field474 LWe;
.field public static final enum field475 LWe;
.field public static final enum field476 LWe;
.field public static final enum field477 LWe;
.field public static final enum field478 LWe;
.field public static final enum false LWe;
.field public static final enum field479 LWe;
.field public static final enum field480 LWe;
.field public static final enum true LWe;
.field public field481 Z
.field public static final enum field482 LWe;
.field public field483 LvD;
.field public static final enum field484 LWe;
.field public field485 F
.field public field486 Z
.field public field487 Z
.field public static final enum field488 LWe;
.field public field489 F
.field public static final enum field490 LWe;
.field public static final enum try LWe;
.field public static final enum field491 LWe;
.field public static final enum new LWe;
.field public static final enum field492 LWe;
.field public this F
.field public static final enum field493 LWe;
.field private static final synthetic field494 [LWe;
.field public static final enum field495 LWe;
.field public static final field496 F = 2.5e-1f

.method public static values : ()[LWe;
    .code stack 1 locals 0
L0:     getstatic Field We field494 [LWe;
L3:     invokevirtual Method [LWe; clone ()Ljava/lang/Object;
L6:     checkcast [LWe;
L9:     areturn
L10:    
    .end code
.end method

.method public static <clinit> : ()V
    .code stack 16 locals 0
L0:     new We
L3:     dup
L4:     ldc "BIG_GRAY_LABEL"
L6:     iconst_0
L7:     iconst_1
L8:     dup
L9:     pop2
L10:    ldc 9e-1f
L12:    ldc 6e-1f
L14:    dup
L15:    dup_x1
L16:    fconst_1
L17:    getstatic Field vD field359 LvD;
L20:    iconst_1
L21:    dup
L22:    pop2
L23:    iconst_1
L24:    dup
L25:    pop2
L26:    iconst_0
L27:    iconst_1
L28:    dup
L29:    pop2
L30:    iconst_0
L31:    dup_x1
L32:    dup_x2
L33:    iconst_1
L34:    dup
L35:    pop2
L36:    invokespecial Method We <init> (Ljava/lang/String;IFFFFFLvD;ZZZZ)V
L39:    putstatic Field We field495 LWe;
L42:    new We
L45:    dup
L46:    ldc "BIG_LABEL"
L48:    iconst_1
L49:    dup
L50:    dup
L51:    pop2
L52:    ldc 7.5e-1f
L54:    fconst_1
L55:    dup
L56:    dup_x1
L57:    dup_x2
L58:    getstatic Field vD field358 LvD;
L61:    iconst_1
L62:    dup
L63:    pop2
L64:    iconst_1
L65:    dup
L66:    pop2
L67:    iconst_0
L68:    iconst_1
L69:    dup
L70:    pop2
L71:    iconst_0
L72:    dup_x1
L73:    dup_x2
L74:    iconst_1
L75:    dup
L76:    pop2
L77:    invokespecial Method We <init> (Ljava/lang/String;IFFFFFLvD;ZZZZ)V
L80:    putstatic Field We field475 LWe;
L83:    new We
L86:    dup
L87:    ldc "DEFAULT"
L89:    iconst_2
L90:    iconst_1
L91:    dup
L92:    pop2
L93:    ldc 2.8e-1f
L95:    ldc 6e-1f
L97:    dup
L98:    dup_x1
L99:    fconst_1
L100:   getstatic Field vD field359 LvD;
L103:   iconst_1
L104:   dup
L105:   pop2
L106:   iconst_1
L107:   dup
L108:   pop2
L109:   iconst_0
L110:   iconst_1
L111:   dup
L112:   pop2
L113:   iconst_0
L114:   dup_x1
L115:   dup_x2
L116:   iconst_1
L117:   dup
L118:   pop2
L119:   invokespecial Method We <init> (Ljava/lang/String;IFFFFFLvD;ZZZZ)V
L122:   putstatic Field We new LWe;
L125:   new We
L128:   dup
L129:   ldc "DIALOG_TITLE"
L131:   iconst_3
L132:   iconst_1
L133:   dup
L134:   pop2
L135:   ldc 2.8e-1f
L137:   fconst_1
L138:   dup
L139:   dup_x1
L140:   dup_x2
L141:   getstatic Field vD field359 LvD;
L144:   iconst_1
L145:   dup
L146:   pop2
L147:   iconst_1
L148:   dup
L149:   pop2
L150:   iconst_0
L151:   iconst_1
L152:   dup
L153:   pop2
L154:   iconst_0
L155:   dup_x1
L156:   dup_x2
L157:   iconst_1
L158:   dup
L159:   pop2
L160:   invokespecial Method We <init> (Ljava/lang/String;IFFFFFLvD;ZZZZ)V
L163:   putstatic Field We field474 LWe;
L166:   new We
L169:   dup
L170:   ldc "DIALOG_NOTE"
L172:   iconst_4
L173:   iconst_1
L174:   dup
L175:   pop2
L176:   ldc 2e-1f
L178:   ldc 6e-1f
L180:   dup
L181:   dup_x1
L182:   fconst_1
L183:   getstatic Field vD field359 LvD;
L186:   iconst_1
L187:   dup
L188:   pop2
L189:   iconst_1
L190:   dup
L191:   pop2
L192:   iconst_0
L193:   iconst_1
L194:   dup_x1
L195:   dup
L196:   pop2
L197:   iconst_0
L198:   dup_x2
L199:   iconst_1
L200:   dup
L201:   pop2
L202:   invokespecial Method We <init> (Ljava/lang/String;IFFFFFLvD;ZZZZ)V
L205:   putstatic Field We true LWe;
L208:   new We
L211:   dup
L212:   ldc "GAME_INFO"
L214:   iconst_5
L215:   iconst_1
L216:   dup
L217:   pop2
L218:   ldc 2.8e-1f
L220:   fconst_1
L221:   dup
L222:   dup_x1
L223:   dup_x2
L224:   getstatic Field vD field359 LvD;
L227:   iconst_1
L228:   dup
L229:   pop2
L230:   iconst_1
L231:   dup
L232:   pop2
L233:   iconst_0
L234:   iconst_1
L235:   dup
L236:   pop2
L237:   iconst_0
L238:   dup_x1
L239:   dup_x2
L240:   iconst_1
L241:   dup
L242:   pop2
L243:   invokespecial Method We <init> (Ljava/lang/String;IFFFFFLvD;ZZZZ)V
L246:   putstatic Field We field469 LWe;
L249:   new We
L252:   dup
L253:   ldc "MENU_BAR"
L255:   bipush 6
L257:   iconst_1
L258:   dup
L259:   pop2
L260:   ldc 4e-1f
L262:   ldc 6e-1f
L264:   dup
L265:   dup_x1
L266:   fconst_1
L267:   getstatic Field vD field359 LvD;
L270:   iconst_1
L271:   dup
L272:   pop2
L273:   iconst_1
L274:   dup
L275:   pop2
L276:   iconst_0
L277:   iconst_1
L278:   dup
L279:   pop2
L280:   iconst_0
L281:   dup_x1
L282:   dup_x2
L283:   iconst_1
L284:   dup
L285:   pop2
L286:   invokespecial Method We <init> (Ljava/lang/String;IFFFFFLvD;ZZZZ)V
L289:   putstatic Field We field493 LWe;
L292:   new We
L295:   dup
L296:   ldc "MENU_TITLE"
L298:   bipush 7
L300:   iconst_1
L301:   dup
L302:   pop2
L303:   fconst_1
L304:   dup
L305:   dup_x1
L306:   dup_x2
L307:   fconst_1
L308:   getstatic Field vD field359 LvD;
L311:   iconst_1
L312:   dup
L313:   pop2
L314:   iconst_1
L315:   dup
L316:   pop2
L317:   iconst_0
L318:   iconst_1
L319:   dup
L320:   pop2
L321:   iconst_0
L322:   dup_x1
L323:   dup_x2
L324:   iconst_1
L325:   dup
L326:   pop2
L327:   invokespecial Method We <init> (Ljava/lang/String;IFFFFFLvD;ZZZZ)V
L330:   putstatic Field We field477 LWe;
L333:   new We
L336:   dup
L337:   ldc "SMALL_LABEL"
L339:   bipush 8
L341:   iconst_1
L342:   dup
L343:   pop2
L344:   ldc 2e-1f
L346:   ldc 6e-1f
L348:   dup
L349:   dup_x1
L350:   fconst_1
L351:   getstatic Field vD field358 LvD;
L354:   iconst_1
L355:   dup
L356:   pop2
L357:   iconst_1
L358:   dup
L359:   pop2
L360:   iconst_0
L361:   iconst_1
L362:   dup
L363:   pop2
L364:   iconst_0
L365:   dup_x1
L366:   dup_x2
L367:   iconst_1
L368:   dup
L369:   pop2
L370:   invokespecial Method We <init> (Ljava/lang/String;IFFFFFLvD;ZZZZ)V
L373:   putstatic Field We try LWe;
L376:   new We
L379:   dup
L380:   ldc "COUNTRY_ISO_LABEL"
L382:   bipush 9
L384:   iconst_1
L385:   dup
L386:   pop2
L387:   ldc 1.5e-1f
L389:   ldc 6e-1f
L391:   dup
L392:   dup_x1
L393:   fconst_1
L394:   getstatic Field vD this LvD;
L397:   iconst_1
L398:   dup
L399:   pop2
L400:   iconst_1
L401:   dup
L402:   pop2
L403:   iconst_0
L404:   iconst_1
L405:   dup
L406:   pop2
L407:   iconst_0
L408:   dup_x1
L409:   dup_x2
L410:   iconst_1
L411:   dup
L412:   pop2
L413:   invokespecial Method We <init> (Ljava/lang/String;IFFFFFLvD;ZZZZ)V
L416:   putstatic Field We field482 LWe;
L419:   new We
L422:   dup
L423:   ldc "CHAT_USR_MESSAGE"
L425:   bipush 10
L427:   iconst_1
L428:   dup
L429:   pop2
L430:   ldc 2.5e-1f
L432:   ldc 6e-1f
L434:   dup
L435:   dup_x1
L436:   fconst_1
L437:   getstatic Field vD new LvD;
L440:   iconst_0
L441:   iconst_1
L442:   dup
L443:   pop2
L444:   iconst_0
L445:   iconst_1
L446:   dup
L447:   pop2
L448:   iconst_1
L449:   dup
L450:   pop2
L451:   iconst_1
L452:   dup
L453:   dup_x1
L454:   dup
L455:   pop2
L456:   invokespecial Method We <init> (Ljava/lang/String;IFFFFFLvD;ZZZZ)V
L459:   putstatic Field We field472 LWe;
L462:   new We
L465:   dup
L466:   ldc "CHAT_USR_NAME"
L468:   bipush 11
L470:   iconst_1
L471:   dup
L472:   pop2
L473:   ldc 2.5e-1f
L475:   ldc 6e-1f
L477:   dup
L478:   dup_x1
L479:   fconst_1
L480:   getstatic Field vD new LvD;
L483:   iconst_1
L484:   dup
L485:   pop2
L486:   iconst_1
L487:   dup
L488:   pop2
L489:   iconst_0
L490:   iconst_1
L491:   dup
L492:   pop2
L493:   iconst_0
L494:   dup_x1
L495:   dup_x2
L496:   iconst_1
L497:   dup
L498:   pop2
L499:   invokespecial Method We <init> (Ljava/lang/String;IFFFFFLvD;ZZZZ)V
L502:   putstatic Field We field491 LWe;
L505:   new We
L508:   dup
L509:   ldc "CHAT_STATUS"
L511:   bipush 12
L513:   iconst_1
L514:   dup
L515:   pop2
L516:   ldc 2e-1f
L518:   ldc 6e-1f
L520:   dup
L521:   dup_x1
L522:   fconst_1
L523:   getstatic Field vD new LvD;
L526:   iconst_1
L527:   dup
L528:   pop2
L529:   iconst_0
L530:   iconst_1
L531:   dup
L532:   pop2
L533:   iconst_1
L534:   dup
L535:   dup_x2
L536:   dup
L537:   pop2
L538:   iconst_0
L539:   iconst_1
L540:   dup
L541:   pop2
L542:   invokespecial Method We <init> (Ljava/lang/String;IFFFFFLvD;ZZZZ)V
L545:   putstatic Field We field476 LWe;
L548:   new We
L551:   dup
L552:   ldc "CONTEXT_MENU_LABEL"
L554:   bipush 13
L556:   iconst_1
L557:   dup
L558:   pop2
L559:   ldc 2.5e-1f
L561:   ldc 4e-1f
L563:   dup
L564:   dup_x1
L565:   fconst_1
L566:   getstatic Field vD field359 LvD;
L569:   iconst_1
L570:   dup
L571:   pop2
L572:   iconst_1
L573:   dup
L574:   pop2
L575:   iconst_0
L576:   iconst_1
L577:   dup
L578:   pop2
L579:   iconst_0
L580:   dup_x1
L581:   dup_x2
L582:   iconst_1
L583:   dup
L584:   pop2
L585:   invokespecial Method We <init> (Ljava/lang/String;IFFFFFLvD;ZZZZ)V
L588:   putstatic Field We field471 LWe;
L591:   new We
L594:   dup
L595:   ldc "CONTEXT_MENU_IMPORTANT"
L597:   bipush 14
L599:   iconst_1
L600:   dup
L601:   pop2
L602:   ldc 2.5e-1f
L604:   fconst_1
L605:   dup
L606:   dup_x1
L607:   dup_x2
L608:   getstatic Field vD field359 LvD;
L611:   iconst_1
L612:   dup
L613:   pop2
L614:   iconst_0
L615:   iconst_1
L616:   dup
L617:   pop2
L618:   iconst_0
L619:   iconst_1
L620:   dup_x2
L621:   dup
L622:   pop2
L623:   iconst_0
L624:   iconst_1
L625:   dup
L626:   pop2
L627:   invokespecial Method We <init> (Ljava/lang/String;IFFFFFLvD;ZZZZ)V
L630:   putstatic Field We field488 LWe;
L633:   new We
L636:   dup
L637:   ldc "CHALLENGE_TITLE"
L639:   bipush 15
L641:   iconst_1
L642:   dup
L643:   pop2
L644:   ldc 5e-1f
L646:   ldc 6e-1f
L648:   dup
L649:   dup_x1
L650:   fconst_1
L651:   getstatic Field vD field359 LvD;
L654:   iconst_1
L655:   dup
L656:   pop2
L657:   iconst_1
L658:   dup
L659:   pop2
L660:   iconst_0
L661:   iconst_1
L662:   dup_x1
L663:   dup
L664:   pop2
L665:   iconst_0
L666:   dup_x2
L667:   iconst_1
L668:   dup
L669:   pop2
L670:   invokespecial Method We <init> (Ljava/lang/String;IFFFFFLvD;ZZZZ)V
L673:   putstatic Field We field467 LWe;
L676:   new We
L679:   dup
L680:   ldc "CHALLENGE_DETAIL"
L682:   bipush 16
L684:   iconst_1
L685:   dup
L686:   pop2
L687:   ldc 2.8e-1f
L689:   ldc 6e-1f
L691:   dup
L692:   dup_x1
L693:   fconst_1
L694:   getstatic Field vD field359 LvD;
L697:   iconst_1
L698:   dup
L699:   pop2
L700:   iconst_1
L701:   dup
L702:   pop2
L703:   iconst_0
L704:   iconst_1
L705:   dup_x1
L706:   dup
L707:   pop2
L708:   iconst_0
L709:   dup_x2
L710:   iconst_1
L711:   dup
L712:   pop2
L713:   invokespecial Method We <init> (Ljava/lang/String;IFFFFFLvD;ZZZZ)V
L716:   putstatic Field We field479 LWe;
L719:   new We
L722:   dup
L723:   ldc "ACHIEVEMENT_TITLE"
L725:   bipush 17
L727:   iconst_1
L728:   dup
L729:   pop2
L730:   ldc 4e-1f
L732:   ldc 6e-1f
L734:   dup
L735:   dup_x1
L736:   fconst_1
L737:   getstatic Field vD field359 LvD;
L740:   iconst_1
L741:   dup
L742:   pop2
L743:   iconst_1
L744:   dup
L745:   pop2
L746:   iconst_0
L747:   iconst_1
L748:   dup
L749:   pop2
L750:   iconst_0
L751:   dup_x1
L752:   dup_x2
L753:   iconst_1
L754:   dup
L755:   pop2
L756:   invokespecial Method We <init> (Ljava/lang/String;IFFFFFLvD;ZZZZ)V
L759:   putstatic Field We field478 LWe;
L762:   new We
L765:   dup
L766:   ldc "ACHIEVEMENT_POINTS"
L768:   bipush 18
L770:   iconst_1
L771:   dup
L772:   pop2
L773:   ldc 9e-1f
L775:   ldc 6e-1f
L777:   dup
L778:   dup_x1
L779:   fconst_1
L780:   getstatic Field vD field357 LvD;
L783:   iconst_1
L784:   dup
L785:   pop2
L786:   iconst_1
L787:   dup
L788:   pop2
L789:   iconst_0
L790:   iconst_1
L791:   dup
L792:   pop2
L793:   iconst_0
L794:   dup_x1
L795:   dup_x2
L796:   iconst_1
L797:   dup
L798:   pop2
L799:   invokespecial Method We <init> (Ljava/lang/String;IFFFFFLvD;ZZZZ)V
L802:   putstatic Field We field492 LWe;
L805:   new We
L808:   dup
L809:   ldc "ACHIEVEMENT_DESCRIPTION"
L811:   bipush 19
L813:   iconst_1
L814:   dup
L815:   pop2
L816:   ldc 2.8e-1f
L818:   ldc 6e-1f
L820:   dup
L821:   dup_x1
L822:   fconst_1
L823:   getstatic Field vD field359 LvD;
L826:   iconst_1
L827:   dup
L828:   pop2
L829:   iconst_1
L830:   dup
L831:   pop2
L832:   iconst_0
L833:   iconst_1
L834:   dup_x1
L835:   dup
L836:   pop2
L837:   iconst_0
L838:   dup_x2
L839:   iconst_1
L840:   dup
L841:   pop2
L842:   invokespecial Method We <init> (Ljava/lang/String;IFFFFFLvD;ZZZZ)V
L845:   putstatic Field We field480 LWe;
L848:   new We
L851:   dup
L852:   ldc "CREDITS_TITLE"
L854:   bipush 20
L856:   iconst_1
L857:   dup
L858:   pop2
L859:   ldc 7.5e-1f
L861:   fconst_1
L862:   dup
L863:   dup_x1
L864:   dup_x2
L865:   getstatic Field vD field359 LvD;
L868:   iconst_1
L869:   dup
L870:   pop2
L871:   iconst_1
L872:   dup
L873:   pop2
L874:   iconst_0
L875:   iconst_1
L876:   dup
L877:   pop2
L878:   iconst_0
L879:   dup_x1
L880:   dup_x2
L881:   iconst_1
L882:   dup
L883:   pop2
L884:   invokespecial Method We <init> (Ljava/lang/String;IFFFFFLvD;ZZZZ)V
L887:   putstatic Field We false LWe;
L890:   new We
L893:   dup
L894:   ldc "CREDITS_HEADER"
L896:   bipush 21
L898:   iconst_1
L899:   dup
L900:   pop2
L901:   ldc 2e-1f
L903:   fconst_1
L904:   dup
L905:   dup_x1
L906:   dup_x2
L907:   getstatic Field vD field359 LvD;
L910:   iconst_1
L911:   dup
L912:   pop2
L913:   iconst_1
L914:   dup
L915:   pop2
L916:   iconst_0
L917:   iconst_1
L918:   dup
L919:   pop2
L920:   iconst_0
L921:   dup_x1
L922:   dup_x2
L923:   iconst_1
L924:   dup
L925:   pop2
L926:   invokespecial Method We <init> (Ljava/lang/String;IFFFFFLvD;ZZZZ)V
L929:   putstatic Field We field490 LWe;
L932:   new We
L935:   dup
L936:   ldc "CREDITS_TEXT"
L938:   bipush 22
L940:   iconst_1
L941:   dup
L942:   pop2
L943:   ldc 4e-1f
L945:   fconst_1
L946:   dup
L947:   dup_x1
L948:   dup_x2
L949:   getstatic Field vD field359 LvD;
L952:   iconst_1
L953:   dup
L954:   pop2
L955:   iconst_1
L956:   dup
L957:   pop2
L958:   iconst_1
L959:   dup
L960:   dup
L961:   pop2
L962:   iconst_0
L963:   dup_x1
L964:   dup_x2
L965:   iconst_1
L966:   dup
L967:   pop2
L968:   invokespecial Method We <init> (Ljava/lang/String;IFFFFFLvD;ZZZZ)V
L971:   putstatic Field We field484 LWe;
L974:   new We
L977:   dup
L978:   ldc "ROOM_DETAIL_TITLE"
L980:   bipush 23
L982:   iconst_1
L983:   dup
L984:   pop2
L985:   ldc 4e-1f
L987:   fconst_1
L988:   dup
L989:   dup_x1
L990:   dup_x2
L991:   getstatic Field vD field359 LvD;
L994:   iconst_1
L995:   dup
L996:   pop2
L997:   iconst_1
L998:   dup
L999:   pop2
L1000:  iconst_0
L1001:  iconst_1
L1002:  dup
L1003:  pop2
L1004:  iconst_0
L1005:  dup_x1
L1006:  dup_x2
L1007:  iconst_1
L1008:  dup
L1009:  pop2
L1010:  invokespecial Method We <init> (Ljava/lang/String;IFFFFFLvD;ZZZZ)V
L1013:  putstatic Field We field470 LWe;
L1016:  bipush 24
L1018:  iconst_1
L1019:  dup
L1020:  pop2
L1021:  anewarray We
L1024:  iconst_1
L1025:  dup
L1026:  pop2
L1027:  dup
L1028:  iconst_0
L1029:  iconst_1
L1030:  dup
L1031:  pop2
L1032:  getstatic Field We field495 LWe;
L1035:  aastore
L1036:  dup
L1037:  iconst_1
L1038:  dup
L1039:  dup
L1040:  pop2
L1041:  getstatic Field We field475 LWe;
L1044:  aastore
L1045:  dup
L1046:  iconst_2
L1047:  iconst_1
L1048:  dup
L1049:  pop2
L1050:  getstatic Field We new LWe;
L1053:  aastore
L1054:  dup
L1055:  iconst_3
L1056:  iconst_1
L1057:  dup
L1058:  pop2
L1059:  getstatic Field We field474 LWe;
L1062:  aastore
L1063:  dup
L1064:  iconst_4
L1065:  iconst_1
L1066:  dup
L1067:  pop2
L1068:  getstatic Field We true LWe;
L1071:  aastore
L1072:  dup
L1073:  iconst_5
L1074:  iconst_1
L1075:  dup
L1076:  pop2
L1077:  getstatic Field We field469 LWe;
L1080:  aastore
L1081:  dup
L1082:  bipush 6
L1084:  iconst_1
L1085:  dup
L1086:  pop2
L1087:  getstatic Field We field493 LWe;
L1090:  aastore
L1091:  dup
L1092:  bipush 7
L1094:  iconst_1
L1095:  dup
L1096:  pop2
L1097:  getstatic Field We field477 LWe;
L1100:  aastore
L1101:  dup
L1102:  bipush 8
L1104:  iconst_1
L1105:  dup
L1106:  pop2
L1107:  getstatic Field We try LWe;
L1110:  aastore
L1111:  dup
L1112:  bipush 9
L1114:  iconst_1
L1115:  dup
L1116:  pop2
L1117:  getstatic Field We field482 LWe;
L1120:  aastore
L1121:  dup
L1122:  bipush 10
L1124:  iconst_1
L1125:  dup
L1126:  pop2
L1127:  getstatic Field We field472 LWe;
L1130:  aastore
L1131:  dup
L1132:  bipush 11
L1134:  iconst_1
L1135:  dup
L1136:  pop2
L1137:  getstatic Field We field491 LWe;
L1140:  aastore
L1141:  dup
L1142:  bipush 12
L1144:  iconst_1
L1145:  dup
L1146:  pop2
L1147:  getstatic Field We field476 LWe;
L1150:  aastore
L1151:  dup
L1152:  bipush 13
L1154:  iconst_1
L1155:  dup
L1156:  pop2
L1157:  getstatic Field We field471 LWe;
L1160:  aastore
L1161:  dup
L1162:  bipush 14
L1164:  iconst_1
L1165:  dup
L1166:  pop2
L1167:  getstatic Field We field488 LWe;
L1170:  aastore
L1171:  dup
L1172:  bipush 15
L1174:  iconst_1
L1175:  dup
L1176:  pop2
L1177:  getstatic Field We field467 LWe;
L1180:  aastore
L1181:  dup
L1182:  bipush 16
L1184:  iconst_1
L1185:  dup
L1186:  pop2
L1187:  getstatic Field We field479 LWe;
L1190:  aastore
L1191:  dup
L1192:  bipush 17
L1194:  iconst_1
L1195:  dup
L1196:  pop2
L1197:  getstatic Field We field478 LWe;
L1200:  aastore
L1201:  dup
L1202:  bipush 18
L1204:  iconst_1
L1205:  dup
L1206:  pop2
L1207:  getstatic Field We field492 LWe;
L1210:  aastore
L1211:  dup
L1212:  bipush 19
L1214:  iconst_1
L1215:  dup
L1216:  pop2
L1217:  getstatic Field We field480 LWe;
L1220:  aastore
L1221:  dup
L1222:  bipush 20
L1224:  iconst_1
L1225:  dup
L1226:  pop2
L1227:  getstatic Field We false LWe;
L1230:  aastore
L1231:  dup
L1232:  bipush 21
L1234:  iconst_1
L1235:  dup
L1236:  pop2
L1237:  getstatic Field We field490 LWe;
L1240:  aastore
L1241:  dup
L1242:  bipush 22
L1244:  iconst_1
L1245:  dup
L1246:  pop2
L1247:  getstatic Field We field484 LWe;
L1250:  aastore
L1251:  dup
L1252:  bipush 23
L1254:  iconst_1
L1255:  dup
L1256:  pop2
L1257:  getstatic Field We field470 LWe;
L1260:  aastore
L1261:  putstatic Field We field494 [LWe;
L1264:  return
L1265:  
    .end code
.end method

.method public static valueOf : (Ljava/lang/String;)LWe;
    .code stack 2 locals 1
L0:     ldc Class We
L2:     aload_0
L3:     invokestatic Method java/lang/Enum valueOf (Ljava/lang/Class;Ljava/lang/String;)Ljava/lang/Enum;
L6:     checkcast We
L9:     areturn
L10:    
    .end code
.end method

.method private <init> : (Ljava/lang/String;IFFFFFLvD;ZZZZ)V
    .code stack 23 locals 13
L0:     iload 12
L2:     aload_0
L3:     dup_x1
L4:     iload 11
L6:     iload 10
L8:     aload_0
L9:     dup_x1
L10:    iload 9
L12:    aload 8
L14:    aload_0
L15:    dup_x1
L16:    fload 7
L18:    fload 6
L20:    aload_0
L21:    dup_x1
L22:    fload 5
L24:    fload 4
L26:    aload_0
L27:    dup_x1
L28:    fload_3
L29:    aload_0
L30:    aload_1
L31:    iload_2
L32:    invokespecial Method java/lang/Enum <init> (Ljava/lang/String;I)V
L35:    putfield Field We field489 F
L38:    putfield Field We while F
L41:    putfield Field We field485 F
L44:    putfield Field We this F
L47:    putfield Field We field473 F
L50:    putfield Field We field483 LvD;
L53:    putfield Field We field486 Z
L56:    putfield Field We field468 Z
L59:    putfield Field We field487 Z
L62:    putfield Field We field481 Z
L65:    return
L66:    
    .end code
.end method
.innerclasses
    vD DF [0] public static final enum
.end innerclasses
.end class
