.version 49 0
.class public final super wF
.super td
.field public instanceof [[I
.field public static final "protected" I = 4
.field public import Z
.field public "native" I
.field public throws F
.field public static final "static" I = 1024
.field public continue Lff;
.field public extends I
.field public static final float I = 2
.field public "final" D
.field public catch LNE;
.field public static final false I = 128
.field public static final class I = 512
.field public static final if I = 16
.field public true F
.field public static final for I = 32
.field public case Lff;
.field public byte I
.field public "super" Ljava/util/List;
.field public static final int I = 1
.field public short I
.field public static final goto I = 0
.field public break Z
.field public static final long I = 2048
.field public void I
.field public try I
.field public const I
.field public new LRg;
.field public null LAC;
.field public this Ljava/util/List;
.field public static final char I = 64
.field public static final else I = 256
.field public static final "enum" I = 8
.field public do I

.method public <init> : (LNE;LRg;LAC;)V
    .code stack 9 locals 4
L0:     aload_0
L1:     dup
L2:     aload_3
L3:     aload_0
L4:     dup_x1
L5:     aload_2
L6:     aload_1
L7:     aload_0
L8:     dup_x1
L9:     invokespecial Method td <init> ()V
L12:    putfield Field wF catch LNE;
L15:    putfield Field wF new LRg;
L18:    putfield Field wF null LAC;
L21:    new java/util/ArrayList
L24:    aload_0
L25:    dup_x2
L26:    dup
L27:    pop2
L28:    dup
L29:    invokespecial Method java/util/ArrayList <init> ()V
L32:    putfield Field wF "super" Ljava/util/List;
L35:    new java/util/ArrayList
L38:    aload_0
L39:    dup
L40:    pop2
L41:    dup
L42:    invokespecial Method java/util/ArrayList <init> ()V
L45:    putfield Field wF this Ljava/util/List;
L48:    getfield Field wF null LAC;
L51:    aload_0
L52:    getfield Field wF new LRg;
L55:    getfield Field Rg short LsE;
L58:    ifnull L69
L61:    iconst_1
L62:    dup
L63:    dup
L64:    pop2
L65:    goto L73
L68:    athrow
L69:    iconst_0
L70:    iconst_1
L71:    dup
L72:    pop2
L73:    invokevirtual Method AC break (Z)V
L76:    aload_0
L77:    getfield Field wF new LRg;
L80:    getfield Field Rg short LsE;
L83:    ifnull L104
L86:    aload_0
L87:    dup
L88:    getfield Field wF null LAC;
L91:    swap
L92:    getfield Field wF new LRg;
L95:    getfield Field Rg short LsE;
L98:    invokevirtual Method sE ordinal ()I
L101:   invokevirtual Method AC short (I)V
L104:   aload_0
L105:   getfield Field wF null LAC;
L108:   aload_0
L109:   aload_2
L110:   getfield Field Rg this [[I
L113:   invokestatic Method OC break ([[I)[[I
L116:   dup_x1
L117:   putfield Field wF instanceof [[I
L120:   invokevirtual Method AC break ([[I)V
L123:   aload_0
L124:   aload_2
L125:   getfield Field Rg float Lff;
L128:   invokevirtual Method ff catch ()Lff;
L131:   dup_x1
L132:   putfield Field wF continue Lff;
L135:   aload_0
L136:   getfield Field wF null LAC;
L139:   invokevirtual Method ff break (LAC;)V
L142:   aload_2
L143:   aload_0
L144:   dup
L145:   dup_x2
L146:   getfield Field wF null LAC;
L149:   aload_0
L150:   getfield Field wF continue Lff;
L153:   getfield Field ff else I
L156:   invokevirtual Method AC break (I)V
L159:   getfield Field wF null LAC;
L162:   aload_0
L163:   getfield Field wF continue Lff;
L166:   getfield Field ff do I
L169:   invokevirtual Method AC break (I)V
L172:   getfield Field Rg char Lff;
L175:   invokevirtual Method ff catch ()Lff;
L178:   dup_x1
L179:   putfield Field wF case Lff;
L182:   aload_0
L183:   getfield Field wF null LAC;
L186:   invokevirtual Method ff break (LAC;)V
L189:   aload_0
L190:   getfield Field wF null LAC;
L193:   aload_0
L194:   aload_2
L195:   getfield Field Rg try I
L198:   dup_x1
L199:   putfield Field wF byte I
L202:   invokevirtual Method AC break (I)V
L205:   aload_0
L206:   getfield Field wF null LAC;
L209:   aload_0
L210:   aload_2
L211:   getfield Field Rg void Ljava/util/LinkedList;
L214:   invokevirtual Method java/util/LinkedList size ()I
L217:   dup_x1
L218:   putfield Field wF short I
L221:   invokevirtual Method AC break (I)V
L224:   aload_0
L225:   getfield Field wF null LAC;
L228:   aload_0
L229:   aload_2
L230:   getfield Field Rg else Lqd;
L233:   getfield Field qd void Leb;
L236:   aload_2
L237:   invokevirtual Method eb short (LRg;)I
L240:   dup_x1
L241:   putfield Field wF try I
L244:   invokevirtual Method AC break (I)V
L247:   aload_0
L248:   dup
L249:   iconst_1
L250:   dup
L251:   dup
L252:   pop2
L253:   putfield Field wF import Z
L256:   getfield Field wF new LRg;
L259:   aload_0
L260:   invokevirtual Method Rg break (LF;)V
L263:   return
L264:   
        .attribute StackMap b'\x00\x04\x00\x44\x00\x00\x00\x01\x07\x00\x58\x00\x45\x00\x04\x07\x00\x02\x07\x00\x5A\x07\x00\x53\x07\x00\x5C\x00\x01\x07\x00\x5C\x00\x49\x00\x04\x07\x00\x02\x07\x00\x5A\x07\x00\x53\x07\x00\x5C\x00\x02\x07\x00\x5C\x01\x00\x68\x00\x04\x07\x00\x02\x07\x00\x5A\x07\x00\x53\x07\x00\x5C\x00\x00'
    .end code
    .exceptions java/io/IOException
.end method

.method public break : (IIF)V
    .code stack 7 locals 4
L0:     fload_3
L1:     aload_0
L2:     dup_x1
L3:     dup
L4:     getfield Field wF extends I
L7:     iconst_1
L8:     dup
L9:     dup
L10:    pop2
L11:    iadd
L12:    putfield Field wF extends I
L15:    putfield Field wF true F
L18:    return
L19:    
    .end code
.end method

.method public break : (Led;I[I)V
    .code stack 6 locals 4
L0:     aload_0
L1:     getfield Field wF this Ljava/util/List;
L4:     new Zd
L7:     dup
L8:     aload_1
L9:     iload_2
L10:    invokestatic Method java/lang/Integer valueOf (I)Ljava/lang/Integer;
L13:    aload_3
L14:    invokespecial Method Zd <init> (Ljava/lang/Object;Ljava/lang/Object;Ljava/lang/Object;)V
L17:    invokeinterface InterfaceMethod java/util/List add (Ljava/lang/Object;)Z 2
L22:    pop
L23:    return
L24:    
    .end code
.end method

.method public char : ()V
    .code stack 4 locals 1
L0:     aload_0
L1:     iconst_1
L2:     dup
L3:     dup
L4:     pop2
L5:     putfield Field wF break Z
L8:     return
L9:     
    .end code
.end method

.method public break : ([I)V
    .code stack 3 locals 5
L0:     aload_1
L1:     dup
L2:     astore_1
L3:     arraylength
L4:     istore_2
L5:     iconst_0
L6:     iconst_1
L7:     dup
L8:     pop2
L9:     dup
L10:    istore_3
L11:    iload_2
L12:    if_icmpge L43
L15:    aload_0
L16:    aload_1
L17:    iload_3
L18:    iinc 3 1
L21:    iaload
L22:    istore 4
L24:    getfield Field wF "super" Ljava/util/List;
L27:    iload 4
L29:    invokestatic Method java/lang/Integer valueOf (I)Ljava/lang/Integer;
L32:    invokeinterface InterfaceMethod java/util/List add (Ljava/lang/Object;)Z 2
L37:    pop
L38:    iload_3
L39:    goto L11
L42:    athrow
L43:    return
L44:    
        .attribute StackMap b'\x00\x03\x00\x0B\x00\x04\x07\x00\x02\x07\x00\xC7\x01\x01\x00\x01\x01\x00\x2A\x00\x00\x00\x01\x07\x00\x58\x00\x2B\x00\x04\x07\x00\x02\x07\x00\xC7\x01\x01\x00\x00'
    .end code
.end method

.method public break : (Lff;)V
    .code stack 4 locals 2
L0:     aload_0
L1:     iconst_1
L2:     dup
L3:     dup
L4:     pop2
L5:     putfield Field wF break Z
L8:     return
L9:     
    .end code
.end method

.method public long : ()V
    .code stack 12 locals 4
L0:     aload_0
L1:     getfield Field wF import Z
L4:     ifne L9
L7:     return
L8:     athrow
L9:     iconst_0
L10:    iconst_1
L11:    dup
L12:    pop2
L13:    istore_1
L14:    aload_0
L15:    getfield Field wF new LRg;
L18:    invokevirtual Method Rg new ()I
L21:    aload_0
L22:    getfield Field wF do I
L25:    if_icmpeq L56
L28:    iload_1
L29:    aload_0
L30:    dup
L31:    dup_x2
L32:    getfield Field wF new LRg;
L35:    invokevirtual Method Rg new ()I
L38:    putfield Field wF do I
L41:    sipush 1024
L44:    iconst_1
L45:    dup
L46:    pop2
L47:    ior
L48:    istore_1
L49:    iconst_0
L50:    iconst_1
L51:    dup
L52:    pop2
L53:    putfield Field wF import Z
L56:    aload_0
L57:    getfield Field wF continue Lff;
L60:    invokevirtual Method java/lang/Object getClass ()Ljava/lang/Class;
L63:    aload_0
L64:    getfield Field wF new LRg;
L67:    getfield Field Rg float Lff;
L70:    invokevirtual Method java/lang/Object getClass ()Ljava/lang/Class;
L73:    if_acmpne L141
L76:    aload_0
L77:    getfield Field wF continue Lff;
L80:    getfield Field ff "enum" I
L83:    aload_0
L84:    getfield Field wF new LRg;
L87:    getfield Field Rg float Lff;
L90:    getfield Field ff "enum" I
L93:    if_icmpne L141
L96:    aload_0
L97:    getfield Field wF continue Lff;
L100:   getfield Field ff else I
L103:   aload_0
L104:   getfield Field wF new LRg;
L107:   getfield Field Rg float Lff;
L110:   getfield Field ff else I
L113:   if_icmpeq L141
L116:   iload_1
L117:   aload_0
L118:   dup
L119:   getfield Field wF continue Lff;
L122:   swap
L123:   getfield Field wF new LRg;
L126:   getfield Field Rg float Lff;
L129:   getfield Field ff else I
L132:   putfield Field ff else I
L135:   iconst_1
L136:   dup
L137:   dup
L138:   pop2
L139:   ior
L140:   istore_1
L141:   aload_0
L142:   getfield Field wF continue Lff;
L145:   invokevirtual Method java/lang/Object getClass ()Ljava/lang/Class;
L148:   aload_0
L149:   getfield Field wF new LRg;
L152:   getfield Field Rg float Lff;
L155:   invokevirtual Method java/lang/Object getClass ()Ljava/lang/Class;
L158:   if_acmpne L226
L161:   aload_0
L162:   getfield Field wF continue Lff;
L165:   getfield Field ff "enum" I
L168:   aload_0
L169:   getfield Field wF new LRg;
L172:   getfield Field Rg float Lff;
L175:   getfield Field ff "enum" I
L178:   if_icmpne L226
L181:   aload_0
L182:   getfield Field wF continue Lff;
L185:   getfield Field ff do I
L188:   aload_0
L189:   getfield Field wF new LRg;
L192:   getfield Field Rg float Lff;
L195:   getfield Field ff do I
L198:   if_icmpeq L226
L201:   iload_1
L202:   aload_0
L203:   dup
L204:   getfield Field wF continue Lff;
L207:   swap
L208:   getfield Field wF new LRg;
L211:   getfield Field Rg float Lff;
L214:   getfield Field ff do I
L217:   putfield Field ff do I
L220:   iconst_2
L221:   iconst_1
L222:   dup
L223:   pop2
L224:   ior
L225:   istore_1
L226:   aload_0
L227:   getfield Field wF continue Lff;
L230:   invokevirtual Method java/lang/Object getClass ()Ljava/lang/Class;
L233:   aload_0
L234:   getfield Field wF new LRg;
L237:   getfield Field Rg float Lff;
L240:   invokevirtual Method java/lang/Object getClass ()Ljava/lang/Class;
L243:   if_acmpne L311
L246:   aload_0
L247:   getfield Field wF continue Lff;
L250:   getfield Field ff "enum" I
L253:   aload_0
L254:   getfield Field wF new LRg;
L257:   getfield Field Rg float Lff;
L260:   getfield Field ff "enum" I
L263:   if_icmpne L311
L266:   aload_0
L267:   getfield Field wF continue Lff;
L270:   getfield Field ff null I
L273:   aload_0
L274:   getfield Field wF new LRg;
L277:   getfield Field Rg float Lff;
L280:   getfield Field ff null I
L283:   if_icmpeq L311
L286:   iload_1
L287:   aload_0
L288:   dup
L289:   getfield Field wF continue Lff;
L292:   swap
L293:   getfield Field wF new LRg;
L296:   getfield Field Rg float Lff;
L299:   getfield Field ff null I
L302:   putfield Field ff null I
L305:   iconst_4
L306:   iconst_1
L307:   dup
L308:   pop2
L309:   ior
L310:   istore_1
L311:   aload_0
L312:   dup
L313:   getfield Field wF continue Lff;
L316:   swap
L317:   getfield Field wF new LRg;
L320:   getfield Field Rg float Lff;
L323:   invokevirtual Method ff break (Lff;)Z
L326:   ifeq L347
L329:   aload_0
L330:   dup
L331:   getfield Field wF case Lff;
L334:   swap
L335:   getfield Field wF new LRg;
L338:   getfield Field Rg char Lff;
L341:   invokevirtual Method ff break (Lff;)Z
L344:   ifne L407
L347:   aload_0
L348:   dup
L349:   dup2
L350:   getfield Field wF new LRg;
L353:   getfield Field Rg float Lff;
L356:   invokevirtual Method ff catch ()Lff;
L359:   putfield Field wF continue Lff;
L362:   getfield Field wF new LRg;
L365:   getfield Field Rg char Lff;
L368:   invokevirtual Method ff catch ()Lff;
L371:   putfield Field wF case Lff;
L374:   iload_1
L375:   bipush -2
L377:   iconst_1
L378:   dup
L379:   pop2
L380:   iand
L381:   dup
L382:   istore_1
L383:   bipush -3
L385:   iconst_1
L386:   dup
L387:   pop2
L388:   iand
L389:   dup
L390:   istore_1
L391:   bipush -5
L393:   iconst_1
L394:   dup
L395:   pop2
L396:   iand
L397:   dup
L398:   istore_1
L399:   sipush 2048
L402:   iconst_1
L403:   dup
L404:   pop2
L405:   ior
L406:   istore_1
L407:   aload_0
L408:   getfield Field wF new LRg;
L411:   getfield Field Rg this [[I
L414:   aload_0
L415:   getfield Field wF instanceof [[I
L418:   invokestatic Method java/util/Arrays deepEquals ([Ljava/lang/Object;[Ljava/lang/Object;)Z
L421:   ifne L471
L424:   iload_1
L425:   aload_0
L426:   dup
L427:   getfield Field wF new LRg;
L430:   getfield Field Rg this [[I
L433:   invokestatic Method OC break ([[I)[[I
L436:   putfield Field wF instanceof [[I
L439:   bipush -2
L441:   iconst_1
L442:   dup
L443:   pop2
L444:   iand
L445:   dup
L446:   istore_1
L447:   bipush -3
L449:   iconst_1
L450:   dup
L451:   pop2
L452:   iand
L453:   dup
L454:   istore_1
L455:   bipush -5
L457:   iconst_1
L458:   dup
L459:   pop2
L460:   iand
L461:   dup
L462:   istore_1
L463:   sipush 2048
L466:   iconst_1
L467:   dup
L468:   pop2
L469:   ior
L470:   istore_1
L471:   aload_0
L472:   getfield Field wF "super" Ljava/util/List;
L475:   invokeinterface InterfaceMethod java/util/List isEmpty ()Z 1
L480:   ifne L516
L483:   iload_1
L484:   bipush -2
L486:   iconst_1
L487:   dup
L488:   pop2
L489:   iand
L490:   dup
L491:   istore_1
L492:   bipush -3
L494:   iconst_1
L495:   dup
L496:   pop2
L497:   iand
L498:   dup
L499:   istore_1
L500:   bipush -5
L502:   iconst_1
L503:   dup
L504:   pop2
L505:   iand
L506:   dup
L507:   istore_1
L508:   sipush 2048
L511:   iconst_1
L512:   dup
L513:   pop2
L514:   ior
L515:   istore_1
L516:   aload_0
L517:   dup
L518:   getfield Field wF byte I
L521:   swap
L522:   getfield Field wF new LRg;
L525:   getfield Field Rg try I
L528:   if_icmpeq L551
L531:   iload_1
L532:   aload_0
L533:   dup
L534:   getfield Field wF new LRg;
L537:   getfield Field Rg try I
L540:   putfield Field wF byte I
L543:   sipush 512
L546:   iconst_1
L547:   dup
L548:   pop2
L549:   ior
L550:   istore_1
L551:   aload_0
L552:   dup
L553:   getfield Field wF short I
L556:   swap
L557:   getfield Field wF new LRg;
L560:   getfield Field Rg void Ljava/util/LinkedList;
L563:   invokevirtual Method java/util/LinkedList size ()I
L566:   if_icmpeq L591
L569:   iload_1
L570:   aload_0
L571:   dup
L572:   getfield Field wF new LRg;
L575:   getfield Field Rg void Ljava/util/LinkedList;
L578:   invokevirtual Method java/util/LinkedList size ()I
L581:   putfield Field wF short I
L584:   bipush 64
L586:   iconst_1
L587:   dup
L588:   pop2
L589:   ior
L590:   istore_1
L591:   aload_0
L592:   dup
L593:   getfield Field wF try I
L596:   swap
L597:   getfield Field wF new LRg;
L600:   getfield Field Rg else Lqd;
L603:   getfield Field qd void Leb;
L606:   aload_0
L607:   getfield Field wF new LRg;
L610:   invokevirtual Method eb short (LRg;)I
L613:   if_icmpne L662
L616:   aload_0
L617:   dup
L618:   getfield Field wF const I
L621:   swap
L622:   getfield Field wF new LRg;
L625:   getfield Field Rg true I
L628:   if_icmpne L662
L631:   aload_0
L632:   dup
L633:   getfield Field wF throws F
L636:   swap
L637:   getfield Field wF new LRg;
L640:   getfield Field Rg import F
L643:   fcmpl
L644:   ifne L662
L647:   aload_0
L648:   dup
L649:   getfield Field wF void I
L652:   swap
L653:   getfield Field wF new LRg;
L656:   getfield Field Rg goto I
L659:   if_icmpeq L723
L662:   aload_0
L663:   dup
L664:   dup_x1
L665:   dup2
L666:   dup2
L667:   getfield Field wF new LRg;
L670:   getfield Field Rg else Lqd;
L673:   getfield Field qd void Leb;
L676:   aload_0
L677:   dup_x2
L678:   getfield Field wF new LRg;
L681:   invokevirtual Method eb short (LRg;)I
L684:   putfield Field wF try I
L687:   getfield Field wF new LRg;
L690:   getfield Field Rg true I
L693:   putfield Field wF const I
L696:   getfield Field wF new LRg;
L699:   getfield Field Rg goto I
L702:   putfield Field wF void I
L705:   getfield Field wF new LRg;
L708:   getfield Field Rg import F
L711:   putfield Field wF throws F
L714:   iload_1
L715:   sipush 128
L718:   iconst_1
L719:   dup
L720:   pop2
L721:   ior
L722:   istore_1
L723:   aload_0
L724:   dup
L725:   getfield Field wF "native" I
L728:   swap
L729:   getfield Field wF new LRg;
L732:   getfield Field Rg catch I
L735:   if_icmpne L763
L738:   aload_0
L739:   getfield Field wF new LRg;
L742:   getfield Field Rg if I
L745:   ifle L792
L748:   aload_0
L749:   getfield Field wF "final" D
L752:   aload_0
L753:   getfield Field wF new LRg;
L756:   getfield Field Rg "enum" D
L759:   dcmpl
L760:   ifeq L792
L763:   aload_0
L764:   dup
L765:   dup2
L766:   getfield Field wF new LRg;
L769:   getfield Field Rg catch I
L772:   putfield Field wF "native" I
L775:   getfield Field wF new LRg;
L778:   getfield Field Rg "enum" D
L781:   putfield Field wF "final" D
L784:   iload_1
L785:   bipush 32
L787:   iconst_1
L788:   dup
L789:   pop2
L790:   ior
L791:   istore_1
L792:   aload_0
L793:   getfield Field wF extends I
L796:   ifle L807
L799:   iload_1
L800:   bipush 16
L802:   iconst_1
L803:   dup
L804:   pop2
L805:   ior
L806:   istore_1
L807:   aload_0
L808:   getfield Field wF this Ljava/util/List;
L811:   invokeinterface InterfaceMethod java/util/List isEmpty ()Z 1
L816:   ifne L828
L819:   iload_1
L820:   sipush 256
L823:   iconst_1
L824:   dup
L825:   pop2
L826:   ior
L827:   istore_1
L828:   aload_0
L829:   getfield Field wF break Z
L832:   ifeq L851
L835:   iload_1
L836:   bipush 8
L838:   iconst_1
L839:   dup
L840:   pop2
L841:   ior
L842:   istore_1
L843:   aload_0
L844:   iconst_0
L845:   iconst_1
L846:   dup
L847:   pop2
L848:   putfield Field wF break Z
L851:   aload_0
L852:   getfield Field wF null LAC;
L855:   iload_1
L856:   invokevirtual Method AC break (I)V
L859:   iload_1
L860:   sipush 1024
L863:   iconst_1
L864:   dup
L865:   pop2
L866:   iand
L867:   ifeq L1017
L870:   aload_0
L871:   dup
L872:   dup2
L873:   dup2
L874:   dup2
L875:   dup2
L876:   getfield Field wF null LAC;
L879:   aload_0
L880:   dup_x2
L881:   getfield Field wF do I
L884:   invokevirtual Method AC break (I)V
L887:   getfield Field wF null LAC;
L890:   aload_0
L891:   getfield Field wF new LRg;
L894:   getfield Field Rg continue F
L897:   invokevirtual Method AC break (F)V
L900:   getfield Field wF null LAC;
L903:   aload_0
L904:   getfield Field wF new LRg;
L907:   getfield Field Rg "final" I
L910:   invokevirtual Method AC break (I)V
L913:   getfield Field wF null LAC;
L916:   aload_0
L917:   getfield Field wF new LRg;
L920:   getfield Field Rg goto I
L923:   invokevirtual Method AC break (I)V
L926:   getfield Field wF null LAC;
L929:   aload_0
L930:   getfield Field wF new LRg;
L933:   getfield Field Rg instanceof I
L936:   invokevirtual Method AC break (I)V
L939:   getfield Field wF null LAC;
L942:   aload_0
L943:   getfield Field wF new LRg;
L946:   getfield Field Rg int I
L949:   invokevirtual Method AC break (I)V
L952:   getfield Field wF null LAC;
L955:   aload_0
L956:   getfield Field wF new LRg;
L959:   getfield Field Rg "static" I
L962:   invokevirtual Method AC break (I)V
L965:   getfield Field wF null LAC;
L968:   aload_0
L969:   getfield Field wF new LRg;
L972:   getfield Field Rg true I
L975:   invokevirtual Method AC break (I)V
L978:   getfield Field wF null LAC;
L981:   aload_0
L982:   getfield Field wF new LRg;
L985:   getfield Field Rg const I
L988:   invokevirtual Method AC break (I)V
L991:   getfield Field wF null LAC;
L994:   aload_0
L995:   getfield Field wF new LRg;
L998:   getfield Field Rg import F
L1001:  invokevirtual Method AC break (F)V
L1004:  getfield Field wF null LAC;
L1007:  aload_0
L1008:  getfield Field wF new LRg;
L1011:  getfield Field Rg byte I
L1014:  invokevirtual Method AC break (I)V
L1017:  iload_1
L1018:  bipush 32
L1020:  iconst_1
L1021:  dup
L1022:  pop2
L1023:  iand
L1024:  ifeq L1063
L1027:  aload_0
L1028:  getfield Field wF null LAC;
L1031:  aload_0
L1032:  dup_x1
L1033:  getfield Field wF "native" I
L1036:  invokevirtual Method AC break (I)V
L1039:  getfield Field wF null LAC;
L1042:  fconst_0
L1043:  aload_0
L1044:  getfield Field wF "final" D
L1047:  aload_0
L1048:  getfield Field wF new LRg;
L1051:  getfield Field Rg do F
L1054:  f2d
L1055:  dsub
L1056:  d2f
L1057:  invokestatic Method java/lang/Math max (FF)F
L1060:  invokevirtual Method AC break (F)V
L1063:  iload_1
L1064:  sipush 128
L1067:  iconst_1
L1068:  dup
L1069:  pop2
L1070:  iand
L1071:  ifeq L1118
L1074:  aload_0
L1075:  dup
L1076:  dup_x1
L1077:  getfield Field wF null LAC;
L1080:  aload_0
L1081:  dup_x2
L1082:  getfield Field wF try I
L1085:  invokevirtual Method AC break (I)V
L1088:  getfield Field wF null LAC;
L1091:  aload_0
L1092:  getfield Field wF const I
L1095:  invokevirtual Method AC break (I)V
L1098:  getfield Field wF null LAC;
L1101:  aload_0
L1102:  getfield Field wF void I
L1105:  invokevirtual Method AC break (I)V
L1108:  getfield Field wF null LAC;
L1111:  aload_0
L1112:  getfield Field wF throws F
L1115:  invokevirtual Method AC break (F)V
L1118:  iload_1
L1119:  sipush 2048
L1122:  iconst_1
L1123:  dup
L1124:  pop2
L1125:  iand
L1126:  ifeq L1284
L1129:  aload_0
L1130:  dup
L1131:  dup_x1
L1132:  dup2
L1133:  dup2
L1134:  getfield Field wF null LAC;
L1137:  aload_0
L1138:  dup_x2
L1139:  getfield Field wF instanceof [[I
L1142:  invokevirtual Method AC break ([[I)V
L1145:  getfield Field wF new LRg;
L1148:  getfield Field Rg char Lff;
L1151:  aload_0
L1152:  getfield Field wF null LAC;
L1155:  invokevirtual Method ff break (LAC;)V
L1158:  getfield Field wF new LRg;
L1161:  getfield Field Rg float Lff;
L1164:  aload_0
L1165:  getfield Field wF null LAC;
L1168:  invokevirtual Method ff break (LAC;)V
L1171:  getfield Field wF null LAC;
L1174:  aload_0
L1175:  getfield Field wF new LRg;
L1178:  getfield Field Rg float Lff;
L1181:  getfield Field ff else I
L1184:  invokevirtual Method AC break (I)V
L1187:  getfield Field wF null LAC;
L1190:  aload_0
L1191:  getfield Field wF new LRg;
L1194:  getfield Field Rg float Lff;
L1197:  getfield Field ff do I
L1200:  invokevirtual Method AC break (I)V
L1203:  getfield Field wF null LAC;
L1206:  aload_0
L1207:  getfield Field wF new LRg;
L1210:  getfield Field Rg "transient" F
L1213:  invokevirtual Method AC break (F)V
L1216:  getfield Field wF null LAC;
L1219:  aload_0
L1220:  getfield Field wF "super" Ljava/util/List;
L1223:  invokeinterface InterfaceMethod java/util/List size ()I 1
L1228:  invokevirtual Method AC break (I)V
L1231:  getfield Field wF "super" Ljava/util/List;
L1234:  invokeinterface InterfaceMethod java/util/List iterator ()Ljava/util/Iterator; 1
L1239:  dup
L1240:  astore_2
L1241:  invokeinterface InterfaceMethod java/util/Iterator hasNext ()Z 1
L1246:  ifeq L1275
L1249:  aload_2
L1250:  invokeinterface InterfaceMethod java/util/Iterator next ()Ljava/lang/Object; 1
L1255:  checkcast java/lang/Integer
L1258:  invokevirtual Method java/lang/Integer intValue ()I
L1261:  istore_3
L1262:  aload_2
L1263:  aload_0
L1264:  getfield Field wF null LAC;
L1267:  iload_3
L1268:  invokevirtual Method AC break (I)V
L1271:  goto L1241
L1274:  athrow
L1275:  aload_0
L1276:  getfield Field wF "super" Ljava/util/List;
L1279:  invokeinterface InterfaceMethod java/util/List clear ()V 1
L1284:  iload_1
L1285:  iconst_1
L1286:  dup
L1287:  dup
L1288:  pop2
L1289:  iand
L1290:  ifeq L1308
L1293:  aload_0
L1294:  dup
L1295:  getfield Field wF null LAC;
L1298:  swap
L1299:  getfield Field wF continue Lff;
L1302:  getfield Field ff else I
L1305:  invokevirtual Method AC break (I)V
L1308:  iload_1
L1309:  iconst_2
L1310:  iconst_1
L1311:  dup
L1312:  pop2
L1313:  iand
L1314:  ifeq L1332
L1317:  aload_0
L1318:  dup
L1319:  getfield Field wF null LAC;
L1322:  swap
L1323:  getfield Field wF continue Lff;
L1326:  getfield Field ff do I
L1329:  invokevirtual Method AC break (I)V
L1332:  iload_1
L1333:  iconst_4
L1334:  iconst_1
L1335:  dup
L1336:  pop2
L1337:  iand
L1338:  ifeq L1356
L1341:  aload_0
L1342:  dup
L1343:  getfield Field wF null LAC;
L1346:  swap
L1347:  getfield Field wF continue Lff;
L1350:  getfield Field ff null I
L1353:  invokevirtual Method AC break (I)V
L1356:  iload_1
L1357:  bipush 64
L1359:  iconst_1
L1360:  dup
L1361:  pop2
L1362:  iand
L1363:  ifeq L1378
L1366:  aload_0
L1367:  dup
L1368:  getfield Field wF null LAC;
L1371:  swap
L1372:  getfield Field wF short I
L1375:  invokevirtual Method AC break (I)V
L1378:  iload_1
L1379:  bipush 16
L1381:  iconst_1
L1382:  dup
L1383:  pop2
L1384:  iand
L1385:  ifeq L1418
L1388:  iconst_0
L1389:  aload_0
L1390:  dup
L1391:  dup_x2
L1392:  getfield Field wF null LAC;
L1395:  aload_0
L1396:  getfield Field wF extends I
L1399:  invokevirtual Method AC break (I)V
L1402:  getfield Field wF null LAC;
L1405:  aload_0
L1406:  getfield Field wF true F
L1409:  invokevirtual Method AC break (F)V
L1412:  iconst_1
L1413:  dup
L1414:  pop2
L1415:  putfield Field wF extends I
L1418:  iload_1
L1419:  sipush 512
L1422:  iconst_1
L1423:  dup
L1424:  pop2
L1425:  iand
L1426:  ifeq L1441
L1429:  aload_0
L1430:  dup
L1431:  getfield Field wF null LAC;
L1434:  swap
L1435:  getfield Field wF byte I
L1438:  invokevirtual Method AC break (I)V
L1441:  iload_1
L1442:  sipush 256
L1445:  iconst_1
L1446:  dup
L1447:  pop2
L1448:  iand
L1449:  ifeq L1563
L1452:  aload_0
L1453:  getfield Field wF null LAC;
L1456:  aload_0
L1457:  dup_x1
L1458:  getfield Field wF this Ljava/util/List;
L1461:  invokeinterface InterfaceMethod java/util/List size ()I 1
L1466:  invokevirtual Method AC break (I)V
L1469:  getfield Field wF this Ljava/util/List;
L1472:  invokeinterface InterfaceMethod java/util/List iterator ()Ljava/util/Iterator; 1
L1477:  dup
L1478:  astore_2
L1479:  invokeinterface InterfaceMethod java/util/Iterator hasNext ()Z 1
L1484:  ifeq L1554
L1487:  aload_2
L1488:  invokeinterface InterfaceMethod java/util/Iterator next ()Ljava/lang/Object; 1
L1493:  checkcast Zd
L1496:  astore_3
L1497:  aload_0
L1498:  dup
L1499:  getfield Field wF null LAC;
L1502:  swap
L1503:  getfield Field wF catch LNE;
L1506:  aload_3
L1507:  getfield Field Zd else Ljava/lang/Object;
L1510:  checkcast ed
L1513:  invokevirtual Method NE break (Led;)I
L1516:  invokevirtual Method AC break (I)V
L1519:  aload_0
L1520:  getfield Field wF null LAC;
L1523:  aload_3
L1524:  getfield Field Zd do Ljava/lang/Object;
L1527:  checkcast java/lang/Integer
L1530:  invokevirtual Method java/lang/Integer intValue ()I
L1533:  invokevirtual Method AC break (I)V
L1536:  aload_0
L1537:  getfield Field wF null LAC;
L1540:  aload_3
L1541:  getfield Field Zd "enum" Ljava/lang/Object;
L1544:  checkcast [I
L1547:  invokevirtual Method AC break ([I)V
L1550:  aload_2
L1551:  goto L1479
L1554:  aload_0
L1555:  getfield Field wF this Ljava/util/List;
L1558:  invokeinterface InterfaceMethod java/util/List clear ()V 1
L1563:  return
L1564:  
        .attribute StackMap b'\x00\x23\x00\x08\x00\x00\x00\x01\x07\x00\x58\x00\x09\x00\x01\x07\x00\x02\x00\x00\x00\x38\x00\x02\x07\x00\x02\x01\x00\x00\x00\x8D\x00\x02\x07\x00\x02\x01\x00\x00\x00\xE2\x00\x02\x07\x00\x02\x01\x00\x00\x01\x37\x00\x02\x07\x00\x02\x01\x00\x00\x01\x5B\x00\x02\x07\x00\x02\x01\x00\x00\x01\x97\x00\x02\x07\x00\x02\x01\x00\x00\x01\xD7\x00\x02\x07\x00\x02\x01\x00\x00\x02\x04\x00\x02\x07\x00\x02\x01\x00\x00\x02\x27\x00\x02\x07\x00\x02\x01\x00\x00\x02\x4F\x00\x02\x07\x00\x02\x01\x00\x00\x02\x96\x00\x02\x07\x00\x02\x01\x00\x00\x02\xD3\x00\x02\x07\x00\x02\x01\x00\x00\x02\xFB\x00\x02\x07\x00\x02\x01\x00\x00\x03\x18\x00\x02\x07\x00\x02\x01\x00\x00\x03\x27\x00\x02\x07\x00\x02\x01\x00\x00\x03\x3C\x00\x02\x07\x00\x02\x01\x00\x00\x03\x53\x00\x02\x07\x00\x02\x01\x00\x00\x03\xF9\x00\x02\x07\x00\x02\x01\x00\x00\x04\x27\x00\x02\x07\x00\x02\x01\x00\x00\x04\x5E\x00\x02\x07\x00\x02\x01\x00\x00\x04\xD9\x00\x03\x07\x00\x02\x01\x07\x01\x19\x00\x01\x07\x01\x19\x04\xFA\x00\x00\x00\x01\x07\x00\x58\x04\xFB\x00\x03\x07\x00\x02\x01\x07\x01\x19\x00\x00\x05\x04\x00\x02\x07\x00\x02\x01\x00\x00\x05\x1C\x00\x02\x07\x00\x02\x01\x00\x00\x05\x34\x00\x02\x07\x00\x02\x01\x00\x00\x05\x4C\x00\x02\x07\x00\x02\x01\x00\x00\x05\x62\x00\x02\x07\x00\x02\x01\x00\x00\x05\x8A\x00\x02\x07\x00\x02\x01\x00\x00\x05\xA1\x00\x02\x07\x00\x02\x01\x00\x00\x05\xC7\x00\x03\x07\x00\x02\x01\x07\x01\x19\x00\x01\x07\x01\x19\x06\x12\x00\x03\x07\x00\x02\x01\x07\x01\x19\x00\x00\x06\x1B\x00\x02\x07\x00\x02\x01\x00\x00'
    .end code
    .exceptions java/io/IOException
.end method

.method public for : ()V
    .code stack 2 locals 1
L0:     aload_0
L1:     getfield Field wF new LRg;
L4:     aload_0
L5:     invokevirtual Method Rg else (LF;)V
L8:     return
L9:     
    .end code
.end method

.method public goto : ()V
    .code stack 2 locals 1
L0:     aload_0
L1:     getfield Field wF new LRg;
L4:     getfield Field Rg case LqE;
L7:     getstatic Field qE this LqE;
L10:    if_acmpeq L21
L13:    aload_0
L14:    getfield Field wF new LRg;
L17:    aload_0
L18:    invokevirtual Method Rg else (LF;)V
L21:    return
L22:    
        .attribute StackMap b'\x00\x01\x00\x15\x00\x01\x07\x00\x02\x00\x00'
    .end code
.end method
.end class
