.version 49 0
.class public final super Wg
.super Uf

.method private break : ([[II)I
    .code stack 4 locals 4
L0:     iconst_0
L1:     iconst_1
L2:     dup
L3:     pop2
L4:     dup
L5:     istore_3
L6:     bipush 28
L8:     iconst_1
L9:     dup
L10:    pop2
L11:    if_icmpge L39
L14:    aload_1
L15:    iload_2
L16:    aaload
L17:    iload_3
L18:    iaload
L19:    ifeq L31
L22:    bipush 28
L24:    iconst_1
L25:    dup
L26:    pop2
L27:    iload_3
L28:    isub
L29:    ireturn
L30:    athrow
L31:    iinc 3 1
L34:    iload_3
L35:    goto L6
L38:    athrow
L39:    iconst_0
L40:    iconst_1
L41:    dup
L42:    pop2
L43:    ireturn
L44:    
        .attribute StackMap b'\x00\x05\x00\x06\x00\x04\x07\x00\x02\x07\x00\x08\x01\x01\x00\x01\x01\x00\x1E\x00\x00\x00\x01\x07\x00\x0A\x00\x1F\x00\x04\x07\x00\x02\x07\x00\x08\x01\x01\x00\x00\x00\x26\x00\x00\x00\x01\x07\x00\x0A\x00\x27\x00\x04\x07\x00\x02\x07\x00\x08\x01\x01\x00\x00'
    .end code
.end method

.method public break : (LRg;[[ILff;[I)Z
    .code stack 7 locals 7
L0:     aload_3
L1:     instanceof tF
L4:     ifne L13
L7:     iconst_0
L8:     iconst_1
L9:     dup
L10:    pop2
L11:    ireturn
L12:    athrow
L13:    aload_3
L14:    getfield Field ff null I
L17:    iconst_1
L18:    dup
L19:    dup
L20:    pop2
L21:    if_icmpeq L41
L24:    aload_3
L25:    getfield Field ff null I
L28:    iconst_3
L29:    iconst_1
L30:    dup
L31:    pop2
L32:    if_icmpeq L41
L35:    iconst_0
L36:    iconst_1
L37:    dup
L38:    pop2
L39:    ireturn
L40:    athrow
L41:    aload 4
L43:    arraylength
L44:    ifne L304
L47:    aload_1
L48:    getfield Field Rg if I
L51:    iconst_2
L52:    iconst_1
L53:    dup
L54:    pop2
L55:    if_icmple L304
L58:    bipush 28
L60:    iconst_1
L61:    dup
L62:    pop2
L63:    istore_1
L64:    iconst_m1
L65:    iconst_1
L66:    dup
L67:    pop2
L68:    istore 4
L70:    bipush 10
L72:    iconst_1
L73:    dup
L74:    pop2
L75:    newarray int
L77:    iconst_1
L78:    dup
L79:    pop2
L80:    astore 5
L82:    iconst_0
L83:    iconst_1
L84:    dup
L85:    pop2
L86:    dup
L87:    istore 6
L89:    bipush 10
L91:    iconst_1
L92:    dup
L93:    pop2
L94:    if_icmpge L134
L97:    iload 6
L99:    aload 5
L101:   dup_x1
L102:   aload_0
L103:   aload_2
L104:   iload 6
L106:   dup_x2
L107:   invokespecial Method Wg break ([[II)I
L110:   iastore
L111:   iaload
L112:   iload_1
L113:   if_icmpge L126
L116:   aload 5
L118:   iload 6
L120:   iaload
L121:   istore_1
L122:   iload 6
L124:   istore 4
L126:   iinc 6 1
L129:   iload 6
L131:   goto L89
L134:   bipush 28
L136:   iconst_1
L137:   dup
L138:   pop2
L139:   istore 6
L141:   iconst_0
L142:   iconst_1
L143:   dup
L144:   pop2
L145:   dup
L146:   istore_2
L147:   bipush 10
L149:   iconst_1
L150:   dup
L151:   pop2
L152:   if_icmpge L181
L155:   iload_2
L156:   iload 4
L158:   if_icmpeq L174
L161:   iload 6
L163:   aload 5
L165:   iload_2
L166:   iaload
L167:   iload_1
L168:   isub
L169:   invokestatic Method java/lang/Math min (II)I
L172:   istore 6
L174:   iinc 2 1
L177:   iload_2
L178:   goto L147
L181:   iload 6
L183:   bipush 6
L185:   iconst_1
L186:   dup
L187:   pop2
L188:   if_icmpge L196
L191:   iconst_0
L192:   iconst_1
L193:   dup
L194:   pop2
L195:   ireturn
L196:   aload_3
L197:   getfield Field ff null I
L200:   iconst_3
L201:   iconst_1
L202:   dup
L203:   pop2
L204:   if_icmpne L250
L207:   aload_3
L208:   getfield Field ff else I
L211:   iconst_1
L212:   dup
L213:   dup
L214:   pop2
L215:   iadd
L216:   iload 4
L218:   iconst_1
L219:   dup
L220:   dup
L221:   pop2
L222:   isub
L223:   if_icmpeq L245
L226:   aload_3
L227:   getfield Field ff else I
L230:   iconst_1
L231:   dup
L232:   dup
L233:   pop2
L234:   iadd
L235:   iload 4
L237:   iconst_1
L238:   dup
L239:   dup
L240:   pop2
L241:   iadd
L242:   if_icmpne L250
L245:   iconst_1
L246:   dup
L247:   dup
L248:   pop2
L249:   ireturn
L250:   aload_3
L251:   getfield Field ff null I
L254:   iconst_1
L255:   dup
L256:   dup
L257:   pop2
L258:   if_icmpne L304
L261:   aload_3
L262:   getfield Field ff else I
L265:   iconst_2
L266:   iconst_1
L267:   dup
L268:   pop2
L269:   iadd
L270:   iload 4
L272:   iconst_1
L273:   dup
L274:   dup
L275:   pop2
L276:   isub
L277:   if_icmpeq L299
L280:   aload_3
L281:   getfield Field ff else I
L284:   iconst_2
L285:   iconst_1
L286:   dup
L287:   pop2
L288:   iadd
L289:   iload 4
L291:   iconst_1
L292:   dup
L293:   dup
L294:   pop2
L295:   iadd
L296:   if_icmpne L304
L299:   iconst_1
L300:   dup
L301:   dup
L302:   pop2
L303:   ireturn
L304:   iconst_0
L305:   iconst_1
L306:   dup
L307:   pop2
L308:   ireturn
L309:   
        .attribute StackMap b'\x00\x0F\x00\x0C\x00\x00\x00\x01\x07\x00\x0A\x00\x0D\x00\x05\x07\x00\x02\x07\x00\x0F\x07\x00\x08\x07\x00\x11\x07\x00\x13\x00\x00\x00\x28\x00\x00\x00\x01\x07\x00\x0A\x00\x29\x00\x05\x07\x00\x02\x07\x00\x0F\x07\x00\x08\x07\x00\x11\x07\x00\x13\x00\x00\x00\x59\x00\x07\x07\x00\x02\x01\x07\x00\x08\x07\x00\x11\x01\x07\x00\x13\x01\x00\x01\x01\x00\x7E\x00\x07\x07\x00\x02\x01\x07\x00\x08\x07\x00\x11\x01\x07\x00\x13\x01\x00\x00\x00\x86\x00\x07\x07\x00\x02\x01\x07\x00\x08\x07\x00\x11\x01\x07\x00\x13\x01\x00\x00\x00\x93\x00\x07\x07\x00\x02\x01\x01\x07\x00\x11\x01\x07\x00\x13\x01\x00\x01\x01\x00\xAE\x00\x07\x07\x00\x02\x01\x01\x07\x00\x11\x01\x07\x00\x13\x01\x00\x00\x00\xB5\x00\x07\x07\x00\x02\x01\x01\x07\x00\x11\x01\x07\x00\x13\x01\x00\x00\x00\xC4\x00\x07\x07\x00\x02\x01\x01\x07\x00\x11\x01\x07\x00\x13\x01\x00\x00\x00\xF5\x00\x07\x07\x00\x02\x01\x01\x07\x00\x11\x01\x07\x00\x13\x01\x00\x00\x00\xFA\x00\x07\x07\x00\x02\x01\x01\x07\x00\x11\x01\x07\x00\x13\x01\x00\x00\x01\x2B\x00\x07\x07\x00\x02\x01\x01\x07\x00\x11\x01\x07\x00\x13\x01\x00\x00\x01\x30\x00\x04\x07\x00\x02\x00\x00\x07\x00\x11\x00\x00'
    .end code
.end method

.method public <init> : (Ljava/lang/String;Ljava/lang/String;Ljava/lang/String;IZ)V
    .code stack 7 locals 6
L0:     aload_0
L1:     aload_1
L2:     aload_2
L3:     aload_3
L4:     aconst_null
L5:     iload 4
L7:     iload 5
L9:     invokespecial Method Uf <init> (Ljava/lang/String;Ljava/lang/String;Ljava/lang/String;Ljava/lang/String;IZ)V
L12:    return
L13:    
    .end code
.end method
.end class
