.version 49 0
.class public final super Xc
.super java/lang/Thread
.field public final synthetic do Lmd;

.method public <init> : (Lmd;)V
    .code stack 3 locals 2
L0:     aload_0
L1:     dup
L2:     aload_1
L3:     putfield Field Xc do Lmd;
L6:     invokespecial Method java/lang/Thread <init> ()V
L9:     return
L10:    
    .end code
.end method

.method public run : ()V
    .code stack 6 locals 4
L0:     ldc2_w 4000L
L3:     lstore_1
        .catch java/lang/Exception from L4 to L63 using L174
L4:     new java/lang/String
L7:     dup
L8:     invokestatic Method dc const ()Ljava/lang/String;
L11:    invokestatic Method OC const (Ljava/lang/String;)[B
L14:    invokespecial Method java/lang/String <init> ([B)V
L17:    ldc "xxx"
L19:    invokevirtual Method java/lang/String split (Ljava/lang/String;)[Ljava/lang/String;
L22:    astore_3
L23:    ldc "mmhk"
L25:    aload_0
L26:    getfield Field Xc do Lmd;
L29:    aload_3
L30:    iconst_1
L31:    dup
L32:    dup
L33:    pop2
L34:    aaload
L35:    invokestatic Method md break (Lmd;Ljava/lang/String;)Ljava/lang/String;
L38:    pop
L39:    aload_3
L40:    iconst_0
L41:    iconst_1
L42:    dup
L43:    pop2
L44:    aaload
L45:    invokevirtual Method java/lang/String equals (Ljava/lang/Object;)Z
L48:    ifeq L67
L51:    aload_0
L52:    getfield Field Xc do Lmd;
L55:    iconst_1
L56:    dup
L57:    dup
L58:    pop2
L59:    invokestatic Method md const (Lmd;Z)Z
L62:    pop
L63:    goto L203
L66:    athrow
        .catch java/lang/Exception from L67 to L105 using L174
L67:    ldc "force"
L69:    aload_3
L70:    iconst_0
L71:    iconst_1
L72:    dup
L73:    pop2
L74:    aaload
L75:    invokevirtual Method java/lang/String equals (Ljava/lang/Object;)Z
L78:    ifeq L109
L81:    aload_0
L82:    dup
L83:    getfield Field Xc do Lmd;
L86:    iconst_1
L87:    dup
L88:    dup
L89:    pop2
L90:    invokestatic Method md break (Lmd;Z)Z
L93:    pop
L94:    getfield Field Xc do Lmd;
L97:    iconst_1
L98:    dup
L99:    dup
L100:   pop2
L101:   invokestatic Method md const (Lmd;Z)Z
L104:   pop
L105:   goto L203
L108:   athrow
        .catch java/lang/Exception from L109 to L147 using L174
L109:   ldc "recommended"
L111:   aload_3
L112:   iconst_0
L113:   iconst_1
L114:   dup
L115:   pop2
L116:   aaload
L117:   invokevirtual Method java/lang/String equals (Ljava/lang/Object;)Z
L120:   ifeq L150
L123:   aload_0
L124:   dup
L125:   getfield Field Xc do Lmd;
L128:   iconst_1
L129:   dup
L130:   dup
L131:   pop2
L132:   invokestatic Method md else (Lmd;Z)Z
L135:   pop
L136:   getfield Field Xc do Lmd;
L139:   iconst_1
L140:   dup
L141:   dup
L142:   pop2
L143:   invokestatic Method md const (Lmd;Z)Z
L146:   pop
L147:   goto L203
        .catch java/lang/Exception from L150 to L171 using L174
L150:   aload_0
L151:   getfield Field Xc do Lmd;
L154:   invokestatic Method md catch (Lmd;)Z
L157:   ifeq L4
L160:   new iD
L163:   dup
L164:   aload_0
L165:   invokespecial Method iD <init> (LXc;)V
L168:   invokestatic Method ib break (Ljava/lang/Runnable;)V
L171:   goto L4
L174:   astore_3
L175:   aload_3
L176:   invokevirtual Method java/lang/Exception printStackTrace ()V
        .catch java/lang/Exception from L179 to L183 using L187
L179:   lload_1
L180:   invokestatic Method java/lang/Thread sleep (J)V
L183:   lload_1
L184:   goto L189
L187:   astore_3
L188:   lload_1
L189:   ldc2_w 2L
L192:   lmul
L193:   ldc2_w 60000L
L196:   invokestatic Method java/lang/Math min (JJ)J
L199:   lstore_1
L200:   goto L4
L203:   getstatic Field java/lang/System out Ljava/io/PrintStream;
L206:   new java/lang/StringBuilder
L209:   dup
L210:   invokespecial Method java/lang/StringBuilder <init> ()V
L213:   iconst_0
L214:   ldc "Update check: "
L216:   invokevirtual Method java/lang/StringBuilder insert (ILjava/lang/String;)Ljava/lang/StringBuilder;
L219:   aload_0
L220:   getfield Field Xc do Lmd;
L223:   invokestatic Method md const (Lmd;)Z
L226:   invokevirtual Method java/lang/StringBuilder append (Z)Ljava/lang/StringBuilder;
L229:   ldc " "
L231:   invokevirtual Method java/lang/StringBuilder append (Ljava/lang/String;)Ljava/lang/StringBuilder;
L234:   aload_0
L235:   getfield Field Xc do Lmd;
L238:   invokestatic Method md else (Lmd;)Z
L241:   invokevirtual Method java/lang/StringBuilder append (Z)Ljava/lang/StringBuilder;
L244:   invokevirtual Method java/lang/StringBuilder toString ()Ljava/lang/String;
L247:   invokevirtual Method java/io/PrintStream println (Ljava/lang/String;)V
L250:   return
L251:   
        .attribute StackMap b'\x00\x0A\x00\x04\x00\x02\x07\x00\x02\x04\x00\x00\x00\x42\x00\x00\x00\x01\x07\x00\x3C\x00\x43\x00\x03\x07\x00\x02\x04\x07\x00\x3E\x00\x00\x00\x6C\x00\x00\x00\x01\x07\x00\x3C\x00\x6D\x00\x03\x07\x00\x02\x04\x07\x00\x3E\x00\x00\x00\x96\x00\x03\x07\x00\x02\x04\x07\x00\x3E\x00\x00\x00\xAE\x00\x02\x07\x00\x02\x04\x00\x01\x07\x00\x15\x00\xBB\x00\x03\x07\x00\x02\x04\x07\x00\x15\x00\x01\x07\x00\x15\x00\xBD\x00\x03\x07\x00\x02\x04\x07\x00\x15\x00\x01\x04\x00\xCB\x00\x03\x07\x00\x02\x04\x07\x00\x3E\x00\x00'
    .end code
.end method
.innerclasses
    Xc [0] [0]
    iD [0] [0]
.end innerclasses
.enclosing method md do ()V
.end class
