.version 49 0
.class public final super xC
.super java/lang/Object
.implements D
.field public this Ljava/util/LinkedHashMap;
.field public char Ljava/util/LinkedHashMap;
.field public else Ljava/util/Map;
.field public "enum" LQB;
.field public do J

.method public <init> : (LMd;)V
    .code stack 5 locals 6
L0:     aload_0
L1:     dup
L2:     invokespecial Method java/lang/Object <init> ()V
L5:     invokestatic Method QB values ()[LQB;
L8:     aload_1
L9:     invokevirtual Method Md long ()I
L12:    aaload
L13:    putfield Field xC "enum" LQB;
L16:    getstatic Field xd do [I
L19:    aload_0
L20:    getfield Field xC "enum" LQB;
L23:    invokevirtual Method QB ordinal ()I
L26:    iaload
L27:    tableswitch 1
            L56
            L70
            L300
            L300
            default : L300
L56:    aload_0
L57:    iconst_0
L58:    ifne L297
L61:    aload_1
L62:    invokevirtual Method Md const ()J
L65:    putfield Field xC do J
L68:    return
L69:    athrow
L70:    aload_1
L71:    invokevirtual Method Md long ()I
L74:    istore_2
L75:    iconst_0
L76:    new java/util/HashMap
L79:    aload_0
L80:    dup_x1
L81:    dup
L82:    pop2
L83:    dup
L84:    iload_2
L85:    invokespecial Method java/util/HashMap <init> (I)V
L88:    putfield Field xC else Ljava/util/Map;
L91:    iconst_1
L92:    dup
L93:    pop2
L94:    dup
L95:    istore_3
L96:    iload_2
L97:    if_icmpge L136
L100:   aload_0
L101:   aload_1
L102:   invokevirtual Method Md long ()I
L105:   istore 4
L107:   getfield Field xC else Ljava/util/Map;
L110:   iload 4
L112:   invokestatic Method java/lang/Integer valueOf (I)Ljava/lang/Integer;
L115:   aload_1
L116:   iinc 3 1
L119:   invokevirtual Method Md long ()I
L122:   invokestatic Method java/lang/Integer valueOf (I)Ljava/lang/Integer;
L125:   invokeinterface InterfaceMethod java/util/Map put (Ljava/lang/Object;Ljava/lang/Object;)Ljava/lang/Object; 3
L130:   pop
L131:   iload_3
L132:   goto L96
L135:   athrow
L136:   aload_1
L137:   invokevirtual Method Md long ()I
L140:   istore_2
L141:   iconst_0
L142:   new java/util/LinkedHashMap
L145:   aload_0
L146:   dup_x1
L147:   dup
L148:   pop2
L149:   dup
L150:   iload_2
L151:   invokespecial Method java/util/LinkedHashMap <init> (I)V
L154:   putfield Field xC this Ljava/util/LinkedHashMap;
L157:   iconst_1
L158:   dup
L159:   pop2
L160:   dup
L161:   istore_3
L162:   iload_2
L163:   if_icmpge L225
L166:   aconst_null
L167:   astore 4
        .catch java/lang/Exception from L169 to L181 using L186
L169:   getstatic Field Kc else LKc;
L172:   aload_1
L173:   invokevirtual Method Md long ()I
L176:   invokevirtual Method Kc break (I)Led;
L179:   astore 4
L181:   aload 4
L183:   goto L190
L186:   astore 5
L188:   aload 4
L190:   ifnull L213
L193:   aload_0
L194:   getfield Field xC this Ljava/util/LinkedHashMap;
L197:   aload 4
L199:   aload_1
L200:   invokevirtual Method Md long ()I
L203:   invokestatic Method java/lang/Integer valueOf (I)Ljava/lang/Integer;
L206:   invokevirtual Method java/util/LinkedHashMap put (Ljava/lang/Object;Ljava/lang/Object;)Ljava/lang/Object;
L209:   pop
L210:   goto L218
L213:   aload_1
L214:   invokevirtual Method Md long ()I
L217:   pop
L218:   iinc 3 1
L221:   iload_3
L222:   goto L162
L225:   aload_0
L226:   new java/util/LinkedHashMap
L229:   dup
L230:   invokespecial Method java/util/LinkedHashMap <init> ()V
L233:   putfield Field xC char Ljava/util/LinkedHashMap;
L236:   invokestatic Method sE values ()[LsE;
L239:   dup
L240:   astore_3
L241:   arraylength
L242:   istore 4
L244:   iconst_0
L245:   iconst_1
L246:   dup
L247:   pop2
L248:   dup
L249:   istore 5
L251:   iload 4
L253:   if_icmpge L285
L256:   aload_3
L257:   iload 5
L259:   iinc 5 1
L262:   aaload
L263:   astore_2
L264:   aload_0
L265:   getfield Field xC char Ljava/util/LinkedHashMap;
L268:   aload_2
L269:   aload_1
L270:   invokevirtual Method Md long ()I
L273:   invokestatic Method java/lang/Integer valueOf (I)Ljava/lang/Integer;
L276:   invokevirtual Method java/util/LinkedHashMap put (Ljava/lang/Object;Ljava/lang/Object;)Ljava/lang/Object;
L279:   pop
L280:   iload 5
L282:   goto L251
L285:   aload_0
L286:   getfield Field xC char Ljava/util/LinkedHashMap;
L289:   iconst_0
L290:   iconst_1
L291:   dup
L292:   pop2
L293:   invokestatic Method OC break (Ljava/util/LinkedHashMap;Z)V
L296:   return
L297:   goto L57
L300:   return
L301:   
        .attribute StackMap b'\x00\x11\x00\x38\x00\x02\x07\x00\x02\x07\x00\x29\x00\x00\x00\x39\x00\x02\x07\x00\x02\x07\x00\x29\x00\x01\x07\x00\x02\x00\x45\x00\x00\x00\x01\x07\x00\x3D\x00\x46\x00\x02\x07\x00\x02\x07\x00\x29\x00\x00\x00\x60\x00\x04\x07\x00\x02\x07\x00\x29\x01\x01\x00\x01\x01\x00\x87\x00\x00\x00\x01\x07\x00\x3D\x00\x88\x00\x04\x07\x00\x02\x07\x00\x29\x01\x01\x00\x00\x00\xA2\x00\x04\x07\x00\x02\x07\x00\x29\x01\x01\x00\x01\x01\x00\xBA\x00\x05\x07\x00\x02\x07\x00\x29\x01\x01\x07\x00\x5E\x00\x01\x07\x00\x20\x00\xBE\x00\x05\x07\x00\x02\x07\x00\x29\x01\x01\x07\x00\x5E\x00\x01\x07\x00\x5E\x00\xD5\x00\x05\x07\x00\x02\x07\x00\x29\x01\x01\x07\x00\x5E\x00\x00\x00\xDA\x00\x05\x07\x00\x02\x07\x00\x29\x01\x01\x07\x00\x5E\x00\x00\x00\xE1\x00\x04\x07\x00\x02\x07\x00\x29\x01\x01\x00\x00\x00\xFB\x00\x06\x07\x00\x02\x07\x00\x29\x00\x07\x00\x69\x01\x01\x00\x01\x01\x01\x1D\x00\x06\x07\x00\x02\x07\x00\x29\x00\x07\x00\x69\x01\x01\x00\x00\x01\x29\x00\x02\x07\x00\x02\x07\x00\x29\x00\x01\x07\x00\x02\x01\x2C\x00\x02\x07\x00\x02\x07\x00\x29\x00\x00'
    .end code
    .exceptions java/io/IOException
.end method

.method public <init> : (LQB;J)V
    .code stack 5 locals 4
L0:     aload_1
L1:     aload_0
L2:     invokespecial Method java/lang/Object <init> ()V
L5:     getstatic Field QB "enum" LQB;
L8:     if_acmpeq L21
L11:    new java/lang/RuntimeException
L14:    dup
L15:    ldc "Wrong constructor"
L17:    invokespecial Method java/lang/RuntimeException <init> (Ljava/lang/String;)V
L20:    athrow
L21:    aload_0
L22:    lload_2
L23:    aload_0
L24:    getstatic Field QB "enum" LQB;
L27:    putfield Field xC "enum" LQB;
L30:    putfield Field xC do J
L33:    return
L34:    
        .attribute StackMap b'\x00\x01\x00\x15\x00\x03\x07\x00\x02\x07\x00\x08\x04\x00\x00'
    .end code
.end method

.method public break : (LAC;)V
    .code stack 3 locals 6
L0:     aload_1
L1:     aload_0
L2:     getfield Field xC "enum" LQB;
L5:     invokevirtual Method QB ordinal ()I
L8:     invokevirtual Method AC break (I)V
L11:    getstatic Field xd do [I
L14:    aload_0
L15:    getfield Field xC "enum" LQB;
L18:    invokevirtual Method QB ordinal ()I
L21:    iaload
L22:    tableswitch 1
            L52
            L66
            L284
            L284
            default : L284
L52:    aload_1
L53:    iconst_0
L54:    ifne L281
L57:    aload_0
L58:    getfield Field xC do J
L61:    invokevirtual Method AC break (J)V
L64:    return
L65:    athrow
L66:    aload_1
L67:    aload_0
L68:    getfield Field xC else Ljava/util/Map;
L71:    invokeinterface InterfaceMethod java/util/Map size ()I 1
L76:    invokevirtual Method AC break (I)V
L79:    aload_0
L80:    getfield Field xC else Ljava/util/Map;
L83:    invokeinterface InterfaceMethod java/util/Map entrySet ()Ljava/util/Set; 1
L88:    invokeinterface InterfaceMethod java/util/Set iterator ()Ljava/util/Iterator; 1
L93:    dup
L94:    astore_2
L95:    invokeinterface InterfaceMethod java/util/Iterator hasNext ()Z 1
L100:   ifeq L150
L103:   aload_2
L104:   invokeinterface InterfaceMethod java/util/Iterator next ()Ljava/lang/Object; 1
L109:   checkcast java/util/Map$Entry
L112:   astore_3
L113:   aload_1
L114:   aload_3
L115:   invokeinterface InterfaceMethod java/util/Map$Entry getKey ()Ljava/lang/Object; 1
L120:   checkcast java/lang/Integer
L123:   invokevirtual Method java/lang/Integer intValue ()I
L126:   invokevirtual Method AC break (I)V
L129:   aload_1
L130:   aload_3
L131:   invokeinterface InterfaceMethod java/util/Map$Entry getValue ()Ljava/lang/Object; 1
L136:   checkcast java/lang/Integer
L139:   invokevirtual Method java/lang/Integer intValue ()I
L142:   invokevirtual Method AC break (I)V
L145:   aload_2
L146:   goto L95
L149:   athrow
L150:   aload_1
L151:   aload_0
L152:   getfield Field xC this Ljava/util/LinkedHashMap;
L155:   invokevirtual Method java/util/LinkedHashMap size ()I
L158:   invokevirtual Method AC break (I)V
L161:   aload_0
L162:   getfield Field xC this Ljava/util/LinkedHashMap;
L165:   invokevirtual Method java/util/LinkedHashMap entrySet ()Ljava/util/Set;
L168:   invokeinterface InterfaceMethod java/util/Set iterator ()Ljava/util/Iterator; 1
L173:   dup
L174:   astore_2
L175:   invokeinterface InterfaceMethod java/util/Iterator hasNext ()Z 1
L180:   ifeq L229
L183:   aload_2
L184:   invokeinterface InterfaceMethod java/util/Iterator next ()Ljava/lang/Object; 1
L189:   checkcast java/util/Map$Entry
L192:   astore_3
L193:   aload_1
L194:   aload_3
L195:   invokeinterface InterfaceMethod java/util/Map$Entry getKey ()Ljava/lang/Object; 1
L200:   checkcast ed
L203:   getfield Field ed try I
L206:   invokevirtual Method AC break (I)V
L209:   aload_1
L210:   aload_3
L211:   invokeinterface InterfaceMethod java/util/Map$Entry getValue ()Ljava/lang/Object; 1
L216:   checkcast java/lang/Integer
L219:   invokevirtual Method java/lang/Integer intValue ()I
L222:   invokevirtual Method AC break (I)V
L225:   aload_2
L226:   goto L175
L229:   invokestatic Method sE values ()[LsE;
L232:   dup
L233:   astore_2
L234:   arraylength
L235:   istore_3
L236:   iconst_0
L237:   iconst_1
L238:   dup
L239:   pop2
L240:   dup
L241:   istore 4
L243:   iload_3
L244:   if_icmpge L284
L247:   aload_2
L248:   iload 4
L250:   iinc 4 1
L253:   aaload
L254:   astore 5
L256:   aload_1
L257:   aload_0
L258:   getfield Field xC char Ljava/util/LinkedHashMap;
L261:   aload 5
L263:   invokevirtual Method java/util/LinkedHashMap get (Ljava/lang/Object;)Ljava/lang/Object;
L266:   checkcast java/lang/Integer
L269:   invokevirtual Method java/lang/Integer intValue ()I
L272:   invokevirtual Method AC break (I)V
L275:   iload 4
L277:   goto L243
L280:   athrow
L281:   goto L53
L284:   return
L285:   
        .attribute StackMap b'\x00\x0D\x00\x34\x00\x02\x07\x00\x02\x07\x00\x7A\x00\x00\x00\x35\x00\x02\x07\x00\x02\x07\x00\x7A\x00\x01\x07\x00\x7A\x00\x41\x00\x00\x00\x01\x07\x00\x3D\x00\x42\x00\x02\x07\x00\x02\x07\x00\x7A\x00\x00\x00\x5F\x00\x03\x07\x00\x02\x07\x00\x7A\x07\x00\x8E\x00\x01\x07\x00\x8E\x00\x95\x00\x00\x00\x01\x07\x00\x3D\x00\x96\x00\x03\x07\x00\x02\x07\x00\x7A\x07\x00\x8E\x00\x00\x00\xAF\x00\x03\x07\x00\x02\x07\x00\x7A\x07\x00\x8E\x00\x01\x07\x00\x8E\x00\xE5\x00\x03\x07\x00\x02\x07\x00\x7A\x07\x00\x8E\x00\x00\x00\xF3\x00\x05\x07\x00\x02\x07\x00\x7A\x07\x00\x69\x01\x01\x00\x01\x01\x01\x18\x00\x00\x00\x01\x07\x00\x3D\x01\x19\x00\x02\x07\x00\x02\x07\x00\x7A\x00\x01\x07\x00\x7A\x01\x1C\x00\x02\x07\x00\x02\x07\x00\x7A\x00\x00'
    .end code
    .exceptions java/io/IOException
.end method

.method public <init> : (LQB;)V
    .code stack 3 locals 2
L0:     aload_1
L1:     aload_0
L2:     invokespecial Method java/lang/Object <init> ()V
L5:     getstatic Field QB "enum" LQB;
L8:     if_acmpeq L18
L11:    aload_1
L12:    getstatic Field QB else LQB;
L15:    if_acmpne L28
L18:    new java/lang/RuntimeException
L21:    dup
L22:    ldc "Wrong constructor"
L24:    invokespecial Method java/lang/RuntimeException <init> (Ljava/lang/String;)V
L27:    athrow
L28:    aload_0
L29:    aload_1
L30:    putfield Field xC "enum" LQB;
L33:    return
L34:    
        .attribute StackMap b'\x00\x02\x00\x12\x00\x02\x07\x00\x02\x07\x00\x08\x00\x00\x00\x1C\x00\x02\x07\x00\x02\x07\x00\x08\x00\x00'
    .end code
.end method

.method public <init> : (LQB;Ljava/util/Map;Ljava/util/Map;Ljava/util/Map;)V
    .code stack 5 locals 5
L0:     aload_1
L1:     aload_0
L2:     invokespecial Method java/lang/Object <init> ()V
L5:     getstatic Field QB else LQB;
L8:     if_acmpeq L21
L11:    new java/lang/RuntimeException
L14:    dup
L15:    ldc "Wrong constructor"
L17:    invokespecial Method java/lang/RuntimeException <init> (Ljava/lang/String;)V
L20:    athrow
L21:    aload_0
L22:    dup
L23:    getstatic Field QB else LQB;
L26:    putfield Field xC "enum" LQB;
L29:    new java/util/HashMap
L32:    aload_0
L33:    dup
L34:    pop2
L35:    dup
L36:    invokespecial Method java/util/HashMap <init> ()V
L39:    putfield Field xC else Ljava/util/Map;
L42:    aload_2
L43:    invokeinterface InterfaceMethod java/util/Map entrySet ()Ljava/util/Set; 1
L48:    invokeinterface InterfaceMethod java/util/Set iterator ()Ljava/util/Iterator; 1
L53:    dup
L54:    astore_1
L55:    invokeinterface InterfaceMethod java/util/Iterator hasNext ()Z 1
L60:    ifeq L112
L63:    aload_1
L64:    invokeinterface InterfaceMethod java/util/Iterator next ()Ljava/lang/Object; 1
L69:    checkcast java/util/Map$Entry
L72:    astore_2
L73:    aload_0
L74:    getfield Field xC else Ljava/util/Map;
L77:    aload_2
L78:    invokeinterface InterfaceMethod java/util/Map$Entry getKey ()Ljava/lang/Object; 1
L83:    checkcast Rg
L86:    getfield Field Rg false Led;
L89:    getfield Field ed try I
L92:    invokestatic Method java/lang/Integer valueOf (I)Ljava/lang/Integer;
L95:    aload_2
L96:    invokeinterface InterfaceMethod java/util/Map$Entry getValue ()Ljava/lang/Object; 1
L101:   invokeinterface InterfaceMethod java/util/Map put (Ljava/lang/Object;Ljava/lang/Object;)Ljava/lang/Object; 3
L106:   pop
L107:   aload_1
L108:   goto L55
L111:   athrow
L112:   aload_0
L113:   dup
L114:   new java/util/LinkedHashMap
L117:   dup
L118:   aload_3
L119:   invokespecial Method java/util/LinkedHashMap <init> (Ljava/util/Map;)V
L122:   putfield Field xC this Ljava/util/LinkedHashMap;
L125:   new java/util/LinkedHashMap
L128:   aload_0
L129:   dup
L130:   pop2
L131:   dup
L132:   aload 4
L134:   invokespecial Method java/util/LinkedHashMap <init> (Ljava/util/Map;)V
L137:   putfield Field xC char Ljava/util/LinkedHashMap;
L140:   return
L141:   
        .attribute StackMap b'\x00\x04\x00\x15\x00\x05\x07\x00\x02\x07\x00\x08\x07\x00\x0E\x07\x00\x0E\x07\x00\x0E\x00\x00\x00\x37\x00\x05\x07\x00\x02\x07\x00\x8E\x07\x00\x04\x07\x00\x0E\x07\x00\x0E\x00\x01\x07\x00\x8E\x00\x6F\x00\x00\x00\x01\x07\x00\x3D\x00\x70\x00\x05\x07\x00\x02\x07\x00\x8E\x07\x00\x04\x07\x00\x0E\x07\x00\x0E\x00\x00'
    .end code
.end method
.innerclasses
    QB qd [0] public static final enum
    java/util/Map$Entry java/util/Map Entry public static interface abstract
    xd xC [0] static synthetic
.end innerclasses
.end class
