.version 49 0
.class public final super xF
.super java/lang/Object
.field public static final field5850 Ljava/util/List;

.method public static <clinit> : ()V
    .code stack 41 locals 3
L0:     new java/util/ArrayList
L3:     dup
L4:     invokespecial Method java/util/ArrayList <init> ()V
L7:     putstatic Field xF field5850 Ljava/util/List;
L10:    getstatic Field xF field5850 Ljava/util/List;
L13:    new wg
L16:    dup
L17:    ldc "sa1"
L19:    ldc "Berne"
L21:    ldc "Win despite staying below 40 BPM."
L23:    bipush 40
L25:    iconst_1
L26:    dup
L27:    pop2
L28:    bipush 20
L30:    iconst_1
L31:    dup
L32:    pop2
L33:    iconst_0
L34:    iconst_1
L35:    dup
L36:    pop2
L37:    invokespecial Method wg <init> (Ljava/lang/String;Ljava/lang/String;Ljava/lang/String;IIZ)V
L40:    invokeinterface InterfaceMethod java/util/List add (Ljava/lang/Object;)Z 2
L45:    getstatic Field xF field5850 Ljava/util/List;
L48:    new sf
L51:    dup
L52:    ldc "sp6"
L54:    ldc "St0rmDog"
L56:    ldc "Play with a higher BPM than 60."
L58:    bipush 60
L60:    iconst_1
L61:    dup
L62:    pop2
L63:    ldc 8e0f
L65:    iconst_5
L66:    iconst_1
L67:    dup
L68:    pop2
L69:    iconst_1
L70:    dup
L71:    dup
L72:    pop2
L73:    invokespecial Method sf <init> (Ljava/lang/String;Ljava/lang/String;Ljava/lang/String;IFIZ)V
L76:    invokeinterface InterfaceMethod java/util/List add (Ljava/lang/Object;)Z 2
L81:    getstatic Field xF field5850 Ljava/util/List;
L84:    new sf
L87:    dup
L88:    ldc "sp12"
L90:    ldc "Autobahn"
L92:    ldc "Play with a higher BPM than 120."
L94:    bipush 120
L96:    iconst_1
L97:    dup
L98:    pop2
L99:    ldc 8e0f
L101:   bipush 20
L103:   iconst_1
L104:   dup
L105:   pop2
L106:   iconst_1
L107:   dup
L108:   dup
L109:   pop2
L110:   invokespecial Method sf <init> (Ljava/lang/String;Ljava/lang/String;Ljava/lang/String;IFIZ)V
L113:   invokeinterface InterfaceMethod java/util/List add (Ljava/lang/Object;)Z 2
L118:   getstatic Field xF field5850 Ljava/util/List;
L121:   new sf
L124:   dup
L125:   ldc "jta20"
L127:   ldc "Je t'adore"
L129:   ldc "Play with a higher BPM than 200."
L131:   sipush 200
L134:   iconst_1
L135:   dup
L136:   pop2
L137:   ldc 8e0f
L139:   bipush 50
L141:   iconst_1
L142:   dup
L143:   pop2
L144:   iconst_0
L145:   iconst_1
L146:   dup
L147:   pop2
L148:   invokespecial Method sf <init> (Ljava/lang/String;Ljava/lang/String;Ljava/lang/String;IFIZ)V
L151:   invokeinterface InterfaceMethod java/util/List add (Ljava/lang/Object;)Z 2
L156:   getstatic Field xF field5850 Ljava/util/List;
L159:   new jF
L162:   dup
L163:   ldc "tri"
L165:   ldc "Triforce"
L167:   ldc "Make a god-like combo."
L169:   bipush 10
L171:   iconst_1
L172:   dup
L173:   pop2
L174:   iconst_1
L175:   dup
L176:   pop2
L177:   bipush 25
L179:   iconst_1
L180:   dup
L181:   pop2
L182:   iconst_1
L183:   dup
L184:   dup_x2
L185:   dup
L186:   pop2
L187:   invokespecial Method jF <init> (Ljava/lang/String;Ljava/lang/String;Ljava/lang/String;IIIZ)V
L190:   invokeinterface InterfaceMethod java/util/List add (Ljava/lang/Object;)Z 2
L195:   getstatic Field xF field5850 Ljava/util/List;
L198:   new jF
L201:   dup
L202:   ldc "guki"
L204:   ldc "Chuck"
L206:   ldc "Make two god-like combos in a match."
L208:   bipush 10
L210:   iconst_1
L211:   dup
L212:   pop2
L213:   iconst_2
L214:   iconst_1
L215:   dup
L216:   pop2
L217:   bipush 25
L219:   iconst_1
L220:   dup
L221:   pop2
L222:   iconst_0
L223:   iconst_1
L224:   dup
L225:   pop2
L226:   invokespecial Method jF <init> (Ljava/lang/String;Ljava/lang/String;Ljava/lang/String;IIIZ)V
L229:   invokeinterface InterfaceMethod java/util/List add (Ljava/lang/Object;)Z 2
L234:   getstatic Field xF field5850 Ljava/util/List;
L237:   new jF
L240:   dup
L241:   ldc "chuck"
L243:   ldc "Gutknecht"
L245:   ldc "Make three god-like combos in a match."
L247:   bipush 10
L249:   iconst_1
L250:   dup
L251:   pop2
L252:   iconst_3
L253:   iconst_1
L254:   dup
L255:   pop2
L256:   bipush 35
L258:   iconst_1
L259:   dup
L260:   pop2
L261:   iconst_0
L262:   iconst_1
L263:   dup
L264:   pop2
L265:   invokespecial Method jF <init> (Ljava/lang/String;Ljava/lang/String;Ljava/lang/String;IIIZ)V
L268:   invokeinterface InterfaceMethod java/util/List add (Ljava/lang/Object;)Z 2
L273:   getstatic Field xF field5850 Ljava/util/List;
L276:   new qf
L279:   dup
L280:   ldc "bff"
L282:   ldc "Buddy Fenyne fan"
L284:   ldc "Make a god-like combo in a non-standard game mode."
L286:   bipush 10
L288:   iconst_1
L289:   dup
L290:   pop2
L291:   iconst_1
L292:   dup
L293:   pop2
L294:   bipush 15
L296:   iconst_1
L297:   dup
L298:   pop2
L299:   iconst_1
L300:   dup
L301:   dup_x2
L302:   dup
L303:   pop2
L304:   invokespecial Method qf <init> (Ljava/lang/String;Ljava/lang/String;Ljava/lang/String;IIIZ)V
L307:   invokeinterface InterfaceMethod java/util/List add (Ljava/lang/Object;)Z 2
L312:   getstatic Field xF field5850 Ljava/util/List;
L315:   new Lg
L318:   dup
L319:   ldc "tw9yc"
L321:   ldc "The whole nine yards"
L323:   ldc "Make a combo of every single level, from one to nine in a match."
L325:   bipush 28
L327:   iconst_1
L328:   dup
L329:   pop2
L330:   iconst_1
L331:   dup
L332:   pop2
L333:   iconst_1
L334:   dup
L335:   pop2
L336:   bipush 9
L338:   iconst_1
L339:   dup_x1
L340:   dup_x2
L341:   dup
L342:   pop2
L343:   newarray int
L345:   iconst_1
L346:   dup
L347:   pop2
L348:   dup
L349:   iconst_0
L350:   iconst_1
L351:   dup
L352:   pop2
L353:   iconst_1
L354:   dup
L355:   dup
L356:   pop2
L357:   iastore
L358:   dup
L359:   iconst_1
L360:   dup
L361:   pop2
L362:   iconst_2
L363:   iconst_1
L364:   dup_x1
L365:   dup
L366:   pop2
L367:   iastore
L368:   dup
L369:   iconst_2
L370:   iconst_1
L371:   dup
L372:   pop2
L373:   iconst_3
L374:   iconst_1
L375:   dup
L376:   pop2
L377:   iastore
L378:   dup
L379:   iconst_3
L380:   iconst_1
L381:   dup
L382:   pop2
L383:   iconst_4
L384:   iconst_1
L385:   dup
L386:   pop2
L387:   iastore
L388:   dup
L389:   iconst_4
L390:   iconst_1
L391:   dup
L392:   pop2
L393:   iconst_5
L394:   iconst_1
L395:   dup
L396:   pop2
L397:   iastore
L398:   dup
L399:   iconst_5
L400:   iconst_1
L401:   dup
L402:   pop2
L403:   bipush 6
L405:   iconst_1
L406:   dup
L407:   pop2
L408:   iastore
L409:   dup
L410:   bipush 6
L412:   iconst_1
L413:   dup
L414:   pop2
L415:   bipush 7
L417:   iconst_1
L418:   dup
L419:   pop2
L420:   iastore
L421:   dup
L422:   bipush 7
L424:   iconst_1
L425:   dup
L426:   pop2
L427:   bipush 8
L429:   iconst_1
L430:   dup
L431:   pop2
L432:   iastore
L433:   dup
L434:   bipush 8
L436:   iconst_1
L437:   dup
L438:   pop2
L439:   bipush 9
L441:   iconst_1
L442:   dup
L443:   pop2
L444:   iastore
L445:   invokespecial Method Lg <init> (Ljava/lang/String;Ljava/lang/String;Ljava/lang/String;IIZ[I)V
L448:   invokeinterface InterfaceMethod java/util/List add (Ljava/lang/Object;)Z 2
L453:   getstatic Field xF field5850 Ljava/util/List;
L456:   new YF
L459:   dup
L460:   ldc "tetris1"
L462:   ldc "\u041F\u0430\u0436\u0438\u0442\u043D\u043E\u0432"
L464:   ldc "Clear 4 lines at once."
L466:   iconst_4
L467:   iconst_1
L468:   dup
L469:   pop2
L470:   iconst_1
L471:   dup
L472:   pop2
L473:   iconst_5
L474:   iconst_1
L475:   dup
L476:   pop2
L477:   iconst_1
L478:   dup
L479:   dup_x2
L480:   dup
L481:   pop2
L482:   iconst_1
L483:   dup
L484:   dup
L485:   pop2
L486:   invokespecial Method YF <init> (Ljava/lang/String;Ljava/lang/String;Ljava/lang/String;IIIZZ)V
L489:   invokeinterface InterfaceMethod java/util/List add (Ljava/lang/Object;)Z 2
L494:   getstatic Field xF field5850 Ljava/util/List;
L497:   new YF
L500:   dup
L501:   ldc "tetris4"
L503:   ldc "\u0410\u043B\u0435\u043A\u0441\u0435\u0439"
L505:   ldc "Do four Tetrises in a match."
L507:   iconst_4
L508:   iconst_1
L509:   dup
L510:   pop2
L511:   iconst_4
L512:   iconst_1
L513:   dup
L514:   pop2
L515:   bipush 20
L517:   iconst_1
L518:   dup
L519:   pop2
L520:   iconst_0
L521:   iconst_1
L522:   dup
L523:   pop2
L524:   iconst_1
L525:   dup
L526:   dup
L527:   pop2
L528:   invokespecial Method YF <init> (Ljava/lang/String;Ljava/lang/String;Ljava/lang/String;IIIZZ)V
L531:   invokeinterface InterfaceMethod java/util/List add (Ljava/lang/Object;)Z 2
L536:   getstatic Field xF field5850 Ljava/util/List;
L539:   new jF
L542:   dup
L543:   ldc "cm"
L545:   ldc "Combo master"
L547:   ldc "Do 40 3-combos in a match."
L549:   iconst_3
L550:   iconst_1
L551:   dup
L552:   pop2
L553:   bipush 40
L555:   iconst_1
L556:   dup
L557:   pop2
L558:   bipush 18
L560:   iconst_1
L561:   dup
L562:   pop2
L563:   iconst_1
L564:   dup
L565:   dup
L566:   pop2
L567:   invokespecial Method jF <init> (Ljava/lang/String;Ljava/lang/String;Ljava/lang/String;IIIZ)V
L570:   invokeinterface InterfaceMethod java/util/List add (Ljava/lang/Object;)Z 2
L575:   getstatic Field xF field5850 Ljava/util/List;
L578:   new uD
L581:   dup
L582:   ldc "fw"
L584:   ldc "Welcome!"
L586:   ldc "Win your first match."
L588:   iconst_1
L589:   dup
L590:   pop2
L591:   iconst_2
L592:   iconst_1
L593:   dup
L594:   pop2
L595:   iconst_1
L596:   dup
L597:   dup_x2
L598:   dup
L599:   pop2
L600:   invokespecial Method uD <init> (Ljava/lang/String;Ljava/lang/String;Ljava/lang/String;IIZ)V
L603:   invokeinterface InterfaceMethod java/util/List add (Ljava/lang/Object;)Z 2
L608:   getstatic Field xF field5850 Ljava/util/List;
L611:   new nE
L614:   dup
L615:   ldc "wA"
L617:   ldc "For teh lulz"
L619:   ldc "Win 100 matches."
L621:   bipush 100
L623:   iconst_1
L624:   dup
L625:   pop2
L626:   bipush 12
L628:   iconst_1
L629:   dup
L630:   pop2
L631:   iconst_1
L632:   dup
L633:   dup
L634:   pop2
L635:   invokespecial Method nE <init> (Ljava/lang/String;Ljava/lang/String;Ljava/lang/String;IIZ)V
L638:   invokeinterface InterfaceMethod java/util/List add (Ljava/lang/Object;)Z 2
L643:   getstatic Field xF field5850 Ljava/util/List;
L646:   new nE
L649:   dup
L650:   ldc "wB"
L652:   ldc "For teh ego"
L654:   ldc "Win 1'000 matches."
L656:   sipush 1000
L659:   iconst_1
L660:   dup
L661:   pop2
L662:   bipush 24
L664:   iconst_1
L665:   dup
L666:   pop2
L667:   iconst_0
L668:   iconst_1
L669:   dup
L670:   pop2
L671:   invokespecial Method nE <init> (Ljava/lang/String;Ljava/lang/String;Ljava/lang/String;IIZ)V
L674:   invokeinterface InterfaceMethod java/util/List add (Ljava/lang/Object;)Z 2
L679:   getstatic Field xF field5850 Ljava/util/List;
L682:   new nE
L685:   dup
L686:   ldc "wC"
L688:   ldc "For teh win"
L690:   ldc "Win 10'000 matches."
L692:   sipush 10000
L695:   iconst_1
L696:   dup
L697:   pop2
L698:   bipush 45
L700:   iconst_1
L701:   dup
L702:   pop2
L703:   iconst_0
L704:   iconst_1
L705:   dup
L706:   pop2
L707:   invokespecial Method nE <init> (Ljava/lang/String;Ljava/lang/String;Ljava/lang/String;IIZ)V
L710:   invokeinterface InterfaceMethod java/util/List add (Ljava/lang/Object;)Z 2
L715:   getstatic Field xF field5850 Ljava/util/List;
L718:   new nE
L721:   dup
L722:   ldc "wD"
L724:   ldc "New overlord"
L726:   ldc "Win 50'000 matches."
L728:   ldc 50000
L730:   bipush 95
L732:   iconst_1
L733:   dup
L734:   pop2
L735:   iconst_0
L736:   iconst_1
L737:   dup
L738:   pop2
L739:   invokespecial Method nE <init> (Ljava/lang/String;Ljava/lang/String;Ljava/lang/String;IIZ)V
L742:   invokeinterface InterfaceMethod java/util/List add (Ljava/lang/Object;)Z 2
L747:   getstatic Field xF field5850 Ljava/util/List;
L750:   new VE
L753:   dup
L754:   ldc "rA"
L756:   ldc "Techno Viking"
L758:   ldc "Play 100 matches."
L760:   bipush 100
L762:   iconst_1
L763:   dup
L764:   pop2
L765:   bipush 22
L767:   iconst_1
L768:   dup
L769:   pop2
L770:   iconst_1
L771:   dup
L772:   dup
L773:   pop2
L774:   invokespecial Method VE <init> (Ljava/lang/String;Ljava/lang/String;Ljava/lang/String;IIZ)V
L777:   invokeinterface InterfaceMethod java/util/List add (Ljava/lang/Object;)Z 2
L782:   getstatic Field xF field5850 Ljava/util/List;
L785:   new VE
L788:   dup
L789:   ldc "rB"
L791:   ldc "Professor Badass"
L793:   ldc "Play 1'000 matches."
L795:   sipush 1000
L798:   iconst_1
L799:   dup
L800:   pop2
L801:   bipush 50
L803:   iconst_1
L804:   dup
L805:   pop2
L806:   iconst_0
L807:   iconst_1
L808:   dup
L809:   pop2
L810:   invokespecial Method VE <init> (Ljava/lang/String;Ljava/lang/String;Ljava/lang/String;IIZ)V
L813:   invokeinterface InterfaceMethod java/util/List add (Ljava/lang/Object;)Z 2
L818:   getstatic Field xF field5850 Ljava/util/List;
L821:   new VE
L824:   dup
L825:   ldc "rC"
L827:   ldc "Yo dawg!"
L829:   ldc "Play 10'000 matches."
L831:   sipush 10000
L834:   iconst_1
L835:   dup
L836:   pop2
L837:   bipush 75
L839:   iconst_1
L840:   dup
L841:   pop2
L842:   iconst_0
L843:   iconst_1
L844:   dup
L845:   pop2
L846:   invokespecial Method VE <init> (Ljava/lang/String;Ljava/lang/String;Ljava/lang/String;IIZ)V
L849:   invokeinterface InterfaceMethod java/util/List add (Ljava/lang/Object;)Z 2
L854:   getstatic Field xF field5850 Ljava/util/List;
L857:   new VE
L860:   dup
L861:   ldc "rD"
L863:   ldc "Great justice"
L865:   ldc "Play 100'000 matches."
L867:   ldc 100000
L869:   bipush 100
L871:   iconst_1
L872:   dup
L873:   pop2
L874:   iconst_0
L875:   iconst_1
L876:   dup
L877:   pop2
L878:   invokespecial Method VE <init> (Ljava/lang/String;Ljava/lang/String;Ljava/lang/String;IIZ)V
L881:   invokeinterface InterfaceMethod java/util/List add (Ljava/lang/Object;)Z 2
L886:   getstatic Field xF field5850 Ljava/util/List;
L889:   new mg
L892:   dup
L893:   ldc "spencer"
L895:   ldc "Spencer Davis Group"
L897:   ldc "Keep on playing for 4 minutes."
L899:   ldc 2.4e2f
L901:   iconst_0
L902:   iconst_1
L903:   dup
L904:   pop2
L905:   iconst_1
L906:   dup
L907:   pop2
L908:   bipush 10
L910:   iconst_1
L911:   dup
L912:   pop2
L913:   iconst_1
L914:   dup
L915:   dup_x2
L916:   dup
L917:   pop2
L918:   invokespecial Method mg <init> (Ljava/lang/String;Ljava/lang/String;Ljava/lang/String;FZZIZ)V
L921:   invokeinterface InterfaceMethod java/util/List add (Ljava/lang/Object;)Z 2
L926:   getstatic Field xF field5850 Ljava/util/List;
L929:   new mg
L932:   dup
L933:   ldc "da"
L935:   ldc "Eye of the tiger"
L937:   ldc "Survive longer than 5 minutes."
L939:   ldc 3e2f
L941:   iconst_1
L942:   dup
L943:   pop2
L944:   iconst_1
L945:   dup
L946:   pop2
L947:   bipush 15
L949:   iconst_1
L950:   dup_x1
L951:   dup
L952:   pop2
L953:   iconst_0
L954:   dup_x2
L955:   iconst_1
L956:   dup
L957:   pop2
L958:   invokespecial Method mg <init> (Ljava/lang/String;Ljava/lang/String;Ljava/lang/String;FZZIZ)V
L961:   invokeinterface InterfaceMethod java/util/List add (Ljava/lang/Object;)Z 2
L966:   getstatic Field xF field5850 Ljava/util/List;
L969:   new mg
L972:   dup
L973:   ldc "dass"
L975:   ldc "Imma let you finish"
L977:   ldc "Survive longer than 6 minutes."
L979:   ldc 3.6e2f
L981:   iconst_1
L982:   dup
L983:   pop2
L984:   iconst_1
L985:   dup
L986:   pop2
L987:   bipush 20
L989:   iconst_1
L990:   dup_x1
L991:   dup
L992:   pop2
L993:   iconst_0
L994:   dup_x2
L995:   iconst_1
L996:   dup
L997:   pop2
L998:   invokespecial Method mg <init> (Ljava/lang/String;Ljava/lang/String;Ljava/lang/String;FZZIZ)V
L1001:  invokeinterface InterfaceMethod java/util/List add (Ljava/lang/Object;)Z 2
L1006:  getstatic Field xF field5850 Ljava/util/List;
L1009:  new mg
L1012:  dup
L1013:  ldc "freddie"
L1015:  ldc "Who wants to live forever"
L1017:  ldc "Stay alive for 7:30."
L1019:  ldc 4.5e2f
L1021:  iconst_1
L1022:  dup
L1023:  pop2
L1024:  iconst_1
L1025:  dup
L1026:  pop2
L1027:  bipush 50
L1029:  iconst_1
L1030:  dup_x1
L1031:  dup
L1032:  pop2
L1033:  iconst_0
L1034:  dup_x2
L1035:  iconst_1
L1036:  dup
L1037:  pop2
L1038:  invokespecial Method mg <init> (Ljava/lang/String;Ljava/lang/String;Ljava/lang/String;FZZIZ)V
L1041:  invokeinterface InterfaceMethod java/util/List add (Ljava/lang/Object;)Z 2
L1046:  getstatic Field xF field5850 Ljava/util/List;
L1049:  new yD
L1052:  dup
L1053:  ldc "fb"
L1055:  ldc "First blood"
L1057:  ldc "Send a line to an opponent."
L1059:  iconst_1
L1060:  dup
L1061:  pop2
L1062:  iconst_1
L1063:  dup
L1064:  pop2
L1065:  iconst_1
L1066:  dup
L1067:  dup_x1
L1068:  dup_x2
L1069:  dup
L1070:  pop2
L1071:  iconst_1
L1072:  dup
L1073:  dup
L1074:  pop2
L1075:  invokespecial Method yD <init> (Ljava/lang/String;Ljava/lang/String;Ljava/lang/String;IZIZ)V
L1078:  invokeinterface InterfaceMethod java/util/List add (Ljava/lang/Object;)Z 2
L1083:  getstatic Field xF field5850 Ljava/util/List;
L1086:  new yD
L1089:  dup
L1090:  ldc "sdw"
L1092:  ldc "Shoop Da Whoop"
L1094:  ldc "Send 100 lines to your opponents in a match."
L1096:  bipush 100
L1098:  iconst_1
L1099:  dup
L1100:  pop2
L1101:  iconst_1
L1102:  dup
L1103:  pop2
L1104:  bipush 25
L1106:  iconst_1
L1107:  dup
L1108:  pop2
L1109:  iconst_1
L1110:  dup
L1111:  dup_x2
L1112:  dup
L1113:  pop2
L1114:  invokespecial Method yD <init> (Ljava/lang/String;Ljava/lang/String;Ljava/lang/String;IZIZ)V
L1117:  invokeinterface InterfaceMethod java/util/List add (Ljava/lang/Object;)Z 2
L1122:  pop
L1123:  pop2
L1124:  pop2
L1125:  pop2
L1126:  pop2
L1127:  pop2
L1128:  pop2
L1129:  pop2
L1130:  pop2
L1131:  pop2
L1132:  pop2
L1133:  pop2
L1134:  pop2
L1135:  getstatic Field xF field5850 Ljava/util/List;
L1138:  new yD
L1141:  dup
L1142:  ldc "lazer"
L1144:  ldc "Firin' mah lazer"
L1146:  ldc "Send 200 lines to your opponents in a match."
L1148:  sipush 200
L1151:  iconst_1
L1152:  dup
L1153:  pop2
L1154:  iconst_1
L1155:  dup
L1156:  pop2
L1157:  bipush 55
L1159:  iconst_1
L1160:  dup
L1161:  pop2
L1162:  iconst_0
L1163:  iconst_1
L1164:  dup_x2
L1165:  dup
L1166:  pop2
L1167:  invokespecial Method yD <init> (Ljava/lang/String;Ljava/lang/String;Ljava/lang/String;IZIZ)V
L1170:  invokeinterface InterfaceMethod java/util/List add (Ljava/lang/Object;)Z 2
L1175:  getstatic Field xF field5850 Ljava/util/List;
L1178:  new yD
L1181:  dup
L1182:  ldc "300"
L1184:  ldc "Spartaaa!"
L1186:  ldc "Send 300 lines to your opponents in a match."
L1188:  sipush 300
L1191:  iconst_1
L1192:  dup
L1193:  pop2
L1194:  iconst_1
L1195:  dup
L1196:  pop2
L1197:  bipush 83
L1199:  iconst_1
L1200:  dup
L1201:  pop2
L1202:  iconst_0
L1203:  iconst_1
L1204:  dup_x2
L1205:  dup
L1206:  pop2
L1207:  invokespecial Method yD <init> (Ljava/lang/String;Ljava/lang/String;Ljava/lang/String;IZIZ)V
L1210:  invokeinterface InterfaceMethod java/util/List add (Ljava/lang/Object;)Z 2
L1215:  getstatic Field xF field5850 Ljava/util/List;
L1218:  new ze
L1221:  dup
L1222:  ldc "eff"
L1224:  ldc "Efficiency?"
L1226:  ldc_w "Lose an epic round after fighting for three minutes."
L1229:  ldc_w 1.8e2f
L1232:  bipush 10
L1234:  iconst_1
L1235:  dup
L1236:  pop2
L1237:  iconst_0
L1238:  iconst_1
L1239:  dup
L1240:  pop2
L1241:  invokespecial Method ze <init> (Ljava/lang/String;Ljava/lang/String;Ljava/lang/String;FIZ)V
L1244:  invokeinterface InterfaceMethod java/util/List add (Ljava/lang/Object;)Z 2
L1249:  getstatic Field xF field5850 Ljava/util/List;
L1252:  new ZD
L1255:  dup
L1256:  ldc_w "derp"
L1259:  ldc_w "Derp!"
L1262:  ldc_w "Lose a round in less than 15 seconds."
L1265:  ldc_w 1.5e1f
L1268:  iconst_1
L1269:  dup
L1270:  pop2
L1271:  iconst_0
L1272:  iconst_1
L1273:  dup_x1
L1274:  dup
L1275:  pop2
L1276:  invokespecial Method ZD <init> (Ljava/lang/String;Ljava/lang/String;Ljava/lang/String;FIZ)V
L1279:  invokeinterface InterfaceMethod java/util/List add (Ljava/lang/Object;)Z 2
L1284:  getstatic Field xF field5850 Ljava/util/List;
L1287:  new aE
L1290:  dup
L1291:  ldc_w "9000"
L1294:  ldc_w "It's over 9000!"
L1297:  ldc_w "Clear 9'000 lines in matches."
L1300:  sipush 9000
L1303:  iconst_1
L1304:  dup
L1305:  pop2
L1306:  bipush 22
L1308:  iconst_1
L1309:  dup
L1310:  pop2
L1311:  iconst_1
L1312:  dup
L1313:  dup
L1314:  pop2
L1315:  invokespecial Method aE <init> [_24]
L1318:  invokeinterface InterfaceMethod java/util/List add (Ljava/lang/Object;)Z 2
L1323:  getstatic Field xF field5850 Ljava/util/List;
L1326:  new aE
L1329:  dup
L1330:  ldc_w "lifetime"
L1333:  ldc_w "Lifetime"
L1336:  ldc_w "Clear a million lines in matches."
L1339:  ldc_w 1000000
L1342:  bipush 100
L1344:  iconst_1
L1345:  dup
L1346:  pop2
L1347:  iconst_1
L1348:  dup
L1349:  dup
L1350:  pop2
L1351:  invokespecial Method aE <init> [_24]
L1354:  invokeinterface InterfaceMethod java/util/List add (Ljava/lang/Object;)Z 2
L1359:  getstatic Field xF field5850 Ljava/util/List;
L1362:  new aE
L1365:  dup
L1366:  ldc_w "lifetimes"
L1369:  ldc_w "Two lifetimes"
L1372:  ldc_w "Clear two million lines in matches."
L1375:  ldc_w 2000000
L1378:  bipush 100
L1380:  iconst_1
L1381:  dup
L1382:  pop2
L1383:  iconst_0
L1384:  iconst_1
L1385:  dup
L1386:  pop2
L1387:  invokespecial Method aE <init> [_24]
L1390:  invokeinterface InterfaceMethod java/util/List add (Ljava/lang/Object;)Z 2
L1395:  getstatic Field xF field5850 Ljava/util/List;
L1398:  new BG
L1401:  dup
L1402:  ldc_w "doctor"
L1405:  ldc_w "Doctor"
L1408:  ldc_w "Accumulate an hour of playtime in matches."
L1411:  sipush 3600
L1414:  iconst_1
L1415:  dup
L1416:  pop2
L1417:  bipush 8
L1419:  iconst_1
L1420:  dup
L1421:  pop2
L1422:  iconst_1
L1423:  dup
L1424:  dup
L1425:  pop2
L1426:  invokespecial Method BG <init> [_24]
L1429:  invokeinterface InterfaceMethod java/util/List add (Ljava/lang/Object;)Z 2
L1434:  getstatic Field xF field5850 Ljava/util/List;
L1437:  new BG
L1440:  dup
L1441:  ldc_w "amber_lamps"
L1444:  ldc_w "Amber Lamps"
L1447:  ldc_w "Accumulate a day of playtime in matches."
L1450:  ldc_w 86400
L1453:  bipush 18
L1455:  iconst_1
L1456:  dup
L1457:  pop2
L1458:  iconst_1
L1459:  dup
L1460:  dup
L1461:  pop2
L1462:  invokespecial Method BG <init> [_24]
L1465:  invokeinterface InterfaceMethod java/util/List add (Ljava/lang/Object;)Z 2
L1470:  getstatic Field xF field5850 Ljava/util/List;
L1473:  new BG
L1476:  dup
L1477:  ldc_w "chuck_testa"
L1480:  ldc_w "Chuck Testa"
L1483:  ldc_w "Accumulate a week of playtime in matches."
L1486:  ldc_w 604800
L1489:  bipush 36
L1491:  iconst_1
L1492:  dup
L1493:  pop2
L1494:  iconst_1
L1495:  dup
L1496:  dup
L1497:  pop2
L1498:  invokespecial Method BG <init> [_24]
L1501:  invokeinterface InterfaceMethod java/util/List add (Ljava/lang/Object;)Z 2
L1506:  getstatic Field xF field5850 Ljava/util/List;
L1509:  new BG
L1512:  dup
L1513:  ldc_w "epic_beard"
L1516:  ldc_w "Epic Beard Man"
L1519:  ldc_w "Accumulate a month of playtime in matches."
L1522:  ldc_w 2678400
L1525:  bipush 42
L1527:  iconst_1
L1528:  dup
L1529:  pop2
L1530:  iconst_0
L1531:  iconst_1
L1532:  dup
L1533:  pop2
L1534:  invokespecial Method BG <init> [_24]
L1537:  invokeinterface InterfaceMethod java/util/List add (Ljava/lang/Object;)Z 2
L1542:  getstatic Field xF field5850 Ljava/util/List;
L1545:  new WF
L1548:  dup
L1549:  ldc_w "omnom0"
L1552:  ldc_w "Om"
L1555:  ldc_w "Win your first Swiss cheese match."
L1558:  ldc_w 6e3f
L1561:  iconst_1
L1562:  dup
L1563:  pop2
L1564:  iconst_5
L1565:  iconst_1
L1566:  dup
L1567:  pop2
L1568:  iconst_1
L1569:  dup
L1570:  dup_x2
L1571:  dup
L1572:  pop2
L1573:  invokespecial Method WF <init> (Ljava/lang/String;Ljava/lang/String;Ljava/lang/String;FZIZ)V
L1576:  invokeinterface InterfaceMethod java/util/List add (Ljava/lang/Object;)Z 2
L1581:  getstatic Field xF field5850 Ljava/util/List;
L1584:  new WF
L1587:  dup
L1588:  ldc_w "omnom"
L1591:  ldc_w "Om Nom"
L1594:  ldc_w "Win a Swiss cheese match in less than 20 seconds."
L1597:  ldc_w 2e1f
L1600:  iconst_0
L1601:  iconst_1
L1602:  dup
L1603:  pop2
L1604:  bipush 32
L1606:  iconst_1
L1607:  dup
L1608:  pop2
L1609:  iconst_1
L1610:  dup
L1611:  dup
L1612:  pop2
L1613:  invokespecial Method WF <init> (Ljava/lang/String;Ljava/lang/String;Ljava/lang/String;FZIZ)V
L1616:  invokeinterface InterfaceMethod java/util/List add (Ljava/lang/Object;)Z 2
L1621:  getstatic Field xF field5850 Ljava/util/List;
L1624:  new WF
L1627:  dup
L1628:  ldc_w "omnom2"
L1631:  ldc_w "Om Nom Nom"
L1634:  ldc_w "Win a Swiss cheese match in less than 10 seconds."
L1637:  ldc_w 1e1f
L1640:  iconst_1
L1641:  dup
L1642:  pop2
L1643:  bipush 42
L1645:  iconst_1
L1646:  dup
L1647:  pop2
L1648:  iconst_0
L1649:  dup_x1
L1650:  iconst_1
L1651:  dup
L1652:  pop2
L1653:  invokespecial Method WF <init> (Ljava/lang/String;Ljava/lang/String;Ljava/lang/String;FZIZ)V
L1656:  invokeinterface InterfaceMethod java/util/List add (Ljava/lang/Object;)Z 2
L1661:  getstatic Field xF field5850 Ljava/util/List;
L1664:  new Wg
L1667:  dup
L1668:  ldc_w "jean-luc"
L1671:  ldc_w "Facepalm"
L1674:  ldc_w "Misplace an I."
L1677:  iconst_1
L1678:  dup
L1679:  pop2
L1680:  iconst_0
L1681:  iconst_1
L1682:  dup_x1
L1683:  dup
L1684:  pop2
L1685:  invokespecial Method Wg <init> (Ljava/lang/String;Ljava/lang/String;Ljava/lang/String;IZ)V
L1688:  invokeinterface InterfaceMethod java/util/List add (Ljava/lang/Object;)Z 2
L1693:  getstatic Field xF field5850 Ljava/util/List;
L1696:  new cf
L1699:  dup
L1700:  ldc_w "konami"
L1703:  ldc_w "Kazuhisa Hashimoto"
L1706:  ldc_w "Yeah, as if it worked."
L1709:  bipush 15
L1711:  iconst_1
L1712:  dup
L1713:  pop2
L1714:  iconst_0
L1715:  iconst_1
L1716:  dup
L1717:  pop2
L1718:  invokespecial Method cf <init> (Ljava/lang/String;Ljava/lang/String;Ljava/lang/String;IZ)V
L1721:  invokeinterface InterfaceMethod java/util/List add (Ljava/lang/Object;)Z 2
L1726:  getstatic Field xF field5850 Ljava/util/List;
L1729:  new bE
L1732:  dup
L1733:  ldc_w "ef2"
L1736:  ldc_w "Ray LaMontagne"
L1739:  ldc_w "Clear your field twice in a match."
L1742:  iconst_2
L1743:  iconst_1
L1744:  dup
L1745:  pop2
L1746:  bipush 8
L1748:  iconst_1
L1749:  dup
L1750:  pop2
L1751:  iconst_1
L1752:  dup
L1753:  dup
L1754:  pop2
L1755:  invokespecial Method bE <init> [_24]
L1758:  invokeinterface InterfaceMethod java/util/List add (Ljava/lang/Object;)Z 2
L1763:  getstatic Field xF field5850 Ljava/util/List;
L1766:  new bE
L1769:  dup
L1770:  ldc_w "ef3"
L1773:  ldc_w "Metric"
L1776:  ldc_w "Clear your field three times in a match."
L1779:  iconst_3
L1780:  iconst_1
L1781:  dup
L1782:  pop2
L1783:  bipush 12
L1785:  iconst_1
L1786:  dup
L1787:  pop2
L1788:  iconst_0
L1789:  iconst_1
L1790:  dup
L1791:  pop2
L1792:  invokespecial Method bE <init> [_24]
L1795:  invokeinterface InterfaceMethod java/util/List add (Ljava/lang/Object;)Z 2
L1800:  getstatic Field xF field5850 Ljava/util/List;
L1803:  new Zg
L1806:  dup
L1807:  ldc_w "dw"
L1810:  ldc_w "Duh, winning!"
L1813:  ldc_w "Win an official tournament."
L1816:  sipush 200
L1819:  iconst_1
L1820:  dup
L1821:  pop2
L1822:  iconst_0
L1823:  iconst_1
L1824:  dup
L1825:  pop2
L1826:  invokespecial Method Zg <init> (Ljava/lang/String;Ljava/lang/String;Ljava/lang/String;IZ)V
L1829:  invokeinterface InterfaceMethod java/util/List add (Ljava/lang/Object;)Z 2
L1834:  getstatic Field xF field5850 Ljava/util/List;
L1837:  new Zg
L1840:  dup
L1841:  ldc_w "dw2"
L1844:  ldc_w "Duh, almost winning!"
L1847:  ldc_w "Place second or third in an official tournament."
L1850:  bipush 100
L1852:  iconst_1
L1853:  dup
L1854:  pop2
L1855:  iconst_0
L1856:  iconst_1
L1857:  dup
L1858:  pop2
L1859:  invokespecial Method Zg <init> (Ljava/lang/String;Ljava/lang/String;Ljava/lang/String;IZ)V
L1862:  invokeinterface InterfaceMethod java/util/List add (Ljava/lang/Object;)Z 2
L1867:  getstatic Field xF field5850 Ljava/util/List;
L1870:  new Zg
L1873:  dup
L1874:  ldc_w "comm"
L1877:  ldc_w "Never gonna let you down"
L1880:  ldc_w "Do good for the community."
L1883:  bipush 100
L1885:  iconst_1
L1886:  dup
L1887:  pop2
L1888:  iconst_0
L1889:  iconst_1
L1890:  dup
L1891:  pop2
L1892:  invokespecial Method Zg <init> (Ljava/lang/String;Ljava/lang/String;Ljava/lang/String;IZ)V
L1895:  invokeinterface InterfaceMethod java/util/List add (Ljava/lang/Object;)Z 2
L1900:  getstatic Field xF field5850 Ljava/util/List;
L1903:  new Zg
L1906:  dup
L1907:  ldc_w "gw"
L1910:  ldc_w "The golden voice"
L1913:  ldc_w "Be an awesome commentator."
L1916:  bipush 60
L1918:  iconst_1
L1919:  dup
L1920:  pop2
L1921:  iconst_0
L1922:  iconst_1
L1923:  dup
L1924:  pop2
L1925:  invokespecial Method Zg <init> (Ljava/lang/String;Ljava/lang/String;Ljava/lang/String;IZ)V
L1928:  invokeinterface InterfaceMethod java/util/List add (Ljava/lang/Object;)Z 2
L1933:  getstatic Field xF field5850 Ljava/util/List;
L1936:  new Zg
L1939:  dup
L1940:  ldc_w "data"
L1943:  ldc_w "Data analyst"
L1946:  ldc_w "Instead of going out or meeting people, spend your free time analyzing Cultris."
L1949:  bipush 30
L1951:  iconst_1
L1952:  dup
L1953:  pop2
L1954:  iconst_0
L1955:  iconst_1
L1956:  dup
L1957:  pop2
L1958:  invokespecial Method Zg <init> (Ljava/lang/String;Ljava/lang/String;Ljava/lang/String;IZ)V
L1961:  invokeinterface InterfaceMethod java/util/List add (Ljava/lang/Object;)Z 2
L1966:  getstatic Field xF field5850 Ljava/util/List;
L1969:  new of
L1972:  dup
L1973:  ldc_w "swm1"
L1976:  ldc_w "The cheese is a lie"
L1979:  ldc_w "Win a Swiss Cheese with 12 pieces or less."
L1982:  bipush 12
L1984:  iconst_1
L1985:  dup
L1986:  pop2
L1987:  bipush 35
L1989:  iconst_1
L1990:  dup
L1991:  pop2
L1992:  iconst_1
L1993:  dup
L1994:  dup
L1995:  pop2
L1996:  invokespecial Method of <init> [_24]
L1999:  invokeinterface InterfaceMethod java/util/List add (Ljava/lang/Object;)Z 2
L2004:  getstatic Field xF field5850 Ljava/util/List;
L2007:  new of
L2010:  dup
L2011:  ldc_w "swm2"
L2014:  ldc_w "Thine curd is untrue"
L2017:  ldc_w "Win a Swiss Cheese with 10 pieces."
L2020:  bipush 10
L2022:  iconst_1
L2023:  dup
L2024:  pop2
L2025:  bipush 50
L2027:  iconst_1
L2028:  dup
L2029:  pop2
L2030:  iconst_0
L2031:  iconst_1
L2032:  dup
L2033:  pop2
L2034:  invokespecial Method of <init> [_24]
L2037:  invokeinterface InterfaceMethod java/util/List add (Ljava/lang/Object;)Z 2
L2042:  getstatic Field xF field5850 Ljava/util/List;
L2045:  new Je
L2048:  dup
L2049:  ldc_w "rs1"
L2052:  ldc_w "Collector"
L2055:  ldc_w "Collect more than 50 points in a room."
L2058:  bipush 50
L2060:  iconst_1
L2061:  dup
L2062:  pop2
L2063:  bipush 10
L2065:  iconst_1
L2066:  dup
L2067:  pop2
L2068:  iconst_1
L2069:  dup
L2070:  dup
L2071:  pop2
L2072:  invokespecial Method Je <init> [_24]
L2075:  invokeinterface InterfaceMethod java/util/List add (Ljava/lang/Object;)Z 2
L2080:  getstatic Field xF field5850 Ljava/util/List;
L2083:  new Je
L2086:  dup
L2087:  ldc_w "rs2"
L2090:  ldc_w "Hunter"
L2093:  ldc_w "Collect more than 100 points in a room."
L2096:  bipush 100
L2098:  iconst_1
L2099:  dup
L2100:  pop2
L2101:  bipush 25
L2103:  iconst_1
L2104:  dup
L2105:  pop2
L2106:  iconst_0
L2107:  iconst_1
L2108:  dup
L2109:  pop2
L2110:  invokespecial Method Je <init> [_24]
L2113:  invokeinterface InterfaceMethod java/util/List add (Ljava/lang/Object;)Z 2
L2118:  getstatic Field xF field5850 Ljava/util/List;
L2121:  new Je
L2124:  dup
L2125:  ldc_w "rs3"
L2128:  ldc_w "Freak"
L2131:  ldc_w "Collect more than 500 points in a room."
L2134:  sipush 500
L2137:  iconst_1
L2138:  dup
L2139:  pop2
L2140:  bipush 50
L2142:  iconst_1
L2143:  dup
L2144:  pop2
L2145:  iconst_0
L2146:  iconst_1
L2147:  dup
L2148:  pop2
L2149:  invokespecial Method Je <init> [_24]
L2152:  invokeinterface InterfaceMethod java/util/List add (Ljava/lang/Object;)Z 2
L2157:  getstatic Field xF field5850 Ljava/util/List;
L2160:  new uD
L2163:  dup
L2164:  ldc_w "cdp"
L2167:  ldc_w "Crowd pleaser"
L2170:  ldc_w "Win in a room with 25 people."
L2173:  bipush 25
L2175:  iconst_1
L2176:  dup
L2177:  pop2
L2178:  iconst_5
L2179:  iconst_1
L2180:  dup
L2181:  pop2
L2182:  iconst_1
L2183:  dup
L2184:  dup
L2185:  pop2
L2186:  invokespecial Method uD <init> [_24]
L2189:  invokeinterface InterfaceMethod java/util/List add (Ljava/lang/Object;)Z 2
L2194:  new java/util/HashSet
L2197:  dup
L2198:  invokespecial Method java/util/HashSet <init> ()V
L2201:  astore_0
L2202:  getstatic Field xF field5850 Ljava/util/List;
L2205:  invokeinterface InterfaceMethod java/util/List iterator ()Ljava/util/Iterator; 1
L2210:  astore_1
L2211:  pop
L2212:  pop2
L2213:  pop2
L2214:  pop2
L2215:  pop2
L2216:  pop2
L2217:  pop2
L2218:  pop2
L2219:  pop2
L2220:  pop2
L2221:  pop2
L2222:  pop2
L2223:  pop2
L2224:  pop2
L2225:  pop2
L2226:  pop2
L2227:  aload_1
L2228:  invokeinterface InterfaceMethod java/util/Iterator hasNext ()Z 1
L2233:  ifeq L2272
L2236:  aload_1
L2237:  invokeinterface InterfaceMethod java/util/Iterator next ()Ljava/lang/Object; 1
L2242:  checkcast Uf
L2245:  astore_2
L2246:  aload_0
L2247:  aload_2
L2248:  getfield Field Uf field1348 Ljava/lang/String;
L2251:  invokevirtual Method java/util/HashSet add (Ljava/lang/Object;)Z
L2254:  ifne L2227
L2257:  new java/lang/RuntimeException
L2260:  dup
L2261:  ldc_w "Duplicate key"
L2264:  invokespecial Method java/lang/RuntimeException <init> (Ljava/lang/String;)V
L2267:  athrow
L2268:  nop
L2269:  nop
L2270:  nop
L2271:  athrow
L2272:  return
L2273:  
        .attribute StackMap b'\x00\x03\x08\xB3\x00\x02\x07\x01\xCE\x07\x01\xD5\x00\x00\x08\xDC\x00\x00\x00\x01\x07\x01\xED\x08\xE0\x00\x02\x07\x01\xCE\x07\x01\xD5\x00\x00'
    .end code
.end method

.method public static method5824 : (Ljava/lang/String;)LUf;
    .code stack 2 locals 3
L0:     getstatic Field xF field5850 Ljava/util/List;
L3:     invokeinterface InterfaceMethod java/util/List iterator ()Ljava/util/Iterator; 1
L8:     astore_1
L9:     aload_1
L10:    invokeinterface InterfaceMethod java/util/Iterator hasNext ()Z 1
L15:    ifeq L46
L18:    aload_1
L19:    invokeinterface InterfaceMethod java/util/Iterator next ()Ljava/lang/Object; 1
L24:    checkcast Uf
L27:    dup
L28:    astore_2
L29:    getfield Field Uf field1348 Ljava/lang/String;
L32:    aload_0
L33:    invokevirtual Method java/lang/String equals (Ljava/lang/Object;)Z
L36:    ifeq L9
L39:    aload_2
L40:    areturn
L41:    nop
L42:    nop
L43:    nop
L44:    nop
L45:    athrow
L46:    aconst_null
L47:    areturn
L48:    
        .attribute StackMap b'\x00\x03\x00\x09\x00\x02\x07\x01\xF1\x07\x01\xD5\x00\x00\x00\x29\x00\x00\x00\x01\x07\x01\xED\x00\x2E\x00\x02\x07\x01\xF1\x07\x01\xD5\x00\x00'
    .end code
.end method

.method public <init> : ()V
    .code stack 1 locals 1
L0:     aload_0
L1:     invokespecial Method java/lang/Object <init> ()V
L4:     return
L5:     
    .end code
.end method
.const [_24] = Utf8 (Ljava/lang/String;Ljava/lang/String;Ljava/lang/String;IIZ)V
.end class
