.version 49 0
.class public final super YA
.super java/lang/Object
.field private this [I
.field private char [LzA;
.field private else [I
.field private "enum" LNA;
.field private do [I

.method public const : ([I)V
    .code stack 2 locals 2
L0:     aload_0
L1:     aload_1
L2:     putfield Field YA do [I
L5:     return
L6:     
    .end code
.end method

.method private break : ([Ljava/lang/Object;)[I
    .code stack 5 locals 5
L0:     aload_1
L1:     arraylength
L2:     newarray int
L4:     iconst_1
L5:     dup
L6:     pop2
L7:     astore_2
L8:     new java/util/HashMap
L11:    dup
L12:    aload_1
L13:    arraylength
L14:    invokespecial Method java/util/HashMap <init> (I)V
L17:    astore_3
L18:    iconst_0
L19:    iconst_1
L20:    dup
L21:    pop2
L22:    dup
L23:    istore 4
L25:    aload_1
L26:    arraylength
L27:    if_icmpge L90
L30:    aload_3
L31:    aload_1
L32:    iload 4
L34:    aaload
L35:    invokevirtual Method java/util/HashMap containsKey (Ljava/lang/Object;)Z
L38:    ifne L64
L41:    aload_3
L42:    aload_1
L43:    aload_2
L44:    iload 4
L46:    dup
L47:    iastore
L48:    iload 4
L50:    aaload
L51:    iload 4
L53:    invokestatic Method java/lang/Integer valueOf (I)Ljava/lang/Integer;
L56:    invokevirtual Method java/util/HashMap put (Ljava/lang/Object;Ljava/lang/Object;)Ljava/lang/Object;
L59:    pop
L60:    goto L81
L63:    athrow
L64:    aload_2
L65:    aload_3
L66:    aload_1
L67:    iload 4
L69:    dup_x2
L70:    aaload
L71:    invokevirtual Method java/util/HashMap get (Ljava/lang/Object;)Ljava/lang/Object;
L74:    checkcast java/lang/Integer
L77:    invokevirtual Method java/lang/Integer intValue ()I
L80:    iastore
L81:    iinc 4 1
L84:    iload 4
L86:    goto L25
L89:    athrow
L90:    aload_2
L91:    areturn
L92:    
        .attribute StackMap b'\x00\x06\x00\x19\x00\x05\x07\x00\x02\x07\x00\x1E\x07\x00\x1F\x07\x00\x18\x01\x00\x01\x01\x00\x3F\x00\x00\x00\x01\x07\x00\x2F\x00\x40\x00\x05\x07\x00\x02\x07\x00\x1E\x07\x00\x1F\x07\x00\x18\x01\x00\x00\x00\x51\x00\x05\x07\x00\x02\x07\x00\x1E\x07\x00\x1F\x07\x00\x18\x01\x00\x00\x00\x59\x00\x00\x00\x01\x07\x00\x2F\x00\x5A\x00\x05\x07\x00\x02\x07\x00\x1E\x07\x00\x1F\x07\x00\x18\x01\x00\x00'
    .end code
.end method

.method public <init> : ()V
    .code stack 10 locals 1
L0:     aconst_null
L1:     aload_0
L2:     dup_x1
L3:     dup_x2
L4:     aconst_null
L5:     dup
L6:     aload_0
L7:     dup_x1
L8:     aconst_null
L9:     aload_0
L10:    invokespecial Method java/lang/Object <init> ()V
L13:    putfield Field YA char [LzA;
L16:    putfield Field YA do [I
L19:    putfield Field YA else [I
L22:    putfield Field YA this [I
L25:    new NA
L28:    aload_0
L29:    dup
L30:    pop2
L31:    dup
L32:    invokespecial Method NA <init> ()V
L35:    putfield Field YA "enum" LNA;
L38:    return
L39:    
    .end code
.end method

.method public else : ([I)V
    .code stack 2 locals 2
L0:     aload_0
L1:     aload_1
L2:     putfield Field YA this [I
L5:     return
L6:     
    .end code
.end method

.method public break : ([LzA;)V
    .code stack 2 locals 2
L0:     aload_0
L1:     aload_1
L2:     putfield Field YA char [LzA;
L5:     return
L6:     
    .end code
.end method

.method public catch : ()Ljava/util/List;
    .code stack 13 locals 3
L0:     aload_0
L1:     getfield Field YA "enum" LNA;
L4:     aload_0
L5:     dup_x1
L6:     invokevirtual Method NA break (LYA;)V
L9:     getfield Field YA do [I
L12:    ifnull L74
L15:    aload_0
L16:    getfield Field YA do [I
L19:    arraylength
L20:    anewarray zA
L23:    iconst_1
L24:    dup
L25:    pop2
L26:    astore_1
L27:    iconst_0
L28:    iconst_1
L29:    dup
L30:    pop2
L31:    dup
L32:    istore_2
L33:    aload_0
L34:    getfield Field YA do [I
L37:    arraylength
L38:    if_icmpge L64
L41:    aload_1
L42:    aload_0
L43:    dup
L44:    getfield Field YA char [LzA;
L47:    swap
L48:    getfield Field YA do [I
L51:    iload_2
L52:    dup_x2
L53:    iaload
L54:    aaload
L55:    iinc 2 1
L58:    aastore
L59:    iload_2
L60:    goto L33
L63:    athrow
L64:    aload_0
L65:    aconst_null
L66:    aload_0
L67:    aload_1
L68:    putfield Field YA char [LzA;
L71:    putfield Field YA do [I
L74:    new java/util/ArrayList
L77:    dup
L78:    invokespecial Method java/util/ArrayList <init> ()V
L81:    astore_1
L82:    iconst_0
L83:    iconst_1
L84:    dup
L85:    pop2
L86:    dup
L87:    istore_2
L88:    aload_0
L89:    getfield Field YA char [LzA;
L92:    arraylength
L93:    if_icmpge L205
L96:    new nA
L99:    aload_1
L100:   dup_x1
L101:   dup
L102:   pop2
L103:   dup
L104:   aload_0
L105:   getfield Field YA char [LzA;
L108:   iload_2
L109:   iconst_0
L110:   iconst_1
L111:   dup
L112:   pop2
L113:   iadd
L114:   aaload
L115:   getfield Field zA do F
L118:   aload_0
L119:   getfield Field YA char [LzA;
L122:   iload_2
L123:   iconst_0
L124:   iconst_1
L125:   dup
L126:   pop2
L127:   iadd
L128:   aaload
L129:   getfield Field zA else F
L132:   aload_0
L133:   getfield Field YA char [LzA;
L136:   iload_2
L137:   iconst_1
L138:   dup
L139:   dup
L140:   pop2
L141:   iadd
L142:   aaload
L143:   getfield Field zA do F
L146:   aload_0
L147:   getfield Field YA char [LzA;
L150:   iload_2
L151:   iconst_1
L152:   dup
L153:   dup
L154:   pop2
L155:   iadd
L156:   aaload
L157:   getfield Field zA else F
L160:   aload_0
L161:   getfield Field YA char [LzA;
L164:   iload_2
L165:   iconst_2
L166:   iconst_1
L167:   dup
L168:   pop2
L169:   iadd
L170:   aaload
L171:   getfield Field zA do F
L174:   aload_0
L175:   getfield Field YA char [LzA;
L178:   iload_2
L179:   iconst_2
L180:   iconst_1
L181:   dup
L182:   pop2
L183:   iadd
L184:   iinc 2 3
L187:   aaload
L188:   getfield Field zA else F
L191:   invokespecial Method nA <init> (FFFFFF)V
L194:   invokeinterface InterfaceMethod java/util/List add (Ljava/lang/Object;)Z 2
L199:   pop
L200:   iload_2
L201:   goto L88
L204:   athrow
L205:   aload_1
L206:   areturn
L207:   
        .attribute StackMap b'\x00\x07\x00\x21\x00\x03\x07\x00\x02\x07\x00\x4E\x01\x00\x01\x01\x00\x3F\x00\x00\x00\x01\x07\x00\x2F\x00\x40\x00\x03\x07\x00\x02\x07\x00\x4E\x01\x00\x00\x00\x4A\x00\x01\x07\x00\x02\x00\x00\x00\x58\x00\x03\x07\x00\x02\x07\x00\x50\x01\x00\x01\x01\x00\xCC\x00\x00\x00\x01\x07\x00\x2F\x00\xCD\x00\x03\x07\x00\x02\x07\x00\x50\x01\x00\x00'
    .end code
.end method

.method public float : ()[LzA;
    .code stack 1 locals 1
L0:     aload_0
L1:     getfield Field YA char [LzA;
L4:     areturn
L5:     
    .end code
.end method

.method public short : ()V
    .code stack 3 locals 1
L0:     aload_0
L1:     getfield Field YA do [I
L4:     ifnull L9
L7:     return
L8:     athrow
L9:     aload_0
L10:    dup
L11:    dup_x1
L12:    getfield Field YA char [LzA;
L15:    invokespecial Method YA break ([Ljava/lang/Object;)[I
L18:    putfield Field YA do [I
L21:    return
L22:    
        .attribute StackMap b'\x00\x02\x00\x08\x00\x00\x00\x01\x07\x00\x2F\x00\x09\x00\x01\x07\x00\x02\x00\x00'
    .end code
.end method

.method public break : ([I)V
    .code stack 2 locals 2
L0:     aload_0
L1:     aload_1
L2:     putfield Field YA else [I
L5:     return
L6:     
    .end code
.end method

.method public const : ()[I
    .code stack 1 locals 1
L0:     aload_0
L1:     getfield Field YA else [I
L4:     areturn
L5:     
    .end code
.end method

.method public else : ()[I
    .code stack 1 locals 1
L0:     aload_0
L1:     getfield Field YA this [I
L4:     areturn
L5:     
    .end code
.end method

.method public break : ()[I
    .code stack 1 locals 1
L0:     aload_0
L1:     getfield Field YA do [I
L4:     areturn
L5:     
    .end code
.end method
.innerclasses
    nA zc [0] public static
.end innerclasses
.end class
