.version 49 0
.class public final super yF
.super eb

.method public <init> : ()V
    .code stack 1 locals 1
L0:     aload_0
L1:     invokespecial Method eb <init> ()V
L4:     return
L5:     
    .end code
.end method

.method public method766 : (LRg;[I)F
    .code stack 3 locals 3
L0:     aload_0
L1:     aload_1
L2:     aload_2
L3:     invokespecial Method eb method766 (LRg;[I)F
L6:     ldc 4e0f
L8:     fmul
L9:     ldc 1.5e0f
L11:    fadd
L12:    freturn
L13:    
    .end code
.end method

.method public method750 : (LRg;)F
    .code stack 1 locals 2
L0:     ldc 3e-1f
L2:     freturn
L3:     
    .end code
.end method

.method public method762 : (LRg;)V
    .code stack 5 locals 2
L0:     aload_1
L1:     iconst_m1
L2:     iconst_1
L3:     dup
L4:     pop2
L5:     bipush 43
L7:     iconst_1
L8:     dup
L9:     pop2
L10:    invokevirtual Method Rg method236 (II)V
L13:    return
L14:    
    .end code
.end method

.method public method765 : (LRg;[I)V
    .code stack 3 locals 3
L0:     aload_1
L1:     instanceof oF
L4:     ifeq L13
L7:     aload_0
L8:     aload_1
L9:     aload_2
L10:    invokespecial Method eb method765 (LRg;[I)V
L13:    return
L14:    
        .attribute StackMap b'\x00\x01\x00\x0D\x00\x03\x07\x00\x02\x07\x00\x1A\x07\x00\x26\x00\x00'
    .end code
.end method

.method public method759 : (LRg;[I)I
    .code stack 6 locals 3
L0:     iconst_3
L1:     iconst_1
L2:     dup
L3:     pop2
L4:     aload_1
L5:     getfield Field Rg field225 I
L8:     iconst_1
L9:     dup
L10:    dup
L11:    pop2
L12:    isub
L13:    imul
L14:    iconst_2
L15:    iconst_1
L16:    dup
L17:    pop2
L18:    aload_2
L19:    arraylength
L20:    iconst_1
L21:    dup
L22:    dup
L23:    pop2
L24:    isub
L25:    imul
L26:    iadd
L27:    ireturn
L28:    
    .end code
.end method

.method public method764 : (Lqd;)F
    .code stack 1 locals 2
L0:     fconst_0
L1:     freturn
L2:     
    .end code
.end method
.innerclasses
    yF [0] [0] static
.end innerclasses
.enclosing method SE shep ([LTe;)LTe;
.end class
