.version 49 0
.class public final super YF
.super Uf
.field public this I
.field public field1363 I
.field public field1364 LDF;
.field public field1365 I

.method public method700 : ()LgB;
    .code stack 8 locals 2
L0:     new qc
L3:     dup
L4:     new VD
L7:     dup
L8:     invokespecial Method VD <init> ()V
L11:    invokespecial Method qc <init> (Ld;)V
L14:    astore_1
L15:    new DF
L18:    aload_1
L19:    dup_x1
L20:    dup
L21:    pop2
L22:    dup
L23:    new java/lang/StringBuilder
L26:    dup
L27:    invokespecial Method java/lang/StringBuilder <init> ()V
L30:    aload_0
L31:    getfield Field YF field1363 I
L34:    ifne L43
L37:    ldc ""
L39:    goto L45
L42:    athrow
L43:    ldc "Remaining "
L45:    invokevirtual Method java/lang/StringBuilder append (Ljava/lang/String;)Ljava/lang/StringBuilder;
L48:    aload_0
L49:    getfield Field YF this I
L52:    iconst_4
L53:    iconst_1
L54:    dup
L55:    pop2
L56:    if_icmpne L65
L59:    ldc "Tetrises"
L61:    goto L87
L64:    athrow
L65:    new java/lang/StringBuilder
L68:    dup
L69:    invokespecial Method java/lang/StringBuilder <init> ()V
L72:    aload_0
L73:    getfield Field YF this I
L76:    invokevirtual Method java/lang/StringBuilder append (I)Ljava/lang/StringBuilder;
L79:    ldc "-line clears"
L81:    invokevirtual Method java/lang/StringBuilder append (Ljava/lang/String;)Ljava/lang/StringBuilder;
L84:    invokevirtual Method java/lang/StringBuilder toString ()Ljava/lang/String;
L87:    invokevirtual Method java/lang/StringBuilder append (Ljava/lang/String;)Ljava/lang/StringBuilder;
L90:    invokevirtual Method java/lang/StringBuilder toString ()Ljava/lang/String;
L93:    getstatic Field We try LWe;
L96:    invokespecial Method DF <init> (Ljava/lang/String;LWe;)V
L99:    getstatic Field VD field150 Ljava/lang/Object;
L102:   invokevirtual Method qc method31 (LgB;Ljava/lang/Object;)V
L105:   aload_1
L106:   new DF
L109:   aload_0
L110:   dup_x1
L111:   dup
L112:   pop2
L113:   dup
L114:   ldc " "
L116:   getstatic Field We field475 LWe;
L119:   invokespecial Method DF <init> (Ljava/lang/String;LWe;)V
L122:   dup_x1
L123:   putfield Field YF field1364 LDF;
L126:   invokevirtual Method qc method36 (LgB;)LgB;
L129:   aload_0
L130:   getfield Field YF field1364 LDF;
L133:   iconst_1
L134:   dup
L135:   dup
L136:   pop2
L137:   invokevirtual Method DF method95 (Z)V
L140:   pop
L141:   aload_1
L142:   areturn
L143:   
        .attribute StackMap b'\x00\x06\x00\x2A\x00\x00\x00\x01\x07\x00\x22\x00\x2B\x00\x02\x07\x00\x02\x07\x00\x0E\x00\x04\x07\x00\x0E\x08\x00\x0F\x08\x00\x0F\x07\x00\x1B\x00\x2D\x00\x02\x07\x00\x02\x07\x00\x0E\x00\x05\x07\x00\x0E\x08\x00\x0F\x08\x00\x0F\x07\x00\x1B\x07\x00\x26\x00\x40\x00\x00\x00\x01\x07\x00\x22\x00\x41\x00\x02\x07\x00\x02\x07\x00\x0E\x00\x04\x07\x00\x0E\x08\x00\x0F\x08\x00\x0F\x07\x00\x1B\x00\x57\x00\x02\x07\x00\x02\x07\x00\x0E\x00\x05\x07\x00\x0E\x08\x00\x0F\x08\x00\x0F\x07\x00\x1B\x07\x00\x26'
    .end code
.end method

.method public method703 : (LRg;)V
    .code stack 5 locals 2
L0:     aload_0
L1:     dup
L2:     iconst_0
L3:     iconst_1
L4:     dup
L5:     pop2
L6:     putfield Field YF field1365 I
L9:     getfield Field YF field1364 LDF;
L12:    ifnull L44
L15:    aload_0
L16:    getfield Field YF field1364 LDF;
L19:    new java/lang/StringBuilder
L22:    dup
L23:    invokespecial Method java/lang/StringBuilder <init> ()V
L26:    aload_0
L27:    getfield Field YF field1363 I
L30:    invokevirtual Method java/lang/StringBuilder append (I)Ljava/lang/StringBuilder;
L33:    ldc ""
L35:    invokevirtual Method java/lang/StringBuilder append (Ljava/lang/String;)Ljava/lang/StringBuilder;
L38:    invokevirtual Method java/lang/StringBuilder toString ()Ljava/lang/String;
L41:    invokevirtual Method DF method12 (Ljava/lang/String;)V
L44:    return
L45:    
        .attribute StackMap b'\x00\x01\x00\x2C\x00\x02\x07\x00\x02\x07\x00\x61\x00\x00'
    .end code
.end method

.method public <init> : (Ljava/lang/String;Ljava/lang/String;Ljava/lang/String;IIIZZ)V
    .code stack 15 locals 9
L0:     iload 8
L2:     aload_0
L3:     dup_x1
L4:     iload 5
L6:     iload 4
L8:     aload_0
L9:     dup_x1
L10:    iconst_0
L11:    aload_0
L12:    aload_1
L13:    aload_2
L14:    new java/lang/StringBuilder
L17:    aload_3
L18:    dup_x1
L19:    dup
L20:    pop2
L21:    dup
L22:    invokespecial Method java/lang/StringBuilder <init> ()V
L25:    iload 4
L27:    invokevirtual Method java/lang/StringBuilder append (I)Ljava/lang/StringBuilder;
L30:    ldc "-line clears to do: "
L32:    invokevirtual Method java/lang/StringBuilder append (Ljava/lang/String;)Ljava/lang/StringBuilder;
L35:    iload 5
L37:    invokevirtual Method java/lang/StringBuilder append (I)Ljava/lang/StringBuilder;
L40:    invokevirtual Method java/lang/StringBuilder toString ()Ljava/lang/String;
L43:    iload 6
L45:    iload 7
L47:    invokespecial Method Uf <init> (Ljava/lang/String;Ljava/lang/String;Ljava/lang/String;Ljava/lang/String;IZ)V
L50:    iconst_1
L51:    dup
L52:    pop2
L53:    putfield Field YF field1365 I
L56:    putfield Field YF this I
L59:    putfield Field YF field1363 I
L62:    putfield Field YF field1352 Z
L65:    return
L66:    
    .end code
.end method

.method public method704 : (LRg;)Z
    .code stack 7 locals 2
L0:     aload_0
L1:     aload_1
L2:     aconst_null
L3:     checkcast [[I
L6:     aconst_null
L7:     iconst_0
L8:     iconst_1
L9:     dup
L10:    pop2
L11:    newarray int
L13:    iconst_1
L14:    dup
L15:    pop2
L16:    invokevirtual Method YF method699 (LRg;[[ILff;[I)Z
L19:    ireturn
L20:    
    .end code
.end method

.method public method699 : (LRg;[[ILff;[I)Z
    .code stack 5 locals 5
L0:     aload_0
L1:     getfield Field YF this I
L4:     iconst_4
L5:     iconst_1
L6:     dup
L7:     pop2
L8:     if_icmpne L124
L11:    aload_0
L12:    getfield Field YF field1363 I
L15:    ifne L26
L18:    aload_1
L19:    getfield Field Rg field215 F
L22:    goto L36
L25:    athrow
L26:    aload_0
L27:    getfield Field YF field1363 I
L30:    i2f
L31:    aload_1
L32:    getfield Field Rg field215 F
L35:    fsub
L36:    fstore_2
L37:    fload_2
L38:    fconst_0
L39:    fcmpg
L40:    ifge L45
L43:    fconst_0
L44:    fstore_2
L45:    aload_0
L46:    getfield Field YF field1364 LDF;
L49:    ifnull L88
L52:    aload_0
L53:    getfield Field YF field1364 LDF;
L56:    new java/lang/StringBuilder
L59:    dup
L60:    invokespecial Method java/lang/StringBuilder <init> ()V
L63:    iconst_0
L64:    getstatic Field fE try LfE;
L67:    fload_2
L68:    invokevirtual Method fE method302 (F)Ljava/lang/String;
L71:    invokevirtual Method java/lang/String trim ()Ljava/lang/String;
L74:    invokevirtual Method java/lang/StringBuilder insert (ILjava/lang/String;)Ljava/lang/StringBuilder;
L77:    ldc ""
L79:    invokevirtual Method java/lang/StringBuilder append (Ljava/lang/String;)Ljava/lang/StringBuilder;
L82:    invokevirtual Method java/lang/StringBuilder toString ()Ljava/lang/String;
L85:    invokevirtual Method DF method12 (Ljava/lang/String;)V
L88:    aload_0
L89:    getfield Field YF field1363 I
L92:    ifne L101
L95:    iconst_0
L96:    iconst_1
L97:    dup
L98:    pop2
L99:    ireturn
L100:   athrow
L101:   aload_1
L102:   getfield Field Rg field215 F
L105:   aload_0
L106:   getfield Field YF field1363 I
L109:   i2f
L110:   fcmpl
L111:   iflt L119
L114:   iconst_1
L115:   dup
L116:   dup
L117:   pop2
L118:   ireturn
L119:   iconst_0
L120:   iconst_1
L121:   dup
L122:   pop2
L123:   ireturn
L124:   aload 4
L126:   arraylength
L127:   aload_0
L128:   getfield Field YF this I
L131:   if_icmpne L147
L134:   aload_0
L135:   dup
L136:   getfield Field YF field1365 I
L139:   iconst_1
L140:   dup
L141:   dup
L142:   pop2
L143:   iadd
L144:   putfield Field YF field1365 I
L147:   aload_0
L148:   getfield Field YF field1363 I
L151:   aload_0
L152:   swap
L153:   ifne L162
L156:   getfield Field YF field1365 I
L159:   goto L170
L162:   getfield Field YF field1363 I
L165:   aload_0
L166:   getfield Field YF field1365 I
L169:   isub
L170:   istore_2
L171:   iload_2
L172:   ifge L180
L175:   iconst_0
L176:   iconst_1
L177:   dup
L178:   pop2
L179:   istore_2
L180:   aload_0
L181:   getfield Field YF field1364 LDF;
L184:   ifnull L213
L187:   aload_0
L188:   getfield Field YF field1364 LDF;
L191:   new java/lang/StringBuilder
L194:   dup
L195:   invokespecial Method java/lang/StringBuilder <init> ()V
L198:   iload_2
L199:   invokevirtual Method java/lang/StringBuilder append (I)Ljava/lang/StringBuilder;
L202:   ldc ""
L204:   invokevirtual Method java/lang/StringBuilder append (Ljava/lang/String;)Ljava/lang/StringBuilder;
L207:   invokevirtual Method java/lang/StringBuilder toString ()Ljava/lang/String;
L210:   invokevirtual Method DF method12 (Ljava/lang/String;)V
L213:   aload_0
L214:   getfield Field YF field1363 I
L217:   ifne L225
L220:   iconst_0
L221:   iconst_1
L222:   dup
L223:   pop2
L224:   ireturn
L225:   aload_0
L226:   dup
L227:   getfield Field YF field1365 I
L230:   swap
L231:   getfield Field YF field1363 I
L234:   if_icmplt L242
L237:   iconst_1
L238:   dup
L239:   dup
L240:   pop2
L241:   ireturn
L242:   iconst_0
L243:   iconst_1
L244:   dup
L245:   pop2
L246:   ireturn
L247:   
        .attribute StackMap b'\x00\x10\x00\x19\x00\x00\x00\x01\x07\x00\x22\x00\x1A\x00\x05\x07\x00\x02\x07\x00\x61\x07\x00\x6F\x07\x00\x79\x07\x00\x7B\x00\x00\x00\x24\x00\x05\x07\x00\x02\x07\x00\x61\x07\x00\x6F\x07\x00\x79\x07\x00\x7B\x00\x01\x02\x00\x2D\x00\x05\x07\x00\x02\x07\x00\x61\x02\x07\x00\x79\x07\x00\x7B\x00\x00\x00\x58\x00\x05\x07\x00\x02\x07\x00\x61\x02\x07\x00\x79\x07\x00\x7B\x00\x00\x00\x64\x00\x00\x00\x01\x07\x00\x22\x00\x65\x00\x05\x07\x00\x02\x07\x00\x61\x02\x07\x00\x79\x07\x00\x7B\x00\x00\x00\x77\x00\x05\x07\x00\x02\x07\x00\x61\x02\x07\x00\x79\x07\x00\x7B\x00\x00\x00\x7C\x00\x05\x07\x00\x02\x07\x00\x61\x07\x00\x6F\x07\x00\x79\x07\x00\x7B\x00\x00\x00\x93\x00\x05\x07\x00\x02\x07\x00\x61\x07\x00\x6F\x07\x00\x79\x07\x00\x7B\x00\x00\x00\xA2\x00\x05\x07\x00\x02\x07\x00\x61\x07\x00\x6F\x07\x00\x79\x07\x00\x7B\x00\x01\x07\x00\x02\x00\xAA\x00\x05\x07\x00\x02\x07\x00\x61\x07\x00\x6F\x07\x00\x79\x07\x00\x7B\x00\x01\x01\x00\xB4\x00\x05\x07\x00\x02\x07\x00\x61\x01\x07\x00\x79\x07\x00\x7B\x00\x00\x00\xD5\x00\x05\x07\x00\x02\x07\x00\x61\x01\x07\x00\x79\x07\x00\x7B\x00\x00\x00\xE1\x00\x05\x07\x00\x02\x07\x00\x61\x01\x07\x00\x79\x07\x00\x7B\x00\x00\x00\xF2\x00\x05\x07\x00\x02\x07\x00\x61\x01\x07\x00\x79\x07\x00\x7B\x00\x00'
    .end code
.end method
.end class
