.version 49 0
.class public final super yg
.super Uf

.method private break : ([[I)I
    .code stack 4 locals 5
L0:     aload_1
L1:     iconst_0
L2:     iconst_1
L3:     dup
L4:     pop2
L5:     aaload
L6:     arraylength
L7:     istore_2
L8:     iconst_0
L9:     iconst_1
L10:    dup
L11:    pop2
L12:    dup
L13:    istore_3
L14:    aload_1
L15:    arraylength
L16:    if_icmpge L62
L19:    iconst_0
L20:    iconst_1
L21:    dup
L22:    pop2
L23:    dup
L24:    istore 4
L26:    iload_2
L27:    if_icmpge L55
L30:    aload_1
L31:    iload_3
L32:    aaload
L33:    iload 4
L35:    iaload
L36:    ifeq L46
L39:    iload 4
L41:    istore_2
L42:    goto L55
L45:    athrow
L46:    iinc 4 1
L49:    iload 4
L51:    goto L26
L54:    athrow
L55:    iinc 3 1
L58:    iload_3
L59:    goto L14
L62:    aload_1
L63:    iconst_0
L64:    iconst_1
L65:    dup
L66:    pop2
L67:    aaload
L68:    arraylength
L69:    iload_2
L70:    isub
L71:    ireturn
L72:    
        .attribute StackMap b'\x00\x07\x00\x0E\x00\x04\x07\x00\x02\x07\x00\x08\x01\x01\x00\x01\x01\x00\x1A\x00\x05\x07\x00\x02\x07\x00\x08\x01\x01\x01\x00\x01\x01\x00\x2D\x00\x00\x00\x01\x07\x00\x0A\x00\x2E\x00\x05\x07\x00\x02\x07\x00\x08\x01\x01\x01\x00\x00\x00\x36\x00\x00\x00\x01\x07\x00\x0A\x00\x37\x00\x05\x07\x00\x02\x07\x00\x08\x01\x01\x01\x00\x00\x00\x3E\x00\x04\x07\x00\x02\x07\x00\x08\x01\x01\x00\x00'
    .end code
.end method

.method public break : (LRg;[[ILff;[I)Z
    .code stack 4 locals 5
L0:     aload_2
L1:     invokestatic Method OC break ([[I)[[I
L4:     astore_1
L5:     aload_0
L6:     aload_2
L7:     aload_3
L8:     aload_1
L9:     invokevirtual Method ff else ([[I)V
L12:    invokespecial Method yg break ([[I)I
L15:    aload_0
L16:    aload_1
L17:    invokespecial Method yg break ([[I)I
L20:    if_icmpge L29
L23:    iconst_1
L24:    dup
L25:    dup
L26:    pop2
L27:    ireturn
L28:    athrow
L29:    iconst_0
L30:    iconst_1
L31:    dup
L32:    pop2
L33:    ireturn
L34:    
        .attribute StackMap b'\x00\x02\x00\x1C\x00\x00\x00\x01\x07\x00\x0A\x00\x1D\x00\x05\x07\x00\x02\x07\x00\x08\x07\x00\x08\x07\x00\x12\x07\x00\x1A\x00\x00'
    .end code
.end method

.method public <init> : (Ljava/lang/String;Ljava/lang/String;Ljava/lang/String;IZ)V
    .code stack 7 locals 6
L0:     aload_0
L1:     aload_1
L2:     aload_2
L3:     aload_3
L4:     aconst_null
L5:     iload 4
L7:     iload 5
L9:     invokespecial Method Uf <init> (Ljava/lang/String;Ljava/lang/String;Ljava/lang/String;Ljava/lang/String;IZ)V
L12:    return
L13:    
    .end code
.end method
.end class
