.version 49 0
.class public final super zc
.super java/lang/Object
.field private field5902 D
.field private field5903 Ljava/awt/Font;
.field private field5904 Ljava/awt/font/FontRenderContext;
.field private static final field5905 F = 1e-6f

.method public static final method5837 : (LzA;)Z
    .code stack 6 locals 2
L0:     aload_0
L1:     invokevirtual Method zA method5834 ()F
L4:     dup
L5:     fstore_1
L6:     fconst_0
L7:     fcmpl
L8:     ifle L51
L11:    fconst_1
L12:    fload_1
L13:    fdiv
L14:    fstore_1
L15:    iconst_1
L16:    aload_0
L17:    dup
L18:    dup_x1
L19:    dup
L20:    getfield Field zA field5900 F
L23:    fload_1
L24:    fmul
L25:    putfield Field zA field5900 F
L28:    dup
L29:    getfield Field zA field5898 F
L32:    fload_1
L33:    fmul
L34:    putfield Field zA field5898 F
L37:    dup
L38:    getfield Field zA field5899 F
L41:    fload_1
L42:    fmul
L43:    putfield Field zA field5899 F
L46:    iconst_1
L47:    dup
L48:    pop2
L49:    ireturn
L50:    athrow
L51:    iconst_0
L52:    iconst_1
L53:    dup
L54:    pop2
L55:    ireturn
L56:    
        .attribute StackMap b'\x00\x02\x00\x32\x00\x00\x00\x01\x07\x00\x28\x00\x33\x00\x02\x07\x00\x19\x02\x00\x00'
    .end code
.end method

.method public static method5838 : (FFII[LzA;)Z
    .code stack 8 locals 8
L0:     iconst_0
L1:     iconst_1
L2:     dup
L3:     pop2
L4:     istore 6
L6:     iload_2
L7:     dup
L8:     istore 5
L10:    iload_3
L11:    iconst_1
L12:    dup
L13:    dup
L14:    pop2
L15:    isub
L16:    if_icmpge L171
L19:    aload 4
L21:    iload 5
L23:    aaload
L24:    getfield Field zA field5898 F
L27:    fload_1
L28:    fcmpl
L29:    iflt L50
L32:    aload 4
L34:    iload 5
L36:    iconst_1
L37:    dup
L38:    dup
L39:    pop2
L40:    iadd
L41:    aaload
L42:    getfield Field zA field5898 F
L45:    fload_1
L46:    fcmpl
L47:    ifge L162
L50:    aload 4
L52:    iload 5
L54:    aaload
L55:    getfield Field zA field5898 F
L58:    fload_1
L59:    fcmpg
L60:    ifge L85
L63:    aload 4
L65:    iload 5
L67:    iconst_1
L68:    dup
L69:    dup
L70:    pop2
L71:    iadd
L72:    aaload
L73:    getfield Field zA field5898 F
L76:    fload_1
L77:    fcmpg
L78:    ifge L85
L81:    goto L162
L84:    athrow
L85:    aload 4
L87:    iload 5
L89:    aaload
L90:    getfield Field zA field5900 F
L93:    aload 4
L95:    iload 5
L97:    aaload
L98:    getfield Field zA field5900 F
L101:   aload 4
L103:   iload 5
L105:   iconst_1
L106:   dup
L107:   dup
L108:   pop2
L109:   iadd
L110:   aaload
L111:   getfield Field zA field5900 F
L114:   fsub
L115:   fload_1
L116:   aload 4
L118:   iload 5
L120:   aaload
L121:   getfield Field zA field5898 F
L124:   fsub
L125:   fmul
L126:   aload 4
L128:   iload 5
L130:   aaload
L131:   getfield Field zA field5898 F
L134:   aload 4
L136:   iload 5
L138:   iconst_1
L139:   dup
L140:   dup
L141:   pop2
L142:   iadd
L143:   aaload
L144:   getfield Field zA field5898 F
L147:   fsub
L148:   fdiv
L149:   fadd
L150:   fstore 7
L152:   fload_0
L153:   fload 7
L155:   fcmpg
L156:   ifge L162
L159:   iinc 6 1
L162:   iinc 5 1
L165:   iload 5
L167:   goto L10
L170:   athrow
L171:   aload 4
L173:   iload 5
L175:   aaload
L176:   getfield Field zA field5898 F
L179:   fload_1
L180:   fcmpl
L181:   iflt L196
L184:   aload 4
L186:   iload_2
L187:   aaload
L188:   getfield Field zA field5898 F
L191:   fload_1
L192:   fcmpl
L193:   ifge L286
L196:   aload 4
L198:   iload 5
L200:   aaload
L201:   getfield Field zA field5898 F
L204:   fload_1
L205:   fcmpg
L206:   ifge L221
L209:   aload 4
L211:   iload_2
L212:   aaload
L213:   getfield Field zA field5898 F
L216:   fload_1
L217:   fcmpg
L218:   iflt L286
L221:   aload 4
L223:   iload 5
L225:   aaload
L226:   getfield Field zA field5900 F
L229:   aload 4
L231:   iload 5
L233:   aaload
L234:   getfield Field zA field5900 F
L237:   aload 4
L239:   iload_2
L240:   aaload
L241:   getfield Field zA field5900 F
L244:   fsub
L245:   fload_1
L246:   aload 4
L248:   iload 5
L250:   aaload
L251:   getfield Field zA field5898 F
L254:   fsub
L255:   fmul
L256:   aload 4
L258:   iload 5
L260:   aaload
L261:   getfield Field zA field5898 F
L264:   aload 4
L266:   iload_2
L267:   aaload
L268:   getfield Field zA field5898 F
L271:   fsub
L272:   fdiv
L273:   fadd
L274:   fstore 7
L276:   fload_0
L277:   fload 7
L279:   fcmpg
L280:   ifge L286
L283:   iinc 6 1
L286:   iload 6
L288:   iconst_2
L289:   iconst_1
L290:   dup
L291:   pop2
L292:   irem
L293:   ifeq L301
L296:   iconst_1
L297:   dup
L298:   dup
L299:   pop2
L300:   ireturn
L301:   iconst_0
L302:   iconst_1
L303:   dup
L304:   pop2
L305:   ireturn
L306:   
        .attribute StackMap b'\x00\x0B\x00\x0A\x00\x07\x02\x02\x01\x01\x07\x00\x2C\x01\x01\x00\x01\x01\x00\x32\x00\x07\x02\x02\x01\x01\x07\x00\x2C\x01\x01\x00\x00\x00\x54\x00\x00\x00\x01\x07\x00\x28\x00\x55\x00\x07\x02\x02\x01\x01\x07\x00\x2C\x01\x01\x00\x00\x00\xA2\x00\x07\x02\x02\x01\x01\x07\x00\x2C\x01\x01\x00\x00\x00\xAA\x00\x00\x00\x01\x07\x00\x28\x00\xAB\x00\x07\x02\x02\x01\x01\x07\x00\x2C\x01\x01\x00\x00\x00\xC4\x00\x07\x02\x02\x01\x01\x07\x00\x2C\x01\x01\x00\x00\x00\xDD\x00\x07\x02\x02\x01\x01\x07\x00\x2C\x01\x01\x00\x00\x01\x1E\x00\x07\x02\x02\x01\x01\x07\x00\x2C\x01\x01\x00\x00\x01\x2D\x00\x07\x02\x02\x01\x01\x07\x00\x2C\x01\x01\x00\x00'
    .end code
.end method

.method public <init> : (Ljava/awt/Font;D)V
    .code stack 8 locals 4
L0:     aload_0
L1:     dload_2
L2:     aload_1
L3:     aload_0
L4:     dup_x1
L5:     invokespecial Method java/lang/Object <init> ()V
L8:     putfield Field zc field5903 Ljava/awt/Font;
L11:    putfield Field zc field5902 D
L14:    new java/awt/font/FontRenderContext
L17:    aload_0
L18:    dup_x1
L19:    dup
L20:    pop2
L21:    dup
L22:    aconst_null
L23:    iconst_1
L24:    dup
L25:    pop2
L26:    iconst_1
L27:    dup
L28:    dup_x1
L29:    dup
L30:    pop2
L31:    invokespecial Method java/awt/font/FontRenderContext <init> (Ljava/awt/geom/AffineTransform;ZZ)V
L34:    putfield Field zc field5904 Ljava/awt/font/FontRenderContext;
L37:    return
L38:    
    .end code
.end method

.method public static method5839 : (IIII[LzA;)LtA;
    .code stack 5 locals 7
L0:     aload 4
L2:     iload_0
L3:     aaload
L4:     getfield Field zA field5900 F
L7:     aload 4
L9:     iload_0
L10:    aaload
L11:    getfield Field zA field5898 F
L14:    iload_2
L15:    iload_3
L16:    aload 4
L18:    invokestatic Method zc method5838 (FFII[LzA;)Z
L21:    istore 5
L23:    iload_0
L24:    iconst_1
L25:    dup
L26:    dup
L27:    pop2
L28:    iadd
L29:    dup
L30:    istore 6
L32:    iload_1
L33:    if_icmpge L78
L36:    aload 4
L38:    iload 6
L40:    aaload
L41:    getfield Field zA field5900 F
L44:    aload 4
L46:    iload 6
L48:    aaload
L49:    getfield Field zA field5898 F
L52:    iload_2
L53:    iload_3
L54:    aload 4
L56:    invokestatic Method zc method5838 (FFII[LzA;)Z
L59:    iload 5
L61:    if_icmpeq L69
L64:    getstatic Field tA field355 LtA;
L67:    areturn
L68:    athrow
L69:    iinc 6 1
L72:    iload 6
L74:    goto L32
L77:    athrow
L78:    aload 4
L80:    iload_2
L81:    aaload
L82:    getfield Field zA field5900 F
L85:    aload 4
L87:    iload_2
L88:    aaload
L89:    getfield Field zA field5898 F
L92:    iload_0
L93:    iload_1
L94:    aload 4
L96:    invokestatic Method zc method5838 (FFII[LzA;)Z
L99:    istore 6
L101:   iload_2
L102:   iconst_1
L103:   dup
L104:   dup
L105:   pop2
L106:   iadd
L107:   dup
L108:   istore_2
L109:   iload_3
L110:   if_icmpge L150
L113:   aload 4
L115:   iload_2
L116:   aaload
L117:   getfield Field zA field5900 F
L120:   aload 4
L122:   iload_2
L123:   aaload
L124:   getfield Field zA field5898 F
L127:   iload_0
L128:   iload_1
L129:   aload 4
L131:   invokestatic Method zc method5838 (FFII[LzA;)Z
L134:   iload 6
L136:   if_icmpeq L143
L139:   getstatic Field tA field355 LtA;
L142:   areturn
L143:   iinc 2 1
L146:   iload_2
L147:   goto L109
L150:   iload 5
L152:   ifeq L159
L155:   getstatic Field tA field354 LtA;
L158:   areturn
L159:   iload 6
L161:   ifeq L168
L164:   getstatic Field tA field353 LtA;
L167:   areturn
L168:   getstatic Field tA field352 LtA;
L171:   areturn
L172:   
        .attribute StackMap b'\x00\x0A\x00\x20\x00\x07\x01\x01\x01\x01\x07\x00\x2C\x01\x01\x00\x01\x01\x00\x44\x00\x00\x00\x01\x07\x00\x28\x00\x45\x00\x07\x01\x01\x01\x01\x07\x00\x2C\x01\x01\x00\x00\x00\x4D\x00\x00\x00\x01\x07\x00\x28\x00\x4E\x00\x07\x01\x01\x01\x01\x07\x00\x2C\x01\x01\x00\x00\x00\x6D\x00\x07\x01\x01\x01\x01\x07\x00\x2C\x01\x01\x00\x01\x01\x00\x8F\x00\x07\x01\x01\x01\x01\x07\x00\x2C\x01\x01\x00\x00\x00\x96\x00\x07\x01\x01\x01\x01\x07\x00\x2C\x01\x01\x00\x00\x00\x9F\x00\x07\x01\x01\x01\x01\x07\x00\x2C\x01\x01\x00\x00\x00\xA8\x00\x07\x01\x01\x01\x01\x07\x00\x2C\x01\x01\x00\x00'
    .end code
.end method

.method public method5840 : (C)[F
    .code stack 10 locals 20
L0:     aload_0
L1:     dup
L2:     getfield Field zc field5903 Ljava/awt/Font;
L5:     swap
L6:     getfield Field zc field5904 Ljava/awt/font/FontRenderContext;
L9:     new java/lang/StringBuilder
L12:    dup
L13:    invokespecial Method java/lang/StringBuilder <init> ()V
L16:    iload_1
L17:    invokevirtual Method java/lang/StringBuilder append (C)Ljava/lang/StringBuilder;
L20:    ldc ""
L22:    invokevirtual Method java/lang/StringBuilder append (Ljava/lang/String;)Ljava/lang/StringBuilder;
L25:    invokevirtual Method java/lang/StringBuilder toString ()Ljava/lang/String;
L28:    invokevirtual Method java/awt/Font createGlyphVector (Ljava/awt/font/FontRenderContext;Ljava/lang/String;)Ljava/awt/font/GlyphVector;
L31:    invokevirtual Method java/awt/font/GlyphVector getOutline ()Ljava/awt/Shape;
L34:    aconst_null
L35:    aload_0
L36:    getfield Field zc field5902 D
L39:    invokeinterface InterfaceMethod java/awt/Shape getPathIterator (Ljava/awt/geom/AffineTransform;D)Ljava/awt/geom/PathIterator; 4
L44:    astore_1
L45:    iconst_m1
L46:    iconst_1
L47:    dup
L48:    pop2
L49:    istore_2
L50:    iconst_0
L51:    iconst_1
L52:    dup
L53:    pop2
L54:    istore_3
L55:    iconst_0
L56:    iconst_1
L57:    dup
L58:    pop2
L59:    istore 4
L61:    new java/util/ArrayList
L64:    dup
L65:    invokespecial Method java/util/ArrayList <init> ()V
L68:    astore 5
L70:    bipush 6
L72:    iconst_1
L73:    dup
L74:    pop2
L75:    newarray float
L77:    iconst_1
L78:    dup
L79:    pop2
L80:    astore 6
L82:    fconst_0
L83:    fstore 7
L85:    fconst_0
L86:    fstore 8
L88:    ldc 3.4028235e38f
L90:    fstore 9
L92:    ldc 3.4028235e38f
L94:    fstore 10
L96:    aconst_null
L97:    astore 11
L99:    new java/util/ArrayList
L102:   dup
L103:   invokespecial Method java/util/ArrayList <init> ()V
L106:   astore 12
L108:   ldc -3.4028235e38f
L110:   fstore 13
L112:   iconst_0
L113:   iconst_1
L114:   dup
L115:   pop2
L116:   istore 14
L118:   iconst_0
L119:   iconst_1
L120:   dup
L121:   pop2
L122:   istore 15
L124:   iconst_0
L125:   iconst_1
L126:   dup
L127:   pop2
L128:   istore 16
L130:   iconst_0
L131:   iconst_1
L132:   dup
L133:   pop2
L134:   istore 17
L136:   iconst_0
L137:   iconst_1
L138:   dup
L139:   pop2
L140:   istore 18
L142:   aload_1
L143:   invokeinterface InterfaceMethod java/awt/geom/PathIterator isDone ()Z 1
L148:   ifne L479
L151:   new zA
L154:   dup
L155:   invokespecial Method zA <init> ()V
L158:   astore 19
L160:   aload_1
L161:   aload 6
L163:   invokeinterface InterfaceMethod java/awt/geom/PathIterator currentSegment ([F)I 2
L168:   dup
L169:   istore_2
L170:   iconst_4
L171:   iconst_1
L172:   dup
L173:   pop2
L174:   if_icmpne L223
L177:   iload 4
L179:   ifle L469
L182:   iload 18
L184:   ifeq L199
L187:   iload 17
L189:   istore 15
L191:   iload_3
L192:   iconst_1
L193:   dup
L194:   dup
L195:   pop2
L196:   isub
L197:   istore 16
L199:   aload 12
L201:   iload 4
L203:   invokestatic Method java/lang/Integer valueOf (I)Ljava/lang/Integer;
L206:   invokeinterface InterfaceMethod java/util/List add (Ljava/lang/Object;)Z 2
L211:   iconst_0
L212:   iconst_1
L213:   dup
L214:   pop2
L215:   istore 4
L217:   pop
L218:   aload_1
L219:   goto L470
L222:   athrow
L223:   iload_2
L224:   ifne L351
L227:   aload 19
L229:   dup
L230:   aload 6
L232:   iconst_1
L233:   aload 19
L235:   dup_x2
L236:   aload 6
L238:   iconst_0
L239:   iconst_1
L240:   dup
L241:   pop2
L242:   faload
L243:   putfield Field zA field5900 F
L246:   iconst_1
L247:   dup
L248:   pop2
L249:   faload
L250:   putfield Field zA field5898 F
L253:   getfield Field zA field5900 F
L256:   fstore 7
L258:   getfield Field zA field5898 F
L261:   fstore 8
L263:   fload 7
L265:   fload 9
L267:   fcmpl
L268:   ifne L290
L271:   fload 8
L273:   fload 10
L275:   fcmpl
L276:   ifne L290
L279:   aload_1
L280:   dup
L281:   invokeinterface InterfaceMethod java/awt/geom/PathIterator next ()V 1
L286:   goto L143
L289:   athrow
L290:   iconst_0
L291:   iconst_1
L292:   dup
L293:   pop2
L294:   istore 18
L296:   aload 5
L298:   aload 19
L300:   invokeinterface InterfaceMethod java/util/List add (Ljava/lang/Object;)Z 2
L305:   fload 7
L307:   fstore 9
L309:   fload 8
L311:   fstore 10
L313:   pop
L314:   iload 4
L316:   ifle L338
L319:   aload 12
L321:   iload 4
L323:   invokestatic Method java/lang/Integer valueOf (I)Ljava/lang/Integer;
L326:   invokeinterface InterfaceMethod java/util/List add (Ljava/lang/Object;)Z 2
L331:   iconst_0
L332:   iconst_1
L333:   dup
L334:   pop2
L335:   istore 4
L337:   pop
L338:   iinc 4 1
L341:   iinc 3 1
L344:   iload_3
L345:   istore 17
L347:   aload_1
L348:   goto L470
L351:   iload_2
L352:   iconst_1
L353:   dup
L354:   dup
L355:   pop2
L356:   if_icmpne L469
L359:   aload 6
L361:   iconst_1
L362:   aload 19
L364:   dup_x2
L365:   dup_x2
L366:   aload 6
L368:   iconst_0
L369:   iconst_1
L370:   dup
L371:   pop2
L372:   faload
L373:   putfield Field zA field5900 F
L376:   iconst_1
L377:   dup
L378:   pop2
L379:   faload
L380:   putfield Field zA field5898 F
L383:   getfield Field zA field5900 F
L386:   fload 7
L388:   fcmpl
L389:   ifne L413
L392:   aload 19
L394:   getfield Field zA field5898 F
L397:   fload 8
L399:   fcmpl
L400:   ifne L413
L403:   aload_1
L404:   dup
L405:   invokeinterface InterfaceMethod java/awt/geom/PathIterator next ()V 1
L410:   goto L143
L413:   aload 19
L415:   getfield Field zA field5898 F
L418:   fload 13
L420:   fcmpl
L421:   ifle L440
L424:   aload 19
L426:   getfield Field zA field5898 F
L429:   fstore 13
L431:   iload_3
L432:   istore 14
L434:   iconst_1
L435:   dup
L436:   dup
L437:   pop2
L438:   istore 18
L440:   aload 19
L442:   dup
L443:   getfield Field zA field5900 F
L446:   fstore 7
L448:   getfield Field zA field5898 F
L451:   fstore 8
L453:   iinc 4 1
L456:   aload 5
L458:   aload 19
L460:   invokeinterface InterfaceMethod java/util/List add (Ljava/lang/Object;)Z 2
L465:   iinc 3 1
L468:   pop
L469:   aload_1
L470:   invokeinterface InterfaceMethod java/awt/geom/PathIterator next ()V 1
L475:   aload_1
L476:   goto L143
L479:   iload_3
L480:   ifne L493
L483:   iconst_0
L484:   iconst_1
L485:   dup
L486:   pop2
L487:   newarray float
L489:   iconst_1
L490:   dup
L491:   pop2
L492:   areturn
L493:   new zA
L496:   dup
L497:   invokespecial Method zA <init> ()V
L500:   astore 19
L502:   new zA
L505:   dup
L506:   invokespecial Method zA <init> ()V
L509:   astore_1
L510:   new zA
L513:   dup
L514:   invokespecial Method zA <init> ()V
L517:   astore_2
L518:   aload 5
L520:   invokeinterface InterfaceMethod java/util/List size ()I 1
L525:   anewarray zA
L528:   iconst_1
L529:   dup
L530:   pop2
L531:   astore 4
L533:   iconst_0
L534:   iconst_1
L535:   dup
L536:   pop2
L537:   istore 6
L539:   aload 5
L541:   invokeinterface InterfaceMethod java/util/List iterator ()Ljava/util/Iterator; 1
L546:   dup
L547:   astore 7
L549:   invokeinterface InterfaceMethod java/util/Iterator hasNext ()Z 1
L554:   ifeq L584
L557:   aload 7
L559:   invokeinterface InterfaceMethod java/util/Iterator next ()Ljava/lang/Object; 1
L564:   checkcast zA
L567:   astore 8
L569:   aload 7
L571:   aload 4
L573:   iload 6
L575:   aload 8
L577:   iinc 6 1
L580:   aastore
L581:   goto L549
L584:   iload 16
L586:   iload 15
L588:   isub
L589:   ifle L670
L592:   iload 14
L594:   iload 15
L596:   if_icmpne L613
L599:   aload_1
L600:   aload 19
L602:   aload 4
L604:   iload 16
L606:   aaload
L607:   invokevirtual Method zA method5836 (LzA;)V
L610:   goto L629
L613:   aload 19
L615:   aload 4
L617:   iload 14
L619:   iconst_1
L620:   dup
L621:   dup
L622:   pop2
L623:   isub
L624:   aaload
L625:   invokevirtual Method zA method5836 (LzA;)V
L628:   aload_1
L629:   aload 4
L631:   iload 14
L633:   aaload
L634:   invokevirtual Method zA method5836 (LzA;)V
L637:   iload 14
L639:   iload 16
L641:   if_icmpne L656
L644:   aload_2
L645:   aload 4
L647:   iload 15
L649:   aaload
L650:   invokevirtual Method zA method5836 (LzA;)V
L653:   goto L670
L656:   aload_2
L657:   aload 4
L659:   iload 14
L661:   iconst_1
L662:   dup
L663:   dup
L664:   pop2
L665:   iadd
L666:   aaload
L667:   invokevirtual Method zA method5836 (LzA;)V
L670:   iconst_0
L671:   iconst_1
L672:   dup
L673:   pop2
L674:   istore 7
L676:   new VA
L679:   dup
L680:   iconst_m1
L681:   iconst_1
L682:   dup
L683:   pop2
L684:   iconst_m1
L685:   iconst_1
L686:   dup
L687:   pop2
L688:   invokespecial Method VA <init> (II)V
L691:   astore 8
L693:   aload 12
L695:   invokeinterface InterfaceMethod java/util/List iterator ()Ljava/util/Iterator; 1
L700:   dup
L701:   astore 6
L703:   invokeinterface InterfaceMethod java/util/Iterator hasNext ()Z 1
L708:   ifeq L763
L711:   aload 6
L713:   invokeinterface InterfaceMethod java/util/Iterator next ()Ljava/lang/Object; 1
L718:   checkcast java/lang/Integer
L721:   invokevirtual Method java/lang/Integer intValue ()I
L724:   istore 9
L726:   iload 7
L728:   iload 9
L730:   iadd
L731:   istore 16
L733:   aload 6
L735:   iload 16
L737:   new VA
L740:   aload 8
L742:   dup_x1
L743:   dup
L744:   pop2
L745:   dup
L746:   iload 7
L748:   iload 16
L750:   invokespecial Method VA <init> (II)V
L753:   aload 4
L755:   invokevirtual Method VA method1070 (LVA;[LzA;)V
L758:   istore 7
L760:   goto L703
L763:   aconst_null
L764:   astore 5
L766:   aconst_null
L767:   astore 12
L769:   new java/util/ArrayList
L772:   dup
L773:   invokespecial Method java/util/ArrayList <init> ()V
L776:   astore 6
L778:   iconst_0
L779:   aload 8
L781:   aload 6
L783:   dup_x2
L784:   iconst_0
L785:   iconst_1
L786:   dup
L787:   pop2
L788:   invokevirtual Method VA method1073 (Ljava/util/List;I)V
L791:   iconst_1
L792:   dup
L793:   pop2
L794:   anewarray VA
L797:   iconst_1
L798:   dup
L799:   pop2
L800:   invokeinterface InterfaceMethod java/util/List toArray ([Ljava/lang/Object;)[Ljava/lang/Object; 2
L805:   checkcast [LVA;
L808:   astore 9
L810:   aload 6
L812:   invokeinterface InterfaceMethod java/util/List size ()I 1
L817:   anewarray [I
L820:   iconst_1
L821:   dup
L822:   pop2
L823:   dup
L824:   astore 5
L826:   arraylength
L827:   anewarray [LzA;
L830:   iconst_1
L831:   dup
L832:   pop2
L833:   astore 10
L835:   iconst_0
L836:   iconst_1
L837:   dup
L838:   pop2
L839:   dup
L840:   istore 14
L842:   aload 5
L844:   arraylength
L845:   if_icmpge L1110
L848:   aload 9
L850:   iload 14
L852:   aaload
L853:   dup
L854:   astore 13
L856:   invokevirtual Method VA method1067 ()I
L859:   istore 15
L861:   iload 14
L863:   aload 5
L865:   dup_x1
L866:   iload 14
L868:   iload 15
L870:   iconst_1
L871:   dup
L872:   dup
L873:   pop2
L874:   iadd
L875:   newarray int
L877:   iconst_1
L878:   dup
L879:   pop2
L880:   aastore
L881:   aaload
L882:   iconst_0
L883:   iconst_1
L884:   dup
L885:   pop2
L886:   aload 13
L888:   invokevirtual Method VA method1069 ()I
L891:   iastore
L892:   iconst_0
L893:   iconst_1
L894:   dup
L895:   pop2
L896:   dup
L897:   istore 12
L899:   aload 5
L901:   iload 14
L903:   aaload
L904:   iconst_0
L905:   iconst_1
L906:   dup
L907:   pop2
L908:   iaload
L909:   iadd
L910:   istore 12
L912:   iconst_0
L913:   iconst_1
L914:   dup
L915:   pop2
L916:   dup
L917:   istore 16
L919:   iload 15
L921:   if_icmpge L973
L924:   iload 12
L926:   aload 5
L928:   iload 14
L930:   aaload
L931:   iload 16
L933:   iconst_1
L934:   dup
L935:   dup
L936:   pop2
L937:   iadd
L938:   aload 13
L940:   iload 16
L942:   invokevirtual Method VA method1072 (I)LVA;
L945:   invokevirtual Method VA method1069 ()I
L948:   iastore
L949:   aload 5
L951:   iload 14
L953:   aaload
L954:   iload 16
L956:   iconst_1
L957:   dup
L958:   dup
L959:   pop2
L960:   iadd
L961:   iinc 16 1
L964:   iaload
L965:   iadd
L966:   istore 12
L968:   iload 16
L970:   goto L919
L973:   aload 10
L975:   iload 14
L977:   iload 12
L979:   anewarray zA
L982:   iconst_1
L983:   dup
L984:   pop2
L985:   aastore
L986:   iconst_0
L987:   iconst_1
L988:   dup
L989:   pop2
L990:   istore 7
L992:   aload 13
L994:   getfield Field VA field2144 I
L997:   dup
L998:   istore 16
L1000:  aload 13
L1002:  getfield Field VA field2142 I
L1005:  if_icmpge L1032
L1008:  aload 10
L1010:  iload 14
L1012:  aaload
L1013:  iload 7
L1015:  aload 4
L1017:  iload 16
L1019:  iinc 7 1
L1022:  aaload
L1023:  iinc 16 1
L1026:  aastore
L1027:  iload 16
L1029:  goto L1000
L1032:  iconst_0
L1033:  iconst_1
L1034:  dup
L1035:  pop2
L1036:  dup
L1037:  istore 16
L1039:  iload 15
L1041:  if_icmpge L1102
L1044:  aload 13
L1046:  iload 16
L1048:  invokevirtual Method VA method1072 (I)LVA;
L1051:  getfield Field VA field2144 I
L1054:  dup
L1055:  istore 17
L1057:  aload 13
L1059:  iload 16
L1061:  invokevirtual Method VA method1072 (I)LVA;
L1064:  getfield Field VA field2142 I
L1067:  if_icmpge L1094
L1070:  aload 10
L1072:  iload 14
L1074:  aaload
L1075:  iload 7
L1077:  aload 4
L1079:  iload 17
L1081:  iinc 7 1
L1084:  aaload
L1085:  iinc 17 1
L1088:  aastore
L1089:  iload 17
L1091:  goto L1057
L1094:  iinc 16 1
L1097:  iload 16
L1099:  goto L1039
L1102:  iinc 14 1
L1105:  iload 14
L1107:  goto L842
L1110:  aconst_null
L1111:  astore 8
L1113:  aconst_null
L1114:  astore 6
L1116:  aconst_null
L1117:  astore 4
L1119:  iconst_1
L1120:  dup
L1121:  dup
L1122:  pop2
L1123:  newarray int
L1125:  iconst_1
L1126:  dup
L1127:  pop2
L1128:  astore 14
L1130:  new java/util/ArrayList
L1133:  dup
L1134:  invokespecial Method java/util/ArrayList <init> ()V
L1137:  astore 15
L1139:  new zA
L1142:  dup
L1143:  invokespecial Method zA <init> ()V
L1146:  astore 16
L1148:  iconst_0
L1149:  iconst_1
L1150:  dup
L1151:  pop2
L1152:  istore_3
L1153:  iconst_0
L1154:  iconst_1
L1155:  dup
L1156:  pop2
L1157:  dup
L1158:  istore 17
L1160:  aload 5
L1162:  arraylength
L1163:  if_icmpge L1578
L1166:  aload 14
L1168:  iconst_0
L1169:  iconst_1
L1170:  dup
L1171:  pop2
L1172:  aload 5
L1174:  iload 17
L1176:  aaload
L1177:  arraylength
L1178:  iastore
L1179:  iload_3
L1180:  aload 10
L1182:  iload 17
L1184:  aaload
L1185:  arraylength
L1186:  iadd
L1187:  istore_3
L1188:  new YA
L1191:  dup
L1192:  invokespecial Method YA <init> ()V
L1195:  astore 11
L1197:  iconst_0
L1198:  aload 11
L1200:  dup_x1
L1201:  aload 14
L1203:  aload 5
L1205:  iload 17
L1207:  aload 11
L1209:  dup_x2
L1210:  aload 10
L1212:  iload 17
L1214:  aaload
L1215:  invokevirtual Method YA method1099 ([LzA;)V
L1218:  aaload
L1219:  invokevirtual Method YA method1103 ([I)V
L1222:  invokevirtual Method YA method1098 ([I)V
L1225:  iconst_1
L1226:  dup
L1227:  pop2
L1228:  istore 4
L1230:  iconst_0
L1231:  iconst_1
L1232:  dup
L1233:  pop2
L1234:  istore 6
L1236:  invokevirtual Method YA method1100 ()Ljava/util/List;
L1239:  invokeinterface InterfaceMethod java/util/List iterator ()Ljava/util/Iterator; 1
L1244:  astore 7
L1246:  aload 7
L1248:  invokeinterface InterfaceMethod java/util/Iterator hasNext ()Z 1
L1253:  ifeq L1570
L1256:  aload 7
L1258:  invokeinterface InterfaceMethod java/util/Iterator next ()Ljava/lang/Object; 1
L1263:  checkcast nA
L1266:  astore 8
L1268:  iload 4
L1270:  ifne L1401
L1273:  aload_1
L1274:  aload_2
L1275:  aload 19
L1277:  dup_x2
L1278:  fconst_0
L1279:  aload 8
L1281:  aload 19
L1283:  dup_x1
L1284:  aload 8
L1286:  getfield Field nA field2387 F
L1289:  putfield Field zA field5900 F
L1292:  getfield Field nA field2386 F
L1295:  putfield Field zA field5898 F
L1298:  putfield Field zA field5899 F
L1301:  aload 16
L1303:  fconst_0
L1304:  aload_1
L1305:  dup_x1
L1306:  aload_1
L1307:  aload 8
L1309:  dup_x1
L1310:  getfield Field nA field2389 F
L1313:  putfield Field zA field5900 F
L1316:  getfield Field nA field2388 F
L1319:  putfield Field zA field5898 F
L1322:  putfield Field zA field5899 F
L1325:  fconst_0
L1326:  aload_2
L1327:  dup_x1
L1328:  aload_2
L1329:  aload 8
L1331:  dup_x1
L1332:  getfield Field nA field2390 F
L1335:  putfield Field zA field5900 F
L1338:  getfield Field nA this F
L1341:  putfield Field zA field5898 F
L1344:  putfield Field zA field5899 F
L1347:  invokestatic Method zc method5841 (LzA;LzA;LzA;LzA;)Z
L1350:  ifne L1358
L1353:  aload 7
L1355:  goto L1248
L1358:  aload 16
L1360:  getfield Field zA field5899 F
L1363:  ldc 1e-6f
L1365:  fcmpl
L1366:  iflt L1378
L1369:  iconst_0
L1370:  iconst_1
L1371:  dup
L1372:  pop2
L1373:  istore 6
L1375:  goto L1395
L1378:  aload 16
L1380:  getfield Field zA field5899 F
L1383:  ldc -1e-6f
L1385:  fcmpg
L1386:  ifgt L1246
L1389:  iconst_1
L1390:  dup
L1391:  dup
L1392:  pop2
L1393:  istore 6
L1395:  iconst_1
L1396:  dup
L1397:  dup
L1398:  pop2
L1399:  istore 4
L1401:  iload 6
L1403:  aload 15
L1405:  swap
L1406:  ifeq L1474
L1409:  aload 8
L1411:  getfield Field nA field2387 F
L1414:  invokestatic Method java/lang/Float valueOf (F)Ljava/lang/Float;
L1417:  invokeinterface InterfaceMethod java/util/List add (Ljava/lang/Object;)Z 2
L1422:  aload 15
L1424:  aload 8
L1426:  getfield Field nA field2386 F
L1429:  invokestatic Method java/lang/Float valueOf (F)Ljava/lang/Float;
L1432:  invokeinterface InterfaceMethod java/util/List add (Ljava/lang/Object;)Z 2
L1437:  aload 15
L1439:  aload 8
L1441:  getfield Field nA field2389 F
L1444:  invokestatic Method java/lang/Float valueOf (F)Ljava/lang/Float;
L1447:  invokeinterface InterfaceMethod java/util/List add (Ljava/lang/Object;)Z 2
L1452:  aload 15
L1454:  aload 8
L1456:  getfield Field nA field2388 F
L1459:  invokestatic Method java/lang/Float valueOf (F)Ljava/lang/Float;
L1462:  invokeinterface InterfaceMethod java/util/List add (Ljava/lang/Object;)Z 2
L1467:  pop2
L1468:  pop2
L1469:  aload 15
L1471:  goto L1536
L1474:  aload 8
L1476:  getfield Field nA field2389 F
L1479:  invokestatic Method java/lang/Float valueOf (F)Ljava/lang/Float;
L1482:  invokeinterface InterfaceMethod java/util/List add (Ljava/lang/Object;)Z 2
L1487:  aload 15
L1489:  aload 8
L1491:  getfield Field nA field2388 F
L1494:  invokestatic Method java/lang/Float valueOf (F)Ljava/lang/Float;
L1497:  invokeinterface InterfaceMethod java/util/List add (Ljava/lang/Object;)Z 2
L1502:  aload 15
L1504:  aload 8
L1506:  getfield Field nA field2387 F
L1509:  invokestatic Method java/lang/Float valueOf (F)Ljava/lang/Float;
L1512:  invokeinterface InterfaceMethod java/util/List add (Ljava/lang/Object;)Z 2
L1517:  aload 15
L1519:  aload 8
L1521:  getfield Field nA field2386 F
L1524:  invokestatic Method java/lang/Float valueOf (F)Ljava/lang/Float;
L1527:  invokeinterface InterfaceMethod java/util/List add (Ljava/lang/Object;)Z 2
L1532:  pop2
L1533:  pop2
L1534:  aload 15
L1536:  aload 8
L1538:  getfield Field nA field2390 F
L1541:  invokestatic Method java/lang/Float valueOf (F)Ljava/lang/Float;
L1544:  invokeinterface InterfaceMethod java/util/List add (Ljava/lang/Object;)Z 2
L1549:  aload 15
L1551:  aload 8
L1553:  getfield Field nA this F
L1556:  invokestatic Method java/lang/Float valueOf (F)Ljava/lang/Float;
L1559:  invokeinterface InterfaceMethod java/util/List add (Ljava/lang/Object;)Z 2
L1564:  pop2
L1565:  aload 7
L1567:  goto L1248
L1570:  iinc 17 1
L1573:  iload 17
L1575:  goto L1160
L1578:  iconst_0
L1579:  iconst_1
L1580:  dup
L1581:  pop2
L1582:  istore 17
L1584:  aload 15
L1586:  dup
L1587:  invokeinterface InterfaceMethod java/util/List size ()I 1
L1592:  newarray float
L1594:  iconst_1
L1595:  dup
L1596:  pop2
L1597:  astore 4
L1599:  invokeinterface InterfaceMethod java/util/List iterator ()Ljava/util/Iterator; 1
L1604:  dup
L1605:  astore 6
L1607:  invokeinterface InterfaceMethod java/util/Iterator hasNext ()Z 1
L1612:  ifeq L1645
L1615:  aload 6
L1617:  invokeinterface InterfaceMethod java/util/Iterator next ()Ljava/lang/Object; 1
L1622:  checkcast java/lang/Float
L1625:  invokevirtual Method java/lang/Float floatValue ()F
L1628:  fstore 7
L1630:  aload 6
L1632:  aload 4
L1634:  iload 17
L1636:  fload 7
L1638:  iinc 17 1
L1641:  fastore
L1642:  goto L1607
L1645:  aload 4
L1647:  areturn
L1648:  
        .attribute StackMap b'\x00\x2D\x00\x8F\x00\x13\x07\x00\x02\x07\x00\x78\x01\x01\x01\x07\x00\x73\x07\x00\x7A\x02\x02\x02\x02\x05\x07\x00\x73\x02\x01\x01\x01\x01\x01\x00\x01\x07\x00\x78\x00\xC7\x00\x14\x07\x00\x02\x07\x00\x78\x01\x01\x01\x07\x00\x73\x07\x00\x7A\x02\x02\x02\x02\x05\x07\x00\x73\x02\x01\x01\x01\x01\x01\x07\x00\x19\x00\x00\x00\xDE\x00\x00\x00\x01\x07\x00\x28\x00\xDF\x00\x14\x07\x00\x02\x07\x00\x78\x01\x01\x01\x07\x00\x73\x07\x00\x7A\x02\x02\x02\x02\x05\x07\x00\x73\x02\x01\x01\x01\x01\x01\x07\x00\x19\x00\x00\x01\x21\x00\x00\x00\x01\x07\x00\x28\x01\x22\x00\x14\x07\x00\x02\x07\x00\x78\x01\x01\x01\x07\x00\x73\x07\x00\x7A\x02\x02\x02\x02\x05\x07\x00\x73\x02\x01\x01\x01\x01\x01\x07\x00\x19\x00\x00\x01\x52\x00\x14\x07\x00\x02\x07\x00\x78\x01\x01\x01\x07\x00\x73\x07\x00\x7A\x02\x02\x02\x02\x05\x07\x00\x73\x02\x01\x01\x01\x01\x01\x07\x00\x19\x00\x00\x01\x5F\x00\x14\x07\x00\x02\x07\x00\x78\x01\x01\x01\x07\x00\x73\x07\x00\x7A\x02\x02\x02\x02\x05\x07\x00\x73\x02\x01\x01\x01\x01\x01\x07\x00\x19\x00\x00\x01\x9D\x00\x14\x07\x00\x02\x07\x00\x78\x01\x01\x01\x07\x00\x73\x07\x00\x7A\x02\x02\x02\x02\x05\x07\x00\x73\x02\x01\x01\x01\x01\x01\x07\x00\x19\x00\x00\x01\xB8\x00\x14\x07\x00\x02\x07\x00\x78\x01\x01\x01\x07\x00\x73\x07\x00\x7A\x02\x02\x02\x02\x05\x07\x00\x73\x02\x01\x01\x01\x01\x01\x07\x00\x19\x00\x00\x01\xD5\x00\x14\x07\x00\x02\x07\x00\x78\x01\x01\x01\x07\x00\x73\x07\x00\x7A\x02\x02\x02\x02\x05\x07\x00\x73\x02\x01\x01\x01\x01\x01\x07\x00\x19\x00\x00\x01\xD6\x00\x14\x07\x00\x02\x07\x00\x78\x01\x01\x01\x07\x00\x73\x07\x00\x7A\x02\x02\x02\x02\x05\x07\x00\x73\x02\x01\x01\x01\x01\x01\x07\x00\x19\x00\x01\x07\x00\x78\x01\xDF\x00\x13\x07\x00\x02\x07\x00\x78\x01\x01\x01\x07\x00\x73\x07\x00\x7A\x02\x02\x02\x02\x05\x07\x00\x73\x02\x01\x01\x01\x01\x01\x00\x00\x01\xED\x00\x13\x07\x00\x02\x07\x00\x78\x01\x01\x01\x07\x00\x73\x07\x00\x7A\x02\x02\x02\x02\x05\x07\x00\x73\x02\x01\x01\x01\x01\x01\x00\x00\x02\x25\x00\x14\x07\x00\x02\x07\x00\x19\x07\x00\x19\x01\x07\x00\x2C\x07\x00\x73\x01\x07\x00\x9C\x00\x02\x02\x05\x07\x00\x73\x02\x01\x01\x01\x01\x01\x07\x00\x19\x00\x01\x07\x00\x9C\x02\x48\x00\x14\x07\x00\x02\x07\x00\x19\x07\x00\x19\x01\x07\x00\x2C\x07\x00\x73\x01\x07\x00\x9C\x00\x02\x02\x05\x07\x00\x73\x02\x01\x01\x01\x01\x01\x07\x00\x19\x00\x00\x02\x65\x00\x14\x07\x00\x02\x07\x00\x19\x07\x00\x19\x01\x07\x00\x2C\x07\x00\x73\x01\x07\x00\x9C\x00\x02\x02\x05\x07\x00\x73\x02\x01\x01\x01\x01\x01\x07\x00\x19\x00\x00\x02\x75\x00\x14\x07\x00\x02\x07\x00\x19\x07\x00\x19\x01\x07\x00\x2C\x07\x00\x73\x01\x07\x00\x9C\x00\x02\x02\x05\x07\x00\x73\x02\x01\x01\x01\x01\x01\x07\x00\x19\x00\x01\x07\x00\x19\x02\x90\x00\x14\x07\x00\x02\x07\x00\x19\x07\x00\x19\x01\x07\x00\x2C\x07\x00\x73\x01\x07\x00\x9C\x00\x02\x02\x05\x07\x00\x73\x02\x01\x01\x01\x01\x01\x07\x00\x19\x00\x00\x02\x9E\x00\x14\x07\x00\x02\x07\x00\x19\x07\x00\x19\x01\x07\x00\x2C\x07\x00\x73\x01\x07\x00\x9C\x00\x02\x02\x05\x07\x00\x73\x02\x01\x01\x01\x01\x01\x07\x00\x19\x00\x00\x02\xBF\x00\x14\x07\x00\x02\x07\x00\x19\x07\x00\x19\x01\x07\x00\x2C\x07\x00\x73\x07\x00\x9C\x01\x07\x00\x06\x00\x02\x05\x07\x00\x73\x02\x01\x01\x01\x01\x01\x07\x00\x19\x00\x01\x07\x00\x9C\x02\xFB\x00\x14\x07\x00\x02\x07\x00\x19\x07\x00\x19\x01\x07\x00\x2C\x07\x00\x73\x07\x00\x9C\x01\x07\x00\x06\x00\x02\x05\x07\x00\x73\x02\x01\x01\x01\x01\x01\x07\x00\x19\x00\x00\x03\x4A\x00\x14\x07\x00\x02\x07\x00\x19\x07\x00\x19\x01\x07\x00\x2C\x07\x00\xBE\x07\x00\x73\x01\x07\x00\x06\x07\x00\xBA\x07\x00\xC0\x05\x00\x00\x01\x01\x01\x01\x01\x07\x00\x19\x00\x01\x01\x03\x97\x00\x14\x07\x00\x02\x07\x00\x19\x07\x00\x19\x01\x07\x00\x2C\x07\x00\xBE\x07\x00\x73\x01\x07\x00\x06\x07\x00\xBA\x07\x00\xC0\x05\x01\x07\x00\x06\x01\x01\x01\x01\x01\x07\x00\x19\x00\x01\x01\x03\xCD\x00\x14\x07\x00\x02\x07\x00\x19\x07\x00\x19\x01\x07\x00\x2C\x07\x00\xBE\x07\x00\x73\x01\x07\x00\x06\x07\x00\xBA\x07\x00\xC0\x05\x01\x07\x00\x06\x01\x01\x01\x01\x01\x07\x00\x19\x00\x00\x03\xE8\x00\x14\x07\x00\x02\x07\x00\x19\x07\x00\x19\x01\x07\x00\x2C\x07\x00\xBE\x07\x00\x73\x01\x07\x00\x06\x07\x00\xBA\x07\x00\xC0\x05\x01\x07\x00\x06\x01\x01\x01\x01\x01\x07\x00\x19\x00\x01\x01\x04\x08\x00\x14\x07\x00\x02\x07\x00\x19\x07\x00\x19\x01\x07\x00\x2C\x07\x00\xBE\x07\x00\x73\x01\x07\x00\x06\x07\x00\xBA\x07\x00\xC0\x05\x01\x07\x00\x06\x01\x01\x01\x01\x01\x07\x00\x19\x00\x00\x04\x0F\x00\x14\x07\x00\x02\x07\x00\x19\x07\x00\x19\x01\x07\x00\x2C\x07\x00\xBE\x07\x00\x73\x01\x07\x00\x06\x07\x00\xBA\x07\x00\xC0\x05\x01\x07\x00\x06\x01\x01\x01\x01\x01\x07\x00\x19\x00\x01\x01\x04\x21\x00\x14\x07\x00\x02\x07\x00\x19\x07\x00\x19\x01\x07\x00\x2C\x07\x00\xBE\x07\x00\x73\x01\x07\x00\x06\x07\x00\xBA\x07\x00\xC0\x05\x01\x07\x00\x06\x01\x01\x01\x01\x01\x07\x00\x19\x00\x01\x01\x04\x46\x00\x14\x07\x00\x02\x07\x00\x19\x07\x00\x19\x01\x07\x00\x2C\x07\x00\xBE\x07\x00\x73\x01\x07\x00\x06\x07\x00\xBA\x07\x00\xC0\x05\x01\x07\x00\x06\x01\x01\x01\x01\x01\x07\x00\x19\x00\x00\x04\x4E\x00\x14\x07\x00\x02\x07\x00\x19\x07\x00\x19\x01\x07\x00\x2C\x07\x00\xBE\x07\x00\x73\x01\x07\x00\x06\x07\x00\xBA\x07\x00\xC0\x05\x01\x07\x00\x06\x01\x01\x01\x01\x01\x07\x00\x19\x00\x00\x04\x56\x00\x14\x07\x00\x02\x07\x00\x19\x07\x00\x19\x01\x07\x00\x2C\x07\x00\xBE\x07\x00\x73\x01\x07\x00\x06\x07\x00\xBA\x07\x00\xC0\x05\x00\x00\x01\x01\x01\x01\x01\x07\x00\x19\x00\x00\x04\x88\x00\x14\x07\x00\x02\x07\x00\x19\x07\x00\x19\x01\x00\x07\x00\xBE\x00\x00\x07\x00\x08\x07\x00\xBA\x07\x00\xC0\x07\x00\xD3\x00\x00\x07\x00\xBC\x07\x00\x73\x07\x00\x19\x01\x01\x07\x00\x19\x00\x01\x01\x04\xDE\x00\x14\x07\x00\x02\x07\x00\x19\x07\x00\x19\x01\x01\x07\x00\xBE\x01\x07\x00\x9C\x07\x00\x08\x07\x00\xBA\x07\x00\xC0\x07\x00\xD3\x00\x00\x07\x00\xBC\x07\x00\x73\x07\x00\x19\x01\x01\x07\x00\x19\x00\x00\x04\xE0\x00\x14\x07\x00\x02\x07\x00\x19\x07\x00\x19\x01\x01\x07\x00\xBE\x01\x07\x00\x9C\x07\x00\x08\x07\x00\xBA\x07\x00\xC0\x07\x00\xD3\x00\x00\x07\x00\xBC\x07\x00\x73\x07\x00\x19\x01\x01\x07\x00\x19\x00\x01\x07\x00\x9C\x05\x4E\x00\x14\x07\x00\x02\x07\x00\x19\x07\x00\x19\x01\x01\x07\x00\xBE\x01\x07\x00\x9C\x07\x00\x08\x07\x00\xBA\x07\x00\xC0\x07\x00\xD3\x00\x00\x07\x00\xBC\x07\x00\x73\x07\x00\x19\x01\x01\x07\x00\x19\x00\x00\x05\x62\x00\x14\x07\x00\x02\x07\x00\x19\x07\x00\x19\x01\x01\x07\x00\xBE\x01\x07\x00\x9C\x07\x00\x08\x07\x00\xBA\x07\x00\xC0\x07\x00\xD3\x00\x00\x07\x00\xBC\x07\x00\x73\x07\x00\x19\x01\x01\x07\x00\x19\x00\x00\x05\x73\x00\x14\x07\x00\x02\x07\x00\x19\x07\x00\x19\x01\x01\x07\x00\xBE\x01\x07\x00\x9C\x07\x00\x08\x07\x00\xBA\x07\x00\xC0\x07\x00\xD3\x00\x00\x07\x00\xBC\x07\x00\x73\x07\x00\x19\x01\x01\x07\x00\x19\x00\x00\x05\x79\x00\x14\x07\x00\x02\x07\x00\x19\x07\x00\x19\x01\x01\x07\x00\xBE\x01\x07\x00\x9C\x07\x00\x08\x07\x00\xBA\x07\x00\xC0\x07\x00\xD3\x00\x00\x07\x00\xBC\x07\x00\x73\x07\x00\x19\x01\x01\x07\x00\x19\x00\x00\x05\xC2\x00\x14\x07\x00\x02\x07\x00\x19\x07\x00\x19\x01\x01\x07\x00\xBE\x01\x07\x00\x9C\x07\x00\x08\x07\x00\xBA\x07\x00\xC0\x07\x00\xD3\x00\x00\x07\x00\xBC\x07\x00\x73\x07\x00\x19\x01\x01\x07\x00\x19\x00\x01\x07\x00\x73\x06\x00\x00\x14\x07\x00\x02\x07\x00\x19\x07\x00\x19\x01\x01\x07\x00\xBE\x01\x07\x00\x9C\x07\x00\x08\x07\x00\xBA\x07\x00\xC0\x07\x00\xD3\x00\x00\x07\x00\xBC\x07\x00\x73\x07\x00\x19\x01\x01\x07\x00\x19\x00\x01\x07\x00\x73\x06\x22\x00\x14\x07\x00\x02\x07\x00\x19\x07\x00\x19\x01\x01\x07\x00\xBE\x01\x07\x00\x9C\x07\x00\x08\x07\x00\xBA\x07\x00\xC0\x07\x00\xD3\x00\x00\x07\x00\xBC\x07\x00\x73\x07\x00\x19\x01\x01\x07\x00\x19\x00\x00\x06\x2A\x00\x14\x07\x00\x02\x07\x00\x19\x07\x00\x19\x01\x00\x07\x00\xBE\x00\x00\x07\x00\x08\x07\x00\xBA\x07\x00\xC0\x07\x00\xD3\x00\x00\x07\x00\xBC\x07\x00\x73\x07\x00\x19\x01\x01\x07\x00\x19\x00\x00\x06\x47\x00\x14\x07\x00\x02\x07\x00\x19\x07\x00\x19\x01\x07\x00\x7A\x07\x00\xBE\x07\x00\x9C\x00\x07\x00\x08\x07\x00\xBA\x07\x00\xC0\x07\x00\xD3\x00\x00\x07\x00\xBC\x07\x00\x73\x07\x00\x19\x01\x01\x07\x00\x19\x00\x01\x07\x00\x9C\x06\x6D\x00\x14\x07\x00\x02\x07\x00\x19\x07\x00\x19\x01\x07\x00\x7A\x07\x00\xBE\x07\x00\x9C\x00\x07\x00\x08\x07\x00\xBA\x07\x00\xC0\x07\x00\xD3\x00\x00\x07\x00\xBC\x07\x00\x73\x07\x00\x19\x01\x01\x07\x00\x19\x00\x00'
    .end code
.end method

.method public static method5841 : (LzA;LzA;LzA;LzA;)Z
    .code stack 6 locals 6
L0:     new zA
L3:     dup
L4:     invokespecial Method zA <init> ()V
L7:     astore 4
L9:     new zA
L12:    dup
L13:    invokespecial Method zA <init> ()V
L16:    astore 5
L18:    aload_3
L19:    aload 5
L21:    aload 4
L23:    aload_1
L24:    dup_x1
L25:    aload_0
L26:    invokevirtual Method zA method5835 (LzA;LzA;)V
L29:    aload_2
L30:    invokevirtual Method zA method5835 (LzA;LzA;)V
L33:    aload_3
L34:    dup_x1
L35:    aload 4
L37:    aload 5
L39:    invokevirtual Method zA method5833 (LzA;LzA;)V
L42:    invokevirtual Method zA method5832 ()V
L45:    invokevirtual Method zA method5834 ()F
L48:    dup
L49:    fstore_1
L50:    fconst_0
L51:    fcmpl
L52:    ifle L95
L55:    fconst_1
L56:    fload_1
L57:    fdiv
L58:    fstore_1
L59:    iconst_1
L60:    aload_3
L61:    dup
L62:    dup_x1
L63:    dup
L64:    getfield Field zA field5900 F
L67:    fload_1
L68:    fmul
L69:    putfield Field zA field5900 F
L72:    dup
L73:    getfield Field zA field5898 F
L76:    fload_1
L77:    fmul
L78:    putfield Field zA field5898 F
L81:    dup
L82:    getfield Field zA field5899 F
L85:    fload_1
L86:    fmul
L87:    putfield Field zA field5899 F
L90:    iconst_1
L91:    dup
L92:    pop2
L93:    ireturn
L94:    athrow
L95:    iconst_0
L96:    iconst_1
L97:    dup
L98:    pop2
L99:    ireturn
L100:   
        .attribute StackMap b'\x00\x02\x00\x5E\x00\x00\x00\x01\x07\x00\x28\x00\x5F\x00\x06\x07\x00\x19\x02\x07\x00\x19\x07\x00\x19\x07\x00\x19\x07\x00\x19\x00\x00'
    .end code
.end method
.innerclasses
    VA zc [0] private static
    nA zc [0] public static
    oA zc [0] static synthetic
    tA zc [0] static final enum
.end innerclasses
.end class
