.version 49 0
.class public final super Zd
.super java/lang/Object
.field public else Ljava/lang/Object;
.field public "enum" Ljava/lang/Object;
.field public do Ljava/lang/Object;

.method public <init> : (Ljava/lang/Object;Ljava/lang/Object;Ljava/lang/Object;)V
    .code stack 7 locals 4
L0:     aload_3
L1:     aload_0
L2:     dup_x1
L3:     aload_2
L4:     aload_1
L5:     aload_0
L6:     dup_x1
L7:     invokespecial Method java/lang/Object <init> ()V
L10:    putfield Field Zd else Ljava/lang/Object;
L13:    putfield Field Zd do Ljava/lang/Object;
L16:    putfield Field Zd "enum" Ljava/lang/Object;
L19:    return
L20:    
    .end code
.end method

.method public hashCode : ()I
    .code stack 2 locals 1
L0:     aload_0
L1:     getfield Field Zd else Ljava/lang/Object;
L4:     invokevirtual Method java/lang/Object hashCode ()I
L7:     aload_0
L8:     getfield Field Zd do Ljava/lang/Object;
L11:    invokevirtual Method java/lang/Object hashCode ()I
L14:    ixor
L15:    aload_0
L16:    getfield Field Zd "enum" Ljava/lang/Object;
L19:    invokevirtual Method java/lang/Object hashCode ()I
L22:    ixor
L23:    ireturn
L24:    
    .end code
.end method

.method public equals : (Ljava/lang/Object;)Z
    .code stack 3 locals 2
L0:     aload_1
L1:     instanceof Zd
L4:     ifne L13
L7:     iconst_0
L8:     iconst_1
L9:     dup
L10:    pop2
L11:    ireturn
L12:    athrow
L13:    aload_1
L14:    checkcast Zd
L17:    astore_1
L18:    aload_0
L19:    getfield Field Zd else Ljava/lang/Object;
L22:    aload_1
L23:    getfield Field Zd else Ljava/lang/Object;
L26:    invokevirtual Method java/lang/Object equals (Ljava/lang/Object;)Z
L29:    ifeq L66
L32:    aload_0
L33:    getfield Field Zd do Ljava/lang/Object;
L36:    aload_1
L37:    getfield Field Zd do Ljava/lang/Object;
L40:    invokevirtual Method java/lang/Object equals (Ljava/lang/Object;)Z
L43:    ifeq L66
L46:    aload_0
L47:    getfield Field Zd "enum" Ljava/lang/Object;
L50:    aload_1
L51:    getfield Field Zd "enum" Ljava/lang/Object;
L54:    invokevirtual Method java/lang/Object equals (Ljava/lang/Object;)Z
L57:    ifeq L66
L60:    iconst_1
L61:    dup
L62:    dup
L63:    pop2
L64:    ireturn
L65:    athrow
L66:    iconst_0
L67:    iconst_1
L68:    dup
L69:    pop2
L70:    ireturn
L71:    
        .attribute StackMap b'\x00\x04\x00\x0C\x00\x00\x00\x01\x07\x00\x1B\x00\x0D\x00\x02\x07\x00\x02\x07\x00\x04\x00\x00\x00\x41\x00\x00\x00\x01\x07\x00\x1B\x00\x42\x00\x02\x07\x00\x02\x07\x00\x02\x00\x00'
    .end code
.end method
.end class
