.version 49 0
.class public final super zE
.super bC
.implements G
.field public try Leb;
.field public const [LPc;
.field public new I
.field public null Lsb;
.field public this Lqd;
.field public char [Led;
.field public else Z
.field public "enum" F

.method public "strictfp" : ()V
    .code stack 13 locals 5
L0:     aload_0
L1:     dup
L2:     getfield Field zE const [LPc;
L5:     arraylength
L6:     anewarray ed
L9:     iconst_1
L10:    dup
L11:    pop2
L12:    putfield Field zE char [Led;
L15:    iconst_0
L16:    iconst_1
L17:    dup
L18:    pop2
L19:    dup
L20:    istore_1
L21:    aload_0
L22:    getfield Field zE const [LPc;
L25:    arraylength
L26:    if_icmpge L59
L29:    aload_0
L30:    getfield Field zE char [Led;
L33:    new ed
L36:    iload_1
L37:    dup_x1
L38:    dup
L39:    pop2
L40:    dup
L41:    aload_0
L42:    getfield Field zE const [LPc;
L45:    iload_1
L46:    aaload
L47:    invokespecial Method ed <init> (LPc;)V
L50:    iinc 1 1
L53:    aastore
L54:    iload_1
L55:    goto L21
L58:    athrow
L59:    aload_0
L60:    new ab
L63:    dup
L64:    aload_0
L65:    dup_x2
L66:    getfield Field zE try Leb;
L69:    aload_0
L70:    getfield Field zE char [Led;
L73:    invokespecial Method ab <init> (Leb;[Led;)V
L76:    putfield Field zE this Lqd;
L79:    new sb
L82:    aload_0
L83:    dup
L84:    pop2
L85:    dup
L86:    aload_0
L87:    getfield Field zE const [LPc;
L90:    arraylength
L91:    iconst_2
L92:    iconst_1
L93:    dup
L94:    pop2
L95:    if_icmpne L106
L98:    getstatic Field Id void LId;
L101:   aload_0
L102:   goto L124
L105:   athrow
L106:   aload_0
L107:   getfield Field zE new I
L110:   ifle L120
L113:   getstatic Field Id try LId;
L116:   aload_0
L117:   goto L124
L120:   getstatic Field Id new LId;
L123:   aload_0
L124:   getfield Field zE this Lqd;
L127:   invokespecial Method sb <init> (LId;Lqd;)V
L130:   putfield Field zE null Lsb;
L133:   aload_0
L134:   dup
L135:   getfield Field zE null Lsb;
L138:   invokevirtual Method zE float (LgB;)LgB;
L141:   aload_0
L142:   getfield Field zE char [Led;
L145:   astore_1
L146:   pop
L147:   aload_1
L148:   arraylength
L149:   istore_2
L150:   iconst_0
L151:   iconst_1
L152:   dup
L153:   pop2
L154:   dup
L155:   istore_3
L156:   iload_2
L157:   if_icmpge L197
L160:   aload_1
L161:   iload_3
L162:   iinc 3 1
L165:   aaload
L166:   astore 4
L168:   aload_0
L169:   getfield Field zE this Lqd;
L172:   aload 4
L174:   iconst_0
L175:   iconst_1
L176:   dup
L177:   pop2
L178:   new iF
L181:   aconst_null
L182:   dup_x1
L183:   dup
L184:   pop2
L185:   dup
L186:   aload_0
L187:   invokespecial Method iF <init> (LzE;)V
L190:   invokevirtual Method qd break (Led;ZLjava/lang/String;LK;)V
L193:   iload_3
L194:   goto L156
L197:   iconst_0
L198:   iconst_1
L199:   dup
L200:   pop2
L201:   dup
L202:   istore_1
L203:   aload_0
L204:   getfield Field zE new I
L207:   if_icmpge L266
L210:   invokestatic Method fB break ()LfB;
L213:   astore_2
L214:   aload_0
L215:   getfield Field zE this Lqd;
L218:   new ed
L221:   dup
L222:   aload_2
L223:   getfield Field fB else Ljava/lang/String;
L226:   getstatic Field Pc do LPc;
L229:   iconst_m1
L230:   iconst_1
L231:   dup
L232:   pop2
L233:   new java/util/LinkedHashSet
L236:   dup
L237:   invokespecial Method java/util/LinkedHashSet <init> ()V
L240:   aload_2
L241:   getfield Field fB do Ljava/lang/String;
L244:   iconst_0
L245:   iconst_1
L246:   dup
L247:   pop2
L248:   ldc2_w -1L
L251:   aconst_null
L252:   iinc 1 1
L255:   dup
L256:   invokespecial Method ed <init> (Ljava/lang/String;LPc;ILjava/util/Set;Ljava/lang/String;IJLjava/lang/String;Ljava/lang/String;)V
L259:   invokevirtual Method qd break (Led;)V
L262:   iload_1
L263:   goto L203
L266:   aload_0
L267:   getfield Field zE this Lqd;
L270:   aload_0
L271:   getstatic Field mc do Lmc;
L274:   invokevirtual Method qd break (LG;Lmc;)V
L277:   return
L278:   
        .attribute StackMap b'\x00\x0B\x00\x15\x00\x02\x07\x00\x02\x01\x00\x01\x01\x00\x3A\x00\x00\x00\x01\x07\x00\x3A\x00\x3B\x00\x02\x07\x00\x02\x01\x00\x00\x00\x69\x00\x00\x00\x01\x07\x00\x3A\x00\x6A\x00\x02\x07\x00\x02\x01\x00\x03\x07\x00\x02\x08\x00\x4F\x08\x00\x4F\x00\x78\x00\x02\x07\x00\x02\x01\x00\x03\x07\x00\x02\x08\x00\x4F\x08\x00\x4F\x00\x7C\x00\x02\x07\x00\x02\x01\x00\x05\x07\x00\x02\x08\x00\x4F\x08\x00\x4F\x07\x00\x0C\x07\x00\x02\x00\x9C\x00\x04\x07\x00\x02\x07\x00\x57\x01\x01\x00\x01\x01\x00\xC5\x00\x04\x07\x00\x02\x07\x00\x57\x01\x01\x00\x00\x00\xCB\x00\x04\x07\x00\x02\x01\x00\x01\x00\x01\x01\x01\x0A\x00\x04\x07\x00\x02\x01\x00\x01\x00\x00'
    .end code
.end method

.method public break : (LD;)V
    .code stack 4 locals 6
L0:     aload_1
L1:     instanceof xC
L4:     ifeq L243
L7:     aload_1
L8:     checkcast xC
L11:    astore_1
L12:    getstatic Field yE do [I
L15:    aload_1
L16:    getfield Field xC "enum" LQB;
L19:    invokevirtual Method QB ordinal ()I
L22:    iaload
L23:    tableswitch 1
            L52
            L115
            L243
            L243
            default : L243
L52:    aload_0
L53:    iconst_0
L54:    ifne L240
L57:    getfield Field zE this Lqd;
L60:    getfield Field qd new Ljava/util/LinkedHashMap;
L63:    invokevirtual Method java/util/LinkedHashMap values ()Ljava/util/Collection;
L66:    invokeinterface InterfaceMethod java/util/Collection iterator ()Ljava/util/Iterator; 1
L71:    astore_1
L72:    aload_1
L73:    invokeinterface InterfaceMethod java/util/Iterator hasNext ()Z 1
L78:    ifeq L243
L81:    aload_1
L82:    invokeinterface InterfaceMethod java/util/Iterator next ()Ljava/lang/Object; 1
L87:    checkcast Rg
L90:    dup
L91:    astore_2
L92:    instanceof ae
L95:    ifeq L72
L98:    aload_2
L99:    checkcast ae
L102:   aload_0
L103:   getfield Field zE "enum" F
L106:   invokevirtual Method ae const (F)V
L109:   goto L72
L112:   nop
L113:   nop
L114:   athrow
L115:   iconst_0
L116:   iconst_1
L117:   dup
L118:   pop2
L119:   istore_1
L120:   aload_0
L121:   getfield Field zE char [Led;
L124:   dup
L125:   astore_2
L126:   arraylength
L127:   istore_3
L128:   iconst_0
L129:   iconst_1
L130:   dup
L131:   pop2
L132:   dup
L133:   istore 4
L135:   iload_3
L136:   if_icmpge L222
L139:   aload_2
L140:   iload 4
L142:   aaload
L143:   astore 5
L145:   aload_0
L146:   getfield Field zE this Lqd;
L149:   getfield Field qd "enum" Ljava/util/Map;
L152:   aload_0
L153:   getfield Field zE this Lqd;
L156:   getfield Field qd new Ljava/util/LinkedHashMap;
L159:   aload 5
L161:   invokevirtual Method java/util/LinkedHashMap get (Ljava/lang/Object;)Ljava/lang/Object;
L164:   invokeinterface InterfaceMethod java/util/Map containsKey (Ljava/lang/Object;)Z 2
L169:   ifeq L214
L172:   aload_0
L173:   getfield Field zE this Lqd;
L176:   getfield Field qd "enum" Ljava/util/Map;
L179:   aload_0
L180:   getfield Field zE this Lqd;
L183:   getfield Field qd new Ljava/util/LinkedHashMap;
L186:   aload 5
L188:   invokevirtual Method java/util/LinkedHashMap get (Ljava/lang/Object;)Ljava/lang/Object;
L191:   invokeinterface InterfaceMethod java/util/Map get (Ljava/lang/Object;)Ljava/lang/Object; 2
L196:   checkcast java/lang/Integer
L199:   invokevirtual Method java/lang/Integer intValue ()I
L202:   iconst_1
L203:   dup
L204:   dup
L205:   pop2
L206:   if_icmpne L214
L209:   iconst_1
L210:   dup
L211:   dup
L212:   pop2
L213:   istore_1
L214:   iinc 4 1
L217:   iload 4
L219:   goto L135
L222:   iload_1
L223:   aload_0
L224:   swap
L225:   ifeq L234
L228:   ldc 1e-2f
L230:   invokespecial Method zE else (F)V
L233:   return
L234:   ldc -2e-2f
L236:   invokespecial Method zE else (F)V
L239:   return
L240:   goto L53
L243:   return
L244:   
        .attribute StackMap b'\x00\x0B\x00\x34\x00\x02\x07\x00\x02\x07\x00\x83\x00\x00\x00\x35\x00\x02\x07\x00\x02\x07\x00\x83\x00\x01\x07\x00\x02\x00\x48\x00\x02\x07\x00\x02\x07\x00\x9E\x00\x00\x00\x70\x00\x00\x00\x01\x07\x00\x3A\x00\x73\x00\x02\x07\x00\x02\x07\x00\x83\x00\x00\x00\x87\x00\x05\x07\x00\x02\x01\x07\x00\x57\x01\x01\x00\x01\x01\x00\xD6\x00\x06\x07\x00\x02\x01\x07\x00\x57\x01\x01\x07\x00\x32\x00\x00\x00\xDE\x00\x05\x07\x00\x02\x01\x07\x00\x57\x01\x01\x00\x00\x00\xEA\x00\x05\x07\x00\x02\x01\x07\x00\x57\x01\x01\x00\x01\x07\x00\x02\x00\xF0\x00\x02\x07\x00\x02\x07\x00\x83\x00\x01\x07\x00\x02\x00\xF3\x00\x02\x07\x00\x02\x07\x00\xC8\x00\x00'
    .end code
.end method

.method public break : ()V
    .code stack 7 locals 1
L0:     aload_0
L1:     getfield Field zE null LFE;
L4:     getstatic Field Ae break LAe;
L7:     ldc "Do you want to leave this game?"
L9:     getstatic Field jC "enum" [Ljava/lang/String;
L12:    new eE
L15:    dup
L16:    aload_0
L17:    invokespecial Method eE <init> (LzE;)V
L20:    invokevirtual Method FE break (LAe;Ljava/lang/String;[Ljava/lang/String;Lh;)LjC;
L23:    pop
L24:    return
L25:    
    .end code
.end method

.method public break : (LgB;IC)Z
    .code stack 3 locals 4
L0:     iload_2
L1:     lookupswitch
            1 : L20
            default : L34
L20:    aload_0
L21:    iconst_0
L22:    ifne L21
L25:    invokevirtual Method zE break ()V
L28:    iconst_1
L29:    dup
L30:    dup
L31:    pop2
L32:    ireturn
L33:    athrow
L34:    iconst_0
L35:    iconst_1
L36:    dup
L37:    pop2
L38:    ireturn
L39:    
        .attribute StackMap b'\x00\x04\x00\x14\x00\x04\x07\x00\x02\x07\x00\xDE\x01\x01\x00\x00\x00\x15\x00\x04\x07\x00\x02\x07\x00\xDE\x01\x01\x00\x01\x07\x00\x02\x00\x21\x00\x00\x00\x01\x07\x00\x3A\x00\x22\x00\x04\x07\x00\x02\x07\x00\xDE\x01\x01\x00\x00'
    .end code
.end method

.method public else : (LgB;IC)Z
    .code stack 6 locals 4
L0:     iload_2
L1:     bipush 60
L3:     iconst_1
L4:     dup
L5:     pop2
L6:     if_icmpne L57
L9:     aload_0
L10:    getfield Field zE this Lqd;
L13:    getfield Field qd null LQB;
L16:    getstatic Field QB do LQB;
L19:    if_acmpne L57
L22:    iconst_1
L23:    aload_0
L24:    dup
L25:    getfield Field zE this Lqd;
L28:    invokevirtual Method qd class ()V
L31:    getfield Field zE this Lqd;
L34:    invokestatic Method OC else ()D
L37:    aload_0
L38:    getfield Field zE this Lqd;
L41:    invokevirtual Method qd long ()D
L44:    dsub
L45:    ldc2_w 5e-1
L48:    dadd
L49:    putfield Field qd while D
L52:    iconst_1
L53:    dup
L54:    pop2
L55:    ireturn
L56:    athrow
L57:    aload_0
L58:    getfield Field zE null Lsb;
L61:    aload_1
L62:    iload_2
L63:    iload_3
L64:    invokevirtual Method sb else (LgB;IC)Z
L67:    ireturn
L68:    
        .attribute StackMap b'\x00\x02\x00\x38\x00\x00\x00\x01\x07\x00\x3A\x00\x39\x00\x04\x07\x00\x02\x07\x00\xDE\x01\x01\x00\x00'
    .end code
.end method

.method private else : (F)V
    .code stack 6 locals 3
L0:     aload_0
L1:     getfield Field zE new I
L4:     ifeq L14
L7:     aload_0
L8:     getfield Field zE else Z
L11:    ifne L16
L14:    return
L15:    athrow
L16:    aload_0
L17:    dup
L18:    dup_x1
L19:    getfield Field zE "enum" F
L22:    f2d
L23:    ldc2_w 6.666666666666666e-1
L26:    invokestatic Method java/lang/Math pow (DD)D
L29:    fload_1
L30:    f2d
L31:    dadd
L32:    ldc2_w 1.5e0
L35:    invokestatic Method java/lang/Math pow (DD)D
L38:    d2f
L39:    fconst_0
L40:    fconst_1
L41:    invokestatic Method OC else (FFF)F
L44:    putfield Field zE "enum" F
L47:    getfield Field zE "enum" F
L50:    invokestatic Method java/lang/Float isNaN (F)Z
L53:    ifeq L61
L56:    aload_0
L57:    fconst_0
L58:    putfield Field zE "enum" F
L61:    ldc_w "u"
L64:    aload_0
L65:    getfield Field zE "enum" F
L68:    f2d
L69:    ldc2_w 6.666666666666666e-1
L72:    invokestatic Method java/lang/Math pow (DD)D
L75:    ldc2_w 3.999999e2
L78:    dmul
L79:    d2i
L80:    invokestatic Method JB break (Ljava/lang/String;I)V
L83:    aload_0
L84:    getfield Field zE this Lqd;
L87:    getfield Field qd new Ljava/util/LinkedHashMap;
L90:    invokevirtual Method java/util/LinkedHashMap values ()Ljava/util/Collection;
L93:    invokeinterface InterfaceMethod java/util/Collection iterator ()Ljava/util/Iterator; 1
L98:    astore_1
L99:    aload_1
L100:   invokeinterface InterfaceMethod java/util/Iterator hasNext ()Z 1
L105:   ifeq L140
L108:   aload_1
L109:   invokeinterface InterfaceMethod java/util/Iterator next ()Ljava/lang/Object; 1
L114:   checkcast Rg
L117:   dup
L118:   astore_2
L119:   instanceof ae
L122:   ifeq L99
L125:   aload_2
L126:   checkcast ae
L129:   aload_0
L130:   getfield Field zE "enum" F
L133:   invokevirtual Method ae const (F)V
L136:   goto L99
L139:   athrow
L140:   return
L141:   
        .attribute StackMap b'\x00\x07\x00\x0E\x00\x02\x07\x00\x02\x02\x00\x00\x00\x0F\x00\x00\x00\x01\x07\x00\x3A\x00\x10\x00\x02\x07\x00\x02\x02\x00\x00\x00\x3D\x00\x02\x07\x00\x02\x02\x00\x00\x00\x63\x00\x02\x07\x00\x02\x07\x00\x9E\x00\x00\x00\x8B\x00\x00\x00\x01\x07\x00\x3A\x00\x8C\x00\x02\x07\x00\x02\x07\x00\x9E\x00\x00'
    .end code
.end method

.method public static synthetic const : (LzE;)LFE;
    .code stack 1 locals 1
L0:     aload_0
L1:     getfield Field zE null LFE;
L4:     areturn
L5:     
    .end code
.end method

.method public static synthetic else : (LzE;)LFE;
    .code stack 1 locals 1
L0:     aload_0
L1:     getfield Field zE null LFE;
L4:     areturn
L5:     
    .end code
.end method

.method public case : ()V
    .code stack 3 locals 3
L0:     aload_0
L1:     dup
L2:     invokespecial Method bC case ()V
L5:     getfield Field zE this Lqd;
L8:     ifnull L69
L11:    aload_0
L12:    getfield Field zE this Lqd;
L15:    getfield Field qd new Ljava/util/LinkedHashMap;
L18:    ifnull L69
L21:    aload_0
L22:    getfield Field zE this Lqd;
L25:    getfield Field qd new Ljava/util/LinkedHashMap;
L28:    invokevirtual Method java/util/LinkedHashMap keySet ()Ljava/util/Set;
L31:    invokeinterface InterfaceMethod java/util/Set iterator ()Ljava/util/Iterator; 1
L36:    dup
L37:    astore_1
L38:    invokeinterface InterfaceMethod java/util/Iterator hasNext ()Z 1
L43:    ifeq L69
L46:    aload_1
L47:    invokeinterface InterfaceMethod java/util/Iterator next ()Ljava/lang/Object; 1
L52:    checkcast ed
L55:    astore_2
L56:    aload_1
L57:    aload_0
L58:    getfield Field zE this Lqd;
L61:    aload_2
L62:    invokevirtual Method qd else (Led;)V
L65:    goto L38
L68:    athrow
L69:    return
L70:    
        .attribute StackMap b'\x00\x03\x00\x26\x00\x02\x07\x00\x02\x07\x00\x9E\x00\x01\x07\x00\x9E\x00\x44\x00\x00\x00\x01\x07\x00\x3A\x00\x45\x00\x01\x07\x00\x02\x00\x00'
    .end code
.end method

.method public varargs <init> : (IFZLeb;[LPc;)V
    .code stack 11 locals 6
L0:     aload 5
L2:     aload_0
L3:     dup_x1
L4:     aload 4
L6:     iload_3
L7:     aload_0
L8:     dup_x1
L9:     fload_2
L10:    iload_1
L11:    aload_0
L12:    dup_x1
L13:    invokespecial Method bC <init> ()V
L16:    putfield Field zE new I
L19:    putfield Field zE "enum" F
L22:    putfield Field zE else Z
L25:    putfield Field zE try Leb;
L28:    putfield Field zE const [LPc;
L31:    return
L32:    
    .end code
.end method

.method public static synthetic break : (LzE;)LFE;
    .code stack 1 locals 1
L0:     aload_0
L1:     getfield Field zE null LFE;
L4:     areturn
L5:     
    .end code
.end method

.method public else : (LgB;I)Z
    .code stack 3 locals 3
L0:     aload_0
L1:     getfield Field zE null Lsb;
L4:     aload_1
L5:     iload_2
L6:     invokevirtual Method sb else (LgB;I)Z
L9:     ireturn
L10:    
    .end code
.end method

.method public const : (LgB;I)V
    .code stack 3 locals 3
L0:     aload_0
L1:     getfield Field zE null Lsb;
L4:     aload_1
L5:     iload_2
L6:     invokevirtual Method sb const (LgB;I)V
L9:     return
L10:    
    .end code
.end method
.innerclasses
    Ae ig [0] public static final enum
    Id sb [0] public static final enum
    Pc JB [0] public static final enum
    QB qd [0] public static final enum
    eE [0] [0]
    iF [0] [0]
    yE zE [0] static synthetic
.end innerclasses
.end class
