.version 49 0
.class public final super zf
.super java/lang/Object
.implements h
.field public final synthetic field1477 LjC;

.method public method728 : (LgB;)V
    .code stack 6 locals 4
L0:     aload_0
L1:     getfield Field zf field1477 LjC;
L4:     getfield Field jC field1133 Z
L7:     ifne L12
L10:    return
L11:    athrow
L12:    iconst_0
L13:    iconst_1
L14:    dup
L15:    pop2
L16:    dup
L17:    istore_2
L18:    aload_0
L19:    getfield Field zf field1477 LjC;
L22:    invokestatic Method jC method517 (LjC;)[LYg;
L25:    arraylength
L26:    if_icmpge L145
L29:    aload_0
L30:    getfield Field zf field1477 LjC;
L33:    invokestatic Method jC method517 (LjC;)[LYg;
L36:    iload_2
L37:    aaload
L38:    aload_1
L39:    if_acmpne L138
L42:    aload_0
L43:    getfield Field zf field1477 LjC;
L46:    iload_2
L47:    invokestatic Method jC method519 (LjC;I)I
L50:    aload_0
L51:    dup_x1
L52:    getfield Field zf field1477 LjC;
L55:    iconst_0
L56:    iconst_1
L57:    dup
L58:    pop2
L59:    invokestatic Method jC method515 (LjC;I)I
L62:    pop2
L63:    getfield Field zf field1477 LjC;
L66:    getfield Field jC field1037 Ljava/util/List;
L69:    invokeinterface InterfaceMethod java/util/List isEmpty ()Z 1
L74:    ifeq L93
L77:    aload_0
L78:    getfield Field zf field1477 LjC;
L81:    getfield Field jC field1136 LFE;
L84:    aload_0
L85:    getfield Field zf field1477 LjC;
L88:    invokevirtual Method FE method458 (LjC;)V
L91:    return
L92:    athrow
L93:    aload_0
L94:    getfield Field zf field1477 LjC;
L97:    getfield Field jC field1037 Ljava/util/List;
L100:   invokeinterface InterfaceMethod java/util/List iterator ()Ljava/util/Iterator; 1
L105:   dup
L106:   astore_3
L107:   invokeinterface InterfaceMethod java/util/Iterator hasNext ()Z 1
L112:   ifeq L137
L115:   aload_3
L116:   invokeinterface InterfaceMethod java/util/Iterator next ()Ljava/lang/Object; 1
L121:   checkcast h
L124:   aload_0
L125:   getfield Field zf field1477 LjC;
L128:   invokeinterface InterfaceMethod h method728 (LgB;)V 2
L133:   aload_3
L134:   goto L107
L137:   return
L138:   iinc 2 1
L141:   iload_2
L142:   goto L18
L145:   return
L146:   
        .attribute StackMap b'\x00\x09\x00\x0B\x00\x00\x00\x01\x07\x00\x17\x00\x0C\x00\x02\x07\x00\x02\x07\x00\x19\x00\x00\x00\x12\x00\x03\x07\x00\x02\x07\x00\x19\x01\x00\x01\x01\x00\x5C\x00\x00\x00\x01\x07\x00\x17\x00\x5D\x00\x03\x07\x00\x02\x07\x00\x19\x01\x00\x00\x00\x6B\x00\x04\x07\x00\x02\x07\x00\x19\x01\x07\x00\x3E\x00\x01\x07\x00\x3E\x00\x89\x00\x04\x07\x00\x02\x07\x00\x19\x01\x07\x00\x3E\x00\x00\x00\x8A\x00\x03\x07\x00\x02\x07\x00\x19\x01\x00\x00\x00\x91\x00\x03\x07\x00\x02\x07\x00\x19\x01\x00\x00'
    .end code
.end method

.method public <init> : (LjC;)V
    .code stack 3 locals 2
L0:     aload_0
L1:     dup
L2:     aload_1
L3:     putfield Field zf field1477 LjC;
L6:     invokespecial Method java/lang/Object <init> ()V
L9:     return
L10:    
    .end code
.end method
.innerclasses
    zf [0] [0]
.end innerclasses
.enclosing method jC method49 ()V
.end class
