.version 49 0
.class public final super enum zg
.super java/lang/Enum
.field public static final enum byte Lzg;
.field public static final enum "super" Lzg;
.field private static final synthetic int [Lzg;
.field public static final enum short Lzg;
.field public static final enum goto Lzg;
.field public static final enum break Lzg;
.field public static final enum long Lzg;
.field public static final enum void Lzg;
.field public static final enum try Lzg;
.field public static final enum const Lzg;
.field public static final enum new Lzg;
.field public static final enum null Lzg;
.field public static final enum this Lzg;
.field public static final enum char Lzg;
.field public static final enum else Lzg;
.field public static final enum "enum" Lzg;
.field public static final enum do Lzg;

.method public static values : ()[Lzg;
    .code stack 1 locals 0
L0:     getstatic Field zg int [Lzg;
L3:     invokevirtual Method [Lzg; clone ()Ljava/lang/Object;
L6:     checkcast [Lzg;
L9:     areturn
L10:    
    .end code
.end method

.method public static <clinit> : ()V
    .code stack 6 locals 0
L0:     new zg
L3:     dup
L4:     ldc "PIECE_INSERT"
L6:     iconst_0
L7:     iconst_1
L8:     dup
L9:     pop2
L10:    invokespecial Method zg <init> (Ljava/lang/String;I)V
L13:    putstatic Field zg new Lzg;
L16:    new zg
L19:    dup
L20:    ldc "PIECE_GRAVITIZZLE"
L22:    iconst_1
L23:    dup
L24:    dup
L25:    pop2
L26:    invokespecial Method zg <init> (Ljava/lang/String;I)V
L29:    putstatic Field zg "super" Lzg;
L32:    new zg
L35:    dup
L36:    ldc "COUNTDOWN"
L38:    iconst_2
L39:    iconst_1
L40:    dup
L41:    pop2
L42:    invokespecial Method zg <init> (Ljava/lang/String;I)V
L45:    putstatic Field zg char Lzg;
L48:    new zg
L51:    dup
L52:    ldc "COUNTDOWN_DING"
L54:    iconst_3
L55:    iconst_1
L56:    dup
L57:    pop2
L58:    invokespecial Method zg <init> (Ljava/lang/String;I)V
L61:    putstatic Field zg const Lzg;
L64:    new zg
L67:    dup
L68:    ldc "BLOCKED_BY_SPEED_BLOCK"
L70:    iconst_4
L71:    iconst_1
L72:    dup
L73:    pop2
L74:    invokespecial Method zg <init> (Ljava/lang/String;I)V
L77:    putstatic Field zg null Lzg;
L80:    new zg
L83:    dup
L84:    ldc "IMPRESSIVE"
L86:    iconst_5
L87:    iconst_1
L88:    dup
L89:    pop2
L90:    invokespecial Method zg <init> (Ljava/lang/String;I)V
L93:    putstatic Field zg long Lzg;
L96:    new zg
L99:    dup
L100:   ldc "PERFECT"
L102:   bipush 6
L104:   iconst_1
L105:   dup
L106:   pop2
L107:   invokespecial Method zg <init> (Ljava/lang/String;I)V
L110:   putstatic Field zg break Lzg;
L113:   new zg
L116:   dup
L117:   ldc "GOD_LIKE"
L119:   bipush 7
L121:   iconst_1
L122:   dup
L123:   pop2
L124:   invokespecial Method zg <init> (Ljava/lang/String;I)V
L127:   putstatic Field zg try Lzg;
L130:   new zg
L133:   dup
L134:   ldc "LINE_BLOCKED"
L136:   bipush 8
L138:   iconst_1
L139:   dup
L140:   pop2
L141:   invokespecial Method zg <init> (Ljava/lang/String;I)V
L144:   putstatic Field zg else Lzg;
L147:   new zg
L150:   dup
L151:   ldc "LINE_RECEIVED"
L153:   bipush 9
L155:   iconst_1
L156:   dup
L157:   pop2
L158:   invokespecial Method zg <init> (Ljava/lang/String;I)V
L161:   putstatic Field zg this Lzg;
L164:   new zg
L167:   dup
L168:   ldc "LINE_SENT"
L170:   bipush 10
L172:   iconst_1
L173:   dup
L174:   pop2
L175:   invokespecial Method zg <init> (Ljava/lang/String;I)V
L178:   putstatic Field zg "enum" Lzg;
L181:   new zg
L184:   dup
L185:   ldc "LINE_CLEARED"
L187:   bipush 11
L189:   iconst_1
L190:   dup
L191:   pop2
L192:   invokespecial Method zg <init> (Ljava/lang/String;I)V
L195:   putstatic Field zg byte Lzg;
L198:   new zg
L201:   dup
L202:   ldc "PLAYFIELD_SHRUNK"
L204:   bipush 12
L206:   iconst_1
L207:   dup
L208:   pop2
L209:   invokespecial Method zg <init> (Ljava/lang/String;I)V
L212:   putstatic Field zg short Lzg;
L215:   new zg
L218:   dup
L219:   ldc "UI_DIALOG"
L221:   bipush 13
L223:   iconst_1
L224:   dup
L225:   pop2
L226:   invokespecial Method zg <init> (Ljava/lang/String;I)V
L229:   putstatic Field zg do Lzg;
L232:   new zg
L235:   dup
L236:   ldc "UI_SLIDE"
L238:   bipush 14
L240:   iconst_1
L241:   dup
L242:   pop2
L243:   invokespecial Method zg <init> (Ljava/lang/String;I)V
L246:   putstatic Field zg goto Lzg;
L249:   new zg
L252:   dup
L253:   ldc "UI_TRANSITION"
L255:   bipush 15
L257:   iconst_1
L258:   dup
L259:   pop2
L260:   invokespecial Method zg <init> (Ljava/lang/String;I)V
L263:   putstatic Field zg void Lzg;
L266:   bipush 16
L268:   iconst_1
L269:   dup
L270:   pop2
L271:   anewarray zg
L274:   iconst_1
L275:   dup
L276:   pop2
L277:   dup
L278:   iconst_0
L279:   iconst_1
L280:   dup
L281:   pop2
L282:   getstatic Field zg new Lzg;
L285:   aastore
L286:   dup
L287:   iconst_1
L288:   dup
L289:   dup
L290:   pop2
L291:   getstatic Field zg "super" Lzg;
L294:   aastore
L295:   dup
L296:   iconst_2
L297:   iconst_1
L298:   dup
L299:   pop2
L300:   getstatic Field zg char Lzg;
L303:   aastore
L304:   dup
L305:   iconst_3
L306:   iconst_1
L307:   dup
L308:   pop2
L309:   getstatic Field zg const Lzg;
L312:   aastore
L313:   dup
L314:   iconst_4
L315:   iconst_1
L316:   dup
L317:   pop2
L318:   getstatic Field zg null Lzg;
L321:   aastore
L322:   dup
L323:   iconst_5
L324:   iconst_1
L325:   dup
L326:   pop2
L327:   getstatic Field zg long Lzg;
L330:   aastore
L331:   dup
L332:   bipush 6
L334:   iconst_1
L335:   dup
L336:   pop2
L337:   getstatic Field zg break Lzg;
L340:   aastore
L341:   dup
L342:   bipush 7
L344:   iconst_1
L345:   dup
L346:   pop2
L347:   getstatic Field zg try Lzg;
L350:   aastore
L351:   dup
L352:   bipush 8
L354:   iconst_1
L355:   dup
L356:   pop2
L357:   getstatic Field zg else Lzg;
L360:   aastore
L361:   dup
L362:   bipush 9
L364:   iconst_1
L365:   dup
L366:   pop2
L367:   getstatic Field zg this Lzg;
L370:   aastore
L371:   dup
L372:   bipush 10
L374:   iconst_1
L375:   dup
L376:   pop2
L377:   getstatic Field zg "enum" Lzg;
L380:   aastore
L381:   dup
L382:   bipush 11
L384:   iconst_1
L385:   dup
L386:   pop2
L387:   getstatic Field zg byte Lzg;
L390:   aastore
L391:   dup
L392:   bipush 12
L394:   iconst_1
L395:   dup
L396:   pop2
L397:   getstatic Field zg short Lzg;
L400:   aastore
L401:   dup
L402:   bipush 13
L404:   iconst_1
L405:   dup
L406:   pop2
L407:   getstatic Field zg do Lzg;
L410:   aastore
L411:   dup
L412:   bipush 14
L414:   iconst_1
L415:   dup
L416:   pop2
L417:   getstatic Field zg goto Lzg;
L420:   aastore
L421:   dup
L422:   bipush 15
L424:   iconst_1
L425:   dup
L426:   pop2
L427:   getstatic Field zg void Lzg;
L430:   aastore
L431:   putstatic Field zg int [Lzg;
L434:   return
L435:   
    .end code
.end method

.method private <init> : (Ljava/lang/String;I)V
    .code stack 3 locals 3
L0:     aload_0
L1:     aload_1
L2:     iload_2
L3:     invokespecial Method java/lang/Enum <init> (Ljava/lang/String;I)V
L6:     return
L7:     
    .end code
.end method

.method public static valueOf : (Ljava/lang/String;)Lzg;
    .code stack 2 locals 1
L0:     ldc Class zg
L2:     aload_0
L3:     invokestatic Method java/lang/Enum valueOf (Ljava/lang/Class;Ljava/lang/String;)Ljava/lang/Enum;
L6:     checkcast zg
L9:     areturn
L10:    
    .end code
.end method
.innerclasses
    zg UE [0] public static final enum
.end innerclasses
.end class
