.version 46 0
.class public final super jouvieje/bass/structures/J
.super jouvieje/bass/utils/m

.method public static method1600 : (Ljouvieje/bass/utils/m;)Ljouvieje/bass/structures/J;
    .code stack 4 locals 3
L0:     aload_0
L1:     invokestatic Method jouvieje/bass/utils/m method1176 (Ljouvieje/bass/utils/m;)J
L4:     dup2
L5:     lstore_1
L6:     lconst_0
L7:     lcmp
L8:     ifne L14
L11:    aconst_null
L12:    areturn
L13:    athrow
L14:    new jouvieje/bass/structures/J
L17:    dup
L18:    lload_1
L19:    invokespecial Method jouvieje/bass/structures/J <init> (J)V
L22:    areturn
L23:    
        .attribute StackMap b'\x00\x02\x00\x0D\x00\x00\x00\x01\x07\x00\x0C\x00\x0E\x00\x02\x07\x00\x04\x04\x00\x00'
    .end code
.end method

.method public method1218 : ()V
    .code stack 3 locals 1
L0:     aload_0
L1:     lconst_0
L2:     putfield Field jouvieje/bass/structures/J field2319 J
L5:     return
L6:     
    .end code
.end method

.method protected <init> : (J)V
    .code stack 3 locals 3
L0:     aload_0
L1:     lload_1
L2:     invokespecial Method jouvieje/bass/utils/m <init> (J)V
L5:     return
L6:     
    .end code
.end method

.method public static method1601 : (I)[Ljouvieje/bass/structures/J;
    .code stack 10 locals 7
L0:     iload_0
L1:     ifgt L7
L4:     aconst_null
L5:     areturn
L6:     athrow
L7:     iload_0
L8:     invokestatic Method jouvieje/bass/structures/StructureJNI HCHANNEL_newArray (I)J
L11:    dup2
L12:    lstore_1
L13:    lconst_0
L14:    lcmp
L15:    ifne L26
L18:    new java/lang/OutOfMemoryError
L21:    dup
L22:    invokespecial Method java/lang/OutOfMemoryError <init> ()V
L25:    athrow
L26:    invokestatic Method jouvieje/bass/structures/StructureJNI HCHANNEL_SIZEOF ()I
L29:    i2l
L30:    lstore_3
L31:    iload_0
L32:    anewarray jouvieje/bass/structures/J
L35:    iconst_1
L36:    dup
L37:    pop2
L38:    astore 5
L40:    iconst_0
L41:    iconst_1
L42:    dup
L43:    pop2
L44:    dup
L45:    istore 6
L47:    goto L78
L50:    athrow
L51:    aload 5
L53:    new jouvieje/bass/structures/J
L56:    iload 6
L58:    dup_x1
L59:    dup
L60:    pop2
L61:    dup
L62:    lload_1
L63:    iload 6
L65:    i2l
L66:    lload_3
L67:    lmul
L68:    ladd
L69:    invokespecial Method jouvieje/bass/structures/J <init> (J)V
L72:    iinc 6 1
L75:    aastore
L76:    iload 6
L78:    iload_0
L79:    if_icmplt L51
L82:    aload 5
L84:    areturn
L85:    
        .attribute StackMap b'\x00\x06\x00\x06\x00\x00\x00\x01\x07\x00\x0C\x00\x07\x00\x01\x01\x00\x00\x00\x1A\x00\x02\x01\x04\x00\x00\x00\x32\x00\x00\x00\x01\x07\x00\x0C\x00\x33\x00\x05\x01\x04\x04\x07\x00\x29\x01\x00\x00\x00\x4E\x00\x05\x01\x04\x04\x07\x00\x29\x01\x00\x01\x01'
    .end code
.end method

.method public <init> : ()V
    .code stack 1 locals 1
L0:     aload_0
L1:     invokespecial Method jouvieje/bass/utils/m <init> ()V
L4:     return
L5:     
    .end code
.end method
.end class
