.version 46 0
.class public final super jouvieje/bass/structures/u
.super jouvieje/bass/utils/m

.method public method1219 : (I)V
    .code stack 4 locals 2
L0:     aload_0
L1:     getfield Field jouvieje/bass/structures/u field2319 J
L4:     lconst_0
L5:     lcmp
L6:     ifne L17
L9:     new java/lang/NullPointerException
L12:    dup
L13:    invokespecial Method java/lang/NullPointerException <init> ()V
L16:    athrow
L17:    aload_0
L18:    getfield Field jouvieje/bass/structures/u field2319 J
L21:    iload_1
L22:    invokestatic Method jouvieje/bass/structures/StructureJNI BASS_INFO_set_freesam (JI)V
L25:    return
L26:    
        .attribute StackMap b'\x00\x01\x00\x11\x00\x02\x07\x00\x02\x01\x00\x00'
    .end code
.end method

.method public method1220 : ()I
    .code stack 4 locals 1
L0:     aload_0
L1:     getfield Field jouvieje/bass/structures/u field2319 J
L4:     lconst_0
L5:     lcmp
L6:     ifne L17
L9:     new java/lang/NullPointerException
L12:    dup
L13:    invokespecial Method java/lang/NullPointerException <init> ()V
L16:    athrow
L17:    aload_0
L18:    getfield Field jouvieje/bass/structures/u field2319 J
L21:    invokestatic Method jouvieje/bass/structures/StructureJNI BASS_INFO_get_initflags (J)I
L24:    ireturn
L25:    
        .attribute StackMap b'\x00\x01\x00\x11\x00\x01\x07\x00\x02\x00\x00'
    .end code
.end method

.method public new : (I)V
    .code stack 4 locals 2
L0:     aload_0
L1:     getfield Field jouvieje/bass/structures/u field2319 J
L4:     lconst_0
L5:     lcmp
L6:     ifne L17
L9:     new java/lang/NullPointerException
L12:    dup
L13:    invokespecial Method java/lang/NullPointerException <init> ()V
L16:    athrow
L17:    aload_0
L18:    getfield Field jouvieje/bass/structures/u field2319 J
L21:    iload_1
L22:    invokestatic Method jouvieje/bass/structures/StructureJNI BASS_INFO_set_speakers (JI)V
L25:    return
L26:    
        .attribute StackMap b'\x00\x01\x00\x11\x00\x02\x07\x00\x02\x01\x00\x00'
    .end code
.end method

.method public method1221 : ()I
    .code stack 4 locals 1
L0:     aload_0
L1:     getfield Field jouvieje/bass/structures/u field2319 J
L4:     lconst_0
L5:     lcmp
L6:     ifne L17
L9:     new java/lang/NullPointerException
L12:    dup
L13:    invokespecial Method java/lang/NullPointerException <init> ()V
L16:    athrow
L17:    aload_0
L18:    getfield Field jouvieje/bass/structures/u field2319 J
L21:    invokestatic Method jouvieje/bass/structures/StructureJNI BASS_INFO_get_hwfree (J)I
L24:    ireturn
L25:    
        .attribute StackMap b'\x00\x01\x00\x11\x00\x01\x07\x00\x02\x00\x00'
    .end code
.end method

.method public try : (I)V
    .code stack 4 locals 2
L0:     aload_0
L1:     getfield Field jouvieje/bass/structures/u field2319 J
L4:     lconst_0
L5:     lcmp
L6:     ifne L17
L9:     new java/lang/NullPointerException
L12:    dup
L13:    invokespecial Method java/lang/NullPointerException <init> ()V
L16:    athrow
L17:    aload_0
L18:    getfield Field jouvieje/bass/structures/u field2319 J
L21:    iload_1
L22:    invokestatic Method jouvieje/bass/structures/StructureJNI BASS_INFO_set_free3d (JI)V
L25:    return
L26:    
        .attribute StackMap b'\x00\x01\x00\x11\x00\x02\x07\x00\x02\x01\x00\x00'
    .end code
.end method

.method public this : (I)V
    .code stack 4 locals 2
L0:     aload_0
L1:     getfield Field jouvieje/bass/structures/u field2319 J
L4:     lconst_0
L5:     lcmp
L6:     ifne L17
L9:     new java/lang/NullPointerException
L12:    dup
L13:    invokespecial Method java/lang/NullPointerException <init> ()V
L16:    athrow
L17:    aload_0
L18:    getfield Field jouvieje/bass/structures/u field2319 J
L21:    iload_1
L22:    invokestatic Method jouvieje/bass/structures/StructureJNI BASS_INFO_set_initflags (JI)V
L25:    return
L26:    
        .attribute StackMap b'\x00\x01\x00\x11\x00\x02\x07\x00\x02\x01\x00\x00'
    .end code
.end method

.method public <init> : ()V
    .code stack 1 locals 1
L0:     aload_0
L1:     invokespecial Method jouvieje/bass/utils/m <init> ()V
L4:     return
L5:     
    .end code
.end method

.method public method1222 : (I)V
    .code stack 4 locals 2
L0:     aload_0
L1:     getfield Field jouvieje/bass/structures/u field2319 J
L4:     lconst_0
L5:     lcmp
L6:     ifne L17
L9:     new java/lang/NullPointerException
L12:    dup
L13:    invokespecial Method java/lang/NullPointerException <init> ()V
L16:    athrow
L17:    aload_0
L18:    getfield Field jouvieje/bass/structures/u field2319 J
L21:    iload_1
L22:    invokestatic Method jouvieje/bass/structures/StructureJNI BASS_INFO_set_freq (JI)V
L25:    return
L26:    
        .attribute StackMap b'\x00\x01\x00\x11\x00\x02\x07\x00\x02\x01\x00\x00'
    .end code
.end method

.method public method1223 : ()I
    .code stack 4 locals 1
L0:     aload_0
L1:     getfield Field jouvieje/bass/structures/u field2319 J
L4:     lconst_0
L5:     lcmp
L6:     ifne L17
L9:     new java/lang/NullPointerException
L12:    dup
L13:    invokespecial Method java/lang/NullPointerException <init> ()V
L16:    athrow
L17:    aload_0
L18:    getfield Field jouvieje/bass/structures/u field2319 J
L21:    invokestatic Method jouvieje/bass/structures/StructureJNI BASS_INFO_get_latency (J)I
L24:    ireturn
L25:    
        .attribute StackMap b'\x00\x01\x00\x11\x00\x01\x07\x00\x02\x00\x00'
    .end code
.end method

.method public method1224 : (I)V
    .code stack 4 locals 2
L0:     aload_0
L1:     getfield Field jouvieje/bass/structures/u field2319 J
L4:     lconst_0
L5:     lcmp
L6:     ifne L17
L9:     new java/lang/NullPointerException
L12:    dup
L13:    invokespecial Method java/lang/NullPointerException <init> ()V
L16:    athrow
L17:    aload_0
L18:    getfield Field jouvieje/bass/structures/u field2319 J
L21:    iload_1
L22:    invokestatic Method jouvieje/bass/structures/StructureJNI BASS_INFO_set_minbuf (JI)V
L25:    return
L26:    
        .attribute StackMap b'\x00\x01\x00\x11\x00\x02\x07\x00\x02\x01\x00\x00'
    .end code
.end method

.method public method1225 : ()I
    .code stack 4 locals 1
L0:     aload_0
L1:     getfield Field jouvieje/bass/structures/u field2319 J
L4:     lconst_0
L5:     lcmp
L6:     ifne L17
L9:     new java/lang/NullPointerException
L12:    dup
L13:    invokespecial Method java/lang/NullPointerException <init> ()V
L16:    athrow
L17:    aload_0
L18:    getfield Field jouvieje/bass/structures/u field2319 J
L21:    invokestatic Method jouvieje/bass/structures/StructureJNI BASS_INFO_get_minrate (J)I
L24:    ireturn
L25:    
        .attribute StackMap b'\x00\x01\x00\x11\x00\x01\x07\x00\x02\x00\x00'
    .end code
.end method

.method public method1226 : (I)V
    .code stack 4 locals 2
L0:     aload_0
L1:     getfield Field jouvieje/bass/structures/u field2319 J
L4:     lconst_0
L5:     lcmp
L6:     ifne L17
L9:     new java/lang/NullPointerException
L12:    dup
L13:    invokespecial Method java/lang/NullPointerException <init> ()V
L16:    athrow
L17:    aload_0
L18:    getfield Field jouvieje/bass/structures/u field2319 J
L21:    iload_1
L22:    invokestatic Method jouvieje/bass/structures/StructureJNI BASS_INFO_set_flags (JI)V
L25:    return
L26:    
        .attribute StackMap b'\x00\x01\x00\x11\x00\x02\x07\x00\x02\x01\x00\x00'
    .end code
.end method

.method public new : ()V
    .code stack 4 locals 1
L0:     aload_0
L1:     getfield Field jouvieje/bass/structures/u field2319 J
L4:     lconst_0
L5:     lcmp
L6:     ifeq L16
L9:     aload_0
L10:    getfield Field jouvieje/bass/structures/u field2319 J
L13:    invokestatic Method jouvieje/bass/structures/StructureJNI BASS_INFO_delete (J)V
L16:    aload_0
L17:    lconst_0
L18:    putfield Field jouvieje/bass/structures/u field2319 J
L21:    return
L22:    
        .attribute StackMap b'\x00\x01\x00\x10\x00\x01\x07\x00\x02\x00\x00'
    .end code
.end method

.method public try : ()I
    .code stack 4 locals 1
L0:     aload_0
L1:     getfield Field jouvieje/bass/structures/u field2319 J
L4:     lconst_0
L5:     lcmp
L6:     ifne L17
L9:     new java/lang/NullPointerException
L12:    dup
L13:    invokespecial Method java/lang/NullPointerException <init> ()V
L16:    athrow
L17:    aload_0
L18:    getfield Field jouvieje/bass/structures/u field2319 J
L21:    invokestatic Method jouvieje/bass/structures/StructureJNI BASS_INFO_get_hwsize (J)I
L24:    ireturn
L25:    
        .attribute StackMap b'\x00\x01\x00\x11\x00\x01\x07\x00\x02\x00\x00'
    .end code
.end method

.method public method1227 : (I)V
    .code stack 4 locals 2
L0:     aload_0
L1:     getfield Field jouvieje/bass/structures/u field2319 J
L4:     lconst_0
L5:     lcmp
L6:     ifne L17
L9:     new java/lang/NullPointerException
L12:    dup
L13:    invokespecial Method java/lang/NullPointerException <init> ()V
L16:    athrow
L17:    aload_0
L18:    getfield Field jouvieje/bass/structures/u field2319 J
L21:    iload_1
L22:    invokestatic Method jouvieje/bass/structures/StructureJNI BASS_INFO_set_maxrate (JI)V
L25:    return
L26:    
        .attribute StackMap b'\x00\x01\x00\x11\x00\x02\x07\x00\x02\x01\x00\x00'
    .end code
.end method

.method public method1186 : (I)V
    .code stack 4 locals 2
L0:     aload_0
L1:     getfield Field jouvieje/bass/structures/u field2319 J
L4:     lconst_0
L5:     lcmp
L6:     ifne L17
L9:     new java/lang/NullPointerException
L12:    dup
L13:    invokespecial Method java/lang/NullPointerException <init> ()V
L16:    athrow
L17:    aload_0
L18:    getfield Field jouvieje/bass/structures/u field2319 J
L21:    iload_1
L22:    invokestatic Method jouvieje/bass/structures/StructureJNI BASS_INFO_set_hwsize (JI)V
L25:    return
L26:    
        .attribute StackMap b'\x00\x01\x00\x11\x00\x02\x07\x00\x02\x01\x00\x00'
    .end code
.end method

.method public method1194 : (I)V
    .code stack 4 locals 2
L0:     aload_0
L1:     getfield Field jouvieje/bass/structures/u field2319 J
L4:     lconst_0
L5:     lcmp
L6:     ifne L17
L9:     new java/lang/NullPointerException
L12:    dup
L13:    invokespecial Method java/lang/NullPointerException <init> ()V
L16:    athrow
L17:    aload_0
L18:    getfield Field jouvieje/bass/structures/u field2319 J
L21:    iload_1
L22:    invokestatic Method jouvieje/bass/structures/StructureJNI BASS_INFO_set_latency (JI)V
L25:    return
L26:    
        .attribute StackMap b'\x00\x01\x00\x11\x00\x02\x07\x00\x02\x01\x00\x00'
    .end code
.end method

.method public this : ()I
    .code stack 4 locals 1
L0:     aload_0
L1:     getfield Field jouvieje/bass/structures/u field2319 J
L4:     lconst_0
L5:     lcmp
L6:     ifne L17
L9:     new java/lang/NullPointerException
L12:    dup
L13:    invokespecial Method java/lang/NullPointerException <init> ()V
L16:    athrow
L17:    aload_0
L18:    getfield Field jouvieje/bass/structures/u field2319 J
L21:    invokestatic Method jouvieje/bass/structures/StructureJNI BASS_INFO_get_dsver (J)I
L24:    ireturn
L25:    
        .attribute StackMap b'\x00\x01\x00\x11\x00\x01\x07\x00\x02\x00\x00'
    .end code
.end method

.method public method1228 : ()I
    .code stack 4 locals 1
L0:     aload_0
L1:     getfield Field jouvieje/bass/structures/u field2319 J
L4:     lconst_0
L5:     lcmp
L6:     ifne L17
L9:     new java/lang/NullPointerException
L12:    dup
L13:    invokespecial Method java/lang/NullPointerException <init> ()V
L16:    athrow
L17:    aload_0
L18:    getfield Field jouvieje/bass/structures/u field2319 J
L21:    invokestatic Method jouvieje/bass/structures/StructureJNI BASS_INFO_get_freesam (J)I
L24:    ireturn
L25:    
        .attribute StackMap b'\x00\x01\x00\x11\x00\x01\x07\x00\x02\x00\x00'
    .end code
.end method

.method public static method1229 : ()Ljouvieje/bass/structures/u;
    .code stack 4 locals 2
L0:     invokestatic Method jouvieje/bass/structures/StructureJNI BASS_INFO_new ()J
L3:     dup2
L4:     lstore_0
L5:     lconst_0
L6:     lcmp
L7:     ifne L18
L10:    new java/lang/OutOfMemoryError
L13:    dup
L14:    invokespecial Method java/lang/OutOfMemoryError <init> ()V
L17:    athrow
L18:    new jouvieje/bass/structures/u
L21:    dup
L22:    lload_0
L23:    invokespecial Method jouvieje/bass/structures/u <init> (J)V
L26:    areturn
L27:    
        .attribute StackMap b'\x00\x01\x00\x12\x00\x01\x04\x00\x00'
    .end code
.end method

.method public method1191 : ()I
    .code stack 4 locals 1
L0:     aload_0
L1:     getfield Field jouvieje/bass/structures/u field2319 J
L4:     lconst_0
L5:     lcmp
L6:     ifne L17
L9:     new java/lang/NullPointerException
L12:    dup
L13:    invokespecial Method java/lang/NullPointerException <init> ()V
L16:    athrow
L17:    aload_0
L18:    getfield Field jouvieje/bass/structures/u field2319 J
L21:    invokestatic Method jouvieje/bass/structures/StructureJNI BASS_INFO_get_freq (J)I
L24:    ireturn
L25:    
        .attribute StackMap b'\x00\x01\x00\x11\x00\x01\x07\x00\x02\x00\x00'
    .end code
.end method

.method public method1196 : (I)V
    .code stack 4 locals 2
L0:     aload_0
L1:     getfield Field jouvieje/bass/structures/u field2319 J
L4:     lconst_0
L5:     lcmp
L6:     ifne L17
L9:     new java/lang/NullPointerException
L12:    dup
L13:    invokespecial Method java/lang/NullPointerException <init> ()V
L16:    athrow
L17:    aload_0
L18:    getfield Field jouvieje/bass/structures/u field2319 J
L21:    iload_1
L22:    invokestatic Method jouvieje/bass/structures/StructureJNI BASS_INFO_set_hwfree (JI)V
L25:    return
L26:    
        .attribute StackMap b'\x00\x01\x00\x11\x00\x02\x07\x00\x02\x01\x00\x00'
    .end code
.end method

.method public method1192 : ()I
    .code stack 4 locals 1
L0:     aload_0
L1:     getfield Field jouvieje/bass/structures/u field2319 J
L4:     lconst_0
L5:     lcmp
L6:     ifne L17
L9:     new java/lang/NullPointerException
L12:    dup
L13:    invokespecial Method java/lang/NullPointerException <init> ()V
L16:    athrow
L17:    aload_0
L18:    getfield Field jouvieje/bass/structures/u field2319 J
L21:    invokestatic Method jouvieje/bass/structures/StructureJNI BASS_INFO_get_flags (J)I
L24:    ireturn
L25:    
        .attribute StackMap b'\x00\x01\x00\x11\x00\x01\x07\x00\x02\x00\x00'
    .end code
.end method

.method public method1195 : ()I
    .code stack 4 locals 1
L0:     aload_0
L1:     getfield Field jouvieje/bass/structures/u field2319 J
L4:     lconst_0
L5:     lcmp
L6:     ifne L17
L9:     new java/lang/NullPointerException
L12:    dup
L13:    invokespecial Method java/lang/NullPointerException <init> ()V
L16:    athrow
L17:    aload_0
L18:    getfield Field jouvieje/bass/structures/u field2319 J
L21:    invokestatic Method jouvieje/bass/structures/StructureJNI BASS_INFO_get_speakers (J)I
L24:    ireturn
L25:    
        .attribute StackMap b'\x00\x01\x00\x11\x00\x01\x07\x00\x02\x00\x00'
    .end code
.end method

.method public method1230 : (Z)V
    .code stack 4 locals 2
L0:     aload_0
L1:     getfield Field jouvieje/bass/structures/u field2319 J
L4:     lconst_0
L5:     lcmp
L6:     ifne L17
L9:     new java/lang/NullPointerException
L12:    dup
L13:    invokespecial Method java/lang/NullPointerException <init> ()V
L16:    athrow
L17:    aload_0
L18:    getfield Field jouvieje/bass/structures/u field2319 J
L21:    iload_1
L22:    invokestatic Method jouvieje/bass/structures/StructureJNI BASS_INFO_set_eax (JZ)V
L25:    return
L26:    
        .attribute StackMap b'\x00\x01\x00\x11\x00\x02\x07\x00\x02\x01\x00\x00'
    .end code
.end method

.method public method1197 : (I)V
    .code stack 4 locals 2
L0:     aload_0
L1:     getfield Field jouvieje/bass/structures/u field2319 J
L4:     lconst_0
L5:     lcmp
L6:     ifne L17
L9:     new java/lang/NullPointerException
L12:    dup
L13:    invokespecial Method java/lang/NullPointerException <init> ()V
L16:    athrow
L17:    aload_0
L18:    getfield Field jouvieje/bass/structures/u field2319 J
L21:    iload_1
L22:    invokestatic Method jouvieje/bass/structures/StructureJNI BASS_INFO_set_dsver (JI)V
L25:    return
L26:    
        .attribute StackMap b'\x00\x01\x00\x11\x00\x02\x07\x00\x02\x01\x00\x00'
    .end code
.end method

.method public method1231 : ()Z
    .code stack 4 locals 1
L0:     aload_0
L1:     getfield Field jouvieje/bass/structures/u field2319 J
L4:     lconst_0
L5:     lcmp
L6:     ifne L17
L9:     new java/lang/NullPointerException
L12:    dup
L13:    invokespecial Method java/lang/NullPointerException <init> ()V
L16:    athrow
L17:    aload_0
L18:    getfield Field jouvieje/bass/structures/u field2319 J
L21:    invokestatic Method jouvieje/bass/structures/StructureJNI BASS_INFO_get_eax (J)Z
L24:    ireturn
L25:    
        .attribute StackMap b'\x00\x01\x00\x11\x00\x01\x07\x00\x02\x00\x00'
    .end code
.end method

.method public static method1232 : (Ljouvieje/bass/utils/m;)Ljouvieje/bass/structures/u;
    .code stack 4 locals 3
L0:     aload_0
L1:     invokestatic Method jouvieje/bass/utils/m method1176 (Ljouvieje/bass/utils/m;)J
L4:     dup2
L5:     lstore_1
L6:     lconst_0
L7:     lcmp
L8:     ifne L14
L11:    aconst_null
L12:    areturn
L13:    athrow
L14:    new jouvieje/bass/structures/u
L17:    dup
L18:    lload_1
L19:    invokespecial Method jouvieje/bass/structures/u <init> (J)V
L22:    areturn
L23:    
        .attribute StackMap b'\x00\x02\x00\x0D\x00\x00\x00\x01\x07\x00\x8E\x00\x0E\x00\x02\x07\x00\x04\x04\x00\x00'
    .end code
.end method

.method protected <init> : (J)V
    .code stack 3 locals 3
L0:     aload_0
L1:     lload_1
L2:     invokespecial Method jouvieje/bass/utils/m <init> (J)V
L5:     return
L6:     
    .end code
.end method

.method public method1199 : ()I
    .code stack 4 locals 1
L0:     aload_0
L1:     getfield Field jouvieje/bass/structures/u field2319 J
L4:     lconst_0
L5:     lcmp
L6:     ifne L17
L9:     new java/lang/NullPointerException
L12:    dup
L13:    invokespecial Method java/lang/NullPointerException <init> ()V
L16:    athrow
L17:    aload_0
L18:    getfield Field jouvieje/bass/structures/u field2319 J
L21:    invokestatic Method jouvieje/bass/structures/StructureJNI BASS_INFO_get_minbuf (J)I
L24:    ireturn
L25:    
        .attribute StackMap b'\x00\x01\x00\x11\x00\x01\x07\x00\x02\x00\x00'
    .end code
.end method

.method public method1180 : (I)V
    .code stack 4 locals 2
L0:     aload_0
L1:     getfield Field jouvieje/bass/structures/u field2319 J
L4:     lconst_0
L5:     lcmp
L6:     ifne L17
L9:     new java/lang/NullPointerException
L12:    dup
L13:    invokespecial Method java/lang/NullPointerException <init> ()V
L16:    athrow
L17:    aload_0
L18:    getfield Field jouvieje/bass/structures/u field2319 J
L21:    iload_1
L22:    invokestatic Method jouvieje/bass/structures/StructureJNI BASS_INFO_set_minrate (JI)V
L25:    return
L26:    
        .attribute StackMap b'\x00\x01\x00\x11\x00\x02\x07\x00\x02\x01\x00\x00'
    .end code
.end method

.method public method1233 : ()I
    .code stack 4 locals 1
L0:     aload_0
L1:     getfield Field jouvieje/bass/structures/u field2319 J
L4:     lconst_0
L5:     lcmp
L6:     ifne L17
L9:     new java/lang/NullPointerException
L12:    dup
L13:    invokespecial Method java/lang/NullPointerException <init> ()V
L16:    athrow
L17:    aload_0
L18:    getfield Field jouvieje/bass/structures/u field2319 J
L21:    invokestatic Method jouvieje/bass/structures/StructureJNI BASS_INFO_get_maxrate (J)I
L24:    ireturn
L25:    
        .attribute StackMap b'\x00\x01\x00\x11\x00\x01\x07\x00\x02\x00\x00'
    .end code
.end method

.method public method1184 : ()I
    .code stack 4 locals 1
L0:     aload_0
L1:     getfield Field jouvieje/bass/structures/u field2319 J
L4:     lconst_0
L5:     lcmp
L6:     ifne L17
L9:     new java/lang/NullPointerException
L12:    dup
L13:    invokespecial Method java/lang/NullPointerException <init> ()V
L16:    athrow
L17:    aload_0
L18:    getfield Field jouvieje/bass/structures/u field2319 J
L21:    invokestatic Method jouvieje/bass/structures/StructureJNI BASS_INFO_get_free3d (J)I
L24:    ireturn
L25:    
        .attribute StackMap b'\x00\x01\x00\x11\x00\x01\x07\x00\x02\x00\x00'
    .end code
.end method
.end class
