.version 46 0
.class public final super jouvieje/bass/structures/W
.super jouvieje/bass/utils/m

.method public method1230 : (Z)V
    .code stack 4 locals 2
L0:     aload_0
L1:     getfield Field jouvieje/bass/structures/W field2319 J
L4:     lconst_0
L5:     lcmp
L6:     ifne L17
L9:     new java/lang/NullPointerException
L12:    dup
L13:    invokespecial Method java/lang/NullPointerException <init> ()V
L16:    athrow
L17:    aload_0
L18:    getfield Field jouvieje/bass/structures/W field2319 J
L21:    iload_1
L22:    invokestatic Method jouvieje/bass/structures/StructureJNI BASS_BFX_VOLUME_ENV_set_bFollow (JZ)V
L25:    return
L26:    
        .attribute StackMap b'\x00\x01\x00\x11\x00\x02\x07\x00\x02\x01\x00\x00'
    .end code
.end method

.method public method1286 : ()Z
    .code stack 4 locals 1
L0:     aload_0
L1:     getfield Field jouvieje/bass/structures/W field2319 J
L4:     lconst_0
L5:     lcmp
L6:     ifne L17
L9:     new java/lang/NullPointerException
L12:    dup
L13:    invokespecial Method java/lang/NullPointerException <init> ()V
L16:    athrow
L17:    aload_0
L18:    getfield Field jouvieje/bass/structures/W field2319 J
L21:    invokestatic Method jouvieje/bass/structures/StructureJNI BASS_BFX_VOLUME_ENV_get_bFollow (J)Z
L24:    ireturn
L25:    
        .attribute StackMap b'\x00\x01\x00\x11\x00\x01\x07\x00\x02\x00\x00'
    .end code
.end method

.method public method1383 : ()Ljouvieje/bass/structures/Z;
    .code stack 4 locals 3
L0:     aload_0
L1:     getfield Field jouvieje/bass/structures/W field2319 J
L4:     lconst_0
L5:     lcmp
L6:     ifne L17
L9:     new java/lang/NullPointerException
L12:    dup
L13:    invokespecial Method java/lang/NullPointerException <init> ()V
L16:    athrow
L17:    aload_0
L18:    getfield Field jouvieje/bass/structures/W field2319 J
L21:    invokestatic Method jouvieje/bass/structures/StructureJNI BASS_BFX_VOLUME_ENV_get_pNodes (J)J
L24:    dup2
L25:    lstore_1
L26:    lconst_0
L27:    lcmp
L28:    ifne L34
L31:    aconst_null
L32:    areturn
L33:    athrow
L34:    lload_1
L35:    invokestatic Method jouvieje/bass/utils/m method1177 (J)Ljouvieje/bass/utils/m;
L38:    invokestatic Method jouvieje/bass/structures/Z method1388 (Ljouvieje/bass/utils/m;)Ljouvieje/bass/structures/Z;
L41:    areturn
L42:    
        .attribute StackMap b'\x00\x03\x00\x11\x00\x01\x07\x00\x02\x00\x00\x00\x21\x00\x00\x00\x01\x07\x00\x24\x00\x22\x00\x02\x07\x00\x02\x04\x00\x00'
    .end code
.end method

.method protected <init> : (J)V
    .code stack 3 locals 3
L0:     aload_0
L1:     lload_1
L2:     invokespecial Method jouvieje/bass/utils/m <init> (J)V
L5:     return
L6:     
    .end code
.end method

.method public method1336 : ()I
    .code stack 4 locals 1
L0:     aload_0
L1:     getfield Field jouvieje/bass/structures/W field2319 J
L4:     lconst_0
L5:     lcmp
L6:     ifne L17
L9:     new java/lang/NullPointerException
L12:    dup
L13:    invokespecial Method java/lang/NullPointerException <init> ()V
L16:    athrow
L17:    aload_0
L18:    getfield Field jouvieje/bass/structures/W field2319 J
L21:    invokestatic Method jouvieje/bass/structures/StructureJNI BASS_BFX_VOLUME_ENV_get_lNodeCount (J)I
L24:    ireturn
L25:    
        .attribute StackMap b'\x00\x01\x00\x11\x00\x01\x07\x00\x02\x00\x00'
    .end code
.end method

.method public <init> : ()V
    .code stack 1 locals 1
L0:     aload_0
L1:     invokespecial Method jouvieje/bass/utils/m <init> ()V
L4:     return
L5:     
    .end code
.end method

.method public static method1384 : (Ljouvieje/bass/utils/m;)Ljouvieje/bass/structures/W;
    .code stack 4 locals 3
L0:     aload_0
L1:     invokestatic Method jouvieje/bass/utils/m method1176 (Ljouvieje/bass/utils/m;)J
L4:     dup2
L5:     lstore_1
L6:     lconst_0
L7:     lcmp
L8:     ifne L14
L11:    aconst_null
L12:    areturn
L13:    athrow
L14:    new jouvieje/bass/structures/W
L17:    dup
L18:    lload_1
L19:    invokespecial Method jouvieje/bass/structures/W <init> (J)V
L22:    areturn
L23:    
        .attribute StackMap b'\x00\x02\x00\x0D\x00\x00\x00\x01\x07\x00\x24\x00\x0E\x00\x02\x07\x00\x04\x04\x00\x00'
    .end code
.end method

.method public method1197 : (I)V
    .code stack 4 locals 2
L0:     aload_0
L1:     getfield Field jouvieje/bass/structures/W field2319 J
L4:     lconst_0
L5:     lcmp
L6:     ifne L17
L9:     new java/lang/NullPointerException
L12:    dup
L13:    invokespecial Method java/lang/NullPointerException <init> ()V
L16:    athrow
L17:    aload_0
L18:    getfield Field jouvieje/bass/structures/W field2319 J
L21:    iload_1
L22:    invokestatic Method jouvieje/bass/structures/StructureJNI BASS_BFX_VOLUME_ENV_set_lChannel (JI)V
L25:    return
L26:    
        .attribute StackMap b'\x00\x01\x00\x11\x00\x02\x07\x00\x02\x01\x00\x00'
    .end code
.end method

.method public method1180 : (I)V
    .code stack 4 locals 2
L0:     aload_0
L1:     getfield Field jouvieje/bass/structures/W field2319 J
L4:     lconst_0
L5:     lcmp
L6:     ifne L17
L9:     new java/lang/NullPointerException
L12:    dup
L13:    invokespecial Method java/lang/NullPointerException <init> ()V
L16:    athrow
L17:    aload_0
L18:    getfield Field jouvieje/bass/structures/W field2319 J
L21:    iload_1
L22:    invokestatic Method jouvieje/bass/structures/StructureJNI BASS_BFX_VOLUME_ENV_set_lNodeCount (JI)V
L25:    return
L26:    
        .attribute StackMap b'\x00\x01\x00\x11\x00\x02\x07\x00\x02\x01\x00\x00'
    .end code
.end method

.method public static method1385 : ()Ljouvieje/bass/structures/W;
    .code stack 4 locals 2
L0:     invokestatic Method jouvieje/bass/structures/StructureJNI BASS_BFX_VOLUME_ENV_new ()J
L3:     dup2
L4:     lstore_0
L5:     lconst_0
L6:     lcmp
L7:     ifne L18
L10:    new java/lang/OutOfMemoryError
L13:    dup
L14:    invokespecial Method java/lang/OutOfMemoryError <init> ()V
L17:    athrow
L18:    new jouvieje/bass/structures/W
L21:    dup
L22:    lload_0
L23:    invokespecial Method jouvieje/bass/structures/W <init> (J)V
L26:    areturn
L27:    
        .attribute StackMap b'\x00\x01\x00\x12\x00\x01\x04\x00\x00'
    .end code
.end method

.method public method1386 : (Ljouvieje/bass/structures/Z;)V
    .code stack 4 locals 2
L0:     aload_0
L1:     getfield Field jouvieje/bass/structures/W field2319 J
L4:     lconst_0
L5:     lcmp
L6:     ifne L17
L9:     new java/lang/NullPointerException
L12:    dup
L13:    invokespecial Method java/lang/NullPointerException <init> ()V
L16:    athrow
L17:    aload_0
L18:    getfield Field jouvieje/bass/structures/W field2319 J
L21:    aload_1
L22:    invokestatic Method jouvieje/bass/utils/m method1176 (Ljouvieje/bass/utils/m;)J
L25:    invokestatic Method jouvieje/bass/structures/StructureJNI BASS_BFX_VOLUME_ENV_set_pNodes (JJ)V
L28:    return
L29:    
        .attribute StackMap b'\x00\x01\x00\x11\x00\x02\x07\x00\x02\x07\x00\x2A\x00\x00'
    .end code
.end method

.method public method1233 : ()I
    .code stack 4 locals 1
L0:     aload_0
L1:     getfield Field jouvieje/bass/structures/W field2319 J
L4:     lconst_0
L5:     lcmp
L6:     ifne L17
L9:     new java/lang/NullPointerException
L12:    dup
L13:    invokespecial Method java/lang/NullPointerException <init> ()V
L16:    athrow
L17:    aload_0
L18:    getfield Field jouvieje/bass/structures/W field2319 J
L21:    invokestatic Method jouvieje/bass/structures/StructureJNI BASS_BFX_VOLUME_ENV_get_lChannel (J)I
L24:    ireturn
L25:    
        .attribute StackMap b'\x00\x01\x00\x11\x00\x01\x07\x00\x02\x00\x00'
    .end code
.end method

.method public method1218 : ()V
    .code stack 4 locals 1
L0:     aload_0
L1:     getfield Field jouvieje/bass/structures/W field2319 J
L4:     lconst_0
L5:     lcmp
L6:     ifeq L16
L9:     aload_0
L10:    getfield Field jouvieje/bass/structures/W field2319 J
L13:    invokestatic Method jouvieje/bass/structures/StructureJNI BASS_BFX_VOLUME_ENV_delete (J)V
L16:    aload_0
L17:    lconst_0
L18:    putfield Field jouvieje/bass/structures/W field2319 J
L21:    return
L22:    
        .attribute StackMap b'\x00\x01\x00\x10\x00\x01\x07\x00\x02\x00\x00'
    .end code
.end method
.end class
