.version 49 0
.class public final super org/lwjgl/opengl/aB
.super java/awt/Canvas
.implements org/lwjgl/opengl/C
.implements java/awt/event/ComponentListener
.implements java/awt/event/HierarchyListener
.field private final long Lorg/lwjgl/opengl/PixelFormat;
.field private void Ljava/lang/Object;
.field private try Lorg/lwjgl/opengl/a;
.field private static final const J = 1L
.field private new Lorg/lwjgl/opengl/Jb;
.field private null Z
.field private this Z
.field private static final char Lorg/lwjgl/opengl/e;
.field private final else Lorg/lwjgl/opengl/k;
.field private final "enum" Lorg/lwjgl/opengl/CB;
.field private do I

.method public addNotify : ()V
    .code stack 1 locals 1
L0:     aload_0
L1:     invokespecial Method java/awt/Canvas addNotify ()V
L4:     return
L5:     
    .end code
.end method

.method public bridge synthetic do : ()Lorg/lwjgl/opengl/G;
    .code stack 1 locals 1
L0:     aload_0
L1:     invokevirtual Method org/lwjgl/opengl/aB new ()Lorg/lwjgl/opengl/Jb;
L4:     areturn
L5:     
    .end code
.end method

.method protected class : ()V
    .code stack 0 locals 1
L0:     return
L1:     
    .end code
.end method

.method public setLocation : (Ljava/awt/Point;)V
    .code stack 3 locals 2
L0:     aload_0
L1:     dup
L2:     aload_1
L3:     invokespecial Method java/awt/Canvas setLocation (Ljava/awt/Point;)V
L6:     invokespecial Method org/lwjgl/opengl/aB if ()V
L9:     return
L10:    
    .end code
.end method

.method public hierarchyChanged : (Ljava/awt/event/HierarchyEvent;)V
    .code stack 1 locals 2
L0:     aload_0
L1:     invokespecial Method org/lwjgl/opengl/aB if ()V
L4:     return
L5:     
    .end code
.end method

.method public removeNotify : ()V
    .code stack 2 locals 3
L0:     aload_0
L1:     getfield Field org/lwjgl/opengl/aB void Ljava/lang/Object;
L4:     dup
L5:     astore_1
L6:     monitorenter
        .catch [0] from L7 to L17 using L19
L7:     aload_0
L8:     dup
L9:     invokevirtual Method org/lwjgl/opengl/aB short ()V
L12:    invokespecial Method java/awt/Canvas removeNotify ()V
L15:    aload_1
L16:    monitorexit
L17:    return
L18:    athrow
        .catch [0] from L19 to L22 using L19
L19:    astore_2
L20:    aload_1
L21:    monitorexit
L22:    aload_2
L23:    athrow
L24:    athrow
L25:    
        .attribute StackMap b'\x00\x03\x00\x12\x00\x00\x00\x01\x07\x00\x3D\x00\x13\x00\x02\x07\x00\x02\x07\x00\x3F\x00\x01\x07\x00\x3D\x00\x18\x00\x00\x00\x01\x07\x00\x3D'
    .end code
.end method

.method public const : ()Z
    .code stack 3 locals 3
L0:     aload_0
L1:     getfield Field org/lwjgl/opengl/aB void Ljava/lang/Object;
L4:     dup
L5:     astore_1
L6:     monitorenter
        .catch [0] from L7 to L33 using L35
L7:     aload_0
L8:     getfield Field org/lwjgl/opengl/aB new Lorg/lwjgl/opengl/Jb;
L11:    ifnonnull L24
L14:    new java/lang/IllegalStateException
L17:    dup
L18:    ldc "Canvas not yet displayable"
L20:    invokespecial Method java/lang/IllegalStateException <init> (Ljava/lang/String;)V
L23:    athrow
L24:    aload_0
L25:    getfield Field org/lwjgl/opengl/aB new Lorg/lwjgl/opengl/Jb;
L28:    invokevirtual Method org/lwjgl/opengl/Jb else ()Z
L31:    aload_1
L32:    monitorexit
L33:    ireturn
L34:    athrow
        .catch [0] from L35 to L38 using L35
L35:    astore_2
L36:    aload_1
L37:    monitorexit
L38:    aload_2
L39:    athrow
L40:    
        .attribute StackMap b'\x00\x03\x00\x18\x00\x02\x07\x00\x02\x07\x00\x3F\x00\x00\x00\x22\x00\x00\x00\x01\x07\x00\x3D\x00\x23\x00\x02\x07\x00\x02\x07\x00\x3F\x00\x01\x07\x00\x3D'
    .end code
    .exceptions org/lwjgl/LWJGLException
.end method

.method public float : ()V
    .code stack 3 locals 3
L0:     aload_0
L1:     getfield Field org/lwjgl/opengl/aB void Ljava/lang/Object;
L4:     dup
L5:     astore_1
L6:     monitorenter
        .catch [0] from L7 to L29 using L31
L7:     aload_0
L8:     getfield Field org/lwjgl/opengl/aB new Lorg/lwjgl/opengl/Jb;
L11:    ifnonnull L24
L14:    new java/lang/IllegalStateException
L17:    dup
L18:    ldc "Canvas not yet displayable"
L20:    invokespecial Method java/lang/IllegalStateException <init> (Ljava/lang/String;)V
L23:    athrow
L24:    invokestatic Method org/lwjgl/opengl/Jb char ()V
L27:    aload_1
L28:    monitorexit
L29:    return
L30:    athrow
        .catch [0] from L31 to L34 using L31
L31:    astore_2
L32:    aload_1
L33:    monitorexit
L34:    aload_2
L35:    athrow
L36:    athrow
L37:    
        .attribute StackMap b'\x00\x04\x00\x18\x00\x02\x07\x00\x02\x07\x00\x3F\x00\x00\x00\x1E\x00\x00\x00\x01\x07\x00\x3D\x00\x1F\x00\x02\x07\x00\x02\x07\x00\x3F\x00\x01\x07\x00\x3D\x00\x24\x00\x00\x00\x01\x07\x00\x3D'
    .end code
    .exceptions org/lwjgl/LWJGLException
.end method

.method public componentHidden : (Ljava/awt/event/ComponentEvent;)V
    .code stack 0 locals 2
L0:     return
L1:     
    .end code
.end method

.method public setSize : (II)V
    .code stack 4 locals 3
L0:     aload_0
L1:     dup
L2:     iload_1
L3:     iload_2
L4:     invokespecial Method java/awt/Canvas setSize (II)V
L7:     invokespecial Method org/lwjgl/opengl/aB if ()V
L10:    return
L11:    
    .end code
.end method

.method public break : (Lorg/lwjgl/opengl/h;)V
    .code stack 2 locals 2
L0:     new java/lang/UnsupportedOperationException
L3:     dup
L4:     invokespecial Method java/lang/UnsupportedOperationException <init> ()V
L7:     athrow
L8:     
    .end code
    .exceptions org/lwjgl/LWJGLException
.end method

.method public componentShown : (Ljava/awt/event/ComponentEvent;)V
    .code stack 0 locals 2
L0:     return
L1:     
    .end code
.end method

.method private if : ()V
    .code stack 4 locals 3
L0:     aload_0
L1:     getfield Field org/lwjgl/opengl/aB void Ljava/lang/Object;
L4:     dup
L5:     astore_1
L6:     monitorenter
        .catch [0] from L7 to L17 using L19
L7:     aload_0
L8:     iconst_1
L9:     dup
L10:    dup
L11:    pop2
L12:    putfield Field org/lwjgl/opengl/aB null Z
L15:    aload_1
L16:    monitorexit
L17:    return
L18:    athrow
        .catch [0] from L19 to L22 using L19
L19:    astore_2
L20:    aload_1
L21:    monitorexit
L22:    aload_2
L23:    athrow
L24:    athrow
L25:    
        .attribute StackMap b'\x00\x03\x00\x12\x00\x00\x00\x01\x07\x00\x3D\x00\x13\x00\x02\x07\x00\x02\x07\x00\x3F\x00\x01\x07\x00\x3D\x00\x18\x00\x00\x00\x01\x07\x00\x3D'
    .end code
.end method

.method protected char : ()V
    .code stack 0 locals 1
L0:     return
L1:     
    .end code
.end method

.method public setLocation : (II)V
    .code stack 4 locals 3
L0:     aload_0
L1:     dup
L2:     iload_1
L3:     iload_2
L4:     invokespecial Method java/awt/Canvas setLocation (II)V
L7:     invokespecial Method org/lwjgl/opengl/aB if ()V
L10:    return
L11:    
    .end code
.end method

.method public <init> : (Ljava/awt/GraphicsDevice;Lorg/lwjgl/opengl/PixelFormat;Lorg/lwjgl/opengl/k;Lorg/lwjgl/opengl/CB;)V
    .code stack 10 locals 5
L0:     aload_2
L1:     aload_0
L2:     getstatic Field org/lwjgl/opengl/aB char Lorg/lwjgl/opengl/e;
L5:     aload_1
L6:     aload_2
L7:     invokeinterface InterfaceMethod org/lwjgl/opengl/e break (Ljava/awt/GraphicsDevice;Lorg/lwjgl/opengl/PixelFormat;)Ljava/awt/GraphicsConfiguration; 3
L12:    invokespecial Method java/awt/Canvas <init> (Ljava/awt/GraphicsConfiguration;)V
L15:    new java/lang/Object
L18:    aload_0
L19:    dup_x1
L20:    dup
L21:    pop2
L22:    dup
L23:    invokespecial Method java/lang/Object <init> ()V
L26:    putfield Field org/lwjgl/opengl/aB void Ljava/lang/Object;
L29:    ifnonnull L42
L32:    new java/lang/NullPointerException
L35:    dup
L36:    ldc "Pixel format must be non-null"
L38:    invokespecial Method java/lang/NullPointerException <init> (Ljava/lang/String;)V
L41:    athrow
L42:    aload_0
L43:    aload 4
L45:    aload_2
L46:    aload_0
L47:    dup_x1
L48:    aload_3
L49:    aload_0
L50:    dup
L51:    dup2
L52:    invokevirtual Method org/lwjgl/opengl/aB addHierarchyListener (Ljava/awt/event/HierarchyListener;)V
L55:    invokevirtual Method org/lwjgl/opengl/aB addComponentListener (Ljava/awt/event/ComponentListener;)V
L58:    putfield Field org/lwjgl/opengl/aB else Lorg/lwjgl/opengl/k;
L61:    putfield Field org/lwjgl/opengl/aB long Lorg/lwjgl/opengl/PixelFormat;
L64:    putfield Field org/lwjgl/opengl/aB "enum" Lorg/lwjgl/opengl/CB;
L67:    return
L68:    
        .attribute StackMap b'\x00\x01\x00\x2A\x00\x05\x07\x00\x02\x07\x00\x77\x07\x00\x79\x07\x00\x7B\x07\x00\x7D\x00\x00'
    .end code
    .exceptions org/lwjgl/LWJGLException
.end method

.method public <init> : ()V
    .code stack 4 locals 1
L0:     new org/lwjgl/opengl/PixelFormat
L3:     aload_0
L4:     dup_x1
L5:     dup
L6:     pop2
L7:     dup
L8:     invokespecial Method org/lwjgl/opengl/PixelFormat <init> ()V
L11:    invokespecial Method org/lwjgl/opengl/aB <init> (Lorg/lwjgl/opengl/PixelFormat;)V
L14:    return
L15:    
    .end code
    .exceptions org/lwjgl/LWJGLException
.end method

.method public bridge synthetic for : ()Lorg/lwjgl/opengl/G;
    .code stack 1 locals 1
L0:     aload_0
L1:     invokevirtual Method org/lwjgl/opengl/aB try ()Lorg/lwjgl/opengl/Jb;
L4:     areturn
L5:     
    .end code
    .exceptions org/lwjgl/LWJGLException
.end method

.method public break : (Z)V
    .code stack 4 locals 2
L0:     aload_0
L1:     iload_1
L2:     ifeq L13
L5:     iconst_1
L6:     dup
L7:     dup
L8:     pop2
L9:     goto L17
L12:    athrow
L13:    iconst_0
L14:    iconst_1
L15:    dup
L16:    pop2
L17:    invokevirtual Method org/lwjgl/opengl/aB break (I)V
L20:    return
L21:    
        .attribute StackMap b'\x00\x03\x00\x0C\x00\x00\x00\x01\x07\x00\x3D\x00\x0D\x00\x02\x07\x00\x02\x01\x00\x01\x07\x00\x02\x00\x11\x00\x02\x07\x00\x02\x01\x00\x02\x07\x00\x02\x01'
    .end code
.end method

.method public else : ()V
    .code stack 3 locals 3
L0:     aload_0
L1:     getfield Field org/lwjgl/opengl/aB void Ljava/lang/Object;
L4:     dup
L5:     astore_1
L6:     monitorenter
        .catch [0] from L7 to L43 using L45
L7:     aload_0
L8:     getfield Field org/lwjgl/opengl/aB new Lorg/lwjgl/opengl/Jb;
L11:    ifnonnull L24
L14:    new java/lang/IllegalStateException
L17:    dup
L18:    ldc "Canvas not yet displayable"
L20:    invokespecial Method java/lang/IllegalStateException <init> (Ljava/lang/String;)V
L23:    athrow
L24:    aload_0
L25:    getfield Field org/lwjgl/opengl/aB new Lorg/lwjgl/opengl/Jb;
L28:    invokevirtual Method org/lwjgl/opengl/Jb else ()Z
L31:    ifeq L41
L34:    aload_0
L35:    getfield Field org/lwjgl/opengl/aB new Lorg/lwjgl/opengl/Jb;
L38:    invokevirtual Method org/lwjgl/opengl/Jb short ()V
L41:    aload_1
L42:    monitorexit
L43:    return
L44:    athrow
        .catch [0] from L45 to L48 using L45
L45:    astore_2
L46:    aload_1
L47:    monitorexit
L48:    aload_2
L49:    athrow
L50:    athrow
L51:    
        .attribute StackMap b'\x00\x05\x00\x18\x00\x02\x07\x00\x02\x07\x00\x3F\x00\x00\x00\x29\x00\x02\x07\x00\x02\x07\x00\x3F\x00\x00\x00\x2C\x00\x00\x00\x01\x07\x00\x3D\x00\x2D\x00\x02\x07\x00\x02\x07\x00\x3F\x00\x01\x07\x00\x3D\x00\x32\x00\x00\x00\x01\x07\x00\x3D'
    .end code
    .exceptions org/lwjgl/LWJGLException
.end method

.method public goto : ()Lorg/lwjgl/opengl/h;
    .code stack 1 locals 1
L0:     aload_0
L1:     getfield Field org/lwjgl/opengl/aB long Lorg/lwjgl/opengl/PixelFormat;
L4:     areturn
L5:     
    .end code
.end method

.method public break : (I)V
    .code stack 3 locals 4
L0:     aload_0
L1:     getfield Field org/lwjgl/opengl/aB void Ljava/lang/Object;
L4:     dup
L5:     astore_2
L6:     monitorenter
        .catch [0] from L7 to L30 using L32
L7:     aload_0
L8:     getfield Field org/lwjgl/opengl/aB new Lorg/lwjgl/opengl/Jb;
L11:    ifnonnull L24
L14:    new java/lang/IllegalStateException
L17:    dup
L18:    ldc "Canvas not yet displayable"
L20:    invokespecial Method java/lang/IllegalStateException <init> (Ljava/lang/String;)V
L23:    athrow
L24:    iload_1
L25:    invokestatic Method org/lwjgl/opengl/Jb break (I)V
L28:    aload_2
L29:    monitorexit
L30:    return
L31:    athrow
        .catch [0] from L32 to L35 using L32
L32:    astore_3
L33:    aload_2
L34:    monitorexit
L35:    aload_3
L36:    athrow
L37:    athrow
L38:    
        .attribute StackMap b'\x00\x04\x00\x18\x00\x03\x07\x00\x02\x01\x07\x00\x3F\x00\x00\x00\x1F\x00\x00\x00\x01\x07\x00\x3D\x00\x20\x00\x03\x07\x00\x02\x01\x07\x00\x3F\x00\x01\x07\x00\x3D\x00\x25\x00\x00\x00\x01\x07\x00\x3D'
    .end code
.end method

.method public final break : (Lorg/lwjgl/h;)V
    .code stack 3 locals 4
L0:     aload_0
L1:     getfield Field org/lwjgl/opengl/aB void Ljava/lang/Object;
L4:     dup
L5:     astore_2
L6:     monitorenter
        .catch [0] from L7 to L34 using L36
L7:     aload_0
L8:     getfield Field org/lwjgl/opengl/aB new Lorg/lwjgl/opengl/Jb;
L11:    ifnonnull L24
L14:    new java/lang/IllegalStateException
L17:    dup
L18:    ldc "Canvas not yet displayable"
L20:    invokespecial Method java/lang/IllegalStateException <init> (Ljava/lang/String;)V
L23:    athrow
L24:    aload_0
L25:    getfield Field org/lwjgl/opengl/aB new Lorg/lwjgl/opengl/Jb;
L28:    aload_1
L29:    invokevirtual Method org/lwjgl/opengl/Jb break (Lorg/lwjgl/h;)V
L32:    aload_2
L33:    monitorexit
L34:    return
L35:    athrow
        .catch [0] from L36 to L39 using L36
L36:    astore_3
L37:    aload_2
L38:    monitorexit
L39:    aload_3
L40:    athrow
L41:    athrow
L42:    
        .attribute StackMap b'\x00\x04\x00\x18\x00\x03\x07\x00\x02\x07\x00\x9D\x07\x00\x3F\x00\x00\x00\x23\x00\x00\x00\x01\x07\x00\x3D\x00\x24\x00\x03\x07\x00\x02\x07\x00\x9D\x07\x00\x3F\x00\x01\x07\x00\x3D\x00\x29\x00\x00\x00\x01\x07\x00\x3D'
    .end code
    .exceptions org/lwjgl/LWJGLException
.end method

.method public setBounds : (IIII)V
    .code stack 6 locals 5
L0:     aload_0
L1:     dup
L2:     iload_1
L3:     iload_2
L4:     iload_3
L5:     iload 4
L7:     invokespecial Method java/awt/Canvas setBounds (IIII)V
L10:    invokespecial Method org/lwjgl/opengl/aB if ()V
L13:    return
L14:    
    .end code
.end method

.method public break : (FFF)V
    .code stack 4 locals 4
L0:     fload_1
L1:     fload_2
L2:     fload_3
L3:     fconst_0
L4:     invokestatic Method org/lwjgl/opengl/GL11 break (FFFF)V
L7:     sipush 16384
L10:    iconst_1
L11:    dup
L12:    pop2
L13:    invokestatic Method org/lwjgl/opengl/GL11 new (I)V
L16:    return
L17:    
    .end code
.end method

.method public catch : ()V
    .code stack 0 locals 1
L0:     invokestatic Method org/lwjgl/opengl/n break ()V
L3:     return
L4:     
    .end code
.end method

.method public update : (Ljava/awt/Graphics;)V
    .code stack 2 locals 2
L0:     aload_0
L1:     aload_1
L2:     invokevirtual Method org/lwjgl/opengl/aB paint (Ljava/awt/Graphics;)V
L5:     return
L6:     
    .end code
.end method

.method public final short : ()V
    .code stack 8 locals 4
L0:     aload_0
L1:     getfield Field org/lwjgl/opengl/aB void Ljava/lang/Object;
L4:     dup
L5:     astore_1
L6:     monitorenter
        .catch org/lwjgl/LWJGLException from L7 to L46 using L50
        .catch [0] from L7 to L49 using L64
L7:     aload_0
L8:     getfield Field org/lwjgl/opengl/aB new Lorg/lwjgl/opengl/Jb;
L11:    ifnull L60
L14:    aconst_null
L15:    aload_0
L16:    dup
L17:    dup_x2
L18:    iconst_0
L19:    aconst_null
L20:    aload_0
L21:    dup_x1
L22:    getfield Field org/lwjgl/opengl/aB new Lorg/lwjgl/opengl/Jb;
L25:    invokevirtual Method org/lwjgl/opengl/Jb goto ()V
L28:    putfield Field org/lwjgl/opengl/aB new Lorg/lwjgl/opengl/Jb;
L31:    iconst_1
L32:    dup
L33:    pop2
L34:    putfield Field org/lwjgl/opengl/aB do I
L37:    getfield Field org/lwjgl/opengl/aB try Lorg/lwjgl/opengl/a;
L40:    invokevirtual Method org/lwjgl/opengl/a short ()V
L43:    putfield Field org/lwjgl/opengl/aB try Lorg/lwjgl/opengl/a;
L46:    goto L60
L49:    athrow
        .catch [0] from L50 to L62 using L64
L50:    astore_2
L51:    new java/lang/RuntimeException
L54:    dup
L55:    aload_2
L56:    invokespecial Method java/lang/RuntimeException <init> (Ljava/lang/Throwable;)V
L59:    athrow
L60:    aload_1
L61:    monitorexit
L62:    return
L63:    athrow
        .catch [0] from L64 to L67 using L64
L64:    astore_3
L65:    aload_1
L66:    monitorexit
L67:    aload_3
L68:    athrow
L69:    athrow
L70:    
        .attribute StackMap b'\x00\x06\x00\x31\x00\x00\x00\x01\x07\x00\x3D\x00\x32\x00\x02\x07\x00\x02\x07\x00\x3F\x00\x01\x07\x00\x42\x00\x3C\x00\x02\x07\x00\x02\x07\x00\x3F\x00\x00\x00\x3F\x00\x00\x00\x01\x07\x00\x3D\x00\x40\x00\x02\x07\x00\x02\x07\x00\x3F\x00\x01\x07\x00\x3D\x00\x45\x00\x00\x00\x01\x07\x00\x3D'
    .end code
.end method

.method public componentMoved : (Ljava/awt/event/ComponentEvent;)V
    .code stack 1 locals 2
L0:     aload_0
L1:     invokespecial Method org/lwjgl/opengl/aB if ()V
L4:     return
L5:     
    .end code
.end method

.method public new : ()Lorg/lwjgl/opengl/Jb;
    .code stack 1 locals 1
L0:     aload_0
L1:     getfield Field org/lwjgl/opengl/aB new Lorg/lwjgl/opengl/Jb;
L4:     areturn
L5:     
    .end code
.end method

.method public break : ()V
    .code stack 3 locals 3
L0:     aload_0
L1:     getfield Field org/lwjgl/opengl/aB void Ljava/lang/Object;
L4:     dup
L5:     astore_1
L6:     monitorenter
        .catch [0] from L7 to L33 using L35
L7:     aload_0
L8:     getfield Field org/lwjgl/opengl/aB new Lorg/lwjgl/opengl/Jb;
L11:    ifnonnull L24
L14:    new java/lang/IllegalStateException
L17:    dup
L18:    ldc "Canvas not yet displayable"
L20:    invokespecial Method java/lang/IllegalStateException <init> (Ljava/lang/String;)V
L23:    athrow
L24:    aload_0
L25:    getfield Field org/lwjgl/opengl/aB new Lorg/lwjgl/opengl/Jb;
L28:    invokevirtual Method org/lwjgl/opengl/Jb const ()V
L31:    aload_1
L32:    monitorexit
L33:    return
L34:    athrow
        .catch [0] from L35 to L38 using L35
L35:    astore_2
L36:    aload_1
L37:    monitorexit
L38:    aload_2
L39:    athrow
L40:    athrow
L41:    
        .attribute StackMap b'\x00\x04\x00\x18\x00\x02\x07\x00\x02\x07\x00\x3F\x00\x00\x00\x22\x00\x00\x00\x01\x07\x00\x3D\x00\x23\x00\x02\x07\x00\x02\x07\x00\x3F\x00\x01\x07\x00\x3D\x00\x28\x00\x00\x00\x01\x07\x00\x3D'
    .end code
    .exceptions org/lwjgl/LWJGLException
.end method

.method public try : ()Lorg/lwjgl/opengl/Jb;
    .code stack 5 locals 3
L0:     aload_0
L1:     getfield Field org/lwjgl/opengl/aB void Ljava/lang/Object;
L4:     dup
L5:     astore_1
L6:     monitorenter
        .catch [0] from L7 to L49 using L51
L7:     aload_0
L8:     getfield Field org/lwjgl/opengl/aB new Lorg/lwjgl/opengl/Jb;
L11:    ifnonnull L24
L14:    new java/lang/IllegalStateException
L17:    dup
L18:    ldc "Canvas not yet displayable"
L20:    invokespecial Method java/lang/IllegalStateException <init> (Ljava/lang/String;)V
L23:    athrow
L24:    new org/lwjgl/opengl/Jb
L27:    dup
L28:    aload_0
L29:    dup
L30:    getfield Field org/lwjgl/opengl/aB try Lorg/lwjgl/opengl/a;
L33:    swap
L34:    getfield Field org/lwjgl/opengl/aB new Lorg/lwjgl/opengl/Jb;
L37:    invokevirtual Method org/lwjgl/opengl/Jb this ()Lorg/lwjgl/opengl/CB;
L40:    aload_0
L41:    getfield Field org/lwjgl/opengl/aB new Lorg/lwjgl/opengl/Jb;
L44:    invokespecial Method org/lwjgl/opengl/Jb <init> (Lorg/lwjgl/opengl/a;Lorg/lwjgl/opengl/CB;Lorg/lwjgl/opengl/Jb;)V
L47:    aload_1
L48:    monitorexit
L49:    areturn
L50:    athrow
        .catch [0] from L51 to L54 using L51
L51:    astore_2
L52:    aload_1
L53:    monitorexit
L54:    aload_2
L55:    athrow
L56:    
        .attribute StackMap b'\x00\x03\x00\x18\x00\x02\x07\x00\x02\x07\x00\x3F\x00\x00\x00\x32\x00\x00\x00\x01\x07\x00\x3D\x00\x33\x00\x02\x07\x00\x02\x07\x00\x3F\x00\x01\x07\x00\x3D'
    .end code
    .exceptions org/lwjgl/LWJGLException
.end method

.method public setSize : (Ljava/awt/Dimension;)V
    .code stack 3 locals 2
L0:     aload_0
L1:     dup
L2:     aload_1
L3:     invokespecial Method java/awt/Canvas setSize (Ljava/awt/Dimension;)V
L6:     invokespecial Method org/lwjgl/opengl/aB if ()V
L9:     return
L10:    
    .end code
.end method

.method public break : (Lorg/lwjgl/opengl/h;Lorg/lwjgl/opengl/CB;)V
    .code stack 2 locals 3
L0:     new java/lang/UnsupportedOperationException
L3:     dup
L4:     invokespecial Method java/lang/UnsupportedOperationException <init> ()V
L7:     athrow
L8:     
    .end code
    .exceptions org/lwjgl/LWJGLException
.end method

.method public componentResized : (Ljava/awt/event/ComponentEvent;)V
    .code stack 1 locals 2
L0:     aload_0
L1:     invokespecial Method org/lwjgl/opengl/aB if ()V
L4:     return
L5:     
    .end code
.end method

.method public final paint : (Ljava/awt/Graphics;)V
    .code stack 6 locals 6
L0:     aconst_null
L1:     astore_1
L2:     aload_0
L3:     getfield Field org/lwjgl/opengl/aB void Ljava/lang/Object;
L6:     dup
L7:     astore_2
L8:     monitorenter
L9:     aload_0
L10:    invokevirtual Method org/lwjgl/opengl/aB isDisplayable ()Z
L13:    ifne L20
L16:    aload_2
L17:    monitorexit
L18:    return
L19:    athrow
L20:    aload_0
L21:    getfield Field org/lwjgl/opengl/aB try Lorg/lwjgl/opengl/a;
L24:    ifnonnull L48
L27:    getstatic Field org/lwjgl/opengl/aB char Lorg/lwjgl/opengl/e;
L30:    aload_0
L31:    dup
L32:    dup_x2
L33:    getfield Field org/lwjgl/opengl/aB long Lorg/lwjgl/opengl/PixelFormat;
L36:    aload_0
L37:    getfield Field org/lwjgl/opengl/aB "enum" Lorg/lwjgl/opengl/CB;
L40:    invokeinterface InterfaceMethod org/lwjgl/opengl/e break (Ljava/awt/Canvas;Lorg/lwjgl/opengl/PixelFormat;Lorg/lwjgl/opengl/CB;)Lorg/lwjgl/opengl/a; 4
L45:    putfield Field org/lwjgl/opengl/aB try Lorg/lwjgl/opengl/a;
L48:    aload_0
L49:    getfield Field org/lwjgl/opengl/aB try Lorg/lwjgl/opengl/a;
L52:    invokevirtual Method org/lwjgl/opengl/a break ()Ljava/nio/ByteBuffer;
L55:    pop
L56:    aload_0
L57:    getfield Field org/lwjgl/opengl/aB new Lorg/lwjgl/opengl/Jb;
L60:    ifnonnull L121
L63:    new org/lwjgl/opengl/Jb
L66:    aload_0
L67:    dup
L68:    pop2
L69:    dup
L70:    aload_0
L71:    dup_x2
L72:    getfield Field org/lwjgl/opengl/aB try Lorg/lwjgl/opengl/a;
L75:    aload_0
L76:    dup
L77:    getfield Field org/lwjgl/opengl/aB "enum" Lorg/lwjgl/opengl/CB;
L80:    swap
L81:    getfield Field org/lwjgl/opengl/aB else Lorg/lwjgl/opengl/k;
L84:    ifnull L106
L87:    aload_0
L88:    getfield Field org/lwjgl/opengl/aB else Lorg/lwjgl/opengl/k;
L91:    checkcast org/lwjgl/opengl/C
L94:    invokeinterface InterfaceMethod org/lwjgl/opengl/C do ()Lorg/lwjgl/opengl/G; 1
L99:    checkcast org/lwjgl/opengl/Jb
L102:   goto L107
L105:   athrow
L106:   aconst_null
L107:   invokespecial Method org/lwjgl/opengl/Jb <init> (Lorg/lwjgl/opengl/a;Lorg/lwjgl/opengl/CB;Lorg/lwjgl/opengl/Jb;)V
L110:   putfield Field org/lwjgl/opengl/aB new Lorg/lwjgl/opengl/Jb;
L113:   aload_0
L114:   iconst_1
L115:   dup
L116:   dup
L117:   pop2
L118:   putfield Field org/lwjgl/opengl/aB this Z
L121:   aload_0
L122:   getfield Field org/lwjgl/opengl/aB do I
L125:   ifne L135
L128:   aload_0
L129:   getfield Field org/lwjgl/opengl/aB new Lorg/lwjgl/opengl/Jb;
L132:   invokevirtual Method org/lwjgl/opengl/Jb const ()V
L135:   aload_0
L136:   dup
L137:   getfield Field org/lwjgl/opengl/aB do I
L140:   iconst_1
L141:   dup
L142:   dup
L143:   pop2
L144:   iadd
L145:   putfield Field org/lwjgl/opengl/aB do I
        .catch [0] from L148 to L193 using L224
L148:   aload_0
L149:   getfield Field org/lwjgl/opengl/aB null Z
L152:   ifeq L170
L155:   iconst_0
L156:   aload_0
L157:   dup_x1
L158:   getfield Field org/lwjgl/opengl/aB new Lorg/lwjgl/opengl/Jb;
L161:   invokevirtual Method org/lwjgl/opengl/Jb long ()V
L164:   iconst_1
L165:   dup
L166:   pop2
L167:   putfield Field org/lwjgl/opengl/aB null Z
L170:   aload_0
L171:   getfield Field org/lwjgl/opengl/aB this Z
L174:   ifeq L189
L177:   aload_0
L178:   dup
L179:   iconst_0
L180:   iconst_1
L181:   dup
L182:   pop2
L183:   putfield Field org/lwjgl/opengl/aB this Z
L186:   invokevirtual Method org/lwjgl/opengl/aB class ()V
L189:   aload_0
L190:   invokevirtual Method org/lwjgl/opengl/aB char ()V
L193:   aload_0
L194:   dup
L195:   dup
L196:   getfield Field org/lwjgl/opengl/aB do I
L199:   iconst_1
L200:   dup
L201:   dup
L202:   pop2
L203:   isub
L204:   putfield Field org/lwjgl/opengl/aB do I
L207:   getfield Field org/lwjgl/opengl/aB do I
L210:   ifne L254
L213:   aload_0
L214:   dup
L215:   getfield Field org/lwjgl/opengl/aB new Lorg/lwjgl/opengl/Jb;
L218:   invokevirtual Method org/lwjgl/opengl/Jb short ()V
L221:   goto L255
        .catch [0] from L224 to L225 using L224
        .catch [0] from L56 to L105 using L264
        .catch [0] from L106 to L254 using L264
L224:   astore_3
L225:   aload_0
L226:   dup
L227:   dup
L228:   getfield Field org/lwjgl/opengl/aB do I
L231:   iconst_1
L232:   dup
L233:   dup
L234:   pop2
L235:   isub
L236:   putfield Field org/lwjgl/opengl/aB do I
L239:   getfield Field org/lwjgl/opengl/aB do I
L242:   ifne L252
L245:   aload_0
L246:   getfield Field org/lwjgl/opengl/aB new Lorg/lwjgl/opengl/Jb;
L249:   invokevirtual Method org/lwjgl/opengl/Jb short ()V
L252:   aload_3
L253:   athrow
L254:   aload_0
L255:   getfield Field org/lwjgl/opengl/aB try Lorg/lwjgl/opengl/a;
L258:   invokevirtual Method org/lwjgl/opengl/a for ()V
L261:   goto L282
        .catch [0] from L264 to L266 using L264
        .catch org/lwjgl/LWJGLException from L20 to L105 using L279
        .catch org/lwjgl/LWJGLException from L106 to L276 using L279
        .catch [0] from L9 to L18 using L288
        .catch [0] from L20 to L105 using L288
        .catch [0] from L106 to L276 using L288
L264:   astore 4
L266:   aload 4
L268:   aload_0
L269:   getfield Field org/lwjgl/opengl/aB try Lorg/lwjgl/opengl/a;
L272:   invokevirtual Method org/lwjgl/opengl/a for ()V
L275:   athrow
L276:   nop
L277:   nop
L278:   athrow
        .catch [0] from L279 to L284 using L288
L279:   astore_3
L280:   aload_3
L281:   astore_1
L282:   aload_2
L283:   monitorexit
L284:   aload_1
L285:   goto L296
        .catch [0] from L288 to L292 using L288
L288:   astore 5
L290:   aload_2
L291:   monitorexit
L292:   aload 5
L294:   athrow
L295:   athrow
L296:   ifnull L304
L299:   aload_0
L300:   aload_1
L301:   invokevirtual Method org/lwjgl/opengl/aB break (Lorg/lwjgl/LWJGLException;)V
L304:   return
L305:   
        .attribute StackMap b'\x00\x16\x00\x13\x00\x00\x00\x01\x07\x00\x3D\x00\x14\x00\x03\x07\x00\x02\x05\x07\x00\x3F\x00\x00\x00\x30\x00\x03\x07\x00\x02\x05\x07\x00\x3F\x00\x00\x00\x69\x00\x00\x00\x01\x07\x00\x3D\x00\x6A\x00\x03\x07\x00\x02\x05\x07\x00\x3F\x00\x05\x07\x00\x02\x08\x00\x3F\x08\x00\x3F\x07\x00\xBD\x07\x00\x7D\x00\x6B\x00\x03\x07\x00\x02\x05\x07\x00\x3F\x00\x06\x07\x00\x02\x08\x00\x3F\x08\x00\x3F\x07\x00\xBD\x07\x00\x7D\x07\x00\x4E\x00\x79\x00\x03\x07\x00\x02\x05\x07\x00\x3F\x00\x00\x00\x87\x00\x03\x07\x00\x02\x05\x07\x00\x3F\x00\x00\x00\xAA\x00\x03\x07\x00\x02\x05\x07\x00\x3F\x00\x00\x00\xBD\x00\x03\x07\x00\x02\x05\x07\x00\x3F\x00\x00\x00\xE0\x00\x03\x07\x00\x02\x05\x07\x00\x3F\x00\x01\x07\x00\x3D\x00\xFC\x00\x04\x07\x00\x02\x05\x07\x00\x3F\x07\x00\x3D\x00\x00\x00\xFE\x00\x03\x07\x00\x02\x05\x07\x00\x3F\x00\x00\x00\xFF\x00\x03\x07\x00\x02\x05\x07\x00\x3F\x00\x01\x07\x00\x02\x01\x08\x00\x03\x07\x00\x02\x05\x07\x00\x3F\x00\x01\x07\x00\x3D\x01\x14\x00\x00\x00\x01\x07\x00\x3D\x01\x17\x00\x03\x07\x00\x02\x05\x07\x00\x3F\x00\x01\x07\x00\x42\x01\x1A\x00\x03\x07\x00\x02\x07\x00\x42\x07\x00\x3F\x00\x00\x01\x20\x00\x03\x07\x00\x02\x07\x00\x42\x07\x00\x3F\x00\x01\x07\x00\x3D\x01\x27\x00\x00\x00\x01\x07\x00\x3D\x01\x28\x00\x03\x07\x00\x02\x07\x00\x42\x07\x00\x3F\x00\x01\x07\x00\x42\x01\x30\x00\x03\x07\x00\x02\x07\x00\x42\x07\x00\x3F\x00\x00'
    .end code
.end method

.method static this : ()Lorg/lwjgl/opengl/e;
    .code stack 3 locals 0
L0:     invokestatic Method org/lwjgl/LWJGLUtil getPlatform ()I
L3:     tableswitch 1
            L28
            L50
            L41
            default : L58
L28:    new org/lwjgl/opengl/LinuxCanvasImplementation
L31:    iconst_0
L32:    ifne L31
L35:    dup
L36:    invokespecial Method org/lwjgl/opengl/LinuxCanvasImplementation <init> ()V
L39:    areturn
L40:    athrow
L41:    new org/lwjgl/opengl/H
L44:    dup
L45:    invokespecial Method org/lwjgl/opengl/H <init> ()V
L48:    areturn
L49:    athrow
L50:    new org/lwjgl/opengl/ZA
L53:    dup
L54:    invokespecial Method org/lwjgl/opengl/ZA <init> ()V
L57:    areturn
L58:    new java/lang/IllegalStateException
L61:    dup
L62:    ldc "Unsupported platform"
L64:    invokespecial Method java/lang/IllegalStateException <init> (Ljava/lang/String;)V
L67:    athrow
L68:    
        .attribute StackMap b'\x00\x07\x00\x1C\x00\x00\x00\x00\x00\x1F\x00\x00\x00\x01\x08\x00\x1C\x00\x28\x00\x00\x00\x01\x07\x00\x3D\x00\x29\x00\x00\x00\x00\x00\x31\x00\x00\x00\x01\x07\x00\x3D\x00\x32\x00\x00\x00\x00\x00\x3A\x00\x00\x00\x00'
    .end code
.end method

.method public <init> : (Lorg/lwjgl/opengl/PixelFormat;)V
    .code stack 3 locals 2
L0:     aload_0
L1:     invokestatic Method java/awt/GraphicsEnvironment getLocalGraphicsEnvironment ()Ljava/awt/GraphicsEnvironment;
L4:     invokevirtual Method java/awt/GraphicsEnvironment getDefaultScreenDevice ()Ljava/awt/GraphicsDevice;
L7:     aload_1
L8:     invokespecial Method org/lwjgl/opengl/aB <init> (Ljava/awt/GraphicsDevice;Lorg/lwjgl/opengl/PixelFormat;)V
L11:    return
L12:    
    .end code
    .exceptions org/lwjgl/LWJGLException
.end method

.method static <clinit> : ()V
    .code stack 1 locals 0
L0:     invokestatic Method org/lwjgl/Sys short ()V
L3:     invokestatic Method org/lwjgl/opengl/aB this ()Lorg/lwjgl/opengl/e;
L6:     putstatic Field org/lwjgl/opengl/aB char Lorg/lwjgl/opengl/e;
L9:     return
L10:    
    .end code
.end method

.method public <init> : (Ljava/awt/GraphicsDevice;Lorg/lwjgl/opengl/PixelFormat;Lorg/lwjgl/opengl/k;)V
    .code stack 5 locals 4
L0:     aload_0
L1:     aload_1
L2:     aload_2
L3:     aload_3
L4:     aconst_null
L5:     invokespecial Method org/lwjgl/opengl/aB <init> (Ljava/awt/GraphicsDevice;Lorg/lwjgl/opengl/PixelFormat;Lorg/lwjgl/opengl/k;Lorg/lwjgl/opengl/CB;)V
L8:     return
L9:     
    .end code
    .exceptions org/lwjgl/LWJGLException
.end method

.method public <init> : (Ljava/awt/GraphicsDevice;Lorg/lwjgl/opengl/PixelFormat;)V
    .code stack 4 locals 3
L0:     aload_0
L1:     aload_1
L2:     aload_2
L3:     aconst_null
L4:     invokespecial Method org/lwjgl/opengl/aB <init> (Ljava/awt/GraphicsDevice;Lorg/lwjgl/opengl/PixelFormat;Lorg/lwjgl/opengl/k;)V
L7:     return
L8:     
    .end code
    .exceptions org/lwjgl/LWJGLException
.end method

.method protected break : (Lorg/lwjgl/LWJGLException;)V
    .code stack 3 locals 2
L0:     new java/lang/StringBuilder
L3:     dup
L4:     invokespecial Method java/lang/StringBuilder <init> ()V
L7:     iconst_0
L8:     ldc_w "Unhandled exception occurred, skipping paint(): "
L11:    invokevirtual Method java/lang/StringBuilder insert (ILjava/lang/String;)Ljava/lang/StringBuilder;
L14:    aload_1
L15:    invokevirtual Method java/lang/StringBuilder append (Ljava/lang/Object;)Ljava/lang/StringBuilder;
L18:    invokevirtual Method java/lang/StringBuilder toString ()Ljava/lang/String;
L21:    invokestatic Method org/lwjgl/LWJGLUtil log (Ljava/lang/CharSequence;)V
L24:    return
L25:    
    .end code
.end method
.end class
