.version 49 0
.class public final super org/lwjgl/opengl/ARBShaderObjects
.super java/lang/Object
.field public static final instanceof I = 35720
.field public static final "protected" I = 35682
.field public static final import I = 35665
.field public static final "native" I = 35680
.field public static final throws I = 35678
.field public static final "static" I = 35667
.field public static final continue I = 35675
.field public static final extends I = 35666
.field public static final float I = 35669
.field public static final "final" I = 35717
.field public static final catch I = 35662
.field public static final false I = 35648
.field public static final class I = 35716
.field public static final if I = 35684
.field public static final true I = 35671
.field public static final for I = 35714
.field public static final case I = 35656
.field public static final byte I = 35677
.field public static final "super" I = 35679
.field public static final int I = 35712
.field public static final short I = 35715
.field public static final goto I = 35674
.field public static final break I = 35676
.field public static final long I = 35713
.field public static final void I = 35681
.field public static final try I = 35683
.field public static final const I = 35672
.field public static final new I = 35664
.field public static final null I = 35670
.field public static final this I = 35668
.field public static final char I = 35719
.field public static final else I = 35673
.field public static final "enum" I = 35718
.field public static final do I = 35663

.method static native nglDetachObjectARB : (IIJ)V
.end method

.method public static break : (IIIII)V
    .code stack 7 locals 7
L0:     invokestatic Method org/lwjgl/opengl/GLContext break ()Lorg/lwjgl/opengl/kb;
L3:     getfield Field org/lwjgl/opengl/kb ct J
L6:     dup2
L7:     lstore 5
L9:     invokestatic Method org/lwjgl/l break (J)V
L12:    iload_0
L13:    iload_1
L14:    iload_2
L15:    iload_3
L16:    iload 4
L18:    lload 5
L20:    invokestatic Method org/lwjgl/opengl/ARBShaderObjects nglUniform4iARB (IIIIIJ)V
L23:    return
L24:    
    .end code
.end method

.method public static for : (I)V
    .code stack 4 locals 3
L0:     invokestatic Method org/lwjgl/opengl/GLContext break ()Lorg/lwjgl/opengl/kb;
L3:     getfield Field org/lwjgl/opengl/kb eI J
L6:     dup2
L7:     lstore_1
L8:     invokestatic Method org/lwjgl/l break (J)V
L11:    iload_0
L12:    lload_1
L13:    invokestatic Method org/lwjgl/opengl/ARBShaderObjects nglLinkProgramARB (IJ)V
L16:    return
L17:    
    .end code
.end method

.method public static goto : (II)V
    .code stack 4 locals 4
L0:     invokestatic Method org/lwjgl/opengl/GLContext break ()Lorg/lwjgl/opengl/kb;
L3:     getfield Field org/lwjgl/opengl/kb QD J
L6:     dup2
L7:     lstore_2
L8:     invokestatic Method org/lwjgl/l break (J)V
L11:    iload_0
L12:    iload_1
L13:    lload_2
L14:    invokestatic Method org/lwjgl/opengl/ARBShaderObjects nglUniform1iARB (IIJ)V
L17:    return
L18:    
    .end code
.end method

.method public static break : (IIII)V
    .code stack 6 locals 6
L0:     invokestatic Method org/lwjgl/opengl/GLContext break ()Lorg/lwjgl/opengl/kb;
L3:     getfield Field org/lwjgl/opengl/kb NO J
L6:     dup2
L7:     lstore 4
L9:     invokestatic Method org/lwjgl/l break (J)V
L12:    iload_0
L13:    iload_1
L14:    iload_2
L15:    iload_3
L16:    lload 4
L18:    invokestatic Method org/lwjgl/opengl/ARBShaderObjects nglUniform3iARB (IIIIJ)V
L21:    return
L22:    
    .end code
.end method

.method static native nglUniform1ivARB : (IIJJ)V
.end method

.method static native nglUniformMatrix3fvARB : (IIZJJ)V
.end method

.method public static else : (ILjava/nio/ByteBuffer;)V
    .code stack 7 locals 4
L0:     invokestatic Method org/lwjgl/opengl/GLContext break ()Lorg/lwjgl/opengl/kb;
L3:     getfield Field org/lwjgl/opengl/kb aS J
L6:     dup2
L7:     lstore_2
L8:     invokestatic Method org/lwjgl/l break (J)V
L11:    iload_0
L12:    aload_1
L13:    invokestatic Method org/lwjgl/l break (Ljava/nio/ByteBuffer;)V
L16:    iconst_1
L17:    dup
L18:    dup
L19:    pop2
L20:    aload_1
L21:    invokestatic Method org/lwjgl/MemoryUtil const (Ljava/nio/ByteBuffer;)J
L24:    aload_1
L25:    invokevirtual Method java/nio/ByteBuffer remaining ()I
L28:    lload_2
L29:    invokestatic Method org/lwjgl/opengl/ARBShaderObjects nglShaderSourceARB (IIJIJ)V
L32:    return
L33:    
    .end code
.end method

.method static native nglGetUniformivARB : (IIJJ)V
.end method

.method static native nglUniform3ivARB : (IIJJ)V
.end method

.method public static do : (II)I
    .code stack 13 locals 6
L0:     invokestatic Method org/lwjgl/opengl/GLContext break ()Lorg/lwjgl/opengl/kb;
L3:     dup
L4:     astore_2
L5:     dup
L6:     getfield Field org/lwjgl/opengl/kb tf J
L9:     dup2
L10:    lstore_3
L11:    invokestatic Method org/lwjgl/l break (J)V
L14:    invokestatic Method org/lwjgl/opengl/bB short (Lorg/lwjgl/opengl/kb;)Ljava/nio/IntBuffer;
L17:    astore 5
L19:    iload_0
L20:    iload_1
L21:    iconst_0
L22:    iconst_1
L23:    dup
L24:    pop2
L25:    lconst_0
L26:    aload 5
L28:    invokestatic Method org/lwjgl/MemoryUtil break (Ljava/nio/IntBuffer;)J
L31:    aload 5
L33:    iconst_1
L34:    dup
L35:    dup
L36:    pop2
L37:    invokestatic Method org/lwjgl/MemoryUtil break (Ljava/nio/IntBuffer;I)J
L40:    aload_2
L41:    invokestatic Method org/lwjgl/opengl/bB catch (Lorg/lwjgl/opengl/kb;)J
L44:    lload_3
L45:    invokestatic Method org/lwjgl/opengl/ARBShaderObjects nglGetActiveUniformARB (IIIJJJJJ)V
L48:    aload 5
L50:    iconst_0
L51:    iconst_1
L52:    dup
L53:    pop2
L54:    invokevirtual Method java/nio/IntBuffer get (I)I
L57:    ireturn
L58:    
    .end code
.end method

.method public static const : (IZLjava/nio/FloatBuffer;)V
    .code stack 7 locals 5
L0:     invokestatic Method org/lwjgl/opengl/GLContext break ()Lorg/lwjgl/opengl/kb;
L3:     getfield Field org/lwjgl/opengl/kb Ug J
L6:     dup2
L7:     lstore_3
L8:     invokestatic Method org/lwjgl/l break (J)V
L11:    iload_0
L12:    aload_2
L13:    invokestatic Method org/lwjgl/l break (Ljava/nio/FloatBuffer;)V
L16:    aload_2
L17:    invokevirtual Method java/nio/FloatBuffer remaining ()I
L20:    iconst_4
L21:    iconst_1
L22:    dup
L23:    pop2
L24:    ishr
L25:    iload_1
L26:    aload_2
L27:    invokestatic Method org/lwjgl/MemoryUtil break (Ljava/nio/FloatBuffer;)J
L30:    lload_3
L31:    invokestatic Method org/lwjgl/opengl/ARBShaderObjects nglUniformMatrix4fvARB (IIZJJ)V
L34:    return
L35:    
    .end code
.end method

.method public static break : (IFF)V
    .code stack 5 locals 5
L0:     invokestatic Method org/lwjgl/opengl/GLContext break ()Lorg/lwjgl/opengl/kb;
L3:     getfield Field org/lwjgl/opengl/kb ik J
L6:     dup2
L7:     lstore_3
L8:     invokestatic Method org/lwjgl/l break (J)V
L11:    iload_0
L12:    fload_1
L13:    fload_2
L14:    lload_3
L15:    invokestatic Method org/lwjgl/opengl/ARBShaderObjects nglUniform2fARB (IFFJ)V
L18:    return
L19:    
    .end code
.end method

.method public static for : (II)I
    .code stack 6 locals 5
L0:     invokestatic Method org/lwjgl/opengl/GLContext break ()Lorg/lwjgl/opengl/kb;
L3:     dup
L4:     getfield Field org/lwjgl/opengl/kb CD J
L7:     dup2
L8:     lstore_3
L9:     invokestatic Method org/lwjgl/l break (J)V
L12:    invokestatic Method org/lwjgl/opengl/bB short (Lorg/lwjgl/opengl/kb;)Ljava/nio/IntBuffer;
L15:    astore_2
L16:    iload_0
L17:    iload_1
L18:    aload_2
L19:    invokestatic Method org/lwjgl/MemoryUtil break (Ljava/nio/IntBuffer;)J
L22:    lload_3
L23:    invokestatic Method org/lwjgl/opengl/ARBShaderObjects nglGetObjectParameterivARB (IIJJ)V
L26:    aload_2
L27:    iconst_0
L28:    iconst_1
L29:    dup
L30:    pop2
L31:    invokevirtual Method java/nio/IntBuffer get (I)I
L34:    ireturn
L35:    
    .end code
.end method

.method static native nglGetInfoLogARB : (IIJJJ)V
.end method

.method static native nglUniform2iARB : (IIIJ)V
.end method

.method public static catch : (I)V
    .code stack 4 locals 3
L0:     invokestatic Method org/lwjgl/opengl/GLContext break ()Lorg/lwjgl/opengl/kb;
L3:     getfield Field org/lwjgl/opengl/kb return J
L6:     dup2
L7:     lstore_1
L8:     invokestatic Method org/lwjgl/l break (J)V
L11:    iload_0
L12:    lload_1
L13:    invokestatic Method org/lwjgl/opengl/ARBShaderObjects nglCompileShaderARB (IJ)V
L16:    return
L17:    
    .end code
.end method

.method static native nglGetActiveUniformARB : (IIIJJJJJ)V
.end method

.method public static else : (IILjava/nio/IntBuffer;)V
    .code stack 6 locals 5
L0:     invokestatic Method org/lwjgl/opengl/GLContext break ()Lorg/lwjgl/opengl/kb;
L3:     getfield Field org/lwjgl/opengl/kb CD J
L6:     dup2
L7:     lstore_3
L8:     invokestatic Method org/lwjgl/l break (J)V
L11:    iload_0
L12:    aload_2
L13:    invokestatic Method org/lwjgl/l else (Ljava/nio/IntBuffer;)V
L16:    iload_1
L17:    aload_2
L18:    invokestatic Method org/lwjgl/MemoryUtil break (Ljava/nio/IntBuffer;)J
L21:    lload_3
L22:    invokestatic Method org/lwjgl/opengl/ARBShaderObjects nglGetObjectParameterivARB (IIJJ)V
L25:    return
L26:    
    .end code
.end method

.method public static catch : (II)Ljava/lang/String;
    .code stack 9 locals 6
L0:     invokestatic Method org/lwjgl/opengl/GLContext break ()Lorg/lwjgl/opengl/kb;
L3:     dup
L4:     dup2
L5:     getfield Field org/lwjgl/opengl/kb pE J
L8:     dup2
L9:     lstore_3
L10:    invokestatic Method org/lwjgl/l break (J)V
L13:    invokestatic Method org/lwjgl/opengl/bB break (Lorg/lwjgl/opengl/kb;)Ljava/nio/IntBuffer;
L16:    astore_2
L17:    iload_1
L18:    invokestatic Method org/lwjgl/opengl/bB float (Lorg/lwjgl/opengl/kb;I)Ljava/nio/ByteBuffer;
L21:    astore 5
L23:    iload_0
L24:    iload_1
L25:    aload_2
L26:    invokestatic Method org/lwjgl/MemoryUtil break (Ljava/nio/Buffer;)J
L29:    aload 5
L31:    invokestatic Method org/lwjgl/MemoryUtil const (Ljava/nio/ByteBuffer;)J
L34:    lload_3
L35:    invokestatic Method org/lwjgl/opengl/ARBShaderObjects nglGetShaderSourceARB (IIJJJ)V
L38:    aload 5
L40:    dup
L41:    aload_2
L42:    iconst_0
L43:    iconst_1
L44:    dup
L45:    pop2
L46:    invokevirtual Method java/nio/IntBuffer get (I)I
L49:    invokevirtual Method java/nio/ByteBuffer limit (I)Ljava/nio/Buffer;
L52:    pop
L53:    invokestatic Method org/lwjgl/opengl/bB break (Lorg/lwjgl/opengl/kb;Ljava/nio/ByteBuffer;)Ljava/lang/String;
L56:    areturn
L57:    
    .end code
.end method

.method static native nglShaderSourceARB3 : (IIJJJ)V
.end method

.method public static else : (ILjava/lang/CharSequence;)I
    .code stack 5 locals 5
L0:     invokestatic Method org/lwjgl/opengl/GLContext break ()Lorg/lwjgl/opengl/kb;
L3:     dup
L4:     astore_2
L5:     getfield Field org/lwjgl/opengl/kb Tb J
L8:     dup2
L9:     lstore_3
L10:    invokestatic Method org/lwjgl/l break (J)V
L13:    iload_0
L14:    aload_2
L15:    aload_1
L16:    invokestatic Method org/lwjgl/opengl/bB break (Lorg/lwjgl/opengl/kb;Ljava/lang/CharSequence;)J
L19:    lload_3
L20:    invokestatic Method org/lwjgl/opengl/ARBShaderObjects nglGetUniformLocationARB (IJJ)I
L23:    ireturn
L24:    
    .end code
.end method

.method public static short : (ILjava/nio/FloatBuffer;)V
    .code stack 6 locals 4
L0:     invokestatic Method org/lwjgl/opengl/GLContext break ()Lorg/lwjgl/opengl/kb;
L3:     getfield Field org/lwjgl/opengl/kb tC J
L6:     dup2
L7:     lstore_2
L8:     invokestatic Method org/lwjgl/l break (J)V
L11:    iload_0
L12:    aload_1
L13:    invokestatic Method org/lwjgl/l break (Ljava/nio/FloatBuffer;)V
L16:    aload_1
L17:    invokevirtual Method java/nio/FloatBuffer remaining ()I
L20:    aload_1
L21:    invokestatic Method org/lwjgl/MemoryUtil break (Ljava/nio/FloatBuffer;)J
L24:    lload_2
L25:    invokestatic Method org/lwjgl/opengl/ARBShaderObjects nglUniform1fvARB (IIJJ)V
L28:    return
L29:    
    .end code
.end method

.method static native nglUniform1iARB : (IIJ)V
.end method

.method static native nglCreateProgramObjectARB : (J)I
.end method

.method public static short : (ILjava/nio/IntBuffer;)V
    .code stack 6 locals 4
L0:     invokestatic Method org/lwjgl/opengl/GLContext break ()Lorg/lwjgl/opengl/kb;
L3:     getfield Field org/lwjgl/opengl/kb P J
L6:     dup2
L7:     lstore_2
L8:     invokestatic Method org/lwjgl/l break (J)V
L11:    iload_0
L12:    aload_1
L13:    invokestatic Method org/lwjgl/l else (Ljava/nio/IntBuffer;)V
L16:    aload_1
L17:    invokevirtual Method java/nio/IntBuffer remaining ()I
L20:    iconst_1
L21:    dup
L22:    dup
L23:    pop2
L24:    ishr
L25:    aload_1
L26:    invokestatic Method org/lwjgl/MemoryUtil break (Ljava/nio/IntBuffer;)J
L29:    lload_2
L30:    invokestatic Method org/lwjgl/opengl/ARBShaderObjects nglUniform2ivARB (IIJJ)V
L33:    return
L34:    
    .end code
.end method

.method public static else : (IILjava/nio/FloatBuffer;)V
    .code stack 6 locals 5
L0:     invokestatic Method org/lwjgl/opengl/GLContext break ()Lorg/lwjgl/opengl/kb;
L3:     getfield Field org/lwjgl/opengl/kb yc J
L6:     dup2
L7:     lstore_3
L8:     invokestatic Method org/lwjgl/l break (J)V
L11:    iload_0
L12:    aload_2
L13:    invokestatic Method org/lwjgl/l break (Ljava/nio/FloatBuffer;)V
L16:    iload_1
L17:    aload_2
L18:    invokestatic Method org/lwjgl/MemoryUtil break (Ljava/nio/FloatBuffer;)J
L21:    lload_3
L22:    invokestatic Method org/lwjgl/opengl/ARBShaderObjects nglGetUniformfvARB (IIJJ)V
L25:    return
L26:    
    .end code
.end method

.method public static else : (ILjava/nio/IntBuffer;Ljava/nio/ByteBuffer;)V
    .code stack 8 locals 5
L0:     invokestatic Method org/lwjgl/opengl/GLContext break ()Lorg/lwjgl/opengl/kb;
L3:     getfield Field org/lwjgl/opengl/kb pE J
L6:     dup2
L7:     lstore_3
L8:     invokestatic Method org/lwjgl/l break (J)V
L11:    aload_1
L12:    ifnull L23
L15:    aload_1
L16:    iconst_1
L17:    dup
L18:    dup
L19:    pop2
L20:    invokestatic Method org/lwjgl/l break (Ljava/nio/IntBuffer;I)V
L23:    aload_2
L24:    invokestatic Method org/lwjgl/l break (Ljava/nio/ByteBuffer;)V
L27:    iload_0
L28:    aload_2
L29:    invokevirtual Method java/nio/ByteBuffer remaining ()I
L32:    aload_1
L33:    invokestatic Method org/lwjgl/MemoryUtil else (Ljava/nio/IntBuffer;)J
L36:    aload_2
L37:    invokestatic Method org/lwjgl/MemoryUtil const (Ljava/nio/ByteBuffer;)J
L40:    lload_3
L41:    invokestatic Method org/lwjgl/opengl/ARBShaderObjects nglGetShaderSourceARB (IIJJJ)V
L44:    return
L45:    
        .attribute StackMap b'\x00\x01\x00\x17\x00\x04\x01\x07\x00\xAB\x07\x00\x89\x04\x00\x00'
    .end code
.end method

.method public static float : (II)I
    .code stack 13 locals 6
L0:     invokestatic Method org/lwjgl/opengl/GLContext break ()Lorg/lwjgl/opengl/kb;
L3:     dup
L4:     astore_2
L5:     dup
L6:     getfield Field org/lwjgl/opengl/kb tf J
L9:     dup2
L10:    lstore_3
L11:    invokestatic Method org/lwjgl/l break (J)V
L14:    invokestatic Method org/lwjgl/opengl/bB short (Lorg/lwjgl/opengl/kb;)Ljava/nio/IntBuffer;
L17:    astore 5
L19:    iload_0
L20:    iload_1
L21:    iconst_0
L22:    iconst_1
L23:    dup
L24:    pop2
L25:    lconst_0
L26:    aload 5
L28:    iconst_1
L29:    dup
L30:    dup
L31:    pop2
L32:    invokestatic Method org/lwjgl/MemoryUtil break (Ljava/nio/IntBuffer;I)J
L35:    aload 5
L37:    invokestatic Method org/lwjgl/MemoryUtil break (Ljava/nio/IntBuffer;)J
L40:    aload_2
L41:    invokestatic Method org/lwjgl/opengl/bB catch (Lorg/lwjgl/opengl/kb;)J
L44:    lload_3
L45:    invokestatic Method org/lwjgl/opengl/ARBShaderObjects nglGetActiveUniformARB (IIIJJJJJ)V
L48:    aload 5
L50:    iconst_0
L51:    iconst_1
L52:    dup
L53:    pop2
L54:    invokevirtual Method java/nio/IntBuffer get (I)I
L57:    ireturn
L58:    
    .end code
.end method

.method static native nglUniform1fARB : (IFJ)V
.end method

.method static native nglUniform1fvARB : (IIJJ)V
.end method

.method public static break : (IFFF)V
    .code stack 6 locals 6
L0:     invokestatic Method org/lwjgl/opengl/GLContext break ()Lorg/lwjgl/opengl/kb;
L3:     getfield Field org/lwjgl/opengl/kb sE J
L6:     dup2
L7:     lstore 4
L9:     invokestatic Method org/lwjgl/l break (J)V
L12:    iload_0
L13:    fload_1
L14:    fload_2
L15:    fload_3
L16:    lload 4
L18:    invokestatic Method org/lwjgl/opengl/ARBShaderObjects nglUniform3fARB (IFFFJ)V
L21:    return
L22:    
    .end code
.end method

.method static native nglLinkProgramARB : (IJ)V
.end method

.method public static break : (ILjava/nio/ByteBuffer;)I
    .code stack 5 locals 4
L0:     invokestatic Method org/lwjgl/opengl/GLContext break ()Lorg/lwjgl/opengl/kb;
L3:     getfield Field org/lwjgl/opengl/kb Tb J
L6:     dup2
L7:     lstore_2
L8:     invokestatic Method org/lwjgl/l break (J)V
L11:    iload_0
L12:    aload_1
L13:    dup
L14:    invokestatic Method org/lwjgl/l break (Ljava/nio/ByteBuffer;)V
L17:    invokestatic Method org/lwjgl/l else (Ljava/nio/ByteBuffer;)V
L20:    aload_1
L21:    invokestatic Method org/lwjgl/MemoryUtil const (Ljava/nio/ByteBuffer;)J
L24:    lload_2
L25:    invokestatic Method org/lwjgl/opengl/ARBShaderObjects nglGetUniformLocationARB (IJJ)I
L28:    ireturn
L29:    
    .end code
.end method

.method public static const : (ILjava/nio/FloatBuffer;)V
    .code stack 6 locals 4
L0:     invokestatic Method org/lwjgl/opengl/GLContext break ()Lorg/lwjgl/opengl/kb;
L3:     getfield Field org/lwjgl/opengl/kb FN J
L6:     dup2
L7:     lstore_2
L8:     invokestatic Method org/lwjgl/l break (J)V
L11:    iload_0
L12:    aload_1
L13:    invokestatic Method org/lwjgl/l break (Ljava/nio/FloatBuffer;)V
L16:    aload_1
L17:    invokevirtual Method java/nio/FloatBuffer remaining ()I
L20:    iconst_3
L21:    iconst_1
L22:    dup
L23:    pop2
L24:    idiv
L25:    aload_1
L26:    invokestatic Method org/lwjgl/MemoryUtil break (Ljava/nio/FloatBuffer;)J
L29:    lload_2
L30:    invokestatic Method org/lwjgl/opengl/ARBShaderObjects nglUniform3fvARB (IIJJ)V
L33:    return
L34:    
    .end code
.end method

.method static native nglUniform3fARB : (IFFFJ)V
.end method

.method public static break : (IILjava/nio/FloatBuffer;)V
    .code stack 6 locals 5
L0:     invokestatic Method org/lwjgl/opengl/GLContext break ()Lorg/lwjgl/opengl/kb;
L3:     getfield Field org/lwjgl/opengl/kb sC J
L6:     dup2
L7:     lstore_3
L8:     invokestatic Method org/lwjgl/l break (J)V
L11:    iload_0
L12:    aload_2
L13:    invokestatic Method org/lwjgl/l break (Ljava/nio/FloatBuffer;)V
L16:    iload_1
L17:    aload_2
L18:    invokestatic Method org/lwjgl/MemoryUtil break (Ljava/nio/FloatBuffer;)J
L21:    lload_3
L22:    invokestatic Method org/lwjgl/opengl/ARBShaderObjects nglGetObjectParameterfvARB (IIJJ)V
L25:    return
L26:    
    .end code
.end method

.method public static break : (IF)V
    .code stack 4 locals 4
L0:     invokestatic Method org/lwjgl/opengl/GLContext break ()Lorg/lwjgl/opengl/kb;
L3:     getfield Field org/lwjgl/opengl/kb uP J
L6:     dup2
L7:     lstore_2
L8:     invokestatic Method org/lwjgl/l break (J)V
L11:    iload_0
L12:    fload_1
L13:    lload_2
L14:    invokestatic Method org/lwjgl/opengl/ARBShaderObjects nglUniform1fARB (IFJ)V
L17:    return
L18:    
    .end code
.end method

.method public static else : (III)V
    .code stack 5 locals 5
L0:     invokestatic Method org/lwjgl/opengl/GLContext break ()Lorg/lwjgl/opengl/kb;
L3:     getfield Field org/lwjgl/opengl/kb nO J
L6:     dup2
L7:     lstore_3
L8:     invokestatic Method org/lwjgl/l break (J)V
L11:    iload_0
L12:    iload_1
L13:    iload_2
L14:    lload_3
L15:    invokestatic Method org/lwjgl/opengl/ARBShaderObjects nglUniform2iARB (IIIJ)V
L18:    return
L19:    
    .end code
.end method

.method static native nglGetObjectParameterfvARB : (IIJJ)V
.end method

.method public static else : (IZLjava/nio/FloatBuffer;)V
    .code stack 7 locals 5
L0:     invokestatic Method org/lwjgl/opengl/GLContext break ()Lorg/lwjgl/opengl/kb;
L3:     getfield Field org/lwjgl/opengl/kb QL J
L6:     dup2
L7:     lstore_3
L8:     invokestatic Method org/lwjgl/l break (J)V
L11:    iload_0
L12:    aload_2
L13:    invokestatic Method org/lwjgl/l break (Ljava/nio/FloatBuffer;)V
L16:    aload_2
L17:    invokevirtual Method java/nio/FloatBuffer remaining ()I
L20:    iconst_2
L21:    iconst_1
L22:    dup
L23:    pop2
L24:    ishr
L25:    iload_1
L26:    aload_2
L27:    invokestatic Method org/lwjgl/MemoryUtil break (Ljava/nio/FloatBuffer;)J
L30:    lload_3
L31:    invokestatic Method org/lwjgl/opengl/ARBShaderObjects nglUniformMatrix2fvARB (IIZJJ)V
L34:    return
L35:    
    .end code
.end method

.method public static break : (IIILjava/nio/IntBuffer;)Ljava/lang/String;
    .code stack 14 locals 8
L0:     invokestatic Method org/lwjgl/opengl/GLContext break ()Lorg/lwjgl/opengl/kb;
L3:     dup
L4:     astore 4
L6:     dup
L7:     aload_3
L8:     aload 4
L10:    dup_x2
L11:    getfield Field org/lwjgl/opengl/kb tf J
L14:    dup2
L15:    lstore 5
L17:    invokestatic Method org/lwjgl/l break (J)V
L20:    iconst_2
L21:    iconst_1
L22:    dup
L23:    pop2
L24:    invokestatic Method org/lwjgl/l break (Ljava/nio/IntBuffer;I)V
L27:    invokestatic Method org/lwjgl/opengl/bB break (Lorg/lwjgl/opengl/kb;)Ljava/nio/IntBuffer;
L30:    astore 4
L32:    iload_2
L33:    invokestatic Method org/lwjgl/opengl/bB float (Lorg/lwjgl/opengl/kb;I)Ljava/nio/ByteBuffer;
L36:    astore 7
L38:    iload_0
L39:    iload_1
L40:    iload_2
L41:    aload 4
L43:    invokestatic Method org/lwjgl/MemoryUtil break (Ljava/nio/Buffer;)J
L46:    aload_3
L47:    invokestatic Method org/lwjgl/MemoryUtil break (Ljava/nio/IntBuffer;)J
L50:    aload_3
L51:    dup
L52:    invokevirtual Method java/nio/IntBuffer position ()I
L55:    iconst_1
L56:    dup
L57:    dup
L58:    pop2
L59:    iadd
L60:    invokestatic Method org/lwjgl/MemoryUtil break (Ljava/nio/IntBuffer;I)J
L63:    aload 7
L65:    invokestatic Method org/lwjgl/MemoryUtil const (Ljava/nio/ByteBuffer;)J
L68:    lload 5
L70:    invokestatic Method org/lwjgl/opengl/ARBShaderObjects nglGetActiveUniformARB (IIIJJJJJ)V
L73:    aload 7
L75:    dup
L76:    aload 4
L78:    iconst_0
L79:    iconst_1
L80:    dup
L81:    pop2
L82:    invokevirtual Method java/nio/IntBuffer get (I)I
L85:    invokevirtual Method java/nio/ByteBuffer limit (I)Ljava/nio/Buffer;
L88:    pop
L89:    invokestatic Method org/lwjgl/opengl/bB break (Lorg/lwjgl/opengl/kb;Ljava/nio/ByteBuffer;)Ljava/lang/String;
L92:    areturn
L93:    
    .end code
.end method

.method public static break : ()I
    .code stack 4 locals 2
L0:     invokestatic Method org/lwjgl/opengl/GLContext break ()Lorg/lwjgl/opengl/kb;
L3:     getfield Field org/lwjgl/opengl/kb VO J
L6:     dup2
L7:     lstore_0
L8:     invokestatic Method org/lwjgl/l break (J)V
L11:    lload_0
L12:    invokestatic Method org/lwjgl/opengl/ARBShaderObjects nglCreateProgramObjectARB (J)I
L15:    ireturn
L16:    
    .end code
.end method

.method public static break : (ILjava/nio/IntBuffer;Ljava/nio/ByteBuffer;)V
    .code stack 8 locals 5
L0:     invokestatic Method org/lwjgl/opengl/GLContext break ()Lorg/lwjgl/opengl/kb;
L3:     getfield Field org/lwjgl/opengl/kb BE J
L6:     dup2
L7:     lstore_3
L8:     invokestatic Method org/lwjgl/l break (J)V
L11:    aload_1
L12:    ifnull L23
L15:    aload_1
L16:    iconst_1
L17:    dup
L18:    dup
L19:    pop2
L20:    invokestatic Method org/lwjgl/l break (Ljava/nio/IntBuffer;I)V
L23:    aload_2
L24:    invokestatic Method org/lwjgl/l break (Ljava/nio/ByteBuffer;)V
L27:    iload_0
L28:    aload_2
L29:    invokevirtual Method java/nio/ByteBuffer remaining ()I
L32:    aload_1
L33:    invokestatic Method org/lwjgl/MemoryUtil else (Ljava/nio/IntBuffer;)J
L36:    aload_2
L37:    invokestatic Method org/lwjgl/MemoryUtil const (Ljava/nio/ByteBuffer;)J
L40:    lload_3
L41:    invokestatic Method org/lwjgl/opengl/ARBShaderObjects nglGetInfoLogARB (IIJJJ)V
L44:    return
L45:    
        .attribute StackMap b'\x00\x01\x00\x17\x00\x04\x01\x07\x00\xAB\x07\x00\x89\x04\x00\x00'
    .end code
.end method

.method static native nglUniform4iARB : (IIIIIJ)V
.end method

.method static native nglGetShaderSourceARB : (IIJJJ)V
.end method

.method public static float : (I)V
    .code stack 4 locals 3
L0:     invokestatic Method org/lwjgl/opengl/GLContext break ()Lorg/lwjgl/opengl/kb;
L3:     getfield Field org/lwjgl/opengl/kb KA J
L6:     dup2
L7:     lstore_1
L8:     invokestatic Method org/lwjgl/l break (J)V
L11:    iload_0
L12:    lload_1
L13:    invokestatic Method org/lwjgl/opengl/ARBShaderObjects nglDeleteObjectARB (IJ)V
L16:    return
L17:    
    .end code
.end method

.method static native nglUniform3iARB : (IIIIJ)V
.end method

.method public static break : (ILjava/lang/CharSequence;)V
    .code stack 7 locals 5
L0:     invokestatic Method org/lwjgl/opengl/GLContext break ()Lorg/lwjgl/opengl/kb;
L3:     dup
L4:     astore_2
L5:     getfield Field org/lwjgl/opengl/kb aS J
L8:     dup2
L9:     lstore_3
L10:    invokestatic Method org/lwjgl/l break (J)V
L13:    iload_0
L14:    iconst_1
L15:    dup
L16:    dup
L17:    pop2
L18:    aload_2
L19:    aload_1
L20:    invokestatic Method org/lwjgl/opengl/bB else (Lorg/lwjgl/opengl/kb;Ljava/lang/CharSequence;)J
L23:    aload_1
L24:    invokeinterface InterfaceMethod java/lang/CharSequence length ()I 1
L29:    lload_3
L30:    invokestatic Method org/lwjgl/opengl/ARBShaderObjects nglShaderSourceARB (IIJIJ)V
L33:    return
L34:    
    .end code
.end method

.method static native nglCreateShaderObjectARB : (IJ)I
.end method

.method static native nglCompileShaderARB : (IJ)V
.end method

.method public static short : (II)V
    .code stack 4 locals 4
L0:     invokestatic Method org/lwjgl/opengl/GLContext break ()Lorg/lwjgl/opengl/kb;
L3:     getfield Field org/lwjgl/opengl/kb KP J
L6:     dup2
L7:     lstore_2
L8:     invokestatic Method org/lwjgl/l break (J)V
L11:    iload_0
L12:    iload_1
L13:    lload_2
L14:    invokestatic Method org/lwjgl/opengl/ARBShaderObjects nglAttachObjectARB (IIJ)V
L17:    return
L18:    
    .end code
.end method

.method public static const : (ILjava/nio/IntBuffer;)V
    .code stack 6 locals 4
L0:     invokestatic Method org/lwjgl/opengl/GLContext break ()Lorg/lwjgl/opengl/kb;
L3:     getfield Field org/lwjgl/opengl/kb hA J
L6:     dup2
L7:     lstore_2
L8:     invokestatic Method org/lwjgl/l break (J)V
L11:    iload_0
L12:    aload_1
L13:    invokestatic Method org/lwjgl/l else (Ljava/nio/IntBuffer;)V
L16:    aload_1
L17:    invokevirtual Method java/nio/IntBuffer remaining ()I
L20:    aload_1
L21:    invokestatic Method org/lwjgl/MemoryUtil break (Ljava/nio/IntBuffer;)J
L24:    lload_2
L25:    invokestatic Method org/lwjgl/opengl/ARBShaderObjects nglUniform1ivARB (IIJJ)V
L28:    return
L29:    
    .end code
.end method

.method public static short : (I)I
    .code stack 4 locals 3
L0:     invokestatic Method org/lwjgl/opengl/GLContext break ()Lorg/lwjgl/opengl/kb;
L3:     getfield Field org/lwjgl/opengl/kb GS J
L6:     dup2
L7:     lstore_1
L8:     invokestatic Method org/lwjgl/l break (J)V
L11:    iload_0
L12:    lload_1
L13:    invokestatic Method org/lwjgl/opengl/ARBShaderObjects nglGetHandleARB (IJ)I
L16:    ireturn
L17:    
    .end code
.end method

.method static native nglGetUniformfvARB : (IIJJ)V
.end method

.method static native nglGetAttachedObjectsARB : (IIJJJ)V
.end method

.method static native nglUniform2fvARB : (IIJJ)V
.end method

.method static native nglDeleteObjectARB : (IJ)V
.end method

.method static native nglUniform4fARB : (IFFFFJ)V
.end method

.method static native nglUniform3fvARB : (IIJJ)V
.end method

.method static native nglAttachObjectARB : (IIJ)V
.end method

.method private <init> : ()V
    .code stack 1 locals 1
L0:     aload_0
L1:     invokespecial Method java/lang/Object <init> ()V
L4:     return
L5:     
    .end code
.end method

.method public static break : (IILjava/nio/IntBuffer;Ljava/nio/IntBuffer;Ljava/nio/IntBuffer;Ljava/nio/ByteBuffer;)V
    .code stack 13 locals 8
L0:     invokestatic Method org/lwjgl/opengl/GLContext break ()Lorg/lwjgl/opengl/kb;
L3:     getfield Field org/lwjgl/opengl/kb tf J
L6:     dup2
L7:     lstore 6
L9:     invokestatic Method org/lwjgl/l break (J)V
L12:    aload_2
L13:    ifnull L24
L16:    aload_2
L17:    iconst_1
L18:    dup
L19:    dup
L20:    pop2
L21:    invokestatic Method org/lwjgl/l break (Ljava/nio/IntBuffer;I)V
L24:    aload_3
L25:    iconst_1
L26:    dup
L27:    dup
L28:    pop2
L29:    invokestatic Method org/lwjgl/l break (Ljava/nio/IntBuffer;I)V
L32:    iload_0
L33:    aload 5
L35:    aload 4
L37:    iconst_1
L38:    dup
L39:    dup
L40:    pop2
L41:    invokestatic Method org/lwjgl/l break (Ljava/nio/IntBuffer;I)V
L44:    invokestatic Method org/lwjgl/l break (Ljava/nio/ByteBuffer;)V
L47:    iload_1
L48:    aload 5
L50:    invokevirtual Method java/nio/ByteBuffer remaining ()I
L53:    aload_2
L54:    invokestatic Method org/lwjgl/MemoryUtil else (Ljava/nio/IntBuffer;)J
L57:    aload_3
L58:    invokestatic Method org/lwjgl/MemoryUtil break (Ljava/nio/IntBuffer;)J
L61:    aload 4
L63:    invokestatic Method org/lwjgl/MemoryUtil break (Ljava/nio/IntBuffer;)J
L66:    aload 5
L68:    invokestatic Method org/lwjgl/MemoryUtil const (Ljava/nio/ByteBuffer;)J
L71:    lload 6
L73:    invokestatic Method org/lwjgl/opengl/ARBShaderObjects nglGetActiveUniformARB (IIIJJJJJ)V
L76:    return
L77:    
        .attribute StackMap b'\x00\x01\x00\x18\x00\x07\x01\x01\x07\x00\xAB\x07\x00\xAB\x07\x00\xAB\x07\x00\x89\x04\x00\x00'
    .end code
.end method

.method static native nglValidateProgramARB : (IJ)V
.end method

.method public static else : (ILjava/nio/FloatBuffer;)V
    .code stack 6 locals 4
L0:     invokestatic Method org/lwjgl/opengl/GLContext break ()Lorg/lwjgl/opengl/kb;
L3:     getfield Field org/lwjgl/opengl/kb m J
L6:     dup2
L7:     lstore_2
L8:     invokestatic Method org/lwjgl/l break (J)V
L11:    iload_0
L12:    aload_1
L13:    invokestatic Method org/lwjgl/l break (Ljava/nio/FloatBuffer;)V
L16:    aload_1
L17:    invokevirtual Method java/nio/FloatBuffer remaining ()I
L20:    iconst_2
L21:    iconst_1
L22:    dup
L23:    pop2
L24:    ishr
L25:    aload_1
L26:    invokestatic Method org/lwjgl/MemoryUtil break (Ljava/nio/FloatBuffer;)J
L29:    lload_2
L30:    invokestatic Method org/lwjgl/opengl/ARBShaderObjects nglUniform4fvARB (IIJJ)V
L33:    return
L34:    
    .end code
.end method

.method public static const : (I)V
    .code stack 4 locals 3
L0:     invokestatic Method org/lwjgl/opengl/GLContext break ()Lorg/lwjgl/opengl/kb;
L3:     getfield Field org/lwjgl/opengl/kb WG J
L6:     dup2
L7:     lstore_1
L8:     invokestatic Method org/lwjgl/l break (J)V
L11:    iload_0
L12:    lload_1
L13:    invokestatic Method org/lwjgl/opengl/ARBShaderObjects nglUseProgramObjectARB (IJ)V
L16:    return
L17:    
    .end code
.end method

.method public static break : (I[Ljava/lang/CharSequence;)V
    .code stack 8 locals 5
L0:     invokestatic Method org/lwjgl/opengl/GLContext break ()Lorg/lwjgl/opengl/kb;
L3:     astore_2
L4:     aload_1
L5:     aload_2
L6:     getfield Field org/lwjgl/opengl/kb aS J
L9:     dup2
L10:    lstore_3
L11:    invokestatic Method org/lwjgl/l break (J)V
L14:    invokestatic Method org/lwjgl/l break ([Ljava/lang/Object;)V
L17:    iload_0
L18:    aload_1
L19:    arraylength
L20:    aload_2
L21:    aload_1
L22:    invokestatic Method org/lwjgl/opengl/bB else (Lorg/lwjgl/opengl/kb;[Ljava/lang/CharSequence;)J
L25:    aload_2
L26:    aload_1
L27:    invokestatic Method org/lwjgl/opengl/bB break (Lorg/lwjgl/opengl/kb;[Ljava/lang/CharSequence;)J
L30:    lload_3
L31:    invokestatic Method org/lwjgl/opengl/ARBShaderObjects nglShaderSourceARB3 (IIJJJ)V
L34:    return
L35:    
    .end code
.end method

.method public static else : (I)I
    .code stack 4 locals 3
L0:     invokestatic Method org/lwjgl/opengl/GLContext break ()Lorg/lwjgl/opengl/kb;
L3:     getfield Field org/lwjgl/opengl/kb nT J
L6:     dup2
L7:     lstore_1
L8:     invokestatic Method org/lwjgl/l break (J)V
L11:    iload_0
L12:    lload_1
L13:    invokestatic Method org/lwjgl/opengl/ARBShaderObjects nglCreateShaderObjectARB (IJ)I
L16:    ireturn
L17:    
    .end code
.end method

.method public static else : (ILjava/nio/IntBuffer;)V
    .code stack 6 locals 4
L0:     invokestatic Method org/lwjgl/opengl/GLContext break ()Lorg/lwjgl/opengl/kb;
L3:     getfield Field org/lwjgl/opengl/kb KM J
L6:     dup2
L7:     lstore_2
L8:     invokestatic Method org/lwjgl/l break (J)V
L11:    iload_0
L12:    aload_1
L13:    invokestatic Method org/lwjgl/l else (Ljava/nio/IntBuffer;)V
L16:    aload_1
L17:    invokevirtual Method java/nio/IntBuffer remaining ()I
L20:    iconst_3
L21:    iconst_1
L22:    dup
L23:    pop2
L24:    idiv
L25:    aload_1
L26:    invokestatic Method org/lwjgl/MemoryUtil break (Ljava/nio/IntBuffer;)J
L29:    lload_2
L30:    invokestatic Method org/lwjgl/opengl/ARBShaderObjects nglUniform3ivARB (IIJJ)V
L33:    return
L34:    
    .end code
.end method

.method static native nglUniform4ivARB : (IIJJ)V
.end method

.method static native nglUniformMatrix2fvARB : (IIZJJ)V
.end method

.method public static break : (IZLjava/nio/FloatBuffer;)V
    .code stack 7 locals 5
L0:     invokestatic Method org/lwjgl/opengl/GLContext break ()Lorg/lwjgl/opengl/kb;
L3:     getfield Field org/lwjgl/opengl/kb zm J
L6:     dup2
L7:     lstore_3
L8:     invokestatic Method org/lwjgl/l break (J)V
L11:    iload_0
L12:    aload_2
L13:    invokestatic Method org/lwjgl/l break (Ljava/nio/FloatBuffer;)V
L16:    aload_2
L17:    invokevirtual Method java/nio/FloatBuffer remaining ()I
L20:    bipush 9
L22:    iconst_1
L23:    dup
L24:    pop2
L25:    idiv
L26:    iload_1
L27:    aload_2
L28:    invokestatic Method org/lwjgl/MemoryUtil break (Ljava/nio/FloatBuffer;)J
L31:    lload_3
L32:    invokestatic Method org/lwjgl/opengl/ARBShaderObjects nglUniformMatrix3fvARB (IIZJJ)V
L35:    return
L36:    
    .end code
.end method

.method public static break : (ILjava/nio/IntBuffer;)V
    .code stack 6 locals 4
L0:     invokestatic Method org/lwjgl/opengl/GLContext break ()Lorg/lwjgl/opengl/kb;
L3:     getfield Field org/lwjgl/opengl/kb tj J
L6:     dup2
L7:     lstore_2
L8:     invokestatic Method org/lwjgl/l break (J)V
L11:    iload_0
L12:    aload_1
L13:    invokestatic Method org/lwjgl/l else (Ljava/nio/IntBuffer;)V
L16:    aload_1
L17:    invokevirtual Method java/nio/IntBuffer remaining ()I
L20:    iconst_2
L21:    iconst_1
L22:    dup
L23:    pop2
L24:    ishr
L25:    aload_1
L26:    invokestatic Method org/lwjgl/MemoryUtil break (Ljava/nio/IntBuffer;)J
L29:    lload_2
L30:    invokestatic Method org/lwjgl/opengl/ARBShaderObjects nglUniform4ivARB (IIJJ)V
L33:    return
L34:    
    .end code
.end method

.method public static const : (II)Ljava/lang/String;
    .code stack 9 locals 6
L0:     invokestatic Method org/lwjgl/opengl/GLContext break ()Lorg/lwjgl/opengl/kb;
L3:     dup
L4:     dup2
L5:     getfield Field org/lwjgl/opengl/kb BE J
L8:     dup2
L9:     lstore_3
L10:    invokestatic Method org/lwjgl/l break (J)V
L13:    invokestatic Method org/lwjgl/opengl/bB break (Lorg/lwjgl/opengl/kb;)Ljava/nio/IntBuffer;
L16:    astore_2
L17:    iload_1
L18:    invokestatic Method org/lwjgl/opengl/bB float (Lorg/lwjgl/opengl/kb;I)Ljava/nio/ByteBuffer;
L21:    astore 5
L23:    iload_0
L24:    iload_1
L25:    aload_2
L26:    invokestatic Method org/lwjgl/MemoryUtil break (Ljava/nio/Buffer;)J
L29:    aload 5
L31:    invokestatic Method org/lwjgl/MemoryUtil const (Ljava/nio/ByteBuffer;)J
L34:    lload_3
L35:    invokestatic Method org/lwjgl/opengl/ARBShaderObjects nglGetInfoLogARB (IIJJJ)V
L38:    aload 5
L40:    dup
L41:    aload_2
L42:    iconst_0
L43:    iconst_1
L44:    dup
L45:    pop2
L46:    invokevirtual Method java/nio/IntBuffer get (I)I
L49:    invokevirtual Method java/nio/ByteBuffer limit (I)Ljava/nio/Buffer;
L52:    pop
L53:    invokestatic Method org/lwjgl/opengl/bB break (Lorg/lwjgl/opengl/kb;Ljava/nio/ByteBuffer;)Ljava/lang/String;
L56:    areturn
L57:    
    .end code
.end method

.method public static break : (I)V
    .code stack 4 locals 3
L0:     invokestatic Method org/lwjgl/opengl/GLContext break ()Lorg/lwjgl/opengl/kb;
L3:     getfield Field org/lwjgl/opengl/kb Gb J
L6:     dup2
L7:     lstore_1
L8:     invokestatic Method org/lwjgl/l break (J)V
L11:    iload_0
L12:    lload_1
L13:    invokestatic Method org/lwjgl/opengl/ARBShaderObjects nglValidateProgramARB (IJ)V
L16:    return
L17:    
    .end code
.end method

.method static native nglUniformMatrix4fvARB : (IIZJJ)V
.end method

.method public static else : (II)V
    .code stack 4 locals 4
L0:     invokestatic Method org/lwjgl/opengl/GLContext break ()Lorg/lwjgl/opengl/kb;
L3:     getfield Field org/lwjgl/opengl/kb VI J
L6:     dup2
L7:     lstore_2
L8:     invokestatic Method org/lwjgl/l break (J)V
L11:    iload_0
L12:    iload_1
L13:    lload_2
L14:    invokestatic Method org/lwjgl/opengl/ARBShaderObjects nglDetachObjectARB (IIJ)V
L17:    return
L18:    
    .end code
.end method

.method public static break : (II)F
    .code stack 6 locals 5
L0:     invokestatic Method org/lwjgl/opengl/GLContext break ()Lorg/lwjgl/opengl/kb;
L3:     dup
L4:     getfield Field org/lwjgl/opengl/kb sC J
L7:     dup2
L8:     lstore_3
L9:     invokestatic Method org/lwjgl/l break (J)V
L12:    invokestatic Method org/lwjgl/opengl/bB float (Lorg/lwjgl/opengl/kb;)Ljava/nio/FloatBuffer;
L15:    astore_2
L16:    iload_0
L17:    iload_1
L18:    aload_2
L19:    invokestatic Method org/lwjgl/MemoryUtil break (Ljava/nio/FloatBuffer;)J
L22:    lload_3
L23:    invokestatic Method org/lwjgl/opengl/ARBShaderObjects nglGetObjectParameterfvARB (IIJJ)V
L26:    aload_2
L27:    iconst_0
L28:    iconst_1
L29:    dup
L30:    pop2
L31:    invokevirtual Method java/nio/FloatBuffer get (I)F
L34:    freturn
L35:    
    .end code
.end method

.method static native nglGetObjectParameterivARB : (IIJJ)V
.end method

.method static native nglShaderSourceARB : (IIJIJ)V
.end method

.method public static break : (ILjava/nio/IntBuffer;Ljava/nio/IntBuffer;)V
    .code stack 8 locals 5
L0:     invokestatic Method org/lwjgl/opengl/GLContext break ()Lorg/lwjgl/opengl/kb;
L3:     getfield Field org/lwjgl/opengl/kb mg J
L6:     dup2
L7:     lstore_3
L8:     invokestatic Method org/lwjgl/l break (J)V
L11:    aload_1
L12:    ifnull L23
L15:    aload_1
L16:    iconst_1
L17:    dup
L18:    dup
L19:    pop2
L20:    invokestatic Method org/lwjgl/l break (Ljava/nio/IntBuffer;I)V
L23:    aload_2
L24:    invokestatic Method org/lwjgl/l else (Ljava/nio/IntBuffer;)V
L27:    iload_0
L28:    aload_2
L29:    invokevirtual Method java/nio/IntBuffer remaining ()I
L32:    aload_1
L33:    invokestatic Method org/lwjgl/MemoryUtil else (Ljava/nio/IntBuffer;)J
L36:    aload_2
L37:    invokestatic Method org/lwjgl/MemoryUtil break (Ljava/nio/IntBuffer;)J
L40:    lload_3
L41:    invokestatic Method org/lwjgl/opengl/ARBShaderObjects nglGetAttachedObjectsARB (IIJJJ)V
L44:    return
L45:    
        .attribute StackMap b'\x00\x01\x00\x17\x00\x04\x01\x07\x00\xAB\x07\x00\xAB\x04\x00\x00'
    .end code
.end method

.method public static break : (ILjava/nio/FloatBuffer;)V
    .code stack 6 locals 4
L0:     invokestatic Method org/lwjgl/opengl/GLContext break ()Lorg/lwjgl/opengl/kb;
L3:     getfield Field org/lwjgl/opengl/kb Zq J
L6:     dup2
L7:     lstore_2
L8:     invokestatic Method org/lwjgl/l break (J)V
L11:    iload_0
L12:    aload_1
L13:    invokestatic Method org/lwjgl/l break (Ljava/nio/FloatBuffer;)V
L16:    aload_1
L17:    invokevirtual Method java/nio/FloatBuffer remaining ()I
L20:    iconst_1
L21:    dup
L22:    dup
L23:    pop2
L24:    ishr
L25:    aload_1
L26:    invokestatic Method org/lwjgl/MemoryUtil break (Ljava/nio/FloatBuffer;)J
L29:    lload_2
L30:    invokestatic Method org/lwjgl/opengl/ARBShaderObjects nglUniform2fvARB (IIJJ)V
L33:    return
L34:    
    .end code
.end method

.method static native nglGetUniformLocationARB : (IJJ)I
.end method

.method public static break : (IFFFF)V
    .code stack 7 locals 7
L0:     invokestatic Method org/lwjgl/opengl/GLContext break ()Lorg/lwjgl/opengl/kb;
L3:     getfield Field org/lwjgl/opengl/kb null J
L6:     dup2
L7:     lstore 5
L9:     invokestatic Method org/lwjgl/l break (J)V
L12:    iload_0
L13:    fload_1
L14:    fload_2
L15:    fload_3
L16:    fload 4
L18:    lload 5
L20:    invokestatic Method org/lwjgl/opengl/ARBShaderObjects nglUniform4fARB (IFFFFJ)V
L23:    return
L24:    
    .end code
.end method

.method static native nglUniform4fvARB : (IIJJ)V
.end method

.method public static break : (III)Ljava/lang/String;
    .code stack 14 locals 8
L0:     invokestatic Method org/lwjgl/opengl/GLContext break ()Lorg/lwjgl/opengl/kb;
L3:     dup
L4:     astore_3
L5:     dup
L6:     dup2
L7:     getfield Field org/lwjgl/opengl/kb tf J
L10:    dup2
L11:    lstore 4
L13:    invokestatic Method org/lwjgl/l break (J)V
L16:    invokestatic Method org/lwjgl/opengl/bB break (Lorg/lwjgl/opengl/kb;)Ljava/nio/IntBuffer;
L19:    astore 6
L21:    iload_2
L22:    invokestatic Method org/lwjgl/opengl/bB float (Lorg/lwjgl/opengl/kb;I)Ljava/nio/ByteBuffer;
L25:    astore 7
L27:    iload_0
L28:    iload_1
L29:    iload_2
L30:    aload 6
L32:    invokestatic Method org/lwjgl/MemoryUtil break (Ljava/nio/Buffer;)J
L35:    aload_3
L36:    invokestatic Method org/lwjgl/opengl/bB short (Lorg/lwjgl/opengl/kb;)Ljava/nio/IntBuffer;
L39:    invokestatic Method org/lwjgl/MemoryUtil break (Ljava/nio/Buffer;)J
L42:    aload_3
L43:    invokestatic Method org/lwjgl/opengl/bB short (Lorg/lwjgl/opengl/kb;)Ljava/nio/IntBuffer;
L46:    iconst_1
L47:    dup
L48:    dup
L49:    pop2
L50:    invokestatic Method org/lwjgl/MemoryUtil break (Ljava/nio/IntBuffer;I)J
L53:    aload 7
L55:    invokestatic Method org/lwjgl/MemoryUtil const (Ljava/nio/ByteBuffer;)J
L58:    lload 4
L60:    invokestatic Method org/lwjgl/opengl/ARBShaderObjects nglGetActiveUniformARB (IIIJJJJJ)V
L63:    aload 7
L65:    dup
L66:    aload 6
L68:    iconst_0
L69:    iconst_1
L70:    dup
L71:    pop2
L72:    invokevirtual Method java/nio/IntBuffer get (I)I
L75:    invokevirtual Method java/nio/ByteBuffer limit (I)Ljava/nio/Buffer;
L78:    pop
L79:    invokestatic Method org/lwjgl/opengl/bB break (Lorg/lwjgl/opengl/kb;Ljava/nio/ByteBuffer;)Ljava/lang/String;
L82:    areturn
L83:    
    .end code
.end method

.method static native nglUniform2ivARB : (IIJJ)V
.end method

.method public static break : (IILjava/nio/IntBuffer;)V
    .code stack 6 locals 5
L0:     invokestatic Method org/lwjgl/opengl/GLContext break ()Lorg/lwjgl/opengl/kb;
L3:     getfield Field org/lwjgl/opengl/kb XH J
L6:     dup2
L7:     lstore_3
L8:     invokestatic Method org/lwjgl/l break (J)V
L11:    iload_0
L12:    aload_2
L13:    invokestatic Method org/lwjgl/l else (Ljava/nio/IntBuffer;)V
L16:    iload_1
L17:    aload_2
L18:    invokestatic Method org/lwjgl/MemoryUtil break (Ljava/nio/IntBuffer;)J
L21:    lload_3
L22:    invokestatic Method org/lwjgl/opengl/ARBShaderObjects nglGetUniformivARB (IIJJ)V
L25:    return
L26:    
    .end code
.end method

.method static native nglUniform2fARB : (IFFJ)V
.end method

.method static native nglUseProgramObjectARB : (IJ)V
.end method

.method static native nglGetHandleARB : (IJ)I
.end method
.end class
