.version 49 0
.class public final super org/lwjgl/opengl/b
.super java/lang/Object
.field private static char Ljava/util/Map;
.field private static final else Ljava/util/regex/Pattern;
.field private static "enum" [Lorg/lwjgl/opengl/j;
.field private static final do Ljava/util/regex/Pattern;

.method public static break : (Ljava/lang/String;)[Lorg/lwjgl/opengl/j;
    .code stack 2 locals 1
L0:     invokestatic Method org/lwjgl/opengl/b const ()V
L3:     getstatic Field org/lwjgl/opengl/b char Ljava/util/Map;
L6:     aload_0
L7:     invokeinterface InterfaceMethod java/util/Map get (Ljava/lang/Object;)Ljava/lang/Object; 2
L12:    checkcast [Lorg/lwjgl/opengl/j;
L15:    invokevirtual Method [Lorg/lwjgl/opengl/j; clone ()Ljava/lang/Object;
L18:    checkcast [Lorg/lwjgl/opengl/j;
L21:    areturn
L22:    
    .end code
.end method

.method private static const : ()V
    .code stack 6 locals 6
L0:     getstatic Field org/lwjgl/opengl/b char Ljava/util/Map;
L3:     ifnonnull L322
L6:     new java/util/HashMap
L9:     dup
L10:    invokespecial Method java/util/HashMap <init> ()V
L13:    putstatic Field org/lwjgl/opengl/b char Ljava/util/Map;
        .catch java/lang/Throwable from L16 to L189 using L274
L16:    invokestatic Method java/lang/Runtime getRuntime ()Ljava/lang/Runtime;
L19:    iconst_2
L20:    iconst_1
L21:    dup
L22:    pop2
L23:    anewarray java/lang/String
L26:    iconst_1
L27:    dup
L28:    pop2
L29:    dup
L30:    iconst_0
L31:    iconst_1
L32:    dup
L33:    pop2
L34:    ldc "xrandr"
L36:    aastore
L37:    dup
L38:    iconst_1
L39:    dup
L40:    dup
L41:    pop2
L42:    ldc "-q"
L44:    aastore
L45:    invokevirtual Method java/lang/Runtime exec ([Ljava/lang/String;)Ljava/lang/Process;
L48:    astore_0
L49:    new java/util/ArrayList
L52:    dup
L53:    invokespecial Method java/util/ArrayList <init> ()V
L56:    astore_1
L57:    new java/util/ArrayList
L60:    dup
L61:    invokespecial Method java/util/ArrayList <init> ()V
L64:    astore_2
L65:    aconst_null
L66:    astore_3
L67:    new java/io/BufferedReader
L70:    dup
L71:    new java/io/InputStreamReader
L74:    dup
L75:    aload_0
L76:    invokevirtual Method java/lang/Process getInputStream ()Ljava/io/InputStream;
L79:    invokespecial Method java/io/InputStreamReader <init> (Ljava/io/InputStream;)V
L82:    invokespecial Method java/io/BufferedReader <init> (Ljava/io/Reader;)V
L85:    astore 4
L87:    aload 4
L89:    invokevirtual Method java/io/BufferedReader readLine ()Ljava/lang/String;
L92:    dup
L93:    astore 5
L95:    ifnull L221
L98:    aload 5
L100:   invokevirtual Method java/lang/String trim ()Ljava/lang/String;
L103:   dup
L104:   astore 5
L106:   ldc "\\s+"
L108:   invokevirtual Method java/lang/String split (Ljava/lang/String;)[Ljava/lang/String;
L111:   astore 5
L113:   ldc "connected"
L115:   aload 5
L117:   iconst_1
L118:   dup
L119:   dup
L120:   pop2
L121:   aaload
L122:   invokevirtual Method java/lang/String equals (Ljava/lang/Object;)Z
L125:   ifeq L190
L128:   aload_3
L129:   ifnull L166
L132:   getstatic Field org/lwjgl/opengl/b char Ljava/util/Map;
L135:   aload_3
L136:   aload_2
L137:   dup
L138:   invokeinterface InterfaceMethod java/util/List size ()I 1
L143:   anewarray org/lwjgl/opengl/j
L146:   iconst_1
L147:   dup
L148:   pop2
L149:   invokeinterface InterfaceMethod java/util/List toArray ([Ljava/lang/Object;)[Ljava/lang/Object; 2
L154:   invokeinterface InterfaceMethod java/util/Map put (Ljava/lang/Object;Ljava/lang/Object;)Ljava/lang/Object; 3
L159:   aload_2
L160:   invokeinterface InterfaceMethod java/util/List clear ()V 1
L165:   pop
L166:   aload 5
L168:   iconst_0
L169:   iconst_1
L170:   dup
L171:   pop2
L172:   aaload
L173:   astore_3
L174:   aload_1
L175:   aload_3
L176:   aload 5
L178:   iconst_2
L179:   iconst_1
L180:   dup
L181:   pop2
L182:   aaload
L183:   invokestatic Method org/lwjgl/opengl/b break (Ljava/util/List;Ljava/lang/String;Ljava/lang/String;)V
L186:   goto L87
L189:   athrow
        .catch java/lang/Throwable from L190 to L220 using L274
L190:   ldc "\\d*x\\d*"
L192:   aload 5
L194:   iconst_0
L195:   iconst_1
L196:   dup
L197:   pop2
L198:   aaload
L199:   invokestatic Method java/util/regex/Pattern matches (Ljava/lang/String;Ljava/lang/CharSequence;)Z
L202:   ifeq L87
L205:   aload_2
L206:   aload_3
L207:   aload 5
L209:   iconst_0
L210:   iconst_1
L211:   dup
L212:   pop2
L213:   aaload
L214:   invokestatic Method org/lwjgl/opengl/b break (Ljava/util/List;Ljava/lang/String;Ljava/lang/String;)V
L217:   goto L87
L220:   athrow
        .catch java/lang/Throwable from L221 to L273 using L274
L221:   getstatic Field org/lwjgl/opengl/b char Ljava/util/Map;
L224:   aload_3
L225:   aload_2
L226:   dup
L227:   invokeinterface InterfaceMethod java/util/List size ()I 1
L232:   anewarray org/lwjgl/opengl/j
L235:   iconst_1
L236:   dup
L237:   pop2
L238:   invokeinterface InterfaceMethod java/util/List toArray ([Ljava/lang/Object;)[Ljava/lang/Object; 2
L243:   invokeinterface InterfaceMethod java/util/Map put (Ljava/lang/Object;Ljava/lang/Object;)Ljava/lang/Object; 3
L248:   pop
L249:   aload_1
L250:   dup
L251:   invokeinterface InterfaceMethod java/util/List size ()I 1
L256:   anewarray org/lwjgl/opengl/j
L259:   iconst_1
L260:   dup
L261:   pop2
L262:   invokeinterface InterfaceMethod java/util/List toArray ([Ljava/lang/Object;)[Ljava/lang/Object; 2
L267:   checkcast [Lorg/lwjgl/opengl/j;
L270:   putstatic Field org/lwjgl/opengl/b "enum" [Lorg/lwjgl/opengl/j;
L273:   return
L274:   astore_0
L275:   new java/lang/StringBuilder
L278:   dup
L279:   invokespecial Method java/lang/StringBuilder <init> ()V
L282:   iconst_0
L283:   ldc "Exception in XRandR.populate(): "
L285:   invokevirtual Method java/lang/StringBuilder insert (ILjava/lang/String;)Ljava/lang/StringBuilder;
L288:   aload_0
L289:   invokevirtual Method java/lang/Throwable getMessage ()Ljava/lang/String;
L292:   invokevirtual Method java/lang/StringBuilder append (Ljava/lang/String;)Ljava/lang/StringBuilder;
L295:   invokevirtual Method java/lang/StringBuilder toString ()Ljava/lang/String;
L298:   invokestatic Method org/lwjgl/LWJGLUtil log (Ljava/lang/CharSequence;)V
L301:   getstatic Field org/lwjgl/opengl/b char Ljava/util/Map;
L304:   invokeinterface InterfaceMethod java/util/Map clear ()V 1
L309:   iconst_0
L310:   iconst_1
L311:   dup
L312:   pop2
L313:   anewarray org/lwjgl/opengl/j
L316:   iconst_1
L317:   dup
L318:   pop2
L319:   putstatic Field org/lwjgl/opengl/b "enum" [Lorg/lwjgl/opengl/j;
L322:   return
L323:   
        .attribute StackMap b'\x00\x08\x00\x57\x00\x05\x07\x00\x42\x07\x00\x3B\x07\x00\x3B\x07\x00\x31\x07\x00\x3E\x00\x00\x00\xA6\x00\x06\x07\x00\x42\x07\x00\x3B\x07\x00\x3B\x07\x00\x31\x07\x00\x3E\x07\x00\x72\x00\x00\x00\xBD\x00\x00\x00\x01\x07\x00\x24\x00\xBE\x00\x06\x07\x00\x42\x07\x00\x3B\x07\x00\x3B\x07\x00\x31\x07\x00\x3E\x07\x00\x72\x00\x00\x00\xDC\x00\x00\x00\x01\x07\x00\x24\x00\xDD\x00\x06\x07\x00\x42\x07\x00\x3B\x07\x00\x3B\x07\x00\x31\x07\x00\x3E\x07\x00\x31\x00\x00\x01\x12\x00\x00\x00\x01\x07\x00\x24\x01\x42\x00\x00\x00\x00'
    .end code
.end method

.method public static else : ()[Lorg/lwjgl/opengl/j;
    .code stack 1 locals 0
L0:     invokestatic Method org/lwjgl/opengl/b const ()V
L3:     getstatic Field org/lwjgl/opengl/b "enum" [Lorg/lwjgl/opengl/j;
L6:     invokevirtual Method [Lorg/lwjgl/opengl/j; clone ()Ljava/lang/Object;
L9:     checkcast [Lorg/lwjgl/opengl/j;
L12:    areturn
L13:    
    .end code
.end method

.method public <init> : ()V
    .code stack 1 locals 1
L0:     aload_0
L1:     invokespecial Method java/lang/Object <init> ()V
L4:     return
L5:     
    .end code
.end method

.method static <clinit> : ()V
    .code stack 1 locals 0
L0:     ldc "^(\\d+)x(\\d+)\\+(\\d+)\\+(\\d+)$"
L2:     invokestatic Method java/util/regex/Pattern compile (Ljava/lang/String;)Ljava/util/regex/Pattern;
L5:     putstatic Field org/lwjgl/opengl/b else Ljava/util/regex/Pattern;
L8:     ldc "^(\\d+)x(\\d+)$"
L10:    invokestatic Method java/util/regex/Pattern compile (Ljava/lang/String;)Ljava/util/regex/Pattern;
L13:    putstatic Field org/lwjgl/opengl/b do Ljava/util/regex/Pattern;
L16:    return
L17:    
    .end code
.end method

.method private static break : (Ljava/util/List;Ljava/lang/String;Ljava/lang/String;)V
    .code stack 9 locals 7
L0:     getstatic Field org/lwjgl/opengl/b else Ljava/util/regex/Pattern;
L3:     aload_2
L4:     invokevirtual Method java/util/regex/Pattern matcher (Ljava/lang/CharSequence;)Ljava/util/regex/Matcher;
L7:     dup
L8:     astore_3
L9:     invokevirtual Method java/util/regex/Matcher matches ()Z
L12:    ifne L55
L15:    getstatic Field org/lwjgl/opengl/b do Ljava/util/regex/Pattern;
L18:    aload_2
L19:    invokevirtual Method java/util/regex/Pattern matcher (Ljava/lang/CharSequence;)Ljava/util/regex/Matcher;
L22:    dup
L23:    astore_3
L24:    invokevirtual Method java/util/regex/Matcher matches ()Z
L27:    ifne L55
L30:    new java/lang/StringBuilder
L33:    dup
L34:    invokespecial Method java/lang/StringBuilder <init> ()V
L37:    iconst_0
L38:    ldc "Did not match: "
L40:    invokevirtual Method java/lang/StringBuilder insert (ILjava/lang/String;)Ljava/lang/StringBuilder;
L43:    aload_2
L44:    invokevirtual Method java/lang/StringBuilder append (Ljava/lang/String;)Ljava/lang/StringBuilder;
L47:    invokevirtual Method java/lang/StringBuilder toString ()Ljava/lang/String;
L50:    invokestatic Method org/lwjgl/LWJGLUtil log (Ljava/lang/CharSequence;)V
L53:    return
L54:    athrow
L55:    aload_3
L56:    dup
L57:    dup_x1
L58:    iconst_1
L59:    dup
L60:    dup
L61:    pop2
L62:    invokevirtual Method java/util/regex/Matcher group (I)Ljava/lang/String;
L65:    invokestatic Method java/lang/Integer parseInt (Ljava/lang/String;)I
L68:    istore_2
L69:    iconst_2
L70:    iconst_1
L71:    dup
L72:    pop2
L73:    invokevirtual Method java/util/regex/Matcher group (I)Ljava/lang/String;
L76:    invokestatic Method java/lang/Integer parseInt (Ljava/lang/String;)I
L79:    istore 4
L81:    invokevirtual Method java/util/regex/Matcher groupCount ()I
L84:    iconst_3
L85:    iconst_1
L86:    dup
L87:    pop2
L88:    if_icmple L122
L91:    aload_0
L92:    aload_3
L93:    dup
L94:    iconst_3
L95:    iconst_1
L96:    dup
L97:    pop2
L98:    invokevirtual Method java/util/regex/Matcher group (I)Ljava/lang/String;
L101:   invokestatic Method java/lang/Integer parseInt (Ljava/lang/String;)I
L104:   istore 5
L106:   iconst_4
L107:   iconst_1
L108:   dup
L109:   pop2
L110:   invokevirtual Method java/util/regex/Matcher group (I)Ljava/lang/String;
L113:   invokestatic Method java/lang/Integer parseInt (Ljava/lang/String;)I
L116:   istore 6
L118:   goto L135
L121:   athrow
L122:   iconst_0
L123:   iconst_1
L124:   dup
L125:   pop2
L126:   istore 5
L128:   iconst_0
L129:   iconst_1
L130:   dup
L131:   pop2
L132:   istore 6
L134:   aload_0
L135:   new org/lwjgl/opengl/j
L138:   dup
L139:   aload_1
L140:   iload_2
L141:   iload 4
L143:   iload 5
L145:   iload 6
L147:   aconst_null
L148:   invokespecial Method org/lwjgl/opengl/j <init> (Ljava/lang/String;IIIILorg/lwjgl/opengl/f;)V
L151:   invokeinterface InterfaceMethod java/util/List add (Ljava/lang/Object;)Z 2
L156:   pop
L157:   return
L158:   
        .attribute StackMap b'\x00\x05\x00\x36\x00\x00\x00\x01\x07\x00\x24\x00\x37\x00\x04\x07\x00\x61\x07\x00\x31\x07\x00\x31\x07\x00\xAE\x00\x00\x00\x79\x00\x00\x00\x01\x07\x00\x24\x00\x7A\x00\x05\x07\x00\x61\x07\x00\x31\x01\x07\x00\xAE\x01\x00\x00\x00\x87\x00\x07\x07\x00\x61\x07\x00\x31\x01\x07\x00\xAE\x01\x01\x01\x00\x01\x07\x00\x61'
    .end code
.end method

.method public static varargs break : ([Lorg/lwjgl/opengl/j;)V
    .code stack 5 locals 10
L0:     aload_0
L1:     arraylength
L2:     ifne L15
L5:     new java/lang/IllegalArgumentException
L8:     dup
L9:     ldc "Must specify at least one screen"
L11:    invokespecial Method java/lang/IllegalArgumentException <init> (Ljava/lang/String;)V
L14:    athrow
L15:    new java/util/ArrayList
L18:    dup
L19:    invokespecial Method java/util/ArrayList <init> ()V
L22:    dup
L23:    astore_1
L24:    ldc "xrandr"
L26:    invokeinterface InterfaceMethod java/util/List add (Ljava/lang/Object;)Z 2
L31:    getstatic Field org/lwjgl/opengl/b "enum" [Lorg/lwjgl/opengl/j;
L34:    astore_2
L35:    pop
L36:    aload_2
L37:    arraylength
L38:    istore_3
L39:    iconst_0
L40:    iconst_1
L41:    dup
L42:    pop2
L43:    dup
L44:    istore 4
L46:    iload_3
L47:    if_icmpge L162
L50:    aload_2
L51:    iload 4
L53:    aaload
L54:    astore 5
L56:    iconst_0
L57:    iconst_1
L58:    dup
L59:    pop2
L60:    istore 6
L62:    aload_0
L63:    dup
L64:    astore 7
L66:    arraylength
L67:    istore 8
L69:    iconst_0
L70:    iconst_1
L71:    dup
L72:    pop2
L73:    dup
L74:    istore 9
L76:    iload 8
L78:    if_icmpge L120
L81:    aload 7
L83:    iload 9
L85:    aaload
L86:    getfield Field org/lwjgl/opengl/j this Ljava/lang/String;
L89:    aload 5
L91:    getfield Field org/lwjgl/opengl/j this Ljava/lang/String;
L94:    invokevirtual Method java/lang/String equals (Ljava/lang/Object;)Z
L97:    ifeq L111
L100:   iconst_1
L101:   dup
L102:   dup
L103:   pop2
L104:   dup
L105:   istore 6
L107:   goto L122
L110:   athrow
L111:   iinc 9 1
L114:   iload 9
L116:   goto L76
L119:   athrow
L120:   iload 6
L122:   ifne L154
L125:   aload_1
L126:   ldc "--output"
L128:   invokeinterface InterfaceMethod java/util/List add (Ljava/lang/Object;)Z 2
L133:   aload_1
L134:   aload 5
L136:   getfield Field org/lwjgl/opengl/j this Ljava/lang/String;
L139:   invokeinterface InterfaceMethod java/util/List add (Ljava/lang/Object;)Z 2
L144:   aload_1
L145:   ldc "--off"
L147:   invokeinterface InterfaceMethod java/util/List add (Ljava/lang/Object;)Z 2
L152:   pop
L153:   pop2
L154:   iinc 4 1
L157:   iload 4
L159:   goto L46
L162:   aload_0
L163:   dup
L164:   astore_2
L165:   arraylength
L166:   istore_3
L167:   iconst_0
L168:   iconst_1
L169:   dup
L170:   pop2
L171:   dup
L172:   istore 4
L174:   iload_3
L175:   if_icmpge L197
L178:   aload_2
L179:   iload 4
L181:   iinc 4 1
L184:   aaload
L185:   dup
L186:   astore 5
L188:   aload_1
L189:   invokestatic Method org/lwjgl/opengl/j break (Lorg/lwjgl/opengl/j;Ljava/util/List;)V
L192:   iload 4
L194:   goto L174
        .catch java/io/IOException from L197 to L286 using L287
L197:   invokestatic Method java/lang/Runtime getRuntime ()Ljava/lang/Runtime;
L200:   aload_1
L201:   dup
L202:   invokeinterface InterfaceMethod java/util/List size ()I 1
L207:   anewarray java/lang/String
L210:   iconst_1
L211:   dup
L212:   pop2
L213:   invokeinterface InterfaceMethod java/util/List toArray ([Ljava/lang/Object;)[Ljava/lang/Object; 2
L218:   checkcast [Ljava/lang/String;
L221:   invokevirtual Method java/lang/Runtime exec ([Ljava/lang/String;)Ljava/lang/Process;
L224:   astore_2
L225:   new java/io/BufferedReader
L228:   dup
L229:   new java/io/InputStreamReader
L232:   dup
L233:   aload_2
L234:   invokevirtual Method java/lang/Process getInputStream ()Ljava/io/InputStream;
L237:   invokespecial Method java/io/InputStreamReader <init> (Ljava/io/InputStream;)V
L240:   invokespecial Method java/io/BufferedReader <init> (Ljava/io/Reader;)V
L243:   dup
L244:   astore_3
L245:   invokevirtual Method java/io/BufferedReader readLine ()Ljava/lang/String;
L248:   dup
L249:   astore 4
L251:   ifnull L282
L254:   new java/lang/StringBuilder
L257:   dup
L258:   invokespecial Method java/lang/StringBuilder <init> ()V
L261:   iconst_0
L262:   ldc "Unexpected output from xrandr process: "
L264:   invokevirtual Method java/lang/StringBuilder insert (ILjava/lang/String;)Ljava/lang/StringBuilder;
L267:   aload 4
L269:   invokevirtual Method java/lang/StringBuilder append (Ljava/lang/String;)Ljava/lang/StringBuilder;
L272:   invokevirtual Method java/lang/StringBuilder toString ()Ljava/lang/String;
L275:   invokestatic Method org/lwjgl/LWJGLUtil log (Ljava/lang/CharSequence;)V
L278:   aload_3
L279:   goto L245
L282:   aload_0
L283:   putstatic Field org/lwjgl/opengl/b "enum" [Lorg/lwjgl/opengl/j;
L286:   return
L287:   astore_2
L288:   new java/lang/StringBuilder
L291:   dup
L292:   invokespecial Method java/lang/StringBuilder <init> ()V
L295:   iconst_0
L296:   ldc "XRandR exception in setConfiguration(): "
L298:   invokevirtual Method java/lang/StringBuilder insert (ILjava/lang/String;)Ljava/lang/StringBuilder;
L301:   aload_2
L302:   invokevirtual Method java/io/IOException getMessage ()Ljava/lang/String;
L305:   invokevirtual Method java/lang/StringBuilder append (Ljava/lang/String;)Ljava/lang/StringBuilder;
L308:   invokevirtual Method java/lang/StringBuilder toString ()Ljava/lang/String;
L311:   invokestatic Method org/lwjgl/LWJGLUtil log (Ljava/lang/CharSequence;)V
L314:   return
L315:   
        .attribute StackMap b'\x00\x0F\x00\x0F\x00\x01\x07\x00\x1E\x00\x00\x00\x2E\x00\x05\x07\x00\x1E\x07\x00\x3B\x07\x00\x1E\x01\x01\x00\x01\x01\x00\x4C\x00\x0A\x07\x00\x1E\x07\x00\x3B\x07\x00\x1E\x01\x01\x07\x00\x08\x01\x07\x00\x1E\x01\x01\x00\x01\x01\x00\x6E\x00\x00\x00\x01\x07\x00\x24\x00\x6F\x00\x0A\x07\x00\x1E\x07\x00\x3B\x07\x00\x1E\x01\x01\x07\x00\x08\x01\x07\x00\x1E\x01\x01\x00\x00\x00\x77\x00\x00\x00\x01\x07\x00\x24\x00\x78\x00\x0A\x07\x00\x1E\x07\x00\x3B\x07\x00\x1E\x01\x01\x07\x00\x08\x01\x07\x00\x1E\x01\x01\x00\x00\x00\x7A\x00\x0A\x07\x00\x1E\x07\x00\x3B\x07\x00\x1E\x01\x01\x07\x00\x08\x01\x07\x00\x1E\x01\x01\x00\x01\x01\x00\x9A\x00\x0A\x07\x00\x1E\x07\x00\x3B\x07\x00\x1E\x01\x01\x07\x00\x08\x01\x07\x00\x1E\x01\x01\x00\x00\x00\xA2\x00\x05\x07\x00\x1E\x07\x00\x3B\x07\x00\x1E\x01\x01\x00\x00\x00\xAE\x00\x05\x07\x00\x1E\x07\x00\x3B\x07\x00\x1E\x01\x01\x00\x01\x01\x00\xC5\x00\x05\x07\x00\x1E\x07\x00\x3B\x07\x00\x1E\x01\x01\x00\x00\x00\xF5\x00\x04\x07\x00\x1E\x07\x00\x3B\x07\x00\x42\x07\x00\x3E\x00\x01\x07\x00\x3E\x01\x1A\x00\x05\x07\x00\x1E\x07\x00\x3B\x07\x00\x42\x07\x00\x3E\x07\x00\x31\x00\x00\x01\x1F\x00\x03\x07\x00\x1E\x07\x00\x3B\x07\x00\x04\x00\x01\x07\x00\xC9'
    .end code
.end method

.method public static break : ()[Ljava/lang/String;
    .code stack 4 locals 0
L0:     invokestatic Method org/lwjgl/opengl/b const ()V
L3:     getstatic Field org/lwjgl/opengl/b char Ljava/util/Map;
L6:     invokeinterface InterfaceMethod java/util/Map keySet ()Ljava/util/Set; 1
L11:    getstatic Field org/lwjgl/opengl/b char Ljava/util/Map;
L14:    invokeinterface InterfaceMethod java/util/Map size ()I 1
L19:    anewarray java/lang/String
L22:    iconst_1
L23:    dup
L24:    pop2
L25:    invokeinterface InterfaceMethod java/util/Set toArray ([Ljava/lang/Object;)[Ljava/lang/Object; 2
L30:    checkcast [Ljava/lang/String;
L33:    areturn
L34:    
    .end code
.end method
.innerclasses
    org/lwjgl/opengl/f org/lwjgl/opengl/b [0] static synthetic
    org/lwjgl/opengl/j org/lwjgl/opengl/b [0] public static
.end innerclasses
.end class
