.version 49 0
.class public final super org/lwjgl/opengl/BB
.super java/lang/Object
.field public static final CA I = 33425
.field public static final DB I = 33479
.field public static final yB I = 33434
.field public static final FB I = 33395
.field public static final Rd I = 33440
.field public static final dc I = 33463
.field public static final hd I = 33433
.field public static final RA I = 33481
.field public static final md I = 33437
.field public static final TA I = 33450
.field public static final Sb I = 33454
.field public static final v I = 33469
.field public static final p I = 33477
.field public static final U I = 33470
.field public static final V I = 33404
.field public static final R I = 33394
.field public static final z I = 33478
.field public static final q I = 37120
.field public static final X I = 33473
.field public static final P I = 33415
.field public static final O I = 33420
.field public static final w I = 33441
.field public static final y I = 33392
.field public static final o I = 33407
.field public static final Y I = 33396
.field public static final S I = 33475
.field public static final N I = 33455
.field public static final u I = 33461
.field public static final s I = 36873
.field public static final t I = 35866
.field public static final W I = 33466
.field public static final Q I = 33391
.field public static final T I = 33403
.field public static final r I = 33421
.field public static final x I = 33438
.field public static final n I = 33471
.field public static final M I = 33410
.field public static final L I = 33399
.field public static final H I = 33427
.field public static final d I = 33435
.field public static final e I = 33432
.field public static final g I = 33408
.field public static final k I = 35864
.field public static final a I = 33405
.field public static final F I = 33457
.field public static final A I = 33480
.field public static final E I = 33467
.field public static final C I = 33422
.field public static final K I = 33412
.field public static final G I = 33418
.field public static final B I = 33459
.field public static final c I = 33476
.field public static final "synchronized" I = 33443
.field public static final i I = 33468
.field public static final m I = 33464
.field public static final h I = 37760
.field public static final J I = 33485
.field public static final l I = 33472
.field public static final D I = 33402
.field public static final f I = 33452
.field public static final j I = 35882
.field public static final I I = 36161
.field public static final b I = 33423
.field public static final implements I = 33490
.field public static final return I = 33445
.field public static final default I = 32937
.field public static final switch I = 33486
.field public static final "interface" I = 33453
.field public static final "private" I = 34465
.field public static final assert I = 3552
.field public static final boolean I = 34037
.field public static final "strictfp" I = 37122
.field public static final "abstract" I = 33400
.field public static final "public" I = 33458
.field public static final "volatile" I = 33393
.field public static final double I = 34067
.field public static final throw I = 33431
.field public static final package I = 33439
.field public static final finally I = 33449
.field public static final "transient" I = 33462
.field public static final while I = 33446
.field public static final instanceof I = 33487
.field public static final "protected" I = 33489
.field public static final import I = 33442
.field public static final "native" I = 33417
.field public static final throws I = 33460
.field public static final "static" I = 33465
.field public static final continue I = 33448
.field public static final extends I = 33401
.field public static final float I = 33411
.field public static final "final" I = 33447
.field public static final catch I = 33429
.field public static final false I = 33488
.field public static final class I = 33416
.field public static final if I = 3553
.field public static final true I = 33474
.field public static final for I = 33491
.field public static final case I = 33428
.field public static final byte I = 33444
.field public static final "super" I = 33414
.field public static final int I = 33483
.field public static final short I = 33398
.field public static final goto I = 33426
.field public static final break I = 33406
.field public static final long I = 33409
.field public static final void I = 33436
.field public static final try I = 32879
.field public static final const I = 33484
.field public static final new I = 33424
.field public static final null I = 33419
.field public static final this I = 33482
.field public static final char I = 33397
.field public static final else I = 37063
.field public static final "enum" I = 33413
.field public static final do I = 33430

.method private <init> : ()V
    .code stack 1 locals 1
L0:     aload_0
L1:     invokespecial Method java/lang/Object <init> ()V
L4:     return
L5:     
    .end code
.end method

.method public static break : (IIILjava/nio/LongBuffer;)V
    .code stack 4 locals 4
L0:     iload_0
L1:     iload_1
L2:     iload_2
L3:     aload_3
L4:     invokestatic Method org/lwjgl/opengl/GL43 break (IIILjava/nio/LongBuffer;)V
L7:     return
L8:     
    .end code
.end method

.method public static break : (III)J
    .code stack 3 locals 3
L0:     iload_0
L1:     iload_1
L2:     iload_2
L3:     invokestatic Method org/lwjgl/opengl/GL43 float (III)J
L6:     lreturn
L7:     
    .end code
.end method
.end class
