.version 49 0
.class public final super org/lwjgl/opengl/ed
.super java/lang/Object

.method private <init> : ()V
    .code stack 1 locals 1
L0:     aload_0
L1:     invokespecial Method java/lang/Object <init> ()V
L4:     return
L5:     
    .end code
.end method

.method public static break : (ILjava/nio/ByteBuffer;II)V
    .code stack 4 locals 4
L0:     iload_0
L1:     aload_1
L2:     iload_2
L3:     iload_3
L4:     invokestatic Method org/lwjgl/opengl/GL43 break (ILjava/nio/ByteBuffer;II)V
L7:     return
L8:     
    .end code
.end method

.method public static break : (IILjava/nio/IntBuffer;II)V
    .code stack 5 locals 5
L0:     iload_0
L1:     iload_1
L2:     aload_2
L3:     iload_3
L4:     iload 4
L6:     invokestatic Method org/lwjgl/opengl/GL43 break (IILjava/nio/IntBuffer;II)V
L9:     return
L10:    
    .end code
.end method

.method public static break : (ILjava/nio/IntBuffer;II)V
    .code stack 4 locals 4
L0:     iload_0
L1:     aload_1
L2:     iload_2
L3:     iload_3
L4:     invokestatic Method org/lwjgl/opengl/GL43 break (ILjava/nio/IntBuffer;II)V
L7:     return
L8:     
    .end code
.end method

.method public static break : (IIJII)V
    .code stack 6 locals 6
L0:     iload_0
L1:     iload_1
L2:     lload_2
L3:     iload 4
L5:     iload 5
L7:     invokestatic Method org/lwjgl/opengl/GL43 break (IIJII)V
L10:    return
L11:    
    .end code
.end method

.method public static break : (IILjava/nio/ByteBuffer;II)V
    .code stack 5 locals 5
L0:     iload_0
L1:     iload_1
L2:     aload_2
L3:     iload_3
L4:     iload 4
L6:     invokestatic Method org/lwjgl/opengl/GL43 break (IILjava/nio/ByteBuffer;II)V
L9:     return
L10:    
    .end code
.end method

.method public static break : (IJII)V
    .code stack 5 locals 5
L0:     iload_0
L1:     lload_1
L2:     iload_3
L3:     iload 4
L5:     invokestatic Method org/lwjgl/opengl/GL43 break (IJII)V
L8:     return
L9:     
    .end code
.end method
.end class
