.version 49 0
.class public final super org/lwjgl/opengl/fc
.super java/lang/Object
.field public static final field5294 I = 35097

.method public static method5491 : (IIF)V
    .code stack 3 locals 3
L0:     iload_0
L1:     iload_1
L2:     fload_2
L3:     invokestatic Method org/lwjgl/opengl/GL33 method4326 (IIF)V
L6:     return
L7:     
    .end code
.end method

.method public static method5492 : (II)F
    .code stack 2 locals 2
L0:     iload_0
L1:     iload_1
L2:     invokestatic Method org/lwjgl/opengl/GL33 method4339 (II)F
L5:     freturn
L6:     
    .end code
.end method

.method private <init> : ()V
    .code stack 1 locals 1
L0:     aload_0
L1:     invokespecial Method java/lang/Object <init> ()V
L4:     return
L5:     
    .end code
.end method

.method public static method5493 : (II)I
    .code stack 2 locals 2
L0:     iload_0
L1:     iload_1
L2:     invokestatic Method org/lwjgl/opengl/GL33 method4314 (II)I
L5:     ireturn
L6:     
    .end code
.end method

.method public static method5494 : (II)I
    .code stack 2 locals 2
L0:     iload_0
L1:     iload_1
L2:     invokestatic Method org/lwjgl/opengl/GL33 method4309 (II)I
L5:     ireturn
L6:     
    .end code
.end method

.method public static method5495 : ()I
    .code stack 1 locals 0
L0:     invokestatic Method org/lwjgl/opengl/GL33 method4329 ()I
L3:     ireturn
L4:     
    .end code
.end method

.method public static method5496 : (III)V
    .code stack 3 locals 3
L0:     iload_0
L1:     iload_1
L2:     iload_2
L3:     invokestatic Method org/lwjgl/opengl/GL33 method4330 (III)V
L6:     return
L7:     
    .end code
.end method

.method public static method5497 : (I)Z
    .code stack 1 locals 1
L0:     iload_0
L1:     invokestatic Method org/lwjgl/opengl/GL33 method4349 (I)Z
L4:     ireturn
L5:     
    .end code
.end method

.method public static method5498 : (IILjava/nio/FloatBuffer;)V
    .code stack 3 locals 3
L0:     iload_0
L1:     iload_1
L2:     aload_2
L3:     invokestatic Method org/lwjgl/opengl/GL33 method4336 (IILjava/nio/FloatBuffer;)V
L6:     return
L7:     
    .end code
.end method

.method public static method5499 : (IILjava/nio/IntBuffer;)V
    .code stack 3 locals 3
L0:     iload_0
L1:     iload_1
L2:     aload_2
L3:     invokestatic Method org/lwjgl/opengl/GL33 method4348 (IILjava/nio/IntBuffer;)V
L6:     return
L7:     
    .end code
.end method

.method public static method5500 : (II)I
    .code stack 2 locals 2
L0:     iload_0
L1:     iload_1
L2:     invokestatic Method org/lwjgl/opengl/GL33 method4343 (II)I
L5:     ireturn
L6:     
    .end code
.end method

.method public static method5501 : (IILjava/nio/IntBuffer;)V
    .code stack 3 locals 3
L0:     iload_0
L1:     iload_1
L2:     aload_2
L3:     invokestatic Method org/lwjgl/opengl/GL33 method4324 (IILjava/nio/IntBuffer;)V
L6:     return
L7:     
    .end code
.end method

.method public static method5502 : (IILjava/nio/IntBuffer;)V
    .code stack 3 locals 3
L0:     iload_0
L1:     iload_1
L2:     aload_2
L3:     invokestatic Method org/lwjgl/opengl/GL33 method4303 (IILjava/nio/IntBuffer;)V
L6:     return
L7:     
    .end code
.end method

.method public static method5503 : (Ljava/nio/IntBuffer;)V
    .code stack 1 locals 1
L0:     aload_0
L1:     invokestatic Method org/lwjgl/opengl/GL33 method4299 (Ljava/nio/IntBuffer;)V
L4:     return
L5:     
    .end code
.end method

.method public static method5504 : (I)V
    .code stack 1 locals 1
L0:     iload_0
L1:     invokestatic Method org/lwjgl/opengl/GL33 method4296 (I)V
L4:     return
L5:     
    .end code
.end method

.method public static method5505 : (IILjava/nio/IntBuffer;)V
    .code stack 3 locals 3
L0:     iload_0
L1:     iload_1
L2:     aload_2
L3:     invokestatic Method org/lwjgl/opengl/GL33 method4341 (IILjava/nio/IntBuffer;)V
L6:     return
L7:     
    .end code
.end method

.method public static method5506 : (IILjava/nio/IntBuffer;)V
    .code stack 3 locals 3
L0:     iload_0
L1:     iload_1
L2:     aload_2
L3:     invokestatic Method org/lwjgl/opengl/GL33 method4319 (IILjava/nio/IntBuffer;)V
L6:     return
L7:     
    .end code
.end method

.method public static method5507 : (Ljava/nio/IntBuffer;)V
    .code stack 1 locals 1
L0:     aload_0
L1:     invokestatic Method org/lwjgl/opengl/GL33 method4354 (Ljava/nio/IntBuffer;)V
L4:     return
L5:     
    .end code
.end method

.method public static method5508 : (II)V
    .code stack 2 locals 2
L0:     iload_0
L1:     iload_1
L2:     invokestatic Method org/lwjgl/opengl/GL33 new (II)V
L5:     return
L6:     
    .end code
.end method

.method public static method5509 : (IILjava/nio/FloatBuffer;)V
    .code stack 3 locals 3
L0:     iload_0
L1:     iload_1
L2:     aload_2
L3:     invokestatic Method org/lwjgl/opengl/GL33 method4344 (IILjava/nio/FloatBuffer;)V
L6:     return
L7:     
    .end code
.end method

.method public static method5510 : (IILjava/nio/IntBuffer;)V
    .code stack 3 locals 3
L0:     iload_0
L1:     iload_1
L2:     aload_2
L3:     invokestatic Method org/lwjgl/opengl/GL33 method4301 (IILjava/nio/IntBuffer;)V
L6:     return
L7:     
    .end code
.end method
.end class
