.version 49 0
.class public final super org/lwjgl/opengl/Gb
.super java/lang/Object
.field public static final field4210 I = 37122
.field public static final true I = 37128
.field public static final field4211 I = 37136
.field public static final field4212 I = 37126
.field public static final field4213 I = 37131
.field public static final field4214 I = 37134
.field public static final field4215 I = 37133
.field public static final field4216 I = 36433
.field public static final field4217 I = 37124
.field public static final field4218 I = 37132
.field public static final field4219 I = 37129
.field public static final field4220 I = 36441
.field public static final try I = 36434
.field public static final field4221 I = 37121
.field public static final new I = 37130
.field public static final field4222 I = 37135
.field public static final this I = 37127
.field public static final field4223 I = 37125
.field public static final field4224 I = 37120
.field public static final field4225 I = 37123
.field public static final field4226 I = 36432

.method public static method4615 : (IIIIIZ)V
    .code stack 6 locals 6
L0:     iload_0
L1:     iload_1
L2:     iload_2
L3:     iload_3
L4:     iload 4
L6:     iload 5
L8:     invokestatic Method org/lwjgl/opengl/GL32 method4272 (IIIIIZ)V
L11:    return
L12:    
    .end code
.end method

.method public static method4616 : (II)V
    .code stack 2 locals 2
L0:     iload_0
L1:     iload_1
L2:     invokestatic Method org/lwjgl/opengl/GL32 method4277 (II)V
L5:     return
L6:     
    .end code
.end method

.method private <init> : ()V
    .code stack 1 locals 1
L0:     aload_0
L1:     invokespecial Method java/lang/Object <init> ()V
L4:     return
L5:     
    .end code
.end method

.method public static method4617 : (IIIIIIZ)V
    .code stack 7 locals 7
L0:     iload_0
L1:     iload_1
L2:     iload_2
L3:     iload_3
L4:     iload 4
L6:     iload 5
L8:     iload 6
L10:    invokestatic Method org/lwjgl/opengl/GL32 method4265 (IIIIIIZ)V
L13:    return
L14:    
    .end code
.end method

.method public static method4618 : (IILjava/nio/FloatBuffer;)V
    .code stack 3 locals 3
L0:     iload_0
L1:     iload_1
L2:     aload_2
L3:     invokestatic Method org/lwjgl/opengl/GL32 method4268 (IILjava/nio/FloatBuffer;)V
L6:     return
L7:     
    .end code
.end method
.end class
