.version 49 0
.class public final super org/lwjgl/opengl/GL11
.super java/lang/Object
.field public static final TE I = 512
.field public static final wD I = 65536
.field public static final mf I = 3344
.field public static final tf I = 519
.field public static final Yd I = 32915
.field public static final GE I = 3155
.field public static final ve I = 32847
.field public static final Fe I = 3418
.field public static final DF I = 64
.field public static final ud I = 3185
.field public static final VE I = 32839
.field public static final Of I = 3257
.field public static final OE I = 3169
.field public static final Vd I = 2852
.field public static final Jg I = 1
.field public static final of I = 3419
.field public static final rE I = 0
.field public static final Nf I = 16389
.field public static final Jf I = 3168
.field public static final kE I = 32831
.field public static final Hf I = 10752
.field public static final QF I = 9217
.field public static final KD I = 3153
.field public static final Eg I = 3381
.field public static final Lf I = 32913
.field public static final De I = 3379
.field public static final aD I = 1028
.field public static final KF I = 12288
.field public static final me I = 514
.field public static final uf I = 5383
.field public static final vf I = 256
.field public static final ze I = 262144
.field public static final he I = 3330
.field public static final Cg I = 9472
.field public static final uD I = 32904
.field public static final AD I = 2880
.field public static final qE I = 4096
.field public static final UF I = 2918
.field public static final eg I = 32899
.field public static final zF I = 8
.field public static final xf I = 2885
.field public static final ID I = 32901
.field public static final Wd I = 10768
.field public static final QD I = 2048
.field public static final Ve I = 2928
.field public static final Ee I = 16385
.field public static final td I = 7425
.field public static final de I = 2930
.field public static final iD I = 2931
.field public static final Dg I = 32894
.field public static final pf I = 4
.field public static final SE I = 2968
.field public static final mg I = 4097
.field public static final Qf I = 4864
.field public static final OF I = 2960
.field public static final VF I = 3456
.field public static final ue I = 4611
.field public static final dD I = 3552
.field public static final vd I = 32836
.field public static final jF I = 7169
.field public static final wE I = 3355
.field public static final lE I = 2824
.field public static final kg I = 2929
.field public static final cg I = 2944
.field public static final We I = 12290
.field public static final XF I = 2961
.field public static final UE I = 3315
.field public static final iE I = 32902
.field public static final Df I = 3356
.field public static final CF I = 32895
.field public static final aE I = 1540
.field public static final tE I = 7938
.field public static final Ef I = 2900
.field public static final YE I = 32833
.field public static final NF I = 12289
.field public static final GD I = 1797
.field public static final ae I = 3104
.field public static final Pf I = 12292
.field public static final zD I = 3072
.field public static final xD I = 8960
.field public static final ge I = 515
.field public static final Be I = 2977
.field public static final KE I = 4354
.field public static final Xd I = 3056
.field public static final TF I = 10240
.field public static final BF I = 3352
.field public static final sf I = 3057
.field public static final Ne I = 32770
.field public static final Ye I = 5381
.field public static final sD I = 3252
.field public static final JE I = 3106
.field public static final qF I = 768
.field public static final bg I = 3568
.field public static final Wf I = 5379
.field public static final IE I = 3256
.field public static final ce I = 7424
.field public static final Bg I = 771
.field public static final fe I = 3569
.field public static final sF I = 513
.field public static final oD I = 3538
.field public static final jg I = 3
.field public static final gF I = 6
.field public static final fD I = 3136
.field public static final CD I = 2560
.field public static final fF I = 3536
.field public static final ND I = 1281
.field public static final sE I = 32832
.field public static final VD I = 5128
.field public static final ig I = 773
.field public static final AF I = 2850
.field public static final zE I = 6408
.field public static final Kf I = 5391
.field public static final ye I = 2898
.field public static final se I = 2049
.field public static final xE I = 5390
.field public static final lF I = 32856
.field public static final pE I = 7682
.field public static final nF I = 32910
.field public static final tF I = 3386
.field public static final Gf I = 5385
.field public static final Oe I = 10243
.field public static final Le I = 9728
.field public static final vD I = 9985
.field public static final dg I = 2962
.field public static final ZD I = 1030
.field public static final je I = 5888
.field public static final xd I = 258
.field public static final Td I = 10791
.field public static final gg I = 32855
.field public static final nb I = 4612
.field public static final Yc I = 10796
.field public static final wC I = 8448
.field public static final wb I = 2902
.field public static final mA I = 7680
.field public static final ld I = 6914
.field public static final Rc I = 3410
.field public static final GC I = 32865
.field public static final fd I = 32845
.field public static final ad I = 2992
.field public static final Bc I = 32908
.field public static final eA I = 3122
.field public static final rd I = 7681
.field public static final Tc I = 3475
.field public static final bB I = 10792
.field public static final gA I = 6407
.field public static final pc I = 3415
.field public static final Hb I = 2981
.field public static final db I = 16386
.field public static final HB I = 3409
.field public static final mC I = 2562
.field public static final lC I = 16390
.field public static final Xc I = 5124
.field public static final XB I = 32853
.field public static final rC I = 2853
.field public static final KC I = 8
.field public static final nC I = 259
.field public static final yA I = 0
.field public static final pd I = 3187
.field public static final KA I = 32
.field public static final dd I = 2984
.field public static final zc I = 32857
.field public static final dA I = 16
.field public static final dC I = 32868
.field public static final kd I = 32862
.field public static final BC I = 3332
.field public static final sA I = 131072
.field public static final BB I = 3058
.field public static final RB I = 1
.field public static final QA I = 2901
.field public static final qC I = 3188
.field public static final BA I = 32848
.field public static final uA I = 32843
.field public static final bb I = 3382
.field public static final JC I = 2917
.field public static final YC I = 4614
.field public static final vA I = 32824
.field public static final Pd I = 32768
.field public static final XC I = 3152
.field public static final oA I = 6913
.field public static final lA I = 3008
.field public static final mc I = 1795
.field public static final FA I = 32890
.field public static final Ec I = 3572
.field public static final ac I = 3190
.field public static final UC I = 2963
.field public static final pA I = 0
.field public static final SC I = 3184
.field public static final mb I = 1539
.field public static final gC I = 32851
.field public static final VC I = 2825
.field public static final kb I = 10497
.field public static final qB I = 1035
.field public static final OB I = 3120
.field public static final VA I = 3411
.field public static final UB I = 2
.field public static final uB I = 6656
.field public static final HA I = 1284
.field public static final Bb I = 32858
.field public static final vb I = 8704
.field public static final Qc I = 2817
.field public static final ib I = 1048575
.field public static final ZB I = 32911
.field public static final Zc I = 2818
.field public static final Gc I = 10795
.field public static final SA I = 16384
.field public static final gd I = 2913
.field public static final Ob I = 2896
.field public static final Jb I = 257
.field public static final qA I = 1031
.field public static final rb I = 32873
.field public static final pC I = 16384
.field public static final fA I = 1280
.field public static final qb I = 5388
.field public static final OA I = 2883
.field public static final xb I = 3193
.field public static final lb I = 5377
.field public static final iB I = 2819
.field public static final DC I = 3387
.field public static final pb I = 2820
.field public static final ec I = 9473
.field public static final Qb I = 2
.field public static final UA I = 774
.field public static final AB I = 2864
.field public static final fc I = 3349
.field public static final GA I = 2978
.field public static final Gd I = 10793
.field public static final nB I = 10790
.field public static final jA I = 2561
.field public static final tB I = 256
.field public static final tA I = 32889
.field public static final WA I = 2914
.field public static final Mb I = 5389
.field public static final MA I = 3314
.field public static final sd I = 5127
.field public static final sb I = 32852
.field public static final lB I = 3384
.field public static final Kc I = 3010
.field public static final Dd I = 4099
.field public static final Qd I = 3345
.field public static final YB I = 8195
.field public static final aA I = 32864
.field public static final cb I = 1024
.field public static final qc I = 3570
.field public static final rA I = 3331
.field public static final ic I = 3412
.field public static final YA I = 32888
.field public static final jb I = 32827
.field public static final Ub I = 2848
.field public static final rc I = 3505
.field public static final Cd I = 2897
.field public static final fb I = 5
.field public static final Kb I = 10753
.field public static final Rb I = 32861
.field public static final EB I = 32829
.field public static final Hd I = 3348
.field public static final Fb I = 3385
.field public static final bd I = 8449
.field public static final tC I = 32771
.field public static final gc I = 9216
.field public static final oB I = 32897
.field public static final Wc I = 0
.field public static final aB I = 1792
.field public static final IC I = 32840
.field public static final Zb I = 16391
.field public static final DA I = 32886
.field public static final Jd I = 524288
.field public static final WC I = 1282
.field public static final Fc I = 6146
.field public static final Ad I = 1
.field public static final hc I = 32870
.field public static final xc I = 3512
.field public static final TB I = 3358
.field public static final SB I = 3186
.field public static final hB I = 1285
.field public static final Mc I = 10784
.field public static final rB I = 516
.field public static final Sc I = 3506
.field public static final Lc I = 3041
.field public static final EA I = 5125
.field public static final cA I = 3507
.field public static final XA I = 6404
.field public static final jB I = 3105
.field public static final CC I = 32860
.field public static final Uc I = 32884
.field public static final Fd I = 7170
.field public static final MB I = 32850
.field public static final hb I = 3553
.field public static final sC I = 32844
.field public static final nd I = 2965
.field public static final Eb I = 260
.field public static final Jc I = 10786
.field public static final gB I = 32898
.field public static final Ib I = 5635
.field public static final zB I = 3377
.field public static final NA I = 6405
.field public static final pB I = 3353
.field public static final ub I = 9729
.field public static final uC I = 32906
.field public static final Md I = 128
.field public static final fC I = 3333
.field public static final PA I = 9
.field public static final Tb I = 5122
.field public static final bA I = 3416
.field public static final IB I = 2964
.field public static final jC I = 10794
.field public static final ZC I = 9984
.field public static final cd I = 3413
.field public static final Id I = 5890
.field public static final RC I = 1033
.field public static final gb I = 3121
.field public static final vB I = 2916
.field public static final EC I = 16387
.field public static final Pc I = 3250
.field public static final Cb I = 776
.field public static final yc I = 3089
.field public static final nc I = 6403
.field public static final iA I = 32891
.field public static final kc I = 3253
.field public static final KB I = 3329
.field public static final yC I = 3251
.field public static final Ed I = 5123
.field public static final Wb I = 6402
.field public static final qd I = 12293
.field public static final mB I = 10788
.field public static final Ab I = 6409
.field public static final Vb I = 3477
.field public static final OC I = 32849
.field public static final Bd I = 8705
.field public static final Dc I = 0
.field public static final cC I = 3057
.field public static final Kd I = 775
.field public static final IA I = 3024
.field public static final QC I = 32830
.field public static final VB I = 7683
.field public static final ab I = 1026
.field public static final hC I = 2967
.field public static final zb I = 3359
.field public static final Cc I = 8194
.field public static final AC I = 3380
.field public static final Od I = 32892
.field public static final dB I = 3476
.field public static final NC I = 10789
.field public static final Yb I = 5387
.field public static final Sd I = 3473
.field public static final hA I = 5384
.field public static final Db I = 4610
.field public static final NB I = 2865
.field public static final id I = 512
.field public static final TC I = 3156
.field public static final kB I = 3357
.field public static final bC I = 3351
.field public static final xC I = 3248
.field public static final vc I = 3170
.field public static final kC I = 3414
.field public static final zC I = 3480
.field public static final kA I = 2882
.field public static final wc I = 4617
.field public static final od I = 2305
.field public static final oC I = 3510
.field public static final ZA I = 2979
.field public static final wA I = 5121
.field public static final aC I = 32837
.field public static final GB I = 2976
.field public static final cB I = 3154
.field public static final wB I = 4100
.field public static final Ld I = 4613
.field public static final HC I = 6912
.field public static final oc I = 3249
.field public static final zA I = 3472
.field public static final lc I = 2816
.field public static final ed I = 7937
.field public static final Xb I = 5376
.field public static final Ac I = 4615
.field public static final iC I = 32905
.field public static final uc I = 1798
.field public static final FC I = 32872
.field public static final WB I = 3478
.field public static final cc I = 4
.field public static final eB I = 4608
.field public static final Nc I = 32912
.field public static final yb I = 3354
.field public static final xA I = 1793
.field public static final Nd I = 7936
.field public static final Vc I = 3537
.field public static final LC I = 3479
.field public static final jd I = 5126
.field public static final LA I = 10496
.field public static final ob I = 3508
.field public static final jc I = 9218
.field public static final nA I = 2867
.field public static final sc I = 5633
.field public static final QB I = 3189
.field public static final AA I = 2866
.field public static final sB I = 32914
.field public static final Ic I = 3316
.field public static final fB I = 32859
.field public static final eC I = 2993
.field public static final JA I = 5382
.field public static final tc I = 7168
.field public static final MC I = 3255
.field public static final vC I = 16388
.field public static final PB I = 4353
.field public static final Gb I = 32772
.field public static final Nb I = 10242
.field public static final CB I = 6144
.field public static final xB I = 2
.field public static final bc I = 1538
.field public static final Hc I = 32854
.field public static final PC I = 4616
.field public static final tb I = 3317
.field public static final LB I = 1537
.field public static final eb I = 2881
.field public static final Oc I = 9986
.field public static final Lb I = 9474
.field public static final JB I = 32871
.field public static final Z I = 2983
.field public static final Pb I = 1025
.field public static final CA I = 2834
.field public static final DB I = -1
.field public static final yB I = 3474
.field public static final FB I = 2835
.field public static final Rd I = 1
.field public static final dc I = 4865
.field public static final hd I = 3123
.field public static final RA I = 6145
.field public static final md I = 4609
.field public static final TA I = 3192
.field public static final Sb I = 10797
.field public static final v I = 2966
.field public static final p I = 3073
.field public static final U I = 6401
.field public static final V I = 32867
.field public static final R I = 2832
.field public static final z I = 1536
.field public static final q I = 3511
.field public static final X I = 10785
.field public static final P I = 3074
.field public static final O I = 1
.field public static final w I = 2884
.field public static final y I = 3376
.field public static final o I = 32887
.field public static final Y I = 32842
.field public static final S I = 2851
.field public static final N I = 3350
.field public static final u I = 3383
.field public static final s I = 2980
.field public static final t I = 3042
.field public static final W I = 6410
.field public static final Q I = 2932
.field public static final T I = 1034
.field public static final r I = 3254
.field public static final x I = 8193
.field public static final n I = 5380
.field public static final M I = 32828
.field public static final L I = 5130
.field public static final H I = 3504
.field public static final d I = 3509
.field public static final e I = 12291
.field public static final g I = 5889
.field public static final k I = 5634
.field public static final a I = 2915
.field public static final F I = 2912
.field public static final A I = 5386
.field public static final E I = 32823
.field public static final C I = 2854
.field public static final K I = 3191
.field public static final G I = 2048
.field public static final B I = 10787
.field public static final c I = 32885
.field public static final field3632 I = 1799
.field public static final i I = 32834
.field public static final m I = 3440
.field public static final h I = 3539
.field public static final J I = 3346
.field public static final l I = 4099
.field public static final D I = 1024
.field public static final f I = 3313
.field public static final j I = 4096
.field public static final I I = 3417
.field public static final b I = 1036
.field public static final field3633 I = 2903
.field public static final return I = 1796
.field public static final field3634 I = 32841
.field public static final switch I = 4101
.field public static final field3635 I = 3312
.field public static final field3636 I = 2886
.field public static final field3637 I = 8192
.field public static final field3638 I = 32769
.field public static final field3639 I = 2304
.field public static final field3640 I = 5632
.field public static final field3641 I = 6406
.field public static final field3642 I = 2899
.field public static final field3643 I = 3009
.field public static final throw I = 1029
.field public static final package I = 517
.field public static final field3644 I = 2833
.field public static final field3645 I = 32863
.field public static final while I = 3088
.field public static final field3646 I = 2822
.field public static final field3647 I = 7939
.field public static final field3648 I = 32838
.field public static final field3649 I = 5378
.field public static final field3650 I = 3571
.field public static final field3651 I = 1032
.field public static final field3652 I = 770
.field public static final field3653 I = 3378
.field public static final field3654 I = 1283
.field public static final field3655 I = 10754
.field public static final field3656 I = 2821
.field public static final false I = 32835
.field public static final field3657 I = 4352
.field public static final field3658 I = 772
.field public static final true I = 3347
.field public static final field3659 I = 7
.field public static final field3660 I = 9987
.field public static final field3661 I = 3040
.field public static final field3662 I = 6400
.field public static final field3663 I = 518
.field public static final field3664 I = 3328
.field public static final field3665 I = 1794
.field public static final field3666 I = 2849
.field public static final field3667 I = 3408
.field public static final field3668 I = 2823
.field public static final try I = 2982
.field public static final field3669 I = 769
.field public static final new I = 5120
.field public static final field3670 I = 5129
.field public static final this I = 3107
.field public static final field3671 I = 8192
.field public static final field3672 I = 3171
.field public static final field3673 I = 1027
.field public static final field3674 I = 10241

.method public static method3636 : (IILjava/nio/DoubleBuffer;)V
    .code stack 7 locals 6
L0:     invokestatic Method org/lwjgl/opengl/GLContext method4611 ()Lorg/lwjgl/opengl/kb;
L3:     astore_3
L4:     aload_2
L5:     aload_3
L6:     dup
L7:     getfield Field org/lwjgl/opengl/kb rt J
L10:    dup2
L11:    lstore 4
L13:    invokestatic Method org/lwjgl/l method2052 (J)V
L16:    invokestatic Method org/lwjgl/opengl/Zd method5454 (Lorg/lwjgl/opengl/kb;)V
L19:    invokestatic Method org/lwjgl/l method2036 (Ljava/nio/DoubleBuffer;)V
L22:    getstatic Field org/lwjgl/LWJGLUtil CHECKS Z
L25:    ifeq L44
L28:    aload_3
L29:    invokestatic Method org/lwjgl/opengl/w method5768 (Lorg/lwjgl/opengl/kb;)Lorg/lwjgl/opengl/P;
L32:    getfield Field org/lwjgl/opengl/P field4953 [Ljava/nio/Buffer;
L35:    aload_3
L36:    invokestatic Method org/lwjgl/opengl/w method5768 (Lorg/lwjgl/opengl/kb;)Lorg/lwjgl/opengl/P;
L39:    getfield Field org/lwjgl/opengl/P this I
L42:    aload_2
L43:    aastore
L44:    iload_0
L45:    sipush 5130
L48:    iconst_1
L49:    dup
L50:    pop2
L51:    iload_1
L52:    aload_2
L53:    invokestatic Method org/lwjgl/MemoryUtil method1840 (Ljava/nio/DoubleBuffer;)J
L56:    lload 4
L58:    invokestatic Method org/lwjgl/opengl/GL11 nglTexCoordPointer (IIIJJ)V
L61:    return
L62:    
        .attribute StackMap b'\x00\x01\x00\x2C\x00\x05\x01\x01\x07\x04\x49\x07\x04\x21\x04\x00\x00'
    .end code
.end method

.method static native nglFogi : (IIJ)V
.end method

.method public static method3637 : (Ljava/nio/IntBuffer;)V
    .code stack 5 locals 3
L0:     invokestatic Method org/lwjgl/opengl/GLContext method4611 ()Lorg/lwjgl/opengl/kb;
L3:     getfield Field org/lwjgl/opengl/kb yG J
L6:     dup2
L7:     lstore_1
L8:     invokestatic Method org/lwjgl/l method2052 (J)V
L11:    aload_0
L12:    dup
L13:    invokestatic Method org/lwjgl/l method2043 (Ljava/nio/IntBuffer;)V
L16:    invokevirtual Method java/nio/IntBuffer remaining ()I
L19:    aload_0
L20:    invokestatic Method org/lwjgl/MemoryUtil method1884 (Ljava/nio/IntBuffer;)J
L23:    lload_1
L24:    invokestatic Method org/lwjgl/opengl/GL11 nglDeleteTextures (IJJ)V
L27:    return
L28:    
    .end code
.end method

.method static native nglPixelZoom : (FFJ)V
.end method

.method static native nglShadeModel : (IJ)V
.end method

.method static native nglTexParameteriv : (IIJJ)V
.end method

.method static native nglFogf : (IFJ)V
.end method

.method public static method3638 : (ILjava/nio/FloatBuffer;)V
    .code stack 6 locals 5
L0:     invokestatic Method org/lwjgl/opengl/GLContext method4611 ()Lorg/lwjgl/opengl/kb;
L3:     astore_2
L4:     aload_1
L5:     aload_2
L6:     dup
L7:     getfield Field org/lwjgl/opengl/kb Vg J
L10:    dup2
L11:    lstore_3
L12:    invokestatic Method org/lwjgl/l method2052 (J)V
L15:    invokestatic Method org/lwjgl/opengl/Zd method5449 (Lorg/lwjgl/opengl/kb;)V
L18:    sipush 256
L21:    iconst_1
L22:    dup
L23:    pop2
L24:    invokestatic Method org/lwjgl/l method2044 (Ljava/nio/FloatBuffer;I)V
L27:    iload_0
L28:    aload_1
L29:    invokestatic Method org/lwjgl/MemoryUtil method1878 (Ljava/nio/FloatBuffer;)J
L32:    lload_3
L33:    invokestatic Method org/lwjgl/opengl/GL11 nglGetPixelMapfv (IJJ)V
L36:    return
L37:    
    .end code
.end method

.method static native nglPixelMapuivBO : (IIJJ)V
.end method

.method static native nglTexCoord2d : (DDJ)V
.end method

.method static native nglGetMapdv : (IIJJ)V
.end method

.method static native nglDrawPixels : (IIIIJJ)V
.end method

.method public static method3639 : (IIIIIIIILjava/nio/ByteBuffer;)V
    .code stack 12 locals 12
L0:     invokestatic Method org/lwjgl/opengl/GLContext method4611 ()Lorg/lwjgl/opengl/kb;
L3:     astore 9
L5:     aload 8
L7:     aload 9
L9:     dup
L10:    getfield Field org/lwjgl/opengl/kb PJ J
L13:    dup2
L14:    lstore 10
L16:    invokestatic Method org/lwjgl/l method2052 (J)V
L19:    invokestatic Method org/lwjgl/opengl/Zd method5446 (Lorg/lwjgl/opengl/kb;)V
L22:    aload 8
L24:    iload 6
L26:    iload 7
L28:    iload 4
L30:    iload 5
L32:    iconst_1
L33:    dup
L34:    dup
L35:    pop2
L36:    invokestatic Method org/lwjgl/opengl/Zd method5429 (Ljava/nio/Buffer;IIIII)I
L39:    invokestatic Method org/lwjgl/l method2054 (Ljava/nio/ByteBuffer;I)V
L42:    iload_0
L43:    iload_1
L44:    iload_2
L45:    iload_3
L46:    iload 4
L48:    iload 5
L50:    iload 6
L52:    iload 7
L54:    aload 8
L56:    invokestatic Method org/lwjgl/MemoryUtil method1873 (Ljava/nio/ByteBuffer;)J
L59:    lload 10
L61:    invokestatic Method org/lwjgl/opengl/GL11 nglTexSubImage2D (IIIIIIIIJJ)V
L64:    return
L65:    
    .end code
.end method

.method public static method3640 : (II)I
    .code stack 6 locals 5
L0:     invokestatic Method org/lwjgl/opengl/GLContext method4611 ()Lorg/lwjgl/opengl/kb;
L3:     dup
L4:     getfield Field org/lwjgl/opengl/kb tA J
L7:     dup2
L8:     lstore_3
L9:     invokestatic Method org/lwjgl/l method2052 (J)V
L12:    invokestatic Method org/lwjgl/opengl/bB method5467 (Lorg/lwjgl/opengl/kb;)Ljava/nio/IntBuffer;
L15:    astore_2
L16:    iload_0
L17:    iload_1
L18:    aload_2
L19:    invokestatic Method org/lwjgl/MemoryUtil method1884 (Ljava/nio/IntBuffer;)J
L22:    lload_3
L23:    invokestatic Method org/lwjgl/opengl/GL11 nglGetTexGeniv (IIJJ)V
L26:    aload_2
L27:    iconst_0
L28:    iconst_1
L29:    dup
L30:    pop2
L31:    invokevirtual Method java/nio/IntBuffer get (I)I
L34:    ireturn
L35:    
    .end code
.end method

.method static native nglLoadMatrixd : (JJ)V
.end method

.method public static method3641 : (IDDIDD)V
    .code stack 12 locals 12
L0:     invokestatic Method org/lwjgl/opengl/GLContext method4611 ()Lorg/lwjgl/opengl/kb;
L3:     getfield Field org/lwjgl/opengl/kb YP J
L6:     dup2
L7:     lstore 10
L9:     invokestatic Method org/lwjgl/l method2052 (J)V
L12:    iload_0
L13:    dload_1
L14:    dload_3
L15:    iload 5
L17:    dload 6
L19:    dload 8
L21:    lload 10
L23:    invokestatic Method org/lwjgl/opengl/GL11 nglMapGrid2d (IDDIDDJ)V
L26:    return
L27:    
    .end code
.end method

.method public static method3642 : (IIIIIIILjava/nio/ByteBuffer;)V
    .code stack 11 locals 11
L0:     invokestatic Method org/lwjgl/opengl/GLContext method4611 ()Lorg/lwjgl/opengl/kb;
L3:     astore 8
L5:     aload 7
L7:     aload 8
L9:     dup
L10:    getfield Field org/lwjgl/opengl/kb hM J
L13:    dup2
L14:    lstore 9
L16:    invokestatic Method org/lwjgl/l method2052 (J)V
L19:    invokestatic Method org/lwjgl/opengl/Zd method5446 (Lorg/lwjgl/opengl/kb;)V
L22:    ifnull L39
L25:    aload 7
L27:    dup
L28:    iload 5
L30:    iload 6
L32:    iload_3
L33:    invokestatic Method org/lwjgl/opengl/Zd method5456 (Ljava/nio/Buffer;III)I
L36:    invokestatic Method org/lwjgl/l method2054 (Ljava/nio/ByteBuffer;I)V
L39:    iload_0
L40:    iload_1
L41:    iload_2
L42:    iload_3
L43:    iload 4
L45:    iload 5
L47:    iload 6
L49:    aload 7
L51:    invokestatic Method org/lwjgl/MemoryUtil method1883 (Ljava/nio/ByteBuffer;)J
L54:    lload 9
L56:    invokestatic Method org/lwjgl/opengl/GL11 nglTexImage1D (IIIIIIIJJ)V
L59:    return
L60:    
        .attribute StackMap b'\x00\x01\x00\x27\x00\x0A\x01\x01\x01\x01\x01\x01\x01\x07\x04\xCB\x07\x04\x21\x04\x00\x00'
    .end code
.end method

.method static native nglDeleteTextures : (IJJ)V
.end method

.method static native nglTexEnvfv : (IIJJ)V
.end method

.method public static method3643 : (IF)V
    .code stack 4 locals 4
L0:     invokestatic Method org/lwjgl/opengl/GLContext method4611 ()Lorg/lwjgl/opengl/kb;
L3:     getfield Field org/lwjgl/opengl/kb Gk J
L6:     dup2
L7:     lstore_2
L8:     invokestatic Method org/lwjgl/l method2052 (J)V
L11:    iload_0
L12:    fload_1
L13:    lload_2
L14:    invokestatic Method org/lwjgl/opengl/GL11 nglAlphaFunc (IFJ)V
L17:    return
L18:    
    .end code
.end method

.method public static method3644 : (IIIIIIII)V
    .code stack 10 locals 10
L0:     invokestatic Method org/lwjgl/opengl/GLContext method4611 ()Lorg/lwjgl/opengl/kb;
L3:     getfield Field org/lwjgl/opengl/kb yr J
L6:     dup2
L7:     lstore 8
L9:     invokestatic Method org/lwjgl/l method2052 (J)V
L12:    iload_0
L13:    iload_1
L14:    iload_2
L15:    iload_3
L16:    iload 4
L18:    iload 5
L20:    iload 6
L22:    iload 7
L24:    lload 8
L26:    invokestatic Method org/lwjgl/opengl/GL11 nglCopyTexSubImage2D (IIIIIIIIJ)V
L29:    return
L30:    
    .end code
.end method

.method public static method3645 : (IIIIIII)V
    .code stack 9 locals 9
L0:     invokestatic Method org/lwjgl/opengl/GLContext method4611 ()Lorg/lwjgl/opengl/kb;
L3:     getfield Field org/lwjgl/opengl/kb xo J
L6:     dup2
L7:     lstore 7
L9:     invokestatic Method org/lwjgl/l method2052 (J)V
L12:    iload_0
L13:    iload_1
L14:    iload_2
L15:    iload_3
L16:    iload 4
L18:    iload 5
L20:    iload 6
L22:    lload 7
L24:    invokestatic Method org/lwjgl/opengl/GL11 nglCopyTexImage1D (IIIIIIIJ)V
L27:    return
L28:    
    .end code
.end method

.method static native nglDrawElements : (IIIJJ)V
.end method

.method static native nglGetMapiv : (IIJJ)V
.end method

.method public static method3646 : (IILjava/nio/IntBuffer;)V
    .code stack 6 locals 5
L0:     invokestatic Method org/lwjgl/opengl/GLContext method4611 ()Lorg/lwjgl/opengl/kb;
L3:     getfield Field org/lwjgl/opengl/kb XP J
L6:     dup2
L7:     lstore_3
L8:     invokestatic Method org/lwjgl/l method2052 (J)V
L11:    iload_0
L12:    aload_2
L13:    iconst_4
L14:    iconst_1
L15:    dup
L16:    pop2
L17:    invokestatic Method org/lwjgl/l method2041 (Ljava/nio/IntBuffer;I)V
L20:    iload_1
L21:    aload_2
L22:    invokestatic Method org/lwjgl/MemoryUtil method1884 (Ljava/nio/IntBuffer;)J
L25:    lload_3
L26:    invokestatic Method org/lwjgl/opengl/GL11 nglLightiv (IIJJ)V
L29:    return
L30:    
    .end code
.end method

.method public static method3647 : (III)V
    .code stack 5 locals 5
L0:     invokestatic Method org/lwjgl/opengl/GLContext method4611 ()Lorg/lwjgl/opengl/kb;
L3:     getfield Field org/lwjgl/opengl/kb fA J
L6:     dup2
L7:     lstore_3
L8:     invokestatic Method org/lwjgl/l method2052 (J)V
L11:    iload_0
L12:    iload_1
L13:    iload_2
L14:    lload_3
L15:    invokestatic Method org/lwjgl/opengl/GL11 nglNormal3i (IIIJ)V
L18:    return
L19:    
    .end code
.end method

.method public static method3648 : (IFF)V
    .code stack 5 locals 5
L0:     invokestatic Method org/lwjgl/opengl/GLContext method4611 ()Lorg/lwjgl/opengl/kb;
L3:     getfield Field org/lwjgl/opengl/kb Lg J
L6:     dup2
L7:     lstore_3
L8:     invokestatic Method org/lwjgl/l method2052 (J)V
L11:    iload_0
L12:    fload_1
L13:    fload_2
L14:    lload_3
L15:    invokestatic Method org/lwjgl/opengl/GL11 nglMapGrid1f (IFFJ)V
L18:    return
L19:    
    .end code
.end method

.method public static method3649 : (Ljava/nio/ByteBuffer;)V
    .code stack 6 locals 4
L0:     invokestatic Method org/lwjgl/opengl/GLContext method4611 ()Lorg/lwjgl/opengl/kb;
L3:     astore_1
L4:     aload_0
L5:     aload_1
L6:     dup
L7:     getfield Field org/lwjgl/opengl/kb DH J
L10:    dup2
L11:    lstore_2
L12:    invokestatic Method org/lwjgl/l method2052 (J)V
L15:    invokestatic Method org/lwjgl/opengl/Zd method5449 (Lorg/lwjgl/opengl/kb;)V
L18:    aload_0
L19:    sipush 128
L22:    iconst_1
L23:    dup
L24:    pop2
L25:    invokestatic Method org/lwjgl/l method2054 (Ljava/nio/ByteBuffer;I)V
L28:    invokestatic Method org/lwjgl/MemoryUtil method1873 (Ljava/nio/ByteBuffer;)J
L31:    lload_2
L32:    invokestatic Method org/lwjgl/opengl/GL11 nglGetPolygonStipple (JJ)V
L35:    return
L36:    
    .end code
.end method

.method static native nglGetPixelMapuiv : (IJJ)V
.end method

.method public static method3650 : (FF)V
    .code stack 4 locals 4
L0:     invokestatic Method org/lwjgl/opengl/GLContext method4611 ()Lorg/lwjgl/opengl/kb;
L3:     getfield Field org/lwjgl/opengl/kb gd J
L6:     dup2
L7:     lstore_2
L8:     invokestatic Method org/lwjgl/l method2052 (J)V
L11:    fload_0
L12:    fload_1
L13:    lload_2
L14:    invokestatic Method org/lwjgl/opengl/GL11 nglTexCoord2f (FFJ)V
L17:    return
L18:    
    .end code
.end method

.method public static method3651 : (II)V
    .code stack 4 locals 4
L0:     invokestatic Method org/lwjgl/opengl/GLContext method4611 ()Lorg/lwjgl/opengl/kb;
L3:     getfield Field org/lwjgl/opengl/kb Gg J
L6:     dup2
L7:     lstore_2
L8:     invokestatic Method org/lwjgl/l method2052 (J)V
L11:    iload_0
L12:    iload_1
L13:    lload_2
L14:    invokestatic Method org/lwjgl/opengl/GL11 nglPixelTransferi (IIJ)V
L17:    return
L18:    
    .end code
.end method

.method static native nglScaled : (DDDJ)V
.end method

.method static native nglTexImage2DBO : (IIIIIIIIJJ)V
.end method

.method public static method3652 : (DDD)V
    .code stack 8 locals 8
L0:     invokestatic Method org/lwjgl/opengl/GLContext method4611 ()Lorg/lwjgl/opengl/kb;
L3:     getfield Field org/lwjgl/opengl/kb tP J
L6:     dup2
L7:     lstore 6
L9:     invokestatic Method org/lwjgl/l method2052 (J)V
L12:    dload_0
L13:    dload_2
L14:    dload 4
L16:    lload 6
L18:    invokestatic Method org/lwjgl/opengl/GL11 nglVertex3d (DDDJ)V
L21:    return
L22:    
    .end code
.end method

.method public static method3653 : (IZILjava/nio/ByteBuffer;)V
    .code stack 7 locals 7
L0:     invokestatic Method org/lwjgl/opengl/GLContext method4611 ()Lorg/lwjgl/opengl/kb;
L3:     astore 4
L5:     aload_3
L6:     aload 4
L8:     dup
L9:     getfield Field org/lwjgl/opengl/kb De J
L12:    dup2
L13:    lstore 5
L15:    invokestatic Method org/lwjgl/l method2052 (J)V
L18:    invokestatic Method org/lwjgl/opengl/Zd method5454 (Lorg/lwjgl/opengl/kb;)V
L21:    invokestatic Method org/lwjgl/l method2034 (Ljava/nio/ByteBuffer;)V
L24:    getstatic Field org/lwjgl/LWJGLUtil CHECKS Z
L27:    ifeq L39
L30:    aload 4
L32:    invokestatic Method org/lwjgl/opengl/w method5768 (Lorg/lwjgl/opengl/kb;)Lorg/lwjgl/opengl/P;
L35:    aload_3
L36:    putfield Field org/lwjgl/opengl/P field4949 Ljava/nio/Buffer;
L39:    iload_0
L40:    iload_1
L41:    ifeq L55
L44:    sipush 5121
L47:    iconst_1
L48:    dup
L49:    pop2
L50:    iload_2
L51:    goto L62
L54:    athrow
L55:    sipush 5120
L58:    iconst_1
L59:    dup
L60:    pop2
L61:    iload_2
L62:    aload_3
L63:    invokestatic Method org/lwjgl/MemoryUtil method1873 (Ljava/nio/ByteBuffer;)J
L66:    lload 5
L68:    invokestatic Method org/lwjgl/opengl/GL11 nglColorPointer (IIIJJ)V
L71:    return
L72:    
        .attribute StackMap b'\x00\x04\x00\x27\x00\x06\x01\x01\x01\x07\x04\xCB\x07\x04\x21\x04\x00\x00\x00\x36\x00\x00\x00\x01\x07\x05\x3C\x00\x37\x00\x06\x01\x01\x01\x07\x04\xCB\x07\x04\x21\x04\x00\x01\x01\x00\x3E\x00\x06\x01\x01\x01\x07\x04\xCB\x07\x04\x21\x04\x00\x03\x01\x01\x01'
    .end code
.end method

.method static native nglVertexPointerBO : (IIIJJ)V
.end method

.method static native nglClearAccum : (FFFFJ)V
.end method

.method public static method3654 : (FF)V
    .code stack 4 locals 4
L0:     invokestatic Method org/lwjgl/opengl/GLContext method4611 ()Lorg/lwjgl/opengl/kb;
L3:     getfield Field org/lwjgl/opengl/kb np J
L6:     dup2
L7:     lstore_2
L8:     invokestatic Method org/lwjgl/l method2052 (J)V
L11:    fload_0
L12:    fload_1
L13:    lload_2
L14:    invokestatic Method org/lwjgl/opengl/GL11 nglPixelZoom (FFJ)V
L17:    return
L18:    
    .end code
.end method

.method static native nglIsTexture : (IJ)Z
.end method

.method public static method3655 : (DDD)V
    .code stack 8 locals 8
L0:     invokestatic Method org/lwjgl/opengl/GLContext method4611 ()Lorg/lwjgl/opengl/kb;
L3:     getfield Field org/lwjgl/opengl/kb mE J
L6:     dup2
L7:     lstore 6
L9:     invokestatic Method org/lwjgl/l method2052 (J)V
L12:    dload_0
L13:    dload_2
L14:    dload 4
L16:    lload 6
L18:    invokestatic Method org/lwjgl/opengl/GL11 nglTranslated (DDDJ)V
L21:    return
L22:    
    .end code
.end method

.method static native nglTexSubImage2DBO : (IIIIIIIIJJ)V
.end method

.method public static method3656 : (DDD)V
    .code stack 8 locals 8
L0:     invokestatic Method org/lwjgl/opengl/GLContext method4611 ()Lorg/lwjgl/opengl/kb;
L3:     getfield Field org/lwjgl/opengl/kb z J
L6:     dup2
L7:     lstore 6
L9:     invokestatic Method org/lwjgl/l method2052 (J)V
L12:    dload_0
L13:    dload_2
L14:    dload 4
L16:    lload 6
L18:    invokestatic Method org/lwjgl/opengl/GL11 nglNormal3d (DDDJ)V
L21:    return
L22:    
    .end code
.end method

.method static native nglRasterPos3f : (FFFJ)V
.end method

.method public static method3657 : (ILjava/nio/ShortBuffer;)V
    .code stack 6 locals 5
L0:     invokestatic Method org/lwjgl/opengl/GLContext method4611 ()Lorg/lwjgl/opengl/kb;
L3:     astore_2
L4:     aload_1
L5:     aload_2
L6:     dup
L7:     getfield Field org/lwjgl/opengl/kb rj J
L10:    dup2
L11:    lstore_3
L12:    invokestatic Method org/lwjgl/l method2052 (J)V
L15:    invokestatic Method org/lwjgl/opengl/Zd method5446 (Lorg/lwjgl/opengl/kb;)V
L18:    invokestatic Method org/lwjgl/l method2057 (Ljava/nio/ShortBuffer;)V
L21:    iload_0
L22:    aload_1
L23:    invokevirtual Method java/nio/ShortBuffer remaining ()I
L26:    aload_1
L27:    invokestatic Method org/lwjgl/MemoryUtil method1853 (Ljava/nio/ShortBuffer;)J
L30:    lload_3
L31:    invokestatic Method org/lwjgl/opengl/GL11 nglPixelMapusv (IIJJ)V
L34:    return
L35:    
    .end code
.end method

.method public static method3658 : (IIIIIIILjava/nio/IntBuffer;)V
    .code stack 11 locals 11
L0:     invokestatic Method org/lwjgl/opengl/GLContext method4611 ()Lorg/lwjgl/opengl/kb;
L3:     astore 8
L5:     aload 7
L7:     aload 8
L9:     dup
L10:    getfield Field org/lwjgl/opengl/kb hM J
L13:    dup2
L14:    lstore 9
L16:    invokestatic Method org/lwjgl/l method2052 (J)V
L19:    invokestatic Method org/lwjgl/opengl/Zd method5446 (Lorg/lwjgl/opengl/kb;)V
L22:    ifnull L39
L25:    aload 7
L27:    dup
L28:    iload 5
L30:    iload 6
L32:    iload_3
L33:    invokestatic Method org/lwjgl/opengl/Zd method5456 (Ljava/nio/Buffer;III)I
L36:    invokestatic Method org/lwjgl/l method2041 (Ljava/nio/IntBuffer;I)V
L39:    iload_0
L40:    iload_1
L41:    iload_2
L42:    iload_3
L43:    iload 4
L45:    iload 5
L47:    iload 6
L49:    aload 7
L51:    invokestatic Method org/lwjgl/MemoryUtil method1865 (Ljava/nio/IntBuffer;)J
L54:    lload 9
L56:    invokestatic Method org/lwjgl/opengl/GL11 nglTexImage1D (IIIIIIIJJ)V
L59:    return
L60:    
        .attribute StackMap b'\x00\x01\x00\x27\x00\x0A\x01\x01\x01\x01\x01\x01\x01\x07\x04\x5F\x07\x04\x21\x04\x00\x00'
    .end code
.end method

.method static native nglPixelStoref : (IFJ)V
.end method

.method static native nglGetMapfv : (IIJJ)V
.end method

.method public static method3659 : (I)V
    .code stack 5 locals 3
L0:     invokestatic Method org/lwjgl/opengl/GLContext method4611 ()Lorg/lwjgl/opengl/kb;
L3:     dup
L4:     getfield Field org/lwjgl/opengl/kb cT J
L7:     dup2
L8:     lstore_1
L9:     invokestatic Method org/lwjgl/l method2052 (J)V
L12:    iload_0
L13:    invokestatic Method org/lwjgl/opengl/w method5765 (Lorg/lwjgl/opengl/kb;I)V
L16:    iload_0
L17:    lload_1
L18:    invokestatic Method org/lwjgl/opengl/GL11 nglPushClientAttrib (IJ)V
L21:    return
L22:    
    .end code
.end method

.method static native nglBlendFunc : (IIJ)V
.end method

.method public static method3660 : (BBB)V
    .code stack 5 locals 5
L0:     invokestatic Method org/lwjgl/opengl/GLContext method4611 ()Lorg/lwjgl/opengl/kb;
L3:     getfield Field org/lwjgl/opengl/kb vA J
L6:     dup2
L7:     lstore_3
L8:     invokestatic Method org/lwjgl/l method2052 (J)V
L11:    iload_0
L12:    iload_1
L13:    iload_2
L14:    lload_3
L15:    invokestatic Method org/lwjgl/opengl/GL11 nglColor3ub (BBBJ)V
L18:    return
L19:    
    .end code
.end method

.method static native nglFlush : (J)V
.end method

.method static native nglLightiv : (IIJJ)V
.end method

.method static native nglEvalCoord1f : (FJ)V
.end method

.method static native nglVertex4i : (IIIIJ)V
.end method

.method public static method3661 : (IIIIJ)V
    .code stack 8 locals 8
L0:     invokestatic Method org/lwjgl/opengl/GLContext method4611 ()Lorg/lwjgl/opengl/kb;
L3:     dup
L4:     getfield Field org/lwjgl/opengl/kb cj J
L7:     dup2
L8:     lstore 6
L10:    invokestatic Method org/lwjgl/l method2052 (J)V
L13:    invokestatic Method org/lwjgl/opengl/Zd method5436 (Lorg/lwjgl/opengl/kb;)V
L16:    iload_0
L17:    iload_1
L18:    iload_2
L19:    iload_3
L20:    lload 4
L22:    lload 6
L24:    invokestatic Method org/lwjgl/opengl/GL11 nglGetTexImageBO (IIIIJJ)V
L27:    return
L28:    
    .end code
.end method

.method static native nglVertex4f : (FFFFJ)V
.end method

.method static native nglFrontFace : (IJ)V
.end method

.method static native nglTexCoord4f : (FFFFJ)V
.end method

.method public static method3662 : (IILjava/nio/FloatBuffer;)V
    .code stack 6 locals 5
L0:     invokestatic Method org/lwjgl/opengl/GLContext method4611 ()Lorg/lwjgl/opengl/kb;
L3:     getfield Field org/lwjgl/opengl/kb qu J
L6:     dup2
L7:     lstore_3
L8:     invokestatic Method org/lwjgl/l method2052 (J)V
L11:    iload_0
L12:    aload_2
L13:    iconst_4
L14:    iconst_1
L15:    dup
L16:    pop2
L17:    invokestatic Method org/lwjgl/l method2044 (Ljava/nio/FloatBuffer;I)V
L20:    iload_1
L21:    aload_2
L22:    invokestatic Method org/lwjgl/MemoryUtil method1878 (Ljava/nio/FloatBuffer;)J
L25:    lload_3
L26:    invokestatic Method org/lwjgl/opengl/GL11 nglGetLightfv (IIJJ)V
L29:    return
L30:    
    .end code
.end method

.method public static method3663 : (IILjava/nio/ByteBuffer;)V
    .code stack 6 locals 6
L0:     invokestatic Method org/lwjgl/opengl/GLContext method4611 ()Lorg/lwjgl/opengl/kb;
L3:     astore_3
L4:     aload_2
L5:     aload_3
L6:     dup
L7:     getfield Field org/lwjgl/opengl/kb MB J
L10:    dup2
L11:    lstore 4
L13:    invokestatic Method org/lwjgl/l method2052 (J)V
L16:    invokestatic Method org/lwjgl/opengl/Zd method5454 (Lorg/lwjgl/opengl/kb;)V
L19:    invokestatic Method org/lwjgl/l method2034 (Ljava/nio/ByteBuffer;)V
L22:    iload_0
L23:    iload_1
L24:    aload_2
L25:    invokestatic Method org/lwjgl/MemoryUtil method1873 (Ljava/nio/ByteBuffer;)J
L28:    lload 4
L30:    invokestatic Method org/lwjgl/opengl/GL11 nglInterleavedArrays (IIJJ)V
L33:    return
L34:    
    .end code
.end method

.method public static method3664 : (I)V
    .code stack 4 locals 3
L0:     invokestatic Method org/lwjgl/opengl/GLContext method4611 ()Lorg/lwjgl/opengl/kb;
L3:     getfield Field org/lwjgl/opengl/kb Dj J
L6:     dup2
L7:     lstore_1
L8:     invokestatic Method org/lwjgl/l method2052 (J)V
L11:    iload_0
L12:    lload_1
L13:    invokestatic Method org/lwjgl/opengl/GL11 nglBegin (IJ)V
L16:    return
L17:    
    .end code
.end method

.method public static method3665 : (I)V
    .code stack 4 locals 3
L0:     invokestatic Method org/lwjgl/opengl/GLContext method4611 ()Lorg/lwjgl/opengl/kb;
L3:     getfield Field org/lwjgl/opengl/kb sI J
L6:     dup2
L7:     lstore_1
L8:     invokestatic Method org/lwjgl/l method2052 (J)V
L11:    iload_0
L12:    lload_1
L13:    invokestatic Method org/lwjgl/opengl/GL11 nglListBase (IJ)V
L16:    return
L17:    
    .end code
.end method

.method static native nglEnable : (IJ)V
.end method

.method static native nglTexEnviv : (IIJJ)V
.end method

.method public static method3666 : (II)V
    .code stack 4 locals 4
L0:     invokestatic Method org/lwjgl/opengl/GLContext method4611 ()Lorg/lwjgl/opengl/kb;
L3:     getfield Field org/lwjgl/opengl/kb sl J
L6:     dup2
L7:     lstore_2
L8:     invokestatic Method org/lwjgl/l method2052 (J)V
L11:    iload_0
L12:    iload_1
L13:    lload_2
L14:    invokestatic Method org/lwjgl/opengl/GL11 nglLightModeli (IIJ)V
L17:    return
L18:    
    .end code
.end method

.method public static method3667 : (IIIIIIIILjava/nio/IntBuffer;)V
    .code stack 12 locals 12
L0:     invokestatic Method org/lwjgl/opengl/GLContext method4611 ()Lorg/lwjgl/opengl/kb;
L3:     astore 9
L5:     aload 8
L7:     aload 9
L9:     dup
L10:    getfield Field org/lwjgl/opengl/kb kD J
L13:    dup2
L14:    lstore 10
L16:    invokestatic Method org/lwjgl/l method2052 (J)V
L19:    invokestatic Method org/lwjgl/opengl/Zd method5446 (Lorg/lwjgl/opengl/kb;)V
L22:    ifnull L41
L25:    aload 8
L27:    dup
L28:    iload 6
L30:    iload 7
L32:    iload_3
L33:    iload 4
L35:    invokestatic Method org/lwjgl/opengl/Zd method5453 (Ljava/nio/Buffer;IIII)I
L38:    invokestatic Method org/lwjgl/l method2041 (Ljava/nio/IntBuffer;I)V
L41:    iload_0
L42:    iload_1
L43:    iload_2
L44:    iload_3
L45:    iload 4
L47:    iload 5
L49:    iload 6
L51:    iload 7
L53:    aload 8
L55:    invokestatic Method org/lwjgl/MemoryUtil method1865 (Ljava/nio/IntBuffer;)J
L58:    lload 10
L60:    invokestatic Method org/lwjgl/opengl/GL11 nglTexImage2D (IIIIIIIIJJ)V
L63:    return
L64:    
        .attribute StackMap b'\x00\x01\x00\x29\x00\x0B\x01\x01\x01\x01\x01\x01\x01\x01\x07\x04\x5F\x07\x04\x21\x04\x00\x00'
    .end code
.end method

.method public static method3668 : (Ljava/nio/IntBuffer;)V
    .code stack 6 locals 3
L0:     invokestatic Method org/lwjgl/opengl/GLContext method4611 ()Lorg/lwjgl/opengl/kb;
L3:     getfield Field org/lwjgl/opengl/kb Kf J
L6:     dup2
L7:     lstore_1
L8:     invokestatic Method org/lwjgl/l method2052 (J)V
L11:    aload_0
L12:    dup
L13:    invokestatic Method org/lwjgl/l method2043 (Ljava/nio/IntBuffer;)V
L16:    invokevirtual Method java/nio/IntBuffer remaining ()I
L19:    sipush 5125
L22:    iconst_1
L23:    dup
L24:    pop2
L25:    aload_0
L26:    invokestatic Method org/lwjgl/MemoryUtil method1884 (Ljava/nio/IntBuffer;)J
L29:    lload_1
L30:    invokestatic Method org/lwjgl/opengl/GL11 nglCallLists (IIJJ)V
L33:    return
L34:    
    .end code
.end method

.method public static method3669 : (FFF)V
    .code stack 5 locals 5
L0:     invokestatic Method org/lwjgl/opengl/GLContext method4611 ()Lorg/lwjgl/opengl/kb;
L3:     getfield Field org/lwjgl/opengl/kb wJ J
L6:     dup2
L7:     lstore_3
L8:     invokestatic Method org/lwjgl/l method2052 (J)V
L11:    fload_0
L12:    fload_1
L13:    fload_2
L14:    lload_3
L15:    invokestatic Method org/lwjgl/opengl/GL11 nglNormal3f (FFFJ)V
L18:    return
L19:    
    .end code
.end method

.method static native nglNormalPointerBO : (IIJJ)V
.end method

.method static native nglTexParameteri : (IIIJ)V
.end method

.method static native nglMapGrid1d : (IDDJ)V
.end method

.method public static method3670 : (I)V
    .code stack 4 locals 3
L0:     invokestatic Method org/lwjgl/opengl/GLContext method4611 ()Lorg/lwjgl/opengl/kb;
L3:     getfield Field org/lwjgl/opengl/kb YI J
L6:     dup2
L7:     lstore_1
L8:     invokestatic Method org/lwjgl/l method2052 (J)V
L11:    iload_0
L12:    lload_1
L13:    invokestatic Method org/lwjgl/opengl/GL11 nglFrontFace (IJ)V
L16:    return
L17:    
    .end code
.end method

.method public static method3671 : (IIIIIIIILjava/nio/ByteBuffer;)V
    .code stack 12 locals 12
L0:     invokestatic Method org/lwjgl/opengl/GLContext method4611 ()Lorg/lwjgl/opengl/kb;
L3:     astore 9
L5:     aload 8
L7:     aload 9
L9:     dup
L10:    getfield Field org/lwjgl/opengl/kb kD J
L13:    dup2
L14:    lstore 10
L16:    invokestatic Method org/lwjgl/l method2052 (J)V
L19:    invokestatic Method org/lwjgl/opengl/Zd method5446 (Lorg/lwjgl/opengl/kb;)V
L22:    ifnull L41
L25:    aload 8
L27:    dup
L28:    iload 6
L30:    iload 7
L32:    iload_3
L33:    iload 4
L35:    invokestatic Method org/lwjgl/opengl/Zd method5453 (Ljava/nio/Buffer;IIII)I
L38:    invokestatic Method org/lwjgl/l method2054 (Ljava/nio/ByteBuffer;I)V
L41:    iload_0
L42:    iload_1
L43:    iload_2
L44:    iload_3
L45:    iload 4
L47:    iload 5
L49:    iload 6
L51:    iload 7
L53:    aload 8
L55:    invokestatic Method org/lwjgl/MemoryUtil method1883 (Ljava/nio/ByteBuffer;)J
L58:    lload 10
L60:    invokestatic Method org/lwjgl/opengl/GL11 nglTexImage2D (IIIIIIIIJJ)V
L63:    return
L64:    
        .attribute StackMap b'\x00\x01\x00\x29\x00\x0B\x01\x01\x01\x01\x01\x01\x01\x01\x07\x04\xCB\x07\x04\x21\x04\x00\x00'
    .end code
.end method

.method public static method3672 : ()V
    .code stack 4 locals 2
L0:     invokestatic Method org/lwjgl/opengl/GLContext method4611 ()Lorg/lwjgl/opengl/kb;
L3:     getfield Field org/lwjgl/opengl/kb Ro J
L6:     dup2
L7:     lstore_0
L8:     invokestatic Method org/lwjgl/l method2052 (J)V
L11:    lload_0
L12:    invokestatic Method org/lwjgl/opengl/GL11 nglPushMatrix (J)V
L15:    return
L16:    
    .end code
.end method

.method static native nglTexSubImage1DBO : (IIIIIIJJ)V
.end method

.method public static method3673 : (D)V
    .code stack 4 locals 4
L0:     invokestatic Method org/lwjgl/opengl/GLContext method4611 ()Lorg/lwjgl/opengl/kb;
L3:     getfield Field org/lwjgl/opengl/kb Pr J
L6:     dup2
L7:     lstore_2
L8:     invokestatic Method org/lwjgl/l method2052 (J)V
L11:    dload_0
L12:    lload_2
L13:    invokestatic Method org/lwjgl/opengl/GL11 nglEvalCoord1d (DJ)V
L16:    return
L17:    
    .end code
.end method

.method static native nglGetIntegerv : (IJJ)V
.end method

.method static native nglTexImage2D : (IIIIIIIIJJ)V
.end method

.method public static method3674 : (IIIIIIILjava/nio/FloatBuffer;)V
    .code stack 11 locals 11
L0:     invokestatic Method org/lwjgl/opengl/GLContext method4611 ()Lorg/lwjgl/opengl/kb;
L3:     astore 8
L5:     aload 7
L7:     aload 8
L9:     dup
L10:    getfield Field org/lwjgl/opengl/kb hM J
L13:    dup2
L14:    lstore 9
L16:    invokestatic Method org/lwjgl/l method2052 (J)V
L19:    invokestatic Method org/lwjgl/opengl/Zd method5446 (Lorg/lwjgl/opengl/kb;)V
L22:    ifnull L39
L25:    aload 7
L27:    dup
L28:    iload 5
L30:    iload 6
L32:    iload_3
L33:    invokestatic Method org/lwjgl/opengl/Zd method5456 (Ljava/nio/Buffer;III)I
L36:    invokestatic Method org/lwjgl/l method2044 (Ljava/nio/FloatBuffer;I)V
L39:    iload_0
L40:    iload_1
L41:    iload_2
L42:    iload_3
L43:    iload 4
L45:    iload 5
L47:    iload 6
L49:    aload 7
L51:    invokestatic Method org/lwjgl/MemoryUtil method1852 (Ljava/nio/FloatBuffer;)J
L54:    lload 9
L56:    invokestatic Method org/lwjgl/opengl/GL11 nglTexImage1D (IIIIIIIJJ)V
L59:    return
L60:    
        .attribute StackMap b'\x00\x01\x00\x27\x00\x0A\x01\x01\x01\x01\x01\x01\x01\x07\x05\xFE\x07\x04\x21\x04\x00\x00'
    .end code
.end method

.method public static method3675 : (IILjava/nio/DoubleBuffer;)V
    .code stack 7 locals 6
L0:     invokestatic Method org/lwjgl/opengl/GLContext method4611 ()Lorg/lwjgl/opengl/kb;
L3:     astore_3
L4:     aload_2
L5:     aload_3
L6:     dup
L7:     getfield Field org/lwjgl/opengl/kb De J
L10:    dup2
L11:    lstore 4
L13:    invokestatic Method org/lwjgl/l method2052 (J)V
L16:    invokestatic Method org/lwjgl/opengl/Zd method5454 (Lorg/lwjgl/opengl/kb;)V
L19:    invokestatic Method org/lwjgl/l method2036 (Ljava/nio/DoubleBuffer;)V
L22:    getstatic Field org/lwjgl/LWJGLUtil CHECKS Z
L25:    ifeq L36
L28:    aload_3
L29:    invokestatic Method org/lwjgl/opengl/w method5768 (Lorg/lwjgl/opengl/kb;)Lorg/lwjgl/opengl/P;
L32:    aload_2
L33:    putfield Field org/lwjgl/opengl/P field4949 Ljava/nio/Buffer;
L36:    iload_0
L37:    sipush 5130
L40:    iconst_1
L41:    dup
L42:    pop2
L43:    iload_1
L44:    aload_2
L45:    invokestatic Method org/lwjgl/MemoryUtil method1840 (Ljava/nio/DoubleBuffer;)J
L48:    lload 4
L50:    invokestatic Method org/lwjgl/opengl/GL11 nglColorPointer (IIIJJ)V
L53:    return
L54:    
        .attribute StackMap b'\x00\x01\x00\x24\x00\x05\x01\x01\x07\x04\x49\x07\x04\x21\x04\x00\x00'
    .end code
.end method

.method public static method3676 : (IIIIIILjava/nio/DoubleBuffer;)V
    .code stack 10 locals 10
L0:     invokestatic Method org/lwjgl/opengl/GLContext method4611 ()Lorg/lwjgl/opengl/kb;
L3:     astore 7
L5:     aload 6
L7:     aload 7
L9:     dup
L10:    getfield Field org/lwjgl/opengl/kb Zi J
L13:    dup2
L14:    lstore 8
L16:    invokestatic Method org/lwjgl/l method2052 (J)V
L19:    invokestatic Method org/lwjgl/opengl/Zd method5446 (Lorg/lwjgl/opengl/kb;)V
L22:    aload 6
L24:    iload 4
L26:    iload 5
L28:    iload_3
L29:    iconst_1
L30:    dup
L31:    pop2
L32:    iconst_1
L33:    dup
L34:    dup_x1
L35:    dup
L36:    pop2
L37:    invokestatic Method org/lwjgl/opengl/Zd method5429 (Ljava/nio/Buffer;IIIII)I
L40:    invokestatic Method org/lwjgl/l method2056 (Ljava/nio/DoubleBuffer;I)V
L43:    iload_0
L44:    iload_1
L45:    iload_2
L46:    iload_3
L47:    iload 4
L49:    iload 5
L51:    aload 6
L53:    invokestatic Method org/lwjgl/MemoryUtil method1840 (Ljava/nio/DoubleBuffer;)J
L56:    lload 8
L58:    invokestatic Method org/lwjgl/opengl/GL11 nglTexSubImage1D (IIIIIIJJ)V
L61:    return
L62:    
    .end code
.end method

.method static native nglGenTextures : (IJJ)V
.end method

.method public static method3677 : (I)V
    .code stack 4 locals 3
L0:     invokestatic Method org/lwjgl/opengl/GLContext method4611 ()Lorg/lwjgl/opengl/kb;
L3:     getfield Field org/lwjgl/opengl/kb Cm J
L6:     dup2
L7:     lstore_1
L8:     invokestatic Method org/lwjgl/l method2052 (J)V
L11:    iload_0
L12:    lload_1
L13:    invokestatic Method org/lwjgl/opengl/GL11 nglEvalPoint1 (IJ)V
L16:    return
L17:    
    .end code
.end method

.method public static method3678 : (III)V
    .code stack 5 locals 5
L0:     invokestatic Method org/lwjgl/opengl/GLContext method4611 ()Lorg/lwjgl/opengl/kb;
L3:     getfield Field org/lwjgl/opengl/kb PR J
L6:     dup2
L7:     lstore_3
L8:     invokestatic Method org/lwjgl/l method2052 (J)V
L11:    iload_0
L12:    iload_1
L13:    iload_2
L14:    lload_3
L15:    invokestatic Method org/lwjgl/opengl/GL11 nglTexEnvi (IIIJ)V
L18:    return
L19:    
    .end code
.end method

.method public static method3679 : (II)F
    .code stack 6 locals 5
L0:     invokestatic Method org/lwjgl/opengl/GLContext method4611 ()Lorg/lwjgl/opengl/kb;
L3:     dup
L4:     getfield Field org/lwjgl/opengl/kb Ws J
L7:     dup2
L8:     lstore_3
L9:     invokestatic Method org/lwjgl/l method2052 (J)V
L12:    invokestatic Method org/lwjgl/opengl/bB method5465 (Lorg/lwjgl/opengl/kb;)Ljava/nio/FloatBuffer;
L15:    astore_2
L16:    iload_0
L17:    iload_1
L18:    aload_2
L19:    invokestatic Method org/lwjgl/MemoryUtil method1878 (Ljava/nio/FloatBuffer;)J
L22:    lload_3
L23:    invokestatic Method org/lwjgl/opengl/GL11 nglGetTexGenfv (IIJJ)V
L26:    aload_2
L27:    iconst_0
L28:    iconst_1
L29:    dup
L30:    pop2
L31:    invokevirtual Method java/nio/FloatBuffer get (I)F
L34:    freturn
L35:    
    .end code
.end method

.method static native nglMaterialfv : (IIJJ)V
.end method

.method static native nglRasterPos4d : (DDDDJ)V
.end method

.method static native nglBitmap : (IIFFFFJJ)V
.end method

.method public static method3680 : (I)V
    .code stack 4 locals 3
L0:     invokestatic Method org/lwjgl/opengl/GLContext method4611 ()Lorg/lwjgl/opengl/kb;
L3:     getfield Field org/lwjgl/opengl/kb cr J
L6:     dup2
L7:     lstore_1
L8:     invokestatic Method org/lwjgl/l method2052 (J)V
L11:    iload_0
L12:    lload_1
L13:    invokestatic Method org/lwjgl/opengl/GL11 nglPushAttrib (IJ)V
L16:    return
L17:    
    .end code
.end method

.method static native nglViewport : (IIIIJ)V
.end method

.method static native nglPushAttrib : (IJ)V
.end method

.method public static method3681 : (IIIIJ)V
    .code stack 8 locals 8
L0:     invokestatic Method org/lwjgl/opengl/GLContext method4611 ()Lorg/lwjgl/opengl/kb;
L3:     dup
L4:     getfield Field org/lwjgl/opengl/kb Ps J
L7:     dup2
L8:     lstore 6
L10:    invokestatic Method org/lwjgl/l method2052 (J)V
L13:    invokestatic Method org/lwjgl/opengl/Zd method5428 (Lorg/lwjgl/opengl/kb;)V
L16:    iload_0
L17:    iload_1
L18:    iload_2
L19:    iload_3
L20:    lload 4
L22:    lload 6
L24:    invokestatic Method org/lwjgl/opengl/GL11 nglDrawPixelsBO (IIIIJJ)V
L27:    return
L28:    
    .end code
.end method

.method public static return : (I)V
    .code stack 4 locals 3
L0:     invokestatic Method org/lwjgl/opengl/GLContext method4611 ()Lorg/lwjgl/opengl/kb;
L3:     getfield Field org/lwjgl/opengl/kb DA J
L6:     dup2
L7:     lstore_1
L8:     invokestatic Method org/lwjgl/l method2052 (J)V
L11:    iload_0
L12:    lload_1
L13:    invokestatic Method org/lwjgl/opengl/GL11 nglDrawBuffer (IJ)V
L16:    return
L17:    
    .end code
.end method

.method static native nglCopyTexImage2D : (IIIIIIIIJ)V
.end method

.method public static method3682 : (IIIIIIIILjava/nio/DoubleBuffer;)V
    .code stack 12 locals 12
L0:     invokestatic Method org/lwjgl/opengl/GLContext method4611 ()Lorg/lwjgl/opengl/kb;
L3:     astore 9
L5:     aload 8
L7:     aload 9
L9:     dup
L10:    getfield Field org/lwjgl/opengl/kb PJ J
L13:    dup2
L14:    lstore 10
L16:    invokestatic Method org/lwjgl/l method2052 (J)V
L19:    invokestatic Method org/lwjgl/opengl/Zd method5446 (Lorg/lwjgl/opengl/kb;)V
L22:    aload 8
L24:    iload 6
L26:    iload 7
L28:    iload 4
L30:    iload 5
L32:    iconst_1
L33:    dup
L34:    dup
L35:    pop2
L36:    invokestatic Method org/lwjgl/opengl/Zd method5429 (Ljava/nio/Buffer;IIIII)I
L39:    invokestatic Method org/lwjgl/l method2056 (Ljava/nio/DoubleBuffer;I)V
L42:    iload_0
L43:    iload_1
L44:    iload_2
L45:    iload_3
L46:    iload 4
L48:    iload 5
L50:    iload 6
L52:    iload 7
L54:    aload 8
L56:    invokestatic Method org/lwjgl/MemoryUtil method1840 (Ljava/nio/DoubleBuffer;)J
L59:    lload 10
L61:    invokestatic Method org/lwjgl/opengl/GL11 nglTexSubImage2D (IIIIIIIIJJ)V
L64:    return
L65:    
    .end code
.end method

.method public static method3683 : (IILjava/nio/FloatBuffer;)V
    .code stack 6 locals 6
L0:     invokestatic Method org/lwjgl/opengl/GLContext method4611 ()Lorg/lwjgl/opengl/kb;
L3:     astore_3
L4:     aload_2
L5:     aload_3
L6:     dup
L7:     getfield Field org/lwjgl/opengl/kb MB J
L10:    dup2
L11:    lstore 4
L13:    invokestatic Method org/lwjgl/l method2052 (J)V
L16:    invokestatic Method org/lwjgl/opengl/Zd method5454 (Lorg/lwjgl/opengl/kb;)V
L19:    invokestatic Method org/lwjgl/l method2048 (Ljava/nio/FloatBuffer;)V
L22:    iload_0
L23:    iload_1
L24:    aload_2
L25:    invokestatic Method org/lwjgl/MemoryUtil method1878 (Ljava/nio/FloatBuffer;)J
L28:    lload 4
L30:    invokestatic Method org/lwjgl/opengl/GL11 nglInterleavedArrays (IIJJ)V
L33:    return
L34:    
    .end code
.end method

.method public static method3684 : (IILjava/nio/DoubleBuffer;)V
    .code stack 6 locals 5
L0:     invokestatic Method org/lwjgl/opengl/GLContext method4611 ()Lorg/lwjgl/opengl/kb;
L3:     getfield Field org/lwjgl/opengl/kb zG J
L6:     dup2
L7:     lstore_3
L8:     invokestatic Method org/lwjgl/l method2052 (J)V
L11:    iload_0
L12:    aload_2
L13:    iconst_4
L14:    iconst_1
L15:    dup
L16:    pop2
L17:    invokestatic Method org/lwjgl/l method2056 (Ljava/nio/DoubleBuffer;I)V
L20:    iload_1
L21:    aload_2
L22:    invokestatic Method org/lwjgl/MemoryUtil method1840 (Ljava/nio/DoubleBuffer;)J
L25:    lload_3
L26:    invokestatic Method org/lwjgl/opengl/GL11 nglGetTexGendv (IIJJ)V
L29:    return
L30:    
    .end code
.end method

.method public static method3685 : (IIILjava/nio/FloatBuffer;)V
    .code stack 7 locals 6
L0:     invokestatic Method org/lwjgl/opengl/GLContext method4611 ()Lorg/lwjgl/opengl/kb;
L3:     getfield Field org/lwjgl/opengl/kb HB J
L6:     dup2
L7:     lstore 4
L9:     invokestatic Method org/lwjgl/l method2052 (J)V
L12:    iload_0
L13:    aload_3
L14:    iconst_4
L15:    iconst_1
L16:    dup
L17:    pop2
L18:    invokestatic Method org/lwjgl/l method2044 (Ljava/nio/FloatBuffer;I)V
L21:    iload_1
L22:    iload_2
L23:    aload_3
L24:    invokestatic Method org/lwjgl/MemoryUtil method1878 (Ljava/nio/FloatBuffer;)J
L27:    lload 4
L29:    invokestatic Method org/lwjgl/opengl/GL11 nglGetTexLevelParameterfv (IIIJJ)V
L32:    return
L33:    
    .end code
.end method

.method public static new : (III)V
    .code stack 5 locals 5
L0:     invokestatic Method org/lwjgl/opengl/GLContext method4611 ()Lorg/lwjgl/opengl/kb;
L3:     getfield Field org/lwjgl/opengl/kb Lf J
L6:     dup2
L7:     lstore_3
L8:     invokestatic Method org/lwjgl/l method2052 (J)V
L11:    iload_0
L12:    iload_1
L13:    iload_2
L14:    lload_3
L15:    invokestatic Method org/lwjgl/opengl/GL11 nglStencilFunc (IIIJ)V
L18:    return
L19:    
    .end code
.end method

.method public static method3686 : (I)V
    .code stack 4 locals 3
L0:     invokestatic Method org/lwjgl/opengl/GLContext method4611 ()Lorg/lwjgl/opengl/kb;
L3:     getfield Field org/lwjgl/opengl/kb FA J
L6:     dup2
L7:     lstore_1
L8:     invokestatic Method org/lwjgl/l method2052 (J)V
L11:    iload_0
L12:    lload_1
L13:    invokestatic Method org/lwjgl/opengl/GL11 nglCullFace (IJ)V
L16:    return
L17:    
    .end code
.end method

.method public static method3687 : (ILjava/nio/DoubleBuffer;)V
    .code stack 5 locals 4
L0:     invokestatic Method org/lwjgl/opengl/GLContext method4611 ()Lorg/lwjgl/opengl/kb;
L3:     getfield Field org/lwjgl/opengl/kb pA J
L6:     dup2
L7:     lstore_2
L8:     invokestatic Method org/lwjgl/l method2052 (J)V
L11:    iload_0
L12:    aload_1
L13:    iconst_4
L14:    iconst_1
L15:    dup
L16:    pop2
L17:    invokestatic Method org/lwjgl/l method2056 (Ljava/nio/DoubleBuffer;I)V
L20:    aload_1
L21:    invokestatic Method org/lwjgl/MemoryUtil method1840 (Ljava/nio/DoubleBuffer;)J
L24:    lload_2
L25:    invokestatic Method org/lwjgl/opengl/GL11 nglGetClipPlane (IJJ)V
L28:    return
L29:    
    .end code
.end method

.method static native nglRasterPos3d : (DDDJ)V
.end method

.method public static method3688 : (ILjava/nio/IntBuffer;)V
    .code stack 5 locals 4
L0:     invokestatic Method org/lwjgl/opengl/GLContext method4611 ()Lorg/lwjgl/opengl/kb;
L3:     getfield Field org/lwjgl/opengl/kb try J
L6:     dup2
L7:     lstore_2
L8:     invokestatic Method org/lwjgl/l method2052 (J)V
L11:    iload_0
L12:    aload_1
L13:    bipush 16
L15:    iconst_1
L16:    dup
L17:    pop2
L18:    invokestatic Method org/lwjgl/l method2041 (Ljava/nio/IntBuffer;I)V
L21:    aload_1
L22:    invokestatic Method org/lwjgl/MemoryUtil method1884 (Ljava/nio/IntBuffer;)J
L25:    lload_2
L26:    invokestatic Method org/lwjgl/opengl/GL11 nglGetIntegerv (IJJ)V
L29:    return
L30:    
    .end code
.end method

.method static native nglLightModelfv : (IJJ)V
.end method

.method public static method3689 : (IIIII)V
    .code stack 7 locals 7
L0:     invokestatic Method org/lwjgl/opengl/GLContext method4611 ()Lorg/lwjgl/opengl/kb;
L3:     getfield Field org/lwjgl/opengl/kb lL J
L6:     dup2
L7:     lstore 5
L9:     invokestatic Method org/lwjgl/l method2052 (J)V
L12:    iload_0
L13:    iload_1
L14:    iload_2
L15:    iload_3
L16:    iload 4
L18:    lload 5
L20:    invokestatic Method org/lwjgl/opengl/GL11 nglEvalMesh2 (IIIIIJ)V
L23:    return
L24:    
    .end code
.end method

.method public static method3690 : (ILjava/nio/IntBuffer;)V
    .code stack 5 locals 4
L0:     invokestatic Method org/lwjgl/opengl/GLContext method4611 ()Lorg/lwjgl/opengl/kb;
L3:     getfield Field org/lwjgl/opengl/kb Mk J
L6:     dup2
L7:     lstore_2
L8:     invokestatic Method org/lwjgl/l method2052 (J)V
L11:    iload_0
L12:    aload_1
L13:    iconst_4
L14:    iconst_1
L15:    dup
L16:    pop2
L17:    invokestatic Method org/lwjgl/l method2041 (Ljava/nio/IntBuffer;I)V
L20:    aload_1
L21:    invokestatic Method org/lwjgl/MemoryUtil method1884 (Ljava/nio/IntBuffer;)J
L24:    lload_2
L25:    invokestatic Method org/lwjgl/opengl/GL11 nglFogiv (IJJ)V
L28:    return
L29:    
    .end code
.end method

.method public static method3691 : (IIIJ)V
    .code stack 7 locals 7
L0:     invokestatic Method org/lwjgl/opengl/GLContext method4611 ()Lorg/lwjgl/opengl/kb;
L3:     dup
L4:     getfield Field org/lwjgl/opengl/kb rt J
L7:     dup2
L8:     lstore 5
L10:    invokestatic Method org/lwjgl/l method2052 (J)V
L13:    invokestatic Method org/lwjgl/opengl/Zd method5441 (Lorg/lwjgl/opengl/kb;)V
L16:    iload_0
L17:    iload_1
L18:    iload_2
L19:    lload_3
L20:    lload 5
L22:    invokestatic Method org/lwjgl/opengl/GL11 nglTexCoordPointerBO (IIIJJ)V
L25:    return
L26:    
    .end code
.end method

.method static native nglVertexPointer : (IIIJJ)V
.end method

.method static native nglColor4d : (DDDDJ)V
.end method

.method static native nglColor3f : (FFFJ)V
.end method

.method public static method3692 : (DDDD)V
    .code stack 10 locals 10
L0:     invokestatic Method org/lwjgl/opengl/GLContext method4611 ()Lorg/lwjgl/opengl/kb;
L3:     getfield Field org/lwjgl/opengl/kb OJ J
L6:     dup2
L7:     lstore 8
L9:     invokestatic Method org/lwjgl/l method2052 (J)V
L12:    dload_0
L13:    dload_2
L14:    dload 4
L16:    dload 6
L18:    lload 8
L20:    invokestatic Method org/lwjgl/opengl/GL11 nglTexCoord4d (DDDDJ)V
L23:    return
L24:    
    .end code
.end method

.method static native nglBegin : (IJ)V
.end method

.method public static new : ()I
    .code stack 4 locals 2
L0:     invokestatic Method org/lwjgl/opengl/GLContext method4611 ()Lorg/lwjgl/opengl/kb;
L3:     getfield Field org/lwjgl/opengl/kb ou J
L6:     dup2
L7:     lstore_0
L8:     invokestatic Method org/lwjgl/l method2052 (J)V
L11:    lload_0
L12:    invokestatic Method org/lwjgl/opengl/GL11 nglGetError (J)I
L15:    ireturn
L16:    
    .end code
.end method

.method static native nglRasterPos2f : (FFJ)V
.end method

.method public static method3693 : (IILjava/nio/FloatBuffer;)V
    .code stack 6 locals 5
L0:     invokestatic Method org/lwjgl/opengl/GLContext method4611 ()Lorg/lwjgl/opengl/kb;
L3:     getfield Field org/lwjgl/opengl/kb Nt J
L6:     dup2
L7:     lstore_3
L8:     invokestatic Method org/lwjgl/l method2052 (J)V
L11:    iload_0
L12:    aload_2
L13:    iconst_4
L14:    iconst_1
L15:    dup
L16:    pop2
L17:    invokestatic Method org/lwjgl/l method2044 (Ljava/nio/FloatBuffer;I)V
L20:    iload_1
L21:    aload_2
L22:    invokestatic Method org/lwjgl/MemoryUtil method1878 (Ljava/nio/FloatBuffer;)J
L25:    lload_3
L26:    invokestatic Method org/lwjgl/opengl/GL11 nglMaterialfv (IIJJ)V
L29:    return
L30:    
    .end code
.end method

.method static native nglColor3b : (BBBJ)V
.end method

.method public static try : (III)V
    .code stack 5 locals 5
L0:     invokestatic Method org/lwjgl/opengl/GLContext method4611 ()Lorg/lwjgl/opengl/kb;
L3:     getfield Field org/lwjgl/opengl/kb hR J
L6:     dup2
L7:     lstore_3
L8:     invokestatic Method org/lwjgl/l method2052 (J)V
L11:    iload_0
L12:    iload_1
L13:    iload_2
L14:    lload_3
L15:    invokestatic Method org/lwjgl/opengl/GL11 nglLighti (IIIJ)V
L18:    return
L19:    
    .end code
.end method

.method public static try : ()V
    .code stack 4 locals 2
L0:     invokestatic Method org/lwjgl/opengl/GLContext method4611 ()Lorg/lwjgl/opengl/kb;
L3:     getfield Field org/lwjgl/opengl/kb Rj J
L6:     dup2
L7:     lstore_0
L8:     invokestatic Method org/lwjgl/l method2052 (J)V
L11:    lload_0
L12:    invokestatic Method org/lwjgl/opengl/GL11 nglEndList (J)V
L15:    return
L16:    
    .end code
.end method

.method public static method3694 : (Z)V
    .code stack 4 locals 3
L0:     invokestatic Method org/lwjgl/opengl/GLContext method4611 ()Lorg/lwjgl/opengl/kb;
L3:     getfield Field org/lwjgl/opengl/kb wd J
L6:     dup2
L7:     lstore_1
L8:     invokestatic Method org/lwjgl/l method2052 (J)V
L11:    iload_0
L12:    lload_1
L13:    invokestatic Method org/lwjgl/opengl/GL11 nglEdgeFlag (ZJ)V
L16:    return
L17:    
    .end code
.end method

.method public static method3695 : (IIILjava/nio/IntBuffer;)V
    .code stack 7 locals 6
L0:     invokestatic Method org/lwjgl/opengl/GLContext method4611 ()Lorg/lwjgl/opengl/kb;
L3:     getfield Field org/lwjgl/opengl/kb Yi J
L6:     dup2
L7:     lstore 4
L9:     invokestatic Method org/lwjgl/l method2052 (J)V
L12:    iload_0
L13:    aload_3
L14:    iconst_4
L15:    iconst_1
L16:    dup
L17:    pop2
L18:    invokestatic Method org/lwjgl/l method2041 (Ljava/nio/IntBuffer;I)V
L21:    iload_1
L22:    iload_2
L23:    aload_3
L24:    invokestatic Method org/lwjgl/MemoryUtil method1884 (Ljava/nio/IntBuffer;)J
L27:    lload 4
L29:    invokestatic Method org/lwjgl/opengl/GL11 nglGetTexLevelParameteriv (IIIJJ)V
L32:    return
L33:    
    .end code
.end method

.method static native nglRotatef : (FFFFJ)V
.end method

.method public static method3696 : (F)V
    .code stack 4 locals 3
L0:     invokestatic Method org/lwjgl/opengl/GLContext method4611 ()Lorg/lwjgl/opengl/kb;
L3:     getfield Field org/lwjgl/opengl/kb HH J
L6:     dup2
L7:     lstore_1
L8:     invokestatic Method org/lwjgl/l method2052 (J)V
L11:    fload_0
L12:    lload_1
L13:    invokestatic Method org/lwjgl/opengl/GL11 nglPointSize (FJ)V
L16:    return
L17:    
    .end code
.end method

.method static native nglReadPixelsBO : (IIIIIIJJ)V
.end method

.method public static method3697 : (II)I
    .code stack 6 locals 5
L0:     invokestatic Method org/lwjgl/opengl/GLContext method4611 ()Lorg/lwjgl/opengl/kb;
L3:     dup
L4:     getfield Field org/lwjgl/opengl/kb Wr J
L7:     dup2
L8:     lstore_3
L9:     invokestatic Method org/lwjgl/l method2052 (J)V
L12:    invokestatic Method org/lwjgl/opengl/bB method5467 (Lorg/lwjgl/opengl/kb;)Ljava/nio/IntBuffer;
L15:    astore_2
L16:    iload_0
L17:    iload_1
L18:    aload_2
L19:    invokestatic Method org/lwjgl/MemoryUtil method1884 (Ljava/nio/IntBuffer;)J
L22:    lload_3
L23:    invokestatic Method org/lwjgl/opengl/GL11 nglGetTexEnviv (IIJJ)V
L26:    aload_2
L27:    iconst_0
L28:    iconst_1
L29:    dup
L30:    pop2
L31:    invokevirtual Method java/nio/IntBuffer get (I)I
L34:    ireturn
L35:    
    .end code
.end method

.method public static method3698 : (F)V
    .code stack 4 locals 3
L0:     invokestatic Method org/lwjgl/opengl/GLContext method4611 ()Lorg/lwjgl/opengl/kb;
L3:     getfield Field org/lwjgl/opengl/kb field5442 J
L6:     dup2
L7:     lstore_1
L8:     invokestatic Method org/lwjgl/l method2052 (J)V
L11:    fload_0
L12:    lload_1
L13:    invokestatic Method org/lwjgl/opengl/GL11 nglLineWidth (FJ)V
L16:    return
L17:    
    .end code
.end method

.method static native nglRectd : (DDDDJ)V
.end method

.method public static method3699 : (ILjava/nio/ShortBuffer;)V
    .code stack 6 locals 5
L0:     invokestatic Method org/lwjgl/opengl/GLContext method4611 ()Lorg/lwjgl/opengl/kb;
L3:     astore_2
L4:     aload_1
L5:     aload_2
L6:     dup
L7:     getfield Field org/lwjgl/opengl/kb FU J
L10:    dup2
L11:    lstore_3
L12:    invokestatic Method org/lwjgl/l method2052 (J)V
L15:    invokestatic Method org/lwjgl/opengl/Zd method5449 (Lorg/lwjgl/opengl/kb;)V
L18:    sipush 256
L21:    iconst_1
L22:    dup
L23:    pop2
L24:    invokestatic Method org/lwjgl/l method2031 (Ljava/nio/ShortBuffer;I)V
L27:    iload_0
L28:    aload_1
L29:    invokestatic Method org/lwjgl/MemoryUtil method1853 (Ljava/nio/ShortBuffer;)J
L32:    lload_3
L33:    invokestatic Method org/lwjgl/opengl/GL11 nglGetPixelMapusv (IJJ)V
L36:    return
L37:    
    .end code
.end method

.method public static method3700 : (IILjava/nio/IntBuffer;)V
    .code stack 6 locals 5
L0:     invokestatic Method org/lwjgl/opengl/GLContext method4611 ()Lorg/lwjgl/opengl/kb;
L3:     getfield Field org/lwjgl/opengl/kb Oq J
L6:     dup2
L7:     lstore_3
L8:     invokestatic Method org/lwjgl/l method2052 (J)V
L11:    iload_0
L12:    aload_2
L13:    sipush 256
L16:    iconst_1
L17:    dup
L18:    pop2
L19:    invokestatic Method org/lwjgl/l method2041 (Ljava/nio/IntBuffer;I)V
L22:    iload_1
L23:    aload_2
L24:    invokestatic Method org/lwjgl/MemoryUtil method1884 (Ljava/nio/IntBuffer;)J
L27:    lload_3
L28:    invokestatic Method org/lwjgl/opengl/GL11 nglGetMapiv (IIJJ)V
L31:    return
L32:    
    .end code
.end method

.method public static method3701 : (II)D
    .code stack 6 locals 5
L0:     invokestatic Method org/lwjgl/opengl/GLContext method4611 ()Lorg/lwjgl/opengl/kb;
L3:     dup
L4:     getfield Field org/lwjgl/opengl/kb zG J
L7:     dup2
L8:     lstore_3
L9:     invokestatic Method org/lwjgl/l method2052 (J)V
L12:    invokestatic Method org/lwjgl/opengl/bB method5474 (Lorg/lwjgl/opengl/kb;)Ljava/nio/DoubleBuffer;
L15:    astore_2
L16:    iload_0
L17:    iload_1
L18:    aload_2
L19:    invokestatic Method org/lwjgl/MemoryUtil method1840 (Ljava/nio/DoubleBuffer;)J
L22:    lload_3
L23:    invokestatic Method org/lwjgl/opengl/GL11 nglGetTexGendv (IIJJ)V
L26:    aload_2
L27:    iconst_0
L28:    iconst_1
L29:    dup
L30:    pop2
L31:    invokevirtual Method java/nio/DoubleBuffer get (I)D
L34:    dreturn
L35:    
    .end code
.end method

.method static native nglColorPointerBO : (IIIJJ)V
.end method

.method public static method3702 : (II)F
    .code stack 6 locals 5
L0:     invokestatic Method org/lwjgl/opengl/GLContext method4611 ()Lorg/lwjgl/opengl/kb;
L3:     dup
L4:     getfield Field org/lwjgl/opengl/kb iu J
L7:     dup2
L8:     lstore_3
L9:     invokestatic Method org/lwjgl/l method2052 (J)V
L12:    invokestatic Method org/lwjgl/opengl/bB method5465 (Lorg/lwjgl/opengl/kb;)Ljava/nio/FloatBuffer;
L15:    astore_2
L16:    iload_0
L17:    iload_1
L18:    aload_2
L19:    invokestatic Method org/lwjgl/MemoryUtil method1878 (Ljava/nio/FloatBuffer;)J
L22:    lload_3
L23:    invokestatic Method org/lwjgl/opengl/GL11 nglGetTexEnvfv (IIJJ)V
L26:    aload_2
L27:    iconst_0
L28:    iconst_1
L29:    dup
L30:    pop2
L31:    invokevirtual Method java/nio/FloatBuffer get (I)F
L34:    freturn
L35:    
    .end code
.end method

.method static native nglPixelMapuiv : (IIJJ)V
.end method

.method static native nglEndList : (J)V
.end method

.method public static method3703 : (F)V
    .code stack 4 locals 3
L0:     invokestatic Method org/lwjgl/opengl/GLContext method4611 ()Lorg/lwjgl/opengl/kb;
L3:     getfield Field org/lwjgl/opengl/kb rN J
L6:     dup2
L7:     lstore_1
L8:     invokestatic Method org/lwjgl/l method2052 (J)V
L11:    fload_0
L12:    lload_1
L13:    invokestatic Method org/lwjgl/opengl/GL11 nglEvalCoord1f (FJ)V
L16:    return
L17:    
    .end code
.end method

.method static native nglTexParameterfv : (IIJJ)V
.end method

.method static native nglPopClientAttrib : (J)V
.end method

.method public static this : (III)V
    .code stack 5 locals 5
L0:     invokestatic Method org/lwjgl/opengl/GLContext method4611 ()Lorg/lwjgl/opengl/kb;
L3:     getfield Field org/lwjgl/opengl/kb Od J
L6:     dup2
L7:     lstore_3
L8:     invokestatic Method org/lwjgl/l method2052 (J)V
L11:    iload_0
L12:    iload_1
L13:    iload_2
L14:    lload_3
L15:    invokestatic Method org/lwjgl/opengl/GL11 nglStencilOp (IIIJ)V
L18:    return
L19:    
    .end code
.end method

.method public static new : (IILjava/nio/IntBuffer;)V
    .code stack 7 locals 6
L0:     invokestatic Method org/lwjgl/opengl/GLContext method4611 ()Lorg/lwjgl/opengl/kb;
L3:     astore_3
L4:     aload_2
L5:     aload_3
L6:     dup
L7:     getfield Field org/lwjgl/opengl/kb VM J
L10:    dup2
L11:    lstore 4
L13:    invokestatic Method org/lwjgl/l method2052 (J)V
L16:    invokestatic Method org/lwjgl/opengl/Zd method5454 (Lorg/lwjgl/opengl/kb;)V
L19:    invokestatic Method org/lwjgl/l method2043 (Ljava/nio/IntBuffer;)V
L22:    getstatic Field org/lwjgl/LWJGLUtil CHECKS Z
L25:    ifeq L36
L28:    aload_3
L29:    invokestatic Method org/lwjgl/opengl/w method5768 (Lorg/lwjgl/opengl/kb;)Lorg/lwjgl/opengl/P;
L32:    aload_2
L33:    putfield Field org/lwjgl/opengl/P field4944 Ljava/nio/Buffer;
L36:    iload_0
L37:    sipush 5124
L40:    iconst_1
L41:    dup
L42:    pop2
L43:    iload_1
L44:    aload_2
L45:    invokestatic Method org/lwjgl/MemoryUtil method1884 (Ljava/nio/IntBuffer;)J
L48:    lload 4
L50:    invokestatic Method org/lwjgl/opengl/GL11 nglVertexPointer (IIIJJ)V
L53:    return
L54:    
        .attribute StackMap b'\x00\x01\x00\x24\x00\x05\x01\x01\x07\x04\x5F\x07\x04\x21\x04\x00\x00'
    .end code
.end method

.method public static method3704 : (IIIIIIII)V
    .code stack 10 locals 10
L0:     invokestatic Method org/lwjgl/opengl/GLContext method4611 ()Lorg/lwjgl/opengl/kb;
L3:     getfield Field org/lwjgl/opengl/kb in J
L6:     dup2
L7:     lstore 8
L9:     invokestatic Method org/lwjgl/l method2052 (J)V
L12:    iload_0
L13:    iload_1
L14:    iload_2
L15:    iload_3
L16:    iload 4
L18:    iload 5
L20:    iload 6
L22:    iload 7
L24:    lload 8
L26:    invokestatic Method org/lwjgl/opengl/GL11 nglCopyTexImage2D (IIIIIIIIJ)V
L29:    return
L30:    
    .end code
.end method

.method public static method3705 : (I)V
    .code stack 4 locals 3
L0:     invokestatic Method org/lwjgl/opengl/GLContext method4611 ()Lorg/lwjgl/opengl/kb;
L3:     getfield Field org/lwjgl/opengl/kb HK J
L6:     dup2
L7:     lstore_1
L8:     invokestatic Method org/lwjgl/l method2052 (J)V
L11:    iload_0
L12:    lload_1
L13:    invokestatic Method org/lwjgl/opengl/GL11 nglMatrixMode (IJ)V
L16:    return
L17:    
    .end code
.end method

.method public static method3706 : (I)I
    .code stack 4 locals 3
L0:     invokestatic Method org/lwjgl/opengl/GLContext method4611 ()Lorg/lwjgl/opengl/kb;
L3:     getfield Field org/lwjgl/opengl/kb kM J
L6:     dup2
L7:     lstore_1
L8:     invokestatic Method org/lwjgl/l method2052 (J)V
L11:    iload_0
L12:    lload_1
L13:    invokestatic Method org/lwjgl/opengl/GL11 nglGenLists (IJ)I
L16:    ireturn
L17:    
    .end code
.end method

.method public static method3707 : (IIIIIILjava/nio/ShortBuffer;)V
    .code stack 10 locals 10
L0:     invokestatic Method org/lwjgl/opengl/GLContext method4611 ()Lorg/lwjgl/opengl/kb;
L3:     astore 7
L5:     aload 6
L7:     aload 7
L9:     dup
L10:    getfield Field org/lwjgl/opengl/kb oL J
L13:    dup2
L14:    lstore 8
L16:    invokestatic Method org/lwjgl/l method2052 (J)V
L19:    invokestatic Method org/lwjgl/opengl/Zd method5449 (Lorg/lwjgl/opengl/kb;)V
L22:    aload 6
L24:    iload 4
L26:    iload 5
L28:    iload_2
L29:    iload_3
L30:    iconst_1
L31:    dup
L32:    dup
L33:    pop2
L34:    invokestatic Method org/lwjgl/opengl/Zd method5429 (Ljava/nio/Buffer;IIIII)I
L37:    invokestatic Method org/lwjgl/l method2031 (Ljava/nio/ShortBuffer;I)V
L40:    iload_0
L41:    iload_1
L42:    iload_2
L43:    iload_3
L44:    iload 4
L46:    iload 5
L48:    aload 6
L50:    invokestatic Method org/lwjgl/MemoryUtil method1853 (Ljava/nio/ShortBuffer;)J
L53:    lload 8
L55:    invokestatic Method org/lwjgl/opengl/GL11 nglReadPixels (IIIIIIJJ)V
L58:    return
L59:    
    .end code
.end method

.method static native nglRasterPos4i : (IIIIJ)V
.end method

.method static native nglCopyTexSubImage1D : (IIIIIIJ)V
.end method

.method public static method3708 : (IJ)V
    .code stack 5 locals 5
L0:     invokestatic Method org/lwjgl/opengl/GLContext method4611 ()Lorg/lwjgl/opengl/kb;
L3:     dup
L4:     getfield Field org/lwjgl/opengl/kb FU J
L7:     dup2
L8:     lstore_3
L9:     invokestatic Method org/lwjgl/l method2052 (J)V
L12:    invokestatic Method org/lwjgl/opengl/Zd method5436 (Lorg/lwjgl/opengl/kb;)V
L15:    iload_0
L16:    lload_1
L17:    lload_3
L18:    invokestatic Method org/lwjgl/opengl/GL11 nglGetPixelMapusvBO (IJJ)V
L21:    return
L22:    
    .end code
.end method

.method public static method3709 : (I)V
    .code stack 4 locals 3
L0:     invokestatic Method org/lwjgl/opengl/GLContext method4611 ()Lorg/lwjgl/opengl/kb;
L3:     getfield Field org/lwjgl/opengl/kb SN J
L6:     dup2
L7:     lstore_1
L8:     invokestatic Method org/lwjgl/l method2052 (J)V
L11:    iload_0
L12:    lload_1
L13:    invokestatic Method org/lwjgl/opengl/GL11 nglPushName (IJ)V
L16:    return
L17:    
    .end code
.end method

.method static native nglLineWidth : (FJ)V
.end method

.method static native nglLighti : (IIIJ)V
.end method

.method public static method3710 : (IIIIIILjava/nio/ShortBuffer;)V
    .code stack 10 locals 10
L0:     invokestatic Method org/lwjgl/opengl/GLContext method4611 ()Lorg/lwjgl/opengl/kb;
L3:     astore 7
L5:     aload 6
L7:     aload 7
L9:     dup
L10:    getfield Field org/lwjgl/opengl/kb Zi J
L13:    dup2
L14:    lstore 8
L16:    invokestatic Method org/lwjgl/l method2052 (J)V
L19:    invokestatic Method org/lwjgl/opengl/Zd method5446 (Lorg/lwjgl/opengl/kb;)V
L22:    aload 6
L24:    iload 4
L26:    iload 5
L28:    iload_3
L29:    iconst_1
L30:    dup
L31:    pop2
L32:    iconst_1
L33:    dup
L34:    dup_x1
L35:    dup
L36:    pop2
L37:    invokestatic Method org/lwjgl/opengl/Zd method5429 (Ljava/nio/Buffer;IIIII)I
L40:    invokestatic Method org/lwjgl/l method2031 (Ljava/nio/ShortBuffer;I)V
L43:    iload_0
L44:    iload_1
L45:    iload_2
L46:    iload_3
L47:    iload 4
L49:    iload 5
L51:    aload 6
L53:    invokestatic Method org/lwjgl/MemoryUtil method1853 (Ljava/nio/ShortBuffer;)J
L56:    lload 8
L58:    invokestatic Method org/lwjgl/opengl/GL11 nglTexSubImage1D (IIIIIIJJ)V
L61:    return
L62:    
    .end code
.end method

.method public static method3711 : (IJ)V
    .code stack 5 locals 5
L0:     invokestatic Method org/lwjgl/opengl/GLContext method4611 ()Lorg/lwjgl/opengl/kb;
L3:     dup
L4:     getfield Field org/lwjgl/opengl/kb cG J
L7:     dup2
L8:     lstore_3
L9:     invokestatic Method org/lwjgl/l method2052 (J)V
L12:    invokestatic Method org/lwjgl/opengl/Zd method5436 (Lorg/lwjgl/opengl/kb;)V
L15:    iload_0
L16:    lload_1
L17:    lload_3
L18:    invokestatic Method org/lwjgl/opengl/GL11 nglGetPixelMapuivBO (IJJ)V
L21:    return
L22:    
    .end code
.end method

.method static native nglGetError : (J)I
.end method

.method public static method3712 : (FFFF)V
    .code stack 6 locals 6
L0:     invokestatic Method org/lwjgl/opengl/GLContext method4611 ()Lorg/lwjgl/opengl/kb;
L3:     getfield Field org/lwjgl/opengl/kb Wo J
L6:     dup2
L7:     lstore 4
L9:     invokestatic Method org/lwjgl/l method2052 (J)V
L12:    fload_0
L13:    fload_1
L14:    fload_2
L15:    fload_3
L16:    lload 4
L18:    invokestatic Method org/lwjgl/opengl/GL11 nglRasterPos4f (FFFFJ)V
L21:    return
L22:    
    .end code
.end method

.method public static method3713 : (III)V
    .code stack 5 locals 5
L0:     invokestatic Method org/lwjgl/opengl/GLContext method4611 ()Lorg/lwjgl/opengl/kb;
L3:     getfield Field org/lwjgl/opengl/kb JG J
L6:     dup2
L7:     lstore_3
L8:     invokestatic Method org/lwjgl/l method2052 (J)V
L11:    iload_0
L12:    iload_1
L13:    iload_2
L14:    lload_3
L15:    invokestatic Method org/lwjgl/opengl/GL11 nglMateriali (IIIJ)V
L18:    return
L19:    
    .end code
.end method

.method static native nglColor3ub : (BBBJ)V
.end method

.method public static method3714 : (I)V
    .code stack 4 locals 3
L0:     invokestatic Method org/lwjgl/opengl/GLContext method4611 ()Lorg/lwjgl/opengl/kb;
L3:     getfield Field org/lwjgl/opengl/kb xD J
L6:     dup2
L7:     lstore_1
L8:     invokestatic Method org/lwjgl/l method2052 (J)V
L11:    iload_0
L12:    lload_1
L13:    invokestatic Method org/lwjgl/opengl/GL11 nglArrayElement (IJ)V
L16:    return
L17:    
    .end code
.end method

.method public static method3715 : (DD)V
    .code stack 6 locals 6
L0:     invokestatic Method org/lwjgl/opengl/GLContext method4611 ()Lorg/lwjgl/opengl/kb;
L3:     getfield Field org/lwjgl/opengl/kb Cs J
L6:     dup2
L7:     lstore 4
L9:     invokestatic Method org/lwjgl/l method2052 (J)V
L12:    dload_0
L13:    dload_2
L14:    lload 4
L16:    invokestatic Method org/lwjgl/opengl/GL11 nglRasterPos2d (DDJ)V
L19:    return
L20:    
    .end code
.end method

.method static native nglNormal3f : (FFFJ)V
.end method

.method static native nglNormal3b : (BBBJ)V
.end method

.method static native nglMaterialf : (IIFJ)V
.end method

.method static native nglDrawPixelsBO : (IIIIJJ)V
.end method

.method static native nglGetTexGenfv : (IIJJ)V
.end method

.method public static new : (IILjava/nio/FloatBuffer;)V
    .code stack 6 locals 5
L0:     invokestatic Method org/lwjgl/opengl/GLContext method4611 ()Lorg/lwjgl/opengl/kb;
L3:     getfield Field org/lwjgl/opengl/kb mK J
L6:     dup2
L7:     lstore_3
L8:     invokestatic Method org/lwjgl/l method2052 (J)V
L11:    iload_0
L12:    aload_2
L13:    iconst_4
L14:    iconst_1
L15:    dup
L16:    pop2
L17:    invokestatic Method org/lwjgl/l method2044 (Ljava/nio/FloatBuffer;I)V
L20:    iload_1
L21:    aload_2
L22:    invokestatic Method org/lwjgl/MemoryUtil method1878 (Ljava/nio/FloatBuffer;)J
L25:    lload_3
L26:    invokestatic Method org/lwjgl/opengl/GL11 nglGetMaterialfv (IIJJ)V
L29:    return
L30:    
    .end code
.end method

.method static native nglGetString : (IJ)Ljava/lang/String;
.end method

.method static native nglMap2f : (IFFIIFFIIJJ)V
.end method

.method static native nglGetPolygonStipple : (JJ)V
.end method

.method public static method3716 : (IIF)V
    .code stack 5 locals 5
L0:     invokestatic Method org/lwjgl/opengl/GLContext method4611 ()Lorg/lwjgl/opengl/kb;
L3:     getfield Field org/lwjgl/opengl/kb yn J
L6:     dup2
L7:     lstore_3
L8:     invokestatic Method org/lwjgl/l method2052 (J)V
L11:    iload_0
L12:    iload_1
L13:    fload_2
L14:    lload_3
L15:    invokestatic Method org/lwjgl/opengl/GL11 nglTexEnvf (IIFJ)V
L18:    return
L19:    
    .end code
.end method

.method static native nglGetPixelMapfv : (IJJ)V
.end method

.method public static method3717 : (F)V
    .code stack 4 locals 3
L0:     invokestatic Method org/lwjgl/opengl/GLContext method4611 ()Lorg/lwjgl/opengl/kb;
L3:     getfield Field org/lwjgl/opengl/kb Kc J
L6:     dup2
L7:     lstore_1
L8:     invokestatic Method org/lwjgl/l method2052 (J)V
L11:    fload_0
L12:    lload_1
L13:    invokestatic Method org/lwjgl/opengl/GL11 nglPassThrough (FJ)V
L16:    return
L17:    
    .end code
.end method

.method static native nglEvalPoint1 : (IJ)V
.end method

.method public static false : (I)Z
    .code stack 4 locals 3
L0:     invokestatic Method org/lwjgl/opengl/GLContext method4611 ()Lorg/lwjgl/opengl/kb;
L3:     getfield Field org/lwjgl/opengl/kb TH J
L6:     dup2
L7:     lstore_1
L8:     invokestatic Method org/lwjgl/l method2052 (J)V
L11:    iload_0
L12:    lload_1
L13:    invokestatic Method org/lwjgl/opengl/GL11 nglIsTexture (IJ)Z
L16:    ireturn
L17:    
    .end code
.end method

.method public static method3718 : (IIII)V
    .code stack 6 locals 6
L0:     invokestatic Method org/lwjgl/opengl/GLContext method4611 ()Lorg/lwjgl/opengl/kb;
L3:     getfield Field org/lwjgl/opengl/kb IS J
L6:     dup2
L7:     lstore 4
L9:     invokestatic Method org/lwjgl/l method2052 (J)V
L12:    iload_0
L13:    iload_1
L14:    iload_2
L15:    iload_3
L16:    lload 4
L18:    invokestatic Method org/lwjgl/opengl/GL11 nglRasterPos4i (IIIIJ)V
L21:    return
L22:    
    .end code
.end method

.method public static method3719 : (ILjava/nio/FloatBuffer;)V
    .code stack 5 locals 4
L0:     invokestatic Method org/lwjgl/opengl/GLContext method4611 ()Lorg/lwjgl/opengl/kb;
L3:     getfield Field org/lwjgl/opengl/kb wQ J
L6:     dup2
L7:     lstore_2
L8:     invokestatic Method org/lwjgl/l method2052 (J)V
L11:    iload_0
L12:    aload_1
L13:    iconst_4
L14:    iconst_1
L15:    dup
L16:    pop2
L17:    invokestatic Method org/lwjgl/l method2044 (Ljava/nio/FloatBuffer;I)V
L20:    aload_1
L21:    invokestatic Method org/lwjgl/MemoryUtil method1878 (Ljava/nio/FloatBuffer;)J
L24:    lload_2
L25:    invokestatic Method org/lwjgl/opengl/GL11 nglLightModelfv (IJJ)V
L28:    return
L29:    
    .end code
.end method

.method public static try : (IILjava/nio/FloatBuffer;)V
    .code stack 6 locals 5
L0:     invokestatic Method org/lwjgl/opengl/GLContext method4611 ()Lorg/lwjgl/opengl/kb;
L3:     getfield Field org/lwjgl/opengl/kb Pl J
L6:     dup2
L7:     lstore_3
L8:     invokestatic Method org/lwjgl/l method2052 (J)V
L11:    iload_0
L12:    aload_2
L13:    iconst_4
L14:    iconst_1
L15:    dup
L16:    pop2
L17:    invokestatic Method org/lwjgl/l method2044 (Ljava/nio/FloatBuffer;I)V
L20:    iload_1
L21:    aload_2
L22:    invokestatic Method org/lwjgl/MemoryUtil method1878 (Ljava/nio/FloatBuffer;)J
L25:    lload_3
L26:    invokestatic Method org/lwjgl/opengl/GL11 nglLightfv (IIJJ)V
L29:    return
L30:    
    .end code
.end method

.method static native nglLoadMatrixf : (JJ)V
.end method

.method static native nglVertex2i : (IIJ)V
.end method

.method public static try : (IILjava/nio/IntBuffer;)V
    .code stack 6 locals 6
L0:     invokestatic Method org/lwjgl/opengl/GLContext method4611 ()Lorg/lwjgl/opengl/kb;
L3:     astore_3
L4:     aload_2
L5:     aload_3
L6:     dup
L7:     getfield Field org/lwjgl/opengl/kb MB J
L10:    dup2
L11:    lstore 4
L13:    invokestatic Method org/lwjgl/l method2052 (J)V
L16:    invokestatic Method org/lwjgl/opengl/Zd method5454 (Lorg/lwjgl/opengl/kb;)V
L19:    invokestatic Method org/lwjgl/l method2043 (Ljava/nio/IntBuffer;)V
L22:    iload_0
L23:    iload_1
L24:    aload_2
L25:    invokestatic Method org/lwjgl/MemoryUtil method1884 (Ljava/nio/IntBuffer;)J
L28:    lload 4
L30:    invokestatic Method org/lwjgl/opengl/GL11 nglInterleavedArrays (IIJJ)V
L33:    return
L34:    
    .end code
.end method

.method static native nglVertex2f : (FFJ)V
.end method

.method public static true : (I)Z
    .code stack 4 locals 3
L0:     invokestatic Method org/lwjgl/opengl/GLContext method4611 ()Lorg/lwjgl/opengl/kb;
L3:     getfield Field org/lwjgl/opengl/kb Uu J
L6:     dup2
L7:     lstore_1
L8:     invokestatic Method org/lwjgl/l method2052 (J)V
L11:    iload_0
L12:    lload_1
L13:    invokestatic Method org/lwjgl/opengl/GL11 nglIsList (IJ)Z
L16:    ireturn
L17:    
    .end code
.end method

.method static native nglLoadIdentity : (J)V
.end method

.method static native nglAccum : (IFJ)V
.end method

.method static native nglTranslated : (DDDJ)V
.end method

.method static native nglArrayElement : (IJ)V
.end method

.method static native nglCopyTexSubImage2D : (IIIIIIIIJ)V
.end method

.method public static this : ()V
    .code stack 4 locals 2
L0:     invokestatic Method org/lwjgl/opengl/GLContext method4611 ()Lorg/lwjgl/opengl/kb;
L3:     getfield Field org/lwjgl/opengl/kb BF J
L6:     dup2
L7:     lstore_0
L8:     invokestatic Method org/lwjgl/l method2052 (J)V
L11:    lload_0
L12:    invokestatic Method org/lwjgl/opengl/GL11 nglPopAttrib (J)V
L15:    return
L16:    
    .end code
.end method

.method public static method3720 : (II)V
    .code stack 4 locals 4
L0:     invokestatic Method org/lwjgl/opengl/GLContext method4611 ()Lorg/lwjgl/opengl/kb;
L3:     getfield Field org/lwjgl/opengl/kb gT J
L6:     dup2
L7:     lstore_2
L8:     invokestatic Method org/lwjgl/l method2052 (J)V
L11:    iload_0
L12:    iload_1
L13:    lload_2
L14:    invokestatic Method org/lwjgl/opengl/GL11 nglPixelStorei (IIJ)V
L17:    return
L18:    
    .end code
.end method

.method static native nglHint : (IIJ)V
.end method

.method static native nglPolygonMode : (IIJ)V
.end method

.method static native nglCallList : (IJ)V
.end method

.method static native nglPixelMapfvBO : (IIJJ)V
.end method

.method public static method3721 : (I)I
    .code stack 5 locals 4
L0:     invokestatic Method org/lwjgl/opengl/GLContext method4611 ()Lorg/lwjgl/opengl/kb;
L3:     dup
L4:     getfield Field org/lwjgl/opengl/kb try J
L7:     dup2
L8:     lstore_2
L9:     invokestatic Method org/lwjgl/l method2052 (J)V
L12:    invokestatic Method org/lwjgl/opengl/bB method5467 (Lorg/lwjgl/opengl/kb;)Ljava/nio/IntBuffer;
L15:    astore_1
L16:    iload_0
L17:    aload_1
L18:    invokestatic Method org/lwjgl/MemoryUtil method1884 (Ljava/nio/IntBuffer;)J
L21:    lload_2
L22:    invokestatic Method org/lwjgl/opengl/GL11 nglGetIntegerv (IJJ)V
L25:    aload_1
L26:    iconst_0
L27:    iconst_1
L28:    dup
L29:    pop2
L30:    invokevirtual Method java/nio/IntBuffer get (I)I
L33:    ireturn
L34:    
    .end code
.end method

.method public static method3722 : (DDDD)V
    .code stack 10 locals 10
L0:     invokestatic Method org/lwjgl/opengl/GLContext method4611 ()Lorg/lwjgl/opengl/kb;
L3:     getfield Field org/lwjgl/opengl/kb zp J
L6:     dup2
L7:     lstore 8
L9:     invokestatic Method org/lwjgl/l method2052 (J)V
L12:    dload_0
L13:    dload_2
L14:    dload 4
L16:    dload 6
L18:    lload 8
L20:    invokestatic Method org/lwjgl/opengl/GL11 nglRotated (DDDDJ)V
L23:    return
L24:    
    .end code
.end method

.method static native nglGetDoublev : (IJJ)V
.end method

.method public static method3723 : (IIIILjava/nio/FloatBuffer;)V
    .code stack 9 locals 8
L0:     invokestatic Method org/lwjgl/opengl/GLContext method4611 ()Lorg/lwjgl/opengl/kb;
L3:     astore 5
L5:     aload 4
L7:     aload 5
L9:     dup
L10:    getfield Field org/lwjgl/opengl/kb cj J
L13:    dup2
L14:    lstore 6
L16:    invokestatic Method org/lwjgl/l method2052 (J)V
L19:    invokestatic Method org/lwjgl/opengl/Zd method5449 (Lorg/lwjgl/opengl/kb;)V
L22:    aload 4
L24:    iload_2
L25:    iload_3
L26:    iconst_1
L27:    dup
L28:    pop2
L29:    iconst_1
L30:    dup
L31:    pop2
L32:    iconst_1
L33:    dup
L34:    dup_x1
L35:    dup_x2
L36:    dup
L37:    pop2
L38:    invokestatic Method org/lwjgl/opengl/Zd method5429 (Ljava/nio/Buffer;IIIII)I
L41:    invokestatic Method org/lwjgl/l method2044 (Ljava/nio/FloatBuffer;I)V
L44:    iload_0
L45:    iload_1
L46:    iload_2
L47:    iload_3
L48:    aload 4
L50:    invokestatic Method org/lwjgl/MemoryUtil method1878 (Ljava/nio/FloatBuffer;)J
L53:    lload 6
L55:    invokestatic Method org/lwjgl/opengl/GL11 nglGetTexImage (IIIIJJ)V
L58:    return
L59:    
    .end code
.end method

.method public static this : (IILjava/nio/IntBuffer;)V
    .code stack 6 locals 5
L0:     invokestatic Method org/lwjgl/opengl/GLContext method4611 ()Lorg/lwjgl/opengl/kb;
L3:     getfield Field org/lwjgl/opengl/kb fp J
L6:     dup2
L7:     lstore_3
L8:     invokestatic Method org/lwjgl/l method2052 (J)V
L11:    iload_0
L12:    aload_2
L13:    iconst_4
L14:    iconst_1
L15:    dup
L16:    pop2
L17:    invokestatic Method org/lwjgl/l method2041 (Ljava/nio/IntBuffer;I)V
L20:    iload_1
L21:    aload_2
L22:    invokestatic Method org/lwjgl/MemoryUtil method1884 (Ljava/nio/IntBuffer;)J
L25:    lload_3
L26:    invokestatic Method org/lwjgl/opengl/GL11 nglTexGeniv (IIJJ)V
L29:    return
L30:    
    .end code
.end method

.method public static method3724 : ()I
    .code stack 5 locals 3
L0:     invokestatic Method org/lwjgl/opengl/GLContext method4611 ()Lorg/lwjgl/opengl/kb;
L3:     dup
L4:     getfield Field org/lwjgl/opengl/kb field5414 J
L7:     dup2
L8:     lstore_0
L9:     invokestatic Method org/lwjgl/l method2052 (J)V
L12:    invokestatic Method org/lwjgl/opengl/bB method5467 (Lorg/lwjgl/opengl/kb;)Ljava/nio/IntBuffer;
L15:    astore_2
L16:    iconst_1
L17:    dup
L18:    dup
L19:    pop2
L20:    aload_2
L21:    invokestatic Method org/lwjgl/MemoryUtil method1884 (Ljava/nio/IntBuffer;)J
L24:    lload_0
L25:    invokestatic Method org/lwjgl/opengl/GL11 nglGenTextures (IJJ)V
L28:    aload_2
L29:    iconst_0
L30:    iconst_1
L31:    dup
L32:    pop2
L33:    invokevirtual Method java/nio/IntBuffer get (I)I
L36:    ireturn
L37:    
    .end code
.end method

.method public static method3725 : (ZZZZ)V
    .code stack 6 locals 6
L0:     invokestatic Method org/lwjgl/opengl/GLContext method4611 ()Lorg/lwjgl/opengl/kb;
L3:     getfield Field org/lwjgl/opengl/kb Tf J
L6:     dup2
L7:     lstore 4
L9:     invokestatic Method org/lwjgl/l method2052 (J)V
L12:    iload_0
L13:    iload_1
L14:    iload_2
L15:    iload_3
L16:    lload 4
L18:    invokestatic Method org/lwjgl/opengl/GL11 nglColorMask (ZZZZJ)V
L21:    return
L22:    
    .end code
.end method

.method public static method3726 : (DDD)V
    .code stack 8 locals 8
L0:     invokestatic Method org/lwjgl/opengl/GLContext method4611 ()Lorg/lwjgl/opengl/kb;
L3:     getfield Field org/lwjgl/opengl/kb RL J
L6:     dup2
L7:     lstore 6
L9:     invokestatic Method org/lwjgl/l method2052 (J)V
L12:    dload_0
L13:    dload_2
L14:    dload 4
L16:    lload 6
L18:    invokestatic Method org/lwjgl/opengl/GL11 nglScaled (DDDJ)V
L21:    return
L22:    
    .end code
.end method

.method public static method3727 : (I)F
    .code stack 5 locals 4
L0:     invokestatic Method org/lwjgl/opengl/GLContext method4611 ()Lorg/lwjgl/opengl/kb;
L3:     dup
L4:     getfield Field org/lwjgl/opengl/kb eD J
L7:     dup2
L8:     lstore_2
L9:     invokestatic Method org/lwjgl/l method2052 (J)V
L12:    invokestatic Method org/lwjgl/opengl/bB method5465 (Lorg/lwjgl/opengl/kb;)Ljava/nio/FloatBuffer;
L15:    astore_1
L16:    iload_0
L17:    aload_1
L18:    invokestatic Method org/lwjgl/MemoryUtil method1878 (Ljava/nio/FloatBuffer;)J
L21:    lload_2
L22:    invokestatic Method org/lwjgl/opengl/GL11 nglGetFloatv (IJJ)V
L25:    aload_1
L26:    iconst_0
L27:    iconst_1
L28:    dup
L29:    pop2
L30:    invokevirtual Method java/nio/FloatBuffer get (I)F
L33:    freturn
L34:    
    .end code
.end method

.method public static method3728 : (D)V
    .code stack 4 locals 4
L0:     invokestatic Method org/lwjgl/opengl/GLContext method4611 ()Lorg/lwjgl/opengl/kb;
L3:     getfield Field org/lwjgl/opengl/kb Lr J
L6:     dup2
L7:     lstore_2
L8:     invokestatic Method org/lwjgl/l method2052 (J)V
L11:    dload_0
L12:    lload_2
L13:    invokestatic Method org/lwjgl/opengl/GL11 nglClearDepth (DJ)V
L16:    return
L17:    
    .end code
.end method

.method public static method3729 : (J)V
    .code stack 5 locals 4
L0:     invokestatic Method org/lwjgl/opengl/GLContext method4611 ()Lorg/lwjgl/opengl/kb;
L3:     dup
L4:     getfield Field org/lwjgl/opengl/kb DH J
L7:     dup2
L8:     lstore_2
L9:     invokestatic Method org/lwjgl/l method2052 (J)V
L12:    invokestatic Method org/lwjgl/opengl/Zd method5436 (Lorg/lwjgl/opengl/kb;)V
L15:    lload_0
L16:    lload_2
L17:    invokestatic Method org/lwjgl/opengl/GL11 nglGetPolygonStippleBO (JJ)V
L20:    return
L21:    
    .end code
.end method

.method static native nglPointSize : (FJ)V
.end method

.method static native nglIsEnabled : (IJ)Z
.end method

.method public static this : (IILjava/nio/FloatBuffer;)V
    .code stack 6 locals 5
L0:     invokestatic Method org/lwjgl/opengl/GLContext method4611 ()Lorg/lwjgl/opengl/kb;
L3:     getfield Field org/lwjgl/opengl/kb Ws J
L6:     dup2
L7:     lstore_3
L8:     invokestatic Method org/lwjgl/l method2052 (J)V
L11:    iload_0
L12:    aload_2
L13:    iconst_4
L14:    iconst_1
L15:    dup
L16:    pop2
L17:    invokestatic Method org/lwjgl/l method2044 (Ljava/nio/FloatBuffer;I)V
L20:    iload_1
L21:    aload_2
L22:    invokestatic Method org/lwjgl/MemoryUtil method1878 (Ljava/nio/FloatBuffer;)J
L25:    lload_3
L26:    invokestatic Method org/lwjgl/opengl/GL11 nglGetTexGenfv (IIJJ)V
L29:    return
L30:    
    .end code
.end method

.method static native nglPopMatrix : (J)V
.end method

.method public static method3730 : ()V
    .code stack 4 locals 2
L0:     invokestatic Method org/lwjgl/opengl/GLContext method4611 ()Lorg/lwjgl/opengl/kb;
L3:     getfield Field org/lwjgl/opengl/kb TI J
L6:     dup2
L7:     lstore_0
L8:     invokestatic Method org/lwjgl/l method2052 (J)V
L11:    lload_0
L12:    invokestatic Method org/lwjgl/opengl/GL11 nglPopMatrix (J)V
L15:    return
L16:    
    .end code
.end method

.method public static method3731 : (IFFIILjava/nio/FloatBuffer;)V
    .code stack 9 locals 8
L0:     invokestatic Method org/lwjgl/opengl/GLContext method4611 ()Lorg/lwjgl/opengl/kb;
L3:     getfield Field org/lwjgl/opengl/kb field5427 J
L6:     dup2
L7:     lstore 6
L9:     invokestatic Method org/lwjgl/l method2052 (J)V
L12:    iload_0
L13:    aload 5
L15:    invokestatic Method org/lwjgl/l method2048 (Ljava/nio/FloatBuffer;)V
L18:    fload_1
L19:    fload_2
L20:    iload_3
L21:    iload 4
L23:    aload 5
L25:    invokestatic Method org/lwjgl/MemoryUtil method1878 (Ljava/nio/FloatBuffer;)J
L28:    lload 6
L30:    invokestatic Method org/lwjgl/opengl/GL11 nglMap1f (IFFIIJJ)V
L33:    return
L34:    
    .end code
.end method

.method public static method3732 : (FF)V
    .code stack 4 locals 4
L0:     invokestatic Method org/lwjgl/opengl/GLContext method4611 ()Lorg/lwjgl/opengl/kb;
L3:     getfield Field org/lwjgl/opengl/kb tE J
L6:     dup2
L7:     lstore_2
L8:     invokestatic Method org/lwjgl/l method2052 (J)V
L11:    fload_0
L12:    fload_1
L13:    lload_2
L14:    invokestatic Method org/lwjgl/opengl/GL11 nglEvalCoord2f (FFJ)V
L17:    return
L18:    
    .end code
.end method

.method static native nglTexCoord1f : (FJ)V
.end method

.method static native nglEdgeFlagPointer : (IJJ)V
.end method

.method static native nglGetPixelMapusvBO : (IJJ)V
.end method

.method public static method3733 : (I)V
    .code stack 4 locals 3
L0:     invokestatic Method org/lwjgl/opengl/GLContext method4611 ()Lorg/lwjgl/opengl/kb;
L3:     getfield Field org/lwjgl/opengl/kb XN J
L6:     dup2
L7:     lstore_1
L8:     invokestatic Method org/lwjgl/l method2052 (J)V
L11:    iload_0
L12:    lload_1
L13:    invokestatic Method org/lwjgl/opengl/GL11 nglStencilMask (IJ)V
L16:    return
L17:    
    .end code
.end method

.method public static method3734 : (ILjava/nio/IntBuffer;)V
    .code stack 6 locals 5
L0:     invokestatic Method org/lwjgl/opengl/GLContext method4611 ()Lorg/lwjgl/opengl/kb;
L3:     astore_2
L4:     aload_1
L5:     aload_2
L6:     dup
L7:     getfield Field org/lwjgl/opengl/kb PS J
L10:    dup2
L11:    lstore_3
L12:    invokestatic Method org/lwjgl/l method2052 (J)V
L15:    invokestatic Method org/lwjgl/opengl/Zd method5446 (Lorg/lwjgl/opengl/kb;)V
L18:    invokestatic Method org/lwjgl/l method2043 (Ljava/nio/IntBuffer;)V
L21:    iload_0
L22:    aload_1
L23:    invokevirtual Method java/nio/IntBuffer remaining ()I
L26:    aload_1
L27:    invokestatic Method org/lwjgl/MemoryUtil method1884 (Ljava/nio/IntBuffer;)J
L30:    lload_3
L31:    invokestatic Method org/lwjgl/opengl/GL11 nglPixelMapuiv (IIJJ)V
L34:    return
L35:    
    .end code
.end method

.method public static method3735 : (IIF)V
    .code stack 5 locals 5
L0:     invokestatic Method org/lwjgl/opengl/GLContext method4611 ()Lorg/lwjgl/opengl/kb;
L3:     getfield Field org/lwjgl/opengl/kb Zu J
L6:     dup2
L7:     lstore_3
L8:     invokestatic Method org/lwjgl/l method2052 (J)V
L11:    iload_0
L12:    iload_1
L13:    fload_2
L14:    lload_3
L15:    invokestatic Method org/lwjgl/opengl/GL11 nglMaterialf (IIFJ)V
L18:    return
L19:    
    .end code
.end method

.method static native nglDepthRange : (DDJ)V
.end method

.method static native nglEvalMesh1 : (IIIJ)V
.end method

.method static native nglTexGeni : (IIIJ)V
.end method

.method static native nglBindTexture : (IIJ)V
.end method

.method static native nglTexCoord3f : (FFFJ)V
.end method

.method static native nglGetFloatv : (IJJ)V
.end method

.method public static method3736 : (IIIIIIIILjava/nio/IntBuffer;)V
    .code stack 12 locals 12
L0:     invokestatic Method org/lwjgl/opengl/GLContext method4611 ()Lorg/lwjgl/opengl/kb;
L3:     astore 9
L5:     aload 8
L7:     aload 9
L9:     dup
L10:    getfield Field org/lwjgl/opengl/kb PJ J
L13:    dup2
L14:    lstore 10
L16:    invokestatic Method org/lwjgl/l method2052 (J)V
L19:    invokestatic Method org/lwjgl/opengl/Zd method5446 (Lorg/lwjgl/opengl/kb;)V
L22:    aload 8
L24:    iload 6
L26:    iload 7
L28:    iload 4
L30:    iload 5
L32:    iconst_1
L33:    dup
L34:    dup
L35:    pop2
L36:    invokestatic Method org/lwjgl/opengl/Zd method5429 (Ljava/nio/Buffer;IIIII)I
L39:    invokestatic Method org/lwjgl/l method2041 (Ljava/nio/IntBuffer;I)V
L42:    iload_0
L43:    iload_1
L44:    iload_2
L45:    iload_3
L46:    iload 4
L48:    iload 5
L50:    iload 6
L52:    iload 7
L54:    aload 8
L56:    invokestatic Method org/lwjgl/MemoryUtil method1884 (Ljava/nio/IntBuffer;)J
L59:    lload 10
L61:    invokestatic Method org/lwjgl/opengl/GL11 nglTexSubImage2D (IIIIIIIIJJ)V
L64:    return
L65:    
    .end code
.end method

.method public static method3737 : (IILjava/nio/ShortBuffer;)V
    .code stack 7 locals 6
L0:     invokestatic Method org/lwjgl/opengl/GLContext method4611 ()Lorg/lwjgl/opengl/kb;
L3:     astore_3
L4:     aload_2
L5:     aload_3
L6:     dup
L7:     getfield Field org/lwjgl/opengl/kb VM J
L10:    dup2
L11:    lstore 4
L13:    invokestatic Method org/lwjgl/l method2052 (J)V
L16:    invokestatic Method org/lwjgl/opengl/Zd method5454 (Lorg/lwjgl/opengl/kb;)V
L19:    invokestatic Method org/lwjgl/l method2057 (Ljava/nio/ShortBuffer;)V
L22:    getstatic Field org/lwjgl/LWJGLUtil CHECKS Z
L25:    ifeq L36
L28:    aload_3
L29:    invokestatic Method org/lwjgl/opengl/w method5768 (Lorg/lwjgl/opengl/kb;)Lorg/lwjgl/opengl/P;
L32:    aload_2
L33:    putfield Field org/lwjgl/opengl/P field4944 Ljava/nio/Buffer;
L36:    iload_0
L37:    sipush 5122
L40:    iconst_1
L41:    dup
L42:    pop2
L43:    iload_1
L44:    aload_2
L45:    invokestatic Method org/lwjgl/MemoryUtil method1853 (Ljava/nio/ShortBuffer;)J
L48:    lload 4
L50:    invokestatic Method org/lwjgl/opengl/GL11 nglVertexPointer (IIIJJ)V
L53:    return
L54:    
        .attribute StackMap b'\x00\x01\x00\x24\x00\x05\x01\x01\x07\x05\x65\x07\x04\x21\x04\x00\x00'
    .end code
.end method

.method public static method3738 : (IIIIIIIIJ)V
    .code stack 12 locals 12
L0:     invokestatic Method org/lwjgl/opengl/GLContext method4611 ()Lorg/lwjgl/opengl/kb;
L3:     dup
L4:     getfield Field org/lwjgl/opengl/kb PJ J
L7:     dup2
L8:     lstore 10
L10:    invokestatic Method org/lwjgl/l method2052 (J)V
L13:    invokestatic Method org/lwjgl/opengl/Zd method5428 (Lorg/lwjgl/opengl/kb;)V
L16:    iload_0
L17:    iload_1
L18:    iload_2
L19:    iload_3
L20:    iload 4
L22:    iload 5
L24:    iload 6
L26:    iload 7
L28:    lload 8
L30:    lload 10
L32:    invokestatic Method org/lwjgl/opengl/GL11 nglTexSubImage2DBO (IIIIIIIIJJ)V
L35:    return
L36:    
    .end code
.end method

.method static native nglGetPointerv : (IJJ)Ljava/nio/ByteBuffer;
.end method

.method static native nglColorMaterial : (IIJ)V
.end method

.method public static method3739 : (DDDDDD)V
    .code stack 14 locals 14
L0:     invokestatic Method org/lwjgl/opengl/GLContext method4611 ()Lorg/lwjgl/opengl/kb;
L3:     getfield Field org/lwjgl/opengl/kb BT J
L6:     dup2
L7:     lstore 12
L9:     invokestatic Method org/lwjgl/l method2052 (J)V
L12:    dload_0
L13:    dload_2
L14:    dload 4
L16:    dload 6
L18:    dload 8
L20:    dload 10
L22:    lload 12
L24:    invokestatic Method org/lwjgl/opengl/GL11 nglOrtho (DDDDDDJ)V
L27:    return
L28:    
    .end code
.end method

.method static native nglMultMatrixf : (JJ)V
.end method

.method public static method3740 : (FFF)V
    .code stack 5 locals 5
L0:     invokestatic Method org/lwjgl/opengl/GLContext method4611 ()Lorg/lwjgl/opengl/kb;
L3:     getfield Field org/lwjgl/opengl/kb lr J
L6:     dup2
L7:     lstore_3
L8:     invokestatic Method org/lwjgl/l method2052 (J)V
L11:    fload_0
L12:    fload_1
L13:    fload_2
L14:    lload_3
L15:    invokestatic Method org/lwjgl/opengl/GL11 nglVertex3f (FFFJ)V
L18:    return
L19:    
    .end code
.end method

.method public static method3741 : (Ljava/nio/FloatBuffer;)V
    .code stack 5 locals 3
L0:     invokestatic Method org/lwjgl/opengl/GLContext method4611 ()Lorg/lwjgl/opengl/kb;
L3:     getfield Field org/lwjgl/opengl/kb field5420 J
L6:     dup2
L7:     lstore_1
L8:     invokestatic Method org/lwjgl/l method2052 (J)V
L11:    aload_0
L12:    dup
L13:    bipush 16
L15:    iconst_1
L16:    dup
L17:    pop2
L18:    invokestatic Method org/lwjgl/l method2044 (Ljava/nio/FloatBuffer;I)V
L21:    invokestatic Method org/lwjgl/MemoryUtil method1878 (Ljava/nio/FloatBuffer;)J
L24:    lload_1
L25:    invokestatic Method org/lwjgl/opengl/GL11 nglMultMatrixf (JJ)V
L28:    return
L29:    
    .end code
.end method

.method static native nglTexEnvi : (IIIJ)V
.end method

.method public static method3742 : (IIJ)V
    .code stack 6 locals 6
L0:     invokestatic Method org/lwjgl/opengl/GLContext method4611 ()Lorg/lwjgl/opengl/kb;
L3:     dup
L4:     getfield Field org/lwjgl/opengl/kb PS J
L7:     dup2
L8:     lstore 4
L10:    invokestatic Method org/lwjgl/l method2052 (J)V
L13:    invokestatic Method org/lwjgl/opengl/Zd method5428 (Lorg/lwjgl/opengl/kb;)V
L16:    iload_0
L17:    iload_1
L18:    lload_2
L19:    lload 4
L21:    invokestatic Method org/lwjgl/opengl/GL11 nglPixelMapuivBO (IIJJ)V
L24:    return
L25:    
    .end code
.end method

.method static native nglRasterPos4f : (FFFFJ)V
.end method

.method static native nglLightModelf : (IFJ)V
.end method

.method public static method3743 : (IILjava/nio/IntBuffer;)V
    .code stack 6 locals 5
L0:     invokestatic Method org/lwjgl/opengl/GLContext method4611 ()Lorg/lwjgl/opengl/kb;
L3:     getfield Field org/lwjgl/opengl/kb tA J
L6:     dup2
L7:     lstore_3
L8:     invokestatic Method org/lwjgl/l method2052 (J)V
L11:    iload_0
L12:    aload_2
L13:    iconst_4
L14:    iconst_1
L15:    dup
L16:    pop2
L17:    invokestatic Method org/lwjgl/l method2041 (Ljava/nio/IntBuffer;I)V
L20:    iload_1
L21:    aload_2
L22:    invokestatic Method org/lwjgl/MemoryUtil method1884 (Ljava/nio/IntBuffer;)J
L25:    lload_3
L26:    invokestatic Method org/lwjgl/opengl/GL11 nglGetTexGeniv (IIJJ)V
L29:    return
L30:    
    .end code
.end method

.method static native nglGetPixelMapusv : (IJJ)V
.end method

.method static native nglColor4f : (FFFFJ)V
.end method

.method static native nglTexGend : (IIDJ)V
.end method

.method public static method3744 : (I)Z
    .code stack 4 locals 3
L0:     invokestatic Method org/lwjgl/opengl/GLContext method4611 ()Lorg/lwjgl/opengl/kb;
L3:     getfield Field org/lwjgl/opengl/kb M J
L6:     dup2
L7:     lstore_1
L8:     invokestatic Method org/lwjgl/l method2052 (J)V
L11:    iload_0
L12:    lload_1
L13:    invokestatic Method org/lwjgl/opengl/GL11 nglIsEnabled (IJ)Z
L16:    ireturn
L17:    
    .end code
.end method

.method public static method3745 : (IIJ)V
    .code stack 6 locals 6
L0:     invokestatic Method org/lwjgl/opengl/GLContext method4611 ()Lorg/lwjgl/opengl/kb;
L3:     dup
L4:     getfield Field org/lwjgl/opengl/kb rj J
L7:     dup2
L8:     lstore 4
L10:    invokestatic Method org/lwjgl/l method2052 (J)V
L13:    invokestatic Method org/lwjgl/opengl/Zd method5428 (Lorg/lwjgl/opengl/kb;)V
L16:    iload_0
L17:    iload_1
L18:    lload_2
L19:    lload 4
L21:    invokestatic Method org/lwjgl/opengl/GL11 nglPixelMapusvBO (IIJJ)V
L24:    return
L25:    
    .end code
.end method

.method public static method3746 : (FFFF)V
    .code stack 6 locals 6
L0:     invokestatic Method org/lwjgl/opengl/GLContext method4611 ()Lorg/lwjgl/opengl/kb;
L3:     getfield Field org/lwjgl/opengl/kb mc J
L6:     dup2
L7:     lstore 4
L9:     invokestatic Method org/lwjgl/l method2052 (J)V
L12:    fload_0
L13:    fload_1
L14:    fload_2
L15:    fload_3
L16:    lload 4
L18:    invokestatic Method org/lwjgl/opengl/GL11 nglRotatef (FFFFJ)V
L21:    return
L22:    
    .end code
.end method

.method public static method3747 : (IILjava/nio/FloatBuffer;)V
    .code stack 6 locals 5
L0:     invokestatic Method org/lwjgl/opengl/GLContext method4611 ()Lorg/lwjgl/opengl/kb;
L3:     getfield Field org/lwjgl/opengl/kb NM J
L6:     dup2
L7:     lstore_3
L8:     invokestatic Method org/lwjgl/l method2052 (J)V
L11:    iload_0
L12:    aload_2
L13:    iconst_4
L14:    iconst_1
L15:    dup
L16:    pop2
L17:    invokestatic Method org/lwjgl/l method2044 (Ljava/nio/FloatBuffer;I)V
L20:    iload_1
L21:    aload_2
L22:    invokestatic Method org/lwjgl/MemoryUtil method1878 (Ljava/nio/FloatBuffer;)J
L25:    lload_3
L26:    invokestatic Method org/lwjgl/opengl/GL11 nglTexGenfv (IIJJ)V
L29:    return
L30:    
    .end code
.end method

.method public static method3748 : (DDD)V
    .code stack 8 locals 8
L0:     invokestatic Method org/lwjgl/opengl/GLContext method4611 ()Lorg/lwjgl/opengl/kb;
L3:     getfield Field org/lwjgl/opengl/kb jP J
L6:     dup2
L7:     lstore 6
L9:     invokestatic Method org/lwjgl/l method2052 (J)V
L12:    dload_0
L13:    dload_2
L14:    dload 4
L16:    lload 6
L18:    invokestatic Method org/lwjgl/opengl/GL11 nglTexCoord3d (DDDJ)V
L21:    return
L22:    
    .end code
.end method

.method static native nglMap1d : (IDDIIJJ)V
.end method

.method public static method3749 : (DDDDDD)V
    .code stack 14 locals 14
L0:     invokestatic Method org/lwjgl/opengl/GLContext method4611 ()Lorg/lwjgl/opengl/kb;
L3:     getfield Field org/lwjgl/opengl/kb field5440 J
L6:     dup2
L7:     lstore 12
L9:     invokestatic Method org/lwjgl/l method2052 (J)V
L12:    dload_0
L13:    dload_2
L14:    dload 4
L16:    dload 6
L18:    dload 8
L20:    dload 10
L22:    lload 12
L24:    invokestatic Method org/lwjgl/opengl/GL11 nglFrustum (DDDDDDJ)V
L27:    return
L28:    
    .end code
.end method

.method static native nglGetClipPlane : (IJJ)V
.end method

.method public static method3750 : (FFF)V
    .code stack 5 locals 5
L0:     invokestatic Method org/lwjgl/opengl/GLContext method4611 ()Lorg/lwjgl/opengl/kb;
L3:     getfield Field org/lwjgl/opengl/kb field5448 J
L6:     dup2
L7:     lstore_3
L8:     invokestatic Method org/lwjgl/l method2052 (J)V
L11:    fload_0
L12:    fload_1
L13:    fload_2
L14:    lload_3
L15:    invokestatic Method org/lwjgl/opengl/GL11 nglRasterPos3f (FFFJ)V
L18:    return
L19:    
    .end code
.end method

.method static native nglPushMatrix : (J)V
.end method

.method public static method3751 : (Ljava/nio/IntBuffer;Ljava/nio/ByteBuffer;)Z
    .code stack 7 locals 4
L0:     invokestatic Method org/lwjgl/opengl/GLContext method4611 ()Lorg/lwjgl/opengl/kb;
L3:     getfield Field org/lwjgl/opengl/kb Pm J
L6:     dup2
L7:     lstore_2
L8:     invokestatic Method org/lwjgl/l method2052 (J)V
L11:    aload_1
L12:    aload_0
L13:    dup
L14:    dup_x2
L15:    invokestatic Method org/lwjgl/l method2043 (Ljava/nio/IntBuffer;)V
L18:    invokevirtual Method java/nio/IntBuffer remaining ()I
L21:    invokestatic Method org/lwjgl/l method2054 (Ljava/nio/ByteBuffer;I)V
L24:    invokevirtual Method java/nio/IntBuffer remaining ()I
L27:    aload_0
L28:    invokestatic Method org/lwjgl/MemoryUtil method1884 (Ljava/nio/IntBuffer;)J
L31:    aload_1
L32:    invokestatic Method org/lwjgl/MemoryUtil method1873 (Ljava/nio/ByteBuffer;)J
L35:    lload_2
L36:    invokestatic Method org/lwjgl/opengl/GL11 nglAreTexturesResident (IJJJ)Z
L39:    ireturn
L40:    
    .end code
.end method

.method public static method3752 : (FFFF)V
    .code stack 6 locals 6
L0:     invokestatic Method org/lwjgl/opengl/GLContext method4611 ()Lorg/lwjgl/opengl/kb;
L3:     getfield Field org/lwjgl/opengl/kb di J
L6:     dup2
L7:     lstore 4
L9:     invokestatic Method org/lwjgl/l method2052 (J)V
L12:    fload_0
L13:    fload_1
L14:    fload_2
L15:    fload_3
L16:    lload 4
L18:    invokestatic Method org/lwjgl/opengl/GL11 nglVertex4f (FFFFJ)V
L21:    return
L22:    
    .end code
.end method

.method static native nglLogicOp : (IJ)V
.end method

.method public static method3753 : (Ljava/nio/ShortBuffer;)V
    .code stack 6 locals 3
L0:     invokestatic Method org/lwjgl/opengl/GLContext method4611 ()Lorg/lwjgl/opengl/kb;
L3:     getfield Field org/lwjgl/opengl/kb Kf J
L6:     dup2
L7:     lstore_1
L8:     invokestatic Method org/lwjgl/l method2052 (J)V
L11:    aload_0
L12:    dup
L13:    invokestatic Method org/lwjgl/l method2057 (Ljava/nio/ShortBuffer;)V
L16:    invokevirtual Method java/nio/ShortBuffer remaining ()I
L19:    sipush 5123
L22:    iconst_1
L23:    dup
L24:    pop2
L25:    aload_0
L26:    invokestatic Method org/lwjgl/MemoryUtil method1853 (Ljava/nio/ShortBuffer;)J
L29:    lload_1
L30:    invokestatic Method org/lwjgl/opengl/GL11 nglCallLists (IIJJ)V
L33:    return
L34:    
    .end code
.end method

.method static native nglTexGeniv : (IIJJ)V
.end method

.method public static method3754 : (I)I
    .code stack 4 locals 3
L0:     invokestatic Method org/lwjgl/opengl/GLContext method4611 ()Lorg/lwjgl/opengl/kb;
L3:     getfield Field org/lwjgl/opengl/kb eo J
L6:     dup2
L7:     lstore_1
L8:     invokestatic Method org/lwjgl/l method2052 (J)V
L11:    iload_0
L12:    lload_1
L13:    invokestatic Method org/lwjgl/opengl/GL11 nglRenderMode (IJ)I
L16:    ireturn
L17:    
    .end code
.end method

.method static native nglLightf : (IIFJ)V
.end method

.method public static method3755 : (I)V
    .code stack 4 locals 3
L0:     invokestatic Method org/lwjgl/opengl/GLContext method4611 ()Lorg/lwjgl/opengl/kb;
L3:     getfield Field org/lwjgl/opengl/kb IO J
L6:     dup2
L7:     lstore_1
L8:     invokestatic Method org/lwjgl/l method2052 (J)V
L11:    iload_0
L12:    lload_1
L13:    invokestatic Method org/lwjgl/opengl/GL11 nglDepthFunc (IJ)V
L16:    return
L17:    
    .end code
.end method

.method public static method3756 : (IIIJ)V
    .code stack 7 locals 7
L0:     invokestatic Method org/lwjgl/opengl/GLContext method4611 ()Lorg/lwjgl/opengl/kb;
L3:     dup
L4:     getfield Field org/lwjgl/opengl/kb De J
L7:     dup2
L8:     lstore 5
L10:    invokestatic Method org/lwjgl/l method2052 (J)V
L13:    invokestatic Method org/lwjgl/opengl/Zd method5441 (Lorg/lwjgl/opengl/kb;)V
L16:    iload_0
L17:    iload_1
L18:    iload_2
L19:    lload_3
L20:    lload 5
L22:    invokestatic Method org/lwjgl/opengl/GL11 nglColorPointerBO (IIIJJ)V
L25:    return
L26:    
    .end code
.end method

.method static native nglClearStencil : (IJ)V
.end method

.method static native nglGetTexGendv : (IIJJ)V
.end method

.method static native nglNewList : (IIJ)V
.end method

.method static native nglOrtho : (DDDDDDJ)V
.end method

.method static native nglTexCoordPointerBO : (IIIJJ)V
.end method

.method static native nglFinish : (J)V
.end method

.method public static method3757 : (IIFFFFLjava/nio/ByteBuffer;)V
    .code stack 10 locals 10
L0:     invokestatic Method org/lwjgl/opengl/GLContext method4611 ()Lorg/lwjgl/opengl/kb;
L3:     astore 7
L5:     aload 6
L7:     aload 7
L9:     dup
L10:    getfield Field org/lwjgl/opengl/kb Ys J
L13:    dup2
L14:    lstore 8
L16:    invokestatic Method org/lwjgl/l method2052 (J)V
L19:    invokestatic Method org/lwjgl/opengl/Zd method5446 (Lorg/lwjgl/opengl/kb;)V
L22:    iload_0
L23:    bipush 7
L25:    iconst_1
L26:    dup
L27:    pop2
L28:    iadd
L29:    bipush 8
L31:    iconst_1
L32:    dup
L33:    pop2
L34:    idiv
L35:    iload_1
L36:    imul
L37:    invokestatic Method org/lwjgl/l method2054 (Ljava/nio/ByteBuffer;I)V
L40:    iload_0
L41:    iload_1
L42:    fload_2
L43:    fload_3
L44:    fload 4
L46:    fload 5
L48:    aload 6
L50:    invokestatic Method org/lwjgl/MemoryUtil method1873 (Ljava/nio/ByteBuffer;)J
L53:    lload 8
L55:    invokestatic Method org/lwjgl/opengl/GL11 nglBitmap (IIFFFFJJ)V
L58:    return
L59:    
    .end code
.end method

.method public static method3758 : (IFFIIFFIILjava/nio/FloatBuffer;)V
    .code stack 13 locals 12
L0:     invokestatic Method org/lwjgl/opengl/GLContext method4611 ()Lorg/lwjgl/opengl/kb;
L3:     getfield Field org/lwjgl/opengl/kb pD J
L6:     dup2
L7:     lstore 10
L9:     invokestatic Method org/lwjgl/l method2052 (J)V
L12:    iload_0
L13:    aload 9
L15:    invokestatic Method org/lwjgl/l method2048 (Ljava/nio/FloatBuffer;)V
L18:    fload_1
L19:    fload_2
L20:    iload_3
L21:    iload 4
L23:    fload 5
L25:    fload 6
L27:    iload 7
L29:    iload 8
L31:    aload 9
L33:    invokestatic Method org/lwjgl/MemoryUtil method1878 (Ljava/nio/FloatBuffer;)J
L36:    lload 10
L38:    invokestatic Method org/lwjgl/opengl/GL11 nglMap2f (IFFIIFFIIJJ)V
L41:    return
L42:    
    .end code
.end method

.method public static method3759 : (IIJ)V
    .code stack 6 locals 6
L0:     invokestatic Method org/lwjgl/opengl/GLContext method4611 ()Lorg/lwjgl/opengl/kb;
L3:     dup
L4:     getfield Field org/lwjgl/opengl/kb fC J
L7:     dup2
L8:     lstore 4
L10:    invokestatic Method org/lwjgl/l method2052 (J)V
L13:    invokestatic Method org/lwjgl/opengl/Zd method5428 (Lorg/lwjgl/opengl/kb;)V
L16:    iload_0
L17:    iload_1
L18:    lload_2
L19:    lload 4
L21:    invokestatic Method org/lwjgl/opengl/GL11 nglPixelMapfvBO (IIJJ)V
L24:    return
L25:    
    .end code
.end method

.method public static method3760 : ()V
    .code stack 4 locals 2
L0:     invokestatic Method org/lwjgl/opengl/GLContext method4611 ()Lorg/lwjgl/opengl/kb;
L3:     getfield Field org/lwjgl/opengl/kb du J
L6:     dup2
L7:     lstore_0
L8:     invokestatic Method org/lwjgl/l method2052 (J)V
L11:    lload_0
L12:    invokestatic Method org/lwjgl/opengl/GL11 nglPopName (J)V
L15:    return
L16:    
    .end code
.end method

.method public static method3761 : (IIIIIIIJ)V
    .code stack 11 locals 11
L0:     invokestatic Method org/lwjgl/opengl/GLContext method4611 ()Lorg/lwjgl/opengl/kb;
L3:     dup
L4:     getfield Field org/lwjgl/opengl/kb hM J
L7:     dup2
L8:     lstore 9
L10:    invokestatic Method org/lwjgl/l method2052 (J)V
L13:    invokestatic Method org/lwjgl/opengl/Zd method5428 (Lorg/lwjgl/opengl/kb;)V
L16:    iload_0
L17:    iload_1
L18:    iload_2
L19:    iload_3
L20:    iload 4
L22:    iload 5
L24:    iload 6
L26:    lload 7
L28:    lload 9
L30:    invokestatic Method org/lwjgl/opengl/GL11 nglTexImage1DBO (IIIIIIIJJ)V
L33:    return
L34:    
    .end code
.end method

.method static native nglTexGendv : (IIJJ)V
.end method

.method public static method3762 : (IIIIIILjava/nio/ByteBuffer;)V
    .code stack 10 locals 10
L0:     invokestatic Method org/lwjgl/opengl/GLContext method4611 ()Lorg/lwjgl/opengl/kb;
L3:     astore 7
L5:     aload 6
L7:     aload 7
L9:     dup
L10:    getfield Field org/lwjgl/opengl/kb Zi J
L13:    dup2
L14:    lstore 8
L16:    invokestatic Method org/lwjgl/l method2052 (J)V
L19:    invokestatic Method org/lwjgl/opengl/Zd method5446 (Lorg/lwjgl/opengl/kb;)V
L22:    aload 6
L24:    iload 4
L26:    iload 5
L28:    iload_3
L29:    iconst_1
L30:    dup
L31:    pop2
L32:    iconst_1
L33:    dup
L34:    dup_x1
L35:    dup
L36:    pop2
L37:    invokestatic Method org/lwjgl/opengl/Zd method5429 (Ljava/nio/Buffer;IIIII)I
L40:    invokestatic Method org/lwjgl/l method2054 (Ljava/nio/ByteBuffer;I)V
L43:    iload_0
L44:    iload_1
L45:    iload_2
L46:    iload_3
L47:    iload 4
L49:    iload 5
L51:    aload 6
L53:    invokestatic Method org/lwjgl/MemoryUtil method1873 (Ljava/nio/ByteBuffer;)J
L56:    lload 8
L58:    invokestatic Method org/lwjgl/opengl/GL11 nglTexSubImage1D (IIIIIIJJ)V
L61:    return
L62:    
    .end code
.end method

.method static native nglEdgeFlagPointerBO : (IJJ)V
.end method

.method static native nglLightModeliv : (IJJ)V
.end method

.method public static method3763 : (IID)V
    .code stack 6 locals 6
L0:     invokestatic Method org/lwjgl/opengl/GLContext method4611 ()Lorg/lwjgl/opengl/kb;
L3:     getfield Field org/lwjgl/opengl/kb qK J
L6:     dup2
L7:     lstore 4
L9:     invokestatic Method org/lwjgl/l method2052 (J)V
L12:    iload_0
L13:    iload_1
L14:    dload_2
L15:    lload 4
L17:    invokestatic Method org/lwjgl/opengl/GL11 nglTexGend (IIDJ)V
L20:    return
L21:    
    .end code
.end method

.method public static method3764 : (DDD)V
    .code stack 8 locals 8
L0:     invokestatic Method org/lwjgl/opengl/GLContext method4611 ()Lorg/lwjgl/opengl/kb;
L3:     getfield Field org/lwjgl/opengl/kb EG J
L6:     dup2
L7:     lstore 6
L9:     invokestatic Method org/lwjgl/l method2052 (J)V
L12:    dload_0
L13:    dload_2
L14:    dload 4
L16:    lload 6
L18:    invokestatic Method org/lwjgl/opengl/GL11 nglRasterPos3d (DDDJ)V
L21:    return
L22:    
    .end code
.end method

.method public static method3765 : (Ljava/nio/IntBuffer;)V
    .code stack 5 locals 3
L0:     invokestatic Method org/lwjgl/opengl/GLContext method4611 ()Lorg/lwjgl/opengl/kb;
L3:     getfield Field org/lwjgl/opengl/kb YB J
L6:     dup2
L7:     lstore_1
L8:     invokestatic Method org/lwjgl/l method2052 (J)V
L11:    aload_0
L12:    dup
L13:    invokestatic Method org/lwjgl/l method2043 (Ljava/nio/IntBuffer;)V
L16:    invokevirtual Method java/nio/IntBuffer remaining ()I
L19:    aload_0
L20:    invokestatic Method org/lwjgl/MemoryUtil method1884 (Ljava/nio/IntBuffer;)J
L23:    lload_1
L24:    invokestatic Method org/lwjgl/opengl/GL11 nglSelectBuffer (IJJ)V
L27:    return
L28:    
    .end code
.end method

.method static native nglRasterPos3i : (IIIJ)V
.end method

.method public static method3766 : ()V
    .code stack 4 locals 2
L0:     invokestatic Method org/lwjgl/opengl/GLContext method4611 ()Lorg/lwjgl/opengl/kb;
L3:     getfield Field org/lwjgl/opengl/kb Vt J
L6:     dup2
L7:     lstore_0
L8:     invokestatic Method org/lwjgl/l method2052 (J)V
L11:    lload_0
L12:    invokestatic Method org/lwjgl/opengl/GL11 nglFlush (J)V
L15:    return
L16:    
    .end code
.end method

.method public static method3767 : (IILjava/nio/IntBuffer;)V
    .code stack 6 locals 5
L0:     invokestatic Method org/lwjgl/opengl/GLContext method4611 ()Lorg/lwjgl/opengl/kb;
L3:     getfield Field org/lwjgl/opengl/kb dF J
L6:     dup2
L7:     lstore_3
L8:     invokestatic Method org/lwjgl/l method2052 (J)V
L11:    iload_0
L12:    aload_2
L13:    iconst_4
L14:    iconst_1
L15:    dup
L16:    pop2
L17:    invokestatic Method org/lwjgl/l method2041 (Ljava/nio/IntBuffer;I)V
L20:    iload_1
L21:    aload_2
L22:    invokestatic Method org/lwjgl/MemoryUtil method1884 (Ljava/nio/IntBuffer;)J
L25:    lload_3
L26:    invokestatic Method org/lwjgl/opengl/GL11 nglGetMaterialiv (IIJJ)V
L29:    return
L30:    
    .end code
.end method

.method public static method3768 : (I)V
    .code stack 4 locals 3
L0:     invokestatic Method org/lwjgl/opengl/GLContext method4611 ()Lorg/lwjgl/opengl/kb;
L3:     getfield Field org/lwjgl/opengl/kb th J
L6:     dup2
L7:     lstore_1
L8:     invokestatic Method org/lwjgl/l method2052 (J)V
L11:    iload_0
L12:    lload_1
L13:    invokestatic Method org/lwjgl/opengl/GL11 nglClearStencil (IJ)V
L16:    return
L17:    
    .end code
.end method

.method public static method3769 : (IF)V
    .code stack 4 locals 4
L0:     invokestatic Method org/lwjgl/opengl/GLContext method4611 ()Lorg/lwjgl/opengl/kb;
L3:     getfield Field org/lwjgl/opengl/kb eu J
L6:     dup2
L7:     lstore_2
L8:     invokestatic Method org/lwjgl/l method2052 (J)V
L11:    iload_0
L12:    fload_1
L13:    lload_2
L14:    invokestatic Method org/lwjgl/opengl/GL11 nglFogf (IFJ)V
L17:    return
L18:    
    .end code
.end method

.method static native nglAlphaFunc : (IFJ)V
.end method

.method static native nglColorPointer : (IIIJJ)V
.end method

.method public static method3770 : (IILjava/nio/IntBuffer;)V
    .code stack 6 locals 5
L0:     invokestatic Method org/lwjgl/opengl/GLContext method4611 ()Lorg/lwjgl/opengl/kb;
L3:     getfield Field org/lwjgl/opengl/kb pK J
L6:     dup2
L7:     lstore_3
L8:     invokestatic Method org/lwjgl/l method2052 (J)V
L11:    iload_0
L12:    aload_2
L13:    iconst_4
L14:    iconst_1
L15:    dup
L16:    pop2
L17:    invokestatic Method org/lwjgl/l method2041 (Ljava/nio/IntBuffer;I)V
L20:    iload_1
L21:    aload_2
L22:    invokestatic Method org/lwjgl/MemoryUtil method1884 (Ljava/nio/IntBuffer;)J
L25:    lload_3
L26:    invokestatic Method org/lwjgl/opengl/GL11 nglGetTexParameteriv (IIJJ)V
L29:    return
L30:    
    .end code
.end method

.method static native nglLightModeli : (IIJ)V
.end method

.method public static method3771 : (II)V
    .code stack 4 locals 4
L0:     invokestatic Method org/lwjgl/opengl/GLContext method4611 ()Lorg/lwjgl/opengl/kb;
L3:     getfield Field org/lwjgl/opengl/kb field5437 J
L6:     dup2
L7:     lstore_2
L8:     invokestatic Method org/lwjgl/l method2052 (J)V
L11:    iload_0
L12:    iload_1
L13:    lload_2
L14:    invokestatic Method org/lwjgl/opengl/GL11 nglBlendFunc (IIJ)V
L17:    return
L18:    
    .end code
.end method

.method public static method3772 : (I)D
    .code stack 5 locals 4
L0:     invokestatic Method org/lwjgl/opengl/GLContext method4611 ()Lorg/lwjgl/opengl/kb;
L3:     dup
L4:     getfield Field org/lwjgl/opengl/kb Gq J
L7:     dup2
L8:     lstore_2
L9:     invokestatic Method org/lwjgl/l method2052 (J)V
L12:    invokestatic Method org/lwjgl/opengl/bB method5474 (Lorg/lwjgl/opengl/kb;)Ljava/nio/DoubleBuffer;
L15:    astore_1
L16:    iload_0
L17:    aload_1
L18:    invokestatic Method org/lwjgl/MemoryUtil method1840 (Ljava/nio/DoubleBuffer;)J
L21:    lload_2
L22:    invokestatic Method org/lwjgl/opengl/GL11 nglGetDoublev (IJJ)V
L25:    aload_1
L26:    iconst_0
L27:    iconst_1
L28:    dup
L29:    pop2
L30:    invokevirtual Method java/nio/DoubleBuffer get (I)D
L33:    dreturn
L34:    
    .end code
.end method

.method static native nglPushClientAttrib : (IJ)V
.end method

.method static native nglListBase : (IJ)V
.end method

.method static native nglEdgeFlag : (ZJ)V
.end method

.method static native nglScalef : (FFFJ)V
.end method

.method static native nglDrawArrays : (IIIJ)V
.end method

.method public static method3773 : (IILjava/nio/FloatBuffer;)V
    .code stack 6 locals 5
L0:     invokestatic Method org/lwjgl/opengl/GLContext method4611 ()Lorg/lwjgl/opengl/kb;
L3:     getfield Field org/lwjgl/opengl/kb Ul J
L6:     dup2
L7:     lstore_3
L8:     invokestatic Method org/lwjgl/l method2052 (J)V
L11:    iload_0
L12:    aload_2
L13:    sipush 256
L16:    iconst_1
L17:    dup
L18:    pop2
L19:    invokestatic Method org/lwjgl/l method2044 (Ljava/nio/FloatBuffer;I)V
L22:    iload_1
L23:    aload_2
L24:    invokestatic Method org/lwjgl/MemoryUtil method1878 (Ljava/nio/FloatBuffer;)J
L27:    lload_3
L28:    invokestatic Method org/lwjgl/opengl/GL11 nglGetMapfv (IIJJ)V
L31:    return
L32:    
    .end code
.end method

.method public static method3774 : (BBBB)V
    .code stack 6 locals 6
L0:     invokestatic Method org/lwjgl/opengl/GLContext method4611 ()Lorg/lwjgl/opengl/kb;
L3:     getfield Field org/lwjgl/opengl/kb jh J
L6:     dup2
L7:     lstore 4
L9:     invokestatic Method org/lwjgl/l method2052 (J)V
L12:    iload_0
L13:    iload_1
L14:    iload_2
L15:    iload_3
L16:    lload 4
L18:    invokestatic Method org/lwjgl/opengl/GL11 nglColor4ub (BBBBJ)V
L21:    return
L22:    
    .end code
.end method

.method public static method3775 : (IF)V
    .code stack 4 locals 4
L0:     invokestatic Method org/lwjgl/opengl/GLContext method4611 ()Lorg/lwjgl/opengl/kb;
L3:     getfield Field org/lwjgl/opengl/kb gb J
L6:     dup2
L7:     lstore_2
L8:     invokestatic Method org/lwjgl/l method2052 (J)V
L11:    iload_0
L12:    fload_1
L13:    lload_2
L14:    invokestatic Method org/lwjgl/opengl/GL11 nglPixelStoref (IFJ)V
L17:    return
L18:    
    .end code
.end method

.method static native nglGetTexImageBO : (IIIIJJ)V
.end method

.method public static method3776 : (IILjava/nio/IntBuffer;)V
    .code stack 6 locals 5
L0:     invokestatic Method org/lwjgl/opengl/GLContext method4611 ()Lorg/lwjgl/opengl/kb;
L3:     getfield Field org/lwjgl/opengl/kb ZE J
L6:     dup2
L7:     lstore_3
L8:     invokestatic Method org/lwjgl/l method2052 (J)V
L11:    iload_0
L12:    aload_2
L13:    iconst_4
L14:    iconst_1
L15:    dup
L16:    pop2
L17:    invokestatic Method org/lwjgl/l method2041 (Ljava/nio/IntBuffer;I)V
L20:    iload_1
L21:    aload_2
L22:    invokestatic Method org/lwjgl/MemoryUtil method1884 (Ljava/nio/IntBuffer;)J
L25:    lload_3
L26:    invokestatic Method org/lwjgl/opengl/GL11 nglGetLightiv (IIJJ)V
L29:    return
L30:    
    .end code
.end method

.method public static method3777 : (IIIILjava/nio/ByteBuffer;)V
    .code stack 9 locals 8
L0:     invokestatic Method org/lwjgl/opengl/GLContext method4611 ()Lorg/lwjgl/opengl/kb;
L3:     astore 5
L5:     aload 4
L7:     aload 5
L9:     dup
L10:    getfield Field org/lwjgl/opengl/kb Ps J
L13:    dup2
L14:    lstore 6
L16:    invokestatic Method org/lwjgl/l method2052 (J)V
L19:    invokestatic Method org/lwjgl/opengl/Zd method5446 (Lorg/lwjgl/opengl/kb;)V
L22:    aload 4
L24:    iload_2
L25:    iload_3
L26:    iload_0
L27:    iload_1
L28:    iconst_1
L29:    dup
L30:    dup
L31:    pop2
L32:    invokestatic Method org/lwjgl/opengl/Zd method5429 (Ljava/nio/Buffer;IIIII)I
L35:    invokestatic Method org/lwjgl/l method2054 (Ljava/nio/ByteBuffer;I)V
L38:    iload_0
L39:    iload_1
L40:    iload_2
L41:    iload_3
L42:    aload 4
L44:    invokestatic Method org/lwjgl/MemoryUtil method1873 (Ljava/nio/ByteBuffer;)J
L47:    lload 6
L49:    invokestatic Method org/lwjgl/opengl/GL11 nglDrawPixels (IIIIJJ)V
L52:    return
L53:    
    .end code
.end method

.method public static method3778 : (IS)V
    .code stack 4 locals 4
L0:     invokestatic Method org/lwjgl/opengl/GLContext method4611 ()Lorg/lwjgl/opengl/kb;
L3:     getfield Field org/lwjgl/opengl/kb dm J
L6:     dup2
L7:     lstore_2
L8:     invokestatic Method org/lwjgl/l method2052 (J)V
L11:    iload_0
L12:    iload_1
L13:    lload_2
L14:    invokestatic Method org/lwjgl/opengl/GL11 nglLineStipple (ISJ)V
L17:    return
L18:    
    .end code
.end method

.method static native nglTexSubImage1D : (IIIIIIJJ)V
.end method

.method static native nglReadPixels : (IIIIIIJJ)V
.end method

.method static native nglTexEnvf : (IIFJ)V
.end method

.method public static method3779 : (ILjava/nio/FloatBuffer;)V
    .code stack 6 locals 5
L0:     invokestatic Method org/lwjgl/opengl/GLContext method4611 ()Lorg/lwjgl/opengl/kb;
L3:     astore_2
L4:     aload_1
L5:     aload_2
L6:     dup
L7:     getfield Field org/lwjgl/opengl/kb op J
L10:    dup2
L11:    lstore_3
L12:    invokestatic Method org/lwjgl/l method2052 (J)V
L15:    invokestatic Method org/lwjgl/opengl/Zd method5454 (Lorg/lwjgl/opengl/kb;)V
L18:    invokestatic Method org/lwjgl/l method2048 (Ljava/nio/FloatBuffer;)V
L21:    getstatic Field org/lwjgl/LWJGLUtil CHECKS Z
L24:    ifeq L35
L27:    aload_2
L28:    invokestatic Method org/lwjgl/opengl/w method5768 (Lorg/lwjgl/opengl/kb;)Lorg/lwjgl/opengl/P;
L31:    aload_1
L32:    putfield Field org/lwjgl/opengl/P field4947 Ljava/nio/Buffer;
L35:    sipush 5126
L38:    iconst_1
L39:    dup
L40:    pop2
L41:    iload_0
L42:    aload_1
L43:    invokestatic Method org/lwjgl/MemoryUtil method1878 (Ljava/nio/FloatBuffer;)J
L46:    lload_3
L47:    invokestatic Method org/lwjgl/opengl/GL11 nglNormalPointer (IIJJ)V
L50:    return
L51:    
        .attribute StackMap b'\x00\x01\x00\x23\x00\x04\x01\x07\x05\xFE\x07\x04\x21\x04\x00\x00'
    .end code
.end method

.method public static method3780 : (IIJ)V
    .code stack 6 locals 6
L0:     invokestatic Method org/lwjgl/opengl/GLContext method4611 ()Lorg/lwjgl/opengl/kb;
L3:     dup
L4:     getfield Field org/lwjgl/opengl/kb MB J
L7:     dup2
L8:     lstore 4
L10:    invokestatic Method org/lwjgl/l method2052 (J)V
L13:    invokestatic Method org/lwjgl/opengl/Zd method5441 (Lorg/lwjgl/opengl/kb;)V
L16:    iload_0
L17:    iload_1
L18:    lload_2
L19:    lload 4
L21:    invokestatic Method org/lwjgl/opengl/GL11 nglInterleavedArraysBO (IIJJ)V
L24:    return
L25:    
    .end code
.end method

.method static native nglVertex2d : (DDJ)V
.end method

.method static native nglMap1f : (IFFIIJJ)V
.end method

.method static native nglGetTexLevelParameterfv : (IIIJJ)V
.end method

.method static native nglRotated : (DDDDJ)V
.end method

.method public static method3781 : (III)V
    .code stack 5 locals 5
L0:     invokestatic Method org/lwjgl/opengl/GLContext method4611 ()Lorg/lwjgl/opengl/kb;
L3:     getfield Field org/lwjgl/opengl/kb qb J
L6:     dup2
L7:     lstore_3
L8:     invokestatic Method org/lwjgl/l method2052 (J)V
L11:    iload_0
L12:    iload_1
L13:    iload_2
L14:    lload_3
L15:    invokestatic Method org/lwjgl/opengl/GL11 nglVertex3i (IIIJ)V
L18:    return
L19:    
    .end code
.end method

.method public static method3782 : (ILjava/nio/DoubleBuffer;)V
    .code stack 5 locals 4
L0:     invokestatic Method org/lwjgl/opengl/GLContext method4611 ()Lorg/lwjgl/opengl/kb;
L3:     getfield Field org/lwjgl/opengl/kb Gq J
L6:     dup2
L7:     lstore_2
L8:     invokestatic Method org/lwjgl/l method2052 (J)V
L11:    iload_0
L12:    aload_1
L13:    bipush 16
L15:    iconst_1
L16:    dup
L17:    pop2
L18:    invokestatic Method org/lwjgl/l method2056 (Ljava/nio/DoubleBuffer;I)V
L21:    aload_1
L22:    invokestatic Method org/lwjgl/MemoryUtil method1840 (Ljava/nio/DoubleBuffer;)J
L25:    lload_2
L26:    invokestatic Method org/lwjgl/opengl/GL11 nglGetDoublev (IJJ)V
L29:    return
L30:    
    .end code
.end method

.method public static method3783 : (F)V
    .code stack 4 locals 3
L0:     invokestatic Method org/lwjgl/opengl/GLContext method4611 ()Lorg/lwjgl/opengl/kb;
L3:     getfield Field org/lwjgl/opengl/kb Mu J
L6:     dup2
L7:     lstore_1
L8:     invokestatic Method org/lwjgl/l method2052 (J)V
L11:    fload_0
L12:    lload_1
L13:    invokestatic Method org/lwjgl/opengl/GL11 nglTexCoord1f (FJ)V
L16:    return
L17:    
    .end code
.end method

.method public static method3784 : (I)V
    .code stack 4 locals 3
L0:     invokestatic Method org/lwjgl/opengl/GLContext method4611 ()Lorg/lwjgl/opengl/kb;
L3:     getfield Field org/lwjgl/opengl/kb sg J
L6:     dup2
L7:     lstore_1
L8:     invokestatic Method org/lwjgl/l method2052 (J)V
L11:    iload_0
L12:    lload_1
L13:    invokestatic Method org/lwjgl/opengl/GL11 nglShadeModel (IJ)V
L16:    return
L17:    
    .end code
.end method

.method public static method3785 : (DD)V
    .code stack 6 locals 6
L0:     invokestatic Method org/lwjgl/opengl/GLContext method4611 ()Lorg/lwjgl/opengl/kb;
L3:     getfield Field org/lwjgl/opengl/kb iN J
L6:     dup2
L7:     lstore 4
L9:     invokestatic Method org/lwjgl/l method2052 (J)V
L12:    dload_0
L13:    dload_2
L14:    lload 4
L16:    invokestatic Method org/lwjgl/opengl/GL11 nglTexCoord2d (DDJ)V
L19:    return
L20:    
    .end code
.end method

.method public static method3786 : (FFFF)V
    .code stack 6 locals 6
L0:     invokestatic Method org/lwjgl/opengl/GLContext method4611 ()Lorg/lwjgl/opengl/kb;
L3:     getfield Field org/lwjgl/opengl/kb KN J
L6:     dup2
L7:     lstore 4
L9:     invokestatic Method org/lwjgl/l method2052 (J)V
L12:    fload_0
L13:    fload_1
L14:    fload_2
L15:    fload_3
L16:    lload 4
L18:    invokestatic Method org/lwjgl/opengl/GL11 nglClearAccum (FFFFJ)V
L21:    return
L22:    
    .end code
.end method

.method public static method3787 : (FFF)V
    .code stack 5 locals 5
L0:     invokestatic Method org/lwjgl/opengl/GLContext method4611 ()Lorg/lwjgl/opengl/kb;
L3:     getfield Field org/lwjgl/opengl/kb RJ J
L6:     dup2
L7:     lstore_3
L8:     invokestatic Method org/lwjgl/l method2052 (J)V
L11:    fload_0
L12:    fload_1
L13:    fload_2
L14:    lload_3
L15:    invokestatic Method org/lwjgl/opengl/GL11 nglScalef (FFFJ)V
L18:    return
L19:    
    .end code
.end method

.method public static method3788 : ()V
    .code stack 4 locals 2
L0:     invokestatic Method org/lwjgl/opengl/GLContext method4611 ()Lorg/lwjgl/opengl/kb;
L3:     getfield Field org/lwjgl/opengl/kb IC J
L6:     dup2
L7:     lstore_0
L8:     invokestatic Method org/lwjgl/l method2052 (J)V
L11:    lload_0
L12:    invokestatic Method org/lwjgl/opengl/GL11 nglEnd (J)V
L15:    return
L16:    
    .end code
.end method

.method public static method3789 : (IILjava/nio/IntBuffer;)V
    .code stack 6 locals 5
L0:     invokestatic Method org/lwjgl/opengl/GLContext method4611 ()Lorg/lwjgl/opengl/kb;
L3:     getfield Field org/lwjgl/opengl/kb Wr J
L6:     dup2
L7:     lstore_3
L8:     invokestatic Method org/lwjgl/l method2052 (J)V
L11:    iload_0
L12:    aload_2
L13:    iconst_4
L14:    iconst_1
L15:    dup
L16:    pop2
L17:    invokestatic Method org/lwjgl/l method2041 (Ljava/nio/IntBuffer;I)V
L20:    iload_1
L21:    aload_2
L22:    invokestatic Method org/lwjgl/MemoryUtil method1884 (Ljava/nio/IntBuffer;)J
L25:    lload_3
L26:    invokestatic Method org/lwjgl/opengl/GL11 nglGetTexEnviv (IIJJ)V
L29:    return
L30:    
    .end code
.end method

.method public static method3790 : (III)V
    .code stack 5 locals 5
L0:     invokestatic Method org/lwjgl/opengl/GLContext method4611 ()Lorg/lwjgl/opengl/kb;
L3:     getfield Field org/lwjgl/opengl/kb Mr J
L6:     dup2
L7:     lstore_3
L8:     invokestatic Method org/lwjgl/l method2052 (J)V
L11:    iload_0
L12:    iload_1
L13:    iload_2
L14:    lload_3
L15:    invokestatic Method org/lwjgl/opengl/GL11 nglTexParameteri (IIIJ)V
L18:    return
L19:    
    .end code
.end method

.method public static method3791 : (IIII)V
    .code stack 6 locals 6
L0:     invokestatic Method org/lwjgl/opengl/GLContext method4611 ()Lorg/lwjgl/opengl/kb;
L3:     getfield Field org/lwjgl/opengl/kb vM J
L6:     dup2
L7:     lstore 4
L9:     invokestatic Method org/lwjgl/l method2052 (J)V
L12:    iload_0
L13:    iload_1
L14:    iload_2
L15:    iload_3
L16:    lload 4
L18:    invokestatic Method org/lwjgl/opengl/GL11 nglRecti (IIIIJ)V
L21:    return
L22:    
    .end code
.end method

.method public static method3792 : (FFFF)V
    .code stack 6 locals 6
L0:     invokestatic Method org/lwjgl/opengl/GLContext method4611 ()Lorg/lwjgl/opengl/kb;
L3:     getfield Field org/lwjgl/opengl/kb Ed J
L6:     dup2
L7:     lstore 4
L9:     invokestatic Method org/lwjgl/l method2052 (J)V
L12:    fload_0
L13:    fload_1
L14:    fload_2
L15:    fload_3
L16:    lload 4
L18:    invokestatic Method org/lwjgl/opengl/GL11 nglTexCoord4f (FFFFJ)V
L21:    return
L22:    
    .end code
.end method

.method static native nglFrustum : (DDDDDDJ)V
.end method

.method static native nglVertex3d : (DDDJ)V
.end method

.method public static method3793 : (ILjava/nio/FloatBuffer;)V
    .code stack 6 locals 5
L0:     invokestatic Method org/lwjgl/opengl/GLContext method4611 ()Lorg/lwjgl/opengl/kb;
L3:     astore_2
L4:     aload_1
L5:     aload_2
L6:     dup
L7:     getfield Field org/lwjgl/opengl/kb fC J
L10:    dup2
L11:    lstore_3
L12:    invokestatic Method org/lwjgl/l method2052 (J)V
L15:    invokestatic Method org/lwjgl/opengl/Zd method5446 (Lorg/lwjgl/opengl/kb;)V
L18:    invokestatic Method org/lwjgl/l method2048 (Ljava/nio/FloatBuffer;)V
L21:    iload_0
L22:    aload_1
L23:    invokevirtual Method java/nio/FloatBuffer remaining ()I
L26:    aload_1
L27:    invokestatic Method org/lwjgl/MemoryUtil method1878 (Ljava/nio/FloatBuffer;)J
L30:    lload_3
L31:    invokestatic Method org/lwjgl/opengl/GL11 nglPixelMapfv (IIJJ)V
L34:    return
L35:    
    .end code
.end method

.method public static new : (II)V
    .code stack 4 locals 4
L0:     invokestatic Method org/lwjgl/opengl/GLContext method4611 ()Lorg/lwjgl/opengl/kb;
L3:     getfield Field org/lwjgl/opengl/kb Xt J
L6:     dup2
L7:     lstore_2
L8:     invokestatic Method org/lwjgl/l method2052 (J)V
L11:    iload_0
L12:    iload_1
L13:    lload_2
L14:    invokestatic Method org/lwjgl/opengl/GL11 nglVertex2i (IIJ)V
L17:    return
L18:    
    .end code
.end method

.method public static method3794 : ()V
    .code stack 4 locals 2
L0:     invokestatic Method org/lwjgl/opengl/GLContext method4611 ()Lorg/lwjgl/opengl/kb;
L3:     getfield Field org/lwjgl/opengl/kb d J
L6:     dup2
L7:     lstore_0
L8:     invokestatic Method org/lwjgl/l method2052 (J)V
L11:    lload_0
L12:    invokestatic Method org/lwjgl/opengl/GL11 nglLoadIdentity (J)V
L15:    return
L16:    
    .end code
.end method

.method static native nglGetBooleanv : (IJJ)V
.end method

.method public static method3795 : (IIIIIIIILjava/nio/DoubleBuffer;)V
    .code stack 12 locals 12
L0:     invokestatic Method org/lwjgl/opengl/GLContext method4611 ()Lorg/lwjgl/opengl/kb;
L3:     astore 9
L5:     aload 8
L7:     aload 9
L9:     dup
L10:    getfield Field org/lwjgl/opengl/kb kD J
L13:    dup2
L14:    lstore 10
L16:    invokestatic Method org/lwjgl/l method2052 (J)V
L19:    invokestatic Method org/lwjgl/opengl/Zd method5446 (Lorg/lwjgl/opengl/kb;)V
L22:    ifnull L41
L25:    aload 8
L27:    dup
L28:    iload 6
L30:    iload 7
L32:    iload_3
L33:    iload 4
L35:    invokestatic Method org/lwjgl/opengl/Zd method5453 (Ljava/nio/Buffer;IIII)I
L38:    invokestatic Method org/lwjgl/l method2056 (Ljava/nio/DoubleBuffer;I)V
L41:    iload_0
L42:    iload_1
L43:    iload_2
L44:    iload_3
L45:    iload 4
L47:    iload 5
L49:    iload 6
L51:    iload 7
L53:    aload 8
L55:    invokestatic Method org/lwjgl/MemoryUtil method1861 (Ljava/nio/DoubleBuffer;)J
L58:    lload 10
L60:    invokestatic Method org/lwjgl/opengl/GL11 nglTexImage2D (IIIIIIIIJJ)V
L63:    return
L64:    
        .attribute StackMap b'\x00\x01\x00\x29\x00\x0B\x01\x01\x01\x01\x01\x01\x01\x01\x07\x04\x49\x07\x04\x21\x04\x00\x00'
    .end code
.end method

.method public static method3796 : ()V
    .code stack 5 locals 2
L0:     invokestatic Method org/lwjgl/opengl/GLContext method4611 ()Lorg/lwjgl/opengl/kb;
L3:     dup
L4:     getfield Field org/lwjgl/opengl/kb while J
L7:     dup2
L8:     lstore_0
L9:     invokestatic Method org/lwjgl/l method2052 (J)V
L12:    invokestatic Method org/lwjgl/opengl/w method5770 (Lorg/lwjgl/opengl/kb;)V
L15:    lload_0
L16:    invokestatic Method org/lwjgl/opengl/GL11 nglPopClientAttrib (J)V
L19:    return
L20:    
    .end code
.end method

.method static native nglPopAttrib : (J)V
.end method

.method static native nglDrawBuffer : (IJ)V
.end method

.method static native nglSelectBuffer : (IJJ)V
.end method

.method static native nglNormal3i : (IIIJ)V
.end method

.method static native nglMateriali : (IIIJ)V
.end method

.method static native nglInterleavedArraysBO : (IIJJ)V
.end method

.method public static method3797 : (IF)V
    .code stack 4 locals 4
L0:     invokestatic Method org/lwjgl/opengl/GLContext method4611 ()Lorg/lwjgl/opengl/kb;
L3:     getfield Field org/lwjgl/opengl/kb jE J
L6:     dup2
L7:     lstore_2
L8:     invokestatic Method org/lwjgl/l method2052 (J)V
L11:    iload_0
L12:    fload_1
L13:    lload_2
L14:    invokestatic Method org/lwjgl/opengl/GL11 nglAccum (IFJ)V
L17:    return
L18:    
    .end code
.end method

.method static native nglVertex3f : (FFFJ)V
.end method

.method static native nglGetPixelMapuivBO : (IJJ)V
.end method

.method public static method3798 : (IIIJ)V
    .code stack 7 locals 7
L0:     invokestatic Method org/lwjgl/opengl/GLContext method4611 ()Lorg/lwjgl/opengl/kb;
L3:     dup
L4:     getfield Field org/lwjgl/opengl/kb field5431 J
L7:     dup2
L8:     lstore 5
L10:    invokestatic Method org/lwjgl/l method2052 (J)V
L13:    invokestatic Method org/lwjgl/opengl/Zd method5437 (Lorg/lwjgl/opengl/kb;)V
L16:    iload_0
L17:    iload_1
L18:    iload_2
L19:    lload_3
L20:    lload 5
L22:    invokestatic Method org/lwjgl/opengl/GL11 nglDrawElementsBO (IIIJJ)V
L25:    return
L26:    
    .end code
.end method

.method public static method3799 : (IIF)V
    .code stack 5 locals 5
L0:     invokestatic Method org/lwjgl/opengl/GLContext method4611 ()Lorg/lwjgl/opengl/kb;
L3:     getfield Field org/lwjgl/opengl/kb SM J
L6:     dup2
L7:     lstore_3
L8:     invokestatic Method org/lwjgl/l method2052 (J)V
L11:    iload_0
L12:    iload_1
L13:    fload_2
L14:    lload_3
L15:    invokestatic Method org/lwjgl/opengl/GL11 nglLightf (IIFJ)V
L18:    return
L19:    
    .end code
.end method

.method public static method3800 : (IIIIIIIILjava/nio/ShortBuffer;)V
    .code stack 12 locals 12
L0:     invokestatic Method org/lwjgl/opengl/GLContext method4611 ()Lorg/lwjgl/opengl/kb;
L3:     astore 9
L5:     aload 8
L7:     aload 9
L9:     dup
L10:    getfield Field org/lwjgl/opengl/kb PJ J
L13:    dup2
L14:    lstore 10
L16:    invokestatic Method org/lwjgl/l method2052 (J)V
L19:    invokestatic Method org/lwjgl/opengl/Zd method5446 (Lorg/lwjgl/opengl/kb;)V
L22:    aload 8
L24:    iload 6
L26:    iload 7
L28:    iload 4
L30:    iload 5
L32:    iconst_1
L33:    dup
L34:    dup
L35:    pop2
L36:    invokestatic Method org/lwjgl/opengl/Zd method5429 (Ljava/nio/Buffer;IIIII)I
L39:    invokestatic Method org/lwjgl/l method2031 (Ljava/nio/ShortBuffer;I)V
L42:    iload_0
L43:    iload_1
L44:    iload_2
L45:    iload_3
L46:    iload 4
L48:    iload 5
L50:    iload 6
L52:    iload 7
L54:    aload 8
L56:    invokestatic Method org/lwjgl/MemoryUtil method1853 (Ljava/nio/ShortBuffer;)J
L59:    lload 10
L61:    invokestatic Method org/lwjgl/opengl/GL11 nglTexSubImage2D (IIIIIIIIJJ)V
L64:    return
L65:    
    .end code
.end method

.method static native nglGetMaterialiv : (IIJJ)V
.end method

.method public static method3801 : (FF)V
    .code stack 4 locals 4
L0:     invokestatic Method org/lwjgl/opengl/GLContext method4611 ()Lorg/lwjgl/opengl/kb;
L3:     getfield Field org/lwjgl/opengl/kb bO J
L6:     dup2
L7:     lstore_2
L8:     invokestatic Method org/lwjgl/l method2052 (J)V
L11:    fload_0
L12:    fload_1
L13:    lload_2
L14:    invokestatic Method org/lwjgl/opengl/GL11 nglRasterPos2f (FFJ)V
L17:    return
L18:    
    .end code
.end method

.method static native nglEnableClientState : (IJ)V
.end method

.method public static method3802 : (BBBB)V
    .code stack 6 locals 6
L0:     invokestatic Method org/lwjgl/opengl/GLContext method4611 ()Lorg/lwjgl/opengl/kb;
L3:     getfield Field org/lwjgl/opengl/kb pS J
L6:     dup2
L7:     lstore 4
L9:     invokestatic Method org/lwjgl/l method2052 (J)V
L12:    iload_0
L13:    iload_1
L14:    iload_2
L15:    iload_3
L16:    lload 4
L18:    invokestatic Method org/lwjgl/opengl/GL11 nglColor4b (BBBBJ)V
L21:    return
L22:    
    .end code
.end method

.method public static method3803 : (DD)V
    .code stack 6 locals 6
L0:     invokestatic Method org/lwjgl/opengl/GLContext method4611 ()Lorg/lwjgl/opengl/kb;
L3:     getfield Field org/lwjgl/opengl/kb NI J
L6:     dup2
L7:     lstore 4
L9:     invokestatic Method org/lwjgl/l method2052 (J)V
L12:    dload_0
L13:    dload_2
L14:    lload 4
L16:    invokestatic Method org/lwjgl/opengl/GL11 nglDepthRange (DDJ)V
L19:    return
L20:    
    .end code
.end method

.method static native nglEvalPoint2 : (IIJ)V
.end method

.method public static method3804 : (IILjava/nio/FloatBuffer;)V
    .code stack 6 locals 5
L0:     invokestatic Method org/lwjgl/opengl/GLContext method4611 ()Lorg/lwjgl/opengl/kb;
L3:     getfield Field org/lwjgl/opengl/kb YM J
L6:     dup2
L7:     lstore_3
L8:     invokestatic Method org/lwjgl/l method2052 (J)V
L11:    iload_0
L12:    aload_2
L13:    iconst_4
L14:    iconst_1
L15:    dup
L16:    pop2
L17:    invokestatic Method org/lwjgl/l method2044 (Ljava/nio/FloatBuffer;I)V
L20:    iload_1
L21:    aload_2
L22:    invokestatic Method org/lwjgl/MemoryUtil method1878 (Ljava/nio/FloatBuffer;)J
L25:    lload_3
L26:    invokestatic Method org/lwjgl/opengl/GL11 nglTexParameterfv (IIJJ)V
L29:    return
L30:    
    .end code
.end method

.method public static method3805 : (IIIILjava/nio/IntBuffer;)V
    .code stack 9 locals 8
L0:     invokestatic Method org/lwjgl/opengl/GLContext method4611 ()Lorg/lwjgl/opengl/kb;
L3:     astore 5
L5:     aload 4
L7:     aload 5
L9:     dup
L10:    getfield Field org/lwjgl/opengl/kb Ps J
L13:    dup2
L14:    lstore 6
L16:    invokestatic Method org/lwjgl/l method2052 (J)V
L19:    invokestatic Method org/lwjgl/opengl/Zd method5446 (Lorg/lwjgl/opengl/kb;)V
L22:    aload 4
L24:    iload_2
L25:    iload_3
L26:    iload_0
L27:    iload_1
L28:    iconst_1
L29:    dup
L30:    dup
L31:    pop2
L32:    invokestatic Method org/lwjgl/opengl/Zd method5429 (Ljava/nio/Buffer;IIIII)I
L35:    invokestatic Method org/lwjgl/l method2041 (Ljava/nio/IntBuffer;I)V
L38:    iload_0
L39:    iload_1
L40:    iload_2
L41:    iload_3
L42:    aload 4
L44:    invokestatic Method org/lwjgl/MemoryUtil method1884 (Ljava/nio/IntBuffer;)J
L47:    lload 6
L49:    invokestatic Method org/lwjgl/opengl/GL11 nglDrawPixels (IIIIJJ)V
L52:    return
L53:    
    .end code
.end method

.method public static method3806 : (IIIIIIJ)V
    .code stack 10 locals 10
L0:     invokestatic Method org/lwjgl/opengl/GLContext method4611 ()Lorg/lwjgl/opengl/kb;
L3:     dup
L4:     getfield Field org/lwjgl/opengl/kb Zi J
L7:     dup2
L8:     lstore 8
L10:    invokestatic Method org/lwjgl/l method2052 (J)V
L13:    invokestatic Method org/lwjgl/opengl/Zd method5428 (Lorg/lwjgl/opengl/kb;)V
L16:    iload_0
L17:    iload_1
L18:    iload_2
L19:    iload_3
L20:    iload 4
L22:    iload 5
L24:    lload 6
L26:    lload 8
L28:    invokestatic Method org/lwjgl/opengl/GL11 nglTexSubImage1DBO (IIIIIIJJ)V
L31:    return
L32:    
    .end code
.end method

.method static native nglPixelTransferi : (IIJ)V
.end method

.method static native nglDisable : (IJ)V
.end method

.method public static method3807 : (FFF)V
    .code stack 5 locals 5
L0:     invokestatic Method org/lwjgl/opengl/GLContext method4611 ()Lorg/lwjgl/opengl/kb;
L3:     getfield Field org/lwjgl/opengl/kb NH J
L6:     dup2
L7:     lstore_3
L8:     invokestatic Method org/lwjgl/l method2052 (J)V
L11:    fload_0
L12:    fload_1
L13:    fload_2
L14:    lload_3
L15:    invokestatic Method org/lwjgl/opengl/GL11 nglTranslatef (FFFJ)V
L18:    return
L19:    
    .end code
.end method

.method public static method3808 : (ILjava/nio/FloatBuffer;)V
    .code stack 5 locals 4
L0:     invokestatic Method org/lwjgl/opengl/GLContext method4611 ()Lorg/lwjgl/opengl/kb;
L3:     getfield Field org/lwjgl/opengl/kb eD J
L6:     dup2
L7:     lstore_2
L8:     invokestatic Method org/lwjgl/l method2052 (J)V
L11:    iload_0
L12:    aload_1
L13:    bipush 16
L15:    iconst_1
L16:    dup
L17:    pop2
L18:    invokestatic Method org/lwjgl/l method2044 (Ljava/nio/FloatBuffer;I)V
L21:    aload_1
L22:    invokestatic Method org/lwjgl/MemoryUtil method1878 (Ljava/nio/FloatBuffer;)J
L25:    lload_2
L26:    invokestatic Method org/lwjgl/opengl/GL11 nglGetFloatv (IJJ)V
L29:    return
L30:    
    .end code
.end method

.method static native nglCopyTexImage1D : (IIIIIIIJ)V
.end method

.method public static method3809 : (III)V
    .code stack 5 locals 5
L0:     invokestatic Method org/lwjgl/opengl/GLContext method4611 ()Lorg/lwjgl/opengl/kb;
L3:     getfield Field org/lwjgl/opengl/kb re J
L6:     dup2
L7:     lstore_3
L8:     invokestatic Method org/lwjgl/l method2052 (J)V
L11:    iload_0
L12:    iload_1
L13:    iload_2
L14:    lload_3
L15:    invokestatic Method org/lwjgl/opengl/GL11 nglTexGeni (IIIJ)V
L18:    return
L19:    
    .end code
.end method

.method public static method3810 : (III)I
    .code stack 7 locals 6
L0:     invokestatic Method org/lwjgl/opengl/GLContext method4611 ()Lorg/lwjgl/opengl/kb;
L3:     dup
L4:     getfield Field org/lwjgl/opengl/kb Yi J
L7:     dup2
L8:     lstore 4
L10:    invokestatic Method org/lwjgl/l method2052 (J)V
L13:    invokestatic Method org/lwjgl/opengl/bB method5467 (Lorg/lwjgl/opengl/kb;)Ljava/nio/IntBuffer;
L16:    astore_3
L17:    iload_0
L18:    iload_1
L19:    iload_2
L20:    aload_3
L21:    invokestatic Method org/lwjgl/MemoryUtil method1884 (Ljava/nio/IntBuffer;)J
L24:    lload 4
L26:    invokestatic Method org/lwjgl/opengl/GL11 nglGetTexLevelParameteriv (IIIJJ)V
L29:    aload_3
L30:    iconst_0
L31:    iconst_1
L32:    dup
L33:    pop2
L34:    invokevirtual Method java/nio/IntBuffer get (I)I
L37:    ireturn
L38:    
    .end code
.end method

.method static native nglCallLists : (IIJJ)V
.end method

.method static native nglColorMask : (ZZZZJ)V
.end method

.method public static method3811 : (Z)V
    .code stack 4 locals 3
L0:     invokestatic Method org/lwjgl/opengl/GLContext method4611 ()Lorg/lwjgl/opengl/kb;
L3:     getfield Field org/lwjgl/opengl/kb Rh J
L6:     dup2
L7:     lstore_1
L8:     invokestatic Method org/lwjgl/l method2052 (J)V
L11:    iload_0
L12:    lload_1
L13:    invokestatic Method org/lwjgl/opengl/GL11 nglDepthMask (ZJ)V
L16:    return
L17:    
    .end code
.end method

.method static native nglEvalCoord2d : (DDJ)V
.end method

.method public static method3812 : (IILjava/nio/DoubleBuffer;)V
    .code stack 7 locals 6
L0:     invokestatic Method org/lwjgl/opengl/GLContext method4611 ()Lorg/lwjgl/opengl/kb;
L3:     astore_3
L4:     aload_2
L5:     aload_3
L6:     dup
L7:     getfield Field org/lwjgl/opengl/kb VM J
L10:    dup2
L11:    lstore 4
L13:    invokestatic Method org/lwjgl/l method2052 (J)V
L16:    invokestatic Method org/lwjgl/opengl/Zd method5454 (Lorg/lwjgl/opengl/kb;)V
L19:    invokestatic Method org/lwjgl/l method2036 (Ljava/nio/DoubleBuffer;)V
L22:    getstatic Field org/lwjgl/LWJGLUtil CHECKS Z
L25:    ifeq L36
L28:    aload_3
L29:    invokestatic Method org/lwjgl/opengl/w method5768 (Lorg/lwjgl/opengl/kb;)Lorg/lwjgl/opengl/P;
L32:    aload_2
L33:    putfield Field org/lwjgl/opengl/P field4944 Ljava/nio/Buffer;
L36:    iload_0
L37:    sipush 5130
L40:    iconst_1
L41:    dup
L42:    pop2
L43:    iload_1
L44:    aload_2
L45:    invokestatic Method org/lwjgl/MemoryUtil method1840 (Ljava/nio/DoubleBuffer;)J
L48:    lload 4
L50:    invokestatic Method org/lwjgl/opengl/GL11 nglVertexPointer (IIIJJ)V
L53:    return
L54:    
        .attribute StackMap b'\x00\x01\x00\x24\x00\x05\x01\x01\x07\x04\x49\x07\x04\x21\x04\x00\x00'
    .end code
.end method

.method static native nglEvalCoord1d : (DJ)V
.end method

.method public static method3813 : (IILjava/nio/FloatBuffer;)V
    .code stack 6 locals 5
L0:     invokestatic Method org/lwjgl/opengl/GLContext method4611 ()Lorg/lwjgl/opengl/kb;
L3:     getfield Field org/lwjgl/opengl/kb iu J
L6:     dup2
L7:     lstore_3
L8:     invokestatic Method org/lwjgl/l method2052 (J)V
L11:    iload_0
L12:    aload_2
L13:    iconst_4
L14:    iconst_1
L15:    dup
L16:    pop2
L17:    invokestatic Method org/lwjgl/l method2044 (Ljava/nio/FloatBuffer;I)V
L20:    iload_1
L21:    aload_2
L22:    invokestatic Method org/lwjgl/MemoryUtil method1878 (Ljava/nio/FloatBuffer;)J
L25:    lload_3
L26:    invokestatic Method org/lwjgl/opengl/GL11 nglGetTexEnvfv (IIJJ)V
L29:    return
L30:    
    .end code
.end method

.method public static method3814 : (IIIILjava/nio/IntBuffer;)V
    .code stack 9 locals 8
L0:     invokestatic Method org/lwjgl/opengl/GLContext method4611 ()Lorg/lwjgl/opengl/kb;
L3:     astore 5
L5:     aload 4
L7:     aload 5
L9:     dup
L10:    getfield Field org/lwjgl/opengl/kb cj J
L13:    dup2
L14:    lstore 6
L16:    invokestatic Method org/lwjgl/l method2052 (J)V
L19:    invokestatic Method org/lwjgl/opengl/Zd method5449 (Lorg/lwjgl/opengl/kb;)V
L22:    aload 4
L24:    iload_2
L25:    iload_3
L26:    iconst_1
L27:    dup
L28:    pop2
L29:    iconst_1
L30:    dup
L31:    pop2
L32:    iconst_1
L33:    dup
L34:    dup_x1
L35:    dup_x2
L36:    dup
L37:    pop2
L38:    invokestatic Method org/lwjgl/opengl/Zd method5429 (Ljava/nio/Buffer;IIIII)I
L41:    invokestatic Method org/lwjgl/l method2041 (Ljava/nio/IntBuffer;I)V
L44:    iload_0
L45:    iload_1
L46:    iload_2
L47:    iload_3
L48:    aload 4
L50:    invokestatic Method org/lwjgl/MemoryUtil method1884 (Ljava/nio/IntBuffer;)J
L53:    lload 6
L55:    invokestatic Method org/lwjgl/opengl/GL11 nglGetTexImage (IIIIJJ)V
L58:    return
L59:    
    .end code
.end method

.method static native nglBitmapBO : (IIFFFFJJ)V
.end method

.method public static method3815 : (FF)V
    .code stack 4 locals 4
L0:     invokestatic Method org/lwjgl/opengl/GLContext method4611 ()Lorg/lwjgl/opengl/kb;
L3:     getfield Field org/lwjgl/opengl/kb NG J
L6:     dup2
L7:     lstore_2
L8:     invokestatic Method org/lwjgl/l method2052 (J)V
L11:    fload_0
L12:    fload_1
L13:    lload_2
L14:    invokestatic Method org/lwjgl/opengl/GL11 nglPolygonOffset (FFJ)V
L17:    return
L18:    
    .end code
.end method

.method static native nglPixelMapusv : (IIJJ)V
.end method

.method public static method3816 : (IDD)V
    .code stack 7 locals 7
L0:     invokestatic Method org/lwjgl/opengl/GLContext method4611 ()Lorg/lwjgl/opengl/kb;
L3:     getfield Field org/lwjgl/opengl/kb UA J
L6:     dup2
L7:     lstore 5
L9:     invokestatic Method org/lwjgl/l method2052 (J)V
L12:    iload_0
L13:    dload_1
L14:    dload_3
L15:    lload 5
L17:    invokestatic Method org/lwjgl/opengl/GL11 nglMapGrid1d (IDDJ)V
L20:    return
L21:    
    .end code
.end method

.method public static method3817 : (IIIIIILjava/nio/IntBuffer;)V
    .code stack 10 locals 10
L0:     invokestatic Method org/lwjgl/opengl/GLContext method4611 ()Lorg/lwjgl/opengl/kb;
L3:     astore 7
L5:     aload 6
L7:     aload 7
L9:     dup
L10:    getfield Field org/lwjgl/opengl/kb Zi J
L13:    dup2
L14:    lstore 8
L16:    invokestatic Method org/lwjgl/l method2052 (J)V
L19:    invokestatic Method org/lwjgl/opengl/Zd method5446 (Lorg/lwjgl/opengl/kb;)V
L22:    aload 6
L24:    iload 4
L26:    iload 5
L28:    iload_3
L29:    iconst_1
L30:    dup
L31:    pop2
L32:    iconst_1
L33:    dup
L34:    dup_x1
L35:    dup
L36:    pop2
L37:    invokestatic Method org/lwjgl/opengl/Zd method5429 (Ljava/nio/Buffer;IIIII)I
L40:    invokestatic Method org/lwjgl/l method2041 (Ljava/nio/IntBuffer;I)V
L43:    iload_0
L44:    iload_1
L45:    iload_2
L46:    iload_3
L47:    iload 4
L49:    iload 5
L51:    aload 6
L53:    invokestatic Method org/lwjgl/MemoryUtil method1884 (Ljava/nio/IntBuffer;)J
L56:    lload 8
L58:    invokestatic Method org/lwjgl/opengl/GL11 nglTexSubImage1D (IIIIIIJJ)V
L61:    return
L62:    
    .end code
.end method

.method public static method3818 : (D)V
    .code stack 4 locals 4
L0:     invokestatic Method org/lwjgl/opengl/GLContext method4611 ()Lorg/lwjgl/opengl/kb;
L3:     getfield Field org/lwjgl/opengl/kb Fp J
L6:     dup2
L7:     lstore_2
L8:     invokestatic Method org/lwjgl/l method2052 (J)V
L11:    dload_0
L12:    lload_2
L13:    invokestatic Method org/lwjgl/opengl/GL11 nglTexCoord1d (DJ)V
L16:    return
L17:    
    .end code
.end method

.method public static try : (II)V
    .code stack 4 locals 4
L0:     invokestatic Method org/lwjgl/opengl/GLContext method4611 ()Lorg/lwjgl/opengl/kb;
L3:     getfield Field org/lwjgl/opengl/kb pH J
L6:     dup2
L7:     lstore_2
L8:     invokestatic Method org/lwjgl/l method2052 (J)V
L11:    iload_0
L12:    iload_1
L13:    lload_2
L14:    invokestatic Method org/lwjgl/opengl/GL11 nglColorMaterial (IIJ)V
L17:    return
L18:    
    .end code
.end method

.method static native nglMultMatrixd : (JJ)V
.end method

.method public static method3819 : (IILjava/nio/FloatBuffer;)V
    .code stack 6 locals 5
L0:     invokestatic Method org/lwjgl/opengl/GLContext method4611 ()Lorg/lwjgl/opengl/kb;
L3:     getfield Field org/lwjgl/opengl/kb Nn J
L6:     dup2
L7:     lstore_3
L8:     invokestatic Method org/lwjgl/l method2052 (J)V
L11:    iload_0
L12:    aload_2
L13:    iconst_4
L14:    iconst_1
L15:    dup
L16:    pop2
L17:    invokestatic Method org/lwjgl/l method2044 (Ljava/nio/FloatBuffer;I)V
L20:    iload_1
L21:    aload_2
L22:    invokestatic Method org/lwjgl/MemoryUtil method1878 (Ljava/nio/FloatBuffer;)J
L25:    lload_3
L26:    invokestatic Method org/lwjgl/opengl/GL11 nglTexEnvfv (IIJJ)V
L29:    return
L30:    
    .end code
.end method

.method public static method3820 : ()V
    .code stack 4 locals 2
L0:     invokestatic Method org/lwjgl/opengl/GLContext method4611 ()Lorg/lwjgl/opengl/kb;
L3:     getfield Field org/lwjgl/opengl/kb Ob J
L6:     dup2
L7:     lstore_0
L8:     invokestatic Method org/lwjgl/l method2052 (J)V
L11:    lload_0
L12:    invokestatic Method org/lwjgl/opengl/GL11 nglFinish (J)V
L15:    return
L16:    
    .end code
.end method

.method static native nglEvalCoord2f : (FFJ)V
.end method

.method public static method3821 : ()V
    .code stack 4 locals 2
L0:     invokestatic Method org/lwjgl/opengl/GLContext method4611 ()Lorg/lwjgl/opengl/kb;
L3:     getfield Field org/lwjgl/opengl/kb XE J
L6:     dup2
L7:     lstore_0
L8:     invokestatic Method org/lwjgl/l method2052 (J)V
L11:    lload_0
L12:    invokestatic Method org/lwjgl/opengl/GL11 nglInitNames (J)V
L15:    return
L16:    
    .end code
.end method

.method public static method3822 : (IILjava/nio/IntBuffer;)V
    .code stack 6 locals 5
L0:     invokestatic Method org/lwjgl/opengl/GLContext method4611 ()Lorg/lwjgl/opengl/kb;
L3:     getfield Field org/lwjgl/opengl/kb Ei J
L6:     dup2
L7:     lstore_3
L8:     invokestatic Method org/lwjgl/l method2052 (J)V
L11:    iload_0
L12:    aload_2
L13:    iconst_4
L14:    iconst_1
L15:    dup
L16:    pop2
L17:    invokestatic Method org/lwjgl/l method2041 (Ljava/nio/IntBuffer;I)V
L20:    iload_1
L21:    aload_2
L22:    invokestatic Method org/lwjgl/MemoryUtil method1884 (Ljava/nio/IntBuffer;)J
L25:    lload_3
L26:    invokestatic Method org/lwjgl/opengl/GL11 nglTexParameteriv (IIJJ)V
L29:    return
L30:    
    .end code
.end method

.method public static method3823 : (IIIIIILjava/nio/ByteBuffer;)V
    .code stack 10 locals 10
L0:     invokestatic Method org/lwjgl/opengl/GLContext method4611 ()Lorg/lwjgl/opengl/kb;
L3:     astore 7
L5:     aload 6
L7:     aload 7
L9:     dup
L10:    getfield Field org/lwjgl/opengl/kb oL J
L13:    dup2
L14:    lstore 8
L16:    invokestatic Method org/lwjgl/l method2052 (J)V
L19:    invokestatic Method org/lwjgl/opengl/Zd method5449 (Lorg/lwjgl/opengl/kb;)V
L22:    aload 6
L24:    iload 4
L26:    iload 5
L28:    iload_2
L29:    iload_3
L30:    iconst_1
L31:    dup
L32:    dup
L33:    pop2
L34:    invokestatic Method org/lwjgl/opengl/Zd method5429 (Ljava/nio/Buffer;IIIII)I
L37:    invokestatic Method org/lwjgl/l method2054 (Ljava/nio/ByteBuffer;I)V
L40:    iload_0
L41:    iload_1
L42:    iload_2
L43:    iload_3
L44:    iload 4
L46:    iload 5
L48:    aload 6
L50:    invokestatic Method org/lwjgl/MemoryUtil method1873 (Ljava/nio/ByteBuffer;)J
L53:    lload 8
L55:    invokestatic Method org/lwjgl/opengl/GL11 nglReadPixels (IIIIIIJJ)V
L58:    return
L59:    
    .end code
.end method

.method static native nglTexCoord4d : (DDDDJ)V
.end method

.method public static this : (II)V
    .code stack 4 locals 4
L0:     invokestatic Method org/lwjgl/opengl/GLContext method4611 ()Lorg/lwjgl/opengl/kb;
L3:     getfield Field org/lwjgl/opengl/kb RR J
L6:     dup2
L7:     lstore_2
L8:     invokestatic Method org/lwjgl/l method2052 (J)V
L11:    iload_0
L12:    iload_1
L13:    lload_2
L14:    invokestatic Method org/lwjgl/opengl/GL11 nglDeleteLists (IIJ)V
L17:    return
L18:    
    .end code
.end method

.method public static method3824 : (II)V
    .code stack 4 locals 4
L0:     invokestatic Method org/lwjgl/opengl/GLContext method4611 ()Lorg/lwjgl/opengl/kb;
L3:     getfield Field org/lwjgl/opengl/kb dL J
L6:     dup2
L7:     lstore_2
L8:     invokestatic Method org/lwjgl/l method2052 (J)V
L11:    iload_0
L12:    iload_1
L13:    lload_2
L14:    invokestatic Method org/lwjgl/opengl/GL11 nglBindTexture (IIJ)V
L17:    return
L18:    
    .end code
.end method

.method public static method3825 : (BBB)V
    .code stack 5 locals 5
L0:     invokestatic Method org/lwjgl/opengl/GLContext method4611 ()Lorg/lwjgl/opengl/kb;
L3:     getfield Field org/lwjgl/opengl/kb kh J
L6:     dup2
L7:     lstore_3
L8:     invokestatic Method org/lwjgl/l method2052 (J)V
L11:    iload_0
L12:    iload_1
L13:    iload_2
L14:    lload_3
L15:    invokestatic Method org/lwjgl/opengl/GL11 nglColor3b (BBBJ)V
L18:    return
L19:    
    .end code
.end method

.method public static new : (I)V
    .code stack 4 locals 3
L0:     invokestatic Method org/lwjgl/opengl/GLContext method4611 ()Lorg/lwjgl/opengl/kb;
L3:     getfield Field org/lwjgl/opengl/kb HS J
L6:     dup2
L7:     lstore_1
L8:     invokestatic Method org/lwjgl/l method2052 (J)V
L11:    iload_0
L12:    lload_1
L13:    invokestatic Method org/lwjgl/opengl/GL11 nglClear (IJ)V
L16:    return
L17:    
    .end code
.end method

.method public static method3826 : (DDD)V
    .code stack 8 locals 8
L0:     invokestatic Method org/lwjgl/opengl/GLContext method4611 ()Lorg/lwjgl/opengl/kb;
L3:     getfield Field org/lwjgl/opengl/kb ad J
L6:     dup2
L7:     lstore 6
L9:     invokestatic Method org/lwjgl/l method2052 (J)V
L12:    dload_0
L13:    dload_2
L14:    dload 4
L16:    lload 6
L18:    invokestatic Method org/lwjgl/opengl/GL11 nglColor3d (DDDJ)V
L21:    return
L22:    
    .end code
.end method

.method static native nglPixelTransferf : (IFJ)V
.end method

.method static native nglEnd : (J)V
.end method

.method public static method3827 : (ILjava/nio/IntBuffer;)V
    .code stack 6 locals 5
L0:     invokestatic Method org/lwjgl/opengl/GLContext method4611 ()Lorg/lwjgl/opengl/kb;
L3:     astore_2
L4:     aload_1
L5:     aload_2
L6:     dup
L7:     getfield Field org/lwjgl/opengl/kb cG J
L10:    dup2
L11:    lstore_3
L12:    invokestatic Method org/lwjgl/l method2052 (J)V
L15:    invokestatic Method org/lwjgl/opengl/Zd method5449 (Lorg/lwjgl/opengl/kb;)V
L18:    sipush 256
L21:    iconst_1
L22:    dup
L23:    pop2
L24:    invokestatic Method org/lwjgl/l method2041 (Ljava/nio/IntBuffer;I)V
L27:    iload_0
L28:    aload_1
L29:    invokestatic Method org/lwjgl/MemoryUtil method1884 (Ljava/nio/IntBuffer;)J
L32:    lload_3
L33:    invokestatic Method org/lwjgl/opengl/GL11 nglGetPixelMapuiv (IJJ)V
L36:    return
L37:    
    .end code
.end method

.method static native nglTexCoord3d : (DDDJ)V
.end method

.method static native nglGetTexLevelParameteriv : (IIIJJ)V
.end method

.method static native nglRectf : (FFFFJ)V
.end method

.method static native nglTexCoordPointer : (IIIJJ)V
.end method

.method static native nglGetLightfv : (IIJJ)V
.end method

.method static native nglTexParameterf : (IIFJ)V
.end method

.method public static try : (I)V
    .code stack 4 locals 3
L0:     invokestatic Method org/lwjgl/opengl/GLContext method4611 ()Lorg/lwjgl/opengl/kb;
L3:     getfield Field org/lwjgl/opengl/kb Zf J
L6:     dup2
L7:     lstore_1
L8:     invokestatic Method org/lwjgl/l method2052 (J)V
L11:    iload_0
L12:    lload_1
L13:    invokestatic Method org/lwjgl/opengl/GL11 nglEnableClientState (IJ)V
L16:    return
L17:    
    .end code
.end method

.method static native nglStencilMask : (IJ)V
.end method

.method public static method3828 : (FFFF)V
    .code stack 6 locals 6
L0:     invokestatic Method org/lwjgl/opengl/GLContext method4611 ()Lorg/lwjgl/opengl/kb;
L3:     getfield Field org/lwjgl/opengl/kb Ap J
L6:     dup2
L7:     lstore 4
L9:     invokestatic Method org/lwjgl/l method2052 (J)V
L12:    fload_0
L13:    fload_1
L14:    fload_2
L15:    fload_3
L16:    lload 4
L18:    invokestatic Method org/lwjgl/opengl/GL11 nglRectf (FFFFJ)V
L21:    return
L22:    
    .end code
.end method

.method static native nglEvalMesh2 : (IIIIIJ)V
.end method

.method public static method3829 : (IIIIIIIILjava/nio/ShortBuffer;)V
    .code stack 12 locals 12
L0:     invokestatic Method org/lwjgl/opengl/GLContext method4611 ()Lorg/lwjgl/opengl/kb;
L3:     astore 9
L5:     aload 8
L7:     aload 9
L9:     dup
L10:    getfield Field org/lwjgl/opengl/kb kD J
L13:    dup2
L14:    lstore 10
L16:    invokestatic Method org/lwjgl/l method2052 (J)V
L19:    invokestatic Method org/lwjgl/opengl/Zd method5446 (Lorg/lwjgl/opengl/kb;)V
L22:    ifnull L41
L25:    aload 8
L27:    dup
L28:    iload 6
L30:    iload 7
L32:    iload_3
L33:    iload 4
L35:    invokestatic Method org/lwjgl/opengl/Zd method5453 (Ljava/nio/Buffer;IIII)I
L38:    invokestatic Method org/lwjgl/l method2031 (Ljava/nio/ShortBuffer;I)V
L41:    iload_0
L42:    iload_1
L43:    iload_2
L44:    iload_3
L45:    iload 4
L47:    iload 5
L49:    iload 6
L51:    iload 7
L53:    aload 8
L55:    invokestatic Method org/lwjgl/MemoryUtil method1875 (Ljava/nio/ShortBuffer;)J
L58:    lload 10
L60:    invokestatic Method org/lwjgl/opengl/GL11 nglTexImage2D (IIIIIIIIJJ)V
L63:    return
L64:    
        .attribute StackMap b'\x00\x01\x00\x29\x00\x0B\x01\x01\x01\x01\x01\x01\x01\x01\x07\x05\x65\x07\x04\x21\x04\x00\x00'
    .end code
.end method

.method public static method3830 : (IIIIIIIILjava/nio/FloatBuffer;)V
    .code stack 12 locals 12
L0:     invokestatic Method org/lwjgl/opengl/GLContext method4611 ()Lorg/lwjgl/opengl/kb;
L3:     astore 9
L5:     aload 8
L7:     aload 9
L9:     dup
L10:    getfield Field org/lwjgl/opengl/kb PJ J
L13:    dup2
L14:    lstore 10
L16:    invokestatic Method org/lwjgl/l method2052 (J)V
L19:    invokestatic Method org/lwjgl/opengl/Zd method5446 (Lorg/lwjgl/opengl/kb;)V
L22:    aload 8
L24:    iload 6
L26:    iload 7
L28:    iload 4
L30:    iload 5
L32:    iconst_1
L33:    dup
L34:    dup
L35:    pop2
L36:    invokestatic Method org/lwjgl/opengl/Zd method5429 (Ljava/nio/Buffer;IIIII)I
L39:    invokestatic Method org/lwjgl/l method2044 (Ljava/nio/FloatBuffer;I)V
L42:    iload_0
L43:    iload_1
L44:    iload_2
L45:    iload_3
L46:    iload 4
L48:    iload 5
L50:    iload 6
L52:    iload 7
L54:    aload 8
L56:    invokestatic Method org/lwjgl/MemoryUtil method1878 (Ljava/nio/FloatBuffer;)J
L59:    lload 10
L61:    invokestatic Method org/lwjgl/opengl/GL11 nglTexSubImage2D (IIIIIIIIJJ)V
L64:    return
L65:    
    .end code
.end method

.method public static method3831 : (BBB)V
    .code stack 5 locals 5
L0:     invokestatic Method org/lwjgl/opengl/GLContext method4611 ()Lorg/lwjgl/opengl/kb;
L3:     getfield Field org/lwjgl/opengl/kb zM J
L6:     dup2
L7:     lstore_3
L8:     invokestatic Method org/lwjgl/l method2052 (J)V
L11:    iload_0
L12:    iload_1
L13:    iload_2
L14:    lload_3
L15:    invokestatic Method org/lwjgl/opengl/GL11 nglNormal3b (BBBJ)V
L18:    return
L19:    
    .end code
.end method

.method static native nglDeleteLists : (IIJ)V
.end method

.method static native nglReadBuffer : (IJ)V
.end method

.method public static method3832 : (IF)V
    .code stack 4 locals 4
L0:     invokestatic Method org/lwjgl/opengl/GLContext method4611 ()Lorg/lwjgl/opengl/kb;
L3:     getfield Field org/lwjgl/opengl/kb ph J
L6:     dup2
L7:     lstore_2
L8:     invokestatic Method org/lwjgl/l method2052 (J)V
L11:    iload_0
L12:    fload_1
L13:    lload_2
L14:    invokestatic Method org/lwjgl/opengl/GL11 nglLightModelf (IFJ)V
L17:    return
L18:    
    .end code
.end method

.method static native nglPopName : (J)V
.end method

.method public static method3833 : (IDDIIDDIILjava/nio/DoubleBuffer;)V
    .code stack 17 locals 16
L0:     invokestatic Method org/lwjgl/opengl/GLContext method4611 ()Lorg/lwjgl/opengl/kb;
L3:     getfield Field org/lwjgl/opengl/kb nl J
L6:     dup2
L7:     lstore 14
L9:     invokestatic Method org/lwjgl/l method2052 (J)V
L12:    iload_0
L13:    aload 13
L15:    invokestatic Method org/lwjgl/l method2036 (Ljava/nio/DoubleBuffer;)V
L18:    dload_1
L19:    dload_3
L20:    iload 5
L22:    iload 6
L24:    dload 7
L26:    dload 9
L28:    iload 11
L30:    iload 12
L32:    aload 13
L34:    invokestatic Method org/lwjgl/MemoryUtil method1840 (Ljava/nio/DoubleBuffer;)J
L37:    lload 14
L39:    invokestatic Method org/lwjgl/opengl/GL11 nglMap2d (IDDIIDDIIJJ)V
L42:    return
L43:    
    .end code
.end method

.method public static method3834 : (IIFFFFJ)V
    .code stack 10 locals 10
L0:     invokestatic Method org/lwjgl/opengl/GLContext method4611 ()Lorg/lwjgl/opengl/kb;
L3:     dup
L4:     getfield Field org/lwjgl/opengl/kb Ys J
L7:     dup2
L8:     lstore 8
L10:    invokestatic Method org/lwjgl/l method2052 (J)V
L13:    invokestatic Method org/lwjgl/opengl/Zd method5428 (Lorg/lwjgl/opengl/kb;)V
L16:    iload_0
L17:    iload_1
L18:    fload_2
L19:    fload_3
L20:    fload 4
L22:    fload 5
L24:    lload 6
L26:    lload 8
L28:    invokestatic Method org/lwjgl/opengl/GL11 nglBitmapBO (IIFFFFJJ)V
L31:    return
L32:    
    .end code
.end method

.method static native nglTexGenfv : (IIJJ)V
.end method

.method static native nglScissor : (IIIIJ)V
.end method

.method static native nglPixelMapusvBO : (IIJJ)V
.end method

.method static native nglInterleavedArrays : (IIJJ)V
.end method

.method public static method3835 : (IIIILjava/nio/ShortBuffer;)V
    .code stack 9 locals 8
L0:     invokestatic Method org/lwjgl/opengl/GLContext method4611 ()Lorg/lwjgl/opengl/kb;
L3:     astore 5
L5:     aload 4
L7:     aload 5
L9:     dup
L10:    getfield Field org/lwjgl/opengl/kb cj J
L13:    dup2
L14:    lstore 6
L16:    invokestatic Method org/lwjgl/l method2052 (J)V
L19:    invokestatic Method org/lwjgl/opengl/Zd method5449 (Lorg/lwjgl/opengl/kb;)V
L22:    aload 4
L24:    iload_2
L25:    iload_3
L26:    iconst_1
L27:    dup
L28:    pop2
L29:    iconst_1
L30:    dup
L31:    pop2
L32:    iconst_1
L33:    dup
L34:    dup_x1
L35:    dup_x2
L36:    dup
L37:    pop2
L38:    invokestatic Method org/lwjgl/opengl/Zd method5429 (Ljava/nio/Buffer;IIIII)I
L41:    invokestatic Method org/lwjgl/l method2031 (Ljava/nio/ShortBuffer;I)V
L44:    iload_0
L45:    iload_1
L46:    iload_2
L47:    iload_3
L48:    aload 4
L50:    invokestatic Method org/lwjgl/MemoryUtil method1853 (Ljava/nio/ShortBuffer;)J
L53:    lload 6
L55:    invokestatic Method org/lwjgl/opengl/GL11 nglGetTexImage (IIIIJJ)V
L58:    return
L59:    
    .end code
.end method

.method static native nglColor3d : (DDDJ)V
.end method

.method public static method3836 : (IILjava/nio/ShortBuffer;)V
    .code stack 7 locals 6
L0:     invokestatic Method org/lwjgl/opengl/GLContext method4611 ()Lorg/lwjgl/opengl/kb;
L3:     astore_3
L4:     aload_2
L5:     aload_3
L6:     dup
L7:     getfield Field org/lwjgl/opengl/kb rt J
L10:    dup2
L11:    lstore 4
L13:    invokestatic Method org/lwjgl/l method2052 (J)V
L16:    invokestatic Method org/lwjgl/opengl/Zd method5454 (Lorg/lwjgl/opengl/kb;)V
L19:    invokestatic Method org/lwjgl/l method2057 (Ljava/nio/ShortBuffer;)V
L22:    getstatic Field org/lwjgl/LWJGLUtil CHECKS Z
L25:    ifeq L44
L28:    aload_3
L29:    invokestatic Method org/lwjgl/opengl/w method5768 (Lorg/lwjgl/opengl/kb;)Lorg/lwjgl/opengl/P;
L32:    getfield Field org/lwjgl/opengl/P field4953 [Ljava/nio/Buffer;
L35:    aload_3
L36:    invokestatic Method org/lwjgl/opengl/w method5768 (Lorg/lwjgl/opengl/kb;)Lorg/lwjgl/opengl/P;
L39:    getfield Field org/lwjgl/opengl/P this I
L42:    aload_2
L43:    aastore
L44:    iload_0
L45:    sipush 5122
L48:    iconst_1
L49:    dup
L50:    pop2
L51:    iload_1
L52:    aload_2
L53:    invokestatic Method org/lwjgl/MemoryUtil method1853 (Ljava/nio/ShortBuffer;)J
L56:    lload 4
L58:    invokestatic Method org/lwjgl/opengl/GL11 nglTexCoordPointer (IIIJJ)V
L61:    return
L62:    
        .attribute StackMap b'\x00\x01\x00\x2C\x00\x05\x01\x01\x07\x05\x65\x07\x04\x21\x04\x00\x00'
    .end code
.end method

.method public static method3837 : (ILjava/nio/IntBuffer;)V
    .code stack 7 locals 5
L0:     invokestatic Method org/lwjgl/opengl/GLContext method4611 ()Lorg/lwjgl/opengl/kb;
L3:     astore_2
L4:     aload_1
L5:     aload_2
L6:     dup
L7:     getfield Field org/lwjgl/opengl/kb field5431 J
L10:    dup2
L11:    lstore_3
L12:    invokestatic Method org/lwjgl/l method2052 (J)V
L15:    invokestatic Method org/lwjgl/opengl/Zd method5435 (Lorg/lwjgl/opengl/kb;)V
L18:    invokestatic Method org/lwjgl/l method2043 (Ljava/nio/IntBuffer;)V
L21:    iload_0
L22:    aload_1
L23:    invokevirtual Method java/nio/IntBuffer remaining ()I
L26:    sipush 5125
L29:    iconst_1
L30:    dup
L31:    pop2
L32:    aload_1
L33:    invokestatic Method org/lwjgl/MemoryUtil method1884 (Ljava/nio/IntBuffer;)J
L36:    lload_3
L37:    invokestatic Method org/lwjgl/opengl/GL11 nglDrawElements (IIIJJ)V
L40:    return
L41:    
    .end code
.end method

.method static native nglGetMaterialfv : (IIJJ)V
.end method

.method public static method3838 : (IILjava/nio/IntBuffer;)V
    .code stack 7 locals 6
L0:     invokestatic Method org/lwjgl/opengl/GLContext method4611 ()Lorg/lwjgl/opengl/kb;
L3:     astore_3
L4:     aload_2
L5:     aload_3
L6:     dup
L7:     getfield Field org/lwjgl/opengl/kb rt J
L10:    dup2
L11:    lstore 4
L13:    invokestatic Method org/lwjgl/l method2052 (J)V
L16:    invokestatic Method org/lwjgl/opengl/Zd method5454 (Lorg/lwjgl/opengl/kb;)V
L19:    invokestatic Method org/lwjgl/l method2043 (Ljava/nio/IntBuffer;)V
L22:    getstatic Field org/lwjgl/LWJGLUtil CHECKS Z
L25:    ifeq L44
L28:    aload_3
L29:    invokestatic Method org/lwjgl/opengl/w method5768 (Lorg/lwjgl/opengl/kb;)Lorg/lwjgl/opengl/P;
L32:    getfield Field org/lwjgl/opengl/P field4953 [Ljava/nio/Buffer;
L35:    aload_3
L36:    invokestatic Method org/lwjgl/opengl/w method5768 (Lorg/lwjgl/opengl/kb;)Lorg/lwjgl/opengl/P;
L39:    getfield Field org/lwjgl/opengl/P this I
L42:    aload_2
L43:    aastore
L44:    iload_0
L45:    sipush 5124
L48:    iconst_1
L49:    dup
L50:    pop2
L51:    iload_1
L52:    aload_2
L53:    invokestatic Method org/lwjgl/MemoryUtil method1884 (Ljava/nio/IntBuffer;)J
L56:    lload 4
L58:    invokestatic Method org/lwjgl/opengl/GL11 nglTexCoordPointer (IIIJJ)V
L61:    return
L62:    
        .attribute StackMap b'\x00\x01\x00\x2C\x00\x05\x01\x01\x07\x04\x5F\x07\x04\x21\x04\x00\x00'
    .end code
.end method

.method public static method3839 : (IFFIFF)V
    .code stack 8 locals 8
L0:     invokestatic Method org/lwjgl/opengl/GLContext method4611 ()Lorg/lwjgl/opengl/kb;
L3:     getfield Field org/lwjgl/opengl/kb hT J
L6:     dup2
L7:     lstore 6
L9:     invokestatic Method org/lwjgl/l method2052 (J)V
L12:    iload_0
L13:    fload_1
L14:    fload_2
L15:    iload_3
L16:    fload 4
L18:    fload 5
L20:    lload 6
L22:    invokestatic Method org/lwjgl/opengl/GL11 nglMapGrid2f (IFFIFFJ)V
L25:    return
L26:    
    .end code
.end method

.method public static method3840 : (IIIILjava/nio/ByteBuffer;)V
    .code stack 9 locals 8
L0:     invokestatic Method org/lwjgl/opengl/GLContext method4611 ()Lorg/lwjgl/opengl/kb;
L3:     astore 5
L5:     aload 4
L7:     aload 5
L9:     dup
L10:    getfield Field org/lwjgl/opengl/kb cj J
L13:    dup2
L14:    lstore 6
L16:    invokestatic Method org/lwjgl/l method2052 (J)V
L19:    invokestatic Method org/lwjgl/opengl/Zd method5449 (Lorg/lwjgl/opengl/kb;)V
L22:    aload 4
L24:    iload_2
L25:    iload_3
L26:    iconst_1
L27:    dup
L28:    pop2
L29:    iconst_1
L30:    dup
L31:    pop2
L32:    iconst_1
L33:    dup
L34:    dup_x1
L35:    dup_x2
L36:    dup
L37:    pop2
L38:    invokestatic Method org/lwjgl/opengl/Zd method5429 (Ljava/nio/Buffer;IIIII)I
L41:    invokestatic Method org/lwjgl/l method2054 (Ljava/nio/ByteBuffer;I)V
L44:    iload_0
L45:    iload_1
L46:    iload_2
L47:    iload_3
L48:    aload 4
L50:    invokestatic Method org/lwjgl/MemoryUtil method1873 (Ljava/nio/ByteBuffer;)J
L53:    lload 6
L55:    invokestatic Method org/lwjgl/opengl/GL11 nglGetTexImage (IIIIJJ)V
L58:    return
L59:    
    .end code
.end method

.method public static method3841 : (IILjava/nio/DoubleBuffer;)V
    .code stack 6 locals 6
L0:     invokestatic Method org/lwjgl/opengl/GLContext method4611 ()Lorg/lwjgl/opengl/kb;
L3:     astore_3
L4:     aload_2
L5:     aload_3
L6:     dup
L7:     getfield Field org/lwjgl/opengl/kb MB J
L10:    dup2
L11:    lstore 4
L13:    invokestatic Method org/lwjgl/l method2052 (J)V
L16:    invokestatic Method org/lwjgl/opengl/Zd method5454 (Lorg/lwjgl/opengl/kb;)V
L19:    invokestatic Method org/lwjgl/l method2036 (Ljava/nio/DoubleBuffer;)V
L22:    iload_0
L23:    iload_1
L24:    aload_2
L25:    invokestatic Method org/lwjgl/MemoryUtil method1840 (Ljava/nio/DoubleBuffer;)J
L28:    lload 4
L30:    invokestatic Method org/lwjgl/opengl/GL11 nglInterleavedArrays (IIJJ)V
L33:    return
L34:    
    .end code
.end method

.method static native nglColor4b : (BBBBJ)V
.end method

.method public static method3842 : (Ljava/nio/ByteBuffer;)V
    .code stack 6 locals 4
L0:     invokestatic Method org/lwjgl/opengl/GLContext method4611 ()Lorg/lwjgl/opengl/kb;
L3:     astore_1
L4:     aload_0
L5:     aload_1
L6:     dup
L7:     getfield Field org/lwjgl/opengl/kb mj J
L10:    dup2
L11:    lstore_2
L12:    invokestatic Method org/lwjgl/l method2052 (J)V
L15:    invokestatic Method org/lwjgl/opengl/Zd method5446 (Lorg/lwjgl/opengl/kb;)V
L18:    aload_0
L19:    sipush 128
L22:    iconst_1
L23:    dup
L24:    pop2
L25:    invokestatic Method org/lwjgl/l method2054 (Ljava/nio/ByteBuffer;I)V
L28:    invokestatic Method org/lwjgl/MemoryUtil method1873 (Ljava/nio/ByteBuffer;)J
L31:    lload_2
L32:    invokestatic Method org/lwjgl/opengl/GL11 nglPolygonStipple (JJ)V
L35:    return
L36:    
    .end code
.end method

.method public static method3843 : (Ljava/nio/FloatBuffer;)V
    .code stack 5 locals 3
L0:     invokestatic Method org/lwjgl/opengl/GLContext method4611 ()Lorg/lwjgl/opengl/kb;
L3:     getfield Field org/lwjgl/opengl/kb PE J
L6:     dup2
L7:     lstore_1
L8:     invokestatic Method org/lwjgl/l method2052 (J)V
L11:    aload_0
L12:    dup
L13:    bipush 16
L15:    iconst_1
L16:    dup
L17:    pop2
L18:    invokestatic Method org/lwjgl/l method2044 (Ljava/nio/FloatBuffer;I)V
L21:    invokestatic Method org/lwjgl/MemoryUtil method1878 (Ljava/nio/FloatBuffer;)J
L24:    lload_1
L25:    invokestatic Method org/lwjgl/opengl/GL11 nglLoadMatrixf (JJ)V
L28:    return
L29:    
    .end code
.end method

.method public static method3844 : (IIF)V
    .code stack 5 locals 5
L0:     invokestatic Method org/lwjgl/opengl/GLContext method4611 ()Lorg/lwjgl/opengl/kb;
L3:     getfield Field org/lwjgl/opengl/kb yA J
L6:     dup2
L7:     lstore_3
L8:     invokestatic Method org/lwjgl/l method2052 (J)V
L11:    iload_0
L12:    iload_1
L13:    fload_2
L14:    lload_3
L15:    invokestatic Method org/lwjgl/opengl/GL11 nglTexParameterf (IIFJ)V
L18:    return
L19:    
    .end code
.end method

.method static native nglVertex3i : (IIIJ)V
.end method

.method static native nglFogiv : (IJJ)V
.end method

.method static native nglGenLists : (IJ)I
.end method

.method public static method3845 : (IILjava/nio/IntBuffer;)V
    .code stack 6 locals 5
L0:     invokestatic Method org/lwjgl/opengl/GLContext method4611 ()Lorg/lwjgl/opengl/kb;
L3:     getfield Field org/lwjgl/opengl/kb Wd J
L6:     dup2
L7:     lstore_3
L8:     invokestatic Method org/lwjgl/l method2052 (J)V
L11:    iload_0
L12:    aload_2
L13:    iconst_4
L14:    iconst_1
L15:    dup
L16:    pop2
L17:    invokestatic Method org/lwjgl/l method2041 (Ljava/nio/IntBuffer;I)V
L20:    iload_1
L21:    aload_2
L22:    invokestatic Method org/lwjgl/MemoryUtil method1884 (Ljava/nio/IntBuffer;)J
L25:    lload_3
L26:    invokestatic Method org/lwjgl/opengl/GL11 nglTexEnviv (IIJJ)V
L29:    return
L30:    
    .end code
.end method

.method static native nglGetTexEnvfv : (IIJJ)V
.end method

.method public static method3846 : (IILjava/nio/IntBuffer;)V
    .code stack 6 locals 5
L0:     invokestatic Method org/lwjgl/opengl/GLContext method4611 ()Lorg/lwjgl/opengl/kb;
L3:     getfield Field org/lwjgl/opengl/kb cp J
L6:     dup2
L7:     lstore_3
L8:     invokestatic Method org/lwjgl/l method2052 (J)V
L11:    iload_0
L12:    aload_2
L13:    iconst_4
L14:    iconst_1
L15:    dup
L16:    pop2
L17:    invokestatic Method org/lwjgl/l method2041 (Ljava/nio/IntBuffer;I)V
L20:    iload_1
L21:    aload_2
L22:    invokestatic Method org/lwjgl/MemoryUtil method1884 (Ljava/nio/IntBuffer;)J
L25:    lload_3
L26:    invokestatic Method org/lwjgl/opengl/GL11 nglMaterialiv (IIJJ)V
L29:    return
L30:    
    .end code
.end method

.method static native nglPixelMapfv : (IIJJ)V
.end method

.method static native nglPushName : (IJ)V
.end method

.method static native nglMaterialiv : (IIJJ)V
.end method

.method public static method3847 : (IIIIIILjava/nio/IntBuffer;)V
    .code stack 10 locals 10
L0:     invokestatic Method org/lwjgl/opengl/GLContext method4611 ()Lorg/lwjgl/opengl/kb;
L3:     astore 7
L5:     aload 6
L7:     aload 7
L9:     dup
L10:    getfield Field org/lwjgl/opengl/kb oL J
L13:    dup2
L14:    lstore 8
L16:    invokestatic Method org/lwjgl/l method2052 (J)V
L19:    invokestatic Method org/lwjgl/opengl/Zd method5449 (Lorg/lwjgl/opengl/kb;)V
L22:    aload 6
L24:    iload 4
L26:    iload 5
L28:    iload_2
L29:    iload_3
L30:    iconst_1
L31:    dup
L32:    dup
L33:    pop2
L34:    invokestatic Method org/lwjgl/opengl/Zd method5429 (Ljava/nio/Buffer;IIIII)I
L37:    invokestatic Method org/lwjgl/l method2041 (Ljava/nio/IntBuffer;I)V
L40:    iload_0
L41:    iload_1
L42:    iload_2
L43:    iload_3
L44:    iload 4
L46:    iload 5
L48:    aload 6
L50:    invokestatic Method org/lwjgl/MemoryUtil method1884 (Ljava/nio/IntBuffer;)J
L53:    lload 8
L55:    invokestatic Method org/lwjgl/opengl/GL11 nglReadPixels (IIIIIIJJ)V
L58:    return
L59:    
    .end code
.end method

.method public static method3848 : (FF)V
    .code stack 4 locals 4
L0:     invokestatic Method org/lwjgl/opengl/GLContext method4611 ()Lorg/lwjgl/opengl/kb;
L3:     getfield Field org/lwjgl/opengl/kb ri J
L6:     dup2
L7:     lstore_2
L8:     invokestatic Method org/lwjgl/l method2052 (J)V
L11:    fload_0
L12:    fload_1
L13:    lload_2
L14:    invokestatic Method org/lwjgl/opengl/GL11 nglVertex2f (FFJ)V
L17:    return
L18:    
    .end code
.end method

.method static native nglGetLightiv : (IIJJ)V
.end method

.method static native nglPassThrough : (FJ)V
.end method

.method public static method3849 : (ILjava/nio/IntBuffer;)V
    .code stack 6 locals 5
L0:     invokestatic Method org/lwjgl/opengl/GLContext method4611 ()Lorg/lwjgl/opengl/kb;
L3:     astore_2
L4:     aload_1
L5:     aload_2
L6:     dup
L7:     getfield Field org/lwjgl/opengl/kb op J
L10:    dup2
L11:    lstore_3
L12:    invokestatic Method org/lwjgl/l method2052 (J)V
L15:    invokestatic Method org/lwjgl/opengl/Zd method5454 (Lorg/lwjgl/opengl/kb;)V
L18:    invokestatic Method org/lwjgl/l method2043 (Ljava/nio/IntBuffer;)V
L21:    getstatic Field org/lwjgl/LWJGLUtil CHECKS Z
L24:    ifeq L35
L27:    aload_2
L28:    invokestatic Method org/lwjgl/opengl/w method5768 (Lorg/lwjgl/opengl/kb;)Lorg/lwjgl/opengl/P;
L31:    aload_1
L32:    putfield Field org/lwjgl/opengl/P field4947 Ljava/nio/Buffer;
L35:    sipush 5124
L38:    iconst_1
L39:    dup
L40:    pop2
L41:    iload_0
L42:    aload_1
L43:    invokestatic Method org/lwjgl/MemoryUtil method1884 (Ljava/nio/IntBuffer;)J
L46:    lload_3
L47:    invokestatic Method org/lwjgl/opengl/GL11 nglNormalPointer (IIJJ)V
L50:    return
L51:    
        .attribute StackMap b'\x00\x01\x00\x23\x00\x04\x01\x07\x04\x5F\x07\x04\x21\x04\x00\x00'
    .end code
.end method

.method static native nglDepthMask : (ZJ)V
.end method

.method static native nglTexImage1DBO : (IIIIIIIJJ)V
.end method

.method public static method3850 : (II)F
    .code stack 6 locals 5
L0:     invokestatic Method org/lwjgl/opengl/GLContext method4611 ()Lorg/lwjgl/opengl/kb;
L3:     dup
L4:     getfield Field org/lwjgl/opengl/kb dh J
L7:     dup2
L8:     lstore_3
L9:     invokestatic Method org/lwjgl/l method2052 (J)V
L12:    invokestatic Method org/lwjgl/opengl/bB method5465 (Lorg/lwjgl/opengl/kb;)Ljava/nio/FloatBuffer;
L15:    astore_2
L16:    iload_0
L17:    iload_1
L18:    aload_2
L19:    invokestatic Method org/lwjgl/MemoryUtil method1878 (Ljava/nio/FloatBuffer;)J
L22:    lload_3
L23:    invokestatic Method org/lwjgl/opengl/GL11 nglGetTexParameterfv (IIJJ)V
L26:    aload_2
L27:    iconst_0
L28:    iconst_1
L29:    dup
L30:    pop2
L31:    invokevirtual Method java/nio/FloatBuffer get (I)F
L34:    freturn
L35:    
    .end code
.end method

.method public static method3851 : (II)I
    .code stack 6 locals 5
L0:     invokestatic Method org/lwjgl/opengl/GLContext method4611 ()Lorg/lwjgl/opengl/kb;
L3:     dup
L4:     getfield Field org/lwjgl/opengl/kb pK J
L7:     dup2
L8:     lstore_3
L9:     invokestatic Method org/lwjgl/l method2052 (J)V
L12:    invokestatic Method org/lwjgl/opengl/bB method5467 (Lorg/lwjgl/opengl/kb;)Ljava/nio/IntBuffer;
L15:    astore_2
L16:    iload_0
L17:    iload_1
L18:    aload_2
L19:    invokestatic Method org/lwjgl/MemoryUtil method1884 (Ljava/nio/IntBuffer;)J
L22:    lload_3
L23:    invokestatic Method org/lwjgl/opengl/GL11 nglGetTexParameteriv (IIJJ)V
L26:    aload_2
L27:    iconst_0
L28:    iconst_1
L29:    dup
L30:    pop2
L31:    invokevirtual Method java/nio/IntBuffer get (I)I
L34:    ireturn
L35:    
    .end code
.end method

.method static native nglNormalPointer : (IIJJ)V
.end method

.method static native nglPolygonStippleBO : (JJ)V
.end method

.method public static this : (I)V
    .code stack 4 locals 3
L0:     invokestatic Method org/lwjgl/opengl/GLContext method4611 ()Lorg/lwjgl/opengl/kb;
L3:     getfield Field org/lwjgl/opengl/kb zg J
L6:     dup2
L7:     lstore_1
L8:     invokestatic Method org/lwjgl/l method2052 (J)V
L11:    iload_0
L12:    lload_1
L13:    invokestatic Method org/lwjgl/opengl/GL11 nglLoadName (IJ)V
L16:    return
L17:    
    .end code
.end method

.method static native nglDrawElementsBO : (IIIJJ)V
.end method

.method public static method3852 : (IILjava/nio/DoubleBuffer;)V
    .code stack 6 locals 5
L0:     invokestatic Method org/lwjgl/opengl/GLContext method4611 ()Lorg/lwjgl/opengl/kb;
L3:     getfield Field org/lwjgl/opengl/kb Qo J
L6:     dup2
L7:     lstore_3
L8:     invokestatic Method org/lwjgl/l method2052 (J)V
L11:    iload_0
L12:    aload_2
L13:    iconst_4
L14:    iconst_1
L15:    dup
L16:    pop2
L17:    invokestatic Method org/lwjgl/l method2056 (Ljava/nio/DoubleBuffer;I)V
L20:    iload_1
L21:    aload_2
L22:    invokestatic Method org/lwjgl/MemoryUtil method1840 (Ljava/nio/DoubleBuffer;)J
L25:    lload_3
L26:    invokestatic Method org/lwjgl/opengl/GL11 nglTexGendv (IIJJ)V
L29:    return
L30:    
    .end code
.end method

.method private <init> : ()V
    .code stack 1 locals 1
L0:     aload_0
L1:     invokespecial Method java/lang/Object <init> ()V
L4:     return
L5:     
    .end code
.end method

.method public static method3853 : (IIIILjava/nio/ShortBuffer;)V
    .code stack 9 locals 8
L0:     invokestatic Method org/lwjgl/opengl/GLContext method4611 ()Lorg/lwjgl/opengl/kb;
L3:     astore 5
L5:     aload 4
L7:     aload 5
L9:     dup
L10:    getfield Field org/lwjgl/opengl/kb Ps J
L13:    dup2
L14:    lstore 6
L16:    invokestatic Method org/lwjgl/l method2052 (J)V
L19:    invokestatic Method org/lwjgl/opengl/Zd method5446 (Lorg/lwjgl/opengl/kb;)V
L22:    aload 4
L24:    iload_2
L25:    iload_3
L26:    iload_0
L27:    iload_1
L28:    iconst_1
L29:    dup
L30:    dup
L31:    pop2
L32:    invokestatic Method org/lwjgl/opengl/Zd method5429 (Ljava/nio/Buffer;IIIII)I
L35:    invokestatic Method org/lwjgl/l method2031 (Ljava/nio/ShortBuffer;I)V
L38:    iload_0
L39:    iload_1
L40:    iload_2
L41:    iload_3
L42:    aload 4
L44:    invokestatic Method org/lwjgl/MemoryUtil method1853 (Ljava/nio/ShortBuffer;)J
L47:    lload 6
L49:    invokestatic Method org/lwjgl/opengl/GL11 nglDrawPixels (IIIIJJ)V
L52:    return
L53:    
    .end code
.end method

.method static native nglRecti : (IIIIJ)V
.end method

.method static native nglGetTexParameterfv : (IIJJ)V
.end method

.method public static method3854 : (IIIIIILjava/nio/FloatBuffer;)V
    .code stack 10 locals 10
L0:     invokestatic Method org/lwjgl/opengl/GLContext method4611 ()Lorg/lwjgl/opengl/kb;
L3:     astore 7
L5:     aload 6
L7:     aload 7
L9:     dup
L10:    getfield Field org/lwjgl/opengl/kb Zi J
L13:    dup2
L14:    lstore 8
L16:    invokestatic Method org/lwjgl/l method2052 (J)V
L19:    invokestatic Method org/lwjgl/opengl/Zd method5446 (Lorg/lwjgl/opengl/kb;)V
L22:    aload 6
L24:    iload 4
L26:    iload 5
L28:    iload_3
L29:    iconst_1
L30:    dup
L31:    pop2
L32:    iconst_1
L33:    dup
L34:    dup_x1
L35:    dup
L36:    pop2
L37:    invokestatic Method org/lwjgl/opengl/Zd method5429 (Ljava/nio/Buffer;IIIII)I
L40:    invokestatic Method org/lwjgl/l method2044 (Ljava/nio/FloatBuffer;I)V
L43:    iload_0
L44:    iload_1
L45:    iload_2
L46:    iload_3
L47:    iload 4
L49:    iload 5
L51:    aload 6
L53:    invokestatic Method org/lwjgl/MemoryUtil method1878 (Ljava/nio/FloatBuffer;)J
L56:    lload 8
L58:    invokestatic Method org/lwjgl/opengl/GL11 nglTexSubImage1D (IIIIIIJJ)V
L61:    return
L62:    
    .end code
.end method

.method public static method3855 : (DDDD)V
    .code stack 10 locals 10
L0:     invokestatic Method org/lwjgl/opengl/GLContext method4611 ()Lorg/lwjgl/opengl/kb;
L3:     getfield Field org/lwjgl/opengl/kb FF J
L6:     dup2
L7:     lstore 8
L9:     invokestatic Method org/lwjgl/l method2052 (J)V
L12:    dload_0
L13:    dload_2
L14:    dload 4
L16:    dload 6
L18:    lload 8
L20:    invokestatic Method org/lwjgl/opengl/GL11 nglRasterPos4d (DDDDJ)V
L23:    return
L24:    
    .end code
.end method

.method static native nglCullFace : (IJ)V
.end method

.method public static method3856 : (IJ)V
    .code stack 5 locals 5
L0:     invokestatic Method org/lwjgl/opengl/GLContext method4611 ()Lorg/lwjgl/opengl/kb;
L3:     dup
L4:     getfield Field org/lwjgl/opengl/kb Vg J
L7:     dup2
L8:     lstore_3
L9:     invokestatic Method org/lwjgl/l method2052 (J)V
L12:    invokestatic Method org/lwjgl/opengl/Zd method5436 (Lorg/lwjgl/opengl/kb;)V
L15:    iload_0
L16:    lload_1
L17:    lload_3
L18:    invokestatic Method org/lwjgl/opengl/GL11 nglGetPixelMapfvBO (IJJ)V
L21:    return
L22:    
    .end code
.end method

.method public static method3857 : (I)V
    .code stack 4 locals 3
L0:     invokestatic Method org/lwjgl/opengl/GLContext method4611 ()Lorg/lwjgl/opengl/kb;
L3:     getfield Field org/lwjgl/opengl/kb vc J
L6:     dup2
L7:     lstore_1
L8:     invokestatic Method org/lwjgl/l method2052 (J)V
L11:    iload_0
L12:    lload_1
L13:    invokestatic Method org/lwjgl/opengl/GL11 nglLogicOp (IJ)V
L16:    return
L17:    
    .end code
.end method

.method public static method3858 : (IIIII)V
    .code stack 7 locals 7
L0:     invokestatic Method org/lwjgl/opengl/GLContext method4611 ()Lorg/lwjgl/opengl/kb;
L3:     getfield Field org/lwjgl/opengl/kb eO J
L6:     dup2
L7:     lstore 5
L9:     invokestatic Method org/lwjgl/l method2052 (J)V
L12:    iload_0
L13:    iload_1
L14:    iload_2
L15:    iload_3
L16:    iload 4
L18:    lload 5
L20:    invokestatic Method org/lwjgl/opengl/GL11 nglCopyPixels (IIIIIJ)V
L23:    return
L24:    
    .end code
.end method

.method static native nglClipPlane : (IJJ)V
.end method

.method static native nglMapGrid1f : (IFFJ)V
.end method

.method public static method3859 : (IIIIIIIILjava/nio/FloatBuffer;)V
    .code stack 12 locals 12
L0:     invokestatic Method org/lwjgl/opengl/GLContext method4611 ()Lorg/lwjgl/opengl/kb;
L3:     astore 9
L5:     aload 8
L7:     aload 9
L9:     dup
L10:    getfield Field org/lwjgl/opengl/kb kD J
L13:    dup2
L14:    lstore 10
L16:    invokestatic Method org/lwjgl/l method2052 (J)V
L19:    invokestatic Method org/lwjgl/opengl/Zd method5446 (Lorg/lwjgl/opengl/kb;)V
L22:    ifnull L41
L25:    aload 8
L27:    dup
L28:    iload 6
L30:    iload 7
L32:    iload_3
L33:    iload 4
L35:    invokestatic Method org/lwjgl/opengl/Zd method5453 (Ljava/nio/Buffer;IIII)I
L38:    invokestatic Method org/lwjgl/l method2044 (Ljava/nio/FloatBuffer;I)V
L41:    iload_0
L42:    iload_1
L43:    iload_2
L44:    iload_3
L45:    iload 4
L47:    iload 5
L49:    iload 6
L51:    iload 7
L53:    aload 8
L55:    invokestatic Method org/lwjgl/MemoryUtil method1852 (Ljava/nio/FloatBuffer;)J
L58:    lload 10
L60:    invokestatic Method org/lwjgl/opengl/GL11 nglTexImage2D (IIIIIIIIJJ)V
L63:    return
L64:    
        .attribute StackMap b'\x00\x01\x00\x29\x00\x0B\x01\x01\x01\x01\x01\x01\x01\x01\x07\x05\xFE\x07\x04\x21\x04\x00\x00'
    .end code
.end method

.method public static method3860 : (IILjava/nio/ShortBuffer;)V
    .code stack 6 locals 6
L0:     invokestatic Method org/lwjgl/opengl/GLContext method4611 ()Lorg/lwjgl/opengl/kb;
L3:     astore_3
L4:     aload_2
L5:     aload_3
L6:     dup
L7:     getfield Field org/lwjgl/opengl/kb MB J
L10:    dup2
L11:    lstore 4
L13:    invokestatic Method org/lwjgl/l method2052 (J)V
L16:    invokestatic Method org/lwjgl/opengl/Zd method5454 (Lorg/lwjgl/opengl/kb;)V
L19:    invokestatic Method org/lwjgl/l method2057 (Ljava/nio/ShortBuffer;)V
L22:    iload_0
L23:    iload_1
L24:    aload_2
L25:    invokestatic Method org/lwjgl/MemoryUtil method1853 (Ljava/nio/ShortBuffer;)J
L28:    lload 4
L30:    invokestatic Method org/lwjgl/opengl/GL11 nglInterleavedArrays (IIJJ)V
L33:    return
L34:    
    .end code
.end method

.method static native nglMapGrid2f : (IFFIFFJ)V
.end method

.method public static method3861 : (I)V
    .code stack 4 locals 3
L0:     invokestatic Method org/lwjgl/opengl/GLContext method4611 ()Lorg/lwjgl/opengl/kb;
L3:     getfield Field org/lwjgl/opengl/kb tR J
L6:     dup2
L7:     lstore_1
L8:     invokestatic Method org/lwjgl/l method2052 (J)V
L11:    iload_0
L12:    lload_1
L13:    invokestatic Method org/lwjgl/opengl/GL11 nglReadBuffer (IJ)V
L16:    return
L17:    
    .end code
.end method

.method public static method3862 : (IF)V
    .code stack 4 locals 4
L0:     invokestatic Method org/lwjgl/opengl/GLContext method4611 ()Lorg/lwjgl/opengl/kb;
L3:     getfield Field org/lwjgl/opengl/kb HR J
L6:     dup2
L7:     lstore_2
L8:     invokestatic Method org/lwjgl/l method2052 (J)V
L11:    iload_0
L12:    fload_1
L13:    lload_2
L14:    invokestatic Method org/lwjgl/opengl/GL11 nglPixelTransferf (IFJ)V
L17:    return
L18:    
    .end code
.end method

.method public static method3863 : (II)V
    .code stack 4 locals 4
L0:     invokestatic Method org/lwjgl/opengl/GLContext method4611 ()Lorg/lwjgl/opengl/kb;
L3:     getfield Field org/lwjgl/opengl/kb Fn J
L6:     dup2
L7:     lstore_2
L8:     invokestatic Method org/lwjgl/l method2052 (J)V
L11:    iload_0
L12:    iload_1
L13:    lload_2
L14:    invokestatic Method org/lwjgl/opengl/GL11 nglEvalPoint2 (IIJ)V
L17:    return
L18:    
    .end code
.end method

.method public static method3864 : (Ljava/nio/IntBuffer;Ljava/nio/FloatBuffer;)V
    .code stack 7 locals 4
L0:     invokestatic Method org/lwjgl/opengl/GLContext method4611 ()Lorg/lwjgl/opengl/kb;
L3:     getfield Field org/lwjgl/opengl/kb JH J
L6:     dup2
L7:     lstore_2
L8:     invokestatic Method org/lwjgl/l method2052 (J)V
L11:    aload_1
L12:    aload_0
L13:    dup
L14:    dup_x2
L15:    invokestatic Method org/lwjgl/l method2043 (Ljava/nio/IntBuffer;)V
L18:    invokevirtual Method java/nio/IntBuffer remaining ()I
L21:    invokestatic Method org/lwjgl/l method2044 (Ljava/nio/FloatBuffer;I)V
L24:    invokevirtual Method java/nio/IntBuffer remaining ()I
L27:    aload_0
L28:    invokestatic Method org/lwjgl/MemoryUtil method1884 (Ljava/nio/IntBuffer;)J
L31:    aload_1
L32:    invokestatic Method org/lwjgl/MemoryUtil method1878 (Ljava/nio/FloatBuffer;)J
L35:    lload_2
L36:    invokestatic Method org/lwjgl/opengl/GL11 nglPrioritizeTextures (IJJJ)V
L39:    return
L40:    
    .end code
.end method

.method static native nglStencilFunc : (IIIJ)V
.end method

.method public static method3865 : (IIII)V
    .code stack 6 locals 6
L0:     invokestatic Method org/lwjgl/opengl/GLContext method4611 ()Lorg/lwjgl/opengl/kb;
L3:     getfield Field org/lwjgl/opengl/kb gu J
L6:     dup2
L7:     lstore 4
L9:     invokestatic Method org/lwjgl/l method2052 (J)V
L12:    iload_0
L13:    iload_1
L14:    iload_2
L15:    iload_3
L16:    lload 4
L18:    invokestatic Method org/lwjgl/opengl/GL11 nglViewport (IIIIJ)V
L21:    return
L22:    
    .end code
.end method

.method public static method3866 : (IIIIIILjava/nio/DoubleBuffer;)V
    .code stack 10 locals 10
L0:     invokestatic Method org/lwjgl/opengl/GLContext method4611 ()Lorg/lwjgl/opengl/kb;
L3:     astore 7
L5:     aload 6
L7:     aload 7
L9:     dup
L10:    getfield Field org/lwjgl/opengl/kb oL J
L13:    dup2
L14:    lstore 8
L16:    invokestatic Method org/lwjgl/l method2052 (J)V
L19:    invokestatic Method org/lwjgl/opengl/Zd method5449 (Lorg/lwjgl/opengl/kb;)V
L22:    aload 6
L24:    iload 4
L26:    iload 5
L28:    iload_2
L29:    iload_3
L30:    iconst_1
L31:    dup
L32:    dup
L33:    pop2
L34:    invokestatic Method org/lwjgl/opengl/Zd method5429 (Ljava/nio/Buffer;IIIII)I
L37:    invokestatic Method org/lwjgl/l method2056 (Ljava/nio/DoubleBuffer;I)V
L40:    iload_0
L41:    iload_1
L42:    iload_2
L43:    iload_3
L44:    iload 4
L46:    iload 5
L48:    aload 6
L50:    invokestatic Method org/lwjgl/MemoryUtil method1840 (Ljava/nio/DoubleBuffer;)J
L53:    lload 8
L55:    invokestatic Method org/lwjgl/opengl/GL11 nglReadPixels (IIIIIIJJ)V
L58:    return
L59:    
    .end code
.end method

.method static native nglMap2d : (IDDIIDDIIJJ)V
.end method

.method static native nglGetTexEnviv : (IIJJ)V
.end method

.method public static method3867 : (I)Ljava/lang/String;
    .code stack 4 locals 3
L0:     invokestatic Method org/lwjgl/opengl/GLContext method4611 ()Lorg/lwjgl/opengl/kb;
L3:     getfield Field org/lwjgl/opengl/kb up J
L6:     dup2
L7:     lstore_1
L8:     invokestatic Method org/lwjgl/l method2052 (J)V
L11:    iload_0
L12:    lload_1
L13:    invokestatic Method org/lwjgl/opengl/GL11 nglGetString (IJ)Ljava/lang/String;
L16:    areturn
L17:    
    .end code
.end method

.method static native nglClearDepth : (DJ)V
.end method

.method public static method3868 : (I)V
    .code stack 5 locals 4
L0:     invokestatic Method org/lwjgl/opengl/GLContext method4611 ()Lorg/lwjgl/opengl/kb;
L3:     dup
L4:     astore_1
L5:     getfield Field org/lwjgl/opengl/kb yG J
L8:     dup2
L9:     lstore_2
L10:    invokestatic Method org/lwjgl/l method2052 (J)V
L13:    iconst_1
L14:    dup
L15:    dup
L16:    pop2
L17:    aload_1
L18:    iload_0
L19:    invokestatic Method org/lwjgl/opengl/bB method5479 (Lorg/lwjgl/opengl/kb;I)J
L22:    lload_2
L23:    invokestatic Method org/lwjgl/opengl/GL11 nglDeleteTextures (IJJ)V
L26:    return
L27:    
    .end code
.end method

.method public static method3869 : (Ljava/nio/DoubleBuffer;)V
    .code stack 5 locals 3
L0:     invokestatic Method org/lwjgl/opengl/GLContext method4611 ()Lorg/lwjgl/opengl/kb;
L3:     getfield Field org/lwjgl/opengl/kb CQ J
L6:     dup2
L7:     lstore_1
L8:     invokestatic Method org/lwjgl/l method2052 (J)V
L11:    aload_0
L12:    dup
L13:    bipush 16
L15:    iconst_1
L16:    dup
L17:    pop2
L18:    invokestatic Method org/lwjgl/l method2056 (Ljava/nio/DoubleBuffer;I)V
L21:    invokestatic Method org/lwjgl/MemoryUtil method1840 (Ljava/nio/DoubleBuffer;)J
L24:    lload_1
L25:    invokestatic Method org/lwjgl/opengl/GL11 nglLoadMatrixd (JJ)V
L28:    return
L29:    
    .end code
.end method

.method public static method3870 : (DDDD)V
    .code stack 10 locals 10
L0:     invokestatic Method org/lwjgl/opengl/GLContext method4611 ()Lorg/lwjgl/opengl/kb;
L3:     getfield Field org/lwjgl/opengl/kb I J
L6:     dup2
L7:     lstore 8
L9:     invokestatic Method org/lwjgl/l method2052 (J)V
L12:    dload_0
L13:    dload_2
L14:    dload 4
L16:    dload 6
L18:    lload 8
L20:    invokestatic Method org/lwjgl/opengl/GL11 nglRectd (DDDDJ)V
L23:    return
L24:    
    .end code
.end method

.method public static method3871 : (IIIIIIIIJ)V
    .code stack 12 locals 12
L0:     invokestatic Method org/lwjgl/opengl/GLContext method4611 ()Lorg/lwjgl/opengl/kb;
L3:     dup
L4:     getfield Field org/lwjgl/opengl/kb kD J
L7:     dup2
L8:     lstore 10
L10:    invokestatic Method org/lwjgl/l method2052 (J)V
L13:    invokestatic Method org/lwjgl/opengl/Zd method5428 (Lorg/lwjgl/opengl/kb;)V
L16:    iload_0
L17:    iload_1
L18:    iload_2
L19:    iload_3
L20:    iload 4
L22:    iload 5
L24:    iload 6
L26:    iload 7
L28:    lload 8
L30:    lload 10
L32:    invokestatic Method org/lwjgl/opengl/GL11 nglTexImage2DBO (IIIIIIIIJJ)V
L35:    return
L36:    
    .end code
.end method

.method public static method3872 : (DD)V
    .code stack 6 locals 6
L0:     invokestatic Method org/lwjgl/opengl/GLContext method4611 ()Lorg/lwjgl/opengl/kb;
L3:     getfield Field org/lwjgl/opengl/kb vT J
L6:     dup2
L7:     lstore 4
L9:     invokestatic Method org/lwjgl/l method2052 (J)V
L12:    dload_0
L13:    dload_2
L14:    lload 4
L16:    invokestatic Method org/lwjgl/opengl/GL11 nglVertex2d (DDJ)V
L19:    return
L20:    
    .end code
.end method

.method static native nglTexSubImage2D : (IIIIIIIIJJ)V
.end method

.method static native nglTexCoord1d : (DJ)V
.end method

.method public static method3873 : (IILjava/nio/FloatBuffer;)V
    .code stack 7 locals 6
L0:     invokestatic Method org/lwjgl/opengl/GLContext method4611 ()Lorg/lwjgl/opengl/kb;
L3:     astore_3
L4:     aload_2
L5:     aload_3
L6:     dup
L7:     getfield Field org/lwjgl/opengl/kb rt J
L10:    dup2
L11:    lstore 4
L13:    invokestatic Method org/lwjgl/l method2052 (J)V
L16:    invokestatic Method org/lwjgl/opengl/Zd method5454 (Lorg/lwjgl/opengl/kb;)V
L19:    invokestatic Method org/lwjgl/l method2048 (Ljava/nio/FloatBuffer;)V
L22:    getstatic Field org/lwjgl/LWJGLUtil CHECKS Z
L25:    ifeq L44
L28:    aload_3
L29:    invokestatic Method org/lwjgl/opengl/w method5768 (Lorg/lwjgl/opengl/kb;)Lorg/lwjgl/opengl/P;
L32:    getfield Field org/lwjgl/opengl/P field4953 [Ljava/nio/Buffer;
L35:    aload_3
L36:    invokestatic Method org/lwjgl/opengl/w method5768 (Lorg/lwjgl/opengl/kb;)Lorg/lwjgl/opengl/P;
L39:    getfield Field org/lwjgl/opengl/P this I
L42:    aload_2
L43:    aastore
L44:    iload_0
L45:    sipush 5126
L48:    iconst_1
L49:    dup
L50:    pop2
L51:    iload_1
L52:    aload_2
L53:    invokestatic Method org/lwjgl/MemoryUtil method1878 (Ljava/nio/FloatBuffer;)J
L56:    lload 4
L58:    invokestatic Method org/lwjgl/opengl/GL11 nglTexCoordPointer (IIIJJ)V
L61:    return
L62:    
        .attribute StackMap b'\x00\x01\x00\x2C\x00\x05\x01\x01\x07\x05\xFE\x07\x04\x21\x04\x00\x00'
    .end code
.end method

.method public static method3874 : (ILjava/nio/DoubleBuffer;)V
    .code stack 5 locals 4
L0:     invokestatic Method org/lwjgl/opengl/GLContext method4611 ()Lorg/lwjgl/opengl/kb;
L3:     getfield Field org/lwjgl/opengl/kb bE J
L6:     dup2
L7:     lstore_2
L8:     invokestatic Method org/lwjgl/l method2052 (J)V
L11:    iload_0
L12:    aload_1
L13:    iconst_4
L14:    iconst_1
L15:    dup
L16:    pop2
L17:    invokestatic Method org/lwjgl/l method2056 (Ljava/nio/DoubleBuffer;I)V
L20:    aload_1
L21:    invokestatic Method org/lwjgl/MemoryUtil method1840 (Ljava/nio/DoubleBuffer;)J
L24:    lload_2
L25:    invokestatic Method org/lwjgl/opengl/GL11 nglClipPlane (IJJ)V
L28:    return
L29:    
    .end code
.end method

.method static native nglLoadName : (IJ)V
.end method

.method public static method3875 : (IILjava/nio/FloatBuffer;)V
    .code stack 7 locals 6
L0:     invokestatic Method org/lwjgl/opengl/GLContext method4611 ()Lorg/lwjgl/opengl/kb;
L3:     astore_3
L4:     aload_2
L5:     aload_3
L6:     dup
L7:     getfield Field org/lwjgl/opengl/kb De J
L10:    dup2
L11:    lstore 4
L13:    invokestatic Method org/lwjgl/l method2052 (J)V
L16:    invokestatic Method org/lwjgl/opengl/Zd method5454 (Lorg/lwjgl/opengl/kb;)V
L19:    invokestatic Method org/lwjgl/l method2048 (Ljava/nio/FloatBuffer;)V
L22:    getstatic Field org/lwjgl/LWJGLUtil CHECKS Z
L25:    ifeq L36
L28:    aload_3
L29:    invokestatic Method org/lwjgl/opengl/w method5768 (Lorg/lwjgl/opengl/kb;)Lorg/lwjgl/opengl/P;
L32:    aload_2
L33:    putfield Field org/lwjgl/opengl/P field4949 Ljava/nio/Buffer;
L36:    iload_0
L37:    sipush 5126
L40:    iconst_1
L41:    dup
L42:    pop2
L43:    iload_1
L44:    aload_2
L45:    invokestatic Method org/lwjgl/MemoryUtil method1878 (Ljava/nio/FloatBuffer;)J
L48:    lload 4
L50:    invokestatic Method org/lwjgl/opengl/GL11 nglColorPointer (IIIJJ)V
L53:    return
L54:    
        .attribute StackMap b'\x00\x01\x00\x24\x00\x05\x01\x01\x07\x05\xFE\x07\x04\x21\x04\x00\x00'
    .end code
.end method

.method static native nglLightfv : (IIJJ)V
.end method

.method static native nglGetTexGeniv : (IIJJ)V
.end method

.method static native nglGetPixelMapfvBO : (IJJ)V
.end method

.method static native nglRasterPos2i : (IIJ)V
.end method

.method public static method3876 : (IIIJ)V
    .code stack 7 locals 7
L0:     invokestatic Method org/lwjgl/opengl/GLContext method4611 ()Lorg/lwjgl/opengl/kb;
L3:     dup
L4:     getfield Field org/lwjgl/opengl/kb VM J
L7:     dup2
L8:     lstore 5
L10:    invokestatic Method org/lwjgl/l method2052 (J)V
L13:    invokestatic Method org/lwjgl/opengl/Zd method5441 (Lorg/lwjgl/opengl/kb;)V
L16:    iload_0
L17:    iload_1
L18:    iload_2
L19:    lload_3
L20:    lload 5
L22:    invokestatic Method org/lwjgl/opengl/GL11 nglVertexPointerBO (IIIJJ)V
L25:    return
L26:    
    .end code
.end method

.method public static method3877 : (III)V
    .code stack 5 locals 5
L0:     invokestatic Method org/lwjgl/opengl/GLContext method4611 ()Lorg/lwjgl/opengl/kb;
L3:     getfield Field org/lwjgl/opengl/kb sF J
L6:     dup2
L7:     lstore_3
L8:     invokestatic Method org/lwjgl/l method2052 (J)V
L11:    iload_0
L12:    iload_1
L13:    iload_2
L14:    lload_3
L15:    invokestatic Method org/lwjgl/opengl/GL11 nglRasterPos3i (IIIJ)V
L18:    return
L19:    
    .end code
.end method

.method public static method3878 : (ILjava/nio/ByteBuffer;)V
    .code stack 6 locals 5
L0:     invokestatic Method org/lwjgl/opengl/GLContext method4611 ()Lorg/lwjgl/opengl/kb;
L3:     astore_2
L4:     aload_1
L5:     aload_2
L6:     dup
L7:     getfield Field org/lwjgl/opengl/kb op J
L10:    dup2
L11:    lstore_3
L12:    invokestatic Method org/lwjgl/l method2052 (J)V
L15:    invokestatic Method org/lwjgl/opengl/Zd method5454 (Lorg/lwjgl/opengl/kb;)V
L18:    invokestatic Method org/lwjgl/l method2034 (Ljava/nio/ByteBuffer;)V
L21:    getstatic Field org/lwjgl/LWJGLUtil CHECKS Z
L24:    ifeq L35
L27:    aload_2
L28:    invokestatic Method org/lwjgl/opengl/w method5768 (Lorg/lwjgl/opengl/kb;)Lorg/lwjgl/opengl/P;
L31:    aload_1
L32:    putfield Field org/lwjgl/opengl/P field4947 Ljava/nio/Buffer;
L35:    sipush 5120
L38:    iconst_1
L39:    dup
L40:    pop2
L41:    iload_0
L42:    aload_1
L43:    invokestatic Method org/lwjgl/MemoryUtil method1873 (Ljava/nio/ByteBuffer;)J
L46:    lload_3
L47:    invokestatic Method org/lwjgl/opengl/GL11 nglNormalPointer (IIJJ)V
L50:    return
L51:    
        .attribute StackMap b'\x00\x01\x00\x23\x00\x04\x01\x07\x04\xCB\x07\x04\x21\x04\x00\x00'
    .end code
.end method

.method public static method3879 : (IIIIIIJ)V
    .code stack 10 locals 10
L0:     invokestatic Method org/lwjgl/opengl/GLContext method4611 ()Lorg/lwjgl/opengl/kb;
L3:     dup
L4:     getfield Field org/lwjgl/opengl/kb oL J
L7:     dup2
L8:     lstore 8
L10:    invokestatic Method org/lwjgl/l method2052 (J)V
L13:    invokestatic Method org/lwjgl/opengl/Zd method5436 (Lorg/lwjgl/opengl/kb;)V
L16:    iload_0
L17:    iload_1
L18:    iload_2
L19:    iload_3
L20:    iload 4
L22:    iload 5
L24:    lload 6
L26:    lload 8
L28:    invokestatic Method org/lwjgl/opengl/GL11 nglReadPixelsBO (IIIIIIJJ)V
L31:    return
L32:    
    .end code
.end method

.method public static method3880 : (ILjava/nio/ShortBuffer;)V
    .code stack 7 locals 5
L0:     invokestatic Method org/lwjgl/opengl/GLContext method4611 ()Lorg/lwjgl/opengl/kb;
L3:     astore_2
L4:     aload_1
L5:     aload_2
L6:     dup
L7:     getfield Field org/lwjgl/opengl/kb field5431 J
L10:    dup2
L11:    lstore_3
L12:    invokestatic Method org/lwjgl/l method2052 (J)V
L15:    invokestatic Method org/lwjgl/opengl/Zd method5435 (Lorg/lwjgl/opengl/kb;)V
L18:    invokestatic Method org/lwjgl/l method2057 (Ljava/nio/ShortBuffer;)V
L21:    iload_0
L22:    aload_1
L23:    invokevirtual Method java/nio/ShortBuffer remaining ()I
L26:    sipush 5123
L29:    iconst_1
L30:    dup
L31:    pop2
L32:    aload_1
L33:    invokestatic Method org/lwjgl/MemoryUtil method1853 (Ljava/nio/ShortBuffer;)J
L36:    lload_3
L37:    invokestatic Method org/lwjgl/opengl/GL11 nglDrawElements (IIIJJ)V
L40:    return
L41:    
    .end code
.end method

.method static native nglFeedbackBuffer : (IIJJ)V
.end method

.method public static method3881 : (ILjava/nio/ByteBuffer;)V
    .code stack 5 locals 4
L0:     invokestatic Method org/lwjgl/opengl/GLContext method4611 ()Lorg/lwjgl/opengl/kb;
L3:     getfield Field org/lwjgl/opengl/kb mp J
L6:     dup2
L7:     lstore_2
L8:     invokestatic Method org/lwjgl/l method2052 (J)V
L11:    iload_0
L12:    aload_1
L13:    bipush 16
L15:    iconst_1
L16:    dup
L17:    pop2
L18:    invokestatic Method org/lwjgl/l method2054 (Ljava/nio/ByteBuffer;I)V
L21:    aload_1
L22:    invokestatic Method org/lwjgl/MemoryUtil method1873 (Ljava/nio/ByteBuffer;)J
L25:    lload_2
L26:    invokestatic Method org/lwjgl/opengl/GL11 nglGetBooleanv (IJJ)V
L29:    return
L30:    
    .end code
.end method

.method public static method3882 : (I)V
    .code stack 4 locals 3
L0:     invokestatic Method org/lwjgl/opengl/GLContext method4611 ()Lorg/lwjgl/opengl/kb;
L3:     getfield Field org/lwjgl/opengl/kb de J
L6:     dup2
L7:     lstore_1
L8:     invokestatic Method org/lwjgl/l method2052 (J)V
L11:    iload_0
L12:    lload_1
L13:    invokestatic Method org/lwjgl/opengl/GL11 nglDisable (IJ)V
L16:    return
L17:    
    .end code
.end method

.method static native nglLineStipple : (ISJ)V
.end method

.method static native nglGetPolygonStippleBO : (JJ)V
.end method

.method public static method3883 : (IDDIILjava/nio/DoubleBuffer;)V
    .code stack 11 locals 10
L0:     invokestatic Method org/lwjgl/opengl/GLContext method4611 ()Lorg/lwjgl/opengl/kb;
L3:     getfield Field org/lwjgl/opengl/kb Io J
L6:     dup2
L7:     lstore 8
L9:     invokestatic Method org/lwjgl/l method2052 (J)V
L12:    iload_0
L13:    aload 7
L15:    invokestatic Method org/lwjgl/l method2036 (Ljava/nio/DoubleBuffer;)V
L18:    dload_1
L19:    dload_3
L20:    iload 5
L22:    iload 6
L24:    aload 7
L26:    invokestatic Method org/lwjgl/MemoryUtil method1840 (Ljava/nio/DoubleBuffer;)J
L29:    lload 8
L31:    invokestatic Method org/lwjgl/opengl/GL11 nglMap1d (IDDIIJJ)V
L34:    return
L35:    
    .end code
.end method

.method static native nglAreTexturesResident : (IJJJ)Z
.end method

.method public static method3884 : (II)V
    .code stack 4 locals 4
L0:     invokestatic Method org/lwjgl/opengl/GLContext method4611 ()Lorg/lwjgl/opengl/kb;
L3:     getfield Field org/lwjgl/opengl/kb PA J
L6:     dup2
L7:     lstore_2
L8:     invokestatic Method org/lwjgl/l method2052 (J)V
L11:    iload_0
L12:    iload_1
L13:    lload_2
L14:    invokestatic Method org/lwjgl/opengl/GL11 nglFogi (IIJ)V
L17:    return
L18:    
    .end code
.end method

.method public static method3885 : (IJ)Ljava/nio/ByteBuffer;
    .code stack 5 locals 6
L0:     invokestatic Method org/lwjgl/opengl/GLContext method4611 ()Lorg/lwjgl/opengl/kb;
L3:     getfield Field org/lwjgl/opengl/kb vE J
L6:     dup2
L7:     lstore 4
L9:     invokestatic Method org/lwjgl/l method2052 (J)V
L12:    iload_0
L13:    lload_1
L14:    lload 4
L16:    invokestatic Method org/lwjgl/opengl/GL11 nglGetPointerv (IJJ)Ljava/nio/ByteBuffer;
L19:    astore_3
L20:    getstatic Field org/lwjgl/LWJGLUtil CHECKS Z
L23:    ifeq L33
L26:    aload_3
L27:    ifnonnull L33
L30:    aconst_null
L31:    areturn
L32:    athrow
L33:    aload_3
L34:    invokestatic Method java/nio/ByteOrder nativeOrder ()Ljava/nio/ByteOrder;
L37:    invokevirtual Method java/nio/ByteBuffer order (Ljava/nio/ByteOrder;)Ljava/nio/ByteBuffer;
L40:    areturn
L41:    
        .attribute StackMap b'\x00\x02\x00\x20\x00\x00\x00\x01\x07\x05\x3C\x00\x21\x00\x04\x01\x04\x07\x04\xCB\x04\x00\x00'
    .end code
.end method

.method static native nglPrioritizeTextures : (IJJJ)V
.end method

.method public static method3886 : (Ljava/nio/IntBuffer;)V
    .code stack 5 locals 3
L0:     invokestatic Method org/lwjgl/opengl/GLContext method4611 ()Lorg/lwjgl/opengl/kb;
L3:     getfield Field org/lwjgl/opengl/kb field5414 J
L6:     dup2
L7:     lstore_1
L8:     invokestatic Method org/lwjgl/l method2052 (J)V
L11:    aload_0
L12:    dup
L13:    invokestatic Method org/lwjgl/l method2043 (Ljava/nio/IntBuffer;)V
L16:    invokevirtual Method java/nio/IntBuffer remaining ()I
L19:    aload_0
L20:    invokestatic Method org/lwjgl/MemoryUtil method1884 (Ljava/nio/IntBuffer;)J
L23:    lload_1
L24:    invokestatic Method org/lwjgl/opengl/GL11 nglGenTextures (IJJ)V
L27:    return
L28:    
    .end code
.end method

.method static native nglCopyPixels : (IIIIIJ)V
.end method

.method public static method3887 : (IIJ)V
    .code stack 6 locals 6
L0:     invokestatic Method org/lwjgl/opengl/GLContext method4611 ()Lorg/lwjgl/opengl/kb;
L3:     dup
L4:     getfield Field org/lwjgl/opengl/kb op J
L7:     dup2
L8:     lstore 4
L10:    invokestatic Method org/lwjgl/l method2052 (J)V
L13:    invokestatic Method org/lwjgl/opengl/Zd method5441 (Lorg/lwjgl/opengl/kb;)V
L16:    iload_0
L17:    iload_1
L18:    lload_2
L19:    lload 4
L21:    invokestatic Method org/lwjgl/opengl/GL11 nglNormalPointerBO (IIJJ)V
L24:    return
L25:    
    .end code
.end method

.method public static method3888 : (FFFF)V
    .code stack 6 locals 6
L0:     invokestatic Method org/lwjgl/opengl/GLContext method4611 ()Lorg/lwjgl/opengl/kb;
L3:     getfield Field org/lwjgl/opengl/kb UR J
L6:     dup2
L7:     lstore 4
L9:     invokestatic Method org/lwjgl/l method2052 (J)V
L12:    fload_0
L13:    fload_1
L14:    fload_2
L15:    fload_3
L16:    lload 4
L18:    invokestatic Method org/lwjgl/opengl/GL11 nglColor4f (FFFFJ)V
L21:    return
L22:    
    .end code
.end method

.method public static method3889 : (III)V
    .code stack 5 locals 5
L0:     invokestatic Method org/lwjgl/opengl/GLContext method4611 ()Lorg/lwjgl/opengl/kb;
L3:     getfield Field org/lwjgl/opengl/kb Kt J
L6:     dup2
L7:     lstore_3
L8:     invokestatic Method org/lwjgl/l method2052 (J)V
L11:    iload_0
L12:    iload_1
L13:    iload_2
L14:    lload_3
L15:    invokestatic Method org/lwjgl/opengl/GL11 nglEvalMesh1 (IIIJ)V
L18:    return
L19:    
    .end code
.end method

.method static native nglVertex4d : (DDDDJ)V
.end method

.method public static method3890 : (III)F
    .code stack 7 locals 6
L0:     invokestatic Method org/lwjgl/opengl/GLContext method4611 ()Lorg/lwjgl/opengl/kb;
L3:     dup
L4:     getfield Field org/lwjgl/opengl/kb HB J
L7:     dup2
L8:     lstore 4
L10:    invokestatic Method org/lwjgl/l method2052 (J)V
L13:    invokestatic Method org/lwjgl/opengl/bB method5465 (Lorg/lwjgl/opengl/kb;)Ljava/nio/FloatBuffer;
L16:    astore_3
L17:    iload_0
L18:    iload_1
L19:    iload_2
L20:    aload_3
L21:    invokestatic Method org/lwjgl/MemoryUtil method1878 (Ljava/nio/FloatBuffer;)J
L24:    lload 4
L26:    invokestatic Method org/lwjgl/opengl/GL11 nglGetTexLevelParameterfv (IIIJJ)V
L29:    aload_3
L30:    iconst_0
L31:    iconst_1
L32:    dup
L33:    pop2
L34:    invokevirtual Method java/nio/FloatBuffer get (I)F
L37:    freturn
L38:    
    .end code
.end method

.method static native nglTexCoord2f : (FFJ)V
.end method

.method public static method3891 : (II)V
    .code stack 4 locals 4
L0:     invokestatic Method org/lwjgl/opengl/GLContext method4611 ()Lorg/lwjgl/opengl/kb;
L3:     getfield Field org/lwjgl/opengl/kb iS J
L6:     dup2
L7:     lstore_2
L8:     invokestatic Method org/lwjgl/l method2052 (J)V
L11:    iload_0
L12:    iload_1
L13:    lload_2
L14:    invokestatic Method org/lwjgl/opengl/GL11 nglNewList (IIJ)V
L17:    return
L18:    
    .end code
.end method

.method static native nglRasterPos2d : (DDJ)V
.end method

.method public static method3892 : (IIIIII)V
    .code stack 8 locals 8
L0:     invokestatic Method org/lwjgl/opengl/GLContext method4611 ()Lorg/lwjgl/opengl/kb;
L3:     getfield Field org/lwjgl/opengl/kb XG J
L6:     dup2
L7:     lstore 6
L9:     invokestatic Method org/lwjgl/l method2052 (J)V
L12:    iload_0
L13:    iload_1
L14:    iload_2
L15:    iload_3
L16:    iload 4
L18:    iload 5
L20:    lload 6
L22:    invokestatic Method org/lwjgl/opengl/GL11 nglCopyTexSubImage1D (IIIIIIJ)V
L25:    return
L26:    
    .end code
.end method

.method static native nglColor4ub : (BBBBJ)V
.end method

.method static native nglTexImage1D : (IIIIIIIJJ)V
.end method

.method public static method3893 : (IJ)V
    .code stack 5 locals 5
L0:     invokestatic Method org/lwjgl/opengl/GLContext method4611 ()Lorg/lwjgl/opengl/kb;
L3:     dup
L4:     getfield Field org/lwjgl/opengl/kb cs J
L7:     dup2
L8:     lstore_3
L9:     invokestatic Method org/lwjgl/l method2052 (J)V
L12:    invokestatic Method org/lwjgl/opengl/Zd method5441 (Lorg/lwjgl/opengl/kb;)V
L15:    iload_0
L16:    lload_1
L17:    lload_3
L18:    invokestatic Method org/lwjgl/opengl/GL11 nglEdgeFlagPointerBO (IJJ)V
L21:    return
L22:    
    .end code
.end method

.method static native nglFogfv : (IJJ)V
.end method

.method public static method3894 : (Ljava/nio/DoubleBuffer;)V
    .code stack 5 locals 3
L0:     invokestatic Method org/lwjgl/opengl/GLContext method4611 ()Lorg/lwjgl/opengl/kb;
L3:     getfield Field org/lwjgl/opengl/kb qm J
L6:     dup2
L7:     lstore_1
L8:     invokestatic Method org/lwjgl/l method2052 (J)V
L11:    aload_0
L12:    dup
L13:    bipush 16
L15:    iconst_1
L16:    dup
L17:    pop2
L18:    invokestatic Method org/lwjgl/l method2056 (Ljava/nio/DoubleBuffer;I)V
L21:    invokestatic Method org/lwjgl/MemoryUtil method1840 (Ljava/nio/DoubleBuffer;)J
L24:    lload_1
L25:    invokestatic Method org/lwjgl/opengl/GL11 nglMultMatrixd (JJ)V
L28:    return
L29:    
    .end code
.end method

.method static native nglClearColor : (FFFFJ)V
.end method

.method public static method3895 : (J)V
    .code stack 5 locals 4
L0:     invokestatic Method org/lwjgl/opengl/GLContext method4611 ()Lorg/lwjgl/opengl/kb;
L3:     dup
L4:     getfield Field org/lwjgl/opengl/kb mj J
L7:     dup2
L8:     lstore_2
L9:     invokestatic Method org/lwjgl/l method2052 (J)V
L12:    invokestatic Method org/lwjgl/opengl/Zd method5428 (Lorg/lwjgl/opengl/kb;)V
L15:    lload_0
L16:    lload_2
L17:    invokestatic Method org/lwjgl/opengl/GL11 nglPolygonStippleBO (JJ)V
L20:    return
L21:    
    .end code
.end method

.method public static method3896 : (ILjava/nio/ByteBuffer;)V
    .code stack 6 locals 5
L0:     invokestatic Method org/lwjgl/opengl/GLContext method4611 ()Lorg/lwjgl/opengl/kb;
L3:     astore_2
L4:     aload_1
L5:     aload_2
L6:     dup
L7:     getfield Field org/lwjgl/opengl/kb cs J
L10:    dup2
L11:    lstore_3
L12:    invokestatic Method org/lwjgl/l method2052 (J)V
L15:    invokestatic Method org/lwjgl/opengl/Zd method5454 (Lorg/lwjgl/opengl/kb;)V
L18:    invokestatic Method org/lwjgl/l method2034 (Ljava/nio/ByteBuffer;)V
L21:    getstatic Field org/lwjgl/LWJGLUtil CHECKS Z
L24:    ifeq L35
L27:    aload_2
L28:    invokestatic Method org/lwjgl/opengl/w method5768 (Lorg/lwjgl/opengl/kb;)Lorg/lwjgl/opengl/P;
L31:    aload_1
L32:    putfield Field org/lwjgl/opengl/P try Ljava/nio/Buffer;
L35:    iload_0
L36:    aload_1
L37:    invokestatic Method org/lwjgl/MemoryUtil method1873 (Ljava/nio/ByteBuffer;)J
L40:    lload_3
L41:    invokestatic Method org/lwjgl/opengl/GL11 nglEdgeFlagPointer (IJJ)V
L44:    return
L45:    
        .attribute StackMap b'\x00\x01\x00\x23\x00\x04\x01\x07\x04\xCB\x07\x04\x21\x04\x00\x00'
    .end code
.end method

.method static native nglClear : (IJ)V
.end method

.method public static method3897 : (I)V
    .code stack 4 locals 3
L0:     invokestatic Method org/lwjgl/opengl/GLContext method4611 ()Lorg/lwjgl/opengl/kb;
L3:     getfield Field org/lwjgl/opengl/kb Sb J
L6:     dup2
L7:     lstore_1
L8:     invokestatic Method org/lwjgl/l method2052 (J)V
L11:    iload_0
L12:    lload_1
L13:    invokestatic Method org/lwjgl/opengl/GL11 nglDisableClientState (IJ)V
L16:    return
L17:    
    .end code
.end method

.method public static method3898 : (DDDD)V
    .code stack 10 locals 10
L0:     invokestatic Method org/lwjgl/opengl/GLContext method4611 ()Lorg/lwjgl/opengl/kb;
L3:     getfield Field org/lwjgl/opengl/kb Zb J
L6:     dup2
L7:     lstore 8
L9:     invokestatic Method org/lwjgl/l method2052 (J)V
L12:    dload_0
L13:    dload_2
L14:    dload 4
L16:    dload 6
L18:    lload 8
L20:    invokestatic Method org/lwjgl/opengl/GL11 nglColor4d (DDDDJ)V
L23:    return
L24:    
    .end code
.end method

.method public static method3899 : (IIIIIIILjava/nio/ShortBuffer;)V
    .code stack 11 locals 11
L0:     invokestatic Method org/lwjgl/opengl/GLContext method4611 ()Lorg/lwjgl/opengl/kb;
L3:     astore 8
L5:     aload 7
L7:     aload 8
L9:     dup
L10:    getfield Field org/lwjgl/opengl/kb hM J
L13:    dup2
L14:    lstore 9
L16:    invokestatic Method org/lwjgl/l method2052 (J)V
L19:    invokestatic Method org/lwjgl/opengl/Zd method5446 (Lorg/lwjgl/opengl/kb;)V
L22:    ifnull L39
L25:    aload 7
L27:    dup
L28:    iload 5
L30:    iload 6
L32:    iload_3
L33:    invokestatic Method org/lwjgl/opengl/Zd method5456 (Ljava/nio/Buffer;III)I
L36:    invokestatic Method org/lwjgl/l method2031 (Ljava/nio/ShortBuffer;I)V
L39:    iload_0
L40:    iload_1
L41:    iload_2
L42:    iload_3
L43:    iload 4
L45:    iload 5
L47:    iload 6
L49:    aload 7
L51:    invokestatic Method org/lwjgl/MemoryUtil method1875 (Ljava/nio/ShortBuffer;)J
L54:    lload 9
L56:    invokestatic Method org/lwjgl/opengl/GL11 nglTexImage1D (IIIIIIIJJ)V
L59:    return
L60:    
        .attribute StackMap b'\x00\x01\x00\x27\x00\x0A\x01\x01\x01\x01\x01\x01\x01\x07\x05\x65\x07\x04\x21\x04\x00\x00'
    .end code
.end method

.method static native nglGetTexParameteriv : (IIJJ)V
.end method

.method public static method3900 : (ILjava/nio/ByteBuffer;)V
    .code stack 7 locals 5
L0:     invokestatic Method org/lwjgl/opengl/GLContext method4611 ()Lorg/lwjgl/opengl/kb;
L3:     astore_2
L4:     aload_1
L5:     aload_2
L6:     dup
L7:     getfield Field org/lwjgl/opengl/kb field5431 J
L10:    dup2
L11:    lstore_3
L12:    invokestatic Method org/lwjgl/l method2052 (J)V
L15:    invokestatic Method org/lwjgl/opengl/Zd method5435 (Lorg/lwjgl/opengl/kb;)V
L18:    invokestatic Method org/lwjgl/l method2034 (Ljava/nio/ByteBuffer;)V
L21:    iload_0
L22:    aload_1
L23:    invokevirtual Method java/nio/ByteBuffer remaining ()I
L26:    sipush 5121
L29:    iconst_1
L30:    dup
L31:    pop2
L32:    aload_1
L33:    invokestatic Method org/lwjgl/MemoryUtil method1873 (Ljava/nio/ByteBuffer;)J
L36:    lload_3
L37:    invokestatic Method org/lwjgl/opengl/GL11 nglDrawElements (IIIJJ)V
L40:    return
L41:    
    .end code
.end method

.method public static method3901 : (I)V
    .code stack 4 locals 3
L0:     invokestatic Method org/lwjgl/opengl/GLContext method4611 ()Lorg/lwjgl/opengl/kb;
L3:     getfield Field org/lwjgl/opengl/kb Zo J
L6:     dup2
L7:     lstore_1
L8:     invokestatic Method org/lwjgl/l method2052 (J)V
L11:    iload_0
L12:    lload_1
L13:    invokestatic Method org/lwjgl/opengl/GL11 nglCallList (IJ)V
L16:    return
L17:    
    .end code
.end method

.method public static method3902 : (IIII)V
    .code stack 6 locals 6
L0:     invokestatic Method org/lwjgl/opengl/GLContext method4611 ()Lorg/lwjgl/opengl/kb;
L3:     getfield Field org/lwjgl/opengl/kb TE J
L6:     dup2
L7:     lstore 4
L9:     invokestatic Method org/lwjgl/l method2052 (J)V
L12:    iload_0
L13:    iload_1
L14:    iload_2
L15:    iload_3
L16:    lload 4
L18:    invokestatic Method org/lwjgl/opengl/GL11 nglVertex4i (IIIIJ)V
L21:    return
L22:    
    .end code
.end method

.method public static method3903 : (IIIIIILjava/nio/FloatBuffer;)V
    .code stack 10 locals 10
L0:     invokestatic Method org/lwjgl/opengl/GLContext method4611 ()Lorg/lwjgl/opengl/kb;
L3:     astore 7
L5:     aload 6
L7:     aload 7
L9:     dup
L10:    getfield Field org/lwjgl/opengl/kb oL J
L13:    dup2
L14:    lstore 8
L16:    invokestatic Method org/lwjgl/l method2052 (J)V
L19:    invokestatic Method org/lwjgl/opengl/Zd method5449 (Lorg/lwjgl/opengl/kb;)V
L22:    aload 6
L24:    iload 4
L26:    iload 5
L28:    iload_2
L29:    iload_3
L30:    iconst_1
L31:    dup
L32:    dup
L33:    pop2
L34:    invokestatic Method org/lwjgl/opengl/Zd method5429 (Ljava/nio/Buffer;IIIII)I
L37:    invokestatic Method org/lwjgl/l method2044 (Ljava/nio/FloatBuffer;I)V
L40:    iload_0
L41:    iload_1
L42:    iload_2
L43:    iload_3
L44:    iload 4
L46:    iload 5
L48:    aload 6
L50:    invokestatic Method org/lwjgl/MemoryUtil method1878 (Ljava/nio/FloatBuffer;)J
L53:    lload 8
L55:    invokestatic Method org/lwjgl/opengl/GL11 nglReadPixels (IIIIIIJJ)V
L58:    return
L59:    
    .end code
.end method

.method public static method3904 : (FFF)V
    .code stack 5 locals 5
L0:     invokestatic Method org/lwjgl/opengl/GLContext method4611 ()Lorg/lwjgl/opengl/kb;
L3:     getfield Field org/lwjgl/opengl/kb gi J
L6:     dup2
L7:     lstore_3
L8:     invokestatic Method org/lwjgl/l method2052 (J)V
L11:    fload_0
L12:    fload_1
L13:    fload_2
L14:    lload_3
L15:    invokestatic Method org/lwjgl/opengl/GL11 nglTexCoord3f (FFFJ)V
L18:    return
L19:    
    .end code
.end method

.method static native nglTexGenf : (IIFJ)V
.end method

.method public static method3905 : (I)Z
    .code stack 5 locals 4
L0:     invokestatic Method org/lwjgl/opengl/GLContext method4611 ()Lorg/lwjgl/opengl/kb;
L3:     dup
L4:     getfield Field org/lwjgl/opengl/kb mp J
L7:     dup2
L8:     lstore_2
L9:     invokestatic Method org/lwjgl/l method2052 (J)V
L12:    iconst_1
L13:    dup
L14:    dup
L15:    pop2
L16:    invokestatic Method org/lwjgl/opengl/bB method5470 (Lorg/lwjgl/opengl/kb;I)Ljava/nio/ByteBuffer;
L19:    astore_1
L20:    iload_0
L21:    aload_1
L22:    invokestatic Method org/lwjgl/MemoryUtil method1873 (Ljava/nio/ByteBuffer;)J
L25:    lload_2
L26:    invokestatic Method org/lwjgl/opengl/GL11 nglGetBooleanv (IJJ)V
L29:    aload_1
L30:    iconst_0
L31:    iconst_1
L32:    dup
L33:    pop2
L34:    invokevirtual Method java/nio/ByteBuffer get (I)B
L37:    iconst_1
L38:    dup
L39:    dup
L40:    pop2
L41:    if_icmpne L50
L44:    iconst_1
L45:    dup
L46:    dup
L47:    pop2
L48:    ireturn
L49:    athrow
L50:    iconst_0
L51:    iconst_1
L52:    dup
L53:    pop2
L54:    ireturn
L55:    
        .attribute StackMap b'\x00\x02\x00\x31\x00\x00\x00\x01\x07\x05\x3C\x00\x32\x00\x03\x01\x07\x04\xCB\x04\x00\x00'
    .end code
.end method

.method public static method3906 : (ILjava/nio/IntBuffer;)V
    .code stack 5 locals 4
L0:     invokestatic Method org/lwjgl/opengl/GLContext method4611 ()Lorg/lwjgl/opengl/kb;
L3:     getfield Field org/lwjgl/opengl/kb Kr J
L6:     dup2
L7:     lstore_2
L8:     invokestatic Method org/lwjgl/l method2052 (J)V
L11:    iload_0
L12:    aload_1
L13:    iconst_4
L14:    iconst_1
L15:    dup
L16:    pop2
L17:    invokestatic Method org/lwjgl/l method2041 (Ljava/nio/IntBuffer;I)V
L20:    aload_1
L21:    invokestatic Method org/lwjgl/MemoryUtil method1884 (Ljava/nio/IntBuffer;)J
L24:    lload_2
L25:    invokestatic Method org/lwjgl/opengl/GL11 nglLightModeliv (IJJ)V
L28:    return
L29:    
    .end code
.end method

.method public static method3907 : (IIIIIIILjava/nio/DoubleBuffer;)V
    .code stack 11 locals 11
L0:     invokestatic Method org/lwjgl/opengl/GLContext method4611 ()Lorg/lwjgl/opengl/kb;
L3:     astore 8
L5:     aload 7
L7:     aload 8
L9:     dup
L10:    getfield Field org/lwjgl/opengl/kb hM J
L13:    dup2
L14:    lstore 9
L16:    invokestatic Method org/lwjgl/l method2052 (J)V
L19:    invokestatic Method org/lwjgl/opengl/Zd method5446 (Lorg/lwjgl/opengl/kb;)V
L22:    ifnull L39
L25:    aload 7
L27:    dup
L28:    iload 5
L30:    iload 6
L32:    iload_3
L33:    invokestatic Method org/lwjgl/opengl/Zd method5456 (Ljava/nio/Buffer;III)I
L36:    invokestatic Method org/lwjgl/l method2056 (Ljava/nio/DoubleBuffer;I)V
L39:    iload_0
L40:    iload_1
L41:    iload_2
L42:    iload_3
L43:    iload 4
L45:    iload 5
L47:    iload 6
L49:    aload 7
L51:    invokestatic Method org/lwjgl/MemoryUtil method1861 (Ljava/nio/DoubleBuffer;)J
L54:    lload 9
L56:    invokestatic Method org/lwjgl/opengl/GL11 nglTexImage1D (IIIIIIIJJ)V
L59:    return
L60:    
        .attribute StackMap b'\x00\x01\x00\x27\x00\x0A\x01\x01\x01\x01\x01\x01\x01\x07\x04\x49\x07\x04\x21\x04\x00\x00'
    .end code
.end method

.method public static method3908 : (II)V
    .code stack 4 locals 4
L0:     invokestatic Method org/lwjgl/opengl/GLContext method4611 ()Lorg/lwjgl/opengl/kb;
L3:     getfield Field org/lwjgl/opengl/kb field5443 J
L6:     dup2
L7:     lstore_2
L8:     invokestatic Method org/lwjgl/l method2052 (J)V
L11:    iload_0
L12:    iload_1
L13:    lload_2
L14:    invokestatic Method org/lwjgl/opengl/GL11 nglRasterPos2i (IIJ)V
L17:    return
L18:    
    .end code
.end method

.method static native nglPixelStorei : (IIJ)V
.end method

.method static native nglInitNames : (J)V
.end method

.method static native nglNormal3d : (DDDJ)V
.end method

.method public static method3909 : (IILjava/nio/FloatBuffer;)V
    .code stack 6 locals 5
L0:     invokestatic Method org/lwjgl/opengl/GLContext method4611 ()Lorg/lwjgl/opengl/kb;
L3:     getfield Field org/lwjgl/opengl/kb dh J
L6:     dup2
L7:     lstore_3
L8:     invokestatic Method org/lwjgl/l method2052 (J)V
L11:    iload_0
L12:    aload_2
L13:    iconst_4
L14:    iconst_1
L15:    dup
L16:    pop2
L17:    invokestatic Method org/lwjgl/l method2044 (Ljava/nio/FloatBuffer;I)V
L20:    iload_1
L21:    aload_2
L22:    invokestatic Method org/lwjgl/MemoryUtil method1878 (Ljava/nio/FloatBuffer;)J
L25:    lload_3
L26:    invokestatic Method org/lwjgl/opengl/GL11 nglGetTexParameterfv (IIJJ)V
L29:    return
L30:    
    .end code
.end method

.method public static method3910 : (IIII)V
    .code stack 6 locals 6
L0:     invokestatic Method org/lwjgl/opengl/GLContext method4611 ()Lorg/lwjgl/opengl/kb;
L3:     getfield Field org/lwjgl/opengl/kb El J
L6:     dup2
L7:     lstore 4
L9:     invokestatic Method org/lwjgl/l method2052 (J)V
L12:    iload_0
L13:    iload_1
L14:    iload_2
L15:    iload_3
L16:    lload 4
L18:    invokestatic Method org/lwjgl/opengl/GL11 nglScissor (IIIIJ)V
L21:    return
L22:    
    .end code
.end method

.method public static method3911 : (Ljava/nio/ByteBuffer;)V
    .code stack 6 locals 3
L0:     invokestatic Method org/lwjgl/opengl/GLContext method4611 ()Lorg/lwjgl/opengl/kb;
L3:     getfield Field org/lwjgl/opengl/kb Kf J
L6:     dup2
L7:     lstore_1
L8:     invokestatic Method org/lwjgl/l method2052 (J)V
L11:    aload_0
L12:    dup
L13:    invokestatic Method org/lwjgl/l method2034 (Ljava/nio/ByteBuffer;)V
L16:    invokevirtual Method java/nio/ByteBuffer remaining ()I
L19:    sipush 5121
L22:    iconst_1
L23:    dup
L24:    pop2
L25:    aload_0
L26:    invokestatic Method org/lwjgl/MemoryUtil method1873 (Ljava/nio/ByteBuffer;)J
L29:    lload_1
L30:    invokestatic Method org/lwjgl/opengl/GL11 nglCallLists (IIJJ)V
L33:    return
L34:    
    .end code
.end method

.method public static method3912 : (IILjava/nio/FloatBuffer;)V
    .code stack 7 locals 6
L0:     invokestatic Method org/lwjgl/opengl/GLContext method4611 ()Lorg/lwjgl/opengl/kb;
L3:     astore_3
L4:     aload_2
L5:     aload_3
L6:     dup
L7:     getfield Field org/lwjgl/opengl/kb VM J
L10:    dup2
L11:    lstore 4
L13:    invokestatic Method org/lwjgl/l method2052 (J)V
L16:    invokestatic Method org/lwjgl/opengl/Zd method5454 (Lorg/lwjgl/opengl/kb;)V
L19:    invokestatic Method org/lwjgl/l method2048 (Ljava/nio/FloatBuffer;)V
L22:    getstatic Field org/lwjgl/LWJGLUtil CHECKS Z
L25:    ifeq L36
L28:    aload_3
L29:    invokestatic Method org/lwjgl/opengl/w method5768 (Lorg/lwjgl/opengl/kb;)Lorg/lwjgl/opengl/P;
L32:    aload_2
L33:    putfield Field org/lwjgl/opengl/P field4944 Ljava/nio/Buffer;
L36:    iload_0
L37:    sipush 5126
L40:    iconst_1
L41:    dup
L42:    pop2
L43:    iload_1
L44:    aload_2
L45:    invokestatic Method org/lwjgl/MemoryUtil method1878 (Ljava/nio/FloatBuffer;)J
L48:    lload 4
L50:    invokestatic Method org/lwjgl/opengl/GL11 nglVertexPointer (IIIJJ)V
L53:    return
L54:    
        .attribute StackMap b'\x00\x01\x00\x24\x00\x05\x01\x01\x07\x05\xFE\x07\x04\x21\x04\x00\x00'
    .end code
.end method

.method static native nglMatrixMode : (IJ)V
.end method

.method public static method3913 : (IIF)V
    .code stack 5 locals 5
L0:     invokestatic Method org/lwjgl/opengl/GLContext method4611 ()Lorg/lwjgl/opengl/kb;
L3:     getfield Field org/lwjgl/opengl/kb Vq J
L6:     dup2
L7:     lstore_3
L8:     invokestatic Method org/lwjgl/l method2052 (J)V
L11:    iload_0
L12:    iload_1
L13:    fload_2
L14:    lload_3
L15:    invokestatic Method org/lwjgl/opengl/GL11 nglTexGenf (IIFJ)V
L18:    return
L19:    
    .end code
.end method

.method public static method3914 : (DDDD)V
    .code stack 10 locals 10
L0:     invokestatic Method org/lwjgl/opengl/GLContext method4611 ()Lorg/lwjgl/opengl/kb;
L3:     getfield Field org/lwjgl/opengl/kb field5411 J
L6:     dup2
L7:     lstore 8
L9:     invokestatic Method org/lwjgl/l method2052 (J)V
L12:    dload_0
L13:    dload_2
L14:    dload 4
L16:    dload 6
L18:    lload 8
L20:    invokestatic Method org/lwjgl/opengl/GL11 nglVertex4d (DDDDJ)V
L23:    return
L24:    
    .end code
.end method

.method public static method3915 : (ILjava/nio/FloatBuffer;)V
    .code stack 6 locals 4
L0:     invokestatic Method org/lwjgl/opengl/GLContext method4611 ()Lorg/lwjgl/opengl/kb;
L3:     getfield Field org/lwjgl/opengl/kb VP J
L6:     dup2
L7:     lstore_2
L8:     invokestatic Method org/lwjgl/l method2052 (J)V
L11:    aload_1
L12:    dup
L13:    invokestatic Method org/lwjgl/l method2048 (Ljava/nio/FloatBuffer;)V
L16:    invokevirtual Method java/nio/FloatBuffer remaining ()I
L19:    iload_0
L20:    aload_1
L21:    invokestatic Method org/lwjgl/MemoryUtil method1878 (Ljava/nio/FloatBuffer;)J
L24:    lload_2
L25:    invokestatic Method org/lwjgl/opengl/GL11 nglFeedbackBuffer (IIJJ)V
L28:    return
L29:    
    .end code
.end method

.method public static method3916 : (I)V
    .code stack 4 locals 3
L0:     invokestatic Method org/lwjgl/opengl/GLContext method4611 ()Lorg/lwjgl/opengl/kb;
L3:     getfield Field org/lwjgl/opengl/kb cJ J
L6:     dup2
L7:     lstore_1
L8:     invokestatic Method org/lwjgl/l method2052 (J)V
L11:    iload_0
L12:    lload_1
L13:    invokestatic Method org/lwjgl/opengl/GL11 nglEnable (IJ)V
L16:    return
L17:    
    .end code
.end method

.method public static method3917 : (FFFF)V
    .code stack 6 locals 6
L0:     invokestatic Method org/lwjgl/opengl/GLContext method4611 ()Lorg/lwjgl/opengl/kb;
L3:     getfield Field org/lwjgl/opengl/kb pn J
L6:     dup2
L7:     lstore 4
L9:     invokestatic Method org/lwjgl/l method2052 (J)V
L12:    fload_0
L13:    fload_1
L14:    fload_2
L15:    fload_3
L16:    lload 4
L18:    invokestatic Method org/lwjgl/opengl/GL11 nglClearColor (FFFFJ)V
L21:    return
L22:    
    .end code
.end method

.method static native nglPolygonOffset : (FFJ)V
.end method

.method static native nglStencilOp : (IIIJ)V
.end method

.method public static method3918 : (II)V
    .code stack 4 locals 4
L0:     invokestatic Method org/lwjgl/opengl/GLContext method4611 ()Lorg/lwjgl/opengl/kb;
L3:     getfield Field org/lwjgl/opengl/kb LR J
L6:     dup2
L7:     lstore_2
L8:     invokestatic Method org/lwjgl/l method2052 (J)V
L11:    iload_0
L12:    iload_1
L13:    lload_2
L14:    invokestatic Method org/lwjgl/opengl/GL11 nglHint (IIJ)V
L17:    return
L18:    
    .end code
.end method

.method public static method3919 : (ILjava/nio/FloatBuffer;)V
    .code stack 5 locals 4
L0:     invokestatic Method org/lwjgl/opengl/GLContext method4611 ()Lorg/lwjgl/opengl/kb;
L3:     getfield Field org/lwjgl/opengl/kb hF J
L6:     dup2
L7:     lstore_2
L8:     invokestatic Method org/lwjgl/l method2052 (J)V
L11:    iload_0
L12:    aload_1
L13:    iconst_4
L14:    iconst_1
L15:    dup
L16:    pop2
L17:    invokestatic Method org/lwjgl/l method2044 (Ljava/nio/FloatBuffer;I)V
L20:    aload_1
L21:    invokestatic Method org/lwjgl/MemoryUtil method1878 (Ljava/nio/FloatBuffer;)J
L24:    lload_2
L25:    invokestatic Method org/lwjgl/opengl/GL11 nglFogfv (IJJ)V
L28:    return
L29:    
    .end code
.end method

.method static native nglGetTexImage : (IIIIJJ)V
.end method

.method static native nglDepthFunc : (IJ)V
.end method

.method static native nglDisableClientState : (IJ)V
.end method

.method static native nglTranslatef : (FFFJ)V
.end method

.method public static method3920 : (III)V
    .code stack 5 locals 5
L0:     invokestatic Method org/lwjgl/opengl/GLContext method4611 ()Lorg/lwjgl/opengl/kb;
L3:     getfield Field org/lwjgl/opengl/kb Im J
L6:     dup2
L7:     lstore_3
L8:     invokestatic Method org/lwjgl/l method2052 (J)V
L11:    iload_0
L12:    iload_1
L13:    iload_2
L14:    lload_3
L15:    invokestatic Method org/lwjgl/opengl/GL11 nglDrawArrays (IIIJ)V
L18:    return
L19:    
    .end code
.end method

.method public static method3921 : (ILjava/nio/DoubleBuffer;)V
    .code stack 6 locals 5
L0:     invokestatic Method org/lwjgl/opengl/GLContext method4611 ()Lorg/lwjgl/opengl/kb;
L3:     astore_2
L4:     aload_1
L5:     aload_2
L6:     dup
L7:     getfield Field org/lwjgl/opengl/kb op J
L10:    dup2
L11:    lstore_3
L12:    invokestatic Method org/lwjgl/l method2052 (J)V
L15:    invokestatic Method org/lwjgl/opengl/Zd method5454 (Lorg/lwjgl/opengl/kb;)V
L18:    invokestatic Method org/lwjgl/l method2036 (Ljava/nio/DoubleBuffer;)V
L21:    getstatic Field org/lwjgl/LWJGLUtil CHECKS Z
L24:    ifeq L35
L27:    aload_2
L28:    invokestatic Method org/lwjgl/opengl/w method5768 (Lorg/lwjgl/opengl/kb;)Lorg/lwjgl/opengl/P;
L31:    aload_1
L32:    putfield Field org/lwjgl/opengl/P field4947 Ljava/nio/Buffer;
L35:    sipush 5130
L38:    iconst_1
L39:    dup
L40:    pop2
L41:    iload_0
L42:    aload_1
L43:    invokestatic Method org/lwjgl/MemoryUtil method1840 (Ljava/nio/DoubleBuffer;)J
L46:    lload_3
L47:    invokestatic Method org/lwjgl/opengl/GL11 nglNormalPointer (IIJJ)V
L50:    return
L51:    
        .attribute StackMap b'\x00\x01\x00\x23\x00\x04\x01\x07\x04\x49\x07\x04\x21\x04\x00\x00'
    .end code
.end method

.method public static method3922 : (DD)V
    .code stack 6 locals 6
L0:     invokestatic Method org/lwjgl/opengl/GLContext method4611 ()Lorg/lwjgl/opengl/kb;
L3:     getfield Field org/lwjgl/opengl/kb ck J
L6:     dup2
L7:     lstore 4
L9:     invokestatic Method org/lwjgl/l method2052 (J)V
L12:    dload_0
L13:    dload_2
L14:    lload 4
L16:    invokestatic Method org/lwjgl/opengl/GL11 nglEvalCoord2d (DDJ)V
L19:    return
L20:    
    .end code
.end method

.method public static method3923 : (IILjava/nio/DoubleBuffer;)V
    .code stack 6 locals 5
L0:     invokestatic Method org/lwjgl/opengl/GLContext method4611 ()Lorg/lwjgl/opengl/kb;
L3:     getfield Field org/lwjgl/opengl/kb Hg J
L6:     dup2
L7:     lstore_3
L8:     invokestatic Method org/lwjgl/l method2052 (J)V
L11:    iload_0
L12:    aload_2
L13:    sipush 256
L16:    iconst_1
L17:    dup
L18:    pop2
L19:    invokestatic Method org/lwjgl/l method2056 (Ljava/nio/DoubleBuffer;I)V
L22:    iload_1
L23:    aload_2
L24:    invokestatic Method org/lwjgl/MemoryUtil method1840 (Ljava/nio/DoubleBuffer;)J
L27:    lload_3
L28:    invokestatic Method org/lwjgl/opengl/GL11 nglGetMapdv (IIJJ)V
L31:    return
L32:    
    .end code
.end method

.method static native nglPolygonStipple : (JJ)V
.end method

.method public static method3924 : (II)V
    .code stack 4 locals 4
L0:     invokestatic Method org/lwjgl/opengl/GLContext method4611 ()Lorg/lwjgl/opengl/kb;
L3:     getfield Field org/lwjgl/opengl/kb lJ J
L6:     dup2
L7:     lstore_2
L8:     invokestatic Method org/lwjgl/l method2052 (J)V
L11:    iload_0
L12:    iload_1
L13:    lload_2
L14:    invokestatic Method org/lwjgl/opengl/GL11 nglPolygonMode (IIJ)V
L17:    return
L18:    
    .end code
.end method

.method static native nglIsList : (IJ)Z
.end method

.method public static method3925 : (IIIILjava/nio/DoubleBuffer;)V
    .code stack 9 locals 8
L0:     invokestatic Method org/lwjgl/opengl/GLContext method4611 ()Lorg/lwjgl/opengl/kb;
L3:     astore 5
L5:     aload 4
L7:     aload 5
L9:     dup
L10:    getfield Field org/lwjgl/opengl/kb cj J
L13:    dup2
L14:    lstore 6
L16:    invokestatic Method org/lwjgl/l method2052 (J)V
L19:    invokestatic Method org/lwjgl/opengl/Zd method5449 (Lorg/lwjgl/opengl/kb;)V
L22:    aload 4
L24:    iload_2
L25:    iload_3
L26:    iconst_1
L27:    dup
L28:    pop2
L29:    iconst_1
L30:    dup
L31:    pop2
L32:    iconst_1
L33:    dup
L34:    dup_x1
L35:    dup_x2
L36:    dup
L37:    pop2
L38:    invokestatic Method org/lwjgl/opengl/Zd method5429 (Ljava/nio/Buffer;IIIII)I
L41:    invokestatic Method org/lwjgl/l method2056 (Ljava/nio/DoubleBuffer;I)V
L44:    iload_0
L45:    iload_1
L46:    iload_2
L47:    iload_3
L48:    aload 4
L50:    invokestatic Method org/lwjgl/MemoryUtil method1840 (Ljava/nio/DoubleBuffer;)J
L53:    lload 6
L55:    invokestatic Method org/lwjgl/opengl/GL11 nglGetTexImage (IIIIJJ)V
L58:    return
L59:    
    .end code
.end method

.method static native nglRenderMode : (IJ)I
.end method

.method public static method3926 : (FFF)V
    .code stack 5 locals 5
L0:     invokestatic Method org/lwjgl/opengl/GLContext method4611 ()Lorg/lwjgl/opengl/kb;
L3:     getfield Field org/lwjgl/opengl/kb Hi J
L6:     dup2
L7:     lstore_3
L8:     invokestatic Method org/lwjgl/l method2052 (J)V
L11:    fload_0
L12:    fload_1
L13:    fload_2
L14:    lload_3
L15:    invokestatic Method org/lwjgl/opengl/GL11 nglColor3f (FFFJ)V
L18:    return
L19:    
    .end code
.end method

.method static native nglMapGrid2d : (IDDIDDJ)V
.end method
.end class
