.version 49 0
.class public final super org/lwjgl/opengl/GL15
.super java/lang/Object
.field public static final field3789 I = 33873
.field public static final switch I = 35046
.field public static final field3790 I = 33879
.field public static final field3791 I = 34918
.field public static final field3792 I = 34919
.field public static final field3793 I = 35001
.field public static final field3794 I = 34963
.field public static final field3795 I = 34969
.field public static final field3796 I = 34176
.field public static final field3797 I = 34966
.field public static final field3798 I = 34660
.field public static final throw I = 34968
.field public static final package I = 35004
.field public static final field3799 I = 33877
.field public static final field3800 I = 33872
.field public static final while I = 33878
.field public static final field3801 I = 34972
.field public static final field3802 I = 35003
.field public static final field3803 I = 35000
.field public static final field3804 I = 34964
.field public static final field3805 I = 34971
.field public static final field3806 I = 34185
.field public static final field3807 I = 35042
.field public static final field3808 I = 35041
.field public static final field3809 I = 35048
.field public static final field3810 I = 34184
.field public static final field3811 I = 35044
.field public static final false I = 34973
.field public static final field3812 I = 34177
.field public static final field3813 I = 35049
.field public static final true I = 34974
.field public static final field3814 I = 34917
.field public static final field3815 I = 34965
.field public static final field3816 I = 33875
.field public static final field3817 I = 34962
.field public static final field3818 I = 33876
.field public static final field3819 I = 35040
.field public static final field3820 I = 34178
.field public static final field3821 I = 34916
.field public static final field3822 I = 34973
.field public static final field3823 I = 35050
.field public static final try I = 34970
.field public static final field3824 I = 35002
.field public static final new I = 35045
.field public static final field3825 I = 34661
.field public static final this I = 34975
.field public static final field3826 I = 35092
.field public static final field3827 I = 34186
.field public static final field3828 I = 34967
.field public static final field3829 I = 35005

.method public static method4002 : (IJLjava/nio/IntBuffer;)V
    .code stack 9 locals 6
L0:     invokestatic Method org/lwjgl/opengl/GLContext method4611 ()Lorg/lwjgl/opengl/kb;
L3:     getfield Field org/lwjgl/opengl/kb gD J
L6:     dup2
L7:     lstore 4
L9:     invokestatic Method org/lwjgl/l method2052 (J)V
L12:    iload_0
L13:    aload_3
L14:    invokestatic Method org/lwjgl/l method2043 (Ljava/nio/IntBuffer;)V
L17:    lload_1
L18:    aload_3
L19:    invokevirtual Method java/nio/IntBuffer remaining ()I
L22:    iconst_2
L23:    iconst_1
L24:    dup
L25:    pop2
L26:    ishl
L27:    i2l
L28:    aload_3
L29:    invokestatic Method org/lwjgl/MemoryUtil method1884 (Ljava/nio/IntBuffer;)J
L32:    lload 4
L34:    invokestatic Method org/lwjgl/opengl/GL15 nglBufferSubData (IJJJJ)V
L37:    return
L38:    
    .end code
.end method

.method public static method4003 : (I)V
    .code stack 4 locals 3
L0:     invokestatic Method org/lwjgl/opengl/GLContext method4611 ()Lorg/lwjgl/opengl/kb;
L3:     getfield Field org/lwjgl/opengl/kb gt J
L6:     dup2
L7:     lstore_1
L8:     invokestatic Method org/lwjgl/l method2052 (J)V
L11:    iload_0
L12:    lload_1
L13:    invokestatic Method org/lwjgl/opengl/GL15 nglEndQuery (IJ)V
L16:    return
L17:    
    .end code
.end method

.method static native nglGetBufferPointerv : (IIJJ)Ljava/nio/ByteBuffer;
.end method

.method static native nglDeleteBuffers : (IJJ)V
.end method

.method public static method4004 : (II)V
    .code stack 4 locals 4
L0:     invokestatic Method org/lwjgl/opengl/GLContext method4611 ()Lorg/lwjgl/opengl/kb;
L3:     getfield Field org/lwjgl/opengl/kb vB J
L6:     dup2
L7:     lstore_2
L8:     invokestatic Method org/lwjgl/l method2052 (J)V
L11:    iload_0
L12:    iload_1
L13:    lload_2
L14:    invokestatic Method org/lwjgl/opengl/GL15 nglBeginQuery (IIJ)V
L17:    return
L18:    
    .end code
.end method

.method public static method4005 : (I)V
    .code stack 5 locals 4
L0:     invokestatic Method org/lwjgl/opengl/GLContext method4611 ()Lorg/lwjgl/opengl/kb;
L3:     dup
L4:     astore_1
L5:     getfield Field org/lwjgl/opengl/kb XO J
L8:     dup2
L9:     lstore_2
L10:    invokestatic Method org/lwjgl/l method2052 (J)V
L13:    iconst_1
L14:    dup
L15:    dup
L16:    pop2
L17:    aload_1
L18:    iload_0
L19:    invokestatic Method org/lwjgl/opengl/bB method5479 (Lorg/lwjgl/opengl/kb;I)J
L22:    lload_2
L23:    invokestatic Method org/lwjgl/opengl/GL15 nglDeleteBuffers (IJJ)V
L26:    return
L27:    
    .end code
.end method

.method public static method4006 : (I)Z
    .code stack 4 locals 3
L0:     invokestatic Method org/lwjgl/opengl/GLContext method4611 ()Lorg/lwjgl/opengl/kb;
L3:     getfield Field org/lwjgl/opengl/kb X J
L6:     dup2
L7:     lstore_1
L8:     invokestatic Method org/lwjgl/l method2052 (J)V
L11:    iload_0
L12:    lload_1
L13:    invokestatic Method org/lwjgl/opengl/GL15 nglUnmapBuffer (IJ)Z
L16:    ireturn
L17:    
    .end code
.end method

.method public static method4007 : (ILjava/nio/ByteBuffer;I)V
    .code stack 8 locals 5
L0:     invokestatic Method org/lwjgl/opengl/GLContext method4611 ()Lorg/lwjgl/opengl/kb;
L3:     getfield Field org/lwjgl/opengl/kb jg J
L6:     dup2
L7:     lstore_3
L8:     invokestatic Method org/lwjgl/l method2052 (J)V
L11:    iload_0
L12:    aload_1
L13:    invokestatic Method org/lwjgl/l method2034 (Ljava/nio/ByteBuffer;)V
L16:    aload_1
L17:    invokevirtual Method java/nio/ByteBuffer remaining ()I
L20:    i2l
L21:    aload_1
L22:    invokestatic Method org/lwjgl/MemoryUtil method1873 (Ljava/nio/ByteBuffer;)J
L25:    iload_2
L26:    lload_3
L27:    invokestatic Method org/lwjgl/opengl/GL15 nglBufferData (IJJIJ)V
L30:    return
L31:    
    .end code
.end method

.method public static method4008 : (IJLjava/nio/DoubleBuffer;)V
    .code stack 9 locals 6
L0:     invokestatic Method org/lwjgl/opengl/GLContext method4611 ()Lorg/lwjgl/opengl/kb;
L3:     getfield Field org/lwjgl/opengl/kb Xs J
L6:     dup2
L7:     lstore 4
L9:     invokestatic Method org/lwjgl/l method2052 (J)V
L12:    iload_0
L13:    aload_3
L14:    invokestatic Method org/lwjgl/l method2036 (Ljava/nio/DoubleBuffer;)V
L17:    lload_1
L18:    aload_3
L19:    invokevirtual Method java/nio/DoubleBuffer remaining ()I
L22:    iconst_3
L23:    iconst_1
L24:    dup
L25:    pop2
L26:    ishl
L27:    i2l
L28:    aload_3
L29:    invokestatic Method org/lwjgl/MemoryUtil method1840 (Ljava/nio/DoubleBuffer;)J
L32:    lload 4
L34:    invokestatic Method org/lwjgl/opengl/GL15 nglGetBufferSubData (IJJJJ)V
L37:    return
L38:    
    .end code
.end method

.method static native nglBufferData : (IJJIJ)V
.end method

.method public static method4009 : (Ljava/nio/IntBuffer;)V
    .code stack 5 locals 3
L0:     invokestatic Method org/lwjgl/opengl/GLContext method4611 ()Lorg/lwjgl/opengl/kb;
L3:     getfield Field org/lwjgl/opengl/kb T J
L6:     dup2
L7:     lstore_1
L8:     invokestatic Method org/lwjgl/l method2052 (J)V
L11:    aload_0
L12:    dup
L13:    invokestatic Method org/lwjgl/l method2043 (Ljava/nio/IntBuffer;)V
L16:    invokevirtual Method java/nio/IntBuffer remaining ()I
L19:    aload_0
L20:    invokestatic Method org/lwjgl/MemoryUtil method1884 (Ljava/nio/IntBuffer;)J
L23:    lload_1
L24:    invokestatic Method org/lwjgl/opengl/GL15 nglGenQueries (IJJ)V
L27:    return
L28:    
    .end code
.end method

.method public static method4010 : (II)I
    .code stack 2 locals 2
L0:     iload_0
L1:     iload_1
L2:     invokestatic Method org/lwjgl/opengl/GL15 method4011 (II)I
L5:     ireturn
L6:     
    .end code
    .deprecated
.end method

.method public static method4011 : (II)I
    .code stack 6 locals 5
L0:     invokestatic Method org/lwjgl/opengl/GLContext method4611 ()Lorg/lwjgl/opengl/kb;
L3:     dup
L4:     getfield Field org/lwjgl/opengl/kb Eh J
L7:     dup2
L8:     lstore_3
L9:     invokestatic Method org/lwjgl/l method2052 (J)V
L12:    invokestatic Method org/lwjgl/opengl/bB method5467 (Lorg/lwjgl/opengl/kb;)Ljava/nio/IntBuffer;
L15:    astore_2
L16:    iload_0
L17:    iload_1
L18:    aload_2
L19:    invokestatic Method org/lwjgl/MemoryUtil method1884 (Ljava/nio/IntBuffer;)J
L22:    lload_3
L23:    invokestatic Method org/lwjgl/opengl/GL15 nglGetBufferParameteriv (IIJJ)V
L26:    aload_2
L27:    iconst_0
L28:    iconst_1
L29:    dup
L30:    pop2
L31:    invokevirtual Method java/nio/IntBuffer get (I)I
L34:    ireturn
L35:    
    .end code
.end method

.method public static method4012 : (Ljava/nio/IntBuffer;)V
    .code stack 5 locals 3
L0:     invokestatic Method org/lwjgl/opengl/GLContext method4611 ()Lorg/lwjgl/opengl/kb;
L3:     getfield Field org/lwjgl/opengl/kb XO J
L6:     dup2
L7:     lstore_1
L8:     invokestatic Method org/lwjgl/l method2052 (J)V
L11:    aload_0
L12:    dup
L13:    invokestatic Method org/lwjgl/l method2043 (Ljava/nio/IntBuffer;)V
L16:    invokevirtual Method java/nio/IntBuffer remaining ()I
L19:    aload_0
L20:    invokestatic Method org/lwjgl/MemoryUtil method1884 (Ljava/nio/IntBuffer;)J
L23:    lload_1
L24:    invokestatic Method org/lwjgl/opengl/GL15 nglDeleteBuffers (IJJ)V
L27:    return
L28:    
    .end code
.end method

.method public static method4013 : (I)Z
    .code stack 4 locals 3
L0:     invokestatic Method org/lwjgl/opengl/GLContext method4611 ()Lorg/lwjgl/opengl/kb;
L3:     getfield Field org/lwjgl/opengl/kb DT J
L6:     dup2
L7:     lstore_1
L8:     invokestatic Method org/lwjgl/l method2052 (J)V
L11:    iload_0
L12:    lload_1
L13:    invokestatic Method org/lwjgl/opengl/GL15 nglIsQuery (IJ)Z
L16:    ireturn
L17:    
    .end code
.end method

.method public static method4014 : (IJLjava/nio/FloatBuffer;)V
    .code stack 9 locals 6
L0:     invokestatic Method org/lwjgl/opengl/GLContext method4611 ()Lorg/lwjgl/opengl/kb;
L3:     getfield Field org/lwjgl/opengl/kb Xs J
L6:     dup2
L7:     lstore 4
L9:     invokestatic Method org/lwjgl/l method2052 (J)V
L12:    iload_0
L13:    aload_3
L14:    invokestatic Method org/lwjgl/l method2048 (Ljava/nio/FloatBuffer;)V
L17:    lload_1
L18:    aload_3
L19:    invokevirtual Method java/nio/FloatBuffer remaining ()I
L22:    iconst_2
L23:    iconst_1
L24:    dup
L25:    pop2
L26:    ishl
L27:    i2l
L28:    aload_3
L29:    invokestatic Method org/lwjgl/MemoryUtil method1878 (Ljava/nio/FloatBuffer;)J
L32:    lload 4
L34:    invokestatic Method org/lwjgl/opengl/GL15 nglGetBufferSubData (IJJJJ)V
L37:    return
L38:    
    .end code
.end method

.method public static method4015 : (ILjava/nio/FloatBuffer;I)V
    .code stack 8 locals 5
L0:     invokestatic Method org/lwjgl/opengl/GLContext method4611 ()Lorg/lwjgl/opengl/kb;
L3:     getfield Field org/lwjgl/opengl/kb jg J
L6:     dup2
L7:     lstore_3
L8:     invokestatic Method org/lwjgl/l method2052 (J)V
L11:    iload_0
L12:    aload_1
L13:    invokestatic Method org/lwjgl/l method2048 (Ljava/nio/FloatBuffer;)V
L16:    aload_1
L17:    invokevirtual Method java/nio/FloatBuffer remaining ()I
L20:    iconst_2
L21:    iconst_1
L22:    dup
L23:    pop2
L24:    ishl
L25:    i2l
L26:    aload_1
L27:    invokestatic Method org/lwjgl/MemoryUtil method1878 (Ljava/nio/FloatBuffer;)J
L30:    iload_2
L31:    lload_3
L32:    invokestatic Method org/lwjgl/opengl/GL15 nglBufferData (IJJIJ)V
L35:    return
L36:    
    .end code
.end method

.method public static method4016 : ()I
    .code stack 5 locals 3
L0:     invokestatic Method org/lwjgl/opengl/GLContext method4611 ()Lorg/lwjgl/opengl/kb;
L3:     dup
L4:     getfield Field org/lwjgl/opengl/kb T J
L7:     dup2
L8:     lstore_0
L9:     invokestatic Method org/lwjgl/l method2052 (J)V
L12:    invokestatic Method org/lwjgl/opengl/bB method5467 (Lorg/lwjgl/opengl/kb;)Ljava/nio/IntBuffer;
L15:    astore_2
L16:    iconst_1
L17:    dup
L18:    dup
L19:    pop2
L20:    aload_2
L21:    invokestatic Method org/lwjgl/MemoryUtil method1884 (Ljava/nio/IntBuffer;)J
L24:    lload_0
L25:    invokestatic Method org/lwjgl/opengl/GL15 nglGenQueries (IJJ)V
L28:    aload_2
L29:    iconst_0
L30:    iconst_1
L31:    dup
L32:    pop2
L33:    invokevirtual Method java/nio/IntBuffer get (I)I
L36:    ireturn
L37:    
    .end code
.end method

.method public static method4017 : (IJLjava/nio/FloatBuffer;)V
    .code stack 9 locals 6
L0:     invokestatic Method org/lwjgl/opengl/GLContext method4611 ()Lorg/lwjgl/opengl/kb;
L3:     getfield Field org/lwjgl/opengl/kb gD J
L6:     dup2
L7:     lstore 4
L9:     invokestatic Method org/lwjgl/l method2052 (J)V
L12:    iload_0
L13:    aload_3
L14:    invokestatic Method org/lwjgl/l method2048 (Ljava/nio/FloatBuffer;)V
L17:    lload_1
L18:    aload_3
L19:    invokevirtual Method java/nio/FloatBuffer remaining ()I
L22:    iconst_2
L23:    iconst_1
L24:    dup
L25:    pop2
L26:    ishl
L27:    i2l
L28:    aload_3
L29:    invokestatic Method org/lwjgl/MemoryUtil method1878 (Ljava/nio/FloatBuffer;)J
L32:    lload 4
L34:    invokestatic Method org/lwjgl/opengl/GL15 nglBufferSubData (IJJJJ)V
L37:    return
L38:    
    .end code
.end method

.method static native nglBufferSubData : (IJJJJ)V
.end method

.method static native nglGenQueries : (IJJ)V
.end method

.method public static method4018 : (IJLjava/nio/ShortBuffer;)V
    .code stack 9 locals 6
L0:     invokestatic Method org/lwjgl/opengl/GLContext method4611 ()Lorg/lwjgl/opengl/kb;
L3:     getfield Field org/lwjgl/opengl/kb Xs J
L6:     dup2
L7:     lstore 4
L9:     invokestatic Method org/lwjgl/l method2052 (J)V
L12:    iload_0
L13:    aload_3
L14:    invokestatic Method org/lwjgl/l method2057 (Ljava/nio/ShortBuffer;)V
L17:    lload_1
L18:    aload_3
L19:    invokevirtual Method java/nio/ShortBuffer remaining ()I
L22:    iconst_1
L23:    dup
L24:    dup
L25:    pop2
L26:    ishl
L27:    i2l
L28:    aload_3
L29:    invokestatic Method org/lwjgl/MemoryUtil method1853 (Ljava/nio/ShortBuffer;)J
L32:    lload 4
L34:    invokestatic Method org/lwjgl/opengl/GL15 nglGetBufferSubData (IJJJJ)V
L37:    return
L38:    
    .end code
.end method

.method static native nglGetQueryiv : (IIJJ)V
.end method

.method public static method4019 : (II)V
    .code stack 5 locals 4
L0:     invokestatic Method org/lwjgl/opengl/GLContext method4611 ()Lorg/lwjgl/opengl/kb;
L3:     dup
L4:     getfield Field org/lwjgl/opengl/kb Ck J
L7:     dup2
L8:     lstore_2
L9:     invokestatic Method org/lwjgl/l method2052 (J)V
L12:    iload_0
L13:    iload_1
L14:    invokestatic Method org/lwjgl/opengl/w method5767 (Lorg/lwjgl/opengl/kb;II)V
L17:    iload_0
L18:    iload_1
L19:    lload_2
L20:    invokestatic Method org/lwjgl/opengl/GL15 nglBindBuffer (IIJ)V
L23:    return
L24:    
    .end code
.end method

.method public static method4020 : (IILjava/nio/IntBuffer;)V
    .code stack 6 locals 5
L0:     invokestatic Method org/lwjgl/opengl/GLContext method4611 ()Lorg/lwjgl/opengl/kb;
L3:     getfield Field org/lwjgl/opengl/kb WN J
L6:     dup2
L7:     lstore_3
L8:     invokestatic Method org/lwjgl/l method2052 (J)V
L11:    iload_0
L12:    aload_2
L13:    iconst_1
L14:    dup
L15:    dup
L16:    pop2
L17:    invokestatic Method org/lwjgl/l method2041 (Ljava/nio/IntBuffer;I)V
L20:    iload_1
L21:    aload_2
L22:    invokestatic Method org/lwjgl/MemoryUtil method1884 (Ljava/nio/IntBuffer;)J
L25:    lload_3
L26:    invokestatic Method org/lwjgl/opengl/GL15 nglGetQueryiv (IIJJ)V
L29:    return
L30:    
    .end code
.end method

.method public static method4021 : (IILjava/nio/IntBuffer;)V
    .code stack 6 locals 5
L0:     invokestatic Method org/lwjgl/opengl/GLContext method4611 ()Lorg/lwjgl/opengl/kb;
L3:     getfield Field org/lwjgl/opengl/kb Eh J
L6:     dup2
L7:     lstore_3
L8:     invokestatic Method org/lwjgl/l method2052 (J)V
L11:    iload_0
L12:    aload_2
L13:    iconst_4
L14:    iconst_1
L15:    dup
L16:    pop2
L17:    invokestatic Method org/lwjgl/l method2041 (Ljava/nio/IntBuffer;I)V
L20:    iload_1
L21:    aload_2
L22:    invokestatic Method org/lwjgl/MemoryUtil method1884 (Ljava/nio/IntBuffer;)J
L25:    lload_3
L26:    invokestatic Method org/lwjgl/opengl/GL15 nglGetBufferParameteriv (IIJJ)V
L29:    return
L30:    
    .end code
.end method

.method static native nglIsQuery : (IJ)Z
.end method

.method public static method4022 : (ILjava/nio/IntBuffer;I)V
    .code stack 8 locals 5
L0:     invokestatic Method org/lwjgl/opengl/GLContext method4611 ()Lorg/lwjgl/opengl/kb;
L3:     getfield Field org/lwjgl/opengl/kb jg J
L6:     dup2
L7:     lstore_3
L8:     invokestatic Method org/lwjgl/l method2052 (J)V
L11:    iload_0
L12:    aload_1
L13:    invokestatic Method org/lwjgl/l method2043 (Ljava/nio/IntBuffer;)V
L16:    aload_1
L17:    invokevirtual Method java/nio/IntBuffer remaining ()I
L20:    iconst_2
L21:    iconst_1
L22:    dup
L23:    pop2
L24:    ishl
L25:    i2l
L26:    aload_1
L27:    invokestatic Method org/lwjgl/MemoryUtil method1884 (Ljava/nio/IntBuffer;)J
L30:    iload_2
L31:    lload_3
L32:    invokestatic Method org/lwjgl/opengl/GL15 nglBufferData (IJJIJ)V
L35:    return
L36:    
    .end code
.end method

.method public static method4023 : (IILjava/nio/IntBuffer;)V
    .code stack 6 locals 5
L0:     invokestatic Method org/lwjgl/opengl/GLContext method4611 ()Lorg/lwjgl/opengl/kb;
L3:     getfield Field org/lwjgl/opengl/kb QT J
L6:     dup2
L7:     lstore_3
L8:     invokestatic Method org/lwjgl/l method2052 (J)V
L11:    iload_0
L12:    aload_2
L13:    iconst_1
L14:    dup
L15:    dup
L16:    pop2
L17:    invokestatic Method org/lwjgl/l method2041 (Ljava/nio/IntBuffer;I)V
L20:    iload_1
L21:    aload_2
L22:    invokestatic Method org/lwjgl/MemoryUtil method1884 (Ljava/nio/IntBuffer;)J
L25:    lload_3
L26:    invokestatic Method org/lwjgl/opengl/GL15 nglGetQueryObjectiv (IIJJ)V
L29:    return
L30:    
    .end code
.end method

.method public static method4024 : (IJLjava/nio/ByteBuffer;)V
    .code stack 9 locals 6
L0:     invokestatic Method org/lwjgl/opengl/GLContext method4611 ()Lorg/lwjgl/opengl/kb;
L3:     getfield Field org/lwjgl/opengl/kb Xs J
L6:     dup2
L7:     lstore 4
L9:     invokestatic Method org/lwjgl/l method2052 (J)V
L12:    iload_0
L13:    aload_3
L14:    invokestatic Method org/lwjgl/l method2034 (Ljava/nio/ByteBuffer;)V
L17:    lload_1
L18:    aload_3
L19:    invokevirtual Method java/nio/ByteBuffer remaining ()I
L22:    i2l
L23:    aload_3
L24:    invokestatic Method org/lwjgl/MemoryUtil method1873 (Ljava/nio/ByteBuffer;)J
L27:    lload 4
L29:    invokestatic Method org/lwjgl/opengl/GL15 nglGetBufferSubData (IJJJJ)V
L32:    return
L33:    
    .end code
.end method

.method public static method4025 : (IJLjava/nio/DoubleBuffer;)V
    .code stack 9 locals 6
L0:     invokestatic Method org/lwjgl/opengl/GLContext method4611 ()Lorg/lwjgl/opengl/kb;
L3:     getfield Field org/lwjgl/opengl/kb gD J
L6:     dup2
L7:     lstore 4
L9:     invokestatic Method org/lwjgl/l method2052 (J)V
L12:    iload_0
L13:    aload_3
L14:    invokestatic Method org/lwjgl/l method2036 (Ljava/nio/DoubleBuffer;)V
L17:    lload_1
L18:    aload_3
L19:    invokevirtual Method java/nio/DoubleBuffer remaining ()I
L22:    iconst_3
L23:    iconst_1
L24:    dup
L25:    pop2
L26:    ishl
L27:    i2l
L28:    aload_3
L29:    invokestatic Method org/lwjgl/MemoryUtil method1840 (Ljava/nio/DoubleBuffer;)J
L32:    lload 4
L34:    invokestatic Method org/lwjgl/opengl/GL15 nglBufferSubData (IJJJJ)V
L37:    return
L38:    
    .end code
.end method

.method static native nglBindBuffer : (IIJ)V
.end method

.method static native nglEndQuery : (IJ)V
.end method

.method static native nglGenBuffers : (IJJ)V
.end method

.method public static method4026 : (ILjava/nio/DoubleBuffer;I)V
    .code stack 8 locals 5
L0:     invokestatic Method org/lwjgl/opengl/GLContext method4611 ()Lorg/lwjgl/opengl/kb;
L3:     getfield Field org/lwjgl/opengl/kb jg J
L6:     dup2
L7:     lstore_3
L8:     invokestatic Method org/lwjgl/l method2052 (J)V
L11:    iload_0
L12:    aload_1
L13:    invokestatic Method org/lwjgl/l method2036 (Ljava/nio/DoubleBuffer;)V
L16:    aload_1
L17:    invokevirtual Method java/nio/DoubleBuffer remaining ()I
L20:    iconst_3
L21:    iconst_1
L22:    dup
L23:    pop2
L24:    ishl
L25:    i2l
L26:    aload_1
L27:    invokestatic Method org/lwjgl/MemoryUtil method1840 (Ljava/nio/DoubleBuffer;)J
L30:    iload_2
L31:    lload_3
L32:    invokestatic Method org/lwjgl/opengl/GL15 nglBufferData (IJJIJ)V
L35:    return
L36:    
    .end code
.end method

.method public static method4027 : (IILjava/nio/ByteBuffer;)Ljava/nio/ByteBuffer;
    .code stack 7 locals 6
L0:     invokestatic Method org/lwjgl/opengl/GLContext method4611 ()Lorg/lwjgl/opengl/kb;
L3:     astore_3
L4:     aload_2
L5:     aload_3
L6:     getfield Field org/lwjgl/opengl/kb mL J
L9:     dup2
L10:    lstore 4
L12:    invokestatic Method org/lwjgl/l method2052 (J)V
L15:    ifnull L22
L18:    aload_2
L19:    invokestatic Method org/lwjgl/l method2034 (Ljava/nio/ByteBuffer;)V
L22:    iload_0
L23:    iload_1
L24:    aload_3
L25:    iload_0
L26:    invokestatic Method org/lwjgl/opengl/Zd method5438 (Lorg/lwjgl/opengl/kb;I)I
L29:    i2l
L30:    aload_2
L31:    lload 4
L33:    invokestatic Method org/lwjgl/opengl/GL15 nglMapBuffer (IIJLjava/nio/ByteBuffer;J)Ljava/nio/ByteBuffer;
L36:    astore_1
L37:    getstatic Field org/lwjgl/LWJGLUtil CHECKS Z
L40:    ifeq L50
L43:    aload_1
L44:    ifnonnull L50
L47:    aconst_null
L48:    areturn
L49:    athrow
L50:    aload_1
L51:    invokestatic Method java/nio/ByteOrder nativeOrder ()Ljava/nio/ByteOrder;
L54:    invokevirtual Method java/nio/ByteBuffer order (Ljava/nio/ByteOrder;)Ljava/nio/ByteBuffer;
L57:    areturn
L58:    
        .attribute StackMap b'\x00\x03\x00\x16\x00\x05\x01\x01\x07\x00\xC6\x07\x00\x72\x04\x00\x00\x00\x31\x00\x00\x00\x01\x07\x01\x63\x00\x32\x00\x05\x01\x07\x00\xC6\x07\x00\xC6\x07\x00\x72\x04\x00\x00'
    .end code
.end method

.method public static method4028 : (IILjava/nio/IntBuffer;)V
    .code stack 6 locals 5
L0:     invokestatic Method org/lwjgl/opengl/GLContext method4611 ()Lorg/lwjgl/opengl/kb;
L3:     getfield Field org/lwjgl/opengl/kb CJ J
L6:     dup2
L7:     lstore_3
L8:     invokestatic Method org/lwjgl/l method2052 (J)V
L11:    iload_0
L12:    aload_2
L13:    iconst_1
L14:    dup
L15:    dup
L16:    pop2
L17:    invokestatic Method org/lwjgl/l method2041 (Ljava/nio/IntBuffer;I)V
L20:    iload_1
L21:    aload_2
L22:    invokestatic Method org/lwjgl/MemoryUtil method1884 (Ljava/nio/IntBuffer;)J
L25:    lload_3
L26:    invokestatic Method org/lwjgl/opengl/GL15 nglGetQueryObjectuiv (IIJJ)V
L29:    return
L30:    
    .end code
.end method

.method static native nglGetQueryObjectiv : (IIJJ)V
.end method

.method public static method4029 : (II)I
    .code stack 6 locals 5
L0:     invokestatic Method org/lwjgl/opengl/GLContext method4611 ()Lorg/lwjgl/opengl/kb;
L3:     dup
L4:     getfield Field org/lwjgl/opengl/kb QT J
L7:     dup2
L8:     lstore_3
L9:     invokestatic Method org/lwjgl/l method2052 (J)V
L12:    invokestatic Method org/lwjgl/opengl/bB method5467 (Lorg/lwjgl/opengl/kb;)Ljava/nio/IntBuffer;
L15:    astore_2
L16:    iload_0
L17:    iload_1
L18:    aload_2
L19:    invokestatic Method org/lwjgl/MemoryUtil method1884 (Ljava/nio/IntBuffer;)J
L22:    lload_3
L23:    invokestatic Method org/lwjgl/opengl/GL15 nglGetQueryObjectiv (IIJJ)V
L26:    aload_2
L27:    iconst_0
L28:    iconst_1
L29:    dup
L30:    pop2
L31:    invokevirtual Method java/nio/IntBuffer get (I)I
L34:    ireturn
L35:    
    .end code
.end method

.method static native nglGetQueryObjectuiv : (IIJJ)V
.end method

.method public static method4030 : (II)I
    .code stack 6 locals 5
L0:     invokestatic Method org/lwjgl/opengl/GLContext method4611 ()Lorg/lwjgl/opengl/kb;
L3:     dup
L4:     getfield Field org/lwjgl/opengl/kb WN J
L7:     dup2
L8:     lstore_3
L9:     invokestatic Method org/lwjgl/l method2052 (J)V
L12:    invokestatic Method org/lwjgl/opengl/bB method5467 (Lorg/lwjgl/opengl/kb;)Ljava/nio/IntBuffer;
L15:    astore_2
L16:    iload_0
L17:    iload_1
L18:    aload_2
L19:    invokestatic Method org/lwjgl/MemoryUtil method1884 (Ljava/nio/IntBuffer;)J
L22:    lload_3
L23:    invokestatic Method org/lwjgl/opengl/GL15 nglGetQueryiv (IIJJ)V
L26:    aload_2
L27:    iconst_0
L28:    iconst_1
L29:    dup
L30:    pop2
L31:    invokevirtual Method java/nio/IntBuffer get (I)I
L34:    ireturn
L35:    
    .end code
.end method

.method public static method4031 : (II)Ljava/nio/ByteBuffer;
    .code stack 6 locals 5
L0:     invokestatic Method org/lwjgl/opengl/GLContext method4611 ()Lorg/lwjgl/opengl/kb;
L3:     dup
L4:     astore_2
L5:     getfield Field org/lwjgl/opengl/kb field5430 J
L8:     dup2
L9:     lstore_3
L10:    invokestatic Method org/lwjgl/l method2052 (J)V
L13:    iload_1
L14:    aload_2
L15:    iload_0
L16:    dup_x2
L17:    invokestatic Method org/lwjgl/opengl/Zd method5438 (Lorg/lwjgl/opengl/kb;I)I
L20:    i2l
L21:    lload_3
L22:    invokestatic Method org/lwjgl/opengl/GL15 nglGetBufferPointerv (IIJJ)Ljava/nio/ByteBuffer;
L25:    astore_1
L26:    getstatic Field org/lwjgl/LWJGLUtil CHECKS Z
L29:    ifeq L39
L32:    aload_1
L33:    ifnonnull L39
L36:    aconst_null
L37:    areturn
L38:    athrow
L39:    aload_1
L40:    invokestatic Method java/nio/ByteOrder nativeOrder ()Ljava/nio/ByteOrder;
L43:    invokevirtual Method java/nio/ByteBuffer order (Ljava/nio/ByteOrder;)Ljava/nio/ByteBuffer;
L46:    areturn
L47:    
        .attribute StackMap b'\x00\x02\x00\x26\x00\x00\x00\x01\x07\x01\x63\x00\x27\x00\x04\x01\x07\x00\xC6\x07\x00\x72\x04\x00\x00'
    .end code
.end method

.method static native nglUnmapBuffer : (IJ)Z
.end method

.method public static method4032 : (IJLjava/nio/ShortBuffer;)V
    .code stack 9 locals 6
L0:     invokestatic Method org/lwjgl/opengl/GLContext method4611 ()Lorg/lwjgl/opengl/kb;
L3:     getfield Field org/lwjgl/opengl/kb gD J
L6:     dup2
L7:     lstore 4
L9:     invokestatic Method org/lwjgl/l method2052 (J)V
L12:    iload_0
L13:    aload_3
L14:    invokestatic Method org/lwjgl/l method2057 (Ljava/nio/ShortBuffer;)V
L17:    lload_1
L18:    aload_3
L19:    invokevirtual Method java/nio/ShortBuffer remaining ()I
L22:    iconst_1
L23:    dup
L24:    dup
L25:    pop2
L26:    ishl
L27:    i2l
L28:    aload_3
L29:    invokestatic Method org/lwjgl/MemoryUtil method1853 (Ljava/nio/ShortBuffer;)J
L32:    lload 4
L34:    invokestatic Method org/lwjgl/opengl/GL15 nglBufferSubData (IJJJJ)V
L37:    return
L38:    
    .end code
.end method

.method public static method4033 : (Ljava/nio/IntBuffer;)V
    .code stack 5 locals 3
L0:     invokestatic Method org/lwjgl/opengl/GLContext method4611 ()Lorg/lwjgl/opengl/kb;
L3:     getfield Field org/lwjgl/opengl/kb GD J
L6:     dup2
L7:     lstore_1
L8:     invokestatic Method org/lwjgl/l method2052 (J)V
L11:    aload_0
L12:    dup
L13:    invokestatic Method org/lwjgl/l method2043 (Ljava/nio/IntBuffer;)V
L16:    invokevirtual Method java/nio/IntBuffer remaining ()I
L19:    aload_0
L20:    invokestatic Method org/lwjgl/MemoryUtil method1884 (Ljava/nio/IntBuffer;)J
L23:    lload_1
L24:    invokestatic Method org/lwjgl/opengl/GL15 nglDeleteQueries (IJJ)V
L27:    return
L28:    
    .end code
.end method

.method public static method4034 : (II)I
    .code stack 2 locals 2
L0:     iload_0
L1:     iload_1
L2:     invokestatic Method org/lwjgl/opengl/GL15 method4030 (II)I
L5:     ireturn
L6:     
    .end code
    .deprecated
.end method

.method public static method4035 : (IJI)V
    .code stack 8 locals 6
L0:     invokestatic Method org/lwjgl/opengl/GLContext method4611 ()Lorg/lwjgl/opengl/kb;
L3:     getfield Field org/lwjgl/opengl/kb jg J
L6:     dup2
L7:     lstore 4
L9:     invokestatic Method org/lwjgl/l method2052 (J)V
L12:    iload_0
L13:    lload_1
L14:    lconst_0
L15:    iload_3
L16:    lload 4
L18:    invokestatic Method org/lwjgl/opengl/GL15 nglBufferData (IJJIJ)V
L21:    return
L22:    
    .end code
.end method

.method public static method4036 : ()I
    .code stack 5 locals 3
L0:     invokestatic Method org/lwjgl/opengl/GLContext method4611 ()Lorg/lwjgl/opengl/kb;
L3:     dup
L4:     getfield Field org/lwjgl/opengl/kb No J
L7:     dup2
L8:     lstore_0
L9:     invokestatic Method org/lwjgl/l method2052 (J)V
L12:    invokestatic Method org/lwjgl/opengl/bB method5467 (Lorg/lwjgl/opengl/kb;)Ljava/nio/IntBuffer;
L15:    astore_2
L16:    iconst_1
L17:    dup
L18:    dup
L19:    pop2
L20:    aload_2
L21:    invokestatic Method org/lwjgl/MemoryUtil method1884 (Ljava/nio/IntBuffer;)J
L24:    lload_0
L25:    invokestatic Method org/lwjgl/opengl/GL15 nglGenBuffers (IJJ)V
L28:    aload_2
L29:    iconst_0
L30:    iconst_1
L31:    dup
L32:    pop2
L33:    invokevirtual Method java/nio/IntBuffer get (I)I
L36:    ireturn
L37:    
    .end code
.end method

.method public static method4037 : (I)Z
    .code stack 4 locals 3
L0:     invokestatic Method org/lwjgl/opengl/GLContext method4611 ()Lorg/lwjgl/opengl/kb;
L3:     getfield Field org/lwjgl/opengl/kb field5445 J
L6:     dup2
L7:     lstore_1
L8:     invokestatic Method org/lwjgl/l method2052 (J)V
L11:    iload_0
L12:    lload_1
L13:    invokestatic Method org/lwjgl/opengl/GL15 nglIsBuffer (IJ)Z
L16:    ireturn
L17:    
    .end code
.end method

.method public static method4038 : (II)I
    .code stack 6 locals 5
L0:     invokestatic Method org/lwjgl/opengl/GLContext method4611 ()Lorg/lwjgl/opengl/kb;
L3:     dup
L4:     getfield Field org/lwjgl/opengl/kb CJ J
L7:     dup2
L8:     lstore_3
L9:     invokestatic Method org/lwjgl/l method2052 (J)V
L12:    invokestatic Method org/lwjgl/opengl/bB method5467 (Lorg/lwjgl/opengl/kb;)Ljava/nio/IntBuffer;
L15:    astore_2
L16:    iload_0
L17:    iload_1
L18:    aload_2
L19:    invokestatic Method org/lwjgl/MemoryUtil method1884 (Ljava/nio/IntBuffer;)J
L22:    lload_3
L23:    invokestatic Method org/lwjgl/opengl/GL15 nglGetQueryObjectuiv (IIJJ)V
L26:    aload_2
L27:    iconst_0
L28:    iconst_1
L29:    dup
L30:    pop2
L31:    invokevirtual Method java/nio/IntBuffer get (I)I
L34:    ireturn
L35:    
    .end code
.end method

.method static native nglGetBufferParameteriv : (IIJJ)V
.end method

.method static native nglIsBuffer : (IJ)Z
.end method

.method public static method4039 : (IJLjava/nio/ByteBuffer;)V
    .code stack 9 locals 6
L0:     invokestatic Method org/lwjgl/opengl/GLContext method4611 ()Lorg/lwjgl/opengl/kb;
L3:     getfield Field org/lwjgl/opengl/kb gD J
L6:     dup2
L7:     lstore 4
L9:     invokestatic Method org/lwjgl/l method2052 (J)V
L12:    iload_0
L13:    aload_3
L14:    invokestatic Method org/lwjgl/l method2034 (Ljava/nio/ByteBuffer;)V
L17:    lload_1
L18:    aload_3
L19:    invokevirtual Method java/nio/ByteBuffer remaining ()I
L22:    i2l
L23:    aload_3
L24:    invokestatic Method org/lwjgl/MemoryUtil method1873 (Ljava/nio/ByteBuffer;)J
L27:    lload 4
L29:    invokestatic Method org/lwjgl/opengl/GL15 nglBufferSubData (IJJJJ)V
L32:    return
L33:    
    .end code
.end method

.method static native nglMapBuffer : (IIJLjava/nio/ByteBuffer;J)Ljava/nio/ByteBuffer;
.end method

.method public static method4040 : (ILjava/nio/ShortBuffer;I)V
    .code stack 8 locals 5
L0:     invokestatic Method org/lwjgl/opengl/GLContext method4611 ()Lorg/lwjgl/opengl/kb;
L3:     getfield Field org/lwjgl/opengl/kb jg J
L6:     dup2
L7:     lstore_3
L8:     invokestatic Method org/lwjgl/l method2052 (J)V
L11:    iload_0
L12:    aload_1
L13:    invokestatic Method org/lwjgl/l method2057 (Ljava/nio/ShortBuffer;)V
L16:    aload_1
L17:    invokevirtual Method java/nio/ShortBuffer remaining ()I
L20:    iconst_1
L21:    dup
L22:    dup
L23:    pop2
L24:    ishl
L25:    i2l
L26:    aload_1
L27:    invokestatic Method org/lwjgl/MemoryUtil method1853 (Ljava/nio/ShortBuffer;)J
L30:    iload_2
L31:    lload_3
L32:    invokestatic Method org/lwjgl/opengl/GL15 nglBufferData (IJJIJ)V
L35:    return
L36:    
    .end code
.end method

.method public static method4041 : (IIJLjava/nio/ByteBuffer;)Ljava/nio/ByteBuffer;
    .code stack 7 locals 7
L0:     invokestatic Method org/lwjgl/opengl/GLContext method4611 ()Lorg/lwjgl/opengl/kb;
L3:     getfield Field org/lwjgl/opengl/kb mL J
L6:     dup2
L7:     lstore 5
L9:     invokestatic Method org/lwjgl/l method2052 (J)V
L12:    aload 4
L14:    ifnull L22
L17:    aload 4
L19:    invokestatic Method org/lwjgl/l method2034 (Ljava/nio/ByteBuffer;)V
L22:    iload_0
L23:    iload_1
L24:    lload_2
L25:    aload 4
L27:    lload 5
L29:    invokestatic Method org/lwjgl/opengl/GL15 nglMapBuffer (IIJLjava/nio/ByteBuffer;J)Ljava/nio/ByteBuffer;
L32:    astore_1
L33:    getstatic Field org/lwjgl/LWJGLUtil CHECKS Z
L36:    ifeq L46
L39:    aload_1
L40:    ifnonnull L46
L43:    aconst_null
L44:    areturn
L45:    athrow
L46:    aload_1
L47:    invokestatic Method java/nio/ByteOrder nativeOrder ()Ljava/nio/ByteOrder;
L50:    invokevirtual Method java/nio/ByteBuffer order (Ljava/nio/ByteOrder;)Ljava/nio/ByteBuffer;
L53:    areturn
L54:    
        .attribute StackMap b'\x00\x03\x00\x16\x00\x05\x01\x01\x04\x07\x00\xC6\x04\x00\x00\x00\x2D\x00\x00\x00\x01\x07\x01\x63\x00\x2E\x00\x05\x01\x07\x00\xC6\x04\x07\x00\xC6\x04\x00\x00'
    .end code
.end method

.method private <init> : ()V
    .code stack 1 locals 1
L0:     aload_0
L1:     invokespecial Method java/lang/Object <init> ()V
L4:     return
L5:     
    .end code
.end method

.method public static method4042 : (IJLjava/nio/IntBuffer;)V
    .code stack 9 locals 6
L0:     invokestatic Method org/lwjgl/opengl/GLContext method4611 ()Lorg/lwjgl/opengl/kb;
L3:     getfield Field org/lwjgl/opengl/kb Xs J
L6:     dup2
L7:     lstore 4
L9:     invokestatic Method org/lwjgl/l method2052 (J)V
L12:    iload_0
L13:    aload_3
L14:    invokestatic Method org/lwjgl/l method2043 (Ljava/nio/IntBuffer;)V
L17:    lload_1
L18:    aload_3
L19:    invokevirtual Method java/nio/IntBuffer remaining ()I
L22:    iconst_2
L23:    iconst_1
L24:    dup
L25:    pop2
L26:    ishl
L27:    i2l
L28:    aload_3
L29:    invokestatic Method org/lwjgl/MemoryUtil method1884 (Ljava/nio/IntBuffer;)J
L32:    lload 4
L34:    invokestatic Method org/lwjgl/opengl/GL15 nglGetBufferSubData (IJJJJ)V
L37:    return
L38:    
    .end code
.end method

.method public static method4043 : (I)V
    .code stack 5 locals 4
L0:     invokestatic Method org/lwjgl/opengl/GLContext method4611 ()Lorg/lwjgl/opengl/kb;
L3:     dup
L4:     astore_1
L5:     getfield Field org/lwjgl/opengl/kb GD J
L8:     dup2
L9:     lstore_2
L10:    invokestatic Method org/lwjgl/l method2052 (J)V
L13:    iconst_1
L14:    dup
L15:    dup
L16:    pop2
L17:    aload_1
L18:    iload_0
L19:    invokestatic Method org/lwjgl/opengl/bB method5479 (Lorg/lwjgl/opengl/kb;I)J
L22:    lload_2
L23:    invokestatic Method org/lwjgl/opengl/GL15 nglDeleteQueries (IJJ)V
L26:    return
L27:    
    .end code
.end method

.method public static method4044 : (Ljava/nio/IntBuffer;)V
    .code stack 5 locals 3
L0:     invokestatic Method org/lwjgl/opengl/GLContext method4611 ()Lorg/lwjgl/opengl/kb;
L3:     getfield Field org/lwjgl/opengl/kb No J
L6:     dup2
L7:     lstore_1
L8:     invokestatic Method org/lwjgl/l method2052 (J)V
L11:    aload_0
L12:    dup
L13:    invokestatic Method org/lwjgl/l method2043 (Ljava/nio/IntBuffer;)V
L16:    invokevirtual Method java/nio/IntBuffer remaining ()I
L19:    aload_0
L20:    invokestatic Method org/lwjgl/MemoryUtil method1884 (Ljava/nio/IntBuffer;)J
L23:    lload_1
L24:    invokestatic Method org/lwjgl/opengl/GL15 nglGenBuffers (IJJ)V
L27:    return
L28:    
    .end code
.end method

.method static native nglDeleteQueries : (IJJ)V
.end method

.method static native nglBeginQuery : (IIJ)V
.end method

.method static native nglGetBufferSubData : (IJJJJ)V
.end method
.end class
