.version 49 0
.class public final super org/lwjgl/opengl/GL20
.super java/lang/Object
.field public static final W I = 36005
.field public static final Q I = 35632
.field public static final T I = 34854
.field public static final r I = 35669
.field public static final x I = 35723
.field public static final n I = 35657
.field public static final M I = 35712
.field public static final L I = 34370
.field public static final H I = 34914
.field public static final d I = 34855
.field public static final e I = 35665
.field public static final g I = 35659
.field public static final k I = 34861
.field public static final a I = 34852
.field public static final F I = 34857
.field public static final A I = 35724
.field public static final E I = 36001
.field public static final C I = 34371
.field public static final K I = 35633
.field public static final G I = 34929
.field public static final B I = 35663
.field public static final c I = 35725
.field public static final "synchronized" I = 34868
.field public static final i I = 35718
.field public static final m I = 35674
.field public static final h I = 34338
.field public static final J I = 35716
.field public static final l I = 34921
.field public static final D I = 35673
.field public static final f I = 35679
.field public static final j I = 34817
.field public static final I I = 35719
.field public static final b I = 34340
.field public static final implements I = 34866
.field public static final return I = 35672
.field public static final default I = 35717
.field public static final switch I = 34818
.field public static final "interface" I = 36003
.field public static final "private" I = 34819
.field public static final assert I = 34373
.field public static final boolean I = 34859
.field public static final "strictfp" I = 35680
.field public static final "abstract" I = 36002
.field public static final "public" I = 35722
.field public static final "volatile" I = 35678
.field public static final double I = 34341
.field public static final throw I = 35676
.field public static final package I = 34863
.field public static final finally I = 34342
.field public static final "transient" I = 35660
.field public static final while I = 35715
.field public static final instanceof I = 36000
.field public static final "protected" I = 35720
.field public static final import I = 35670
.field public static final "native" I = 34913
.field public static final throws I = 35682
.field public static final "static" I = 35714
.field public static final continue I = 34853
.field public static final extends I = 35671
.field public static final float I = 34816
.field public static final "final" I = 35666
.field public static final catch I = 35681
.field public static final false I = 36004
.field public static final class I = 35668
.field public static final if I = 35658
.field public static final true I = 34862
.field public static final for I = 34877
.field public static final case I = 34856
.field public static final byte I = 34339
.field public static final "super" I = 35661
.field public static final int I = 35656
.field public static final short I = 34867
.field public static final goto I = 34864
.field public static final break I = 35713
.field public static final long I = 34858
.field public static final void I = 34922
.field public static final try I = 34865
.field public static final const I = 34860
.field public static final new I = 35664
.field public static final null I = 34930
.field public static final this I = 35721
.field public static final char I = 35675
.field public static final else I = 32777
.field public static final "enum" I = 35677
.field public static final do I = 35667

.method static native nglGetAttachedShaders : (IIJJJ)V
.end method

.method public static const : (III)V
    .code stack 5 locals 5
L0:     invokestatic Method org/lwjgl/opengl/GLContext break ()Lorg/lwjgl/opengl/kb;
L3:     getfield Field org/lwjgl/opengl/kb DD J
L6:     dup2
L7:     lstore_3
L8:     invokestatic Method org/lwjgl/l break (J)V
L11:    iload_0
L12:    iload_1
L13:    iload_2
L14:    lload_3
L15:    invokestatic Method org/lwjgl/opengl/GL20 nglUniform2i (IIIJ)V
L18:    return
L19:    
    .end code
.end method

.method static native nglVertexAttrib3s : (ISSSJ)V
.end method

.method public static long : (II)V
    .code stack 4 locals 4
L0:     invokestatic Method org/lwjgl/opengl/GLContext break ()Lorg/lwjgl/opengl/kb;
L3:     getfield Field org/lwjgl/opengl/kb BQ J
L6:     dup2
L7:     lstore_2
L8:     invokestatic Method org/lwjgl/l break (J)V
L11:    iload_0
L12:    iload_1
L13:    lload_2
L14:    invokestatic Method org/lwjgl/opengl/GL20 nglAttachShader (IIJ)V
L17:    return
L18:    
    .end code
.end method

.method static native nglEnableVertexAttribArray : (IJ)V
.end method

.method public static const : (ILjava/lang/CharSequence;)V
    .code stack 7 locals 5
L0:     invokestatic Method org/lwjgl/opengl/GLContext break ()Lorg/lwjgl/opengl/kb;
L3:     dup
L4:     astore_2
L5:     getfield Field org/lwjgl/opengl/kb kb J
L8:     dup2
L9:     lstore_3
L10:    invokestatic Method org/lwjgl/l break (J)V
L13:    iload_0
L14:    iconst_1
L15:    dup
L16:    dup
L17:    pop2
L18:    aload_2
L19:    aload_1
L20:    invokestatic Method org/lwjgl/opengl/bB else (Lorg/lwjgl/opengl/kb;Ljava/lang/CharSequence;)J
L23:    aload_1
L24:    invokeinterface InterfaceMethod java/lang/CharSequence length ()I 1
L29:    lload_3
L30:    invokestatic Method org/lwjgl/opengl/GL20 nglShaderSource (IIJIJ)V
L33:    return
L34:    
    .end code
.end method

.method public static class : (II)I
    .code stack 6 locals 5
L0:     invokestatic Method org/lwjgl/opengl/GLContext break ()Lorg/lwjgl/opengl/kb;
L3:     dup
L4:     getfield Field org/lwjgl/opengl/kb nL J
L7:     dup2
L8:     lstore_3
L9:     invokestatic Method org/lwjgl/l break (J)V
L12:    invokestatic Method org/lwjgl/opengl/bB short (Lorg/lwjgl/opengl/kb;)Ljava/nio/IntBuffer;
L15:    astore_2
L16:    iload_0
L17:    iload_1
L18:    aload_2
L19:    invokestatic Method org/lwjgl/MemoryUtil break (Ljava/nio/IntBuffer;)J
L22:    lload_3
L23:    invokestatic Method org/lwjgl/opengl/GL20 nglGetProgramiv (IIJJ)V
L26:    aload_2
L27:    iconst_0
L28:    iconst_1
L29:    dup
L30:    pop2
L31:    invokevirtual Method java/nio/IntBuffer get (I)I
L34:    ireturn
L35:    
    .end code
.end method

.method public static else : (IF)V
    .code stack 4 locals 4
L0:     invokestatic Method org/lwjgl/opengl/GLContext break ()Lorg/lwjgl/opengl/kb;
L3:     getfield Field org/lwjgl/opengl/kb rg J
L6:     dup2
L7:     lstore_2
L8:     invokestatic Method org/lwjgl/l break (J)V
L11:    iload_0
L12:    fload_1
L13:    lload_2
L14:    invokestatic Method org/lwjgl/opengl/GL20 nglUniform1f (IFJ)V
L17:    return
L18:    
    .end code
.end method

.method public static if : (II)V
    .code stack 4 locals 4
L0:     invokestatic Method org/lwjgl/opengl/GLContext break ()Lorg/lwjgl/opengl/kb;
L3:     getfield Field org/lwjgl/opengl/kb nf J
L6:     dup2
L7:     lstore_2
L8:     invokestatic Method org/lwjgl/l break (J)V
L11:    iload_0
L12:    iload_1
L13:    lload_2
L14:    invokestatic Method org/lwjgl/opengl/GL20 nglUniform1i (IIJ)V
L17:    return
L18:    
    .end code
.end method

.method static native nglGetVertexAttribfv : (IIJJ)V
.end method

.method static native nglVertexAttrib1s : (ISJ)V
.end method

.method public static const : (IIII)V
    .code stack 6 locals 6
L0:     invokestatic Method org/lwjgl/opengl/GLContext break ()Lorg/lwjgl/opengl/kb;
L3:     getfield Field org/lwjgl/opengl/kb WQ J
L6:     dup2
L7:     lstore 4
L9:     invokestatic Method org/lwjgl/l break (J)V
L12:    iload_0
L13:    iload_1
L14:    iload_2
L15:    iload_3
L16:    lload 4
L18:    invokestatic Method org/lwjgl/opengl/GL20 nglStencilOpSeparate (IIIIJ)V
L21:    return
L22:    
    .end code
.end method

.method public static break : ()I
    .code stack 4 locals 2
L0:     invokestatic Method org/lwjgl/opengl/GLContext break ()Lorg/lwjgl/opengl/kb;
L3:     getfield Field org/lwjgl/opengl/kb ZQ J
L6:     dup2
L7:     lstore_0
L8:     invokestatic Method org/lwjgl/l break (J)V
L11:    lload_0
L12:    invokestatic Method org/lwjgl/opengl/GL20 nglCreateProgram (J)I
L15:    ireturn
L16:    
    .end code
.end method

.method static native nglCreateProgram : (J)I
.end method

.method static native nglGetActiveUniform : (IIIJJJJJ)V
.end method

.method public static char : (II)V
    .code stack 4 locals 4
L0:     invokestatic Method org/lwjgl/opengl/GLContext break ()Lorg/lwjgl/opengl/kb;
L3:     getfield Field org/lwjgl/opengl/kb Fl J
L6:     dup2
L7:     lstore_2
L8:     invokestatic Method org/lwjgl/l break (J)V
L11:    iload_0
L12:    iload_1
L13:    lload_2
L14:    invokestatic Method org/lwjgl/opengl/GL20 nglBlendEquationSeparate (IIJ)V
L17:    return
L18:    
    .end code
.end method

.method public static break : (IIZZILjava/nio/ByteBuffer;)V
    .code stack 9 locals 9
L0:     invokestatic Method org/lwjgl/opengl/GLContext break ()Lorg/lwjgl/opengl/kb;
L3:     astore 6
L5:     aload 5
L7:     aload 6
L9:     dup
L10:    getfield Field org/lwjgl/opengl/kb ch J
L13:    dup2
L14:    lstore 7
L16:    invokestatic Method org/lwjgl/l break (J)V
L19:    invokestatic Method org/lwjgl/opengl/Zd break (Lorg/lwjgl/opengl/kb;)V
L22:    invokestatic Method org/lwjgl/l break (Ljava/nio/ByteBuffer;)V
L25:    getstatic Field org/lwjgl/LWJGLUtil CHECKS Z
L28:    ifeq L43
L31:    aload 6
L33:    invokestatic Method org/lwjgl/opengl/w const (Lorg/lwjgl/opengl/kb;)Lorg/lwjgl/opengl/P;
L36:    getfield Field org/lwjgl/opengl/P do [Ljava/nio/Buffer;
L39:    iload_0
L40:    aload 5
L42:    aastore
L43:    iload_0
L44:    iload_1
L45:    iload_2
L46:    ifeq L60
L49:    sipush 5121
L52:    iconst_1
L53:    dup
L54:    pop2
L55:    iload_3
L56:    goto L67
L59:    athrow
L60:    sipush 5120
L63:    iconst_1
L64:    dup
L65:    pop2
L66:    iload_3
L67:    iload 4
L69:    aload 5
L71:    invokestatic Method org/lwjgl/MemoryUtil const (Ljava/nio/ByteBuffer;)J
L74:    lload 7
L76:    invokestatic Method org/lwjgl/opengl/GL20 nglVertexAttribPointer (IIIZIJJ)V
L79:    return
L80:    
        .attribute StackMap b'\x00\x04\x00\x2B\x00\x08\x01\x01\x01\x01\x01\x07\x01\x3F\x07\x00\xB8\x04\x00\x00\x00\x3B\x00\x00\x00\x01\x07\x01\x41\x00\x3C\x00\x08\x01\x01\x01\x01\x01\x07\x01\x3F\x07\x00\xB8\x04\x00\x02\x01\x01\x00\x43\x00\x08\x01\x01\x01\x01\x01\x07\x01\x3F\x07\x00\xB8\x04\x00\x04\x01\x01\x01\x01'
    .end code
.end method

.method static native nglUniform2fv : (IIJJ)V
.end method

.method private <init> : ()V
    .code stack 1 locals 1
L0:     aload_0
L1:     invokespecial Method java/lang/Object <init> ()V
L4:     return
L5:     
    .end code
.end method

.method public static const : (IZLjava/nio/FloatBuffer;)V
    .code stack 7 locals 5
L0:     invokestatic Method org/lwjgl/opengl/GLContext break ()Lorg/lwjgl/opengl/kb;
L3:     getfield Field org/lwjgl/opengl/kb Xd J
L6:     dup2
L7:     lstore_3
L8:     invokestatic Method org/lwjgl/l break (J)V
L11:    iload_0
L12:    aload_2
L13:    invokestatic Method org/lwjgl/l break (Ljava/nio/FloatBuffer;)V
L16:    aload_2
L17:    invokevirtual Method java/nio/FloatBuffer remaining ()I
L20:    bipush 9
L22:    iconst_1
L23:    dup
L24:    pop2
L25:    idiv
L26:    iload_1
L27:    aload_2
L28:    invokestatic Method org/lwjgl/MemoryUtil break (Ljava/nio/FloatBuffer;)J
L31:    lload_3
L32:    invokestatic Method org/lwjgl/opengl/GL20 nglUniformMatrix3fv (IIZJJ)V
L35:    return
L36:    
    .end code
.end method

.method static native nglUniform4fv : (IIJJ)V
.end method

.method public static break : (ISS)V
    .code stack 5 locals 5
L0:     invokestatic Method org/lwjgl/opengl/GLContext break ()Lorg/lwjgl/opengl/kb;
L3:     getfield Field org/lwjgl/opengl/kb mH J
L6:     dup2
L7:     lstore_3
L8:     invokestatic Method org/lwjgl/l break (J)V
L11:    iload_0
L12:    iload_1
L13:    iload_2
L14:    lload_3
L15:    invokestatic Method org/lwjgl/opengl/GL20 nglVertexAttrib2s (ISSJ)V
L18:    return
L19:    
    .end code
.end method

.method public static new : (I)V
    .code stack 4 locals 3
L0:     invokestatic Method org/lwjgl/opengl/GLContext break ()Lorg/lwjgl/opengl/kb;
L3:     getfield Field org/lwjgl/opengl/kb gF J
L6:     dup2
L7:     lstore_1
L8:     invokestatic Method org/lwjgl/l break (J)V
L11:    iload_0
L12:    lload_1
L13:    invokestatic Method org/lwjgl/opengl/GL20 nglLinkProgram (IJ)V
L16:    return
L17:    
    .end code
.end method

.method static native nglUniform2i : (IIIJ)V
.end method

.method static native nglVertexAttrib2s : (ISSJ)V
.end method

.method public static new : (II)Ljava/lang/String;
    .code stack 9 locals 6
L0:     invokestatic Method org/lwjgl/opengl/GLContext break ()Lorg/lwjgl/opengl/kb;
L3:     dup
L4:     dup2
L5:     getfield Field org/lwjgl/opengl/kb eB J
L8:     dup2
L9:     lstore_3
L10:    invokestatic Method org/lwjgl/l break (J)V
L13:    invokestatic Method org/lwjgl/opengl/bB break (Lorg/lwjgl/opengl/kb;)Ljava/nio/IntBuffer;
L16:    astore_2
L17:    iload_1
L18:    invokestatic Method org/lwjgl/opengl/bB float (Lorg/lwjgl/opengl/kb;I)Ljava/nio/ByteBuffer;
L21:    astore 5
L23:    iload_0
L24:    iload_1
L25:    aload_2
L26:    invokestatic Method org/lwjgl/MemoryUtil break (Ljava/nio/Buffer;)J
L29:    aload 5
L31:    invokestatic Method org/lwjgl/MemoryUtil const (Ljava/nio/ByteBuffer;)J
L34:    lload_3
L35:    invokestatic Method org/lwjgl/opengl/GL20 nglGetShaderSource (IIJJJ)V
L38:    aload 5
L40:    dup
L41:    aload_2
L42:    iconst_0
L43:    iconst_1
L44:    dup
L45:    pop2
L46:    invokevirtual Method java/nio/IntBuffer get (I)I
L49:    invokevirtual Method java/nio/ByteBuffer limit (I)Ljava/nio/Buffer;
L52:    pop
L53:    invokestatic Method org/lwjgl/opengl/bB break (Lorg/lwjgl/opengl/kb;Ljava/nio/ByteBuffer;)Ljava/lang/String;
L56:    areturn
L57:    
    .end code
.end method

.method public static break : (IIZILjava/nio/FloatBuffer;)V
    .code stack 9 locals 8
L0:     invokestatic Method org/lwjgl/opengl/GLContext break ()Lorg/lwjgl/opengl/kb;
L3:     astore 5
L5:     aload 4
L7:     aload 5
L9:     dup
L10:    getfield Field org/lwjgl/opengl/kb ch J
L13:    dup2
L14:    lstore 6
L16:    invokestatic Method org/lwjgl/l break (J)V
L19:    invokestatic Method org/lwjgl/opengl/Zd break (Lorg/lwjgl/opengl/kb;)V
L22:    invokestatic Method org/lwjgl/l break (Ljava/nio/FloatBuffer;)V
L25:    getstatic Field org/lwjgl/LWJGLUtil CHECKS Z
L28:    ifeq L43
L31:    aload 5
L33:    invokestatic Method org/lwjgl/opengl/w const (Lorg/lwjgl/opengl/kb;)Lorg/lwjgl/opengl/P;
L36:    getfield Field org/lwjgl/opengl/P do [Ljava/nio/Buffer;
L39:    iload_0
L40:    aload 4
L42:    aastore
L43:    iload_0
L44:    iload_1
L45:    sipush 5126
L48:    iconst_1
L49:    dup
L50:    pop2
L51:    iload_2
L52:    iload_3
L53:    aload 4
L55:    invokestatic Method org/lwjgl/MemoryUtil break (Ljava/nio/FloatBuffer;)J
L58:    lload 6
L60:    invokestatic Method org/lwjgl/opengl/GL20 nglVertexAttribPointer (IIIZIJJ)V
L63:    return
L64:    
        .attribute StackMap b'\x00\x01\x00\x2B\x00\x07\x01\x01\x01\x01\x07\x01\x56\x07\x00\xB8\x04\x00\x00'
    .end code
.end method

.method static native nglUniformMatrix2fv : (IIZJJ)V
.end method

.method public static const : (ILjava/nio/ByteBuffer;)V
    .code stack 7 locals 4
L0:     invokestatic Method org/lwjgl/opengl/GLContext break ()Lorg/lwjgl/opengl/kb;
L3:     getfield Field org/lwjgl/opengl/kb kb J
L6:     dup2
L7:     lstore_2
L8:     invokestatic Method org/lwjgl/l break (J)V
L11:    iload_0
L12:    aload_1
L13:    invokestatic Method org/lwjgl/l break (Ljava/nio/ByteBuffer;)V
L16:    iconst_1
L17:    dup
L18:    dup
L19:    pop2
L20:    aload_1
L21:    invokestatic Method org/lwjgl/MemoryUtil const (Ljava/nio/ByteBuffer;)J
L24:    aload_1
L25:    invokevirtual Method java/nio/ByteBuffer remaining ()I
L28:    lload_2
L29:    invokestatic Method org/lwjgl/opengl/GL20 nglShaderSource (IIJIJ)V
L32:    return
L33:    
    .end code
.end method

.method public static short : (ILjava/nio/FloatBuffer;)V
    .code stack 6 locals 4
L0:     invokestatic Method org/lwjgl/opengl/GLContext break ()Lorg/lwjgl/opengl/kb;
L3:     getfield Field org/lwjgl/opengl/kb dt J
L6:     dup2
L7:     lstore_2
L8:     invokestatic Method org/lwjgl/l break (J)V
L11:    iload_0
L12:    aload_1
L13:    invokestatic Method org/lwjgl/l break (Ljava/nio/FloatBuffer;)V
L16:    aload_1
L17:    invokevirtual Method java/nio/FloatBuffer remaining ()I
L20:    aload_1
L21:    invokestatic Method org/lwjgl/MemoryUtil break (Ljava/nio/FloatBuffer;)J
L24:    lload_2
L25:    invokestatic Method org/lwjgl/opengl/GL20 nglUniform1fv (IIJJ)V
L28:    return
L29:    
    .end code
.end method

.method static native nglGetUniformfv : (IIJJ)V
.end method

.method static native nglUniform4i : (IIIIIJ)V
.end method

.method static native nglVertexAttrib4f : (IFFFFJ)V
.end method

.method public static try : (I)V
    .code stack 5 locals 4
L0:     invokestatic Method org/lwjgl/opengl/GLContext break ()Lorg/lwjgl/opengl/kb;
L3:     dup
L4:     astore_1
L5:     getfield Field org/lwjgl/opengl/kb jT J
L8:     dup2
L9:     lstore_2
L10:    invokestatic Method org/lwjgl/l break (J)V
L13:    iconst_1
L14:    dup
L15:    dup
L16:    pop2
L17:    aload_1
L18:    iload_0
L19:    invokestatic Method org/lwjgl/opengl/bB const (Lorg/lwjgl/opengl/kb;I)J
L22:    lload_2
L23:    invokestatic Method org/lwjgl/opengl/GL20 nglDrawBuffers (IJJ)V
L26:    return
L27:    
    .end code
.end method

.method public static break : (IIIZIJ)V
    .code stack 9 locals 9
L0:     invokestatic Method org/lwjgl/opengl/GLContext break ()Lorg/lwjgl/opengl/kb;
L3:     dup
L4:     getfield Field org/lwjgl/opengl/kb ch J
L7:     dup2
L8:     lstore 7
L10:    invokestatic Method org/lwjgl/l break (J)V
L13:    invokestatic Method org/lwjgl/opengl/Zd float (Lorg/lwjgl/opengl/kb;)V
L16:    iload_0
L17:    iload_1
L18:    iload_2
L19:    iload_3
L20:    iload 4
L22:    lload 5
L24:    lload 7
L26:    invokestatic Method org/lwjgl/opengl/GL20 nglVertexAttribPointerBO (IIIZIJJ)V
L29:    return
L30:    
    .end code
.end method

.method static native nglVertexAttrib4d : (IDDDDJ)V
.end method

.method public static try : (II)V
    .code stack 4 locals 4
L0:     invokestatic Method org/lwjgl/opengl/GLContext break ()Lorg/lwjgl/opengl/kb;
L3:     getfield Field org/lwjgl/opengl/kb Ub J
L6:     dup2
L7:     lstore_2
L8:     invokestatic Method org/lwjgl/l break (J)V
L11:    iload_0
L12:    iload_1
L13:    lload_2
L14:    invokestatic Method org/lwjgl/opengl/GL20 nglDetachShader (IIJ)V
L17:    return
L18:    
    .end code
.end method

.method public static this : (I)V
    .code stack 4 locals 3
L0:     invokestatic Method org/lwjgl/opengl/GLContext break ()Lorg/lwjgl/opengl/kb;
L3:     getfield Field org/lwjgl/opengl/kb uc J
L6:     dup2
L7:     lstore_1
L8:     invokestatic Method org/lwjgl/l break (J)V
L11:    iload_0
L12:    lload_1
L13:    invokestatic Method org/lwjgl/opengl/GL20 nglEnableVertexAttribArray (IJ)V
L16:    return
L17:    
    .end code
.end method

.method static native nglGetUniformiv : (IIJJ)V
.end method

.method public static this : (II)V
    .code stack 4 locals 4
L0:     invokestatic Method org/lwjgl/opengl/GLContext break ()Lorg/lwjgl/opengl/kb;
L3:     getfield Field org/lwjgl/opengl/kb XL J
L6:     dup2
L7:     lstore_2
L8:     invokestatic Method org/lwjgl/l break (J)V
L11:    iload_0
L12:    iload_1
L13:    lload_2
L14:    invokestatic Method org/lwjgl/opengl/GL20 nglStencilMaskSeparate (IIJ)V
L17:    return
L18:    
    .end code
.end method

.method public static const : (ILjava/nio/FloatBuffer;)V
    .code stack 6 locals 4
L0:     invokestatic Method org/lwjgl/opengl/GLContext break ()Lorg/lwjgl/opengl/kb;
L3:     getfield Field org/lwjgl/opengl/kb Ik J
L6:     dup2
L7:     lstore_2
L8:     invokestatic Method org/lwjgl/l break (J)V
L11:    iload_0
L12:    aload_1
L13:    invokestatic Method org/lwjgl/l break (Ljava/nio/FloatBuffer;)V
L16:    aload_1
L17:    invokevirtual Method java/nio/FloatBuffer remaining ()I
L20:    iconst_3
L21:    iconst_1
L22:    dup
L23:    pop2
L24:    idiv
L25:    aload_1
L26:    invokestatic Method org/lwjgl/MemoryUtil break (Ljava/nio/FloatBuffer;)J
L29:    lload_2
L30:    invokestatic Method org/lwjgl/opengl/GL20 nglUniform3fv (IIJJ)V
L33:    return
L34:    
    .end code
.end method

.method static native nglGetProgramiv : (IIJJ)V
.end method

.method static native nglUniformMatrix3fv : (IIZJJ)V
.end method

.method static native nglUniform1iv : (IIJJ)V
.end method

.method public static short : (IILjava/nio/IntBuffer;)V
    .code stack 6 locals 5
L0:     invokestatic Method org/lwjgl/opengl/GLContext break ()Lorg/lwjgl/opengl/kb;
L3:     getfield Field org/lwjgl/opengl/kb Mt J
L6:     dup2
L7:     lstore_3
L8:     invokestatic Method org/lwjgl/l break (J)V
L11:    iload_0
L12:    aload_2
L13:    invokestatic Method org/lwjgl/l else (Ljava/nio/IntBuffer;)V
L16:    iload_1
L17:    aload_2
L18:    invokestatic Method org/lwjgl/MemoryUtil break (Ljava/nio/IntBuffer;)J
L21:    lload_3
L22:    invokestatic Method org/lwjgl/opengl/GL20 nglGetUniformiv (IIJJ)V
L25:    return
L26:    
    .end code
.end method

.method static native nglGetActiveAttrib : (IIIJJJJJ)V
.end method

.method public static break : (IDD)V
    .code stack 7 locals 7
L0:     invokestatic Method org/lwjgl/opengl/GLContext break ()Lorg/lwjgl/opengl/kb;
L3:     getfield Field org/lwjgl/opengl/kb eR J
L6:     dup2
L7:     lstore 5
L9:     invokestatic Method org/lwjgl/l break (J)V
L12:    iload_0
L13:    dload_1
L14:    dload_3
L15:    lload 5
L17:    invokestatic Method org/lwjgl/opengl/GL20 nglVertexAttrib2d (IDDJ)V
L20:    return
L21:    
    .end code
.end method

.method public static break : (IILjava/nio/DoubleBuffer;)V
    .code stack 6 locals 5
L0:     invokestatic Method org/lwjgl/opengl/GLContext break ()Lorg/lwjgl/opengl/kb;
L3:     getfield Field org/lwjgl/opengl/kb qF J
L6:     dup2
L7:     lstore_3
L8:     invokestatic Method org/lwjgl/l break (J)V
L11:    iload_0
L12:    aload_2
L13:    iconst_4
L14:    iconst_1
L15:    dup
L16:    pop2
L17:    invokestatic Method org/lwjgl/l break (Ljava/nio/DoubleBuffer;I)V
L20:    iload_1
L21:    aload_2
L22:    invokestatic Method org/lwjgl/MemoryUtil else (Ljava/nio/DoubleBuffer;)J
L25:    lload_3
L26:    invokestatic Method org/lwjgl/opengl/GL20 nglGetVertexAttribdv (IIJJ)V
L29:    return
L30:    
    .end code
.end method

.method public static short : (ILjava/nio/IntBuffer;)V
    .code stack 6 locals 4
L0:     invokestatic Method org/lwjgl/opengl/GLContext break ()Lorg/lwjgl/opengl/kb;
L3:     getfield Field org/lwjgl/opengl/kb eH J
L6:     dup2
L7:     lstore_2
L8:     invokestatic Method org/lwjgl/l break (J)V
L11:    iload_0
L12:    aload_1
L13:    invokestatic Method org/lwjgl/l else (Ljava/nio/IntBuffer;)V
L16:    aload_1
L17:    invokevirtual Method java/nio/IntBuffer remaining ()I
L20:    iconst_2
L21:    iconst_1
L22:    dup
L23:    pop2
L24:    ishr
L25:    aload_1
L26:    invokestatic Method org/lwjgl/MemoryUtil break (Ljava/nio/IntBuffer;)J
L29:    lload_2
L30:    invokestatic Method org/lwjgl/opengl/GL20 nglUniform4iv (IIJJ)V
L33:    return
L34:    
    .end code
.end method

.method static native nglUniform2f : (IFFJ)V
.end method

.method static native nglDisableVertexAttribArray : (IJ)V
.end method

.method static native nglVertexAttrib2d : (IDDJ)V
.end method

.method public static const : (ILjava/nio/IntBuffer;)V
    .code stack 6 locals 4
L0:     invokestatic Method org/lwjgl/opengl/GLContext break ()Lorg/lwjgl/opengl/kb;
L3:     getfield Field org/lwjgl/opengl/kb Pk J
L6:     dup2
L7:     lstore_2
L8:     invokestatic Method org/lwjgl/l break (J)V
L11:    iload_0
L12:    aload_1
L13:    invokestatic Method org/lwjgl/l else (Ljava/nio/IntBuffer;)V
L16:    aload_1
L17:    invokevirtual Method java/nio/IntBuffer remaining ()I
L20:    iconst_1
L21:    dup
L22:    dup
L23:    pop2
L24:    ishr
L25:    aload_1
L26:    invokestatic Method org/lwjgl/MemoryUtil break (Ljava/nio/IntBuffer;)J
L29:    lload_2
L30:    invokestatic Method org/lwjgl/opengl/GL20 nglUniform2iv (IIJJ)V
L33:    return
L34:    
    .end code
.end method

.method public static break : (ILjava/nio/IntBuffer;Ljava/nio/IntBuffer;)V
    .code stack 8 locals 5
L0:     invokestatic Method org/lwjgl/opengl/GLContext break ()Lorg/lwjgl/opengl/kb;
L3:     getfield Field org/lwjgl/opengl/kb Tp J
L6:     dup2
L7:     lstore_3
L8:     invokestatic Method org/lwjgl/l break (J)V
L11:    aload_1
L12:    ifnull L23
L15:    aload_1
L16:    iconst_1
L17:    dup
L18:    dup
L19:    pop2
L20:    invokestatic Method org/lwjgl/l break (Ljava/nio/IntBuffer;I)V
L23:    aload_2
L24:    invokestatic Method org/lwjgl/l else (Ljava/nio/IntBuffer;)V
L27:    iload_0
L28:    aload_2
L29:    invokevirtual Method java/nio/IntBuffer remaining ()I
L32:    aload_1
L33:    invokestatic Method org/lwjgl/MemoryUtil else (Ljava/nio/IntBuffer;)J
L36:    aload_2
L37:    invokestatic Method org/lwjgl/MemoryUtil break (Ljava/nio/IntBuffer;)J
L40:    lload_3
L41:    invokestatic Method org/lwjgl/opengl/GL20 nglGetAttachedShaders (IIJJJ)V
L44:    return
L45:    
        .attribute StackMap b'\x00\x01\x00\x17\x00\x04\x01\x07\x00\xF5\x07\x00\xF5\x04\x00\x00'
    .end code
.end method

.method public static else : (IFFFF)V
    .code stack 7 locals 7
L0:     invokestatic Method org/lwjgl/opengl/GLContext break ()Lorg/lwjgl/opengl/kb;
L3:     getfield Field org/lwjgl/opengl/kb Ci J
L6:     dup2
L7:     lstore 5
L9:     invokestatic Method org/lwjgl/l break (J)V
L12:    iload_0
L13:    fload_1
L14:    fload_2
L15:    fload_3
L16:    fload 4
L18:    lload 5
L20:    invokestatic Method org/lwjgl/opengl/GL20 nglUniform4f (IFFFFJ)V
L23:    return
L24:    
    .end code
.end method

.method static native nglVertexAttrib4Nub : (IBBBBJ)V
.end method

.method public static goto : (I)V
    .code stack 4 locals 3
L0:     invokestatic Method org/lwjgl/opengl/GLContext break ()Lorg/lwjgl/opengl/kb;
L3:     getfield Field org/lwjgl/opengl/kb Os J
L6:     dup2
L7:     lstore_1
L8:     invokestatic Method org/lwjgl/l break (J)V
L11:    iload_0
L12:    lload_1
L13:    invokestatic Method org/lwjgl/opengl/GL20 nglDeleteProgram (IJ)V
L16:    return
L17:    
    .end code
.end method

.method public static goto : (II)I
    .code stack 2 locals 2
L0:     iload_0
L1:     iload_1
L2:     invokestatic Method org/lwjgl/opengl/GL20 class (II)I
L5:     ireturn
L6:     
    .end code
    .deprecated
.end method

.method public static do : (II)Ljava/lang/String;
    .code stack 9 locals 6
L0:     invokestatic Method org/lwjgl/opengl/GLContext break ()Lorg/lwjgl/opengl/kb;
L3:     dup
L4:     dup2
L5:     getfield Field org/lwjgl/opengl/kb iT J
L8:     dup2
L9:     lstore_3
L10:    invokestatic Method org/lwjgl/l break (J)V
L13:    invokestatic Method org/lwjgl/opengl/bB break (Lorg/lwjgl/opengl/kb;)Ljava/nio/IntBuffer;
L16:    astore_2
L17:    iload_1
L18:    invokestatic Method org/lwjgl/opengl/bB float (Lorg/lwjgl/opengl/kb;I)Ljava/nio/ByteBuffer;
L21:    astore 5
L23:    iload_0
L24:    iload_1
L25:    aload_2
L26:    invokestatic Method org/lwjgl/MemoryUtil break (Ljava/nio/Buffer;)J
L29:    aload 5
L31:    invokestatic Method org/lwjgl/MemoryUtil const (Ljava/nio/ByteBuffer;)J
L34:    lload_3
L35:    invokestatic Method org/lwjgl/opengl/GL20 nglGetProgramInfoLog (IIJJJ)V
L38:    aload 5
L40:    dup
L41:    aload_2
L42:    iconst_0
L43:    iconst_1
L44:    dup
L45:    pop2
L46:    invokevirtual Method java/nio/IntBuffer get (I)I
L49:    invokevirtual Method java/nio/ByteBuffer limit (I)Ljava/nio/Buffer;
L52:    pop
L53:    invokestatic Method org/lwjgl/opengl/bB break (Lorg/lwjgl/opengl/kb;Ljava/nio/ByteBuffer;)Ljava/lang/String;
L56:    areturn
L57:    
    .end code
.end method

.method public static break : (ISSSS)V
    .code stack 7 locals 7
L0:     invokestatic Method org/lwjgl/opengl/GLContext break ()Lorg/lwjgl/opengl/kb;
L3:     getfield Field org/lwjgl/opengl/kb dq J
L6:     dup2
L7:     lstore 5
L9:     invokestatic Method org/lwjgl/l break (J)V
L12:    iload_0
L13:    iload_1
L14:    iload_2
L15:    iload_3
L16:    iload 4
L18:    lload 5
L20:    invokestatic Method org/lwjgl/opengl/GL20 nglVertexAttrib4s (ISSSSJ)V
L23:    return
L24:    
    .end code
.end method

.method public static break : (IF)V
    .code stack 4 locals 4
L0:     invokestatic Method org/lwjgl/opengl/GLContext break ()Lorg/lwjgl/opengl/kb;
L3:     getfield Field org/lwjgl/opengl/kb Hm J
L6:     dup2
L7:     lstore_2
L8:     invokestatic Method org/lwjgl/l break (J)V
L11:    iload_0
L12:    fload_1
L13:    lload_2
L14:    invokestatic Method org/lwjgl/opengl/GL20 nglVertexAttrib1f (IFJ)V
L17:    return
L18:    
    .end code
.end method

.method public static for : (II)Ljava/lang/String;
    .code stack 9 locals 6
L0:     invokestatic Method org/lwjgl/opengl/GLContext break ()Lorg/lwjgl/opengl/kb;
L3:     dup
L4:     dup2
L5:     getfield Field org/lwjgl/opengl/kb cn J
L8:     dup2
L9:     lstore_3
L10:    invokestatic Method org/lwjgl/l break (J)V
L13:    invokestatic Method org/lwjgl/opengl/bB break (Lorg/lwjgl/opengl/kb;)Ljava/nio/IntBuffer;
L16:    astore_2
L17:    iload_1
L18:    invokestatic Method org/lwjgl/opengl/bB float (Lorg/lwjgl/opengl/kb;I)Ljava/nio/ByteBuffer;
L21:    astore 5
L23:    iload_0
L24:    iload_1
L25:    aload_2
L26:    invokestatic Method org/lwjgl/MemoryUtil break (Ljava/nio/Buffer;)J
L29:    aload 5
L31:    invokestatic Method org/lwjgl/MemoryUtil const (Ljava/nio/ByteBuffer;)J
L34:    lload_3
L35:    invokestatic Method org/lwjgl/opengl/GL20 nglGetShaderInfoLog (IIJJJ)V
L38:    aload 5
L40:    dup
L41:    aload_2
L42:    iconst_0
L43:    iconst_1
L44:    dup
L45:    pop2
L46:    invokevirtual Method java/nio/IntBuffer get (I)I
L49:    invokevirtual Method java/nio/ByteBuffer limit (I)Ljava/nio/Buffer;
L52:    pop
L53:    invokestatic Method org/lwjgl/opengl/bB break (Lorg/lwjgl/opengl/kb;Ljava/nio/ByteBuffer;)Ljava/lang/String;
L56:    areturn
L57:    
    .end code
.end method

.method public static break : (IS)V
    .code stack 4 locals 4
L0:     invokestatic Method org/lwjgl/opengl/GLContext break ()Lorg/lwjgl/opengl/kb;
L3:     getfield Field org/lwjgl/opengl/kb uA J
L6:     dup2
L7:     lstore_2
L8:     invokestatic Method org/lwjgl/l break (J)V
L11:    iload_0
L12:    iload_1
L13:    lload_2
L14:    invokestatic Method org/lwjgl/opengl/GL20 nglVertexAttrib1s (ISJ)V
L17:    return
L18:    
    .end code
.end method

.method static native nglGetShaderSource : (IIJJJ)V
.end method

.method static native nglGetUniformLocation : (IJJ)I
.end method

.method public static catch : (II)I
    .code stack 13 locals 6
L0:     invokestatic Method org/lwjgl/opengl/GLContext break ()Lorg/lwjgl/opengl/kb;
L3:     dup
L4:     astore_2
L5:     dup
L6:     getfield Field org/lwjgl/opengl/kb cS J
L9:     dup2
L10:    lstore_3
L11:    invokestatic Method org/lwjgl/l break (J)V
L14:    invokestatic Method org/lwjgl/opengl/bB short (Lorg/lwjgl/opengl/kb;)Ljava/nio/IntBuffer;
L17:    astore 5
L19:    iload_0
L20:    iload_1
L21:    iconst_0
L22:    iconst_1
L23:    dup
L24:    pop2
L25:    lconst_0
L26:    aload 5
L28:    iconst_1
L29:    dup
L30:    dup
L31:    pop2
L32:    invokestatic Method org/lwjgl/MemoryUtil break (Ljava/nio/IntBuffer;I)J
L35:    aload 5
L37:    invokestatic Method org/lwjgl/MemoryUtil break (Ljava/nio/IntBuffer;)J
L40:    aload_2
L41:    invokestatic Method org/lwjgl/opengl/bB catch (Lorg/lwjgl/opengl/kb;)J
L44:    lload_3
L45:    invokestatic Method org/lwjgl/opengl/GL20 nglGetActiveAttrib (IIIJJJJJ)V
L48:    aload 5
L50:    iconst_0
L51:    iconst_1
L52:    dup
L53:    pop2
L54:    invokevirtual Method java/nio/IntBuffer get (I)I
L57:    ireturn
L58:    
    .end code
.end method

.method static native nglVertexAttribPointer : (IIIZIJJ)V
.end method

.method static native nglGetShaderiv : (IIJJ)V
.end method

.method static native nglCreateShader : (IJ)I
.end method

.method static native nglAttachShader : (IIJ)V
.end method

.method public static else : (III)Ljava/lang/String;
    .code stack 14 locals 8
L0:     invokestatic Method org/lwjgl/opengl/GLContext break ()Lorg/lwjgl/opengl/kb;
L3:     dup
L4:     astore_3
L5:     dup
L6:     dup2
L7:     getfield Field org/lwjgl/opengl/kb pi J
L10:    dup2
L11:    lstore 4
L13:    invokestatic Method org/lwjgl/l break (J)V
L16:    invokestatic Method org/lwjgl/opengl/bB break (Lorg/lwjgl/opengl/kb;)Ljava/nio/IntBuffer;
L19:    astore 6
L21:    iload_2
L22:    invokestatic Method org/lwjgl/opengl/bB float (Lorg/lwjgl/opengl/kb;I)Ljava/nio/ByteBuffer;
L25:    astore 7
L27:    iload_0
L28:    iload_1
L29:    iload_2
L30:    aload 6
L32:    invokestatic Method org/lwjgl/MemoryUtil break (Ljava/nio/Buffer;)J
L35:    aload_3
L36:    invokestatic Method org/lwjgl/opengl/bB short (Lorg/lwjgl/opengl/kb;)Ljava/nio/IntBuffer;
L39:    invokestatic Method org/lwjgl/MemoryUtil break (Ljava/nio/Buffer;)J
L42:    aload_3
L43:    invokestatic Method org/lwjgl/opengl/bB short (Lorg/lwjgl/opengl/kb;)Ljava/nio/IntBuffer;
L46:    iconst_1
L47:    dup
L48:    dup
L49:    pop2
L50:    invokestatic Method org/lwjgl/MemoryUtil break (Ljava/nio/IntBuffer;I)J
L53:    aload 7
L55:    invokestatic Method org/lwjgl/MemoryUtil const (Ljava/nio/ByteBuffer;)J
L58:    lload 4
L60:    invokestatic Method org/lwjgl/opengl/GL20 nglGetActiveUniform (IIIJJJJJ)V
L63:    aload 7
L65:    dup
L66:    aload 6
L68:    iconst_0
L69:    iconst_1
L70:    dup
L71:    pop2
L72:    invokevirtual Method java/nio/IntBuffer get (I)I
L75:    invokevirtual Method java/nio/ByteBuffer limit (I)Ljava/nio/Buffer;
L78:    pop
L79:    invokestatic Method org/lwjgl/opengl/bB break (Lorg/lwjgl/opengl/kb;Ljava/nio/ByteBuffer;)Ljava/lang/String;
L82:    areturn
L83:    
    .end code
.end method

.method static native nglIsProgram : (IJ)Z
.end method

.method static native nglVertexAttrib2f : (IFFJ)V
.end method

.method public static break : (ISSS)V
    .code stack 6 locals 6
L0:     invokestatic Method org/lwjgl/opengl/GLContext break ()Lorg/lwjgl/opengl/kb;
L3:     getfield Field org/lwjgl/opengl/kb vG J
L6:     dup2
L7:     lstore 4
L9:     invokestatic Method org/lwjgl/l break (J)V
L12:    iload_0
L13:    iload_1
L14:    iload_2
L15:    iload_3
L16:    lload 4
L18:    invokestatic Method org/lwjgl/opengl/GL20 nglVertexAttrib3s (ISSSJ)V
L21:    return
L22:    
    .end code
.end method

.method public static else : (IIII)V
    .code stack 6 locals 6
L0:     invokestatic Method org/lwjgl/opengl/GLContext break ()Lorg/lwjgl/opengl/kb;
L3:     getfield Field org/lwjgl/opengl/kb Po J
L6:     dup2
L7:     lstore 4
L9:     invokestatic Method org/lwjgl/l break (J)V
L12:    iload_0
L13:    iload_1
L14:    iload_2
L15:    iload_3
L16:    lload 4
L18:    invokestatic Method org/lwjgl/opengl/GL20 nglUniform3i (IIIIJ)V
L21:    return
L22:    
    .end code
.end method

.method public static do : (I)V
    .code stack 4 locals 3
L0:     invokestatic Method org/lwjgl/opengl/GLContext break ()Lorg/lwjgl/opengl/kb;
L3:     getfield Field org/lwjgl/opengl/kb nr J
L6:     dup2
L7:     lstore_1
L8:     invokestatic Method org/lwjgl/l break (J)V
L11:    iload_0
L12:    lload_1
L13:    invokestatic Method org/lwjgl/opengl/GL20 nglUseProgram (IJ)V
L16:    return
L17:    
    .end code
.end method

.method public static const : (ILjava/nio/IntBuffer;Ljava/nio/ByteBuffer;)V
    .code stack 8 locals 5
L0:     invokestatic Method org/lwjgl/opengl/GLContext break ()Lorg/lwjgl/opengl/kb;
L3:     getfield Field org/lwjgl/opengl/kb cn J
L6:     dup2
L7:     lstore_3
L8:     invokestatic Method org/lwjgl/l break (J)V
L11:    aload_1
L12:    ifnull L23
L15:    aload_1
L16:    iconst_1
L17:    dup
L18:    dup
L19:    pop2
L20:    invokestatic Method org/lwjgl/l break (Ljava/nio/IntBuffer;I)V
L23:    aload_2
L24:    invokestatic Method org/lwjgl/l break (Ljava/nio/ByteBuffer;)V
L27:    iload_0
L28:    aload_2
L29:    invokevirtual Method java/nio/ByteBuffer remaining ()I
L32:    aload_1
L33:    invokestatic Method org/lwjgl/MemoryUtil else (Ljava/nio/IntBuffer;)J
L36:    aload_2
L37:    invokestatic Method org/lwjgl/MemoryUtil const (Ljava/nio/ByteBuffer;)J
L40:    lload_3
L41:    invokestatic Method org/lwjgl/opengl/GL20 nglGetShaderInfoLog (IIJJJ)V
L44:    return
L45:    
        .attribute StackMap b'\x00\x01\x00\x17\x00\x04\x01\x07\x00\xF5\x07\x01\x3F\x04\x00\x00'
    .end code
.end method

.method public static break : (III)Ljava/lang/String;
    .code stack 14 locals 8
L0:     invokestatic Method org/lwjgl/opengl/GLContext break ()Lorg/lwjgl/opengl/kb;
L3:     dup
L4:     astore_3
L5:     dup
L6:     dup2
L7:     getfield Field org/lwjgl/opengl/kb cS J
L10:    dup2
L11:    lstore 4
L13:    invokestatic Method org/lwjgl/l break (J)V
L16:    invokestatic Method org/lwjgl/opengl/bB break (Lorg/lwjgl/opengl/kb;)Ljava/nio/IntBuffer;
L19:    astore 6
L21:    iload_2
L22:    invokestatic Method org/lwjgl/opengl/bB float (Lorg/lwjgl/opengl/kb;I)Ljava/nio/ByteBuffer;
L25:    astore 7
L27:    iload_0
L28:    iload_1
L29:    iload_2
L30:    aload 6
L32:    invokestatic Method org/lwjgl/MemoryUtil break (Ljava/nio/Buffer;)J
L35:    aload_3
L36:    invokestatic Method org/lwjgl/opengl/bB short (Lorg/lwjgl/opengl/kb;)Ljava/nio/IntBuffer;
L39:    invokestatic Method org/lwjgl/MemoryUtil break (Ljava/nio/Buffer;)J
L42:    aload_3
L43:    invokestatic Method org/lwjgl/opengl/bB short (Lorg/lwjgl/opengl/kb;)Ljava/nio/IntBuffer;
L46:    iconst_1
L47:    dup
L48:    dup
L49:    pop2
L50:    invokestatic Method org/lwjgl/MemoryUtil break (Ljava/nio/IntBuffer;I)J
L53:    aload 7
L55:    invokestatic Method org/lwjgl/MemoryUtil const (Ljava/nio/ByteBuffer;)J
L58:    lload 4
L60:    invokestatic Method org/lwjgl/opengl/GL20 nglGetActiveAttrib (IIIJJJJJ)V
L63:    aload 7
L65:    dup
L66:    aload 6
L68:    iconst_0
L69:    iconst_1
L70:    dup
L71:    pop2
L72:    invokevirtual Method java/nio/IntBuffer get (I)I
L75:    invokevirtual Method java/nio/ByteBuffer limit (I)Ljava/nio/Buffer;
L78:    pop
L79:    invokestatic Method org/lwjgl/opengl/bB break (Lorg/lwjgl/opengl/kb;Ljava/nio/ByteBuffer;)Ljava/lang/String;
L82:    areturn
L83:    
    .end code
.end method

.method static native nglUniform3f : (IFFFJ)V
.end method

.method public static break : (Ljava/nio/IntBuffer;)V
    .code stack 5 locals 3
L0:     invokestatic Method org/lwjgl/opengl/GLContext break ()Lorg/lwjgl/opengl/kb;
L3:     getfield Field org/lwjgl/opengl/kb jT J
L6:     dup2
L7:     lstore_1
L8:     invokestatic Method org/lwjgl/l break (J)V
L11:    aload_0
L12:    dup
L13:    invokestatic Method org/lwjgl/l else (Ljava/nio/IntBuffer;)V
L16:    invokevirtual Method java/nio/IntBuffer remaining ()I
L19:    aload_0
L20:    invokestatic Method org/lwjgl/MemoryUtil break (Ljava/nio/IntBuffer;)J
L23:    lload_1
L24:    invokestatic Method org/lwjgl/opengl/GL20 nglDrawBuffers (IJJ)V
L27:    return
L28:    
    .end code
.end method

.method static native nglUniform3fv : (IIJJ)V
.end method

.method public static break : (IDDDD)V
    .code stack 11 locals 11
L0:     invokestatic Method org/lwjgl/opengl/GLContext break ()Lorg/lwjgl/opengl/kb;
L3:     getfield Field org/lwjgl/opengl/kb iH J
L6:     dup2
L7:     lstore 9
L9:     invokestatic Method org/lwjgl/l break (J)V
L12:    iload_0
L13:    dload_1
L14:    dload_3
L15:    dload 5
L17:    dload 7
L19:    lload 9
L21:    invokestatic Method org/lwjgl/opengl/GL20 nglVertexAttrib4d (IDDDDJ)V
L24:    return
L25:    
    .end code
.end method

.method public static else : (IFF)V
    .code stack 5 locals 5
L0:     invokestatic Method org/lwjgl/opengl/GLContext break ()Lorg/lwjgl/opengl/kb;
L3:     getfield Field org/lwjgl/opengl/kb mI J
L6:     dup2
L7:     lstore_3
L8:     invokestatic Method org/lwjgl/l break (J)V
L11:    iload_0
L12:    fload_1
L13:    fload_2
L14:    lload_3
L15:    invokestatic Method org/lwjgl/opengl/GL20 nglUniform2f (IFFJ)V
L18:    return
L19:    
    .end code
.end method

.method static native nglCompileShader : (IJ)V
.end method

.method static native nglShaderSource3 : (IIJJJ)V
.end method

.method public static float : (II)I
    .code stack 13 locals 6
L0:     invokestatic Method org/lwjgl/opengl/GLContext break ()Lorg/lwjgl/opengl/kb;
L3:     dup
L4:     astore_2
L5:     dup
L6:     getfield Field org/lwjgl/opengl/kb cS J
L9:     dup2
L10:    lstore_3
L11:    invokestatic Method org/lwjgl/l break (J)V
L14:    invokestatic Method org/lwjgl/opengl/bB short (Lorg/lwjgl/opengl/kb;)Ljava/nio/IntBuffer;
L17:    astore 5
L19:    iload_0
L20:    iload_1
L21:    iconst_0
L22:    iconst_1
L23:    dup
L24:    pop2
L25:    lconst_0
L26:    aload 5
L28:    invokestatic Method org/lwjgl/MemoryUtil break (Ljava/nio/IntBuffer;)J
L31:    aload 5
L33:    iconst_1
L34:    dup
L35:    dup
L36:    pop2
L37:    invokestatic Method org/lwjgl/MemoryUtil break (Ljava/nio/IntBuffer;I)J
L40:    aload_2
L41:    invokestatic Method org/lwjgl/opengl/bB catch (Lorg/lwjgl/opengl/kb;)J
L44:    lload_3
L45:    invokestatic Method org/lwjgl/opengl/GL20 nglGetActiveAttrib (IIIJJJJJ)V
L48:    aload 5
L50:    iconst_0
L51:    iconst_1
L52:    dup
L53:    pop2
L54:    invokevirtual Method java/nio/IntBuffer get (I)I
L57:    ireturn
L58:    
    .end code
.end method

.method public static break : (IIZZILjava/nio/ShortBuffer;)V
    .code stack 9 locals 9
L0:     invokestatic Method org/lwjgl/opengl/GLContext break ()Lorg/lwjgl/opengl/kb;
L3:     astore 6
L5:     aload 5
L7:     aload 6
L9:     dup
L10:    getfield Field org/lwjgl/opengl/kb ch J
L13:    dup2
L14:    lstore 7
L16:    invokestatic Method org/lwjgl/l break (J)V
L19:    invokestatic Method org/lwjgl/opengl/Zd break (Lorg/lwjgl/opengl/kb;)V
L22:    invokestatic Method org/lwjgl/l break (Ljava/nio/ShortBuffer;)V
L25:    getstatic Field org/lwjgl/LWJGLUtil CHECKS Z
L28:    ifeq L43
L31:    aload 6
L33:    invokestatic Method org/lwjgl/opengl/w const (Lorg/lwjgl/opengl/kb;)Lorg/lwjgl/opengl/P;
L36:    getfield Field org/lwjgl/opengl/P do [Ljava/nio/Buffer;
L39:    iload_0
L40:    aload 5
L42:    aastore
L43:    iload_0
L44:    iload_1
L45:    iload_2
L46:    ifeq L60
L49:    sipush 5123
L52:    iconst_1
L53:    dup
L54:    pop2
L55:    iload_3
L56:    goto L67
L59:    athrow
L60:    sipush 5122
L63:    iconst_1
L64:    dup
L65:    pop2
L66:    iload_3
L67:    iload 4
L69:    aload 5
L71:    invokestatic Method org/lwjgl/MemoryUtil else (Ljava/nio/ShortBuffer;)J
L74:    lload 7
L76:    invokestatic Method org/lwjgl/opengl/GL20 nglVertexAttribPointer (IIIZIJJ)V
L79:    return
L80:    
        .attribute StackMap b'\x00\x04\x00\x2B\x00\x08\x01\x01\x01\x01\x01\x07\x02\x6F\x07\x00\xB8\x04\x00\x00\x00\x3B\x00\x00\x00\x01\x07\x01\x41\x00\x3C\x00\x08\x01\x01\x01\x01\x01\x07\x02\x6F\x07\x00\xB8\x04\x00\x02\x01\x01\x00\x43\x00\x08\x01\x01\x01\x01\x01\x07\x02\x6F\x07\x00\xB8\x04\x00\x04\x01\x01\x01\x01'
    .end code
.end method

.method static native nglGetAttribLocation : (IJJ)I
.end method

.method static native nglUniform3iv : (IIJJ)V
.end method

.method static native nglUseProgram : (IJ)V
.end method

.method static native nglUniform1i : (IIJ)V
.end method

.method static native nglUniformMatrix4fv : (IIZJJ)V
.end method

.method public static break : (IILjava/lang/CharSequence;)V
    .code stack 6 locals 6
L0:     invokestatic Method org/lwjgl/opengl/GLContext break ()Lorg/lwjgl/opengl/kb;
L3:     dup
L4:     astore_3
L5:     getfield Field org/lwjgl/opengl/kb Go J
L8:     dup2
L9:     lstore 4
L11:    invokestatic Method org/lwjgl/l break (J)V
L14:    iload_0
L15:    iload_1
L16:    aload_3
L17:    aload_2
L18:    invokestatic Method org/lwjgl/opengl/bB break (Lorg/lwjgl/opengl/kb;Ljava/lang/CharSequence;)J
L21:    lload 4
L23:    invokestatic Method org/lwjgl/opengl/GL20 nglBindAttribLocation (IIJJ)V
L26:    return
L27:    
    .end code
.end method

.method static native nglVertexAttribPointerBO : (IIIZIJJ)V
.end method

.method static native nglDeleteShader : (IJ)V
.end method

.method static native nglBindAttribLocation : (IIJJ)V
.end method

.method public static else : (IILjava/nio/FloatBuffer;)V
    .code stack 6 locals 5
L0:     invokestatic Method org/lwjgl/opengl/GLContext break ()Lorg/lwjgl/opengl/kb;
L3:     getfield Field org/lwjgl/opengl/kb p J
L6:     dup2
L7:     lstore_3
L8:     invokestatic Method org/lwjgl/l break (J)V
L11:    iload_0
L12:    aload_2
L13:    iconst_4
L14:    iconst_1
L15:    dup
L16:    pop2
L17:    invokestatic Method org/lwjgl/l break (Ljava/nio/FloatBuffer;I)V
L20:    iload_1
L21:    aload_2
L22:    invokestatic Method org/lwjgl/MemoryUtil break (Ljava/nio/FloatBuffer;)J
L25:    lload_3
L26:    invokestatic Method org/lwjgl/opengl/GL20 nglGetVertexAttribfv (IIJJ)V
L29:    return
L30:    
    .end code
.end method

.method public static break : (IIIII)V
    .code stack 7 locals 7
L0:     invokestatic Method org/lwjgl/opengl/GLContext break ()Lorg/lwjgl/opengl/kb;
L3:     getfield Field org/lwjgl/opengl/kb IF J
L6:     dup2
L7:     lstore 5
L9:     invokestatic Method org/lwjgl/l break (J)V
L12:    iload_0
L13:    iload_1
L14:    iload_2
L15:    iload_3
L16:    iload 4
L18:    lload 5
L20:    invokestatic Method org/lwjgl/opengl/GL20 nglUniform4i (IIIIIJ)V
L23:    return
L24:    
    .end code
.end method

.method static native nglStencilMaskSeparate : (IIJ)V
.end method

.method static native nglLinkProgram : (IJ)V
.end method

.method public static short : (II)I
    .code stack 13 locals 6
L0:     invokestatic Method org/lwjgl/opengl/GLContext break ()Lorg/lwjgl/opengl/kb;
L3:     dup
L4:     astore_2
L5:     dup
L6:     getfield Field org/lwjgl/opengl/kb pi J
L9:     dup2
L10:    lstore_3
L11:    invokestatic Method org/lwjgl/l break (J)V
L14:    invokestatic Method org/lwjgl/opengl/bB short (Lorg/lwjgl/opengl/kb;)Ljava/nio/IntBuffer;
L17:    astore 5
L19:    iload_0
L20:    iload_1
L21:    iconst_0
L22:    iconst_1
L23:    dup
L24:    pop2
L25:    lconst_0
L26:    aload 5
L28:    invokestatic Method org/lwjgl/MemoryUtil break (Ljava/nio/IntBuffer;)J
L31:    aload 5
L33:    iconst_1
L34:    dup
L35:    dup
L36:    pop2
L37:    invokestatic Method org/lwjgl/MemoryUtil break (Ljava/nio/IntBuffer;I)J
L40:    aload_2
L41:    invokestatic Method org/lwjgl/opengl/bB catch (Lorg/lwjgl/opengl/kb;)J
L44:    lload_3
L45:    invokestatic Method org/lwjgl/opengl/GL20 nglGetActiveUniform (IIIJJJJJ)V
L48:    aload 5
L50:    iconst_0
L51:    iconst_1
L52:    dup
L53:    pop2
L54:    invokevirtual Method java/nio/IntBuffer get (I)I
L57:    ireturn
L58:    
    .end code
.end method

.method static native nglVertexAttrib1d : (IDJ)V
.end method

.method public static break : (IIII)V
    .code stack 6 locals 6
L0:     invokestatic Method org/lwjgl/opengl/GLContext break ()Lorg/lwjgl/opengl/kb;
L3:     getfield Field org/lwjgl/opengl/kb qp J
L6:     dup2
L7:     lstore 4
L9:     invokestatic Method org/lwjgl/l break (J)V
L12:    iload_0
L13:    iload_1
L14:    iload_2
L15:    iload_3
L16:    lload 4
L18:    invokestatic Method org/lwjgl/opengl/GL20 nglStencilFuncSeparate (IIIIJ)V
L21:    return
L22:    
    .end code
.end method

.method public static else : (ILjava/nio/ByteBuffer;)I
    .code stack 5 locals 4
L0:     invokestatic Method org/lwjgl/opengl/GLContext break ()Lorg/lwjgl/opengl/kb;
L3:     getfield Field org/lwjgl/opengl/kb we J
L6:     dup2
L7:     lstore_2
L8:     invokestatic Method org/lwjgl/l break (J)V
L11:    iload_0
L12:    aload_1
L13:    dup
L14:    invokestatic Method org/lwjgl/l break (Ljava/nio/ByteBuffer;)V
L17:    invokestatic Method org/lwjgl/l else (Ljava/nio/ByteBuffer;)V
L20:    aload_1
L21:    invokestatic Method org/lwjgl/MemoryUtil const (Ljava/nio/ByteBuffer;)J
L24:    lload_2
L25:    invokestatic Method org/lwjgl/opengl/GL20 nglGetAttribLocation (IJJ)I
L28:    ireturn
L29:    
    .end code
.end method

.method static native nglIsShader : (IJ)Z
.end method

.method public static else : (IIILjava/nio/IntBuffer;)Ljava/lang/String;
    .code stack 14 locals 8
L0:     invokestatic Method org/lwjgl/opengl/GLContext break ()Lorg/lwjgl/opengl/kb;
L3:     dup
L4:     astore 4
L6:     dup
L7:     aload_3
L8:     aload 4
L10:    dup_x2
L11:    getfield Field org/lwjgl/opengl/kb pi J
L14:    dup2
L15:    lstore 5
L17:    invokestatic Method org/lwjgl/l break (J)V
L20:    iconst_2
L21:    iconst_1
L22:    dup
L23:    pop2
L24:    invokestatic Method org/lwjgl/l break (Ljava/nio/IntBuffer;I)V
L27:    invokestatic Method org/lwjgl/opengl/bB break (Lorg/lwjgl/opengl/kb;)Ljava/nio/IntBuffer;
L30:    astore 4
L32:    iload_2
L33:    invokestatic Method org/lwjgl/opengl/bB float (Lorg/lwjgl/opengl/kb;I)Ljava/nio/ByteBuffer;
L36:    astore 7
L38:    iload_0
L39:    iload_1
L40:    iload_2
L41:    aload 4
L43:    invokestatic Method org/lwjgl/MemoryUtil break (Ljava/nio/Buffer;)J
L46:    aload_3
L47:    invokestatic Method org/lwjgl/MemoryUtil break (Ljava/nio/IntBuffer;)J
L50:    aload_3
L51:    dup
L52:    invokevirtual Method java/nio/IntBuffer position ()I
L55:    iconst_1
L56:    dup
L57:    dup
L58:    pop2
L59:    iadd
L60:    invokestatic Method org/lwjgl/MemoryUtil break (Ljava/nio/IntBuffer;I)J
L63:    aload 7
L65:    invokestatic Method org/lwjgl/MemoryUtil const (Ljava/nio/ByteBuffer;)J
L68:    lload 5
L70:    invokestatic Method org/lwjgl/opengl/GL20 nglGetActiveUniform (IIIJJJJJ)V
L73:    aload 7
L75:    dup
L76:    aload 4
L78:    iconst_0
L79:    iconst_1
L80:    dup
L81:    pop2
L82:    invokevirtual Method java/nio/IntBuffer get (I)I
L85:    invokevirtual Method java/nio/ByteBuffer limit (I)Ljava/nio/Buffer;
L88:    pop
L89:    invokestatic Method org/lwjgl/opengl/bB break (Lorg/lwjgl/opengl/kb;Ljava/nio/ByteBuffer;)Ljava/lang/String;
L92:    areturn
L93:    
    .end code
.end method

.method public static break : (IIJ)Ljava/nio/ByteBuffer;
    .code stack 6 locals 6
L0:     invokestatic Method org/lwjgl/opengl/GLContext break ()Lorg/lwjgl/opengl/kb;
L3:     getfield Field org/lwjgl/opengl/kb Vi J
L6:     dup2
L7:     lstore 4
L9:     invokestatic Method org/lwjgl/l break (J)V
L12:    iload_0
L13:    iload_1
L14:    lload_2
L15:    lload 4
L17:    invokestatic Method org/lwjgl/opengl/GL20 nglGetVertexAttribPointerv (IIJJ)Ljava/nio/ByteBuffer;
L20:    astore_1
L21:    getstatic Field org/lwjgl/LWJGLUtil CHECKS Z
L24:    ifeq L34
L27:    aload_1
L28:    ifnonnull L34
L31:    aconst_null
L32:    areturn
L33:    athrow
L34:    aload_1
L35:    invokestatic Method java/nio/ByteOrder nativeOrder ()Ljava/nio/ByteOrder;
L38:    invokevirtual Method java/nio/ByteBuffer order (Ljava/nio/ByteOrder;)Ljava/nio/ByteBuffer;
L41:    areturn
L42:    
        .attribute StackMap b'\x00\x02\x00\x21\x00\x00\x00\x01\x07\x01\x41\x00\x22\x00\x04\x01\x07\x01\x3F\x04\x04\x00\x00'
    .end code
.end method

.method static native nglUniform3i : (IIIIJ)V
.end method

.method public static else : (ILjava/nio/IntBuffer;)V
    .code stack 6 locals 4
L0:     invokestatic Method org/lwjgl/opengl/GLContext break ()Lorg/lwjgl/opengl/kb;
L3:     getfield Field org/lwjgl/opengl/kb oD J
L6:     dup2
L7:     lstore_2
L8:     invokestatic Method org/lwjgl/l break (J)V
L11:    iload_0
L12:    aload_1
L13:    invokestatic Method org/lwjgl/l else (Ljava/nio/IntBuffer;)V
L16:    aload_1
L17:    invokevirtual Method java/nio/IntBuffer remaining ()I
L20:    aload_1
L21:    invokestatic Method org/lwjgl/MemoryUtil break (Ljava/nio/IntBuffer;)J
L24:    lload_2
L25:    invokestatic Method org/lwjgl/opengl/GL20 nglUniform1iv (IIJJ)V
L28:    return
L29:    
    .end code
.end method

.method static native nglBlendEquationSeparate : (IIJ)V
.end method

.method public static break : (IILjava/nio/FloatBuffer;)V
    .code stack 6 locals 5
L0:     invokestatic Method org/lwjgl/opengl/GLContext break ()Lorg/lwjgl/opengl/kb;
L3:     getfield Field org/lwjgl/opengl/kb Tr J
L6:     dup2
L7:     lstore_3
L8:     invokestatic Method org/lwjgl/l break (J)V
L11:    iload_0
L12:    aload_2
L13:    invokestatic Method org/lwjgl/l break (Ljava/nio/FloatBuffer;)V
L16:    iload_1
L17:    aload_2
L18:    invokestatic Method org/lwjgl/MemoryUtil break (Ljava/nio/FloatBuffer;)J
L21:    lload_3
L22:    invokestatic Method org/lwjgl/opengl/GL20 nglGetUniformfv (IIJJ)V
L25:    return
L26:    
    .end code
.end method

.method static native nglDeleteProgram : (IJ)V
.end method

.method public static break : (IIZILjava/nio/DoubleBuffer;)V
    .code stack 9 locals 8
L0:     invokestatic Method org/lwjgl/opengl/GLContext break ()Lorg/lwjgl/opengl/kb;
L3:     astore 5
L5:     aload 4
L7:     aload 5
L9:     dup
L10:    getfield Field org/lwjgl/opengl/kb ch J
L13:    dup2
L14:    lstore 6
L16:    invokestatic Method org/lwjgl/l break (J)V
L19:    invokestatic Method org/lwjgl/opengl/Zd break (Lorg/lwjgl/opengl/kb;)V
L22:    invokestatic Method org/lwjgl/l break (Ljava/nio/DoubleBuffer;)V
L25:    getstatic Field org/lwjgl/LWJGLUtil CHECKS Z
L28:    ifeq L43
L31:    aload 5
L33:    invokestatic Method org/lwjgl/opengl/w const (Lorg/lwjgl/opengl/kb;)Lorg/lwjgl/opengl/P;
L36:    getfield Field org/lwjgl/opengl/P do [Ljava/nio/Buffer;
L39:    iload_0
L40:    aload 4
L42:    aastore
L43:    iload_0
L44:    iload_1
L45:    sipush 5130
L48:    iconst_1
L49:    dup
L50:    pop2
L51:    iload_2
L52:    iload_3
L53:    aload 4
L55:    invokestatic Method org/lwjgl/MemoryUtil else (Ljava/nio/DoubleBuffer;)J
L58:    lload 6
L60:    invokestatic Method org/lwjgl/opengl/GL20 nglVertexAttribPointer (IIIZIJJ)V
L63:    return
L64:    
        .attribute StackMap b'\x00\x01\x00\x2B\x00\x07\x01\x01\x01\x01\x07\x02\xC5\x07\x00\xB8\x04\x00\x00'
    .end code
.end method

.method public static break : (IBBBB)V
    .code stack 7 locals 7
L0:     invokestatic Method org/lwjgl/opengl/GLContext break ()Lorg/lwjgl/opengl/kb;
L3:     getfield Field org/lwjgl/opengl/kb Mj J
L6:     dup2
L7:     lstore 5
L9:     invokestatic Method org/lwjgl/l break (J)V
L12:    iload_0
L13:    iload_1
L14:    iload_2
L15:    iload_3
L16:    iload 4
L18:    lload 5
L20:    invokestatic Method org/lwjgl/opengl/GL20 nglVertexAttrib4Nub (IBBBBJ)V
L23:    return
L24:    
    .end code
.end method

.method public static break : (ILjava/nio/ByteBuffer;)I
    .code stack 6 locals 4
L0:     invokestatic Method org/lwjgl/opengl/GLContext break ()Lorg/lwjgl/opengl/kb;
L3:     getfield Field org/lwjgl/opengl/kb UL J
L6:     dup2
L7:     lstore_2
L8:     invokestatic Method org/lwjgl/l break (J)V
L11:    iload_0
L12:    aload_1
L13:    dup
L14:    iconst_1
L15:    dup
L16:    dup
L17:    pop2
L18:    invokestatic Method org/lwjgl/l break (Ljava/nio/ByteBuffer;I)V
L21:    invokestatic Method org/lwjgl/l else (Ljava/nio/ByteBuffer;)V
L24:    aload_1
L25:    invokestatic Method org/lwjgl/MemoryUtil const (Ljava/nio/ByteBuffer;)J
L28:    lload_2
L29:    invokestatic Method org/lwjgl/opengl/GL20 nglGetUniformLocation (IJJ)I
L32:    ireturn
L33:    
    .end code
.end method

.method public static const : (IILjava/nio/IntBuffer;)V
    .code stack 6 locals 5
L0:     invokestatic Method org/lwjgl/opengl/GLContext break ()Lorg/lwjgl/opengl/kb;
L3:     getfield Field org/lwjgl/opengl/kb nL J
L6:     dup2
L7:     lstore_3
L8:     invokestatic Method org/lwjgl/l break (J)V
L11:    iload_0
L12:    aload_2
L13:    invokestatic Method org/lwjgl/l else (Ljava/nio/IntBuffer;)V
L16:    iload_1
L17:    aload_2
L18:    invokestatic Method org/lwjgl/MemoryUtil break (Ljava/nio/IntBuffer;)J
L21:    lload_3
L22:    invokestatic Method org/lwjgl/opengl/GL20 nglGetProgramiv (IIJJ)V
L25:    return
L26:    
    .end code
.end method

.method public static else : (ILjava/nio/FloatBuffer;)V
    .code stack 6 locals 4
L0:     invokestatic Method org/lwjgl/opengl/GLContext break ()Lorg/lwjgl/opengl/kb;
L3:     getfield Field org/lwjgl/opengl/kb WI J
L6:     dup2
L7:     lstore_2
L8:     invokestatic Method org/lwjgl/l break (J)V
L11:    iload_0
L12:    aload_1
L13:    invokestatic Method org/lwjgl/l break (Ljava/nio/FloatBuffer;)V
L16:    aload_1
L17:    invokevirtual Method java/nio/FloatBuffer remaining ()I
L20:    iconst_1
L21:    dup
L22:    dup
L23:    pop2
L24:    ishr
L25:    aload_1
L26:    invokestatic Method org/lwjgl/MemoryUtil break (Ljava/nio/FloatBuffer;)J
L29:    lload_2
L30:    invokestatic Method org/lwjgl/opengl/GL20 nglUniform2fv (IIJJ)V
L33:    return
L34:    
    .end code
.end method

.method public static break : (IIZZILjava/nio/IntBuffer;)V
    .code stack 9 locals 9
L0:     invokestatic Method org/lwjgl/opengl/GLContext break ()Lorg/lwjgl/opengl/kb;
L3:     astore 6
L5:     aload 5
L7:     aload 6
L9:     dup
L10:    getfield Field org/lwjgl/opengl/kb ch J
L13:    dup2
L14:    lstore 7
L16:    invokestatic Method org/lwjgl/l break (J)V
L19:    invokestatic Method org/lwjgl/opengl/Zd break (Lorg/lwjgl/opengl/kb;)V
L22:    invokestatic Method org/lwjgl/l else (Ljava/nio/IntBuffer;)V
L25:    getstatic Field org/lwjgl/LWJGLUtil CHECKS Z
L28:    ifeq L43
L31:    aload 6
L33:    invokestatic Method org/lwjgl/opengl/w const (Lorg/lwjgl/opengl/kb;)Lorg/lwjgl/opengl/P;
L36:    getfield Field org/lwjgl/opengl/P do [Ljava/nio/Buffer;
L39:    iload_0
L40:    aload 5
L42:    aastore
L43:    iload_0
L44:    iload_1
L45:    iload_2
L46:    ifeq L60
L49:    sipush 5125
L52:    iconst_1
L53:    dup
L54:    pop2
L55:    iload_3
L56:    goto L67
L59:    athrow
L60:    sipush 5124
L63:    iconst_1
L64:    dup
L65:    pop2
L66:    iload_3
L67:    iload 4
L69:    aload 5
L71:    invokestatic Method org/lwjgl/MemoryUtil break (Ljava/nio/IntBuffer;)J
L74:    lload 7
L76:    invokestatic Method org/lwjgl/opengl/GL20 nglVertexAttribPointer (IIIZIJJ)V
L79:    return
L80:    
        .attribute StackMap b'\x00\x04\x00\x2B\x00\x08\x01\x01\x01\x01\x01\x07\x00\xF5\x07\x00\xB8\x04\x00\x00\x00\x3B\x00\x00\x00\x01\x07\x01\x41\x00\x3C\x00\x08\x01\x01\x01\x01\x01\x07\x00\xF5\x07\x00\xB8\x04\x00\x02\x01\x01\x00\x43\x00\x08\x01\x01\x01\x01\x01\x07\x00\xF5\x07\x00\xB8\x04\x00\x04\x01\x01\x01\x01'
    .end code
.end method

.method static native nglStencilFuncSeparate : (IIIIJ)V
.end method

.method static native nglUniform2iv : (IIJJ)V
.end method

.method public static for : (I)V
    .code stack 4 locals 3
L0:     invokestatic Method org/lwjgl/opengl/GLContext break ()Lorg/lwjgl/opengl/kb;
L3:     getfield Field org/lwjgl/opengl/kb dO J
L6:     dup2
L7:     lstore_1
L8:     invokestatic Method org/lwjgl/l break (J)V
L11:    iload_0
L12:    lload_1
L13:    invokestatic Method org/lwjgl/opengl/GL20 nglValidateProgram (IJ)V
L16:    return
L17:    
    .end code
.end method

.method static native nglUniform4iv : (IIJJ)V
.end method

.method static native nglVertexAttrib4s : (ISSSSJ)V
.end method

.method public static else : (IILjava/nio/IntBuffer;Ljava/nio/IntBuffer;Ljava/nio/IntBuffer;Ljava/nio/ByteBuffer;)V
    .code stack 13 locals 8
L0:     invokestatic Method org/lwjgl/opengl/GLContext break ()Lorg/lwjgl/opengl/kb;
L3:     getfield Field org/lwjgl/opengl/kb cS J
L6:     dup2
L7:     lstore 6
L9:     invokestatic Method org/lwjgl/l break (J)V
L12:    aload_2
L13:    ifnull L24
L16:    aload_2
L17:    iconst_1
L18:    dup
L19:    dup
L20:    pop2
L21:    invokestatic Method org/lwjgl/l break (Ljava/nio/IntBuffer;I)V
L24:    aload_3
L25:    iconst_1
L26:    dup
L27:    dup
L28:    pop2
L29:    invokestatic Method org/lwjgl/l break (Ljava/nio/IntBuffer;I)V
L32:    iload_0
L33:    aload 5
L35:    aload 4
L37:    iconst_1
L38:    dup
L39:    dup
L40:    pop2
L41:    invokestatic Method org/lwjgl/l break (Ljava/nio/IntBuffer;I)V
L44:    invokestatic Method org/lwjgl/l break (Ljava/nio/ByteBuffer;)V
L47:    iload_1
L48:    aload 5
L50:    invokevirtual Method java/nio/ByteBuffer remaining ()I
L53:    aload_2
L54:    invokestatic Method org/lwjgl/MemoryUtil else (Ljava/nio/IntBuffer;)J
L57:    aload_3
L58:    invokestatic Method org/lwjgl/MemoryUtil break (Ljava/nio/IntBuffer;)J
L61:    aload 4
L63:    invokestatic Method org/lwjgl/MemoryUtil break (Ljava/nio/IntBuffer;)J
L66:    aload 5
L68:    invokestatic Method org/lwjgl/MemoryUtil const (Ljava/nio/ByteBuffer;)J
L71:    lload 6
L73:    invokestatic Method org/lwjgl/opengl/GL20 nglGetActiveAttrib (IIIJJJJJ)V
L76:    return
L77:    
        .attribute StackMap b'\x00\x01\x00\x18\x00\x07\x01\x01\x07\x00\xF5\x07\x00\xF5\x07\x00\xF5\x07\x01\x3F\x04\x00\x00'
    .end code
.end method

.method static native nglUniform4f : (IFFFFJ)V
.end method

.method public static catch : (I)V
    .code stack 4 locals 3
L0:     invokestatic Method org/lwjgl/opengl/GLContext break ()Lorg/lwjgl/opengl/kb;
L3:     getfield Field org/lwjgl/opengl/kb mO J
L6:     dup2
L7:     lstore_1
L8:     invokestatic Method org/lwjgl/l break (J)V
L11:    iload_0
L12:    lload_1
L13:    invokestatic Method org/lwjgl/opengl/GL20 nglDisableVertexAttribArray (IJ)V
L16:    return
L17:    
    .end code
.end method

.method static native nglDetachShader : (IIJ)V
.end method

.method public static break : (IFFFF)V
    .code stack 7 locals 7
L0:     invokestatic Method org/lwjgl/opengl/GLContext break ()Lorg/lwjgl/opengl/kb;
L3:     getfield Field org/lwjgl/opengl/kb oK J
L6:     dup2
L7:     lstore 5
L9:     invokestatic Method org/lwjgl/l break (J)V
L12:    iload_0
L13:    fload_1
L14:    fload_2
L15:    fload_3
L16:    fload 4
L18:    lload 5
L20:    invokestatic Method org/lwjgl/opengl/GL20 nglVertexAttrib4f (IFFFFJ)V
L23:    return
L24:    
    .end code
.end method

.method static native nglVertexAttrib3d : (IDDDJ)V
.end method

.method static native nglDrawBuffers : (IJJ)V
.end method

.method public static else : (ILjava/nio/IntBuffer;Ljava/nio/ByteBuffer;)V
    .code stack 8 locals 5
L0:     invokestatic Method org/lwjgl/opengl/GLContext break ()Lorg/lwjgl/opengl/kb;
L3:     getfield Field org/lwjgl/opengl/kb iT J
L6:     dup2
L7:     lstore_3
L8:     invokestatic Method org/lwjgl/l break (J)V
L11:    aload_1
L12:    ifnull L23
L15:    aload_1
L16:    iconst_1
L17:    dup
L18:    dup
L19:    pop2
L20:    invokestatic Method org/lwjgl/l break (Ljava/nio/IntBuffer;I)V
L23:    aload_2
L24:    invokestatic Method org/lwjgl/l break (Ljava/nio/ByteBuffer;)V
L27:    iload_0
L28:    aload_2
L29:    invokevirtual Method java/nio/ByteBuffer remaining ()I
L32:    aload_1
L33:    invokestatic Method org/lwjgl/MemoryUtil else (Ljava/nio/IntBuffer;)J
L36:    aload_2
L37:    invokestatic Method org/lwjgl/MemoryUtil const (Ljava/nio/ByteBuffer;)J
L40:    lload_3
L41:    invokestatic Method org/lwjgl/opengl/GL20 nglGetProgramInfoLog (IIJJJ)V
L44:    return
L45:    
        .attribute StackMap b'\x00\x01\x00\x17\x00\x04\x01\x07\x00\xF5\x07\x01\x3F\x04\x00\x00'
    .end code
.end method

.method public static break : (ILjava/nio/IntBuffer;)V
    .code stack 6 locals 4
L0:     invokestatic Method org/lwjgl/opengl/GLContext break ()Lorg/lwjgl/opengl/kb;
L3:     getfield Field org/lwjgl/opengl/kb Kq J
L6:     dup2
L7:     lstore_2
L8:     invokestatic Method org/lwjgl/l break (J)V
L11:    iload_0
L12:    aload_1
L13:    invokestatic Method org/lwjgl/l else (Ljava/nio/IntBuffer;)V
L16:    aload_1
L17:    invokevirtual Method java/nio/IntBuffer remaining ()I
L20:    iconst_3
L21:    iconst_1
L22:    dup
L23:    pop2
L24:    idiv
L25:    aload_1
L26:    invokestatic Method org/lwjgl/MemoryUtil break (Ljava/nio/IntBuffer;)J
L29:    lload_2
L30:    invokestatic Method org/lwjgl/opengl/GL20 nglUniform3iv (IIJJ)V
L33:    return
L34:    
    .end code
.end method

.method static native nglVertexAttrib1f : (IFJ)V
.end method

.method public static const : (II)I
    .code stack 2 locals 2
L0:     iload_0
L1:     iload_1
L2:     invokestatic Method org/lwjgl/opengl/GL20 break (II)I
L5:     ireturn
L6:     
    .end code
    .deprecated
.end method

.method public static float : (I)Z
    .code stack 4 locals 3
L0:     invokestatic Method org/lwjgl/opengl/GLContext break ()Lorg/lwjgl/opengl/kb;
L3:     getfield Field org/lwjgl/opengl/kb wf J
L6:     dup2
L7:     lstore_1
L8:     invokestatic Method org/lwjgl/l break (J)V
L11:    iload_0
L12:    lload_1
L13:    invokestatic Method org/lwjgl/opengl/GL20 nglIsProgram (IJ)Z
L16:    ireturn
L17:    
    .end code
.end method

.method public static else : (ILjava/lang/CharSequence;)I
    .code stack 5 locals 5
L0:     invokestatic Method org/lwjgl/opengl/GLContext break ()Lorg/lwjgl/opengl/kb;
L3:     dup
L4:     astore_2
L5:     getfield Field org/lwjgl/opengl/kb UL J
L8:     dup2
L9:     lstore_3
L10:    invokestatic Method org/lwjgl/l break (J)V
L13:    iload_0
L14:    aload_2
L15:    aload_1
L16:    invokestatic Method org/lwjgl/opengl/bB break (Lorg/lwjgl/opengl/kb;Ljava/lang/CharSequence;)J
L19:    lload_3
L20:    invokestatic Method org/lwjgl/opengl/GL20 nglGetUniformLocation (IJJ)I
L23:    ireturn
L24:    
    .end code
.end method

.method public static else : (II)I
    .code stack 13 locals 6
L0:     invokestatic Method org/lwjgl/opengl/GLContext break ()Lorg/lwjgl/opengl/kb;
L3:     dup
L4:     astore_2
L5:     dup
L6:     getfield Field org/lwjgl/opengl/kb pi J
L9:     dup2
L10:    lstore_3
L11:    invokestatic Method org/lwjgl/l break (J)V
L14:    invokestatic Method org/lwjgl/opengl/bB short (Lorg/lwjgl/opengl/kb;)Ljava/nio/IntBuffer;
L17:    astore 5
L19:    iload_0
L20:    iload_1
L21:    iconst_0
L22:    iconst_1
L23:    dup
L24:    pop2
L25:    lconst_0
L26:    aload 5
L28:    iconst_1
L29:    dup
L30:    dup
L31:    pop2
L32:    invokestatic Method org/lwjgl/MemoryUtil break (Ljava/nio/IntBuffer;I)J
L35:    aload 5
L37:    invokestatic Method org/lwjgl/MemoryUtil break (Ljava/nio/IntBuffer;)J
L40:    aload_2
L41:    invokestatic Method org/lwjgl/opengl/bB catch (Lorg/lwjgl/opengl/kb;)J
L44:    lload_3
L45:    invokestatic Method org/lwjgl/opengl/GL20 nglGetActiveUniform (IIIJJJJJ)V
L48:    aload 5
L50:    iconst_0
L51:    iconst_1
L52:    dup
L53:    pop2
L54:    invokevirtual Method java/nio/IntBuffer get (I)I
L57:    ireturn
L58:    
    .end code
.end method

.method static native nglGetProgramInfoLog : (IIJJJ)V
.end method

.method public static break : (ILjava/nio/FloatBuffer;)V
    .code stack 6 locals 4
L0:     invokestatic Method org/lwjgl/opengl/GLContext break ()Lorg/lwjgl/opengl/kb;
L3:     getfield Field org/lwjgl/opengl/kb U J
L6:     dup2
L7:     lstore_2
L8:     invokestatic Method org/lwjgl/l break (J)V
L11:    iload_0
L12:    aload_1
L13:    invokestatic Method org/lwjgl/l break (Ljava/nio/FloatBuffer;)V
L16:    aload_1
L17:    invokevirtual Method java/nio/FloatBuffer remaining ()I
L20:    iconst_2
L21:    iconst_1
L22:    dup
L23:    pop2
L24:    ishr
L25:    aload_1
L26:    invokestatic Method org/lwjgl/MemoryUtil break (Ljava/nio/FloatBuffer;)J
L29:    lload_2
L30:    invokestatic Method org/lwjgl/opengl/GL20 nglUniform4fv (IIJJ)V
L33:    return
L34:    
    .end code
.end method

.method public static break : (IIILjava/nio/IntBuffer;)Ljava/lang/String;
    .code stack 14 locals 8
L0:     invokestatic Method org/lwjgl/opengl/GLContext break ()Lorg/lwjgl/opengl/kb;
L3:     dup
L4:     astore 4
L6:     dup
L7:     aload_3
L8:     aload 4
L10:    dup_x2
L11:    getfield Field org/lwjgl/opengl/kb cS J
L14:    dup2
L15:    lstore 5
L17:    invokestatic Method org/lwjgl/l break (J)V
L20:    iconst_2
L21:    iconst_1
L22:    dup
L23:    pop2
L24:    invokestatic Method org/lwjgl/l break (Ljava/nio/IntBuffer;I)V
L27:    invokestatic Method org/lwjgl/opengl/bB break (Lorg/lwjgl/opengl/kb;)Ljava/nio/IntBuffer;
L30:    astore 4
L32:    iload_2
L33:    invokestatic Method org/lwjgl/opengl/bB float (Lorg/lwjgl/opengl/kb;I)Ljava/nio/ByteBuffer;
L36:    astore 7
L38:    iload_0
L39:    iload_1
L40:    iload_2
L41:    aload 4
L43:    invokestatic Method org/lwjgl/MemoryUtil break (Ljava/nio/Buffer;)J
L46:    aload_3
L47:    invokestatic Method org/lwjgl/MemoryUtil break (Ljava/nio/IntBuffer;)J
L50:    aload_3
L51:    dup
L52:    invokevirtual Method java/nio/IntBuffer position ()I
L55:    iconst_1
L56:    dup
L57:    dup
L58:    pop2
L59:    iadd
L60:    invokestatic Method org/lwjgl/MemoryUtil break (Ljava/nio/IntBuffer;I)J
L63:    aload 7
L65:    invokestatic Method org/lwjgl/MemoryUtil const (Ljava/nio/ByteBuffer;)J
L68:    lload 5
L70:    invokestatic Method org/lwjgl/opengl/GL20 nglGetActiveAttrib (IIIJJJJJ)V
L73:    aload 7
L75:    dup
L76:    aload 4
L78:    iconst_0
L79:    iconst_1
L80:    dup
L81:    pop2
L82:    invokevirtual Method java/nio/IntBuffer get (I)I
L85:    invokevirtual Method java/nio/ByteBuffer limit (I)Ljava/nio/Buffer;
L88:    pop
L89:    invokestatic Method org/lwjgl/opengl/bB break (Lorg/lwjgl/opengl/kb;Ljava/nio/ByteBuffer;)Ljava/lang/String;
L92:    areturn
L93:    
    .end code
.end method

.method public static short : (I)Z
    .code stack 4 locals 3
L0:     invokestatic Method org/lwjgl/opengl/GLContext break ()Lorg/lwjgl/opengl/kb;
L3:     getfield Field org/lwjgl/opengl/kb Cd J
L6:     dup2
L7:     lstore_1
L8:     invokestatic Method org/lwjgl/l break (J)V
L11:    iload_0
L12:    lload_1
L13:    invokestatic Method org/lwjgl/opengl/GL20 nglIsShader (IJ)Z
L16:    ireturn
L17:    
    .end code
.end method

.method public static break : (II)I
    .code stack 6 locals 5
L0:     invokestatic Method org/lwjgl/opengl/GLContext break ()Lorg/lwjgl/opengl/kb;
L3:     dup
L4:     getfield Field org/lwjgl/opengl/kb eA J
L7:     dup2
L8:     lstore_3
L9:     invokestatic Method org/lwjgl/l break (J)V
L12:    invokestatic Method org/lwjgl/opengl/bB short (Lorg/lwjgl/opengl/kb;)Ljava/nio/IntBuffer;
L15:    astore_2
L16:    iload_0
L17:    iload_1
L18:    aload_2
L19:    invokestatic Method org/lwjgl/MemoryUtil break (Ljava/nio/IntBuffer;)J
L22:    lload_3
L23:    invokestatic Method org/lwjgl/opengl/GL20 nglGetShaderiv (IIJJ)V
L26:    aload_2
L27:    iconst_0
L28:    iconst_1
L29:    dup
L30:    pop2
L31:    invokevirtual Method java/nio/IntBuffer get (I)I
L34:    ireturn
L35:    
    .end code
.end method

.method public static else : (IZLjava/nio/FloatBuffer;)V
    .code stack 7 locals 5
L0:     invokestatic Method org/lwjgl/opengl/GLContext break ()Lorg/lwjgl/opengl/kb;
L3:     getfield Field org/lwjgl/opengl/kb ir J
L6:     dup2
L7:     lstore_3
L8:     invokestatic Method org/lwjgl/l break (J)V
L11:    iload_0
L12:    aload_2
L13:    invokestatic Method org/lwjgl/l break (Ljava/nio/FloatBuffer;)V
L16:    aload_2
L17:    invokevirtual Method java/nio/FloatBuffer remaining ()I
L20:    iconst_2
L21:    iconst_1
L22:    dup
L23:    pop2
L24:    ishr
L25:    iload_1
L26:    aload_2
L27:    invokestatic Method org/lwjgl/MemoryUtil break (Ljava/nio/FloatBuffer;)J
L30:    lload_3
L31:    invokestatic Method org/lwjgl/opengl/GL20 nglUniformMatrix2fv (IIZJJ)V
L34:    return
L35:    
    .end code
.end method

.method public static const : (I)V
    .code stack 4 locals 3
L0:     invokestatic Method org/lwjgl/opengl/GLContext break ()Lorg/lwjgl/opengl/kb;
L3:     getfield Field org/lwjgl/opengl/kb KH J
L6:     dup2
L7:     lstore_1
L8:     invokestatic Method org/lwjgl/l break (J)V
L11:    iload_0
L12:    lload_1
L13:    invokestatic Method org/lwjgl/opengl/GL20 nglCompileShader (IJ)V
L16:    return
L17:    
    .end code
.end method

.method public static break : (IILjava/nio/ByteBuffer;)V
    .code stack 6 locals 5
L0:     invokestatic Method org/lwjgl/opengl/GLContext break ()Lorg/lwjgl/opengl/kb;
L3:     getfield Field org/lwjgl/opengl/kb Go J
L6:     dup2
L7:     lstore_3
L8:     invokestatic Method org/lwjgl/l break (J)V
L11:    iload_0
L12:    aload_2
L13:    dup
L14:    invokestatic Method org/lwjgl/l break (Ljava/nio/ByteBuffer;)V
L17:    invokestatic Method org/lwjgl/l else (Ljava/nio/ByteBuffer;)V
L20:    iload_1
L21:    aload_2
L22:    invokestatic Method org/lwjgl/MemoryUtil const (Ljava/nio/ByteBuffer;)J
L25:    lload_3
L26:    invokestatic Method org/lwjgl/opengl/GL20 nglBindAttribLocation (IIJJ)V
L29:    return
L30:    
    .end code
.end method

.method static native nglUniform1fv : (IIJJ)V
.end method

.method static native nglGetVertexAttribdv : (IIJJ)V
.end method

.method static native nglStencilOpSeparate : (IIIIJ)V
.end method

.method public static else : (IILjava/nio/IntBuffer;)V
    .code stack 6 locals 5
L0:     invokestatic Method org/lwjgl/opengl/GLContext break ()Lorg/lwjgl/opengl/kb;
L3:     getfield Field org/lwjgl/opengl/kb XA J
L6:     dup2
L7:     lstore_3
L8:     invokestatic Method org/lwjgl/l break (J)V
L11:    iload_0
L12:    aload_2
L13:    iconst_4
L14:    iconst_1
L15:    dup
L16:    pop2
L17:    invokestatic Method org/lwjgl/l break (Ljava/nio/IntBuffer;I)V
L20:    iload_1
L21:    aload_2
L22:    invokestatic Method org/lwjgl/MemoryUtil break (Ljava/nio/IntBuffer;)J
L25:    lload_3
L26:    invokestatic Method org/lwjgl/opengl/GL20 nglGetVertexAttribiv (IIJJ)V
L29:    return
L30:    
    .end code
.end method

.method public static break : (I[Ljava/lang/CharSequence;)V
    .code stack 8 locals 5
L0:     invokestatic Method org/lwjgl/opengl/GLContext break ()Lorg/lwjgl/opengl/kb;
L3:     astore_2
L4:     aload_1
L5:     aload_2
L6:     getfield Field org/lwjgl/opengl/kb kb J
L9:     dup2
L10:    lstore_3
L11:    invokestatic Method org/lwjgl/l break (J)V
L14:    invokestatic Method org/lwjgl/l break ([Ljava/lang/Object;)V
L17:    iload_0
L18:    aload_1
L19:    arraylength
L20:    aload_2
L21:    aload_1
L22:    invokestatic Method org/lwjgl/opengl/bB else (Lorg/lwjgl/opengl/kb;[Ljava/lang/CharSequence;)J
L25:    aload_2
L26:    aload_1
L27:    invokestatic Method org/lwjgl/opengl/bB break (Lorg/lwjgl/opengl/kb;[Ljava/lang/CharSequence;)J
L30:    lload_3
L31:    invokestatic Method org/lwjgl/opengl/GL20 nglShaderSource3 (IIJJJ)V
L34:    return
L35:    
    .end code
.end method

.method static native nglVertexAttrib3f : (IFFFJ)V
.end method

.method static native nglShaderSource : (IIJIJ)V
.end method

.method public static break : (IDDD)V
    .code stack 9 locals 9
L0:     invokestatic Method org/lwjgl/opengl/GLContext break ()Lorg/lwjgl/opengl/kb;
L3:     getfield Field org/lwjgl/opengl/kb xb J
L6:     dup2
L7:     lstore 7
L9:     invokestatic Method org/lwjgl/l break (J)V
L12:    iload_0
L13:    dload_1
L14:    dload_3
L15:    dload 5
L17:    lload 7
L19:    invokestatic Method org/lwjgl/opengl/GL20 nglVertexAttrib3d (IDDDJ)V
L22:    return
L23:    
    .end code
.end method

.method public static break : (IZLjava/nio/FloatBuffer;)V
    .code stack 7 locals 5
L0:     invokestatic Method org/lwjgl/opengl/GLContext break ()Lorg/lwjgl/opengl/kb;
L3:     getfield Field org/lwjgl/opengl/kb hm J
L6:     dup2
L7:     lstore_3
L8:     invokestatic Method org/lwjgl/l break (J)V
L11:    iload_0
L12:    aload_2
L13:    invokestatic Method org/lwjgl/l break (Ljava/nio/FloatBuffer;)V
L16:    aload_2
L17:    invokevirtual Method java/nio/FloatBuffer remaining ()I
L20:    iconst_4
L21:    iconst_1
L22:    dup
L23:    pop2
L24:    ishr
L25:    iload_1
L26:    aload_2
L27:    invokestatic Method org/lwjgl/MemoryUtil break (Ljava/nio/FloatBuffer;)J
L30:    lload_3
L31:    invokestatic Method org/lwjgl/opengl/GL20 nglUniformMatrix4fv (IIZJJ)V
L34:    return
L35:    
    .end code
.end method

.method public static break : (IILjava/nio/IntBuffer;)V
    .code stack 6 locals 5
L0:     invokestatic Method org/lwjgl/opengl/GLContext break ()Lorg/lwjgl/opengl/kb;
L3:     getfield Field org/lwjgl/opengl/kb eA J
L6:     dup2
L7:     lstore_3
L8:     invokestatic Method org/lwjgl/l break (J)V
L11:    iload_0
L12:    aload_2
L13:    invokestatic Method org/lwjgl/l else (Ljava/nio/IntBuffer;)V
L16:    iload_1
L17:    aload_2
L18:    invokestatic Method org/lwjgl/MemoryUtil break (Ljava/nio/IntBuffer;)J
L21:    lload_3
L22:    invokestatic Method org/lwjgl/opengl/GL20 nglGetShaderiv (IIJJ)V
L25:    return
L26:    
    .end code
.end method

.method static native nglGetVertexAttribPointerv : (IIJJ)Ljava/nio/ByteBuffer;
.end method

.method public static break : (ILjava/lang/CharSequence;)I
    .code stack 5 locals 5
L0:     invokestatic Method org/lwjgl/opengl/GLContext break ()Lorg/lwjgl/opengl/kb;
L3:     dup
L4:     astore_2
L5:     getfield Field org/lwjgl/opengl/kb we J
L8:     dup2
L9:     lstore_3
L10:    invokestatic Method org/lwjgl/l break (J)V
L13:    iload_0
L14:    aload_2
L15:    aload_1
L16:    invokestatic Method org/lwjgl/opengl/bB break (Lorg/lwjgl/opengl/kb;Ljava/lang/CharSequence;)J
L19:    lload_3
L20:    invokestatic Method org/lwjgl/opengl/GL20 nglGetAttribLocation (IJJ)I
L23:    ireturn
L24:    
    .end code
.end method

.method static native nglUniform1f : (IFJ)V
.end method

.method public static break : (ID)V
    .code stack 5 locals 5
L0:     invokestatic Method org/lwjgl/opengl/GLContext break ()Lorg/lwjgl/opengl/kb;
L3:     getfield Field org/lwjgl/opengl/kb oB J
L6:     dup2
L7:     lstore_3
L8:     invokestatic Method org/lwjgl/l break (J)V
L11:    iload_0
L12:    dload_1
L13:    lload_3
L14:    invokestatic Method org/lwjgl/opengl/GL20 nglVertexAttrib1d (IDJ)V
L17:    return
L18:    
    .end code
.end method

.method public static else : (I)I
    .code stack 4 locals 3
L0:     invokestatic Method org/lwjgl/opengl/GLContext break ()Lorg/lwjgl/opengl/kb;
L3:     getfield Field org/lwjgl/opengl/kb dA J
L6:     dup2
L7:     lstore_1
L8:     invokestatic Method org/lwjgl/l break (J)V
L11:    iload_0
L12:    lload_1
L13:    invokestatic Method org/lwjgl/opengl/GL20 nglCreateShader (IJ)I
L16:    ireturn
L17:    
    .end code
.end method

.method static native nglGetVertexAttribiv : (IIJJ)V
.end method

.method public static break : (IILjava/nio/IntBuffer;Ljava/nio/IntBuffer;Ljava/nio/IntBuffer;Ljava/nio/ByteBuffer;)V
    .code stack 13 locals 8
L0:     invokestatic Method org/lwjgl/opengl/GLContext break ()Lorg/lwjgl/opengl/kb;
L3:     getfield Field org/lwjgl/opengl/kb pi J
L6:     dup2
L7:     lstore 6
L9:     invokestatic Method org/lwjgl/l break (J)V
L12:    aload_2
L13:    ifnull L24
L16:    aload_2
L17:    iconst_1
L18:    dup
L19:    dup
L20:    pop2
L21:    invokestatic Method org/lwjgl/l break (Ljava/nio/IntBuffer;I)V
L24:    aload_3
L25:    iconst_1
L26:    dup
L27:    dup
L28:    pop2
L29:    invokestatic Method org/lwjgl/l break (Ljava/nio/IntBuffer;I)V
L32:    iload_0
L33:    aload 5
L35:    aload 4
L37:    iconst_1
L38:    dup
L39:    dup
L40:    pop2
L41:    invokestatic Method org/lwjgl/l break (Ljava/nio/IntBuffer;I)V
L44:    invokestatic Method org/lwjgl/l break (Ljava/nio/ByteBuffer;)V
L47:    iload_1
L48:    aload 5
L50:    invokevirtual Method java/nio/ByteBuffer remaining ()I
L53:    aload_2
L54:    invokestatic Method org/lwjgl/MemoryUtil else (Ljava/nio/IntBuffer;)J
L57:    aload_3
L58:    invokestatic Method org/lwjgl/MemoryUtil break (Ljava/nio/IntBuffer;)J
L61:    aload 4
L63:    invokestatic Method org/lwjgl/MemoryUtil break (Ljava/nio/IntBuffer;)J
L66:    aload 5
L68:    invokestatic Method org/lwjgl/MemoryUtil const (Ljava/nio/ByteBuffer;)J
L71:    lload 6
L73:    invokestatic Method org/lwjgl/opengl/GL20 nglGetActiveUniform (IIIJJJJJ)V
L76:    return
L77:    
        .attribute StackMap b'\x00\x01\x00\x18\x00\x07\x01\x01\x07\x00\xF5\x07\x00\xF5\x07\x00\xF5\x07\x01\x3F\x04\x00\x00'
    .end code
.end method

.method static native nglGetShaderInfoLog : (IIJJJ)V
.end method

.method public static else : (IFFF)V
    .code stack 6 locals 6
L0:     invokestatic Method org/lwjgl/opengl/GLContext break ()Lorg/lwjgl/opengl/kb;
L3:     getfield Field org/lwjgl/opengl/kb oH J
L6:     dup2
L7:     lstore 4
L9:     invokestatic Method org/lwjgl/l break (J)V
L12:    iload_0
L13:    fload_1
L14:    fload_2
L15:    fload_3
L16:    lload 4
L18:    invokestatic Method org/lwjgl/opengl/GL20 nglUniform3f (IFFFJ)V
L21:    return
L22:    
    .end code
.end method

.method public static break : (ILjava/nio/IntBuffer;Ljava/nio/ByteBuffer;)V
    .code stack 8 locals 5
L0:     invokestatic Method org/lwjgl/opengl/GLContext break ()Lorg/lwjgl/opengl/kb;
L3:     getfield Field org/lwjgl/opengl/kb eB J
L6:     dup2
L7:     lstore_3
L8:     invokestatic Method org/lwjgl/l break (J)V
L11:    aload_1
L12:    ifnull L23
L15:    aload_1
L16:    iconst_1
L17:    dup
L18:    dup
L19:    pop2
L20:    invokestatic Method org/lwjgl/l break (Ljava/nio/IntBuffer;I)V
L23:    aload_2
L24:    invokestatic Method org/lwjgl/l break (Ljava/nio/ByteBuffer;)V
L27:    iload_0
L28:    aload_2
L29:    invokevirtual Method java/nio/ByteBuffer remaining ()I
L32:    aload_1
L33:    invokestatic Method org/lwjgl/MemoryUtil else (Ljava/nio/IntBuffer;)J
L36:    aload_2
L37:    invokestatic Method org/lwjgl/MemoryUtil const (Ljava/nio/ByteBuffer;)J
L40:    lload_3
L41:    invokestatic Method org/lwjgl/opengl/GL20 nglGetShaderSource (IIJJJ)V
L44:    return
L45:    
        .attribute StackMap b'\x00\x01\x00\x17\x00\x04\x01\x07\x00\xF5\x07\x01\x3F\x04\x00\x00'
    .end code
.end method

.method public static break : (IFFF)V
    .code stack 6 locals 6
L0:     invokestatic Method org/lwjgl/opengl/GLContext break ()Lorg/lwjgl/opengl/kb;
L3:     getfield Field org/lwjgl/opengl/kb BA J
L6:     dup2
L7:     lstore 4
L9:     invokestatic Method org/lwjgl/l break (J)V
L12:    iload_0
L13:    fload_1
L14:    fload_2
L15:    fload_3
L16:    lload 4
L18:    invokestatic Method org/lwjgl/opengl/GL20 nglVertexAttrib3f (IFFFJ)V
L21:    return
L22:    
    .end code
.end method

.method public static break : (IFF)V
    .code stack 5 locals 5
L0:     invokestatic Method org/lwjgl/opengl/GLContext break ()Lorg/lwjgl/opengl/kb;
L3:     getfield Field org/lwjgl/opengl/kb iD J
L6:     dup2
L7:     lstore_3
L8:     invokestatic Method org/lwjgl/l break (J)V
L11:    iload_0
L12:    fload_1
L13:    fload_2
L14:    lload_3
L15:    invokestatic Method org/lwjgl/opengl/GL20 nglVertexAttrib2f (IFFJ)V
L18:    return
L19:    
    .end code
.end method

.method public static break : (I)V
    .code stack 4 locals 3
L0:     invokestatic Method org/lwjgl/opengl/GLContext break ()Lorg/lwjgl/opengl/kb;
L3:     getfield Field org/lwjgl/opengl/kb lc J
L6:     dup2
L7:     lstore_1
L8:     invokestatic Method org/lwjgl/l break (J)V
L11:    iload_0
L12:    lload_1
L13:    invokestatic Method org/lwjgl/opengl/GL20 nglDeleteShader (IJ)V
L16:    return
L17:    
    .end code
.end method

.method static native nglValidateProgram : (IJ)V
.end method
.end class
