.version 49 0
.class public final super org/lwjgl/opengl/GL30
.super java/lang/Object
.field public static final zB I = 5131
.field public static final NA I = 36055
.field public static final pB I = 36304
.field public static final ub I = 35983
.field public static final uC I = 35902
.field public static final Md I = 36297
.field public static final fC I = 36011
.field public static final PA I = 33331
.field public static final Tb I = 36301
.field public static final bA I = 34844
.field public static final IB I = 36182
.field public static final jC I = 36292
.field public static final ZC I = 36248
.field public static final cd I = 35056
.field public static final Id I = 36298
.field public static final RC I = 33298
.field public static final gb I = 36226
.field public static final vB I = 36291
.field public static final EC I = 33333
.field public static final Pc I = 1
.field public static final Cb I = 34024
.field public static final yc I = 36078
.field public static final nc I = 36293
.field public static final iA I = 36180
.field public static final kc I = 36010
.field public static final KB I = 36008
.field public static final yC I = 12288
.field public static final Ed I = 34842
.field public static final Wb I = 36061
.field public static final qd I = 37153
.field public static final mB I = 36164
.field public static final Ab I = 36249
.field public static final Vb I = 33334
.field public static final OC I = 33304
.field public static final Bd I = 35867
.field public static final Dc I = 36063
.field public static final cC I = 33300
.field public static final Kd I = 35968
.field public static final IA I = 36373
.field public static final QC I = 36214
.field public static final VB I = 33316
.field public static final ab I = 33335
.field public static final hC I = 35659
.field public static final zb I = 36286
.field public static final Cc I = 36076
.field public static final AC I = 36210
.field public static final Od I = 36372
.field public static final dB I = 36208
.field public static final NC I = 33336
.field public static final Yb I = 36374
.field public static final Sd I = 36006
.field public static final hA I = 35868
.field public static final Db I = 33307
.field public static final NB I = 33321
.field public static final id I = 35057
.field public static final TC I = 36311
.field public static final kB I = 37151
.field public static final bC I = 36306
.field public static final xC I = 36227
.field public static final vc I = 36246
.field public static final kC I = 35982
.field public static final zC I = 36267
.field public static final kA I = 36179
.field public static final wc I = 36228
.field public static final od I = 36283
.field public static final oC I = 35978
.field public static final ZA I = 36163
.field public static final wA I = 33302
.field public static final aC I = 35977
.field public static final GB I = 34843
.field public static final cB I = 35972
.field public static final wB I = 35856
.field public static final Ld I = 36067
.field public static final HC I = 33297
.field public static final oc I = 33324
.field public static final zA I = 35858
.field public static final lc I = 36048
.field public static final ed I = 34041
.field public static final Xb I = 36162
.field public static final Ac I = 33309
.field public static final iC I = 36066
.field public static final uc I = 12294
.field public static final FC I = 35099
.field public static final WB I = 36299
.field public static final cc I = 33306
.field public static final eB I = 33328
.field public static final Nc I = 36079
.field public static final yb I = 35863
.field public static final xA I = 36168
.field public static final Nd I = 33337
.field public static final Vc I = 36209
.field public static final LC I = 34894
.field public static final jd I = 35981
.field public static final LA I = 1
.field public static final ob I = 36285
.field public static final jc I = 36007
.field public static final nA I = 33322
.field public static final sc I = 36064
.field public static final QB I = 35976
.field public static final AA I = 33299
.field public static final sB I = 35071
.field public static final Ic I = 36128
.field public static final fB I = 36294
.field public static final eC I = 36167
.field public static final JA I = 36077
.field public static final tc I = 35869
.field public static final MC I = 33315
.field public static final vC I = 36050
.field public static final PB I = 35975
.field public static final Gb I = 33327
.field public static final Nb I = 36183
.field public static final CB I = 35069
.field public static final xB I = 35859
.field public static final bc I = 33329
.field public static final Hc I = 35866
.field public static final PC I = 33310
.field public static final tb I = 36281
.field public static final LB I = 36284
.field public static final eb I = 36308
.field public static final Oc I = 35857
.field public static final Lb I = 36009
.field public static final JB I = 36302
.field public static final Z I = 36312
.field public static final Pb I = 33318
.field public static final CA I = 36250
.field public static final DB I = 35862
.field public static final yB I = 33338
.field public static final FB I = 36072
.field public static final Rd I = 36239
.field public static final dc I = 35100
.field public static final hd I = 36073
.field public static final RA I = 35101
.field public static final md I = 12292
.field public static final TA I = 35958
.field public static final Sb I = 36074
.field public static final v I = 36238
.field public static final p I = 36216
.field public static final U I = 35098
.field public static final V I = 33319
.field public static final R I = 35076
.field public static final z I = 33339
.field public static final q I = 36295
.field public static final X I = 33332
.field public static final P I = 36305
.field public static final O I = 33340
.field public static final w I = 34229
.field public static final y I = 36233
.field public static final o I = 36065
.field public static final Y I = 36070
.field public static final S I = 37152
.field public static final N I = 33317
.field public static final u I = 36071
.field public static final s I = 33308
.field public static final t I = 12293
.field public static final W I = 12291
.field public static final Q I = 12295
.field public static final T I = 36221
.field public static final r I = 36232
.field public static final x I = 36269
.field public static final n I = 35860
.field public static final M I = 36006
.field public static final L I = 3378
.field public static final H I = 36309
.field public static final d I = 36051
.field public static final e I = 36075
.field public static final g I = 36310
.field public static final k I = 33320
.field public static final a I = 36160
.field public static final F I = 36176
.field public static final A I = 36220
.field public static final E I = 36240
.field public static final C I = 35899
.field public static final K I = 33314
.field public static final G I = 34838
.field public static final B I = 36161
.field public static final c I = 35861
.field public static final "synchronized" I = 32
.field public static final i I = 36289
.field public static final m I = 16
.field public static final h I = 36178
.field public static final J I = 12290
.field public static final l I = 36268
.field public static final D I = 36371
.field public static final f I = 36215
.field public static final j I = 35898
.field public static final I I = 36282
.field public static final b I = 36060
.field public static final implements I = 36251
.field public static final return I = 33296
.field public static final default I = 4
.field public static final switch I = 36049
.field public static final "interface" I = 36053
.field public static final "private" I = 36247
.field public static final assert I = 12289
.field public static final boolean I = 35903
.field public static final "strictfp" I = 36288
.field public static final "abstract" I = 1286
.field public static final "public" I = 33330
.field public static final "volatile" I = 36296
.field public static final double I = 35967
.field public static final throw I = 36290
.field public static final package I = 8
.field public static final finally I = 35864
.field public static final "transient" I = 34836
.field public static final while I = 33303
.field public static final instanceof I = 36059
.field public static final "protected" I = 34837
.field public static final import I = 36068
.field public static final "native" I = 36181
.field public static final throws I = 36169
.field public static final "static" I = 33326
.field public static final continue I = 35901
.field public static final extends I = 36303
.field public static final float I = 36254
.field public static final "final" I = 34042
.field public static final catch I = 36300
.field public static final false I = 36166
.field public static final class I = 33301
.field public static final if I = 2
.field public static final true I = 35979
.field public static final for I = 35971
.field public static final case I = 36052
.field public static final byte I = 36096
.field public static final "super" I = 34894
.field public static final int I = 36245
.field public static final short I = 36069
.field public static final goto I = 36244
.field public static final break I = 33323
.field public static final long I = 35077
.field public static final void I = 36054
.field public static final try I = 36177
.field public static final const I = 33305
.field public static final new I = 36222
.field public static final null I = 36234
.field public static final this I = 35973
.field public static final char I = 33325
.field public static final else I = 35980
.field public static final "enum" I = 36307
.field public static final do I = 35865

.method public static "enum" : (II)V
    .code stack 4 locals 4
L0:     invokestatic Method org/lwjgl/opengl/GLContext break ()Lorg/lwjgl/opengl/kb;
L3:     getfield Field org/lwjgl/opengl/kb xe J
L6:     dup2
L7:     lstore_2
L8:     invokestatic Method org/lwjgl/l break (J)V
L11:    iload_0
L12:    iload_1
L13:    lload_2
L14:    invokestatic Method org/lwjgl/opengl/GL30 nglVertexAttribI1i (IIJ)V
L17:    return
L18:    
    .end code
.end method

.method static native nglGetVertexAttribIiv : (IIJJ)V
.end method

.method static native nglUniform4uiv : (IIJJ)V
.end method

.method public static try : (IILjava/nio/IntBuffer;)V
    .code stack 6 locals 5
L0:     invokestatic Method org/lwjgl/opengl/GLContext break ()Lorg/lwjgl/opengl/kb;
L3:     getfield Field org/lwjgl/opengl/kb rp J
L6:     dup2
L7:     lstore_3
L8:     invokestatic Method org/lwjgl/l break (J)V
L11:    iload_0
L12:    aload_2
L13:    iconst_4
L14:    iconst_1
L15:    dup
L16:    pop2
L17:    invokestatic Method org/lwjgl/l break (Ljava/nio/IntBuffer;I)V
L20:    iload_1
L21:    aload_2
L22:    invokestatic Method org/lwjgl/MemoryUtil break (Ljava/nio/IntBuffer;)J
L25:    lload_3
L26:    invokestatic Method org/lwjgl/opengl/GL30 nglGetIntegeri_v (IIJJ)V
L29:    return
L30:    
    .end code
.end method

.method public static for : (IIIII)V
    .code stack 7 locals 7
L0:     invokestatic Method org/lwjgl/opengl/GLContext break ()Lorg/lwjgl/opengl/kb;
L3:     getfield Field org/lwjgl/opengl/kb rs J
L6:     dup2
L7:     lstore 5
L9:     invokestatic Method org/lwjgl/l break (J)V
L12:    iload_0
L13:    iload_1
L14:    iload_2
L15:    iload_3
L16:    iload 4
L18:    lload 5
L20:    invokestatic Method org/lwjgl/opengl/GL30 nglFramebufferTextureLayer (IIIIIJ)V
L23:    return
L24:    
    .end code
.end method

.method public static this : (IILjava/nio/IntBuffer;)V
    .code stack 6 locals 5
L0:     invokestatic Method org/lwjgl/opengl/GLContext break ()Lorg/lwjgl/opengl/kb;
L3:     getfield Field org/lwjgl/opengl/kb st J
L6:     dup2
L7:     lstore_3
L8:     invokestatic Method org/lwjgl/l break (J)V
L11:    iload_0
L12:    aload_2
L13:    iconst_4
L14:    iconst_1
L15:    dup
L16:    pop2
L17:    invokestatic Method org/lwjgl/l break (Ljava/nio/IntBuffer;I)V
L20:    iload_1
L21:    aload_2
L22:    invokestatic Method org/lwjgl/MemoryUtil break (Ljava/nio/IntBuffer;)J
L25:    lload_3
L26:    invokestatic Method org/lwjgl/opengl/GL30 nglClearBufferiv (IIJJ)V
L29:    return
L30:    
    .end code
.end method

.method public static goto : (IILjava/nio/IntBuffer;)V
    .code stack 6 locals 5
L0:     invokestatic Method org/lwjgl/opengl/GLContext break ()Lorg/lwjgl/opengl/kb;
L3:     getfield Field org/lwjgl/opengl/kb Vd J
L6:     dup2
L7:     lstore_3
L8:     invokestatic Method org/lwjgl/l break (J)V
L11:    iload_0
L12:    aload_2
L13:    iconst_4
L14:    iconst_1
L15:    dup
L16:    pop2
L17:    invokestatic Method org/lwjgl/l break (Ljava/nio/IntBuffer;I)V
L20:    iload_1
L21:    aload_2
L22:    invokestatic Method org/lwjgl/MemoryUtil break (Ljava/nio/IntBuffer;)J
L25:    lload_3
L26:    invokestatic Method org/lwjgl/opengl/GL30 nglGetVertexAttribIuiv (IIJJ)V
L29:    return
L30:    
    .end code
.end method

.method public static new : (ILjava/nio/IntBuffer;)V
    .code stack 5 locals 4
L0:     invokestatic Method org/lwjgl/opengl/GLContext break ()Lorg/lwjgl/opengl/kb;
L3:     getfield Field org/lwjgl/opengl/kb MA J
L6:     dup2
L7:     lstore_2
L8:     invokestatic Method org/lwjgl/l break (J)V
L11:    iload_0
L12:    aload_1
L13:    iconst_2
L14:    iconst_1
L15:    dup
L16:    pop2
L17:    invokestatic Method org/lwjgl/l break (Ljava/nio/IntBuffer;I)V
L20:    aload_1
L21:    invokestatic Method org/lwjgl/MemoryUtil break (Ljava/nio/IntBuffer;)J
L24:    lload_2
L25:    invokestatic Method org/lwjgl/opengl/GL30 nglVertexAttribI2iv (IJJ)V
L28:    return
L29:    
    .end code
.end method

.method public static do : (III)V
    .code stack 6 locals 6
L0:     invokestatic Method org/lwjgl/opengl/GLContext break ()Lorg/lwjgl/opengl/kb;
L3:     dup
L4:     astore_3
L5:     getfield Field org/lwjgl/opengl/kb bD J
L8:     dup2
L9:     lstore 4
L11:    invokestatic Method org/lwjgl/l break (J)V
L14:    iload_0
L15:    iload_1
L16:    aload_3
L17:    iload_2
L18:    invokestatic Method org/lwjgl/opengl/bB const (Lorg/lwjgl/opengl/kb;I)J
L21:    lload 4
L23:    invokestatic Method org/lwjgl/opengl/GL30 nglTexParameterIiv (IIJJ)V
L26:    return
L27:    
    .end code
.end method

.method static native nglBeginTransformFeedback : (IJ)V
.end method

.method static native nglTexParameterIiv : (IIJJ)V
.end method

.method public static break : (IIIIIIIIII)V
    .code stack 12 locals 12
L0:     invokestatic Method org/lwjgl/opengl/GLContext break ()Lorg/lwjgl/opengl/kb;
L3:     getfield Field org/lwjgl/opengl/kb fH J
L6:     dup2
L7:     lstore 10
L9:     invokestatic Method org/lwjgl/l break (J)V
L12:    iload_0
L13:    iload_1
L14:    iload_2
L15:    iload_3
L16:    iload 4
L18:    iload 5
L20:    iload 6
L22:    iload 7
L24:    iload 8
L26:    iload 9
L28:    lload 10
L30:    invokestatic Method org/lwjgl/opengl/GL30 nglBlitFramebuffer (IIIIIIIIIIJ)V
L33:    return
L34:    
    .end code
.end method

.method public static catch : (IIIII)V
    .code stack 7 locals 7
L0:     invokestatic Method org/lwjgl/opengl/GLContext break ()Lorg/lwjgl/opengl/kb;
L3:     getfield Field org/lwjgl/opengl/kb OH J
L6:     dup2
L7:     lstore 5
L9:     invokestatic Method org/lwjgl/l break (J)V
L12:    iload_0
L13:    iload_1
L14:    iload_2
L15:    iload_3
L16:    iload 4
L18:    lload 5
L20:    invokestatic Method org/lwjgl/opengl/GL30 nglFramebufferTexture2D (IIIIIJ)V
L23:    return
L24:    
    .end code
.end method

.method static native nglColorMaski : (IZZZZJ)V
.end method

.method static native nglVertexAttribI1uiv : (IJJ)V
.end method

.method public static try : (ILjava/nio/IntBuffer;)V
    .code stack 5 locals 4
L0:     invokestatic Method org/lwjgl/opengl/GLContext break ()Lorg/lwjgl/opengl/kb;
L3:     getfield Field org/lwjgl/opengl/kb je J
L6:     dup2
L7:     lstore_2
L8:     invokestatic Method org/lwjgl/l break (J)V
L11:    iload_0
L12:    aload_1
L13:    iconst_3
L14:    iconst_1
L15:    dup
L16:    pop2
L17:    invokestatic Method org/lwjgl/l break (Ljava/nio/IntBuffer;I)V
L20:    aload_1
L21:    invokestatic Method org/lwjgl/MemoryUtil break (Ljava/nio/IntBuffer;)J
L24:    lload_2
L25:    invokestatic Method org/lwjgl/opengl/GL30 nglVertexAttribI3uiv (IJJ)V
L28:    return
L29:    
    .end code
.end method

.method public static long : (II)I
    .code stack 6 locals 5
L0:     invokestatic Method org/lwjgl/opengl/GLContext break ()Lorg/lwjgl/opengl/kb;
L3:     dup
L4:     getfield Field org/lwjgl/opengl/kb NR J
L7:     dup2
L8:     lstore_3
L9:     invokestatic Method org/lwjgl/l break (J)V
L12:    invokestatic Method org/lwjgl/opengl/bB short (Lorg/lwjgl/opengl/kb;)Ljava/nio/IntBuffer;
L15:    astore_2
L16:    iload_0
L17:    iload_1
L18:    aload_2
L19:    invokestatic Method org/lwjgl/MemoryUtil break (Ljava/nio/IntBuffer;)J
L22:    lload_3
L23:    invokestatic Method org/lwjgl/opengl/GL30 nglGetTexParameterIuiv (IIJJ)V
L26:    aload_2
L27:    iconst_0
L28:    iconst_1
L29:    dup
L30:    pop2
L31:    invokevirtual Method java/nio/IntBuffer get (I)I
L34:    ireturn
L35:    
    .end code
.end method

.method public static do : (IILjava/nio/IntBuffer;)V
    .code stack 6 locals 5
L0:     invokestatic Method org/lwjgl/opengl/GLContext break ()Lorg/lwjgl/opengl/kb;
L3:     getfield Field org/lwjgl/opengl/kb zr J
L6:     dup2
L7:     lstore_3
L8:     invokestatic Method org/lwjgl/l break (J)V
L11:    iload_0
L12:    aload_2
L13:    invokestatic Method org/lwjgl/l else (Ljava/nio/IntBuffer;)V
L16:    iload_1
L17:    aload_2
L18:    invokestatic Method org/lwjgl/MemoryUtil break (Ljava/nio/IntBuffer;)J
L21:    lload_3
L22:    invokestatic Method org/lwjgl/opengl/GL30 nglGetUniformuiv (IIJJ)V
L25:    return
L26:    
    .end code
.end method

.method static native nglBindFramebuffer : (IIJ)V
.end method

.method public static break : (IIIILjava/nio/ByteBuffer;)V
    .code stack 8 locals 8
L0:     invokestatic Method org/lwjgl/opengl/GLContext break ()Lorg/lwjgl/opengl/kb;
L3:     astore 5
L5:     aload 4
L7:     aload 5
L9:     dup
L10:    getfield Field org/lwjgl/opengl/kb fs J
L13:    dup2
L14:    lstore 6
L16:    invokestatic Method org/lwjgl/l break (J)V
L19:    invokestatic Method org/lwjgl/opengl/Zd break (Lorg/lwjgl/opengl/kb;)V
L22:    invokestatic Method org/lwjgl/l break (Ljava/nio/ByteBuffer;)V
L25:    getstatic Field org/lwjgl/LWJGLUtil CHECKS Z
L28:    ifeq L43
L31:    aload 5
L33:    invokestatic Method org/lwjgl/opengl/w const (Lorg/lwjgl/opengl/kb;)Lorg/lwjgl/opengl/P;
L36:    getfield Field org/lwjgl/opengl/P do [Ljava/nio/Buffer;
L39:    iload_0
L40:    aload 4
L42:    aastore
L43:    iload_0
L44:    iload_1
L45:    iload_2
L46:    iload_3
L47:    aload 4
L49:    invokestatic Method org/lwjgl/MemoryUtil const (Ljava/nio/ByteBuffer;)J
L52:    lload 6
L54:    invokestatic Method org/lwjgl/opengl/GL30 nglVertexAttribIPointer (IIIIJJ)V
L57:    return
L58:    
        .attribute StackMap b'\x00\x01\x00\x2B\x00\x07\x01\x01\x01\x01\x07\x02\x7D\x07\x01\xE7\x04\x00\x00'
    .end code
.end method

.method public static for : (III)I
    .code stack 3 locals 3
L0:     iload_0
L1:     iload_1
L2:     iload_2
L3:     invokestatic Method org/lwjgl/opengl/GL30 short (III)I
L6:     ireturn
L7:     
    .end code
    .deprecated
.end method

.method static native nglVertexAttribIPointer : (IIIIJJ)V
.end method

.method public static class : (II)Z
    .code stack 6 locals 5
L0:     invokestatic Method org/lwjgl/opengl/GLContext break ()Lorg/lwjgl/opengl/kb;
L3:     dup
L4:     getfield Field org/lwjgl/opengl/kb uJ J
L7:     dup2
L8:     lstore_3
L9:     invokestatic Method org/lwjgl/l break (J)V
L12:    iconst_1
L13:    dup
L14:    dup
L15:    pop2
L16:    invokestatic Method org/lwjgl/opengl/bB float (Lorg/lwjgl/opengl/kb;I)Ljava/nio/ByteBuffer;
L19:    astore_2
L20:    iload_0
L21:    iload_1
L22:    aload_2
L23:    invokestatic Method org/lwjgl/MemoryUtil const (Ljava/nio/ByteBuffer;)J
L26:    lload_3
L27:    invokestatic Method org/lwjgl/opengl/GL30 nglGetBooleani_v (IIJJ)V
L30:    aload_2
L31:    iconst_0
L32:    iconst_1
L33:    dup
L34:    pop2
L35:    invokevirtual Method java/nio/ByteBuffer get (I)B
L38:    iconst_1
L39:    dup
L40:    dup
L41:    pop2
L42:    if_icmpne L51
L45:    iconst_1
L46:    dup
L47:    dup
L48:    pop2
L49:    ireturn
L50:    athrow
L51:    iconst_0
L52:    iconst_1
L53:    dup
L54:    pop2
L55:    ireturn
L56:    
        .attribute StackMap b'\x00\x02\x00\x32\x00\x00\x00\x01\x07\x02\x96\x00\x33\x00\x04\x01\x01\x07\x02\x7D\x04\x00\x00'
    .end code
.end method

.method public static for : (IILjava/nio/IntBuffer;)V
    .code stack 6 locals 5
L0:     invokestatic Method org/lwjgl/opengl/GLContext break ()Lorg/lwjgl/opengl/kb;
L3:     getfield Field org/lwjgl/opengl/kb UM J
L6:     dup2
L7:     lstore_3
L8:     invokestatic Method org/lwjgl/l break (J)V
L11:    iload_0
L12:    aload_2
L13:    iconst_4
L14:    iconst_1
L15:    dup
L16:    pop2
L17:    invokestatic Method org/lwjgl/l break (Ljava/nio/IntBuffer;I)V
L20:    iload_1
L21:    aload_2
L22:    invokestatic Method org/lwjgl/MemoryUtil break (Ljava/nio/IntBuffer;)J
L25:    lload_3
L26:    invokestatic Method org/lwjgl/opengl/GL30 nglTexParameterIuiv (IIJJ)V
L29:    return
L30:    
    .end code
.end method

.method static native nglGenerateMipmap : (IJ)V
.end method

.method static native nglEndConditionalRender : (J)V
.end method

.method static native nglVertexAttribI4i : (IIIIIJ)V
.end method

.method static native nglGetTexParameterIiv : (IIJJ)V
.end method

.method static native nglVertexAttribI4ui : (IIIIIJ)V
.end method

.method static native nglVertexAttribIPointerBO : (IIIIJJ)V
.end method

.method public static this : (ILjava/nio/IntBuffer;)V
    .code stack 6 locals 4
L0:     invokestatic Method org/lwjgl/opengl/GLContext break ()Lorg/lwjgl/opengl/kb;
L3:     getfield Field org/lwjgl/opengl/kb pj J
L6:     dup2
L7:     lstore_2
L8:     invokestatic Method org/lwjgl/l break (J)V
L11:    iload_0
L12:    aload_1
L13:    invokestatic Method org/lwjgl/l else (Ljava/nio/IntBuffer;)V
L16:    aload_1
L17:    invokevirtual Method java/nio/IntBuffer remaining ()I
L20:    iconst_3
L21:    iconst_1
L22:    dup
L23:    pop2
L24:    idiv
L25:    aload_1
L26:    invokestatic Method org/lwjgl/MemoryUtil break (Ljava/nio/IntBuffer;)J
L29:    lload_2
L30:    invokestatic Method org/lwjgl/opengl/GL30 nglUniform3uiv (IIJJ)V
L33:    return
L34:    
    .end code
.end method

.method static native nglClearBufferfv : (IIJJ)V
.end method

.method static native nglClampColor : (IIJ)V
.end method

.method static native nglGenVertexArrays : (IJJ)V
.end method

.method public static if : (II)I
    .code stack 6 locals 5
L0:     invokestatic Method org/lwjgl/opengl/GLContext break ()Lorg/lwjgl/opengl/kb;
L3:     dup
L4:     getfield Field org/lwjgl/opengl/kb rp J
L7:     dup2
L8:     lstore_3
L9:     invokestatic Method org/lwjgl/l break (J)V
L12:    invokestatic Method org/lwjgl/opengl/bB short (Lorg/lwjgl/opengl/kb;)Ljava/nio/IntBuffer;
L15:    astore_2
L16:    iload_0
L17:    iload_1
L18:    aload_2
L19:    invokestatic Method org/lwjgl/MemoryUtil break (Ljava/nio/IntBuffer;)J
L22:    lload_3
L23:    invokestatic Method org/lwjgl/opengl/GL30 nglGetIntegeri_v (IIJJ)V
L26:    aload_2
L27:    iconst_0
L28:    iconst_1
L29:    dup
L30:    pop2
L31:    invokevirtual Method java/nio/IntBuffer get (I)I
L34:    ireturn
L35:    
    .end code
.end method

.method static native nglGetIntegeri_v : (IIJJ)V
.end method

.method public static else : (ILjava/nio/ShortBuffer;)V
    .code stack 5 locals 4
L0:     invokestatic Method org/lwjgl/opengl/GLContext break ()Lorg/lwjgl/opengl/kb;
L3:     getfield Field org/lwjgl/opengl/kb yj J
L6:     dup2
L7:     lstore_2
L8:     invokestatic Method org/lwjgl/l break (J)V
L11:    iload_0
L12:    aload_1
L13:    iconst_4
L14:    iconst_1
L15:    dup
L16:    pop2
L17:    invokestatic Method org/lwjgl/l break (Ljava/nio/ShortBuffer;I)V
L20:    aload_1
L21:    invokestatic Method org/lwjgl/MemoryUtil else (Ljava/nio/ShortBuffer;)J
L24:    lload_2
L25:    invokestatic Method org/lwjgl/opengl/GL30 nglVertexAttribI4usv (IJJ)V
L28:    return
L29:    
    .end code
.end method

.method static native nglGetFragDataLocation : (IJJ)I
.end method

.method public static float : ()V
    .code stack 4 locals 2
L0:     invokestatic Method org/lwjgl/opengl/GLContext break ()Lorg/lwjgl/opengl/kb;
L3:     getfield Field org/lwjgl/opengl/kb tu J
L6:     dup2
L7:     lstore_0
L8:     invokestatic Method org/lwjgl/l break (J)V
L11:    lload_0
L12:    invokestatic Method org/lwjgl/opengl/GL30 nglEndConditionalRender (J)V
L15:    return
L16:    
    .end code
.end method

.method public static goto : (ILjava/nio/IntBuffer;)V
    .code stack 5 locals 4
L0:     invokestatic Method org/lwjgl/opengl/GLContext break ()Lorg/lwjgl/opengl/kb;
L3:     getfield Field org/lwjgl/opengl/kb JQ J
L6:     dup2
L7:     lstore_2
L8:     invokestatic Method org/lwjgl/l break (J)V
L11:    iload_0
L12:    aload_1
L13:    iconst_2
L14:    iconst_1
L15:    dup
L16:    pop2
L17:    invokestatic Method org/lwjgl/l break (Ljava/nio/IntBuffer;I)V
L20:    aload_1
L21:    invokestatic Method org/lwjgl/MemoryUtil break (Ljava/nio/IntBuffer;)J
L24:    lload_2
L25:    invokestatic Method org/lwjgl/opengl/GL30 nglVertexAttribI2uiv (IJJ)V
L28:    return
L29:    
    .end code
.end method

.method public static this : (I)Z
    .code stack 4 locals 3
L0:     invokestatic Method org/lwjgl/opengl/GLContext break ()Lorg/lwjgl/opengl/kb;
L3:     getfield Field org/lwjgl/opengl/kb Lo J
L6:     dup2
L7:     lstore_1
L8:     invokestatic Method org/lwjgl/l break (J)V
L11:    iload_0
L12:    lload_1
L13:    invokestatic Method org/lwjgl/opengl/GL30 nglIsRenderbuffer (IJ)Z
L16:    ireturn
L17:    
    .end code
.end method

.method static native nglVertexAttribI4usv : (IJJ)V
.end method

.method private <init> : ()V
    .code stack 1 locals 1
L0:     aload_0
L1:     invokespecial Method java/lang/Object <init> ()V
L4:     return
L5:     
    .end code
.end method

.method static native nglBeginConditionalRender : (IIJ)V
.end method

.method static native nglCheckFramebufferStatus : (IJ)I
.end method

.method static native nglRenderbufferStorage : (IIIIJ)V
.end method

.method static native nglFramebufferRenderbuffer : (IIIIJ)V
.end method

.method public static goto : (I)Z
    .code stack 4 locals 3
L0:     invokestatic Method org/lwjgl/opengl/GLContext break ()Lorg/lwjgl/opengl/kb;
L3:     getfield Field org/lwjgl/opengl/kb QO J
L6:     dup2
L7:     lstore_1
L8:     invokestatic Method org/lwjgl/l break (J)V
L11:    iload_0
L12:    lload_1
L13:    invokestatic Method org/lwjgl/opengl/GL30 nglIsVertexArray (IJ)Z
L16:    ireturn
L17:    
    .end code
.end method

.method public static float : (IIII)V
    .code stack 6 locals 6
L0:     invokestatic Method org/lwjgl/opengl/GLContext break ()Lorg/lwjgl/opengl/kb;
L3:     getfield Field org/lwjgl/opengl/kb aD J
L6:     dup2
L7:     lstore 4
L9:     invokestatic Method org/lwjgl/l break (J)V
L12:    iload_0
L13:    iload_1
L14:    iload_2
L15:    iload_3
L16:    lload 4
L18:    invokestatic Method org/lwjgl/opengl/GL30 nglUniform3ui (IIIIJ)V
L21:    return
L22:    
    .end code
.end method

.method public static break : (IILjava/nio/FloatBuffer;)V
    .code stack 6 locals 5
L0:     invokestatic Method org/lwjgl/opengl/GLContext break ()Lorg/lwjgl/opengl/kb;
L3:     getfield Field org/lwjgl/opengl/kb gS J
L6:     dup2
L7:     lstore_3
L8:     invokestatic Method org/lwjgl/l break (J)V
L11:    iload_0
L12:    aload_2
L13:    iconst_4
L14:    iconst_1
L15:    dup
L16:    pop2
L17:    invokestatic Method org/lwjgl/l break (Ljava/nio/FloatBuffer;I)V
L20:    iload_1
L21:    aload_2
L22:    invokestatic Method org/lwjgl/MemoryUtil break (Ljava/nio/FloatBuffer;)J
L25:    lload_3
L26:    invokestatic Method org/lwjgl/opengl/GL30 nglClearBufferfv (IIJJ)V
L29:    return
L30:    
    .end code
.end method

.method public static do : (I)I
    .code stack 4 locals 3
L0:     invokestatic Method org/lwjgl/opengl/GLContext break ()Lorg/lwjgl/opengl/kb;
L3:     getfield Field org/lwjgl/opengl/kb XR J
L6:     dup2
L7:     lstore_1
L8:     invokestatic Method org/lwjgl/l break (J)V
L11:    iload_0
L12:    lload_1
L13:    invokestatic Method org/lwjgl/opengl/GL30 nglCheckFramebufferStatus (IJ)I
L16:    ireturn
L17:    
    .end code
.end method

.method static native nglFramebufferTexture2D : (IIIIIJ)V
.end method

.method public static do : (ILjava/nio/IntBuffer;)V
    .code stack 5 locals 4
L0:     invokestatic Method org/lwjgl/opengl/GLContext break ()Lorg/lwjgl/opengl/kb;
L3:     getfield Field org/lwjgl/opengl/kb Sp J
L6:     dup2
L7:     lstore_2
L8:     invokestatic Method org/lwjgl/l break (J)V
L11:    iload_0
L12:    aload_1
L13:    iconst_1
L14:    dup
L15:    dup
L16:    pop2
L17:    invokestatic Method org/lwjgl/l break (Ljava/nio/IntBuffer;I)V
L20:    aload_1
L21:    invokestatic Method org/lwjgl/MemoryUtil break (Ljava/nio/IntBuffer;)J
L24:    lload_2
L25:    invokestatic Method org/lwjgl/opengl/GL30 nglVertexAttribI1uiv (IJJ)V
L28:    return
L29:    
    .end code
.end method

.method public static else : (IILjava/nio/ByteBuffer;)V
    .code stack 6 locals 5
L0:     invokestatic Method org/lwjgl/opengl/GLContext break ()Lorg/lwjgl/opengl/kb;
L3:     getfield Field org/lwjgl/opengl/kb uJ J
L6:     dup2
L7:     lstore_3
L8:     invokestatic Method org/lwjgl/l break (J)V
L11:    iload_0
L12:    aload_2
L13:    iconst_4
L14:    iconst_1
L15:    dup
L16:    pop2
L17:    invokestatic Method org/lwjgl/l break (Ljava/nio/ByteBuffer;I)V
L20:    iload_1
L21:    aload_2
L22:    invokestatic Method org/lwjgl/MemoryUtil const (Ljava/nio/ByteBuffer;)J
L25:    lload_3
L26:    invokestatic Method org/lwjgl/opengl/GL30 nglGetBooleani_v (IIJJ)V
L29:    return
L30:    
    .end code
.end method

.method static native nglVertexAttribI4ubv : (IJJ)V
.end method

.method public static for : (I)V
    .code stack 5 locals 4
L0:     invokestatic Method org/lwjgl/opengl/GLContext break ()Lorg/lwjgl/opengl/kb;
L3:     dup
L4:     astore_1
L5:     dup
L6:     getfield Field org/lwjgl/opengl/kb lM J
L9:     dup2
L10:    lstore_2
L11:    invokestatic Method org/lwjgl/l break (J)V
L14:    iload_0
L15:    invokestatic Method org/lwjgl/opengl/w else (Lorg/lwjgl/opengl/kb;I)V
L18:    iconst_1
L19:    dup
L20:    dup
L21:    pop2
L22:    aload_1
L23:    iload_0
L24:    invokestatic Method org/lwjgl/opengl/bB const (Lorg/lwjgl/opengl/kb;I)J
L27:    lload_2
L28:    invokestatic Method org/lwjgl/opengl/GL30 nglDeleteVertexArrays (IJJ)V
L31:    return
L32:    
    .end code
.end method

.method static native nglDisablei : (IIJ)V
.end method

.method public static char : (II)V
    .code stack 4 locals 4
L0:     invokestatic Method org/lwjgl/opengl/GLContext break ()Lorg/lwjgl/opengl/kb;
L3:     getfield Field org/lwjgl/opengl/kb YD J
L6:     dup2
L7:     lstore_2
L8:     invokestatic Method org/lwjgl/l break (J)V
L11:    iload_0
L12:    iload_1
L13:    lload_2
L14:    invokestatic Method org/lwjgl/opengl/GL30 nglUniform1ui (IIJ)V
L17:    return
L18:    
    .end code
.end method

.method static native nglGetUniformuiv : (IIJJ)V
.end method

.method public static catch : (IILjava/nio/IntBuffer;)V
    .code stack 6 locals 5
L0:     invokestatic Method org/lwjgl/opengl/GLContext break ()Lorg/lwjgl/opengl/kb;
L3:     getfield Field org/lwjgl/opengl/kb NR J
L6:     dup2
L7:     lstore_3
L8:     invokestatic Method org/lwjgl/l break (J)V
L11:    iload_0
L12:    aload_2
L13:    iconst_4
L14:    iconst_1
L15:    dup
L16:    pop2
L17:    invokestatic Method org/lwjgl/l break (Ljava/nio/IntBuffer;I)V
L20:    iload_1
L21:    aload_2
L22:    invokestatic Method org/lwjgl/MemoryUtil break (Ljava/nio/IntBuffer;)J
L25:    lload_3
L26:    invokestatic Method org/lwjgl/opengl/GL30 nglGetTexParameterIuiv (IIJJ)V
L29:    return
L30:    
    .end code
.end method

.method static native nglVertexAttribI2uiv : (IJJ)V
.end method

.method static native nglClearBufferuiv : (IIJJ)V
.end method

.method static native nglUniform1uiv : (IIJJ)V
.end method

.method public static break : (IIFI)V
    .code stack 6 locals 6
L0:     invokestatic Method org/lwjgl/opengl/GLContext break ()Lorg/lwjgl/opengl/kb;
L3:     getfield Field org/lwjgl/opengl/kb JE J
L6:     dup2
L7:     lstore 4
L9:     invokestatic Method org/lwjgl/l break (J)V
L12:    iload_0
L13:    iload_1
L14:    fload_2
L15:    iload_3
L16:    lload 4
L18:    invokestatic Method org/lwjgl/opengl/GL30 nglClearBufferfi (IIFIJ)V
L21:    return
L22:    
    .end code
.end method

.method static native nglUniform3ui : (IIIIJ)V
.end method

.method public static float : (IIIII)V
    .code stack 7 locals 7
L0:     invokestatic Method org/lwjgl/opengl/GLContext break ()Lorg/lwjgl/opengl/kb;
L3:     getfield Field org/lwjgl/opengl/kb iP J
L6:     dup2
L7:     lstore 5
L9:     invokestatic Method org/lwjgl/l break (J)V
L12:    iload_0
L13:    iload_1
L14:    iload_2
L15:    iload_3
L16:    iload 4
L18:    lload 5
L20:    invokestatic Method org/lwjgl/opengl/GL30 nglRenderbufferStorageMultisample (IIIIIJ)V
L23:    return
L24:    
    .end code
.end method

.method public static catch : (III)V
    .code stack 6 locals 6
L0:     invokestatic Method org/lwjgl/opengl/GLContext break ()Lorg/lwjgl/opengl/kb;
L3:     dup
L4:     astore_3
L5:     getfield Field org/lwjgl/opengl/kb UM J
L8:     dup2
L9:     lstore 4
L11:    invokestatic Method org/lwjgl/l break (J)V
L14:    iload_0
L15:    iload_1
L16:    aload_3
L17:    iload_2
L18:    invokestatic Method org/lwjgl/opengl/bB const (Lorg/lwjgl/opengl/kb;I)J
L21:    lload 4
L23:    invokestatic Method org/lwjgl/opengl/GL30 nglTexParameterIuiv (IIJJ)V
L26:    return
L27:    
    .end code
.end method

.method static native nglGetTransformFeedbackVarying : (IIIJJJJJ)V
.end method

.method public static break : (IIIJJ)V
    .code stack 9 locals 9
L0:     invokestatic Method org/lwjgl/opengl/GLContext break ()Lorg/lwjgl/opengl/kb;
L3:     getfield Field org/lwjgl/opengl/kb Rd J
L6:     dup2
L7:     lstore 7
L9:     invokestatic Method org/lwjgl/l break (J)V
L12:    iload_0
L13:    iload_1
L14:    iload_2
L15:    lload_3
L16:    lload 5
L18:    lload 7
L20:    invokestatic Method org/lwjgl/opengl/GL30 nglBindBufferRange (IIIJJJ)V
L23:    return
L24:    
    .end code
.end method

.method public static float : (IILjava/nio/IntBuffer;)V
    .code stack 6 locals 5
L0:     invokestatic Method org/lwjgl/opengl/GLContext break ()Lorg/lwjgl/opengl/kb;
L3:     getfield Field org/lwjgl/opengl/kb Af J
L6:     dup2
L7:     lstore_3
L8:     invokestatic Method org/lwjgl/l break (J)V
L11:    iload_0
L12:    aload_2
L13:    iconst_4
L14:    iconst_1
L15:    dup
L16:    pop2
L17:    invokestatic Method org/lwjgl/l break (Ljava/nio/IntBuffer;I)V
L20:    iload_1
L21:    aload_2
L22:    invokestatic Method org/lwjgl/MemoryUtil break (Ljava/nio/IntBuffer;)J
L25:    lload_3
L26:    invokestatic Method org/lwjgl/opengl/GL30 nglGetRenderbufferParameteriv (IIJJ)V
L29:    return
L30:    
    .end code
.end method

.method public static break : (IIIIII)V
    .code stack 8 locals 8
L0:     invokestatic Method org/lwjgl/opengl/GLContext break ()Lorg/lwjgl/opengl/kb;
L3:     getfield Field org/lwjgl/opengl/kb N J
L6:     dup2
L7:     lstore 6
L9:     invokestatic Method org/lwjgl/l break (J)V
L12:    iload_0
L13:    iload_1
L14:    iload_2
L15:    iload_3
L16:    iload 4
L18:    iload 5
L20:    lload 6
L22:    invokestatic Method org/lwjgl/opengl/GL30 nglFramebufferTexture3D (IIIIIIJ)V
L25:    return
L26:    
    .end code
.end method

.method public static break : (IIIILjava/nio/IntBuffer;)V
    .code stack 8 locals 8
L0:     invokestatic Method org/lwjgl/opengl/GLContext break ()Lorg/lwjgl/opengl/kb;
L3:     astore 5
L5:     aload 4
L7:     aload 5
L9:     dup
L10:    getfield Field org/lwjgl/opengl/kb fs J
L13:    dup2
L14:    lstore 6
L16:    invokestatic Method org/lwjgl/l break (J)V
L19:    invokestatic Method org/lwjgl/opengl/Zd break (Lorg/lwjgl/opengl/kb;)V
L22:    invokestatic Method org/lwjgl/l else (Ljava/nio/IntBuffer;)V
L25:    getstatic Field org/lwjgl/LWJGLUtil CHECKS Z
L28:    ifeq L43
L31:    aload 5
L33:    invokestatic Method org/lwjgl/opengl/w const (Lorg/lwjgl/opengl/kb;)Lorg/lwjgl/opengl/P;
L36:    getfield Field org/lwjgl/opengl/P do [Ljava/nio/Buffer;
L39:    iload_0
L40:    aload 4
L42:    aastore
L43:    iload_0
L44:    iload_1
L45:    iload_2
L46:    iload_3
L47:    aload 4
L49:    invokestatic Method org/lwjgl/MemoryUtil break (Ljava/nio/IntBuffer;)J
L52:    lload 6
L54:    invokestatic Method org/lwjgl/opengl/GL30 nglVertexAttribIPointer (IIIIJJ)V
L57:    return
L58:    
        .attribute StackMap b'\x00\x01\x00\x2B\x00\x07\x01\x01\x01\x01\x07\x02\x52\x07\x01\xE7\x04\x00\x00'
    .end code
.end method

.method public static catch : (I)V
    .code stack 5 locals 4
L0:     invokestatic Method org/lwjgl/opengl/GLContext break ()Lorg/lwjgl/opengl/kb;
L3:     dup
L4:     astore_1
L5:     getfield Field org/lwjgl/opengl/kb Se J
L8:     dup2
L9:     lstore_2
L10:    invokestatic Method org/lwjgl/l break (J)V
L13:    iconst_1
L14:    dup
L15:    dup
L16:    pop2
L17:    aload_1
L18:    iload_0
L19:    invokestatic Method org/lwjgl/opengl/bB const (Lorg/lwjgl/opengl/kb;I)J
L22:    lload_2
L23:    invokestatic Method org/lwjgl/opengl/GL30 nglDeleteRenderbuffers (IJJ)V
L26:    return
L27:    
    .end code
.end method

.method static native nglClearBufferiv : (IIJJ)V
.end method

.method static native nglFramebufferTexture3D : (IIIIIIJ)V
.end method

.method static native nglUniform2uiv : (IIJJ)V
.end method

.method public static float : (III)V
    .code stack 5 locals 5
L0:     invokestatic Method org/lwjgl/opengl/GLContext break ()Lorg/lwjgl/opengl/kb;
L3:     getfield Field org/lwjgl/opengl/kb QP J
L6:     dup2
L7:     lstore_3
L8:     invokestatic Method org/lwjgl/l break (J)V
L11:    iload_0
L12:    iload_1
L13:    iload_2
L14:    lload_3
L15:    invokestatic Method org/lwjgl/opengl/GL30 nglVertexAttribI2ui (IIIJ)V
L18:    return
L19:    
    .end code
.end method

.method public static for : (ILjava/nio/IntBuffer;)V
    .code stack 6 locals 4
L0:     invokestatic Method org/lwjgl/opengl/GLContext break ()Lorg/lwjgl/opengl/kb;
L3:     getfield Field org/lwjgl/opengl/kb Fe J
L6:     dup2
L7:     lstore_2
L8:     invokestatic Method org/lwjgl/l break (J)V
L11:    iload_0
L12:    aload_1
L13:    invokestatic Method org/lwjgl/l else (Ljava/nio/IntBuffer;)V
L16:    aload_1
L17:    invokevirtual Method java/nio/IntBuffer remaining ()I
L20:    iconst_2
L21:    iconst_1
L22:    dup
L23:    pop2
L24:    ishr
L25:    aload_1
L26:    invokestatic Method org/lwjgl/MemoryUtil break (Ljava/nio/IntBuffer;)J
L29:    lload_2
L30:    invokestatic Method org/lwjgl/opengl/GL30 nglUniform4uiv (IIJJ)V
L33:    return
L34:    
    .end code
.end method

.method static native nglVertexAttribI4bv : (IJJ)V
.end method

.method public static short : (IILjava/nio/IntBuffer;)V
    .code stack 6 locals 5
L0:     invokestatic Method org/lwjgl/opengl/GLContext break ()Lorg/lwjgl/opengl/kb;
L3:     getfield Field org/lwjgl/opengl/kb "strictfp" J
L6:     dup2
L7:     lstore_3
L8:     invokestatic Method org/lwjgl/l break (J)V
L11:    iload_0
L12:    aload_2
L13:    iconst_4
L14:    iconst_1
L15:    dup
L16:    pop2
L17:    invokestatic Method org/lwjgl/l break (Ljava/nio/IntBuffer;I)V
L20:    iload_1
L21:    aload_2
L22:    invokestatic Method org/lwjgl/MemoryUtil break (Ljava/nio/IntBuffer;)J
L25:    lload_3
L26:    invokestatic Method org/lwjgl/opengl/GL30 nglGetTexParameterIiv (IIJJ)V
L29:    return
L30:    
    .end code
.end method

.method public static break : (IILjava/nio/ByteBuffer;)V
    .code stack 6 locals 5
L0:     invokestatic Method org/lwjgl/opengl/GLContext break ()Lorg/lwjgl/opengl/kb;
L3:     getfield Field org/lwjgl/opengl/kb AQ J
L6:     dup2
L7:     lstore_3
L8:     invokestatic Method org/lwjgl/l break (J)V
L11:    iload_0
L12:    aload_2
L13:    dup
L14:    invokestatic Method org/lwjgl/l break (Ljava/nio/ByteBuffer;)V
L17:    invokestatic Method org/lwjgl/l else (Ljava/nio/ByteBuffer;)V
L20:    iload_1
L21:    aload_2
L22:    invokestatic Method org/lwjgl/MemoryUtil const (Ljava/nio/ByteBuffer;)J
L25:    lload_3
L26:    invokestatic Method org/lwjgl/opengl/GL30 nglBindFragDataLocation (IIJJ)V
L29:    return
L30:    
    .end code
.end method

.method public static const : (ILjava/nio/ByteBuffer;)I
    .code stack 5 locals 4
L0:     invokestatic Method org/lwjgl/opengl/GLContext break ()Lorg/lwjgl/opengl/kb;
L3:     getfield Field org/lwjgl/opengl/kb kp J
L6:     dup2
L7:     lstore_2
L8:     invokestatic Method org/lwjgl/l break (J)V
L11:    iload_0
L12:    aload_1
L13:    dup
L14:    invokestatic Method org/lwjgl/l break (Ljava/nio/ByteBuffer;)V
L17:    invokestatic Method org/lwjgl/l else (Ljava/nio/ByteBuffer;)V
L20:    aload_1
L21:    invokestatic Method org/lwjgl/MemoryUtil const (Ljava/nio/ByteBuffer;)J
L24:    lload_2
L25:    invokestatic Method org/lwjgl/opengl/GL30 nglGetFragDataLocation (IJJ)I
L28:    ireturn
L29:    
    .end code
.end method

.method public static short : ()I
    .code stack 5 locals 3
L0:     invokestatic Method org/lwjgl/opengl/GLContext break ()Lorg/lwjgl/opengl/kb;
L3:     dup
L4:     getfield Field org/lwjgl/opengl/kb cI J
L7:     dup2
L8:     lstore_0
L9:     invokestatic Method org/lwjgl/l break (J)V
L12:    invokestatic Method org/lwjgl/opengl/bB short (Lorg/lwjgl/opengl/kb;)Ljava/nio/IntBuffer;
L15:    astore_2
L16:    iconst_1
L17:    dup
L18:    dup
L19:    pop2
L20:    aload_2
L21:    invokestatic Method org/lwjgl/MemoryUtil break (Ljava/nio/IntBuffer;)J
L24:    lload_0
L25:    invokestatic Method org/lwjgl/opengl/GL30 nglGenFramebuffers (IJJ)V
L28:    aload_2
L29:    iconst_0
L30:    iconst_1
L31:    dup
L32:    pop2
L33:    invokevirtual Method java/nio/IntBuffer get (I)I
L36:    ireturn
L37:    
    .end code
.end method

.method public static catch : (ILjava/nio/IntBuffer;)V
    .code stack 6 locals 4
L0:     invokestatic Method org/lwjgl/opengl/GLContext break ()Lorg/lwjgl/opengl/kb;
L3:     getfield Field org/lwjgl/opengl/kb RI J
L6:     dup2
L7:     lstore_2
L8:     invokestatic Method org/lwjgl/l break (J)V
L11:    iload_0
L12:    aload_1
L13:    invokestatic Method org/lwjgl/l else (Ljava/nio/IntBuffer;)V
L16:    aload_1
L17:    invokevirtual Method java/nio/IntBuffer remaining ()I
L20:    aload_1
L21:    invokestatic Method org/lwjgl/MemoryUtil break (Ljava/nio/IntBuffer;)J
L24:    lload_2
L25:    invokestatic Method org/lwjgl/opengl/GL30 nglUniform1uiv (IIJJ)V
L28:    return
L29:    
    .end code
.end method

.method static native nglVertexAttribI3i : (IIIIJ)V
.end method

.method public static break : (I[Ljava/lang/CharSequence;I)V
    .code stack 7 locals 6
L0:     invokestatic Method org/lwjgl/opengl/GLContext break ()Lorg/lwjgl/opengl/kb;
L3:     astore_3
L4:     aload_1
L5:     aload_3
L6:     getfield Field org/lwjgl/opengl/kb NC J
L9:     dup2
L10:    lstore 4
L12:    invokestatic Method org/lwjgl/l break (J)V
L15:    invokestatic Method org/lwjgl/l break ([Ljava/lang/Object;)V
L18:    iload_0
L19:    aload_1
L20:    arraylength
L21:    aload_3
L22:    aload_1
L23:    invokestatic Method org/lwjgl/opengl/bB const (Lorg/lwjgl/opengl/kb;[Ljava/lang/CharSequence;)J
L26:    iload_2
L27:    lload 4
L29:    invokestatic Method org/lwjgl/opengl/GL30 nglTransformFeedbackVaryings (IIJIJ)V
L32:    return
L33:    
    .end code
.end method

.method static native nglVertexAttribI2iv : (IJJ)V
.end method

.method public static short : (IIII)V
    .code stack 6 locals 6
L0:     invokestatic Method org/lwjgl/opengl/GLContext break ()Lorg/lwjgl/opengl/kb;
L3:     getfield Field org/lwjgl/opengl/kb QM J
L6:     dup2
L7:     lstore 4
L9:     invokestatic Method org/lwjgl/l break (J)V
L12:    iload_0
L13:    iload_1
L14:    iload_2
L15:    iload_3
L16:    lload 4
L18:    invokestatic Method org/lwjgl/opengl/GL30 nglRenderbufferStorage (IIIIJ)V
L21:    return
L22:    
    .end code
.end method

.method public static catch : (Ljava/nio/IntBuffer;)V
    .code stack 5 locals 3
L0:     invokestatic Method org/lwjgl/opengl/GLContext break ()Lorg/lwjgl/opengl/kb;
L3:     getfield Field org/lwjgl/opengl/kb Se J
L6:     dup2
L7:     lstore_1
L8:     invokestatic Method org/lwjgl/l break (J)V
L11:    aload_0
L12:    dup
L13:    invokestatic Method org/lwjgl/l else (Ljava/nio/IntBuffer;)V
L16:    invokevirtual Method java/nio/IntBuffer remaining ()I
L19:    aload_0
L20:    invokestatic Method org/lwjgl/MemoryUtil break (Ljava/nio/IntBuffer;)J
L23:    lload_1
L24:    invokestatic Method org/lwjgl/opengl/GL30 nglDeleteRenderbuffers (IJJ)V
L27:    return
L28:    
    .end code
.end method

.method static native nglTransformFeedbackVaryings : (IIJIJ)V
.end method

.method static native nglUniform3uiv : (IIJJ)V
.end method

.method public static new : (II)Z
    .code stack 4 locals 4
L0:     invokestatic Method org/lwjgl/opengl/GLContext break ()Lorg/lwjgl/opengl/kb;
L3:     getfield Field org/lwjgl/opengl/kb yF J
L6:     dup2
L7:     lstore_2
L8:     invokestatic Method org/lwjgl/l break (J)V
L11:    iload_0
L12:    iload_1
L13:    lload_2
L14:    invokestatic Method org/lwjgl/opengl/GL30 nglIsEnabledi (IIJ)Z
L17:    ireturn
L18:    
    .end code
.end method

.method static native nglVertexAttribI4iv : (IJJ)V
.end method

.method public static const : ()I
    .code stack 5 locals 3
L0:     invokestatic Method org/lwjgl/opengl/GLContext break ()Lorg/lwjgl/opengl/kb;
L3:     dup
L4:     getfield Field org/lwjgl/opengl/kb Jb J
L7:     dup2
L8:     lstore_0
L9:     invokestatic Method org/lwjgl/l break (J)V
L12:    invokestatic Method org/lwjgl/opengl/bB short (Lorg/lwjgl/opengl/kb;)Ljava/nio/IntBuffer;
L15:    astore_2
L16:    iconst_1
L17:    dup
L18:    dup
L19:    pop2
L20:    aload_2
L21:    invokestatic Method org/lwjgl/MemoryUtil break (Ljava/nio/IntBuffer;)J
L24:    lload_0
L25:    invokestatic Method org/lwjgl/opengl/GL30 nglGenVertexArrays (IJJ)V
L28:    aload_2
L29:    iconst_0
L30:    iconst_1
L31:    dup
L32:    pop2
L33:    invokevirtual Method java/nio/IntBuffer get (I)I
L36:    ireturn
L37:    
    .end code
.end method

.method public static short : (III)I
    .code stack 7 locals 6
L0:     invokestatic Method org/lwjgl/opengl/GLContext break ()Lorg/lwjgl/opengl/kb;
L3:     dup
L4:     getfield Field org/lwjgl/opengl/kb kr J
L7:     dup2
L8:     lstore 4
L10:    invokestatic Method org/lwjgl/l break (J)V
L13:    invokestatic Method org/lwjgl/opengl/bB short (Lorg/lwjgl/opengl/kb;)Ljava/nio/IntBuffer;
L16:    astore_3
L17:    iload_0
L18:    iload_1
L19:    iload_2
L20:    aload_3
L21:    invokestatic Method org/lwjgl/MemoryUtil break (Ljava/nio/IntBuffer;)J
L24:    lload 4
L26:    invokestatic Method org/lwjgl/opengl/GL30 nglGetFramebufferAttachmentParameteriv (IIIJJ)V
L29:    aload_3
L30:    iconst_0
L31:    iconst_1
L32:    dup
L33:    pop2
L34:    invokevirtual Method java/nio/IntBuffer get (I)I
L37:    ireturn
L38:    
    .end code
.end method

.method public static else : (ILjava/nio/ByteBuffer;)V
    .code stack 5 locals 4
L0:     invokestatic Method org/lwjgl/opengl/GLContext break ()Lorg/lwjgl/opengl/kb;
L3:     getfield Field org/lwjgl/opengl/kb Jl J
L6:     dup2
L7:     lstore_2
L8:     invokestatic Method org/lwjgl/l break (J)V
L11:    iload_0
L12:    aload_1
L13:    iconst_4
L14:    iconst_1
L15:    dup
L16:    pop2
L17:    invokestatic Method org/lwjgl/l break (Ljava/nio/ByteBuffer;I)V
L20:    aload_1
L21:    invokestatic Method org/lwjgl/MemoryUtil const (Ljava/nio/ByteBuffer;)J
L24:    lload_2
L25:    invokestatic Method org/lwjgl/opengl/GL30 nglVertexAttribI4bv (IJJ)V
L28:    return
L29:    
    .end code
.end method

.method static native nglEnablei : (IIJ)V
.end method

.method static native nglDeleteRenderbuffers : (IJJ)V
.end method

.method static native nglGetTexParameterIuiv : (IIJJ)V
.end method

.method public static const : (III)V
    .code stack 5 locals 5
L0:     invokestatic Method org/lwjgl/opengl/GLContext break ()Lorg/lwjgl/opengl/kb;
L3:     getfield Field org/lwjgl/opengl/kb ue J
L6:     dup2
L7:     lstore_3
L8:     invokestatic Method org/lwjgl/l break (J)V
L11:    iload_0
L12:    iload_1
L13:    iload_2
L14:    lload_3
L15:    invokestatic Method org/lwjgl/opengl/GL30 nglBindBufferBase (IIIJ)V
L18:    return
L19:    
    .end code
.end method

.method static native nglFlushMappedBufferRange : (IJJJ)V
.end method

.method public static try : (II)V
    .code stack 4 locals 4
L0:     invokestatic Method org/lwjgl/opengl/GLContext break ()Lorg/lwjgl/opengl/kb;
L3:     getfield Field org/lwjgl/opengl/kb Sm J
L6:     dup2
L7:     lstore_2
L8:     invokestatic Method org/lwjgl/l break (J)V
L11:    iload_0
L12:    iload_1
L13:    lload_2
L14:    invokestatic Method org/lwjgl/opengl/GL30 nglBeginConditionalRender (IIJ)V
L17:    return
L18:    
    .end code
.end method

.method public static const : (IIII)V
    .code stack 6 locals 6
L0:     invokestatic Method org/lwjgl/opengl/GLContext break ()Lorg/lwjgl/opengl/kb;
L3:     getfield Field org/lwjgl/opengl/kb EQ J
L6:     dup2
L7:     lstore 4
L9:     invokestatic Method org/lwjgl/l break (J)V
L12:    iload_0
L13:    iload_1
L14:    iload_2
L15:    iload_3
L16:    lload 4
L18:    invokestatic Method org/lwjgl/opengl/GL30 nglVertexAttribI3ui (IIIIJ)V
L21:    return
L22:    
    .end code
.end method

.method public static float : (Ljava/nio/IntBuffer;)V
    .code stack 5 locals 3
L0:     invokestatic Method org/lwjgl/opengl/GLContext break ()Lorg/lwjgl/opengl/kb;
L3:     getfield Field org/lwjgl/opengl/kb Hl J
L6:     dup2
L7:     lstore_1
L8:     invokestatic Method org/lwjgl/l break (J)V
L11:    aload_0
L12:    dup
L13:    invokestatic Method org/lwjgl/l else (Ljava/nio/IntBuffer;)V
L16:    invokevirtual Method java/nio/IntBuffer remaining ()I
L19:    aload_0
L20:    invokestatic Method org/lwjgl/MemoryUtil break (Ljava/nio/IntBuffer;)J
L23:    lload_1
L24:    invokestatic Method org/lwjgl/opengl/GL30 nglGenRenderbuffers (IJJ)V
L27:    return
L28:    
    .end code
.end method

.method static native nglFramebufferTexture1D : (IIIIIJ)V
.end method

.method static native nglBlitFramebuffer : (IIIIIIIIIIJ)V
.end method

.method public static float : (ILjava/nio/IntBuffer;)V
    .code stack 6 locals 4
L0:     invokestatic Method org/lwjgl/opengl/GLContext break ()Lorg/lwjgl/opengl/kb;
L3:     getfield Field org/lwjgl/opengl/kb Qt J
L6:     dup2
L7:     lstore_2
L8:     invokestatic Method org/lwjgl/l break (J)V
L11:    iload_0
L12:    aload_1
L13:    invokestatic Method org/lwjgl/l else (Ljava/nio/IntBuffer;)V
L16:    aload_1
L17:    invokevirtual Method java/nio/IntBuffer remaining ()I
L20:    iconst_1
L21:    dup
L22:    dup
L23:    pop2
L24:    ishr
L25:    aload_1
L26:    invokestatic Method org/lwjgl/MemoryUtil break (Ljava/nio/IntBuffer;)J
L29:    lload_2
L30:    invokestatic Method org/lwjgl/opengl/GL30 nglUniform2uiv (IIJJ)V
L33:    return
L34:    
    .end code
.end method

.method public static float : (I)V
    .code stack 4 locals 3
L0:     invokestatic Method org/lwjgl/opengl/GLContext break ()Lorg/lwjgl/opengl/kb;
L3:     getfield Field org/lwjgl/opengl/kb Gj J
L6:     dup2
L7:     lstore_1
L8:     invokestatic Method org/lwjgl/l break (J)V
L11:    iload_0
L12:    lload_1
L13:    invokestatic Method org/lwjgl/opengl/GL30 nglBeginTransformFeedback (IJ)V
L16:    return
L17:    
    .end code
.end method

.method public static break : (IZZZZ)V
    .code stack 7 locals 7
L0:     invokestatic Method org/lwjgl/opengl/GLContext break ()Lorg/lwjgl/opengl/kb;
L3:     getfield Field org/lwjgl/opengl/kb Bj J
L6:     dup2
L7:     lstore 5
L9:     invokestatic Method org/lwjgl/l break (J)V
L12:    iload_0
L13:    iload_1
L14:    iload_2
L15:    iload_3
L16:    iload 4
L18:    lload 5
L20:    invokestatic Method org/lwjgl/opengl/GL30 nglColorMaski (IZZZZJ)V
L23:    return
L24:    
    .end code
.end method

.method public static short : (IIIII)V
    .code stack 7 locals 7
L0:     invokestatic Method org/lwjgl/opengl/GLContext break ()Lorg/lwjgl/opengl/kb;
L3:     getfield Field org/lwjgl/opengl/kb bs J
L6:     dup2
L7:     lstore 5
L9:     invokestatic Method org/lwjgl/l break (J)V
L12:    iload_0
L13:    iload_1
L14:    iload_2
L15:    iload_3
L16:    iload 4
L18:    lload 5
L20:    invokestatic Method org/lwjgl/opengl/GL30 nglUniform4ui (IIIIIJ)V
L23:    return
L24:    
    .end code
.end method

.method static native nglBindFragDataLocation : (IIJJ)V
.end method

.method public static this : (II)Ljava/lang/String;
    .code stack 4 locals 4
L0:     invokestatic Method org/lwjgl/opengl/GLContext break ()Lorg/lwjgl/opengl/kb;
L3:     getfield Field org/lwjgl/opengl/kb BR J
L6:     dup2
L7:     lstore_2
L8:     invokestatic Method org/lwjgl/l break (J)V
L11:    iload_0
L12:    iload_1
L13:    lload_2
L14:    invokestatic Method org/lwjgl/opengl/GL30 nglGetStringi (IIJ)Ljava/lang/String;
L17:    areturn
L18:    
    .end code
.end method

.method public static else : ()I
    .code stack 5 locals 3
L0:     invokestatic Method org/lwjgl/opengl/GLContext break ()Lorg/lwjgl/opengl/kb;
L3:     dup
L4:     getfield Field org/lwjgl/opengl/kb Hl J
L7:     dup2
L8:     lstore_0
L9:     invokestatic Method org/lwjgl/l break (J)V
L12:    invokestatic Method org/lwjgl/opengl/bB short (Lorg/lwjgl/opengl/kb;)Ljava/nio/IntBuffer;
L15:    astore_2
L16:    iconst_1
L17:    dup
L18:    dup
L19:    pop2
L20:    aload_2
L21:    invokestatic Method org/lwjgl/MemoryUtil break (Ljava/nio/IntBuffer;)J
L24:    lload_0
L25:    invokestatic Method org/lwjgl/opengl/GL30 nglGenRenderbuffers (IJJ)V
L28:    aload_2
L29:    iconst_0
L30:    iconst_1
L31:    dup
L32:    pop2
L33:    invokevirtual Method java/nio/IntBuffer get (I)I
L36:    ireturn
L37:    
    .end code
.end method

.method static native nglDeleteFramebuffers : (IJJ)V
.end method

.method static native nglIsFramebuffer : (IJ)Z
.end method

.method static native nglDeleteVertexArrays : (IJJ)V
.end method

.method static native nglIsVertexArray : (IJ)Z
.end method

.method static native nglVertexAttribI4uiv : (IJJ)V
.end method

.method public static goto : (II)V
    .code stack 4 locals 4
L0:     invokestatic Method org/lwjgl/opengl/GLContext break ()Lorg/lwjgl/opengl/kb;
L3:     getfield Field org/lwjgl/opengl/kb so J
L6:     dup2
L7:     lstore_2
L8:     invokestatic Method org/lwjgl/l break (J)V
L11:    iload_0
L12:    iload_1
L13:    lload_2
L14:    invokestatic Method org/lwjgl/opengl/GL30 nglVertexAttribI1ui (IIJ)V
L17:    return
L18:    
    .end code
.end method

.method static native nglGenRenderbuffers : (IJJ)V
.end method

.method static native nglVertexAttribI1i : (IIJ)V
.end method

.method public static break : (ILjava/nio/ShortBuffer;)V
    .code stack 5 locals 4
L0:     invokestatic Method org/lwjgl/opengl/GLContext break ()Lorg/lwjgl/opengl/kb;
L3:     getfield Field org/lwjgl/opengl/kb is J
L6:     dup2
L7:     lstore_2
L8:     invokestatic Method org/lwjgl/l break (J)V
L11:    iload_0
L12:    aload_1
L13:    iconst_4
L14:    iconst_1
L15:    dup
L16:    pop2
L17:    invokestatic Method org/lwjgl/l break (Ljava/nio/ShortBuffer;I)V
L20:    aload_1
L21:    invokestatic Method org/lwjgl/MemoryUtil else (Ljava/nio/ShortBuffer;)J
L24:    lload_2
L25:    invokestatic Method org/lwjgl/opengl/GL30 nglVertexAttribI4sv (IJJ)V
L28:    return
L29:    
    .end code
.end method

.method static native nglVertexAttribI1iv : (IJJ)V
.end method

.method public static break : (IILjava/nio/IntBuffer;Ljava/nio/IntBuffer;Ljava/nio/IntBuffer;Ljava/nio/ByteBuffer;)V
    .code stack 13 locals 8
L0:     invokestatic Method org/lwjgl/opengl/GLContext break ()Lorg/lwjgl/opengl/kb;
L3:     getfield Field org/lwjgl/opengl/kb XD J
L6:     dup2
L7:     lstore 6
L9:     invokestatic Method org/lwjgl/l break (J)V
L12:    aload_2
L13:    ifnull L24
L16:    aload_2
L17:    iconst_1
L18:    dup
L19:    dup
L20:    pop2
L21:    invokestatic Method org/lwjgl/l break (Ljava/nio/IntBuffer;I)V
L24:    aload_3
L25:    iconst_1
L26:    dup
L27:    dup
L28:    pop2
L29:    invokestatic Method org/lwjgl/l break (Ljava/nio/IntBuffer;I)V
L32:    iload_0
L33:    aload 5
L35:    aload 4
L37:    iconst_1
L38:    dup
L39:    dup
L40:    pop2
L41:    invokestatic Method org/lwjgl/l break (Ljava/nio/IntBuffer;I)V
L44:    invokestatic Method org/lwjgl/l break (Ljava/nio/ByteBuffer;)V
L47:    iload_1
L48:    aload 5
L50:    invokevirtual Method java/nio/ByteBuffer remaining ()I
L53:    aload_2
L54:    invokestatic Method org/lwjgl/MemoryUtil else (Ljava/nio/IntBuffer;)J
L57:    aload_3
L58:    invokestatic Method org/lwjgl/MemoryUtil break (Ljava/nio/IntBuffer;)J
L61:    aload 4
L63:    invokestatic Method org/lwjgl/MemoryUtil break (Ljava/nio/IntBuffer;)J
L66:    aload 5
L68:    invokestatic Method org/lwjgl/MemoryUtil const (Ljava/nio/ByteBuffer;)J
L71:    lload 6
L73:    invokestatic Method org/lwjgl/opengl/GL30 nglGetTransformFeedbackVarying (IIIJJJJJ)V
L76:    return
L77:    
        .attribute StackMap b'\x00\x01\x00\x18\x00\x07\x01\x01\x07\x02\x52\x07\x02\x52\x07\x02\x52\x07\x02\x7D\x04\x00\x00'
    .end code
.end method

.method public static short : (I)Z
    .code stack 4 locals 3
L0:     invokestatic Method org/lwjgl/opengl/GLContext break ()Lorg/lwjgl/opengl/kb;
L3:     getfield Field org/lwjgl/opengl/kb BD J
L6:     dup2
L7:     lstore_1
L8:     invokestatic Method org/lwjgl/l break (J)V
L11:    iload_0
L12:    lload_1
L13:    invokestatic Method org/lwjgl/opengl/GL30 nglIsFramebuffer (IJ)Z
L16:    ireturn
L17:    
    .end code
.end method

.method public static const : (IILjava/nio/IntBuffer;)V
    .code stack 6 locals 5
L0:     invokestatic Method org/lwjgl/opengl/GLContext break ()Lorg/lwjgl/opengl/kb;
L3:     getfield Field org/lwjgl/opengl/kb bD J
L6:     dup2
L7:     lstore_3
L8:     invokestatic Method org/lwjgl/l break (J)V
L11:    iload_0
L12:    aload_2
L13:    iconst_4
L14:    iconst_1
L15:    dup
L16:    pop2
L17:    invokestatic Method org/lwjgl/l break (Ljava/nio/IntBuffer;I)V
L20:    iload_1
L21:    aload_2
L22:    invokestatic Method org/lwjgl/MemoryUtil break (Ljava/nio/IntBuffer;)J
L25:    lload_3
L26:    invokestatic Method org/lwjgl/opengl/GL30 nglTexParameterIiv (IIJJ)V
L29:    return
L30:    
    .end code
.end method

.method public static short : (ILjava/nio/IntBuffer;)V
    .code stack 5 locals 4
L0:     invokestatic Method org/lwjgl/opengl/GLContext break ()Lorg/lwjgl/opengl/kb;
L3:     getfield Field org/lwjgl/opengl/kb dT J
L6:     dup2
L7:     lstore_2
L8:     invokestatic Method org/lwjgl/l break (J)V
L11:    iload_0
L12:    aload_1
L13:    iconst_4
L14:    iconst_1
L15:    dup
L16:    pop2
L17:    invokestatic Method org/lwjgl/l break (Ljava/nio/IntBuffer;I)V
L20:    aload_1
L21:    invokestatic Method org/lwjgl/MemoryUtil break (Ljava/nio/IntBuffer;)J
L24:    lload_2
L25:    invokestatic Method org/lwjgl/opengl/GL30 nglVertexAttribI4uiv (IJJ)V
L28:    return
L29:    
    .end code
.end method

.method static native nglClearBufferfi : (IIFIJ)V
.end method

.method static native nglFramebufferTextureLayer : (IIIIIJ)V
.end method

.method static native nglVertexAttribI4sv : (IJJ)V
.end method

.method static native nglGenFramebuffers : (IJJ)V
.end method

.method public static else : (IIII)V
    .code stack 6 locals 6
L0:     invokestatic Method org/lwjgl/opengl/GLContext break ()Lorg/lwjgl/opengl/kb;
L3:     getfield Field org/lwjgl/opengl/kb si J
L6:     dup2
L7:     lstore 4
L9:     invokestatic Method org/lwjgl/l break (J)V
L12:    iload_0
L13:    iload_1
L14:    iload_2
L15:    iload_3
L16:    lload 4
L18:    invokestatic Method org/lwjgl/opengl/GL30 nglVertexAttribI3i (IIIIJ)V
L21:    return
L22:    
    .end code
.end method

.method static native nglVertexAttribI2i : (IIIJ)V
.end method

.method static native nglEndTransformFeedback : (J)V
.end method

.method public static const : (IIIII)V
    .code stack 7 locals 7
L0:     invokestatic Method org/lwjgl/opengl/GLContext break ()Lorg/lwjgl/opengl/kb;
L3:     getfield Field org/lwjgl/opengl/kb ED J
L6:     dup2
L7:     lstore 5
L9:     invokestatic Method org/lwjgl/l break (J)V
L12:    iload_0
L13:    iload_1
L14:    iload_2
L15:    iload_3
L16:    iload 4
L18:    lload 5
L20:    invokestatic Method org/lwjgl/opengl/GL30 nglVertexAttribI4i (IIIIIJ)V
L23:    return
L24:    
    .end code
.end method

.method static native nglIsRenderbuffer : (IJ)Z
.end method

.method public static break : (IILjava/lang/CharSequence;)V
    .code stack 6 locals 6
L0:     invokestatic Method org/lwjgl/opengl/GLContext break ()Lorg/lwjgl/opengl/kb;
L3:     dup
L4:     astore_3
L5:     getfield Field org/lwjgl/opengl/kb AQ J
L8:     dup2
L9:     lstore 4
L11:    invokestatic Method org/lwjgl/l break (J)V
L14:    iload_0
L15:    iload_1
L16:    aload_3
L17:    aload_2
L18:    invokestatic Method org/lwjgl/opengl/bB break (Lorg/lwjgl/opengl/kb;Ljava/lang/CharSequence;)J
L21:    lload 4
L23:    invokestatic Method org/lwjgl/opengl/GL30 nglBindFragDataLocation (IIJJ)V
L26:    return
L27:    
    .end code
.end method

.method public static break : (IIIILjava/nio/ShortBuffer;)V
    .code stack 8 locals 8
L0:     invokestatic Method org/lwjgl/opengl/GLContext break ()Lorg/lwjgl/opengl/kb;
L3:     astore 5
L5:     aload 4
L7:     aload 5
L9:     dup
L10:    getfield Field org/lwjgl/opengl/kb fs J
L13:    dup2
L14:    lstore 6
L16:    invokestatic Method org/lwjgl/l break (J)V
L19:    invokestatic Method org/lwjgl/opengl/Zd break (Lorg/lwjgl/opengl/kb;)V
L22:    invokestatic Method org/lwjgl/l break (Ljava/nio/ShortBuffer;)V
L25:    getstatic Field org/lwjgl/LWJGLUtil CHECKS Z
L28:    ifeq L43
L31:    aload 5
L33:    invokestatic Method org/lwjgl/opengl/w const (Lorg/lwjgl/opengl/kb;)Lorg/lwjgl/opengl/P;
L36:    getfield Field org/lwjgl/opengl/P do [Ljava/nio/Buffer;
L39:    iload_0
L40:    aload 4
L42:    aastore
L43:    iload_0
L44:    iload_1
L45:    iload_2
L46:    iload_3
L47:    aload 4
L49:    invokestatic Method org/lwjgl/MemoryUtil else (Ljava/nio/ShortBuffer;)J
L52:    lload 6
L54:    invokestatic Method org/lwjgl/opengl/GL30 nglVertexAttribIPointer (IIIIJJ)V
L57:    return
L58:    
        .attribute StackMap b'\x00\x01\x00\x2B\x00\x07\x01\x01\x01\x01\x07\x04\x0A\x07\x01\xE7\x04\x00\x00'
    .end code
.end method

.method static native nglVertexAttribI3ui : (IIIIJ)V
.end method

.method public static break : (IIILjava/nio/IntBuffer;)V
    .code stack 7 locals 6
L0:     invokestatic Method org/lwjgl/opengl/GLContext break ()Lorg/lwjgl/opengl/kb;
L3:     getfield Field org/lwjgl/opengl/kb kr J
L6:     dup2
L7:     lstore 4
L9:     invokestatic Method org/lwjgl/l break (J)V
L12:    iload_0
L13:    aload_3
L14:    iconst_4
L15:    iconst_1
L16:    dup
L17:    pop2
L18:    invokestatic Method org/lwjgl/l break (Ljava/nio/IntBuffer;I)V
L21:    iload_1
L22:    iload_2
L23:    aload_3
L24:    invokestatic Method org/lwjgl/MemoryUtil break (Ljava/nio/IntBuffer;)J
L27:    lload 4
L29:    invokestatic Method org/lwjgl/opengl/GL30 nglGetFramebufferAttachmentParameteriv (IIIJJ)V
L32:    return
L33:    
    .end code
.end method

.method static native nglVertexAttribI2ui : (IIIJ)V
.end method

.method static native nglGetFramebufferAttachmentParameteriv : (IIIJJ)V
.end method

.method public static else : (III)V
    .code stack 5 locals 5
L0:     invokestatic Method org/lwjgl/opengl/GLContext break ()Lorg/lwjgl/opengl/kb;
L3:     getfield Field org/lwjgl/opengl/kb II J
L6:     dup2
L7:     lstore_3
L8:     invokestatic Method org/lwjgl/l break (J)V
L11:    iload_0
L12:    iload_1
L13:    iload_2
L14:    lload_3
L15:    invokestatic Method org/lwjgl/opengl/GL30 nglVertexAttribI2i (IIIJ)V
L18:    return
L19:    
    .end code
.end method

.method static native nglGetBooleani_v : (IIJJ)V
.end method

.method public static const : (ILjava/nio/IntBuffer;)V
    .code stack 5 locals 4
L0:     invokestatic Method org/lwjgl/opengl/GLContext break ()Lorg/lwjgl/opengl/kb;
L3:     getfield Field org/lwjgl/opengl/kb Pd J
L6:     dup2
L7:     lstore_2
L8:     invokestatic Method org/lwjgl/l break (J)V
L11:    iload_0
L12:    aload_1
L13:    iconst_3
L14:    iconst_1
L15:    dup
L16:    pop2
L17:    invokestatic Method org/lwjgl/l break (Ljava/nio/IntBuffer;I)V
L20:    aload_1
L21:    invokestatic Method org/lwjgl/MemoryUtil break (Ljava/nio/IntBuffer;)J
L24:    lload_2
L25:    invokestatic Method org/lwjgl/opengl/GL30 nglVertexAttribI3iv (IJJ)V
L28:    return
L29:    
    .end code
.end method

.method public static do : (II)I
    .code stack 6 locals 5
L0:     invokestatic Method org/lwjgl/opengl/GLContext break ()Lorg/lwjgl/opengl/kb;
L3:     dup
L4:     getfield Field org/lwjgl/opengl/kb Af J
L7:     dup2
L8:     lstore_3
L9:     invokestatic Method org/lwjgl/l break (J)V
L12:    invokestatic Method org/lwjgl/opengl/bB short (Lorg/lwjgl/opengl/kb;)Ljava/nio/IntBuffer;
L15:    astore_2
L16:    iload_0
L17:    iload_1
L18:    aload_2
L19:    invokestatic Method org/lwjgl/MemoryUtil break (Ljava/nio/IntBuffer;)J
L22:    lload_3
L23:    invokestatic Method org/lwjgl/opengl/GL30 nglGetRenderbufferParameteriv (IIJJ)V
L26:    aload_2
L27:    iconst_0
L28:    iconst_1
L29:    dup
L30:    pop2
L31:    invokevirtual Method java/nio/IntBuffer get (I)I
L34:    ireturn
L35:    
    .end code
.end method

.method public static for : (II)V
    .code stack 4 locals 4
L0:     invokestatic Method org/lwjgl/opengl/GLContext break ()Lorg/lwjgl/opengl/kb;
L3:     getfield Field org/lwjgl/opengl/kb KC J
L6:     dup2
L7:     lstore_2
L8:     invokestatic Method org/lwjgl/l break (J)V
L11:    iload_0
L12:    iload_1
L13:    lload_2
L14:    invokestatic Method org/lwjgl/opengl/GL30 nglBindRenderbuffer (IIJ)V
L17:    return
L18:    
    .end code
.end method

.method public static break : (IIII)V
    .code stack 6 locals 6
L0:     invokestatic Method org/lwjgl/opengl/GLContext break ()Lorg/lwjgl/opengl/kb;
L3:     getfield Field org/lwjgl/opengl/kb Xh J
L6:     dup2
L7:     lstore 4
L9:     invokestatic Method org/lwjgl/l break (J)V
L12:    iload_0
L13:    iload_1
L14:    iload_2
L15:    iload_3
L16:    lload 4
L18:    invokestatic Method org/lwjgl/opengl/GL30 nglFramebufferRenderbuffer (IIIIJ)V
L21:    return
L22:    
    .end code
.end method

.method public static catch : (II)I
    .code stack 6 locals 5
L0:     invokestatic Method org/lwjgl/opengl/GLContext break ()Lorg/lwjgl/opengl/kb;
L3:     dup
L4:     getfield Field org/lwjgl/opengl/kb "strictfp" J
L7:     dup2
L8:     lstore_3
L9:     invokestatic Method org/lwjgl/l break (J)V
L12:    invokestatic Method org/lwjgl/opengl/bB short (Lorg/lwjgl/opengl/kb;)Ljava/nio/IntBuffer;
L15:    astore_2
L16:    iload_0
L17:    iload_1
L18:    aload_2
L19:    invokestatic Method org/lwjgl/MemoryUtil break (Ljava/nio/IntBuffer;)J
L22:    lload_3
L23:    invokestatic Method org/lwjgl/opengl/GL30 nglGetTexParameterIiv (IIJJ)V
L26:    aload_2
L27:    iconst_0
L28:    iconst_1
L29:    dup
L30:    pop2
L31:    invokevirtual Method java/nio/IntBuffer get (I)I
L34:    ireturn
L35:    
    .end code
.end method

.method public static break : (ILjava/lang/CharSequence;)I
    .code stack 5 locals 5
L0:     invokestatic Method org/lwjgl/opengl/GLContext break ()Lorg/lwjgl/opengl/kb;
L3:     dup
L4:     astore_2
L5:     getfield Field org/lwjgl/opengl/kb kp J
L8:     dup2
L9:     lstore_3
L10:    invokestatic Method org/lwjgl/l break (J)V
L13:    iload_0
L14:    aload_2
L15:    aload_1
L16:    invokestatic Method org/lwjgl/opengl/bB break (Lorg/lwjgl/opengl/kb;Ljava/lang/CharSequence;)J
L19:    lload_3
L20:    invokestatic Method org/lwjgl/opengl/GL30 nglGetFragDataLocation (IJJ)I
L23:    ireturn
L24:    
    .end code
.end method

.method static native nglVertexAttribI1ui : (IIJ)V
.end method

.method public static break : (IIILjava/nio/IntBuffer;Ljava/nio/IntBuffer;)Ljava/lang/String;
    .code stack 14 locals 9
L0:     invokestatic Method org/lwjgl/opengl/GLContext break ()Lorg/lwjgl/opengl/kb;
L3:     dup
L4:     astore 5
L6:     dup
L7:     aload 4
L9:     aload_3
L10:    aload 5
L12:    dup_x2
L13:    getfield Field org/lwjgl/opengl/kb XD J
L16:    dup2
L17:    lstore 6
L19:    invokestatic Method org/lwjgl/l break (J)V
L22:    iconst_1
L23:    dup
L24:    dup
L25:    pop2
L26:    invokestatic Method org/lwjgl/l break (Ljava/nio/IntBuffer;I)V
L29:    iconst_1
L30:    dup
L31:    dup
L32:    pop2
L33:    invokestatic Method org/lwjgl/l break (Ljava/nio/IntBuffer;I)V
L36:    invokestatic Method org/lwjgl/opengl/bB break (Lorg/lwjgl/opengl/kb;)Ljava/nio/IntBuffer;
L39:    astore 5
L41:    iload_2
L42:    invokestatic Method org/lwjgl/opengl/bB float (Lorg/lwjgl/opengl/kb;I)Ljava/nio/ByteBuffer;
L45:    astore 8
L47:    iload_0
L48:    iload_1
L49:    iload_2
L50:    aload 5
L52:    invokestatic Method org/lwjgl/MemoryUtil break (Ljava/nio/Buffer;)J
L55:    aload_3
L56:    invokestatic Method org/lwjgl/MemoryUtil break (Ljava/nio/IntBuffer;)J
L59:    aload 4
L61:    invokestatic Method org/lwjgl/MemoryUtil break (Ljava/nio/IntBuffer;)J
L64:    aload 8
L66:    invokestatic Method org/lwjgl/MemoryUtil const (Ljava/nio/ByteBuffer;)J
L69:    lload 6
L71:    invokestatic Method org/lwjgl/opengl/GL30 nglGetTransformFeedbackVarying (IIIJJJJJ)V
L74:    aload 8
L76:    dup
L77:    aload 5
L79:    iconst_0
L80:    iconst_1
L81:    dup
L82:    pop2
L83:    invokevirtual Method java/nio/IntBuffer get (I)I
L86:    invokevirtual Method java/nio/ByteBuffer limit (I)Ljava/nio/Buffer;
L89:    pop
L90:    invokestatic Method org/lwjgl/opengl/bB break (Lorg/lwjgl/opengl/kb;Ljava/nio/ByteBuffer;)Ljava/lang/String;
L93:    areturn
L94:    
    .end code
.end method

.method static native nglIsEnabledi : (IIJ)Z
.end method

.method static native nglBindBufferRange : (IIIJJJ)V
.end method

.method public static else : (IIIII)V
    .code stack 7 locals 7
L0:     invokestatic Method org/lwjgl/opengl/GLContext break ()Lorg/lwjgl/opengl/kb;
L3:     getfield Field org/lwjgl/opengl/kb We J
L6:     dup2
L7:     lstore 5
L9:     invokestatic Method org/lwjgl/l break (J)V
L12:    iload_0
L13:    iload_1
L14:    iload_2
L15:    iload_3
L16:    iload 4
L18:    lload 5
L20:    invokestatic Method org/lwjgl/opengl/GL30 nglVertexAttribI4ui (IIIIIJ)V
L23:    return
L24:    
    .end code
.end method

.method static native nglTexParameterIuiv : (IIJJ)V
.end method

.method public static break : (IJJ)V
    .code stack 7 locals 7
L0:     invokestatic Method org/lwjgl/opengl/GLContext break ()Lorg/lwjgl/opengl/kb;
L3:     getfield Field org/lwjgl/opengl/kb Cg J
L6:     dup2
L7:     lstore 5
L9:     invokestatic Method org/lwjgl/l break (J)V
L12:    iload_0
L13:    lload_1
L14:    lload_3
L15:    lload 5
L17:    invokestatic Method org/lwjgl/opengl/GL30 nglFlushMappedBufferRange (IJJJ)V
L20:    return
L21:    
    .end code
.end method

.method static native nglUniform4ui : (IIIIIJ)V
.end method

.method public static break : (ILjava/nio/ByteBuffer;)V
    .code stack 5 locals 4
L0:     invokestatic Method org/lwjgl/opengl/GLContext break ()Lorg/lwjgl/opengl/kb;
L3:     getfield Field org/lwjgl/opengl/kb LG J
L6:     dup2
L7:     lstore_2
L8:     invokestatic Method org/lwjgl/l break (J)V
L11:    iload_0
L12:    aload_1
L13:    iconst_4
L14:    iconst_1
L15:    dup
L16:    pop2
L17:    invokestatic Method org/lwjgl/l break (Ljava/nio/ByteBuffer;I)V
L20:    aload_1
L21:    invokestatic Method org/lwjgl/MemoryUtil const (Ljava/nio/ByteBuffer;)J
L24:    lload_2
L25:    invokestatic Method org/lwjgl/opengl/GL30 nglVertexAttribI4ubv (IJJ)V
L28:    return
L29:    
    .end code
.end method

.method static native nglBindBufferBase : (IIIJ)V
.end method

.method public static const : (I)V
    .code stack 4 locals 3
L0:     invokestatic Method org/lwjgl/opengl/GLContext break ()Lorg/lwjgl/opengl/kb;
L3:     getfield Field org/lwjgl/opengl/kb Sr J
L6:     dup2
L7:     lstore_1
L8:     invokestatic Method org/lwjgl/l break (J)V
L11:    iload_0
L12:    lload_1
L13:    invokestatic Method org/lwjgl/opengl/GL30 nglGenerateMipmap (IJ)V
L16:    return
L17:    
    .end code
.end method

.method static native nglRenderbufferStorageMultisample : (IIIIIJ)V
.end method

.method public static float : (II)V
    .code stack 4 locals 4
L0:     invokestatic Method org/lwjgl/opengl/GLContext break ()Lorg/lwjgl/opengl/kb;
L3:     getfield Field org/lwjgl/opengl/kb DU J
L6:     dup2
L7:     lstore_2
L8:     invokestatic Method org/lwjgl/l break (J)V
L11:    iload_0
L12:    iload_1
L13:    lload_2
L14:    invokestatic Method org/lwjgl/opengl/GL30 nglClampColor (IIJ)V
L17:    return
L18:    
    .end code
.end method

.method static native nglUniform2ui : (IIIJ)V
.end method

.method public static short : (II)I
    .code stack 2 locals 2
L0:     iload_0
L1:     iload_1
L2:     invokestatic Method org/lwjgl/opengl/GL30 do (II)I
L5:     ireturn
L6:     
    .end code
    .deprecated
.end method

.method static native nglBindVertexArray : (IJ)V
.end method

.method static native nglGetRenderbufferParameteriv : (IIJJ)V
.end method

.method public static else : (I)V
    .code stack 5 locals 4
L0:     invokestatic Method org/lwjgl/opengl/GLContext break ()Lorg/lwjgl/opengl/kb;
L3:     dup
L4:     astore_1
L5:     getfield Field org/lwjgl/opengl/kb Z J
L8:     dup2
L9:     lstore_2
L10:    invokestatic Method org/lwjgl/l break (J)V
L13:    iconst_1
L14:    dup
L15:    dup
L16:    pop2
L17:    aload_1
L18:    iload_0
L19:    invokestatic Method org/lwjgl/opengl/bB const (Lorg/lwjgl/opengl/kb;I)J
L22:    lload_2
L23:    invokestatic Method org/lwjgl/opengl/GL30 nglDeleteFramebuffers (IJJ)V
L26:    return
L27:    
    .end code
.end method

.method public static break : (III)V
    .code stack 5 locals 5
L0:     invokestatic Method org/lwjgl/opengl/GLContext break ()Lorg/lwjgl/opengl/kb;
L3:     getfield Field org/lwjgl/opengl/kb kt J
L6:     dup2
L7:     lstore_3
L8:     invokestatic Method org/lwjgl/l break (J)V
L11:    iload_0
L12:    iload_1
L13:    iload_2
L14:    lload_3
L15:    invokestatic Method org/lwjgl/opengl/GL30 nglUniform2ui (IIIJ)V
L18:    return
L19:    
    .end code
.end method

.method public static short : (Ljava/nio/IntBuffer;)V
    .code stack 7 locals 4
L0:     invokestatic Method org/lwjgl/opengl/GLContext break ()Lorg/lwjgl/opengl/kb;
L3:     dup
L4:     astore_1
L5:     aload_0
L6:     dup_x1
L7:     aload_1
L8:     getfield Field org/lwjgl/opengl/kb lM J
L11:    dup2
L12:    lstore_2
L13:    invokestatic Method org/lwjgl/l break (J)V
L16:    invokestatic Method org/lwjgl/opengl/w break (Lorg/lwjgl/opengl/kb;Ljava/nio/IntBuffer;)V
L19:    aload_0
L20:    invokestatic Method org/lwjgl/l else (Ljava/nio/IntBuffer;)V
L23:    invokevirtual Method java/nio/IntBuffer remaining ()I
L26:    aload_0
L27:    invokestatic Method org/lwjgl/MemoryUtil break (Ljava/nio/IntBuffer;)J
L30:    lload_2
L31:    invokestatic Method org/lwjgl/opengl/GL30 nglDeleteVertexArrays (IJJ)V
L34:    return
L35:    
    .end code
.end method

.method public static const : (II)V
    .code stack 4 locals 4
L0:     invokestatic Method org/lwjgl/opengl/GLContext break ()Lorg/lwjgl/opengl/kb;
L3:     getfield Field org/lwjgl/opengl/kb NS J
L6:     dup2
L7:     lstore_2
L8:     invokestatic Method org/lwjgl/l break (J)V
L11:    iload_0
L12:    iload_1
L13:    lload_2
L14:    invokestatic Method org/lwjgl/opengl/GL30 nglDisablei (IIJ)V
L17:    return
L18:    
    .end code
.end method

.method static native nglVertexAttribI3iv : (IJJ)V
.end method

.method public static break : ()V
    .code stack 4 locals 2
L0:     invokestatic Method org/lwjgl/opengl/GLContext break ()Lorg/lwjgl/opengl/kb;
L3:     getfield Field org/lwjgl/opengl/kb HA J
L6:     dup2
L7:     lstore_0
L8:     invokestatic Method org/lwjgl/l break (J)V
L11:    lload_0
L12:    invokestatic Method org/lwjgl/opengl/GL30 nglEndTransformFeedback (J)V
L15:    return
L16:    
    .end code
.end method

.method public static const : (Ljava/nio/IntBuffer;)V
    .code stack 5 locals 3
L0:     invokestatic Method org/lwjgl/opengl/GLContext break ()Lorg/lwjgl/opengl/kb;
L3:     getfield Field org/lwjgl/opengl/kb cI J
L6:     dup2
L7:     lstore_1
L8:     invokestatic Method org/lwjgl/l break (J)V
L11:    aload_0
L12:    dup
L13:    invokestatic Method org/lwjgl/l else (Ljava/nio/IntBuffer;)V
L16:    invokevirtual Method java/nio/IntBuffer remaining ()I
L19:    aload_0
L20:    invokestatic Method org/lwjgl/MemoryUtil break (Ljava/nio/IntBuffer;)J
L23:    lload_1
L24:    invokestatic Method org/lwjgl/opengl/GL30 nglGenFramebuffers (IJJ)V
L27:    return
L28:    
    .end code
.end method

.method public static else : (IILjava/nio/IntBuffer;)V
    .code stack 6 locals 5
L0:     invokestatic Method org/lwjgl/opengl/GLContext break ()Lorg/lwjgl/opengl/kb;
L3:     getfield Field org/lwjgl/opengl/kb bf J
L6:     dup2
L7:     lstore_3
L8:     invokestatic Method org/lwjgl/l break (J)V
L11:    iload_0
L12:    aload_2
L13:    iconst_4
L14:    iconst_1
L15:    dup
L16:    pop2
L17:    invokestatic Method org/lwjgl/l break (Ljava/nio/IntBuffer;I)V
L20:    iload_1
L21:    aload_2
L22:    invokestatic Method org/lwjgl/MemoryUtil break (Ljava/nio/IntBuffer;)J
L25:    lload_3
L26:    invokestatic Method org/lwjgl/opengl/GL30 nglGetVertexAttribIiv (IIJJ)V
L29:    return
L30:    
    .end code
.end method

.method public static break : (I)V
    .code stack 5 locals 3
L0:     invokestatic Method org/lwjgl/opengl/GLContext break ()Lorg/lwjgl/opengl/kb;
L3:     dup
L4:     getfield Field org/lwjgl/opengl/kb id J
L7:     dup2
L8:     lstore_1
L9:     invokestatic Method org/lwjgl/l break (J)V
L12:    iload_0
L13:    invokestatic Method org/lwjgl/opengl/w const (Lorg/lwjgl/opengl/kb;I)V
L16:    iload_0
L17:    lload_1
L18:    invokestatic Method org/lwjgl/opengl/GL30 nglBindVertexArray (IJ)V
L21:    return
L22:    
    .end code
.end method

.method public static else : (II)V
    .code stack 4 locals 4
L0:     invokestatic Method org/lwjgl/opengl/GLContext break ()Lorg/lwjgl/opengl/kb;
L3:     getfield Field org/lwjgl/opengl/kb HL J
L6:     dup2
L7:     lstore_2
L8:     invokestatic Method org/lwjgl/l break (J)V
L11:    iload_0
L12:    iload_1
L13:    lload_2
L14:    invokestatic Method org/lwjgl/opengl/GL30 nglEnablei (IIJ)V
L17:    return
L18:    
    .end code
.end method

.method static native nglUniform1ui : (IIJ)V
.end method

.method public static break : (II)V
    .code stack 4 locals 4
L0:     invokestatic Method org/lwjgl/opengl/GLContext break ()Lorg/lwjgl/opengl/kb;
L3:     getfield Field org/lwjgl/opengl/kb jN J
L6:     dup2
L7:     lstore_2
L8:     invokestatic Method org/lwjgl/l break (J)V
L11:    iload_0
L12:    iload_1
L13:    lload_2
L14:    invokestatic Method org/lwjgl/opengl/GL30 nglBindFramebuffer (IIJ)V
L17:    return
L18:    
    .end code
.end method

.method public static else : (ILjava/nio/IntBuffer;)V
    .code stack 5 locals 4
L0:     invokestatic Method org/lwjgl/opengl/GLContext break ()Lorg/lwjgl/opengl/kb;
L3:     getfield Field org/lwjgl/opengl/kb nj J
L6:     dup2
L7:     lstore_2
L8:     invokestatic Method org/lwjgl/l break (J)V
L11:    iload_0
L12:    aload_1
L13:    iconst_1
L14:    dup
L15:    dup
L16:    pop2
L17:    invokestatic Method org/lwjgl/l break (Ljava/nio/IntBuffer;I)V
L20:    aload_1
L21:    invokestatic Method org/lwjgl/MemoryUtil break (Ljava/nio/IntBuffer;)J
L24:    lload_2
L25:    invokestatic Method org/lwjgl/opengl/GL30 nglVertexAttribI1iv (IJJ)V
L28:    return
L29:    
    .end code
.end method

.method static native nglVertexAttribI3uiv : (IJJ)V
.end method

.method public static break : (IIIII)V
    .code stack 7 locals 7
L0:     invokestatic Method org/lwjgl/opengl/GLContext break ()Lorg/lwjgl/opengl/kb;
L3:     getfield Field org/lwjgl/opengl/kb Cf J
L6:     dup2
L7:     lstore 5
L9:     invokestatic Method org/lwjgl/l break (J)V
L12:    iload_0
L13:    iload_1
L14:    iload_2
L15:    iload_3
L16:    iload 4
L18:    lload 5
L20:    invokestatic Method org/lwjgl/opengl/GL30 nglFramebufferTexture1D (IIIIIJ)V
L23:    return
L24:    
    .end code
.end method

.method static native nglGetVertexAttribIuiv : (IIJJ)V
.end method

.method public static break : (IIIIJ)V
    .code stack 8 locals 8
L0:     invokestatic Method org/lwjgl/opengl/GLContext break ()Lorg/lwjgl/opengl/kb;
L3:     dup
L4:     getfield Field org/lwjgl/opengl/kb fs J
L7:     dup2
L8:     lstore 6
L10:    invokestatic Method org/lwjgl/l break (J)V
L13:    invokestatic Method org/lwjgl/opengl/Zd float (Lorg/lwjgl/opengl/kb;)V
L16:    iload_0
L17:    iload_1
L18:    iload_2
L19:    iload_3
L20:    lload 4
L22:    lload 6
L24:    invokestatic Method org/lwjgl/opengl/GL30 nglVertexAttribIPointerBO (IIIIJJ)V
L27:    return
L28:    
    .end code
.end method

.method public static else : (Ljava/nio/IntBuffer;)V
    .code stack 5 locals 3
L0:     invokestatic Method org/lwjgl/opengl/GLContext break ()Lorg/lwjgl/opengl/kb;
L3:     getfield Field org/lwjgl/opengl/kb Jb J
L6:     dup2
L7:     lstore_1
L8:     invokestatic Method org/lwjgl/l break (J)V
L11:    aload_0
L12:    dup
L13:    invokestatic Method org/lwjgl/l else (Ljava/nio/IntBuffer;)V
L16:    invokevirtual Method java/nio/IntBuffer remaining ()I
L19:    aload_0
L20:    invokestatic Method org/lwjgl/MemoryUtil break (Ljava/nio/IntBuffer;)J
L23:    lload_1
L24:    invokestatic Method org/lwjgl/opengl/GL30 nglGenVertexArrays (IJJ)V
L27:    return
L28:    
    .end code
.end method

.method public static break : (IILjava/nio/ByteBuffer;I)V
    .code stack 7 locals 6
L0:     invokestatic Method org/lwjgl/opengl/GLContext break ()Lorg/lwjgl/opengl/kb;
L3:     getfield Field org/lwjgl/opengl/kb NC J
L6:     dup2
L7:     lstore 4
L9:     invokestatic Method org/lwjgl/l break (J)V
L12:    iload_0
L13:    iload_1
L14:    aload_2
L15:    dup_x1
L16:    invokestatic Method org/lwjgl/l break (Ljava/nio/ByteBuffer;)V
L19:    invokestatic Method org/lwjgl/l else (Ljava/nio/ByteBuffer;I)V
L22:    iload_1
L23:    aload_2
L24:    invokestatic Method org/lwjgl/MemoryUtil const (Ljava/nio/ByteBuffer;)J
L27:    iload_3
L28:    lload 4
L30:    invokestatic Method org/lwjgl/opengl/GL30 nglTransformFeedbackVaryings (IIJIJ)V
L33:    return
L34:    
    .end code
.end method

.method public static break : (IILjava/nio/IntBuffer;)V
    .code stack 6 locals 5
L0:     invokestatic Method org/lwjgl/opengl/GLContext break ()Lorg/lwjgl/opengl/kb;
L3:     getfield Field org/lwjgl/opengl/kb UK J
L6:     dup2
L7:     lstore_3
L8:     invokestatic Method org/lwjgl/l break (J)V
L11:    iload_0
L12:    aload_2
L13:    iconst_4
L14:    iconst_1
L15:    dup
L16:    pop2
L17:    invokestatic Method org/lwjgl/l break (Ljava/nio/IntBuffer;I)V
L20:    iload_1
L21:    aload_2
L22:    invokestatic Method org/lwjgl/MemoryUtil break (Ljava/nio/IntBuffer;)J
L25:    lload_3
L26:    invokestatic Method org/lwjgl/opengl/GL30 nglClearBufferuiv (IIJJ)V
L29:    return
L30:    
    .end code
.end method

.method public static break : (IJJILjava/nio/ByteBuffer;)Ljava/nio/ByteBuffer;
    .code stack 9 locals 9
L0:     invokestatic Method org/lwjgl/opengl/GLContext break ()Lorg/lwjgl/opengl/kb;
L3:     getfield Field org/lwjgl/opengl/kb tI J
L6:     dup2
L7:     lstore 7
L9:     invokestatic Method org/lwjgl/l break (J)V
L12:    aload 6
L14:    ifnull L22
L17:    aload 6
L19:    invokestatic Method org/lwjgl/l break (Ljava/nio/ByteBuffer;)V
L22:    iload_0
L23:    lload_1
L24:    lload_3
L25:    iload 5
L27:    aload 6
L29:    lload 7
L31:    invokestatic Method org/lwjgl/opengl/GL30 nglMapBufferRange (IJJILjava/nio/ByteBuffer;J)Ljava/nio/ByteBuffer;
L34:    astore 5
L36:    getstatic Field org/lwjgl/LWJGLUtil CHECKS Z
L39:    ifeq L50
L42:    aload 5
L44:    ifnonnull L50
L47:    aconst_null
L48:    areturn
L49:    athrow
L50:    aload 5
L52:    invokestatic Method java/nio/ByteOrder nativeOrder ()Ljava/nio/ByteOrder;
L55:    invokevirtual Method java/nio/ByteBuffer order (Ljava/nio/ByteOrder;)Ljava/nio/ByteBuffer;
L58:    areturn
L59:    
        .attribute StackMap b'\x00\x03\x00\x16\x00\x06\x01\x04\x04\x01\x07\x02\x7D\x04\x00\x00\x00\x31\x00\x00\x00\x01\x07\x02\x96\x00\x32\x00\x06\x01\x04\x04\x07\x02\x7D\x07\x02\x7D\x04\x00\x00'
    .end code
.end method

.method static native nglBindRenderbuffer : (IIJ)V
.end method

.method static native nglMapBufferRange : (IJJILjava/nio/ByteBuffer;J)Ljava/nio/ByteBuffer;
.end method

.method static native nglGetStringi : (IIJ)Ljava/lang/String;
.end method

.method public static break : (ILjava/nio/IntBuffer;)V
    .code stack 5 locals 4
L0:     invokestatic Method org/lwjgl/opengl/GLContext break ()Lorg/lwjgl/opengl/kb;
L3:     getfield Field org/lwjgl/opengl/kb vo J
L6:     dup2
L7:     lstore_2
L8:     invokestatic Method org/lwjgl/l break (J)V
L11:    iload_0
L12:    aload_1
L13:    iconst_4
L14:    iconst_1
L15:    dup
L16:    pop2
L17:    invokestatic Method org/lwjgl/l break (Ljava/nio/IntBuffer;I)V
L20:    aload_1
L21:    invokestatic Method org/lwjgl/MemoryUtil break (Ljava/nio/IntBuffer;)J
L24:    lload_2
L25:    invokestatic Method org/lwjgl/opengl/GL30 nglVertexAttribI4iv (IJJ)V
L28:    return
L29:    
    .end code
.end method

.method public static break : (Ljava/nio/IntBuffer;)V
    .code stack 5 locals 3
L0:     invokestatic Method org/lwjgl/opengl/GLContext break ()Lorg/lwjgl/opengl/kb;
L3:     getfield Field org/lwjgl/opengl/kb Z J
L6:     dup2
L7:     lstore_1
L8:     invokestatic Method org/lwjgl/l break (J)V
L11:    aload_0
L12:    dup
L13:    invokestatic Method org/lwjgl/l else (Ljava/nio/IntBuffer;)V
L16:    invokevirtual Method java/nio/IntBuffer remaining ()I
L19:    aload_0
L20:    invokestatic Method org/lwjgl/MemoryUtil break (Ljava/nio/IntBuffer;)J
L23:    lload_1
L24:    invokestatic Method org/lwjgl/opengl/GL30 nglDeleteFramebuffers (IJJ)V
L27:    return
L28:    
    .end code
.end method
.end class
