.version 49 0
.class public final super org/lwjgl/opengl/GL41
.super java/lang/Object
.field public static final field4077 I = 35739
.field public static final return I = 33370
.field public static final field4078 I = 36678
.field public static final switch I = 36681
.field public static final field4079 I = 36340
.field public static final field4080 I = 36337
.field public static final field4081 I = 2928
.field public static final field4082 I = 36347
.field public static final field4083 I = 36683
.field public static final field4084 I = 36680
.field public static final field4085 I = 1
.field public static final field4086 I = 36431
.field public static final field4087 I = 36860
.field public static final throw I = 34814
.field public static final package I = 36679
.field public static final field4088 I = 16
.field public static final field4089 I = 33375
.field public static final while I = 33372
.field public static final field4090 I = 4
.field public static final field4091 I = 36345
.field public static final field4092 I = 36346
.field public static final field4093 I = 36862
.field public static final field4094 I = 36682
.field public static final field4095 I = 36348
.field public static final field4096 I = 36341
.field public static final field4097 I = 5132
.field public static final field4098 I = 33371
.field public static final field4099 I = 2978
.field public static final field4100 I = 33376
.field public static final false I = 33367
.field public static final field4101 I = 3089
.field public static final field4102 I = 33373
.field public static final true I = 8
.field public static final field4103 I = -1
.field public static final field4104 I = 2
.field public static final field4105 I = 36338
.field public static final field4106 I = 36336
.field public static final field4107 I = 33374
.field public static final field4108 I = 33369
.field public static final field4109 I = 36349
.field public static final field4110 I = 36430
.field public static final field4111 I = 36686
.field public static final field4112 I = 36861
.field public static final try I = 3088
.field public static final field4113 I = 36685
.field public static final new I = 34625
.field public static final field4114 I = 36339
.field public static final this I = 33368
.field public static final field4115 I = 35738
.field public static final field4116 I = 34815
.field public static final field4117 I = 36429
.field public static final field4118 I = 36684

.method public static method4420 : (IILjava/nio/IntBuffer;)V
    .code stack 7 locals 5
L0:     invokestatic Method org/lwjgl/opengl/GLContext method4611 ()Lorg/lwjgl/opengl/kb;
L3:     getfield Field org/lwjgl/opengl/kb qs J
L6:     dup2
L7:     lstore_3
L8:     invokestatic Method org/lwjgl/l method2052 (J)V
L11:    iload_0
L12:    aload_2
L13:    invokestatic Method org/lwjgl/l method2043 (Ljava/nio/IntBuffer;)V
L16:    iload_1
L17:    aload_2
L18:    invokevirtual Method java/nio/IntBuffer remaining ()I
L21:    iconst_2
L22:    iconst_1
L23:    dup
L24:    pop2
L25:    ishr
L26:    aload_2
L27:    invokestatic Method org/lwjgl/MemoryUtil method1884 (Ljava/nio/IntBuffer;)J
L30:    lload_3
L31:    invokestatic Method org/lwjgl/opengl/GL41 nglProgramUniform4iv (IIIJJ)V
L34:    return
L35:    
    .end code
.end method

.method public static method4421 : (IIZLjava/nio/DoubleBuffer;)V
    .code stack 8 locals 6
L0:     invokestatic Method org/lwjgl/opengl/GLContext method4611 ()Lorg/lwjgl/opengl/kb;
L3:     getfield Field org/lwjgl/opengl/kb rC J
L6:     dup2
L7:     lstore 4
L9:     invokestatic Method org/lwjgl/l method2052 (J)V
L12:    iload_0
L13:    aload_3
L14:    invokestatic Method org/lwjgl/l method2036 (Ljava/nio/DoubleBuffer;)V
L17:    iload_1
L18:    aload_3
L19:    invokevirtual Method java/nio/DoubleBuffer remaining ()I
L22:    bipush 6
L24:    iconst_1
L25:    dup
L26:    pop2
L27:    idiv
L28:    iload_2
L29:    aload_3
L30:    invokestatic Method org/lwjgl/MemoryUtil method1840 (Ljava/nio/DoubleBuffer;)J
L33:    lload 4
L35:    invokestatic Method org/lwjgl/opengl/GL41 nglProgramUniformMatrix3x2dv (IIIZJJ)V
L38:    return
L39:    
    .end code
.end method

.method static native nglCreateShaderProgramv2 : (IIJJ)I
.end method

.method static native nglViewportArrayv : (IIJJ)V
.end method

.method public static method4422 : (IIZLjava/nio/FloatBuffer;)V
    .code stack 8 locals 6
L0:     invokestatic Method org/lwjgl/opengl/GLContext method4611 ()Lorg/lwjgl/opengl/kb;
L3:     getfield Field org/lwjgl/opengl/kb xC J
L6:     dup2
L7:     lstore 4
L9:     invokestatic Method org/lwjgl/l method2052 (J)V
L12:    iload_0
L13:    aload_3
L14:    invokestatic Method org/lwjgl/l method2048 (Ljava/nio/FloatBuffer;)V
L17:    iload_1
L18:    aload_3
L19:    invokevirtual Method java/nio/FloatBuffer remaining ()I
L22:    iconst_3
L23:    iconst_1
L24:    dup
L25:    pop2
L26:    ishr
L27:    iload_2
L28:    aload_3
L29:    invokestatic Method org/lwjgl/MemoryUtil method1878 (Ljava/nio/FloatBuffer;)J
L32:    lload 4
L34:    invokestatic Method org/lwjgl/opengl/GL41 nglProgramUniformMatrix2x4fv (IIIZJJ)V
L37:    return
L38:    
    .end code
.end method

.method static native nglVertexAttribL2dv : (IJJ)V
.end method

.method static native nglVertexAttribL4d : (IDDDDJ)V
.end method

.method static native nglProgramUniform3f : (IIFFFJ)V
.end method

.method static native nglReleaseShaderCompiler : (J)V
.end method

.method public static method4423 : (IILjava/nio/FloatBuffer;)V
    .code stack 7 locals 5
L0:     invokestatic Method org/lwjgl/opengl/GLContext method4611 ()Lorg/lwjgl/opengl/kb;
L3:     getfield Field org/lwjgl/opengl/kb kK J
L6:     dup2
L7:     lstore_3
L8:     invokestatic Method org/lwjgl/l method2052 (J)V
L11:    iload_0
L12:    aload_2
L13:    invokestatic Method org/lwjgl/l method2048 (Ljava/nio/FloatBuffer;)V
L16:    iload_1
L17:    aload_2
L18:    invokevirtual Method java/nio/FloatBuffer remaining ()I
L21:    iconst_1
L22:    dup
L23:    dup
L24:    pop2
L25:    ishr
L26:    aload_2
L27:    invokestatic Method org/lwjgl/MemoryUtil method1878 (Ljava/nio/FloatBuffer;)J
L30:    lload_3
L31:    invokestatic Method org/lwjgl/opengl/GL41 nglProgramUniform2fv (IIIJJ)V
L34:    return
L35:    
    .end code
.end method

.method public static method4424 : (ILjava/nio/ByteBuffer;)I
    .code stack 6 locals 4
L0:     invokestatic Method org/lwjgl/opengl/GLContext method4611 ()Lorg/lwjgl/opengl/kb;
L3:     getfield Field org/lwjgl/opengl/kb jH J
L6:     dup2
L7:     lstore_2
L8:     invokestatic Method org/lwjgl/l method2052 (J)V
L11:    iload_0
L12:    aload_1
L13:    dup
L14:    invokestatic Method org/lwjgl/l method2034 (Ljava/nio/ByteBuffer;)V
L17:    invokestatic Method org/lwjgl/l method2033 (Ljava/nio/ByteBuffer;)V
L20:    iconst_1
L21:    dup
L22:    dup
L23:    pop2
L24:    aload_1
L25:    invokestatic Method org/lwjgl/MemoryUtil method1873 (Ljava/nio/ByteBuffer;)J
L28:    lload_2
L29:    invokestatic Method org/lwjgl/opengl/GL41 nglCreateShaderProgramv (IIJJ)I
L32:    ireturn
L33:    
    .end code
.end method

.method static native nglScissorIndexedv : (IJJ)V
.end method

.method static native nglVertexAttribL3d : (IDDDJ)V
.end method

.method public static method4425 : (IDDDD)V
    .code stack 11 locals 11
L0:     invokestatic Method org/lwjgl/opengl/GLContext method4611 ()Lorg/lwjgl/opengl/kb;
L3:     getfield Field org/lwjgl/opengl/kb Nd J
L6:     dup2
L7:     lstore 9
L9:     invokestatic Method org/lwjgl/l method2052 (J)V
L12:    iload_0
L13:    dload_1
L14:    dload_3
L15:    dload 5
L17:    dload 7
L19:    lload 9
L21:    invokestatic Method org/lwjgl/opengl/GL41 nglVertexAttribL4d (IDDDDJ)V
L24:    return
L25:    
    .end code
.end method

.method static native nglDepthRangef : (FFJ)V
.end method

.method public static method4426 : (IILjava/nio/IntBuffer;)V
    .code stack 7 locals 5
L0:     invokestatic Method org/lwjgl/opengl/GLContext method4611 ()Lorg/lwjgl/opengl/kb;
L3:     getfield Field org/lwjgl/opengl/kb UC J
L6:     dup2
L7:     lstore_3
L8:     invokestatic Method org/lwjgl/l method2052 (J)V
L11:    iload_0
L12:    aload_2
L13:    invokestatic Method org/lwjgl/l method2043 (Ljava/nio/IntBuffer;)V
L16:    iload_1
L17:    aload_2
L18:    invokevirtual Method java/nio/IntBuffer remaining ()I
L21:    iconst_2
L22:    iconst_1
L23:    dup
L24:    pop2
L25:    ishr
L26:    aload_2
L27:    invokestatic Method org/lwjgl/MemoryUtil method1884 (Ljava/nio/IntBuffer;)J
L30:    lload_3
L31:    invokestatic Method org/lwjgl/opengl/GL41 nglProgramUniform4uiv (IIIJJ)V
L34:    return
L35:    
    .end code
.end method

.method public static method4427 : (I)V
    .code stack 5 locals 4
L0:     invokestatic Method org/lwjgl/opengl/GLContext method4611 ()Lorg/lwjgl/opengl/kb;
L3:     dup
L4:     astore_1
L5:     getfield Field org/lwjgl/opengl/kb Of J
L8:     dup2
L9:     lstore_2
L10:    invokestatic Method org/lwjgl/l method2052 (J)V
L13:    iconst_1
L14:    dup
L15:    dup
L16:    pop2
L17:    aload_1
L18:    iload_0
L19:    invokestatic Method org/lwjgl/opengl/bB method5479 (Lorg/lwjgl/opengl/kb;I)J
L22:    lload_2
L23:    invokestatic Method org/lwjgl/opengl/GL41 nglDeleteProgramPipelines (IJJ)V
L26:    return
L27:    
    .end code
.end method

.method static native nglProgramBinary : (IIJIJ)V
.end method

.method public static method4428 : (IILjava/nio/FloatBuffer;)V
    .code stack 7 locals 5
L0:     invokestatic Method org/lwjgl/opengl/GLContext method4611 ()Lorg/lwjgl/opengl/kb;
L3:     getfield Field org/lwjgl/opengl/kb AJ J
L6:     dup2
L7:     lstore_3
L8:     invokestatic Method org/lwjgl/l method2052 (J)V
L11:    iload_0
L12:    aload_2
L13:    invokestatic Method org/lwjgl/l method2048 (Ljava/nio/FloatBuffer;)V
L16:    iload_1
L17:    aload_2
L18:    invokevirtual Method java/nio/FloatBuffer remaining ()I
L21:    aload_2
L22:    invokestatic Method org/lwjgl/MemoryUtil method1878 (Ljava/nio/FloatBuffer;)J
L25:    lload_3
L26:    invokestatic Method org/lwjgl/opengl/GL41 nglProgramUniform1fv (IIIJJ)V
L29:    return
L30:    
    .end code
.end method

.method static native nglProgramUniform1i : (IIIJ)V
.end method

.method public static method4429 : (ILjava/nio/FloatBuffer;)V
    .code stack 6 locals 4
L0:     invokestatic Method org/lwjgl/opengl/GLContext method4611 ()Lorg/lwjgl/opengl/kb;
L3:     getfield Field org/lwjgl/opengl/kb WF J
L6:     dup2
L7:     lstore_2
L8:     invokestatic Method org/lwjgl/l method2052 (J)V
L11:    iload_0
L12:    aload_1
L13:    invokestatic Method org/lwjgl/l method2048 (Ljava/nio/FloatBuffer;)V
L16:    aload_1
L17:    invokevirtual Method java/nio/FloatBuffer remaining ()I
L20:    iconst_2
L21:    iconst_1
L22:    dup
L23:    pop2
L24:    ishr
L25:    aload_1
L26:    invokestatic Method org/lwjgl/MemoryUtil method1878 (Ljava/nio/FloatBuffer;)J
L29:    lload_2
L30:    invokestatic Method org/lwjgl/opengl/GL41 nglViewportArrayv (IIJJ)V
L33:    return
L34:    
    .end code
.end method

.method static native nglProgramUniform4f : (IIFFFFJ)V
.end method

.method static native nglProgramUniform1d : (IIDJ)V
.end method

.method static native nglVertexAttribL4dv : (IJJ)V
.end method

.method static native nglProgramUniform1uiv : (IIIJJ)V
.end method

.method public static method4430 : (IILjava/nio/ByteBuffer;)V
    .code stack 7 locals 5
L0:     invokestatic Method org/lwjgl/opengl/GLContext method4611 ()Lorg/lwjgl/opengl/kb;
L3:     getfield Field org/lwjgl/opengl/kb rm J
L6:     dup2
L7:     lstore_3
L8:     invokestatic Method org/lwjgl/l method2052 (J)V
L11:    iload_0
L12:    aload_2
L13:    invokestatic Method org/lwjgl/l method2034 (Ljava/nio/ByteBuffer;)V
L16:    iload_1
L17:    aload_2
L18:    invokestatic Method org/lwjgl/MemoryUtil method1873 (Ljava/nio/ByteBuffer;)J
L21:    aload_2
L22:    invokevirtual Method java/nio/ByteBuffer remaining ()I
L25:    lload_3
L26:    invokestatic Method org/lwjgl/opengl/GL41 nglProgramBinary (IIJIJ)V
L29:    return
L30:    
    .end code
.end method

.method static native nglProgramUniformMatrix2fv : (IIIZJJ)V
.end method

.method public static method4431 : (IIFFF)V
    .code stack 7 locals 7
L0:     invokestatic Method org/lwjgl/opengl/GLContext method4611 ()Lorg/lwjgl/opengl/kb;
L3:     getfield Field org/lwjgl/opengl/kb IL J
L6:     dup2
L7:     lstore 5
L9:     invokestatic Method org/lwjgl/l method2052 (J)V
L12:    iload_0
L13:    iload_1
L14:    fload_2
L15:    fload_3
L16:    fload 4
L18:    lload 5
L20:    invokestatic Method org/lwjgl/opengl/GL41 nglProgramUniform3f (IIFFFJ)V
L23:    return
L24:    
    .end code
.end method

.method public static method4432 : (IIF)V
    .code stack 5 locals 5
L0:     invokestatic Method org/lwjgl/opengl/GLContext method4611 ()Lorg/lwjgl/opengl/kb;
L3:     getfield Field org/lwjgl/opengl/kb xl J
L6:     dup2
L7:     lstore_3
L8:     invokestatic Method org/lwjgl/l method2052 (J)V
L11:    iload_0
L12:    iload_1
L13:    fload_2
L14:    lload_3
L15:    invokestatic Method org/lwjgl/opengl/GL41 nglProgramUniform1f (IIFJ)V
L18:    return
L19:    
    .end code
.end method

.method public static method4433 : (ILjava/nio/DoubleBuffer;)V
    .code stack 6 locals 4
L0:     invokestatic Method org/lwjgl/opengl/GLContext method4611 ()Lorg/lwjgl/opengl/kb;
L3:     getfield Field org/lwjgl/opengl/kb cm J
L6:     dup2
L7:     lstore_2
L8:     invokestatic Method org/lwjgl/l method2052 (J)V
L11:    iload_0
L12:    aload_1
L13:    invokestatic Method org/lwjgl/l method2036 (Ljava/nio/DoubleBuffer;)V
L16:    aload_1
L17:    invokevirtual Method java/nio/DoubleBuffer remaining ()I
L20:    iconst_1
L21:    dup
L22:    dup
L23:    pop2
L24:    ishr
L25:    aload_1
L26:    invokestatic Method org/lwjgl/MemoryUtil method1840 (Ljava/nio/DoubleBuffer;)J
L29:    lload_2
L30:    invokestatic Method org/lwjgl/opengl/GL41 nglDepthRangeArrayv (IIJJ)V
L33:    return
L34:    
    .end code
.end method

.method public static method4434 : (IIDDDD)V
    .code stack 12 locals 12
L0:     invokestatic Method org/lwjgl/opengl/GLContext method4611 ()Lorg/lwjgl/opengl/kb;
L3:     getfield Field org/lwjgl/opengl/kb ME J
L6:     dup2
L7:     lstore 10
L9:     invokestatic Method org/lwjgl/l method2052 (J)V
L12:    iload_0
L13:    iload_1
L14:    dload_2
L15:    dload 4
L17:    dload 6
L19:    dload 8
L21:    lload 10
L23:    invokestatic Method org/lwjgl/opengl/GL41 nglProgramUniform4d (IIDDDDJ)V
L26:    return
L27:    
    .end code
.end method

.method static native nglProgramUniformMatrix4dv : (IIIZJJ)V
.end method

.method static native nglScissorArrayv : (IIJJ)V
.end method

.method public static method4435 : (IILjava/nio/IntBuffer;)V
    .code stack 7 locals 5
L0:     invokestatic Method org/lwjgl/opengl/GLContext method4611 ()Lorg/lwjgl/opengl/kb;
L3:     getfield Field org/lwjgl/opengl/kb jI J
L6:     dup2
L7:     lstore_3
L8:     invokestatic Method org/lwjgl/l method2052 (J)V
L11:    iload_0
L12:    aload_2
L13:    invokestatic Method org/lwjgl/l method2043 (Ljava/nio/IntBuffer;)V
L16:    iload_1
L17:    aload_2
L18:    invokevirtual Method java/nio/IntBuffer remaining ()I
L21:    aload_2
L22:    invokestatic Method org/lwjgl/MemoryUtil method1884 (Ljava/nio/IntBuffer;)J
L25:    lload_3
L26:    invokestatic Method org/lwjgl/opengl/GL41 nglProgramUniform1iv (IIIJJ)V
L29:    return
L30:    
    .end code
.end method

.method static native nglUseProgramStages : (IIIJ)V
.end method

.method public static method4436 : (IIZLjava/nio/FloatBuffer;)V
    .code stack 8 locals 6
L0:     invokestatic Method org/lwjgl/opengl/GLContext method4611 ()Lorg/lwjgl/opengl/kb;
L3:     getfield Field org/lwjgl/opengl/kb gp J
L6:     dup2
L7:     lstore 4
L9:     invokestatic Method org/lwjgl/l method2052 (J)V
L12:    iload_0
L13:    aload_3
L14:    invokestatic Method org/lwjgl/l method2048 (Ljava/nio/FloatBuffer;)V
L17:    iload_1
L18:    aload_3
L19:    invokevirtual Method java/nio/FloatBuffer remaining ()I
L22:    iconst_3
L23:    iconst_1
L24:    dup
L25:    pop2
L26:    ishr
L27:    iload_2
L28:    aload_3
L29:    invokestatic Method org/lwjgl/MemoryUtil method1878 (Ljava/nio/FloatBuffer;)J
L32:    lload 4
L34:    invokestatic Method org/lwjgl/opengl/GL41 nglProgramUniformMatrix4x2fv (IIIZJJ)V
L37:    return
L38:    
    .end code
.end method

.method static native nglProgramUniformMatrix2x4fv : (IIIZJJ)V
.end method

.method public static method4437 : (ID)V
    .code stack 5 locals 5
L0:     invokestatic Method org/lwjgl/opengl/GLContext method4611 ()Lorg/lwjgl/opengl/kb;
L3:     getfield Field org/lwjgl/opengl/kb nN J
L6:     dup2
L7:     lstore_3
L8:     invokestatic Method org/lwjgl/l method2052 (J)V
L11:    iload_0
L12:    dload_1
L13:    lload_3
L14:    invokestatic Method org/lwjgl/opengl/GL41 nglVertexAttribL1d (IDJ)V
L17:    return
L18:    
    .end code
.end method

.method static native nglVertexAttribLPointer : (IIIIJJ)V
.end method

.method static native nglVertexAttribL2d : (IDDJ)V
.end method

.method public static method4438 : (IILjava/nio/IntBuffer;)V
    .code stack 7 locals 5
L0:     invokestatic Method org/lwjgl/opengl/GLContext method4611 ()Lorg/lwjgl/opengl/kb;
L3:     getfield Field org/lwjgl/opengl/kb dK J
L6:     dup2
L7:     lstore_3
L8:     invokestatic Method org/lwjgl/l method2052 (J)V
L11:    iload_0
L12:    aload_2
L13:    invokestatic Method org/lwjgl/l method2043 (Ljava/nio/IntBuffer;)V
L16:    iload_1
L17:    aload_2
L18:    invokevirtual Method java/nio/IntBuffer remaining ()I
L21:    aload_2
L22:    invokestatic Method org/lwjgl/MemoryUtil method1884 (Ljava/nio/IntBuffer;)J
L25:    lload_3
L26:    invokestatic Method org/lwjgl/opengl/GL41 nglProgramUniform1uiv (IIIJJ)V
L29:    return
L30:    
    .end code
.end method

.method static native nglProgramUniformMatrix2x4dv : (IIIZJJ)V
.end method

.method public static method4439 : (ILjava/nio/IntBuffer;)V
    .code stack 5 locals 4
L0:     invokestatic Method org/lwjgl/opengl/GLContext method4611 ()Lorg/lwjgl/opengl/kb;
L3:     getfield Field org/lwjgl/opengl/kb wP J
L6:     dup2
L7:     lstore_2
L8:     invokestatic Method org/lwjgl/l method2052 (J)V
L11:    iload_0
L12:    aload_1
L13:    iconst_4
L14:    iconst_1
L15:    dup
L16:    pop2
L17:    invokestatic Method org/lwjgl/l method2041 (Ljava/nio/IntBuffer;I)V
L20:    aload_1
L21:    invokestatic Method org/lwjgl/MemoryUtil method1884 (Ljava/nio/IntBuffer;)J
L24:    lload_2
L25:    invokestatic Method org/lwjgl/opengl/GL41 nglScissorIndexedv (IJJ)V
L28:    return
L29:    
    .end code
.end method

.method static native nglClearDepthf : (FJ)V
.end method

.method public static method4440 : (I)Z
    .code stack 4 locals 3
L0:     invokestatic Method org/lwjgl/opengl/GLContext method4611 ()Lorg/lwjgl/opengl/kb;
L3:     getfield Field org/lwjgl/opengl/kb NE J
L6:     dup2
L7:     lstore_1
L8:     invokestatic Method org/lwjgl/l method2052 (J)V
L11:    iload_0
L12:    lload_1
L13:    invokestatic Method org/lwjgl/opengl/GL41 nglIsProgramPipeline (IJ)Z
L16:    ireturn
L17:    
    .end code
.end method

.method static native nglVertexAttribL1d : (IDJ)V
.end method

.method static native nglProgramUniform1fv : (IIIJJ)V
.end method

.method public static method4441 : (I[Ljava/nio/ByteBuffer;)I
    .code stack 5 locals 4
L0:     invokestatic Method org/lwjgl/opengl/GLContext method4611 ()Lorg/lwjgl/opengl/kb;
L3:     getfield Field org/lwjgl/opengl/kb jH J
L6:     dup2
L7:     lstore_2
L8:     invokestatic Method org/lwjgl/l method2052 (J)V
L11:    iload_0
L12:    aload_1
L13:    iconst_1
L14:    dup
L15:    dup
L16:    pop2
L17:    invokestatic Method org/lwjgl/l method2051 ([Ljava/lang/Object;I)V
L20:    aload_1
L21:    arraylength
L22:    aload_1
L23:    lload_2
L24:    invokestatic Method org/lwjgl/opengl/GL41 nglCreateShaderProgramv3 (II[Ljava/nio/ByteBuffer;J)I
L27:    ireturn
L28:    
    .end code
.end method

.method public static method4442 : (ILjava/lang/CharSequence;)I
    .code stack 6 locals 5
L0:     invokestatic Method org/lwjgl/opengl/GLContext method4611 ()Lorg/lwjgl/opengl/kb;
L3:     dup
L4:     astore_2
L5:     getfield Field org/lwjgl/opengl/kb jH J
L8:     dup2
L9:     lstore_3
L10:    invokestatic Method org/lwjgl/l method2052 (J)V
L13:    iload_0
L14:    iconst_1
L15:    dup
L16:    dup
L17:    pop2
L18:    aload_2
L19:    aload_1
L20:    invokestatic Method org/lwjgl/opengl/bB method5478 (Lorg/lwjgl/opengl/kb;Ljava/lang/CharSequence;)J
L23:    lload_3
L24:    invokestatic Method org/lwjgl/opengl/GL41 nglCreateShaderProgramv (IIJJ)I
L27:    ireturn
L28:    
    .end code
.end method

.method public static method4443 : (III)V
    .code stack 5 locals 5
L0:     invokestatic Method org/lwjgl/opengl/GLContext method4611 ()Lorg/lwjgl/opengl/kb;
L3:     getfield Field org/lwjgl/opengl/kb EI J
L6:     dup2
L7:     lstore_3
L8:     invokestatic Method org/lwjgl/l method2052 (J)V
L11:    iload_0
L12:    iload_1
L13:    iload_2
L14:    lload_3
L15:    invokestatic Method org/lwjgl/opengl/GL41 nglUseProgramStages (IIIJ)V
L18:    return
L19:    
    .end code
.end method

.method public static method4444 : (II)Ljava/lang/String;
    .code stack 9 locals 6
L0:     invokestatic Method org/lwjgl/opengl/GLContext method4611 ()Lorg/lwjgl/opengl/kb;
L3:     dup
L4:     dup2
L5:     getfield Field org/lwjgl/opengl/kb Ds J
L8:     dup2
L9:     lstore_3
L10:    invokestatic Method org/lwjgl/l method2052 (J)V
L13:    invokestatic Method org/lwjgl/opengl/bB method5483 (Lorg/lwjgl/opengl/kb;)Ljava/nio/IntBuffer;
L16:    astore_2
L17:    iload_1
L18:    invokestatic Method org/lwjgl/opengl/bB method5470 (Lorg/lwjgl/opengl/kb;I)Ljava/nio/ByteBuffer;
L21:    astore 5
L23:    iload_0
L24:    iload_1
L25:    aload_2
L26:    invokestatic Method org/lwjgl/MemoryUtil method1867 (Ljava/nio/Buffer;)J
L29:    aload 5
L31:    invokestatic Method org/lwjgl/MemoryUtil method1873 (Ljava/nio/ByteBuffer;)J
L34:    lload_3
L35:    invokestatic Method org/lwjgl/opengl/GL41 nglGetProgramPipelineInfoLog (IIJJJ)V
L38:    aload 5
L40:    dup
L41:    aload_2
L42:    iconst_0
L43:    iconst_1
L44:    dup
L45:    pop2
L46:    invokevirtual Method java/nio/IntBuffer get (I)I
L49:    invokevirtual Method java/nio/ByteBuffer limit (I)Ljava/nio/Buffer;
L52:    pop
L53:    invokestatic Method org/lwjgl/opengl/bB method5469 (Lorg/lwjgl/opengl/kb;Ljava/nio/ByteBuffer;)Ljava/lang/String;
L56:    areturn
L57:    
    .end code
.end method

.method static native nglProgramUniform2i : (IIIIJ)V
.end method

.method static native nglGetDoublei_v : (IIJJ)V
.end method

.method static native nglProgramUniform3iv : (IIIJJ)V
.end method

.method public static method4445 : (IILjava/nio/DoubleBuffer;)V
    .code stack 6 locals 5
L0:     invokestatic Method org/lwjgl/opengl/GLContext method4611 ()Lorg/lwjgl/opengl/kb;
L3:     getfield Field org/lwjgl/opengl/kb od J
L6:     dup2
L7:     lstore_3
L8:     invokestatic Method org/lwjgl/l method2052 (J)V
L11:    iload_0
L12:    aload_2
L13:    iconst_4
L14:    iconst_1
L15:    dup
L16:    pop2
L17:    invokestatic Method org/lwjgl/l method2056 (Ljava/nio/DoubleBuffer;I)V
L20:    iload_1
L21:    aload_2
L22:    invokestatic Method org/lwjgl/MemoryUtil method1840 (Ljava/nio/DoubleBuffer;)J
L25:    lload_3
L26:    invokestatic Method org/lwjgl/opengl/GL41 nglGetVertexAttribLdv (IIJJ)V
L29:    return
L30:    
    .end code
.end method

.method public static method4446 : (ILjava/nio/IntBuffer;)V
    .code stack 6 locals 4
L0:     invokestatic Method org/lwjgl/opengl/GLContext method4611 ()Lorg/lwjgl/opengl/kb;
L3:     getfield Field org/lwjgl/opengl/kb PT J
L6:     dup2
L7:     lstore_2
L8:     invokestatic Method org/lwjgl/l method2052 (J)V
L11:    iload_0
L12:    aload_1
L13:    invokestatic Method org/lwjgl/l method2043 (Ljava/nio/IntBuffer;)V
L16:    aload_1
L17:    invokevirtual Method java/nio/IntBuffer remaining ()I
L20:    iconst_2
L21:    iconst_1
L22:    dup
L23:    pop2
L24:    ishr
L25:    aload_1
L26:    invokestatic Method org/lwjgl/MemoryUtil method1884 (Ljava/nio/IntBuffer;)J
L29:    lload_2
L30:    invokestatic Method org/lwjgl/opengl/GL41 nglScissorArrayv (IIJJ)V
L33:    return
L34:    
    .end code
.end method

.method public static method4447 : (IILjava/nio/IntBuffer;)V
    .code stack 6 locals 5
L0:     invokestatic Method org/lwjgl/opengl/GLContext method4611 ()Lorg/lwjgl/opengl/kb;
L3:     getfield Field org/lwjgl/opengl/kb ae J
L6:     dup2
L7:     lstore_3
L8:     invokestatic Method org/lwjgl/l method2052 (J)V
L11:    iload_0
L12:    aload_2
L13:    iconst_1
L14:    dup
L15:    dup
L16:    pop2
L17:    invokestatic Method org/lwjgl/l method2041 (Ljava/nio/IntBuffer;I)V
L20:    iload_1
L21:    aload_2
L22:    invokestatic Method org/lwjgl/MemoryUtil method1884 (Ljava/nio/IntBuffer;)J
L25:    lload_3
L26:    invokestatic Method org/lwjgl/opengl/GL41 nglGetProgramPipelineiv (IIJJ)V
L29:    return
L30:    
    .end code
.end method

.method public static method4448 : (IFFFF)V
    .code stack 7 locals 7
L0:     invokestatic Method org/lwjgl/opengl/GLContext method4611 ()Lorg/lwjgl/opengl/kb;
L3:     getfield Field org/lwjgl/opengl/kb xj J
L6:     dup2
L7:     lstore 5
L9:     invokestatic Method org/lwjgl/l method2052 (J)V
L12:    iload_0
L13:    fload_1
L14:    fload_2
L15:    fload_3
L16:    fload 4
L18:    lload 5
L20:    invokestatic Method org/lwjgl/opengl/GL41 nglViewportIndexedf (IFFFFJ)V
L23:    return
L24:    
    .end code
.end method

.method static native nglProgramUniformMatrix3x4dv : (IIIZJJ)V
.end method

.method static native nglProgramUniformMatrix4x2fv : (IIIZJJ)V
.end method

.method static native nglActiveShaderProgram : (IIJ)V
.end method

.method static native nglProgramUniform2f : (IIFFJ)V
.end method

.method public static method4449 : (IILjava/nio/FloatBuffer;)V
    .code stack 6 locals 5
L0:     invokestatic Method org/lwjgl/opengl/GLContext method4611 ()Lorg/lwjgl/opengl/kb;
L3:     getfield Field org/lwjgl/opengl/kb w J
L6:     dup2
L7:     lstore_3
L8:     invokestatic Method org/lwjgl/l method2052 (J)V
L11:    iload_0
L12:    aload_2
L13:    invokestatic Method org/lwjgl/l method2048 (Ljava/nio/FloatBuffer;)V
L16:    iload_1
L17:    aload_2
L18:    invokestatic Method org/lwjgl/MemoryUtil method1878 (Ljava/nio/FloatBuffer;)J
L21:    lload_3
L22:    invokestatic Method org/lwjgl/opengl/GL41 nglGetFloati_v (IIJJ)V
L25:    return
L26:    
    .end code
.end method

.method public static method4450 : (IIIII)V
    .code stack 7 locals 7
L0:     invokestatic Method org/lwjgl/opengl/GLContext method4611 ()Lorg/lwjgl/opengl/kb;
L3:     getfield Field org/lwjgl/opengl/kb JC J
L6:     dup2
L7:     lstore 5
L9:     invokestatic Method org/lwjgl/l method2052 (J)V
L12:    iload_0
L13:    iload_1
L14:    iload_2
L15:    iload_3
L16:    iload 4
L18:    lload 5
L20:    invokestatic Method org/lwjgl/opengl/GL41 nglProgramUniform3i (IIIIIJ)V
L23:    return
L24:    
    .end code
.end method

.method public static method4451 : (III)V
    .code stack 5 locals 5
L0:     invokestatic Method org/lwjgl/opengl/GLContext method4611 ()Lorg/lwjgl/opengl/kb;
L3:     getfield Field org/lwjgl/opengl/kb sR J
L6:     dup2
L7:     lstore_3
L8:     invokestatic Method org/lwjgl/l method2052 (J)V
L11:    iload_0
L12:    iload_1
L13:    iload_2
L14:    lload_3
L15:    invokestatic Method org/lwjgl/opengl/GL41 nglProgramUniform1i (IIIJ)V
L18:    return
L19:    
    .end code
.end method

.method static native nglProgramUniformMatrix3dv : (IIIZJJ)V
.end method

.method static native nglGetFloati_v : (IIJJ)V
.end method

.method public static method4452 : (IILjava/nio/DoubleBuffer;)V
    .code stack 7 locals 5
L0:     invokestatic Method org/lwjgl/opengl/GLContext method4611 ()Lorg/lwjgl/opengl/kb;
L3:     getfield Field org/lwjgl/opengl/kb Tt J
L6:     dup2
L7:     lstore_3
L8:     invokestatic Method org/lwjgl/l method2052 (J)V
L11:    iload_0
L12:    aload_2
L13:    invokestatic Method org/lwjgl/l method2036 (Ljava/nio/DoubleBuffer;)V
L16:    iload_1
L17:    aload_2
L18:    invokevirtual Method java/nio/DoubleBuffer remaining ()I
L21:    iconst_1
L22:    dup
L23:    dup
L24:    pop2
L25:    ishr
L26:    aload_2
L27:    invokestatic Method org/lwjgl/MemoryUtil method1840 (Ljava/nio/DoubleBuffer;)J
L30:    lload_3
L31:    invokestatic Method org/lwjgl/opengl/GL41 nglProgramUniform2dv (IIIJJ)V
L34:    return
L35:    
    .end code
.end method

.method public static method4453 : (IIZLjava/nio/DoubleBuffer;)V
    .code stack 8 locals 6
L0:     invokestatic Method org/lwjgl/opengl/GLContext method4611 ()Lorg/lwjgl/opengl/kb;
L3:     getfield Field org/lwjgl/opengl/kb Qs J
L6:     dup2
L7:     lstore 4
L9:     invokestatic Method org/lwjgl/l method2052 (J)V
L12:    iload_0
L13:    aload_3
L14:    invokestatic Method org/lwjgl/l method2036 (Ljava/nio/DoubleBuffer;)V
L17:    iload_1
L18:    aload_3
L19:    invokevirtual Method java/nio/DoubleBuffer remaining ()I
L22:    bipush 12
L24:    iconst_1
L25:    dup
L26:    pop2
L27:    idiv
L28:    iload_2
L29:    aload_3
L30:    invokestatic Method org/lwjgl/MemoryUtil method1840 (Ljava/nio/DoubleBuffer;)J
L33:    lload 4
L35:    invokestatic Method org/lwjgl/opengl/GL41 nglProgramUniformMatrix3x4dv (IIIZJJ)V
L38:    return
L39:    
    .end code
.end method

.method public static method4454 : (F)V
    .code stack 4 locals 3
L0:     invokestatic Method org/lwjgl/opengl/GLContext method4611 ()Lorg/lwjgl/opengl/kb;
L3:     getfield Field org/lwjgl/opengl/kb Nb J
L6:     dup2
L7:     lstore_1
L8:     invokestatic Method org/lwjgl/l method2052 (J)V
L11:    fload_0
L12:    lload_1
L13:    invokestatic Method org/lwjgl/opengl/GL41 nglClearDepthf (FJ)V
L16:    return
L17:    
    .end code
.end method

.method static native nglProgramUniform3dv : (IIIJJ)V
.end method

.method public static method4455 : (I)V
    .code stack 4 locals 3
L0:     invokestatic Method org/lwjgl/opengl/GLContext method4611 ()Lorg/lwjgl/opengl/kb;
L3:     getfield Field org/lwjgl/opengl/kb xn J
L6:     dup2
L7:     lstore_1
L8:     invokestatic Method org/lwjgl/l method2052 (J)V
L11:    iload_0
L12:    lload_1
L13:    invokestatic Method org/lwjgl/opengl/GL41 nglValidateProgramPipeline (IJ)V
L16:    return
L17:    
    .end code
.end method

.method static native nglProgramUniform2fv : (IIIJJ)V
.end method

.method public static method4456 : ()I
    .code stack 5 locals 3
L0:     invokestatic Method org/lwjgl/opengl/GLContext method4611 ()Lorg/lwjgl/opengl/kb;
L3:     dup
L4:     getfield Field org/lwjgl/opengl/kb ns J
L7:     dup2
L8:     lstore_0
L9:     invokestatic Method org/lwjgl/l method2052 (J)V
L12:    invokestatic Method org/lwjgl/opengl/bB method5467 (Lorg/lwjgl/opengl/kb;)Ljava/nio/IntBuffer;
L15:    astore_2
L16:    iconst_1
L17:    dup
L18:    dup
L19:    pop2
L20:    aload_2
L21:    invokestatic Method org/lwjgl/MemoryUtil method1884 (Ljava/nio/IntBuffer;)J
L24:    lload_0
L25:    invokestatic Method org/lwjgl/opengl/GL41 nglGenProgramPipelines (IJJ)V
L28:    aload_2
L29:    iconst_0
L30:    iconst_1
L31:    dup
L32:    pop2
L33:    invokevirtual Method java/nio/IntBuffer get (I)I
L36:    ireturn
L37:    
    .end code
.end method

.method static native nglProgramUniformMatrix3x4fv : (IIIZJJ)V
.end method

.method public static method4457 : (IIZLjava/nio/DoubleBuffer;)V
    .code stack 8 locals 6
L0:     invokestatic Method org/lwjgl/opengl/GLContext method4611 ()Lorg/lwjgl/opengl/kb;
L3:     getfield Field org/lwjgl/opengl/kb RM J
L6:     dup2
L7:     lstore 4
L9:     invokestatic Method org/lwjgl/l method2052 (J)V
L12:    iload_0
L13:    aload_3
L14:    invokestatic Method org/lwjgl/l method2036 (Ljava/nio/DoubleBuffer;)V
L17:    iload_1
L18:    aload_3
L19:    invokevirtual Method java/nio/DoubleBuffer remaining ()I
L22:    bipush 9
L24:    iconst_1
L25:    dup
L26:    pop2
L27:    idiv
L28:    iload_2
L29:    aload_3
L30:    invokestatic Method org/lwjgl/MemoryUtil method1840 (Ljava/nio/DoubleBuffer;)J
L33:    lload 4
L35:    invokestatic Method org/lwjgl/opengl/GL41 nglProgramUniformMatrix3dv (IIIZJJ)V
L38:    return
L39:    
    .end code
.end method

.method static native nglProgramUniform1f : (IIFJ)V
.end method

.method public static method4458 : ()V
    .code stack 4 locals 2
L0:     invokestatic Method org/lwjgl/opengl/GLContext method4611 ()Lorg/lwjgl/opengl/kb;
L3:     getfield Field org/lwjgl/opengl/kb b J
L6:     dup2
L7:     lstore_0
L8:     invokestatic Method org/lwjgl/l method2052 (J)V
L11:    lload_0
L12:    invokestatic Method org/lwjgl/opengl/GL41 nglReleaseShaderCompiler (J)V
L15:    return
L16:    
    .end code
.end method

.method public static method4459 : (IIZLjava/nio/DoubleBuffer;)V
    .code stack 8 locals 6
L0:     invokestatic Method org/lwjgl/opengl/GLContext method4611 ()Lorg/lwjgl/opengl/kb;
L3:     getfield Field org/lwjgl/opengl/kb hl J
L6:     dup2
L7:     lstore 4
L9:     invokestatic Method org/lwjgl/l method2052 (J)V
L12:    iload_0
L13:    aload_3
L14:    invokestatic Method org/lwjgl/l method2036 (Ljava/nio/DoubleBuffer;)V
L17:    iload_1
L18:    aload_3
L19:    invokevirtual Method java/nio/DoubleBuffer remaining ()I
L22:    iconst_3
L23:    iconst_1
L24:    dup
L25:    pop2
L26:    ishr
L27:    iload_2
L28:    aload_3
L29:    invokestatic Method org/lwjgl/MemoryUtil method1840 (Ljava/nio/DoubleBuffer;)J
L32:    lload 4
L34:    invokestatic Method org/lwjgl/opengl/GL41 nglProgramUniformMatrix2x4dv (IIIZJJ)V
L37:    return
L38:    
    .end code
.end method

.method public static method4460 : (IIIJ)V
    .code stack 8 locals 7
L0:     invokestatic Method org/lwjgl/opengl/GLContext method4611 ()Lorg/lwjgl/opengl/kb;
L3:     dup
L4:     getfield Field org/lwjgl/opengl/kb Hd J
L7:     dup2
L8:     lstore 5
L10:    invokestatic Method org/lwjgl/l method2052 (J)V
L13:    invokestatic Method org/lwjgl/opengl/Zd method5441 (Lorg/lwjgl/opengl/kb;)V
L16:    iload_0
L17:    iload_1
L18:    sipush 5130
L21:    iconst_1
L22:    dup
L23:    pop2
L24:    iload_2
L25:    lload_3
L26:    lload 5
L28:    invokestatic Method org/lwjgl/opengl/GL41 nglVertexAttribLPointerBO (IIIIJJ)V
L31:    return
L32:    
    .end code
.end method

.method public static method4461 : (Ljava/nio/IntBuffer;)V
    .code stack 5 locals 3
L0:     invokestatic Method org/lwjgl/opengl/GLContext method4611 ()Lorg/lwjgl/opengl/kb;
L3:     getfield Field org/lwjgl/opengl/kb ns J
L6:     dup2
L7:     lstore_1
L8:     invokestatic Method org/lwjgl/l method2052 (J)V
L11:    aload_0
L12:    dup
L13:    invokestatic Method org/lwjgl/l method2043 (Ljava/nio/IntBuffer;)V
L16:    invokevirtual Method java/nio/IntBuffer remaining ()I
L19:    aload_0
L20:    invokestatic Method org/lwjgl/MemoryUtil method1884 (Ljava/nio/IntBuffer;)J
L23:    lload_1
L24:    invokestatic Method org/lwjgl/opengl/GL41 nglGenProgramPipelines (IJJ)V
L27:    return
L28:    
    .end code
.end method

.method public static method4462 : (IILjava/nio/IntBuffer;)V
    .code stack 7 locals 5
L0:     invokestatic Method org/lwjgl/opengl/GLContext method4611 ()Lorg/lwjgl/opengl/kb;
L3:     getfield Field org/lwjgl/opengl/kb Xr J
L6:     dup2
L7:     lstore_3
L8:     invokestatic Method org/lwjgl/l method2052 (J)V
L11:    iload_0
L12:    aload_2
L13:    invokestatic Method org/lwjgl/l method2043 (Ljava/nio/IntBuffer;)V
L16:    iload_1
L17:    aload_2
L18:    invokevirtual Method java/nio/IntBuffer remaining ()I
L21:    iconst_3
L22:    iconst_1
L23:    dup
L24:    pop2
L25:    idiv
L26:    aload_2
L27:    invokestatic Method org/lwjgl/MemoryUtil method1884 (Ljava/nio/IntBuffer;)J
L30:    lload_3
L31:    invokestatic Method org/lwjgl/opengl/GL41 nglProgramUniform3iv (IIIJJ)V
L34:    return
L35:    
    .end code
.end method

.method static native nglGetProgramBinary : (IIJJJJ)V
.end method

.method static native nglProgramUniform4uiv : (IIIJJ)V
.end method

.method static native nglCreateShaderProgramv3 : (II[Ljava/nio/ByteBuffer;J)I
.end method

.method public static method4463 : (IIZLjava/nio/DoubleBuffer;)V
    .code stack 8 locals 6
L0:     invokestatic Method org/lwjgl/opengl/GLContext method4611 ()Lorg/lwjgl/opengl/kb;
L3:     getfield Field org/lwjgl/opengl/kb Pi J
L6:     dup2
L7:     lstore 4
L9:     invokestatic Method org/lwjgl/l method2052 (J)V
L12:    iload_0
L13:    aload_3
L14:    invokestatic Method org/lwjgl/l method2036 (Ljava/nio/DoubleBuffer;)V
L17:    iload_1
L18:    aload_3
L19:    invokevirtual Method java/nio/DoubleBuffer remaining ()I
L22:    iconst_4
L23:    iconst_1
L24:    dup
L25:    pop2
L26:    ishr
L27:    iload_2
L28:    aload_3
L29:    invokestatic Method org/lwjgl/MemoryUtil method1840 (Ljava/nio/DoubleBuffer;)J
L32:    lload 4
L34:    invokestatic Method org/lwjgl/opengl/GL41 nglProgramUniformMatrix4dv (IIIZJJ)V
L37:    return
L38:    
    .end code
.end method

.method public static method4464 : (IIDD)V
    .code stack 8 locals 8
L0:     invokestatic Method org/lwjgl/opengl/GLContext method4611 ()Lorg/lwjgl/opengl/kb;
L3:     getfield Field org/lwjgl/opengl/kb O J
L6:     dup2
L7:     lstore 6
L9:     invokestatic Method org/lwjgl/l method2052 (J)V
L12:    iload_0
L13:    iload_1
L14:    dload_2
L15:    dload 4
L17:    lload 6
L19:    invokestatic Method org/lwjgl/opengl/GL41 nglProgramUniform2d (IIDDJ)V
L22:    return
L23:    
    .end code
.end method

.method static native nglGetVertexAttribLdv : (IIJJ)V
.end method

.method public static method4465 : (IILjava/nio/IntBuffer;)V
    .code stack 7 locals 5
L0:     invokestatic Method org/lwjgl/opengl/GLContext method4611 ()Lorg/lwjgl/opengl/kb;
L3:     getfield Field org/lwjgl/opengl/kb PG J
L6:     dup2
L7:     lstore_3
L8:     invokestatic Method org/lwjgl/l method2052 (J)V
L11:    iload_0
L12:    aload_2
L13:    invokestatic Method org/lwjgl/l method2043 (Ljava/nio/IntBuffer;)V
L16:    iload_1
L17:    aload_2
L18:    invokevirtual Method java/nio/IntBuffer remaining ()I
L21:    iconst_1
L22:    dup
L23:    dup
L24:    pop2
L25:    ishr
L26:    aload_2
L27:    invokestatic Method org/lwjgl/MemoryUtil method1884 (Ljava/nio/IntBuffer;)J
L30:    lload_3
L31:    invokestatic Method org/lwjgl/opengl/GL41 nglProgramUniform2uiv (IIIJJ)V
L34:    return
L35:    
    .end code
.end method

.method public static method4466 : (IILjava/nio/DoubleBuffer;)V
    .code stack 7 locals 5
L0:     invokestatic Method org/lwjgl/opengl/GLContext method4611 ()Lorg/lwjgl/opengl/kb;
L3:     getfield Field org/lwjgl/opengl/kb Er J
L6:     dup2
L7:     lstore_3
L8:     invokestatic Method org/lwjgl/l method2052 (J)V
L11:    iload_0
L12:    aload_2
L13:    invokestatic Method org/lwjgl/l method2036 (Ljava/nio/DoubleBuffer;)V
L16:    iload_1
L17:    aload_2
L18:    invokevirtual Method java/nio/DoubleBuffer remaining ()I
L21:    iconst_3
L22:    iconst_1
L23:    dup
L24:    pop2
L25:    idiv
L26:    aload_2
L27:    invokestatic Method org/lwjgl/MemoryUtil method1840 (Ljava/nio/DoubleBuffer;)J
L30:    lload_3
L31:    invokestatic Method org/lwjgl/opengl/GL41 nglProgramUniform3dv (IIIJJ)V
L34:    return
L35:    
    .end code
.end method

.method static native nglGetShaderPrecisionFormat : (IIJJJ)V
.end method

.method static native nglProgramUniform1dv : (IIIJJ)V
.end method

.method public static method4467 : (IIZLjava/nio/DoubleBuffer;)V
    .code stack 8 locals 6
L0:     invokestatic Method org/lwjgl/opengl/GLContext method4611 ()Lorg/lwjgl/opengl/kb;
L3:     getfield Field org/lwjgl/opengl/kb TN J
L6:     dup2
L7:     lstore 4
L9:     invokestatic Method org/lwjgl/l method2052 (J)V
L12:    iload_0
L13:    aload_3
L14:    invokestatic Method org/lwjgl/l method2036 (Ljava/nio/DoubleBuffer;)V
L17:    iload_1
L18:    aload_3
L19:    invokevirtual Method java/nio/DoubleBuffer remaining ()I
L22:    bipush 12
L24:    iconst_1
L25:    dup
L26:    pop2
L27:    idiv
L28:    iload_2
L29:    aload_3
L30:    invokestatic Method org/lwjgl/MemoryUtil method1840 (Ljava/nio/DoubleBuffer;)J
L33:    lload 4
L35:    invokestatic Method org/lwjgl/opengl/GL41 nglProgramUniformMatrix4x3dv (IIIZJJ)V
L38:    return
L39:    
    .end code
.end method

.method public static method4468 : (IILjava/nio/DoubleBuffer;)V
    .code stack 6 locals 5
L0:     invokestatic Method org/lwjgl/opengl/GLContext method4611 ()Lorg/lwjgl/opengl/kb;
L3:     getfield Field org/lwjgl/opengl/kb vh J
L6:     dup2
L7:     lstore_3
L8:     invokestatic Method org/lwjgl/l method2052 (J)V
L11:    iload_0
L12:    aload_2
L13:    invokestatic Method org/lwjgl/l method2036 (Ljava/nio/DoubleBuffer;)V
L16:    iload_1
L17:    aload_2
L18:    invokestatic Method org/lwjgl/MemoryUtil method1840 (Ljava/nio/DoubleBuffer;)J
L21:    lload_3
L22:    invokestatic Method org/lwjgl/opengl/GL41 nglGetDoublei_v (IIJJ)V
L25:    return
L26:    
    .end code
.end method

.method static native nglProgramUniform2ui : (IIIIJ)V
.end method

.method public static method4469 : (IILjava/nio/IntBuffer;)V
    .code stack 7 locals 5
L0:     invokestatic Method org/lwjgl/opengl/GLContext method4611 ()Lorg/lwjgl/opengl/kb;
L3:     getfield Field org/lwjgl/opengl/kb WB J
L6:     dup2
L7:     lstore_3
L8:     invokestatic Method org/lwjgl/l method2052 (J)V
L11:    iload_0
L12:    aload_2
L13:    invokestatic Method org/lwjgl/l method2043 (Ljava/nio/IntBuffer;)V
L16:    iload_1
L17:    aload_2
L18:    invokevirtual Method java/nio/IntBuffer remaining ()I
L21:    iconst_1
L22:    dup
L23:    dup
L24:    pop2
L25:    ishr
L26:    aload_2
L27:    invokestatic Method org/lwjgl/MemoryUtil method1884 (Ljava/nio/IntBuffer;)J
L30:    lload_3
L31:    invokestatic Method org/lwjgl/opengl/GL41 nglProgramUniform2iv (IIIJJ)V
L34:    return
L35:    
    .end code
.end method

.method public static method4470 : (IIIII)V
    .code stack 7 locals 7
L0:     invokestatic Method org/lwjgl/opengl/GLContext method4611 ()Lorg/lwjgl/opengl/kb;
L3:     getfield Field org/lwjgl/opengl/kb ZF J
L6:     dup2
L7:     lstore 5
L9:     invokestatic Method org/lwjgl/l method2052 (J)V
L12:    iload_0
L13:    iload_1
L14:    iload_2
L15:    iload_3
L16:    iload 4
L18:    lload 5
L20:    invokestatic Method org/lwjgl/opengl/GL41 nglScissorIndexed (IIIIIJ)V
L23:    return
L24:    
    .end code
.end method

.method static native nglProgramUniformMatrix4x3fv : (IIIZJJ)V
.end method

.method static native nglProgramUniformMatrix4x2dv : (IIIZJJ)V
.end method

.method public static method4471 : (IIILjava/nio/DoubleBuffer;)V
    .code stack 8 locals 7
L0:     invokestatic Method org/lwjgl/opengl/GLContext method4611 ()Lorg/lwjgl/opengl/kb;
L3:     astore 4
L5:     aload_3
L6:     aload 4
L8:     dup
L9:     getfield Field org/lwjgl/opengl/kb Hd J
L12:    dup2
L13:    lstore 5
L15:    invokestatic Method org/lwjgl/l method2052 (J)V
L18:    invokestatic Method org/lwjgl/opengl/Zd method5454 (Lorg/lwjgl/opengl/kb;)V
L21:    invokestatic Method org/lwjgl/l method2036 (Ljava/nio/DoubleBuffer;)V
L24:    getstatic Field org/lwjgl/LWJGLUtil CHECKS Z
L27:    ifeq L41
L30:    aload 4
L32:    invokestatic Method org/lwjgl/opengl/w method5768 (Lorg/lwjgl/opengl/kb;)Lorg/lwjgl/opengl/P;
L35:    getfield Field org/lwjgl/opengl/P field4956 [Ljava/nio/Buffer;
L38:    iload_0
L39:    aload_3
L40:    aastore
L41:    iload_0
L42:    iload_1
L43:    sipush 5130
L46:    iconst_1
L47:    dup
L48:    pop2
L49:    iload_2
L50:    aload_3
L51:    invokestatic Method org/lwjgl/MemoryUtil method1840 (Ljava/nio/DoubleBuffer;)J
L54:    lload 5
L56:    invokestatic Method org/lwjgl/opengl/GL41 nglVertexAttribLPointer (IIIIJJ)V
L59:    return
L60:    
        .attribute StackMap b'\x00\x01\x00\x29\x00\x06\x01\x01\x01\x07\x00\xA0\x07\x00\x77\x04\x00\x00'
    .end code
.end method

.method public static method4472 : (ILjava/nio/IntBuffer;Ljava/nio/IntBuffer;Ljava/nio/ByteBuffer;)V
    .code stack 10 locals 6
L0:     invokestatic Method org/lwjgl/opengl/GLContext method4611 ()Lorg/lwjgl/opengl/kb;
L3:     getfield Field org/lwjgl/opengl/kb Kn J
L6:     dup2
L7:     lstore 4
L9:     invokestatic Method org/lwjgl/l method2052 (J)V
L12:    aload_1
L13:    ifnull L24
L16:    aload_1
L17:    iconst_1
L18:    dup
L19:    dup
L20:    pop2
L21:    invokestatic Method org/lwjgl/l method2041 (Ljava/nio/IntBuffer;I)V
L24:    aload_2
L25:    iconst_1
L26:    dup
L27:    dup
L28:    pop2
L29:    invokestatic Method org/lwjgl/l method2041 (Ljava/nio/IntBuffer;I)V
L32:    iload_0
L33:    aload_3
L34:    invokestatic Method org/lwjgl/l method2034 (Ljava/nio/ByteBuffer;)V
L37:    aload_3
L38:    invokevirtual Method java/nio/ByteBuffer remaining ()I
L41:    aload_1
L42:    invokestatic Method org/lwjgl/MemoryUtil method1865 (Ljava/nio/IntBuffer;)J
L45:    aload_2
L46:    invokestatic Method org/lwjgl/MemoryUtil method1884 (Ljava/nio/IntBuffer;)J
L49:    aload_3
L50:    invokestatic Method org/lwjgl/MemoryUtil method1873 (Ljava/nio/ByteBuffer;)J
L53:    lload 4
L55:    invokestatic Method org/lwjgl/opengl/GL41 nglGetProgramBinary (IIJJJJ)V
L58:    return
L59:    
        .attribute StackMap b'\x00\x01\x00\x18\x00\x05\x01\x07\x00\x87\x07\x00\x87\x07\x01\x22\x04\x00\x00'
    .end code
.end method

.method public static method4473 : (II)F
    .code stack 6 locals 5
L0:     invokestatic Method org/lwjgl/opengl/GLContext method4611 ()Lorg/lwjgl/opengl/kb;
L3:     dup
L4:     getfield Field org/lwjgl/opengl/kb w J
L7:     dup2
L8:     lstore_3
L9:     invokestatic Method org/lwjgl/l method2052 (J)V
L12:    invokestatic Method org/lwjgl/opengl/bB method5465 (Lorg/lwjgl/opengl/kb;)Ljava/nio/FloatBuffer;
L15:    astore_2
L16:    iload_0
L17:    iload_1
L18:    aload_2
L19:    invokestatic Method org/lwjgl/MemoryUtil method1878 (Ljava/nio/FloatBuffer;)J
L22:    lload_3
L23:    invokestatic Method org/lwjgl/opengl/GL41 nglGetFloati_v (IIJJ)V
L26:    aload_2
L27:    iconst_0
L28:    iconst_1
L29:    dup
L30:    pop2
L31:    invokevirtual Method java/nio/FloatBuffer get (I)F
L34:    freturn
L35:    
    .end code
.end method

.method static native nglProgramUniformMatrix2x3dv : (IIIZJJ)V
.end method

.method static native nglDeleteProgramPipelines : (IJJ)V
.end method

.method static native nglProgramUniform3ui : (IIIIIJ)V
.end method

.method static native nglScissorIndexed : (IIIIIJ)V
.end method

.method static native nglProgramUniform3d : (IIDDDJ)V
.end method

.method static native nglProgramUniform1iv : (IIIJJ)V
.end method

.method public static method4474 : (IIFFFF)V
    .code stack 8 locals 8
L0:     invokestatic Method org/lwjgl/opengl/GLContext method4611 ()Lorg/lwjgl/opengl/kb;
L3:     getfield Field org/lwjgl/opengl/kb field5424 J
L6:     dup2
L7:     lstore 6
L9:     invokestatic Method org/lwjgl/l method2052 (J)V
L12:    iload_0
L13:    iload_1
L14:    fload_2
L15:    fload_3
L16:    fload 4
L18:    fload 5
L20:    lload 6
L22:    invokestatic Method org/lwjgl/opengl/GL41 nglProgramUniform4f (IIFFFFJ)V
L25:    return
L26:    
    .end code
.end method

.method static native nglViewportIndexedfv : (IJJ)V
.end method

.method static native nglProgramUniform4ui : (IIIIIIJ)V
.end method

.method static native nglProgramUniform4i : (IIIIIIJ)V
.end method

.method public static method4475 : (ILjava/nio/DoubleBuffer;)V
    .code stack 5 locals 4
L0:     invokestatic Method org/lwjgl/opengl/GLContext method4611 ()Lorg/lwjgl/opengl/kb;
L3:     getfield Field org/lwjgl/opengl/kb oP J
L6:     dup2
L7:     lstore_2
L8:     invokestatic Method org/lwjgl/l method2052 (J)V
L11:    iload_0
L12:    aload_1
L13:    iconst_2
L14:    iconst_1
L15:    dup
L16:    pop2
L17:    invokestatic Method org/lwjgl/l method2056 (Ljava/nio/DoubleBuffer;I)V
L20:    aload_1
L21:    invokestatic Method org/lwjgl/MemoryUtil method1840 (Ljava/nio/DoubleBuffer;)J
L24:    lload_2
L25:    invokestatic Method org/lwjgl/opengl/GL41 nglVertexAttribL2dv (IJJ)V
L28:    return
L29:    
    .end code
.end method

.method public static method4476 : (IDD)V
    .code stack 7 locals 7
L0:     invokestatic Method org/lwjgl/opengl/GLContext method4611 ()Lorg/lwjgl/opengl/kb;
L3:     getfield Field org/lwjgl/opengl/kb lI J
L6:     dup2
L7:     lstore 5
L9:     invokestatic Method org/lwjgl/l method2052 (J)V
L12:    iload_0
L13:    dload_1
L14:    dload_3
L15:    lload 5
L17:    invokestatic Method org/lwjgl/opengl/GL41 nglDepthRangeIndexed (IDDJ)V
L20:    return
L21:    
    .end code
.end method

.method public static method4477 : (IIZLjava/nio/FloatBuffer;)V
    .code stack 8 locals 6
L0:     invokestatic Method org/lwjgl/opengl/GLContext method4611 ()Lorg/lwjgl/opengl/kb;
L3:     getfield Field org/lwjgl/opengl/kb hC J
L6:     dup2
L7:     lstore 4
L9:     invokestatic Method org/lwjgl/l method2052 (J)V
L12:    iload_0
L13:    aload_3
L14:    invokestatic Method org/lwjgl/l method2048 (Ljava/nio/FloatBuffer;)V
L17:    iload_1
L18:    aload_3
L19:    invokevirtual Method java/nio/FloatBuffer remaining ()I
L22:    bipush 6
L24:    iconst_1
L25:    dup
L26:    pop2
L27:    idiv
L28:    iload_2
L29:    aload_3
L30:    invokestatic Method org/lwjgl/MemoryUtil method1878 (Ljava/nio/FloatBuffer;)J
L33:    lload 4
L35:    invokestatic Method org/lwjgl/opengl/GL41 nglProgramUniformMatrix2x3fv (IIIZJJ)V
L38:    return
L39:    
    .end code
.end method

.method public static method4478 : (Ljava/nio/IntBuffer;ILjava/nio/ByteBuffer;)V
    .code stack 9 locals 5
L0:     invokestatic Method org/lwjgl/opengl/GLContext method4611 ()Lorg/lwjgl/opengl/kb;
L3:     getfield Field org/lwjgl/opengl/kb bH J
L6:     dup2
L7:     lstore_3
L8:     invokestatic Method org/lwjgl/l method2052 (J)V
L11:    aload_2
L12:    aload_0
L13:    dup_x1
L14:    invokestatic Method org/lwjgl/l method2043 (Ljava/nio/IntBuffer;)V
L17:    invokestatic Method org/lwjgl/l method2034 (Ljava/nio/ByteBuffer;)V
L20:    invokevirtual Method java/nio/IntBuffer remaining ()I
L23:    aload_0
L24:    invokestatic Method org/lwjgl/MemoryUtil method1884 (Ljava/nio/IntBuffer;)J
L27:    iload_1
L28:    aload_2
L29:    invokestatic Method org/lwjgl/MemoryUtil method1873 (Ljava/nio/ByteBuffer;)J
L32:    aload_2
L33:    invokevirtual Method java/nio/ByteBuffer remaining ()I
L36:    lload_3
L37:    invokestatic Method org/lwjgl/opengl/GL41 nglShaderBinary (IJIJIJ)V
L40:    return
L41:    
    .end code
.end method

.method static native nglGenProgramPipelines : (IJJ)V
.end method

.method public static method4479 : (I)V
    .code stack 4 locals 3
L0:     invokestatic Method org/lwjgl/opengl/GLContext method4611 ()Lorg/lwjgl/opengl/kb;
L3:     getfield Field org/lwjgl/opengl/kb ge J
L6:     dup2
L7:     lstore_1
L8:     invokestatic Method org/lwjgl/l method2052 (J)V
L11:    iload_0
L12:    lload_1
L13:    invokestatic Method org/lwjgl/opengl/GL41 nglBindProgramPipeline (IJ)V
L16:    return
L17:    
    .end code
.end method

.method private <init> : ()V
    .code stack 1 locals 1
L0:     aload_0
L1:     invokespecial Method java/lang/Object <init> ()V
L4:     return
L5:     
    .end code
.end method

.method public static method4480 : (IILjava/nio/FloatBuffer;)V
    .code stack 7 locals 5
L0:     invokestatic Method org/lwjgl/opengl/GLContext method4611 ()Lorg/lwjgl/opengl/kb;
L3:     getfield Field org/lwjgl/opengl/kb RO J
L6:     dup2
L7:     lstore_3
L8:     invokestatic Method org/lwjgl/l method2052 (J)V
L11:    iload_0
L12:    aload_2
L13:    invokestatic Method org/lwjgl/l method2048 (Ljava/nio/FloatBuffer;)V
L16:    iload_1
L17:    aload_2
L18:    invokevirtual Method java/nio/FloatBuffer remaining ()I
L21:    iconst_2
L22:    iconst_1
L23:    dup
L24:    pop2
L25:    ishr
L26:    aload_2
L27:    invokestatic Method org/lwjgl/MemoryUtil method1878 (Ljava/nio/FloatBuffer;)J
L30:    lload_3
L31:    invokestatic Method org/lwjgl/opengl/GL41 nglProgramUniform4fv (IIIJJ)V
L34:    return
L35:    
    .end code
.end method

.method static native nglProgramUniform4iv : (IIIJJ)V
.end method

.method public static method4481 : (IILjava/nio/IntBuffer;)V
    .code stack 7 locals 5
L0:     invokestatic Method org/lwjgl/opengl/GLContext method4611 ()Lorg/lwjgl/opengl/kb;
L3:     getfield Field org/lwjgl/opengl/kb sS J
L6:     dup2
L7:     lstore_3
L8:     invokestatic Method org/lwjgl/l method2052 (J)V
L11:    iload_0
L12:    aload_2
L13:    invokestatic Method org/lwjgl/l method2043 (Ljava/nio/IntBuffer;)V
L16:    iload_1
L17:    aload_2
L18:    invokevirtual Method java/nio/IntBuffer remaining ()I
L21:    iconst_3
L22:    iconst_1
L23:    dup
L24:    pop2
L25:    idiv
L26:    aload_2
L27:    invokestatic Method org/lwjgl/MemoryUtil method1884 (Ljava/nio/IntBuffer;)J
L30:    lload_3
L31:    invokestatic Method org/lwjgl/opengl/GL41 nglProgramUniform3uiv (IIIJJ)V
L34:    return
L35:    
    .end code
.end method

.method public static method4482 : (III)V
    .code stack 5 locals 5
L0:     invokestatic Method org/lwjgl/opengl/GLContext method4611 ()Lorg/lwjgl/opengl/kb;
L3:     getfield Field org/lwjgl/opengl/kb Fs J
L6:     dup2
L7:     lstore_3
L8:     invokestatic Method org/lwjgl/l method2052 (J)V
L11:    iload_0
L12:    iload_1
L13:    iload_2
L14:    lload_3
L15:    invokestatic Method org/lwjgl/opengl/GL41 nglProgramUniform1ui (IIIJ)V
L18:    return
L19:    
    .end code
.end method

.method public static method4483 : (IILjava/nio/FloatBuffer;)V
    .code stack 7 locals 5
L0:     invokestatic Method org/lwjgl/opengl/GLContext method4611 ()Lorg/lwjgl/opengl/kb;
L3:     getfield Field org/lwjgl/opengl/kb RK J
L6:     dup2
L7:     lstore_3
L8:     invokestatic Method org/lwjgl/l method2052 (J)V
L11:    iload_0
L12:    aload_2
L13:    invokestatic Method org/lwjgl/l method2048 (Ljava/nio/FloatBuffer;)V
L16:    iload_1
L17:    aload_2
L18:    invokevirtual Method java/nio/FloatBuffer remaining ()I
L21:    iconst_3
L22:    iconst_1
L23:    dup
L24:    pop2
L25:    idiv
L26:    aload_2
L27:    invokestatic Method org/lwjgl/MemoryUtil method1878 (Ljava/nio/FloatBuffer;)J
L30:    lload_3
L31:    invokestatic Method org/lwjgl/opengl/GL41 nglProgramUniform3fv (IIIJJ)V
L34:    return
L35:    
    .end code
.end method

.method static native nglCreateShaderProgramv : (IIJJ)I
.end method

.method public static method4484 : (ILjava/nio/FloatBuffer;)V
    .code stack 5 locals 4
L0:     invokestatic Method org/lwjgl/opengl/GLContext method4611 ()Lorg/lwjgl/opengl/kb;
L3:     getfield Field org/lwjgl/opengl/kb Ue J
L6:     dup2
L7:     lstore_2
L8:     invokestatic Method org/lwjgl/l method2052 (J)V
L11:    iload_0
L12:    aload_1
L13:    iconst_4
L14:    iconst_1
L15:    dup
L16:    pop2
L17:    invokestatic Method org/lwjgl/l method2044 (Ljava/nio/FloatBuffer;I)V
L20:    aload_1
L21:    invokestatic Method org/lwjgl/MemoryUtil method1878 (Ljava/nio/FloatBuffer;)J
L24:    lload_2
L25:    invokestatic Method org/lwjgl/opengl/GL41 nglViewportIndexedfv (IJJ)V
L28:    return
L29:    
    .end code
.end method

.method static native nglDepthRangeIndexed : (IDDJ)V
.end method

.method public static method4485 : (II)I
    .code stack 6 locals 5
L0:     invokestatic Method org/lwjgl/opengl/GLContext method4611 ()Lorg/lwjgl/opengl/kb;
L3:     dup
L4:     getfield Field org/lwjgl/opengl/kb ae J
L7:     dup2
L8:     lstore_3
L9:     invokestatic Method org/lwjgl/l method2052 (J)V
L12:    invokestatic Method org/lwjgl/opengl/bB method5467 (Lorg/lwjgl/opengl/kb;)Ljava/nio/IntBuffer;
L15:    astore_2
L16:    iload_0
L17:    iload_1
L18:    aload_2
L19:    invokestatic Method org/lwjgl/MemoryUtil method1884 (Ljava/nio/IntBuffer;)J
L22:    lload_3
L23:    invokestatic Method org/lwjgl/opengl/GL41 nglGetProgramPipelineiv (IIJJ)V
L26:    aload_2
L27:    iconst_0
L28:    iconst_1
L29:    dup
L30:    pop2
L31:    invokevirtual Method java/nio/IntBuffer get (I)I
L34:    ireturn
L35:    
    .end code
.end method

.method static native nglProgramUniformMatrix3x2dv : (IIIZJJ)V
.end method

.method static native nglShaderBinary : (IJIJIJ)V
.end method

.method public static method4486 : (IIZLjava/nio/FloatBuffer;)V
    .code stack 8 locals 6
L0:     invokestatic Method org/lwjgl/opengl/GLContext method4611 ()Lorg/lwjgl/opengl/kb;
L3:     getfield Field org/lwjgl/opengl/kb Qr J
L6:     dup2
L7:     lstore 4
L9:     invokestatic Method org/lwjgl/l method2052 (J)V
L12:    iload_0
L13:    aload_3
L14:    invokestatic Method org/lwjgl/l method2048 (Ljava/nio/FloatBuffer;)V
L17:    iload_1
L18:    aload_3
L19:    invokevirtual Method java/nio/FloatBuffer remaining ()I
L22:    iconst_2
L23:    iconst_1
L24:    dup
L25:    pop2
L26:    ishr
L27:    iload_2
L28:    aload_3
L29:    invokestatic Method org/lwjgl/MemoryUtil method1878 (Ljava/nio/FloatBuffer;)J
L32:    lload 4
L34:    invokestatic Method org/lwjgl/opengl/GL41 nglProgramUniformMatrix2fv (IIIZJJ)V
L37:    return
L38:    
    .end code
.end method

.method public static method4487 : (IILjava/nio/ByteBuffer;)I
    .code stack 6 locals 5
L0:     invokestatic Method org/lwjgl/opengl/GLContext method4611 ()Lorg/lwjgl/opengl/kb;
L3:     getfield Field org/lwjgl/opengl/kb jH J
L6:     dup2
L7:     lstore_3
L8:     invokestatic Method org/lwjgl/l method2052 (J)V
L11:    iload_0
L12:    iload_1
L13:    aload_2
L14:    dup_x1
L15:    invokestatic Method org/lwjgl/l method2034 (Ljava/nio/ByteBuffer;)V
L18:    invokestatic Method org/lwjgl/l method2038 (Ljava/nio/ByteBuffer;I)V
L21:    iload_1
L22:    aload_2
L23:    invokestatic Method org/lwjgl/MemoryUtil method1873 (Ljava/nio/ByteBuffer;)J
L26:    lload_3
L27:    invokestatic Method org/lwjgl/opengl/GL41 nglCreateShaderProgramv2 (IIJJ)I
L30:    ireturn
L31:    
    .end code
.end method

.method static native nglVertexAttribL3dv : (IJJ)V
.end method

.method public static method4488 : (ILjava/nio/DoubleBuffer;)V
    .code stack 5 locals 4
L0:     invokestatic Method org/lwjgl/opengl/GLContext method4611 ()Lorg/lwjgl/opengl/kb;
L3:     getfield Field org/lwjgl/opengl/kb KD J
L6:     dup2
L7:     lstore_2
L8:     invokestatic Method org/lwjgl/l method2052 (J)V
L11:    iload_0
L12:    aload_1
L13:    iconst_3
L14:    iconst_1
L15:    dup
L16:    pop2
L17:    invokestatic Method org/lwjgl/l method2056 (Ljava/nio/DoubleBuffer;I)V
L20:    aload_1
L21:    invokestatic Method org/lwjgl/MemoryUtil method1840 (Ljava/nio/DoubleBuffer;)J
L24:    lload_2
L25:    invokestatic Method org/lwjgl/opengl/GL41 nglVertexAttribL3dv (IJJ)V
L28:    return
L29:    
    .end code
.end method

.method public static method4489 : (IID)V
    .code stack 6 locals 6
L0:     invokestatic Method org/lwjgl/opengl/GLContext method4611 ()Lorg/lwjgl/opengl/kb;
L3:     getfield Field org/lwjgl/opengl/kb HF J
L6:     dup2
L7:     lstore 4
L9:     invokestatic Method org/lwjgl/l method2052 (J)V
L12:    iload_0
L13:    iload_1
L14:    dload_2
L15:    lload 4
L17:    invokestatic Method org/lwjgl/opengl/GL41 nglProgramUniform1d (IIDJ)V
L20:    return
L21:    
    .end code
.end method

.method public static method4490 : (ILjava/nio/DoubleBuffer;)V
    .code stack 5 locals 4
L0:     invokestatic Method org/lwjgl/opengl/GLContext method4611 ()Lorg/lwjgl/opengl/kb;
L3:     getfield Field org/lwjgl/opengl/kb dJ J
L6:     dup2
L7:     lstore_2
L8:     invokestatic Method org/lwjgl/l method2052 (J)V
L11:    iload_0
L12:    aload_1
L13:    iconst_4
L14:    iconst_1
L15:    dup
L16:    pop2
L17:    invokestatic Method org/lwjgl/l method2056 (Ljava/nio/DoubleBuffer;I)V
L20:    aload_1
L21:    invokestatic Method org/lwjgl/MemoryUtil method1840 (Ljava/nio/DoubleBuffer;)J
L24:    lload_2
L25:    invokestatic Method org/lwjgl/opengl/GL41 nglVertexAttribL4dv (IJJ)V
L28:    return
L29:    
    .end code
.end method

.method public static method4491 : (IILjava/nio/DoubleBuffer;)V
    .code stack 7 locals 5
L0:     invokestatic Method org/lwjgl/opengl/GLContext method4611 ()Lorg/lwjgl/opengl/kb;
L3:     getfield Field org/lwjgl/opengl/kb tp J
L6:     dup2
L7:     lstore_3
L8:     invokestatic Method org/lwjgl/l method2052 (J)V
L11:    iload_0
L12:    aload_2
L13:    invokestatic Method org/lwjgl/l method2036 (Ljava/nio/DoubleBuffer;)V
L16:    iload_1
L17:    aload_2
L18:    invokevirtual Method java/nio/DoubleBuffer remaining ()I
L21:    iconst_2
L22:    iconst_1
L23:    dup
L24:    pop2
L25:    ishr
L26:    aload_2
L27:    invokestatic Method org/lwjgl/MemoryUtil method1840 (Ljava/nio/DoubleBuffer;)J
L30:    lload_3
L31:    invokestatic Method org/lwjgl/opengl/GL41 nglProgramUniform4dv (IIIJJ)V
L34:    return
L35:    
    .end code
.end method

.method public static method4492 : (IIZLjava/nio/FloatBuffer;)V
    .code stack 8 locals 6
L0:     invokestatic Method org/lwjgl/opengl/GLContext method4611 ()Lorg/lwjgl/opengl/kb;
L3:     getfield Field org/lwjgl/opengl/kb Eu J
L6:     dup2
L7:     lstore 4
L9:     invokestatic Method org/lwjgl/l method2052 (J)V
L12:    iload_0
L13:    aload_3
L14:    invokestatic Method org/lwjgl/l method2048 (Ljava/nio/FloatBuffer;)V
L17:    iload_1
L18:    aload_3
L19:    invokevirtual Method java/nio/FloatBuffer remaining ()I
L22:    iconst_4
L23:    iconst_1
L24:    dup
L25:    pop2
L26:    ishr
L27:    iload_2
L28:    aload_3
L29:    invokestatic Method org/lwjgl/MemoryUtil method1878 (Ljava/nio/FloatBuffer;)J
L32:    lload 4
L34:    invokestatic Method org/lwjgl/opengl/GL41 nglProgramUniformMatrix4fv (IIIZJJ)V
L37:    return
L38:    
    .end code
.end method

.method public static method4493 : (Ljava/nio/IntBuffer;)V
    .code stack 5 locals 3
L0:     invokestatic Method org/lwjgl/opengl/GLContext method4611 ()Lorg/lwjgl/opengl/kb;
L3:     getfield Field org/lwjgl/opengl/kb Of J
L6:     dup2
L7:     lstore_1
L8:     invokestatic Method org/lwjgl/l method2052 (J)V
L11:    aload_0
L12:    dup
L13:    invokestatic Method org/lwjgl/l method2043 (Ljava/nio/IntBuffer;)V
L16:    invokevirtual Method java/nio/IntBuffer remaining ()I
L19:    aload_0
L20:    invokestatic Method org/lwjgl/MemoryUtil method1884 (Ljava/nio/IntBuffer;)J
L23:    lload_1
L24:    invokestatic Method org/lwjgl/opengl/GL41 nglDeleteProgramPipelines (IJJ)V
L27:    return
L28:    
    .end code
.end method

.method static native nglProgramUniform2d : (IIDDJ)V
.end method

.method public static method4494 : (IIZLjava/nio/DoubleBuffer;)V
    .code stack 8 locals 6
L0:     invokestatic Method org/lwjgl/opengl/GLContext method4611 ()Lorg/lwjgl/opengl/kb;
L3:     getfield Field org/lwjgl/opengl/kb bL J
L6:     dup2
L7:     lstore 4
L9:     invokestatic Method org/lwjgl/l method2052 (J)V
L12:    iload_0
L13:    aload_3
L14:    invokestatic Method org/lwjgl/l method2036 (Ljava/nio/DoubleBuffer;)V
L17:    iload_1
L18:    aload_3
L19:    invokevirtual Method java/nio/DoubleBuffer remaining ()I
L22:    bipush 6
L24:    iconst_1
L25:    dup
L26:    pop2
L27:    idiv
L28:    iload_2
L29:    aload_3
L30:    invokestatic Method org/lwjgl/MemoryUtil method1840 (Ljava/nio/DoubleBuffer;)J
L33:    lload 4
L35:    invokestatic Method org/lwjgl/opengl/GL41 nglProgramUniformMatrix2x3dv (IIIZJJ)V
L38:    return
L39:    
    .end code
.end method

.method static native nglProgramUniformMatrix3x2fv : (IIIZJJ)V
.end method

.method static native nglIsProgramPipeline : (IJ)Z
.end method

.method public static method4495 : (IIIIII)V
    .code stack 8 locals 8
L0:     invokestatic Method org/lwjgl/opengl/GLContext method4611 ()Lorg/lwjgl/opengl/kb;
L3:     getfield Field org/lwjgl/opengl/kb xQ J
L6:     dup2
L7:     lstore 6
L9:     invokestatic Method org/lwjgl/l method2052 (J)V
L12:    iload_0
L13:    iload_1
L14:    iload_2
L15:    iload_3
L16:    iload 4
L18:    iload 5
L20:    lload 6
L22:    invokestatic Method org/lwjgl/opengl/GL41 nglProgramUniform4ui (IIIIIIJ)V
L25:    return
L26:    
    .end code
.end method

.method public static method4496 : (IIII)V
    .code stack 6 locals 6
L0:     invokestatic Method org/lwjgl/opengl/GLContext method4611 ()Lorg/lwjgl/opengl/kb;
L3:     getfield Field org/lwjgl/opengl/kb el J
L6:     dup2
L7:     lstore 4
L9:     invokestatic Method org/lwjgl/l method2052 (J)V
L12:    iload_0
L13:    iload_1
L14:    iload_2
L15:    iload_3
L16:    lload 4
L18:    invokestatic Method org/lwjgl/opengl/GL41 nglProgramUniform2ui (IIIIJ)V
L21:    return
L22:    
    .end code
.end method

.method static native nglViewportIndexedf : (IFFFFJ)V
.end method

.method static native nglProgramUniformMatrix4fv : (IIIZJJ)V
.end method

.method public static method4497 : (IIZLjava/nio/DoubleBuffer;)V
    .code stack 8 locals 6
L0:     invokestatic Method org/lwjgl/opengl/GLContext method4611 ()Lorg/lwjgl/opengl/kb;
L3:     getfield Field org/lwjgl/opengl/kb Gs J
L6:     dup2
L7:     lstore 4
L9:     invokestatic Method org/lwjgl/l method2052 (J)V
L12:    iload_0
L13:    aload_3
L14:    invokestatic Method org/lwjgl/l method2036 (Ljava/nio/DoubleBuffer;)V
L17:    iload_1
L18:    aload_3
L19:    invokevirtual Method java/nio/DoubleBuffer remaining ()I
L22:    iconst_2
L23:    iconst_1
L24:    dup
L25:    pop2
L26:    ishr
L27:    iload_2
L28:    aload_3
L29:    invokestatic Method org/lwjgl/MemoryUtil method1840 (Ljava/nio/DoubleBuffer;)J
L32:    lload 4
L34:    invokestatic Method org/lwjgl/opengl/GL41 nglProgramUniformMatrix2dv (IIIZJJ)V
L37:    return
L38:    
    .end code
.end method

.method static native nglDepthRangeArrayv : (IIJJ)V
.end method

.method static native nglBindProgramPipeline : (IJ)V
.end method

.method static native nglProgramUniform4fv : (IIIJJ)V
.end method

.method public static method4498 : (IIZLjava/nio/DoubleBuffer;)V
    .code stack 8 locals 6
L0:     invokestatic Method org/lwjgl/opengl/GLContext method4611 ()Lorg/lwjgl/opengl/kb;
L3:     getfield Field org/lwjgl/opengl/kb SB J
L6:     dup2
L7:     lstore 4
L9:     invokestatic Method org/lwjgl/l method2052 (J)V
L12:    iload_0
L13:    aload_3
L14:    invokestatic Method org/lwjgl/l method2036 (Ljava/nio/DoubleBuffer;)V
L17:    iload_1
L18:    aload_3
L19:    invokevirtual Method java/nio/DoubleBuffer remaining ()I
L22:    iconst_3
L23:    iconst_1
L24:    dup
L25:    pop2
L26:    ishr
L27:    iload_2
L28:    aload_3
L29:    invokestatic Method org/lwjgl/MemoryUtil method1840 (Ljava/nio/DoubleBuffer;)J
L32:    lload 4
L34:    invokestatic Method org/lwjgl/opengl/GL41 nglProgramUniformMatrix4x2dv (IIIZJJ)V
L37:    return
L38:    
    .end code
.end method

.method static native nglProgramUniformMatrix2dv : (IIIZJJ)V
.end method

.method static native nglProgramUniform4dv : (IIIJJ)V
.end method

.method public static method4499 : (I[Ljava/lang/CharSequence;)I
    .code stack 6 locals 5
L0:     invokestatic Method org/lwjgl/opengl/GLContext method4611 ()Lorg/lwjgl/opengl/kb;
L3:     astore_2
L4:     aload_1
L5:     aload_2
L6:     getfield Field org/lwjgl/opengl/kb jH J
L9:     dup2
L10:    lstore_3
L11:    invokestatic Method org/lwjgl/l method2052 (J)V
L14:    invokestatic Method org/lwjgl/l method2042 ([Ljava/lang/Object;)V
L17:    iload_0
L18:    aload_1
L19:    arraylength
L20:    aload_2
L21:    aload_1
L22:    invokestatic Method org/lwjgl/opengl/bB method5466 (Lorg/lwjgl/opengl/kb;[Ljava/lang/CharSequence;)J
L25:    lload_3
L26:    invokestatic Method org/lwjgl/opengl/GL41 nglCreateShaderProgramv2 (IIJJ)I
L29:    ireturn
L30:    
    .end code
.end method

.method static native nglProgramUniform2iv : (IIIJJ)V
.end method

.method static native nglProgramUniform4d : (IIDDDDJ)V
.end method

.method static native nglProgramUniform2dv : (IIIJJ)V
.end method

.method static native nglProgramUniformMatrix4x3dv : (IIIZJJ)V
.end method

.method public static method4500 : (IDDD)V
    .code stack 9 locals 9
L0:     invokestatic Method org/lwjgl/opengl/GLContext method4611 ()Lorg/lwjgl/opengl/kb;
L3:     getfield Field org/lwjgl/opengl/kb Ri J
L6:     dup2
L7:     lstore 7
L9:     invokestatic Method org/lwjgl/l method2052 (J)V
L12:    iload_0
L13:    dload_1
L14:    dload_3
L15:    dload 5
L17:    lload 7
L19:    invokestatic Method org/lwjgl/opengl/GL41 nglVertexAttribL3d (IDDDJ)V
L22:    return
L23:    
    .end code
.end method

.method public static method4501 : (IILjava/nio/DoubleBuffer;)V
    .code stack 7 locals 5
L0:     invokestatic Method org/lwjgl/opengl/GLContext method4611 ()Lorg/lwjgl/opengl/kb;
L3:     getfield Field org/lwjgl/opengl/kb Cl J
L6:     dup2
L7:     lstore_3
L8:     invokestatic Method org/lwjgl/l method2052 (J)V
L11:    iload_0
L12:    aload_2
L13:    invokestatic Method org/lwjgl/l method2036 (Ljava/nio/DoubleBuffer;)V
L16:    iload_1
L17:    aload_2
L18:    invokevirtual Method java/nio/DoubleBuffer remaining ()I
L21:    aload_2
L22:    invokestatic Method org/lwjgl/MemoryUtil method1840 (Ljava/nio/DoubleBuffer;)J
L25:    lload_3
L26:    invokestatic Method org/lwjgl/opengl/GL41 nglProgramUniform1dv (IIIJJ)V
L29:    return
L30:    
    .end code
.end method

.method static native nglProgramUniform2uiv : (IIIJJ)V
.end method

.method public static method4502 : (II)D
    .code stack 6 locals 5
L0:     invokestatic Method org/lwjgl/opengl/GLContext method4611 ()Lorg/lwjgl/opengl/kb;
L3:     dup
L4:     getfield Field org/lwjgl/opengl/kb vh J
L7:     dup2
L8:     lstore_3
L9:     invokestatic Method org/lwjgl/l method2052 (J)V
L12:    invokestatic Method org/lwjgl/opengl/bB method5474 (Lorg/lwjgl/opengl/kb;)Ljava/nio/DoubleBuffer;
L15:    astore_2
L16:    iload_0
L17:    iload_1
L18:    aload_2
L19:    invokestatic Method org/lwjgl/MemoryUtil method1840 (Ljava/nio/DoubleBuffer;)J
L22:    lload_3
L23:    invokestatic Method org/lwjgl/opengl/GL41 nglGetDoublei_v (IIJJ)V
L26:    aload_2
L27:    iconst_0
L28:    iconst_1
L29:    dup
L30:    pop2
L31:    invokevirtual Method java/nio/DoubleBuffer get (I)D
L34:    dreturn
L35:    
    .end code
.end method

.method public static method4503 : (IILjava/nio/IntBuffer;Ljava/nio/IntBuffer;)V
    .code stack 8 locals 6
L0:     invokestatic Method org/lwjgl/opengl/GLContext method4611 ()Lorg/lwjgl/opengl/kb;
L3:     getfield Field org/lwjgl/opengl/kb Yu J
L6:     dup2
L7:     lstore 4
L9:     invokestatic Method org/lwjgl/l method2052 (J)V
L12:    iload_0
L13:    aload_3
L14:    aload_2
L15:    iconst_2
L16:    iconst_1
L17:    dup_x2
L18:    dup
L19:    pop2
L20:    invokestatic Method org/lwjgl/l method2041 (Ljava/nio/IntBuffer;I)V
L23:    iconst_1
L24:    dup
L25:    pop2
L26:    invokestatic Method org/lwjgl/l method2041 (Ljava/nio/IntBuffer;I)V
L29:    iload_1
L30:    aload_2
L31:    invokestatic Method org/lwjgl/MemoryUtil method1884 (Ljava/nio/IntBuffer;)J
L34:    aload_3
L35:    invokestatic Method org/lwjgl/MemoryUtil method1884 (Ljava/nio/IntBuffer;)J
L38:    lload 4
L40:    invokestatic Method org/lwjgl/opengl/GL41 nglGetShaderPrecisionFormat (IIJJJ)V
L43:    return
L44:    
    .end code
.end method

.method public static method4504 : (IIIII)V
    .code stack 7 locals 7
L0:     invokestatic Method org/lwjgl/opengl/GLContext method4611 ()Lorg/lwjgl/opengl/kb;
L3:     getfield Field org/lwjgl/opengl/kb qQ J
L6:     dup2
L7:     lstore 5
L9:     invokestatic Method org/lwjgl/l method2052 (J)V
L12:    iload_0
L13:    iload_1
L14:    iload_2
L15:    iload_3
L16:    iload 4
L18:    lload 5
L20:    invokestatic Method org/lwjgl/opengl/GL41 nglProgramUniform3ui (IIIIIJ)V
L23:    return
L24:    
    .end code
.end method

.method static native nglProgramUniformMatrix2x3fv : (IIIZJJ)V
.end method

.method static native nglProgramUniformMatrix3fv : (IIIZJJ)V
.end method

.method public static method4505 : (IDD)V
    .code stack 7 locals 7
L0:     invokestatic Method org/lwjgl/opengl/GLContext method4611 ()Lorg/lwjgl/opengl/kb;
L3:     getfield Field org/lwjgl/opengl/kb qJ J
L6:     dup2
L7:     lstore 5
L9:     invokestatic Method org/lwjgl/l method2052 (J)V
L12:    iload_0
L13:    dload_1
L14:    dload_3
L15:    lload 5
L17:    invokestatic Method org/lwjgl/opengl/GL41 nglVertexAttribL2d (IDDJ)V
L20:    return
L21:    
    .end code
.end method

.method public static method4506 : (ILjava/nio/IntBuffer;Ljava/nio/ByteBuffer;)V
    .code stack 8 locals 5
L0:     invokestatic Method org/lwjgl/opengl/GLContext method4611 ()Lorg/lwjgl/opengl/kb;
L3:     getfield Field org/lwjgl/opengl/kb Ds J
L6:     dup2
L7:     lstore_3
L8:     invokestatic Method org/lwjgl/l method2052 (J)V
L11:    aload_1
L12:    ifnull L23
L15:    aload_1
L16:    iconst_1
L17:    dup
L18:    dup
L19:    pop2
L20:    invokestatic Method org/lwjgl/l method2041 (Ljava/nio/IntBuffer;I)V
L23:    aload_2
L24:    invokestatic Method org/lwjgl/l method2034 (Ljava/nio/ByteBuffer;)V
L27:    iload_0
L28:    aload_2
L29:    invokevirtual Method java/nio/ByteBuffer remaining ()I
L32:    aload_1
L33:    invokestatic Method org/lwjgl/MemoryUtil method1865 (Ljava/nio/IntBuffer;)J
L36:    aload_2
L37:    invokestatic Method org/lwjgl/MemoryUtil method1873 (Ljava/nio/ByteBuffer;)J
L40:    lload_3
L41:    invokestatic Method org/lwjgl/opengl/GL41 nglGetProgramPipelineInfoLog (IIJJJ)V
L44:    return
L45:    
        .attribute StackMap b'\x00\x01\x00\x17\x00\x04\x01\x07\x00\x87\x07\x01\x22\x04\x00\x00'
    .end code
.end method

.method public static method4507 : (IIIIII)V
    .code stack 8 locals 8
L0:     invokestatic Method org/lwjgl/opengl/GLContext method4611 ()Lorg/lwjgl/opengl/kb;
L3:     getfield Field org/lwjgl/opengl/kb tt J
L6:     dup2
L7:     lstore 6
L9:     invokestatic Method org/lwjgl/l method2052 (J)V
L12:    iload_0
L13:    iload_1
L14:    iload_2
L15:    iload_3
L16:    iload 4
L18:    iload 5
L20:    lload 6
L22:    invokestatic Method org/lwjgl/opengl/GL41 nglProgramUniform4i (IIIIIIJ)V
L25:    return
L26:    
    .end code
.end method

.method static native nglProgramUniform3uiv : (IIIJJ)V
.end method

.method static native nglGetProgramPipelineInfoLog : (IIJJJ)V
.end method

.method public static method4508 : (IIZLjava/nio/FloatBuffer;)V
    .code stack 8 locals 6
L0:     invokestatic Method org/lwjgl/opengl/GLContext method4611 ()Lorg/lwjgl/opengl/kb;
L3:     getfield Field org/lwjgl/opengl/kb YH J
L6:     dup2
L7:     lstore 4
L9:     invokestatic Method org/lwjgl/l method2052 (J)V
L12:    iload_0
L13:    aload_3
L14:    invokestatic Method org/lwjgl/l method2048 (Ljava/nio/FloatBuffer;)V
L17:    iload_1
L18:    aload_3
L19:    invokevirtual Method java/nio/FloatBuffer remaining ()I
L22:    bipush 9
L24:    iconst_1
L25:    dup
L26:    pop2
L27:    idiv
L28:    iload_2
L29:    aload_3
L30:    invokestatic Method org/lwjgl/MemoryUtil method1878 (Ljava/nio/FloatBuffer;)J
L33:    lload 4
L35:    invokestatic Method org/lwjgl/opengl/GL41 nglProgramUniformMatrix3fv (IIIZJJ)V
L38:    return
L39:    
    .end code
.end method

.method static native nglProgramUniform1ui : (IIIJ)V
.end method

.method public static method4509 : (IIZLjava/nio/FloatBuffer;)V
    .code stack 8 locals 6
L0:     invokestatic Method org/lwjgl/opengl/GLContext method4611 ()Lorg/lwjgl/opengl/kb;
L3:     getfield Field org/lwjgl/opengl/kb Ij J
L6:     dup2
L7:     lstore 4
L9:     invokestatic Method org/lwjgl/l method2052 (J)V
L12:    iload_0
L13:    aload_3
L14:    invokestatic Method org/lwjgl/l method2048 (Ljava/nio/FloatBuffer;)V
L17:    iload_1
L18:    aload_3
L19:    invokevirtual Method java/nio/FloatBuffer remaining ()I
L22:    bipush 12
L24:    iconst_1
L25:    dup
L26:    pop2
L27:    idiv
L28:    iload_2
L29:    aload_3
L30:    invokestatic Method org/lwjgl/MemoryUtil method1878 (Ljava/nio/FloatBuffer;)J
L33:    lload 4
L35:    invokestatic Method org/lwjgl/opengl/GL41 nglProgramUniformMatrix4x3fv (IIIZJJ)V
L38:    return
L39:    
    .end code
.end method

.method public static method4510 : (IIDDD)V
    .code stack 10 locals 10
L0:     invokestatic Method org/lwjgl/opengl/GLContext method4611 ()Lorg/lwjgl/opengl/kb;
L3:     getfield Field org/lwjgl/opengl/kb zN J
L6:     dup2
L7:     lstore 8
L9:     invokestatic Method org/lwjgl/l method2052 (J)V
L12:    iload_0
L13:    iload_1
L14:    dload_2
L15:    dload 4
L17:    dload 6
L19:    lload 8
L21:    invokestatic Method org/lwjgl/opengl/GL41 nglProgramUniform3d (IIDDDJ)V
L24:    return
L25:    
    .end code
.end method

.method static native nglProgramUniform3i : (IIIIIJ)V
.end method

.method static native nglGetProgramPipelineiv : (IIJJ)V
.end method

.method public static method4511 : (IIZLjava/nio/FloatBuffer;)V
    .code stack 8 locals 6
L0:     invokestatic Method org/lwjgl/opengl/GLContext method4611 ()Lorg/lwjgl/opengl/kb;
L3:     getfield Field org/lwjgl/opengl/kb W J
L6:     dup2
L7:     lstore 4
L9:     invokestatic Method org/lwjgl/l method2052 (J)V
L12:    iload_0
L13:    aload_3
L14:    invokestatic Method org/lwjgl/l method2048 (Ljava/nio/FloatBuffer;)V
L17:    iload_1
L18:    aload_3
L19:    invokevirtual Method java/nio/FloatBuffer remaining ()I
L22:    bipush 6
L24:    iconst_1
L25:    dup
L26:    pop2
L27:    idiv
L28:    iload_2
L29:    aload_3
L30:    invokestatic Method org/lwjgl/MemoryUtil method1878 (Ljava/nio/FloatBuffer;)J
L33:    lload 4
L35:    invokestatic Method org/lwjgl/opengl/GL41 nglProgramUniformMatrix3x2fv (IIIZJJ)V
L38:    return
L39:    
    .end code
.end method

.method static native nglProgramUniform3fv : (IIIJJ)V
.end method

.method static native nglValidateProgramPipeline : (IJ)V
.end method

.method public static method4512 : (IIFF)V
    .code stack 6 locals 6
L0:     invokestatic Method org/lwjgl/opengl/GLContext method4611 ()Lorg/lwjgl/opengl/kb;
L3:     getfield Field org/lwjgl/opengl/kb Jh J
L6:     dup2
L7:     lstore 4
L9:     invokestatic Method org/lwjgl/l method2052 (J)V
L12:    iload_0
L13:    iload_1
L14:    fload_2
L15:    fload_3
L16:    lload 4
L18:    invokestatic Method org/lwjgl/opengl/GL41 nglProgramUniform2f (IIFFJ)V
L21:    return
L22:    
    .end code
.end method

.method public static method4513 : (IIII)V
    .code stack 6 locals 6
L0:     invokestatic Method org/lwjgl/opengl/GLContext method4611 ()Lorg/lwjgl/opengl/kb;
L3:     getfield Field org/lwjgl/opengl/kb sd J
L6:     dup2
L7:     lstore 4
L9:     invokestatic Method org/lwjgl/l method2052 (J)V
L12:    iload_0
L13:    iload_1
L14:    iload_2
L15:    iload_3
L16:    lload 4
L18:    invokestatic Method org/lwjgl/opengl/GL41 nglProgramUniform2i (IIIIJ)V
L21:    return
L22:    
    .end code
.end method

.method static native nglVertexAttribL1dv : (IJJ)V
.end method

.method public static method4514 : (II)V
    .code stack 4 locals 4
L0:     invokestatic Method org/lwjgl/opengl/GLContext method4611 ()Lorg/lwjgl/opengl/kb;
L3:     getfield Field org/lwjgl/opengl/kb vP J
L6:     dup2
L7:     lstore_2
L8:     invokestatic Method org/lwjgl/l method2052 (J)V
L11:    iload_0
L12:    iload_1
L13:    lload_2
L14:    invokestatic Method org/lwjgl/opengl/GL41 nglActiveShaderProgram (IIJ)V
L17:    return
L18:    
    .end code
.end method

.method static native nglVertexAttribLPointerBO : (IIIIJJ)V
.end method

.method static native nglProgramParameteri : (IIIJ)V
.end method

.method public static method4515 : (III)V
    .code stack 5 locals 5
L0:     invokestatic Method org/lwjgl/opengl/GLContext method4611 ()Lorg/lwjgl/opengl/kb;
L3:     getfield Field org/lwjgl/opengl/kb rR J
L6:     dup2
L7:     lstore_3
L8:     invokestatic Method org/lwjgl/l method2052 (J)V
L11:    iload_0
L12:    iload_1
L13:    iload_2
L14:    lload_3
L15:    invokestatic Method org/lwjgl/opengl/GL41 nglProgramParameteri (IIIJ)V
L18:    return
L19:    
    .end code
.end method

.method public static method4516 : (IIZLjava/nio/FloatBuffer;)V
    .code stack 8 locals 6
L0:     invokestatic Method org/lwjgl/opengl/GLContext method4611 ()Lorg/lwjgl/opengl/kb;
L3:     getfield Field org/lwjgl/opengl/kb Uj J
L6:     dup2
L7:     lstore 4
L9:     invokestatic Method org/lwjgl/l method2052 (J)V
L12:    iload_0
L13:    aload_3
L14:    invokestatic Method org/lwjgl/l method2048 (Ljava/nio/FloatBuffer;)V
L17:    iload_1
L18:    aload_3
L19:    invokevirtual Method java/nio/FloatBuffer remaining ()I
L22:    bipush 12
L24:    iconst_1
L25:    dup
L26:    pop2
L27:    idiv
L28:    iload_2
L29:    aload_3
L30:    invokestatic Method org/lwjgl/MemoryUtil method1878 (Ljava/nio/FloatBuffer;)J
L33:    lload 4
L35:    invokestatic Method org/lwjgl/opengl/GL41 nglProgramUniformMatrix3x4fv (IIIZJJ)V
L38:    return
L39:    
    .end code
.end method

.method public static method4517 : (FF)V
    .code stack 4 locals 4
L0:     invokestatic Method org/lwjgl/opengl/GLContext method4611 ()Lorg/lwjgl/opengl/kb;
L3:     getfield Field org/lwjgl/opengl/kb pd J
L6:     dup2
L7:     lstore_2
L8:     invokestatic Method org/lwjgl/l method2052 (J)V
L11:    fload_0
L12:    fload_1
L13:    lload_2
L14:    invokestatic Method org/lwjgl/opengl/GL41 nglDepthRangef (FFJ)V
L17:    return
L18:    
    .end code
.end method

.method public static method4518 : (ILjava/nio/DoubleBuffer;)V
    .code stack 5 locals 4
L0:     invokestatic Method org/lwjgl/opengl/GLContext method4611 ()Lorg/lwjgl/opengl/kb;
L3:     getfield Field org/lwjgl/opengl/kb tr J
L6:     dup2
L7:     lstore_2
L8:     invokestatic Method org/lwjgl/l method2052 (J)V
L11:    iload_0
L12:    aload_1
L13:    iconst_1
L14:    dup
L15:    dup
L16:    pop2
L17:    invokestatic Method org/lwjgl/l method2056 (Ljava/nio/DoubleBuffer;I)V
L20:    aload_1
L21:    invokestatic Method org/lwjgl/MemoryUtil method1840 (Ljava/nio/DoubleBuffer;)J
L24:    lload_2
L25:    invokestatic Method org/lwjgl/opengl/GL41 nglVertexAttribL1dv (IJJ)V
L28:    return
L29:    
    .end code
.end method
.end class
