.version 49 0
.class public final super org/lwjgl/opengl/GL43
.super java/lang/Object
.field public static final Fb I = 33489
.field public static final bd I = 33470
.field public static final tC I = 32937
.field public static final gc I = 37760
.field public static final oB I = 33463
.field public static final Wc I = 37623
.field public static final aB I = 33455
.field public static final IC I = 33459
.field public static final Zb I = 33350
.field public static final DA I = 1283
.field public static final Jd I = 33432
.field public static final WC I = 37080
.field public static final Fc I = 33403
.field public static final Ad I = 37649
.field public static final hc I = 37187
.field public static final xc I = 33400
.field public static final TB I = 33406
.field public static final SB I = 33391
.field public static final hB I = 33383
.field public static final Mc I = 37629
.field public static final rB I = 33449
.field public static final Sc I = 37611
.field public static final Lc I = 33471
.field public static final EA I = 33506
.field public static final cA I = 37101
.field public static final XA I = 33419
.field public static final jB I = 33356
.field public static final CC I = 33386
.field public static final Uc I = 33507
.field public static final Fd I = 33500
.field public static final MB I = 33409
.field public static final hb I = 37601
.field public static final sC I = 37098
.field public static final nd I = 37309
.field public static final Eb I = 37083
.field public static final Jc I = 33478
.field public static final gB I = 34037
.field public static final Ib I = 33420
.field public static final zB I = 33433
.field public static final NA I = 33511
.field public static final pB I = 37651
.field public static final ub I = 33443
.field public static final uC I = 37497
.field public static final Md I = 33349
.field public static final fC I = 33513
.field public static final PA I = 33482
.field public static final Tb I = 33437
.field public static final bA I = 33384
.field public static final IB I = 37310
.field public static final jC I = 33458
.field public static final ZC I = 37605
.field public static final cd I = 33379
.field public static final Id I = 37278
.field public static final RC I = 33418
.field public static final gb I = 33361
.field public static final vB I = 33448
.field public static final EC I = 37633
.field public static final Pc I = 32879
.field public static final Cb I = 37087
.field public static final yc I = 33427
.field public static final nc I = 33390
.field public static final iA I = 33464
.field public static final kc I = 33468
.field public static final KB I = 33397
.field public static final yC I = 37078
.field public static final Ed I = 33382
.field public static final Wb I = 33346
.field public static final qd I = 37630
.field public static final mB I = 33435
.field public static final Ab I = 33399
.field public static final Vb I = 37619
.field public static final OC I = 37607
.field public static final Bd I = 37610
.field public static final Dc I = 33476
.field public static final cC I = 37626
.field public static final Kd I = 37631
.field public static final IA I = 37652
.field public static final QC I = 33444
.field public static final VB I = 3553
.field public static final ab I = 35866
.field public static final hC I = 37082
.field public static final zb I = 33410
.field public static final Cc I = 37608
.field public static final AC I = 37644
.field public static final Od I = 33479
.field public static final dB I = 33429
.field public static final NC I = 37076
.field public static final Yb I = 37617
.field public static final Sd I = 37491
.field public static final hA I = 33425
.field public static final Db I = 33417
.field public static final NB I = 37081
.field public static final id I = 37635
.field public static final TC I = 33438
.field public static final kB I = 33439
.field public static final bC I = 33512
.field public static final xC I = 37612
.field public static final vc I = 37628
.field public static final kC I = 33497
.field public static final zC I = 37308
.field public static final kA I = 37621
.field public static final wc I = 33428
.field public static final od I = 33395
.field public static final oC I = 34067
.field public static final ZA I = 33355
.field public static final wA I = 33494
.field public static final aC I = 37640
.field public static final GB I = 33485
.field public static final cB I = 37099
.field public static final wB I = 37656
.field public static final Ld I = 33488
.field public static final HC I = 37305
.field public static final oc I = 33469
.field public static final zA I = 37192
.field public static final lc I = 33493
.field public static final ed I = 37641
.field public static final Xb I = 36201
.field public static final Ac I = 33416
.field public static final iC I = 33402
.field public static final uc I = 34638
.field public static final FC I = 37614
.field public static final WB I = 37636
.field public static final cc I = 37103
.field public static final eB I = 33457
.field public static final Nc I = 37190
.field public static final yb I = 33445
.field public static final xA I = 37085
.field public static final Nd I = 33358
.field public static final Vc I = 37609
.field public static final LC I = 37277
.field public static final jd I = 33398
.field public static final LA I = 33441
.field public static final ob I = 35882
.field public static final jc I = 37496
.field public static final nA I = 33477
.field public static final sc I = 33353
.field public static final QB I = 33461
.field public static final AA I = 33347
.field public static final sB I = 33474
.field public static final Ic I = 33396
.field public static final fB I = 37602
.field public static final eC I = 37643
.field public static final JA I = 33408
.field public static final tc I = 33378
.field public static final MC I = 37653
.field public static final vC I = 37311
.field public static final PB I = 33487
.field public static final Gb I = 33380
.field public static final Nb I = 33411
.field public static final CB I = 33499
.field public static final xB I = 33480
.field public static final bc I = 37632
.field public static final Hc I = 8192
.field public static final PC I = 33492
.field public static final tb I = 33354
.field public static final LB I = 33351
.field public static final eb I = 36203
.field public static final Oc I = 37188
.field public static final Lb I = 37648
.field public static final JB I = 37645
.field public static final Z I = 37618
.field public static final Pb I = 33467
.field public static final CA I = 37616
.field public static final DB I = 33387
.field public static final yB I = 37625
.field public static final FB I = 37638
.field public static final Rd I = 33440
.field public static final dc I = 33454
.field public static final hd I = 37191
.field public static final RA I = 37489
.field public static final md I = 33392
.field public static final TA I = 33465
.field public static final Sb I = 37102
.field public static final v I = 37634
.field public static final p I = 37627
.field public static final U I = 37307
.field public static final V I = 37600
.field public static final R I = 33462
.field public static final z I = 33450
.field public static final q I = 37624
.field public static final X I = 33498
.field public static final P I = 2
.field public static final O I = 33352
.field public static final w I = 36161
.field public static final y I = 37492
.field public static final o I = 37642
.field public static final Y I = 33501
.field public static final S I = 37100
.field public static final N I = 33481
.field public static final u I = 37654
.field public static final s I = 37603
.field public static final t I = 37494
.field public static final W I = 33388
.field public static final Q I = 37604
.field public static final T I = 33473
.field public static final r I = 33414
.field public static final x I = 37613
.field public static final n I = 33405
.field public static final M I = 33452
.field public static final L I = 36202
.field public static final H I = 33486
.field public static final d I = 37279
.field public static final e I = 3552
.field public static final g I = 33504
.field public static final k I = 33505
.field public static final a I = 33401
.field public static final F I = 33422
.field public static final A I = 33484
.field public static final E I = 33436
.field public static final C I = 33490
.field public static final K I = 33502
.field public static final G I = 33460
.field public static final B I = 37086
.field public static final c I = 37639
.field public static final field4162 I = 37077
.field public static final i I = 33430
.field public static final m I = 37647
.field public static final h I = 34465
.field public static final J I = 37620
.field public static final l I = 37488
.field public static final D I = 33508
.field public static final f I = 33413
.field public static final j I = 33483
.field public static final I I = 36665
.field public static final b I = 33434
.field public static final field4163 I = 32
.field public static final return I = 33472
.field public static final field4164 I = 37495
.field public static final switch I = 35864
.field public static final field4165 I = 33426
.field public static final field4166 I = 37650
.field public static final field4167 I = 33385
.field public static final field4168 I = 33442
.field public static final field4169 I = 33412
.field public static final field4170 I = 37075
.field public static final field4171 I = 33423
.field public static final field4172 I = 37490
.field public static final field4173 I = 33360
.field public static final throw I = 33453
.field public static final package I = 37646
.field public static final field4174 I = 33421
.field public static final field4175 I = 33475
.field public static final while I = 37622
.field public static final field4176 I = 1284
.field public static final field4177 I = 33491
.field public static final field4178 I = 37493
.field public static final field4179 I = 37074
.field public static final field4180 I = 33466
.field public static final field4181 I = 37120
.field public static final field4182 I = 33381
.field public static final field4183 I = 33357
.field public static final field4184 I = 37615
.field public static final field4185 I = 37606
.field public static final field4186 I = 36873
.field public static final false I = 33359
.field public static final field4187 I = 33424
.field public static final field4188 I = 37063
.field public static final true I = 33496
.field public static final field4189 I = 33348
.field public static final field4190 I = 37079
.field public static final field4191 I = 33389
.field public static final field4192 I = 33404
.field public static final field4193 I = 33393
.field public static final field4194 I = 37084
.field public static final field4195 I = 33407
.field public static final field4196 I = 37189
.field public static final field4197 I = 33447
.field public static final field4198 I = 33431
.field public static final try I = 33394
.field public static final field4199 I = 33503
.field public static final new I = 33495
.field public static final field4200 I = 33510
.field public static final this I = 37655
.field public static final field4201 I = 33415
.field public static final field4202 I = 37637
.field public static final field4203 I = 33446
.field public static final field4204 I = 37122

.method public static method4539 : (IIILjava/nio/IntBuffer;)V
    .code stack 7 locals 6
L0:     invokestatic Method org/lwjgl/opengl/GLContext method4611 ()Lorg/lwjgl/opengl/kb;
L3:     getfield Field org/lwjgl/opengl/kb Qd J
L6:     dup2
L7:     lstore 4
L9:     invokestatic Method org/lwjgl/l method2052 (J)V
L12:    iload_0
L13:    aload_3
L14:    iconst_1
L15:    dup
L16:    dup
L17:    pop2
L18:    invokestatic Method org/lwjgl/l method2041 (Ljava/nio/IntBuffer;I)V
L21:    iload_1
L22:    iload_2
L23:    aload_3
L24:    invokestatic Method org/lwjgl/MemoryUtil method1884 (Ljava/nio/IntBuffer;)J
L27:    lload 4
L29:    invokestatic Method org/lwjgl/opengl/GL43 nglGetProgramInterfaceiv (IIIJJ)V
L32:    return
L33:    
    .end code
.end method

.method static native nglObjectLabel : (IIIJJ)V
.end method

.method public static method4540 : (IIIJJ)V
    .code stack 9 locals 9
L0:     invokestatic Method org/lwjgl/opengl/GLContext method4611 ()Lorg/lwjgl/opengl/kb;
L3:     getfield Field org/lwjgl/opengl/kb hG J
L6:     dup2
L7:     lstore 7
L9:     invokestatic Method org/lwjgl/l method2052 (J)V
L12:    iload_0
L13:    iload_1
L14:    iload_2
L15:    lload_3
L16:    lload 5
L18:    lload 7
L20:    invokestatic Method org/lwjgl/opengl/GL43 nglTexBufferRange (IIIJJJ)V
L23:    return
L24:    
    .end code
.end method

.method public static method4541 : (II)I
    .code stack 6 locals 5
L0:     invokestatic Method org/lwjgl/opengl/GLContext method4611 ()Lorg/lwjgl/opengl/kb;
L3:     dup
L4:     getfield Field org/lwjgl/opengl/kb he J
L7:     dup2
L8:     lstore_3
L9:     invokestatic Method org/lwjgl/l method2052 (J)V
L12:    invokestatic Method org/lwjgl/opengl/bB method5467 (Lorg/lwjgl/opengl/kb;)Ljava/nio/IntBuffer;
L15:    astore_2
L16:    iload_0
L17:    iload_1
L18:    aload_2
L19:    invokestatic Method org/lwjgl/MemoryUtil method1884 (Ljava/nio/IntBuffer;)J
L22:    lload_3
L23:    invokestatic Method org/lwjgl/opengl/GL43 nglGetFramebufferParameteriv (IIJJ)V
L26:    aload_2
L27:    iconst_0
L28:    iconst_1
L29:    dup
L30:    pop2
L31:    invokevirtual Method java/nio/IntBuffer get (I)I
L34:    ireturn
L35:    
    .end code
.end method

.method static native nglVertexAttribBinding : (IIJ)V
.end method

.method public static method4542 : (IIIIIIZ)V
    .code stack 9 locals 9
L0:     invokestatic Method org/lwjgl/opengl/GLContext method4611 ()Lorg/lwjgl/opengl/kb;
L3:     getfield Field org/lwjgl/opengl/kb rD J
L6:     dup2
L7:     lstore 7
L9:     invokestatic Method org/lwjgl/l method2052 (J)V
L12:    iload_0
L13:    iload_1
L14:    iload_2
L15:    iload_3
L16:    iload 4
L18:    iload 5
L20:    iload 6
L22:    lload 7
L24:    invokestatic Method org/lwjgl/opengl/GL43 nglTexStorage3DMultisample (IIIIIIZJ)V
L27:    return
L28:    
    .end code
.end method

.method static native nglClearBufferData : (IIIIJJ)V
.end method

.method static native nglDebugMessageControl : (IIIIJZJ)V
.end method

.method public static method4543 : (IIILjava/nio/IntBuffer;Ljava/nio/ByteBuffer;)V
    .code stack 10 locals 7
L0:     invokestatic Method org/lwjgl/opengl/GLContext method4611 ()Lorg/lwjgl/opengl/kb;
L3:     getfield Field org/lwjgl/opengl/kb aB J
L6:     dup2
L7:     lstore 5
L9:     invokestatic Method org/lwjgl/l method2052 (J)V
L12:    aload_3
L13:    ifnull L24
L16:    aload_3
L17:    iconst_1
L18:    dup
L19:    dup
L20:    pop2
L21:    invokestatic Method org/lwjgl/l method2041 (Ljava/nio/IntBuffer;I)V
L24:    aload 4
L26:    ifnull L34
L29:    aload 4
L31:    invokestatic Method org/lwjgl/l method2034 (Ljava/nio/ByteBuffer;)V
L34:    iload_0
L35:    iload_1
L36:    iload_2
L37:    aload 4
L39:    ifnonnull L51
L42:    iconst_0
L43:    iconst_1
L44:    dup
L45:    pop2
L46:    aload_3
L47:    goto L57
L50:    athrow
L51:    aload 4
L53:    invokevirtual Method java/nio/ByteBuffer remaining ()I
L56:    aload_3
L57:    invokestatic Method org/lwjgl/MemoryUtil method1865 (Ljava/nio/IntBuffer;)J
L60:    aload 4
L62:    invokestatic Method org/lwjgl/MemoryUtil method1883 (Ljava/nio/ByteBuffer;)J
L65:    lload 5
L67:    invokestatic Method org/lwjgl/opengl/GL43 nglGetProgramResourceName (IIIIJJJ)V
L70:    return
L71:    
        .attribute StackMap b'\x00\x05\x00\x18\x00\x06\x01\x01\x01\x07\x02\x6D\x07\x02\x86\x04\x00\x00\x00\x22\x00\x06\x01\x01\x01\x07\x02\x6D\x07\x02\x86\x04\x00\x00\x00\x32\x00\x00\x00\x01\x07\x02\x8C\x00\x33\x00\x06\x01\x01\x01\x07\x02\x6D\x07\x02\x86\x04\x00\x03\x01\x01\x01\x00\x39\x00\x06\x01\x01\x01\x07\x02\x6D\x07\x02\x86\x04\x00\x05\x01\x01\x01\x01\x07\x02\x6D'
    .end code
.end method

.method static native nglCopyImageSubData : (IIIIIIIIIIIIIIIJ)V
.end method

.method static native nglClearBufferSubData : (IIJJIIJJ)V
.end method

.method static native nglGetObjectLabel : (IIIJJJ)V
.end method

.method public static method4544 : (ILjava/nio/IntBuffer;IIII)V
    .code stack 10 locals 8
L0:     invokestatic Method org/lwjgl/opengl/GLContext method4611 ()Lorg/lwjgl/opengl/kb;
L3:     getfield Field org/lwjgl/opengl/kb aI J
L6:     dup2
L7:     lstore 6
L9:     invokestatic Method org/lwjgl/l method2052 (J)V
L12:    iload_0
L13:    aload_1
L14:    invokestatic Method org/lwjgl/l method2043 (Ljava/nio/IntBuffer;)V
L17:    aload_1
L18:    invokevirtual Method java/nio/IntBuffer remaining ()I
L21:    aload_1
L22:    invokestatic Method org/lwjgl/MemoryUtil method1884 (Ljava/nio/IntBuffer;)J
L25:    iload_2
L26:    iload_3
L27:    iload 4
L29:    iload 5
L31:    lload 6
L33:    invokestatic Method org/lwjgl/opengl/GL43 nglInvalidateSubFramebuffer (IIJIIIIJ)V
L36:    return
L37:    
    .end code
.end method

.method static native nglVertexAttribIFormat : (IIIIJ)V
.end method

.method public static method4545 : (IIII)V
    .code stack 6 locals 6
L0:     invokestatic Method org/lwjgl/opengl/GLContext method4611 ()Lorg/lwjgl/opengl/kb;
L3:     getfield Field org/lwjgl/opengl/kb BN J
L6:     dup2
L7:     lstore 4
L9:     invokestatic Method org/lwjgl/l method2052 (J)V
L12:    iload_0
L13:    iload_1
L14:    iload_2
L15:    iload_3
L16:    lload 4
L18:    invokestatic Method org/lwjgl/opengl/GL43 nglVertexAttribIFormat (IIIIJ)V
L21:    return
L22:    
    .end code
.end method

.method public static method4546 : (IIII)Ljava/lang/String;
    .code stack 11 locals 8
L0:     invokestatic Method org/lwjgl/opengl/GLContext method4611 ()Lorg/lwjgl/opengl/kb;
L3:     dup
L4:     dup2
L5:     getfield Field org/lwjgl/opengl/kb aB J
L8:     dup2
L9:     lstore 5
L11:    invokestatic Method org/lwjgl/l method2052 (J)V
L14:    invokestatic Method org/lwjgl/opengl/bB method5483 (Lorg/lwjgl/opengl/kb;)Ljava/nio/IntBuffer;
L17:    astore 4
L19:    iload_3
L20:    invokestatic Method org/lwjgl/opengl/bB method5470 (Lorg/lwjgl/opengl/kb;I)Ljava/nio/ByteBuffer;
L23:    astore 7
L25:    iload_0
L26:    iload_1
L27:    iload_2
L28:    iload_3
L29:    aload 4
L31:    invokestatic Method org/lwjgl/MemoryUtil method1867 (Ljava/nio/Buffer;)J
L34:    aload 7
L36:    invokestatic Method org/lwjgl/MemoryUtil method1873 (Ljava/nio/ByteBuffer;)J
L39:    lload 5
L41:    invokestatic Method org/lwjgl/opengl/GL43 nglGetProgramResourceName (IIIIJJJ)V
L44:    aload 7
L46:    dup
L47:    aload 4
L49:    iconst_0
L50:    iconst_1
L51:    dup
L52:    pop2
L53:    invokevirtual Method java/nio/IntBuffer get (I)I
L56:    invokevirtual Method java/nio/ByteBuffer limit (I)Ljava/nio/Buffer;
L59:    pop
L60:    invokestatic Method org/lwjgl/opengl/bB method5469 (Lorg/lwjgl/opengl/kb;Ljava/nio/ByteBuffer;)Ljava/lang/String;
L63:    areturn
L64:    
    .end code
.end method

.method public static method4547 : (IIIZI)V
    .code stack 7 locals 7
L0:     invokestatic Method org/lwjgl/opengl/GLContext method4611 ()Lorg/lwjgl/opengl/kb;
L3:     getfield Field org/lwjgl/opengl/kb Vn J
L6:     dup2
L7:     lstore 5
L9:     invokestatic Method org/lwjgl/l method2052 (J)V
L12:    iload_0
L13:    iload_1
L14:    iload_2
L15:    iload_3
L16:    iload 4
L18:    lload 5
L20:    invokestatic Method org/lwjgl/opengl/GL43 nglVertexAttribFormat (IIIZIJ)V
L23:    return
L24:    
    .end code
.end method

.method public static method4548 : (IILjava/lang/CharSequence;)V
    .code stack 7 locals 6
L0:     invokestatic Method org/lwjgl/opengl/GLContext method4611 ()Lorg/lwjgl/opengl/kb;
L3:     dup
L4:     astore_3
L5:     getfield Field org/lwjgl/opengl/kb sO J
L8:     dup2
L9:     lstore 4
L11:    invokestatic Method org/lwjgl/l method2052 (J)V
L14:    iload_0
L15:    iload_1
L16:    aload_2
L17:    invokeinterface InterfaceMethod java/lang/CharSequence length ()I 1
L22:    aload_3
L23:    aload_2
L24:    invokestatic Method org/lwjgl/opengl/bB method5468 (Lorg/lwjgl/opengl/kb;Ljava/lang/CharSequence;)J
L27:    lload 4
L29:    invokestatic Method org/lwjgl/opengl/GL43 nglObjectLabel (IIIJJ)V
L32:    return
L33:    
    .end code
.end method

.method public static method4549 : (IILjava/nio/ByteBuffer;II)V
    .code stack 8 locals 8
L0:     invokestatic Method org/lwjgl/opengl/GLContext method4611 ()Lorg/lwjgl/opengl/kb;
L3:     astore 5
L5:     aload_2
L6:     aload 5
L8:     dup
L9:     getfield Field org/lwjgl/opengl/kb Xe J
L12:    dup2
L13:    lstore 6
L15:    invokestatic Method org/lwjgl/l method2052 (J)V
L18:    invokestatic Method org/lwjgl/opengl/Zd method5447 (Lorg/lwjgl/opengl/kb;)V
L21:    iconst_5
L22:    iconst_1
L23:    dup
L24:    pop2
L25:    iload_3
L26:    imul
L27:    invokestatic Method org/lwjgl/l method2054 (Ljava/nio/ByteBuffer;I)V
L30:    iload_0
L31:    iload_1
L32:    aload_2
L33:    invokestatic Method org/lwjgl/MemoryUtil method1873 (Ljava/nio/ByteBuffer;)J
L36:    iload_3
L37:    iload 4
L39:    lload 6
L41:    invokestatic Method org/lwjgl/opengl/GL43 nglMultiDrawElementsIndirect (IIJIIJ)V
L44:    return
L45:    
    .end code
.end method

.method public static method4550 : (IILjava/lang/CharSequence;)I
    .code stack 6 locals 6
L0:     invokestatic Method org/lwjgl/opengl/GLContext method4611 ()Lorg/lwjgl/opengl/kb;
L3:     dup
L4:     astore_3
L5:     getfield Field org/lwjgl/opengl/kb yg J
L8:     dup2
L9:     lstore 4
L11:    invokestatic Method org/lwjgl/l method2052 (J)V
L14:    iload_0
L15:    iload_1
L16:    aload_3
L17:    aload_2
L18:    invokestatic Method org/lwjgl/opengl/bB method5478 (Lorg/lwjgl/opengl/kb;Ljava/lang/CharSequence;)J
L21:    lload 4
L23:    invokestatic Method org/lwjgl/opengl/GL43 nglGetProgramResourceLocation (IIJJ)I
L26:    ireturn
L27:    
    .end code
.end method

.method public static method4551 : (IILjava/nio/ByteBuffer;)I
    .code stack 6 locals 5
L0:     invokestatic Method org/lwjgl/opengl/GLContext method4611 ()Lorg/lwjgl/opengl/kb;
L3:     getfield Field org/lwjgl/opengl/kb yg J
L6:     dup2
L7:     lstore_3
L8:     invokestatic Method org/lwjgl/l method2052 (J)V
L11:    iload_0
L12:    aload_2
L13:    dup
L14:    invokestatic Method org/lwjgl/l method2034 (Ljava/nio/ByteBuffer;)V
L17:    invokestatic Method org/lwjgl/l method2033 (Ljava/nio/ByteBuffer;)V
L20:    iload_1
L21:    aload_2
L22:    invokestatic Method org/lwjgl/MemoryUtil method1873 (Ljava/nio/ByteBuffer;)J
L25:    lload_3
L26:    invokestatic Method org/lwjgl/opengl/GL43 nglGetProgramResourceLocation (IIJJ)I
L29:    ireturn
L30:    
    .end code
.end method

.method public static method4552 : (IIIIIZ)V
    .code stack 8 locals 8
L0:     invokestatic Method org/lwjgl/opengl/GLContext method4611 ()Lorg/lwjgl/opengl/kb;
L3:     getfield Field org/lwjgl/opengl/kb Jk J
L6:     dup2
L7:     lstore 6
L9:     invokestatic Method org/lwjgl/l method2052 (J)V
L12:    iload_0
L13:    iload_1
L14:    iload_2
L15:    iload_3
L16:    iload 4
L18:    iload 5
L20:    lload 6
L22:    invokestatic Method org/lwjgl/opengl/GL43 nglTexStorage2DMultisample (IIIIIZJ)V
L25:    return
L26:    
    .end code
.end method

.method public static method4553 : (Lorg/lwjgl/PointerWrapper;Ljava/nio/IntBuffer;Ljava/nio/ByteBuffer;)V
    .code stack 9 locals 5
L0:     invokestatic Method org/lwjgl/opengl/GLContext method4611 ()Lorg/lwjgl/opengl/kb;
L3:     getfield Field org/lwjgl/opengl/kb kJ J
L6:     dup2
L7:     lstore_3
L8:     invokestatic Method org/lwjgl/l method2052 (J)V
L11:    aload_1
L12:    ifnull L23
L15:    aload_1
L16:    iconst_1
L17:    dup
L18:    dup
L19:    pop2
L20:    invokestatic Method org/lwjgl/l method2041 (Ljava/nio/IntBuffer;I)V
L23:    aload_2
L24:    invokestatic Method org/lwjgl/l method2034 (Ljava/nio/ByteBuffer;)V
L27:    aload_0
L28:    invokeinterface InterfaceMethod org/lwjgl/PointerWrapper getPointer ()J 1
L33:    aload_2
L34:    invokevirtual Method java/nio/ByteBuffer remaining ()I
L37:    aload_1
L38:    invokestatic Method org/lwjgl/MemoryUtil method1865 (Ljava/nio/IntBuffer;)J
L41:    aload_2
L42:    invokestatic Method org/lwjgl/MemoryUtil method1873 (Ljava/nio/ByteBuffer;)J
L45:    lload_3
L46:    invokestatic Method org/lwjgl/opengl/GL43 nglGetObjectPtrLabel (JIJJJ)V
L49:    return
L50:    
        .attribute StackMap b'\x00\x01\x00\x17\x00\x04\x07\x03\x1C\x07\x02\x6D\x07\x02\x86\x04\x00\x00'
    .end code
.end method

.method private <init> : ()V
    .code stack 1 locals 1
L0:     aload_0
L1:     invokespecial Method java/lang/Object <init> ()V
L4:     return
L5:     
    .end code
.end method

.method public static method4554 : (ILjava/nio/IntBuffer;)V
    .code stack 6 locals 4
L0:     invokestatic Method org/lwjgl/opengl/GLContext method4611 ()Lorg/lwjgl/opengl/kb;
L3:     getfield Field org/lwjgl/opengl/kb sT J
L6:     dup2
L7:     lstore_2
L8:     invokestatic Method org/lwjgl/l method2052 (J)V
L11:    iload_0
L12:    aload_1
L13:    invokestatic Method org/lwjgl/l method2043 (Ljava/nio/IntBuffer;)V
L16:    aload_1
L17:    invokevirtual Method java/nio/IntBuffer remaining ()I
L20:    aload_1
L21:    invokestatic Method org/lwjgl/MemoryUtil method1884 (Ljava/nio/IntBuffer;)J
L24:    lload_2
L25:    invokestatic Method org/lwjgl/opengl/GL43 nglInvalidateFramebuffer (IIJJ)V
L28:    return
L29:    
    .end code
.end method

.method public static method4555 : (IILjava/nio/IntBuffer;II)V
    .code stack 8 locals 8
L0:     invokestatic Method org/lwjgl/opengl/GLContext method4611 ()Lorg/lwjgl/opengl/kb;
L3:     astore 5
L5:     aload_2
L6:     aload 5
L8:     dup
L9:     getfield Field org/lwjgl/opengl/kb Xe J
L12:    dup2
L13:    lstore 6
L15:    invokestatic Method org/lwjgl/l method2052 (J)V
L18:    invokestatic Method org/lwjgl/opengl/Zd method5447 (Lorg/lwjgl/opengl/kb;)V
L21:    iconst_5
L22:    iconst_1
L23:    dup
L24:    pop2
L25:    iload_3
L26:    imul
L27:    invokestatic Method org/lwjgl/l method2041 (Ljava/nio/IntBuffer;I)V
L30:    iload_0
L31:    iload_1
L32:    aload_2
L33:    invokestatic Method org/lwjgl/MemoryUtil method1884 (Ljava/nio/IntBuffer;)J
L36:    iload_3
L37:    iload 4
L39:    lload 6
L41:    invokestatic Method org/lwjgl/opengl/GL43 nglMultiDrawElementsIndirect (IIJIIJ)V
L44:    return
L45:    
    .end code
.end method

.method public static method4556 : (IIILjava/nio/IntBuffer;Z)V
    .code stack 9 locals 7
L0:     invokestatic Method org/lwjgl/opengl/GLContext method4611 ()Lorg/lwjgl/opengl/kb;
L3:     getfield Field org/lwjgl/opengl/kb dg J
L6:     dup2
L7:     lstore 5
L9:     invokestatic Method org/lwjgl/l method2052 (J)V
L12:    aload_3
L13:    ifnull L20
L16:    aload_3
L17:    invokestatic Method org/lwjgl/l method2043 (Ljava/nio/IntBuffer;)V
L20:    iload_0
L21:    iload_1
L22:    iload_2
L23:    aload_3
L24:    ifnonnull L36
L27:    iconst_0
L28:    iconst_1
L29:    dup
L30:    pop2
L31:    aload_3
L32:    goto L41
L35:    athrow
L36:    aload_3
L37:    invokevirtual Method java/nio/IntBuffer remaining ()I
L40:    aload_3
L41:    invokestatic Method org/lwjgl/MemoryUtil method1865 (Ljava/nio/IntBuffer;)J
L44:    iload 4
L46:    lload 5
L48:    invokestatic Method org/lwjgl/opengl/GL43 nglDebugMessageControl (IIIIJZJ)V
L51:    return
L52:    
        .attribute StackMap b'\x00\x04\x00\x14\x00\x06\x01\x01\x01\x07\x02\x6D\x01\x04\x00\x00\x00\x23\x00\x00\x00\x01\x07\x02\x8C\x00\x24\x00\x06\x01\x01\x01\x07\x02\x6D\x01\x04\x00\x03\x01\x01\x01\x00\x29\x00\x06\x01\x01\x01\x07\x02\x6D\x01\x04\x00\x05\x01\x01\x01\x01\x07\x02\x6D'
    .end code
.end method

.method static native nglDispatchComputeIndirect : (JJ)V
.end method

.method public static method4557 : (IILjava/lang/CharSequence;)I
    .code stack 6 locals 6
L0:     invokestatic Method org/lwjgl/opengl/GLContext method4611 ()Lorg/lwjgl/opengl/kb;
L3:     dup
L4:     astore_3
L5:     getfield Field org/lwjgl/opengl/kb sQ J
L8:     dup2
L9:     lstore 4
L11:    invokestatic Method org/lwjgl/l method2052 (J)V
L14:    iload_0
L15:    iload_1
L16:    aload_3
L17:    aload_2
L18:    invokestatic Method org/lwjgl/opengl/bB method5478 (Lorg/lwjgl/opengl/kb;Ljava/lang/CharSequence;)J
L21:    lload 4
L23:    invokestatic Method org/lwjgl/opengl/GL43 nglGetProgramResourceIndex (IIJJ)I
L26:    ireturn
L27:    
    .end code
.end method

.method static native nglGetProgramResourceIndex : (IIJJ)I
.end method

.method static native nglGetProgramResourceName : (IIIIJJJ)V
.end method

.method public static method4558 : (Lorg/lwjgl/opengl/nA;)V
    .code stack 6 locals 5
L0:     invokestatic Method org/lwjgl/opengl/GLContext method4611 ()Lorg/lwjgl/opengl/kb;
L3:     getfield Field org/lwjgl/opengl/kb Et J
L6:     dup2
L7:     lstore_1
L8:     invokestatic Method org/lwjgl/l method2052 (J)V
L11:    aload_0
L12:    ifnonnull L20
L15:    lconst_0
L16:    goto L27
L19:    athrow
L20:    aload_0
L21:    invokevirtual Method org/lwjgl/opengl/nA method1836 ()Lorg/lwjgl/opengl/F;
L24:    invokestatic Method org/lwjgl/opengl/CallbackUtil method2975 (Ljava/lang/Object;)J
L27:    lstore_3
L28:    lload_3
L29:    invokestatic Method org/lwjgl/opengl/CallbackUtil method2974 (J)V
L32:    aload_0
L33:    ifnonnull L42
L36:    lconst_0
L37:    lload_3
L38:    goto L47
L41:    athrow
L42:    aload_0
L43:    invokevirtual Method org/lwjgl/opengl/nA getPointer ()J
L46:    lload_3
L47:    lload_1
L48:    invokestatic Method org/lwjgl/opengl/GL43 nglDebugMessageCallback (JJJ)V
L51:    return
L52:    
        .attribute StackMap b'\x00\x06\x00\x13\x00\x00\x00\x01\x07\x02\x8C\x00\x14\x00\x02\x07\x00\x08\x04\x00\x00\x00\x1B\x00\x02\x07\x00\x08\x04\x00\x01\x04\x00\x29\x00\x00\x00\x01\x07\x02\x8C\x00\x2A\x00\x03\x07\x00\x08\x04\x04\x00\x00\x00\x2F\x00\x03\x07\x00\x08\x04\x04\x00\x02\x04\x04'
    .end code
.end method

.method static native nglInvalidateBufferSubData : (IJJJ)V
.end method

.method public static method4559 : (IIJI)V
    .code stack 7 locals 7
L0:     invokestatic Method org/lwjgl/opengl/GLContext method4611 ()Lorg/lwjgl/opengl/kb;
L3:     getfield Field org/lwjgl/opengl/kb hq J
L6:     dup2
L7:     lstore 5
L9:     invokestatic Method org/lwjgl/l method2052 (J)V
L12:    iload_0
L13:    iload_1
L14:    lload_2
L15:    iload 4
L17:    lload 5
L19:    invokestatic Method org/lwjgl/opengl/GL43 nglBindVertexBuffer (IIJIJ)V
L22:    return
L23:    
    .end code
.end method

.method public static method4560 : (IILjava/nio/ByteBuffer;)I
    .code stack 6 locals 5
L0:     invokestatic Method org/lwjgl/opengl/GLContext method4611 ()Lorg/lwjgl/opengl/kb;
L3:     getfield Field org/lwjgl/opengl/kb lt J
L6:     dup2
L7:     lstore_3
L8:     invokestatic Method org/lwjgl/l method2052 (J)V
L11:    iload_0
L12:    aload_2
L13:    dup
L14:    invokestatic Method org/lwjgl/l method2034 (Ljava/nio/ByteBuffer;)V
L17:    invokestatic Method org/lwjgl/l method2033 (Ljava/nio/ByteBuffer;)V
L20:    iload_1
L21:    aload_2
L22:    invokestatic Method org/lwjgl/MemoryUtil method1873 (Ljava/nio/ByteBuffer;)J
L25:    lload_3
L26:    invokestatic Method org/lwjgl/opengl/GL43 nglGetProgramResourceLocationIndex (IIJJ)I
L29:    ireturn
L30:    
    .end code
.end method

.method static native nglGetFramebufferParameteriv : (IIJJ)V
.end method

.method static native nglInvalidateTexImage : (IIJ)V
.end method

.method static native nglGetProgramResourceLocationIndex : (IIJJ)I
.end method

.method public static method4561 : (IIIIIIII)V
    .code stack 10 locals 10
L0:     invokestatic Method org/lwjgl/opengl/GLContext method4611 ()Lorg/lwjgl/opengl/kb;
L3:     getfield Field org/lwjgl/opengl/kb mJ J
L6:     dup2
L7:     lstore 8
L9:     invokestatic Method org/lwjgl/l method2052 (J)V
L12:    iload_0
L13:    iload_1
L14:    iload_2
L15:    iload_3
L16:    iload 4
L18:    iload 5
L20:    iload 6
L22:    iload 7
L24:    lload 8
L26:    invokestatic Method org/lwjgl/opengl/GL43 nglTextureView (IIIIIIIIJ)V
L29:    return
L30:    
    .end code
.end method

.method public static method4562 : (IIIILjava/nio/ByteBuffer;)V
    .code stack 9 locals 7
L0:     invokestatic Method org/lwjgl/opengl/GLContext method4611 ()Lorg/lwjgl/opengl/kb;
L3:     getfield Field org/lwjgl/opengl/kb uf J
L6:     dup2
L7:     lstore 5
L9:     invokestatic Method org/lwjgl/l method2052 (J)V
L12:    iload_0
L13:    aload 4
L15:    invokestatic Method org/lwjgl/l method2034 (Ljava/nio/ByteBuffer;)V
L18:    iload_1
L19:    iload_2
L20:    iload_3
L21:    aload 4
L23:    invokevirtual Method java/nio/ByteBuffer remaining ()I
L26:    aload 4
L28:    invokestatic Method org/lwjgl/MemoryUtil method1873 (Ljava/nio/ByteBuffer;)J
L31:    lload 5
L33:    invokestatic Method org/lwjgl/opengl/GL43 nglDebugMessageInsert (IIIIIJJ)V
L36:    return
L37:    
    .end code
.end method

.method public static method4563 : (ILjava/nio/IntBuffer;II)V
    .code stack 7 locals 7
L0:     invokestatic Method org/lwjgl/opengl/GLContext method4611 ()Lorg/lwjgl/opengl/kb;
L3:     astore 4
L5:     aload_1
L6:     aload 4
L8:     dup
L9:     getfield Field org/lwjgl/opengl/kb field5429 J
L12:    dup2
L13:    lstore 5
L15:    invokestatic Method org/lwjgl/l method2052 (J)V
L18:    invokestatic Method org/lwjgl/opengl/Zd method5447 (Lorg/lwjgl/opengl/kb;)V
L21:    iconst_4
L22:    iconst_1
L23:    dup
L24:    pop2
L25:    iload_2
L26:    imul
L27:    invokestatic Method org/lwjgl/l method2041 (Ljava/nio/IntBuffer;I)V
L30:    iload_0
L31:    aload_1
L32:    invokestatic Method org/lwjgl/MemoryUtil method1884 (Ljava/nio/IntBuffer;)J
L35:    iload_2
L36:    iload_3
L37:    lload 5
L39:    invokestatic Method org/lwjgl/opengl/GL43 nglMultiDrawArraysIndirect (IJIIJ)V
L42:    return
L43:    
    .end code
.end method

.method public static method4564 : (IIILjava/nio/IntBuffer;Ljava/nio/IntBuffer;Ljava/nio/IntBuffer;)V
    .code stack 13 locals 8
L0:     invokestatic Method org/lwjgl/opengl/GLContext method4611 ()Lorg/lwjgl/opengl/kb;
L3:     getfield Field org/lwjgl/opengl/kb Mn J
L6:     dup2
L7:     lstore 6
L9:     invokestatic Method org/lwjgl/l method2052 (J)V
L12:    aload 4
L14:    aload_3
L15:    invokestatic Method org/lwjgl/l method2043 (Ljava/nio/IntBuffer;)V
L18:    ifnull L30
L21:    aload 4
L23:    iconst_1
L24:    dup
L25:    dup
L26:    pop2
L27:    invokestatic Method org/lwjgl/l method2041 (Ljava/nio/IntBuffer;I)V
L30:    aload 5
L32:    invokestatic Method org/lwjgl/l method2043 (Ljava/nio/IntBuffer;)V
L35:    iload_0
L36:    iload_1
L37:    iload_2
L38:    aload_3
L39:    invokevirtual Method java/nio/IntBuffer remaining ()I
L42:    aload_3
L43:    invokestatic Method org/lwjgl/MemoryUtil method1884 (Ljava/nio/IntBuffer;)J
L46:    aload 5
L48:    invokevirtual Method java/nio/IntBuffer remaining ()I
L51:    aload 4
L53:    invokestatic Method org/lwjgl/MemoryUtil method1865 (Ljava/nio/IntBuffer;)J
L56:    aload 5
L58:    invokestatic Method org/lwjgl/MemoryUtil method1884 (Ljava/nio/IntBuffer;)J
L61:    lload 6
L63:    invokestatic Method org/lwjgl/opengl/GL43 nglGetProgramResourceiv (IIIIJIJJJ)V
L66:    return
L67:    
        .attribute StackMap b'\x00\x01\x00\x1E\x00\x07\x01\x01\x01\x07\x02\x6D\x07\x02\x6D\x07\x02\x6D\x04\x00\x00'
    .end code
.end method

.method static native nglPopDebugGroup : (J)V
.end method

.method public static method4565 : (IILjava/lang/CharSequence;)V
    .code stack 7 locals 6
L0:     invokestatic Method org/lwjgl/opengl/GLContext method4611 ()Lorg/lwjgl/opengl/kb;
L3:     dup
L4:     astore_3
L5:     getfield Field org/lwjgl/opengl/kb qd J
L8:     dup2
L9:     lstore 4
L11:    invokestatic Method org/lwjgl/l method2052 (J)V
L14:    iload_0
L15:    iload_1
L16:    aload_2
L17:    invokeinterface InterfaceMethod java/lang/CharSequence length ()I 1
L22:    aload_3
L23:    aload_2
L24:    invokestatic Method org/lwjgl/opengl/bB method5468 (Lorg/lwjgl/opengl/kb;Ljava/lang/CharSequence;)J
L27:    lload 4
L29:    invokestatic Method org/lwjgl/opengl/GL43 nglPushDebugGroup (IIIJJ)V
L32:    return
L33:    
    .end code
.end method

.method static native nglGetProgramInterfaceiv : (IIIJJ)V
.end method

.method public static method4566 : (I)V
    .code stack 4 locals 3
L0:     invokestatic Method org/lwjgl/opengl/GLContext method4611 ()Lorg/lwjgl/opengl/kb;
L3:     getfield Field org/lwjgl/opengl/kb sD J
L6:     dup2
L7:     lstore_1
L8:     invokestatic Method org/lwjgl/l method2052 (J)V
L11:    iload_0
L12:    lload_1
L13:    invokestatic Method org/lwjgl/opengl/GL43 nglInvalidateBufferData (IJ)V
L16:    return
L17:    
    .end code
.end method

.method public static method4567 : (IIIILjava/lang/CharSequence;)V
    .code stack 9 locals 8
L0:     invokestatic Method org/lwjgl/opengl/GLContext method4611 ()Lorg/lwjgl/opengl/kb;
L3:     dup
L4:     astore 5
L6:     getfield Field org/lwjgl/opengl/kb uf J
L9:     dup2
L10:    lstore 6
L12:    invokestatic Method org/lwjgl/l method2052 (J)V
L15:    iload_0
L16:    iload_1
L17:    iload_2
L18:    iload_3
L19:    aload 4
L21:    invokeinterface InterfaceMethod java/lang/CharSequence length ()I 1
L26:    aload 5
L28:    aload 4
L30:    invokestatic Method org/lwjgl/opengl/bB method5468 (Lorg/lwjgl/opengl/kb;Ljava/lang/CharSequence;)J
L33:    lload 6
L35:    invokestatic Method org/lwjgl/opengl/GL43 nglDebugMessageInsert (IIIIIJJ)V
L38:    return
L39:    
    .end code
.end method

.method static native nglPushDebugGroup : (IIIJJ)V
.end method

.method public static method4568 : (III)I
    .code stack 7 locals 6
L0:     invokestatic Method org/lwjgl/opengl/GLContext method4611 ()Lorg/lwjgl/opengl/kb;
L3:     dup
L4:     getfield Field org/lwjgl/opengl/kb Qd J
L7:     dup2
L8:     lstore 4
L10:    invokestatic Method org/lwjgl/l method2052 (J)V
L13:    invokestatic Method org/lwjgl/opengl/bB method5467 (Lorg/lwjgl/opengl/kb;)Ljava/nio/IntBuffer;
L16:    astore_3
L17:    iload_0
L18:    iload_1
L19:    iload_2
L20:    aload_3
L21:    invokestatic Method org/lwjgl/MemoryUtil method1884 (Ljava/nio/IntBuffer;)J
L24:    lload 4
L26:    invokestatic Method org/lwjgl/opengl/GL43 nglGetProgramInterfaceiv (IIIJJ)V
L29:    aload_3
L30:    iconst_0
L31:    iconst_1
L32:    dup
L33:    pop2
L34:    invokevirtual Method java/nio/IntBuffer get (I)I
L37:    ireturn
L38:    
    .end code
.end method

.method public static method4569 : (IIILjava/nio/LongBuffer;)V
    .code stack 8 locals 6
L0:     invokestatic Method org/lwjgl/opengl/GLContext method4611 ()Lorg/lwjgl/opengl/kb;
L3:     getfield Field org/lwjgl/opengl/kb dU J
L6:     dup2
L7:     lstore 4
L9:     invokestatic Method org/lwjgl/l method2052 (J)V
L12:    iload_0
L13:    aload_3
L14:    invokestatic Method org/lwjgl/l method2058 (Ljava/nio/LongBuffer;)V
L17:    iload_1
L18:    iload_2
L19:    aload_3
L20:    invokevirtual Method java/nio/LongBuffer remaining ()I
L23:    aload_3
L24:    invokestatic Method org/lwjgl/MemoryUtil method1860 (Ljava/nio/LongBuffer;)J
L27:    lload 4
L29:    invokestatic Method org/lwjgl/opengl/GL43 nglGetInternalformati64v (IIIIJJ)V
L32:    return
L33:    
    .end code
.end method

.method public static method4570 : (ILjava/nio/IntBuffer;Ljava/nio/IntBuffer;Ljava/nio/IntBuffer;Ljava/nio/IntBuffer;Ljava/nio/IntBuffer;Ljava/nio/ByteBuffer;)I
    .code stack 16 locals 9
L0:     invokestatic Method org/lwjgl/opengl/GLContext method4611 ()Lorg/lwjgl/opengl/kb;
L3:     getfield Field org/lwjgl/opengl/kb sn J
L6:     dup2
L7:     lstore 7
L9:     invokestatic Method org/lwjgl/l method2052 (J)V
L12:    aload_1
L13:    ifnull L21
L16:    aload_1
L17:    iload_0
L18:    invokestatic Method org/lwjgl/l method2041 (Ljava/nio/IntBuffer;I)V
L21:    aload_2
L22:    ifnull L30
L25:    aload_2
L26:    iload_0
L27:    invokestatic Method org/lwjgl/l method2041 (Ljava/nio/IntBuffer;I)V
L30:    aload_3
L31:    ifnull L39
L34:    aload_3
L35:    iload_0
L36:    invokestatic Method org/lwjgl/l method2041 (Ljava/nio/IntBuffer;I)V
L39:    aload 4
L41:    ifnull L50
L44:    aload 4
L46:    iload_0
L47:    invokestatic Method org/lwjgl/l method2041 (Ljava/nio/IntBuffer;I)V
L50:    aload 5
L52:    ifnull L61
L55:    aload 5
L57:    iload_0
L58:    invokestatic Method org/lwjgl/l method2041 (Ljava/nio/IntBuffer;I)V
L61:    aload 6
L63:    ifnull L71
L66:    aload 6
L68:    invokestatic Method org/lwjgl/l method2034 (Ljava/nio/ByteBuffer;)V
L71:    iload_0
L72:    aload 6
L74:    ifnonnull L86
L77:    iconst_0
L78:    iconst_1
L79:    dup
L80:    pop2
L81:    aload_1
L82:    goto L92
L85:    athrow
L86:    aload 6
L88:    invokevirtual Method java/nio/ByteBuffer remaining ()I
L91:    aload_1
L92:    invokestatic Method org/lwjgl/MemoryUtil method1865 (Ljava/nio/IntBuffer;)J
L95:    aload_2
L96:    invokestatic Method org/lwjgl/MemoryUtil method1865 (Ljava/nio/IntBuffer;)J
L99:    aload_3
L100:   invokestatic Method org/lwjgl/MemoryUtil method1865 (Ljava/nio/IntBuffer;)J
L103:   aload 4
L105:   invokestatic Method org/lwjgl/MemoryUtil method1865 (Ljava/nio/IntBuffer;)J
L108:   aload 5
L110:   invokestatic Method org/lwjgl/MemoryUtil method1865 (Ljava/nio/IntBuffer;)J
L113:   aload 6
L115:   invokestatic Method org/lwjgl/MemoryUtil method1883 (Ljava/nio/ByteBuffer;)J
L118:   lload 7
L120:   invokestatic Method org/lwjgl/opengl/GL43 nglGetDebugMessageLog (IIJJJJJJJ)I
L123:   ireturn
L124:   
        .attribute StackMap b'\x00\x09\x00\x15\x00\x08\x01\x07\x02\x6D\x07\x02\x6D\x07\x02\x6D\x07\x02\x6D\x07\x02\x6D\x07\x02\x86\x04\x00\x00\x00\x1E\x00\x08\x01\x07\x02\x6D\x07\x02\x6D\x07\x02\x6D\x07\x02\x6D\x07\x02\x6D\x07\x02\x86\x04\x00\x00\x00\x27\x00\x08\x01\x07\x02\x6D\x07\x02\x6D\x07\x02\x6D\x07\x02\x6D\x07\x02\x6D\x07\x02\x86\x04\x00\x00\x00\x32\x00\x08\x01\x07\x02\x6D\x07\x02\x6D\x07\x02\x6D\x07\x02\x6D\x07\x02\x6D\x07\x02\x86\x04\x00\x00\x00\x3D\x00\x08\x01\x07\x02\x6D\x07\x02\x6D\x07\x02\x6D\x07\x02\x6D\x07\x02\x6D\x07\x02\x86\x04\x00\x00\x00\x47\x00\x08\x01\x07\x02\x6D\x07\x02\x6D\x07\x02\x6D\x07\x02\x6D\x07\x02\x6D\x07\x02\x86\x04\x00\x00\x00\x55\x00\x00\x00\x01\x07\x02\x8C\x00\x56\x00\x08\x01\x07\x02\x6D\x07\x02\x6D\x07\x02\x6D\x07\x02\x6D\x07\x02\x6D\x07\x02\x86\x04\x00\x01\x01\x00\x5C\x00\x08\x01\x07\x02\x6D\x07\x02\x6D\x07\x02\x6D\x07\x02\x6D\x07\x02\x6D\x07\x02\x86\x04\x00\x03\x01\x01\x07\x02\x6D'
    .end code
.end method

.method static native nglInvalidateTexSubImage : (IIIIIIIIJ)V
.end method

.method public static method4571 : (IILjava/nio/ByteBuffer;)V
    .code stack 7 locals 5
L0:     invokestatic Method org/lwjgl/opengl/GLContext method4611 ()Lorg/lwjgl/opengl/kb;
L3:     getfield Field org/lwjgl/opengl/kb sO J
L6:     dup2
L7:     lstore_3
L8:     invokestatic Method org/lwjgl/l method2052 (J)V
L11:    aload_2
L12:    ifnull L19
L15:    aload_2
L16:    invokestatic Method org/lwjgl/l method2034 (Ljava/nio/ByteBuffer;)V
L19:    iload_0
L20:    iload_1
L21:    aload_2
L22:    ifnonnull L34
L25:    iconst_0
L26:    iconst_1
L27:    dup
L28:    pop2
L29:    aload_2
L30:    goto L39
L33:    athrow
L34:    aload_2
L35:    invokevirtual Method java/nio/ByteBuffer remaining ()I
L38:    aload_2
L39:    invokestatic Method org/lwjgl/MemoryUtil method1883 (Ljava/nio/ByteBuffer;)J
L42:    lload_3
L43:    invokestatic Method org/lwjgl/opengl/GL43 nglObjectLabel (IIIJJ)V
L46:    return
L47:    
        .attribute StackMap b'\x00\x04\x00\x13\x00\x04\x01\x01\x07\x02\x86\x04\x00\x00\x00\x21\x00\x00\x00\x01\x07\x02\x8C\x00\x22\x00\x04\x01\x01\x07\x02\x86\x04\x00\x02\x01\x01\x00\x27\x00\x04\x01\x01\x07\x02\x86\x04\x00\x04\x01\x01\x01\x07\x02\x86'
    .end code
.end method

.method public static method4572 : (Lorg/lwjgl/PointerWrapper;I)Ljava/lang/String;
    .code stack 12 locals 6
L0:     invokestatic Method org/lwjgl/opengl/GLContext method4611 ()Lorg/lwjgl/opengl/kb;
L3:     dup
L4:     dup2
L5:     getfield Field org/lwjgl/opengl/kb kJ J
L8:     dup2
L9:     lstore_3
L10:    invokestatic Method org/lwjgl/l method2052 (J)V
L13:    invokestatic Method org/lwjgl/opengl/bB method5483 (Lorg/lwjgl/opengl/kb;)Ljava/nio/IntBuffer;
L16:    astore_2
L17:    iload_1
L18:    invokestatic Method org/lwjgl/opengl/bB method5470 (Lorg/lwjgl/opengl/kb;I)Ljava/nio/ByteBuffer;
L21:    dup
L22:    astore 5
L24:    dup
L25:    aload_0
L26:    invokeinterface InterfaceMethod org/lwjgl/PointerWrapper getPointer ()J 1
L31:    iload_1
L32:    aload_2
L33:    invokestatic Method org/lwjgl/MemoryUtil method1867 (Ljava/nio/Buffer;)J
L36:    aload 5
L38:    invokestatic Method org/lwjgl/MemoryUtil method1873 (Ljava/nio/ByteBuffer;)J
L41:    lload_3
L42:    invokestatic Method org/lwjgl/opengl/GL43 nglGetObjectPtrLabel (JIJJJ)V
L45:    aload_2
L46:    iconst_0
L47:    iconst_1
L48:    dup
L49:    pop2
L50:    invokevirtual Method java/nio/IntBuffer get (I)I
L53:    invokevirtual Method java/nio/ByteBuffer limit (I)Ljava/nio/Buffer;
L56:    pop
L57:    invokestatic Method org/lwjgl/opengl/bB method5469 (Lorg/lwjgl/opengl/kb;Ljava/nio/ByteBuffer;)Ljava/lang/String;
L60:    areturn
L61:    
    .end code
.end method

.method static native nglTexStorage3DMultisample : (IIIIIIZJ)V
.end method

.method public static method4573 : (IJJ)V
    .code stack 7 locals 7
L0:     invokestatic Method org/lwjgl/opengl/GLContext method4611 ()Lorg/lwjgl/opengl/kb;
L3:     getfield Field org/lwjgl/opengl/kb pO J
L6:     dup2
L7:     lstore 5
L9:     invokestatic Method org/lwjgl/l method2052 (J)V
L12:    iload_0
L13:    lload_1
L14:    lload_3
L15:    lload 5
L17:    invokestatic Method org/lwjgl/opengl/GL43 nglInvalidateBufferSubData (IJJJ)V
L20:    return
L21:    
    .end code
.end method

.method static native nglGetObjectPtrLabel : (JIJJJ)V
.end method

.method static native nglVertexAttribLFormat : (IIIIJ)V
.end method

.method static native nglMultiDrawArraysIndirectBO : (IJIIJ)V
.end method

.method public static method4574 : (II)V
    .code stack 4 locals 4
L0:     invokestatic Method org/lwjgl/opengl/GLContext method4611 ()Lorg/lwjgl/opengl/kb;
L3:     getfield Field org/lwjgl/opengl/kb aK J
L6:     dup2
L7:     lstore_2
L8:     invokestatic Method org/lwjgl/l method2052 (J)V
L11:    iload_0
L12:    iload_1
L13:    lload_2
L14:    invokestatic Method org/lwjgl/opengl/GL43 nglVertexBindingDivisor (IIJ)V
L17:    return
L18:    
    .end code
.end method

.method static native nglTextureView : (IIIIIIIIJ)V
.end method

.method static native nglGetProgramResourceLocation : (IIJJ)I
.end method

.method static native nglObjectPtrLabel : (JIJJ)V
.end method

.method static native nglShaderStorageBlockBinding : (IIIJ)V
.end method

.method public static method4575 : (III)J
    .code stack 8 locals 6
L0:     invokestatic Method org/lwjgl/opengl/GLContext method4611 ()Lorg/lwjgl/opengl/kb;
L3:     dup
L4:     getfield Field org/lwjgl/opengl/kb dU J
L7:     dup2
L8:     lstore 4
L10:    invokestatic Method org/lwjgl/l method2052 (J)V
L13:    invokestatic Method org/lwjgl/opengl/bB method5471 (Lorg/lwjgl/opengl/kb;)Ljava/nio/LongBuffer;
L16:    astore_3
L17:    iload_0
L18:    iload_1
L19:    iload_2
L20:    iconst_1
L21:    dup
L22:    dup
L23:    pop2
L24:    aload_3
L25:    invokestatic Method org/lwjgl/MemoryUtil method1860 (Ljava/nio/LongBuffer;)J
L28:    lload 4
L30:    invokestatic Method org/lwjgl/opengl/GL43 nglGetInternalformati64v (IIIIJJ)V
L33:    aload_3
L34:    iconst_0
L35:    iconst_1
L36:    dup
L37:    pop2
L38:    invokevirtual Method java/nio/LongBuffer get (I)J
L41:    lreturn
L42:    
    .end code
.end method

.method public static method4576 : (III)V
    .code stack 5 locals 5
L0:     invokestatic Method org/lwjgl/opengl/GLContext method4611 ()Lorg/lwjgl/opengl/kb;
L3:     getfield Field org/lwjgl/opengl/kb tm J
L6:     dup2
L7:     lstore_3
L8:     invokestatic Method org/lwjgl/l method2052 (J)V
L11:    iload_0
L12:    iload_1
L13:    iload_2
L14:    lload_3
L15:    invokestatic Method org/lwjgl/opengl/GL43 nglShaderStorageBlockBinding (IIIJ)V
L18:    return
L19:    
    .end code
.end method

.method static native nglGetDebugMessageLog : (IIJJJJJJJ)I
.end method

.method public static method4577 : ()V
    .code stack 4 locals 2
L0:     invokestatic Method org/lwjgl/opengl/GLContext method4611 ()Lorg/lwjgl/opengl/kb;
L3:     getfield Field org/lwjgl/opengl/kb Ne J
L6:     dup2
L7:     lstore_0
L8:     invokestatic Method org/lwjgl/l method2052 (J)V
L11:    lload_0
L12:    invokestatic Method org/lwjgl/opengl/GL43 nglPopDebugGroup (J)V
L15:    return
L16:    
    .end code
.end method

.method public static method4578 : (IILjava/nio/IntBuffer;Ljava/nio/ByteBuffer;)V
    .code stack 9 locals 6
L0:     invokestatic Method org/lwjgl/opengl/GLContext method4611 ()Lorg/lwjgl/opengl/kb;
L3:     getfield Field org/lwjgl/opengl/kb AE J
L6:     dup2
L7:     lstore 4
L9:     invokestatic Method org/lwjgl/l method2052 (J)V
L12:    aload_2
L13:    ifnull L24
L16:    aload_2
L17:    iconst_1
L18:    dup
L19:    dup
L20:    pop2
L21:    invokestatic Method org/lwjgl/l method2041 (Ljava/nio/IntBuffer;I)V
L24:    aload_3
L25:    invokestatic Method org/lwjgl/l method2034 (Ljava/nio/ByteBuffer;)V
L28:    iload_0
L29:    iload_1
L30:    aload_3
L31:    invokevirtual Method java/nio/ByteBuffer remaining ()I
L34:    aload_2
L35:    invokestatic Method org/lwjgl/MemoryUtil method1865 (Ljava/nio/IntBuffer;)J
L38:    aload_3
L39:    invokestatic Method org/lwjgl/MemoryUtil method1873 (Ljava/nio/ByteBuffer;)J
L42:    lload 4
L44:    invokestatic Method org/lwjgl/opengl/GL43 nglGetObjectLabel (IIIJJJ)V
L47:    return
L48:    
        .attribute StackMap b'\x00\x01\x00\x18\x00\x05\x01\x01\x07\x02\x6D\x07\x02\x86\x04\x00\x00'
    .end code
.end method

.method public static method4579 : (IILjava/nio/IntBuffer;)V
    .code stack 6 locals 5
L0:     invokestatic Method org/lwjgl/opengl/GLContext method4611 ()Lorg/lwjgl/opengl/kb;
L3:     getfield Field org/lwjgl/opengl/kb he J
L6:     dup2
L7:     lstore_3
L8:     invokestatic Method org/lwjgl/l method2052 (J)V
L11:    iload_0
L12:    aload_2
L13:    iconst_1
L14:    dup
L15:    dup
L16:    pop2
L17:    invokestatic Method org/lwjgl/l method2041 (Ljava/nio/IntBuffer;I)V
L20:    iload_1
L21:    aload_2
L22:    invokestatic Method org/lwjgl/MemoryUtil method1884 (Ljava/nio/IntBuffer;)J
L25:    lload_3
L26:    invokestatic Method org/lwjgl/opengl/GL43 nglGetFramebufferParameteriv (IIJJ)V
L29:    return
L30:    
    .end code
.end method

.method static native nglDebugMessageInsert : (IIIIIJJ)V
.end method

.method public static method4580 : (IIII)V
    .code stack 6 locals 6
L0:     invokestatic Method org/lwjgl/opengl/GLContext method4611 ()Lorg/lwjgl/opengl/kb;
L3:     getfield Field org/lwjgl/opengl/kb BI J
L6:     dup2
L7:     lstore 4
L9:     invokestatic Method org/lwjgl/l method2052 (J)V
L12:    iload_0
L13:    iload_1
L14:    iload_2
L15:    iload_3
L16:    lload 4
L18:    invokestatic Method org/lwjgl/opengl/GL43 nglVertexAttribLFormat (IIIIJ)V
L21:    return
L22:    
    .end code
.end method

.method static native nglDispatchCompute : (IIIJ)V
.end method

.method static native nglGetInternalformati64v : (IIIIJJ)V
.end method

.method static native nglTexBufferRange : (IIIJJJ)V
.end method

.method static native nglFramebufferParameteri : (IIIJ)V
.end method

.method static native nglDebugMessageCallback : (JJJ)V
.end method

.method static native nglMultiDrawElementsIndirect : (IIJIIJ)V
.end method

.method static native nglMultiDrawElementsIndirectBO : (IIJIIJ)V
.end method

.method public static method4581 : (IILjava/nio/ByteBuffer;)I
    .code stack 6 locals 5
L0:     invokestatic Method org/lwjgl/opengl/GLContext method4611 ()Lorg/lwjgl/opengl/kb;
L3:     getfield Field org/lwjgl/opengl/kb sQ J
L6:     dup2
L7:     lstore_3
L8:     invokestatic Method org/lwjgl/l method2052 (J)V
L11:    iload_0
L12:    aload_2
L13:    dup
L14:    invokestatic Method org/lwjgl/l method2034 (Ljava/nio/ByteBuffer;)V
L17:    invokestatic Method org/lwjgl/l method2033 (Ljava/nio/ByteBuffer;)V
L20:    iload_1
L21:    aload_2
L22:    invokestatic Method org/lwjgl/MemoryUtil method1873 (Ljava/nio/ByteBuffer;)J
L25:    lload_3
L26:    invokestatic Method org/lwjgl/opengl/GL43 nglGetProgramResourceIndex (IIJJ)I
L29:    ireturn
L30:    
    .end code
.end method

.method static native nglMultiDrawArraysIndirect : (IJIIJ)V
.end method

.method static native nglVertexAttribFormat : (IIIZIJ)V
.end method

.method public static method4582 : (III)V
    .code stack 5 locals 5
L0:     invokestatic Method org/lwjgl/opengl/GLContext method4611 ()Lorg/lwjgl/opengl/kb;
L3:     getfield Field org/lwjgl/opengl/kb rI J
L6:     dup2
L7:     lstore_3
L8:     invokestatic Method org/lwjgl/l method2052 (J)V
L11:    iload_0
L12:    iload_1
L13:    iload_2
L14:    lload_3
L15:    invokestatic Method org/lwjgl/opengl/GL43 nglFramebufferParameteri (IIIJ)V
L18:    return
L19:    
    .end code
.end method

.method public static method4583 : (IIIIIIIIIIIIIII)V
    .code stack 17 locals 17
L0:     invokestatic Method org/lwjgl/opengl/GLContext method4611 ()Lorg/lwjgl/opengl/kb;
L3:     getfield Field org/lwjgl/opengl/kb oF J
L6:     dup2
L7:     lstore 15
L9:     invokestatic Method org/lwjgl/l method2052 (J)V
L12:    iload_0
L13:    iload_1
L14:    iload_2
L15:    iload_3
L16:    iload 4
L18:    iload 5
L20:    iload 6
L22:    iload 7
L24:    iload 8
L26:    iload 9
L28:    iload 10
L30:    iload 11
L32:    iload 12
L34:    iload 13
L36:    iload 14
L38:    lload 15
L40:    invokestatic Method org/lwjgl/opengl/GL43 nglCopyImageSubData (IIIIIIIIIIIIIIIJ)V
L43:    return
L44:    
    .end code
.end method

.method static native nglBindVertexBuffer : (IIJIJ)V
.end method

.method public static method4584 : (III)V
    .code stack 5 locals 5
L0:     invokestatic Method org/lwjgl/opengl/GLContext method4611 ()Lorg/lwjgl/opengl/kb;
L3:     getfield Field org/lwjgl/opengl/kb qG J
L6:     dup2
L7:     lstore_3
L8:     invokestatic Method org/lwjgl/l method2052 (J)V
L11:    iload_0
L12:    iload_1
L13:    iload_2
L14:    lload_3
L15:    invokestatic Method org/lwjgl/opengl/GL43 nglDispatchCompute (IIIJ)V
L18:    return
L19:    
    .end code
.end method

.method public static method4585 : (ILjava/nio/ByteBuffer;II)V
    .code stack 7 locals 7
L0:     invokestatic Method org/lwjgl/opengl/GLContext method4611 ()Lorg/lwjgl/opengl/kb;
L3:     astore 4
L5:     aload_1
L6:     aload 4
L8:     dup
L9:     getfield Field org/lwjgl/opengl/kb field5429 J
L12:    dup2
L13:    lstore 5
L15:    invokestatic Method org/lwjgl/l method2052 (J)V
L18:    invokestatic Method org/lwjgl/opengl/Zd method5447 (Lorg/lwjgl/opengl/kb;)V
L21:    bipush 16
L23:    iconst_1
L24:    dup
L25:    pop2
L26:    iload_2
L27:    imul
L28:    invokestatic Method org/lwjgl/l method2054 (Ljava/nio/ByteBuffer;I)V
L31:    iload_0
L32:    aload_1
L33:    invokestatic Method org/lwjgl/MemoryUtil method1873 (Ljava/nio/ByteBuffer;)J
L36:    iload_2
L37:    iload_3
L38:    lload 5
L40:    invokestatic Method org/lwjgl/opengl/GL43 nglMultiDrawArraysIndirect (IJIIJ)V
L43:    return
L44:    
    .end code
.end method

.method public static method4586 : (IIIILjava/nio/ByteBuffer;)V
    .code stack 8 locals 7
L0:     invokestatic Method org/lwjgl/opengl/GLContext method4611 ()Lorg/lwjgl/opengl/kb;
L3:     getfield Field org/lwjgl/opengl/kb um J
L6:     dup2
L7:     lstore 5
L9:     invokestatic Method org/lwjgl/l method2052 (J)V
L12:    iload_0
L13:    aload 4
L15:    iconst_1
L16:    dup
L17:    dup
L18:    pop2
L19:    invokestatic Method org/lwjgl/l method2054 (Ljava/nio/ByteBuffer;I)V
L22:    iload_1
L23:    iload_2
L24:    iload_3
L25:    aload 4
L27:    invokestatic Method org/lwjgl/MemoryUtil method1873 (Ljava/nio/ByteBuffer;)J
L30:    lload 5
L32:    invokestatic Method org/lwjgl/opengl/GL43 nglClearBufferData (IIIIJJ)V
L35:    return
L36:    
    .end code
.end method

.method public static method4587 : (II)V
    .code stack 4 locals 4
L0:     invokestatic Method org/lwjgl/opengl/GLContext method4611 ()Lorg/lwjgl/opengl/kb;
L3:     getfield Field org/lwjgl/opengl/kb PI J
L6:     dup2
L7:     lstore_2
L8:     invokestatic Method org/lwjgl/l method2052 (J)V
L11:    iload_0
L12:    iload_1
L13:    lload_2
L14:    invokestatic Method org/lwjgl/opengl/GL43 nglInvalidateTexImage (IIJ)V
L17:    return
L18:    
    .end code
.end method

.method static native nglGetProgramResourceiv : (IIIIJIJJJ)V
.end method

.method public static method4588 : (IJII)V
    .code stack 7 locals 7
L0:     invokestatic Method org/lwjgl/opengl/GLContext method4611 ()Lorg/lwjgl/opengl/kb;
L3:     dup
L4:     getfield Field org/lwjgl/opengl/kb field5429 J
L7:     dup2
L8:     lstore 5
L10:    invokestatic Method org/lwjgl/l method2052 (J)V
L13:    invokestatic Method org/lwjgl/opengl/Zd this (Lorg/lwjgl/opengl/kb;)V
L16:    iload_0
L17:    lload_1
L18:    iload_3
L19:    iload 4
L21:    lload 5
L23:    invokestatic Method org/lwjgl/opengl/GL43 nglMultiDrawArraysIndirectBO (IJIIJ)V
L26:    return
L27:    
    .end code
.end method

.method public static method4589 : (III)Ljava/lang/String;
    .code stack 10 locals 7
L0:     invokestatic Method org/lwjgl/opengl/GLContext method4611 ()Lorg/lwjgl/opengl/kb;
L3:     dup
L4:     dup2
L5:     getfield Field org/lwjgl/opengl/kb AE J
L8:     dup2
L9:     lstore 4
L11:    invokestatic Method org/lwjgl/l method2052 (J)V
L14:    invokestatic Method org/lwjgl/opengl/bB method5483 (Lorg/lwjgl/opengl/kb;)Ljava/nio/IntBuffer;
L17:    astore_3
L18:    iload_2
L19:    invokestatic Method org/lwjgl/opengl/bB method5470 (Lorg/lwjgl/opengl/kb;I)Ljava/nio/ByteBuffer;
L22:    astore 6
L24:    iload_0
L25:    iload_1
L26:    iload_2
L27:    aload_3
L28:    invokestatic Method org/lwjgl/MemoryUtil method1867 (Ljava/nio/Buffer;)J
L31:    aload 6
L33:    invokestatic Method org/lwjgl/MemoryUtil method1873 (Ljava/nio/ByteBuffer;)J
L36:    lload 4
L38:    invokestatic Method org/lwjgl/opengl/GL43 nglGetObjectLabel (IIIJJJ)V
L41:    aload 6
L43:    dup
L44:    aload_3
L45:    iconst_0
L46:    iconst_1
L47:    dup
L48:    pop2
L49:    invokevirtual Method java/nio/IntBuffer get (I)I
L52:    invokevirtual Method java/nio/ByteBuffer limit (I)Ljava/nio/Buffer;
L55:    pop
L56:    invokestatic Method org/lwjgl/opengl/bB method5469 (Lorg/lwjgl/opengl/kb;Ljava/nio/ByteBuffer;)Ljava/lang/String;
L59:    areturn
L60:    
    .end code
.end method

.method public static method4590 : (IIJIILjava/nio/ByteBuffer;)V
    .code stack 12 locals 9
L0:     invokestatic Method org/lwjgl/opengl/GLContext method4611 ()Lorg/lwjgl/opengl/kb;
L3:     getfield Field org/lwjgl/opengl/kb Ki J
L6:     dup2
L7:     lstore 7
L9:     invokestatic Method org/lwjgl/l method2052 (J)V
L12:    iload_0
L13:    aload 6
L15:    invokestatic Method org/lwjgl/l method2034 (Ljava/nio/ByteBuffer;)V
L18:    iload_1
L19:    lload_2
L20:    aload 6
L22:    invokevirtual Method java/nio/ByteBuffer remaining ()I
L25:    i2l
L26:    iload 4
L28:    iload 5
L30:    aload 6
L32:    invokestatic Method org/lwjgl/MemoryUtil method1873 (Ljava/nio/ByteBuffer;)J
L35:    lload 7
L37:    invokestatic Method org/lwjgl/opengl/GL43 nglClearBufferSubData (IIJJIIJJ)V
L40:    return
L41:    
    .end code
.end method

.method static native nglVertexBindingDivisor : (IIJ)V
.end method

.method public static method4591 : (IILjava/lang/CharSequence;)I
    .code stack 6 locals 6
L0:     invokestatic Method org/lwjgl/opengl/GLContext method4611 ()Lorg/lwjgl/opengl/kb;
L3:     dup
L4:     astore_3
L5:     getfield Field org/lwjgl/opengl/kb lt J
L8:     dup2
L9:     lstore 4
L11:    invokestatic Method org/lwjgl/l method2052 (J)V
L14:    iload_0
L15:    iload_1
L16:    aload_3
L17:    aload_2
L18:    invokestatic Method org/lwjgl/opengl/bB method5478 (Lorg/lwjgl/opengl/kb;Ljava/lang/CharSequence;)J
L21:    lload 4
L23:    invokestatic Method org/lwjgl/opengl/GL43 nglGetProgramResourceLocationIndex (IIJJ)I
L26:    ireturn
L27:    
    .end code
.end method

.method public static method4592 : (IILjava/nio/ByteBuffer;)V
    .code stack 7 locals 5
L0:     invokestatic Method org/lwjgl/opengl/GLContext method4611 ()Lorg/lwjgl/opengl/kb;
L3:     getfield Field org/lwjgl/opengl/kb qd J
L6:     dup2
L7:     lstore_3
L8:     invokestatic Method org/lwjgl/l method2052 (J)V
L11:    iload_0
L12:    aload_2
L13:    invokestatic Method org/lwjgl/l method2034 (Ljava/nio/ByteBuffer;)V
L16:    iload_1
L17:    aload_2
L18:    invokevirtual Method java/nio/ByteBuffer remaining ()I
L21:    aload_2
L22:    invokestatic Method org/lwjgl/MemoryUtil method1873 (Ljava/nio/ByteBuffer;)J
L25:    lload_3
L26:    invokestatic Method org/lwjgl/opengl/GL43 nglPushDebugGroup (IIIJJ)V
L29:    return
L30:    
    .end code
.end method

.method static native nglInvalidateFramebuffer : (IIJJ)V
.end method

.method public static method4593 : (II)V
    .code stack 4 locals 4
L0:     invokestatic Method org/lwjgl/opengl/GLContext method4611 ()Lorg/lwjgl/opengl/kb;
L3:     getfield Field org/lwjgl/opengl/kb sq J
L6:     dup2
L7:     lstore_2
L8:     invokestatic Method org/lwjgl/l method2052 (J)V
L11:    iload_0
L12:    iload_1
L13:    lload_2
L14:    invokestatic Method org/lwjgl/opengl/GL43 nglVertexAttribBinding (IIJ)V
L17:    return
L18:    
    .end code
.end method

.method public static method4594 : (J)V
    .code stack 4 locals 4
L0:     invokestatic Method org/lwjgl/opengl/GLContext method4611 ()Lorg/lwjgl/opengl/kb;
L3:     getfield Field org/lwjgl/opengl/kb sP J
L6:     dup2
L7:     lstore_2
L8:     invokestatic Method org/lwjgl/l method2052 (J)V
L11:    lload_0
L12:    lload_2
L13:    invokestatic Method org/lwjgl/opengl/GL43 nglDispatchComputeIndirect (JJ)V
L16:    return
L17:    
    .end code
.end method

.method public static method4595 : (IIIIIIII)V
    .code stack 10 locals 10
L0:     invokestatic Method org/lwjgl/opengl/GLContext method4611 ()Lorg/lwjgl/opengl/kb;
L3:     getfield Field org/lwjgl/opengl/kb ZI J
L6:     dup2
L7:     lstore 8
L9:     invokestatic Method org/lwjgl/l method2052 (J)V
L12:    iload_0
L13:    iload_1
L14:    iload_2
L15:    iload_3
L16:    iload 4
L18:    iload 5
L20:    iload 6
L22:    iload 7
L24:    lload 8
L26:    invokestatic Method org/lwjgl/opengl/GL43 nglInvalidateTexSubImage (IIIIIIIIJ)V
L29:    return
L30:    
    .end code
.end method

.method public static method4596 : (Lorg/lwjgl/PointerWrapper;Ljava/nio/ByteBuffer;)V
    .code stack 7 locals 4
L0:     invokestatic Method org/lwjgl/opengl/GLContext method4611 ()Lorg/lwjgl/opengl/kb;
L3:     getfield Field org/lwjgl/opengl/kb aF J
L6:     dup2
L7:     lstore_2
L8:     invokestatic Method org/lwjgl/l method2052 (J)V
L11:    aload_1
L12:    ifnull L19
L15:    aload_1
L16:    invokestatic Method org/lwjgl/l method2034 (Ljava/nio/ByteBuffer;)V
L19:    aload_0
L20:    invokeinterface InterfaceMethod org/lwjgl/PointerWrapper getPointer ()J 1
L25:    aload_1
L26:    ifnonnull L38
L29:    iconst_0
L30:    iconst_1
L31:    dup
L32:    pop2
L33:    aload_1
L34:    goto L43
L37:    athrow
L38:    aload_1
L39:    invokevirtual Method java/nio/ByteBuffer remaining ()I
L42:    aload_1
L43:    invokestatic Method org/lwjgl/MemoryUtil method1883 (Ljava/nio/ByteBuffer;)J
L46:    lload_2
L47:    invokestatic Method org/lwjgl/opengl/GL43 nglObjectPtrLabel (JIJJ)V
L50:    return
L51:    
        .attribute StackMap b'\x00\x04\x00\x13\x00\x03\x07\x03\x1C\x07\x02\x86\x04\x00\x00\x00\x25\x00\x00\x00\x01\x07\x02\x8C\x00\x26\x00\x03\x07\x03\x1C\x07\x02\x86\x04\x00\x01\x04\x00\x2B\x00\x03\x07\x03\x1C\x07\x02\x86\x04\x00\x03\x04\x01\x07\x02\x86'
    .end code
.end method

.method public static method4597 : (IIJII)V
    .code stack 8 locals 8
L0:     invokestatic Method org/lwjgl/opengl/GLContext method4611 ()Lorg/lwjgl/opengl/kb;
L3:     dup
L4:     getfield Field org/lwjgl/opengl/kb Xe J
L7:     dup2
L8:     lstore 6
L10:    invokestatic Method org/lwjgl/l method2052 (J)V
L13:    invokestatic Method org/lwjgl/opengl/Zd this (Lorg/lwjgl/opengl/kb;)V
L16:    iload_0
L17:    iload_1
L18:    lload_2
L19:    iload 4
L21:    iload 5
L23:    lload 6
L25:    invokestatic Method org/lwjgl/opengl/GL43 nglMultiDrawElementsIndirectBO (IIJIIJ)V
L28:    return
L29:    
    .end code
.end method

.method static native nglInvalidateSubFramebuffer : (IIJIIIIJ)V
.end method

.method static native nglTexStorage2DMultisample : (IIIIIZJ)V
.end method

.method public static method4598 : (Lorg/lwjgl/PointerWrapper;Ljava/lang/CharSequence;)V
    .code stack 7 locals 5
L0:     invokestatic Method org/lwjgl/opengl/GLContext method4611 ()Lorg/lwjgl/opengl/kb;
L3:     astore_2
L4:     aload_0
L5:     aload_2
L6:     getfield Field org/lwjgl/opengl/kb aF J
L9:     dup2
L10:    lstore_3
L11:    invokestatic Method org/lwjgl/l method2052 (J)V
L14:    invokeinterface InterfaceMethod org/lwjgl/PointerWrapper getPointer ()J 1
L19:    aload_1
L20:    invokeinterface InterfaceMethod java/lang/CharSequence length ()I 1
L25:    aload_2
L26:    aload_1
L27:    invokestatic Method org/lwjgl/opengl/bB method5468 (Lorg/lwjgl/opengl/kb;Ljava/lang/CharSequence;)J
L30:    lload_3
L31:    invokestatic Method org/lwjgl/opengl/GL43 nglObjectPtrLabel (JIJJ)V
L34:    return
L35:    
    .end code
.end method

.method static native nglInvalidateBufferData : (IJ)V
.end method
.innerclasses
    org/lwjgl/opengl/F org/lwjgl/opengl/nA [0] public static interface abstract
.end innerclasses
.end class
