.version 49 0
.class public final super org/lwjgl/opengl/GLContext
.super java/lang/Object
.field private static final field4205 Ljava/lang/ThreadLocal;
.field private static this Lorg/lwjgl/opengl/iB;
.field private static field4206 Z
.field private static final field4207 Ljava/util/Map;
.field private static final field4208 Ljava/lang/ThreadLocal;
.field private static field4209 I

.method private static method4599 : ()Lorg/lwjgl/opengl/kb;
    .code stack 2 locals 1
L0:     getstatic Field org/lwjgl/opengl/GLContext this Lorg/lwjgl/opengl/iB;
L3:     dup
L4:     astore_0
L5:     getfield Field org/lwjgl/opengl/iB field5387 Ljava/lang/Thread;
L8:     invokestatic Method java/lang/Thread currentThread ()Ljava/lang/Thread;
L11:    if_acmpne L20
L14:    aload_0
L15:    getfield Field org/lwjgl/opengl/iB field5386 Lorg/lwjgl/opengl/kb;
L18:    areturn
L19:    athrow
L20:    invokestatic Method org/lwjgl/opengl/GLContext method4601 ()Lorg/lwjgl/opengl/kb;
L23:    areturn
L24:    
        .attribute StackMap b'\x00\x02\x00\x13\x00\x00\x00\x01\x07\x00\x29\x00\x14\x00\x01\x07\x00\x08\x00\x00'
    .end code
.end method

.method static native resetNativeStubs : (Ljava/lang/Class;)V
.end method

.method public static synchronized method4600 : ()V
    .code stack 4 locals 0
L0:     getstatic Field org/lwjgl/opengl/GLContext field4209 I
L3:     ifne L9
L6:     invokestatic Method org/lwjgl/opengl/GLContext nLoadOpenGLLibrary ()V
L9:     getstatic Field org/lwjgl/opengl/GLContext field4209 I
L12:    iconst_1
L13:    dup
L14:    dup
L15:    pop2
L16:    iadd
L17:    putstatic Field org/lwjgl/opengl/GLContext field4209 I
L20:    return
L21:    
        .attribute StackMap b'\x00\x01\x00\x09\x00\x00\x00\x00'
    .end code
    .exceptions org/lwjgl/LWJGLException
.end method

.method private static native nLoadOpenGLLibrary : ()V
    .exceptions org/lwjgl/LWJGLException
.end method

.method private static method4601 : ()Lorg/lwjgl/opengl/kb;
    .code stack 1 locals 0
L0:     getstatic Field org/lwjgl/opengl/GLContext field4208 Ljava/lang/ThreadLocal;
L3:     invokevirtual Method java/lang/ThreadLocal get ()Ljava/lang/Object;
L6:     checkcast org/lwjgl/opengl/kb
L9:     areturn
L10:    
    .end code
.end method

.method public static synchronized method4602 : ()V
    .code stack 4 locals 0
L0:     getstatic Field org/lwjgl/opengl/GLContext field4209 I
L3:     iconst_1
L4:     dup
L5:     dup
L6:     pop2
L7:     isub
L8:     putstatic Field org/lwjgl/opengl/GLContext field4209 I
L11:    getstatic Field org/lwjgl/opengl/GLContext field4209 I
L14:    ifne L30
L17:    invokestatic Method org/lwjgl/LWJGLUtil getPlatform ()I
L20:    iconst_1
L21:    dup
L22:    dup
L23:    pop2
L24:    if_icmpeq L30
L27:    invokestatic Method org/lwjgl/opengl/GLContext nUnloadOpenGLLibrary ()V
L30:    return
L31:    
        .attribute StackMap b'\x00\x01\x00\x1E\x00\x00\x00\x00'
    .end code
.end method

.method static method4603 : ([Ljava/lang/String;)J
    .code stack 4 locals 6
L0:     aload_0
L1:     dup
L2:     astore_1
L3:     arraylength
L4:     istore_2
L5:     iconst_0
L6:     iconst_1
L7:     dup
L8:     pop2
L9:     dup
L10:    istore_3
L11:    iload_2
L12:    if_icmpge L41
L15:    aload_1
L16:    iload_3
L17:    aaload
L18:    invokestatic Method org/lwjgl/opengl/GLContext method4610 (Ljava/lang/String;)J
L21:    dup2
L22:    lstore 4
L24:    lconst_0
L25:    lcmp
L26:    ifeq L33
L29:    lload 4
L31:    lreturn
L32:    athrow
L33:    iinc 3 1
L36:    iload_3
L37:    goto L11
L40:    athrow
L41:    lconst_0
L42:    lreturn
L43:    
        .attribute StackMap b'\x00\x05\x00\x0B\x00\x04\x07\x00\x4F\x07\x00\x4F\x01\x01\x00\x01\x01\x00\x20\x00\x00\x00\x01\x07\x00\x29\x00\x21\x00\x05\x07\x00\x4F\x07\x00\x4F\x01\x01\x04\x00\x00\x00\x28\x00\x00\x00\x01\x07\x00\x29\x00\x29\x00\x04\x07\x00\x4F\x07\x00\x4F\x01\x01\x00\x00'
    .end code
.end method

.method public static synchronized method4604 : (Ljava/lang/Object;Z)V
    .code stack 4 locals 3
L0:     aload_0
L1:     ifnonnull L22
L4:     invokestatic Method org/lwjgl/opengl/kb F ()V
L7:     aconst_null
L8:     invokestatic Method org/lwjgl/opengl/GLContext method4607 (Lorg/lwjgl/opengl/kb;)V
L11:    getstatic Field org/lwjgl/opengl/GLContext field4206 Z
L14:    ifeq L20
L17:    invokestatic Method org/lwjgl/opengl/GLContext method4602 ()V
L20:    return
L21:    athrow
L22:    getstatic Field org/lwjgl/opengl/GLContext field4209 I
L25:    ifne L38
L28:    invokestatic Method org/lwjgl/opengl/GLContext method4600 ()V
L31:    iconst_1
L32:    dup
L33:    dup
L34:    pop2
L35:    putstatic Field org/lwjgl/opengl/GLContext field4206 Z
        .catch org/lwjgl/LWJGLException from L38 to L77 using L83
L38:    getstatic Field org/lwjgl/opengl/GLContext field4207 Ljava/util/Map;
L41:    aload_0
L42:    invokeinterface InterfaceMethod java/util/Map get (Ljava/lang/Object;)Ljava/lang/Object; 2
L47:    checkcast org/lwjgl/opengl/kb
L50:    dup
L51:    astore_2
L52:    ifnonnull L78
L55:    new org/lwjgl/opengl/kb
L58:    dup
L59:    iload_1
L60:    invokespecial Method org/lwjgl/opengl/kb <init> (Z)V
L63:    getstatic Field org/lwjgl/opengl/GLContext field4207 Ljava/util/Map;
L66:    aload_0
L67:    invokestatic Method org/lwjgl/opengl/GLContext method4611 ()Lorg/lwjgl/opengl/kb;
L70:    invokeinterface InterfaceMethod java/util/Map put (Ljava/lang/Object;Ljava/lang/Object;)Ljava/lang/Object; 3
L75:    pop2
L76:    return
L77:    athrow
        .catch org/lwjgl/LWJGLException from L78 to L82 using L83
L78:    aload_2
L79:    invokestatic Method org/lwjgl/opengl/GLContext method4607 (Lorg/lwjgl/opengl/kb;)V
L82:    return
L83:    astore_2
L84:    getstatic Field org/lwjgl/opengl/GLContext field4206 Z
L87:    ifeq L93
L90:    invokestatic Method org/lwjgl/opengl/GLContext method4602 ()V
L93:    aload_2
L94:    athrow
L95:    athrow
L96:    
        .attribute StackMap b'\x00\x09\x00\x14\x00\x02\x07\x00\x04\x01\x00\x00\x00\x15\x00\x00\x00\x01\x07\x00\x29\x00\x16\x00\x02\x07\x00\x04\x01\x00\x00\x00\x26\x00\x02\x07\x00\x04\x01\x00\x00\x00\x4D\x00\x00\x00\x01\x07\x00\x29\x00\x4E\x00\x03\x07\x00\x04\x01\x07\x00\x41\x00\x00\x00\x53\x00\x02\x07\x00\x04\x01\x00\x01\x07\x00\x32\x00\x5D\x00\x03\x07\x00\x04\x01\x07\x00\x32\x00\x00\x00\x5F\x00\x00\x00\x01\x07\x00\x29'
    .end code
    .exceptions org/lwjgl/LWJGLException
.end method

.method static method4605 : (Ljava/lang/Object;)Lorg/lwjgl/opengl/kb;
    .code stack 2 locals 1
L0:     getstatic Field org/lwjgl/opengl/GLContext field4207 Ljava/util/Map;
L3:     aload_0
L4:     invokeinterface InterfaceMethod java/util/Map get (Ljava/lang/Object;)Ljava/lang/Object; 2
L9:     checkcast org/lwjgl/opengl/kb
L12:    areturn
L13:    
    .end code
.end method

.method public static synchronized method4606 : (Ljava/lang/Object;)V
    .code stack 4 locals 1
L0:     aload_0
L1:     iconst_0
L2:     iconst_1
L3:     dup
L4:     pop2
L5:     invokestatic Method org/lwjgl/opengl/GLContext method4604 (Ljava/lang/Object;Z)V
L8:     return
L9:     
    .end code
    .exceptions org/lwjgl/LWJGLException
.end method

.method static <clinit> : ()V
    .code stack 3 locals 0
L0:     new java/lang/ThreadLocal
L3:     dup
L4:     invokespecial Method java/lang/ThreadLocal <init> ()V
L7:     putstatic Field org/lwjgl/opengl/GLContext field4208 Ljava/lang/ThreadLocal;
L10:    new org/lwjgl/opengl/iB
L13:    dup
L14:    aconst_null
L15:    invokespecial Method org/lwjgl/opengl/iB <init> (Lorg/lwjgl/opengl/Dc;)V
L18:    putstatic Field org/lwjgl/opengl/GLContext this Lorg/lwjgl/opengl/iB;
L21:    new java/lang/ThreadLocal
L24:    dup
L25:    invokespecial Method java/lang/ThreadLocal <init> ()V
L28:    putstatic Field org/lwjgl/opengl/GLContext field4205 Ljava/lang/ThreadLocal;
L31:    new java/util/WeakHashMap
L34:    dup
L35:    invokespecial Method java/util/WeakHashMap <init> ()V
L38:    putstatic Field org/lwjgl/opengl/GLContext field4207 Ljava/util/Map;
L41:    invokestatic Method org/lwjgl/Sys method1895 ()V
L44:    return
L45:    
    .end code
.end method

.method static method4607 : (Lorg/lwjgl/opengl/kb;)V
    .code stack 5 locals 2
L0:     getstatic Field org/lwjgl/opengl/GLContext field4208 Ljava/lang/ThreadLocal;
L3:     aload_0
L4:     invokevirtual Method java/lang/ThreadLocal set (Ljava/lang/Object;)V
L7:     getstatic Field org/lwjgl/opengl/GLContext field4205 Ljava/lang/ThreadLocal;
L10:    invokevirtual Method java/lang/ThreadLocal get ()Ljava/lang/Object;
L13:    checkcast org/lwjgl/opengl/iB
L16:    dup
L17:    astore_1
L18:    ifnonnull L37
L21:    new org/lwjgl/opengl/iB
L24:    dup
L25:    aconst_null
L26:    invokespecial Method org/lwjgl/opengl/iB <init> (Lorg/lwjgl/opengl/Dc;)V
L29:    astore_1
L30:    getstatic Field org/lwjgl/opengl/GLContext field4205 Ljava/lang/ThreadLocal;
L33:    aload_1
L34:    invokevirtual Method java/lang/ThreadLocal set (Ljava/lang/Object;)V
L37:    aload_1
L38:    aload_0
L39:    aload_1
L40:    dup_x1
L41:    invokestatic Method java/lang/Thread currentThread ()Ljava/lang/Thread;
L44:    putfield Field org/lwjgl/opengl/iB field5387 Ljava/lang/Thread;
L47:    putfield Field org/lwjgl/opengl/iB field5386 Lorg/lwjgl/opengl/kb;
L50:    putstatic Field org/lwjgl/opengl/GLContext this Lorg/lwjgl/opengl/iB;
L53:    return
L54:    
        .attribute StackMap b'\x00\x01\x00\x25\x00\x02\x07\x00\x41\x07\x00\x08\x00\x00'
    .end code
.end method

.method public <init> : ()V
    .code stack 1 locals 1
L0:     aload_0
L1:     invokespecial Method java/lang/Object <init> ()V
L4:     return
L5:     
    .end code
.end method

.method static method4608 : (Ljava/lang/Class;Ljava/util/Set;Ljava/lang/String;)V
    .code stack 3 locals 4
L0:     aload_1
L1:     aload_2
L2:     aload_0
L3:     invokestatic Method org/lwjgl/opengl/GLContext resetNativeStubs (Ljava/lang/Class;)V
L6:     invokeinterface InterfaceMethod java/util/Set contains (Ljava/lang/Object;)Z 2
L11:    ifeq L69
        .catch java/lang/Exception from L14 to L26 using L28
L14:    new org/lwjgl/opengl/ib
L17:    dup
L18:    aload_0
L19:    invokespecial Method org/lwjgl/opengl/ib <init> (Ljava/lang/Class;)V
L22:    invokestatic Method java/security/AccessController doPrivileged (Ljava/security/PrivilegedExceptionAction;)Ljava/lang/Object;
L25:    pop
L26:    return
L27:    athrow
L28:    astore_3
L29:    new java/lang/StringBuilder
L32:    dup
L33:    invokespecial Method java/lang/StringBuilder <init> ()V
L36:    iconst_0
L37:    ldc "Failed to initialize extension "
L39:    invokevirtual Method java/lang/StringBuilder insert (ILjava/lang/String;)Ljava/lang/StringBuilder;
L42:    aload_0
L43:    invokevirtual Method java/lang/StringBuilder append (Ljava/lang/Object;)Ljava/lang/StringBuilder;
L46:    ldc " - exception: "
L48:    invokevirtual Method java/lang/StringBuilder append (Ljava/lang/String;)Ljava/lang/StringBuilder;
L51:    aload_3
L52:    invokevirtual Method java/lang/StringBuilder append (Ljava/lang/Object;)Ljava/lang/StringBuilder;
L55:    invokevirtual Method java/lang/StringBuilder toString ()Ljava/lang/String;
L58:    invokestatic Method org/lwjgl/LWJGLUtil log (Ljava/lang/CharSequence;)V
L61:    aload_1
L62:    aload_2
L63:    invokeinterface InterfaceMethod java/util/Set remove (Ljava/lang/Object;)Z 2
L68:    pop
L69:    return
L70:    
        .attribute StackMap b'\x00\x03\x00\x1B\x00\x00\x00\x01\x07\x00\x29\x00\x1C\x00\x03\x07\x00\xA4\x07\x00\x96\x07\x00\xA6\x00\x01\x07\x00\x92\x00\x45\x00\x03\x07\x00\xA4\x07\x00\x96\x07\x00\xA6\x00\x00'
    .end code
.end method

.method static method4609 : (Ljava/lang/String;[Ljava/lang/String;[Ljava/lang/String;Ljava/lang/String;)J
    .code stack 4 locals 6
L0:     new org/lwjgl/opengl/Dc
L3:     dup
L4:     invokespecial Method org/lwjgl/opengl/Dc <init> ()V
L7:     invokestatic Method java/security/AccessController doPrivileged (Ljava/security/PrivilegedAction;)Ljava/lang/Object;
L10:    checkcast java/lang/String
L13:    astore 4
L15:    iconst_0
L16:    iconst_1
L17:    dup
L18:    pop2
L19:    dup
L20:    istore 5
L22:    aload_1
L23:    arraylength
L24:    if_icmpge L62
L27:    aload 4
L29:    aload_1
L30:    iload 5
L32:    aaload
L33:    invokevirtual Method java/lang/String startsWith (Ljava/lang/String;)Z
L36:    ifeq L53
L39:    aload_3
L40:    aload_0
L41:    aload_2
L42:    iload 5
L44:    aaload
L45:    invokevirtual Method java/lang/String replaceFirst (Ljava/lang/String;Ljava/lang/String;)Ljava/lang/String;
L48:    invokestatic Method org/lwjgl/opengl/GLContext method4610 (Ljava/lang/String;)J
L51:    lreturn
L52:    athrow
L53:    iinc 5 1
L56:    iload 5
L58:    goto L22
L61:    athrow
L62:    lconst_0
L63:    lreturn
L64:    
        .attribute StackMap b'\x00\x05\x00\x16\x00\x06\x07\x00\xA6\x07\x00\x4F\x07\x00\x4F\x07\x00\xA6\x07\x00\xA6\x01\x00\x01\x01\x00\x34\x00\x00\x00\x01\x07\x00\x29\x00\x35\x00\x06\x07\x00\xA6\x07\x00\x4F\x07\x00\x4F\x07\x00\xA6\x07\x00\xA6\x01\x00\x00\x00\x3D\x00\x00\x00\x01\x07\x00\x29\x00\x3E\x00\x06\x07\x00\xA6\x07\x00\x4F\x07\x00\x4F\x07\x00\xA6\x07\x00\xA6\x01\x00\x00'
    .end code
.end method

.method private static native ngetFunctionAddress : (J)J
.end method

.method private static native nUnloadOpenGLLibrary : ()V
.end method

.method static method4610 : (Ljava/lang/String;)J
    .code stack 2 locals 1
L0:     aload_0
L1:     invokestatic Method org/lwjgl/MemoryUtil method1846 (Ljava/lang/CharSequence;)Ljava/nio/ByteBuffer;
L4:     invokestatic Method org/lwjgl/MemoryUtil method1873 (Ljava/nio/ByteBuffer;)J
L7:     invokestatic Method org/lwjgl/opengl/GLContext ngetFunctionAddress (J)J
L10:    lreturn
L11:    
    .end code
.end method

.method public static method4611 : ()Lorg/lwjgl/opengl/kb;
    .code stack 3 locals 1
L0:     invokestatic Method org/lwjgl/opengl/GLContext method4599 ()Lorg/lwjgl/opengl/kb;
L3:     dup
L4:     astore_0
L5:     ifnonnull L18
L8:     new java/lang/RuntimeException
L11:    dup
L12:    ldc "No OpenGL context found in the current thread."
L14:    invokespecial Method java/lang/RuntimeException <init> (Ljava/lang/String;)V
L17:    athrow
L18:    aload_0
L19:    areturn
L20:    
        .attribute StackMap b'\x00\x01\x00\x12\x00\x01\x07\x00\x41\x00\x00'
    .end code
.end method

.method static method4612 : (Ljava/util/Set;)I
    .code stack 9 locals 10
L0:     sipush 7938
L3:     iconst_1
L4:     dup
L5:     pop2
L6:     invokestatic Method org/lwjgl/opengl/GL11 method3867 (I)Ljava/lang/String;
L9:     dup
L10:    astore_1
L11:    ifnonnull L24
L14:    new java/lang/IllegalStateException
L17:    dup
L18:    ldc "glGetString(GL_VERSION) returned null - possibly caused by missing current context."
L20:    invokespecial Method java/lang/IllegalStateException <init> (Ljava/lang/String;)V
L23:    athrow
L24:    new java/util/StringTokenizer
L27:    dup
L28:    aload_1
L29:    ldc ". "
L31:    invokespecial Method java/util/StringTokenizer <init> (Ljava/lang/String;Ljava/lang/String;)V
L34:    dup
L35:    invokevirtual Method java/util/StringTokenizer nextToken ()Ljava/lang/String;
L38:    astore_1
L39:    invokevirtual Method java/util/StringTokenizer nextToken ()Ljava/lang/String;
L42:    astore_2
L43:    iconst_0
L44:    iconst_1
L45:    dup
L46:    pop2
L47:    istore_3
L48:    iconst_0
L49:    iconst_1
L50:    dup
L51:    pop2
L52:    istore 4
        .catch java/lang/NumberFormatException from L54 to L65 using L69
L54:    aload_1
L55:    invokestatic Method java/lang/Integer parseInt (Ljava/lang/String;)I
L58:    istore_3
L59:    aload_2
L60:    invokestatic Method java/lang/Integer parseInt (Ljava/lang/String;)I
L63:    istore 4
L65:    goto L97
L68:    athrow
L69:    astore_1
L70:    new java/lang/StringBuilder
L73:    dup
L74:    invokespecial Method java/lang/StringBuilder <init> ()V
L77:    iconst_0
L78:    ldc_w "The major and/or minor OpenGL version is malformed: "
L81:    invokevirtual Method java/lang/StringBuilder insert (ILjava/lang/String;)Ljava/lang/StringBuilder;
L84:    aload_1
L85:    invokevirtual Method java/lang/NumberFormatException getMessage ()Ljava/lang/String;
L88:    invokevirtual Method java/lang/StringBuilder append (Ljava/lang/String;)Ljava/lang/StringBuilder;
L91:    invokevirtual Method java/lang/StringBuilder toString ()Ljava/lang/String;
L94:    invokestatic Method org/lwjgl/LWJGLUtil log (Ljava/lang/CharSequence;)V
L97:    iconst_4
L98:    iconst_1
L99:    dup
L100:   pop2
L101:   anewarray [I
L104:   iconst_1
L105:   dup
L106:   pop2
L107:   dup
L108:   iconst_1
L109:   dup
L110:   pop2
L111:   iconst_5
L112:   iconst_1
L113:   dup
L114:   pop2
L115:   newarray int
L117:   iconst_1
L118:   dup
L119:   pop2
L120:   dup
L121:   iconst_0
L122:   dup_x2
L123:   iconst_1
L124:   dup
L125:   pop2
L126:   iconst_1
L127:   dup
L128:   dup
L129:   pop2
L130:   iastore
L131:   dup
L132:   iconst_1
L133:   dup
L134:   pop2
L135:   iconst_2
L136:   iconst_1
L137:   dup_x1
L138:   dup
L139:   pop2
L140:   iastore
L141:   dup
L142:   iconst_2
L143:   iconst_1
L144:   dup
L145:   pop2
L146:   iconst_3
L147:   iconst_1
L148:   dup
L149:   pop2
L150:   iastore
L151:   dup
L152:   iconst_3
L153:   iconst_1
L154:   dup
L155:   pop2
L156:   iconst_4
L157:   iconst_1
L158:   dup
L159:   pop2
L160:   iastore
L161:   dup
L162:   iconst_4
L163:   iconst_1
L164:   dup
L165:   pop2
L166:   iconst_5
L167:   iconst_1
L168:   dup
L169:   pop2
L170:   iastore
L171:   aastore
L172:   dup
L173:   iconst_1
L174:   dup
L175:   pop2
L176:   iconst_2
L177:   iconst_1
L178:   dup
L179:   pop2
L180:   newarray int
L182:   iconst_1
L183:   dup
L184:   pop2
L185:   dup
L186:   iconst_0
L187:   iconst_1
L188:   dup
L189:   pop2
L190:   iconst_0
L191:   iconst_1
L192:   dup
L193:   pop2
L194:   iastore
L195:   dup
L196:   iconst_1
L197:   dup_x2
L198:   iconst_1
L199:   dup
L200:   pop2
L201:   iconst_1
L202:   dup
L203:   dup
L204:   pop2
L205:   iastore
L206:   aastore
L207:   dup
L208:   iconst_1
L209:   dup
L210:   pop2
L211:   iconst_4
L212:   iconst_1
L213:   dup
L214:   pop2
L215:   newarray int
L217:   iconst_1
L218:   dup
L219:   pop2
L220:   dup
L221:   iconst_0
L222:   iconst_1
L223:   dup
L224:   pop2
L225:   iconst_0
L226:   iconst_1
L227:   dup
L228:   pop2
L229:   iastore
L230:   dup
L231:   iconst_1
L232:   dup
L233:   pop2
L234:   iconst_1
L235:   dup
L236:   dup_x1
L237:   dup
L238:   pop2
L239:   iastore
L240:   dup
L241:   iconst_2
L242:   dup_x2
L243:   iconst_1
L244:   dup
L245:   pop2
L246:   iconst_2
L247:   iconst_1
L248:   dup
L249:   pop2
L250:   iastore
L251:   dup
L252:   iconst_3
L253:   iconst_1
L254:   dup
L255:   pop2
L256:   iconst_3
L257:   iconst_1
L258:   dup
L259:   pop2
L260:   iastore
L261:   aastore
L262:   dup
L263:   iconst_3
L264:   iconst_1
L265:   dup
L266:   pop2
L267:   iconst_3
L268:   iconst_1
L269:   dup
L270:   pop2
L271:   newarray int
L273:   iconst_1
L274:   dup
L275:   pop2
L276:   dup
L277:   iconst_0
L278:   iconst_1
L279:   dup
L280:   pop2
L281:   iconst_0
L282:   iconst_1
L283:   dup
L284:   pop2
L285:   iastore
L286:   dup
L287:   iconst_1
L288:   dup
L289:   pop2
L290:   iconst_1
L291:   dup
L292:   dup_x1
L293:   dup
L294:   pop2
L295:   iastore
L296:   dup
L297:   iconst_2
L298:   iconst_1
L299:   dup
L300:   pop2
L301:   iconst_2
L302:   iconst_1
L303:   dup
L304:   pop2
L305:   iastore
L306:   aastore
L307:   astore_1
L308:   iconst_1
L309:   dup
L310:   dup
L311:   pop2
L312:   dup
L313:   istore_2
L314:   aload_1
L315:   arraylength
L316:   if_icmpgt L428
L319:   aload_1
L320:   iload_2
L321:   iconst_1
L322:   dup
L323:   dup
L324:   pop2
L325:   isub
L326:   aaload
L327:   dup
L328:   astore 5
L330:   astore 6
L332:   aload 6
L334:   arraylength
L335:   istore 7
L337:   iconst_0
L338:   iconst_1
L339:   dup
L340:   pop2
L341:   dup
L342:   istore 8
L344:   iload 7
L346:   if_icmpge L421
L349:   aload 6
L351:   iload 8
L353:   iaload
L354:   istore 9
L356:   iload_2
L357:   iload_3
L358:   if_icmplt L373
L361:   iload_2
L362:   iload_3
L363:   if_icmpne L412
L366:   iload 9
L368:   iload 4
L370:   if_icmpgt L412
L373:   aload_0
L374:   new java/lang/StringBuilder
L377:   dup
L378:   invokespecial Method java/lang/StringBuilder <init> ()V
L381:   iconst_0
L382:   ldc_w "OpenGL"
L385:   invokevirtual Method java/lang/StringBuilder insert (ILjava/lang/String;)Ljava/lang/StringBuilder;
L388:   iload_2
L389:   invokestatic Method java/lang/Integer toString (I)Ljava/lang/String;
L392:   invokevirtual Method java/lang/StringBuilder append (Ljava/lang/String;)Ljava/lang/StringBuilder;
L395:   iload 9
L397:   invokestatic Method java/lang/Integer toString (I)Ljava/lang/String;
L400:   invokevirtual Method java/lang/StringBuilder append (Ljava/lang/String;)Ljava/lang/StringBuilder;
L403:   invokevirtual Method java/lang/StringBuilder toString ()Ljava/lang/String;
L406:   invokeinterface InterfaceMethod java/util/Set add (Ljava/lang/Object;)Z 2
L411:   pop
L412:   iinc 8 1
L415:   iload 8
L417:   goto L344
L420:   athrow
L421:   iinc 2 1
L424:   iload_2
L425:   goto L314
L428:   iconst_0
L429:   iconst_1
L430:   dup
L431:   pop2
L432:   istore_2
L433:   iload_3
L434:   iconst_3
L435:   iconst_1
L436:   dup
L437:   pop2
L438:   if_icmpge L504
L441:   sipush 7939
L444:   iconst_1
L445:   dup
L446:   pop2
L447:   invokestatic Method org/lwjgl/opengl/GL11 method3867 (I)Ljava/lang/String;
L450:   dup
L451:   astore 5
L453:   ifnonnull L467
L456:   new java/lang/IllegalStateException
L459:   dup
L460:   ldc_w "glGetString(GL_EXTENSIONS) returned null - is there a context current?"
L463:   invokespecial Method java/lang/IllegalStateException <init> (Ljava/lang/String;)V
L466:   athrow
L467:   new java/util/StringTokenizer
L470:   dup
L471:   aload 5
L473:   invokespecial Method java/util/StringTokenizer <init> (Ljava/lang/String;)V
L476:   dup
L477:   astore 6
L479:   invokevirtual Method java/util/StringTokenizer hasMoreTokens ()Z
L482:   ifeq L590
L485:   aload_0
L486:   aload 6
L488:   dup_x1
L489:   invokevirtual Method java/util/StringTokenizer nextToken ()Ljava/lang/String;
L492:   invokeinterface InterfaceMethod java/util/Set add (Ljava/lang/Object;)Z 2
L497:   pop
L498:   goto L479
L501:   nop
L502:   nop
L503:   athrow
L504:   ldc_w 33309
L507:   invokestatic Method org/lwjgl/opengl/GL11 method3721 (I)I
L510:   istore 5
L512:   iconst_0
L513:   iconst_1
L514:   dup
L515:   pop2
L516:   dup
L517:   istore 6
L519:   iload 5
L521:   if_icmpge L550
L524:   aload_0
L525:   sipush 7939
L528:   iconst_1
L529:   dup
L530:   pop2
L531:   iload 6
L533:   iinc 6 1
L536:   invokestatic Method org/lwjgl/opengl/GL30 this (II)Ljava/lang/String;
L539:   invokeinterface InterfaceMethod java/util/Set add (Ljava/lang/Object;)Z 2
L544:   pop
L545:   iload 6
L547:   goto L519
L550:   iconst_3
L551:   iconst_1
L552:   dup
L553:   pop2
L554:   iload_3
L555:   if_icmplt L567
L558:   iconst_2
L559:   iconst_1
L560:   dup
L561:   pop2
L562:   iload 4
L564:   if_icmpgt L590
L567:   invokestatic Method org/lwjgl/opengl/n method5630 ()V
        .catch org/lwjgl/opengl/x from L570 to L580 using L582
L570:   ldc_w 37158
L573:   invokestatic Method org/lwjgl/opengl/GL11 method3721 (I)I
L576:   istore_2
L577:   invokestatic Method org/lwjgl/opengl/n method5630 ()V
L580:   iload_2
L581:   ireturn
L582:   astore 6
L584:   ldc_w "Failed to retrieve CONTEXT_PROFILE_MASK"
L587:   invokestatic Method org/lwjgl/LWJGLUtil log (Ljava/lang/CharSequence;)V
L590:   iload_2
L591:   ireturn
L592:   
        .attribute StackMap b'\x00\x14\x00\x18\x00\x02\x07\x00\x96\x07\x00\xA6\x00\x00\x00\x44\x00\x00\x00\x01\x07\x00\x29\x00\x45\x00\x05\x07\x00\x96\x07\x00\xA6\x07\x00\xA6\x01\x01\x00\x01\x07\x00\xEC\x00\x61\x00\x05\x07\x00\x96\x07\x00\x04\x07\x00\xA6\x01\x01\x00\x00\x01\x3A\x00\x05\x07\x00\x96\x07\x01\x12\x01\x01\x01\x00\x01\x01\x01\x58\x00\x09\x07\x00\x96\x07\x01\x12\x01\x01\x01\x07\x01\x10\x07\x01\x10\x01\x01\x00\x01\x01\x01\x75\x00\x0A\x07\x00\x96\x07\x01\x12\x01\x01\x01\x07\x01\x10\x07\x01\x10\x01\x01\x01\x00\x00\x01\x9C\x00\x0A\x07\x00\x96\x07\x01\x12\x01\x01\x01\x07\x01\x10\x07\x01\x10\x01\x01\x01\x00\x00\x01\xA4\x00\x00\x00\x01\x07\x00\x29\x01\xA5\x00\x09\x07\x00\x96\x07\x01\x12\x01\x01\x01\x07\x01\x10\x07\x01\x10\x01\x01\x00\x00\x01\xAC\x00\x05\x07\x00\x96\x07\x01\x12\x01\x01\x01\x00\x00\x01\xD3\x00\x06\x07\x00\x96\x07\x01\x12\x01\x01\x01\x07\x00\xA6\x00\x00\x01\xDF\x00\x07\x07\x00\x96\x07\x01\x12\x01\x01\x01\x07\x00\xA6\x07\x00\xFB\x00\x01\x07\x00\xFB\x01\xF5\x00\x00\x00\x01\x07\x00\x29\x01\xF8\x00\x05\x07\x00\x96\x07\x01\x12\x01\x01\x01\x00\x00\x02\x07\x00\x07\x07\x00\x96\x07\x01\x12\x01\x01\x01\x01\x01\x00\x01\x01\x02\x26\x00\x07\x07\x00\x96\x07\x01\x12\x01\x01\x01\x01\x01\x00\x00\x02\x37\x00\x07\x07\x00\x96\x07\x01\x12\x01\x01\x01\x01\x01\x00\x00\x02\x46\x00\x07\x07\x00\x96\x07\x01\x12\x01\x01\x01\x01\x01\x00\x01\x07\x00\xEE\x02\x4E\x00\x05\x07\x00\x96\x07\x01\x12\x01\x01\x01\x00\x00'
    .end code
.end method
.innerclasses
    org/lwjgl/opengl/Dc [0] [0] static
    org/lwjgl/opengl/iB org/lwjgl/opengl/GLContext [0] private static final
    org/lwjgl/opengl/ib [0] [0] static
.end innerclasses
.end class
