.version 49 0
.class public final super org/lwjgl/opengl/Kc
.super java/lang/Object
.field public static final field4342 I = 2978
.field public static final field4343 I = 33374
.field public static final field4344 I = 36431
.field public static final field4345 I = 36429
.field public static final try I = 36430
.field public static final field4346 I = 33373
.field public static final new I = 2928
.field public static final field4347 I = 33371
.field public static final this I = 33375
.field public static final field4348 I = 3088
.field public static final field4349 I = 3089
.field public static final field4350 I = 33372
.field public static final field4351 I = 33376

.method private <init> : ()V
    .code stack 1 locals 1
L0:     aload_0
L1:     invokespecial Method java/lang/Object <init> ()V
L4:     return
L5:     
    .end code
.end method

.method public static method4640 : (II)D
    .code stack 2 locals 2
L0:     iload_0
L1:     iload_1
L2:     invokestatic Method org/lwjgl/opengl/GL41 method4502 (II)D
L5:     dreturn
L6:     
    .end code
.end method

.method public static method4641 : (ILjava/nio/FloatBuffer;)V
    .code stack 2 locals 2
L0:     iload_0
L1:     aload_1
L2:     invokestatic Method org/lwjgl/opengl/GL41 method4484 (ILjava/nio/FloatBuffer;)V
L5:     return
L6:     
    .end code
.end method

.method public static method4642 : (IILjava/nio/DoubleBuffer;)V
    .code stack 3 locals 3
L0:     iload_0
L1:     iload_1
L2:     aload_2
L3:     invokestatic Method org/lwjgl/opengl/GL41 method4468 (IILjava/nio/DoubleBuffer;)V
L6:     return
L7:     
    .end code
.end method

.method public static method4643 : (II)V
    .code stack 2 locals 2
L0:     iload_0
L1:     iload_1
L2:     invokestatic Method org/lwjgl/opengl/EXTDrawBuffers2 method3400 (II)V
L5:     return
L6:     
    .end code
.end method

.method public static method4644 : (IDD)V
    .code stack 5 locals 5
L0:     iload_0
L1:     dload_1
L2:     dload_3
L3:     invokestatic Method org/lwjgl/opengl/GL41 method4476 (IDD)V
L6:     return
L7:     
    .end code
.end method

.method public static method4645 : (ILjava/nio/IntBuffer;)V
    .code stack 2 locals 2
L0:     iload_0
L1:     aload_1
L2:     invokestatic Method org/lwjgl/opengl/GL41 method4439 (ILjava/nio/IntBuffer;)V
L5:     return
L6:     
    .end code
.end method

.method public static method4646 : (IFFFF)V
    .code stack 5 locals 5
L0:     iload_0
L1:     fload_1
L2:     fload_2
L3:     fload_3
L4:     fload 4
L6:     invokestatic Method org/lwjgl/opengl/GL41 method4448 (IFFFF)V
L9:     return
L10:    
    .end code
.end method

.method public static method4647 : (ILjava/nio/DoubleBuffer;)V
    .code stack 2 locals 2
L0:     iload_0
L1:     aload_1
L2:     invokestatic Method org/lwjgl/opengl/GL41 method4433 (ILjava/nio/DoubleBuffer;)V
L5:     return
L6:     
    .end code
.end method

.method public static method4648 : (IILjava/nio/IntBuffer;)V
    .code stack 3 locals 3
L0:     iload_0
L1:     iload_1
L2:     aload_2
L3:     invokestatic Method org/lwjgl/opengl/EXTDrawBuffers2 method3394 (IILjava/nio/IntBuffer;)V
L6:     return
L7:     
    .end code
.end method

.method public static method4649 : (ILjava/nio/FloatBuffer;)V
    .code stack 2 locals 2
L0:     iload_0
L1:     aload_1
L2:     invokestatic Method org/lwjgl/opengl/GL41 method4429 (ILjava/nio/FloatBuffer;)V
L5:     return
L6:     
    .end code
.end method

.method public static method4650 : (II)V
    .code stack 2 locals 2
L0:     iload_0
L1:     iload_1
L2:     invokestatic Method org/lwjgl/opengl/EXTDrawBuffers2 method3399 (II)V
L5:     return
L6:     
    .end code
.end method

.method public static method4651 : (II)F
    .code stack 2 locals 2
L0:     iload_0
L1:     iload_1
L2:     invokestatic Method org/lwjgl/opengl/GL41 method4473 (II)F
L5:     freturn
L6:     
    .end code
.end method

.method public static method4652 : (IILjava/nio/FloatBuffer;)V
    .code stack 3 locals 3
L0:     iload_0
L1:     iload_1
L2:     aload_2
L3:     invokestatic Method org/lwjgl/opengl/GL41 method4449 (IILjava/nio/FloatBuffer;)V
L6:     return
L7:     
    .end code
.end method

.method public static method4653 : (ILjava/nio/IntBuffer;)V
    .code stack 2 locals 2
L0:     iload_0
L1:     aload_1
L2:     invokestatic Method org/lwjgl/opengl/GL41 method4446 (ILjava/nio/IntBuffer;)V
L5:     return
L6:     
    .end code
.end method

.method public static method4654 : (II)Z
    .code stack 2 locals 2
L0:     iload_0
L1:     iload_1
L2:     invokestatic Method org/lwjgl/opengl/EXTDrawBuffers2 method3397 (II)Z
L5:     ireturn
L6:     
    .end code
.end method

.method public static method4655 : (IIIII)V
    .code stack 5 locals 5
L0:     iload_0
L1:     iload_1
L2:     iload_2
L3:     iload_3
L4:     iload 4
L6:     invokestatic Method org/lwjgl/opengl/GL41 method4470 (IIIII)V
L9:     return
L10:    
    .end code
.end method

.method public static method4656 : (II)I
    .code stack 2 locals 2
L0:     iload_0
L1:     iload_1
L2:     invokestatic Method org/lwjgl/opengl/EXTDrawBuffers2 method3396 (II)I
L5:     ireturn
L6:     
    .end code
.end method
.end class
