.version 49 0
.class final super org/lwjgl/opengl/LinuxCanvasImplementation
.super java/lang/Object
.implements org/lwjgl/opengl/e

.method static break : (Ljava/awt/GraphicsDevice;)I
    .code stack 5 locals 2
        .catch java/lang/Exception from L0 to L36 using L38
L0:     new org/lwjgl/opengl/yA
L3:     dup
L4:     aload_0
L5:     invokespecial Method org/lwjgl/opengl/yA <init> (Ljava/awt/GraphicsDevice;)V
L8:     invokestatic Method java/security/AccessController doPrivileged (Ljava/security/PrivilegedExceptionAction;)Ljava/lang/Object;
L11:    checkcast java/lang/reflect/Method
L14:    dup
L15:    astore_1
L16:    aload_0
L17:    iconst_0
L18:    iconst_1
L19:    dup
L20:    pop2
L21:    anewarray java/lang/Object
L24:    iconst_1
L25:    dup
L26:    pop2
L27:    invokevirtual Method java/lang/reflect/Method invoke (Ljava/lang/Object;[Ljava/lang/Object;)Ljava/lang/Object;
L30:    checkcast java/lang/Integer
L33:    invokevirtual Method java/lang/Integer intValue ()I
L36:    ireturn
L37:    athrow
L38:    astore_1
L39:    new org/lwjgl/LWJGLException
L42:    dup
L43:    aload_1
L44:    invokespecial Method org/lwjgl/LWJGLException <init> (Ljava/lang/Throwable;)V
L47:    athrow
L48:    
        .attribute StackMap b'\x00\x02\x00\x25\x00\x00\x00\x01\x07\x00\x28\x00\x26\x00\x01\x07\x00\x2A\x00\x01\x07\x00\x10'
    .end code
    .exceptions org/lwjgl/LWJGLException
.end method

.method private static break : (ILorg/lwjgl/opengl/PixelFormat;)I
    .code stack 4 locals 5
L0:     invokestatic Method org/lwjgl/opengl/LinuxDisplay "interface" ()V
L3:     invokestatic Method org/lwjgl/opengl/GLContext short ()V
        .catch [0] from L6 to L18 using L30
L6:     invokestatic Method org/lwjgl/opengl/LinuxDisplay "private" ()V
L9:     invokestatic Method org/lwjgl/opengl/LinuxDisplay "strictfp" ()J
L12:    iload_0
L13:    aload_1
L14:    invokestatic Method org/lwjgl/opengl/LinuxCanvasImplementation nFindVisualIDFromFormat (JILorg/lwjgl/opengl/PixelFormat;)I
L17:    istore_1
L18:    invokestatic Method org/lwjgl/opengl/LinuxDisplay F ()V
L21:    invokestatic Method org/lwjgl/opengl/GLContext else ()V
L24:    invokestatic Method org/lwjgl/opengl/LinuxDisplay while ()V
L27:    iload_1
L28:    ireturn
L29:    athrow
        .catch [0] from L30 to L31 using L30
        .catch [0] from L3 to L21 using L36
        .catch [0] from L30 to L37 using L36
        .catch [0] from L0 to L24 using L42
        .catch [0] from L30 to L44 using L42
L30:    astore_2
L31:    invokestatic Method org/lwjgl/opengl/LinuxDisplay F ()V
L34:    aload_2
L35:    athrow
L36:    astore_3
L37:    invokestatic Method org/lwjgl/opengl/GLContext else ()V
L40:    aload_3
L41:    athrow
L42:    astore 4
L44:    invokestatic Method org/lwjgl/opengl/LinuxDisplay while ()V
L47:    aload 4
L49:    athrow
L50:    
        .attribute StackMap b'\x00\x04\x00\x1D\x00\x00\x00\x01\x07\x00\x28\x00\x1E\x00\x01\x01\x00\x01\x07\x00\x28\x00\x24\x00\x01\x01\x00\x01\x07\x00\x28\x00\x2A\x00\x01\x01\x00\x01\x07\x00\x28'
    .end code
    .exceptions org/lwjgl/LWJGLException
.end method

.method private static break : (Ljava/awt/GraphicsConfiguration;)I
    .code stack 5 locals 2
        .catch java/lang/Exception from L0 to L36 using L38
L0:     new org/lwjgl/opengl/rA
L3:     dup
L4:     aload_0
L5:     invokespecial Method org/lwjgl/opengl/rA <init> (Ljava/awt/GraphicsConfiguration;)V
L8:     invokestatic Method java/security/AccessController doPrivileged (Ljava/security/PrivilegedExceptionAction;)Ljava/lang/Object;
L11:    checkcast java/lang/reflect/Method
L14:    dup
L15:    astore_1
L16:    aload_0
L17:    iconst_0
L18:    iconst_1
L19:    dup
L20:    pop2
L21:    anewarray java/lang/Object
L24:    iconst_1
L25:    dup
L26:    pop2
L27:    invokevirtual Method java/lang/reflect/Method invoke (Ljava/lang/Object;[Ljava/lang/Object;)Ljava/lang/Object;
L30:    checkcast java/lang/Integer
L33:    invokevirtual Method java/lang/Integer intValue ()I
L36:    ireturn
L37:    athrow
L38:    astore_1
L39:    new org/lwjgl/LWJGLException
L42:    dup
L43:    aload_1
L44:    invokespecial Method org/lwjgl/LWJGLException <init> (Ljava/lang/Throwable;)V
L47:    athrow
L48:    
        .attribute StackMap b'\x00\x02\x00\x25\x00\x00\x00\x01\x07\x00\x28\x00\x26\x00\x01\x07\x00\x53\x00\x01\x07\x00\x10'
    .end code
    .exceptions org/lwjgl/LWJGLException
.end method

.method <init> : ()V
    .code stack 1 locals 1
L0:     aload_0
L1:     invokespecial Method java/lang/Object <init> ()V
L4:     return
L5:     
    .end code
.end method

.method public break : (Ljava/awt/Canvas;Lorg/lwjgl/opengl/PixelFormat;Lorg/lwjgl/opengl/CB;)Lorg/lwjgl/opengl/a;
    .code stack 3 locals 4
L0:     new org/lwjgl/opengl/LinuxAWTGLCanvasPeerInfo
L3:     dup
L4:     aload_1
L5:     invokespecial Method org/lwjgl/opengl/LinuxAWTGLCanvasPeerInfo <init> (Ljava/awt/Canvas;)V
L8:     areturn
L9:     
    .end code
    .exceptions org/lwjgl/LWJGLException
.end method

.method private static native nFindVisualIDFromFormat : (JILorg/lwjgl/opengl/PixelFormat;)I
    .exceptions org/lwjgl/LWJGLException
.end method

.method public break : (Ljava/awt/GraphicsDevice;Lorg/lwjgl/opengl/PixelFormat;)Ljava/awt/GraphicsConfiguration;
    .code stack 3 locals 7
        .catch org/lwjgl/LWJGLException from L0 to L49 using L61
L0:     aload_1
L1:     dup
L2:     invokestatic Method org/lwjgl/opengl/LinuxCanvasImplementation break (Ljava/awt/GraphicsDevice;)I
L5:     dup
L6:     istore_1
L7:     aload_2
L8:     invokestatic Method org/lwjgl/opengl/LinuxCanvasImplementation break (ILorg/lwjgl/opengl/PixelFormat;)I
L11:    istore_2
L12:    invokevirtual Method java/awt/GraphicsDevice getConfigurations ()[Ljava/awt/GraphicsConfiguration;
L15:    dup
L16:    astore_3
L17:    arraylength
L18:    istore 4
L20:    iconst_0
L21:    iconst_1
L22:    dup
L23:    pop2
L24:    istore 5
L26:    iload 5
L28:    iload 4
L30:    if_icmpge L85
L33:    aload_3
L34:    iload 5
L36:    aaload
L37:    dup
L38:    astore 6
L40:    invokestatic Method org/lwjgl/opengl/LinuxCanvasImplementation break (Ljava/awt/GraphicsConfiguration;)I
L43:    iload_2
L44:    if_icmpne L51
L47:    aload 6
L49:    areturn
L50:    athrow
        .catch org/lwjgl/LWJGLException from L51 to L57 using L61
L51:    iinc 5 1
L54:    goto L26
L57:    nop
L58:    nop
L59:    nop
L60:    athrow
L61:    astore_1
L62:    new java/lang/StringBuilder
L65:    dup
L66:    invokespecial Method java/lang/StringBuilder <init> ()V
L69:    iconst_0
L70:    ldc "Got exception while trying to determine configuration: "
L72:    invokevirtual Method java/lang/StringBuilder insert (ILjava/lang/String;)Ljava/lang/StringBuilder;
L75:    aload_1
L76:    invokevirtual Method java/lang/StringBuilder append (Ljava/lang/Object;)Ljava/lang/StringBuilder;
L79:    invokevirtual Method java/lang/StringBuilder toString ()Ljava/lang/String;
L82:    invokestatic Method org/lwjgl/LWJGLUtil log (Ljava/lang/CharSequence;)V
L85:    aconst_null
L86:    areturn
L87:    
        .attribute StackMap b'\x00\x06\x00\x1A\x00\x06\x07\x00\x02\x01\x01\x07\x00\x66\x01\x01\x00\x00\x00\x32\x00\x00\x00\x01\x07\x00\x28\x00\x33\x00\x07\x07\x00\x02\x01\x01\x07\x00\x66\x01\x01\x07\x00\x53\x00\x00\x00\x39\x00\x00\x00\x01\x07\x00\x28\x00\x3D\x00\x01\x07\x00\x02\x00\x01\x07\x00\x0E\x00\x55\x00\x01\x07\x00\x02\x00\x00'
    .end code
    .exceptions org/lwjgl/LWJGLException
.end method
.innerclasses
    org/lwjgl/opengl/rA [0] [0] static
    org/lwjgl/opengl/yA [0] [0] static
.end innerclasses
.end class
