.version 49 0
.class public final super org/lwjgl/opengl/md
.super java/lang/Object
.field public static final field5496 I = 33640
.field public static final field5497 I = 36255

.method public static try : (II)V
    .code stack 2 locals 2
L0:     iload_0
L1:     iload_1
L2:     invokestatic Method org/lwjgl/opengl/GL33 method4350 (II)V
L5:     return
L6:     
    .end code
.end method

.method public static this : (II)V
    .code stack 2 locals 2
L0:     iload_0
L1:     iload_1
L2:     invokestatic Method org/lwjgl/opengl/GL33 method4313 (II)V
L5:     return
L6:     
    .end code
.end method

.method public static method5595 : (III)V
    .code stack 3 locals 3
L0:     iload_0
L1:     iload_1
L2:     iload_2
L3:     invokestatic Method org/lwjgl/opengl/GL33 method4298 (III)V
L6:     return
L7:     
    .end code
.end method

.method public static method5596 : (II)V
    .code stack 2 locals 2
L0:     iload_0
L1:     iload_1
L2:     invokestatic Method org/lwjgl/opengl/GL33 method4320 (II)V
L5:     return
L6:     
    .end code
.end method

.method public static method5597 : (IIZLjava/nio/IntBuffer;)V
    .code stack 4 locals 4
L0:     iload_0
L1:     iload_1
L2:     iload_2
L3:     aload_3
L4:     invokestatic Method org/lwjgl/opengl/GL33 method4334 (IIZLjava/nio/IntBuffer;)V
L7:     return
L8:     
    .end code
.end method

.method public static method5598 : (III)V
    .code stack 3 locals 3
L0:     iload_0
L1:     iload_1
L2:     iload_2
L3:     invokestatic Method org/lwjgl/opengl/GL33 method4321 (III)V
L6:     return
L7:     
    .end code
.end method

.method public static method5599 : (II)V
    .code stack 2 locals 2
L0:     iload_0
L1:     iload_1
L2:     invokestatic Method org/lwjgl/opengl/GL33 method4302 (II)V
L5:     return
L6:     
    .end code
.end method

.method public static method5600 : (IIZI)V
    .code stack 4 locals 4
L0:     iload_0
L1:     iload_1
L2:     iload_2
L3:     iload_3
L4:     invokestatic Method org/lwjgl/opengl/GL33 method4345 (IIZI)V
L7:     return
L8:     
    .end code
.end method

.method public static method5601 : (IIZI)V
    .code stack 4 locals 4
L0:     iload_0
L1:     iload_1
L2:     iload_2
L3:     iload_3
L4:     invokestatic Method org/lwjgl/opengl/GL33 method4346 (IIZI)V
L7:     return
L8:     
    .end code
.end method

.method public static method5602 : (II)V
    .code stack 2 locals 2
L0:     iload_0
L1:     iload_1
L2:     invokestatic Method org/lwjgl/opengl/GL33 method4312 (II)V
L5:     return
L6:     
    .end code
.end method

.method public static method5603 : (II)V
    .code stack 2 locals 2
L0:     iload_0
L1:     iload_1
L2:     invokestatic Method org/lwjgl/opengl/GL33 method4333 (II)V
L5:     return
L6:     
    .end code
.end method

.method private <init> : ()V
    .code stack 1 locals 1
L0:     aload_0
L1:     invokespecial Method java/lang/Object <init> ()V
L4:     return
L5:     
    .end code
.end method

.method public static method5604 : (IIZI)V
    .code stack 4 locals 4
L0:     iload_0
L1:     iload_1
L2:     iload_2
L3:     iload_3
L4:     invokestatic Method org/lwjgl/opengl/GL33 method4353 (IIZI)V
L7:     return
L8:     
    .end code
.end method

.method public static method5605 : (IILjava/nio/IntBuffer;)V
    .code stack 3 locals 3
L0:     iload_0
L1:     iload_1
L2:     aload_2
L3:     invokestatic Method org/lwjgl/opengl/GL33 method4315 (IILjava/nio/IntBuffer;)V
L6:     return
L7:     
    .end code
.end method

.method public static method5606 : (II)V
    .code stack 2 locals 2
L0:     iload_0
L1:     iload_1
L2:     invokestatic Method org/lwjgl/opengl/GL33 method4300 (II)V
L5:     return
L6:     
    .end code
.end method

.method public static method5607 : (II)V
    .code stack 2 locals 2
L0:     iload_0
L1:     iload_1
L2:     invokestatic Method org/lwjgl/opengl/GL33 try (II)V
L5:     return
L6:     
    .end code
.end method

.method public static try : (ILjava/nio/IntBuffer;)V
    .code stack 2 locals 2
L0:     iload_0
L1:     aload_1
L2:     invokestatic Method org/lwjgl/opengl/GL33 method4306 (ILjava/nio/IntBuffer;)V
L5:     return
L6:     
    .end code
.end method

.method public static this : (ILjava/nio/IntBuffer;)V
    .code stack 2 locals 2
L0:     iload_0
L1:     aload_1
L2:     invokestatic Method org/lwjgl/opengl/GL33 method4307 (ILjava/nio/IntBuffer;)V
L5:     return
L6:     
    .end code
.end method

.method public static method5608 : (II)V
    .code stack 2 locals 2
L0:     iload_0
L1:     iload_1
L2:     invokestatic Method org/lwjgl/opengl/GL33 method4342 (II)V
L5:     return
L6:     
    .end code
.end method

.method public static method5609 : (IILjava/nio/IntBuffer;)V
    .code stack 3 locals 3
L0:     iload_0
L1:     iload_1
L2:     aload_2
L3:     invokestatic Method org/lwjgl/opengl/GL33 this (IILjava/nio/IntBuffer;)V
L6:     return
L7:     
    .end code
.end method

.method public static method5610 : (ILjava/nio/IntBuffer;)V
    .code stack 2 locals 2
L0:     iload_0
L1:     aload_1
L2:     invokestatic Method org/lwjgl/opengl/GL33 method4325 (ILjava/nio/IntBuffer;)V
L5:     return
L6:     
    .end code
.end method

.method public static method5611 : (ILjava/nio/IntBuffer;)V
    .code stack 2 locals 2
L0:     iload_0
L1:     aload_1
L2:     invokestatic Method org/lwjgl/opengl/GL33 method4356 (ILjava/nio/IntBuffer;)V
L5:     return
L6:     
    .end code
.end method

.method public static method5612 : (III)V
    .code stack 3 locals 3
L0:     iload_0
L1:     iload_1
L2:     iload_2
L3:     invokestatic Method org/lwjgl/opengl/GL33 method4340 (III)V
L6:     return
L7:     
    .end code
.end method

.method public static method5613 : (ILjava/nio/IntBuffer;)V
    .code stack 2 locals 2
L0:     iload_0
L1:     aload_1
L2:     invokestatic Method org/lwjgl/opengl/GL33 method4323 (ILjava/nio/IntBuffer;)V
L5:     return
L6:     
    .end code
.end method

.method public static method5614 : (IIZLjava/nio/IntBuffer;)V
    .code stack 4 locals 4
L0:     iload_0
L1:     iload_1
L2:     iload_2
L3:     aload_3
L4:     invokestatic Method org/lwjgl/opengl/GL33 method4337 (IIZLjava/nio/IntBuffer;)V
L7:     return
L8:     
    .end code
.end method

.method public static method5615 : (ILjava/nio/IntBuffer;)V
    .code stack 2 locals 2
L0:     iload_0
L1:     aload_1
L2:     invokestatic Method org/lwjgl/opengl/GL33 method4331 (ILjava/nio/IntBuffer;)V
L5:     return
L6:     
    .end code
.end method

.method public static method5616 : (ILjava/nio/IntBuffer;)V
    .code stack 2 locals 2
L0:     iload_0
L1:     aload_1
L2:     invokestatic Method org/lwjgl/opengl/GL33 method4335 (ILjava/nio/IntBuffer;)V
L5:     return
L6:     
    .end code
.end method

.method public static method5617 : (IIZI)V
    .code stack 4 locals 4
L0:     iload_0
L1:     iload_1
L2:     iload_2
L3:     iload_3
L4:     invokestatic Method org/lwjgl/opengl/GL33 method4295 (IIZI)V
L7:     return
L8:     
    .end code
.end method

.method public static method5618 : (IILjava/nio/IntBuffer;)V
    .code stack 3 locals 3
L0:     iload_0
L1:     iload_1
L2:     aload_2
L3:     invokestatic Method org/lwjgl/opengl/GL33 method4322 (IILjava/nio/IntBuffer;)V
L6:     return
L7:     
    .end code
.end method

.method public static method5619 : (IIZLjava/nio/IntBuffer;)V
    .code stack 4 locals 4
L0:     iload_0
L1:     iload_1
L2:     iload_2
L3:     aload_3
L4:     invokestatic Method org/lwjgl/opengl/GL33 method4305 (IIZLjava/nio/IntBuffer;)V
L7:     return
L8:     
    .end code
.end method

.method public static method5620 : (III)V
    .code stack 3 locals 3
L0:     iload_0
L1:     iload_1
L2:     iload_2
L3:     invokestatic Method org/lwjgl/opengl/GL33 method4308 (III)V
L6:     return
L7:     
    .end code
.end method

.method public static method5621 : (II)V
    .code stack 2 locals 2
L0:     iload_0
L1:     iload_1
L2:     invokestatic Method org/lwjgl/opengl/GL33 true (II)V
L5:     return
L6:     
    .end code
.end method

.method public static method5622 : (IILjava/nio/IntBuffer;)V
    .code stack 3 locals 3
L0:     iload_0
L1:     iload_1
L2:     aload_2
L3:     invokestatic Method org/lwjgl/opengl/GL33 method4328 (IILjava/nio/IntBuffer;)V
L6:     return
L7:     
    .end code
.end method

.method public static method5623 : (ILjava/nio/IntBuffer;)V
    .code stack 2 locals 2
L0:     iload_0
L1:     aload_1
L2:     invokestatic Method org/lwjgl/opengl/GL33 this (ILjava/nio/IntBuffer;)V
L5:     return
L6:     
    .end code
.end method

.method public static method5624 : (IIZLjava/nio/IntBuffer;)V
    .code stack 4 locals 4
L0:     iload_0
L1:     iload_1
L2:     iload_2
L3:     aload_3
L4:     invokestatic Method org/lwjgl/opengl/GL33 method4318 (IIZLjava/nio/IntBuffer;)V
L7:     return
L8:     
    .end code
.end method

.method public static method5625 : (ILjava/nio/IntBuffer;)V
    .code stack 2 locals 2
L0:     iload_0
L1:     aload_1
L2:     invokestatic Method org/lwjgl/opengl/GL33 method4332 (ILjava/nio/IntBuffer;)V
L5:     return
L6:     
    .end code
.end method

.method public static method5626 : (ILjava/nio/IntBuffer;)V
    .code stack 2 locals 2
L0:     iload_0
L1:     aload_1
L2:     invokestatic Method org/lwjgl/opengl/GL33 method4357 (ILjava/nio/IntBuffer;)V
L5:     return
L6:     
    .end code
.end method

.method public static method5627 : (ILjava/nio/IntBuffer;)V
    .code stack 2 locals 2
L0:     iload_0
L1:     aload_1
L2:     invokestatic Method org/lwjgl/opengl/GL33 try (ILjava/nio/IntBuffer;)V
L5:     return
L6:     
    .end code
.end method

.method public static method5628 : (II)V
    .code stack 2 locals 2
L0:     iload_0
L1:     iload_1
L2:     invokestatic Method org/lwjgl/opengl/GL33 method4347 (II)V
L5:     return
L6:     
    .end code
.end method
.end class
