.version 49 0
.class public final super org/lwjgl/opengl/nD
.super org/lwjgl/opengl/ARBProgram
.field public static final M I = 34340
.field public static final L I = 34995
.field public static final H I = 34993
.field public static final d I = 34922
.field public static final e I = 34992
.field public static final g I = 33880
.field public static final k I = 34336
.field public static final a I = 34371
.field public static final F I = 34338
.field public static final A I = 34341
.field public static final E I = 34921
.field public static final C I = 34373
.field public static final K I = 34370
.field public static final G I = 34339
.field public static final B I = 34994
.field public static final c I = 34342

.method public static method2497 : (IFF)V
    .code stack 3 locals 3
L0:     iload_0
L1:     fload_1
L2:     fload_2
L3:     invokestatic Method org/lwjgl/opengl/ARBVertexShader method2841 (IFF)V
L6:     return
L7:     
    .end code
.end method

.method public static method2498 : (ID)V
    .code stack 3 locals 3
L0:     iload_0
L1:     dload_1
L2:     invokestatic Method org/lwjgl/opengl/ARBVertexShader method2826 (ID)V
L5:     return
L6:     
    .end code
.end method

.method public static method2499 : (IILjava/nio/FloatBuffer;)V
    .code stack 3 locals 3
L0:     iload_0
L1:     iload_1
L2:     aload_2
L3:     invokestatic Method org/lwjgl/opengl/ARBVertexShader method2832 (IILjava/nio/FloatBuffer;)V
L6:     return
L7:     
    .end code
.end method

.method public static method2500 : (ISSSS)V
    .code stack 5 locals 5
L0:     iload_0
L1:     iload_1
L2:     iload_2
L3:     iload_3
L4:     iload 4
L6:     invokestatic Method org/lwjgl/opengl/ARBVertexShader method2845 (ISSSS)V
L9:     return
L10:    
    .end code
.end method

.method public static method2501 : (IDDDD)V
    .code stack 9 locals 9
L0:     iload_0
L1:     dload_1
L2:     dload_3
L3:     dload 5
L5:     dload 7
L7:     invokestatic Method org/lwjgl/opengl/ARBVertexShader method2818 (IDDDD)V
L10:    return
L11:    
    .end code
.end method

.method public static method2502 : (IILjava/nio/IntBuffer;)V
    .code stack 3 locals 3
L0:     iload_0
L1:     iload_1
L2:     aload_2
L3:     invokestatic Method org/lwjgl/opengl/ARBVertexShader method2823 (IILjava/nio/IntBuffer;)V
L6:     return
L7:     
    .end code
.end method

.method public static method2503 : (IIZZILjava/nio/ByteBuffer;)V
    .code stack 6 locals 6
L0:     iload_0
L1:     iload_1
L2:     iload_2
L3:     iload_3
L4:     iload 4
L6:     aload 5
L8:     invokestatic Method org/lwjgl/opengl/ARBVertexShader method2840 (IIZZILjava/nio/ByteBuffer;)V
L11:    return
L12:    
    .end code
.end method

.method public static method2504 : (IILjava/nio/DoubleBuffer;)V
    .code stack 3 locals 3
L0:     iload_0
L1:     iload_1
L2:     aload_2
L3:     invokestatic Method org/lwjgl/opengl/ARBVertexShader method2835 (IILjava/nio/DoubleBuffer;)V
L6:     return
L7:     
    .end code
.end method

.method public static method2505 : (IIZZILjava/nio/IntBuffer;)V
    .code stack 6 locals 6
L0:     iload_0
L1:     iload_1
L2:     iload_2
L3:     iload_3
L4:     iload 4
L6:     aload 5
L8:     invokestatic Method org/lwjgl/opengl/ARBVertexShader method2837 (IIZZILjava/nio/IntBuffer;)V
L11:    return
L12:    
    .end code
.end method

.method public static method2506 : (IDD)V
    .code stack 5 locals 5
L0:     iload_0
L1:     dload_1
L2:     dload_3
L3:     invokestatic Method org/lwjgl/opengl/ARBVertexShader method2844 (IDD)V
L6:     return
L7:     
    .end code
.end method

.method public static method2507 : (IIZILjava/nio/DoubleBuffer;)V
    .code stack 5 locals 5
L0:     iload_0
L1:     iload_1
L2:     iload_2
L3:     iload_3
L4:     aload 4
L6:     invokestatic Method org/lwjgl/opengl/ARBVertexShader method2825 (IIZILjava/nio/DoubleBuffer;)V
L9:     return
L10:    
    .end code
.end method

.method public static method2508 : (IS)V
    .code stack 2 locals 2
L0:     iload_0
L1:     iload_1
L2:     invokestatic Method org/lwjgl/opengl/ARBVertexShader method2830 (IS)V
L5:     return
L6:     
    .end code
.end method

.method private <init> : ()V
    .code stack 1 locals 1
L0:     aload_0
L1:     invokespecial Method org/lwjgl/opengl/ARBProgram <init> ()V
L4:     return
L5:     
    .end code
.end method

.method public static method2509 : (ISS)V
    .code stack 3 locals 3
L0:     iload_0
L1:     iload_1
L2:     iload_2
L3:     invokestatic Method org/lwjgl/opengl/ARBVertexShader method2849 (ISS)V
L6:     return
L7:     
    .end code
.end method

.method public static method2510 : (I)V
    .code stack 1 locals 1
L0:     iload_0
L1:     invokestatic Method org/lwjgl/opengl/ARBVertexShader method2829 (I)V
L4:     return
L5:     
    .end code
.end method

.method public static method2511 : (IFFFF)V
    .code stack 5 locals 5
L0:     iload_0
L1:     fload_1
L2:     fload_2
L3:     fload_3
L4:     fload 4
L6:     invokestatic Method org/lwjgl/opengl/ARBVertexShader method2822 (IFFFF)V
L9:     return
L10:    
    .end code
.end method

.method public static method2512 : (IIIZIJ)V
    .code stack 7 locals 7
L0:     iload_0
L1:     iload_1
L2:     iload_2
L3:     iload_3
L4:     iload 4
L6:     lload 5
L8:     invokestatic Method org/lwjgl/opengl/ARBVertexShader method2851 (IIIZIJ)V
L11:    return
L12:    
    .end code
.end method

.method public static method2513 : (IIZILjava/nio/FloatBuffer;)V
    .code stack 5 locals 5
L0:     iload_0
L1:     iload_1
L2:     iload_2
L3:     iload_3
L4:     aload 4
L6:     invokestatic Method org/lwjgl/opengl/ARBVertexShader method2842 (IIZILjava/nio/FloatBuffer;)V
L9:     return
L10:    
    .end code
.end method

.method public static method2514 : (IBBBB)V
    .code stack 5 locals 5
L0:     iload_0
L1:     iload_1
L2:     iload_2
L3:     iload_3
L4:     iload 4
L6:     invokestatic Method org/lwjgl/opengl/ARBVertexShader method2833 (IBBBB)V
L9:     return
L10:    
    .end code
.end method

.method public static method2515 : (IIJ)Ljava/nio/ByteBuffer;
    .code stack 4 locals 4
L0:     iload_0
L1:     iload_1
L2:     lload_2
L3:     invokestatic Method org/lwjgl/opengl/ARBVertexShader method2838 (IIJ)Ljava/nio/ByteBuffer;
L6:     areturn
L7:     
    .end code
.end method

.method public static method2516 : (IFFF)V
    .code stack 4 locals 4
L0:     iload_0
L1:     fload_1
L2:     fload_2
L3:     fload_3
L4:     invokestatic Method org/lwjgl/opengl/ARBVertexShader method2827 (IFFF)V
L7:     return
L8:     
    .end code
.end method

.method public static method2517 : (IF)V
    .code stack 2 locals 2
L0:     iload_0
L1:     fload_1
L2:     invokestatic Method org/lwjgl/opengl/ARBVertexShader method2824 (IF)V
L5:     return
L6:     
    .end code
.end method

.method public static method2518 : (ISSS)V
    .code stack 4 locals 4
L0:     iload_0
L1:     iload_1
L2:     iload_2
L3:     iload_3
L4:     invokestatic Method org/lwjgl/opengl/ARBVertexShader method2834 (ISSS)V
L7:     return
L8:     
    .end code
.end method

.method public static method2519 : (I)V
    .code stack 1 locals 1
L0:     iload_0
L1:     invokestatic Method org/lwjgl/opengl/ARBVertexShader method2821 (I)V
L4:     return
L5:     
    .end code
.end method

.method public static method2520 : (IDDD)V
    .code stack 7 locals 7
L0:     iload_0
L1:     dload_1
L2:     dload_3
L3:     dload 5
L5:     invokestatic Method org/lwjgl/opengl/ARBVertexShader method2850 (IDDD)V
L8:     return
L9:     
    .end code
.end method

.method public static method2521 : (IIZZILjava/nio/ShortBuffer;)V
    .code stack 6 locals 6
L0:     iload_0
L1:     iload_1
L2:     iload_2
L3:     iload_3
L4:     iload 4
L6:     aload 5
L8:     invokestatic Method org/lwjgl/opengl/ARBVertexShader method2843 (IIZZILjava/nio/ShortBuffer;)V
L11:    return
L12:    
    .end code
.end method
.end class
