.version 49 0
.class public final super org/lwjgl/opengl/NVGpuProgram4
.super java/lang/Object
.field public static final field4709 I = 36262
.field public static final this I = 36261
.field public static final field4710 I = 35078
.field public static final field4711 I = 35079
.field public static final field4712 I = 35081
.field public static final field4713 I = 35080

.method public static new : (IILjava/nio/IntBuffer;)V
    .code stack 6 locals 5
L0:     invokestatic Method org/lwjgl/opengl/GLContext method4611 ()Lorg/lwjgl/opengl/kb;
L3:     getfield Field org/lwjgl/opengl/kb DB J
L6:     dup2
L7:     lstore_3
L8:     invokestatic Method org/lwjgl/l method2052 (J)V
L11:    iload_0
L12:    aload_2
L13:    iconst_4
L14:    iconst_1
L15:    dup
L16:    pop2
L17:    invokestatic Method org/lwjgl/l method2041 (Ljava/nio/IntBuffer;I)V
L20:    iload_1
L21:    aload_2
L22:    invokestatic Method org/lwjgl/MemoryUtil method1884 (Ljava/nio/IntBuffer;)J
L25:    lload_3
L26:    invokestatic Method org/lwjgl/opengl/NVGpuProgram4 nglProgramEnvParameterI4ivNV (IIJJ)V
L29:    return
L30:    
    .end code
.end method

.method static native nglProgramLocalParameterI4iNV : (IIIIIIJ)V
.end method

.method static native nglGetProgramEnvParameterIuivNV : (IIJJ)V
.end method

.method static native nglProgramLocalParameterI4ivNV : (IIJJ)V
.end method

.method static native nglProgramEnvParameterI4iNV : (IIIIIIJ)V
.end method

.method public static method4987 : (IIIIII)V
    .code stack 8 locals 8
L0:     invokestatic Method org/lwjgl/opengl/GLContext method4611 ()Lorg/lwjgl/opengl/kb;
L3:     getfield Field org/lwjgl/opengl/kb Mh J
L6:     dup2
L7:     lstore 6
L9:     invokestatic Method org/lwjgl/l method2052 (J)V
L12:    iload_0
L13:    iload_1
L14:    iload_2
L15:    iload_3
L16:    iload 4
L18:    iload 5
L20:    lload 6
L22:    invokestatic Method org/lwjgl/opengl/NVGpuProgram4 nglProgramEnvParameterI4uiNV (IIIIIIJ)V
L25:    return
L26:    
    .end code
.end method

.method public static try : (IILjava/nio/IntBuffer;)V
    .code stack 6 locals 5
L0:     invokestatic Method org/lwjgl/opengl/GLContext method4611 ()Lorg/lwjgl/opengl/kb;
L3:     getfield Field org/lwjgl/opengl/kb mB J
L6:     dup2
L7:     lstore_3
L8:     invokestatic Method org/lwjgl/l method2052 (J)V
L11:    iload_0
L12:    aload_2
L13:    iconst_4
L14:    iconst_1
L15:    dup
L16:    pop2
L17:    invokestatic Method org/lwjgl/l method2041 (Ljava/nio/IntBuffer;I)V
L20:    iload_1
L21:    aload_2
L22:    invokestatic Method org/lwjgl/MemoryUtil method1884 (Ljava/nio/IntBuffer;)J
L25:    lload_3
L26:    invokestatic Method org/lwjgl/opengl/NVGpuProgram4 nglGetProgramEnvParameterIivNV (IIJJ)V
L29:    return
L30:    
    .end code
.end method

.method static native nglProgramEnvParameterI4uiNV : (IIIIIIJ)V
.end method

.method public static this : (IILjava/nio/IntBuffer;)V
    .code stack 7 locals 5
L0:     invokestatic Method org/lwjgl/opengl/GLContext method4611 ()Lorg/lwjgl/opengl/kb;
L3:     getfield Field org/lwjgl/opengl/kb qA J
L6:     dup2
L7:     lstore_3
L8:     invokestatic Method org/lwjgl/l method2052 (J)V
L11:    iload_0
L12:    aload_2
L13:    invokestatic Method org/lwjgl/l method2043 (Ljava/nio/IntBuffer;)V
L16:    iload_1
L17:    aload_2
L18:    invokevirtual Method java/nio/IntBuffer remaining ()I
L21:    iconst_2
L22:    iconst_1
L23:    dup
L24:    pop2
L25:    ishr
L26:    aload_2
L27:    invokestatic Method org/lwjgl/MemoryUtil method1884 (Ljava/nio/IntBuffer;)J
L30:    lload_3
L31:    invokestatic Method org/lwjgl/opengl/NVGpuProgram4 nglProgramEnvParametersI4ivNV (IIIJJ)V
L34:    return
L35:    
    .end code
.end method

.method public static method4988 : (IIIIII)V
    .code stack 8 locals 8
L0:     invokestatic Method org/lwjgl/opengl/GLContext method4611 ()Lorg/lwjgl/opengl/kb;
L3:     getfield Field org/lwjgl/opengl/kb Zs J
L6:     dup2
L7:     lstore 6
L9:     invokestatic Method org/lwjgl/l method2052 (J)V
L12:    iload_0
L13:    iload_1
L14:    iload_2
L15:    iload_3
L16:    iload 4
L18:    iload 5
L20:    lload 6
L22:    invokestatic Method org/lwjgl/opengl/NVGpuProgram4 nglProgramLocalParameterI4iNV (IIIIIIJ)V
L25:    return
L26:    
    .end code
.end method

.method public static method4989 : (IIIIII)V
    .code stack 8 locals 8
L0:     invokestatic Method org/lwjgl/opengl/GLContext method4611 ()Lorg/lwjgl/opengl/kb;
L3:     getfield Field org/lwjgl/opengl/kb ms J
L6:     dup2
L7:     lstore 6
L9:     invokestatic Method org/lwjgl/l method2052 (J)V
L12:    iload_0
L13:    iload_1
L14:    iload_2
L15:    iload_3
L16:    iload 4
L18:    iload 5
L20:    lload 6
L22:    invokestatic Method org/lwjgl/opengl/NVGpuProgram4 nglProgramEnvParameterI4iNV (IIIIIIJ)V
L25:    return
L26:    
    .end code
.end method

.method private <init> : ()V
    .code stack 1 locals 1
L0:     aload_0
L1:     invokespecial Method java/lang/Object <init> ()V
L4:     return
L5:     
    .end code
.end method

.method static native nglGetProgramEnvParameterIivNV : (IIJJ)V
.end method

.method public static method4990 : (IIIIII)V
    .code stack 8 locals 8
L0:     invokestatic Method org/lwjgl/opengl/GLContext method4611 ()Lorg/lwjgl/opengl/kb;
L3:     getfield Field org/lwjgl/opengl/kb iM J
L6:     dup2
L7:     lstore 6
L9:     invokestatic Method org/lwjgl/l method2052 (J)V
L12:    iload_0
L13:    iload_1
L14:    iload_2
L15:    iload_3
L16:    iload 4
L18:    iload 5
L20:    lload 6
L22:    invokestatic Method org/lwjgl/opengl/NVGpuProgram4 nglProgramLocalParameterI4uiNV (IIIIIIJ)V
L25:    return
L26:    
    .end code
.end method

.method public static method4991 : (IILjava/nio/IntBuffer;)V
    .code stack 6 locals 5
L0:     invokestatic Method org/lwjgl/opengl/GLContext method4611 ()Lorg/lwjgl/opengl/kb;
L3:     getfield Field org/lwjgl/opengl/kb Lj J
L6:     dup2
L7:     lstore_3
L8:     invokestatic Method org/lwjgl/l method2052 (J)V
L11:    iload_0
L12:    aload_2
L13:    iconst_4
L14:    iconst_1
L15:    dup
L16:    pop2
L17:    invokestatic Method org/lwjgl/l method2041 (Ljava/nio/IntBuffer;I)V
L20:    iload_1
L21:    aload_2
L22:    invokestatic Method org/lwjgl/MemoryUtil method1884 (Ljava/nio/IntBuffer;)J
L25:    lload_3
L26:    invokestatic Method org/lwjgl/opengl/NVGpuProgram4 nglProgramLocalParameterI4uivNV (IIJJ)V
L29:    return
L30:    
    .end code
.end method

.method public static method4992 : (IILjava/nio/IntBuffer;)V
    .code stack 6 locals 5
L0:     invokestatic Method org/lwjgl/opengl/GLContext method4611 ()Lorg/lwjgl/opengl/kb;
L3:     getfield Field org/lwjgl/opengl/kb nc J
L6:     dup2
L7:     lstore_3
L8:     invokestatic Method org/lwjgl/l method2052 (J)V
L11:    iload_0
L12:    aload_2
L13:    iconst_4
L14:    iconst_1
L15:    dup
L16:    pop2
L17:    invokestatic Method org/lwjgl/l method2041 (Ljava/nio/IntBuffer;I)V
L20:    iload_1
L21:    aload_2
L22:    invokestatic Method org/lwjgl/MemoryUtil method1884 (Ljava/nio/IntBuffer;)J
L25:    lload_3
L26:    invokestatic Method org/lwjgl/opengl/NVGpuProgram4 nglGetProgramLocalParameterIuivNV (IIJJ)V
L29:    return
L30:    
    .end code
.end method

.method static native nglProgramLocalParameterI4uiNV : (IIIIIIJ)V
.end method

.method public static method4993 : (IILjava/nio/IntBuffer;)V
    .code stack 7 locals 5
L0:     invokestatic Method org/lwjgl/opengl/GLContext method4611 ()Lorg/lwjgl/opengl/kb;
L3:     getfield Field org/lwjgl/opengl/kb NT J
L6:     dup2
L7:     lstore_3
L8:     invokestatic Method org/lwjgl/l method2052 (J)V
L11:    iload_0
L12:    aload_2
L13:    invokestatic Method org/lwjgl/l method2043 (Ljava/nio/IntBuffer;)V
L16:    iload_1
L17:    aload_2
L18:    invokevirtual Method java/nio/IntBuffer remaining ()I
L21:    iconst_2
L22:    iconst_1
L23:    dup
L24:    pop2
L25:    ishr
L26:    aload_2
L27:    invokestatic Method org/lwjgl/MemoryUtil method1884 (Ljava/nio/IntBuffer;)J
L30:    lload_3
L31:    invokestatic Method org/lwjgl/opengl/NVGpuProgram4 nglProgramLocalParametersI4ivNV (IIIJJ)V
L34:    return
L35:    
    .end code
.end method

.method static native nglProgramEnvParameterI4uivNV : (IIJJ)V
.end method

.method public static method4994 : (IILjava/nio/IntBuffer;)V
    .code stack 7 locals 5
L0:     invokestatic Method org/lwjgl/opengl/GLContext method4611 ()Lorg/lwjgl/opengl/kb;
L3:     getfield Field org/lwjgl/opengl/kb f J
L6:     dup2
L7:     lstore_3
L8:     invokestatic Method org/lwjgl/l method2052 (J)V
L11:    iload_0
L12:    aload_2
L13:    invokestatic Method org/lwjgl/l method2043 (Ljava/nio/IntBuffer;)V
L16:    iload_1
L17:    aload_2
L18:    invokevirtual Method java/nio/IntBuffer remaining ()I
L21:    iconst_2
L22:    iconst_1
L23:    dup
L24:    pop2
L25:    ishr
L26:    aload_2
L27:    invokestatic Method org/lwjgl/MemoryUtil method1884 (Ljava/nio/IntBuffer;)J
L30:    lload_3
L31:    invokestatic Method org/lwjgl/opengl/NVGpuProgram4 nglProgramEnvParametersI4uivNV (IIIJJ)V
L34:    return
L35:    
    .end code
.end method

.method static native nglProgramLocalParametersI4uivNV : (IIIJJ)V
.end method

.method static native nglProgramEnvParameterI4ivNV : (IIJJ)V
.end method

.method public static method4995 : (IILjava/nio/IntBuffer;)V
    .code stack 6 locals 5
L0:     invokestatic Method org/lwjgl/opengl/GLContext method4611 ()Lorg/lwjgl/opengl/kb;
L3:     getfield Field org/lwjgl/opengl/kb EF J
L6:     dup2
L7:     lstore_3
L8:     invokestatic Method org/lwjgl/l method2052 (J)V
L11:    iload_0
L12:    aload_2
L13:    iconst_4
L14:    iconst_1
L15:    dup
L16:    pop2
L17:    invokestatic Method org/lwjgl/l method2041 (Ljava/nio/IntBuffer;I)V
L20:    iload_1
L21:    aload_2
L22:    invokestatic Method org/lwjgl/MemoryUtil method1884 (Ljava/nio/IntBuffer;)J
L25:    lload_3
L26:    invokestatic Method org/lwjgl/opengl/NVGpuProgram4 nglGetProgramLocalParameterIivNV (IIJJ)V
L29:    return
L30:    
    .end code
.end method

.method static native nglGetProgramLocalParameterIuivNV : (IIJJ)V
.end method

.method static native nglProgramEnvParametersI4uivNV : (IIIJJ)V
.end method

.method public static method4996 : (IILjava/nio/IntBuffer;)V
    .code stack 6 locals 5
L0:     invokestatic Method org/lwjgl/opengl/GLContext method4611 ()Lorg/lwjgl/opengl/kb;
L3:     getfield Field org/lwjgl/opengl/kb LC J
L6:     dup2
L7:     lstore_3
L8:     invokestatic Method org/lwjgl/l method2052 (J)V
L11:    iload_0
L12:    aload_2
L13:    iconst_4
L14:    iconst_1
L15:    dup
L16:    pop2
L17:    invokestatic Method org/lwjgl/l method2041 (Ljava/nio/IntBuffer;I)V
L20:    iload_1
L21:    aload_2
L22:    invokestatic Method org/lwjgl/MemoryUtil method1884 (Ljava/nio/IntBuffer;)J
L25:    lload_3
L26:    invokestatic Method org/lwjgl/opengl/NVGpuProgram4 nglProgramLocalParameterI4ivNV (IIJJ)V
L29:    return
L30:    
    .end code
.end method

.method static native nglProgramEnvParametersI4ivNV : (IIIJJ)V
.end method

.method static native nglProgramLocalParameterI4uivNV : (IIJJ)V
.end method

.method static native nglProgramLocalParametersI4ivNV : (IIIJJ)V
.end method

.method public static method4997 : (IILjava/nio/IntBuffer;)V
    .code stack 7 locals 5
L0:     invokestatic Method org/lwjgl/opengl/GLContext method4611 ()Lorg/lwjgl/opengl/kb;
L3:     getfield Field org/lwjgl/opengl/kb cK J
L6:     dup2
L7:     lstore_3
L8:     invokestatic Method org/lwjgl/l method2052 (J)V
L11:    iload_0
L12:    aload_2
L13:    invokestatic Method org/lwjgl/l method2043 (Ljava/nio/IntBuffer;)V
L16:    iload_1
L17:    aload_2
L18:    invokevirtual Method java/nio/IntBuffer remaining ()I
L21:    iconst_2
L22:    iconst_1
L23:    dup
L24:    pop2
L25:    ishr
L26:    aload_2
L27:    invokestatic Method org/lwjgl/MemoryUtil method1884 (Ljava/nio/IntBuffer;)J
L30:    lload_3
L31:    invokestatic Method org/lwjgl/opengl/NVGpuProgram4 nglProgramLocalParametersI4uivNV (IIIJJ)V
L34:    return
L35:    
    .end code
.end method

.method public static method4998 : (IILjava/nio/IntBuffer;)V
    .code stack 6 locals 5
L0:     invokestatic Method org/lwjgl/opengl/GLContext method4611 ()Lorg/lwjgl/opengl/kb;
L3:     getfield Field org/lwjgl/opengl/kb gc J
L6:     dup2
L7:     lstore_3
L8:     invokestatic Method org/lwjgl/l method2052 (J)V
L11:    iload_0
L12:    aload_2
L13:    iconst_4
L14:    iconst_1
L15:    dup
L16:    pop2
L17:    invokestatic Method org/lwjgl/l method2041 (Ljava/nio/IntBuffer;I)V
L20:    iload_1
L21:    aload_2
L22:    invokestatic Method org/lwjgl/MemoryUtil method1884 (Ljava/nio/IntBuffer;)J
L25:    lload_3
L26:    invokestatic Method org/lwjgl/opengl/NVGpuProgram4 nglProgramEnvParameterI4uivNV (IIJJ)V
L29:    return
L30:    
    .end code
.end method

.method static native nglGetProgramLocalParameterIivNV : (IIJJ)V
.end method

.method public static method4999 : (IILjava/nio/IntBuffer;)V
    .code stack 6 locals 5
L0:     invokestatic Method org/lwjgl/opengl/GLContext method4611 ()Lorg/lwjgl/opengl/kb;
L3:     getfield Field org/lwjgl/opengl/kb nJ J
L6:     dup2
L7:     lstore_3
L8:     invokestatic Method org/lwjgl/l method2052 (J)V
L11:    iload_0
L12:    aload_2
L13:    iconst_4
L14:    iconst_1
L15:    dup
L16:    pop2
L17:    invokestatic Method org/lwjgl/l method2041 (Ljava/nio/IntBuffer;I)V
L20:    iload_1
L21:    aload_2
L22:    invokestatic Method org/lwjgl/MemoryUtil method1884 (Ljava/nio/IntBuffer;)J
L25:    lload_3
L26:    invokestatic Method org/lwjgl/opengl/NVGpuProgram4 nglGetProgramEnvParameterIuivNV (IIJJ)V
L29:    return
L30:    
    .end code
.end method
.end class
