.version 49 0
.class public final super org/lwjgl/opengl/NVPixelDataRange
.super java/lang/Object
.field public static final field4791 I = 34939
.field public static final this I = 34937
.field public static final field4792 I = 34940
.field public static final field4793 I = 34941
.field public static final field4794 I = 34938
.field public static final field4795 I = 34936

.method public static method5126 : (ILjava/nio/ShortBuffer;)V
    .code stack 6 locals 4
L0:     invokestatic Method org/lwjgl/opengl/GLContext method4611 ()Lorg/lwjgl/opengl/kb;
L3:     getfield Field org/lwjgl/opengl/kb UD J
L6:     dup2
L7:     lstore_2
L8:     invokestatic Method org/lwjgl/l method2052 (J)V
L11:    iload_0
L12:    aload_1
L13:    invokestatic Method org/lwjgl/l method2057 (Ljava/nio/ShortBuffer;)V
L16:    aload_1
L17:    invokevirtual Method java/nio/ShortBuffer remaining ()I
L20:    iconst_1
L21:    dup
L22:    dup
L23:    pop2
L24:    ishl
L25:    aload_1
L26:    invokestatic Method org/lwjgl/MemoryUtil method1853 (Ljava/nio/ShortBuffer;)J
L29:    lload_2
L30:    invokestatic Method org/lwjgl/opengl/NVPixelDataRange nglPixelDataRangeNV (IIJJ)V
L33:    return
L34:    
    .end code
.end method

.method private <init> : ()V
    .code stack 1 locals 1
L0:     aload_0
L1:     invokespecial Method java/lang/Object <init> ()V
L4:     return
L5:     
    .end code
.end method

.method static native nglPixelDataRangeNV : (IIJJ)V
.end method

.method public static method5127 : (ILjava/nio/IntBuffer;)V
    .code stack 6 locals 4
L0:     invokestatic Method org/lwjgl/opengl/GLContext method4611 ()Lorg/lwjgl/opengl/kb;
L3:     getfield Field org/lwjgl/opengl/kb UD J
L6:     dup2
L7:     lstore_2
L8:     invokestatic Method org/lwjgl/l method2052 (J)V
L11:    iload_0
L12:    aload_1
L13:    invokestatic Method org/lwjgl/l method2043 (Ljava/nio/IntBuffer;)V
L16:    aload_1
L17:    invokevirtual Method java/nio/IntBuffer remaining ()I
L20:    iconst_2
L21:    iconst_1
L22:    dup
L23:    pop2
L24:    ishl
L25:    aload_1
L26:    invokestatic Method org/lwjgl/MemoryUtil method1884 (Ljava/nio/IntBuffer;)J
L29:    lload_2
L30:    invokestatic Method org/lwjgl/opengl/NVPixelDataRange nglPixelDataRangeNV (IIJJ)V
L33:    return
L34:    
    .end code
.end method

.method public static method5128 : (I)V
    .code stack 4 locals 3
L0:     invokestatic Method org/lwjgl/opengl/GLContext method4611 ()Lorg/lwjgl/opengl/kb;
L3:     getfield Field org/lwjgl/opengl/kb field5405 J
L6:     dup2
L7:     lstore_1
L8:     invokestatic Method org/lwjgl/l method2052 (J)V
L11:    iload_0
L12:    lload_1
L13:    invokestatic Method org/lwjgl/opengl/NVPixelDataRange nglFlushPixelDataRangeNV (IJ)V
L16:    return
L17:    
    .end code
.end method

.method public static method5129 : (ILjava/nio/DoubleBuffer;)V
    .code stack 6 locals 4
L0:     invokestatic Method org/lwjgl/opengl/GLContext method4611 ()Lorg/lwjgl/opengl/kb;
L3:     getfield Field org/lwjgl/opengl/kb UD J
L6:     dup2
L7:     lstore_2
L8:     invokestatic Method org/lwjgl/l method2052 (J)V
L11:    iload_0
L12:    aload_1
L13:    invokestatic Method org/lwjgl/l method2036 (Ljava/nio/DoubleBuffer;)V
L16:    aload_1
L17:    invokevirtual Method java/nio/DoubleBuffer remaining ()I
L20:    iconst_3
L21:    iconst_1
L22:    dup
L23:    pop2
L24:    ishl
L25:    aload_1
L26:    invokestatic Method org/lwjgl/MemoryUtil method1840 (Ljava/nio/DoubleBuffer;)J
L29:    lload_2
L30:    invokestatic Method org/lwjgl/opengl/NVPixelDataRange nglPixelDataRangeNV (IIJJ)V
L33:    return
L34:    
    .end code
.end method

.method static native nglFlushPixelDataRangeNV : (IJ)V
.end method

.method public static method5130 : (ILjava/nio/ByteBuffer;)V
    .code stack 6 locals 4
L0:     invokestatic Method org/lwjgl/opengl/GLContext method4611 ()Lorg/lwjgl/opengl/kb;
L3:     getfield Field org/lwjgl/opengl/kb UD J
L6:     dup2
L7:     lstore_2
L8:     invokestatic Method org/lwjgl/l method2052 (J)V
L11:    iload_0
L12:    aload_1
L13:    invokestatic Method org/lwjgl/l method2034 (Ljava/nio/ByteBuffer;)V
L16:    aload_1
L17:    invokevirtual Method java/nio/ByteBuffer remaining ()I
L20:    aload_1
L21:    invokestatic Method org/lwjgl/MemoryUtil method1873 (Ljava/nio/ByteBuffer;)J
L24:    lload_2
L25:    invokestatic Method org/lwjgl/opengl/NVPixelDataRange nglPixelDataRangeNV (IIJJ)V
L28:    return
L29:    
    .end code
.end method

.method public static method5131 : (ILjava/nio/FloatBuffer;)V
    .code stack 6 locals 4
L0:     invokestatic Method org/lwjgl/opengl/GLContext method4611 ()Lorg/lwjgl/opengl/kb;
L3:     getfield Field org/lwjgl/opengl/kb UD J
L6:     dup2
L7:     lstore_2
L8:     invokestatic Method org/lwjgl/l method2052 (J)V
L11:    iload_0
L12:    aload_1
L13:    invokestatic Method org/lwjgl/l method2048 (Ljava/nio/FloatBuffer;)V
L16:    aload_1
L17:    invokevirtual Method java/nio/FloatBuffer remaining ()I
L20:    iconst_2
L21:    iconst_1
L22:    dup
L23:    pop2
L24:    ishl
L25:    aload_1
L26:    invokestatic Method org/lwjgl/MemoryUtil method1878 (Ljava/nio/FloatBuffer;)J
L29:    lload_2
L30:    invokestatic Method org/lwjgl/opengl/NVPixelDataRange nglPixelDataRangeNV (IIJJ)V
L33:    return
L34:    
    .end code
.end method
.end class
