.version 49 0
.class public final super org/lwjgl/opengl/NVTransformFeedback2
.super java/lang/Object
.field public static final field4874 I = 36386
.field public static final field4875 I = 36389
.field public static final field4876 I = 36388
.field public static final field4877 I = 36387

.method public static method5214 : (Ljava/nio/IntBuffer;)V
    .code stack 5 locals 3
L0:     invokestatic Method org/lwjgl/opengl/GLContext method4611 ()Lorg/lwjgl/opengl/kb;
L3:     getfield Field org/lwjgl/opengl/kb JA J
L6:     dup2
L7:     lstore_1
L8:     invokestatic Method org/lwjgl/l method2052 (J)V
L11:    aload_0
L12:    dup
L13:    invokestatic Method org/lwjgl/l method2043 (Ljava/nio/IntBuffer;)V
L16:    invokevirtual Method java/nio/IntBuffer remaining ()I
L19:    aload_0
L20:    invokestatic Method org/lwjgl/MemoryUtil method1884 (Ljava/nio/IntBuffer;)J
L23:    lload_1
L24:    invokestatic Method org/lwjgl/opengl/NVTransformFeedback2 nglGenTransformFeedbacksNV (IJJ)V
L27:    return
L28:    
    .end code
.end method

.method static native nglResumeTransformFeedbackNV : (J)V
.end method

.method static native nglPauseTransformFeedbackNV : (J)V
.end method

.method static native nglDrawTransformFeedbackNV : (IIJ)V
.end method

.method public static method5215 : (Ljava/nio/IntBuffer;)V
    .code stack 5 locals 3
L0:     invokestatic Method org/lwjgl/opengl/GLContext method4611 ()Lorg/lwjgl/opengl/kb;
L3:     getfield Field org/lwjgl/opengl/kb XB J
L6:     dup2
L7:     lstore_1
L8:     invokestatic Method org/lwjgl/l method2052 (J)V
L11:    aload_0
L12:    dup
L13:    invokestatic Method org/lwjgl/l method2043 (Ljava/nio/IntBuffer;)V
L16:    invokevirtual Method java/nio/IntBuffer remaining ()I
L19:    aload_0
L20:    invokestatic Method org/lwjgl/MemoryUtil method1884 (Ljava/nio/IntBuffer;)J
L23:    lload_1
L24:    invokestatic Method org/lwjgl/opengl/NVTransformFeedback2 nglDeleteTransformFeedbacksNV (IJJ)V
L27:    return
L28:    
    .end code
.end method

.method static native nglBindTransformFeedbackNV : (IIJ)V
.end method

.method public static method5216 : (I)V
    .code stack 5 locals 4
L0:     invokestatic Method org/lwjgl/opengl/GLContext method4611 ()Lorg/lwjgl/opengl/kb;
L3:     dup
L4:     astore_1
L5:     getfield Field org/lwjgl/opengl/kb XB J
L8:     dup2
L9:     lstore_2
L10:    invokestatic Method org/lwjgl/l method2052 (J)V
L13:    iconst_1
L14:    dup
L15:    dup
L16:    pop2
L17:    aload_1
L18:    iload_0
L19:    invokestatic Method org/lwjgl/opengl/bB method5479 (Lorg/lwjgl/opengl/kb;I)J
L22:    lload_2
L23:    invokestatic Method org/lwjgl/opengl/NVTransformFeedback2 nglDeleteTransformFeedbacksNV (IJJ)V
L26:    return
L27:    
    .end code
.end method

.method public static method5217 : (II)V
    .code stack 4 locals 4
L0:     invokestatic Method org/lwjgl/opengl/GLContext method4611 ()Lorg/lwjgl/opengl/kb;
L3:     getfield Field org/lwjgl/opengl/kb fe J
L6:     dup2
L7:     lstore_2
L8:     invokestatic Method org/lwjgl/l method2052 (J)V
L11:    iload_0
L12:    iload_1
L13:    lload_2
L14:    invokestatic Method org/lwjgl/opengl/NVTransformFeedback2 nglDrawTransformFeedbackNV (IIJ)V
L17:    return
L18:    
    .end code
.end method

.method public static method5218 : (II)V
    .code stack 4 locals 4
L0:     invokestatic Method org/lwjgl/opengl/GLContext method4611 ()Lorg/lwjgl/opengl/kb;
L3:     getfield Field org/lwjgl/opengl/kb OD J
L6:     dup2
L7:     lstore_2
L8:     invokestatic Method org/lwjgl/l method2052 (J)V
L11:    iload_0
L12:    iload_1
L13:    lload_2
L14:    invokestatic Method org/lwjgl/opengl/NVTransformFeedback2 nglBindTransformFeedbackNV (IIJ)V
L17:    return
L18:    
    .end code
.end method

.method private <init> : ()V
    .code stack 1 locals 1
L0:     aload_0
L1:     invokespecial Method java/lang/Object <init> ()V
L4:     return
L5:     
    .end code
.end method

.method public static method5219 : (I)Z
    .code stack 4 locals 3
L0:     invokestatic Method org/lwjgl/opengl/GLContext method4611 ()Lorg/lwjgl/opengl/kb;
L3:     getfield Field org/lwjgl/opengl/kb Je J
L6:     dup2
L7:     lstore_1
L8:     invokestatic Method org/lwjgl/l method2052 (J)V
L11:    iload_0
L12:    lload_1
L13:    invokestatic Method org/lwjgl/opengl/NVTransformFeedback2 nglIsTransformFeedbackNV (IJ)Z
L16:    ireturn
L17:    
    .end code
.end method

.method public static method5220 : ()V
    .code stack 4 locals 2
L0:     invokestatic Method org/lwjgl/opengl/GLContext method4611 ()Lorg/lwjgl/opengl/kb;
L3:     getfield Field org/lwjgl/opengl/kb wo J
L6:     dup2
L7:     lstore_0
L8:     invokestatic Method org/lwjgl/l method2052 (J)V
L11:    lload_0
L12:    invokestatic Method org/lwjgl/opengl/NVTransformFeedback2 nglResumeTransformFeedbackNV (J)V
L15:    return
L16:    
    .end code
.end method

.method static native nglIsTransformFeedbackNV : (IJ)Z
.end method

.method public static method5221 : ()I
    .code stack 5 locals 3
L0:     invokestatic Method org/lwjgl/opengl/GLContext method4611 ()Lorg/lwjgl/opengl/kb;
L3:     dup
L4:     getfield Field org/lwjgl/opengl/kb JA J
L7:     dup2
L8:     lstore_0
L9:     invokestatic Method org/lwjgl/l method2052 (J)V
L12:    invokestatic Method org/lwjgl/opengl/bB method5467 (Lorg/lwjgl/opengl/kb;)Ljava/nio/IntBuffer;
L15:    astore_2
L16:    iconst_1
L17:    dup
L18:    dup
L19:    pop2
L20:    aload_2
L21:    invokestatic Method org/lwjgl/MemoryUtil method1884 (Ljava/nio/IntBuffer;)J
L24:    lload_0
L25:    invokestatic Method org/lwjgl/opengl/NVTransformFeedback2 nglGenTransformFeedbacksNV (IJJ)V
L28:    aload_2
L29:    iconst_0
L30:    iconst_1
L31:    dup
L32:    pop2
L33:    invokevirtual Method java/nio/IntBuffer get (I)I
L36:    ireturn
L37:    
    .end code
.end method

.method static native nglDeleteTransformFeedbacksNV : (IJJ)V
.end method

.method public static method5222 : ()V
    .code stack 4 locals 2
L0:     invokestatic Method org/lwjgl/opengl/GLContext method4611 ()Lorg/lwjgl/opengl/kb;
L3:     getfield Field org/lwjgl/opengl/kb Om J
L6:     dup2
L7:     lstore_0
L8:     invokestatic Method org/lwjgl/l method2052 (J)V
L11:    lload_0
L12:    invokestatic Method org/lwjgl/opengl/NVTransformFeedback2 nglPauseTransformFeedbackNV (J)V
L15:    return
L16:    
    .end code
.end method

.method static native nglGenTransformFeedbacksNV : (IJJ)V
.end method
.end class
