.version 49 0
.class public final super org/lwjgl/opengl/oc
.super java/lang/Object
.field public static final try I = 8
.field public static final field5507 I = 33370
.field public static final new I = 1
.field public static final field5508 I = 4
.field public static final this I = 33369
.field public static final field5509 I = -1
.field public static final field5510 I = 16
.field public static final field5511 I = 2
.field public static final field5512 I = 33368

.method public static method5634 : (IIDD)V
    .code stack 6 locals 6
L0:     iload_0
L1:     iload_1
L2:     dload_2
L3:     dload 4
L5:     invokestatic Method org/lwjgl/opengl/GL41 method4464 (IIDD)V
L8:     return
L9:     
    .end code
.end method

.method public static method5635 : (IIFF)V
    .code stack 4 locals 4
L0:     iload_0
L1:     iload_1
L2:     fload_2
L3:     fload_3
L4:     invokestatic Method org/lwjgl/opengl/GL41 method4512 (IIFF)V
L7:     return
L8:     
    .end code
.end method

.method public static method5636 : (IILjava/nio/DoubleBuffer;)V
    .code stack 3 locals 3
L0:     iload_0
L1:     iload_1
L2:     aload_2
L3:     invokestatic Method org/lwjgl/opengl/GL41 method4466 (IILjava/nio/DoubleBuffer;)V
L6:     return
L7:     
    .end code
.end method

.method public static method5637 : (IIZLjava/nio/DoubleBuffer;)V
    .code stack 4 locals 4
L0:     iload_0
L1:     iload_1
L2:     iload_2
L3:     aload_3
L4:     invokestatic Method org/lwjgl/opengl/GL41 method4463 (IIZLjava/nio/DoubleBuffer;)V
L7:     return
L8:     
    .end code
.end method

.method public static method5638 : (IILjava/nio/DoubleBuffer;)V
    .code stack 3 locals 3
L0:     iload_0
L1:     iload_1
L2:     aload_2
L3:     invokestatic Method org/lwjgl/opengl/GL41 method4491 (IILjava/nio/DoubleBuffer;)V
L6:     return
L7:     
    .end code
.end method

.method public static method5639 : (IIZLjava/nio/FloatBuffer;)V
    .code stack 4 locals 4
L0:     iload_0
L1:     iload_1
L2:     iload_2
L3:     aload_3
L4:     invokestatic Method org/lwjgl/opengl/GL41 method4492 (IIZLjava/nio/FloatBuffer;)V
L7:     return
L8:     
    .end code
.end method

.method public static method5640 : (IILjava/nio/DoubleBuffer;)V
    .code stack 3 locals 3
L0:     iload_0
L1:     iload_1
L2:     aload_2
L3:     invokestatic Method org/lwjgl/opengl/GL41 method4452 (IILjava/nio/DoubleBuffer;)V
L6:     return
L7:     
    .end code
.end method

.method public static method5641 : (IILjava/nio/DoubleBuffer;)V
    .code stack 3 locals 3
L0:     iload_0
L1:     iload_1
L2:     aload_2
L3:     invokestatic Method org/lwjgl/opengl/GL41 method4501 (IILjava/nio/DoubleBuffer;)V
L6:     return
L7:     
    .end code
.end method

.method public static method5642 : (IID)V
    .code stack 4 locals 4
L0:     iload_0
L1:     iload_1
L2:     dload_2
L3:     invokestatic Method org/lwjgl/opengl/GL41 method4489 (IID)V
L6:     return
L7:     
    .end code
.end method

.method public static method5643 : (IIZLjava/nio/FloatBuffer;)V
    .code stack 4 locals 4
L0:     iload_0
L1:     iload_1
L2:     iload_2
L3:     aload_3
L4:     invokestatic Method org/lwjgl/opengl/GL41 method4511 (IIZLjava/nio/FloatBuffer;)V
L7:     return
L8:     
    .end code
.end method

.method public static method5644 : (I[Ljava/nio/ByteBuffer;)I
    .code stack 2 locals 2
L0:     iload_0
L1:     aload_1
L2:     invokestatic Method org/lwjgl/opengl/GL41 method4441 (I[Ljava/nio/ByteBuffer;)I
L5:     ireturn
L6:     
    .end code
.end method

.method public static method5645 : (IILjava/nio/IntBuffer;)V
    .code stack 3 locals 3
L0:     iload_0
L1:     iload_1
L2:     aload_2
L3:     invokestatic Method org/lwjgl/opengl/GL41 method4462 (IILjava/nio/IntBuffer;)V
L6:     return
L7:     
    .end code
.end method

.method public static method5646 : (Ljava/nio/IntBuffer;)V
    .code stack 1 locals 1
L0:     aload_0
L1:     invokestatic Method org/lwjgl/opengl/GL41 method4493 (Ljava/nio/IntBuffer;)V
L4:     return
L5:     
    .end code
.end method

.method public static method5647 : (IIZLjava/nio/FloatBuffer;)V
    .code stack 4 locals 4
L0:     iload_0
L1:     iload_1
L2:     iload_2
L3:     aload_3
L4:     invokestatic Method org/lwjgl/opengl/GL41 method4477 (IIZLjava/nio/FloatBuffer;)V
L7:     return
L8:     
    .end code
.end method

.method public static method5648 : (IILjava/nio/IntBuffer;)V
    .code stack 3 locals 3
L0:     iload_0
L1:     iload_1
L2:     aload_2
L3:     invokestatic Method org/lwjgl/opengl/GL41 method4420 (IILjava/nio/IntBuffer;)V
L6:     return
L7:     
    .end code
.end method

.method public static method5649 : (IIZLjava/nio/DoubleBuffer;)V
    .code stack 4 locals 4
L0:     iload_0
L1:     iload_1
L2:     iload_2
L3:     aload_3
L4:     invokestatic Method org/lwjgl/opengl/GL41 method4498 (IIZLjava/nio/DoubleBuffer;)V
L7:     return
L8:     
    .end code
.end method

.method public static method5650 : (II)V
    .code stack 2 locals 2
L0:     iload_0
L1:     iload_1
L2:     invokestatic Method org/lwjgl/opengl/GL41 method4514 (II)V
L5:     return
L6:     
    .end code
.end method

.method public static method5651 : (I)V
    .code stack 1 locals 1
L0:     iload_0
L1:     invokestatic Method org/lwjgl/opengl/GL41 method4479 (I)V
L4:     return
L5:     
    .end code
.end method

.method public static method5652 : (IIZLjava/nio/DoubleBuffer;)V
    .code stack 4 locals 4
L0:     iload_0
L1:     iload_1
L2:     iload_2
L3:     aload_3
L4:     invokestatic Method org/lwjgl/opengl/GL41 method4421 (IIZLjava/nio/DoubleBuffer;)V
L7:     return
L8:     
    .end code
.end method

.method public static method5653 : (IIDDD)V
    .code stack 8 locals 8
L0:     iload_0
L1:     iload_1
L2:     dload_2
L3:     dload 4
L5:     dload 6
L7:     invokestatic Method org/lwjgl/opengl/GL41 method4510 (IIDDD)V
L10:    return
L11:    
    .end code
.end method

.method public static method5654 : (IILjava/nio/IntBuffer;)V
    .code stack 3 locals 3
L0:     iload_0
L1:     iload_1
L2:     aload_2
L3:     invokestatic Method org/lwjgl/opengl/GL41 method4438 (IILjava/nio/IntBuffer;)V
L6:     return
L7:     
    .end code
.end method

.method public static method5655 : (IILjava/nio/FloatBuffer;)V
    .code stack 3 locals 3
L0:     iload_0
L1:     iload_1
L2:     aload_2
L3:     invokestatic Method org/lwjgl/opengl/GL41 method4423 (IILjava/nio/FloatBuffer;)V
L6:     return
L7:     
    .end code
.end method

.method public static method5656 : (III)V
    .code stack 3 locals 3
L0:     iload_0
L1:     iload_1
L2:     iload_2
L3:     invokestatic Method org/lwjgl/opengl/GL41 method4451 (III)V
L6:     return
L7:     
    .end code
.end method

.method public static method5657 : (ILjava/nio/ByteBuffer;)I
    .code stack 2 locals 2
L0:     iload_0
L1:     aload_1
L2:     invokestatic Method org/lwjgl/opengl/GL41 method4424 (ILjava/nio/ByteBuffer;)I
L5:     ireturn
L6:     
    .end code
.end method

.method public static method5658 : (III)V
    .code stack 3 locals 3
L0:     iload_0
L1:     iload_1
L2:     iload_2
L3:     invokestatic Method org/lwjgl/opengl/GL41 method4515 (III)V
L6:     return
L7:     
    .end code
.end method

.method public static method5659 : (IILjava/nio/IntBuffer;)V
    .code stack 3 locals 3
L0:     iload_0
L1:     iload_1
L2:     aload_2
L3:     invokestatic Method org/lwjgl/opengl/GL41 method4481 (IILjava/nio/IntBuffer;)V
L6:     return
L7:     
    .end code
.end method

.method public static method5660 : (IIZLjava/nio/FloatBuffer;)V
    .code stack 4 locals 4
L0:     iload_0
L1:     iload_1
L2:     iload_2
L3:     aload_3
L4:     invokestatic Method org/lwjgl/opengl/GL41 method4436 (IIZLjava/nio/FloatBuffer;)V
L7:     return
L8:     
    .end code
.end method

.method public static method5661 : (I)V
    .code stack 1 locals 1
L0:     iload_0
L1:     invokestatic Method org/lwjgl/opengl/GL41 method4455 (I)V
L4:     return
L5:     
    .end code
.end method

.method public static method5662 : (IILjava/nio/IntBuffer;)V
    .code stack 3 locals 3
L0:     iload_0
L1:     iload_1
L2:     aload_2
L3:     invokestatic Method org/lwjgl/opengl/GL41 method4435 (IILjava/nio/IntBuffer;)V
L6:     return
L7:     
    .end code
.end method

.method public static method5663 : (IILjava/nio/FloatBuffer;)V
    .code stack 3 locals 3
L0:     iload_0
L1:     iload_1
L2:     aload_2
L3:     invokestatic Method org/lwjgl/opengl/GL41 method4483 (IILjava/nio/FloatBuffer;)V
L6:     return
L7:     
    .end code
.end method

.method public static method5664 : (IILjava/nio/FloatBuffer;)V
    .code stack 3 locals 3
L0:     iload_0
L1:     iload_1
L2:     aload_2
L3:     invokestatic Method org/lwjgl/opengl/GL41 method4480 (IILjava/nio/FloatBuffer;)V
L6:     return
L7:     
    .end code
.end method

.method public static method5665 : (I)V
    .code stack 1 locals 1
L0:     iload_0
L1:     invokestatic Method org/lwjgl/opengl/GL41 method4427 (I)V
L4:     return
L5:     
    .end code
.end method

.method public static method5666 : (IIZLjava/nio/DoubleBuffer;)V
    .code stack 4 locals 4
L0:     iload_0
L1:     iload_1
L2:     iload_2
L3:     aload_3
L4:     invokestatic Method org/lwjgl/opengl/GL41 method4494 (IIZLjava/nio/DoubleBuffer;)V
L7:     return
L8:     
    .end code
.end method

.method public static method5667 : (Ljava/nio/IntBuffer;)V
    .code stack 1 locals 1
L0:     aload_0
L1:     invokestatic Method org/lwjgl/opengl/GL41 method4461 (Ljava/nio/IntBuffer;)V
L4:     return
L5:     
    .end code
.end method

.method public static method5668 : (IIF)V
    .code stack 3 locals 3
L0:     iload_0
L1:     iload_1
L2:     fload_2
L3:     invokestatic Method org/lwjgl/opengl/GL41 method4432 (IIF)V
L6:     return
L7:     
    .end code
.end method

.method public static method5669 : (IILjava/nio/IntBuffer;)V
    .code stack 3 locals 3
L0:     iload_0
L1:     iload_1
L2:     aload_2
L3:     invokestatic Method org/lwjgl/opengl/GL41 method4465 (IILjava/nio/IntBuffer;)V
L6:     return
L7:     
    .end code
.end method

.method public static method5670 : (IIZLjava/nio/DoubleBuffer;)V
    .code stack 4 locals 4
L0:     iload_0
L1:     iload_1
L2:     iload_2
L3:     aload_3
L4:     invokestatic Method org/lwjgl/opengl/GL41 method4497 (IIZLjava/nio/DoubleBuffer;)V
L7:     return
L8:     
    .end code
.end method

.method public static method5671 : (II)Ljava/lang/String;
    .code stack 2 locals 2
L0:     iload_0
L1:     iload_1
L2:     invokestatic Method org/lwjgl/opengl/GL41 method4444 (II)Ljava/lang/String;
L5:     areturn
L6:     
    .end code
.end method

.method public static method5672 : ()I
    .code stack 1 locals 0
L0:     invokestatic Method org/lwjgl/opengl/GL41 method4456 ()I
L3:     ireturn
L4:     
    .end code
.end method

.method public static method5673 : (IIFFF)V
    .code stack 5 locals 5
L0:     iload_0
L1:     iload_1
L2:     fload_2
L3:     fload_3
L4:     fload 4
L6:     invokestatic Method org/lwjgl/opengl/GL41 method4431 (IIFFF)V
L9:     return
L10:    
    .end code
.end method

.method public static method5674 : (IIFFFF)V
    .code stack 6 locals 6
L0:     iload_0
L1:     iload_1
L2:     fload_2
L3:     fload_3
L4:     fload 4
L6:     fload 5
L8:     invokestatic Method org/lwjgl/opengl/GL41 method4474 (IIFFFF)V
L11:    return
L12:    
    .end code
.end method

.method public static method5675 : (IIZLjava/nio/DoubleBuffer;)V
    .code stack 4 locals 4
L0:     iload_0
L1:     iload_1
L2:     iload_2
L3:     aload_3
L4:     invokestatic Method org/lwjgl/opengl/GL41 method4457 (IIZLjava/nio/DoubleBuffer;)V
L7:     return
L8:     
    .end code
.end method

.method public static method5676 : (IIZLjava/nio/FloatBuffer;)V
    .code stack 4 locals 4
L0:     iload_0
L1:     iload_1
L2:     iload_2
L3:     aload_3
L4:     invokestatic Method org/lwjgl/opengl/GL41 method4508 (IIZLjava/nio/FloatBuffer;)V
L7:     return
L8:     
    .end code
.end method

.method public static method5677 : (IILjava/nio/FloatBuffer;)V
    .code stack 3 locals 3
L0:     iload_0
L1:     iload_1
L2:     aload_2
L3:     invokestatic Method org/lwjgl/opengl/GL41 method4428 (IILjava/nio/FloatBuffer;)V
L6:     return
L7:     
    .end code
.end method

.method public static method5678 : (IILjava/nio/IntBuffer;)V
    .code stack 3 locals 3
L0:     iload_0
L1:     iload_1
L2:     aload_2
L3:     invokestatic Method org/lwjgl/opengl/GL41 method4426 (IILjava/nio/IntBuffer;)V
L6:     return
L7:     
    .end code
.end method

.method private <init> : ()V
    .code stack 1 locals 1
L0:     aload_0
L1:     invokespecial Method java/lang/Object <init> ()V
L4:     return
L5:     
    .end code
.end method

.method public static method5679 : (IIIIII)V
    .code stack 6 locals 6
L0:     iload_0
L1:     iload_1
L2:     iload_2
L3:     iload_3
L4:     iload 4
L6:     iload 5
L8:     invokestatic Method org/lwjgl/opengl/GL41 method4495 (IIIIII)V
L11:    return
L12:    
    .end code
.end method

.method public static method5680 : (III)V
    .code stack 3 locals 3
L0:     iload_0
L1:     iload_1
L2:     iload_2
L3:     invokestatic Method org/lwjgl/opengl/GL41 method4482 (III)V
L6:     return
L7:     
    .end code
.end method

.method public static method5681 : (ILjava/nio/IntBuffer;Ljava/nio/ByteBuffer;)V
    .code stack 3 locals 3
L0:     iload_0
L1:     aload_1
L2:     aload_2
L3:     invokestatic Method org/lwjgl/opengl/GL41 method4506 (ILjava/nio/IntBuffer;Ljava/nio/ByteBuffer;)V
L6:     return
L7:     
    .end code
.end method

.method public static method5682 : (IIZLjava/nio/DoubleBuffer;)V
    .code stack 4 locals 4
L0:     iload_0
L1:     iload_1
L2:     iload_2
L3:     aload_3
L4:     invokestatic Method org/lwjgl/opengl/GL41 method4459 (IIZLjava/nio/DoubleBuffer;)V
L7:     return
L8:     
    .end code
.end method

.method public static method5683 : (IIZLjava/nio/FloatBuffer;)V
    .code stack 4 locals 4
L0:     iload_0
L1:     iload_1
L2:     iload_2
L3:     aload_3
L4:     invokestatic Method org/lwjgl/opengl/GL41 method4486 (IIZLjava/nio/FloatBuffer;)V
L7:     return
L8:     
    .end code
.end method

.method public static method5684 : (IIZLjava/nio/FloatBuffer;)V
    .code stack 4 locals 4
L0:     iload_0
L1:     iload_1
L2:     iload_2
L3:     aload_3
L4:     invokestatic Method org/lwjgl/opengl/GL41 method4422 (IIZLjava/nio/FloatBuffer;)V
L7:     return
L8:     
    .end code
.end method

.method public static method5685 : (IILjava/nio/IntBuffer;)V
    .code stack 3 locals 3
L0:     iload_0
L1:     iload_1
L2:     aload_2
L3:     invokestatic Method org/lwjgl/opengl/GL41 method4469 (IILjava/nio/IntBuffer;)V
L6:     return
L7:     
    .end code
.end method

.method public static method5686 : (ILjava/lang/CharSequence;)I
    .code stack 2 locals 2
L0:     iload_0
L1:     aload_1
L2:     invokestatic Method org/lwjgl/opengl/GL41 method4442 (ILjava/lang/CharSequence;)I
L5:     ireturn
L6:     
    .end code
.end method

.method public static method5687 : (IIZLjava/nio/FloatBuffer;)V
    .code stack 4 locals 4
L0:     iload_0
L1:     iload_1
L2:     iload_2
L3:     aload_3
L4:     invokestatic Method org/lwjgl/opengl/GL41 method4516 (IIZLjava/nio/FloatBuffer;)V
L7:     return
L8:     
    .end code
.end method

.method public static method5688 : (IIIII)V
    .code stack 5 locals 5
L0:     iload_0
L1:     iload_1
L2:     iload_2
L3:     iload_3
L4:     iload 4
L6:     invokestatic Method org/lwjgl/opengl/GL41 method4504 (IIIII)V
L9:     return
L10:    
    .end code
.end method

.method public static method5689 : (IIIIII)V
    .code stack 6 locals 6
L0:     iload_0
L1:     iload_1
L2:     iload_2
L3:     iload_3
L4:     iload 4
L6:     iload 5
L8:     invokestatic Method org/lwjgl/opengl/GL41 method4507 (IIIIII)V
L11:    return
L12:    
    .end code
.end method

.method public static method5690 : (IIDDDD)V
    .code stack 10 locals 10
L0:     iload_0
L1:     iload_1
L2:     dload_2
L3:     dload 4
L5:     dload 6
L7:     dload 8
L9:     invokestatic Method org/lwjgl/opengl/GL41 method4434 (IIDDDD)V
L12:    return
L13:    
    .end code
.end method

.method public static method5691 : (IIZLjava/nio/DoubleBuffer;)V
    .code stack 4 locals 4
L0:     iload_0
L1:     iload_1
L2:     iload_2
L3:     aload_3
L4:     invokestatic Method org/lwjgl/opengl/GL41 method4467 (IIZLjava/nio/DoubleBuffer;)V
L7:     return
L8:     
    .end code
.end method

.method public static method5692 : (IIII)V
    .code stack 4 locals 4
L0:     iload_0
L1:     iload_1
L2:     iload_2
L3:     iload_3
L4:     invokestatic Method org/lwjgl/opengl/GL41 method4496 (IIII)V
L7:     return
L8:     
    .end code
.end method

.method public static method5693 : (IILjava/nio/IntBuffer;)V
    .code stack 3 locals 3
L0:     iload_0
L1:     iload_1
L2:     aload_2
L3:     invokestatic Method org/lwjgl/opengl/GL41 method4447 (IILjava/nio/IntBuffer;)V
L6:     return
L7:     
    .end code
.end method

.method public static method5694 : (IIIII)V
    .code stack 5 locals 5
L0:     iload_0
L1:     iload_1
L2:     iload_2
L3:     iload_3
L4:     iload 4
L6:     invokestatic Method org/lwjgl/opengl/GL41 method4450 (IIIII)V
L9:     return
L10:    
    .end code
.end method

.method public static method5695 : (I)Z
    .code stack 1 locals 1
L0:     iload_0
L1:     invokestatic Method org/lwjgl/opengl/GL41 method4440 (I)Z
L4:     ireturn
L5:     
    .end code
.end method

.method public static method5696 : (IIZLjava/nio/DoubleBuffer;)V
    .code stack 4 locals 4
L0:     iload_0
L1:     iload_1
L2:     iload_2
L3:     aload_3
L4:     invokestatic Method org/lwjgl/opengl/GL41 method4453 (IIZLjava/nio/DoubleBuffer;)V
L7:     return
L8:     
    .end code
.end method

.method public static method5697 : (I[Ljava/lang/CharSequence;)I
    .code stack 2 locals 2
L0:     iload_0
L1:     aload_1
L2:     invokestatic Method org/lwjgl/opengl/GL41 method4499 (I[Ljava/lang/CharSequence;)I
L5:     ireturn
L6:     
    .end code
.end method

.method public static method5698 : (IIII)V
    .code stack 4 locals 4
L0:     iload_0
L1:     iload_1
L2:     iload_2
L3:     iload_3
L4:     invokestatic Method org/lwjgl/opengl/GL41 method4513 (IIII)V
L7:     return
L8:     
    .end code
.end method

.method public static method5699 : (IILjava/nio/ByteBuffer;)I
    .code stack 3 locals 3
L0:     iload_0
L1:     iload_1
L2:     aload_2
L3:     invokestatic Method org/lwjgl/opengl/GL41 method4487 (IILjava/nio/ByteBuffer;)I
L6:     ireturn
L7:     
    .end code
.end method

.method public static method5700 : (IIZLjava/nio/FloatBuffer;)V
    .code stack 4 locals 4
L0:     iload_0
L1:     iload_1
L2:     iload_2
L3:     aload_3
L4:     invokestatic Method org/lwjgl/opengl/GL41 method4509 (IIZLjava/nio/FloatBuffer;)V
L7:     return
L8:     
    .end code
.end method

.method public static method5701 : (III)V
    .code stack 3 locals 3
L0:     iload_0
L1:     iload_1
L2:     iload_2
L3:     invokestatic Method org/lwjgl/opengl/GL41 method4443 (III)V
L6:     return
L7:     
    .end code
.end method

.method public static method5702 : (II)I
    .code stack 2 locals 2
L0:     iload_0
L1:     iload_1
L2:     invokestatic Method org/lwjgl/opengl/GL41 method4485 (II)I
L5:     ireturn
L6:     
    .end code
.end method
.end class
