.version 49 0
.class public final super org/lwjgl/opengl/pB
.super java/lang/Object

.method private <init> : ()V
    .code stack 1 locals 1
L0:     aload_0
L1:     invokespecial Method java/lang/Object <init> ()V
L4:     return
L5:     
    .end code
.end method

.method public static break : (IIIIIIIIIIIIIII)V
    .code stack 15 locals 15
L0:     iload_0
L1:     iload_1
L2:     iload_2
L3:     iload_3
L4:     iload 4
L6:     iload 5
L8:     iload 6
L10:    iload 7
L12:    iload 8
L14:    iload 9
L16:    iload 10
L18:    iload 11
L20:    iload 12
L22:    iload 13
L24:    iload 14
L26:    invokestatic Method org/lwjgl/opengl/GL43 break (IIIIIIIIIIIIIII)V
L29:    return
L30:    
    .end code
.end method
.end class
