.version 49 0
.class public final super org/lwjgl/opengl/pC
.super java/lang/Object
.field public static final field5515 I = 34229

.method private <init> : ()V
    .code stack 1 locals 1
L0:     aload_0
L1:     invokespecial Method java/lang/Object <init> ()V
L4:     return
L5:     
    .end code
.end method

.method public static method5704 : (I)V
    .code stack 1 locals 1
L0:     iload_0
L1:     invokestatic Method org/lwjgl/opengl/GL30 method4227 (I)V
L4:     return
L5:     
    .end code
.end method

.method public static method5705 : ()I
    .code stack 1 locals 0
L0:     invokestatic Method org/lwjgl/opengl/GL30 method4184 ()I
L3:     ireturn
L4:     
    .end code
.end method

.method public static method5706 : (Ljava/nio/IntBuffer;)V
    .code stack 1 locals 1
L0:     aload_0
L1:     invokestatic Method org/lwjgl/opengl/GL30 method4222 (Ljava/nio/IntBuffer;)V
L4:     return
L5:     
    .end code
.end method

.method public static method5707 : (I)Z
    .code stack 1 locals 1
L0:     iload_0
L1:     invokestatic Method org/lwjgl/opengl/GL30 method4157 (I)Z
L4:     ireturn
L5:     
    .end code
.end method

.method public static method5708 : (Ljava/nio/IntBuffer;)V
    .code stack 1 locals 1
L0:     aload_0
L1:     invokestatic Method org/lwjgl/opengl/GL30 method4233 (Ljava/nio/IntBuffer;)V
L4:     return
L5:     
    .end code
.end method

.method public static method5709 : (I)V
    .code stack 1 locals 1
L0:     iload_0
L1:     invokestatic Method org/lwjgl/opengl/GL30 method4163 (I)V
L4:     return
L5:     
    .end code
.end method
.end class
