.version 49 0
.class public final super org/lwjgl/opengl/pc
.super java/lang/Object
.field public static final field5531 I = 37576
.field public static final field5532 I = 37572
.field public static final field5533 I = 37575
.field public static final field5534 I = 37586
.field public static final field5535 I = 37568
.field public static final field5536 I = 37571
.field public static final false I = 37596
.field public static final field5537 I = 37582
.field public static final field5538 I = 37584
.field public static final true I = 37578
.field public static final field5539 I = 37587
.field public static final field5540 I = 37569
.field public static final field5541 I = 37585
.field public static final field5542 I = 37583
.field public static final field5543 I = 37580
.field public static final field5544 I = 37591
.field public static final field5545 I = 37590
.field public static final field5546 I = 37577
.field public static final field5547 I = 37595
.field public static final field5548 I = 37574
.field public static final try I = 37594
.field public static final field5549 I = 37573
.field public static final new I = 37593
.field public static final field5550 I = 37588
.field public static final this I = 37570
.field public static final field5551 I = 37592
.field public static final field5552 I = 37589
.field public static final field5553 I = 37579
.field public static final field5554 I = 37581

.method private <init> : ()V
    .code stack 1 locals 1
L0:     aload_0
L1:     invokespecial Method java/lang/Object <init> ()V
L4:     return
L5:     
    .end code
.end method

.method public static method5710 : (III)I
    .code stack 3 locals 3
L0:     iload_0
L1:     iload_1
L2:     iload_2
L3:     invokestatic Method org/lwjgl/opengl/GL42 method4535 (III)I
L6:     ireturn
L7:     
    .end code
.end method

.method public static method5711 : (IIILjava/nio/IntBuffer;)V
    .code stack 4 locals 4
L0:     iload_0
L1:     iload_1
L2:     iload_2
L3:     aload_3
L4:     invokestatic Method org/lwjgl/opengl/GL42 method4537 (IIILjava/nio/IntBuffer;)V
L7:     return
L8:     
    .end code
.end method
.end class
