.version 49 0
.class super abstract org/lwjgl/opengl/q
.super java/lang/Object
.implements org/lwjgl/opengl/C
.field protected field508 Lorg/lwjgl/opengl/PixelFormat;
.field protected field509 Lorg/lwjgl/opengl/Jb;
.field protected field510 Lorg/lwjgl/opengl/a;

.method public method263 : ()Z
    .code stack 2 locals 3
L0:     getstatic Field org/lwjgl/opengl/GlobalLock lock Ljava/lang/Object;
L3:     dup
L4:     astore_1
L5:     monitorenter
        .catch [0] from L6 to L19 using L21
L6:     aload_0
L7:     dup
L8:     invokevirtual Method org/lwjgl/opengl/q this ()V
L11:    getfield Field org/lwjgl/opengl/q field509 Lorg/lwjgl/opengl/Jb;
L14:    invokevirtual Method org/lwjgl/opengl/Jb method3618 ()Z
L17:    aload_1
L18:    monitorexit
L19:    ireturn
L20:    athrow
        .catch [0] from L21 to L24 using L21
L21:    astore_2
L22:    aload_1
L23:    monitorexit
L24:    aload_2
L25:    athrow
L26:    
        .attribute StackMap b'\x00\x02\x00\x14\x00\x00\x00\x01\x07\x00\x23\x00\x15\x00\x02\x07\x00\x02\x07\x00\x04\x00\x01\x07\x00\x23'
    .end code
    .exceptions org/lwjgl/LWJGLException
.end method

.method public method310 : ()Lorg/lwjgl/opengl/h;
    .code stack 1 locals 1
L0:     aload_0
L1:     getfield Field org/lwjgl/opengl/q field508 Lorg/lwjgl/opengl/PixelFormat;
L4:     areturn
L5:     
    .end code
.end method

.method public method76 : ()V
    .code stack 0 locals 1
L0:     invokestatic Method org/lwjgl/opengl/n method5630 ()V
L3:     return
L4:     
    .end code
.end method

.method public method71 : ()V
    .code stack 5 locals 4
L0:     getstatic Field org/lwjgl/opengl/GlobalLock lock Ljava/lang/Object;
L3:     dup
L4:     astore_1
L5:     monitorenter
L6:     aload_0
L7:     getfield Field org/lwjgl/opengl/q field509 Lorg/lwjgl/opengl/Jb;
L10:    ifnonnull L17
L13:    aload_1
L14:    monitorexit
L15:    return
L16:    athrow
        .catch org/lwjgl/LWJGLException from L17 to L52 using L56
        .catch [0] from L6 to L15 using L83
        .catch [0] from L17 to L55 using L83
L17:    aload_0
L18:    aconst_null
L19:    aload_0
L20:    dup
L21:    dup_x2
L22:    invokevirtual Method org/lwjgl/opengl/q method56 ()V
L25:    getfield Field org/lwjgl/opengl/q field509 Lorg/lwjgl/opengl/Jb;
L28:    invokevirtual Method org/lwjgl/opengl/Jb method3621 ()V
L31:    putfield Field org/lwjgl/opengl/q field509 Lorg/lwjgl/opengl/Jb;
L34:    getfield Field org/lwjgl/opengl/q field510 Lorg/lwjgl/opengl/a;
L37:    ifnull L80
L40:    aconst_null
L41:    aload_0
L42:    dup_x1
L43:    getfield Field org/lwjgl/opengl/q field510 Lorg/lwjgl/opengl/a;
L46:    invokevirtual Method org/lwjgl/opengl/a method4675 ()V
L49:    putfield Field org/lwjgl/opengl/q field510 Lorg/lwjgl/opengl/a;
L52:    goto L80
L55:    athrow
        .catch [0] from L56 to L82 using L83
L56:    astore_2
L57:    new java/lang/StringBuilder
L60:    dup
L61:    invokespecial Method java/lang/StringBuilder <init> ()V
L64:    iconst_0
L65:    ldc "Exception occurred while destroying Drawable: "
L67:    invokevirtual Method java/lang/StringBuilder insert (ILjava/lang/String;)Ljava/lang/StringBuilder;
L70:    aload_2
L71:    invokevirtual Method java/lang/StringBuilder append (Ljava/lang/Object;)Ljava/lang/StringBuilder;
L74:    invokevirtual Method java/lang/StringBuilder toString ()Ljava/lang/String;
L77:    invokestatic Method org/lwjgl/LWJGLUtil log (Ljava/lang/CharSequence;)V
L80:    aload_1
L81:    monitorexit
L82:    return
        .catch [0] from L83 to L86 using L83
L83:    astore_3
L84:    aload_1
L85:    monitorexit
L86:    aload_3
L87:    athrow
L88:    athrow
L89:    
        .attribute StackMap b'\x00\x07\x00\x10\x00\x00\x00\x01\x07\x00\x23\x00\x11\x00\x02\x07\x00\x02\x07\x00\x04\x00\x00\x00\x37\x00\x00\x00\x01\x07\x00\x23\x00\x38\x00\x02\x07\x00\x02\x07\x00\x04\x00\x01\x07\x00\x10\x00\x50\x00\x02\x07\x00\x02\x07\x00\x04\x00\x00\x00\x53\x00\x02\x07\x00\x02\x07\x00\x04\x00\x01\x07\x00\x23\x00\x58\x00\x00\x00\x01\x07\x00\x23'
    .end code
.end method

.method public new : ()Lorg/lwjgl/opengl/Jb;
    .code stack 5 locals 3
L0:     getstatic Field org/lwjgl/opengl/GlobalLock lock Ljava/lang/Object;
L3:     dup
L4:     astore_1
L5:     monitorenter
        .catch [0] from L6 to L35 using L37
L6:     aload_0
L7:     invokevirtual Method org/lwjgl/opengl/q this ()V
L10:    new org/lwjgl/opengl/Jb
L13:    dup
L14:    aload_0
L15:    dup
L16:    getfield Field org/lwjgl/opengl/q field510 Lorg/lwjgl/opengl/a;
L19:    swap
L20:    getfield Field org/lwjgl/opengl/q field509 Lorg/lwjgl/opengl/Jb;
L23:    invokevirtual Method org/lwjgl/opengl/Jb this ()Lorg/lwjgl/opengl/CB;
L26:    aload_0
L27:    getfield Field org/lwjgl/opengl/q field509 Lorg/lwjgl/opengl/Jb;
L30:    invokespecial Method org/lwjgl/opengl/Jb <init> (Lorg/lwjgl/opengl/a;Lorg/lwjgl/opengl/CB;Lorg/lwjgl/opengl/Jb;)V
L33:    aload_1
L34:    monitorexit
L35:    areturn
L36:    athrow
        .catch [0] from L37 to L40 using L37
L37:    astore_2
L38:    aload_1
L39:    monitorexit
L40:    aload_2
L41:    athrow
L42:    
        .attribute StackMap b'\x00\x02\x00\x24\x00\x00\x00\x01\x07\x00\x23\x00\x25\x00\x02\x07\x00\x02\x07\x00\x04\x00\x01\x07\x00\x23'
    .end code
    .exceptions org/lwjgl/LWJGLException
.end method

.method public method74 : ()V
    .code stack 2 locals 3
L0:     getstatic Field org/lwjgl/opengl/GlobalLock lock Ljava/lang/Object;
L3:     dup
L4:     astore_1
L5:     monitorenter
        .catch [0] from L6 to L19 using L21
L6:     aload_0
L7:     dup
L8:     invokevirtual Method org/lwjgl/opengl/q this ()V
L11:    getfield Field org/lwjgl/opengl/q field509 Lorg/lwjgl/opengl/Jb;
L14:    invokevirtual Method org/lwjgl/opengl/Jb method3617 ()V
L17:    aload_1
L18:    monitorexit
L19:    return
L20:    athrow
        .catch [0] from L21 to L24 using L21
L21:    astore_2
L22:    aload_1
L23:    monitorexit
L24:    aload_2
L25:    athrow
L26:    athrow
L27:    
        .attribute StackMap b'\x00\x03\x00\x14\x00\x00\x00\x01\x07\x00\x23\x00\x15\x00\x02\x07\x00\x02\x07\x00\x04\x00\x01\x07\x00\x23\x00\x1A\x00\x00\x00\x01\x07\x00\x23'
    .end code
    .exceptions org/lwjgl/LWJGLException
.end method

.method public try : ()Lorg/lwjgl/opengl/Jb;
    .code stack 2 locals 3
L0:     getstatic Field org/lwjgl/opengl/GlobalLock lock Ljava/lang/Object;
L3:     dup
L4:     astore_1
L5:     monitorenter
        .catch [0] from L6 to L12 using L14
L6:     aload_0
L7:     getfield Field org/lwjgl/opengl/q field509 Lorg/lwjgl/opengl/Jb;
L10:    aload_1
L11:    monitorexit
L12:    areturn
L13:    athrow
        .catch [0] from L14 to L17 using L14
L14:    astore_2
L15:    aload_1
L16:    monitorexit
L17:    aload_2
L18:    athrow
L19:    
        .attribute StackMap b'\x00\x02\x00\x0D\x00\x00\x00\x01\x07\x00\x23\x00\x0E\x00\x02\x07\x00\x02\x07\x00\x04\x00\x01\x07\x00\x23'
    .end code
.end method

.method public bridge synthetic method307 : ()Lorg/lwjgl/opengl/G;
    .code stack 1 locals 1
L0:     aload_0
L1:     invokevirtual Method org/lwjgl/opengl/q try ()Lorg/lwjgl/opengl/Jb;
L4:     areturn
L5:     
    .end code
.end method

.method public method14 : (I)V
    .code stack 1 locals 2
L0:     iload_1
L1:     invokestatic Method org/lwjgl/opengl/Jb method3623 (I)V
L4:     return
L5:     
    .end code
.end method

.method protected <init> : ()V
    .code stack 1 locals 1
L0:     aload_0
L1:     invokespecial Method java/lang/Object <init> ()V
L4:     return
L5:     
    .end code
.end method

.method public method69 : ()V
    .code stack 0 locals 1
L0:     invokestatic Method org/lwjgl/opengl/Jb method3630 ()V
L3:     return
L4:     
    .end code
    .exceptions org/lwjgl/LWJGLException
.end method

.method public method308 : (Lorg/lwjgl/opengl/h;)V
    .code stack 2 locals 2
L0:     new java/lang/UnsupportedOperationException
L3:     dup
L4:     invokespecial Method java/lang/UnsupportedOperationException <init> ()V
L7:     athrow
L8:     
    .end code
    .exceptions org/lwjgl/LWJGLException
.end method

.method public method56 : ()V
    .code stack 2 locals 3
L0:     getstatic Field org/lwjgl/opengl/GlobalLock lock Ljava/lang/Object;
L3:     dup
L4:     astore_1
L5:     monitorenter
        .catch [0] from L6 to L29 using L31
L6:     aload_0
L7:     dup
L8:     invokevirtual Method org/lwjgl/opengl/q this ()V
L11:    getfield Field org/lwjgl/opengl/q field509 Lorg/lwjgl/opengl/Jb;
L14:    invokevirtual Method org/lwjgl/opengl/Jb method3618 ()Z
L17:    ifeq L27
L20:    aload_0
L21:    getfield Field org/lwjgl/opengl/q field509 Lorg/lwjgl/opengl/Jb;
L24:    invokevirtual Method org/lwjgl/opengl/Jb method3616 ()V
L27:    aload_1
L28:    monitorexit
L29:    return
L30:    athrow
        .catch [0] from L31 to L34 using L31
L31:    astore_2
L32:    aload_1
L33:    monitorexit
L34:    aload_2
L35:    athrow
L36:    athrow
L37:    
        .attribute StackMap b'\x00\x04\x00\x1B\x00\x02\x07\x00\x02\x07\x00\x04\x00\x00\x00\x1E\x00\x00\x00\x01\x07\x00\x23\x00\x1F\x00\x02\x07\x00\x02\x07\x00\x04\x00\x01\x07\x00\x23\x00\x24\x00\x00\x00\x01\x07\x00\x23'
    .end code
    .exceptions org/lwjgl/LWJGLException
.end method

.method protected final this : ()V
    .code stack 3 locals 1
L0:     aload_0
L1:     getfield Field org/lwjgl/opengl/q field509 Lorg/lwjgl/opengl/Jb;
L4:     ifnonnull L17
L7:     new java/lang/IllegalStateException
L10:    dup
L11:    ldc "The Drawable has no context available."
L13:    invokespecial Method java/lang/IllegalStateException <init> (Ljava/lang/String;)V
L16:    athrow
L17:    return
L18:    
        .attribute StackMap b'\x00\x01\x00\x11\x00\x01\x07\x00\x02\x00\x00'
    .end code
.end method

.method public bridge synthetic method309 : ()Lorg/lwjgl/opengl/G;
    .code stack 1 locals 1
L0:     aload_0
L1:     invokevirtual Method org/lwjgl/opengl/q new ()Lorg/lwjgl/opengl/Jb;
L4:     areturn
L5:     
    .end code
    .exceptions org/lwjgl/LWJGLException
.end method

.method public method313 : (Lorg/lwjgl/opengl/h;Lorg/lwjgl/opengl/CB;)V
    .code stack 4 locals 3
L0:     aload_0
L1:     aload_1
L2:     checkcast org/lwjgl/opengl/PixelFormat
L5:     putfield Field org/lwjgl/opengl/q field508 Lorg/lwjgl/opengl/PixelFormat;
L8:     invokestatic Method org/lwjgl/opengl/Display getImplementation ()Lorg/lwjgl/opengl/m;
L11:    aload_0
L12:    dup_x1
L13:    getfield Field org/lwjgl/opengl/q field508 Lorg/lwjgl/opengl/PixelFormat;
L16:    aload_2
L17:    invokeinterface InterfaceMethod org/lwjgl/opengl/m method4717 (Lorg/lwjgl/opengl/PixelFormat;Lorg/lwjgl/opengl/CB;)Lorg/lwjgl/opengl/a; 3
L22:    putfield Field org/lwjgl/opengl/q field510 Lorg/lwjgl/opengl/a;
L25:    return
L26:    
    .end code
    .exceptions org/lwjgl/LWJGLException
.end method

.method public method311 : (Lorg/lwjgl/h;)V
    .code stack 2 locals 4
L0:     getstatic Field org/lwjgl/opengl/GlobalLock lock Ljava/lang/Object;
L3:     dup
L4:     astore_2
L5:     monitorenter
        .catch [0] from L6 to L20 using L22
L6:     aload_0
L7:     dup
L8:     invokevirtual Method org/lwjgl/opengl/q this ()V
L11:    getfield Field org/lwjgl/opengl/q field509 Lorg/lwjgl/opengl/Jb;
L14:    aload_1
L15:    invokevirtual Method org/lwjgl/opengl/Jb method3631 (Lorg/lwjgl/h;)V
L18:    aload_2
L19:    monitorexit
L20:    return
L21:    athrow
        .catch [0] from L22 to L25 using L22
L22:    astore_3
L23:    aload_2
L24:    monitorexit
L25:    aload_3
L26:    athrow
L27:    athrow
L28:    
        .attribute StackMap b'\x00\x03\x00\x15\x00\x00\x00\x01\x07\x00\x23\x00\x16\x00\x03\x07\x00\x02\x07\x00\x98\x07\x00\x04\x00\x01\x07\x00\x23\x00\x1B\x00\x00\x00\x01\x07\x00\x23'
    .end code
    .exceptions org/lwjgl/LWJGLException
.end method

.method public method312 : (FFF)V
    .code stack 4 locals 4
L0:     fload_1
L1:     fload_2
L2:     fload_3
L3:     fconst_0
L4:     invokestatic Method org/lwjgl/opengl/GL11 method3917 (FFFF)V
L7:     sipush 16384
L10:    iconst_1
L11:    dup
L12:    pop2
L13:    invokestatic Method org/lwjgl/opengl/GL11 new (I)V
L16:    return
L17:    
    .end code
.end method
.end class
