.version 49 0
.class public final super org/lwjgl/opengl/qB
.super java/lang/Object

.method public static break : (IIIIIIII)V
    .code stack 8 locals 8
L0:     iload_0
L1:     iload_1
L2:     iload_2
L3:     iload_3
L4:     iload 4
L6:     iload 5
L8:     iload 6
L10:    iload 7
L12:    invokestatic Method org/lwjgl/opengl/GL43 break (IIIIIIII)V
L15:    return
L16:    
    .end code
.end method

.method public static break : (I)V
    .code stack 1 locals 1
L0:     iload_0
L1:     invokestatic Method org/lwjgl/opengl/GL43 break (I)V
L4:     return
L5:     
    .end code
.end method

.method public static break : (IJJ)V
    .code stack 5 locals 5
L0:     iload_0
L1:     lload_1
L2:     lload_3
L3:     invokestatic Method org/lwjgl/opengl/GL43 break (IJJ)V
L6:     return
L7:     
    .end code
.end method

.method public static break : (ILjava/nio/IntBuffer;)V
    .code stack 2 locals 2
L0:     iload_0
L1:     aload_1
L2:     invokestatic Method org/lwjgl/opengl/GL43 break (ILjava/nio/IntBuffer;)V
L5:     return
L6:     
    .end code
.end method

.method public static break : (ILjava/nio/IntBuffer;IIII)V
    .code stack 6 locals 6
L0:     iload_0
L1:     aload_1
L2:     iload_2
L3:     iload_3
L4:     iload 4
L6:     iload 5
L8:     invokestatic Method org/lwjgl/opengl/GL43 break (ILjava/nio/IntBuffer;IIII)V
L11:    return
L12:    
    .end code
.end method

.method private <init> : ()V
    .code stack 1 locals 1
L0:     aload_0
L1:     invokespecial Method java/lang/Object <init> ()V
L4:     return
L5:     
    .end code
.end method

.method public static break : (II)V
    .code stack 2 locals 2
L0:     iload_0
L1:     iload_1
L2:     invokestatic Method org/lwjgl/opengl/GL43 else (II)V
L5:     return
L6:     
    .end code
.end method
.end class
