.version 49 0
.class public final super org/lwjgl/opengl/qc
.super java/lang/Object
.field public static final field5580 I = 36675
.field public static final field5581 I = 36671

.method public static method5718 : (ILjava/nio/IntBuffer;)V
    .code stack 2 locals 2
L0:     iload_0
L1:     aload_1
L2:     invokestatic Method org/lwjgl/opengl/GL40 method4360 (ILjava/nio/IntBuffer;)V
L5:     return
L6:     
    .end code
.end method

.method public static method5719 : (ILjava/nio/ByteBuffer;)V
    .code stack 2 locals 2
L0:     iload_0
L1:     aload_1
L2:     invokestatic Method org/lwjgl/opengl/GL40 method4379 (ILjava/nio/ByteBuffer;)V
L5:     return
L6:     
    .end code
.end method

.method public static method5720 : (IILjava/nio/IntBuffer;)V
    .code stack 3 locals 3
L0:     iload_0
L1:     iload_1
L2:     aload_2
L3:     invokestatic Method org/lwjgl/opengl/GL40 method4383 (IILjava/nio/IntBuffer;)V
L6:     return
L7:     
    .end code
.end method

.method public static method5721 : (IIJ)V
    .code stack 4 locals 4
L0:     iload_0
L1:     iload_1
L2:     lload_2
L3:     invokestatic Method org/lwjgl/opengl/GL40 method4410 (IIJ)V
L6:     return
L7:     
    .end code
.end method

.method public static method5722 : (IILjava/nio/ByteBuffer;)V
    .code stack 3 locals 3
L0:     iload_0
L1:     iload_1
L2:     aload_2
L3:     invokestatic Method org/lwjgl/opengl/GL40 method4375 (IILjava/nio/ByteBuffer;)V
L6:     return
L7:     
    .end code
.end method

.method private <init> : ()V
    .code stack 1 locals 1
L0:     aload_0
L1:     invokespecial Method java/lang/Object <init> ()V
L4:     return
L5:     
    .end code
.end method

.method public static method5723 : (IJ)V
    .code stack 3 locals 3
L0:     iload_0
L1:     lload_1
L2:     invokestatic Method org/lwjgl/opengl/GL40 method4373 (IJ)V
L5:     return
L6:     
    .end code
.end method
.end class
