.version 49 0
.class final super org/lwjgl/opengl/RA
.super java/lang/Object
.implements java/awt/event/FocusListener
.field final synthetic do Lorg/lwjgl/opengl/LinuxDisplay;

.method <init> : (Lorg/lwjgl/opengl/LinuxDisplay;)V
    .code stack 3 locals 2
L0:     aload_0
L1:     dup
L2:     aload_1
L3:     putfield Field org/lwjgl/opengl/RA do Lorg/lwjgl/opengl/LinuxDisplay;
L6:     invokespecial Method java/lang/Object <init> ()V
L9:     return
L10:    
    .end code
.end method

.method public focusLost : (Ljava/awt/event/FocusEvent;)V
    .code stack 5 locals 4
L0:     getstatic Field org/lwjgl/opengl/GlobalLock lock Ljava/lang/Object;
L3:     dup
L4:     astore_2
L5:     monitorenter
        .catch [0] from L6 to L31 using L33
L6:     aload_0
L7:     getfield Field org/lwjgl/opengl/RA do Lorg/lwjgl/opengl/LinuxDisplay;
L10:    iconst_0
L11:    iconst_1
L12:    dup
L13:    pop2
L14:    invokestatic Method org/lwjgl/opengl/LinuxDisplay else (Lorg/lwjgl/opengl/LinuxDisplay;Z)Z
L17:    aload_0
L18:    getfield Field org/lwjgl/opengl/RA do Lorg/lwjgl/opengl/LinuxDisplay;
L21:    iconst_1
L22:    dup
L23:    dup
L24:    pop2
L25:    invokestatic Method org/lwjgl/opengl/LinuxDisplay break (Lorg/lwjgl/opengl/LinuxDisplay;Z)Z
L28:    pop2
L29:    aload_2
L30:    monitorexit
L31:    return
L32:    athrow
        .catch [0] from L33 to L36 using L33
L33:    astore_3
L34:    aload_2
L35:    monitorexit
L36:    aload_3
L37:    athrow
L38:    athrow
L39:    
        .attribute StackMap b'\x00\x03\x00\x20\x00\x00\x00\x01\x07\x00\x22\x00\x21\x00\x03\x07\x00\x02\x07\x00\x24\x07\x00\x04\x00\x01\x07\x00\x22\x00\x26\x00\x00\x00\x01\x07\x00\x22'
    .end code
.end method

.method public focusGained : (Ljava/awt/event/FocusEvent;)V
    .code stack 5 locals 4
L0:     getstatic Field org/lwjgl/opengl/GlobalLock lock Ljava/lang/Object;
L3:     dup
L4:     astore_2
L5:     monitorenter
        .catch [0] from L6 to L31 using L33
L6:     aload_0
L7:     getfield Field org/lwjgl/opengl/RA do Lorg/lwjgl/opengl/LinuxDisplay;
L10:    iconst_1
L11:    dup
L12:    dup
L13:    pop2
L14:    invokestatic Method org/lwjgl/opengl/LinuxDisplay else (Lorg/lwjgl/opengl/LinuxDisplay;Z)Z
L17:    aload_0
L18:    getfield Field org/lwjgl/opengl/RA do Lorg/lwjgl/opengl/LinuxDisplay;
L21:    iconst_1
L22:    dup
L23:    dup
L24:    pop2
L25:    invokestatic Method org/lwjgl/opengl/LinuxDisplay break (Lorg/lwjgl/opengl/LinuxDisplay;Z)Z
L28:    pop2
L29:    aload_2
L30:    monitorexit
L31:    return
L32:    athrow
        .catch [0] from L33 to L36 using L33
L33:    astore_3
L34:    aload_2
L35:    monitorexit
L36:    aload_3
L37:    athrow
L38:    athrow
L39:    
        .attribute StackMap b'\x00\x03\x00\x20\x00\x00\x00\x01\x07\x00\x22\x00\x21\x00\x03\x07\x00\x02\x07\x00\x24\x07\x00\x04\x00\x01\x07\x00\x22\x00\x26\x00\x00\x00\x01\x07\x00\x22'
    .end code
.end method
.innerclasses
    org/lwjgl/opengl/RA [0] [0]
.end innerclasses
.enclosing method org/lwjgl/opengl/LinuxDisplay [0]
.end class
