.version 49 0
.class public final super org/lwjgl/opengl/RC
.super java/lang/Object
.field public static final field5027 I = 35381
.field public static final field5028 I = 35388
.field public static final field5029 I = 35379
.field public static final field5030 I = 35391
.field public static final field5031 I = 35386
.field public static final field5032 I = 35387
.field public static final field5033 I = 35376
.field public static final field5034 I = 35389
.field public static final field5035 I = 35383
.field public static final field5036 I = 35374
.field public static final false I = 35375
.field public static final field5037 I = 35393
.field public static final field5038 I = 35390
.field public static final true I = 35377
.field public static final field5039 I = 35396
.field public static final field5040 I = 35368
.field public static final field5041 I = 35382
.field public static final field5042 I = 35378
.field public static final field5043 I = 35397
.field public static final field5044 I = 35395
.field public static final field5045 I = 35384
.field public static final field5046 I = 35380
.field public static final field5047 I = 35372
.field public static final field5048 I = 35345
.field public static final try I = 35369
.field public static final field5049 I = 35392
.field public static final new I = 35371
.field public static final field5050 I = 35385
.field public static final this I = -1
.field public static final field5051 I = 35370
.field public static final field5052 I = 35398
.field public static final field5053 I = 35394
.field public static final field5054 I = 35373

.method public static method5333 : (IILjava/nio/IntBuffer;)V
    .code stack 3 locals 3
L0:     iload_0
L1:     iload_1
L2:     aload_2
L3:     invokestatic Method org/lwjgl/opengl/GL30 try (IILjava/nio/IntBuffer;)V
L6:     return
L7:     
    .end code
.end method

.method public static method5334 : (III)I
    .code stack 3 locals 3
L0:     iload_0
L1:     iload_1
L2:     iload_2
L3:     invokestatic Method org/lwjgl/opengl/GL31 method4239 (III)I
L6:     ireturn
L7:     
    .end code
.end method

.method public static method5335 : (III)I
    .code stack 3 locals 3
L0:     iload_0
L1:     iload_1
L2:     iload_2
L3:     invokestatic Method org/lwjgl/opengl/GL31 method4239 (III)I
L6:     ireturn
L7:     
    .end code
    .deprecated
.end method

.method public static method5336 : (IIILjava/nio/IntBuffer;)V
    .code stack 4 locals 4
L0:     iload_0
L1:     iload_1
L2:     iload_2
L3:     aload_3
L4:     invokestatic Method org/lwjgl/opengl/GL31 method4259 (IIILjava/nio/IntBuffer;)V
L7:     return
L8:     
    .end code
.end method

.method public static method5337 : (ILjava/nio/ByteBuffer;Ljava/nio/IntBuffer;)V
    .code stack 3 locals 3
L0:     iload_0
L1:     aload_1
L2:     aload_2
L3:     invokestatic Method org/lwjgl/opengl/GL31 method4242 (ILjava/nio/ByteBuffer;Ljava/nio/IntBuffer;)V
L6:     return
L7:     
    .end code
.end method

.method public static method5338 : (I[Ljava/lang/CharSequence;Ljava/nio/IntBuffer;)V
    .code stack 3 locals 3
L0:     iload_0
L1:     aload_1
L2:     aload_2
L3:     invokestatic Method org/lwjgl/opengl/GL31 method4245 (I[Ljava/lang/CharSequence;Ljava/nio/IntBuffer;)V
L6:     return
L7:     
    .end code
.end method

.method public static method5339 : (III)V
    .code stack 3 locals 3
L0:     iload_0
L1:     iload_1
L2:     iload_2
L3:     invokestatic Method org/lwjgl/opengl/GL31 method4255 (III)V
L6:     return
L7:     
    .end code
.end method

.method public static method5340 : (IILjava/nio/IntBuffer;Ljava/nio/ByteBuffer;)V
    .code stack 4 locals 4
L0:     iload_0
L1:     iload_1
L2:     aload_2
L3:     aload_3
L4:     invokestatic Method org/lwjgl/opengl/GL31 method4257 (IILjava/nio/IntBuffer;Ljava/nio/ByteBuffer;)V
L7:     return
L8:     
    .end code
.end method

.method public static method5341 : (II)I
    .code stack 2 locals 2
L0:     iload_0
L1:     iload_1
L2:     invokestatic Method org/lwjgl/opengl/GL30 method4153 (II)I
L5:     ireturn
L6:     
    .end code
.end method

.method public static method5342 : (ILjava/lang/CharSequence;)I
    .code stack 2 locals 2
L0:     iload_0
L1:     aload_1
L2:     invokestatic Method org/lwjgl/opengl/GL31 method4248 (ILjava/lang/CharSequence;)I
L5:     ireturn
L6:     
    .end code
.end method

.method private <init> : ()V
    .code stack 1 locals 1
L0:     aload_0
L1:     invokespecial Method java/lang/Object <init> ()V
L4:     return
L5:     
    .end code
.end method

.method public static method5343 : (III)I
    .code stack 3 locals 3
L0:     iload_0
L1:     iload_1
L2:     iload_2
L3:     invokestatic Method org/lwjgl/opengl/GL31 method4258 (III)I
L6:     ireturn
L7:     
    .end code
.end method

.method public static method5344 : (IILjava/nio/IntBuffer;Ljava/nio/ByteBuffer;)V
    .code stack 4 locals 4
L0:     iload_0
L1:     iload_1
L2:     aload_2
L3:     aload_3
L4:     invokestatic Method org/lwjgl/opengl/GL31 method4256 (IILjava/nio/IntBuffer;Ljava/nio/ByteBuffer;)V
L7:     return
L8:     
    .end code
.end method

.method public static method5345 : (IIIJJ)V
    .code stack 7 locals 7
L0:     iload_0
L1:     iload_1
L2:     iload_2
L3:     lload_3
L4:     lload 5
L6:     invokestatic Method org/lwjgl/opengl/GL30 method4169 (IIIJJ)V
L9:     return
L10:    
    .end code
.end method

.method public static method5346 : (ILjava/nio/IntBuffer;ILjava/nio/IntBuffer;)V
    .code stack 4 locals 4
L0:     iload_0
L1:     aload_1
L2:     iload_2
L3:     aload_3
L4:     invokestatic Method org/lwjgl/opengl/GL31 method4244 (ILjava/nio/IntBuffer;ILjava/nio/IntBuffer;)V
L7:     return
L8:     
    .end code
.end method

.method public static method5347 : (ILjava/nio/ByteBuffer;)I
    .code stack 2 locals 2
L0:     iload_0
L1:     aload_1
L2:     invokestatic Method org/lwjgl/opengl/GL31 method4261 (ILjava/nio/ByteBuffer;)I
L5:     ireturn
L6:     
    .end code
.end method

.method public static method5348 : (III)Ljava/lang/String;
    .code stack 3 locals 3
L0:     iload_0
L1:     iload_1
L2:     iload_2
L3:     invokestatic Method org/lwjgl/opengl/GL31 method4247 (III)Ljava/lang/String;
L6:     areturn
L7:     
    .end code
.end method

.method public static method5349 : (III)V
    .code stack 3 locals 3
L0:     iload_0
L1:     iload_1
L2:     iload_2
L3:     invokestatic Method org/lwjgl/opengl/GL30 method4187 (III)V
L6:     return
L7:     
    .end code
.end method

.method public static method5350 : (III)I
    .code stack 3 locals 3
L0:     iload_0
L1:     iload_1
L2:     iload_2
L3:     invokestatic Method org/lwjgl/opengl/GL31 method4258 (III)I
L6:     ireturn
L7:     
    .end code
    .deprecated
.end method

.method public static method5351 : (III)Ljava/lang/String;
    .code stack 3 locals 3
L0:     iload_0
L1:     iload_1
L2:     iload_2
L3:     invokestatic Method org/lwjgl/opengl/GL31 method4254 (III)Ljava/lang/String;
L6:     areturn
L7:     
    .end code
.end method
.end class
