.version 49 0
.class public final super org/lwjgl/opengl/VA
.super java/lang/Object
.field public static final field5101 I = 37191
.field public static final throw I = 33359
.field public static final package I = 33357
.field public static final field5102 I = 37192
.field public static final field5103 I = 33388
.field public static final while I = 37188
.field public static final field5104 I = 33355
.field public static final field5105 I = 33505
.field public static final field5106 I = 1284
.field public static final field5107 I = 33347
.field public static final field5108 I = 33348
.field public static final field5109 I = 37600
.field public static final field5110 I = 33512
.field public static final field5111 I = 33352
.field public static final field5112 I = 33506
.field public static final field5113 I = 33346
.field public static final field5114 I = 37190
.field public static final false I = 33385
.field public static final field5115 I = 33508
.field public static final field5116 I = 33510
.field public static final true I = 33387
.field public static final field5117 I = 33384
.field public static final field5118 I = 33349
.field public static final field5119 I = 33353
.field public static final field5120 I = 33360
.field public static final field5121 I = 33356
.field public static final field5122 I = 33507
.field public static final field5123 I = 33361
.field public static final field5124 I = 33389
.field public static final field5125 I = 33358
.field public static final field5126 I = 33511
.field public static final try I = 33354
.field public static final field5127 I = 33350
.field public static final new I = 37189
.field public static final field5128 I = 33386
.field public static final this I = 33504
.field public static final field5129 I = 33351
.field public static final field5130 I = 2
.field public static final field5131 I = 1283
.field public static final field5132 I = 37187

.method public static method5380 : (Lorg/lwjgl/PointerWrapper;Ljava/nio/IntBuffer;Ljava/nio/ByteBuffer;)V
    .code stack 3 locals 3
L0:     aload_0
L1:     aload_1
L2:     aload_2
L3:     invokestatic Method org/lwjgl/opengl/GL43 method4553 (Lorg/lwjgl/PointerWrapper;Ljava/nio/IntBuffer;Ljava/nio/ByteBuffer;)V
L6:     return
L7:     
    .end code
.end method

.method public static method5381 : (IILjava/nio/ByteBuffer;)V
    .code stack 3 locals 3
L0:     iload_0
L1:     iload_1
L2:     aload_2
L3:     invokestatic Method org/lwjgl/opengl/GL43 method4592 (IILjava/nio/ByteBuffer;)V
L6:     return
L7:     
    .end code
.end method

.method public static method5382 : (IIIILjava/lang/CharSequence;)V
    .code stack 5 locals 5
L0:     iload_0
L1:     iload_1
L2:     iload_2
L3:     iload_3
L4:     aload 4
L6:     invokestatic Method org/lwjgl/opengl/GL43 method4567 (IIIILjava/lang/CharSequence;)V
L9:     return
L10:    
    .end code
.end method

.method public static method5383 : (Lorg/lwjgl/PointerWrapper;I)Ljava/lang/String;
    .code stack 2 locals 2
L0:     aload_0
L1:     iload_1
L2:     invokestatic Method org/lwjgl/opengl/GL43 method4572 (Lorg/lwjgl/PointerWrapper;I)Ljava/lang/String;
L5:     areturn
L6:     
    .end code
.end method

.method public static method5384 : (Lorg/lwjgl/PointerWrapper;Ljava/nio/ByteBuffer;)V
    .code stack 2 locals 2
L0:     aload_0
L1:     aload_1
L2:     invokestatic Method org/lwjgl/opengl/GL43 method4596 (Lorg/lwjgl/PointerWrapper;Ljava/nio/ByteBuffer;)V
L5:     return
L6:     
    .end code
.end method

.method public static method5385 : (IILjava/lang/CharSequence;)V
    .code stack 3 locals 3
L0:     iload_0
L1:     iload_1
L2:     aload_2
L3:     invokestatic Method org/lwjgl/opengl/GL43 method4565 (IILjava/lang/CharSequence;)V
L6:     return
L7:     
    .end code
.end method

.method public static method5386 : (IIILjava/nio/IntBuffer;Z)V
    .code stack 5 locals 5
L0:     iload_0
L1:     iload_1
L2:     iload_2
L3:     aload_3
L4:     iload 4
L6:     invokestatic Method org/lwjgl/opengl/GL43 method4556 (IIILjava/nio/IntBuffer;Z)V
L9:     return
L10:    
    .end code
.end method

.method public static method5387 : (IILjava/nio/IntBuffer;Ljava/nio/ByteBuffer;)V
    .code stack 4 locals 4
L0:     iload_0
L1:     iload_1
L2:     aload_2
L3:     aload_3
L4:     invokestatic Method org/lwjgl/opengl/GL43 method4578 (IILjava/nio/IntBuffer;Ljava/nio/ByteBuffer;)V
L7:     return
L8:     
    .end code
.end method

.method public static method5388 : (IILjava/lang/CharSequence;)V
    .code stack 3 locals 3
L0:     iload_0
L1:     iload_1
L2:     aload_2
L3:     invokestatic Method org/lwjgl/opengl/GL43 method4548 (IILjava/lang/CharSequence;)V
L6:     return
L7:     
    .end code
.end method

.method public static method5389 : ()V
    .code stack 0 locals 0
L0:     invokestatic Method org/lwjgl/opengl/GL43 method4577 ()V
L3:     return
L4:     
    .end code
.end method

.method public static method5390 : (ILjava/nio/IntBuffer;Ljava/nio/IntBuffer;Ljava/nio/IntBuffer;Ljava/nio/IntBuffer;Ljava/nio/IntBuffer;Ljava/nio/ByteBuffer;)I
    .code stack 7 locals 7
L0:     iload_0
L1:     aload_1
L2:     aload_2
L3:     aload_3
L4:     aload 4
L6:     aload 5
L8:     aload 6
L10:    invokestatic Method org/lwjgl/opengl/GL43 method4570 (ILjava/nio/IntBuffer;Ljava/nio/IntBuffer;Ljava/nio/IntBuffer;Ljava/nio/IntBuffer;Ljava/nio/IntBuffer;Ljava/nio/ByteBuffer;)I
L13:    ireturn
L14:    
    .end code
.end method

.method public static method5391 : (III)Ljava/lang/String;
    .code stack 3 locals 3
L0:     iload_0
L1:     iload_1
L2:     iload_2
L3:     invokestatic Method org/lwjgl/opengl/GL43 method4589 (III)Ljava/lang/String;
L6:     areturn
L7:     
    .end code
.end method

.method private <init> : ()V
    .code stack 1 locals 1
L0:     aload_0
L1:     invokespecial Method java/lang/Object <init> ()V
L4:     return
L5:     
    .end code
.end method

.method public static method5392 : (Lorg/lwjgl/opengl/nA;)V
    .code stack 1 locals 1
L0:     aload_0
L1:     invokestatic Method org/lwjgl/opengl/GL43 method4558 (Lorg/lwjgl/opengl/nA;)V
L4:     return
L5:     
    .end code
.end method

.method public static method5393 : (IILjava/nio/ByteBuffer;)V
    .code stack 3 locals 3
L0:     iload_0
L1:     iload_1
L2:     aload_2
L3:     invokestatic Method org/lwjgl/opengl/GL43 method4571 (IILjava/nio/ByteBuffer;)V
L6:     return
L7:     
    .end code
.end method

.method public static method5394 : (Lorg/lwjgl/PointerWrapper;Ljava/lang/CharSequence;)V
    .code stack 2 locals 2
L0:     aload_0
L1:     aload_1
L2:     invokestatic Method org/lwjgl/opengl/GL43 method4598 (Lorg/lwjgl/PointerWrapper;Ljava/lang/CharSequence;)V
L5:     return
L6:     
    .end code
.end method

.method public static method5395 : (IIIILjava/nio/ByteBuffer;)V
    .code stack 5 locals 5
L0:     iload_0
L1:     iload_1
L2:     iload_2
L3:     iload_3
L4:     aload 4
L6:     invokestatic Method org/lwjgl/opengl/GL43 method4562 (IIIILjava/nio/ByteBuffer;)V
L9:     return
L10:    
    .end code
.end method
.end class
