.version 49 0
.class super abstract org/lwjgl/opengl/vC
.super java/lang/Object
.implements org/lwjgl/opengl/C
.field protected field527 Lorg/lwjgl/opengles/EGLDisplay;
.field protected this Lorg/lwjgl/opengl/bd;
.field protected field528 Lorg/lwjgl/opengles/EGLConfig;
.field protected field529 Lorg/lwjgl/opengl/k;
.field protected field530 Lorg/lwjgl/opengles/EGLSurface;
.field protected field531 Lorg/lwjgl/opengles/PixelFormat;

.method public method69 : ()V
    .code stack 0 locals 1
L0:     invokestatic Method org/lwjgl/opengl/bd method3621 ()V
L3:     return
L4:     
    .end code
    .exceptions org/lwjgl/LWJGLException
.end method

.method public method311 : (Lorg/lwjgl/h;)V
    .code stack 2 locals 2
L0:     new java/lang/UnsupportedOperationException
L3:     dup
L4:     invokespecial Method java/lang/UnsupportedOperationException <init> ()V
L7:     athrow
L8:     
    .end code
    .exceptions org/lwjgl/LWJGLException
.end method

.method public method310 : ()Lorg/lwjgl/opengl/h;
    .code stack 2 locals 3
L0:     getstatic Field org/lwjgl/opengl/GlobalLock lock Ljava/lang/Object;
L3:     dup
L4:     astore_1
L5:     monitorenter
        .catch [0] from L6 to L12 using L14
L6:     aload_0
L7:     getfield Field org/lwjgl/opengl/vC field531 Lorg/lwjgl/opengles/PixelFormat;
L10:    aload_1
L11:    monitorexit
L12:    areturn
L13:    pop
        .catch [0] from L14 to L17 using L14
L14:    astore_2
L15:    aload_1
L16:    monitorexit
L17:    aload_2
L18:    athrow
L19:    
    .end code
.end method

.method public method74 : ()V
    .code stack 2 locals 3
L0:     getstatic Field org/lwjgl/opengl/GlobalLock lock Ljava/lang/Object;
L3:     dup
L4:     astore_1
L5:     monitorenter
        .catch [0] from L6 to L19 using L21
L6:     aload_0
L7:     dup
L8:     invokevirtual Method org/lwjgl/opengl/vC method68 ()V
L11:    getfield Field org/lwjgl/opengl/vC this Lorg/lwjgl/opengl/bd;
L14:    invokevirtual Method org/lwjgl/opengl/bd method3617 ()V
L17:    aload_1
L18:    monitorexit
L19:    return
L20:    pop
        .catch [0] from L21 to L24 using L21
L21:    astore_2
L22:    aload_1
L23:    monitorexit
L24:    aload_2
L25:    athrow
L26:    return
L27:    
    .end code
    .exceptions org/lwjgl/LWJGLException org/lwjgl/opengles/PowerManagementEventException
.end method

.method public method71 : ()V
    .code stack 4 locals 4
L0:     getstatic Field org/lwjgl/opengl/GlobalLock lock Ljava/lang/Object;
L3:     dup
L4:     astore_1
L5:     monitorenter
L6:     aload_0
L7:     getfield Field org/lwjgl/opengl/vC this Lorg/lwjgl/opengl/bd;
L10:    ifnull L35
        .catch org/lwjgl/opengles/PowerManagementEventException from L13 to L17 using L22
        .catch org/lwjgl/LWJGLException from L6 to L83 using L88
        .catch [0] from L6 to L114 using L115
L13:    aload_0
L14:    invokevirtual Method org/lwjgl/opengl/vC method56 ()V
L17:    aload_0
L18:    goto L24
L21:    pop
L22:    astore_2
L23:    aload_0
L24:    getfield Field org/lwjgl/opengl/vC this Lorg/lwjgl/opengl/bd;
L27:    invokevirtual Method org/lwjgl/opengl/bd new ()V
L30:    aload_0
L31:    aconst_null
L32:    putfield Field org/lwjgl/opengl/vC this Lorg/lwjgl/opengl/bd;
L35:    aload_0
L36:    getfield Field org/lwjgl/opengl/vC field530 Lorg/lwjgl/opengles/EGLSurface;
L39:    ifnull L54
L42:    aconst_null
L43:    aload_0
L44:    dup_x1
L45:    getfield Field org/lwjgl/opengl/vC field530 Lorg/lwjgl/opengles/EGLSurface;
L48:    invokevirtual Method org/lwjgl/opengles/EGLSurface destroy ()V
L51:    putfield Field org/lwjgl/opengl/vC field530 Lorg/lwjgl/opengles/EGLSurface;
L54:    aload_0
L55:    getfield Field org/lwjgl/opengl/vC field527 Lorg/lwjgl/opengles/EGLDisplay;
L58:    ifnull L73
L61:    aconst_null
L62:    aload_0
L63:    dup_x1
L64:    getfield Field org/lwjgl/opengl/vC field527 Lorg/lwjgl/opengles/EGLDisplay;
L67:    invokevirtual Method org/lwjgl/opengles/EGLDisplay terminate ()V
L70:    putfield Field org/lwjgl/opengl/vC field527 Lorg/lwjgl/opengles/EGLDisplay;
L73:    aload_0
L74:    aload_0
L75:    aconst_null
L76:    dup_x1
L77:    putfield Field org/lwjgl/opengl/vC field531 Lorg/lwjgl/opengles/PixelFormat;
L80:    putfield Field org/lwjgl/opengl/vC field529 Lorg/lwjgl/opengl/k;
L83:    aload_1
L84:    goto L113
L87:    iconst_0
L88:    astore_2
L89:    new java/lang/StringBuilder
L92:    dup
L93:    invokespecial Method java/lang/StringBuilder <init> ()V
L96:    iconst_0
L97:    ldc "Exception occurred while destroying Drawable: "
L99:    invokevirtual Method java/lang/StringBuilder insert (ILjava/lang/String;)Ljava/lang/StringBuilder;
L102:   aload_2
L103:   invokevirtual Method java/lang/StringBuilder append (Ljava/lang/Object;)Ljava/lang/StringBuilder;
L106:   invokevirtual Method java/lang/StringBuilder toString ()Ljava/lang/String;
L109:   invokestatic Method org/lwjgl/LWJGLUtil log (Ljava/lang/CharSequence;)V
L112:   aload_1
L113:   monitorexit
L114:   return
        .catch [0] from L115 to L118 using L115
L115:   astore_3
L116:   aload_1
L117:   monitorexit
L118:   aload_3
L119:   athrow
L120:   return
L121:   
    .end code
.end method

.method protected method68 : ()V
    .code stack 3 locals 1
L0:     aload_0
L1:     getfield Field org/lwjgl/opengl/vC this Lorg/lwjgl/opengl/bd;
L4:     ifnonnull L17
L7:     new java/lang/IllegalStateException
L10:    dup
L11:    ldc "The Drawable has no context available."
L13:    invokespecial Method java/lang/IllegalStateException <init> (Ljava/lang/String;)V
L16:    athrow
L17:    return
L18:    
    .end code
.end method

.method public method309 : ()Lorg/lwjgl/opengl/G;
    .code stack 5 locals 3
L0:     getstatic Field org/lwjgl/opengl/GlobalLock lock Ljava/lang/Object;
L3:     dup
L4:     astore_1
L5:     monitorenter
        .catch [0] from L6 to L31 using L33
L6:     aload_0
L7:     invokevirtual Method org/lwjgl/opengl/vC method68 ()V
L10:    new org/lwjgl/opengl/bd
L13:    dup
L14:    aload_0
L15:    getfield Field org/lwjgl/opengl/vC this Lorg/lwjgl/opengl/bd;
L18:    invokevirtual Method org/lwjgl/opengl/bd method3625 ()LaA;
L21:    aload_0
L22:    dup_x1
L23:    getfield Field org/lwjgl/opengl/vC this Lorg/lwjgl/opengl/bd;
L26:    invokespecial Method org/lwjgl/opengl/bd <init> (Lorg/lwjgl/opengl/vC;LaA;Lorg/lwjgl/opengl/bd;)V
L29:    aload_1
L30:    monitorexit
L31:    areturn
L32:    pop
        .catch [0] from L33 to L36 using L33
L33:    astore_2
L34:    aload_1
L35:    monitorexit
L36:    aload_2
L37:    athrow
L38:    
    .end code
    .exceptions org/lwjgl/LWJGLException
.end method

.method public method56 : ()V
    .code stack 2 locals 3
L0:     getstatic Field org/lwjgl/opengl/GlobalLock lock Ljava/lang/Object;
L3:     dup
L4:     astore_1
L5:     monitorenter
        .catch [0] from L6 to L29 using L31
L6:     aload_0
L7:     dup
L8:     invokevirtual Method org/lwjgl/opengl/vC method68 ()V
L11:    getfield Field org/lwjgl/opengl/vC this Lorg/lwjgl/opengl/bd;
L14:    invokevirtual Method org/lwjgl/opengl/bd method3618 ()Z
L17:    ifeq L27
L20:    aload_0
L21:    getfield Field org/lwjgl/opengl/vC this Lorg/lwjgl/opengl/bd;
L24:    invokevirtual Method org/lwjgl/opengl/bd method3616 ()V
L27:    aload_1
L28:    monitorexit
L29:    return
L30:    pop
        .catch [0] from L31 to L34 using L31
L31:    astore_2
L32:    aload_1
L33:    monitorexit
L34:    aload_2
L35:    athrow
L36:    return
L37:    
    .end code
    .exceptions org/lwjgl/LWJGLException org/lwjgl/opengles/PowerManagementEventException
.end method

.method public method312 : (FFF)V
    .code stack 4 locals 4
L0:     fload_1
L1:     fload_2
L2:     fload_3
L3:     fconst_0
L4:     invokestatic Method org/lwjgl/opengles/GLES20 glClearColor (FFFF)V
L7:     sipush 16384
L10:    iconst_1
L11:    dup
L12:    pop2
L13:    invokestatic Method org/lwjgl/opengles/GLES20 glClear (I)V
L16:    return
L17:    
    .end code
.end method

.method public method76 : ()V
    .code stack 0 locals 1
L0:     invokestatic Method org/lwjgl/opengles/Util checkGLError ()V
L3:     return
L4:     
    .end code
.end method

.method public method320 : ()Lorg/lwjgl/opengles/EGLConfig;
    .code stack 2 locals 3
L0:     getstatic Field org/lwjgl/opengl/GlobalLock lock Ljava/lang/Object;
L3:     dup
L4:     astore_1
L5:     monitorenter
        .catch [0] from L6 to L12 using L14
L6:     aload_0
L7:     getfield Field org/lwjgl/opengl/vC field528 Lorg/lwjgl/opengles/EGLConfig;
L10:    aload_1
L11:    monitorexit
L12:    areturn
L13:    pop
        .catch [0] from L14 to L17 using L14
L14:    astore_2
L15:    aload_1
L16:    monitorexit
L17:    aload_2
L18:    athrow
L19:    
    .end code
.end method

.method protected <init> : ()V
    .code stack 1 locals 1
L0:     aload_0
L1:     invokespecial Method java/lang/Object <init> ()V
L4:     return
L5:     
    .end code
.end method

.method method321 : ()Lorg/lwjgl/opengl/k;
    .code stack 2 locals 3
L0:     getstatic Field org/lwjgl/opengl/GlobalLock lock Ljava/lang/Object;
L3:     dup
L4:     astore_1
L5:     monitorenter
        .catch [0] from L6 to L12 using L14
L6:     aload_0
L7:     getfield Field org/lwjgl/opengl/vC field529 Lorg/lwjgl/opengl/k;
L10:    aload_1
L11:    monitorexit
L12:    areturn
L13:    pop
        .catch [0] from L14 to L17 using L14
L14:    astore_2
L15:    aload_1
L16:    monitorexit
L17:    aload_2
L18:    athrow
L19:    
    .end code
.end method

.method public method322 : (LaA;Lorg/lwjgl/opengl/k;)V
    .code stack 6 locals 5
L0:     getstatic Field org/lwjgl/opengl/GlobalLock lock Ljava/lang/Object;
L3:     dup
L4:     astore_3
L5:     monitorenter
        .catch [0] from L6 to L42 using L44
L6:     aload_0
L7:     new org/lwjgl/opengl/bd
L10:    dup
L11:    aload_0
L12:    aload_1
L13:    aload_2
L14:    ifnull L28
L17:    aload_2
L18:    checkcast org/lwjgl/opengl/vC
L21:    invokevirtual Method org/lwjgl/opengl/vC try ()Lorg/lwjgl/opengl/bd;
L24:    goto L29
L27:    pop
L28:    aconst_null
L29:    invokespecial Method org/lwjgl/opengl/bd <init> (Lorg/lwjgl/opengl/vC;LaA;Lorg/lwjgl/opengl/bd;)V
L32:    putfield Field org/lwjgl/opengl/vC this Lorg/lwjgl/opengl/bd;
L35:    aload_3
L36:    aload_0
L37:    aload_2
L38:    putfield Field org/lwjgl/opengl/vC field529 Lorg/lwjgl/opengl/k;
L41:    monitorexit
L42:    return
L43:    iconst_0
        .catch [0] from L44 to L48 using L44
L44:    astore 4
L46:    aload_3
L47:    monitorexit
L48:    aload 4
L50:    athrow
L51:    return
L52:    
    .end code
    .exceptions org/lwjgl/LWJGLException
.end method

.method public method308 : (Lorg/lwjgl/opengl/h;)V
    .code stack 2 locals 4
L0:     getstatic Field org/lwjgl/opengl/GlobalLock lock Ljava/lang/Object;
L3:     dup
L4:     astore_2
L5:     monitorenter
        .catch [0] from L6 to L16 using L18
L6:     aload_0
L7:     aload_1
L8:     checkcast org/lwjgl/opengles/PixelFormat
L11:    putfield Field org/lwjgl/opengl/vC field531 Lorg/lwjgl/opengles/PixelFormat;
L14:    aload_2
L15:    monitorexit
L16:    return
L17:    pop
        .catch [0] from L18 to L21 using L18
L18:    astore_3
L19:    aload_2
L20:    monitorexit
L21:    aload_3
L22:    athrow
L23:    return
L24:    
    .end code
    .exceptions org/lwjgl/LWJGLException
.end method

.method public bridge synthetic method307 : ()Lorg/lwjgl/opengl/G;
    .code stack 1 locals 1
L0:     aload_0
L1:     invokevirtual Method org/lwjgl/opengl/vC try ()Lorg/lwjgl/opengl/bd;
L4:     areturn
L5:     
    .end code
.end method

.method public new : ()Lorg/lwjgl/opengles/EGLSurface;
    .code stack 2 locals 3
L0:     getstatic Field org/lwjgl/opengl/GlobalLock lock Ljava/lang/Object;
L3:     dup
L4:     astore_1
L5:     monitorenter
        .catch [0] from L6 to L12 using L14
L6:     aload_0
L7:     getfield Field org/lwjgl/opengl/vC field530 Lorg/lwjgl/opengles/EGLSurface;
L10:    aload_1
L11:    monitorexit
L12:    areturn
L13:    pop
        .catch [0] from L14 to L17 using L14
L14:    astore_2
L15:    aload_1
L16:    monitorexit
L17:    aload_2
L18:    athrow
L19:    
    .end code
.end method

.method public try : ()Lorg/lwjgl/opengl/bd;
    .code stack 2 locals 3
L0:     getstatic Field org/lwjgl/opengl/GlobalLock lock Ljava/lang/Object;
L3:     dup
L4:     astore_1
L5:     monitorenter
        .catch [0] from L6 to L12 using L14
L6:     aload_0
L7:     getfield Field org/lwjgl/opengl/vC this Lorg/lwjgl/opengl/bd;
L10:    aload_1
L11:    monitorexit
L12:    areturn
L13:    pop
        .catch [0] from L14 to L17 using L14
L14:    astore_2
L15:    aload_1
L16:    monitorexit
L17:    aload_2
L18:    athrow
L19:    
    .end code
.end method

.method public method14 : (I)V
    .code stack 1 locals 2
L0:     iload_1
L1:     invokestatic Method org/lwjgl/opengl/bd method3623 (I)V
L4:     return
L5:     
    .end code
.end method

.method public method263 : ()Z
    .code stack 2 locals 3
L0:     getstatic Field org/lwjgl/opengl/GlobalLock lock Ljava/lang/Object;
L3:     dup
L4:     astore_1
L5:     monitorenter
        .catch [0] from L6 to L19 using L21
L6:     aload_0
L7:     dup
L8:     invokevirtual Method org/lwjgl/opengl/vC method68 ()V
L11:    getfield Field org/lwjgl/opengl/vC this Lorg/lwjgl/opengl/bd;
L14:    invokevirtual Method org/lwjgl/opengl/bd method3618 ()Z
L17:    aload_1
L18:    monitorexit
L19:    ireturn
L20:    pop
        .catch [0] from L21 to L24 using L21
L21:    astore_2
L22:    aload_1
L23:    monitorexit
L24:    aload_2
L25:    athrow
L26:    
    .end code
    .exceptions org/lwjgl/LWJGLException
.end method

.method public this : ()Lorg/lwjgl/opengles/EGLDisplay;
    .code stack 2 locals 3
L0:     getstatic Field org/lwjgl/opengl/GlobalLock lock Ljava/lang/Object;
L3:     dup
L4:     astore_1
L5:     monitorenter
        .catch [0] from L6 to L12 using L14
L6:     aload_0
L7:     getfield Field org/lwjgl/opengl/vC field527 Lorg/lwjgl/opengles/EGLDisplay;
L10:    aload_1
L11:    monitorexit
L12:    areturn
L13:    pop
        .catch [0] from L14 to L17 using L14
L14:    astore_2
L15:    aload_1
L16:    monitorexit
L17:    aload_2
L18:    athrow
L19:    
    .end code
.end method

.method public method323 : (JJILorg/lwjgl/opengles/PixelFormat;)V
    .code stack 7 locals 9
L0:     getstatic Field org/lwjgl/opengl/GlobalLock lock Ljava/lang/Object;
L3:     dup
L4:     astore 7
L6:     monitorenter
        .catch [0] from L7 to L231 using L233
L7:     aload_0
L8:     getfield Field org/lwjgl/opengl/vC field530 Lorg/lwjgl/opengles/EGLSurface;
L11:    ifnull L26
L14:    aconst_null
L15:    aload_0
L16:    dup_x1
L17:    getfield Field org/lwjgl/opengl/vC field530 Lorg/lwjgl/opengles/EGLSurface;
L20:    invokevirtual Method org/lwjgl/opengles/EGLSurface destroy ()V
L23:    putfield Field org/lwjgl/opengl/vC field530 Lorg/lwjgl/opengles/EGLSurface;
L26:    aload_0
L27:    getfield Field org/lwjgl/opengl/vC field527 Lorg/lwjgl/opengles/EGLDisplay;
L30:    ifnull L45
L33:    aconst_null
L34:    aload_0
L35:    dup_x1
L36:    getfield Field org/lwjgl/opengl/vC field527 Lorg/lwjgl/opengles/EGLDisplay;
L39:    invokevirtual Method org/lwjgl/opengles/EGLDisplay terminate ()V
L42:    putfield Field org/lwjgl/opengl/vC field527 Lorg/lwjgl/opengles/EGLDisplay;
L45:    lload_3
L46:    l2i
L47:    i2l
L48:    invokestatic Method org/lwjgl/opengles/EGL eglGetDisplay (J)Lorg/lwjgl/opengles/EGLDisplay;
L51:    astore_3
L52:    bipush 6
L54:    iconst_1
L55:    dup
L56:    pop2
L57:    newarray int
L59:    iconst_1
L60:    dup
L61:    pop2
L62:    dup
L63:    iconst_0
L64:    iconst_1
L65:    dup
L66:    pop2
L67:    sipush 12329
L70:    iconst_1
L71:    dup
L72:    pop2
L73:    iastore
L74:    dup
L75:    iconst_1
L76:    dup
L77:    pop2
L78:    iconst_0
L79:    iconst_1
L80:    dup_x1
L81:    dup
L82:    pop2
L83:    iastore
L84:    dup
L85:    iconst_2
L86:    iconst_1
L87:    dup
L88:    pop2
L89:    sipush 12352
L92:    iconst_1
L93:    dup
L94:    pop2
L95:    iastore
L96:    dup
L97:    iconst_3
L98:    iconst_1
L99:    dup
L100:   pop2
L101:   iconst_4
L102:   iconst_1
L103:   dup
L104:   pop2
L105:   iastore
L106:   dup
L107:   iconst_4
L108:   iconst_1
L109:   dup
L110:   pop2
L111:   sipush 12333
L114:   iconst_1
L115:   dup
L116:   pop2
L117:   iastore
L118:   dup
L119:   iconst_5
L120:   iconst_1
L121:   dup
L122:   pop2
L123:   iconst_0
L124:   iconst_1
L125:   dup
L126:   pop2
L127:   iastore
L128:   astore 4
L130:   aload 6
L132:   aload_3
L133:   dup_x1
L134:   iload 5
L136:   aload 4
L138:   invokevirtual Method org/lwjgl/opengles/PixelFormat getAttribBuffer (Lorg/lwjgl/opengles/EGLDisplay;I[I)Ljava/nio/IntBuffer;
L141:   aconst_null
L142:   iconst_1
L143:   dup
L144:   dup
L145:   pop2
L146:   invokestatic Method org/lwjgl/BufferUtils createIntBuffer (I)Ljava/nio/IntBuffer;
L149:   invokevirtual Method org/lwjgl/opengles/EGLDisplay chooseConfig (Ljava/nio/IntBuffer;[Lorg/lwjgl/opengles/EGLConfig;Ljava/nio/IntBuffer;)[Lorg/lwjgl/opengles/EGLConfig;
L152:   dup
L153:   astore 5
L155:   arraylength
L156:   ifne L169
L159:   new org/lwjgl/LWJGLException
L162:   dup
L163:   ldc "No EGLConfigs found for the specified PixelFormat."
L165:   invokespecial Method org/lwjgl/LWJGLException <init> (Ljava/lang/String;)V
L168:   athrow
L169:   aload 6
L171:   dup
L172:   aload 5
L174:   invokevirtual Method org/lwjgl/opengles/PixelFormat getBestMatch ([Lorg/lwjgl/opengles/EGLConfig;)Lorg/lwjgl/opengles/EGLConfig;
L177:   astore 5
L179:   aload_3
L180:   aload 5
L182:   lload_1
L183:   aconst_null
L184:   invokevirtual Method org/lwjgl/opengles/EGLDisplay createWindowSurface (Lorg/lwjgl/opengles/EGLConfig;JLjava/nio/IntBuffer;)Lorg/lwjgl/opengles/EGLSurface;
L187:   dup
L188:   astore 6
L190:   invokevirtual Method org/lwjgl/opengles/PixelFormat setSurfaceAttribs (Lorg/lwjgl/opengles/EGLSurface;)V
L193:   aload 6
L195:   aload_0
L196:   dup_x1
L197:   dup_x2
L198:   aload 5
L200:   aload_0
L201:   aload_3
L202:   putfield Field org/lwjgl/opengl/vC field527 Lorg/lwjgl/opengles/EGLDisplay;
L205:   putfield Field org/lwjgl/opengl/vC field528 Lorg/lwjgl/opengles/EGLConfig;
L208:   putfield Field org/lwjgl/opengl/vC field530 Lorg/lwjgl/opengles/EGLSurface;
L211:   getfield Field org/lwjgl/opengl/vC this Lorg/lwjgl/opengl/bd;
L214:   ifnull L228
L217:   aload_0
L218:   getfield Field org/lwjgl/opengl/vC this Lorg/lwjgl/opengl/bd;
L221:   invokevirtual Method org/lwjgl/opengl/bd this ()Lorg/lwjgl/opengles/EGLContext;
L224:   aload_3
L225:   invokevirtual Method org/lwjgl/opengles/EGLContext setDisplay (Lorg/lwjgl/opengles/EGLDisplay;)V
L228:   aload 7
L230:   monitorexit
L231:   return
L232:   pop
        .catch [0] from L233 to L238 using L233
L233:   astore 8
L235:   aload 7
L237:   monitorexit
L238:   aload 8
L240:   athrow
L241:   return
L242:   
    .end code
    .exceptions org/lwjgl/LWJGLException
.end method
.end class
