.version 49 0
.class public final super org/lwjgl/opengl/yb
.super java/lang/Object
.field public static final g I = 36075
.field public static final k I = 36181
.field public static final a I = 1286
.field public static final F I = 35863
.field public static final A I = 36050
.field public static final E I = 36064
.field public static final C I = 36073
.field public static final K I = 36011
.field public static final G I = 36074
.field public static final B I = 36053
.field public static final c I = 36065
.field public static final field5717 I = 36059
.field public static final i I = 36066
.field public static final m I = 35904
.field public static final h I = 34041
.field public static final J I = 33306
.field public static final l I = 36071
.field public static final D I = 36063
.field public static final f I = 36183
.field public static final j I = 36177
.field public static final I I = 36162
.field public static final b I = 33303
.field public static final field5718 I = 36168
.field public static final return I = 34024
.field public static final field5719 I = 36052
.field public static final switch I = 36078
.field public static final field5720 I = 35057
.field public static final field5721 I = 36180
.field public static final field5722 I = 33305
.field public static final field5723 I = 36007
.field public static final field5724 I = 33297
.field public static final field5725 I = 36006
.field public static final field5726 I = 36010
.field public static final field5727 I = 36178
.field public static final field5728 I = 36008
.field public static final throw I = 33301
.field public static final package I = 36076
.field public static final field5729 I = 35056
.field public static final field5730 I = 36054
.field public static final while I = 36006
.field public static final field5731 I = 36069
.field public static final field5732 I = 36049
.field public static final field5733 I = 33299
.field public static final field5734 I = 33296
.field public static final field5735 I = 36160
.field public static final field5736 I = 36051
.field public static final field5737 I = 36166
.field public static final field5738 I = 36070
.field public static final field5739 I = 36163
.field public static final field5740 I = 36079
.field public static final field5741 I = 36068
.field public static final false I = 36061
.field public static final field5742 I = 36164
.field public static final field5743 I = 36176
.field public static final true I = 36167
.field public static final field5744 I = 33298
.field public static final field5745 I = 33302
.field public static final field5746 I = 36128
.field public static final field5747 I = 36096
.field public static final field5748 I = 36067
.field public static final field5749 I = 36009
.field public static final field5750 I = 36048
.field public static final field5751 I = 36072
.field public static final field5752 I = 36169
.field public static final field5753 I = 33314
.field public static final try I = 36161
.field public static final field5754 I = 36179
.field public static final new I = 36182
.field public static final field5755 I = 33300
.field public static final this I = 33304
.field public static final field5756 I = 36060
.field public static final field5757 I = 36055
.field public static final field5758 I = 34042
.field public static final field5759 I = 36077

.method public static method5777 : (I)I
    .code stack 1 locals 1
L0:     iload_0
L1:     invokestatic Method org/lwjgl/opengl/GL30 method4160 (I)I
L4:     ireturn
L5:     
    .end code
.end method

.method public static method5778 : (Ljava/nio/IntBuffer;)V
    .code stack 1 locals 1
L0:     aload_0
L1:     invokestatic Method org/lwjgl/opengl/GL30 method4189 (Ljava/nio/IntBuffer;)V
L4:     return
L5:     
    .end code
.end method

.method public static method5779 : (II)V
    .code stack 2 locals 2
L0:     iload_0
L1:     iload_1
L2:     invokestatic Method org/lwjgl/opengl/GL30 method4229 (II)V
L5:     return
L6:     
    .end code
.end method

.method public static method5780 : (IILjava/nio/IntBuffer;)V
    .code stack 3 locals 3
L0:     iload_0
L1:     iload_1
L2:     aload_2
L3:     invokestatic Method org/lwjgl/opengl/GL30 method4170 (IILjava/nio/IntBuffer;)V
L6:     return
L7:     
    .end code
.end method

.method public static method5781 : (Ljava/nio/IntBuffer;)V
    .code stack 1 locals 1
L0:     aload_0
L1:     invokestatic Method org/lwjgl/opengl/GL30 method4183 (Ljava/nio/IntBuffer;)V
L4:     return
L5:     
    .end code
.end method

.method public static method5782 : (Ljava/nio/IntBuffer;)V
    .code stack 1 locals 1
L0:     aload_0
L1:     invokestatic Method org/lwjgl/opengl/GL30 method4238 (Ljava/nio/IntBuffer;)V
L4:     return
L5:     
    .end code
.end method

.method public static method5783 : (I)V
    .code stack 1 locals 1
L0:     iload_0
L1:     invokestatic Method org/lwjgl/opengl/GL30 method4217 (I)V
L4:     return
L5:     
    .end code
.end method

.method public static method5784 : (III)I
    .code stack 3 locals 3
L0:     iload_0
L1:     iload_1
L2:     iload_2
L3:     invokestatic Method org/lwjgl/opengl/GL30 method4185 (III)I
L6:     ireturn
L7:     
    .end code
    .deprecated
.end method

.method public static method5785 : (IIII)V
    .code stack 4 locals 4
L0:     iload_0
L1:     iload_1
L2:     iload_2
L3:     iload_3
L4:     invokestatic Method org/lwjgl/opengl/GL30 method4210 (IIII)V
L7:     return
L8:     
    .end code
.end method

.method public static method5786 : (IIIIIIIIII)V
    .code stack 10 locals 10
L0:     iload_0
L1:     iload_1
L2:     iload_2
L3:     iload_3
L4:     iload 4
L6:     iload 5
L8:     iload 6
L10:    iload 7
L12:    iload 8
L14:    iload 9
L16:    invokestatic Method org/lwjgl/opengl/GL30 method4145 (IIIIIIIIII)V
L19:    return
L20:    
    .end code
.end method

.method public static method5787 : (IIIIII)V
    .code stack 6 locals 6
L0:     iload_0
L1:     iload_1
L2:     iload_2
L3:     iload_3
L4:     iload 4
L6:     iload 5
L8:     invokestatic Method org/lwjgl/opengl/GL30 method4171 (IIIIII)V
L11:    return
L12:    
    .end code
.end method

.method public static method5788 : (IIIII)V
    .code stack 5 locals 5
L0:     iload_0
L1:     iload_1
L2:     iload_2
L3:     iload_3
L4:     iload 4
L6:     invokestatic Method org/lwjgl/opengl/GL30 method4146 (IIIII)V
L9:     return
L10:    
    .end code
.end method

.method public static method5789 : (II)I
    .code stack 2 locals 2
L0:     iload_0
L1:     iload_1
L2:     invokestatic Method org/lwjgl/opengl/GL30 method4208 (II)I
L5:     ireturn
L6:     
    .end code
.end method

.method public static method5790 : (I)V
    .code stack 1 locals 1
L0:     iload_0
L1:     invokestatic Method org/lwjgl/opengl/GL30 method4173 (I)V
L4:     return
L5:     
    .end code
.end method

.method public static method5791 : (Ljava/nio/IntBuffer;)V
    .code stack 1 locals 1
L0:     aload_0
L1:     invokestatic Method org/lwjgl/opengl/GL30 method4225 (Ljava/nio/IntBuffer;)V
L4:     return
L5:     
    .end code
.end method

.method public static method5792 : (IIIII)V
    .code stack 5 locals 5
L0:     iload_0
L1:     iload_1
L2:     iload_2
L3:     iload_3
L4:     iload 4
L6:     invokestatic Method org/lwjgl/opengl/GL30 method4231 (IIIII)V
L9:     return
L10:    
    .end code
.end method

.method public static method5793 : (I)Z
    .code stack 1 locals 1
L0:     iload_0
L1:     invokestatic Method org/lwjgl/opengl/GL30 method4198 (I)Z
L4:     ireturn
L5:     
    .end code
.end method

.method public static method5794 : (IIIII)V
    .code stack 5 locals 5
L0:     iload_0
L1:     iload_1
L2:     iload_2
L3:     iload_3
L4:     iload 4
L6:     invokestatic Method org/lwjgl/opengl/GL30 method4142 (IIIII)V
L9:     return
L10:    
    .end code
.end method

.method public static method5795 : (IIIII)V
    .code stack 5 locals 5
L0:     iload_0
L1:     iload_1
L2:     iload_2
L3:     iload_3
L4:     iload 4
L6:     invokestatic Method org/lwjgl/opengl/GL30 method4167 (IIIII)V
L9:     return
L10:    
    .end code
.end method

.method public static method5796 : ()I
    .code stack 1 locals 0
L0:     invokestatic Method org/lwjgl/opengl/GL30 method4179 ()I
L3:     ireturn
L4:     
    .end code
.end method

.method public static method5797 : (I)Z
    .code stack 1 locals 1
L0:     iload_0
L1:     invokestatic Method org/lwjgl/opengl/GL30 this (I)Z
L4:     ireturn
L5:     
    .end code
.end method

.method public static method5798 : (IIII)V
    .code stack 4 locals 4
L0:     iload_0
L1:     iload_1
L2:     iload_2
L3:     iload_3
L4:     invokestatic Method org/lwjgl/opengl/GL30 method4182 (IIII)V
L7:     return
L8:     
    .end code
.end method

.method public static method5799 : (IIILjava/nio/IntBuffer;)V
    .code stack 4 locals 4
L0:     iload_0
L1:     iload_1
L2:     iload_2
L3:     aload_3
L4:     invokestatic Method org/lwjgl/opengl/GL30 method4205 (IIILjava/nio/IntBuffer;)V
L7:     return
L8:     
    .end code
.end method

.method private <init> : ()V
    .code stack 1 locals 1
L0:     aload_0
L1:     invokespecial Method java/lang/Object <init> ()V
L4:     return
L5:     
    .end code
.end method

.method public static method5800 : (II)V
    .code stack 2 locals 2
L0:     iload_0
L1:     iload_1
L2:     invokestatic Method org/lwjgl/opengl/GL30 method4209 (II)V
L5:     return
L6:     
    .end code
.end method

.method public static method5801 : (II)I
    .code stack 2 locals 2
L0:     iload_0
L1:     iload_1
L2:     invokestatic Method org/lwjgl/opengl/yb method5789 (II)I
L5:     ireturn
L6:     
    .end code
    .deprecated
.end method

.method public static method5802 : (I)V
    .code stack 1 locals 1
L0:     iload_0
L1:     invokestatic Method org/lwjgl/opengl/GL30 method4220 (I)V
L4:     return
L5:     
    .end code
.end method

.method public static method5803 : ()I
    .code stack 1 locals 0
L0:     invokestatic Method org/lwjgl/opengl/GL30 method4194 ()I
L3:     ireturn
L4:     
    .end code
.end method

.method public static method5804 : (III)I
    .code stack 3 locals 3
L0:     iload_0
L1:     iload_1
L2:     iload_2
L3:     invokestatic Method org/lwjgl/opengl/GL30 method4185 (III)I
L6:     ireturn
L7:     
    .end code
.end method
.end class
