.version 49 0
.class public final super org/lwjgl/opengl/zC
.super java/lang/Object
.field public static final this I = 35065
.field public static final field5763 I = 35066
.field public static final field5764 I = 34185
.field public static final field5765 I = 35067
.field public static final field5766 I = 35068

.method public static method5807 : (ILjava/lang/CharSequence;)I
    .code stack 2 locals 2
L0:     iload_0
L1:     aload_1
L2:     invokestatic Method org/lwjgl/opengl/GL33 method4327 (ILjava/lang/CharSequence;)I
L5:     ireturn
L6:     
    .end code
.end method

.method public static method5808 : (IIILjava/nio/ByteBuffer;)V
    .code stack 4 locals 4
L0:     iload_0
L1:     iload_1
L2:     iload_2
L3:     aload_3
L4:     invokestatic Method org/lwjgl/opengl/GL33 method4317 (IIILjava/nio/ByteBuffer;)V
L7:     return
L8:     
    .end code
.end method

.method public static method5809 : (ILjava/nio/ByteBuffer;)I
    .code stack 2 locals 2
L0:     iload_0
L1:     aload_1
L2:     invokestatic Method org/lwjgl/opengl/GL33 method4310 (ILjava/nio/ByteBuffer;)I
L5:     ireturn
L6:     
    .end code
.end method

.method private <init> : ()V
    .code stack 1 locals 1
L0:     aload_0
L1:     invokespecial Method java/lang/Object <init> ()V
L4:     return
L5:     
    .end code
.end method

.method public static method5810 : (IIILjava/lang/CharSequence;)V
    .code stack 4 locals 4
L0:     iload_0
L1:     iload_1
L2:     iload_2
L3:     aload_3
L4:     invokestatic Method org/lwjgl/opengl/GL33 method4297 (IIILjava/lang/CharSequence;)V
L7:     return
L8:     
    .end code
.end method
.end class
