.version 49 0
.class final super net/gewaltig/cultris/C
.super java/awt/Label
.field final synthetic field575 Lnet/gewaltig/cultris/Applet;
.field final synthetic field576 Ljava/net/URL;
.field private static final field577 J = 1L
.field final synthetic field578 I

.method public paint : (Ljava/awt/Graphics;)V
    .code stack 8 locals 5
L0:     aload_0
L1:     dup
L2:     aload_1
L3:     invokespecial Method java/awt/Label paint (Ljava/awt/Graphics;)V
L6:     getfield Field net/gewaltig/cultris/C field576 Ljava/net/URL;
L9:     ifnull L92
L12:    aload_1
L13:    dup
L14:    invokevirtual Method java/awt/Graphics getClipBounds ()Ljava/awt/Rectangle;
L17:    astore_2
L18:    aload_0
L19:    dup
L20:    invokevirtual Method net/gewaltig/cultris/C getFont ()Ljava/awt/Font;
L23:    invokevirtual Method net/gewaltig/cultris/C getFontMetrics (Ljava/awt/Font;)Ljava/awt/FontMetrics;
L26:    dup
L27:    astore_3
L28:    aload_0
L29:    dup_x1
L30:    invokevirtual Method net/gewaltig/cultris/C getText ()Ljava/lang/String;
L33:    invokevirtual Method java/awt/FontMetrics stringWidth (Ljava/lang/String;)I
L36:    istore 4
L38:    getfield Field net/gewaltig/cultris/C field578 I
L41:    iload 4
L43:    isub
L44:    iconst_2
L45:    iconst_1
L46:    dup
L47:    pop2
L48:    idiv
L49:    aload_2
L50:    getfield Field java/awt/Rectangle height I
L53:    aload_3
L54:    invokevirtual Method java/awt/FontMetrics getDescent ()I
L57:    isub
L58:    iconst_3
L59:    iconst_1
L60:    dup
L61:    pop2
L62:    isub
L63:    aload_0
L64:    getfield Field net/gewaltig/cultris/C field578 I
L67:    iload 4
L69:    iadd
L70:    iconst_2
L71:    iconst_1
L72:    dup
L73:    pop2
L74:    idiv
L75:    aload_2
L76:    getfield Field java/awt/Rectangle height I
L79:    aload_3
L80:    invokevirtual Method java/awt/FontMetrics getDescent ()I
L83:    isub
L84:    iconst_3
L85:    iconst_1
L86:    dup
L87:    pop2
L88:    isub
L89:    invokevirtual Method java/awt/Graphics drawLine (IIII)V
L92:    return
L93:    
        .attribute StackMap b'\x00\x01\x00\x5C\x00\x02\x07\x00\x02\x07\x00\x1B\x00\x00'
    .end code
.end method

.method <init> : (Lnet/gewaltig/cultris/Applet;Ljava/lang/String;ILjava/net/URL;I)V
    .code stack 9 locals 6
L0:     aload_2
L1:     iload_3
L2:     aload_0
L3:     dup_x2
L4:     iload 5
L6:     aload 4
L8:     aload_0
L9:     dup_x1
L10:    aload_1
L11:    putfield Field net/gewaltig/cultris/C field575 Lnet/gewaltig/cultris/Applet;
L14:    putfield Field net/gewaltig/cultris/C field576 Ljava/net/URL;
L17:    putfield Field net/gewaltig/cultris/C field578 I
L20:    invokespecial Method java/awt/Label <init> (Ljava/lang/String;I)V
L23:    return
L24:    
    .end code
.end method
.innerclasses
    net/gewaltig/cultris/C [0] [0]
.end innerclasses
.enclosing method net/gewaltig/cultris/Applet init ()V
.end class
