.version 49 0
.class public final super org/lwjgl/input/Keyboard
.super java/lang/Object
.field public static final KEY_O I = 24
.field public static final KEY_YEN I = 125
.field public static final KEY_SCROLL I = 70
.field public static final KEY_F10 I = 68
.field private static field2567 Z
.field public static final KEY_KANA I = 112
.field public static final KEY_NUMPAD1 I = 79
.field public static final KEY_F1 I = 59
.field public static final KEY_F6 I = 64
.field public static final KEY_0 I = 11
.field public static final KEY_SLASH I = 53
.field public static final KEY_F13 I = 100
.field public static final KEY_U I = 22
.field public static final KEY_NONE I = 0
.field public static final KEY_RCONTROL I = 157
.field public static final KEY_RSHIFT I = 54
.field public static final KEY_NOCONVERT I = 123
.field public static final KEY_NUMPAD6 I = 77
.field public static final KEY_DELETE I = 211
.field public static final KEY_STOP I = 149
.field public static final KEY_CIRCUMFLEX I = 144
.field public static final KEY_M I = 50
.field public static final KEYBOARD_SIZE I = 256
.field public static final KEY_W I = 17
.field public static final KEY_F4 I = 62
.field public static final KEY_LEFT I = 203
.field public static final KEY_UNDERLINE I = 147
.field private static field2568 I
.field public static final KEY_BACK I = 14
.field public static final KEY_RMETA I = 220
.field public static final KEY_1 I = 2
.field private static field2569 Lorg/lwjgl/opengl/i;
.field public static final KEY_LCONTROL I = 29
.field public static final KEY_HOME I = 199
.field public static final KEY_NUMPADENTER I = 156
.field public static final KEY_ADD I = 78
.field public static final EVENT_SIZE I = 18
.field public static final KEY_NUMPAD3 I = 81
.field public static final KEY_5 I = 6
.field public static final KEY_EQUALS I = 13
.field private static field2570 Lorg/lwjgl/input/C;
.field public static final KEY_COLON I = 146
.field public static final KEY_NUMPAD0 I = 82
.field public static final KEY_S I = 31
.field public static final KEY_3 I = 4
.field public static final KEY_AT I = 145
.field public static final KEY_TAB I = 15
.field public static final KEY_LBRACKET I = 26
.field public static final KEY_N I = 49
.field public static final KEY_F8 I = 66
.field public static final KEY_Z I = 44
.field public static final KEY_RBRACKET I = 27
.field public static final KEY_4 I = 5
.field private static final try [Ljava/lang/String;
.field public static final KEY_PRIOR I = 201
.field public static final KEY_D I = 32
.field public static final KEY_UP I = 200
.field public static final KEY_I I = 23
.field public static final KEY_NUMPAD5 I = 76
.field public static final KEY_SEMICOLON I = 39
.field public static final CHAR_NONE I = 0
.field public static final KEY_K I = 37
.field public static final KEY_F11 I = 87
.field private static final field2571 I
.field public static final KEY_9 I = 10
.field public static final KEY_NUMPAD4 I = 75
.field public static final KEY_Q I = 16
.field private static final new Ljava/nio/ByteBuffer;
.field public static final KEY_KANJI I = 148
.field public static final KEY_INSERT I = 210
.field public static final KEY_RMENU I = 184
.field public static final KEY_AX I = 150
.field public static final KEY_DIVIDE I = 181
.field public static final KEY_B I = 48
.field public static final KEY_C I = 46
.field private static field2572 Z
.field public static final KEY_6 I = 7
.field public static final KEY_RETURN I = 28
.field public static final KEY_F5 I = 63
.field public static final KEY_SYSRQ I = 183
.field private static final this Ljava/util/Map;
.field private static final field2573 I = 50
.field public static final KEY_MINUS I = 12
.field public static final KEY_H I = 35
.field public static final KEY_F9 I = 67
.field public static final KEY_MULTIPLY I = 55
.field public static final KEY_CONVERT I = 121
.field public static final KEY_X I = 45
.field public static final KEY_LMENU I = 56
.field public static final KEY_DOWN I = 208
.field public static final KEY_END I = 207
.field public static final KEY_BACKSLASH I = 43
.field public static final KEY_NUMPADCOMMA I = 179
.field public static final KEY_F14 I = 101
.field public static final KEY_F2 I = 60
.field public static final KEY_RIGHT I = 205
.field public static final KEY_SPACE I = 57
.field public static final KEY_APPS I = 221
.field public static final KEY_7 I = 8
.field public static final KEY_NEXT I = 209
.field public static final KEY_T I = 20
.field public static final KEY_NUMPAD8 I = 72
.field public static final KEY_F7 I = 65
.field public static final KEY_LMETA I = 219
.field public static final KEY_PAUSE I = 197
.field public static final KEY_NUMPADEQUALS I = 141
.field public static final KEY_COMMA I = 51
.field public static final KEY_NUMPAD9 I = 73
.field public static final KEY_RWIN I = 220 .fieldattributes
    .deprecated
.end fieldattributes
.field public static final KEY_L I = 38
.field public static final KEY_Y I = 21
.field public static final KEY_GRAVE I = 41
.field private static field2574 Z
.field public static final KEY_SUBTRACT I = 74
.field public static final KEY_V I = 47
.field public static final KEY_2 I = 3
.field public static final KEY_ESCAPE I = 1
.field public static final KEY_G I = 34
.field public static final KEY_NUMPAD7 I = 71
.field public static final KEY_F3 I = 61
.field private static field2575 Ljava/nio/ByteBuffer;
.field public static final KEY_R I = 19
.field public static final KEY_E I = 18
.field public static final KEY_LSHIFT I = 42
.field public static final KEY_F15 I = 102
.field public static final KEY_J I = 36
.field public static final KEY_POWER I = 222
.field public static final KEY_NUMLOCK I = 69
.field public static final KEY_APOSTROPHE I = 40
.field public static final KEY_DECIMAL I = 83
.field public static final KEY_SLEEP I = 223
.field public static final KEY_F I = 33
.field public static final KEY_LWIN I = 219 .fieldattributes
    .deprecated
.end fieldattributes
.field public static final KEY_CAPITAL I = 58
.field private static field2576 Lorg/lwjgl/input/C;
.field public static final KEY_A I = 30
.field public static final KEY_8 I = 9
.field public static final KEY_P I = 25
.field public static final KEY_UNLABELED I = 151
.field public static final KEY_F12 I = 88
.field public static final KEY_PERIOD I = 52
.field public static final KEY_NUMPAD2 I = 80

.method public static method1940 : ()Z
    .code stack 2 locals 2
L0:     getstatic Field org/lwjgl/input/D field2554 Ljava/lang/Object;
L3:     dup
L4:     astore_0
L5:     monitorenter
        .catch [0] from L6 to L14 using L16
L6:     getstatic Field org/lwjgl/input/Keyboard field2570 Lorg/lwjgl/input/C;
L9:     invokestatic Method org/lwjgl/input/C method1910 (Lorg/lwjgl/input/C;)Z
L12:    aload_0
L13:    monitorexit
L14:    ireturn
L15:    athrow
        .catch [0] from L16 to L19 using L16
L16:    astore_1
L17:    aload_0
L18:    monitorexit
L19:    aload_1
L20:    athrow
L21:    
        .attribute StackMap b'\x00\x02\x00\x0F\x00\x00\x00\x01\x07\x01\x2A\x00\x10\x00\x01\x07\x00\x04\x00\x01\x07\x01\x2A'
    .end code
.end method

.method private static method1941 : ()V
    .code stack 3 locals 0
L0:     getstatic Field org/lwjgl/input/Keyboard field2572 Z
L3:     ifeq L8
L6:     return
L7:     athrow
L8:     invokestatic Method org/lwjgl/Sys method1895 ()V
L11:    iconst_1
L12:    dup
L13:    dup
L14:    pop2
L15:    putstatic Field org/lwjgl/input/Keyboard field2572 Z
L18:    return
L19:    
        .attribute StackMap b'\x00\x02\x00\x07\x00\x00\x00\x01\x07\x01\x2A\x00\x08\x00\x00\x00\x00'
    .end code
.end method

.method public static method1942 : ()Z
    .code stack 2 locals 2
L0:     getstatic Field org/lwjgl/input/D field2554 Ljava/lang/Object;
L3:     dup
L4:     astore_0
L5:     monitorenter
        .catch [0] from L6 to L11 using L13
L6:     getstatic Field org/lwjgl/input/Keyboard field2567 Z
L9:     aload_0
L10:    monitorexit
L11:    ireturn
L12:    athrow
        .catch [0] from L13 to L16 using L13
L13:    astore_1
L14:    aload_0
L15:    monitorexit
L16:    aload_1
L17:    athrow
L18:    
        .attribute StackMap b'\x00\x02\x00\x0C\x00\x00\x00\x01\x07\x01\x2A\x00\x0D\x00\x01\x07\x00\x04\x00\x01\x07\x01\x2A'
    .end code
.end method

.method public static method1943 : (Z)V
    .code stack 2 locals 3
L0:     getstatic Field org/lwjgl/input/D field2554 Ljava/lang/Object;
L3:     dup
L4:     astore_1
L5:     monitorenter
        .catch [0] from L6 to L12 using L14
L6:     iload_0
L7:     putstatic Field org/lwjgl/input/Keyboard field2567 Z
L10:    aload_1
L11:    monitorexit
L12:    return
L13:    athrow
        .catch [0] from L14 to L17 using L14
L14:    astore_2
L15:    aload_1
L16:    monitorexit
L17:    aload_2
L18:    athrow
L19:    athrow
L20:    
        .attribute StackMap b'\x00\x03\x00\x0D\x00\x00\x00\x01\x07\x01\x2A\x00\x0E\x00\x02\x01\x07\x00\x04\x00\x01\x07\x01\x2A\x00\x13\x00\x00\x00\x01\x07\x01\x2A'
    .end code
.end method

.method private static method1944 : ()V
    .code stack 5 locals 1
L0:     getstatic Field org/lwjgl/input/Keyboard field2575 Ljava/nio/ByteBuffer;
L3:     iconst_0
L4:     iconst_1
L5:     dup
L6:     pop2
L7:     invokevirtual Method java/nio/ByteBuffer limit (I)Ljava/nio/Buffer;
L10:    iconst_0
L11:    iconst_1
L12:    dup
L13:    pop2
L14:    istore_0
L15:    pop
L16:    iload_0
L17:    getstatic Field org/lwjgl/input/Keyboard new Ljava/nio/ByteBuffer;
L20:    invokevirtual Method java/nio/ByteBuffer remaining ()I
L23:    if_icmpge L46
L26:    getstatic Field org/lwjgl/input/Keyboard new Ljava/nio/ByteBuffer;
L29:    iload_0
L30:    iconst_0
L31:    iconst_1
L32:    iinc 0 1
L35:    dup
L36:    pop2
L37:    invokevirtual Method java/nio/ByteBuffer put (IB)Ljava/nio/ByteBuffer;
L40:    pop
L41:    iload_0
L42:    goto L17
L45:    athrow
L46:    getstatic Field org/lwjgl/input/Keyboard field2570 Lorg/lwjgl/input/C;
L49:    invokestatic Method org/lwjgl/input/C method1904 (Lorg/lwjgl/input/C;)V
L52:    return
L53:    
        .attribute StackMap b'\x00\x03\x00\x11\x00\x01\x01\x00\x01\x01\x00\x2D\x00\x00\x00\x01\x07\x01\x2A\x00\x2E\x00\x01\x01\x00\x00'
    .end code
.end method

.method public static new : ()C
    .code stack 2 locals 2
L0:     getstatic Field org/lwjgl/input/D field2554 Ljava/lang/Object;
L3:     dup
L4:     astore_0
L5:     monitorenter
        .catch [0] from L6 to L15 using L17
L6:     getstatic Field org/lwjgl/input/Keyboard field2570 Lorg/lwjgl/input/C;
L9:     invokestatic Method org/lwjgl/input/C method1907 (Lorg/lwjgl/input/C;)I
L12:    i2c
L13:    aload_0
L14:    monitorexit
L15:    ireturn
L16:    athrow
        .catch [0] from L17 to L20 using L17
L17:    astore_1
L18:    aload_0
L19:    monitorexit
L20:    aload_1
L21:    athrow
L22:    
        .attribute StackMap b'\x00\x02\x00\x10\x00\x00\x00\x01\x07\x01\x2A\x00\x11\x00\x01\x07\x00\x04\x00\x01\x07\x01\x2A'
    .end code
.end method

.method public static try : ()Z
    .code stack 2 locals 2
L0:     getstatic Field org/lwjgl/input/D field2554 Ljava/lang/Object;
L3:     dup
L4:     astore_0
L5:     monitorenter
        .catch [0] from L6 to L11 using L13
L6:     getstatic Field org/lwjgl/input/Keyboard field2574 Z
L9:     aload_0
L10:    monitorexit
L11:    ireturn
L12:    athrow
        .catch [0] from L13 to L16 using L13
L13:    astore_1
L14:    aload_0
L15:    monitorexit
L16:    aload_1
L17:    athrow
L18:    
        .attribute StackMap b'\x00\x02\x00\x0C\x00\x00\x00\x01\x07\x01\x2A\x00\x0D\x00\x01\x07\x00\x04\x00\x01\x07\x01\x2A'
    .end code
.end method

.method public static synchronized method1945 : (Ljava/lang/String;)I
    .code stack 3 locals 2
L0:     getstatic Field org/lwjgl/input/Keyboard this Ljava/util/Map;
L3:     aload_0
L4:     invokeinterface InterfaceMethod java/util/Map get (Ljava/lang/Object;)Ljava/lang/Object; 2
L9:     checkcast java/lang/Integer
L12:    dup
L13:    astore_1
L14:    ifnonnull L23
L17:    iconst_0
L18:    iconst_1
L19:    dup
L20:    pop2
L21:    ireturn
L22:    athrow
L23:    aload_1
L24:    invokevirtual Method java/lang/Integer intValue ()I
L27:    ireturn
L28:    
        .attribute StackMap b'\x00\x02\x00\x16\x00\x00\x00\x01\x07\x01\x2A\x00\x17\x00\x02\x07\x01\x64\x07\x01\x62\x00\x00'
    .end code
.end method

.method public static this : ()J
    .code stack 3 locals 2
L0:     getstatic Field org/lwjgl/input/D field2554 Ljava/lang/Object;
L3:     dup
L4:     astore_0
L5:     monitorenter
        .catch [0] from L6 to L14 using L16
L6:     getstatic Field org/lwjgl/input/Keyboard field2570 Lorg/lwjgl/input/C;
L9:     invokestatic Method org/lwjgl/input/C method1905 (Lorg/lwjgl/input/C;)J
L12:    aload_0
L13:    monitorexit
L14:    lreturn
L15:    athrow
        .catch [0] from L16 to L19 using L16
L16:    astore_1
L17:    aload_0
L18:    monitorexit
L19:    aload_1
L20:    athrow
L21:    
        .attribute StackMap b'\x00\x02\x00\x0F\x00\x00\x00\x01\x07\x01\x2A\x00\x10\x00\x01\x07\x00\x04\x00\x01\x07\x01\x2A'
    .end code
.end method

.method private static method1946 : (Lorg/lwjgl/input/C;)Z
    .code stack 6 locals 1
L0:     getstatic Field org/lwjgl/input/Keyboard field2575 Ljava/nio/ByteBuffer;
L3:     invokevirtual Method java/nio/ByteBuffer hasRemaining ()Z
L6:     ifeq L109
L9:     aload_0
L10:    dup
L11:    getstatic Field org/lwjgl/input/Keyboard field2575 Ljava/nio/ByteBuffer;
L14:    invokevirtual Method java/nio/ByteBuffer getInt ()I
L17:    sipush 255
L20:    iconst_1
L21:    dup
L22:    pop2
L23:    iand
L24:    invokestatic Method org/lwjgl/input/C method1902 (Lorg/lwjgl/input/C;I)I
L27:    pop
L28:    getstatic Field org/lwjgl/input/Keyboard field2575 Ljava/nio/ByteBuffer;
L31:    invokevirtual Method java/nio/ByteBuffer get ()B
L34:    ifeq L45
L37:    iconst_1
L38:    dup
L39:    dup
L40:    pop2
L41:    goto L49
L44:    athrow
L45:    iconst_0
L46:    iconst_1
L47:    dup
L48:    pop2
L49:    invokestatic Method org/lwjgl/input/C method1901 (Lorg/lwjgl/input/C;Z)Z
L52:    aload_0
L53:    getstatic Field org/lwjgl/input/Keyboard field2575 Ljava/nio/ByteBuffer;
L56:    invokevirtual Method java/nio/ByteBuffer getInt ()I
L59:    invokestatic Method org/lwjgl/input/C method1906 (Lorg/lwjgl/input/C;I)I
L62:    aload_0
L63:    getstatic Field org/lwjgl/input/Keyboard field2575 Ljava/nio/ByteBuffer;
L66:    invokevirtual Method java/nio/ByteBuffer getLong ()J
L69:    invokestatic Method org/lwjgl/input/C method1899 (Lorg/lwjgl/input/C;J)J
L72:    pop2
L73:    pop2
L74:    aload_0
L75:    getstatic Field org/lwjgl/input/Keyboard field2575 Ljava/nio/ByteBuffer;
L78:    invokevirtual Method java/nio/ByteBuffer get ()B
L81:    iconst_1
L82:    dup
L83:    dup
L84:    pop2
L85:    if_icmpne L96
L88:    iconst_1
L89:    dup
L90:    dup
L91:    pop2
L92:    goto L100
L95:    athrow
L96:    iconst_0
L97:    iconst_1
L98:    dup
L99:    pop2
L100:   invokestatic Method org/lwjgl/input/C method1908 (Lorg/lwjgl/input/C;Z)Z
L103:   pop
L104:   iconst_1
L105:   dup
L106:   dup
L107:   pop2
L108:   ireturn
L109:   iconst_0
L110:   iconst_1
L111:   dup
L112:   pop2
L113:   ireturn
L114:   
        .attribute StackMap b'\x00\x07\x00\x2C\x00\x00\x00\x01\x07\x01\x2A\x00\x2D\x00\x01\x07\x00\x06\x00\x01\x07\x00\x06\x00\x31\x00\x01\x07\x00\x06\x00\x02\x07\x00\x06\x01\x00\x5F\x00\x00\x00\x01\x07\x01\x2A\x00\x60\x00\x01\x07\x00\x06\x00\x01\x07\x00\x06\x00\x64\x00\x01\x07\x00\x06\x00\x02\x07\x00\x06\x01\x00\x6D\x00\x01\x07\x00\x06\x00\x00'
    .end code
.end method

.method public static method1947 : ()I
    .code stack 2 locals 2
L0:     getstatic Field org/lwjgl/input/D field2554 Ljava/lang/Object;
L3:     dup
L4:     astore_0
L5:     monitorenter
        .catch [0] from L6 to L14 using L16
L6:     getstatic Field org/lwjgl/input/Keyboard field2570 Lorg/lwjgl/input/C;
L9:     invokestatic Method org/lwjgl/input/C method1909 (Lorg/lwjgl/input/C;)I
L12:    aload_0
L13:    monitorexit
L14:    ireturn
L15:    athrow
        .catch [0] from L16 to L19 using L16
L16:    astore_1
L17:    aload_0
L18:    monitorexit
L19:    aload_1
L20:    athrow
L21:    
        .attribute StackMap b'\x00\x02\x00\x0F\x00\x00\x00\x01\x07\x01\x2A\x00\x10\x00\x01\x07\x00\x04\x00\x01\x07\x01\x2A'
    .end code
.end method

.method public static method1948 : ()Z
    .code stack 3 locals 3
L0:     getstatic Field org/lwjgl/input/D field2554 Ljava/lang/Object;
L3:     dup
L4:     astore_0
L5:     monitorenter
        .catch [0] from L6 to L52 using L58
L6:     getstatic Field org/lwjgl/input/Keyboard field2574 Z
L9:     ifne L23
L12:    new java/lang/IllegalStateException
L15:    dup
L16:    ldc_w "Keyboard must be created before you can read events"
L19:    invokespecial Method java/lang/IllegalStateException <init> (Ljava/lang/String;)V
L22:    athrow
L23:    getstatic Field org/lwjgl/input/Keyboard field2570 Lorg/lwjgl/input/C;
L26:    invokestatic Method org/lwjgl/input/Keyboard method1946 (Lorg/lwjgl/input/C;)Z
L29:    dup
L30:    istore_1
L31:    ifeq L53
L34:    getstatic Field org/lwjgl/input/Keyboard field2570 Lorg/lwjgl/input/C;
L37:    invokestatic Method org/lwjgl/input/C method1903 (Lorg/lwjgl/input/C;)Z
L40:    ifeq L53
L43:    getstatic Field org/lwjgl/input/Keyboard field2567 Z
L46:    ifne L53
L49:    goto L23
L52:    athrow
        .catch [0] from L53 to L56 using L58
L53:    iload_1
L54:    aload_0
L55:    monitorexit
L56:    ireturn
L57:    athrow
        .catch [0] from L58 to L61 using L58
L58:    astore_2
L59:    aload_0
L60:    monitorexit
L61:    aload_2
L62:    athrow
L63:    
        .attribute StackMap b'\x00\x05\x00\x17\x00\x01\x07\x00\x04\x00\x00\x00\x34\x00\x00\x00\x01\x07\x01\x2A\x00\x35\x00\x02\x07\x00\x04\x01\x00\x00\x00\x39\x00\x00\x00\x01\x07\x01\x2A\x00\x3A\x00\x01\x07\x00\x04\x00\x01\x07\x01\x2A'
    .end code
.end method

.method public static method1949 : ()I
    .code stack 3 locals 4
L0:     getstatic Field org/lwjgl/input/D field2554 Ljava/lang/Object;
L3:     dup
L4:     astore_0
L5:     monitorenter
        .catch [0] from L6 to L65 using L79
L6:     getstatic Field org/lwjgl/input/Keyboard field2574 Z
L9:     ifne L23
L12:    new java/lang/IllegalStateException
L15:    dup
L16:    ldc_w "Keyboard must be created before you can read events"
L19:    invokespecial Method java/lang/IllegalStateException <init> (Ljava/lang/String;)V
L22:    athrow
L23:    getstatic Field org/lwjgl/input/Keyboard field2575 Ljava/nio/ByteBuffer;
L26:    invokevirtual Method java/nio/ByteBuffer position ()I
L29:    istore_1
L30:    iconst_0
L31:    iconst_1
L32:    dup
L33:    pop2
L34:    istore_2
L35:    getstatic Field org/lwjgl/input/Keyboard field2576 Lorg/lwjgl/input/C;
L38:    invokestatic Method org/lwjgl/input/Keyboard method1946 (Lorg/lwjgl/input/C;)Z
L41:    ifeq L66
L44:    getstatic Field org/lwjgl/input/Keyboard field2576 Lorg/lwjgl/input/C;
L47:    invokestatic Method org/lwjgl/input/C method1903 (Lorg/lwjgl/input/C;)Z
L50:    ifeq L59
L53:    getstatic Field org/lwjgl/input/Keyboard field2567 Z
L56:    ifeq L66
L59:    iinc 2 1
L62:    goto L35
L65:    athrow
        .catch [0] from L66 to L77 using L79
L66:    getstatic Field org/lwjgl/input/Keyboard field2575 Ljava/nio/ByteBuffer;
L69:    iload_1
L70:    invokevirtual Method java/nio/ByteBuffer position (I)Ljava/nio/Buffer;
L73:    pop
L74:    iload_2
L75:    aload_0
L76:    monitorexit
L77:    ireturn
L78:    athrow
        .catch [0] from L79 to L82 using L79
L79:    astore_3
L80:    aload_0
L81:    monitorexit
L82:    aload_3
L83:    athrow
L84:    
        .attribute StackMap b'\x00\x07\x00\x17\x00\x01\x07\x00\x04\x00\x00\x00\x23\x00\x03\x07\x00\x04\x01\x01\x00\x00\x00\x3B\x00\x03\x07\x00\x04\x01\x01\x00\x00\x00\x41\x00\x00\x00\x01\x07\x01\x2A\x00\x42\x00\x03\x07\x00\x04\x01\x01\x00\x00\x00\x4E\x00\x00\x00\x01\x07\x01\x2A\x00\x4F\x00\x01\x07\x00\x04\x00\x01\x07\x01\x2A'
    .end code
.end method

.method public static method1950 : ()I
    .code stack 1 locals 0
L0:     getstatic Field org/lwjgl/input/Keyboard field2571 I
L3:     ireturn
L4:     
    .end code
.end method

.method public static synchronized method1951 : (I)Ljava/lang/String;
    .code stack 2 locals 1
L0:     getstatic Field org/lwjgl/input/Keyboard try [Ljava/lang/String;
L3:     iload_0
L4:     aaload
L5:     areturn
L6:     
    .end code
.end method

.method private static method1952 : ()V
    .code stack 3 locals 0
L0:     getstatic Field org/lwjgl/input/Keyboard field2575 Ljava/nio/ByteBuffer;
L3:     invokevirtual Method java/nio/ByteBuffer compact ()Ljava/nio/ByteBuffer;
L6:     getstatic Field org/lwjgl/input/Keyboard field2569 Lorg/lwjgl/opengl/i;
L9:     getstatic Field org/lwjgl/input/Keyboard field2575 Ljava/nio/ByteBuffer;
L12:    invokeinterface InterfaceMethod org/lwjgl/opengl/i method4777 (Ljava/nio/ByteBuffer;)V 2
L17:    getstatic Field org/lwjgl/input/Keyboard field2575 Ljava/nio/ByteBuffer;
L20:    invokevirtual Method java/nio/ByteBuffer flip ()Ljava/nio/Buffer;
L23:    pop2
L24:    return
L25:    
    .end code
.end method

.method public static method1953 : ()V
    .code stack 3 locals 2
L0:     getstatic Field org/lwjgl/input/D field2554 Ljava/lang/Object;
L3:     dup
L4:     astore_0
L5:     monitorenter
        .catch [0] from L6 to L14 using L38
L6:     getstatic Field org/lwjgl/input/Keyboard field2574 Z
L9:     ifne L16
L12:    aload_0
L13:    monitorexit
L14:    return
L15:    athrow
        .catch [0] from L16 to L36 using L38
L16:    iconst_0
L17:    iconst_1
L18:    dup
L19:    pop2
L20:    putstatic Field org/lwjgl/input/Keyboard field2574 Z
L23:    getstatic Field org/lwjgl/input/Keyboard field2569 Lorg/lwjgl/opengl/i;
L26:    invokeinterface InterfaceMethod org/lwjgl/opengl/i method4724 ()V 1
L31:    invokestatic Method org/lwjgl/input/Keyboard method1944 ()V
L34:    aload_0
L35:    monitorexit
L36:    return
L37:    athrow
        .catch [0] from L38 to L41 using L38
L38:    astore_1
L39:    aload_0
L40:    monitorexit
L41:    aload_1
L42:    athrow
L43:    athrow
L44:    
        .attribute StackMap b'\x00\x05\x00\x0F\x00\x00\x00\x01\x07\x01\x2A\x00\x10\x00\x01\x07\x00\x04\x00\x00\x00\x25\x00\x00\x00\x01\x07\x01\x2A\x00\x26\x00\x01\x07\x00\x04\x00\x01\x07\x01\x2A\x00\x2B\x00\x00\x00\x01\x07\x01\x2A'
    .end code
.end method

.method public static method1954 : ()Z
    .code stack 2 locals 2
L0:     getstatic Field org/lwjgl/input/D field2554 Ljava/lang/Object;
L3:     dup
L4:     astore_0
L5:     monitorenter
        .catch [0] from L6 to L14 using L16
L6:     getstatic Field org/lwjgl/input/Keyboard field2570 Lorg/lwjgl/input/C;
L9:     invokestatic Method org/lwjgl/input/C method1903 (Lorg/lwjgl/input/C;)Z
L12:    aload_0
L13:    monitorexit
L14:    ireturn
L15:    athrow
        .catch [0] from L16 to L19 using L16
L16:    astore_1
L17:    aload_0
L18:    monitorexit
L19:    aload_1
L20:    athrow
L21:    
        .attribute StackMap b'\x00\x02\x00\x0F\x00\x00\x00\x01\x07\x01\x2A\x00\x10\x00\x01\x07\x00\x04\x00\x01\x07\x01\x2A'
    .end code
.end method

.method public static method1955 : ()V
    .code stack 3 locals 2
L0:     getstatic Field org/lwjgl/input/D field2554 Ljava/lang/Object;
L3:     dup
L4:     astore_0
L5:     monitorenter
        .catch [0] from L6 to L39 using L41
L6:     getstatic Field org/lwjgl/input/Keyboard field2574 Z
L9:     ifne L23
L12:    new java/lang/IllegalStateException
L15:    dup
L16:    ldc_w "Keyboard must be created before you can poll the device"
L19:    invokespecial Method java/lang/IllegalStateException <init> (Ljava/lang/String;)V
L22:    athrow
L23:    getstatic Field org/lwjgl/input/Keyboard field2569 Lorg/lwjgl/opengl/i;
L26:    getstatic Field org/lwjgl/input/Keyboard new Ljava/nio/ByteBuffer;
L29:    invokeinterface InterfaceMethod org/lwjgl/opengl/i method4710 (Ljava/nio/ByteBuffer;)V 2
L34:    invokestatic Method org/lwjgl/input/Keyboard method1952 ()V
L37:    aload_0
L38:    monitorexit
L39:    return
L40:    athrow
        .catch [0] from L41 to L44 using L41
L41:    astore_1
L42:    aload_0
L43:    monitorexit
L44:    aload_1
L45:    athrow
L46:    athrow
L47:    
        .attribute StackMap b'\x00\x04\x00\x17\x00\x01\x07\x00\x04\x00\x00\x00\x28\x00\x00\x00\x01\x07\x01\x2A\x00\x29\x00\x01\x07\x00\x04\x00\x01\x07\x01\x2A\x00\x2E\x00\x00\x00\x01\x07\x01\x2A'
    .end code
.end method

.method static <clinit> : ()V
    .code stack 5 locals 6
L0:     sipush 256
L3:     iconst_1
L4:     dup
L5:     pop2
L6:     anewarray java/lang/String
L9:     iconst_1
L10:    dup
L11:    pop2
L12:    putstatic Field org/lwjgl/input/Keyboard try [Ljava/lang/String;
L15:    new java/util/HashMap
L18:    dup
L19:    sipush 253
L22:    iconst_1
L23:    dup
L24:    pop2
L25:    invokespecial Method java/util/HashMap <init> (I)V
L28:    putstatic Field org/lwjgl/input/Keyboard this Ljava/util/Map;
L31:    ldc Class org/lwjgl/input/Keyboard
L33:    invokevirtual Method java/lang/Class getFields ()[Ljava/lang/reflect/Field;
L36:    astore_0
        .catch java/lang/Exception from L37 to L179 using L184
L37:    aload_0
L38:    dup
L39:    astore_1
L40:    arraylength
L41:    istore_2
L42:    iconst_0
L43:    iconst_1
L44:    dup
L45:    pop2
L46:    istore_3
L47:    iload_3
L48:    iload_2
L49:    if_icmpge L185
L52:    aload_1
L53:    iload_3
L54:    aaload
L55:    dup
L56:    astore 4
L58:    invokevirtual Method java/lang/reflect/Field getModifiers ()I
L61:    invokestatic Method java/lang/reflect/Modifier isStatic (I)Z
L64:    ifeq L173
L67:    aload 4
L69:    invokevirtual Method java/lang/reflect/Field getModifiers ()I
L72:    invokestatic Method java/lang/reflect/Modifier isPublic (I)Z
L75:    ifeq L173
L78:    aload 4
L80:    invokevirtual Method java/lang/reflect/Field getModifiers ()I
L83:    invokestatic Method java/lang/reflect/Modifier isFinal (I)Z
L86:    ifeq L173
L89:    aload 4
L91:    invokevirtual Method java/lang/reflect/Field getType ()Ljava/lang/Class;
L94:    getstatic Field java/lang/Integer TYPE Ljava/lang/Class;
L97:    invokevirtual Method java/lang/Object equals (Ljava/lang/Object;)Z
L100:   ifeq L173
L103:   aload 4
L105:   invokevirtual Method java/lang/reflect/Field getName ()Ljava/lang/String;
L108:   ldc_w "KEY_"
L111:   invokevirtual Method java/lang/String startsWith (Ljava/lang/String;)Z
L114:   ifeq L173
L117:   aload 4
L119:   dup
L120:   aconst_null
L121:   invokevirtual Method java/lang/reflect/Field getInt (Ljava/lang/Object;)I
L124:   istore 4
L126:   invokevirtual Method java/lang/reflect/Field getName ()Ljava/lang/String;
L129:   iconst_4
L130:   iconst_1
L131:   dup
L132:   pop2
L133:   invokevirtual Method java/lang/String substring (I)Ljava/lang/String;
L136:   astore 5
L138:   getstatic Field org/lwjgl/input/Keyboard try [Ljava/lang/String;
L141:   iload 4
L143:   aload 5
L145:   aastore
L146:   getstatic Field org/lwjgl/input/Keyboard this Ljava/util/Map;
L149:   aload 5
L151:   iload 4
L153:   invokestatic Method java/lang/Integer valueOf (I)Ljava/lang/Integer;
L156:   invokeinterface InterfaceMethod java/util/Map put (Ljava/lang/Object;Ljava/lang/Object;)Ljava/lang/Object; 3
L161:   getstatic Field org/lwjgl/input/Keyboard field2568 I
L164:   iconst_1
L165:   dup
L166:   dup
L167:   pop2
L168:   iadd
L169:   putstatic Field org/lwjgl/input/Keyboard field2568 I
L172:   pop
L173:   iinc 3 1
L176:   goto L47
L179:   nop
L180:   nop
L181:   nop
L182:   athrow
L183:   athrow
L184:   astore_1
L185:   getstatic Field org/lwjgl/input/Keyboard field2568 I
L188:   putstatic Field org/lwjgl/input/Keyboard field2571 I
L191:   sipush 256
L194:   iconst_1
L195:   dup
L196:   pop2
L197:   invokestatic Method org/lwjgl/BufferUtils createByteBuffer (I)Ljava/nio/ByteBuffer;
L200:   putstatic Field org/lwjgl/input/Keyboard new Ljava/nio/ByteBuffer;
L203:   new org/lwjgl/input/C
L206:   dup
L207:   aconst_null
L208:   invokespecial Method org/lwjgl/input/C <init> (Lorg/lwjgl/input/h;)V
L211:   putstatic Field org/lwjgl/input/Keyboard field2570 Lorg/lwjgl/input/C;
L214:   new org/lwjgl/input/C
L217:   dup
L218:   aconst_null
L219:   invokespecial Method org/lwjgl/input/C <init> (Lorg/lwjgl/input/h;)V
L222:   putstatic Field org/lwjgl/input/Keyboard field2576 Lorg/lwjgl/input/C;
L225:   return
L226:   
        .attribute StackMap b'\x00\x06\x00\x2F\x00\x04\x07\x01\xDC\x07\x01\xDC\x01\x01\x00\x00\x00\xAD\x00\x04\x07\x01\xDC\x07\x01\xDC\x01\x01\x00\x00\x00\xB3\x00\x00\x00\x01\x07\x01\x2A\x00\xB7\x00\x00\x00\x01\x07\x01\x2A\x00\xB8\x00\x01\x07\x01\xDC\x00\x01\x07\x01\xCF\x00\xB9\x00\x02\x07\x01\xDC\x07\x00\x04\x00\x00'
    .end code
.end method

.method private static method1956 : (Lorg/lwjgl/opengl/i;)V
    .code stack 3 locals 1
L0:     getstatic Field org/lwjgl/input/Keyboard field2574 Z
L3:     ifeq L8
L6:     return
L7:     athrow
L8:     getstatic Field org/lwjgl/input/Keyboard field2572 Z
L11:    ifne L17
L14:    invokestatic Method org/lwjgl/input/Keyboard method1941 ()V
L17:    aload_0
L18:    putstatic Field org/lwjgl/input/Keyboard field2569 Lorg/lwjgl/opengl/i;
L21:    getstatic Field org/lwjgl/input/Keyboard field2569 Lorg/lwjgl/opengl/i;
L24:    invokeinterface InterfaceMethod org/lwjgl/opengl/i method4707 ()V 1
L29:    iconst_1
L30:    dup
L31:    dup
L32:    pop2
L33:    putstatic Field org/lwjgl/input/Keyboard field2574 Z
L36:    sipush 900
L39:    iconst_1
L40:    dup
L41:    pop2
L42:    invokestatic Method java/nio/ByteBuffer allocate (I)Ljava/nio/ByteBuffer;
L45:    putstatic Field org/lwjgl/input/Keyboard field2575 Ljava/nio/ByteBuffer;
L48:    invokestatic Method org/lwjgl/input/Keyboard method1944 ()V
L51:    return
L52:    
        .attribute StackMap b'\x00\x03\x00\x07\x00\x00\x00\x01\x07\x01\x2A\x00\x08\x00\x01\x07\x01\xB5\x00\x00\x00\x11\x00\x01\x07\x01\xB5\x00\x00'
    .end code
    .exceptions org/lwjgl/LWJGLException
.end method

.method private <init> : ()V
    .code stack 1 locals 1
L0:     aload_0
L1:     invokespecial Method java/lang/Object <init> ()V
L4:     return
L5:     
    .end code
.end method

.method public static method1957 : (I)Z
    .code stack 3 locals 3
L0:     getstatic Field org/lwjgl/input/D field2554 Ljava/lang/Object;
L3:     dup
L4:     astore_1
L5:     monitorenter
        .catch [0] from L6 to L41 using L50
L6:     getstatic Field org/lwjgl/input/Keyboard field2574 Z
L9:     ifne L23
L12:    new java/lang/IllegalStateException
L15:    dup
L16:    ldc_w "Keyboard must be created before you can query key state"
L19:    invokespecial Method java/lang/IllegalStateException <init> (Ljava/lang/String;)V
L22:    athrow
L23:    getstatic Field org/lwjgl/input/Keyboard new Ljava/nio/ByteBuffer;
L26:    iload_0
L27:    invokevirtual Method java/nio/ByteBuffer get (I)B
L30:    ifeq L42
L33:    iconst_1
L34:    dup
L35:    dup
L36:    pop2
L37:    aload_1
L38:    goto L47
L41:    athrow
        .catch [0] from L42 to L48 using L50
L42:    iconst_0
L43:    iconst_1
L44:    dup
L45:    pop2
L46:    aload_1
L47:    monitorexit
L48:    ireturn
L49:    athrow
        .catch [0] from L50 to L53 using L50
L50:    astore_2
L51:    aload_1
L52:    monitorexit
L53:    aload_2
L54:    athrow
L55:    
        .attribute StackMap b'\x00\x06\x00\x17\x00\x02\x01\x07\x00\x04\x00\x00\x00\x29\x00\x00\x00\x01\x07\x01\x2A\x00\x2A\x00\x02\x01\x07\x00\x04\x00\x00\x00\x2F\x00\x02\x01\x07\x00\x04\x00\x02\x01\x07\x00\x04\x00\x31\x00\x00\x00\x01\x07\x01\x2A\x00\x32\x00\x02\x01\x07\x00\x04\x00\x01\x07\x01\x2A'
    .end code
.end method

.method public static method1958 : ()V
    .code stack 3 locals 2
L0:     getstatic Field org/lwjgl/input/D field2554 Ljava/lang/Object;
L3:     dup
L4:     astore_0
L5:     monitorenter
        .catch [0] from L6 to L31 using L33
L6:     invokestatic Method org/lwjgl/opengl/Display method3019 ()Z
L9:     ifne L23
L12:    new java/lang/IllegalStateException
L15:    dup
L16:    ldc_w "Display must be created."
L19:    invokespecial Method java/lang/IllegalStateException <init> (Ljava/lang/String;)V
L22:    athrow
L23:    invokestatic Method org/lwjgl/input/D method1911 ()Lorg/lwjgl/opengl/i;
L26:    invokestatic Method org/lwjgl/input/Keyboard method1956 (Lorg/lwjgl/opengl/i;)V
L29:    aload_0
L30:    monitorexit
L31:    return
L32:    athrow
        .catch [0] from L33 to L36 using L33
L33:    astore_1
L34:    aload_0
L35:    monitorexit
L36:    aload_1
L37:    athrow
L38:    athrow
L39:    
        .attribute StackMap b'\x00\x04\x00\x17\x00\x01\x07\x00\x04\x00\x00\x00\x20\x00\x00\x00\x01\x07\x01\x2A\x00\x21\x00\x01\x07\x00\x04\x00\x01\x07\x01\x2A\x00\x26\x00\x00\x00\x01\x07\x01\x2A'
    .end code
    .exceptions org/lwjgl/LWJGLException
.end method
.innerclasses
    org/lwjgl/input/C org/lwjgl/input/Keyboard [0] private static final
    org/lwjgl/input/h org/lwjgl/input/Keyboard [0] static synthetic
.end innerclasses
.end class
