.version 49 0
.class final super org/lwjgl/L
.super java/lang/Object
.implements java/security/PrivilegedExceptionAction
.field final synthetic field2470 Ljava/lang/Class;
.field final synthetic field2471 Ljava/lang/String;
.field final synthetic field2472 Ljava/lang/ClassLoader;

.method <init> : (Ljava/lang/Class;Ljava/lang/ClassLoader;Ljava/lang/String;)V
    .code stack 7 locals 4
L0:     aload_3
L1:     aload_0
L2:     dup_x1
L3:     dup_x2
L4:     aload_2
L5:     aload_0
L6:     aload_1
L7:     putfield Field org/lwjgl/L field2470 Ljava/lang/Class;
L10:    putfield Field org/lwjgl/L field2472 Ljava/lang/ClassLoader;
L13:    putfield Field org/lwjgl/L field2471 Ljava/lang/String;
L16:    invokespecial Method java/lang/Object <init> ()V
L19:    return
L20:    
    .end code
.end method

.method public method1760 : ()Ljava/lang/String;
    .code stack 7 locals 2
L0:     aload_0
L1:     getfield Field org/lwjgl/L field2470 Ljava/lang/Class;
L4:     ldc "findLibrary"
L6:     iconst_1
L7:     dup
L8:     dup
L9:     pop2
L10:    anewarray java/lang/Class
L13:    iconst_1
L14:    dup
L15:    pop2
L16:    dup
L17:    iconst_0
L18:    iconst_1
L19:    dup
L20:    pop2
L21:    ldc Class java/lang/String
L23:    aastore
L24:    invokevirtual Method java/lang/Class getDeclaredMethod (Ljava/lang/String;[Ljava/lang/Class;)Ljava/lang/reflect/Method;
L27:    astore_1
L28:    aload_0
L29:    aload_1
L30:    dup_x1
L31:    iconst_1
L32:    dup
L33:    dup
L34:    pop2
L35:    invokevirtual Method java/lang/reflect/Method setAccessible (Z)V
L38:    getfield Field org/lwjgl/L field2472 Ljava/lang/ClassLoader;
L41:    iconst_1
L42:    dup
L43:    dup
L44:    pop2
L45:    anewarray java/lang/Object
L48:    iconst_1
L49:    dup
L50:    pop2
L51:    dup
L52:    iconst_0
L53:    iconst_1
L54:    dup
L55:    pop2
L56:    aload_0
L57:    getfield Field org/lwjgl/L field2471 Ljava/lang/String;
L60:    aastore
L61:    invokevirtual Method java/lang/reflect/Method invoke (Ljava/lang/Object;[Ljava/lang/Object;)Ljava/lang/Object;
L64:    checkcast java/lang/String
L67:    areturn
L68:    
    .end code
    .exceptions java/lang/Exception
.end method

.method public bridge synthetic run : ()Ljava/lang/Object;
    .code stack 1 locals 1
L0:     aload_0
L1:     invokevirtual Method org/lwjgl/L method1760 ()Ljava/lang/String;
L4:     areturn
L5:     
    .end code
    .exceptions java/lang/Exception
.end method
.innerclasses
    org/lwjgl/L [0] [0] static
.end innerclasses
.enclosing method org/lwjgl/LWJGLUtil getPathFromClassLoader (Ljava/lang/String;Ljava/lang/ClassLoader;)Ljava/lang/String;
.end class
