.version 49 0
.class public final super org/lwjgl/LWJGLException
.super java/lang/Exception
.field private static final field613 J = 1L

.method public <init> : (Ljava/lang/String;)V
    .code stack 2 locals 2
L0:     aload_0
L1:     aload_1
L2:     invokespecial Method java/lang/Exception <init> (Ljava/lang/String;)V
L5:     return
L6:     
    .end code
.end method

.method public <init> : ()V
    .code stack 1 locals 1
L0:     aload_0
L1:     invokespecial Method java/lang/Exception <init> ()V
L4:     return
L5:     
    .end code
.end method

.method public <init> : (Ljava/lang/Throwable;)V
    .code stack 2 locals 2
L0:     aload_0
L1:     aload_1
L2:     invokespecial Method java/lang/Exception <init> (Ljava/lang/Throwable;)V
L5:     return
L6:     
    .end code
.end method

.method public <init> : (Ljava/lang/String;Ljava/lang/Throwable;)V
    .code stack 3 locals 3
L0:     aload_0
L1:     aload_1
L2:     aload_2
L3:     invokespecial Method java/lang/Exception <init> (Ljava/lang/String;Ljava/lang/Throwable;)V
L6:     return
L7:     
    .end code
.end method
.end class
