.version 49 0
.class public final super org/lwjgl/LWJGLUtil
.super java/lang/Object
.field private static final LWJGL_ICON_DATA_16x16 Ljava/lang/String;
.field public static final LWJGLIcon32x32 Ljava/nio/ByteBuffer;
.field public static final PLATFORM_MACOSX_NAME Ljava/lang/String;
.field public static final CHECKS Z
.field public static final PLATFORM_MACOSX I = 2
.field public static final PLATFORM_LINUX I = 1
.field public static final DEBUG Z
.field public static final PLATFORM_WINDOWS I = 3
.field private static final LWJGL_ICON_DATA_32x32 Ljava/lang/String;
.field public static final PLATFORM_WINDOWS_NAME Ljava/lang/String;
.field public static final LWJGLIcon16x16 Ljava/nio/ByteBuffer;
.field private static final PLATFORM I
.field public static final PLATFORM_LINUX_NAME Ljava/lang/String;

.method public static getPrivilegedInteger : (Ljava/lang/String;)Ljava/lang/Integer;
    .code stack 3 locals 1
L0:     new org/lwjgl/a
L3:     dup
L4:     aload_0
L5:     invokespecial Method org/lwjgl/a <init> (Ljava/lang/String;)V
L8:     invokestatic Method java/security/AccessController doPrivileged (Ljava/security/PrivilegedAction;)Ljava/lang/Object;
L11:    checkcast java/lang/Integer
L14:    areturn
L15:    
    .end code
.end method

.method public static toHexString : (I)Ljava/lang/String;
    .code stack 3 locals 1
L0:     new java/lang/StringBuilder
L3:     dup
L4:     invokespecial Method java/lang/StringBuilder <init> ()V
L7:     iconst_0
L8:     ldc "0x"
L10:    invokevirtual Method java/lang/StringBuilder insert (ILjava/lang/String;)Ljava/lang/StringBuilder;
L13:    iload_0
L14:    invokestatic Method java/lang/Integer toHexString (I)Ljava/lang/String;
L17:    invokevirtual Method java/lang/String toUpperCase ()Ljava/lang/String;
L20:    invokevirtual Method java/lang/StringBuilder append (Ljava/lang/String;)Ljava/lang/StringBuilder;
L23:    invokevirtual Method java/lang/StringBuilder toString ()Ljava/lang/String;
L26:    areturn
L27:    
    .end code
.end method

.method public static getPrivilegedBoolean : (Ljava/lang/String;)Z
    .code stack 3 locals 1
L0:     new org/lwjgl/A
L3:     dup
L4:     aload_0
L5:     invokespecial Method org/lwjgl/A <init> (Ljava/lang/String;)V
L8:     invokestatic Method java/security/AccessController doPrivileged (Ljava/security/PrivilegedAction;)Ljava/lang/Object;
L11:    checkcast java/lang/Boolean
L14:    invokevirtual Method java/lang/Boolean booleanValue ()Z
L17:    ireturn
L18:    
    .end code
.end method

.method static execPrivileged : ([Ljava/lang/String;)V
    .code stack 3 locals 2
        .catch java/security/PrivilegedActionException from L0 to L36 using L38
L0:     new org/lwjgl/g
L3:     dup
L4:     aload_0
L5:     invokespecial Method org/lwjgl/g <init> ([Ljava/lang/String;)V
L8:     invokestatic Method java/security/AccessController doPrivileged (Ljava/security/PrivilegedExceptionAction;)Ljava/lang/Object;
L11:    checkcast java/lang/Process
L14:    dup
L15:    astore_1
L16:    dup
L17:    dup_x1
L18:    invokevirtual Method java/lang/Process getInputStream ()Ljava/io/InputStream;
L21:    invokevirtual Method java/io/InputStream close ()V
L24:    invokevirtual Method java/lang/Process getOutputStream ()Ljava/io/OutputStream;
L27:    invokevirtual Method java/io/OutputStream close ()V
L30:    invokevirtual Method java/lang/Process getErrorStream ()Ljava/io/InputStream;
L33:    invokevirtual Method java/io/InputStream close ()V
L36:    return
L37:    athrow
L38:    astore_1
L39:    aload_1
L40:    invokevirtual Method java/security/PrivilegedActionException getCause ()Ljava/lang/Throwable;
L43:    checkcast java/lang/Exception
L46:    athrow
L47:    athrow
L48:    
        .attribute StackMap b'\x00\x03\x00\x25\x00\x00\x00\x01\x07\x00\x7B\x00\x26\x00\x01\x07\x00\x7D\x00\x01\x07\x00\x5F\x00\x2F\x00\x00\x00\x01\x07\x00\x7B'
    .end code
    .exceptions java/lang/Exception
.end method

.method public static isMacOSXEqualsOrBetterThan : (II)Z
    .code stack 4 locals 5
L0:     ldc "os.version"
L2:     invokestatic Method org/lwjgl/LWJGLUtil getPrivilegedProperty (Ljava/lang/String;)Ljava/lang/String;
L5:     astore_2
L6:     new java/util/StringTokenizer
L9:     dup
L10:    aload_2
L11:    ldc "."
L13:    invokespecial Method java/util/StringTokenizer <init> (Ljava/lang/String;Ljava/lang/String;)V
L16:    astore_2
        .catch java/lang/Exception from L17 to L37 using L42
L17:    aload_2
L18:    dup
L19:    invokevirtual Method java/util/StringTokenizer nextToken ()Ljava/lang/String;
L22:    astore 4
L24:    invokevirtual Method java/util/StringTokenizer nextToken ()Ljava/lang/String;
L27:    aload 4
L29:    invokestatic Method java/lang/Integer parseInt (Ljava/lang/String;)I
L32:    istore_2
L33:    invokestatic Method java/lang/Integer parseInt (Ljava/lang/String;)I
L36:    istore_3
L37:    iload_2
L38:    goto L75
L41:    athrow
L42:    astore 4
L44:    new java/lang/StringBuilder
L47:    dup
L48:    invokespecial Method java/lang/StringBuilder <init> ()V
L51:    iconst_0
L52:    ldc "Exception occurred while trying to determine OS version: "
L54:    invokevirtual Method java/lang/StringBuilder insert (ILjava/lang/String;)Ljava/lang/StringBuilder;
L57:    aload 4
L59:    invokevirtual Method java/lang/StringBuilder append (Ljava/lang/Object;)Ljava/lang/StringBuilder;
L62:    invokevirtual Method java/lang/StringBuilder toString ()Ljava/lang/String;
L65:    invokestatic Method org/lwjgl/LWJGLUtil log (Ljava/lang/CharSequence;)V
L68:    iconst_0
L69:    iconst_1
L70:    dup
L71:    pop2
L72:    ireturn
L73:    nop
L74:    athrow
L75:    iload_0
L76:    if_icmpgt L89
L79:    iload_2
L80:    iload_0
L81:    if_icmpne L94
L84:    iload_3
L85:    iload_1
L86:    if_icmplt L94
L89:    iconst_1
L90:    dup
L91:    dup
L92:    pop2
L93:    ireturn
L94:    iconst_0
L95:    iconst_1
L96:    dup
L97:    pop2
L98:    ireturn
L99:    
        .attribute StackMap b'\x00\x06\x00\x29\x00\x00\x00\x01\x07\x00\x7B\x00\x2A\x00\x02\x01\x01\x00\x01\x07\x00\x5D\x00\x49\x00\x00\x00\x01\x07\x00\x7B\x00\x4B\x00\x05\x01\x01\x01\x01\x07\x00\x45\x00\x01\x01\x00\x59\x00\x05\x01\x01\x01\x01\x07\x00\x45\x00\x00\x00\x5E\x00\x05\x01\x01\x01\x01\x07\x00\x45\x00\x00'
    .end code
.end method

.method public static varargs getClassTokens : (Lorg/lwjgl/m;Ljava/util/Map;[Ljava/lang/Class;)Ljava/util/Map;
    .code stack 3 locals 3
L0:     aload_0
L1:     aload_1
L2:     aload_2
L3:     invokestatic Method java/util/Arrays asList ([Ljava/lang/Object;)Ljava/util/List;
L6:     invokestatic Method org/lwjgl/LWJGLUtil getClassTokens (Lorg/lwjgl/m;Ljava/util/Map;Ljava/lang/Iterable;)Ljava/util/Map;
L9:     areturn
L10:    
    .end code
.end method

.method public <init> : ()V
    .code stack 1 locals 1
L0:     aload_0
L1:     invokespecial Method java/lang/Object <init> ()V
L4:     return
L5:     
    .end code
.end method

.method public static log : (Ljava/lang/CharSequence;)V
    .code stack 4 locals 1
L0:     getstatic Field org/lwjgl/LWJGLUtil DEBUG Z
L3:     ifeq L32
L6:     getstatic Field java/lang/System err Ljava/io/PrintStream;
L9:     new java/lang/StringBuilder
L12:    dup
L13:    invokespecial Method java/lang/StringBuilder <init> ()V
L16:    iconst_0
L17:    ldc "[LWJGL] "
L19:    invokevirtual Method java/lang/StringBuilder insert (ILjava/lang/String;)Ljava/lang/StringBuilder;
L22:    aload_0
L23:    invokevirtual Method java/lang/StringBuilder append (Ljava/lang/Object;)Ljava/lang/StringBuilder;
L26:    invokevirtual Method java/lang/StringBuilder toString ()Ljava/lang/String;
L29:    invokevirtual Method java/io/PrintStream println (Ljava/lang/String;)V
L32:    return
L33:    
        .attribute StackMap b'\x00\x01\x00\x20\x00\x01\x07\x00\xBD\x00\x00'
    .end code
.end method

.method public static getPlatform : ()I
    .code stack 1 locals 0
L0:     getstatic Field org/lwjgl/LWJGLUtil PLATFORM I
L3:     ireturn
L4:     
    .end code
.end method

.method public static getPrivilegedInteger : (Ljava/lang/String;I)Ljava/lang/Integer;
    .code stack 4 locals 2
L0:     new org/lwjgl/b
L3:     dup
L4:     aload_0
L5:     iload_1
L6:     invokespecial Method org/lwjgl/b <init> (Ljava/lang/String;I)V
L9:     invokestatic Method java/security/AccessController doPrivileged (Ljava/security/PrivilegedAction;)Ljava/lang/Object;
L12:    checkcast java/lang/Integer
L15:    areturn
L16:    
    .end code
.end method

.method private static getPathFromClassLoader : (Ljava/lang/String;Ljava/lang/ClassLoader;)Ljava/lang/String;
    .code stack 5 locals 4
L0:     new java/lang/StringBuilder
L3:     dup
L4:     invokespecial Method java/lang/StringBuilder <init> ()V
L7:     iconst_0
L8:     ldc "getPathFromClassLoader: searching for: "
L10:    invokevirtual Method java/lang/StringBuilder insert (ILjava/lang/String;)Ljava/lang/StringBuilder;
L13:    aload_0
L14:    invokevirtual Method java/lang/StringBuilder append (Ljava/lang/String;)Ljava/lang/StringBuilder;
L17:    invokevirtual Method java/lang/StringBuilder toString ()Ljava/lang/String;
L20:    invokestatic Method org/lwjgl/LWJGLUtil log (Ljava/lang/CharSequence;)V
L23:    aload_1
L24:    invokevirtual Method java/lang/Object getClass ()Ljava/lang/Class;
L27:    astore_2
L28:    aload_2
L29:    ifnull L124
L32:    aload_2
L33:    astore_3
        .catch java/security/PrivilegedActionException from L34 to L50 using L52
        .catch java/lang/Exception from L0 to L50 using L91
L34:    new org/lwjgl/L
L37:    dup
L38:    aload_3
L39:    aload_1
L40:    aload_0
L41:    invokespecial Method org/lwjgl/L <init> (Ljava/lang/Class;Ljava/lang/ClassLoader;Ljava/lang/String;)V
L44:    invokestatic Method java/security/AccessController doPrivileged (Ljava/security/PrivilegedExceptionAction;)Ljava/lang/Object;
L47:    checkcast java/lang/String
L50:    areturn
L51:    athrow
        .catch java/lang/Exception from L52 to L87 using L91
L52:    astore_3
L53:    new java/lang/StringBuilder
L56:    dup
L57:    invokespecial Method java/lang/StringBuilder <init> ()V
L60:    iconst_0
L61:    ldc "Failed to locate findLibrary method: "
L63:    invokevirtual Method java/lang/StringBuilder insert (ILjava/lang/String;)Ljava/lang/StringBuilder;
L66:    aload_3
L67:    invokevirtual Method java/security/PrivilegedActionException getCause ()Ljava/lang/Throwable;
L70:    invokevirtual Method java/lang/StringBuilder append (Ljava/lang/Object;)Ljava/lang/StringBuilder;
L73:    invokevirtual Method java/lang/StringBuilder toString ()Ljava/lang/String;
L76:    invokestatic Method org/lwjgl/LWJGLUtil log (Ljava/lang/CharSequence;)V
L79:    aload_2
L80:    invokevirtual Method java/lang/Class getSuperclass ()Ljava/lang/Class;
L83:    astore_2
L84:    goto L28
L87:    nop
L88:    nop
L89:    nop
L90:    athrow
L91:    astore_2
L92:    new java/lang/StringBuilder
L95:    dup
L96:    invokespecial Method java/lang/StringBuilder <init> ()V
L99:    iconst_0
L100:   ldc "Failure locating "
L102:   invokevirtual Method java/lang/StringBuilder insert (ILjava/lang/String;)Ljava/lang/StringBuilder;
L105:   aload_2
L106:   invokevirtual Method java/lang/StringBuilder append (Ljava/lang/Object;)Ljava/lang/StringBuilder;
L109:   ldc " using classloader:"
L111:   invokevirtual Method java/lang/StringBuilder append (Ljava/lang/String;)Ljava/lang/StringBuilder;
L114:   aload_2
L115:   invokevirtual Method java/lang/StringBuilder append (Ljava/lang/Object;)Ljava/lang/StringBuilder;
L118:   invokevirtual Method java/lang/StringBuilder toString ()Ljava/lang/String;
L121:   invokestatic Method org/lwjgl/LWJGLUtil log (Ljava/lang/CharSequence;)V
L124:   aconst_null
L125:   areturn
L126:   
        .attribute StackMap b'\x00\x06\x00\x1C\x00\x03\x07\x00\x45\x07\x00\xCF\x07\x00\xD1\x00\x00\x00\x33\x00\x00\x00\x01\x07\x00\x7B\x00\x34\x00\x04\x07\x00\x45\x07\x00\xCF\x07\x00\xD1\x07\x00\xD1\x00\x01\x07\x00\x5F\x00\x57\x00\x00\x00\x01\x07\x00\x7B\x00\x5B\x00\x02\x07\x00\x45\x07\x00\xCF\x00\x01\x07\x00\x5D\x00\x7C\x00\x03\x07\x00\x45\x07\x00\xCF\x07\x00\x04\x00\x00'
    .end code
.end method

.method static <clinit> : ()V
    .code stack 5 locals 1
L0:     ldc "linux"
L2:     putstatic Field org/lwjgl/LWJGLUtil PLATFORM_LINUX_NAME Ljava/lang/String;
L5:     ldc "macosx"
L7:     putstatic Field org/lwjgl/LWJGLUtil PLATFORM_MACOSX_NAME Ljava/lang/String;
L10:    ldc "windows"
L12:    putstatic Field org/lwjgl/LWJGLUtil PLATFORM_WINDOWS_NAME Ljava/lang/String;
L15:    ldc [_236]
L17:    putstatic Field org/lwjgl/LWJGLUtil LWJGL_ICON_DATA_16x16 Ljava/lang/String;
L20:    ldc [_240]
L22:    putstatic Field org/lwjgl/LWJGLUtil LWJGL_ICON_DATA_32x32 Ljava/lang/String;
L25:    ldc [_236]
L27:    invokestatic Method org/lwjgl/LWJGLUtil loadIcon (Ljava/lang/String;)Ljava/nio/ByteBuffer;
L30:    putstatic Field org/lwjgl/LWJGLUtil LWJGLIcon16x16 Ljava/nio/ByteBuffer;
L33:    ldc [_240]
L35:    invokestatic Method org/lwjgl/LWJGLUtil loadIcon (Ljava/lang/String;)Ljava/nio/ByteBuffer;
L38:    putstatic Field org/lwjgl/LWJGLUtil LWJGLIcon32x32 Ljava/nio/ByteBuffer;
L41:    ldc "org.lwjgl.util.Debug"
L43:    invokestatic Method org/lwjgl/LWJGLUtil getPrivilegedBoolean (Ljava/lang/String;)Z
L46:    putstatic Field org/lwjgl/LWJGLUtil DEBUG Z
L49:    ldc_w "org.lwjgl.util.NoChecks"
L52:    invokestatic Method org/lwjgl/LWJGLUtil getPrivilegedBoolean (Ljava/lang/String;)Z
L55:    ifne L66
L58:    iconst_1
L59:    dup
L60:    dup
L61:    pop2
L62:    goto L70
L65:    athrow
L66:    iconst_0
L67:    iconst_1
L68:    dup
L69:    pop2
L70:    putstatic Field org/lwjgl/LWJGLUtil CHECKS Z
L73:    ldc_w "os.name"
L76:    invokestatic Method org/lwjgl/LWJGLUtil getPrivilegedProperty (Ljava/lang/String;)Ljava/lang/String;
L79:    dup
L80:    astore_0
L81:    ldc_w "Windows"
L84:    invokevirtual Method java/lang/String startsWith (Ljava/lang/String;)Z
L87:    ifeq L99
L90:    iconst_3
L91:    iconst_1
L92:    dup
L93:    pop2
L94:    putstatic Field org/lwjgl/LWJGLUtil PLATFORM I
L97:    return
L98:    athrow
L99:    aload_0
L100:   ldc_w "Linux"
L103:   invokevirtual Method java/lang/String startsWith (Ljava/lang/String;)Z
L106:   ifne L139
L109:   aload_0
L110:   ldc_w "FreeBSD"
L113:   invokevirtual Method java/lang/String startsWith (Ljava/lang/String;)Z
L116:   ifne L139
L119:   aload_0
L120:   ldc_w "SunOS"
L123:   invokevirtual Method java/lang/String startsWith (Ljava/lang/String;)Z
L126:   ifne L139
L129:   aload_0
L130:   ldc_w "Unix"
L133:   invokevirtual Method java/lang/String startsWith (Ljava/lang/String;)Z
L136:   ifeq L147
L139:   iconst_1
L140:   dup
L141:   dup
L142:   pop2
L143:   putstatic Field org/lwjgl/LWJGLUtil PLATFORM I
L146:   return
L147:   aload_0
L148:   ldc_w "Mac OS X"
L151:   invokevirtual Method java/lang/String startsWith (Ljava/lang/String;)Z
L154:   ifne L167
L157:   aload_0
L158:   ldc_w "Darwin"
L161:   invokevirtual Method java/lang/String startsWith (Ljava/lang/String;)Z
L164:   ifeq L175
L167:   iconst_2
L168:   iconst_1
L169:   dup
L170:   pop2
L171:   putstatic Field org/lwjgl/LWJGLUtil PLATFORM I
L174:   return
L175:   new java/lang/LinkageError
L178:   dup
L179:   new java/lang/StringBuilder
L182:   dup
L183:   invokespecial Method java/lang/StringBuilder <init> ()V
L186:   iconst_0
L187:   ldc_w "Unknown platform: "
L190:   invokevirtual Method java/lang/StringBuilder insert (ILjava/lang/String;)Ljava/lang/StringBuilder;
L193:   aload_0
L194:   invokevirtual Method java/lang/StringBuilder append (Ljava/lang/String;)Ljava/lang/StringBuilder;
L197:   invokevirtual Method java/lang/StringBuilder toString ()Ljava/lang/String;
L200:   invokespecial Method java/lang/LinkageError <init> (Ljava/lang/String;)V
L203:   athrow
L204:   athrow
L205:   
        .attribute StackMap b'\x00\x0A\x00\x41\x00\x00\x00\x01\x07\x00\x7B\x00\x42\x00\x00\x00\x00\x00\x46\x00\x00\x00\x01\x01\x00\x62\x00\x00\x00\x01\x07\x00\x7B\x00\x63\x00\x01\x07\x00\x45\x00\x00\x00\x8B\x00\x01\x07\x00\x45\x00\x00\x00\x93\x00\x01\x07\x00\x45\x00\x00\x00\xA7\x00\x01\x07\x00\x45\x00\x00\x00\xAF\x00\x01\x07\x00\x45\x00\x00\x00\xCC\x00\x00\x00\x01\x07\x00\x7B'
    .end code
.end method

.method private static loadIcon : (Ljava/lang/String;)Ljava/nio/ByteBuffer;
    .code stack 4 locals 4
L0:     aload_0
L1:     invokevirtual Method java/lang/String length ()I
L4:     dup
L5:     istore_1
L6:     invokestatic Method org/lwjgl/BufferUtils createByteBuffer (I)Ljava/nio/ByteBuffer;
L9:     astore_2
L10:    iconst_0
L11:    iconst_1
L12:    dup
L13:    pop2
L14:    dup
L15:    istore_3
L16:    iload_1
L17:    if_icmpge L40
L20:    aload_2
L21:    aload_0
L22:    iload_3
L23:    dup_x1
L24:    iinc 3 1
L27:    invokevirtual Method java/lang/String charAt (I)C
L30:    i2b
L31:    invokevirtual Method java/nio/ByteBuffer put (IB)Ljava/nio/ByteBuffer;
L34:    pop
L35:    iload_3
L36:    goto L16
L39:    athrow
L40:    aload_2
L41:    invokevirtual Method java/nio/ByteBuffer asReadOnlyBuffer ()Ljava/nio/ByteBuffer;
L44:    areturn
L45:    
        .attribute StackMap b'\x00\x03\x00\x10\x00\x04\x07\x00\x45\x01\x07\x01\x25\x01\x00\x01\x01\x00\x27\x00\x00\x00\x01\x07\x00\x7B\x00\x28\x00\x04\x07\x00\x45\x01\x07\x01\x25\x01\x00\x00'
    .end code
.end method

.method public static getClassTokens : (Lorg/lwjgl/m;Ljava/util/Map;Ljava/lang/Iterable;)Ljava/util/Map;
    .code stack 4 locals 8
L0:     aload_1
L1:     ifnonnull L12
L4:     new java/util/HashMap
L7:     dup
L8:     invokespecial Method java/util/HashMap <init> ()V
L11:    astore_1
L12:    bipush 25
L14:    iconst_1
L15:    dup
L16:    pop2
L17:    istore_3
L18:    aload_2
L19:    invokeinterface InterfaceMethod java/lang/Iterable iterator ()Ljava/util/Iterator; 1
L24:    astore_2
L25:    aload_2
L26:    invokeinterface InterfaceMethod java/util/Iterator hasNext ()Z 1
L31:    ifeq L195
L34:    aload_2
L35:    invokeinterface InterfaceMethod java/util/Iterator next ()Ljava/lang/Object; 1
L40:    checkcast java/lang/Class
L43:    invokevirtual Method java/lang/Class getDeclaredFields ()[Ljava/lang/reflect/Field;
L46:    dup
L47:    astore_3
L48:    arraylength
L49:    istore 4
L51:    iconst_0
L52:    iconst_1
L53:    dup
L54:    pop2
L55:    dup
L56:    istore 5
L58:    iload 4
L60:    if_icmpge L25
L63:    aload_3
L64:    iload 5
L66:    aaload
L67:    dup
L68:    astore 6
L70:    invokevirtual Method java/lang/reflect/Field getModifiers ()I
L73:    bipush 25
L75:    iconst_1
L76:    dup
L77:    pop2
L78:    iand
L79:    bipush 25
L81:    iconst_1
L82:    dup
L83:    pop2
L84:    if_icmpne L184
L87:    aload 6
L89:    invokevirtual Method java/lang/reflect/Field getType ()Ljava/lang/Class;
L92:    getstatic Field java/lang/Integer TYPE Ljava/lang/Class;
L95:    if_acmpne L184
        .catch java/lang/IllegalAccessException from L98 to L123 using L182
L98:    aload 6
L100:   aconst_null
L101:   invokevirtual Method java/lang/reflect/Field getInt (Ljava/lang/Object;)I
L104:   istore 7
L106:   aload_0
L107:   ifnull L127
L110:   aload_0
L111:   aload 6
L113:   iload 7
L115:   invokeinterface InterfaceMethod org/lwjgl/m break (Ljava/lang/reflect/Field;I)Z 3
L120:   ifne L127
L123:   goto L184
L126:   athrow
        .catch java/lang/IllegalAccessException from L127 to L161 using L182
L127:   aload_1
L128:   iload 7
L130:   invokestatic Method java/lang/Integer valueOf (I)Ljava/lang/Integer;
L133:   invokeinterface InterfaceMethod java/util/Map containsKey (Ljava/lang/Object;)Z 2
L138:   ifeq L162
L141:   aload_1
L142:   iload 7
L144:   invokestatic Method java/lang/Integer valueOf (I)Ljava/lang/Integer;
L147:   iload 7
L149:   invokestatic Method org/lwjgl/LWJGLUtil toHexString (I)Ljava/lang/String;
L152:   invokeinterface InterfaceMethod java/util/Map put (Ljava/lang/Object;Ljava/lang/Object;)Ljava/lang/Object; 3
L157:   pop
L158:   goto L184
L161:   athrow
        .catch java/lang/IllegalAccessException from L162 to L179 using L182
L162:   aload_1
L163:   iload 7
L165:   invokestatic Method java/lang/Integer valueOf (I)Ljava/lang/Integer;
L168:   aload 6
L170:   invokevirtual Method java/lang/reflect/Field getName ()Ljava/lang/String;
L173:   invokeinterface InterfaceMethod java/util/Map put (Ljava/lang/Object;Ljava/lang/Object;)Ljava/lang/Object; 3
L178:   pop
L179:   goto L184
L182:   astore 7
L184:   iinc 5 1
L187:   iload 5
L189:   goto L58
L192:   nop
L193:   nop
L194:   athrow
L195:   aload_1
L196:   areturn
L197:   
        .attribute StackMap b'\x00\x0B\x00\x0C\x00\x03\x07\x00\x12\x07\x01\x38\x07\x01\x3A\x00\x00\x00\x19\x00\x03\x07\x00\x12\x07\x01\x38\x07\x01\x40\x00\x00\x00\x3A\x00\x06\x07\x00\x12\x07\x01\x38\x07\x01\x40\x07\x01\x4D\x01\x01\x00\x01\x01\x00\x7E\x00\x00\x00\x01\x07\x00\x7B\x00\x7F\x00\x08\x07\x00\x12\x07\x01\x38\x07\x01\x40\x07\x01\x4D\x01\x01\x07\x01\x4F\x01\x00\x00\x00\xA1\x00\x00\x00\x01\x07\x00\x7B\x00\xA2\x00\x08\x07\x00\x12\x07\x01\x38\x07\x01\x40\x07\x01\x4D\x01\x01\x07\x01\x4F\x01\x00\x00\x00\xB6\x00\x07\x07\x00\x12\x07\x01\x38\x07\x01\x40\x07\x01\x4D\x01\x01\x07\x01\x4F\x00\x01\x07\x01\x33\x00\xB8\x00\x07\x07\x00\x12\x07\x01\x38\x07\x01\x40\x07\x01\x4D\x01\x01\x07\x01\x4F\x00\x00\x00\xC0\x00\x00\x00\x01\x07\x00\x7B\x00\xC3\x00\x03\x07\x00\x12\x07\x01\x38\x07\x01\x40\x00\x00'
    .end code
.end method

.method public static getPlatformName : ()Ljava/lang/String;
    .code stack 2 locals 0
L0:     invokestatic Method org/lwjgl/LWJGLUtil getPlatform ()I
L3:     tableswitch 1
            L28
            L36
            L40
            default : L43
L28:    ldc "linux"
L30:    iconst_0
L31:    ifne L30
L34:    areturn
L35:    athrow
L36:    ldc "macosx"
L38:    areturn
L39:    athrow
L40:    ldc "windows"
L42:    areturn
L43:    ldc_w "unknown"
L46:    areturn
L47:    
        .attribute StackMap b'\x00\x07\x00\x1C\x00\x00\x00\x00\x00\x1E\x00\x00\x00\x01\x07\x00\x45\x00\x23\x00\x00\x00\x01\x07\x00\x7B\x00\x24\x00\x00\x00\x00\x00\x27\x00\x00\x00\x01\x07\x00\x7B\x00\x28\x00\x00\x00\x00\x00\x2B\x00\x00\x00\x00'
    .end code
.end method

.method public static getLibraryPaths : (Ljava/lang/String;[Ljava/lang/String;Ljava/lang/ClassLoader;)[Ljava/lang/String;
    .code stack 6 locals 9
L0:     new java/util/ArrayList
L3:     dup
L4:     invokespecial Method java/util/ArrayList <init> ()V
L7:     astore_3
L8:     aload_0
L9:     aload_2
L10:    invokestatic Method org/lwjgl/LWJGLUtil getPathFromClassLoader (Ljava/lang/String;Ljava/lang/ClassLoader;)Ljava/lang/String;
L13:    dup
L14:    astore 4
L16:    ifnull L53
L19:    new java/lang/StringBuilder
L22:    dup
L23:    invokespecial Method java/lang/StringBuilder <init> ()V
L26:    iconst_0
L27:    ldc_w "getPathFromClassLoader: Path found: "
L30:    invokevirtual Method java/lang/StringBuilder insert (ILjava/lang/String;)Ljava/lang/StringBuilder;
L33:    aload 4
L35:    invokevirtual Method java/lang/StringBuilder append (Ljava/lang/String;)Ljava/lang/StringBuilder;
L38:    invokevirtual Method java/lang/StringBuilder toString ()Ljava/lang/String;
L41:    invokestatic Method org/lwjgl/LWJGLUtil log (Ljava/lang/CharSequence;)V
L44:    aload_3
L45:    aload 4
L47:    invokeinterface InterfaceMethod java/util/List add (Ljava/lang/Object;)Z 2
L52:    pop
L53:    aload_1
L54:    dup
L55:    astore_1
L56:    arraylength
L57:    istore 4
L59:    iconst_0
L60:    iconst_1
L61:    dup
L62:    pop2
L63:    dup
L64:    istore 5
L66:    iload 4
L68:    if_icmpge L351
L71:    aload_1
L72:    iload 5
L74:    aaload
L75:    astore 6
L77:    ldc_w "lwjgl"
L80:    aload_2
L81:    invokestatic Method org/lwjgl/LWJGLUtil getPathFromClassLoader (Ljava/lang/String;Ljava/lang/ClassLoader;)Ljava/lang/String;
L84:    dup
L85:    astore 7
L87:    ifnull L165
L90:    new java/lang/StringBuilder
L93:    dup
L94:    invokespecial Method java/lang/StringBuilder <init> ()V
L97:    iconst_0
L98:    ldc_w "getPathFromClassLoader: Path found: "
L101:   invokevirtual Method java/lang/StringBuilder insert (ILjava/lang/String;)Ljava/lang/StringBuilder;
L104:   aload 7
L106:   invokevirtual Method java/lang/StringBuilder append (Ljava/lang/String;)Ljava/lang/StringBuilder;
L109:   invokevirtual Method java/lang/StringBuilder toString ()Ljava/lang/String;
L112:   invokestatic Method org/lwjgl/LWJGLUtil log (Ljava/lang/CharSequence;)V
L115:   new java/lang/StringBuilder
L118:   aload_3
L119:   dup_x1
L120:   dup
L121:   pop2
L122:   dup
L123:   invokespecial Method java/lang/StringBuilder <init> ()V
L126:   iconst_0
L127:   iconst_1
L128:   dup
L129:   pop2
L130:   aload 7
L132:   dup_x1
L133:   getstatic Field java/io/File separator Ljava/lang/String;
L136:   invokevirtual Method java/lang/String lastIndexOf (Ljava/lang/String;)I
L139:   invokevirtual Method java/lang/String substring (II)Ljava/lang/String;
L142:   invokevirtual Method java/lang/StringBuilder append (Ljava/lang/String;)Ljava/lang/StringBuilder;
L145:   getstatic Field java/io/File separator Ljava/lang/String;
L148:   invokevirtual Method java/lang/StringBuilder append (Ljava/lang/String;)Ljava/lang/StringBuilder;
L151:   aload 6
L153:   invokevirtual Method java/lang/StringBuilder append (Ljava/lang/String;)Ljava/lang/StringBuilder;
L156:   invokevirtual Method java/lang/StringBuilder toString ()Ljava/lang/String;
L159:   invokeinterface InterfaceMethod java/util/List add (Ljava/lang/Object;)Z 2
L164:   pop
L165:   ldc_w "org.lwjgl.librarypath"
L168:   invokestatic Method org/lwjgl/LWJGLUtil getPrivilegedProperty (Ljava/lang/String;)Ljava/lang/String;
L171:   dup
L172:   astore 7
L174:   ifnull L213
L177:   new java/lang/StringBuilder
L180:   aload_3
L181:   dup_x1
L182:   dup
L183:   pop2
L184:   dup
L185:   invokespecial Method java/lang/StringBuilder <init> ()V
L188:   aload 7
L190:   invokevirtual Method java/lang/StringBuilder append (Ljava/lang/String;)Ljava/lang/StringBuilder;
L193:   getstatic Field java/io/File separator Ljava/lang/String;
L196:   invokevirtual Method java/lang/StringBuilder append (Ljava/lang/String;)Ljava/lang/StringBuilder;
L199:   aload 6
L201:   invokevirtual Method java/lang/StringBuilder append (Ljava/lang/String;)Ljava/lang/StringBuilder;
L204:   invokevirtual Method java/lang/StringBuilder toString ()Ljava/lang/String;
L207:   invokeinterface InterfaceMethod java/util/List add (Ljava/lang/Object;)Z 2
L212:   pop
L213:   ldc_w "java.library.path"
L216:   invokestatic Method org/lwjgl/LWJGLUtil getPrivilegedProperty (Ljava/lang/String;)Ljava/lang/String;
L219:   astore 7
L221:   new java/util/StringTokenizer
L224:   dup
L225:   aload 7
L227:   getstatic Field java/io/File pathSeparator Ljava/lang/String;
L230:   invokespecial Method java/util/StringTokenizer <init> (Ljava/lang/String;Ljava/lang/String;)V
L233:   dup
L234:   astore 7
L236:   invokevirtual Method java/util/StringTokenizer hasMoreTokens ()Z
L239:   ifeq L290
L242:   aload 7
L244:   dup
L245:   invokevirtual Method java/util/StringTokenizer nextToken ()Ljava/lang/String;
L248:   astore 8
L250:   new java/lang/StringBuilder
L253:   aload_3
L254:   dup_x1
L255:   dup
L256:   pop2
L257:   dup
L258:   invokespecial Method java/lang/StringBuilder <init> ()V
L261:   aload 8
L263:   invokevirtual Method java/lang/StringBuilder append (Ljava/lang/String;)Ljava/lang/StringBuilder;
L266:   getstatic Field java/io/File separator Ljava/lang/String;
L269:   invokevirtual Method java/lang/StringBuilder append (Ljava/lang/String;)Ljava/lang/StringBuilder;
L272:   aload 6
L274:   invokevirtual Method java/lang/StringBuilder append (Ljava/lang/String;)Ljava/lang/StringBuilder;
L277:   invokevirtual Method java/lang/StringBuilder toString ()Ljava/lang/String;
L280:   invokeinterface InterfaceMethod java/util/List add (Ljava/lang/Object;)Z 2
L285:   pop
L286:   goto L236
L289:   athrow
L290:   ldc_w "user.dir"
L293:   invokestatic Method org/lwjgl/LWJGLUtil getPrivilegedProperty (Ljava/lang/String;)Ljava/lang/String;
L296:   astore 8
L298:   new java/lang/StringBuilder
L301:   aload_3
L302:   dup_x1
L303:   dup
L304:   pop2
L305:   dup
L306:   invokespecial Method java/lang/StringBuilder <init> ()V
L309:   aload 8
L311:   invokevirtual Method java/lang/StringBuilder append (Ljava/lang/String;)Ljava/lang/StringBuilder;
L314:   getstatic Field java/io/File separator Ljava/lang/String;
L317:   invokevirtual Method java/lang/StringBuilder append (Ljava/lang/String;)Ljava/lang/StringBuilder;
L320:   aload 6
L322:   invokevirtual Method java/lang/StringBuilder append (Ljava/lang/String;)Ljava/lang/StringBuilder;
L325:   invokevirtual Method java/lang/StringBuilder toString ()Ljava/lang/String;
L328:   invokeinterface InterfaceMethod java/util/List add (Ljava/lang/Object;)Z 2
L333:   iinc 5 1
L336:   aload_3
L337:   aload 6
L339:   invokeinterface InterfaceMethod java/util/List add (Ljava/lang/Object;)Z 2
L344:   pop2
L345:   iload 5
L347:   goto L66
L350:   athrow
L351:   aload_3
L352:   dup
L353:   invokeinterface InterfaceMethod java/util/List size ()I 1
L358:   anewarray java/lang/String
L361:   iconst_1
L362:   dup
L363:   pop2
L364:   invokeinterface InterfaceMethod java/util/List toArray ([Ljava/lang/Object;)[Ljava/lang/Object; 2
L369:   checkcast [Ljava/lang/String;
L372:   areturn
L373:   
        .attribute StackMap b'\x00\x09\x00\x35\x00\x05\x07\x00\x45\x07\x00\x7D\x07\x00\xCF\x07\x01\x79\x07\x00\x45\x00\x00\x00\x42\x00\x06\x07\x00\x45\x07\x00\x7D\x07\x00\xCF\x07\x01\x79\x01\x01\x00\x01\x01\x00\xA5\x00\x08\x07\x00\x45\x07\x00\x7D\x07\x00\xCF\x07\x01\x79\x01\x01\x07\x00\x45\x07\x00\x45\x00\x00\x00\xD5\x00\x08\x07\x00\x45\x07\x00\x7D\x07\x00\xCF\x07\x01\x79\x01\x01\x07\x00\x45\x07\x00\x45\x00\x00\x00\xEC\x00\x08\x07\x00\x45\x07\x00\x7D\x07\x00\xCF\x07\x01\x79\x01\x01\x07\x00\x45\x07\x00\x8B\x00\x01\x07\x00\x8B\x01\x21\x00\x00\x00\x01\x07\x00\x7B\x01\x22\x00\x08\x07\x00\x45\x07\x00\x7D\x07\x00\xCF\x07\x01\x79\x01\x01\x07\x00\x45\x07\x00\x8B\x00\x00\x01\x5E\x00\x00\x00\x01\x07\x00\x7B\x01\x5F\x00\x06\x07\x00\x45\x07\x00\x7D\x07\x00\xCF\x07\x01\x79\x01\x01\x00\x00'
    .end code
.end method

.method private static getPrivilegedProperty : (Ljava/lang/String;)Ljava/lang/String;
    .code stack 3 locals 1
L0:     new org/lwjgl/J
L3:     dup
L4:     aload_0
L5:     invokespecial Method org/lwjgl/J <init> (Ljava/lang/String;)V
L8:     invokestatic Method java/security/AccessController doPrivileged (Ljava/security/PrivilegedAction;)Ljava/lang/Object;
L11:    checkcast java/lang/String
L14:    areturn
L15:    
    .end code
.end method

.method public static getLibraryPaths : (Ljava/lang/String;Ljava/lang/String;Ljava/lang/ClassLoader;)[Ljava/lang/String;
    .code stack 6 locals 3
L0:     aload_0
L1:     iconst_1
L2:     dup
L3:     dup
L4:     pop2
L5:     anewarray java/lang/String
L8:     iconst_1
L9:     dup
L10:    pop2
L11:    dup
L12:    iconst_0
L13:    iconst_1
L14:    dup
L15:    pop2
L16:    aload_1
L17:    aastore
L18:    aload_2
L19:    invokestatic Method org/lwjgl/LWJGLUtil getLibraryPaths (Ljava/lang/String;[Ljava/lang/String;Ljava/lang/ClassLoader;)[Ljava/lang/String;
L22:    areturn
L23:    
    .end code
.end method
.innerclasses
    org/lwjgl/A [0] [0] static
    org/lwjgl/J [0] [0] static
    org/lwjgl/L [0] [0] static
    org/lwjgl/a [0] [0] static
    org/lwjgl/b [0] [0] static
    org/lwjgl/g [0] [0] static
    org/lwjgl/m org/lwjgl/LWJGLUtil [0] public static interface abstract
.end innerclasses
.const [_236] = String [_235]
.const [_240] = String [_239]
.const [_235] = Utf8 "\u00FF\u00FF\u00FF\u00FF\u00FF\u00FF\u00FF\u00FF\u00FF\u00FF\u00FF\u00FF\u00FF\u00FF\u00FF\u00FF\u00FF\u00FF\u00FF\u00FF\u00FF\u00FF\u00FF\u00FF\u00FE\u00FF\u00FF\u00FF\u00C2\u00D7\u00E8\u00FFt\u00A4\u00CB\u00FFP\u008B\u00BD\u00FFT\u008E\u00BF\u00FF\u0086\u00AF\u00D2\u00FF\u00E7\u00EF\u00F6\u00FF\u00FF\u00FF\u00FF\u00FF\u00FF\u00FF\u00FF\u00FF\u00FF\u00FF\u00FF\u00FF\u00FF\u00FF\u00FF\u00FF\u00FF\u00FF\u00FF\u00FF\u00FF\u00FF\u00FF\u00FF\u00FF\u00FF\u00FF\u00FF\u00FF\u00FF\u00FF\u00FF\u00F5\u00F5\u00F5\u00FF\u008D\u008F\u0091\u00FFv\u0082\u008D\u00FF}\u008D\u009B\u00FF\u0084\u0099\u00AA\u00FF\u0094\u00B7\u00D5\u00FF:}\u00B5\u00FFH\u0086\u00BA\u00FF\u00DA\u00E7\u00F1\u00FF\u00FF\u00FF\u00FF\u00FF\u00FF\u00FF\u00FF\u00FF\u00FF\u00FF\u00FF\u00FF\u00FF\u00FF\u00FF\u00FF\u00FF\u00FF\u00FF\u00FF\u00FF\u00FF\u00FF\u00FF\u00F4\u00F8\u00FB\u00FF\u009C\u009E\u00A0\u00FF\u0000\u0000\u0000\u00FF\u0000\u0000\u0000\u00FF\u0000\u0000\u0000\u00FF\u0000\u0000\u0000\u00FF\u00E4\u00E4\u00E4\u00FF\u0084\u00AD\u00D0\u00FF:}\u00B5\u00FF[\u0092\u00C1\u00FF\u00FC\u00FD\u00FE\u00FF\u00FF\u00FF\u00FF\u00FF\u00FF\u00FF\u00FF\u00FF\u00FF\u00FF\u00FF\u00FF\u00FF\u00FF\u00FF\u00FF\u00FF\u00FF\u00FF\u00FF\u0091\u00B6\u00D5\u00FF___\u00FF\u0000\u0000\u0000\u00FF\u0000\u0000\u0000\u00FF\u0000\u0000\u0000\u00FF\"\"\"\u00FF\u00FF\u00FF\u00FF\u00FF\u00E8\u00F0\u00F6\u00FF9|\u00B5\u00FF:}\u00B5\u00FF\u00C4\u00D8\u00E9\u00FF\u00FF\u00FF\u00FF\u00FF\u00FF\u00FF\u00FF\u00FF\u00FF\u00FF\u00FF\u00FF\u00FF\u00FF\u00FF\u00FF\u00C6\u00D9\u00E9\u00FF\u0081\u00AB\u00CE\u00FF\u001D\u001D\u001D\u00FF\u0000\u0000\u0000\u00FF\u0000\u0000\u0000\u00FF\u0000\u0000\u0000\u00FFfff\u00FF\u00FF\u00FF\u00FF\u00FF\u00D0\u00E0\u00ED\u00FF:}\u00B5\u00FF:}\u00B5\u00FF\u008D\u00B4\u00D4\u00FF\u00FF\u00FF\u00FF\u00FF\u00F2\u00F2\u00F2\u00FF\u00A5\u00A5\u00A5\u00FF\u00DF\u00DF\u00DF\u00FF\u00A2\u00C1\u00DC\u00FF\u00B0\u00C5\u00D6\u00FF\u000A\u000A\u000A\u00FF\u0000\u0000\u0000\u00FF\u0000\u0000\u0000\u00FF\u0000\u0000\u0000\u00FF\u00A8\u00A8\u00A8\u00FF\u00FF\u00FF\u00FF\u00FF\u0097\u00BA\u00D8\u00FF:}\u00B5\u00FF:}\u00B5\u00FFq\u00A1\u00CA\u00FF\u00FF\u00FF\u00FF\u00FF\u00A1\u00A1\u00A1\u00FF\u0000\u0000\u0000\u00FF\u0001\u0001\u0001\u00FF###\u00FF\u00CC\u00CC\u00CC\u00FF\u00D0\u00D0\u00D0\u00FF\u00A5\u00A5\u00A5\u00FF\u0084\u0084\u0084\u00FF\\\\\\\u00FF\u00EF\u00EF\u00EF\u00FF\u00FF\u00FF\u00FF\u00FF`\u0096\u00C3\u00FF:}\u00B5\u00FF:}\u00B5\u00FFm\u009E\u00C8\u00FF\u00FF\u00FF\u00FF\u00FF^^^\u00FF\u0000\u0000\u0000\u00FF\u0000\u0000\u0000\u00FF\u0000\u0000\u0000\u00FF\u00CF\u00CF\u00CF\u00FF\u001F\u001F\u001F\u00FF\u0003\u0003\u0003\u00FF+++\u00FFlll\u00FF\u00C6\u00C6\u00C6\u00FF\u00FA\u00FC\u00FD\u00FF\u009E\u00BF\u00DA\u00FFw\u00A5\u00CC\u00FFL\u0089\u00BC\u00FF|\u00A8\u00CE\u00FF\u00FF\u00FF\u00FF\u00FF\u001B\u001B\u001B\u00FF\u0000\u0000\u0000\u00FF\u0000\u0000\u0000\u00FF\u0017\u0017\u0017\u00FF\u00D6\u00D6\u00D6\u00FF\u0001\u0001\u0001\u00FF\u0000\u0000\u0000\u00FF\u0000\u0000\u0000\u00FF\u0000\u0000\u0000\u00FFRRR\u00FF\u00E5\u00E5\u00E5\u00FF===\u00FFhhh\u00FF\u00A6\u00A6\u00A7\u00FF\u00DA\u00DE\u00E1\u00FF\u00FF\u00FF\u00FF\u00FFttt\u00FF\u000E\u000E\u000E\u00FF\u0000\u0000\u0000\u00FFYYY\u00FF\u0095\u0095\u0095\u00FF\u0000\u0000\u0000\u00FF\u0000\u0000\u0000\u00FF\u0000\u0000\u0000\u00FF\u0000\u0000\u0000\u00FF\u0091\u0091\u0091\u00FF\u009B\u009B\u009B\u00FF\u0000\u0000\u0000\u00FF\u0000\u0000\u0000\u00FF\u0000\u0000\u0000\u00FF\u0002\u0002\u0002\u00FFCCC\u00FF\u00FF\u00FF\u00FF\u00FF\u00EE\u00EE\u00EE\u00FF\u008C\u008C\u008C\u00FF\u00BF\u00BF\u00BF\u00FFVVV\u00FF\u0000\u0000\u0000\u00FF\u0000\u0000\u0000\u00FF\u0000\u0000\u0000\u00FF\u0000\u0000\u0000\u00FF\u00D3\u00D3\u00D3\u00FFXXX\u00FF\u0000\u0000\u0000\u00FF\u0000\u0000\u0000\u00FF\u0000\u0000\u0000\u00FF\u0000\u0000\u0000\u00FF333\u00FF\u00FF\u00FF\u00FF\u00FF\u00FF\u00FF\u00FF\u00FF\u00FC\u00FD\u00FE\u00FF\u00FF\u00FF\u00FF\u00FF\u00C0\u00C0\u00C0\u00FF@@@\u00FF\u0002\u0002\u0002\u00FF\u0000\u0000\u0000\u00FF\u001B\u001B\u001B\u00FF\u00FB\u00FB\u00FB\u00FF\u0017\u0017\u0017\u00FF\u0000\u0000\u0000\u00FF\u0000\u0000\u0000\u00FF\u0000\u0000\u0000\u00FF\u0000\u0000\u0000\u00FFxxx\u00FF\u00FF\u00FF\u00FF\u00FF\u00FF\u00FF\u00FF\u00FF\u00D2\u00E1\u00EE\u00FF~\u00A9\u00CE\u00FF\u00E0\u00EA\u00F3\u00FF\u00FF\u00FF\u00FF\u00FF\u00D4\u00D4\u00D4\u00FFmmm\u00FF\u0084\u0084\u0084\u00FF\u00D3\u00D3\u00D3\u00FF\u0000\u0000\u0000\u00FF\u0000\u0000\u0000\u00FF\u0000\u0000\u0000\u00FF\u0000\u0000\u0000\u00FF\u0000\u0000\u0000\u00FF\u00BD\u00BD\u00BD\u00FF\u00FF\u00FF\u00FF\u00FF\u00FF\u00FF\u00FF\u00FF\u00FE\u00FE\u00FE\u00FFf\u009A\u00C5\u00FF=\u007F\u00B6\u00FF\u0082\u00AC\u00D0\u00FF\u00E4\u00ED\u00F5\u00FF\u00FF\u00FF\u00FF\u00FF\u00FF\u00FF\u00FF\u00FF\u00E5\u00E5\u00E5\u00FF---\u00FF\u0000\u0000\u0000\u00FF\u0000\u0000\u0000\u00FF\u0000\u0000\u0000\u00FF\u000C\u000C\u000C\u00FF\u00F6\u00F6\u00F6\u00FF\u00FF\u00FF\u00FF\u00FF\u00FF\u00FF\u00FF\u00FF\u00FF\u00FF\u00FF\u00FF\u00E2\u00EC\u00F4\u00FFM\u0089\u00BC\u00FF:}\u00B5\u00FF>\u0080\u00B6\u00FF\u0087\u00B0\u00D2\u00FF\u00E7\u00EF\u00F6\u00FF\u00FF\u00FF\u00FF\u00FF\u00FE\u00FE\u00FE\u00FF\u00BC\u00BC\u00BC\u00FFOOO\u00FF\u0003\u0003\u0003\u00FFJJJ\u00FF\u00FF\u00FF\u00FF\u00FF\u00FF\u00FF\u00FF\u00FF\u00FF\u00FF\u00FF\u00FF\u00FF\u00FF\u00FF\u00FF\u00FF\u00FF\u00FF\u00FF\u00EB\u00F2\u00F8\u00FF\u008C\u00B3\u00D4\u00FFV\u0090\u00C0\u00FFP\u008C\u00BD\u00FFw\u00A5\u00CC\u00FF\u00ED\u00F3\u00F8\u00FF\u00FF\u00FF\u00FF\u00FF\u00FF\u00FF\u00FF\u00FF\u00FF\u00FF\u00FF\u00FF\u00DF\u00DF\u00DF\u00FF\u00E6\u00E6\u00E6\u00FF\u00FF\u00FF\u00FF\u00FF"
.const [_239] = Utf8 "\u00FF\u00FF\u00FF\u00FF\u00FF\u00FF\u00FF\u00FF\u00FF\u00FF\u00FF\u00FF\u00FF\u00FF\u00FF\u00FF\u00FF\u00FF\u00FF\u00FF\u00FF\u00FF\u00FF\u00FF\u00FF\u00FF\u00FF\u00FF\u00FF\u00FF\u00FF\u00FF\u00FF\u00FF\u00FF\u00FF\u00FF\u00FF\u00FF\u00FF\u00FF\u00FF\u00FF\u00FF\u00FF\u00FF\u00FF\u00FF\u00FF\u00FF\u00FF\u00FF\u00FF\u00FF\u00FF\u00FF\u00FF\u00FF\u00FF\u00FF\u00FA\u00FC\u00FD\u00FF\u00CB\u00DD\u00EC\u00FF\u0093\u00B7\u00D6\u00FFo\u00A0\u00C9\u00FF\\\u0093\u00C2\u00FF`\u0096\u00C3\u00FFz\u00A7\u00CD\u00FF\u00AC\u00C8\u00E0\u00FF\u00ED\u00F3\u00F8\u00FF\u00FF\u00FF\u00FF\u00FF\u00FF\u00FF\u00FF\u00FF\u00FF\u00FF\u00FF\u00FF\u00FF\u00FF\u00FF\u00FF\u00FF\u00FF\u00FF\u00FF\u00FF\u00FF\u00FF\u00FF\u00FF\u00FF\u00FF\u00FF\u00FF\u00FF\u00FF\u00FF\u00FF\u00FF\u00FF\u00FF\u00FF\u00FF\u00FF\u00FF\u00FF\u00FF\u00FF\u00FF\u00FF\u00FF\u00FF\u00FF\u00FF\u00FF\u00FF\u00FF\u00FF\u00FF\u00FF\u00FF\u00FF\u00FF\u00FF\u00FF\u00FF\u00FF\u00FF\u00FF\u00FF\u00FF\u00FF\u00FF\u00FF\u00FF\u00FF\u00FF\u00FF\u00FF\u00FF\u00FF\u00FF\u00FF\u00FF\u00FF\u00FF\u00FF\u00FF\u00FF\u00FC\u00FD\u00FE\u00FF\u00B5\u00CE\u00E3\u00FFZ\u0092\u00C1\u00FF:}\u00B5\u00FF:}\u00B5\u00FF:}\u00B5\u00FF:}\u00B5\u00FF:}\u00B5\u00FF:}\u00B5\u00FF:}\u00B5\u00FFE\u0085\u00B9\u00FF\u00A1\u00C1\u00DC\u00FF\u00FC\u00FD\u00FE\u00FF\u00FF\u00FF\u00FF\u00FF\u00FF\u00FF\u00FF\u00FF\u00FF\u00FF\u00FF\u00FF\u00FF\u00FF\u00FF\u00FF\u00FF\u00FF\u00FF\u00FF\u00FF\u00FF\u00FF\u00FF\u00FF\u00FF\u00FF\u00FF\u00FF\u00FF\u00FF\u00FF\u00FF\u00FF\u00FF\u00FF\u00FF\u00FF\u00FF\u00FF\u00FF\u00FF\u00FF\u00FF\u00FF\u00FF\u00FF\u00FF\u00FF\u00FF\u00FF\u00FF\u00FF\u00FF\u00FF\u00FF\u00FF\u00FF\u00FF\u00FF\u00FF\u00FF\u00FF\u00FF\u00FF\u00FF\u00FF\u00FF\u00FF\u00FF\u00FF\u00FF\u00FC\u00FC\u00FC\u00FF\u00E2\u00EA\u00F1\u00FF\u00B8\u00CF\u00E3\u00FF\u00AE\u00C9\u00E0\u00FF\u00A3\u00C2\u00DC\u00FF\u0098\u00BA\u00D8\u00FF\u008C\u00B3\u00D3\u00FF\u0081\u00AC\u00CF\u00FFn\u009F\u00C8\u00FF=\u007F\u00B6\u00FF:}\u00B5\u00FF:}\u00B5\u00FF:}\u00B5\u00FFr\u00A2\u00CA\u00FF\u00F5\u00F8\u00FB\u00FF\u00FF\u00FF\u00FF\u00FF\u00FF\u00FF\u00FF\u00FF\u00FF\u00FF\u00FF\u00FF\u00FF\u00FF\u00FF\u00FF\u00FF\u00FF\u00FF\u00FF\u00FF\u00FF\u00FF\u00FF\u00FF\u00FF\u00FF\u00FF\u00FF\u00FF\u00FF\u00FF\u00FF\u00FF\u00FF\u00FF\u00FF\u00FF\u00FF\u00FF\u00FF\u00FF\u00FF\u00FF\u00FF\u00FF\u00FF\u00FF\u00FF\u00FF\u00FF\u00FF\u00FF\u00FF\u00FF\u00FF\u00FF\u00FF\u00FF\u00FF\u00FF\u00FF\u00FF\u00FF\u00D8\u00D8\u00D8\u00FF111\u00FF$$$\u00FF111\u00FF@@@\u00FFRRR\u00FFeee\u00FFttt\u00FF\u008F\u008F\u008F\u00FF\u00F7\u00F8\u00F8\u00FF\u00AC\u00C8\u00DF\u00FF;}\u00B5\u00FF:}\u00B5\u00FF:}\u00B5\u00FF:}\u00B5\u00FFy\u00A7\u00CD\u00FF\u00FC\u00FD\u00FE\u00FF\u00FF\u00FF\u00FF\u00FF\u00FF\u00FF\u00FF\u00FF\u00FF\u00FF\u00FF\u00FF\u00FF\u00FF\u00FF\u00FF\u00FF\u00FF\u00FF\u00FF\u00FF\u00FF\u00FF\u00FF\u00FF\u00FF\u00FF\u00FF\u00FF\u00FF\u00FF\u00FF\u00FF\u00FF\u00FF\u00FF\u00FF\u00FF\u00FF\u00FF\u00FF\u00FF\u00FF\u00FF\u00FF\u00FF\u00FF\u00FF\u00FF\u00FF\u00FF\u00FF\u00FF\u00FF\u00FF\u00FF\u00FE\u00FE\u00FE\u00FFhhh\u00FF\u0000\u0000\u0000\u00FF\u0000\u0000\u0000\u00FF\u0000\u0000\u0000\u00FF\u0000\u0000\u0000\u00FF\u0000\u0000\u0000\u00FF\u0000\u0000\u0000\u00FF\u0000\u0000\u0000\u00FF\u0000\u0000\u0000\u00FF\u00B6\u00B6\u00B6\u00FF\u00FE\u00FE\u00FE\u00FF\u0086\u00AE\u00D1\u00FF:}\u00B5\u00FF:}\u00B5\u00FF:}\u00B5\u00FF:}\u00B5\u00FF\u00AE\u00CA\u00E1\u00FF\u00FF\u00FF\u00FF\u00FF\u00FF\u00FF\u00FF\u00FF\u00FF\u00FF\u00FF\u00FF\u00FF\u00FF\u00FF\u00FF\u00FF\u00FF\u00FF\u00FF\u00FF\u00FF\u00FF\u00FF\u00FF\u00FF\u00FF\u00FF\u00FF\u00FF\u00FF\u00FF\u00FF\u00FF\u00FF\u00FF\u00FF\u00FF\u00FF\u00FF\u00FF\u00FF\u00FF\u00FF\u00FF\u00FF\u00FF\u00FF\u00FF\u00FF\u00FF\u00FF\u00D3\u00E2\u00EE\u00FF\u00E1\u00EA\u00F2\u00FF(((\u00FF\u0000\u0000\u0000\u00FF\u0000\u0000\u0000\u00FF\u0000\u0000\u0000\u00FF\u0000\u0000\u0000\u00FF\u0000\u0000\u0000\u00FF\u0000\u0000\u0000\u00FF\u0000\u0000\u0000\u00FF\u0002\u0002\u0002\u00FF\u00DE\u00DE\u00DE\u00FF\u00FF\u00FF\u00FF\u00FF\u00F5\u00F8\u00FB\u00FF[\u0092\u00C1\u00FF:}\u00B5\u00FF:}\u00B5\u00FF:}\u00B5\u00FFH\u0086\u00BA\u00FF\u00F4\u00F8\u00FB\u00FF\u00FF\u00FF\u00FF\u00FF\u00FF\u00FF\u00FF\u00FF\u00FF\u00FF\u00FF\u00FF\u00FF\u00FF\u00FF\u00FF\u00FF\u00FF\u00FF\u00FF\u00FF\u00FF\u00FF\u00FF\u00FF\u00FF\u00FF\u00FF\u00FF\u00FF\u00FF\u00FF\u00FF\u00FF\u00FF\u00FF\u00FF\u00FF\u00FF\u00FF\u00FF\u00FF\u00FF\u00FF\u00EC\u00F3\u00F8\u00FFd\u0099\u00C5\u00FF\u00D7\u00D9\u00DB\u00FF\u0005\u0005\u0005\u00FF\u0000\u0000\u0000\u00FF\u0000\u0000\u0000\u00FF\u0000\u0000\u0000\u00FF\u0000\u0000\u0000\u00FF\u0000\u0000\u0000\u00FF\u0000\u0000\u0000\u00FF\u0000\u0000\u0000\u00FF$$$\u00FF\u00FE\u00FE\u00FE\u00FF\u00FF\u00FF\u00FF\u00FF\u00FF\u00FF\u00FF\u00FF\u00C0\u00D5\u00E7\u00FF9|\u00B5\u00FF:}\u00B5\u00FF:}\u00B5\u00FF:}\u00B5\u00FF\u00AB\u00C8\u00E0\u00FF\u00FF\u00FF\u00FF\u00FF\u00FF\u00FF\u00FF\u00FF\u00FF\u00FF\u00FF\u00FF\u00FF\u00FF\u00FF\u00FF\u00FF\u00FF\u00FF\u00FF\u00FF\u00FF\u00FF\u00FF\u00FF\u00FF\u00FF\u00FF\u00FF\u00FF\u00FF\u00FF\u00FF\u00FF\u00FF\u00FF\u00FF\u00FF\u00FF\u00FF\u00FE\u00FF\u00FF\u00FFx\u00A6\u00CC\u00FF{\u00A7\u00CD\u00FF\u009E\u009E\u009E\u00FF\u0000\u0000\u0000\u00FF\u0000\u0000\u0000\u00FF\u0000\u0000\u0000\u00FF\u0000\u0000\u0000\u00FF\u0000\u0000\u0000\u00FF\u0000\u0000\u0000\u00FF\u0000\u0000\u0000\u00FF\u0000\u0000\u0000\u00FFeee\u00FF\u00FF\u00FF\u00FF\u00FF\u00FF\u00FF\u00FF\u00FF\u00FF\u00FF\u00FF\u00FF\u00E2\u00EC\u00F4\u00FF7{\u00B4\u00FF:}\u00B5\u00FF:}\u00B5\u00FF:}\u00B5\u00FFf\u009A\u00C5\u00FF\u00FF\u00FF\u00FF\u00FF\u00FF\u00FF\u00FF\u00FF\u00FF\u00FF\u00FF\u00FF\u00FF\u00FF\u00FF\u00FF\u00FF\u00FF\u00FF\u00FF\u00FF\u00FF\u00FF\u00FF\u00FF\u00FF\u00FF\u00FF\u00FF\u00FF\u00FF\u00FF\u00FF\u00FF\u00FF\u00FF\u00FF\u00FF\u00FF\u00FF\u00C3\u00D7\u00E8\u00FF9}\u00B5\u00FF\u00B2\u00CC\u00E1\u00FFXXX\u00FF\u0000\u0000\u0000\u00FF\u0000\u0000\u0000\u00FF\u0000\u0000\u0000\u00FF\u0000\u0000\u0000\u00FF\u0000\u0000\u0000\u00FF\u0000\u0000\u0000\u00FF\u0000\u0000\u0000\u00FF\u0000\u0000\u0000\u00FF\u00A9\u00A9\u00A9\u00FF\u00FF\u00FF\u00FF\u00FF\u00FF\u00FF\u00FF\u00FF\u00FF\u00FF\u00FF\u00FF\u00BC\u00D2\u00E5\u00FF:}\u00B5\u00FF:}\u00B5\u00FF:}\u00B5\u00FF:}\u00B5\u00FF@\u0081\u00B7\u00FF\u00EE\u00F4\u00F9\u00FF\u00FF\u00FF\u00FF\u00FF\u00FF\u00FF\u00FF\u00FF\u00FF\u00FF\u00FF\u00FF\u00FF\u00FF\u00FF\u00FF\u00FF\u00FF\u00FF\u00FF\u00FF\u00FF\u00FF\u00FF\u00FF\u00FF\u00FF\u00FF\u00FF\u00FF\u00FF\u00FF\u00FA\u00FC\u00FD\u00FFZ\u0092\u00C1\u00FF=\u007F\u00B6\u00FF\u00DD\u00E5\u00ED\u00FF\u001C\u001C\u001C\u00FF\u0000\u0000\u0000\u00FF\u0000\u0000\u0000\u00FF\u0000\u0000\u0000\u00FF\u0000\u0000\u0000\u00FF\u0000\u0000\u0000\u00FF\u0000\u0000\u0000\u00FF\u0000\u0000\u0000\u00FF\u0007\u0007\u0007\u00FF\u00E7\u00E7\u00E7\u00FF\u00FF\u00FF\u00FF\u00FF\u00FF\u00FF\u00FF\u00FF\u00FF\u00FF\u00FF\u00FF\u0085\u00AE\u00D1\u00FF:}\u00B5\u00FF:}\u00B5\u00FF:}\u00B5\u00FF:}\u00B5\u00FF9}\u00B5\u00FF\u00CC\u00DE\u00EC\u00FF\u00FF\u00FF\u00FF\u00FF\u00FF\u00FF\u00FF\u00FF\u00FF\u00FF\u00FF\u00FF\u00FF\u00FF\u00FF\u00FF\u00FE\u00FE\u00FE\u00FF\u00FF\u00FF\u00FF\u00FF\u00FF\u00FF\u00FF\u00FF\u00FF\u00FF\u00FF\u00FF\u00BA\u00D2\u00E5\u00FF:}\u00B5\u00FFW\u0090\u00BF\u00FF\u00D0\u00D1\u00D1\u00FF\u0003\u0003\u0003\u00FF\u0000\u0000\u0000\u00FF\u0000\u0000\u0000\u00FF\u0000\u0000\u0000\u00FF\u0000\u0000\u0000\u00FF\u0000\u0000\u0000\u00FF\u0000\u0000\u0000\u00FF\u0000\u0000\u0000\u00FF333\u00FF\u00FD\u00FD\u00FD\u00FF\u00FF\u00FF\u00FF\u00FF\u00FF\u00FF\u00FF\u00FF\u00FB\u00FC\u00FD\u00FFP\u008B\u00BD\u00FF:}\u00B5\u00FF:}\u00B5\u00FF:}\u00B5\u00FF:}\u00B5\u00FF9}\u00B5\u00FF\u00B1\u00CC\u00E2\u00FF\u00FF\u00FF\u00FF\u00FF\u00FF\u00FF\u00FF\u00FF\u00FF\u00FF\u00FF\u00FF\u00CA\u00CA\u00CA\u00FF777\u00FFaaa\u00FF\u00A2\u00A2\u00A2\u00FF\u00DD\u00DD\u00DD\u00FF\u00E4\u00EC\u00F3\u00FF\u00B1\u00CB\u00E1\u00FF\u00B4\u00CD\u00E2\u00FF\u00E6\u00E6\u00E6\u00FF###\u00FF\u0000\u0000\u0000\u00FF\u0000\u0000\u0000\u00FF\u0000\u0000\u0000\u00FF\u0000\u0000\u0000\u00FF\u0000\u0000\u0000\u00FF\u0000\u0000\u0000\u00FF\u0000\u0000\u0000\u00FFrrr\u00FF\u00FF\u00FF\u00FF\u00FF\u00FF\u00FF\u00FF\u00FF\u00FF\u00FF\u00FF\u00FF\u00D8\u00E5\u00F0\u00FF:}\u00B5\u00FF:}\u00B5\u00FF:}\u00B5\u00FF:}\u00B5\u00FF:}\u00B5\u00FF:}\u00B5\u00FF\u00A0\u00C0\u00DB\u00FF\u00FF\u00FF\u00FF\u00FF\u00FF\u00FF\u00FF\u00FF\u00FF\u00FF\u00FF\u00FFfff\u00FF\u0000\u0000\u0000\u00FF\u0000\u0000\u0000\u00FF\u0000\u0000\u0000\u00FF\u0006\u0006\u0006\u00FF'''\u00FFfff\u00FF\u00D4\u00D4\u00D4\u00FF\u00FF\u00FF\u00FF\u00FF\u00F6\u00F6\u00F6\u00FF\u00D0\u00D0\u00D0\u00FF\u0097\u0097\u0097\u00FF^^^\u00FF'''\u00FF\u0004\u0004\u0004\u00FF\u0000\u0000\u0000\u00FF\u0003\u0003\u0003\u00FF\u00C0\u00C0\u00C0\u00FF\u00FF\u00FF\u00FF\u00FF\u00FF\u00FF\u00FF\u00FF\u00FF\u00FF\u00FF\u00FF\u00A2\u00C1\u00DB\u00FF:}\u00B5\u00FF:}\u00B5\u00FF:}\u00B5\u00FF:}\u00B5\u00FF:}\u00B5\u00FF:}\u00B5\u00FF\u009E\u00BF\u00DA\u00FF\u00FF\u00FF\u00FF\u00FF\u00FF\u00FF\u00FF\u00FF\u00FB\u00FB\u00FB\u00FF%%%\u00FF\u0000\u0000\u0000\u00FF\u0000\u0000\u0000\u00FF\u0000\u0000\u0000\u00FF\u0000\u0000\u0000\u00FF\u0000\u0000\u0000\u00FF\u0000\u0000\u0000\u00FF\\\\\\\u00FF\u00FF\u00FF\u00FF\u00FF\u00EA\u00EA\u00EA\u00FF\u008F\u008F\u008F\u00FF\u00B5\u00B5\u00B5\u00FF\u00E9\u00E9\u00E9\u00FF\u00FD\u00FD\u00FD\u00FF\u00E7\u00E7\u00E7\u00FF\u00B2\u00B2\u00B2\u00FF\u00BD\u00BD\u00BD\u00FF\u00FE\u00FE\u00FE\u00FF\u00FF\u00FF\u00FF\u00FF\u00FF\u00FF\u00FF\u00FF\u00FF\u00FF\u00FF\u00FFk\u009D\u00C7\u00FF:}\u00B5\u00FF:}\u00B5\u00FF:}\u00B5\u00FF:}\u00B5\u00FF:}\u00B5\u00FF:}\u00B5\u00FF\u00A1\u00C1\u00DC\u00FF\u00FF\u00FF\u00FF\u00FF\u00FF\u00FF\u00FF\u00FF\u00DB\u00DB\u00DB\u00FF\u0003\u0003\u0003\u00FF\u0000\u0000\u0000\u00FF\u0000\u0000\u0000\u00FF\u0000\u0000\u0000\u00FF\u0000\u0000\u0000\u00FF\u0000\u0000\u0000\u00FF\u0000\u0000\u0000\u00FF\u0083\u0083\u0083\u00FF\u00FF\u00FF\u00FF\u00FF___\u00FF\u0000\u0000\u0000\u00FF\u0000\u0000\u0000\u00FF\u000B\u000B\u000B\u00FF777\u00FFvvv\u00FF\u00B7\u00B7\u00B7\u00FF\u00F0\u00F0\u00F0\u00FF\u00FF\u00FF\u00FF\u00FF\u00FF\u00FF\u00FF\u00FF\u00FF\u00FF\u00FF\u00FF\u00F0\u00F5\u00F9\u00FFK\u0088\u00BB\u00FF=\u007F\u00B6\u00FF9|\u00B5\u00FF:}\u00B5\u00FF:}\u00B5\u00FF:}\u00B5\u00FF:}\u00B5\u00FF\u00B2\u00CC\u00E2\u00FF\u00FF\u00FF\u00FF\u00FF\u00FF\u00FF\u00FF\u00FF\u009A\u009A\u009A\u00FF\u0000\u0000\u0000\u00FF\u0000\u0000\u0000\u00FF\u0000\u0000\u0000\u00FF\u0000\u0000\u0000\u00FF\u0000\u0000\u0000\u00FF\u0000\u0000\u0000\u00FF\u0000\u0000\u0000\u00FF\u00C5\u00C5\u00C5\u00FF\u00F7\u00F7\u00F7\u00FF\u001D\u001D\u001D\u00FF\u0000\u0000\u0000\u00FF\u0000\u0000\u0000\u00FF\u0000\u0000\u0000\u00FF\u0000\u0000\u0000\u00FF\u0000\u0000\u0000\u00FF\u0000\u0000\u0000\u00FF\u0007\u0007\u0007\u00FF<<<\u00FF\u00DF\u00DF\u00DF\u00FF\u00FF\u00FF\u00FF\u00FF\u00FB\u00FC\u00FD\u00FF\u00FC\u00FD\u00FE\u00FF\u00F3\u00F7\u00FA\u00FF\u00CC\u00DD\u00EB\u00FF\u009E\u00BE\u00DA\u00FFr\u00A1\u00C9\u00FFL\u0089\u00BB\u00FF:}\u00B5\u00FF\u00C9\u00DC\u00EB\u00FF\u00FF\u00FF\u00FF\u00FF\u00FF\u00FF\u00FF\u00FFVVV\u00FF\u0000\u0000\u0000\u00FF\u0000\u0000\u0000\u00FF\u0000\u0000\u0000\u00FF\u0000\u0000\u0000\u00FF\u0000\u0000\u0000\u00FF\u0000\u0000\u0000\u00FF\u000F\u000F\u000F\u00FF\u00F9\u00F9\u00F9\u00FF\u00D1\u00D1\u00D1\u00FF\u0003\u0003\u0003\u00FF\u0000\u0000\u0000\u00FF\u0000\u0000\u0000\u00FF\u0000\u0000\u0000\u00FF\u0000\u0000\u0000\u00FF\u0000\u0000\u0000\u00FF\u0000\u0000\u0000\u00FF\u0000\u0000\u0000\u00FF\u0000\u0000\u0000\u00FF\u008E\u008E\u008E\u00FF\u00FF\u00FF\u00FF\u00FF\u00F9\u00F9\u00F9\u00FF\u0084\u0084\u0084\u00FFppp\u00FF\u00B0\u00B0\u00B0\u00FF\u00EA\u00EA\u00EA\u00FF\u00FF\u00FF\u00FF\u00FF\u00F9\u00FB\u00FC\u00FF\u00DC\u00E8\u00F2\u00FF\u00F6\u00F9\u00FC\u00FF\u00FF\u00FF\u00FF\u00FF\u00FF\u00FF\u00FF\u00FF\u0015\u0015\u0015\u00FF\u0000\u0000\u0000\u00FF\u0000\u0000\u0000\u00FF\u0000\u0000\u0000\u00FF\u0000\u0000\u0000\u00FF\u0000\u0000\u0000\u00FF\u0000\u0000\u0000\u00FFNNN\u00FF\u00FF\u00FF\u00FF\u00FF\u0091\u0091\u0091\u00FF\u0000\u0000\u0000\u00FF\u0000\u0000\u0000\u00FF\u0000\u0000\u0000\u00FF\u0000\u0000\u0000\u00FF\u0000\u0000\u0000\u00FF\u0000\u0000\u0000\u00FF\u0000\u0000\u0000\u00FF\u0000\u0000\u0000\u00FF\u0000\u0000\u0000\u00FF\u00BB\u00BB\u00BB\u00FF\u00FF\u00FF\u00FF\u00FF\u009E\u009E\u009E\u00FF\u0000\u0000\u0000\u00FF\u0000\u0000\u0000\u00FF\u0000\u0000\u0000\u00FF\u0004\u0004\u0004\u00FF///\u00FFppp\u00FF\u00B0\u00B0\u00B0\u00FF\u00E6\u00E6\u00E6\u00FF\u00FE\u00FE\u00FE\u00FF\u00FF\u00FF\u00FF\u00FF999\u00FF\u0000\u0000\u0000\u00FF\u0000\u0000\u0000\u00FF\u0000\u0000\u0000\u00FF\u0000\u0000\u0000\u00FF\u0000\u0000\u0000\u00FF\u0000\u0000\u0000\u00FF\u0090\u0090\u0090\u00FF\u00FF\u00FF\u00FF\u00FFMMM\u00FF\u0000\u0000\u0000\u00FF\u0000\u0000\u0000\u00FF\u0000\u0000\u0000\u00FF\u0000\u0000\u0000\u00FF\u0000\u0000\u0000\u00FF\u0000\u0000\u0000\u00FF\u0000\u0000\u0000\u00FF\u0000\u0000\u0000\u00FF\u0010\u0010\u0010\u00FF\u00F0\u00F0\u00F0\u00FF\u00FF\u00FF\u00FF\u00FFZZZ\u00FF\u0000\u0000\u0000\u00FF\u0000\u0000\u0000\u00FF\u0000\u0000\u0000\u00FF\u0000\u0000\u0000\u00FF\u0000\u0000\u0000\u00FF\u0000\u0000\u0000\u00FF\u0000\u0000\u0000\u00FF\u0009\u0009\u0009\u00FF222\u00FF\u00B1\u00B1\u00B1\u00FF\u00F6\u00F6\u00F6\u00FF\u00A1\u00A1\u00A1\u00FF555\u00FF\u0002\u0002\u0002\u00FF\u0000\u0000\u0000\u00FF\u0000\u0000\u0000\u00FF\u0002\u0002\u0002\u00FF\u00D1\u00D1\u00D1\u00FF\u00F5\u00F5\u00F5\u00FF\u0013\u0013\u0013\u00FF\u0000\u0000\u0000\u00FF\u0000\u0000\u0000\u00FF\u0000\u0000\u0000\u00FF\u0000\u0000\u0000\u00FF\u0000\u0000\u0000\u00FF\u0000\u0000\u0000\u00FF\u0000\u0000\u0000\u00FF\u0000\u0000\u0000\u00FFEEE\u00FF\u00FE\u00FE\u00FE\u00FF\u00F8\u00F8\u00F8\u00FF\u001D\u001D\u001D\u00FF\u0000\u0000\u0000\u00FF\u0000\u0000\u0000\u00FF\u0000\u0000\u0000\u00FF\u0000\u0000\u0000\u00FF\u0000\u0000\u0000\u00FF\u0000\u0000\u0000\u00FF\u0000\u0000\u0000\u00FF\u0000\u0000\u0000\u00FF\u0000\u0000\u0000\u00FF+++\u00FF\u00FF\u00FF\u00FF\u00FF\u00FF\u00FF\u00FF\u00FF\u00FC\u00FC\u00FC\u00FF\u00BE\u00BE\u00BE\u00FFPPP\u00FF\u0005\u0005\u0005\u00FF%%%\u00FF\u00F9\u00F9\u00F9\u00FF\u00C2\u00C2\u00C2\u00FF\u0000\u0000\u0000\u00FF\u0000\u0000\u0000\u00FF\u0000\u0000\u0000\u00FF\u0000\u0000\u0000\u00FF\u0000\u0000\u0000\u00FF\u0000\u0000\u0000\u00FF\u0000\u0000\u0000\u00FF\u0000\u0000\u0000\u00FF\u0000\u0000\u0000\u00FF\u0086\u0086\u0086\u00FF\u00FF\u00FF\u00FF\u00FF\u00D2\u00D2\u00D2\u00FF\u0001\u0001\u0001\u00FF\u0000\u0000\u0000\u00FF\u0000\u0000\u0000\u00FF\u0000\u0000\u0000\u00FF\u0000\u0000\u0000\u00FF\u0000\u0000\u0000\u00FF\u0000\u0000\u0000\u00FF\u0000\u0000\u0000\u00FF\u0000\u0000\u0000\u00FF\u0000\u0000\u0000\u00FFCCC\u00FF\u00FF\u00FF\u00FF\u00FF\u00FF\u00FF\u00FF\u00FF\u00FF\u00FF\u00FF\u00FF\u00FF\u00FF\u00FF\u00FF\u00FE\u00FE\u00FE\u00FF\u00DC\u00DC\u00DC\u00FF\u00E0\u00E0\u00E0\u00FF\u00FF\u00FF\u00FF\u00FF\u0095\u0095\u0095\u00FF\u0000\u0000\u0000\u00FF\u0000\u0000\u0000\u00FF\u0000\u0000\u0000\u00FF\u0000\u0000\u0000\u00FF\u0000\u0000\u0000\u00FF\u0000\u0000\u0000\u00FF\u0000\u0000\u0000\u00FF\u0000\u0000\u0000\u00FF\u0001\u0001\u0001\u00FF\u00C8\u00C8\u00C8\u00FF\u00FF\u00FF\u00FF\u00FF\u008E\u008E\u008E\u00FF\u0000\u0000\u0000\u00FF\u0000\u0000\u0000\u00FF\u0000\u0000\u0000\u00FF\u0000\u0000\u0000\u00FF\u0000\u0000\u0000\u00FF\u0000\u0000\u0000\u00FF\u0000\u0000\u0000\u00FF\u0000\u0000\u0000\u00FF\u0000\u0000\u0000\u00FF\u0000\u0000\u0000\u00FF\u0088\u0088\u0088\u00FF\u00FF\u00FF\u00FF\u00FF\u00FF\u00FF\u00FF\u00FF\u00FF\u00FF\u00FF\u00FF\u00FF\u00FF\u00FF\u00FF\u00FF\u00FF\u00FF\u00FF\u00FF\u00FF\u00FF\u00FF\u00FF\u00FF\u00FF\u00FF\u00FF\u00FF\u00FF\u00FF\u00DF\u00DF\u00DF\u00FF)))\u00FF\u0000\u0000\u0000\u00FF\u0000\u0000\u0000\u00FF\u0000\u0000\u0000\u00FF\u0000\u0000\u0000\u00FF\u0000\u0000\u0000\u00FF\u0000\u0000\u0000\u00FF\u0000\u0000\u0000\u00FF\u0018\u0018\u0018\u00FF\u00F5\u00F5\u00F5\u00FF\u00FF\u00FF\u00FF\u00FFJJJ\u00FF\u0000\u0000\u0000\u00FF\u0000\u0000\u0000\u00FF\u0000\u0000\u0000\u00FF\u0000\u0000\u0000\u00FF\u0000\u0000\u0000\u00FF\u0000\u0000\u0000\u00FF\u0000\u0000\u0000\u00FF\u0000\u0000\u0000\u00FF\u0000\u0000\u0000\u00FF\u0000\u0000\u0000\u00FF\u00CF\u00CF\u00CF\u00FF\u00FF\u00FF\u00FF\u00FF\u00FF\u00FF\u00FF\u00FF\u00FF\u00FF\u00FF\u00FF\u00FF\u00FF\u00FF\u00FF\u00FF\u00FF\u00FF\u00FF\u00F1\u00F6\u00FA\u00FF\u00FF\u00FF\u00FF\u00FF\u00FF\u00FF\u00FF\u00FF\u00FF\u00FF\u00FF\u00FF\u00F9\u00F9\u00F9\u00FF\u00B5\u00B5\u00B5\u00FFKKK\u00FF\u0006\u0006\u0006\u00FF\u0000\u0000\u0000\u00FF\u0000\u0000\u0000\u00FF\u0000\u0000\u0000\u00FF\u0000\u0000\u0000\u00FFRRR\u00FF\u00FF\u00FF\u00FF\u00FF\u00F8\u00F8\u00F8\u00FF\u0010\u0010\u0010\u00FF\u0000\u0000\u0000\u00FF\u0000\u0000\u0000\u00FF\u0000\u0000\u0000\u00FF\u0000\u0000\u0000\u00FF\u0000\u0000\u0000\u00FF\u0000\u0000\u0000\u00FF\u0000\u0000\u0000\u00FF\u0000\u0000\u0000\u00FF\u0000\u0000\u0000\u00FF\u001C\u001C\u001C\u00FF\u00F8\u00F8\u00F8\u00FF\u00FF\u00FF\u00FF\u00FF\u00FF\u00FF\u00FF\u00FF\u00FF\u00FF\u00FF\u00FF\u00FF\u00FF\u00FF\u00FF\u00FF\u00FF\u00FF\u00FF\u0086\u00AF\u00D1\u00FF\u0090\u00B5\u00D5\u00FF\u00EA\u00F1\u00F7\u00FF\u00FF\u00FF\u00FF\u00FF\u00FF\u00FF\u00FF\u00FF\u00FF\u00FF\u00FF\u00FF\u00FF\u00FF\u00FF\u00FF\u00DB\u00DB\u00DB\u00FFxxx\u00FF\u001B\u001B\u001B\u00FF\u0000\u0000\u0000\u00FF\u0000\u0000\u0000\u00FF\u0096\u0096\u0096\u00FF\u00FF\u00FF\u00FF\u00FF\u00C6\u00C6\u00C6\u00FF\u0000\u0000\u0000\u00FF\u0000\u0000\u0000\u00FF\u0000\u0000\u0000\u00FF\u0000\u0000\u0000\u00FF\u0000\u0000\u0000\u00FF\u0000\u0000\u0000\u00FF\u0000\u0000\u0000\u00FF\u0000\u0000\u0000\u00FF\u0000\u0000\u0000\u00FF\u0000\u0000\u0000\u00FFZZZ\u00FF\u00FF\u00FF\u00FF\u00FF\u00FF\u00FF\u00FF\u00FF\u00FF\u00FF\u00FF\u00FF\u00FF\u00FF\u00FF\u00FF\u00FF\u00FF\u00FF\u00FF\u00FF\u00FF\u00FF\u00FF\u00C3\u00D8\u00E9\u00FF:}\u00B5\u00FFC\u0083\u00B8\u00FF\u0094\u00B8\u00D6\u00FF\u00ED\u00F3\u00F8\u00FF\u00FF\u00FF\u00FF\u00FF\u00FF\u00FF\u00FF\u00FF\u00FF\u00FF\u00FF\u00FF\u00FF\u00FF\u00FF\u00FF\u00F4\u00F4\u00F4\u00FF\u00A7\u00A7\u00A7\u00FF\u0085\u0085\u0085\u00FF\u00F4\u00F4\u00F4\u00FF\u00FF\u00FF\u00FF\u00FF\u0086\u0086\u0086\u00FF\u0000\u0000\u0000\u00FF\u0000\u0000\u0000\u00FF\u0000\u0000\u0000\u00FF\u0000\u0000\u0000\u00FF\u0000\u0000\u0000\u00FF\u0000\u0000\u0000\u00FF\u0000\u0000\u0000\u00FF\u0000\u0000\u0000\u00FF\u0000\u0000\u0000\u00FF\u0000\u0000\u0000\u00FF\u009D\u009D\u009D\u00FF\u00FF\u00FF\u00FF\u00FF\u00FF\u00FF\u00FF\u00FF\u00FF\u00FF\u00FF\u00FF\u00FF\u00FF\u00FF\u00FF\u00FF\u00FF\u00FF\u00FF\u00FF\u00FF\u00FF\u00FF\u00FA\u00FB\u00FD\u00FF]\u0094\u00C2\u00FF:}\u00B5\u00FF:}\u00B5\u00FFF\u0085\u00B9\u00FF\u0098\u00BB\u00D8\u00FF\u00EF\u00F4\u00F9\u00FF\u00FF\u00FF\u00FF\u00FF\u00FF\u00FF\u00FF\u00FF\u00FF\u00FF\u00FF\u00FF\u00FF\u00FF\u00FF\u00FF\u00FF\u00FF\u00FF\u00FF\u00FF\u00FF\u00FF\u00FF\u00FF\u00FF\u00FF\u00FF\u009B\u009B\u009B\u00FF\u0000\u0000\u0000\u00FF\u0000\u0000\u0000\u00FF\u0000\u0000\u0000\u00FF\u0000\u0000\u0000\u00FF\u0000\u0000\u0000\u00FF\u0000\u0000\u0000\u00FF\u0000\u0000\u0000\u00FF\u0000\u0000\u0000\u00FF\u0000\u0000\u0000\u00FF\u0005\u0005\u0005\u00FF\u00DD\u00DD\u00DD\u00FF\u00FF\u00FF\u00FF\u00FF\u00FF\u00FF\u00FF\u00FF\u00FF\u00FF\u00FF\u00FF\u00FF\u00FF\u00FF\u00FF\u00FF\u00FF\u00FF\u00FF\u00FF\u00FF\u00FF\u00FF\u00FF\u00FF\u00FF\u00FF\u00C5\u00D9\u00E9\u00FF;~\u00B6\u00FF:}\u00B5\u00FF:}\u00B5\u00FF:}\u00B5\u00FFH\u0086\u00BA\u00FF\u009E\u00BE\u00DA\u00FF\u00F2\u00F6\u00FA\u00FF\u00FF\u00FF\u00FF\u00FF\u00FF\u00FF\u00FF\u00FF\u00FF\u00FF\u00FF\u00FF\u00FF\u00FF\u00FF\u00FF\u00FF\u00FF\u00FF\u00FF\u00FB\u00FB\u00FB\u00FF\u008E\u008E\u008E\u00FF%%%\u00FF\u0001\u0001\u0001\u00FF\u0000\u0000\u0000\u00FF\u0000\u0000\u0000\u00FF\u0000\u0000\u0000\u00FF\u0000\u0000\u0000\u00FF\u0000\u0000\u0000\u00FF\u0000\u0000\u0000\u00FF,,,\u00FF\u00FC\u00FC\u00FC\u00FF\u00FF\u00FF\u00FF\u00FF\u00FF\u00FF\u00FF\u00FF\u00FF\u00FF\u00FF\u00FF\u00FF\u00FF\u00FF\u00FF\u00FF\u00FF\u00FF\u00FF\u00FF\u00FF\u00FF\u00FF\u00FF\u00FF\u00FF\u00FF\u00FF\u00FF\u00FF\u00FF\u008F\u00B5\u00D5\u00FF:}\u00B5\u00FF:}\u00B5\u00FF:}\u00B5\u00FF:}\u00B5\u00FF:}\u00B5\u00FFJ\u0087\u00BB\u00FF\u00A3\u00C2\u00DC\u00FF\u00F3\u00F7\u00FA\u00FF\u00FF\u00FF\u00FF\u00FF\u00FF\u00FF\u00FF\u00FF\u00FF\u00FF\u00FF\u00FF\u00FF\u00FF\u00FF\u00FF\u00FF\u00FF\u00FF\u00FF\u00FA\u00FA\u00FA\u00FF\u00B0\u00B0\u00B0\u00FFEEE\u00FF\u0004\u0004\u0004\u00FF\u0000\u0000\u0000\u00FF\u0000\u0000\u0000\u00FF\u0000\u0000\u0000\u00FF\u0000\u0000\u0000\u00FFnnn\u00FF\u00FF\u00FF\u00FF\u00FF\u00FF\u00FF\u00FF\u00FF\u00FF\u00FF\u00FF\u00FF\u00FF\u00FF\u00FF\u00FF\u00FF\u00FF\u00FF\u00FF\u00FF\u00FF\u00FF\u00FF\u00FF\u00FF\u00FF\u00FF\u00FF\u00FF\u00FF\u00FF\u00FF\u00FF\u00FF\u00FF\u00FC\u00FD\u00FE\u00FF\u0085\u00AF\u00D1\u00FF:}\u00B5\u00FF:}\u00B5\u00FF:}\u00B5\u00FF:}\u00B5\u00FF:}\u00B5\u00FF:}\u00B5\u00FFM\u0089\u00BC\u00FF\u00A8\u00C5\u00DE\u00FF\u00F6\u00F9\u00FC\u00FF\u00FF\u00FF\u00FF\u00FF\u00FF\u00FF\u00FF\u00FF\u00FF\u00FF\u00FF\u00FF\u00FF\u00FF\u00FF\u00FF\u00FF\u00FF\u00FF\u00FF\u00FE\u00FE\u00FE\u00FF\u00D2\u00D2\u00D2\u00FFhhh\u00FF\u000E\u000E\u000E\u00FF\u0000\u0000\u0000\u00FF\u0001\u0001\u0001\u00FF\u00B8\u00B8\u00B8\u00FF\u00FF\u00FF\u00FF\u00FF\u00FF\u00FF\u00FF\u00FF\u00FF\u00FF\u00FF\u00FF\u00FF\u00FF\u00FF\u00FF\u00FF\u00FF\u00FF\u00FF\u00FF\u00FF\u00FF\u00FF\u00FF\u00FF\u00FF\u00FF\u00FF\u00FF\u00FF\u00FF\u00FF\u00FF\u00FF\u00FF\u00FF\u00FF\u00FF\u00FF\u00FE\u00FE\u00FF\u00FF\u00B1\u00CB\u00E2\u00FFL\u0089\u00BC\u00FF9}\u00B5\u00FF:}\u00B5\u00FF:}\u00B5\u00FF:}\u00B5\u00FF:}\u00B5\u00FF:}\u00B5\u00FFM\u0089\u00BC\u00FF\u00BF\u00D4\u00E7\u00FF\u00FF\u00FF\u00FF\u00FF\u00FF\u00FF\u00FF\u00FF\u00FF\u00FF\u00FF\u00FF\u00FF\u00FF\u00FF\u00FF\u00FF\u00FF\u00FF\u00FF\u00FF\u00FF\u00FF\u00FF\u00FF\u00FF\u00FF\u00FF\u00EC\u00EC\u00EC\u00FF\u0093\u0093\u0093\u00FF\u009B\u009B\u009B\u00FF\u00FD\u00FD\u00FD\u00FF\u00FF\u00FF\u00FF\u00FF\u00FF\u00FF\u00FF\u00FF\u00FF\u00FF\u00FF\u00FF\u00FF\u00FF\u00FF\u00FF\u00FF\u00FF\u00FF\u00FF\u00FF\u00FF\u00FF\u00FF\u00FF\u00FF\u00FF\u00FF\u00FF\u00FF\u00FF\u00FF\u00FF\u00FF\u00FF\u00FF\u00FF\u00FF\u00FF\u00FF\u00FF\u00FF\u00FF\u00FF\u00FF\u00FF\u00FF\u00FF\u00F3\u00F7\u00FA\u00FF\u00B5\u00CE\u00E3\u00FF\u0081\u00AC\u00D0\u00FFe\u0099\u00C5\u00FFa\u0097\u00C4\u00FFl\u009E\u00C8\u00FF\u008F\u00B5\u00D5\u00FF\u00C5\u00D9\u00E9\u00FF\u00F7\u00FA\u00FC\u00FF\u00FF\u00FF\u00FF\u00FF\u00FF\u00FF\u00FF\u00FF\u00FF\u00FF\u00FF\u00FF\u00FF\u00FF\u00FF\u00FF\u00FF\u00FF\u00FF\u00FF\u00FF\u00FF\u00FF\u00FF\u00FF\u00FF\u00FF\u00FF\u00FF\u00FF\u00FF\u00FF\u00FF\u00FF\u00FF\u00FF\u00FF\u00FF\u00FF\u00FF\u00FF\u00FF\u00FF\u00FF\u00FF\u00FF\u00FF\u00FF\u00FF\u00FF\u00FF\u00FF"
.end class
