.version 46 0
.class final super org/jouvieje/libloader/d
.super java/lang/Object
.implements java/security/PrivilegedAction
.field private final field2422 Ljava/io/File; .fieldattributes
    .synthetic
.end fieldattributes
.field private final field2423 Ljava/lang/String; .fieldattributes
    .synthetic
.end fieldattributes
.field private final field2424 Ljava/lang/String; .fieldattributes
    .synthetic
.end fieldattributes

.method public run : ()Ljava/lang/Object;
    .code stack 3 locals 2
        .catch java/lang/Throwable from L0 to L47 using L49
L0:     aload_0
L1:     getfield Field org/jouvieje/libloader/d field2422 Ljava/io/File;
L4:     invokevirtual Method java/io/File getAbsolutePath ()Ljava/lang/String;
L7:     invokestatic Method java/lang/System load (Ljava/lang/String;)V
L10:    new java/lang/StringBuffer
L13:    dup
L14:    ldc "LOADED="
L16:    invokespecial Method java/lang/StringBuffer <init> (Ljava/lang/String;)V
L19:    aload_0
L20:    getfield Field org/jouvieje/libloader/d field2424 Ljava/lang/String;
L23:    invokevirtual Method java/lang/StringBuffer append (Ljava/lang/String;)Ljava/lang/StringBuffer;
L26:    ldc " | FROM="
L28:    invokevirtual Method java/lang/StringBuffer append (Ljava/lang/String;)Ljava/lang/StringBuffer;
L31:    aload_0
L32:    getfield Field org/jouvieje/libloader/d field2423 Ljava/lang/String;
L35:    invokevirtual Method java/lang/StringBuffer append (Ljava/lang/String;)Ljava/lang/StringBuffer;
L38:    invokevirtual Method java/lang/StringBuffer toString ()Ljava/lang/String;
L41:    invokestatic Method org/jouvieje/libloader/G method1733 (Ljava/lang/String;)V
L44:    getstatic Field java/lang/Boolean TRUE Ljava/lang/Boolean;
L47:    areturn
L48:    athrow
L49:    astore_1
L50:    new java/lang/StringBuffer
L53:    dup
L54:    ldc "ERROR="
L56:    invokespecial Method java/lang/StringBuffer <init> (Ljava/lang/String;)V
L59:    aload_1
L60:    invokevirtual Method java/lang/Throwable getMessage ()Ljava/lang/String;
L63:    invokevirtual Method java/lang/StringBuffer append (Ljava/lang/String;)Ljava/lang/StringBuffer;
L66:    invokevirtual Method java/lang/StringBuffer toString ()Ljava/lang/String;
L69:    invokestatic Method org/jouvieje/libloader/G method1733 (Ljava/lang/String;)V
L72:    getstatic Field java/lang/Boolean FALSE Ljava/lang/Boolean;
L75:    areturn
L76:    
        .attribute StackMap b'\x00\x02\x00\x30\x00\x00\x00\x01\x07\x00\x0F\x00\x31\x00\x01\x07\x00\x02\x00\x01\x07\x00\x0F'
    .end code
.end method

.method <init> : (Ljava/io/File;Ljava/lang/String;Ljava/lang/String;)V
    .code stack 7 locals 4
L0:     aload_3
L1:     aload_0
L2:     dup_x1
L3:     aload_2
L4:     aload_1
L5:     aload_0
L6:     dup_x1
L7:     invokespecial Method java/lang/Object <init> ()V
L10:    putfield Field org/jouvieje/libloader/d field2422 Ljava/io/File;
L13:    putfield Field org/jouvieje/libloader/d field2424 Ljava/lang/String;
L16:    putfield Field org/jouvieje/libloader/d field2423 Ljava/lang/String;
L19:    return
L20:    
    .end code
.end method
.innerclasses
    org/jouvieje/libloader/d [0] [0]
.end innerclasses
.end class
