.version 46 0
.class final super org/jouvieje/libloader/D
.super java/lang/Object
.implements java/security/PrivilegedAction
.field private final field2430 Ljava/lang/String; .fieldattributes
    .synthetic
.end fieldattributes

.method public run : ()Ljava/lang/Object;
    .code stack 5 locals 9
L0:     new java/lang/StringBuffer
L3:     dup
L4:     ldc "/"
L6:     invokespecial Method java/lang/StringBuffer <init> (Ljava/lang/String;)V
L9:     aload_0
L10:    getfield Field org/jouvieje/libloader/D field2430 Ljava/lang/String;
L13:    invokevirtual Method java/lang/StringBuffer append (Ljava/lang/String;)Ljava/lang/StringBuffer;
L16:    invokevirtual Method java/lang/StringBuffer toString ()Ljava/lang/String;
L19:    astore_1
L20:    new java/lang/StringBuffer
L23:    dup
L24:    ldc "Opening for reading: "
L26:    invokespecial Method java/lang/StringBuffer <init> (Ljava/lang/String;)V
L29:    aload_1
L30:    invokevirtual Method java/lang/StringBuffer append (Ljava/lang/String;)Ljava/lang/StringBuffer;
L33:    invokevirtual Method java/lang/StringBuffer toString ()Ljava/lang/String;
L36:    invokestatic Method org/jouvieje/libloader/G method1733 (Ljava/lang/String;)V
L39:    new org/jouvieje/libloader/G
L42:    dup
L43:    invokespecial Method org/jouvieje/libloader/G <init> ()V
L46:    invokevirtual Method java/lang/Object getClass ()Ljava/lang/Class;
L49:    aload_1
L50:    invokevirtual Method java/lang/Class getResourceAsStream (Ljava/lang/String;)Ljava/io/InputStream;
L53:    dup
L54:    astore_2
L55:    ifnonnull L178
L58:    new java/lang/StringBuffer
L61:    dup
L62:    ldc "Re-Opening for reading: "
L64:    invokespecial Method java/lang/StringBuffer <init> (Ljava/lang/String;)V
L67:    aload_1
L68:    invokevirtual Method java/lang/StringBuffer append (Ljava/lang/String;)Ljava/lang/StringBuffer;
L71:    invokevirtual Method java/lang/StringBuffer toString ()Ljava/lang/String;
L74:    invokestatic Method org/jouvieje/libloader/G method1733 (Ljava/lang/String;)V
L77:    getstatic Field org/jouvieje/libloader/G field2442 Ljava/lang/Class;
L80:    dup
L81:    ifnonnull L111
L84:    pop
        .catch java/lang/ClassNotFoundException from L85 to L90 using L99
L85:    ldc "org.jouvieje.libloader.G"
L87:    invokestatic Method java/lang/Class forName (Ljava/lang/String;)Ljava/lang/Class;
L90:    dup
L91:    putstatic Field org/jouvieje/libloader/G field2442 Ljava/lang/Class;
L94:    aload_1
L95:    goto L112
L98:    athrow
L99:    new java/lang/NoClassDefFoundError
L102:   dup_x1
L103:   swap
L104:   invokevirtual Method java/lang/Throwable getMessage ()Ljava/lang/String;
L107:   invokespecial Method java/lang/NoClassDefFoundError <init> (Ljava/lang/String;)V
L110:   athrow
L111:   aload_1
L112:   invokevirtual Method java/lang/Class getResourceAsStream (Ljava/lang/String;)Ljava/io/InputStream;
L115:   dup
L116:   astore_2
L117:   ifnonnull L178
L120:   new java/lang/StringBuffer
L123:   dup
L124:   ldc "Re-Re-Opening for reading: "
L126:   invokespecial Method java/lang/StringBuffer <init> (Ljava/lang/String;)V
L129:   aload_1
L130:   invokevirtual Method java/lang/StringBuffer append (Ljava/lang/String;)Ljava/lang/StringBuffer;
L133:   invokevirtual Method java/lang/StringBuffer toString ()Ljava/lang/String;
L136:   invokestatic Method org/jouvieje/libloader/G method1733 (Ljava/lang/String;)V
L139:   getstatic Field org/jouvieje/libloader/G field2444 Ljava/lang/Class;
L142:   dup
L143:   ifnonnull L173
L146:   pop
        .catch java/lang/ClassNotFoundException from L147 to L152 using L161
L147:   ldc "java.lang.Class"
L149:   invokestatic Method java/lang/Class forName (Ljava/lang/String;)Ljava/lang/Class;
L152:   dup
L153:   putstatic Field org/jouvieje/libloader/G field2444 Ljava/lang/Class;
L156:   aload_1
L157:   goto L174
L160:   athrow
L161:   new java/lang/NoClassDefFoundError
L164:   dup_x1
L165:   swap
L166:   invokevirtual Method java/lang/Throwable getMessage ()Ljava/lang/String;
L169:   invokespecial Method java/lang/NoClassDefFoundError <init> (Ljava/lang/String;)V
L172:   athrow
L173:   aload_1
L174:   invokevirtual Method java/lang/Class getResourceAsStream (Ljava/lang/String;)Ljava/io/InputStream;
L177:   astore_2
L178:   aload_2
L179:   ifnull L403
L182:   ldc "Open succeed."
L184:   invokestatic Method org/jouvieje/libloader/G method1733 (Ljava/lang/String;)V
L187:   new java/lang/StringBuffer
L190:   dup
L191:   ldc "java.io.tmpdir"
L193:   invokestatic Method org/jouvieje/libloader/G method1737 (Ljava/lang/String;)Ljava/lang/String;
L196:   invokestatic Method java/lang/String valueOf (Ljava/lang/Object;)Ljava/lang/String;
L199:   invokespecial Method java/lang/StringBuffer <init> (Ljava/lang/String;)V
L202:   getstatic Field java/io/File separator Ljava/lang/String;
L205:   invokevirtual Method java/lang/StringBuffer append (Ljava/lang/String;)Ljava/lang/StringBuffer;
L208:   ldc "LibLoader"
L210:   invokevirtual Method java/lang/StringBuffer append (Ljava/lang/String;)Ljava/lang/StringBuffer;
L213:   getstatic Field java/io/File separator Ljava/lang/String;
L216:   invokevirtual Method java/lang/StringBuffer append (Ljava/lang/String;)Ljava/lang/StringBuffer;
L219:   invokevirtual Method java/lang/StringBuffer toString ()Ljava/lang/String;
L222:   astore_3
L223:   new java/io/File
L226:   dup
L227:   aload_3
L228:   invokespecial Method java/io/File <init> (Ljava/lang/String;)V
L231:   astore 4
L233:   new java/lang/StringBuffer
L236:   dup
L237:   ldc "Creating destination : "
L239:   invokespecial Method java/lang/StringBuffer <init> (Ljava/lang/String;)V
L242:   aload_3
L243:   invokevirtual Method java/lang/StringBuffer append (Ljava/lang/String;)Ljava/lang/StringBuffer;
L246:   invokevirtual Method java/lang/StringBuffer toString ()Ljava/lang/String;
L249:   invokestatic Method org/jouvieje/libloader/G method1733 (Ljava/lang/String;)V
L252:   aload 4
L254:   invokevirtual Method java/io/File mkdirs ()Z
L257:   new java/io/File
L260:   dup
L261:   aload 4
L263:   aload_0
L264:   getfield Field org/jouvieje/libloader/D field2430 Ljava/lang/String;
L267:   invokespecial Method java/io/File <init> (Ljava/io/File;Ljava/lang/String;)V
L270:   astore 4
L272:   pop
        .catch java/lang/Throwable from L273 to L380 using L381
        .catch java/lang/Throwable from L0 to L98 using L398
        .catch java/lang/Throwable from L99 to L160 using L398
        .catch java/lang/Throwable from L161 to L380 using L398
L273:   new java/io/BufferedInputStream
L276:   dup
L277:   aload_2
L278:   invokespecial Method java/io/BufferedInputStream <init> (Ljava/io/InputStream;)V
L281:   astore 5
L283:   ldc "Opening output"
L285:   invokestatic Method org/jouvieje/libloader/G method1733 (Ljava/lang/String;)V
L288:   new java/io/BufferedOutputStream
L291:   dup
L292:   new java/io/FileOutputStream
L295:   dup
L296:   aload 4
L298:   invokespecial Method java/io/FileOutputStream <init> (Ljava/io/File;)V
L301:   invokespecial Method java/io/BufferedOutputStream <init> (Ljava/io/OutputStream;)V
L304:   astore 6
L306:   ldc "Writting to output"
L308:   invokestatic Method org/jouvieje/libloader/G method1733 (Ljava/lang/String;)V
L311:   sipush 8192
L314:   iconst_1
L315:   dup
L316:   pop2
L317:   newarray byte
L319:   iconst_1
L320:   dup
L321:   pop2
L322:   astore 7
L324:   iconst_0
L325:   iconst_1
L326:   dup
L327:   pop2
L328:   istore 8
L330:   aload_2
L331:   goto L348
L334:   aload 6
L336:   aload 7
L338:   iconst_0
L339:   iconst_1
L340:   dup
L341:   pop2
L342:   iload 8
L344:   invokevirtual Method java/io/BufferedOutputStream write ([BII)V
L347:   aload_2
L348:   aload 7
L350:   invokevirtual Method java/io/InputStream read ([B)I
L353:   dup
L354:   istore 8
L356:   ifgt L334
L359:   ldc "Closing files"
L361:   invokestatic Method org/jouvieje/libloader/G method1733 (Ljava/lang/String;)V
L364:   ldc "Extraction succeed"
L366:   aload 6
L368:   aload 5
L370:   invokevirtual Method java/io/BufferedInputStream close ()V
L373:   invokevirtual Method java/io/BufferedOutputStream close ()V
L376:   invokestatic Method org/jouvieje/libloader/G method1733 (Ljava/lang/String;)V
L379:   aload_3
L380:   areturn
        .catch java/lang/Throwable from L381 to L397 using L398
L381:   astore 5
L383:   aload 4
L385:   aload 5
L387:   invokestatic Method org/jouvieje/libloader/G method1756 (Ljava/lang/Throwable;)V
L390:   invokestatic Method org/jouvieje/libloader/G method1749 (Ljava/io/File;)Z
L393:   ifeq L403
L396:   aload_3
L397:   areturn
L398:   astore_1
L399:   aload_1
L400:   invokestatic Method org/jouvieje/libloader/G method1756 (Ljava/lang/Throwable;)V
L403:   aconst_null
L404:   areturn
L405:   
        .attribute StackMap b'\x00\x0E\x00\x62\x00\x00\x00\x01\x07\x00\x0E\x00\x63\x00\x03\x07\x00\x02\x07\x00\x42\x07\x00\x44\x00\x01\x07\x00\x0C\x00\x6F\x00\x03\x07\x00\x02\x07\x00\x42\x07\x00\x44\x00\x01\x07\x00\x30\x00\x70\x00\x03\x07\x00\x02\x07\x00\x42\x07\x00\x44\x00\x02\x07\x00\x30\x07\x00\x42\x00\xA0\x00\x00\x00\x01\x07\x00\x0E\x00\xA1\x00\x03\x07\x00\x02\x07\x00\x42\x07\x00\x44\x00\x01\x07\x00\x0C\x00\xAD\x00\x03\x07\x00\x02\x07\x00\x42\x07\x00\x44\x00\x01\x07\x00\x30\x00\xAE\x00\x03\x07\x00\x02\x07\x00\x42\x07\x00\x44\x00\x02\x07\x00\x30\x07\x00\x42\x00\xB2\x00\x03\x07\x00\x02\x07\x00\x42\x07\x00\x44\x00\x00\x01\x4E\x00\x09\x07\x00\x02\x07\x00\x42\x07\x00\x44\x07\x00\x42\x07\x00\x5F\x07\x00\x70\x07\x00\x77\x07\x00\x83\x01\x00\x00\x01\x5C\x00\x09\x07\x00\x02\x07\x00\x42\x07\x00\x44\x07\x00\x42\x07\x00\x5F\x07\x00\x70\x07\x00\x77\x07\x00\x83\x01\x00\x01\x07\x00\x44\x01\x7D\x00\x05\x07\x00\x02\x07\x00\x42\x07\x00\x44\x07\x00\x42\x07\x00\x5F\x00\x01\x07\x00\x0E\x01\x8E\x00\x01\x07\x00\x02\x00\x01\x07\x00\x0E\x01\x93\x00\x02\x07\x00\x02\x07\x00\x04\x00\x00'
    .end code
.end method

.method <init> : (Ljava/lang/String;)V
    .code stack 3 locals 2
L0:     aload_1
L1:     aload_0
L2:     dup_x1
L3:     invokespecial Method java/lang/Object <init> ()V
L6:     putfield Field org/jouvieje/libloader/D field2430 Ljava/lang/String;
L9:     return
L10:    
    .end code
.end method
.innerclasses
    org/jouvieje/libloader/D [0] [0]
.end innerclasses
.end class
