.version 49 0
.class public final super EG
.super Fg
.field public static final else Ljava/lang/String;
.field public static final "enum" Ljava/lang/String;
.field public static final do Ljava/lang/String;

.method public break : ()Ljava/lang/String;
    .code stack 1 locals 1
L0:     ldc "winner"
L2:     areturn
L3:     
    .end code
.end method

.method public <init> : (Ljava/lang/String;FF)V
    .code stack 4 locals 4
L0:     aload_0
L1:     aload_1
L2:     fload_2
L3:     fload_3
L4:     invokespecial Method Fg <init> (Ljava/lang/String;FF)V
L7:     return
L8:     
    .end code
.end method

.method public static <clinit> : ()V
    .code stack 6 locals 0
L0:     ldc "winner"
L2:     putstatic Field EG else Ljava/lang/String;
L5:     ldc "anon"
L7:     putstatic Field EG "enum" Ljava/lang/String;
L10:    ldc "winner"
L12:    putstatic Field EG do Ljava/lang/String;
L15:    ldc Class EG
L17:    ldc "anon"
L19:    ldc "avatar_none.png"
L21:    iconst_1
L22:    dup
L23:    dup
L24:    pop2
L25:    invokestatic Method EG break (Ljava/lang/Class;Ljava/lang/String;Ljava/lang/String;Z)V
L28:    ldc Class EG
L30:    ldc "winner"
L32:    ldc "avatar_winner.png"
L34:    iconst_1
L35:    dup
L36:    dup
L37:    pop2
L38:    invokestatic Method EG break (Ljava/lang/Class;Ljava/lang/String;Ljava/lang/String;Z)V
L41:    ldc Class EG
L43:    ldc "chuck"
L45:    ldc "avatar_chuck.png"
L47:    iconst_0
L48:    iconst_1
L49:    dup
L50:    pop2
L51:    invokestatic Method EG break (Ljava/lang/Class;Ljava/lang/String;Ljava/lang/String;Z)V
L54:    ldc Class EG
L56:    ldc "guki"
L58:    ldc "avatar_guki.png"
L60:    iconst_0
L61:    iconst_1
L62:    dup
L63:    pop2
L64:    invokestatic Method EG break (Ljava/lang/Class;Ljava/lang/String;Ljava/lang/String;Z)V
L67:    ldc Class EG
L69:    ldc "miyagi"
L71:    ldc "avatar_miyagi.png"
L73:    iconst_0
L74:    iconst_1
L75:    dup
L76:    pop2
L77:    invokestatic Method EG break (Ljava/lang/Class;Ljava/lang/String;Ljava/lang/String;Z)V
L80:    ldc Class EG
L82:    ldc "jeanluc"
L84:    ldc "avatar_jeanluc.png"
L86:    iconst_0
L87:    iconst_1
L88:    dup
L89:    pop2
L90:    invokestatic Method EG break (Ljava/lang/Class;Ljava/lang/String;Ljava/lang/String;Z)V
L93:    ldc Class EG
L95:    ldc "t"
L97:    ldc "avatar_t.png"
L99:    iconst_0
L100:   iconst_1
L101:   dup
L102:   pop2
L103:   invokestatic Method EG break (Ljava/lang/Class;Ljava/lang/String;Ljava/lang/String;Z)V
L106:   ldc Class EG
L108:   ldc "schneier"
L110:   ldc "avatar_schneier.png"
L112:   iconst_0
L113:   iconst_1
L114:   dup
L115:   pop2
L116:   invokestatic Method EG break (Ljava/lang/Class;Ljava/lang/String;Ljava/lang/String;Z)V
L119:   ldc Class EG
L121:   ldc "schaefer"
L123:   ldc "avatar_schaefer.png"
L125:   iconst_0
L126:   iconst_1
L127:   dup
L128:   pop2
L129:   invokestatic Method EG break (Ljava/lang/Class;Ljava/lang/String;Ljava/lang/String;Z)V
L132:   ldc Class EG
L134:   ldc "mcclane"
L136:   ldc "avatar_mcclane.png"
L138:   iconst_0
L139:   iconst_1
L140:   dup
L141:   pop2
L142:   invokestatic Method EG break (Ljava/lang/Class;Ljava/lang/String;Ljava/lang/String;Z)V
L145:   ldc Class EG
L147:   ldc "300"
L149:   ldc "avatar_300.png"
L151:   iconst_0
L152:   iconst_1
L153:   dup
L154:   pop2
L155:   invokestatic Method EG break [_29]
L158:   ldc Class EG
L160:   ldc "hartman"
L162:   ldc "avatar_hartman.png"
L164:   iconst_0
L165:   iconst_1
L166:   dup
L167:   pop2
L168:   invokestatic Method EG break [_29]
L171:   ldc Class EG
L173:   ldc "seagal"
L175:   ldc "avatar_seagal.png"
L177:   iconst_0
L178:   iconst_1
L179:   dup
L180:   pop2
L181:   invokestatic Method EG break [_29]
L184:   ldc Class EG
L186:   ldc "rocky"
L188:   ldc "avatar_rocky.png"
L190:   iconst_0
L191:   iconst_1
L192:   dup
L193:   pop2
L194:   invokestatic Method EG break [_29]
L197:   ldc Class EG
L199:   ldc "bud"
L201:   ldc "avatar_bud.png"
L203:   iconst_0
L204:   iconst_1
L205:   dup
L206:   pop2
L207:   invokestatic Method EG break [_29]
L210:   ldc Class EG
L212:   ldc "terence"
L214:   ldc "avatar_terence.png"
L216:   iconst_0
L217:   iconst_1
L218:   dup
L219:   pop2
L220:   invokestatic Method EG break [_29]
L223:   ldc Class EG
L225:   ldc "grossman"
L227:   ldc "avatar_grossman.png"
L229:   iconst_0
L230:   iconst_1
L231:   dup
L232:   pop2
L233:   invokestatic Method EG break [_29]
L236:   ldc Class EG
L238:   ldc "interesting"
L240:   ldc "avatar_interesting.png"
L242:   iconst_0
L243:   iconst_1
L244:   dup
L245:   pop2
L246:   invokestatic Method EG break [_29]
L249:   ldc Class EG
L251:   ldc "harddrop"
L253:   ldc "avatar_harddrop.png"
L255:   iconst_0
L256:   iconst_1
L257:   dup
L258:   pop2
L259:   invokestatic Method EG break [_29]
L262:   ldc Class EG
L264:   ldc "blink"
L266:   ldc "avatar_blink.png"
L268:   iconst_0
L269:   iconst_1
L270:   dup
L271:   pop2
L272:   invokestatic Method EG break [_29]
L275:   return
L276:   
    .end code
.end method

.method public static fetchIcon : (Ljava/lang/String;)Ljava/nio/ByteBuffer;
    .code stack 3 locals 1
L0:     new java/lang/StringBuilder
L3:     dup
L4:     invokespecial Method java/lang/StringBuilder <init> ()V
L7:     iconst_0
L8:     ldc "https://c2.tail.ws/avatars/"
L10:    invokevirtual Method java/lang/StringBuilder insert (ILjava/lang/String;)Ljava/lang/StringBuilder;
L13:    aload_0
L14:    invokevirtual Method java/lang/StringBuilder append (Ljava/lang/String;)Ljava/lang/StringBuilder;
L17:    ldc ".png"
L19:    invokevirtual Method java/lang/StringBuilder append (Ljava/lang/String;)Ljava/lang/StringBuilder;
L22:    invokevirtual Method java/lang/StringBuilder toString ()Ljava/lang/String;
L25:    invokestatic Method EG break (Ljava/lang/String;)Ljava/nio/ByteBuffer;
L28:    areturn
L29:    
    .end code
    .exceptions java/lang/Exception
.end method
.const [_29] = Utf8 (Ljava/lang/Class;Ljava/lang/String;Ljava/lang/String;Z)V
.end class
